{
  "type": "Feature",
  "properties": {
    "iso:country":"US",
    "sg:address":"7145 Pole Green Rd",
    "sg:city":"Mechanicsville",
    "sg:classifiers":[
        {
            "category":"Personal",
            "subcategory":"Beauty Salon",
            "type":"Services"
        }
    ],
    "sg:phone":"+1 804 746 5886",
    "sg:postcode":"23116",
    "sg:province":"VA",
    "sg:tags":[
        "shop"
    ],
    "wof:name":"Bagbys Beauty Lounge",
    "wof:placetype":"venue"
},
  "geometry": {"coordinates":[-77.345871,37.636265],"type":"Point"}
}