{
  "type": "Feature",
  "properties": {
    "addr:full":"7510 Pollen St Lorton VA 22079",
    "addr:postcode":"7510;22079",
    "addr:street":"Pollen St",
    "iso:country":"US",
    "sg:address":"7510 Pollen St",
    "sg:city":"Lorton",
    "sg:classifiers":[
        {
            "category":"Professional",
            "subcategory":"Business Services",
            "type":"Services"
        }
    ],
    "sg:phone":"+1 703 339 2070",
    "sg:postcode":"22079",
    "sg:province":"VA",
    "wof:name":"PR & Assoc",
    "wof:placetype":"venue"
},
  "geometry": {"coordinates":[-77.20478300000001,38.716705],"type":"Point"}
}