{
  "type": "Feature",
  "properties": {
    "addr:full":"103 Lake View Way NW Leesburg VA 20176",
    "addr:housenumber":"103",
    "addr:postcode":"20176",
    "addr:street":"Lake View Way Nw",
    "iso:country":"US",
    "sg:address":"103 Lake View Way NW",
    "sg:city":"Leesburg",
    "sg:classifiers":[
        {
            "category":"Real Estate",
            "subcategory":"Real Estate Agent",
            "type":"Services"
        }
    ],
    "sg:phone":"+1 703 443 9558",
    "sg:postcode":"20176",
    "sg:province":"VA",
    "wof:name":"TLC Homes Inc",
    "wof:placetype":"venue"
},
  "geometry": {"coordinates":[-77.57521800000001,39.123133],"type":"Point"}
}