{
  "type": "Feature",
  "properties": {
    "addr:full":"1868 Floyd Pike Hillsville VA 24343",
    "addr:housenumber":"1868",
    "addr:postcode":"24343",
    "addr:street":"Floyd Pike",
    "iso:country":"US",
    "sg:address":"1868 Floyd Pike",
    "sg:city":"Hillsville",
    "sg:classifiers":[
        {
            "category":"Shopping",
            "subcategory":"Clothing, Apparel, & Fashions",
            "type":"Retail Goods"
        }
    ],
    "sg:phone":"+1 276 728 9317",
    "sg:postcode":"24343",
    "sg:province":"VA",
    "sg:tags":[
        "ready"
    ],
    "wof:name":"Slushers Clothing Outlet",
    "wof:placetype":"venue"
},
  "geometry": {"coordinates":[-80.70775399999999,36.777501],"type":"Point"}
}