{
  "type": "Feature",
  "properties": {
    "addr:full":"4597 Adams Swamp Rd Suffolk VA 23434",
    "addr:housenumber":"4597",
    "addr:postcode":"23434",
    "addr:street":"Adams Swamp Rd",
    "iso:country":"US",
    "sg:address":"4597 Adams Swamp Rd",
    "sg:city":"Suffolk",
    "sg:classifiers":[
        {
            "category":"Retail",
            "subcategory":"Auto Repair",
            "type":"Services"
        },
        {
            "category":"Home & Garden",
            "subcategory":"Garden Supply",
            "type":"Retail Goods"
        }
    ],
    "sg:phone":"+1 757 986 4123",
    "sg:postcode":"23434",
    "sg:province":"VA",
    "sg:tags":[
        "lawn",
        "mower",
        "general"
    ],
    "wof:name":"Aswell's Garage",
    "wof:placetype":"venue"
},
  "geometry": {"coordinates":[-76.616373,36.552918],"type":"Point"}
}