{
  "type": "Feature",
  "properties": {
    "iso:country":"US",
    "sg:address":"8092 Crescent Park Dr",
    "sg:city":"Gainesville",
    "sg:classifiers":[
        {
            "category":"Banks & Credit Unions",
            "subcategory":"Bank",
            "type":"Services"
        }
    ],
    "sg:phone":"+1 703 753 6468",
    "sg:postcode":"20136",
    "sg:province":"VA",
    "sg:website":"www.chevychasebank.com",
    "wof:name":"Chevy Chase Bank",
    "wof:placetype":"venue"
},
  "geometry": {"coordinates":[-77.663641,38.78413],"type":"Point"}
}