{
  "type": "Feature",
  "properties": {
    "addr:full":"146 S Main St Woodstock VA 22664",
    "addr:housenumber":"146",
    "addr:postcode":"22664",
    "addr:street":"S Main St",
    "iso:country":"US",
    "sg:address":"146 S Main St",
    "sg:city":"Woodstock",
    "sg:classifiers":[
        {
            "category":"Real Estate",
            "subcategory":"Real Estate Agent",
            "type":"Services"
        }
    ],
    "sg:phone":"+1 540 459 2123",
    "sg:postcode":"22664",
    "sg:province":"VA",
    "sg:website":"www.erabeasley.com",
    "wof:name":"Beasley Realty Inc",
    "wof:placetype":"venue"
},
  "geometry": {"coordinates":[-78.50578400000001,38.881191],"type":"Point"}
}