{
  "type": "Feature",
  "properties": {
    "addr:full":"2976 River Rd W Goochland VA 23063",
    "addr:housenumber":"2976",
    "addr:postcode":"23063",
    "addr:street":"River Rd W Goochland",
    "iso:country":"US",
    "sg:address":"2976 River Rd W",
    "sg:city":"Goochland",
    "sg:classifiers":[
        {
            "category":"Personal",
            "subcategory":"Beauty Salon",
            "type":"Services"
        }
    ],
    "sg:phone":"+1 804 556 9060",
    "sg:postcode":"23063",
    "sg:province":"VA",
    "sg:tags":[
        "manicuring"
    ],
    "wof:name":"Nail Details",
    "wof:placetype":"venue"
},
  "geometry": {"coordinates":[-77.885451,37.686145],"type":"Point"}
}