{
  "type": "Feature",
  "properties": {
    "iso:country":"US",
    "sg:address":"158 Lakeview Dr",
    "sg:city":"Madison Heights",
    "sg:classifiers":[
        {
            "category":"Government",
            "subcategory":"Post Office",
            "type":"Public Place"
        }
    ],
    "sg:phone":"+1 434 845 3051",
    "sg:postcode":"24572",
    "sg:province":"VA",
    "wof:name":"US Post Office",
    "wof:placetype":"venue"
},
  "geometry": {"coordinates":[-79.117228,37.44117],"type":"Point"}
}