{
  "type": "Feature",
  "properties": {
    "addr:full":"8367 Hoover Dr King George VA 22485",
    "addr:housenumber":"8367",
    "addr:postcode":"22485",
    "addr:street":"Hoover Dr",
    "iso:country":"US",
    "sg:address":"8367 Hoover Dr",
    "sg:city":"King George",
    "sg:classifiers":[
        {
            "category":"Organizations",
            "subcategory":"Religious Organization",
            "type":"Services"
        }
    ],
    "sg:phone":"+1 540 775 2690",
    "sg:postcode":"22485",
    "sg:province":"VA",
    "wof:name":"King George Church of God",
    "wof:placetype":"venue"
},
  "geometry": {"coordinates":[-77.20151,38.273652],"type":"Point"}
}