{
  "type": "Feature",
  "properties": {
    "addr:full":"5604 Norlina Rd Virginia Beach VA 23455",
    "addr:housenumber":"5604",
    "addr:postcode":"23455",
    "addr:street":"Norlina Rd",
    "iso:country":"US",
    "sg:address":"5604 Norlina Rd",
    "sg:city":"Virginia Beach",
    "sg:classifiers":[
        {
            "category":"Autos & Motor Vehicles",
            "subcategory":"Fuel & Gas Station",
            "type":"Retail Goods"
        }
    ],
    "sg:phone":"+1 757 460 5851",
    "sg:postcode":"23455",
    "sg:province":"VA",
    "sg:tags":[
        "station",
        "gasoline"
    ],
    "wof:name":"Aaron Lee Griggs",
    "wof:placetype":"venue"
},
  "geometry": {"coordinates":[-76.176193,36.895872],"type":"Point"}
}