{
  "type": "Feature",
  "properties": {
    "addr:full":"1056 Courthouse Rd Stafford VA 22554",
    "addr:housenumber":"1056",
    "addr:postcode":"22554",
    "addr:street":"Courthouse Rd",
    "iso:country":"US",
    "sg:address":"1056 Courthouse Rd",
    "sg:city":"Stafford",
    "sg:classifiers":[
        {
            "category":"Personal",
            "type":"Services"
        }
    ],
    "sg:phone":"+1 540 658 1400",
    "sg:postcode":"22554",
    "sg:province":"VA",
    "wof:name":"Stafford Shell",
    "wof:placetype":"venue"
},
  "geometry": {"coordinates":[-77.42546900000001,38.421948],"type":"Point"}
}