{
  "type": "Feature",
  "properties": {
    "iso:country":"US",
    "sg:address":"222 Tinkling Spring Rd",
    "sg:city":"Fishersville",
    "sg:classifiers":[
        {
            "category":"Professional",
            "subcategory":"Computer Services",
            "type":"Services"
        }
    ],
    "sg:phone":"+1 540 942 2991",
    "sg:postcode":"22939",
    "sg:province":"VA",
    "sg:tags":[
        "repair"
    ],
    "wof:name":"Advanced Electronic Solutions",
    "wof:placetype":"venue"
},
  "geometry": {"coordinates":[-78.971557,38.097047],"type":"Point"}
}