{
  "type": "Feature",
  "properties": {
    "iso:country":"US",
    "sg:address":"401 Lee Blvd",
    "sg:city":"Newport News",
    "sg:classifiers":[
        {
            "category":"Recreation",
            "type":"Entertainment"
        }
    ],
    "sg:phone":"+1 757 887 0983",
    "sg:postcode":"23604",
    "sg:province":"VA",
    "sg:tags":[
        "concessionaire"
    ],
    "wof:name":"Business Opportunities-Blind",
    "wof:placetype":"venue"
},
  "geometry": {"coordinates":[-76.60329,37.166717],"type":"Point"}
}