{
  "type": "Feature",
  "properties": {
    "addr:full":"5201 8th Rd S Arlington VA 22204",
    "addr:housenumber":"5201",
    "addr:postcode":"22204",
    "addr:street":"8Th Rd S",
    "iso:country":"US",
    "sg:address":"5201 8th Rd S",
    "sg:city":"Arlington",
    "sg:classifiers":[
        {
            "category":"Retail",
            "subcategory":"Laundry & Dry Cleaning",
            "type":"Services"
        }
    ],
    "sg:phone":"+1 703 845 0096",
    "sg:postcode":"22204",
    "sg:province":"VA",
    "sg:tags":[
        "cleaners",
        "rug",
        "carpet"
    ],
    "wof:name":"Eastern Cleaning Svc",
    "wof:placetype":"venue"
},
  "geometry": {"coordinates":[-77.117699,38.856736],"type":"Point"}
}