{
  "type": "Feature",
  "properties": {
    "addr:full":"13727 Blackwells Mill Rd Goldvein VA 22720",
    "addr:housenumber":"13727",
    "addr:postcode":"22720",
    "addr:street":"Blackwells Mill Rd",
    "iso:country":"US",
    "sg:address":"13727 Blackwells Mill Rd",
    "sg:city":"Goldvein",
    "sg:classifiers":[
        {
            "category":"Farming",
            "subcategory":"Livestock Farm",
            "type":"Manufacturing & Wholesale Goods"
        },
        {
            "category":"Retail",
            "subcategory":"Animal Services",
            "type":"Services"
        }
    ],
    "sg:phone":"+1 540 752 4710",
    "sg:postcode":"22720",
    "sg:province":"VA",
    "sg:tags":[
        "pet",
        "boarding",
        "general",
        "sitting"
    ],
    "sg:website":"www.deeprunretrievers.com",
    "wof:name":"Deep Run Farms",
    "wof:placetype":"venue"
},
  "geometry": {"coordinates":[-77.648945,38.466442],"type":"Point"}
}