{
  "type": "Feature",
  "properties": {
    "addr:full":"212 E Main St Bedford VA 24523",
    "addr:housenumber":"212",
    "addr:postcode":"24523",
    "addr:street":"E Main St",
    "iso:country":"US",
    "sg:address":"212 E Main St",
    "sg:city":"Bedford",
    "sg:classifiers":[
        {
            "category":"Organizations",
            "subcategory":"Religious Organization",
            "type":"Services"
        }
    ],
    "sg:phone":"+1 540 586 8878",
    "sg:postcode":"24523",
    "sg:province":"VA",
    "sg:tags":[
        "church"
    ],
    "wof:name":"Main Street Methodist Church",
    "wof:placetype":"venue"
},
  "geometry": {"coordinates":[-79.522138,37.333985],"type":"Point"}
}