{
  "type": "Feature",
  "properties": {
    "addr:full":"120 Washington St NE Leesburg VA 20176",
    "addr:housenumber":"120",
    "addr:postcode":"20176",
    "addr:street":"Washington St Ne",
    "iso:country":"US",
    "sg:address":"120 Washington St NE",
    "sg:city":"Leesburg",
    "sg:classifiers":[
        {
            "category":"Recreation",
            "type":"Entertainment"
        }
    ],
    "sg:phone":"+1 703 777 9705",
    "sg:postcode":"20176",
    "sg:province":"VA",
    "sg:tags":[
        "club",
        "membership",
        "swimming"
    ],
    "wof:name":"Cavalier Arms Pool",
    "wof:placetype":"venue"
},
  "geometry": {"coordinates":[-77.54983300000001,39.113431],"type":"Point"}
}