{
  "type": "Feature",
  "properties": {
    "iso:country":"US",
    "sg:address":"2425 Nottingham Dr",
    "sg:city":"Falls Church",
    "sg:classifiers":[
        {
            "category":"Real Estate",
            "subcategory":"Real Estate Agent",
            "type":"Services"
        }
    ],
    "sg:phone":"+1 703 876 0076",
    "sg:postcode":"22043",
    "sg:province":"VA",
    "wof:name":"Chantilly Westfields Realty Co",
    "wof:placetype":"venue"
},
  "geometry": {"coordinates":[-77.215181,38.890979],"type":"Point"}
}