{
  "type": "Feature",
  "properties": {
    "addr:full":"3004 Lee Hwy Apt D333 Arlington VA 22201",
    "addr:housenumber":"3004",
    "addr:postcode":"22201",
    "addr:street":"Lee Hwy Apt D333",
    "iso:country":"US",
    "sg:address":"3004 Lee Hwy Apt D333",
    "sg:city":"Arlington",
    "sg:classifiers":[
        {
            "category":"Professional",
            "type":"Services"
        }
    ],
    "sg:phone":"+1 703 465 7725",
    "sg:postcode":"22201",
    "sg:province":"VA",
    "sg:tags":[
        "publication",
        "editorial"
    ],
    "wof:name":"The Grackle Group",
    "wof:placetype":"venue"
},
  "geometry": {"coordinates":[-77.09543499999999,38.895522],"type":"Point"}
}