{
  "type": "Feature",
  "properties": {
    "addr:full":"3776 Anderson Hwy Powhatan VA 23139",
    "addr:housenumber":"3776",
    "addr:postcode":"23139",
    "addr:street":"Anderson Hwy",
    "iso:country":"US",
    "sg:address":"3776 Anderson Hwy",
    "sg:city":"Powhatan",
    "sg:classifiers":[
        {
            "category":"Shopping",
            "type":"Retail Goods"
        }
    ],
    "sg:phone":"+1 804 598 7000",
    "sg:postcode":"23139",
    "sg:province":"VA",
    "sg:tags":[
        "awning",
        "canopy"
    ],
    "wof:name":"American Awning",
    "wof:placetype":"venue"
},
  "geometry": {"coordinates":[-77.91078,37.546327],"type":"Point"}
}