{
  "type": "Feature",
  "properties": {
    "addr:full":"5205 Leesburg Pike Suite 210, Floor 2 Falls Church VA 22041",
    "addr:housenumber":"5205;2",
    "addr:postcode":"22041",
    "addr:street":"Leesburg Pike Suite 210 Floor",
    "iso:country":"US",
    "sg:address":"5205 Leesburg Pike Suite 210, Floor 2",
    "sg:city":"Falls Church",
    "sg:classifiers":[
        {
            "category":"Professional",
            "subcategory":"Computer Services",
            "type":"Services"
        }
    ],
    "sg:phone":"+1 617 864 0636",
    "sg:postcode":"22041",
    "sg:province":"VA",
    "sg:tags":[
        "clinical-analytics",
        "health",
        "ehealth",
        "robotics",
        "robots",
        "kiosk",
        "infection-control",
        "surveillance",
        "boston"
    ],
    "sg:website":"http://www.vecna.com",
    "wof:name":"Vecna Technologies",
    "wof:placetype":"venue"
},
  "geometry": {"coordinates":[-77.11569900000001,38.845206],"type":"Point"}
}