{
  "type": "Feature",
  "properties": {
    "addr:full":"2932 Prince William Pkwy Woodbridge VA 22192",
    "addr:housenumber":"2932",
    "addr:postcode":"22192",
    "addr:street":"Prince William Pkwy",
    "iso:country":"US",
    "sg:address":"2932 Prince William Pkwy",
    "sg:city":"Woodbridge",
    "sg:classifiers":[
        {
            "category":"Shopping",
            "subcategory":"Jewelry",
            "type":"Retail Goods"
        },
        {
            "category":"Manufacturing",
            "subcategory":"Jewelry",
            "type":"Manufacturing & Wholesale Goods"
        }
    ],
    "sg:phone":"+1 703 580 8880",
    "sg:postcode":"22192",
    "sg:province":"VA",
    "sg:tags":[
        "repairing",
        "designer",
        "jeweler"
    ],
    "sg:website":"http://www.jbd4u.com",
    "wof:name":"Jewelry By Design",
    "wof:placetype":"venue"
},
  "geometry": {"coordinates":[-77.301351,38.651387],"type":"Point"}
}