{
  "type": "Feature",
  "properties": {
    "addr:full":"606 Denbigh Blvd Newport News VA 23608",
    "addr:housenumber":"606",
    "addr:postcode":"23608",
    "addr:street":"Denbigh Blvd",
    "iso:country":"US",
    "sg:address":"606 Denbigh Blvd",
    "sg:city":"Newport News",
    "sg:classifiers":[
        {
            "category":"Health Services",
            "subcategory":"Health Practitioner",
            "type":"Services"
        }
    ],
    "sg:phone":"+1 757 668 7473",
    "sg:postcode":"23608",
    "sg:province":"VA",
    "wof:name":"Frank Aiello",
    "wof:placetype":"venue"
},
  "geometry": {"coordinates":[-76.523139,37.136828],"type":"Point"}
}