{
  "type": "Feature",
  "properties": {
    "addr:full":"39859 The Narrows Rd Waterford VA 20197",
    "addr:housenumber":"39859",
    "addr:postcode":"20197",
    "addr:street":"The Narrows Rd",
    "iso:country":"US",
    "sg:address":"39859 The Narrows Rd",
    "sg:city":"Waterford",
    "sg:classifiers":[
        {
            "category":"Professional",
            "subcategory":"Management & Consulting",
            "type":"Services"
        }
    ],
    "sg:phone":"+1 540 882 3593",
    "sg:postcode":"20197",
    "sg:province":"VA",
    "sg:tags":[
        "consultant"
    ],
    "wof:name":"Catoctin Consulting LLC",
    "wof:placetype":"venue"
},
  "geometry": {"coordinates":[-77.631119,39.211994],"type":"Point"}
}