{
  "type": "Feature",
  "properties": {
    "addr:full":"7068 Little Thames Dr Gainesville VA 20155",
    "addr:housenumber":"7068",
    "addr:postcode":"20155",
    "addr:street":"Little Thames Dr",
    "iso:country":"US",
    "sg:address":"7068 Little Thames Dr",
    "sg:city":"Gainesville",
    "sg:classifiers":[
        {
            "category":"Professional",
            "subcategory":"Business Services",
            "type":"Services"
        }
    ],
    "sg:phone":"+1 703 753 9216",
    "sg:postcode":"20155",
    "sg:province":"VA",
    "sg:tags":[
        "organizing",
        "services-household"
    ],
    "wof:name":"Cmc Management",
    "wof:placetype":"venue"
},
  "geometry": {"coordinates":[-77.624374,38.804377],"type":"Point"}
}