{
  "type": "Feature",
  "properties": {
    "addr:full":"3109 Sand Pine Rd Virginia Beach VA 23451",
    "addr:housenumber":"3109",
    "addr:postcode":"23451",
    "addr:street":"Sand Pine Rd",
    "iso:country":"US",
    "sg:address":"3109 Sand Pine Rd",
    "sg:city":"Virginia Beach",
    "sg:classifiers":[
        {
            "category":"Building & Trades",
            "subcategory":"Construction",
            "type":"Services"
        }
    ],
    "sg:phone":"+1 757 496 7912",
    "sg:postcode":"23451",
    "sg:province":"VA",
    "sg:tags":[
        "specializing",
        "contracting",
        "contractor",
        "vinyl",
        "general"
    ],
    "wof:name":"Dbi Siding",
    "wof:placetype":"venue"
},
  "geometry": {"coordinates":[-76.08222600000001,36.907357],"type":"Point"}
}