{
  "type": "Feature",
  "properties": {
    "iso:country":"US",
    "sg:address":"85 Cleremont Dr",
    "sg:city":"Fredericksburg",
    "sg:classifiers":[
        {
            "category":"Social Services",
            "subcategory":"Child Care",
            "type":"Services"
        }
    ],
    "sg:phone":"+1 540 373 7791",
    "sg:postcode":"22405",
    "sg:province":"VA",
    "wof:name":"Learn 'n Play Children's Ctr",
    "wof:placetype":"venue"
},
  "geometry": {"coordinates":[-77.437269,38.32839],"type":"Point"}
}