{
  "type": "Feature",
  "properties": {
    "iso:country":"US",
    "sg:address":"5909 High St W",
    "sg:city":"Portsmouth",
    "sg:classifiers":[
        {
            "category":"Restaurant",
            "type":"Food & Drink"
        }
    ],
    "sg:phone":"+1 757 483 1518",
    "sg:postcode":"23703",
    "sg:province":"VA",
    "sg:tags":[
        "seafood"
    ],
    "wof:name":"Amory's Seafood Restaurant",
    "wof:placetype":"venue"
},
  "geometry": {"coordinates":[-76.39752,36.860835],"type":"Point"}
}