{
  "type": "Feature",
  "properties": {
    "addr:full":"11712 Decade Ct Reston VA 20191",
    "addr:housenumber":"11712",
    "addr:postcode":"20191",
    "addr:street":"Decade Ct",
    "iso:country":"US",
    "sg:address":"11712 Decade Ct",
    "sg:city":"Reston",
    "sg:classifiers":[
        {
            "category":"Professional",
            "subcategory":"Computer Services",
            "type":"Services"
        }
    ],
    "sg:phone":"+1 703 980 3763",
    "sg:postcode":"20191",
    "sg:province":"VA",
    "sg:tags":[
        "technical",
        "support"
    ],
    "wof:name":"Digital Image Group",
    "wof:placetype":"venue"
},
  "geometry": {"coordinates":[-77.35141299999999,38.929445],"type":"Point"}
}