{
  "type": "Feature",
  "properties": {
    "iso:country":"US",
    "sg:address":"621 Shadow Brooke Dr",
    "sg:city":"Chesapeake",
    "sg:classifiers":[
        {
            "category":"Building & Trades",
            "subcategory":"Plumbing",
            "type":"Services"
        }
    ],
    "sg:phone":"+1 757 436 5792",
    "sg:postcode":"23320",
    "sg:province":"VA",
    "sg:tags":[
        "contractor"
    ],
    "wof:name":"James Constur",
    "wof:placetype":"venue"
},
  "geometry": {"coordinates":[-76.235406,36.741137],"type":"Point"}
}