{
  "type": "Feature",
  "properties": {
    "addr:full":"506 Salem Ave SW Roanoke VA 24016",
    "addr:housenumber":"506",
    "addr:postcode":"24016",
    "addr:street":"Salem Ave Sw",
    "iso:country":"US",
    "sg:address":"506 Salem Ave SW",
    "sg:city":"Roanoke",
    "sg:classifiers":[
        {
            "category":"Autos & Motor Vehicles",
            "subcategory":"Automobile Sales",
            "type":"Retail Goods"
        }
    ],
    "sg:phone":"+1 540 342 1752",
    "sg:postcode":"24016",
    "sg:province":"VA",
    "sg:tags":[
        "car",
        "dealer"
    ],
    "wof:name":"Valley Motor Co",
    "wof:placetype":"venue"
},
  "geometry": {"coordinates":[-79.952033,37.272572],"type":"Point"}
}