{
  "type": "Feature",
  "properties": {
    "addr:full":"1595 International Blvd Norfolk VA 23513",
    "addr:housenumber":"1595",
    "addr:postcode":"23513",
    "addr:street":"International Blvd",
    "iso:country":"US",
    "sg:address":"1595 International Blvd",
    "sg:city":"Norfolk",
    "sg:classifiers":[
        {
            "category":"Restaurant",
            "type":"Food & Drink"
        }
    ],
    "sg:phone":"+1 757 853 0200",
    "sg:postcode":"23513",
    "sg:province":"VA",
    "wof:name":"China One",
    "wof:placetype":"venue"
},
  "geometry": {"coordinates":[-76.22594599999999,36.896578],"type":"Point"}
}