{
  "type": "Feature",
  "properties": {
    "addr:full":"242 Staley St Marion VA 24354",
    "addr:housenumber":"242",
    "addr:postcode":"24354",
    "addr:street":"Staley St",
    "iso:country":"US",
    "sg:address":"242 Staley St",
    "sg:city":"Marion",
    "sg:classifiers":[
        {
            "category":"Professional",
            "type":"Services"
        }
    ],
    "sg:phone":"+1 276 783 9223",
    "sg:postcode":"24354",
    "sg:province":"VA",
    "wof:name":"I Mark Services",
    "wof:placetype":"venue"
},
  "geometry": {"coordinates":[-81.50722500000001,36.843547],"type":"Point"}
}