{
  "type": "Feature",
  "properties": {
    "iso:country":"US",
    "sg:address":"435 N Armistead St",
    "sg:city":"Alexandria",
    "sg:classifiers":[
        {
            "category":"Professional",
            "subcategory":"Business Services",
            "type":"Services"
        }
    ],
    "sg:phone":"+1 703 354 2917",
    "sg:postcode":"22312",
    "sg:province":"VA",
    "wof:name":"Carters Aquariums",
    "wof:placetype":"venue"
},
  "geometry": {"coordinates":[-77.134249,38.819975],"type":"Point"}
}