{
  "type": "Feature",
  "properties": {
    "addr:full":"10331 Apache Rd Richmond VA 23235",
    "addr:housenumber":"10331",
    "addr:postcode":"23235",
    "addr:street":"Apache Rd",
    "iso:country":"US",
    "sg:address":"10331 Apache Rd",
    "sg:city":"Richmond",
    "sg:classifiers":[
        {
            "category":"Professional",
            "subcategory":"Management & Consulting",
            "type":"Services"
        }
    ],
    "sg:phone":"+1 804 320 5467",
    "sg:postcode":"23235",
    "sg:province":"VA",
    "wof:name":"Nexgen Hospital Remittance Sol",
    "wof:placetype":"venue"
},
  "geometry": {"coordinates":[-77.58661499999999,37.55033],"type":"Point"}
}