{
  "type": "Feature",
  "properties": {
    "iso:country":"US",
    "sg:address":"5100 Marshall Ave",
    "sg:city":"Newport News",
    "sg:classifiers":[
        {
            "category":"Professional",
            "subcategory":"Management & Consulting",
            "type":"Services"
        }
    ],
    "sg:phone":"+1 757 244 5200",
    "sg:postcode":"23605",
    "sg:province":"VA",
    "sg:tags":[
        "correction",
        "managed",
        "privately",
        "detention",
        "facility"
    ],
    "wof:name":"Youth Services International",
    "wof:placetype":"venue"
},
  "geometry": {"coordinates":[-76.42568,36.999839],"type":"Point"}
}