{
  "type": "Feature",
  "properties": {
    "addr:full":"290 Remount Rd Front Royal VA 22630",
    "addr:housenumber":"290",
    "addr:postcode":"22630",
    "addr:street":"Remount Rd",
    "iso:country":"US",
    "sg:address":"290 Remount Rd",
    "sg:city":"Front Royal",
    "sg:classifiers":[
        {
            "category":"Banks & Credit Unions",
            "subcategory":"Bank",
            "type":"Services"
        }
    ],
    "sg:phone":"+1 540 635 4125",
    "sg:postcode":"22630",
    "sg:province":"VA",
    "sg:tags":[
        "financing"
    ],
    "wof:name":"American General Finance Inc",
    "wof:placetype":"venue"
},
  "geometry": {"coordinates":[-78.184826,38.908495],"type":"Point"}
}