{
  "type": "Feature",
  "properties": {
    "addr:full":"1219 First St Alexandria VA 22314",
    "addr:housenumber":"1219",
    "addr:postcode":"22314",
    "addr:street":"First St",
    "iso:country":"US",
    "sg:address":"1219 First St",
    "sg:city":"Alexandria",
    "sg:classifiers":[
        {
            "category":"Building & Trades",
            "subcategory":"Construction",
            "type":"Services"
        }
    ],
    "sg:phone":"+1 703 549 0001",
    "sg:postcode":"22314",
    "sg:province":"VA",
    "sg:tags":[
        "contractor"
    ],
    "wof:name":"Jaguar Development Llc",
    "wof:placetype":"venue"
},
  "geometry": {"coordinates":[-77.050388,38.81618],"type":"Point"}
}