{
  "type": "Feature",
  "properties": {
    "iso:country":"US",
    "sg:address":"615 Caroline St",
    "sg:city":"Fredericksburg",
    "sg:classifiers":[
        {
            "category":"Restaurant",
            "type":"Food & Drink"
        }
    ],
    "sg:phone":"+1 540 371 4435",
    "sg:postcode":"22401",
    "sg:province":"VA",
    "sg:tags":[
        "parlor",
        "ice",
        "cream"
    ],
    "wof:name":"Cone Connection",
    "wof:placetype":"venue"
},
  "geometry": {"coordinates":[-77.457763,38.300764],"type":"Point"}
}