{
  "type": "Feature",
  "properties": {
    "iso:country":"US",
    "sg:address":"1515 Courtland Rd NE",
    "sg:city":"Roanoke",
    "sg:classifiers":[
        {
            "category":"Government",
            "subcategory":"Post Office",
            "type":"Public Place"
        }
    ],
    "sg:phone":"+1 540 344 2004",
    "sg:postcode":"24012",
    "sg:province":"VA",
    "wof:name":"US Post Office",
    "wof:placetype":"venue"
},
  "geometry": {"coordinates":[-79.934634,37.285277],"type":"Point"}
}