{
  "type": "Feature",
  "properties": {
    "addr:full":"8711 Virginia Meadows Dr Manassas VA 20109",
    "addr:housenumber":"8711",
    "addr:postcode":"20109",
    "addr:street":"Virginia Meadows Dr",
    "iso:country":"US",
    "sg:address":"8711 Virginia Meadows Dr",
    "sg:city":"Manassas",
    "sg:classifiers":[
        {
            "category":"Building & Trades",
            "subcategory":"Construction",
            "type":"Services"
        }
    ],
    "sg:phone":"+1 703 393 1244",
    "sg:postcode":"20109",
    "sg:province":"VA",
    "sg:tags":[
        "flooring"
    ],
    "wof:name":"Chesapeake Flooring",
    "wof:placetype":"venue"
},
  "geometry": {"coordinates":[-77.55484,38.770666],"type":"Point"}
}