{
  "type": "Feature",
  "properties": {
    "iso:country":"US",
    "sg:address":"1511 Stuart Rd",
    "sg:city":"Reston",
    "sg:classifiers":[
        {
            "category":"Autos & Motor Vehicles",
            "subcategory":"Motorcycle Sales",
            "type":"Retail Goods"
        }
    ],
    "sg:phone":"+1 703 787 7618",
    "sg:postcode":"20194",
    "sg:province":"VA",
    "sg:tags":[
        "scooter"
    ],
    "sg:website":"www.euromotoparts.com",
    "wof:name":"Euromotoparts Inc",
    "wof:placetype":"venue"
},
  "geometry": {"coordinates":[-77.360393,38.983112],"type":"Point"}
}