{
  "type": "Feature",
  "properties": {
    "addr:full":"3218 Wallingford Ln Keswick VA 22947",
    "addr:housenumber":"3218",
    "addr:postcode":"22947",
    "addr:street":"Wallingford Ln",
    "iso:country":"US",
    "sg:address":"3218 Wallingford Ln",
    "sg:city":"Keswick",
    "sg:classifiers":[
        {
            "category":"Building & Trades",
            "subcategory":"Construction",
            "type":"Services"
        }
    ],
    "sg:phone":"+1 434 973 9383",
    "sg:postcode":"22947",
    "sg:province":"VA",
    "sg:tags":[
        "home",
        "builder"
    ],
    "wof:name":"Preston Stallings Inc",
    "wof:placetype":"venue"
},
  "geometry": {"coordinates":[-78.384739,37.996419],"type":"Point"}
}