{
  "type": "Feature",
  "properties": {
    "iso:country":"US",
    "sg:address":"7907 Kincannon Pl",
    "sg:city":"Lorton",
    "sg:classifiers":[
        {
            "category":"Manufacturing",
            "subcategory":"Furniture",
            "type":"Manufacturing & Wholesale Goods"
        }
    ],
    "sg:phone":"+1 703 550 1035",
    "sg:postcode":"22079",
    "sg:province":"VA",
    "sg:tags":[
        "wood",
        "mfg"
    ],
    "wof:name":"Perceptions Of Virginia Inc",
    "wof:placetype":"venue"
},
  "geometry": {"coordinates":[-77.176277,38.741156],"type":"Point"}
}