{
  "type": "Feature",
  "properties": {
    "addr:full":"20605 Bellwood Ct Sterling VA 20165",
    "addr:postcode":"20605;20165",
    "addr:street":"Bellwood Ct",
    "iso:country":"US",
    "sg:address":"20605 Bellwood Ct",
    "sg:city":"Sterling",
    "sg:classifiers":[
        {
            "category":"Retail",
            "subcategory":"Laundry & Dry Cleaning",
            "type":"Services"
        }
    ],
    "sg:phone":"+1 703 430 3915",
    "sg:postcode":"20165",
    "sg:province":"VA",
    "wof:name":"Esques Inc",
    "wof:placetype":"venue"
},
  "geometry": {"coordinates":[-77.396761,39.045267],"type":"Point"}
}