{
  "type": "Feature",
  "properties": {
    "iso:country":"US",
    "sg:address":"210 Harmony Dr SW",
    "sg:city":"Vienna",
    "sg:classifiers":[
        {
            "category":"Professional",
            "subcategory":"Management & Consulting",
            "type":"Services"
        }
    ],
    "sg:phone":"+1 703 938 4014",
    "sg:postcode":"22180",
    "sg:province":"VA",
    "sg:tags":[
        "coaching",
        "executive"
    ],
    "wof:name":"Fearthainne Group LLC",
    "wof:placetype":"venue"
},
  "geometry": {"coordinates":[-77.258054,38.888852],"type":"Point"}
}