{
  "type": "Feature",
  "properties": {
    "addr:full":"6662 Chestnut Ave Falls Church VA 22042",
    "addr:housenumber":"6662",
    "addr:postcode":"22042",
    "addr:street":"Chestnut Ave",
    "iso:country":"US",
    "sg:address":"6662 Chestnut Ave",
    "sg:city":"Falls Church",
    "sg:classifiers":[
        {
            "category":"Professional",
            "type":"Services"
        }
    ],
    "sg:phone":"+1 703 241 9351",
    "sg:postcode":"22042",
    "sg:province":"VA",
    "wof:name":"Intrepid Inc",
    "wof:placetype":"venue"
},
  "geometry": {"coordinates":[-77.17510900000001,38.87369],"type":"Point"}
}