{
  "type": "Feature",
  "properties": {
    "addr:full":"84 Southgate Sq Colonial Heights VA 23834",
    "addr:housenumber":"84",
    "addr:postcode":"23834",
    "addr:street":"Southgate Sq",
    "iso:country":"US",
    "sg:address":"84 Southgate Sq",
    "sg:city":"Colonial Heights",
    "sg:classifiers":[
        {
            "category":"Shopping",
            "subcategory":"Stationery & Office Supplies",
            "type":"Retail Goods"
        }
    ],
    "sg:phone":"+1 804 524 9010",
    "sg:postcode":"23834",
    "sg:province":"VA",
    "wof:name":"Staples The Office Superstore",
    "wof:placetype":"venue"
},
  "geometry": {"coordinates":[-77.39176399999999,37.246851],"type":"Point"}
}