{
  "type": "Feature",
  "properties": {
    "iso:country":"US",
    "sg:address":"5220 Hazelridge Rd NW",
    "sg:city":"Roanoke",
    "sg:classifiers":[
        {
            "category":"Health Services",
            "subcategory":"Hospital",
            "type":"Services"
        }
    ],
    "sg:phone":"+1 540 366 9156",
    "sg:postcode":"24012",
    "sg:province":"VA",
    "sg:tags":[
        "mental"
    ],
    "sg:website":"www.brbh.org",
    "wof:name":"Hazelridge Intermediate Care",
    "wof:placetype":"venue"
},
  "geometry": {"coordinates":[-79.95135999999999,37.325089],"type":"Point"}
}