{
  "type": "Feature",
  "properties": {
    "addr:full":"2601 Castle Hill Rd Midlothian VA 23113",
    "addr:housenumber":"2601",
    "addr:postcode":"23113",
    "addr:street":"Castle Hill Rd",
    "iso:country":"US",
    "sg:address":"2601 Castle Hill Rd",
    "sg:city":"Midlothian",
    "sg:classifiers":[
        {
            "category":"Communications",
            "type":"Services"
        }
    ],
    "sg:phone":"+1 804 330 2929",
    "sg:postcode":"23113",
    "sg:province":"VA",
    "sg:tags":[
        "communication"
    ],
    "wof:name":"E & C Communications LLC",
    "wof:placetype":"venue"
},
  "geometry": {"coordinates":[-77.604551,37.53139],"type":"Point"}
}