{
  "type": "Feature",
  "properties": {
    "iso:country":"US",
    "sg:address":"6612 Spring Valley Dr",
    "sg:city":"Alexandria",
    "sg:classifiers":[
        {
            "category":"Shopping",
            "subcategory":"Computers & Home Electronics",
            "type":"Retail Goods"
        }
    ],
    "sg:phone":"+1 703 750 2228",
    "sg:postcode":"22312",
    "sg:province":"VA",
    "sg:tags":[
        "software"
    ],
    "wof:name":"MAI Enterprises Inc",
    "wof:placetype":"venue"
},
  "geometry": {"coordinates":[-77.171964,38.81486],"type":"Point"}
}