{
  "type": "Feature",
  "properties": {
    "addr:full":"2168 White House Rd Moneta VA 24121",
    "addr:housenumber":"2168",
    "addr:postcode":"24121",
    "addr:street":"White House Rd",
    "iso:country":"US",
    "sg:address":"2168 White House Rd",
    "sg:city":"Moneta",
    "sg:classifiers":[
        {
            "category":"Freight",
            "type":"Transportation"
        }
    ],
    "sg:phone":"+1 540 297 3529",
    "sg:postcode":"24121",
    "sg:province":"VA",
    "sg:tags":[
        "commercial",
        "storage"
    ],
    "wof:name":"608 Mini Storage",
    "wof:placetype":"venue"
},
  "geometry": {"coordinates":[-79.61432499999999,37.165907],"type":"Point"}
}