{
  "type": "Feature",
  "properties": {
    "addr:full":"176 Commodore Dr Norfolk VA 23503",
    "addr:housenumber":"176",
    "addr:postcode":"23503",
    "addr:street":"Commodore Dr",
    "iso:country":"US",
    "sg:address":"176 Commodore Dr",
    "sg:city":"Norfolk",
    "sg:classifiers":[
        {
            "category":"Health Services",
            "subcategory":"Clinic",
            "type":"Services"
        }
    ],
    "sg:phone":"+1 757 588 4262",
    "sg:postcode":"23503",
    "sg:province":"VA",
    "sg:tags":[
        "merchandise"
    ],
    "wof:name":"Pickering Hearing Aids",
    "wof:placetype":"venue"
},
  "geometry": {"coordinates":[-76.26652,36.939492],"type":"Point"}
}