{
  "type": "Feature",
  "properties": {
    "iso:country":"US",
    "sg:address":"113 S Hill Ave",
    "sg:city":"South Hill",
    "sg:classifiers":[
        {
            "category":"Professional",
            "subcategory":"Business Services",
            "type":"Services"
        }
    ],
    "sg:phone":"+1 434 447 2606",
    "sg:postcode":"23970",
    "sg:province":"VA",
    "wof:name":"A Bail Bonds",
    "wof:placetype":"venue"
},
  "geometry": {"coordinates":[-78.130735,36.724545],"type":"Point"}
}