{
  "type": "Feature",
  "properties": {
    "addr:full":"1750 Tysons Blvd Vienna VA 22182",
    "addr:housenumber":"1750",
    "addr:postcode":"22182",
    "addr:street":"Tysons Blvd",
    "iso:country":"US",
    "sg:address":"1750 Tysons Blvd",
    "sg:city":"Vienna",
    "sg:classifiers":[
        {
            "category":"Professional",
            "subcategory":"Employment Agencies",
            "type":"Services"
        }
    ],
    "sg:phone":"+1 703 790 1100",
    "sg:postcode":"22182",
    "sg:province":"VA",
    "wof:name":"Spherion",
    "wof:placetype":"venue"
},
  "geometry": {"coordinates":[-77.2603,38.923801],"type":"Point"}
}