{
  "type": "Feature",
  "properties": {
    "iso:country":"US",
    "sg:address":"3323 Willow Cresent Dr",
    "sg:city":"Fairfax",
    "sg:classifiers":[
        {
            "category":"Manufacturing",
            "subcategory":"Printing",
            "type":"Manufacturing & Wholesale Goods"
        }
    ],
    "sg:phone":"+1 703 691 9778",
    "sg:postcode":"22030",
    "sg:province":"VA",
    "sg:tags":[
        "printer"
    ],
    "wof:name":"Progress Printing Co",
    "wof:placetype":"venue"
},
  "geometry": {"coordinates":[-77.30390199999999,38.868573],"type":"Point"}
}