{
  "type": "Feature",
  "properties": {
    "addr:full":"2420 Wilson Blvd Ste 101 Arlington VA 22201",
    "addr:housenumber":"2420",
    "addr:postcode":"22201",
    "addr:street":"Wilson Blvd Ste 101",
    "iso:country":"US",
    "sg:address":"2420 Wilson Blvd Ste 101",
    "sg:city":"Arlington",
    "sg:classifiers":[
        {
            "category":"Real Estate",
            "subcategory":"Developer",
            "type":"Services"
        }
    ],
    "sg:phone":"+1 703 524 9639",
    "sg:postcode":"22201",
    "sg:province":"VA",
    "sg:tags":[
        "investing"
    ],
    "wof:name":"Griffin Head R&D",
    "wof:placetype":"venue"
},
  "geometry": {"coordinates":[-77.087737,38.890764],"type":"Point"}
}