{
  "type": "Feature",
  "properties": {
    "addr:full":"100 Club Way Seaford VA 23696",
    "addr:housenumber":"100",
    "addr:postcode":"23696",
    "addr:street":"Club Way",
    "iso:country":"US",
    "sg:address":"100 Club Way",
    "sg:city":"Seaford",
    "sg:classifiers":[
        {
            "category":"Organizations",
            "subcategory":"Community Association",
            "type":"Services"
        }
    ],
    "sg:phone":"+1 757 890 2878",
    "sg:postcode":"23696",
    "sg:province":"VA",
    "sg:tags":[
        "club"
    ],
    "wof:name":"Seaford Woman's Club",
    "wof:placetype":"venue"
},
  "geometry": {"coordinates":[-76.43046099999999,37.194691],"type":"Point"}
}