{
  "type": "Feature",
  "properties": {
    "addr:full":"14452 del Mar Dr Woodbridge VA 22193",
    "addr:housenumber":"14452",
    "addr:postcode":"22193",
    "addr:street":"Del Mar Dr",
    "iso:country":"US",
    "sg:address":"14452 del Mar Dr",
    "sg:city":"Woodbridge",
    "sg:classifiers":[
        {
            "category":"Professional",
            "type":"Services"
        }
    ],
    "sg:phone":"+1 703 680 4347",
    "sg:postcode":"22193",
    "sg:province":"VA",
    "sg:tags":[
        "establishment"
    ],
    "wof:name":"Phoenix Enterprise Of Virginia",
    "wof:placetype":"venue"
},
  "geometry": {"coordinates":[-77.33233799999999,38.638391],"type":"Point"}
}