{
  "type": "Feature",
  "properties": {
    "addr:full":"4626 Jefferson Davis Hwy Richmond VA 23234",
    "addr:housenumber":"4626",
    "addr:postcode":"23234",
    "addr:street":"Jefferson Davis Hwy",
    "iso:country":"US",
    "sg:address":"4626 Jefferson Davis Hwy",
    "sg:city":"Richmond",
    "sg:classifiers":[
        {
            "category":"Shopping",
            "subcategory":"Clothing, Apparel, & Fashions",
            "type":"Retail Goods"
        }
    ],
    "sg:phone":"+1 804 279 0808",
    "sg:postcode":"23234",
    "sg:province":"VA",
    "sg:tags":[
        "item",
        "boutique"
    ],
    "wof:name":"Commercial Marielena",
    "wof:placetype":"venue"
},
  "geometry": {"coordinates":[-77.442533,37.463138],"type":"Point"}
}