{
  "type": "Feature",
  "properties": {
    "addr:full":"14501 Hancock Village St Chesterfield VA 23832",
    "addr:housenumber":"14501",
    "addr:postcode":"23832",
    "addr:street":"Hancock Village St",
    "iso:country":"US",
    "sg:address":"14501 Hancock Village St",
    "sg:city":"Chesterfield",
    "sg:classifiers":[
        {
            "category":"Shopping",
            "subcategory":"Department Store",
            "type":"Retail Goods"
        },
        {
            "category":"Shopping",
            "subcategory":"Clothing, Apparel, & Fashions",
            "type":"Retail Goods"
        },
        {
            "category":"Shopping",
            "type":"Retail Goods"
        },
        {
            "category":"Shopping",
            "subcategory":"Discount & Variety Stores",
            "type":"Retail Goods"
        }
    ],
    "sg:phone":"+1 804 739 2119",
    "sg:postcode":"23832",
    "sg:province":"VA",
    "sg:tags":[
        "clothing",
        "merchandise"
    ],
    "sg:website":"http://www.walmart.com",
    "wof:name":"Wal-Mart",
    "wof:placetype":"venue"
},
  "geometry": {"coordinates":[-77.67604799999999,37.40229],"type":"Point"}
}