{
  "type": "Feature",
  "properties": {
    "iso:country":"US",
    "sg:address":"10481 Cobbs Rd",
    "sg:city":"Glen Allen",
    "sg:classifiers":[
        {
            "category":"Retail",
            "subcategory":"Auto Repair",
            "type":"Services"
        }
    ],
    "sg:phone":"+1 804 752 6004",
    "sg:postcode":"23059",
    "sg:province":"VA",
    "sg:tags":[
        "repairing",
        "automobile"
    ],
    "wof:name":"Basic Auto Sales Shop",
    "wof:placetype":"venue"
},
  "geometry": {"coordinates":[-77.469718,37.721182],"type":"Point"}
}