{
  "type": "Feature",
  "properties": {
    "addr:full":"1541 Indiana Ave Virginia Beach VA 23454",
    "addr:housenumber":"1541",
    "addr:postcode":"23454",
    "addr:street":"Indiana Ave",
    "iso:country":"US",
    "sg:address":"1541 Indiana Ave",
    "sg:city":"Virginia Beach",
    "sg:classifiers":[
        {
            "category":"Building & Trades",
            "subcategory":"Construction",
            "type":"Services"
        }
    ],
    "sg:phone":"+1 757 435 4240",
    "sg:postcode":"23454",
    "sg:province":"VA",
    "sg:tags":[
        "contractor"
    ],
    "wof:name":"J P Martin Contracting",
    "wof:placetype":"venue"
},
  "geometry": {"coordinates":[-76.01716500000001,36.840002],"type":"Point"}
}