{
  "type": "Feature",
  "properties": {
    "addr:full":"11913 Tidewater Trl Fredericksburg VA 22408",
    "addr:housenumber":"11913",
    "addr:postcode":"22408",
    "addr:street":"Tidewater Trl",
    "iso:country":"US",
    "sg:address":"11913 Tidewater Trl",
    "sg:city":"Fredericksburg",
    "sg:classifiers":[
        {
            "category":"Retail",
            "subcategory":"Car Wash",
            "type":"Services"
        }
    ],
    "sg:phone":"+1 540 372 9911",
    "sg:postcode":"22408",
    "sg:province":"VA",
    "sg:tags":[
        "carwash"
    ],
    "wof:name":"Mobile Detailers",
    "wof:placetype":"venue"
},
  "geometry": {"coordinates":[-77.454234,38.2834],"type":"Point"}
}