{
  "type": "Feature",
  "properties": {
    "iso:country":"US",
    "sg:address":"3530 Glisson Rd",
    "sg:city":"Richmond",
    "sg:classifiers":[
        {
            "category":"Professional",
            "subcategory":"Computer Services",
            "type":"Services"
        }
    ],
    "sg:phone":"+1 804 275 8880",
    "sg:postcode":"23237",
    "sg:province":"VA",
    "sg:tags":[
        "design",
        "system"
    ],
    "wof:name":"Precision Computer Consulting",
    "wof:placetype":"venue"
},
  "geometry": {"coordinates":[-77.45258800000001,37.402496],"type":"Point"}
}