{
  "type": "Feature",
  "properties": {
    "addr:full":"200 E Carolina Ave Crewe VA 23930",
    "addr:housenumber":"200",
    "addr:postcode":"23930",
    "addr:street":"E Carolina Ave",
    "iso:country":"US",
    "sg:address":"200 E Carolina Ave",
    "sg:city":"Crewe",
    "sg:classifiers":[
        {
            "category":"Utilities",
            "subcategory":"Mobile Phone",
            "type":"Services"
        }
    ],
    "sg:phone":"+1 434 645 1687",
    "sg:postcode":"23930",
    "sg:province":"VA",
    "sg:tags":[
        "equipment",
        "paging",
        "signaling",
        "system"
    ],
    "wof:name":"Mc Millian Pager Svc",
    "wof:placetype":"venue"
},
  "geometry": {"coordinates":[-78.12338,37.174893],"type":"Point"}
}