{
  "type": "Feature",
  "properties": {
    "iso:country":"US",
    "sg:address":"685 Tripple Creek Rd",
    "sg:city":"Rocky Mount",
    "sg:classifiers":[
        {
            "category":"Professional",
            "type":"Services"
        }
    ],
    "sg:phone":"+1 540 484 0355",
    "sg:postcode":"24151",
    "sg:province":"VA",
    "sg:tags":[
        "establishment"
    ],
    "wof:name":"Ronile Inc",
    "wof:placetype":"venue"
},
  "geometry": {"coordinates":[-79.869896,36.971861],"type":"Point"}
}