{
  "type": "Feature",
  "properties": {
    "iso:country":"US",
    "sg:address":"719 Tanbark Dr",
    "sg:city":"Newport News",
    "sg:classifiers":[
        {
            "category":"Professional",
            "subcategory":"Employment Agencies",
            "type":"Services"
        }
    ],
    "sg:phone":"+1 757 329 7888",
    "sg:postcode":"23601",
    "sg:province":"VA",
    "sg:tags":[
        "help",
        "supply"
    ],
    "wof:name":"George K Horsley",
    "wof:placetype":"venue"
},
  "geometry": {"coordinates":[-76.456395,37.058955],"type":"Point"}
}