{
  "type": "Feature",
  "properties": {
    "addr:full":"6351 Columbia Pike Falls Church VA 22041",
    "addr:housenumber":"6351",
    "addr:postcode":"22041",
    "addr:street":"Columbia Pike",
    "iso:country":"US",
    "sg:address":"6351 Columbia Pike",
    "sg:city":"Falls Church",
    "sg:classifiers":[
        {
            "category":"Food & Beverages",
            "subcategory":"Groceries & Convenience Stores",
            "type":"Retail Goods"
        }
    ],
    "sg:phone":"+1 703 256 6615",
    "sg:postcode":"22041",
    "sg:province":"VA",
    "sg:tags":[
        "grocer",
        "supermarket"
    ],
    "wof:name":"Harris Teeter Inc",
    "wof:placetype":"venue"
},
  "geometry": {"coordinates":[-77.156092,38.836986],"type":"Point"}
}