{
  "type": "Feature",
  "properties": {
    "iso:country":"US",
    "sg:address":"8393 Sudley Rd",
    "sg:city":"Manassas",
    "sg:classifiers":[
        {
            "category":"Shopping",
            "subcategory":"Shoes",
            "type":"Retail Goods"
        }
    ],
    "sg:phone":"+1 703 361 6143",
    "sg:postcode":"20109",
    "sg:province":"VA",
    "wof:name":"Payless Shoesource",
    "wof:placetype":"venue"
},
  "geometry": {"coordinates":[-77.503974,38.776007],"type":"Point"}
}