{
  "type": "Feature",
  "properties": {
    "addr:full":"300 N River Rd Bridgewater VA 22812",
    "addr:housenumber":"300",
    "addr:postcode":"22812",
    "addr:street":"N River Rd",
    "iso:country":"US",
    "sg:address":"300 N River Rd",
    "sg:city":"Bridgewater",
    "sg:classifiers":[
        {
            "category":"Banks & Credit Unions",
            "subcategory":"Investment Brokerage",
            "type":"Services"
        },
        {
            "category":"Professional",
            "subcategory":"Business Services",
            "type":"Services"
        }
    ],
    "sg:phone":"+1 540 828 2002",
    "sg:postcode":"22812",
    "sg:province":"VA",
    "sg:tags":[
        "advisory",
        "financial"
    ],
    "wof:name":"Summit Debt Solutions Inc",
    "wof:placetype":"venue"
},
  "geometry": {"coordinates":[-78.972635,38.388824],"type":"Point"}
}