{
  "type": "Feature",
  "properties": {
    "addr:full":"6405C Dickens Pl Richmond VA 23230",
    "addr:housenumber":"6405c",
    "addr:postcode":"23230",
    "addr:street":"Dickens Pl",
    "iso:country":"US",
    "sg:address":"6405C Dickens Pl",
    "sg:city":"Richmond",
    "sg:classifiers":[
        {
            "category":"Utilities",
            "subcategory":"Mobile Phone",
            "type":"Services"
        },
        {
            "category":"Shopping",
            "subcategory":"Mobile Phones",
            "type":"Retail Goods"
        }
    ],
    "sg:phone":"+1 804 912 2657",
    "sg:postcode":"23230",
    "sg:province":"VA",
    "sg:tags":[
        "supply",
        "communication",
        "telephone",
        "wireless",
        "equipment",
        "cellular"
    ],
    "sg:website":"http://www.cellularsales.com",
    "wof:name":"Cellular Sales",
    "wof:placetype":"venue"
},
  "geometry": {"coordinates":[-77.510935,37.598777],"type":"Point"}
}