{
  "type": "Feature",
  "properties": {
    "addr:full":"4293 Holland Rd Virginia Beach VA 23452",
    "addr:housenumber":"4293",
    "addr:postcode":"23452",
    "addr:street":"Holland Rd",
    "iso:country":"US",
    "sg:address":"4293 Holland Rd",
    "sg:city":"Virginia Beach",
    "sg:classifiers":[
        {
            "category":"Freight",
            "type":"Transportation"
        }
    ],
    "sg:phone":"+1 757 495 8738",
    "sg:postcode":"23452",
    "sg:province":"VA",
    "sg:tags":[
        "commercial",
        "storage"
    ],
    "wof:name":"Jack Rabbit Self Storage",
    "wof:placetype":"venue"
},
  "geometry": {"coordinates":[-76.121809,36.820391],"type":"Point"}
}