{
  "type": "Feature",
  "properties": {
    "iso:country":"US",
    "sg:address":"11110 Kimages Rd",
    "sg:city":"Charles City",
    "sg:classifiers":[
        {
            "category":"Government",
            "subcategory":"Office",
            "type":"Public Place"
        }
    ],
    "sg:phone":"+1 804 829 2421",
    "sg:postcode":"23030",
    "sg:province":"VA",
    "sg:tags":[
        "fish",
        "wildlife"
    ],
    "wof:name":"Harrison Lake Nat Fish Htchy",
    "wof:placetype":"venue"
},
  "geometry": {"coordinates":[-77.194365,37.338799],"type":"Point"}
}