{
  "type": "Feature",
  "properties": {
    "iso:country":"US",
    "sg:address":"2185 Haden Martin Rd",
    "sg:city":"Palmyra",
    "sg:classifiers":[
        {
            "category":"Manufacturing",
            "subcategory":"Printing",
            "type":"Manufacturing & Wholesale Goods"
        }
    ],
    "sg:phone":"+1 434 589 6634",
    "sg:postcode":"22963",
    "sg:province":"VA",
    "sg:tags":[
        "printer",
        "commercial"
    ],
    "wof:name":"Palmyra Press Inc",
    "wof:placetype":"venue"
},
  "geometry": {"coordinates":[-78.325461,37.833314],"type":"Point"}
}