{
  "type": "Feature",
  "properties": {
    "addr:full":"47022 Bainbridge Pl Sterling VA 20165",
    "addr:housenumber":"47022",
    "addr:postcode":"20165",
    "addr:street":"Bainbridge Pl",
    "iso:country":"US",
    "sg:address":"47022 Bainbridge Pl",
    "sg:city":"Sterling",
    "sg:classifiers":[
        {
            "category":"Banks & Credit Unions",
            "subcategory":"Investment Brokerage",
            "type":"Services"
        }
    ],
    "sg:phone":"+1 703 404 6969",
    "sg:postcode":"20165",
    "sg:province":"VA",
    "sg:tags":[
        "advisory"
    ],
    "wof:name":"Synergy Financial Services",
    "wof:placetype":"venue"
},
  "geometry": {"coordinates":[-77.372291,39.046591],"type":"Point"}
}