{
  "type": "Feature",
  "properties": {
    "iso:country":"US",
    "sg:address":"6420 George Washington Memorial Hwy",
    "sg:city":"Grafton",
    "sg:classifiers":[
        {
            "category":"Retail",
            "subcategory":"Repair Shop",
            "type":"Services"
        }
    ],
    "sg:phone":"+1 757 898 6665",
    "sg:postcode":"23692",
    "sg:province":"VA",
    "sg:tags":[
        "appliance"
    ],
    "wof:name":"Baker Appliance & Refrig Svc",
    "wof:placetype":"venue"
},
  "geometry": {"coordinates":[-76.47224799999999,37.170011],"type":"Point"}
}