{
  "type": "Feature",
  "properties": {
    "addr:full":"408 Hale St Pearisburg VA 24134",
    "addr:housenumber":"408",
    "addr:postcode":"24134",
    "addr:street":"Hale St",
    "iso:country":"US",
    "sg:address":"408 Hale St",
    "sg:city":"Pearisburg",
    "sg:classifiers":[
        {
            "category":"Professional",
            "subcategory":"Management & Consulting",
            "type":"Services"
        }
    ],
    "sg:phone":"+1 540 921 1606",
    "sg:postcode":"24134",
    "sg:province":"VA",
    "sg:tags":[
        "development",
        "industrial"
    ],
    "wof:name":"New River Valley Planning",
    "wof:placetype":"venue"
},
  "geometry": {"coordinates":[-80.725987,37.331706],"type":"Point"}
}