{
  "type": "Feature",
  "properties": {
    "iso:country":"US",
    "sg:address":"1600 Grady Ave Apt 201",
    "sg:city":"Charlottesvle",
    "sg:classifiers":[
        {
            "category":"Real Estate",
            "subcategory":"Real Estate Operator",
            "type":"Services"
        }
    ],
    "sg:phone":"+1 434 971 8013",
    "sg:postcode":"22903",
    "sg:province":"VA",
    "sg:tags":[
        "apartment"
    ],
    "wof:name":"Preston Court Limited",
    "wof:placetype":"venue"
},
  "geometry": {"coordinates":[-78.498249,38.040849],"type":"Point"}
}