{
  "type": "Feature",
  "properties": {
    "addr:full":"1021 E Main St Waynesboro VA 22980",
    "addr:housenumber":"1021",
    "addr:postcode":"22980",
    "addr:street":"E Main St",
    "iso:country":"US",
    "sg:address":"1021 E Main St",
    "sg:city":"Waynesboro",
    "sg:classifiers":[
        {
            "category":"Real Estate",
            "subcategory":"Real Estate Operator",
            "type":"Services"
        }
    ],
    "sg:phone":"+1 540 943 4411",
    "sg:postcode":"22980",
    "sg:province":"VA",
    "sg:tags":[
        "mobile",
        "home",
        "community"
    ],
    "wof:name":"Patch's Trailer Sales",
    "wof:placetype":"venue"
},
  "geometry": {"coordinates":[-78.873696,38.064425],"type":"Point"}
}