{
  "type": "Feature",
  "properties": {
    "addr:full":"1292 W Main St Abingdon VA 24210",
    "addr:housenumber":"1292",
    "addr:postcode":"24210",
    "addr:street":"W Main St",
    "iso:country":"US",
    "sg:address":"1292 W Main St",
    "sg:city":"Abingdon",
    "sg:classifiers":[
        {
            "category":"Home & Garden",
            "subcategory":"Garden Supply",
            "type":"Retail Goods"
        }
    ],
    "sg:phone":"+1 276 628 8182",
    "sg:postcode":"24210",
    "sg:province":"VA",
    "sg:tags":[
        "lawn",
        "mower"
    ],
    "wof:name":"Abingdon Mower & Service Ctr",
    "wof:placetype":"venue"
},
  "geometry": {"coordinates":[-82.017644,36.695193],"type":"Point"}
}