{
  "type": "Feature",
  "properties": {
    "addr:full":"1909 Pelham Dr Roanoke VA 24018",
    "addr:housenumber":"1909",
    "addr:postcode":"24018",
    "addr:street":"Pelham Dr",
    "iso:country":"US",
    "sg:address":"1909 Pelham Dr",
    "sg:city":"Roanoke",
    "sg:classifiers":[
        {
            "category":"Real Estate",
            "subcategory":"Real Estate Agent",
            "type":"Services"
        }
    ],
    "sg:phone":"+1 540 989 3444",
    "sg:postcode":"24018",
    "sg:province":"VA",
    "wof:name":"Batey Enterprises Inc",
    "wof:placetype":"venue"
},
  "geometry": {"coordinates":[-80.03761299999999,37.238488],"type":"Point"}
}