{
  "type": "Feature",
  "properties": {
    "iso:country":"US",
    "sg:address":"1127 Marion Ave",
    "sg:city":"Mc Lean",
    "sg:classifiers":[
        {
            "category":"Shopping",
            "type":"Retail Goods"
        }
    ],
    "sg:phone":"+1 703 356 4807",
    "sg:postcode":"22101",
    "sg:province":"VA",
    "sg:tags":[
        "art",
        "dealer"
    ],
    "wof:name":"Allen Water Fowl Art",
    "wof:placetype":"venue"
},
  "geometry": {"coordinates":[-77.168808,38.942212],"type":"Point"}
}