{
  "type": "Feature",
  "properties": {
    "iso:country":"US",
    "sg:address":"324 Capon Springs Grade",
    "sg:city":"Star Tannery",
    "sg:classifiers":[
        {
            "category":"Professional",
            "subcategory":"Business Services",
            "type":"Services"
        }
    ],
    "sg:phone":"+1 540 465 8889",
    "sg:postcode":"22654",
    "sg:province":"VA",
    "sg:tags":[
        "product",
        "mfg"
    ],
    "wof:name":"Shutru LLC",
    "wof:placetype":"venue"
},
  "geometry": {"coordinates":[-78.483239,39.101316],"type":"Point"}
}