{
  "type": "Feature",
  "properties": {
    "addr:full":"1626 Craig Ln Mc Lean VA 22101",
    "addr:housenumber":"1626",
    "addr:postcode":"22101",
    "addr:street":"Craig Ln Mc Lean",
    "iso:country":"US",
    "sg:address":"1626 Craig Ln",
    "sg:city":"Mc Lean",
    "sg:classifiers":[
        {
            "category":"Building & Trades",
            "subcategory":"Construction",
            "type":"Services"
        }
    ],
    "sg:phone":"+1 703 506 8506",
    "sg:postcode":"22101",
    "sg:province":"VA",
    "sg:tags":[
        "concrete",
        "contractor"
    ],
    "wof:name":"Bravos Concrete Inc",
    "wof:placetype":"venue"
},
  "geometry": {"coordinates":[-77.183438,38.92315],"type":"Point"}
}