{
  "type": "Feature",
  "properties": {
    "iso:country":"US",
    "sg:address":"403 Stockton St",
    "sg:city":"Richmond",
    "sg:classifiers":[
        {
            "category":"Real Estate",
            "subcategory":"Architect",
            "type":"Services"
        }
    ],
    "sg:phone":"+1 804 233 5343",
    "sg:postcode":"23224",
    "sg:province":"VA",
    "wof:name":"SMBW Architects",
    "wof:placetype":"venue"
},
  "geometry": {"coordinates":[-77.436841,37.522855],"type":"Point"}
}