{
  "type": "Feature",
  "properties": {
    "iso:country":"US",
    "sg:address":"10377 Warwick Blvd",
    "sg:city":"Newport News",
    "sg:classifiers":[
        {
            "category":"Shopping",
            "subcategory":"Used Merchandise",
            "type":"Retail Goods"
        }
    ],
    "sg:phone":"+1 757 595 1545",
    "sg:postcode":"23601",
    "sg:province":"VA",
    "sg:tags":[
        "antique",
        "craft",
        "flower",
        "gift"
    ],
    "wof:name":"Plantiques-Hilton Village",
    "wof:placetype":"venue"
},
  "geometry": {"coordinates":[-76.46049499999999,37.032363],"type":"Point"}
}