{
  "type": "Feature",
  "properties": {
    "iso:country":"US",
    "sg:address":"8724 Clydesdale Rd",
    "sg:city":"Springfield",
    "sg:classifiers":[
        {
            "category":"Shopping",
            "subcategory":"Florist",
            "type":"Retail Goods"
        }
    ],
    "sg:phone":"+1 703 425 9824",
    "sg:postcode":"22151",
    "sg:province":"VA",
    "wof:name":"Garlands",
    "wof:placetype":"venue"
},
  "geometry": {"coordinates":[-77.249048,38.80377],"type":"Point"}
}