{
  "type": "Feature",
  "properties": {
    "iso:country":"US",
    "sg:address":"1800 Seaboard Ave",
    "sg:city":"Portsmouth",
    "sg:classifiers":[
        {
            "category":"Freight",
            "type":"Transportation"
        }
    ],
    "sg:phone":"+1 757 398 9234",
    "sg:postcode":"23707",
    "sg:province":"VA",
    "sg:tags":[
        "arrangement"
    ],
    "wof:name":"A P L Limited",
    "wof:placetype":"venue"
},
  "geometry": {"coordinates":[-76.327326,36.855999],"type":"Point"}
}