{
  "type": "Feature",
  "properties": {
    "addr:full":"17026 Bull Church Rd Woodford VA 22580",
    "addr:housenumber":"17026",
    "addr:postcode":"22580",
    "addr:street":"Bull Church Rd",
    "iso:country":"US",
    "sg:address":"17026 Bull Church Rd",
    "sg:city":"Woodford",
    "sg:classifiers":[
        {
            "category":"Professional",
            "subcategory":"Advertising",
            "type":"Services"
        }
    ],
    "sg:phone":"+1 804 448 8900",
    "sg:postcode":"22580",
    "sg:province":"VA",
    "sg:tags":[
        "mailing",
        "shipping"
    ],
    "wof:name":"Patton Kiehl Group Inc",
    "wof:placetype":"venue"
},
  "geometry": {"coordinates":[-77.491471,38.030772],"type":"Point"}
}