{
  "type": "Feature",
  "properties": {
    "iso:country":"US",
    "sg:address":"200 Four Seasons Dr",
    "sg:city":"Charlottesville",
    "sg:classifiers":[
        {
            "category":"Social Services",
            "subcategory":"Child Care",
            "type":"Services"
        }
    ],
    "sg:phone":"+1 434 295 9055",
    "sg:postcode":"22901",
    "sg:province":"VA",
    "sg:tags":[
        "kindergarten",
        "academic",
        "school"
    ],
    "wof:name":"Montessori School Inc",
    "wof:placetype":"venue"
},
  "geometry": {"coordinates":[-78.48509799999999,38.07842],"type":"Point"}
}