{
  "type": "Feature",
  "properties": {
    "addr:full":"14900 Conference Center Dr Chantilly VA 20151",
    "addr:housenumber":"14900",
    "addr:postcode":"20151",
    "addr:street":"Conference Center Dr",
    "iso:country":"US",
    "sg:address":"14900 Conference Center Dr",
    "sg:city":"Chantilly",
    "sg:classifiers":[
        {
            "category":"Professional",
            "subcategory":"Management & Consulting",
            "type":"Services"
        }
    ],
    "sg:phone":"+1 703 961 7927",
    "sg:postcode":"20151",
    "sg:province":"VA",
    "sg:tags":[
        "subcontractor",
        "gov"
    ],
    "wof:name":"Sosacorp",
    "wof:placetype":"venue"
},
  "geometry": {"coordinates":[-77.456934,38.875677],"type":"Point"}
}