{
  "type": "Feature",
  "properties": {
    "addr:full":"10467 White Granite Dr Oakton VA 22124",
    "addr:housenumber":"10467",
    "addr:postcode":"22124",
    "addr:street":"White Granite Dr",
    "iso:country":"US",
    "sg:address":"10467 White Granite Dr",
    "sg:city":"Oakton",
    "sg:classifiers":[
        {
            "category":"Professional",
            "subcategory":"Engineering",
            "type":"Services"
        }
    ],
    "sg:phone":"+1 703 591 0615",
    "sg:postcode":"22124",
    "sg:province":"VA",
    "sg:tags":[
        "engineer"
    ],
    "wof:name":"Oakton Three Engineers Ofc",
    "wof:placetype":"venue"
},
  "geometry": {"coordinates":[-77.30551699999999,38.87268],"type":"Point"}
}