{
  "type": "Feature",
  "properties": {
    "addr:full":"8341 Lewinsville Rd Mc Lean VA 22102",
    "addr:housenumber":"8341",
    "addr:postcode":"22102",
    "addr:street":"Lewinsville Rd",
    "iso:country":"US",
    "sg:address":"8341 Lewinsville Rd",
    "sg:city":"Mc Lean",
    "sg:classifiers":[
        {
            "category":"Utilities",
            "subcategory":"Refuse",
            "type":"Services"
        }
    ],
    "sg:phone":"+1 703 893 8934",
    "sg:postcode":"22102",
    "sg:province":"VA",
    "sg:tags":[
        "garbage",
        "collection"
    ],
    "wof:name":"Gordon's Refuse Svc",
    "wof:placetype":"venue"
},
  "geometry": {"coordinates":[-77.233322,38.937335],"type":"Point"}
}