{
  "type": "Feature",
  "properties": {
    "iso:country":"US",
    "sg:address":"383 Autumn Hills Ln",
    "sg:city":"Front Royal",
    "sg:classifiers":[
        {
            "category":"Building & Trades",
            "subcategory":"Construction",
            "type":"Services"
        }
    ],
    "sg:phone":"+1 540 635 0444",
    "sg:postcode":"22630",
    "sg:province":"VA",
    "sg:tags":[
        "contractor"
    ],
    "wof:name":"Skyline Drywall & Acoustics",
    "wof:placetype":"venue"
},
  "geometry": {"coordinates":[-78.229827,38.860745],"type":"Point"}
}