{
  "type": "Feature",
  "properties": {
    "addr:full":"6518 Iron Bridge Rd Richmond VA 23234",
    "addr:housenumber":"6518",
    "addr:postcode":"23234",
    "addr:street":"Iron Bridge Rd",
    "iso:country":"US",
    "sg:address":"6518 Iron Bridge Rd",
    "sg:city":"Richmond",
    "sg:classifiers":[
        {
            "category":"Organizations",
            "subcategory":"Religious Organization",
            "type":"Services"
        }
    ],
    "sg:phone":"+1 804 271 1446",
    "sg:postcode":"23234",
    "sg:province":"VA",
    "sg:tags":[
        "church"
    ],
    "wof:name":"Iglesia Triunfante De Jesucris",
    "wof:placetype":"venue"
},
  "geometry": {"coordinates":[-77.494641,37.427895],"type":"Point"}
}