{
  "type": "Feature",
  "properties": {
    "addr:full":"5820 Railroad Ave Crozet VA 22932",
    "addr:housenumber":"5820",
    "addr:postcode":"22932",
    "addr:street":"Railroad Ave",
    "iso:country":"US",
    "sg:address":"5820 Railroad Ave",
    "sg:city":"Crozet",
    "sg:classifiers":[
        {
            "category":"Banks & Credit Unions",
            "subcategory":"Bank",
            "type":"Services"
        }
    ],
    "sg:phone":"+1 434 964 2001",
    "sg:postcode":"22932",
    "sg:province":"VA",
    "wof:name":"University OF Virginia Cu",
    "wof:placetype":"venue"
},
  "geometry": {"coordinates":[-78.701672,38.070564],"type":"Point"}
}