{
  "type": "Feature",
  "properties": {
    "addr:full":"12030 Waples Mill Rd Oakton VA 22124",
    "addr:housenumber":"12030",
    "addr:postcode":"22124",
    "addr:street":"Waples Mill Rd",
    "iso:country":"US",
    "sg:address":"12030 Waples Mill Rd",
    "sg:city":"Oakton",
    "sg:classifiers":[
        {
            "category":"Professional",
            "subcategory":"Management & Consulting",
            "type":"Services"
        }
    ],
    "sg:phone":"+1 703 620 9447",
    "sg:postcode":"22124",
    "sg:province":"VA",
    "wof:name":"Asia Ink",
    "wof:placetype":"venue"
},
  "geometry": {"coordinates":[-77.362433,38.878081],"type":"Point"}
}