{
  "type": "Feature",
  "properties": {
    "addr:full":"108 Pasedena Knoll Martinsville VA 24112",
    "addr:housenumber":"108",
    "addr:postcode":"24112",
    "addr:street":"Pasedena Knoll",
    "iso:country":"US",
    "sg:address":"108 Pasedena Knoll",
    "sg:city":"Martinsville",
    "sg:classifiers":[
        {
            "category":"Retail",
            "subcategory":"Repair Shop",
            "type":"Services"
        }
    ],
    "sg:phone":"+1 276 650 8077",
    "sg:postcode":"24112",
    "sg:province":"VA",
    "sg:tags":[
        "electrical"
    ],
    "wof:name":"Eccles Appliance Repair & Svc",
    "wof:placetype":"venue"
},
  "geometry": {"coordinates":[-79.751594,36.67826],"type":"Point"}
}