{
  "type": "Feature",
  "properties": {
    "iso:country":"US",
    "sg:address":"308 Cambridge Rd",
    "sg:city":"Alexandria",
    "sg:classifiers":[
        {
            "category":"Professional",
            "subcategory":"Testing Lab",
            "type":"Services"
        }
    ],
    "sg:phone":"+1 703 751 4433",
    "sg:postcode":"22314",
    "sg:province":"VA",
    "sg:tags":[
        "consulting",
        "plastic"
    ],
    "wof:name":"S B Swenson",
    "wof:placetype":"venue"
},
  "geometry": {"coordinates":[-77.081428,38.812687],"type":"Point"}
}