{
  "type": "Feature",
  "properties": {
    "addr:full":"1400 Kempsville Rd Chesapeake VA 23320",
    "addr:housenumber":"1400",
    "addr:postcode":"23320",
    "addr:street":"Kempsville Rd",
    "iso:country":"US",
    "sg:address":"1400 Kempsville Rd",
    "sg:city":"Chesapeake",
    "sg:classifiers":[
        {
            "category":"Professional",
            "subcategory":"Advertising",
            "type":"Services"
        }
    ],
    "sg:phone":"+1 757 549 7665",
    "sg:postcode":"23320",
    "sg:province":"VA",
    "sg:tags":[
        "mailing",
        "shipping"
    ],
    "sg:website":"www.shippersheaven.com",
    "wof:name":"Shippers' Heaven",
    "wof:placetype":"venue"
},
  "geometry": {"coordinates":[-76.203773,36.765043],"type":"Point"}
}