{
  "type": "Feature",
  "properties": {
    "addr:full":"9757 Martinsville Hwy Danville VA 24541",
    "addr:housenumber":"9757",
    "addr:postcode":"24541",
    "addr:street":"Martinsville Hwy",
    "iso:country":"US",
    "sg:address":"9757 Martinsville Hwy",
    "sg:city":"Danville",
    "sg:classifiers":[
        {
            "category":"Organizations",
            "subcategory":"Religious Organization",
            "type":"Services"
        }
    ],
    "sg:phone":"+1 434 685 3959",
    "sg:postcode":"24541",
    "sg:province":"VA",
    "wof:name":"Brosville Untd Methdst Church",
    "wof:placetype":"venue"
},
  "geometry": {"coordinates":[-79.57184599999999,36.612476],"type":"Point"}
}