{
  "type": "Feature",
  "properties": {
    "addr:full":"6605 George Washington Memorial Hwy Yorktown VA 23692",
    "addr:housenumber":"6605",
    "addr:postcode":"23692",
    "addr:street":"George Washington Memorial Hwy",
    "iso:country":"US",
    "sg:address":"6605 George Washington Memorial Hwy",
    "sg:city":"Yorktown",
    "sg:classifiers":[
        {
            "category":"Banks & Credit Unions",
            "subcategory":"Bank",
            "type":"Services"
        }
    ],
    "sg:phone":"+1 757 890 3200",
    "sg:postcode":"23692",
    "sg:province":"VA",
    "sg:tags":[
        "national",
        "commercial"
    ],
    "wof:name":"Wachovia Bank National Assn",
    "wof:placetype":"venue"
},
  "geometry": {"coordinates":[-76.47563700000001,37.173549],"type":"Point"}
}