{
  "type": "Feature",
  "properties": {
    "addr:full":"24 N Mallory St Hampton VA 23663",
    "addr:housenumber":"24",
    "addr:postcode":"23663",
    "addr:street":"N Mallory St",
    "iso:country":"US",
    "sg:address":"24 N Mallory St",
    "sg:city":"Hampton",
    "sg:classifiers":[
        {
            "category":"Restaurant",
            "type":"Food & Drink"
        }
    ],
    "sg:phone":"+1 757 726 0820",
    "sg:postcode":"23663",
    "sg:province":"VA",
    "sg:tags":[
        "eating"
    ],
    "wof:name":"Hat Trix",
    "wof:placetype":"venue"
},
  "geometry": {"coordinates":[-76.319883,37.020025],"type":"Point"}
}