{
  "type": "Feature",
  "properties": {
    "addr:full":"3300 17th St N Arlington VA 22201",
    "addr:housenumber":"3300",
    "addr:postcode":"22201",
    "addr:street":"17Th St N",
    "iso:country":"US",
    "sg:address":"3300 17th St N",
    "sg:city":"Arlington",
    "sg:classifiers":[
        {
            "category":"Professional",
            "subcategory":"Management & Consulting",
            "type":"Services"
        }
    ],
    "sg:phone":"+1 703 528 1592",
    "sg:postcode":"22201",
    "sg:province":"VA",
    "wof:name":"Triantis Assoc",
    "wof:placetype":"venue"
},
  "geometry": {"coordinates":[-77.100077,38.891197],"type":"Point"}
}