{
  "type": "Feature",
  "properties": {
    "addr:full":"122 Bedwell St Independence VA 24348",
    "addr:housenumber":"122",
    "addr:postcode":"24348",
    "addr:street":"Bedwell St",
    "iso:country":"US",
    "sg:address":"122 Bedwell St",
    "sg:city":"Independence",
    "sg:classifiers":[
        {
            "category":"Real Estate",
            "subcategory":"Real Estate Operator",
            "type":"Services"
        }
    ],
    "sg:phone":"+1 276 773 3782",
    "sg:postcode":"24348",
    "sg:province":"VA",
    "sg:tags":[
        "apartment"
    ],
    "wof:name":"Penn Court Apartments",
    "wof:placetype":"venue"
},
  "geometry": {"coordinates":[-81.151644,36.619942],"type":"Point"}
}