{
  "type": "Feature",
  "properties": {
    "addr:full":"635 Slaters Ln Ste 400 Alexandria VA 22314",
    "addr:housenumber":"635",
    "addr:postcode":"22314",
    "addr:street":"Slaters Ln Ste 400",
    "iso:country":"US",
    "sg:address":"635 Slaters Ln Ste 400",
    "sg:city":"Alexandria",
    "sg:classifiers":[
        {
            "category":"Shopping",
            "subcategory":"Stationery & Office Supplies",
            "type":"Retail Goods"
        }
    ],
    "sg:phone":"+1 703 548 4040",
    "sg:postcode":"22314",
    "sg:province":"VA",
    "sg:tags":[
        "equipment"
    ],
    "wof:name":"Omnifics",
    "wof:placetype":"venue"
},
  "geometry": {"coordinates":[-77.04270200000001,38.8218],"type":"Point"}
}