{
  "type": "Feature",
  "properties": {
    "addr:full":"314 E Mc Ginnis Cir Norfolk VA 23502",
    "addr:housenumber":"314",
    "addr:postcode":"23502",
    "addr:street":"E Mc Ginnis Cir",
    "iso:country":"US",
    "sg:address":"314 E Mc Ginnis Cir",
    "sg:city":"Norfolk",
    "sg:classifiers":[
        {
            "category":"Manufacturing",
            "subcategory":"Tools & Machinery",
            "type":"Manufacturing & Wholesale Goods"
        }
    ],
    "sg:phone":"+1 757 466 8214",
    "sg:postcode":"23502",
    "sg:province":"VA",
    "sg:tags":[
        "field",
        "mfg"
    ],
    "wof:name":"Drill Pro Inc",
    "wof:placetype":"venue"
},
  "geometry": {"coordinates":[-76.20165299999999,36.83252],"type":"Point"}
}