{
  "type": "Feature",
  "properties": {
    "iso:country":"US",
    "sg:address":"1870 Grimes Rd",
    "sg:city":"Petersburg",
    "sg:classifiers":[
        {
            "category":"Organizations",
            "subcategory":"Community Association",
            "type":"Services"
        }
    ],
    "sg:phone":"+1 804 863 2367",
    "sg:postcode":"23805",
    "sg:province":"VA",
    "sg:tags":[
        "sorority",
        "fraternity"
    ],
    "wof:name":"Fraternal Order Of Police",
    "wof:placetype":"venue"
},
  "geometry": {"coordinates":[-77.41880999999999,37.200101],"type":"Point"}
}