{
  "type": "Feature",
  "properties": {
    "iso:country":"US",
    "sg:address":"395 Maple Ave E",
    "sg:city":"Vienna",
    "sg:classifiers":[
        {
            "category":"Autos & Motor Vehicles",
            "subcategory":"Fuel & Gas Station",
            "type":"Retail Goods"
        }
    ],
    "sg:phone":"+1 703 281 9857",
    "sg:postcode":"22180",
    "sg:province":"VA",
    "sg:tags":[
        "oil"
    ],
    "wof:name":"James Gulf Svc Ctr",
    "wof:placetype":"venue"
},
  "geometry": {"coordinates":[-77.25850199999999,38.906699],"type":"Point"}
}