{
  "type": "Feature",
  "properties": {
    "iso:country":"US",
    "sg:address":"659 Old Hunt Way",
    "sg:city":"Herndon",
    "sg:classifiers":[
        {
            "category":"Professional",
            "subcategory":"Engineering",
            "type":"Services"
        }
    ],
    "sg:phone":"+1 703 796 0400",
    "sg:postcode":"20170",
    "sg:province":"VA",
    "wof:name":"MWH Americas Inc",
    "wof:placetype":"venue"
},
  "geometry": {"coordinates":[-77.377396,38.983287],"type":"Point"}
}