{
  "type": "Feature",
  "properties": {
    "addr:full":"110 E Hicks St Lawrenceville VA 23868",
    "addr:housenumber":"110",
    "addr:postcode":"23868",
    "addr:street":"E Hicks St",
    "iso:country":"US",
    "sg:address":"110 E Hicks St",
    "sg:city":"Lawrenceville",
    "sg:classifiers":[
        {
            "category":"Home & Garden",
            "subcategory":"Furniture",
            "type":"Retail Goods"
        }
    ],
    "sg:phone":"+1 434 848 8353",
    "sg:postcode":"23868",
    "sg:province":"VA",
    "wof:name":"Hometown Furniture Outlet",
    "wof:placetype":"venue"
},
  "geometry": {"coordinates":[-77.846371,36.757765],"type":"Point"}
}