{
  "type": "Feature",
  "properties": {
    "addr:full":"12821 Percival St Chester VA 23831",
    "addr:housenumber":"12821",
    "addr:postcode":"23831",
    "addr:street":"Percival St",
    "iso:country":"US",
    "sg:address":"12821 Percival St",
    "sg:city":"Chester",
    "sg:classifiers":[
        {
            "category":"Manufacturing",
            "subcategory":"Rubber & Plastics",
            "type":"Manufacturing & Wholesale Goods"
        }
    ],
    "sg:phone":"+1 804 748 8717",
    "sg:postcode":"23831",
    "sg:province":"VA",
    "sg:tags":[
        "product",
        "mfg"
    ],
    "wof:name":"Classic Engravers",
    "wof:placetype":"venue"
},
  "geometry": {"coordinates":[-77.43132,37.344632],"type":"Point"}
}