{
  "type": "Feature",
  "properties": {
    "iso:country":"US",
    "sg:address":"4455 John Tyler Hwy",
    "sg:city":"Williamsburg",
    "sg:classifiers":[
        {
            "category":"Food & Beverages",
            "subcategory":"Groceries & Convenience Stores",
            "type":"Retail Goods"
        }
    ],
    "sg:phone":"+1 757 220 3244",
    "sg:postcode":"23185",
    "sg:province":"VA",
    "sg:tags":[
        "grocer"
    ],
    "wof:name":"Zooms Inc",
    "wof:placetype":"venue"
},
  "geometry": {"coordinates":[-76.7677,37.250674],"type":"Point"}
}