{
  "type": "Feature",
  "properties": {
    "addr:full":"9720 Gayton Rd Richmond VA 23238",
    "addr:housenumber":"9720",
    "addr:postcode":"23238",
    "addr:street":"Gayton Rd",
    "iso:country":"US",
    "sg:address":"9720 Gayton Rd",
    "sg:city":"Richmond",
    "sg:classifiers":[
        {
            "category":"Restaurant",
            "type":"Food & Drink"
        }
    ],
    "sg:phone":"+1 804 740 1940",
    "sg:postcode":"23238",
    "sg:province":"VA",
    "wof:name":"Fu Jian Chinese Restaurant",
    "wof:placetype":"venue"
},
  "geometry": {"coordinates":[-77.59285300000001,37.604477],"type":"Point"}
}