{
  "type": "Feature",
  "properties": {
    "addr:full":"2100 Westwood Ave Richmond VA 23230",
    "addr:housenumber":"2100",
    "addr:postcode":"23230",
    "addr:street":"Westwood Ave",
    "iso:country":"US",
    "sg:address":"2100 Westwood Ave",
    "sg:city":"Richmond",
    "sg:classifiers":[
        {
            "category":"Railroad",
            "type":"Transportation"
        }
    ],
    "sg:phone":"+1 804 226 7624",
    "sg:postcode":"23230",
    "sg:province":"VA",
    "wof:name":"CSX Transportation Inc",
    "wof:placetype":"venue"
},
  "geometry": {"coordinates":[-77.472933,37.57844],"type":"Point"}
}