{
  "type": "Feature",
  "properties": {
    "addr:full":"4472 Remount Rd Front Royal VA 22630",
    "addr:housenumber":"4472",
    "addr:postcode":"22630",
    "addr:street":"Remount Rd",
    "iso:country":"US",
    "sg:address":"4472 Remount Rd",
    "sg:city":"Front Royal",
    "sg:classifiers":[
        {
            "category":"Building & Trades",
            "subcategory":"Landscaping Services",
            "type":"Services"
        }
    ],
    "sg:phone":"+1 540 635 8002",
    "sg:postcode":"22630",
    "sg:province":"VA",
    "sg:tags":[
        "landscape"
    ],
    "wof:name":"Robert Rector",
    "wof:placetype":"venue"
},
  "geometry": {"coordinates":[-78.13275400000001,38.864297],"type":"Point"}
}