{
  "type": "Feature",
  "properties": {
    "iso:country":"US",
    "sg:address":"708 Potomac Knolls Dr",
    "sg:city":"Mc Lean",
    "sg:classifiers":[
        {
            "category":"Professional",
            "subcategory":"Research",
            "type":"Services"
        }
    ],
    "sg:phone":"+1 703 893 1542",
    "sg:postcode":"22102",
    "sg:province":"VA",
    "sg:tags":[
        "consulting",
        "education"
    ],
    "wof:name":"Gifford Research Services",
    "wof:placetype":"venue"
},
  "geometry": {"coordinates":[-77.22366599999999,38.969834],"type":"Point"}
}