{
  "type": "Feature",
  "properties": {
    "iso:country":"US",
    "sg:address":"2411 Dulles Corner Park",
    "sg:city":"Herndon",
    "sg:classifiers":[
        {
            "category":"Restaurant",
            "type":"Food & Drink"
        }
    ],
    "sg:phone":"+1 703 793 0223",
    "sg:postcode":"20171",
    "sg:province":"VA",
    "sg:tags":[
        "eating"
    ],
    "wof:name":"Park South Deli",
    "wof:placetype":"venue"
},
  "geometry": {"coordinates":[-77.42553100000001,38.957275],"type":"Point"}
}