{
  "type": "Feature",
  "properties": {
    "iso:country":"US",
    "sg:address":"2958 Browns Gap Tpke",
    "sg:city":"Crozet",
    "sg:classifiers":[
        {
            "category":"Food & Beverages",
            "subcategory":"Groceries & Convenience Stores",
            "type":"Retail Goods"
        }
    ],
    "sg:phone":"+1 434 823 6670",
    "sg:postcode":"22932",
    "sg:province":"VA",
    "wof:name":"Piedmont Store",
    "wof:placetype":"venue"
},
  "geometry": {"coordinates":[-78.662666,38.124611],"type":"Point"}
}