{
  "type": "Feature",
  "properties": {
    "addr:full":"1423 N Great Neck Rd Virginia Beach VA 23454",
    "addr:housenumber":"1423",
    "addr:postcode":"23454",
    "addr:street":"N Great Neck Rd",
    "iso:country":"US",
    "sg:address":"1423 N Great Neck Rd",
    "sg:city":"Virginia Beach",
    "sg:classifiers":[
        {
            "category":"Professional",
            "subcategory":"Management & Consulting",
            "type":"Services"
        }
    ],
    "sg:phone":"+1 757 412 0669",
    "sg:postcode":"23454",
    "sg:province":"VA",
    "wof:name":"Liquid Assets",
    "wof:placetype":"venue"
},
  "geometry": {"coordinates":[-76.04333699999999,36.879901],"type":"Point"}
}