{
  "type": "Feature",
  "properties": {
    "iso:country":"US",
    "sg:address":"558 Mount Vernon Ave",
    "sg:city":"Portsmouth",
    "sg:classifiers":[
        {
            "category":"Professional",
            "subcategory":"Business Services",
            "type":"Services"
        }
    ],
    "sg:phone":"+1 757 397 7149",
    "sg:postcode":"23707",
    "sg:province":"VA",
    "sg:tags":[
        "translation"
    ],
    "wof:name":"Jill Steen",
    "wof:placetype":"venue"
},
  "geometry": {"coordinates":[-76.336523,36.845738],"type":"Point"}
}