{
  "type": "Feature",
  "properties": {
    "iso:country":"US",
    "sg:address":"504 Culpeper Town Sq",
    "sg:city":"Culpeper",
    "sg:classifiers":[
        {
            "category":"Shopping",
            "subcategory":"Used Merchandise",
            "type":"Retail Goods"
        }
    ],
    "sg:phone":"+1 540 829 8068",
    "sg:postcode":"22701",
    "sg:province":"VA",
    "sg:tags":[
        "shop",
        "thrift"
    ],
    "wof:name":"Goodwill Industries",
    "wof:placetype":"venue"
},
  "geometry": {"coordinates":[-77.988151,38.47997],"type":"Point"}
}