{
  "type": "Feature",
  "properties": {
    "iso:country":"US",
    "sg:address":"10210 Sager Ave",
    "sg:city":"Fairfax",
    "sg:classifiers":[
        {
            "category":"Building & Trades",
            "subcategory":"Construction",
            "type":"Services"
        }
    ],
    "sg:phone":"+1 703 267 6988",
    "sg:postcode":"22030",
    "sg:province":"VA",
    "sg:tags":[
        "general",
        "contractor"
    ],
    "wof:name":"SAL Construction Inc",
    "wof:placetype":"venue"
},
  "geometry": {"coordinates":[-77.29749200000001,38.841087],"type":"Point"}
}