{
  "type": "Feature",
  "properties": {
    "addr:full":"2699 Jubal Early Hwy Boones Mill VA 24065",
    "addr:housenumber":"2699",
    "addr:postcode":"24065",
    "addr:street":"Jubal Early Hwy",
    "iso:country":"US",
    "sg:address":"2699 Jubal Early Hwy",
    "sg:city":"Boones Mill",
    "sg:classifiers":[
        {
            "category":"Food & Beverages",
            "subcategory":"Bakery",
            "type":"Retail Goods"
        }
    ],
    "sg:phone":"+1 540 721 2478",
    "sg:postcode":"24065",
    "sg:province":"VA",
    "sg:tags":[
        "baker"
    ],
    "wof:name":"Boone's Country Store",
    "wof:placetype":"venue"
},
  "geometry": {"coordinates":[-79.850122,37.130139],"type":"Point"}
}