{
  "type": "Feature",
  "properties": {
    "addr:full":"12979 Fair Lakes Shopping Center Fairfax VA 22033",
    "addr:housenumber":"12979",
    "addr:postcode":"22033",
    "addr:street":"Fair Lakes Shopping Center",
    "iso:country":"US",
    "sg:address":"12979 Fair Lakes Shopping Center",
    "sg:city":"Fairfax",
    "sg:classifiers":[
        {
            "category":"Shopping",
            "subcategory":"Clothing, Apparel, & Fashions",
            "type":"Retail Goods"
        }
    ],
    "sg:phone":"+1 703 818 3749",
    "sg:postcode":"22033",
    "sg:province":"VA",
    "wof:name":"Lane Bryant",
    "wof:placetype":"venue"
},
  "geometry": {"coordinates":[-77.390804,38.858654],"type":"Point"}
}