{
  "type": "Feature",
  "properties": {
    "addr:full":"145 Commerce Dr Ruckersville VA 22968",
    "addr:housenumber":"145",
    "addr:postcode":"22968",
    "addr:street":"Commerce Dr",
    "iso:country":"US",
    "sg:address":"145 Commerce Dr",
    "sg:city":"Ruckersville",
    "sg:classifiers":[
        {
            "category":"Home & Garden",
            "subcategory":"Furniture",
            "type":"Retail Goods"
        }
    ],
    "sg:phone":"+1 434 985 1899",
    "sg:postcode":"22968",
    "sg:province":"VA",
    "sg:tags":[
        "cabinet"
    ],
    "wof:name":"Home Options",
    "wof:placetype":"venue"
},
  "geometry": {"coordinates":[-78.372334,38.22476],"type":"Point"}
}