{
  "type": "Feature",
  "properties": {
    "addr:full":"6310 Backlick Rd Springfield VA 22150",
    "addr:housenumber":"6310",
    "addr:postcode":"22150",
    "addr:street":"Backlick Rd",
    "iso:country":"US",
    "sg:address":"6310 Backlick Rd",
    "sg:city":"Springfield",
    "sg:classifiers":[
        {
            "category":"Restaurant",
            "type":"Food & Drink"
        }
    ],
    "sg:phone":"+1 703 451 5664",
    "sg:postcode":"22150",
    "sg:province":"VA",
    "sg:tags":[
        "eating"
    ],
    "wof:name":"Pizza Hut",
    "wof:placetype":"venue"
},
  "geometry": {"coordinates":[-77.18520100000001,38.781003],"type":"Point"}
}