{
  "type": "Feature",
  "properties": {
    "iso:country":"US",
    "sg:address":"148 Hook St",
    "sg:city":"Chesapeake",
    "sg:classifiers":[
        {
            "category":"Government",
            "subcategory":"Police Station",
            "type":"Public Place"
        }
    ],
    "sg:phone":"+1 757 382 6159",
    "sg:postcode":"23324",
    "sg:province":"VA",
    "sg:tags":[
        "protection"
    ],
    "wof:name":"Chesapeake Sheriffs Office",
    "wof:placetype":"venue"
},
  "geometry": {"coordinates":[-76.257244,36.796624],"type":"Point"}
}