{
  "type": "Feature",
  "properties": {
    "iso:country":"US",
    "sg:address":"12600 Fair Lakes Cir",
    "sg:city":"Fairfax",
    "sg:classifiers":[
        {
            "category":"Professional",
            "subcategory":"Lawyer & Legal Services",
            "type":"Services"
        }
    ],
    "sg:phone":"+1 703 818 0223",
    "sg:postcode":"22033",
    "sg:province":"VA",
    "wof:name":"Nathan A Colman",
    "wof:placetype":"venue"
},
  "geometry": {"coordinates":[-77.384348,38.858172],"type":"Point"}
}