{
  "type": "Feature",
  "properties": {
    "addr:full":"4851 State Park Rd Dublin VA 24084",
    "addr:housenumber":"4851",
    "addr:postcode":"24084",
    "addr:street":"State Park Rd",
    "iso:country":"US",
    "sg:address":"4851 State Park Rd",
    "sg:city":"Dublin",
    "sg:classifiers":[
        {
            "category":"Building & Trades",
            "subcategory":"Plumbing",
            "type":"Services"
        }
    ],
    "sg:phone":"+1 540 674 8051",
    "sg:postcode":"24084",
    "sg:province":"VA",
    "sg:tags":[
        "conditioning",
        "air",
        "system",
        "contractor"
    ],
    "wof:name":"Advantage Heating & Cooling",
    "wof:placetype":"venue"
},
  "geometry": {"coordinates":[-80.636319,37.078147],"type":"Point"}
}