{
  "type": "Feature",
  "properties": {
    "iso:country":"US",
    "sg:address":"12829 Shadow Oak Ln",
    "sg:city":"Fairfax",
    "sg:classifiers":[
        {
            "category":"Professional",
            "subcategory":"Computer Services",
            "type":"Services"
        }
    ],
    "sg:phone":"+1 703 758 6777",
    "sg:postcode":"22033",
    "sg:province":"VA",
    "sg:tags":[
        "system",
        "custom",
        "programming",
        "integration",
        "software"
    ],
    "wof:name":"Network Computer Systems Inc",
    "wof:placetype":"venue"
},
  "geometry": {"coordinates":[-77.38752599999999,38.890171],"type":"Point"}
}