{
  "type": "Feature",
  "properties": {
    "iso:country":"US",
    "sg:address":"2258 Huntington Ave",
    "sg:city":"Alexandria",
    "sg:classifiers":[
        {
            "category":"Food & Beverages",
            "subcategory":"Bakery",
            "type":"Retail Goods"
        }
    ],
    "sg:phone":"+1 703 317 9125",
    "sg:postcode":"22303",
    "sg:province":"VA",
    "wof:name":"Casa Blanca",
    "wof:placetype":"venue"
},
  "geometry": {"coordinates":[-77.068338,38.793047],"type":"Point"}
}