{
  "type": "Feature",
  "properties": {
    "addr:full":"3106 Collins Rd Richmond VA 23223",
    "addr:housenumber":"3106",
    "addr:postcode":"23223",
    "addr:street":"Collins Rd",
    "iso:country":"US",
    "sg:address":"3106 Collins Rd",
    "sg:city":"Richmond",
    "sg:classifiers":[
        {
            "category":"Freight",
            "type":"Transportation"
        }
    ],
    "sg:phone":"+1 804 351 4793",
    "sg:postcode":"23223",
    "sg:province":"VA",
    "sg:tags":[
        "delivery"
    ],
    "wof:name":"C & M Delivery",
    "wof:placetype":"venue"
},
  "geometry": {"coordinates":[-77.395172,37.564807],"type":"Point"}
}