{
  "type": "Feature",
  "properties": {
    "iso:country":"US",
    "sg:address":"720 N Henry St",
    "sg:city":"Alexandria",
    "sg:classifiers":[
        {
            "category":"Professional",
            "subcategory":"Business Services",
            "type":"Services"
        }
    ],
    "sg:phone":"+1 703 684 5175",
    "sg:postcode":"22314",
    "sg:province":"VA",
    "wof:name":"Studio E Design",
    "wof:placetype":"venue"
},
  "geometry": {"coordinates":[-77.049774,38.813361],"type":"Point"}
}