{
  "type": "Feature",
  "properties": {
    "addr:full":"9507 Warwick Blvd Newport News VA 23601",
    "addr:housenumber":"9507",
    "addr:postcode":"23601",
    "addr:street":"Warwick Blvd",
    "iso:country":"US",
    "sg:address":"9507 Warwick Blvd",
    "sg:city":"Newport News",
    "sg:classifiers":[
        {
            "category":"Manufacturing",
            "subcategory":"Printing",
            "type":"Manufacturing & Wholesale Goods"
        }
    ],
    "sg:phone":"+1 757 873 2846",
    "sg:postcode":"23601",
    "sg:province":"VA",
    "sg:tags":[
        "commercial"
    ],
    "wof:name":"Gates Designs Inc",
    "wof:placetype":"venue"
},
  "geometry": {"coordinates":[-76.45440600000001,37.023973],"type":"Point"}
}