{
  "type": "Feature",
  "properties": {
    "addr:full":"6000 White House Rd Nelson VA 24580",
    "addr:housenumber":"6000",
    "addr:postcode":"24580",
    "addr:street":"White House Rd",
    "iso:country":"US",
    "sg:address":"6000 White House Rd",
    "sg:city":"Nelson",
    "sg:classifiers":[
        {
            "category":"Building & Trades",
            "subcategory":"Construction",
            "type":"Services"
        }
    ],
    "sg:phone":"+1 434 374 4920",
    "sg:postcode":"24580",
    "sg:province":"VA",
    "sg:tags":[
        "excavation",
        "contractor"
    ],
    "wof:name":"Little Creek Excavating",
    "wof:placetype":"venue"
},
  "geometry": {"coordinates":[-78.70112,36.609983],"type":"Point"}
}