{
  "type": "Feature",
  "properties": {
    "addr:full":"2272 Claymill Dr Newport News VA 23602",
    "addr:housenumber":"2272",
    "addr:postcode":"23602",
    "addr:street":"Claymill Dr",
    "iso:country":"US",
    "sg:address":"2272 Claymill Dr",
    "sg:city":"Newport News",
    "sg:classifiers":[
        {
            "category":"Professional",
            "subcategory":"Business Services",
            "type":"Services"
        }
    ],
    "sg:phone":"+1 757 877 5287",
    "sg:postcode":"23602",
    "sg:province":"VA",
    "sg:tags":[
        "consulting"
    ],
    "wof:name":"African American Images",
    "wof:placetype":"venue"
},
  "geometry": {"coordinates":[-76.49004100000001,37.118015],"type":"Point"}
}