{
  "type": "Feature",
  "properties": {
    "iso:country":"US",
    "sg:address":"116 Whitewood Rd",
    "sg:city":"Charlottesville",
    "sg:classifiers":[
        {
            "category":"Shopping",
            "subcategory":"Computers & Home Electronics",
            "type":"Retail Goods"
        }
    ],
    "sg:phone":"+1 434 977 0600",
    "sg:postcode":"22901",
    "sg:province":"VA",
    "sg:tags":[
        "software"
    ],
    "wof:name":"Commonwealth Computer Research",
    "wof:placetype":"venue"
},
  "geometry": {"coordinates":[-78.492299,38.074316],"type":"Point"}
}