{
  "type": "Feature",
  "properties": {
    "addr:full":"14826 Build America Dr Woodbridge VA 22191",
    "addr:postcode":"14826;22191",
    "addr:street":"America Dr",
    "iso:country":"US",
    "sg:address":"14826 Build America Dr",
    "sg:city":"Woodbridge",
    "sg:classifiers":[
        {
            "category":"Home & Garden",
            "subcategory":"Carpets & Floor Coverings",
            "type":"Retail Goods"
        }
    ],
    "sg:phone":"+1 703 491 5155",
    "sg:postcode":"22191",
    "sg:province":"VA",
    "sg:tags":[
        "dealer",
        "rug"
    ],
    "wof:name":"C & C Carpet",
    "wof:placetype":"venue"
},
  "geometry": {"coordinates":[-77.27271399999999,38.631287],"type":"Point"}
}