{
  "type": "Feature",
  "properties": {
    "addr:full":"704 Thimble Shoals Blvd Newport News VA 23606",
    "addr:housenumber":"704",
    "addr:postcode":"23606",
    "addr:street":"Thimble Shoals Blvd",
    "iso:country":"US",
    "sg:address":"704 Thimble Shoals Blvd",
    "sg:city":"Newport News",
    "sg:classifiers":[
        {
            "category":"Health Services",
            "subcategory":"Doctor",
            "type":"Services"
        }
    ],
    "sg:phone":"+1 757 873 6434",
    "sg:postcode":"23606",
    "sg:province":"VA",
    "sg:tags":[
        "medical"
    ],
    "wof:name":"Cross John Armstrong Jr",
    "wof:placetype":"venue"
},
  "geometry": {"coordinates":[-76.46918599999999,37.08433],"type":"Point"}
}