{
  "type": "Feature",
  "properties": {
    "addr:full":"509 N Military Hwy Norfolk VA 23502",
    "addr:housenumber":"509",
    "addr:postcode":"23502",
    "addr:street":"N Military Hwy",
    "iso:country":"US",
    "sg:address":"509 N Military Hwy",
    "sg:city":"Norfolk",
    "sg:classifiers":[
        {
            "category":"Health Services",
            "subcategory":"Optometrist",
            "type":"Services"
        }
    ],
    "sg:phone":"+1 757 466 9056",
    "sg:postcode":"23502",
    "sg:province":"VA",
    "wof:name":"Jack Cadenhead OD",
    "wof:placetype":"venue"
},
  "geometry": {"coordinates":[-76.210262,36.849005],"type":"Point"}
}