{
  "type": "Feature",
  "properties": {
    "iso:country":"US",
    "sg:address":"7306 Yates Ct",
    "sg:city":"Mc Lean",
    "sg:classifiers":[
        {
            "category":"Organizations",
            "subcategory":"Community Association",
            "type":"Services"
        }
    ],
    "sg:phone":"+1 703 356 8870",
    "sg:postcode":"22101",
    "sg:province":"VA",
    "wof:name":"McLean Knolls Civic Assoc Inc",
    "wof:placetype":"venue"
},
  "geometry": {"coordinates":[-77.19874900000001,38.935083],"type":"Point"}
}