{
  "type": "Feature",
  "properties": {
    "addr:full":"2120 Valley Ave Winchester VA 22601",
    "addr:housenumber":"2120",
    "addr:postcode":"22601",
    "addr:street":"Valley Ave",
    "iso:country":"US",
    "sg:address":"2120 Valley Ave",
    "sg:city":"Winchester",
    "sg:classifiers":[
        {
            "category":"Home & Garden",
            "subcategory":"Building Materials",
            "type":"Retail Goods"
        },
        {
            "category":"Retail",
            "subcategory":"Auto Repair",
            "type":"Services"
        }
    ],
    "sg:phone":"+1 540 545 8030",
    "sg:postcode":"22601",
    "sg:province":"VA",
    "sg:tags":[
        "glass",
        "window",
        "plate",
        "replacement"
    ],
    "wof:name":"Crystal Auto Glass LLC",
    "wof:placetype":"venue"
},
  "geometry": {"coordinates":[-78.18319700000001,39.163492],"type":"Point"}
}