{
  "type": "Feature",
  "properties": {
    "iso:country":"US",
    "sg:address":"4900 Seminary Rd Ste 104",
    "sg:city":"Alexandria",
    "sg:classifiers":[
        {
            "category":"Health Services",
            "subcategory":"Optometrist",
            "type":"Services"
        }
    ],
    "sg:phone":"+1 703 820 3322",
    "sg:postcode":"22311",
    "sg:province":"VA",
    "wof:name":"Northern Virginia Vision",
    "wof:placetype":"venue"
},
  "geometry": {"coordinates":[-77.11602499999999,38.83181],"type":"Point"}
}