{
  "type": "Feature",
  "properties": {
    "iso:country":"US",
    "sg:address":"951 S Rolfe St",
    "sg:city":"Arlington",
    "sg:classifiers":[
        {
            "category":"Professional",
            "subcategory":"Business Services",
            "type":"Services"
        }
    ],
    "sg:phone":"+1 703 979 2080",
    "sg:postcode":"22204",
    "sg:province":"VA",
    "wof:name":"Kmm Assoc",
    "wof:placetype":"venue"
},
  "geometry": {"coordinates":[-77.075879,38.86612],"type":"Point"}
}