{
  "type": "Feature",
  "properties": {
    "addr:full":"155 Lynnhaven Dr Alexandria VA 22305",
    "addr:housenumber":"155",
    "addr:postcode":"22305",
    "addr:street":"Lynnhaven Dr",
    "iso:country":"US",
    "sg:address":"155 Lynnhaven Dr",
    "sg:city":"Alexandria",
    "sg:classifiers":[
        {
            "category":"Home & Garden",
            "subcategory":"Building Materials",
            "type":"Retail Goods"
        }
    ],
    "sg:phone":"+1 703 451 1960",
    "sg:postcode":"22305",
    "sg:province":"VA",
    "sg:tags":[
        "windows"
    ],
    "wof:name":"Anderson Aluminum Co",
    "wof:placetype":"venue"
},
  "geometry": {"coordinates":[-77.054782,38.835949],"type":"Point"}
}