{
  "type": "Feature",
  "properties": {
    "addr:full":"2670 Greensboro Rd Martinsville VA 24112",
    "addr:housenumber":"2670",
    "addr:postcode":"24112",
    "addr:street":"Greensboro Rd",
    "iso:country":"US",
    "sg:address":"2670 Greensboro Rd",
    "sg:city":"Martinsville",
    "sg:classifiers":[
        {
            "category":"Autos & Motor Vehicles",
            "subcategory":"Auto Supplies",
            "type":"Retail Goods"
        }
    ],
    "sg:phone":"+1 276 638 7224",
    "sg:postcode":"24112",
    "sg:province":"VA",
    "sg:tags":[
        "automobile",
        "parts"
    ],
    "wof:name":"Advance Auto Parts Inc",
    "wof:placetype":"venue"
},
  "geometry": {"coordinates":[-79.87617899999999,36.654365],"type":"Point"}
}