{
  "type": "Feature",
  "properties": {
    "addr:full":"2501 Genito Pl Midlothian VA 23112",
    "addr:housenumber":"2501",
    "addr:postcode":"23112",
    "addr:street":"Genito Pl",
    "iso:country":"US",
    "sg:address":"2501 Genito Pl",
    "sg:city":"Midlothian",
    "sg:classifiers":[
        {
            "category":"Freight",
            "type":"Transportation"
        }
    ],
    "sg:phone":"+1 804 744 3043",
    "sg:postcode":"23112",
    "sg:province":"VA",
    "sg:tags":[
        "special",
        "general"
    ],
    "wof:name":"Genito Mini Storage",
    "wof:placetype":"venue"
},
  "geometry": {"coordinates":[-77.642528,37.46034],"type":"Point"}
}