{
  "type": "Feature",
  "properties": {
    "addr:full":"132 N Main St Stuart VA 24171",
    "addr:housenumber":"132",
    "addr:postcode":"24171",
    "addr:street":"N Main St",
    "iso:country":"US",
    "sg:address":"132 N Main St",
    "sg:city":"Stuart",
    "sg:classifiers":[
        {
            "category":"Food & Beverages",
            "subcategory":"Meat & Fish",
            "type":"Retail Goods"
        }
    ],
    "sg:phone":"+1 276 694 3175",
    "sg:postcode":"24171",
    "sg:province":"VA",
    "wof:name":"Alexander's IGA",
    "wof:placetype":"venue"
},
  "geometry": {"coordinates":[-80.271224,36.64044],"type":"Point"}
}