{
  "type": "Feature",
  "properties": {
    "addr:full":"3515 Jefferson Davis Hwy Fredericksburg VA 22408",
    "addr:housenumber":"3515",
    "addr:postcode":"22408",
    "addr:street":"Jefferson Davis Hwy",
    "iso:country":"US",
    "sg:address":"3515 Jefferson Davis Hwy",
    "sg:city":"Fredericksburg",
    "sg:classifiers":[
        {
            "category":"Autos & Motor Vehicles",
            "subcategory":"Automobile Sales",
            "type":"Retail Goods"
        }
    ],
    "sg:phone":"+1 540 898 3367",
    "sg:postcode":"22408",
    "sg:province":"VA",
    "sg:tags":[
        "car",
        "used",
        "dealer"
    ],
    "wof:name":"C & C Auto Sales Inc",
    "wof:placetype":"venue"
},
  "geometry": {"coordinates":[-77.493303,38.270229],"type":"Point"}
}