{
  "type": "Feature",
  "properties": {
    "iso:country":"US",
    "sg:address":"801 Volvo Pkwy",
    "sg:city":"Chesapeake",
    "sg:classifiers":[
        {
            "category":"Health Services",
            "subcategory":"Doctor",
            "type":"Services"
        }
    ],
    "sg:phone":"+1 757 547 3668",
    "sg:postcode":"23320",
    "sg:province":"VA",
    "sg:tags":[
        "foot",
        "clinic",
        "care"
    ],
    "wof:name":"Family Foot Care Centers PC",
    "wof:placetype":"venue"
},
  "geometry": {"coordinates":[-76.229328,36.768726],"type":"Point"}
}