{
  "type": "Feature",
  "properties": {
    "addr:full":"180 Horse Landing Rd King William VA 23086",
    "addr:housenumber":"180",
    "addr:postcode":"23086",
    "addr:street":"Horse Landing Rd",
    "iso:country":"US",
    "sg:address":"180 Horse Landing Rd",
    "sg:city":"King William",
    "sg:classifiers":[
        {
            "category":"Government",
            "subcategory":"Office",
            "type":"Public Place"
        }
    ],
    "sg:phone":"+1 804 769 4929",
    "sg:postcode":"23086",
    "sg:province":"VA",
    "wof:name":"King William County Accounting",
    "wof:placetype":"venue"
},
  "geometry": {"coordinates":[-77.010272,37.690562],"type":"Point"}
}