{
  "type": "Feature",
  "properties": {
    "iso:country":"US",
    "sg:address":"219 N Main St",
    "sg:city":"Lawrenceville",
    "sg:classifiers":[
        {
            "category":"Government",
            "subcategory":"Office",
            "type":"Public Place"
        }
    ],
    "sg:phone":"+1 434 848 3232",
    "sg:postcode":"23868",
    "sg:province":"VA",
    "wof:name":"Brunswick County Title I Ofc",
    "wof:placetype":"venue"
},
  "geometry": {"coordinates":[-77.847122,36.758711],"type":"Point"}
}