{
  "type": "Feature",
  "properties": {
    "addr:full":"329 Potomac Ave Quantico VA 22134",
    "addr:housenumber":"329",
    "addr:postcode":"22134",
    "addr:street":"Potomac Ave",
    "iso:country":"US",
    "sg:address":"329 Potomac Ave",
    "sg:city":"Quantico",
    "sg:classifiers":[
        {
            "category":"Retail",
            "subcategory":"Laundry & Dry Cleaning",
            "type":"Services"
        }
    ],
    "sg:phone":"+1 703 630 4812",
    "sg:postcode":"22134",
    "sg:province":"VA",
    "sg:tags":[
        "drycleaning"
    ],
    "wof:name":"TLC Cleaners",
    "wof:placetype":"venue"
},
  "geometry": {"coordinates":[-77.292119,38.522281],"type":"Point"}
}