{
  "type": "Feature",
  "properties": {
    "addr:full":"2035 Roanoke Blvd Salem VA 24153",
    "addr:housenumber":"2035",
    "addr:postcode":"24153",
    "addr:street":"Roanoke Blvd",
    "iso:country":"US",
    "sg:address":"2035 Roanoke Blvd",
    "sg:city":"Salem",
    "sg:classifiers":[
        {
            "category":"Food & Beverages",
            "subcategory":"Specialty",
            "type":"Retail Goods"
        },
        {
            "category":"Food & Beverages",
            "subcategory":"Groceries & Convenience Stores",
            "type":"Retail Goods"
        }
    ],
    "sg:phone":"+1 540 345 5659",
    "sg:postcode":"24153",
    "sg:province":"VA",
    "sg:tags":[
        "grocers-specialty"
    ],
    "wof:name":"Orange Market",
    "wof:placetype":"venue"
},
  "geometry": {"coordinates":[-80.050087,37.28805],"type":"Point"}
}