{
  "type": "Feature",
  "properties": {
    "iso:country":"US",
    "sg:address":"11 Rockcroft Dr",
    "sg:city":"Berryville",
    "sg:classifiers":[
        {
            "category":"Shopping",
            "subcategory":"Catalog Store",
            "type":"Retail Goods"
        }
    ],
    "sg:phone":"+1 540 955 1274",
    "sg:postcode":"22611",
    "sg:province":"VA",
    "sg:tags":[
        "mail",
        "house"
    ],
    "wof:name":"Racquet Corner",
    "wof:placetype":"venue"
},
  "geometry": {"coordinates":[-77.977808,39.155533],"type":"Point"}
}