{
  "type": "Feature",
  "properties": {
    "addr:full":"1313 Columbia Rd Bristol VA 37620",
    "addr:housenumber":"1313",
    "addr:postcode":"37620",
    "addr:street":"Columbia Rd",
    "iso:country":"US",
    "sg:address":"1313 Columbia Rd",
    "sg:city":"Bristol",
    "sg:classifiers":[
        {
            "category":"Utilities",
            "subcategory":"Fuel Oil & Lpg",
            "type":"Services"
        }
    ],
    "sg:phone":"+1 423 968 2625",
    "sg:postcode":"37620",
    "sg:province":"VA",
    "sg:tags":[
        "coal",
        "coke"
    ],
    "wof:name":"Hall's Coal Yard",
    "wof:placetype":"venue"
},
  "geometry": {"coordinates":[-82.172679,36.577049],"type":"Point"}
}