{
  "type": "Feature",
  "properties": {
    "addr:full":"4295 Blue Ridge Blvd Blue Ridge VA 24064",
    "addr:housenumber":"4295",
    "addr:postcode":"24064",
    "addr:street":"Blue Ridge Blvd",
    "iso:country":"US",
    "sg:address":"4295 Blue Ridge Blvd",
    "sg:city":"Blue Ridge",
    "sg:classifiers":[
        {
            "category":"Retail",
            "subcategory":"Auto Repair",
            "type":"Services"
        }
    ],
    "sg:phone":"+1 540 977 3300",
    "sg:postcode":"24064",
    "sg:province":"VA",
    "sg:tags":[
        "body",
        "automobile",
        "painting"
    ],
    "wof:name":"Blue Ridge Auto Svc",
    "wof:placetype":"venue"
},
  "geometry": {"coordinates":[-79.811615,37.372213],"type":"Point"}
}