{
  "type": "Feature",
  "properties": {
    "iso:country":"US",
    "sg:address":"9 N King St",
    "sg:city":"Leesburg",
    "sg:classifiers":[
        {
            "category":"Professional",
            "subcategory":"Accounting & Tax Preparation",
            "type":"Services"
        }
    ],
    "sg:phone":"+1 703 771 8871",
    "sg:postcode":"20176",
    "sg:province":"VA",
    "sg:tags":[
        "accountant"
    ],
    "wof:name":"Lovelace & Colville",
    "wof:placetype":"venue"
},
  "geometry": {"coordinates":[-77.564103,39.116559],"type":"Point"}
}