{
  "type": "Feature",
  "properties": {
    "iso:country":"US",
    "sg:address":"4701 Arlington Blvd",
    "sg:city":"Arlington",
    "sg:classifiers":[
        {
            "category":"Arts & Performance",
            "subcategory":"Theater",
            "type":"Entertainment"
        }
    ],
    "sg:phone":"+1 703 525 1397",
    "sg:postcode":"22203",
    "sg:province":"VA",
    "sg:tags":[
        "group"
    ],
    "wof:name":"Ron Freeman Chorale",
    "wof:placetype":"venue"
},
  "geometry": {"coordinates":[-77.11208000000001,38.868122],"type":"Point"}
}