{
  "type": "Feature",
  "properties": {
    "iso:country":"US",
    "sg:address":"36 Old Farm Rd",
    "sg:city":"Charlottesville",
    "sg:classifiers":[
        {
            "category":"Restaurant",
            "type":"Food & Drink"
        }
    ],
    "sg:phone":"+1 434 295 5066",
    "sg:postcode":"22903",
    "sg:province":"VA",
    "sg:tags":[
        "eating"
    ],
    "wof:name":"Five Guys Burgers",
    "wof:placetype":"venue"
},
  "geometry": {"coordinates":[-78.530991,38.038166],"type":"Point"}
}