{
  "type": "Feature",
  "properties": {
    "addr:full":"4770 Shady Grove Rd Glen Allen VA 23059",
    "addr:housenumber":"4770",
    "addr:postcode":"23059",
    "addr:street":"Shady Grove Rd",
    "iso:country":"US",
    "sg:address":"4770 Shady Grove Rd",
    "sg:city":"Glen Allen",
    "sg:classifiers":[
        {
            "category":"Building & Trades",
            "subcategory":"Plumbing",
            "type":"Services"
        }
    ],
    "sg:phone":"+1 804 364 4342",
    "sg:postcode":"23059",
    "sg:province":"VA",
    "sg:tags":[
        "contractor"
    ],
    "wof:name":"Virginia Mech Hting Arcndtning",
    "wof:placetype":"venue"
},
  "geometry": {"coordinates":[-77.608769,37.673311],"type":"Point"}
}