{
  "type": "Feature",
  "properties": {
    "addr:full":"123 S Chestnut St Marion VA 24354",
    "addr:housenumber":"123",
    "addr:postcode":"24354",
    "addr:street":"S Chestnut St",
    "iso:country":"US",
    "sg:address":"123 S Chestnut St",
    "sg:city":"Marion",
    "sg:classifiers":[
        {
            "category":"Professional",
            "subcategory":"Employment Agencies",
            "type":"Services"
        }
    ],
    "sg:phone":"+1 276 783 1002",
    "sg:postcode":"24354",
    "sg:province":"VA",
    "sg:tags":[
        "help",
        "contractor"
    ],
    "wof:name":"Atwork Personnel Svc",
    "wof:placetype":"venue"
},
  "geometry": {"coordinates":[-81.517439,36.832632],"type":"Point"}
}