{
  "type": "Feature",
  "properties": {
    "iso:country":"US",
    "sg:address":"1131 Crawford Pkwy",
    "sg:city":"Portsmouth",
    "sg:classifiers":[
        {
            "category":"Organizations",
            "subcategory":"Religious Organization",
            "type":"Services"
        }
    ],
    "sg:phone":"+1 757 399 1279",
    "sg:postcode":"23704",
    "sg:province":"VA",
    "sg:tags":[
        "church"
    ],
    "wof:name":"Park View United Methodist Chr",
    "wof:placetype":"venue"
},
  "geometry": {"coordinates":[-76.31284100000001,36.841201],"type":"Point"}
}