{
  "type": "Feature",
  "properties": {
    "iso:country":"US",
    "sg:address":"11650 New Kent Hwy",
    "sg:city":"New Kent",
    "sg:classifiers":[
        {
            "category":"Organizations",
            "subcategory":"Religious Organization",
            "type":"Services"
        }
    ],
    "sg:phone":"+1 804 966 5635",
    "sg:postcode":"23124",
    "sg:province":"VA",
    "sg:tags":[
        "church"
    ],
    "wof:name":"Corinth Baptist Church",
    "wof:placetype":"venue"
},
  "geometry": {"coordinates":[-76.99953600000001,37.519714],"type":"Point"}
}