{
  "type": "Feature",
  "properties": {
    "addr:full":"306 Little Florida Rd Poquoson VA 23662",
    "addr:housenumber":"306",
    "addr:postcode":"23662",
    "addr:street":"Little Florida Rd",
    "iso:country":"US",
    "sg:address":"306 Little Florida Rd",
    "sg:city":"Poquoson",
    "sg:classifiers":[
        {
            "category":"Building & Trades",
            "subcategory":"Plumbing",
            "type":"Services"
        }
    ],
    "sg:phone":"+1 757 868 4469",
    "sg:postcode":"23662",
    "sg:province":"VA",
    "sg:tags":[
        "plumbing-drain",
        "cleaning",
        "sewer"
    ],
    "wof:name":"Best Way Plumbing & Drain Cleaning",
    "wof:placetype":"venue"
},
  "geometry": {"coordinates":[-76.37181099999999,37.12664],"type":"Point"}
}