{
  "type": "Feature",
  "properties": {
    "addr:full":"903 E Timber Branch Pkwy Alexandria VA 22302",
    "addr:housenumber":"903",
    "addr:postcode":"22302",
    "addr:street":"E Timber Branch Pkwy",
    "iso:country":"US",
    "sg:address":"903 E Timber Branch Pkwy",
    "sg:city":"Alexandria",
    "sg:classifiers":[
        {
            "category":"Real Estate",
            "subcategory":"Real Estate Services",
            "type":"Services"
        },
        {
            "category":"Banks & Credit Unions",
            "subcategory":"Financial Services",
            "type":"Services"
        }
    ],
    "sg:phone":"+1 703 548 4853",
    "sg:postcode":"22302",
    "sg:province":"VA",
    "sg:tags":[
        "loan",
        "processing"
    ],
    "wof:name":"Mid Atlantic Mortgage Solution",
    "wof:placetype":"venue"
},
  "geometry": {"coordinates":[-77.077213,38.824691],"type":"Point"}
}