{
  "type": "Feature",
  "properties": {
    "addr:full":"86 Lee St Radford VA 24141",
    "addr:housenumber":"86",
    "addr:postcode":"24141",
    "addr:street":"Lee St",
    "iso:country":"US",
    "sg:address":"86 Lee St",
    "sg:city":"Radford",
    "sg:classifiers":[
        {
            "category":"Organizations",
            "subcategory":"Religious Organization",
            "type":"Services"
        }
    ],
    "sg:phone":"+1 540 633 2814",
    "sg:postcode":"24141",
    "sg:province":"VA",
    "wof:name":"Liberty Full Gospel Fello",
    "wof:placetype":"venue"
},
  "geometry": {"coordinates":[-80.591931,37.114043],"type":"Point"}
}