{
  "type": "Feature",
  "properties": {
    "addr:full":"406 Rotary St Hampton VA 23661",
    "addr:housenumber":"406",
    "addr:postcode":"23661",
    "addr:street":"Rotary St",
    "iso:country":"US",
    "sg:address":"406 Rotary St",
    "sg:city":"Hampton",
    "sg:classifiers":[
        {
            "category":"Wholesale",
            "subcategory":"Chemicals & Plastics",
            "type":"Manufacturing & Wholesale Goods"
        }
    ],
    "sg:phone":"+1 757 262 1530",
    "sg:postcode":"23661",
    "sg:province":"VA",
    "sg:tags":[
        "equipment",
        "industrial"
    ],
    "wof:name":"Linde Gas LLC",
    "wof:placetype":"venue"
},
  "geometry": {"coordinates":[-76.40030299999999,37.008443],"type":"Point"}
}