{
  "type": "Feature",
  "properties": {
    "addr:full":"1031 Sterling Rd Herndon VA 20170",
    "addr:housenumber":"1031",
    "addr:postcode":"20170",
    "addr:street":"Sterling Rd",
    "iso:country":"US",
    "sg:address":"1031 Sterling Rd",
    "sg:city":"Herndon",
    "sg:classifiers":[
        {
            "category":"Professional",
            "subcategory":"Management & Consulting",
            "type":"Services"
        }
    ],
    "sg:phone":"+1 703 478 9800",
    "sg:postcode":"20170",
    "sg:province":"VA",
    "wof:name":"Italias Deli & Pizzaria",
    "wof:placetype":"venue"
},
  "geometry": {"coordinates":[-77.397172,38.969575],"type":"Point"}
}