{
  "type": "Feature",
  "properties": {
    "iso:country":"US",
    "sg:address":"112 N Sycamore St",
    "sg:city":"Petersburg",
    "sg:classifiers":[
        {
            "category":"Shopping",
            "subcategory":"Discount & Variety Stores",
            "type":"Retail Goods"
        },
        {
            "category":"Shopping",
            "subcategory":"Department Store",
            "type":"Retail Goods"
        }
    ],
    "sg:phone":"+1 804 732 5519",
    "sg:postcode":"23803",
    "sg:province":"VA",
    "sg:tags":[
        "shop"
    ],
    "wof:name":"Family Dollar Stores",
    "wof:placetype":"venue"
},
  "geometry": {"coordinates":[-77.404128,37.229736],"type":"Point"}
}