{
  "type": "Feature",
  "properties": {
    "iso:country":"US",
    "sg:address":"8674 Mary Ball Rd",
    "sg:city":"Lancaster",
    "sg:classifiers":[
        {
            "category":"Insurance",
            "subcategory":"Insurance Agent",
            "type":"Services"
        }
    ],
    "sg:phone":"+1 804 462 7631",
    "sg:postcode":"22503",
    "sg:province":"VA",
    "wof:name":"Michael B Callis Insurance",
    "wof:placetype":"venue"
},
  "geometry": {"coordinates":[-76.47358199999999,37.769779],"type":"Point"}
}