{
  "type": "Feature",
  "properties": {
    "iso:country":"US",
    "sg:address":"751 Thimble Shoals Blvd",
    "sg:city":"Newport News",
    "sg:classifiers":[
        {
            "category":"Banks & Credit Unions",
            "subcategory":"Bank",
            "type":"Services"
        }
    ],
    "sg:phone":"+1 757 873 0646",
    "sg:postcode":"23606",
    "sg:province":"VA",
    "sg:tags":[
        "mortgage",
        "loan",
        "broker",
        "lender",
        "real estate"
    ],
    "wof:name":"Mortgage Credit Corporation",
    "wof:placetype":"venue"
},
  "geometry": {"coordinates":[-76.46647900000001,37.082446],"type":"Point"}
}