{
  "type": "Feature",
  "properties": {
    "addr:full":"2044 Victory Blvd Portsmouth VA 23702",
    "addr:housenumber":"2044",
    "addr:postcode":"23702",
    "addr:street":"Victory Blvd",
    "iso:country":"US",
    "sg:address":"2044 Victory Blvd",
    "sg:city":"Portsmouth",
    "sg:classifiers":[
        {
            "category":"Insurance",
            "subcategory":"Insurance Agent",
            "type":"Services"
        }
    ],
    "sg:phone":"+1 757 558 6500",
    "sg:postcode":"23702",
    "sg:province":"VA",
    "wof:name":"Brenda Miller",
    "wof:placetype":"venue"
},
  "geometry": {"coordinates":[-76.328255,36.795293],"type":"Point"}
}