{
  "type": "Feature",
  "properties": {
    "addr:full":"2475 Shady Oaks Trl Maidens VA 23102",
    "addr:housenumber":"2475",
    "addr:postcode":"23102",
    "addr:street":"Shady Oaks Trl",
    "iso:country":"US",
    "sg:address":"2475 Shady Oaks Trl",
    "sg:city":"Maidens",
    "sg:classifiers":[
        {
            "category":"Wholesale",
            "subcategory":"Painting Supplies",
            "type":"Manufacturing & Wholesale Goods"
        }
    ],
    "sg:phone":"+1 804 556 2475",
    "sg:postcode":"23102",
    "sg:province":"VA",
    "sg:tags":[
        "paint-wholesale",
        "manufacturer"
    ],
    "wof:name":"Paint The Town",
    "wof:placetype":"venue"
},
  "geometry": {"coordinates":[-77.830101,37.727303],"type":"Point"}
}