{
  "type": "Feature",
  "properties": {
    "addr:full":"210 Fort Collier Rd Winchester VA 22603",
    "addr:housenumber":"210",
    "addr:postcode":"22603",
    "addr:street":"Fort Collier Rd",
    "iso:country":"US",
    "sg:address":"210 Fort Collier Rd",
    "sg:city":"Winchester",
    "sg:classifiers":[
        {
            "category":"Wholesale",
            "subcategory":"Machinery & Supplies",
            "type":"Manufacturing & Wholesale Goods"
        },
        {
            "category":"Wholesale",
            "subcategory":"Durable Goods & Equipment",
            "type":"Manufacturing & Wholesale Goods"
        }
    ],
    "sg:phone":"+1 703 779 9600",
    "sg:postcode":"22603",
    "sg:province":"VA",
    "sg:tags":[
        "fire",
        "extinguisher",
        "establishment"
    ],
    "wof:name":"Fire Protection Co",
    "wof:placetype":"venue"
},
  "geometry": {"coordinates":[-78.147848,39.195638],"type":"Point"}
}