{
  "type": "Feature",
  "properties": {
    "addr:full":"31 E Market St Harrisonburg VA 22801",
    "addr:housenumber":"31",
    "addr:postcode":"22801",
    "addr:street":"E Market St",
    "iso:country":"US",
    "sg:address":"31 E Market St",
    "sg:city":"Harrisonburg",
    "sg:classifiers":[
        {
            "category":"Organizations",
            "subcategory":"Religious Organization",
            "type":"Services"
        }
    ],
    "sg:phone":"+1 540 434 0386",
    "sg:postcode":"22801",
    "sg:province":"VA",
    "sg:tags":[
        "church"
    ],
    "wof:name":"House Of Refuge Agape Church",
    "wof:placetype":"venue"
},
  "geometry": {"coordinates":[-78.868313,38.449264],"type":"Point"}
}