{
  "type": "Feature",
  "properties": {
    "iso:country":"US",
    "sg:address":"13946 History Land Hwy",
    "sg:city":"Warsaw",
    "sg:classifiers":[
        {
            "category":"Education",
            "subcategory":"School",
            "type":"Public Place"
        }
    ],
    "sg:phone":"+1 804 333 9349",
    "sg:postcode":"22572",
    "sg:province":"VA",
    "wof:name":"Northern Neck Regional Altrntv",
    "wof:placetype":"venue"
},
  "geometry": {"coordinates":[-76.74951799999999,37.947485],"type":"Point"}
}