{
  "type": "Feature",
  "properties": {
    "iso:country":"US",
    "sg:address":"75 Holcombe Rd",
    "sg:city":"Lynchburg",
    "sg:classifiers":[
        {
            "category":"Wholesale",
            "subcategory":"Machinery & Supplies",
            "type":"Manufacturing & Wholesale Goods"
        }
    ],
    "sg:phone":"+1 434 239 5808",
    "sg:postcode":"24502",
    "sg:province":"VA",
    "sg:tags":[
        "equipment",
        "establishment"
    ],
    "wof:name":"Brenda Sligh Crawford",
    "wof:placetype":"venue"
},
  "geometry": {"coordinates":[-79.184631,37.323834],"type":"Point"}
}