{
  "type": "Feature",
  "properties": {
    "iso:country":"US",
    "sg:address":"1207 Forestwood Dr",
    "sg:city":"Mc Lean",
    "sg:classifiers":[
        {
            "category":"Health Services",
            "subcategory":"Doctor",
            "type":"Services"
        }
    ],
    "sg:phone":"+1 703 893 0028",
    "sg:postcode":"22101",
    "sg:province":"VA",
    "sg:tags":[
        "physician"
    ],
    "wof:name":"Ray E Stutzman M D",
    "wof:placetype":"venue"
},
  "geometry": {"coordinates":[-77.19080700000001,38.940858],"type":"Point"}
}