{
  "type": "Feature",
  "properties": {
    "addr:full":"2219 N Columbus St Arlington VA 22207",
    "addr:housenumber":"2219",
    "addr:postcode":"22207",
    "addr:street":"N Columbus St",
    "iso:country":"US",
    "sg:address":"2219 N Columbus St",
    "sg:city":"Arlington",
    "sg:classifiers":[
        {
            "category":"Building & Trades",
            "subcategory":"Construction",
            "type":"Services"
        }
    ],
    "sg:phone":"+1 703 525 3395",
    "sg:postcode":"22207",
    "sg:province":"VA",
    "sg:tags":[
        "carpentry",
        "contractor"
    ],
    "wof:name":"Dura Vent Aluminum Co",
    "wof:placetype":"venue"
},
  "geometry": {"coordinates":[-77.126216,38.896627],"type":"Point"}
}