{
  "type": "Feature",
  "properties": {
    "addr:full":"16363 King William Rd King William VA 23086",
    "addr:housenumber":"16363",
    "addr:postcode":"23086",
    "addr:street":"King William Rd",
    "iso:country":"US",
    "sg:address":"16363 King William Rd",
    "sg:city":"King William",
    "sg:classifiers":[
        {
            "category":"Building & Trades",
            "subcategory":"Landscaping Services",
            "type":"Services"
        }
    ],
    "sg:phone":"+1 804 769 8626",
    "sg:postcode":"23086",
    "sg:province":"VA",
    "wof:name":"Alexander Tree Service",
    "wof:placetype":"venue"
},
  "geometry": {"coordinates":[-77.063305,37.713775],"type":"Point"}
}