{
  "type": "Feature",
  "properties": {
    "iso:country":"US",
    "sg:address":"2023 Ridge Rd",
    "sg:city":"Haymarket",
    "sg:classifiers":[
        {
            "category":"Professional",
            "type":"Services"
        }
    ],
    "sg:phone":"+1 703 753 3699",
    "sg:postcode":"20169",
    "sg:province":"VA",
    "wof:name":"Robert Koev",
    "wof:placetype":"venue"
},
  "geometry": {"coordinates":[-77.66467900000001,38.918183],"type":"Point"}
}