{
  "type": "Feature",
  "properties": {
    "iso:country":"US",
    "sg:address":"10132 Colvin Run Rd",
    "sg:city":"Great Falls",
    "sg:classifiers":[
        {
            "category":"Professional",
            "type":"Services"
        }
    ],
    "sg:phone":"+1 703 757 9034",
    "sg:postcode":"22066",
    "sg:province":"VA",
    "wof:name":"Linsco Private Ledger Fncl Svc",
    "wof:placetype":"venue"
},
  "geometry": {"coordinates":[-77.29671999999999,38.973791],"type":"Point"}
}