{
  "type": "Feature",
  "properties": {
    "addr:full":"8000 Woodland Hills Ln Fairfax Station VA 22039",
    "addr:housenumber":"8000",
    "addr:postcode":"22039",
    "addr:street":"Woodland Hills Ln",
    "iso:country":"US",
    "sg:address":"8000 Woodland Hills Ln",
    "sg:city":"Fairfax Station",
    "sg:classifiers":[
        {
            "category":"Real Estate",
            "subcategory":"Real Estate Operator",
            "type":"Services"
        }
    ],
    "sg:phone":"+1 703 425 5432",
    "sg:postcode":"22039",
    "sg:province":"VA",
    "sg:tags":[
        "building",
        "nonresidential"
    ],
    "wof:name":"Suburban Shopping Center",
    "wof:placetype":"venue"
},
  "geometry": {"coordinates":[-77.316503,38.739154],"type":"Point"}
}