{
  "type": "Feature",
  "properties": {
    "addr:full":"4333 Black Beard Rd Virginia Beach VA 23455",
    "addr:housenumber":"4333",
    "addr:postcode":"23455",
    "addr:street":"Black Beard Rd",
    "iso:country":"US",
    "sg:address":"4333 Black Beard Rd",
    "sg:city":"Virginia Beach",
    "sg:classifiers":[
        {
            "category":"Real Estate",
            "subcategory":"Real Estate Agent",
            "type":"Services"
        }
    ],
    "sg:phone":"+1 757 363 1297",
    "sg:postcode":"23455",
    "sg:province":"VA",
    "wof:name":"Scotts Creek Properties Inc",
    "wof:placetype":"venue"
},
  "geometry": {"coordinates":[-76.122033,36.90729],"type":"Point"}
}