{
  "type": "Feature",
  "properties": {
    "addr:full":"455 Carlisle Dr Herndon VA 20170",
    "addr:housenumber":"455",
    "addr:postcode":"20170",
    "addr:street":"Carlisle Dr",
    "iso:country":"US",
    "sg:address":"455 Carlisle Dr",
    "sg:city":"Herndon",
    "sg:classifiers":[
        {
            "category":"Professional",
            "subcategory":"Management & Consulting",
            "type":"Services"
        }
    ],
    "sg:phone":"+1 703 834 6014",
    "sg:postcode":"20170",
    "sg:province":"VA",
    "sg:tags":[
        "business"
    ],
    "sg:website":"www.dmrisolutions.com",
    "wof:name":"Direct Marketing Results Inc",
    "wof:placetype":"venue"
},
  "geometry": {"coordinates":[-77.369067,38.966087],"type":"Point"}
}