{
  "type": "Feature",
  "properties": {
    "addr:full":"370 Fairfax Pike Stephens City VA 22655",
    "addr:housenumber":"370",
    "addr:postcode":"22655",
    "addr:street":"Fairfax Pike",
    "iso:country":"US",
    "sg:address":"370 Fairfax Pike",
    "sg:city":"Stephens City",
    "sg:classifiers":[
        {
            "category":"Health Services",
            "subcategory":"Doctor",
            "type":"Services"
        }
    ],
    "sg:phone":"+1 540 868 4100",
    "sg:postcode":"22655",
    "sg:province":"VA",
    "sg:tags":[
        "physician",
        "surgeon"
    ],
    "wof:name":"Stephens City Family Medicine",
    "wof:placetype":"venue"
},
  "geometry": {"coordinates":[-78.20451199999999,39.080781],"type":"Point"}
}