{
  "type": "Feature",
  "properties": {
    "addr:full":"6305 Horsepen Rd Richmond VA 23226",
    "addr:housenumber":"6305",
    "addr:postcode":"23226",
    "addr:street":"Horsepen Rd",
    "iso:country":"US",
    "sg:address":"6305 Horsepen Rd",
    "sg:city":"Richmond",
    "sg:classifiers":[
        {
            "category":"Autos & Motor Vehicles",
            "subcategory":"Automobile Sales",
            "type":"Retail Goods"
        }
    ],
    "sg:phone":"+1 804 282 0195",
    "sg:postcode":"23226",
    "sg:province":"VA",
    "sg:tags":[
        "repair",
        "used",
        "general"
    ],
    "wof:name":"Virginia Import Service Inc",
    "wof:placetype":"venue"
},
  "geometry": {"coordinates":[-77.513752,37.595112],"type":"Point"}
}