{
  "type": "Feature",
  "properties": {
    "iso:country":"US",
    "sg:address":"1160 Pickett Rd",
    "sg:city":"Norfolk",
    "sg:classifiers":[
        {
            "category":"Building & Trades",
            "subcategory":"Construction",
            "type":"Services"
        }
    ],
    "sg:phone":"+1 757 857 4900",
    "sg:postcode":"23502",
    "sg:province":"VA",
    "sg:tags":[
        "control",
        "corrosion"
    ],
    "sg:website":"www.corrpro.com",
    "wof:name":"Corrpro Co Inc",
    "wof:placetype":"venue"
},
  "geometry": {"coordinates":[-76.220772,36.860678],"type":"Point"}
}