{
  "type": "Feature",
  "properties": {
    "iso:country":"US",
    "sg:address":"102 Old Tobacco Dr",
    "sg:city":"Lawrenceville",
    "sg:classifiers":[
        {
            "category":"Government",
            "subcategory":"Office",
            "type":"Public Place"
        }
    ],
    "sg:phone":"+1 434 848 3107",
    "sg:postcode":"23868",
    "sg:province":"VA",
    "wof:name":"Brunswick County Administrator",
    "wof:placetype":"venue"
},
  "geometry": {"coordinates":[-77.783874,36.811475],"type":"Point"}
}