{
  "type": "Feature",
  "properties": {
    "addr:full":"1077 Copper Line Rd Bumpass VA 23024",
    "addr:housenumber":"1077",
    "addr:postcode":"23024",
    "addr:street":"Copper Line Rd",
    "iso:country":"US",
    "sg:address":"1077 Copper Line Rd",
    "sg:city":"Bumpass",
    "sg:classifiers":[
        {
            "category":"Building & Trades",
            "subcategory":"Construction",
            "type":"Services"
        }
    ],
    "sg:phone":"+1 540 872 5520",
    "sg:postcode":"23024",
    "sg:province":"VA",
    "sg:tags":[
        "contractor"
    ],
    "wof:name":"Hanover Masonry Inc",
    "wof:placetype":"venue"
},
  "geometry": {"coordinates":[-77.821022,37.854946],"type":"Point"}
}