{
  "type": "Feature",
  "properties": {
    "iso:country":"US",
    "sg:address":"9 Wildwood Rd",
    "sg:city":"Salem",
    "sg:classifiers":[
        {
            "category":"Building & Trades",
            "subcategory":"Construction",
            "type":"Services"
        }
    ],
    "sg:phone":"+1 540 389 6950",
    "sg:postcode":"24153",
    "sg:province":"VA",
    "sg:tags":[
        "house",
        "general",
        "design",
        "contractor"
    ],
    "wof:name":"American U S A Homes",
    "wof:placetype":"venue"
},
  "geometry": {"coordinates":[-80.095263,37.288815],"type":"Point"}
}