{
  "type": "Feature",
  "properties": {
    "iso:country":"US",
    "sg:address":"6 Pidgeon Hill Dr",
    "sg:city":"Sterling",
    "sg:classifiers":[
        {
            "category":"Professional",
            "subcategory":"Engineering",
            "type":"Services"
        }
    ],
    "sg:phone":"+1 703 450 9704",
    "sg:postcode":"20165",
    "sg:province":"VA",
    "wof:name":"Face Assoc Inc",
    "wof:placetype":"venue"
},
  "geometry": {"coordinates":[-77.414033,39.038582],"type":"Point"}
}