{
  "type": "Feature",
  "properties": {
    "iso:country":"US",
    "sg:address":"1001 N Main St",
    "sg:city":"Blacksburg",
    "sg:classifiers":[
        {
            "category":"Restaurant",
            "type":"Food & Drink"
        }
    ],
    "sg:menulink":"http://www.allmenus.com/va/blacksburg/257480-abbys/menu/",
    "sg:phone":"+1 540 953 0100",
    "sg:postcode":"24060",
    "sg:province":"VA",
    "sg:tags":[
        "american",
        "sandwich",
        "pub",
        "salad",
        "wing"
    ],
    "wof:name":"Abby's",
    "wof:placetype":"venue"
},
  "geometry": {"coordinates":[-80.4204,37.238654],"type":"Point"}
}