{
  "type": "Feature",
  "properties": {
    "addr:full":"202 Mason Ave Cape Charles VA 23310",
    "addr:housenumber":"202",
    "addr:postcode":"charles;23310",
    "addr:street":"Mason Ave",
    "iso:country":"US",
    "sg:address":"202 Mason Ave",
    "sg:city":"Cape Charles",
    "sg:classifiers":[
        {
            "category":"Railroad",
            "type":"Transportation"
        }
    ],
    "sg:phone":"+1 757 331 1094",
    "sg:postcode":"23310",
    "sg:province":"VA",
    "wof:name":"Eastern Shore Railroad",
    "wof:placetype":"venue"
},
  "geometry": {"coordinates":[-76.019593,37.267154],"type":"Point"}
}