{
  "type": "Feature",
  "properties": {
    "iso:country":"US",
    "sg:address":"114 Alderman Rd",
    "sg:city":"Charlottesville",
    "sg:classifiers":[
        {
            "category":"Shopping",
            "subcategory":"Books",
            "type":"Retail Goods"
        }
    ],
    "sg:phone":"+1 434 924 8851",
    "sg:postcode":"22903",
    "sg:province":"VA",
    "wof:name":"Rare Book School",
    "wof:placetype":"venue"
},
  "geometry": {"coordinates":[-78.51321,38.040918],"type":"Point"}
}