{
  "type": "Feature",
  "properties": {
    "iso:country":"US",
    "sg:address":"2707 Silkwood Ct",
    "sg:city":"Oakton",
    "sg:classifiers":[
        {
            "category":"Professional",
            "subcategory":"Business Services",
            "type":"Services"
        }
    ],
    "sg:phone":"+1 703 860 2006",
    "sg:postcode":"22124",
    "sg:province":"VA",
    "sg:tags":[
        "development",
        "marketing",
        "product",
        "design"
    ],
    "sg:website":"http://www.maxarc.com",
    "wof:name":"Maxwell Design Assoc",
    "wof:placetype":"venue"
},
  "geometry": {"coordinates":[-77.33306,38.89919],"type":"Point"}
}