{
  "type": "Feature",
  "properties": {
    "addr:full":"838 Lucy Wade Rd Rocky Mount VA 24151",
    "addr:housenumber":"838",
    "addr:postcode":"24151",
    "addr:street":"Lucy Wade Rd",
    "iso:country":"US",
    "sg:address":"838 Lucy Wade Rd",
    "sg:city":"Rocky Mount",
    "sg:classifiers":[
        {
            "category":"Building & Trades",
            "subcategory":"Construction",
            "type":"Services"
        }
    ],
    "sg:phone":"+1 540 483 8630",
    "sg:postcode":"24151",
    "sg:province":"VA",
    "sg:tags":[
        "tile",
        "contractor"
    ],
    "wof:name":"Hodges Tile",
    "wof:placetype":"venue"
},
  "geometry": {"coordinates":[-79.833432,36.934878],"type":"Point"}
}