{
  "type": "Feature",
  "properties": {
    "iso:country":"US",
    "sg:address":"4626 King St",
    "sg:city":"Alexandria",
    "sg:classifiers":[
        {
            "category":"Fast Food",
            "type":"Food & Drink"
        }
    ],
    "sg:phone":"+1 703 671 1606",
    "sg:postcode":"22302",
    "sg:province":"VA",
    "sg:tags":[
        "burger"
    ],
    "sg:website":"www.fiveguys.com/",
    "wof:name":"Five Guys Burgers and Fries",
    "wof:placetype":"venue"
},
  "geometry": {"coordinates":[-77.10772,38.841355],"type":"Point"}
}