{
  "type": "Feature",
  "properties": {
    "addr:full":"7106 Williamson Rd Roanoke VA 24019",
    "addr:housenumber":"7106",
    "addr:postcode":"24019",
    "addr:street":"Williamson Rd",
    "iso:country":"US",
    "sg:address":"7106 Williamson Rd",
    "sg:city":"Roanoke",
    "sg:classifiers":[
        {
            "category":"Wholesale",
            "subcategory":"Auto Parts",
            "type":"Manufacturing & Wholesale Goods"
        }
    ],
    "sg:phone":"+1 540 362 3923",
    "sg:postcode":"24019",
    "sg:province":"VA",
    "sg:tags":[
        "automobile",
        "used",
        "general"
    ],
    "wof:name":"WEBB Motors Inc",
    "wof:placetype":"venue"
},
  "geometry": {"coordinates":[-79.95575599999999,37.344654],"type":"Point"}
}