{
  "type": "Feature",
  "properties": {
    "iso:country":"US",
    "sg:address":"2441 Temple Ct",
    "sg:city":"Alexandria",
    "sg:classifiers":[
        {
            "category":"Professional",
            "subcategory":"Management & Consulting",
            "type":"Services"
        }
    ],
    "sg:phone":"+1 703 765 0714",
    "sg:postcode":"22307",
    "sg:province":"VA",
    "sg:tags":[
        "public",
        "relations"
    ],
    "wof:name":"Vampyrum Publicity Inc",
    "wof:placetype":"venue"
},
  "geometry": {"coordinates":[-77.075186,38.765365],"type":"Point"}
}