{
  "type": "Feature",
  "properties": {
    "addr:full":"6401 Old Dominion Dr Mc Lean VA 22101",
    "addr:housenumber":"6401",
    "addr:postcode":"22101",
    "addr:street":"Old Dominion Dr",
    "iso:country":"US",
    "sg:address":"6401 Old Dominion Dr",
    "sg:city":"Mc Lean",
    "sg:classifiers":[
        {
            "category":"Real Estate",
            "subcategory":"Developer",
            "type":"Services"
        },
        {
            "category":"Education",
            "subcategory":"Special Training",
            "type":"Public Place"
        }
    ],
    "sg:phone":"+1 703 827 9282",
    "sg:postcode":"22101",
    "sg:province":"VA",
    "sg:tags":[
        "program"
    ],
    "wof:name":"Lifestyles Development Inst",
    "wof:placetype":"venue"
},
  "geometry": {"coordinates":[-77.161475,38.924065],"type":"Point"}
}