{
  "type": "Feature",
  "properties": {
    "addr:full":"261 Summit Point Rd Berryville VA 22611",
    "addr:housenumber":"261",
    "addr:postcode":"22611",
    "addr:street":"Summit Point Rd",
    "iso:country":"US",
    "sg:address":"261 Summit Point Rd",
    "sg:city":"Berryville",
    "sg:phone":"+1 540 955 3865",
    "sg:postcode":"22611",
    "sg:province":"VA",
    "sg:tags":[
        "farm",
        "field",
        "corn",
        "crop"
    ],
    "wof:name":"Ashwill Farm",
    "wof:placetype":"venue"
},
  "geometry": {"coordinates":[-77.971926,39.181588],"type":"Point"}
}