{
  "type": "Feature",
  "properties": {
    "addr:full":"122 E Main St Bedford VA 24523",
    "addr:housenumber":"122",
    "addr:postcode":"24523",
    "addr:street":"E Main St",
    "iso:country":"US",
    "sg:address":"122 E Main St",
    "sg:city":"Bedford",
    "sg:classifiers":[
        {
            "category":"Government",
            "subcategory":"Office",
            "type":"Public Place"
        }
    ],
    "sg:phone":"+1 540 586 7670",
    "sg:postcode":"24523",
    "sg:province":"VA",
    "sg:tags":[
        "county",
        "taxation"
    ],
    "wof:name":"Bedford County Treasurer",
    "wof:placetype":"venue"
},
  "geometry": {"coordinates":[-79.523301,37.334313],"type":"Point"}
}