{
  "type": "Feature",
  "properties": {
    "addr:full":"4036 Bolling Rd Richmond VA 23223",
    "addr:housenumber":"4036",
    "addr:postcode":"23223",
    "addr:street":"Bolling Rd",
    "iso:country":"US",
    "sg:address":"4036 Bolling Rd",
    "sg:city":"Richmond",
    "sg:classifiers":[
        {
            "category":"Building & Trades",
            "subcategory":"Construction",
            "type":"Services"
        }
    ],
    "sg:phone":"+1 804 321 5508",
    "sg:postcode":"23223",
    "sg:province":"VA",
    "sg:tags":[
        "painting",
        "contractor"
    ],
    "wof:name":"D & H Painting & Wallcovering Co",
    "wof:placetype":"venue"
},
  "geometry": {"coordinates":[-77.38463299999999,37.580417],"type":"Point"}
}