{
  "type": "Feature",
  "properties": {
    "addr:full":"2913 Shore Dr Virginia Beach VA 23451",
    "addr:housenumber":"2913",
    "addr:postcode":"23451",
    "addr:street":"Shore Dr",
    "iso:country":"US",
    "sg:address":"2913 Shore Dr",
    "sg:city":"Virginia Beach",
    "sg:classifiers":[
        {
            "category":"Restaurant",
            "type":"Food & Drink"
        }
    ],
    "sg:phone":"+1 757 481 7425",
    "sg:postcode":"23451",
    "sg:province":"VA",
    "sg:tags":[
        "drinking",
        "eating"
    ],
    "wof:name":"Reef Lounge",
    "wof:placetype":"venue"
},
  "geometry": {"coordinates":[-76.072148,36.911299],"type":"Point"}
}