{
  "type": "Feature",
  "properties": {
    "addr:full":"9501 Maji Dr Richmond VA 23228",
    "addr:housenumber":"9501",
    "addr:postcode":"23228",
    "addr:street":"Maji Dr",
    "iso:country":"US",
    "sg:address":"9501 Maji Dr",
    "sg:city":"Richmond",
    "sg:classifiers":[
        {
            "category":"Retail",
            "subcategory":"Repair Shop",
            "type":"Services"
        }
    ],
    "sg:phone":"+1 804 264 5558",
    "sg:postcode":"23228",
    "sg:province":"VA",
    "wof:name":"Mitchell Clean",
    "wof:placetype":"venue"
},
  "geometry": {"coordinates":[-77.46692899999999,37.644622],"type":"Point"}
}