{
  "type": "Feature",
  "properties": {
    "addr:full":"7927 Jones Branch Dr Mc Lean VA 22102",
    "addr:housenumber":"7927",
    "addr:postcode":"22102",
    "addr:street":"Jones Branch Dr",
    "iso:country":"US",
    "sg:address":"7927 Jones Branch Dr",
    "sg:city":"Mc Lean",
    "sg:classifiers":[
        {
            "category":"Manufacturing",
            "subcategory":"Tools & Machinery",
            "type":"Manufacturing & Wholesale Goods"
        }
    ],
    "sg:phone":"+1 703 734 5315",
    "sg:postcode":"22102",
    "sg:province":"VA",
    "sg:tags":[
        "equipment",
        "peripheral",
        "computer",
        "mfg"
    ],
    "wof:name":"Saic",
    "wof:placetype":"venue"
},
  "geometry": {"coordinates":[-77.218971,38.931472],"type":"Point"}
}