{
  "type": "Feature",
  "properties": {
    "addr:full":"17794 Main St Dumfries VA 22026",
    "addr:housenumber":"17794",
    "addr:postcode":"22026",
    "addr:street":"Main St",
    "iso:country":"US",
    "sg:address":"17794 Main St",
    "sg:city":"Dumfries",
    "sg:classifiers":[
        {
            "category":"Organizations",
            "subcategory":"Religious Organization",
            "type":"Services"
        }
    ],
    "sg:phone":"+1 703 221 3456",
    "sg:postcode":"22026",
    "sg:province":"VA",
    "sg:tags":[
        "church"
    ],
    "wof:name":"Open Door Apostolic Christian",
    "wof:placetype":"venue"
},
  "geometry": {"coordinates":[-77.328289,38.566927],"type":"Point"}
}