{
  "type": "Feature",
  "properties": {
    "addr:full":"3503 Norris Pl Alexandria VA 22305",
    "addr:housenumber":"3503",
    "addr:postcode":"22305",
    "addr:street":"Norris Pl",
    "iso:country":"US",
    "sg:address":"3503 Norris Pl",
    "sg:city":"Alexandria",
    "sg:classifiers":[
        {
            "category":"Professional",
            "subcategory":"Computer Services",
            "type":"Services"
        }
    ],
    "sg:phone":"+1 703 548 5227",
    "sg:postcode":"22305",
    "sg:province":"VA",
    "sg:tags":[
        "programing",
        "custom"
    ],
    "wof:name":"Hh Research Co",
    "wof:placetype":"venue"
},
  "geometry": {"coordinates":[-77.06594800000001,38.838183],"type":"Point"}
}