{
  "type": "Feature",
  "properties": {
    "addr:full":"4429 Revere Dr Virginia Beach VA 23456",
    "addr:housenumber":"4429",
    "addr:postcode":"23456",
    "addr:street":"Revere Dr",
    "iso:country":"US",
    "sg:address":"4429 Revere Dr",
    "sg:city":"Virginia Beach",
    "sg:classifiers":[
        {
            "category":"Shopping",
            "type":"Retail Goods"
        }
    ],
    "sg:phone":"+1 757 467 4700",
    "sg:postcode":"23456",
    "sg:province":"VA",
    "sg:tags":[
        "merchandise"
    ],
    "wof:name":"Frames On Go",
    "wof:placetype":"venue"
},
  "geometry": {"coordinates":[-76.131984,36.795462],"type":"Point"}
}