{
  "type": "Feature",
  "properties": {
    "iso:country":"US",
    "sg:address":"701 12th St S",
    "sg:city":"Arlington",
    "sg:classifiers":[
        {
            "category":"Banks & Credit Unions",
            "subcategory":"Investment Brokerage",
            "type":"Services"
        }
    ],
    "sg:phone":"+1 703 522 5064",
    "sg:postcode":"22202",
    "sg:province":"VA",
    "sg:tags":[
        "advisory"
    ],
    "wof:name":"Axp Financial Advisors Tm",
    "wof:placetype":"venue"
},
  "geometry": {"coordinates":[-77.058088,38.862913],"type":"Point"}
}