{
  "type": "Feature",
  "properties": {
    "iso:country":"US",
    "sg:address":"3139 Shore Dr",
    "sg:city":"Virginia Beach",
    "sg:classifiers":[
        {
            "category":"Restaurant",
            "type":"Food & Drink"
        }
    ],
    "sg:phone":"+1 757 481 9863",
    "sg:postcode":"23451",
    "sg:province":"VA",
    "sg:website":"www.charliesseafood.com",
    "wof:name":"Charlie's Seafood Restaurant",
    "wof:placetype":"venue"
},
  "geometry": {"coordinates":[-76.079812,36.909839],"type":"Point"}
}