{
  "type": "Feature",
  "properties": {
    "addr:full":"5601 Cayuga Ct Virginia Beach VA 23462",
    "addr:housenumber":"5601",
    "addr:postcode":"23462",
    "addr:street":"Cayuga Ct",
    "iso:country":"US",
    "sg:address":"5601 Cayuga Ct",
    "sg:city":"Virginia Beach",
    "sg:classifiers":[
        {
            "category":"Building & Trades",
            "subcategory":"Landscaping Services",
            "type":"Services"
        }
    ],
    "sg:phone":"+1 757 473 1625",
    "sg:postcode":"23462",
    "sg:province":"VA",
    "wof:name":"Smith Tree Svc",
    "wof:placetype":"venue"
},
  "geometry": {"coordinates":[-76.18295999999999,36.838114],"type":"Point"}
}