{
  "type": "Feature",
  "properties": {
    "addr:full":"105 Ridge St Charlottesville VA 22902",
    "addr:housenumber":"105",
    "addr:postcode":"22902",
    "addr:street":"Ridge St",
    "iso:country":"US",
    "sg:address":"105 Ridge St",
    "sg:city":"Charlottesville",
    "sg:classifiers":[
        {
            "category":"Social Services",
            "type":"Services"
        }
    ],
    "sg:phone":"+1 434 979 5478",
    "sg:postcode":"22902",
    "sg:province":"VA",
    "sg:tags":[
        "youth",
        "organization",
        "center"
    ],
    "wof:name":"Music Resource Ctr",
    "wof:placetype":"venue"
},
  "geometry": {"coordinates":[-78.48558800000001,38.029668],"type":"Point"}
}