{
  "type": "Feature",
  "properties": {
    "addr:full":"6821 Rocky Bar Rd Elkton VA 22827",
    "addr:housenumber":"6821",
    "addr:postcode":"22827",
    "addr:street":"Rocky Bar Rd",
    "iso:country":"US",
    "sg:address":"6821 Rocky Bar Rd",
    "sg:city":"Elkton",
    "sg:classifiers":[
        {
            "category":"Autos & Motor Vehicles",
            "subcategory":"Automobile Sales",
            "type":"Retail Goods"
        }
    ],
    "sg:phone":"+1 540 289 5536",
    "sg:postcode":"22827",
    "sg:province":"VA",
    "sg:tags":[
        "car",
        "dealer"
    ],
    "wof:name":"Odell's Used Cars",
    "wof:placetype":"venue"
},
  "geometry": {"coordinates":[-78.684721,38.345323],"type":"Point"}
}