{
  "type": "Feature",
  "properties": {
    "iso:country":"US",
    "sg:address":"463 Camp Ground Rd",
    "sg:city":"Emporia",
    "sg:classifiers":[
        {
            "category":"Retail",
            "subcategory":"Repair Shop",
            "type":"Services"
        }
    ],
    "sg:phone":"+1 434 348 3666",
    "sg:postcode":"23847",
    "sg:province":"VA",
    "sg:tags":[
        "machine",
        "sewing",
        "vacuum"
    ],
    "wof:name":"Lows Sew and Vacuum",
    "wof:placetype":"venue"
},
  "geometry": {"coordinates":[-77.60477400000001,36.681765],"type":"Point"}
}