{
  "type": "Feature",
  "properties": {
    "addr:full":"110 N Sycamore St Petersburg VA 23803",
    "addr:housenumber":"110",
    "addr:postcode":"23803",
    "addr:street":"N Sycamore",
    "iso:country":"US",
    "sg:address":"110 N Sycamore St",
    "sg:city":"Petersburg",
    "sg:classifiers":[
        {
            "category":"Building & Trades",
            "subcategory":"Construction",
            "type":"Services"
        }
    ],
    "sg:phone":"+1 804 732 1545",
    "sg:postcode":"23803",
    "sg:province":"VA",
    "sg:tags":[
        "hanging",
        "contractor"
    ],
    "wof:name":"Beauty Master",
    "wof:placetype":"venue"
},
  "geometry": {"coordinates":[-77.40414800000001,37.229804],"type":"Point"}
}