{
  "type": "Feature",
  "properties": {
    "addr:full":"7356 Atlee Rd Mechanicsville VA 23111",
    "addr:housenumber":"7356",
    "addr:postcode":"23111",
    "addr:street":"Atlee Rd",
    "iso:country":"US",
    "sg:address":"7356 Atlee Rd",
    "sg:city":"Mechanicsville",
    "sg:classifiers":[
        {
            "category":"Organizations",
            "subcategory":"Religious Organization",
            "type":"Services"
        }
    ],
    "sg:phone":"+1 804 746 5118",
    "sg:postcode":"23111",
    "sg:province":"VA",
    "sg:tags":[
        "church"
    ],
    "sg:website":"www.mechanicsvilleumc.org",
    "wof:name":"Mechanicsville United Mthdst",
    "wof:placetype":"venue"
},
  "geometry": {"coordinates":[-77.37415,37.608043],"type":"Point"}
}