{
  "type": "Feature",
  "properties": {
    "addr:full":"1 Lear Dr Newport News VA 23602",
    "addr:housenumber":"1",
    "addr:postcode":"23602",
    "addr:street":"Lear Dr",
    "iso:country":"US",
    "sg:address":"1 Lear Dr",
    "sg:city":"Newport News",
    "sg:classifiers":[
        {
            "category":"Professional",
            "type":"Services"
        }
    ],
    "sg:phone":"+1 757 874 8100",
    "sg:postcode":"23602",
    "sg:province":"VA",
    "sg:tags":[
        "establishment"
    ],
    "wof:name":"Atac",
    "wof:placetype":"venue"
},
  "geometry": {"coordinates":[-76.501119,37.135023],"type":"Point"}
}