{
  "type": "Feature",
  "properties": {
    "iso:country":"US",
    "sg:address":"10246 Staples Mill Rd",
    "sg:city":"Glen Allen",
    "sg:classifiers":[
        {
            "category":"Shopping",
            "subcategory":"Tobacco",
            "type":"Retail Goods"
        }
    ],
    "sg:phone":"+1 804 864 3880",
    "sg:postcode":"23060",
    "sg:province":"VA",
    "sg:tags":[
        "cigarette",
        "cigar",
        "dealer"
    ],
    "wof:name":"Private Stock Cigar & Wine Co",
    "wof:placetype":"venue"
},
  "geometry": {"coordinates":[-77.524494,37.657677],"type":"Point"}
}