{
  "type": "Feature",
  "properties": {
    "addr:full":"3601 E Broad St Richmond VA 23223",
    "addr:housenumber":"3601",
    "addr:postcode":"23223",
    "addr:street":"E Broad St",
    "iso:country":"US",
    "sg:address":"3601 E Broad St",
    "sg:city":"Richmond",
    "sg:classifiers":[
        {
            "category":"Building & Trades",
            "subcategory":"Construction",
            "type":"Services"
        }
    ],
    "sg:phone":"+1 804 236 1073",
    "sg:postcode":"23223",
    "sg:province":"VA",
    "sg:tags":[
        "concrete",
        "contractor"
    ],
    "wof:name":"Slab Concrete",
    "wof:placetype":"venue"
},
  "geometry": {"coordinates":[-77.40720399999999,37.525214],"type":"Point"}
}