{
  "type": "Feature",
  "properties": {
    "addr:full":"141 E Market St Harrisonburg VA 22801",
    "addr:housenumber":"141",
    "addr:postcode":"22801",
    "addr:street":"E Market St",
    "iso:country":"US",
    "sg:address":"141 E Market St",
    "sg:city":"Harrisonburg",
    "sg:classifiers":[
        {
            "category":"Professional",
            "subcategory":"Lawyer & Legal Services",
            "type":"Services"
        }
    ],
    "sg:phone":"+1 540 437 3129",
    "sg:postcode":"22801",
    "sg:province":"VA",
    "sg:tags":[
        "attorney"
    ],
    "wof:name":"Mary Hall",
    "wof:placetype":"venue"
},
  "geometry": {"coordinates":[-78.86725199999999,38.44909],"type":"Point"}
}