{
  "type": "Feature",
  "properties": {
    "iso:country":"US",
    "sg:address":"227 N Locust St",
    "sg:city":"Floyd",
    "sg:classifiers":[
        {
            "category":"Professional",
            "type":"Services"
        }
    ],
    "sg:phone":"+1 540 745 2782",
    "sg:postcode":"24091",
    "sg:province":"VA",
    "sg:tags":[
        "establishment"
    ],
    "wof:name":"Over The Moon",
    "wof:placetype":"venue"
},
  "geometry": {"coordinates":[-80.32069799999999,36.913768],"type":"Point"}
}