{
  "type": "Feature",
  "properties": {
    "iso:country":"US",
    "sg:address":"4500 Mc Gregor Dr",
    "sg:city":"Virginia Beach",
    "sg:classifiers":[
        {
            "category":"Building & Trades",
            "subcategory":"Construction",
            "type":"Services"
        }
    ],
    "sg:phone":"+1 757 493 0691",
    "sg:postcode":"23462",
    "sg:province":"VA",
    "sg:tags":[
        "house"
    ],
    "wof:name":"Invictus Construction Co Inc",
    "wof:placetype":"venue"
},
  "geometry": {"coordinates":[-76.13005699999999,36.823396],"type":"Point"}
}