{
  "type": "Feature",
  "properties": {
    "addr:full":"1315 N Fort Myer Dr Arlington VA 22209",
    "addr:housenumber":"1315",
    "addr:postcode":"22209",
    "addr:street":"N Fort Myer Dr",
    "iso:country":"US",
    "sg:address":"1315 N Fort Myer Dr",
    "sg:city":"Arlington",
    "sg:classifiers":[
        {
            "category":"Professional",
            "subcategory":"Business Services",
            "type":"Services"
        }
    ],
    "sg:phone":"+1 703 312 4616",
    "sg:postcode":"22209",
    "sg:province":"VA",
    "sg:tags":[
        "translation",
        "research"
    ],
    "wof:name":"Heidi A Holz",
    "wof:placetype":"venue"
},
  "geometry": {"coordinates":[-77.074606,38.889282],"type":"Point"}
}