{
  "type": "Feature",
  "properties": {
    "addr:full":"684 Harpersville Rd Newport News VA 23601",
    "addr:housenumber":"684",
    "addr:postcode":"23601",
    "addr:street":"Harpersville Rd",
    "iso:country":"US",
    "sg:address":"684 Harpersville Rd",
    "sg:city":"Newport News",
    "sg:classifiers":[
        {
            "category":"Building & Trades",
            "subcategory":"Construction",
            "type":"Services"
        }
    ],
    "sg:phone":"+1 757 595 2209",
    "sg:postcode":"23601",
    "sg:province":"VA",
    "sg:tags":[
        "house"
    ],
    "wof:name":"Tony Juliano Construction",
    "wof:placetype":"venue"
},
  "geometry": {"coordinates":[-76.45691100000001,37.075358],"type":"Point"}
}