{
  "type": "Feature",
  "properties": {
    "addr:full":"620 Court St Lynchburg VA 24504",
    "addr:housenumber":"620",
    "addr:postcode":"24504",
    "addr:street":"Court St",
    "iso:country":"US",
    "sg:address":"620 Court St",
    "sg:city":"Lynchburg",
    "sg:classifiers":[
        {
            "category":"Health Services",
            "subcategory":"Hospital",
            "type":"Services"
        }
    ],
    "sg:phone":"+1 434 525 5723",
    "sg:postcode":"24504",
    "sg:province":"VA",
    "sg:tags":[
        "medicine",
        "physician",
        "addiction",
        "surgeons",
        "specialty"
    ],
    "sg:website":"http://www.cvcsb.org",
    "wof:name":"Arise Residential Trtmnt Ctr",
    "wof:placetype":"venue"
},
  "geometry": {"coordinates":[-79.146153,37.416118],"type":"Point"}
}