{
  "type": "Feature",
  "properties": {
    "iso:country":"US",
    "sg:address":"7627 Jordon Hollow Ct",
    "sg:city":"Manassas",
    "sg:classifiers":[
        {
            "category":"Sports & Exercise",
            "subcategory":"Gym",
            "type":"Entertainment"
        }
    ],
    "sg:phone":"+1 703 330 1774",
    "sg:postcode":"20109",
    "sg:province":"VA",
    "sg:tags":[
        "fitness",
        "physical",
        "facility"
    ],
    "wof:name":"Bradfords Jeff Personal Train",
    "wof:placetype":"venue"
},
  "geometry": {"coordinates":[-77.50796,38.792586],"type":"Point"}
}