{
  "type": "Feature",
  "properties": {
    "addr:full":"3008 Berkmar Dr Charlottesville VA 22901",
    "addr:housenumber":"3008",
    "addr:postcode":"22901",
    "addr:street":"Berkmar Dr",
    "iso:country":"US",
    "sg:address":"3008 Berkmar Dr",
    "sg:city":"Charlottesville",
    "sg:classifiers":[
        {
            "category":"Personal",
            "type":"Services"
        }
    ],
    "sg:phone":"+1 434 964 6504",
    "sg:postcode":"22901",
    "sg:province":"VA",
    "wof:name":"Great Hands Massage",
    "wof:placetype":"venue"
},
  "geometry": {"coordinates":[-78.478887,38.083437],"type":"Point"}
}