{
  "type": "Feature",
  "properties": {
    "addr:full":"1025 S Crater Rd Petersburg VA 23805",
    "addr:housenumber":"1025",
    "addr:postcode":"23805",
    "addr:street":"S Crater Rd",
    "iso:country":"US",
    "sg:address":"1025 S Crater Rd",
    "sg:city":"Petersburg",
    "sg:classifiers":[
        {
            "category":"Real Estate",
            "subcategory":"Real Estate Agent",
            "type":"Services"
        },
        {
            "category":"Real Estate",
            "subcategory":"Real Estate Operator",
            "type":"Services"
        }
    ],
    "sg:phone":"+1 804 733 6298",
    "sg:postcode":"23805",
    "sg:province":"VA",
    "sg:tags":[
        "apartment"
    ],
    "wof:name":"Crater Square Apartments",
    "wof:placetype":"venue"
},
  "geometry": {"coordinates":[-77.384303,37.213495],"type":"Point"}
}