{
  "type": "Feature",
  "properties": {
    "iso:country":"US",
    "sg:address":"960 Willbrook Rd",
    "sg:city":"Newport News",
    "sg:classifiers":[
        {
            "category":"Manufacturing",
            "subcategory":"Printing",
            "type":"Manufacturing & Wholesale Goods"
        }
    ],
    "sg:phone":"+1 757 369 3879",
    "sg:postcode":"23602",
    "sg:province":"VA",
    "sg:tags":[
        "book"
    ],
    "wof:name":"Champs Create A Book",
    "wof:placetype":"venue"
},
  "geometry": {"coordinates":[-76.478309,37.112091],"type":"Point"}
}