{
  "type": "Feature",
  "properties": {
    "iso:country":"US",
    "sg:address":"2267 Providence St",
    "sg:city":"Falls Church",
    "sg:classifiers":[
        {
            "category":"Building & Trades",
            "subcategory":"Plumbing",
            "type":"Services"
        }
    ],
    "sg:phone":"+1 703 560 2158",
    "sg:postcode":"22043",
    "sg:province":"VA",
    "sg:tags":[
        "plumbing",
        "contractor"
    ],
    "wof:name":"David S Hooper Sewer & Water",
    "wof:placetype":"venue"
},
  "geometry": {"coordinates":[-77.211935,38.897853],"type":"Point"}
}