{
  "type": "Feature",
  "properties": {
    "addr:full":"3719 N Edison St Arlington VA 22207",
    "addr:housenumber":"3719",
    "addr:postcode":"22207",
    "addr:street":"N Edison St",
    "iso:country":"US",
    "sg:address":"3719 N Edison St",
    "sg:city":"Arlington",
    "sg:classifiers":[
        {
            "category":"Marine",
            "type":"Transportation"
        }
    ],
    "sg:phone":"+1 703 534 8140",
    "sg:postcode":"22207",
    "sg:province":"VA",
    "sg:tags":[
        "water",
        "credit",
        "transport",
        "business"
    ],
    "wof:name":"Barge Lease Inc",
    "wof:placetype":"venue"
},
  "geometry": {"coordinates":[-77.144312,38.912273],"type":"Point"}
}