{
  "type": "Feature",
  "properties": {
    "addr:full":"941 Fir St Waynesboro VA 22980",
    "addr:housenumber":"941",
    "addr:postcode":"22980",
    "addr:street":"Fir St",
    "iso:country":"US",
    "sg:address":"941 Fir St",
    "sg:city":"Waynesboro",
    "sg:classifiers":[
        {
            "category":"Building & Trades",
            "subcategory":"Construction",
            "type":"Services"
        }
    ],
    "sg:phone":"+1 540 942 6624",
    "sg:postcode":"22980",
    "sg:province":"VA",
    "sg:tags":[
        "marking",
        "maintenance",
        "parking"
    ],
    "wof:name":"Waynesboro Public Works",
    "wof:placetype":"venue"
},
  "geometry": {"coordinates":[-78.88854499999999,38.077061],"type":"Point"}
}