{
  "type": "Feature",
  "properties": {
    "iso:country":"US",
    "sg:address":"955 Quail Ridge Cir",
    "sg:city":"Earlysville",
    "sg:classifiers":[
        {
            "category":"Professional",
            "subcategory":"Business Services",
            "type":"Services"
        }
    ],
    "sg:phone":"+1 434 973 0697",
    "sg:postcode":"22936",
    "sg:province":"VA",
    "wof:name":"Site Tech Co Inc",
    "wof:placetype":"venue"
},
  "geometry": {"coordinates":[-78.469972,38.160912],"type":"Point"}
}