{
  "type": "Feature",
  "properties": {
    "addr:full":"483 Church Ave Stanley VA 22851",
    "addr:housenumber":"483",
    "addr:postcode":"22851",
    "addr:street":"Church Ave",
    "iso:country":"US",
    "sg:address":"483 Church Ave",
    "sg:city":"Stanley",
    "sg:classifiers":[
        {
            "category":"Professional",
            "subcategory":"Computer Services",
            "type":"Services"
        }
    ],
    "sg:phone":"+1 540 778 3423",
    "sg:postcode":"22851",
    "sg:province":"VA",
    "wof:name":"Able Computer",
    "wof:placetype":"venue"
},
  "geometry": {"coordinates":[-78.515618,38.579856],"type":"Point"}
}