{
  "type": "Feature",
  "properties": {
    "addr:full":"4660 Hickory Signpost Rd Williamsburg VA 23185",
    "addr:housenumber":"4660",
    "addr:postcode":"23185",
    "addr:street":"Hickory Signpost Rd",
    "iso:country":"US",
    "sg:address":"4660 Hickory Signpost Rd",
    "sg:city":"Williamsburg",
    "sg:classifiers":[
        {
            "category":"Professional",
            "type":"Services"
        }
    ],
    "sg:phone":"+1 757 220 3562",
    "sg:postcode":"23185",
    "sg:province":"VA",
    "wof:name":"Blands Handyman Serv",
    "wof:placetype":"venue"
},
  "geometry": {"coordinates":[-76.75963400000001,37.245316],"type":"Point"}
}