{
  "type": "Feature",
  "properties": {
    "iso:country":"US",
    "sg:address":"3102 Plank Rd",
    "sg:city":"Fredericksburg",
    "sg:classifiers":[
        {
            "category":"Professional",
            "type":"Services"
        }
    ],
    "sg:phone":"+1 540 548 4888",
    "sg:postcode":"22407",
    "sg:province":"VA",
    "wof:name":"Ta Glassworks",
    "wof:placetype":"venue"
},
  "geometry": {"coordinates":[-77.517805,38.294267],"type":"Point"}
}