{
  "type": "Feature",
  "properties": {
    "iso:country":"US",
    "sg:address":"12100 Sunset Hills Rd",
    "sg:city":"Reston",
    "sg:classifiers":[
        {
            "category":"Professional",
            "subcategory":"Computer Services",
            "type":"Services"
        }
    ],
    "sg:phone":"+1 703 525 7500",
    "sg:postcode":"20190",
    "sg:province":"VA",
    "sg:tags":[
        "consultant",
        "designer"
    ],
    "sg:website":"www.sysmanagement.com",
    "wof:name":"Systems Management Engineering",
    "wof:placetype":"venue"
},
  "geometry": {"coordinates":[-77.36805699999999,38.954792],"type":"Point"}
}