{
  "type": "Feature",
  "properties": {
    "addr:full":"1401 Johnston Willis Dr Richmond VA 23235",
    "addr:housenumber":"1401",
    "addr:postcode":"23235",
    "addr:street":"Johnston Willis Dr",
    "iso:country":"US",
    "sg:address":"1401 Johnston Willis Dr",
    "sg:city":"Richmond",
    "sg:classifiers":[
        {
            "category":"Shopping",
            "subcategory":"Pharmacy",
            "type":"Retail Goods"
        }
    ],
    "sg:phone":"+1 804 560 8000",
    "sg:postcode":"23235",
    "sg:province":"VA",
    "wof:name":"Med Center Pharmacy",
    "wof:placetype":"venue"
},
  "geometry": {"coordinates":[-77.597387,37.51084],"type":"Point"}
}