{
  "type": "Feature",
  "properties": {
    "iso:country":"US",
    "sg:address":"4290 Anderson Hwy",
    "sg:city":"Powhatan",
    "sg:classifiers":[
        {
            "category":"Education",
            "subcategory":"School",
            "type":"Public Place"
        }
    ],
    "sg:phone":"+1 804 598 5720",
    "sg:postcode":"23139",
    "sg:province":"VA",
    "wof:name":"Pocahontas Middle School",
    "wof:placetype":"venue"
},
  "geometry": {"coordinates":[-77.946736,37.557421],"type":"Point"}
}