{
  "type": "Feature",
  "properties": {
    "addr:full":"427 Glen Ave Staunton VA 24401",
    "addr:housenumber":"427",
    "addr:postcode":"24401",
    "addr:street":"Glen Ave",
    "iso:country":"US",
    "sg:address":"427 Glen Ave",
    "sg:city":"Staunton",
    "sg:classifiers":[
        {
            "category":"Retail",
            "subcategory":"Car Wash",
            "type":"Services"
        }
    ],
    "sg:phone":"+1 540 886 0098",
    "sg:postcode":"24401",
    "sg:province":"VA",
    "sg:tags":[
        "carwash"
    ],
    "wof:name":"Oakes Pro Wash",
    "wof:placetype":"venue"
},
  "geometry": {"coordinates":[-79.075311,38.162681],"type":"Point"}
}