{
  "type": "Feature",
  "properties": {
    "iso:country":"US",
    "sg:address":"335 Centerville Tpke S",
    "sg:city":"Chesapeake",
    "sg:phone":"+1 757 482 2179",
    "sg:postcode":"23322",
    "sg:province":"VA",
    "sg:tags":[
        "oil"
    ],
    "wof:name":"Crossroads Fuel Svc Inc",
    "wof:placetype":"venue"
},
  "geometry": {"coordinates":[-76.185293,36.715191],"type":"Point"}
}