{
  "type": "Feature",
  "properties": {
    "iso:country":"US",
    "sg:address":"23 N King St",
    "sg:city":"Leesburg",
    "sg:classifiers":[
        {
            "category":"Professional",
            "subcategory":"Lawyer & Legal Services",
            "type":"Services"
        }
    ],
    "sg:phone":"+1 703 669 8013",
    "sg:postcode":"20176",
    "sg:province":"VA",
    "sg:tags":[
        "attorney"
    ],
    "wof:name":"Karen Harris Law Office",
    "wof:placetype":"venue"
},
  "geometry": {"coordinates":[-77.56416299999999,39.11639],"type":"Point"}
}