{
  "type": "Feature",
  "properties": {
    "addr:full":"1238 Muse Field Rd Rocky Mount VA 24151",
    "addr:housenumber":"1238",
    "addr:postcode":"24151",
    "addr:street":"Muse Field Rd",
    "iso:country":"US",
    "sg:address":"1238 Muse Field Rd",
    "sg:city":"Rocky Mount",
    "sg:classifiers":[
        {
            "category":"Manufacturing",
            "subcategory":"Lumber",
            "type":"Manufacturing & Wholesale Goods"
        }
    ],
    "sg:phone":"+1 540 263 0042",
    "sg:postcode":"24151",
    "sg:province":"VA",
    "sg:tags":[
        "hardwood",
        "mill"
    ],
    "wof:name":"Franklin Hardwood Flooring",
    "wof:placetype":"venue"
},
  "geometry": {"coordinates":[-79.86928399999999,37.006089],"type":"Point"}
}