{
  "type": "Feature",
  "properties": {
    "addr:full":"1314 Amicus Rd Stanardsville VA 22973",
    "addr:housenumber":"1314",
    "addr:postcode":"22973",
    "addr:street":"Amicus Rd",
    "iso:country":"US",
    "sg:address":"1314 Amicus Rd",
    "sg:city":"Stanardsville",
    "sg:classifiers":[
        {
            "category":"Retail",
            "subcategory":"Animal Services",
            "type":"Services"
        }
    ],
    "sg:phone":"+1 434 985 9660",
    "sg:postcode":"22973",
    "sg:province":"VA",
    "sg:tags":[
        "training",
        "dog"
    ],
    "wof:name":"Atlantic Coast K-9 Training",
    "wof:placetype":"venue"
},
  "geometry": {"coordinates":[-78.499234,38.260655],"type":"Point"}
}