{
  "type": "Feature",
  "properties": {
    "addr:full":"33 Bullitt Ave SW Roanoke VA 24011",
    "addr:housenumber":"33",
    "addr:postcode":"24011",
    "addr:street":"Bullitt Ave Sw",
    "iso:country":"US",
    "sg:address":"33 Bullitt Ave SW",
    "sg:city":"Roanoke",
    "sg:classifiers":[
        {
            "category":"Professional",
            "type":"Services"
        }
    ],
    "sg:phone":"+1 540 985 2300",
    "sg:postcode":"24011",
    "sg:province":"VA",
    "wof:name":"Appalachian Power Company",
    "wof:placetype":"venue"
},
  "geometry": {"coordinates":[-79.942058,37.268441],"type":"Point"}
}