{
  "type": "Feature",
  "properties": {
    "addr:full":"238 Battlefield Blvd S Chesapeake VA 23322",
    "addr:housenumber":"238",
    "addr:postcode":"23322",
    "addr:street":"Battlefield Blvd",
    "iso:country":"US",
    "sg:address":"238 Battlefield Blvd S",
    "sg:city":"Chesapeake",
    "sg:classifiers":[
        {
            "category":"Banks & Credit Unions",
            "subcategory":"Bank",
            "type":"Services"
        }
    ],
    "sg:phone":"+1 757 523 4475",
    "sg:postcode":"23322",
    "sg:province":"VA",
    "sg:tags":[
        "commercial"
    ],
    "wof:name":"BB&T",
    "wof:placetype":"venue"
},
  "geometry": {"coordinates":[-76.238828,36.715449],"type":"Point"}
}