{
  "type": "Feature",
  "properties": {
    "iso:country":"US",
    "sg:address":"300 Main St",
    "sg:city":"Narrows",
    "sg:classifiers":[
        {
            "category":"Banks & Credit Unions",
            "subcategory":"Bank",
            "type":"Services"
        }
    ],
    "sg:phone":"+1 540 726 2353",
    "sg:postcode":"24124",
    "sg:province":"VA",
    "wof:name":"B B & T",
    "wof:placetype":"venue"
},
  "geometry": {"coordinates":[-80.81060600000001,37.331094],"type":"Point"}
}