{
  "type": "Feature",
  "properties": {
    "addr:full":"4318 Cinnamon Ridge Dr Virginia Beach VA 23462",
    "addr:housenumber":"4318",
    "addr:postcode":"23462",
    "addr:street":"Cinnamon Ridge Dr",
    "iso:country":"US",
    "sg:address":"4318 Cinnamon Ridge Dr",
    "sg:city":"Virginia Beach",
    "sg:classifiers":[
        {
            "category":"Shopping",
            "subcategory":"Department Store",
            "type":"Retail Goods"
        }
    ],
    "sg:phone":"+1 757 474 2592",
    "sg:postcode":"23462",
    "sg:province":"VA",
    "wof:name":"Wal-Mart",
    "wof:placetype":"venue"
},
  "geometry": {"coordinates":[-76.125818,36.80394],"type":"Point"}
}