{
  "type": "Feature",
  "properties": {
    "addr:full":"8809 Sudley Rd Manassas VA 20110",
    "addr:housenumber":"8809",
    "addr:postcode":"20110",
    "addr:street":"Sudley Rd",
    "iso:country":"US",
    "sg:address":"8809 Sudley Rd",
    "sg:city":"Manassas",
    "sg:classifiers":[
        {
            "category":"Professional",
            "subcategory":"Lawyer & Legal Services",
            "type":"Services"
        }
    ],
    "sg:phone":"+1 703 257 0552",
    "sg:postcode":"20110",
    "sg:province":"VA",
    "sg:tags":[
        "attorney"
    ],
    "wof:name":"Dan Park Law Offices",
    "wof:placetype":"venue"
},
  "geometry": {"coordinates":[-77.481274,38.765142],"type":"Point"}
}