{
  "type": "Feature",
  "properties": {
    "iso:country":"US",
    "sg:address":"1229 King St Fl 2",
    "sg:city":"Alexandria",
    "sg:classifiers":[
        {
            "category":"Travel",
            "subcategory":"Bed & Breakfast",
            "type":"Entertainment"
        }
    ],
    "sg:phone":"+1 703 684 3590",
    "sg:postcode":"22314",
    "sg:province":"VA",
    "sg:tags":[
        "inn"
    ],
    "sg:website":"http://www.innsofcourt.org",
    "wof:name":"American Inns Of Court Foundation",
    "wof:placetype":"venue"
},
  "geometry": {"coordinates":[-77.05275,38.805824],"type":"Point"}
}