{
  "type": "Feature",
  "properties": {
    "addr:full":"3913 Portsmouth Blvd Chesapeake VA 23321",
    "addr:housenumber":"3913",
    "addr:postcode":"23321",
    "addr:street":"Portsmouth Blvd",
    "iso:country":"US",
    "sg:address":"3913 Portsmouth Blvd",
    "sg:city":"Chesapeake",
    "sg:classifiers":[
        {
            "category":"Building & Trades",
            "subcategory":"Landscaping Services",
            "type":"Services"
        }
    ],
    "sg:phone":"+1 757 650 0998",
    "sg:postcode":"23321",
    "sg:province":"VA",
    "sg:tags":[
        "landscape",
        "contractor"
    ],
    "wof:name":"Perfect Image Landscaping",
    "wof:placetype":"venue"
},
  "geometry": {"coordinates":[-76.403746,36.824776],"type":"Point"}
}