{
  "type": "Feature",
  "properties": {
    "addr:full":"37054 State Line Rd New Church VA 23415",
    "addr:housenumber":"37054",
    "addr:postcode":"23415",
    "addr:street":"State Line Rd New",
    "iso:country":"US",
    "sg:address":"37054 State Line Rd",
    "sg:city":"New Church",
    "sg:classifiers":[
        {
            "category":"Real Estate",
            "subcategory":"Real Estate Agent",
            "type":"Services"
        }
    ],
    "sg:phone":"+1 757 854 4141",
    "sg:postcode":"23415",
    "sg:province":"VA",
    "sg:website":"www.cbmove.com",
    "wof:name":"Coldwell Banker",
    "wof:placetype":"venue"
},
  "geometry": {"coordinates":[-75.42272699999999,38.011251],"type":"Point"}
}