{
  "type": "Feature",
  "properties": {
    "addr:full":"2826 Linkhorne Dr Lynchburg VA 24503",
    "addr:housenumber":"2826",
    "addr:postcode":"24503",
    "addr:street":"Linkhorne Dr",
    "iso:country":"US",
    "sg:address":"2826 Linkhorne Dr",
    "sg:city":"Lynchburg",
    "sg:classifiers":[
        {
            "category":"Building & Trades",
            "subcategory":"Construction",
            "type":"Services"
        }
    ],
    "sg:phone":"+1 434 384 9500",
    "sg:postcode":"24503",
    "sg:province":"VA",
    "sg:tags":[
        "contractor",
        "kitchen",
        "bath"
    ],
    "wof:name":"Luxury Bath Systems",
    "wof:placetype":"venue"
},
  "geometry": {"coordinates":[-79.20319000000001,37.415994],"type":"Point"}
}