{
  "type": "Feature",
  "properties": {
    "iso:country":"US",
    "sg:address":"241 Cedar Rd",
    "sg:city":"Chesapeake",
    "sg:classifiers":[
        {
            "category":"Professional",
            "subcategory":"Detective & Security Services",
            "type":"Services"
        }
    ],
    "sg:phone":"+1 757 382 9797",
    "sg:postcode":"23322",
    "sg:province":"VA",
    "sg:tags":[
        "information",
        "bureau"
    ],
    "wof:name":"Eddies Bus Service Inc",
    "wof:placetype":"venue"
},
  "geometry": {"coordinates":[-76.244535,36.714391],"type":"Point"}
}