{
  "type": "Feature",
  "properties": {
    "addr:full":"4934 Long Shadow Dr Midlothian VA 23112",
    "addr:housenumber":"4934",
    "addr:postcode":"23112",
    "addr:street":"Long Shadow Dr",
    "iso:country":"US",
    "sg:address":"4934 Long Shadow Dr",
    "sg:city":"Midlothian",
    "sg:classifiers":[
        {
            "category":"Professional",
            "subcategory":"Business Services",
            "type":"Services"
        }
    ],
    "sg:phone":"+1 804 337 6723",
    "sg:postcode":"23112",
    "sg:province":"VA",
    "wof:name":"Atkinson & Deskin Contrs Inc",
    "wof:placetype":"venue"
},
  "geometry": {"coordinates":[-77.646186,37.419191],"type":"Point"}
}