{
  "type": "Feature",
  "properties": {
    "iso:country":"US",
    "sg:address":"532 Carolina Ave",
    "sg:city":"Norfolk",
    "sg:classifiers":[
        {
            "category":"Health Services",
            "subcategory":"Clinic",
            "type":"Services"
        }
    ],
    "sg:phone":"+1 757 233 9936",
    "sg:postcode":"23508",
    "sg:province":"VA",
    "wof:name":"Terry Spencer",
    "wof:placetype":"venue"
},
  "geometry": {"coordinates":[-76.28910999999999,36.881363],"type":"Point"}
}