{
  "type": "Feature",
  "properties": {
    "iso:country":"US",
    "sg:address":"142 Greenville Ave",
    "sg:city":"Staunton",
    "sg:classifiers":[
        {
            "category":"Building & Trades",
            "subcategory":"Plumbing",
            "type":"Services"
        }
    ],
    "sg:phone":"+1 540 885 3139",
    "sg:postcode":"24401",
    "sg:province":"VA",
    "sg:tags":[
        "contractor"
    ],
    "wof:name":"Lees Heating & AC",
    "wof:placetype":"venue"
},
  "geometry": {"coordinates":[-79.07016900000001,38.147751],"type":"Point"}
}