{
  "type": "Feature",
  "properties": {
    "iso:country":"US",
    "sg:address":"7122 Westmoreland Rd",
    "sg:city":"Falls Church",
    "sg:classifiers":[
        {
            "category":"Local Transit",
            "type":"Transportation"
        }
    ],
    "sg:phone":"+1 703 560 0421",
    "sg:postcode":"22042",
    "sg:province":"VA",
    "sg:tags":[
        "passenger",
        "limousine"
    ],
    "wof:name":"Professional Sedan Service",
    "wof:placetype":"venue"
},
  "geometry": {"coordinates":[-77.193006,38.864106],"type":"Point"}
}