{
  "type": "Feature",
  "properties": {
    "iso:country":"US",
    "sg:address":"1325 Redgate Ave",
    "sg:city":"Norfolk",
    "sg:classifiers":[
        {
            "category":"Wholesale",
            "subcategory":"Machinery & Supplies",
            "type":"Manufacturing & Wholesale Goods"
        }
    ],
    "sg:phone":"+1 757 623 1906",
    "sg:postcode":"23507",
    "sg:province":"VA",
    "sg:tags":[
        "industrial"
    ],
    "wof:name":"Supply America Company Inc",
    "wof:placetype":"venue"
},
  "geometry": {"coordinates":[-76.311138,36.871752],"type":"Point"}
}