{
  "type": "Feature",
  "properties": {
    "addr:full":"4412 Hilltop Dr Lynchburg VA 24502",
    "addr:housenumber":"4412",
    "addr:postcode":"24502",
    "addr:street":"Hilltop Dr",
    "iso:country":"US",
    "sg:address":"4412 Hilltop Dr",
    "sg:city":"Lynchburg",
    "sg:classifiers":[
        {
            "category":"Home & Garden",
            "subcategory":"Home Furnishings",
            "type":"Retail Goods"
        }
    ],
    "sg:phone":"+1 434 582 1245",
    "sg:postcode":"24502",
    "sg:province":"VA",
    "wof:name":"Litn Up",
    "wof:placetype":"venue"
},
  "geometry": {"coordinates":[-79.179757,37.384606],"type":"Point"}
}