{
  "type": "Feature",
  "properties": {
    "addr:full":"13235 Spotswood Trl Ruckersville VA 22968",
    "addr:housenumber":"13235",
    "addr:postcode":"22968",
    "addr:street":"Spotswood Trl",
    "iso:country":"US",
    "sg:address":"13235 Spotswood Trl",
    "sg:city":"Ruckersville",
    "sg:classifiers":[
        {
            "category":"Retail",
            "subcategory":"Auto Repair",
            "type":"Services"
        }
    ],
    "sg:phone":"+1 434 985 7261",
    "sg:postcode":"22968",
    "sg:province":"VA",
    "sg:tags":[
        "brake"
    ],
    "wof:name":"Ruckersville Auto Clinic Inc",
    "wof:placetype":"venue"
},
  "geometry": {"coordinates":[-78.392484,38.244739],"type":"Point"}
}