{
  "type": "Feature",
  "properties": {
    "addr:full":"505 Beauregard Dr SE Leesburg VA 20175",
    "addr:housenumber":"505",
    "addr:postcode":"20175",
    "addr:street":"Beauregard Dr Se",
    "iso:country":"US",
    "sg:address":"505 Beauregard Dr SE",
    "sg:city":"Leesburg",
    "sg:classifiers":[
        {
            "category":"Professional",
            "subcategory":"Computer Services",
            "type":"Services"
        }
    ],
    "sg:phone":"+1 703 777 7322",
    "sg:postcode":"20175",
    "sg:province":"VA",
    "sg:tags":[
        "information",
        "security",
        "technology"
    ],
    "wof:name":"It Affiliates",
    "wof:placetype":"venue"
},
  "geometry": {"coordinates":[-77.549819,39.094],"type":"Point"}
}