{
  "type": "Feature",
  "properties": {
    "iso:country":"US",
    "sg:address":"10145 Ferbie Rd",
    "sg:city":"Pound",
    "sg:classifiers":[
        {
            "category":"Organizations",
            "subcategory":"Religious Organization",
            "type":"Services"
        }
    ],
    "sg:phone":"+1 276 796 9201",
    "sg:postcode":"24279",
    "sg:province":"VA",
    "wof:name":"Ferbie Chapel Church",
    "wof:placetype":"venue"
},
  "geometry": {"coordinates":[-82.559377,37.093338],"type":"Point"}
}