{
  "type": "Feature",
  "properties": {
    "addr:full":"7409 Brock Rd Spotsylvania VA 22553",
    "addr:housenumber":"7409",
    "addr:postcode":"22553",
    "addr:street":"Brock Rd",
    "iso:country":"US",
    "sg:address":"7409 Brock Rd",
    "sg:city":"Spotsylvania",
    "sg:classifiers":[
        {
            "category":"Education",
            "subcategory":"Special Training",
            "type":"Public Place"
        }
    ],
    "sg:phone":"+1 540 582 1069",
    "sg:postcode":"22553",
    "sg:province":"VA",
    "wof:name":"Courthouse Academy",
    "wof:placetype":"venue"
},
  "geometry": {"coordinates":[-77.590118,38.201705],"type":"Point"}
}