{
  "type": "Feature",
  "properties": {
    "addr:full":"5614 Davis Ford Rd Manassas VA 20112",
    "addr:housenumber":"5614",
    "addr:postcode":"20112",
    "addr:street":"Davis Ford Rd",
    "iso:country":"US",
    "sg:address":"5614 Davis Ford Rd",
    "sg:city":"Manassas",
    "sg:classifiers":[
        {
            "category":"Building & Trades",
            "subcategory":"Construction",
            "type":"Services"
        }
    ],
    "sg:phone":"+1 703 897 6152",
    "sg:postcode":"20112",
    "sg:province":"VA",
    "sg:tags":[
        "excavation",
        "contractor"
    ],
    "wof:name":"Amar Excavation Inc",
    "wof:placetype":"venue"
},
  "geometry": {"coordinates":[-77.378362,38.699432],"type":"Point"}
}