{
  "type": "Feature",
  "properties": {
    "addr:full":"3396 Radford Rd Christiansburg VA 24073",
    "addr:housenumber":"3396",
    "addr:postcode":"24073",
    "addr:street":"Radford Rd",
    "iso:country":"US",
    "sg:address":"3396 Radford Rd",
    "sg:city":"Christiansburg",
    "sg:classifiers":[
        {
            "category":"Wholesale",
            "subcategory":"Machinery & Supplies",
            "type":"Manufacturing & Wholesale Goods"
        }
    ],
    "sg:phone":"+1 540 639 1169",
    "sg:postcode":"24073",
    "sg:province":"VA",
    "sg:tags":[
        "machine",
        "tool"
    ],
    "sg:website":"www.advancedmachineserv.com",
    "wof:name":"Advanced Machine Svc",
    "wof:placetype":"venue"
},
  "geometry": {"coordinates":[-80.50546300000001,37.129119],"type":"Point"}
}