{
  "type": "Feature",
  "properties": {
    "addr:full":"949 Robin Ridge Rd Rocky Mount VA 24151",
    "addr:housenumber":"949",
    "addr:postcode":"24151",
    "addr:street":"Robin Ridge Rd",
    "iso:country":"US",
    "sg:address":"949 Robin Ridge Rd",
    "sg:city":"Rocky Mount",
    "sg:classifiers":[
        {
            "category":"Retail",
            "subcategory":"Auto Repair",
            "type":"Services"
        }
    ],
    "sg:phone":"+1 540 365 2416",
    "sg:postcode":"24151",
    "sg:province":"VA",
    "sg:tags":[
        "body",
        "automobile",
        "painting"
    ],
    "wof:name":"Martin's Auto Body Repairing",
    "wof:placetype":"venue"
},
  "geometry": {"coordinates":[-79.920586,36.847025],"type":"Point"}
}