{
  "type": "Feature",
  "properties": {
    "iso:country":"US",
    "sg:address":"5244 Brook Rd",
    "sg:city":"Richmond",
    "sg:classifiers":[
        {
            "category":"Food & Beverages",
            "subcategory":"Groceries & Convenience Stores",
            "type":"Retail Goods"
        }
    ],
    "sg:phone":"+1 804 261 3316",
    "sg:postcode":"23227",
    "sg:province":"VA",
    "wof:name":"Shiva Management Inc",
    "wof:placetype":"venue"
},
  "geometry": {"coordinates":[-77.454797,37.603651],"type":"Point"}
}