{
  "type": "Feature",
  "properties": {
    "addr:full":"424 Graves Mill Rd Lynchburg VA 24502",
    "addr:housenumber":"424",
    "addr:postcode":"24502",
    "addr:street":"Graves Mill Rd",
    "iso:country":"US",
    "sg:address":"424 Graves Mill Rd",
    "sg:city":"Lynchburg",
    "sg:classifiers":[
        {
            "category":"Professional",
            "subcategory":"Accounting & Tax Preparation",
            "type":"Services"
        }
    ],
    "sg:phone":"+1 434 832 8200",
    "sg:postcode":"24502",
    "sg:province":"VA",
    "sg:tags":[
        "accountant"
    ],
    "sg:website":"www.ceco-cpas.com",
    "wof:name":"Coley Eubank & Co",
    "wof:placetype":"venue"
},
  "geometry": {"coordinates":[-79.210644,37.37306],"type":"Point"}
}