{
  "type": "Feature",
  "properties": {
    "addr:full":"1400 3rd St Richlands VA 24641",
    "addr:housenumber":"1400",
    "addr:postcode":"24641",
    "addr:street":"3Rd St",
    "iso:country":"US",
    "sg:address":"1400 3rd St",
    "sg:city":"Richlands",
    "sg:classifiers":[
        {
            "category":"Home & Garden",
            "subcategory":"Building Materials",
            "type":"Retail Goods"
        }
    ],
    "sg:phone":"+1 276 963 5500",
    "sg:postcode":"24641",
    "sg:province":"VA",
    "sg:tags":[
        "concrete",
        "contractor"
    ],
    "wof:name":"Va Highway Department",
    "wof:placetype":"venue"
},
  "geometry": {"coordinates":[-81.797813,37.095348],"type":"Point"}
}