{
  "type": "Feature",
  "properties": {
    "addr:full":"710 Pleasants Dr Fredericksburg VA 22407",
    "addr:housenumber":"710",
    "addr:postcode":"22407",
    "addr:street":"Pleasants Dr",
    "iso:country":"US",
    "sg:address":"710 Pleasants Dr",
    "sg:city":"Fredericksburg",
    "sg:classifiers":[
        {
            "category":"Building & Trades",
            "subcategory":"Construction",
            "type":"Services"
        }
    ],
    "sg:phone":"+1 540 898 8508",
    "sg:postcode":"22407",
    "sg:province":"VA",
    "sg:tags":[
        "nonresidential"
    ],
    "wof:name":"Quality Kleening Inc",
    "wof:placetype":"venue"
},
  "geometry": {"coordinates":[-77.51670300000001,38.231507],"type":"Point"}
}