{
  "type": "Feature",
  "properties": {
    "iso:country":"US",
    "sg:address":"1673 Castlefield Rd.",
    "sg:city":"Virginia Beach",
    "sg:classifiers":[
        {
            "category":"Professional",
            "subcategory":"Management & Consulting",
            "type":"Services"
        }
    ],
    "sg:phone":"+1 757 619 6456",
    "sg:postcode":"23456",
    "sg:province":"VA",
    "sg:tags":[
        "web-development",
        "professional-web-design",
        "custom-database",
        "dot-net-nuke",
        "branding"
    ],
    "sg:website":"http://www.visionefx.net",
    "wof:name":"VISIONEFX",
    "wof:placetype":"venue"
},
  "geometry": {"coordinates":[-76.13355799999999,36.784233],"type":"Point"}
}