{
  "type": "Feature",
  "properties": {
    "addr:full":"5322 Patterson Ave Richmond VA 23226",
    "addr:housenumber":"5322",
    "addr:postcode":"23226",
    "addr:street":"Patterson Ave",
    "iso:country":"US",
    "sg:address":"5322 Patterson Ave",
    "sg:city":"Richmond",
    "sg:classifiers":[
        {
            "category":"Retail",
            "subcategory":"Veterinary Services",
            "type":"Services"
        }
    ],
    "sg:phone":"+1 804 288 7387",
    "sg:postcode":"23226",
    "sg:province":"VA",
    "sg:tags":[
        "hospital",
        "animal"
    ],
    "wof:name":"Betty Baugh's Animal Clinic",
    "wof:placetype":"venue"
},
  "geometry": {"coordinates":[-77.509377,37.576355],"type":"Point"}
}