{
  "type": "Feature",
  "properties": {
    "addr:full":"2425 Baker Ave NW Roanoke VA 24017",
    "addr:housenumber":"2425",
    "addr:postcode":"24017",
    "addr:street":"Baker Ave Nw",
    "iso:country":"US",
    "sg:address":"2425 Baker Ave NW",
    "sg:city":"Roanoke",
    "sg:classifiers":[
        {
            "category":"Retail",
            "subcategory":"Repair Shop",
            "type":"Services"
        }
    ],
    "sg:phone":"+1 540 342 6258",
    "sg:postcode":"24017",
    "sg:province":"VA",
    "sg:tags":[
        "welding"
    ],
    "wof:name":"Scott's Machinery Svc",
    "wof:placetype":"venue"
},
  "geometry": {"coordinates":[-79.97886800000001,37.28078],"type":"Point"}
}