{
  "type": "Feature",
  "properties": {
    "addr:full":"165 Virginia St Union Hall VA 24134",
    "addr:housenumber":"165",
    "addr:postcode":"24134",
    "addr:street":"Virginia St Union Hall",
    "iso:country":"US",
    "sg:address":"165 Virginia St",
    "sg:city":"Union Hall",
    "sg:classifiers":[
        {
            "category":"Professional",
            "subcategory":"Business Services",
            "type":"Services"
        }
    ],
    "sg:phone":"+1 540 576 2073",
    "sg:postcode":"24134",
    "sg:province":"VA",
    "wof:name":"Horizon Homes & Interiors Inc",
    "wof:placetype":"venue"
},
  "geometry": {"coordinates":[-80.73663999999999,37.310456],"type":"Point"}
}