{
  "type": "Feature",
  "properties": {
    "iso:country":"US",
    "sg:address":"211 5th St NE",
    "sg:city":"Charlottesville",
    "sg:classifiers":[
        {
            "category":"Professional",
            "subcategory":"Management & Consulting",
            "type":"Services"
        }
    ],
    "sg:phone":"+1 434 972 7278",
    "sg:postcode":"22902",
    "sg:province":"VA",
    "sg:tags":[
        "counselor",
        "relation",
        "public"
    ],
    "sg:website":"http://www.fourleafpr.com",
    "wof:name":"Four Leaf Public Relations",
    "wof:placetype":"venue"
},
  "geometry": {"coordinates":[-78.478033,38.030666],"type":"Point"}
}