{
  "type": "Feature",
  "properties": {
    "iso:country":"US",
    "sg:address":"9701 Warwick Blvd",
    "sg:city":"Newport News",
    "sg:classifiers":[
        {
            "category":"Shopping",
            "type":"Retail Goods"
        }
    ],
    "sg:phone":"+1 757 595 2646",
    "sg:postcode":"23601",
    "sg:province":"VA",
    "sg:tags":[
        "machine",
        "repair"
    ],
    "wof:name":"Powers Business Machines Inc",
    "wof:placetype":"venue"
},
  "geometry": {"coordinates":[-76.455714,37.026222],"type":"Point"}
}