{
  "type": "Feature",
  "properties": {
    "iso:country":"US",
    "sg:address":"4106 Mount Vernon Ave",
    "sg:city":"Alexandria",
    "sg:classifiers":[
        {
            "category":"Restaurant",
            "type":"Food & Drink"
        }
    ],
    "sg:phone":"+1 703 299 9555",
    "sg:postcode":"22305",
    "sg:province":"VA",
    "sg:tags":[
        "pizza"
    ],
    "sg:website":"www.papajohns.com/index.html",
    "wof:name":"Papa John's",
    "wof:placetype":"venue"
},
  "geometry": {"coordinates":[-77.06410200000001,38.843498],"type":"Point"}
}