{
  "type": "Feature",
  "properties": {
    "iso:country":"US",
    "sg:address":"160 Goodwin Neck Rd",
    "sg:city":"Yorktown",
    "sg:classifiers":[
        {
            "category":"Professional",
            "type":"Services"
        }
    ],
    "sg:phone":"+1 757 898 0697",
    "sg:postcode":"23692",
    "sg:province":"VA",
    "wof:name":"Bryant Scott Byrd",
    "wof:placetype":"venue"
},
  "geometry": {"coordinates":[-76.471677,37.176732],"type":"Point"}
}