{
  "type": "Feature",
  "properties": {
    "iso:country":"US",
    "sg:address":"12286 Ashmont Ct",
    "sg:city":"Woodbridge",
    "sg:classifiers":[
        {
            "category":"Professional",
            "subcategory":"Management & Consulting",
            "type":"Services"
        }
    ],
    "sg:phone":"+1 703 580 8787",
    "sg:postcode":"22192",
    "sg:province":"VA",
    "sg:tags":[
        "consultant"
    ],
    "wof:name":"John F Wells",
    "wof:placetype":"venue"
},
  "geometry": {"coordinates":[-77.318956,38.687038],"type":"Point"}
}