{
  "type": "Feature",
  "properties": {
    "iso:country":"US",
    "sg:address":"6419 Charnwood St",
    "sg:city":"Springfield",
    "sg:classifiers":[
        {
            "category":"Professional",
            "subcategory":"Detective & Security Services",
            "type":"Services"
        }
    ],
    "sg:phone":"+1 703 451 2708",
    "sg:postcode":"22152",
    "sg:province":"VA",
    "sg:tags":[
        "system"
    ],
    "wof:name":"T T M",
    "wof:placetype":"venue"
},
  "geometry": {"coordinates":[-77.21685600000001,38.778083],"type":"Point"}
}