{
  "type": "Feature",
  "properties": {
    "iso:country":"US",
    "sg:address":"8385 Sinclair Mill Rd",
    "sg:city":"Manassas",
    "sg:classifiers":[
        {
            "category":"Communications",
            "subcategory":"Radio Station",
            "type":"Services"
        }
    ],
    "sg:phone":"+1 703 794 1103",
    "sg:postcode":"20112",
    "sg:province":"VA",
    "sg:tags":[
        "news",
        "editor"
    ],
    "wof:name":"Peter L Macleod",
    "wof:placetype":"venue"
},
  "geometry": {"coordinates":[-77.45362299999999,38.68528],"type":"Point"}
}