{
  "type": "Feature",
  "properties": {
    "iso:country":"US",
    "sg:address":"7928 Edinburgh Dr",
    "sg:city":"Springfield",
    "sg:classifiers":[
        {
            "category":"Professional",
            "type":"Services"
        }
    ],
    "sg:phone":"+1 703 451 7367",
    "sg:postcode":"22153",
    "sg:province":"VA",
    "wof:name":"Gladys Bisetti",
    "wof:placetype":"venue"
},
  "geometry": {"coordinates":[-77.21544299999999,38.741853],"type":"Point"}
}