{
  "type": "Feature",
  "properties": {
    "addr:full":"12589 Fair Lakes Cir Fairfax VA 22033",
    "addr:housenumber":"12589",
    "addr:postcode":"22033",
    "addr:street":"Fair Lakes Cir",
    "iso:country":"US",
    "sg:address":"12589 Fair Lakes Cir",
    "sg:city":"Fairfax",
    "sg:classifiers":[
        {
            "category":"Restaurant",
            "type":"Food & Drink"
        }
    ],
    "sg:menulink":"http://www.allmenus.com/va/sully/256706-super-suppers/menu/",
    "sg:phone":"+1 703 378 7782",
    "sg:postcode":"22033",
    "sg:province":"VA",
    "sg:tags":[
        "new",
        "american"
    ],
    "wof:name":"Super Suppers",
    "wof:placetype":"venue"
},
  "geometry": {"coordinates":[-77.381179,38.858205],"type":"Point"}
}