{
  "type": "Feature",
  "properties": {
    "iso:country":"US",
    "sg:address":"309 Lynnhaven Pkwy",
    "sg:city":"Virginia Beach",
    "sg:classifiers":[
        {
            "category":"Professional",
            "subcategory":"Engineering",
            "type":"Services"
        }
    ],
    "sg:phone":"+1 757 463 4306",
    "sg:postcode":"23452",
    "sg:province":"VA",
    "sg:tags":[
        "engineer"
    ],
    "sg:website":"www.langleymcdonald.com",
    "wof:name":"Langley & Mc Donald Inc",
    "wof:placetype":"venue"
},
  "geometry": {"coordinates":[-76.065392,36.837491],"type":"Point"}
}