{
  "type": "Feature",
  "properties": {
    "addr:full":"8934 Burke Lake Rd Springfield VA 22151",
    "addr:housenumber":"8934",
    "addr:postcode":"22151",
    "addr:street":"Burke Lake Rd",
    "iso:country":"US",
    "sg:address":"8934 Burke Lake Rd",
    "sg:city":"Springfield",
    "sg:classifiers":[
        {
            "category":"Professional",
            "type":"Services"
        }
    ],
    "sg:phone":"+1 703 764 3748",
    "sg:postcode":"22151",
    "sg:province":"VA",
    "wof:name":"Nicely Done Kitchens",
    "wof:placetype":"venue"
},
  "geometry": {"coordinates":[-77.254713,38.808076],"type":"Point"}
}