{
  "type": "Feature",
  "properties": {
    "iso:country":"US",
    "sg:address":"1410 Virginia Ave",
    "sg:city":"Bluefield",
    "sg:classifiers":[
        {
            "category":"Shopping",
            "subcategory":"Books",
            "type":"Retail Goods"
        }
    ],
    "sg:phone":"+1 276 322 2222",
    "sg:postcode":"24605",
    "sg:province":"VA",
    "sg:tags":[
        "dealer"
    ],
    "wof:name":"Good Shephard Christian Book",
    "wof:placetype":"venue"
},
  "geometry": {"coordinates":[-81.28549,37.250447],"type":"Point"}
}