{
  "type": "Feature",
  "properties": {
    "addr:full":"484 Denbigh Blvd Newport News VA 23608",
    "addr:housenumber":"484",
    "addr:postcode":"23608",
    "addr:street":"Denbigh Blvd",
    "iso:country":"US",
    "sg:address":"484 Denbigh Blvd",
    "sg:city":"Newport News",
    "sg:classifiers":[
        {
            "category":"Food & Beverages",
            "subcategory":"Specialty",
            "type":"Retail Goods"
        }
    ],
    "sg:phone":"+1 757 875 9780",
    "sg:postcode":"23608",
    "sg:province":"VA",
    "wof:name":"Acorn Market",
    "wof:placetype":"venue"
},
  "geometry": {"coordinates":[-76.530627,37.132902],"type":"Point"}
}