{
  "type": "Feature",
  "properties": {
    "addr:full":"1403 Milnwood Rd Farmville VA 23901",
    "addr:housenumber":"1403",
    "addr:postcode":"23901",
    "addr:street":"Milnwood Rd",
    "iso:country":"US",
    "sg:address":"1403 Milnwood Rd",
    "sg:city":"Farmville",
    "sg:classifiers":[
        {
            "category":"Health Services",
            "subcategory":"Chiropractor",
            "type":"Services"
        }
    ],
    "sg:phone":"+1 434 392 3131",
    "sg:postcode":"23901",
    "sg:province":"VA",
    "wof:name":"Back & Neck Ctr",
    "wof:placetype":"venue"
},
  "geometry": {"coordinates":[-78.391869,37.281743],"type":"Point"}
}