{
  "type": "Feature",
  "properties": {
    "iso:country":"US",
    "sg:address":"16023 Porterfield Hwy",
    "sg:city":"Abingdon",
    "sg:classifiers":[
        {
            "category":"Restaurant",
            "type":"Food & Drink"
        }
    ],
    "sg:phone":"+1 276 676 2014",
    "sg:postcode":"24210",
    "sg:province":"VA",
    "wof:name":"Lyon's Den Pizza",
    "wof:placetype":"venue"
},
  "geometry": {"coordinates":[-82.01278499999999,36.72115],"type":"Point"}
}