{
  "type": "Feature",
  "properties": {
    "addr:full":"2610 Huntington Ave Alexandria VA 22303",
    "addr:housenumber":"2610",
    "addr:postcode":"22303",
    "addr:street":"Huntington Ave",
    "iso:country":"US",
    "sg:address":"2610 Huntington Ave",
    "sg:city":"Alexandria",
    "sg:classifiers":[
        {
            "category":"Retail",
            "subcategory":"Auto Repair",
            "type":"Services"
        }
    ],
    "sg:phone":"+1 703 960 1994",
    "sg:postcode":"22303",
    "sg:province":"VA",
    "sg:tags":[
        "general"
    ],
    "wof:name":"JAS E Furchess Garage",
    "wof:placetype":"venue"
},
  "geometry": {"coordinates":[-77.078126,38.797755],"type":"Point"}
}