{
  "type": "Feature",
  "properties": {
    "iso:country":"US",
    "sg:address":"200 Fireweed Ct",
    "sg:city":"Chesapeake",
    "sg:classifiers":[
        {
            "category":"Education",
            "subcategory":"Special Training",
            "type":"Public Place"
        }
    ],
    "sg:phone":"+1 757 382 5030",
    "sg:postcode":"23320",
    "sg:province":"VA",
    "wof:name":"Computer Tudor",
    "wof:placetype":"venue"
},
  "geometry": {"coordinates":[-76.25988599999999,36.742557],"type":"Point"}
}