{
  "type": "Feature",
  "properties": {
    "addr:full":"2121 Tulip St Lynchburg VA 24504",
    "addr:housenumber":"2121",
    "addr:postcode":"24504",
    "addr:street":"Tulip St",
    "iso:country":"US",
    "sg:address":"2121 Tulip St",
    "sg:city":"Lynchburg",
    "sg:classifiers":[
        {
            "category":"Professional",
            "subcategory":"Business Services",
            "type":"Services"
        }
    ],
    "sg:phone":"+1 434 845 1853",
    "sg:postcode":"24504",
    "sg:province":"VA",
    "wof:name":"Jane Kuhn",
    "wof:placetype":"venue"
},
  "geometry": {"coordinates":[-79.134069,37.403013],"type":"Point"}
}