{
  "type": "Feature",
  "properties": {
    "iso:country":"US",
    "sg:address":"3412 22nd St S",
    "sg:city":"Arlington",
    "sg:classifiers":[
        {
            "category":"Organizations",
            "subcategory":"Religious Organization",
            "type":"Services"
        }
    ],
    "sg:phone":"+1 703 521 7663",
    "sg:postcode":"22204",
    "sg:province":"VA",
    "sg:tags":[
        "baptist",
        "church"
    ],
    "sg:website":"www.macedoniabaptistchurch.ws",
    "wof:name":"Macedonia Baptist Church Inc",
    "wof:placetype":"venue"
},
  "geometry": {"coordinates":[-77.085126,38.849999],"type":"Point"}
}