{
  "type": "Feature",
  "properties": {
    "addr:full":"912 Colonial Ave Colonial Beach VA 22443",
    "addr:housenumber":"912",
    "addr:postcode":"beach;22443",
    "addr:street":"Colonial Ave",
    "iso:country":"US",
    "sg:address":"912 Colonial Ave",
    "sg:city":"Colonial Beach",
    "sg:classifiers":[
        {
            "category":"Real Estate",
            "subcategory":"Real Estate Agent",
            "type":"Services"
        }
    ],
    "sg:phone":"+1 804 224 8448",
    "sg:postcode":"22443",
    "sg:province":"VA",
    "sg:tags":[
        "appraiser"
    ],
    "wof:name":"Lynch Appraisal Svc",
    "wof:placetype":"venue"
},
  "geometry": {"coordinates":[-76.97351999999999,38.254345],"type":"Point"}
}