{
  "type": "Feature",
  "properties": {
    "addr:full":"116 W Lee Hwy Chilhowie VA 24319",
    "addr:housenumber":"116",
    "addr:postcode":"24319",
    "addr:street":"W Lee Hwy",
    "iso:country":"US",
    "sg:address":"116 W Lee Hwy",
    "sg:city":"Chilhowie",
    "sg:classifiers":[
        {
            "category":"Shopping",
            "type":"Retail Goods"
        }
    ],
    "sg:phone":"+1 276 646 5030",
    "sg:postcode":"24319",
    "sg:province":"VA",
    "sg:tags":[
        "equipment",
        "care",
        "health",
        "home"
    ],
    "wof:name":"Lifeline Home Medical Inc",
    "wof:placetype":"venue"
},
  "geometry": {"coordinates":[-81.68247,36.798441],"type":"Point"}
}