{
  "type": "Feature",
  "properties": {
    "addr:full":"2036 E Market St Harrisonburg VA 22801",
    "addr:housenumber":"2036",
    "addr:postcode":"22801",
    "addr:street":"E Market St",
    "iso:country":"US",
    "sg:address":"2036 E Market St",
    "sg:city":"Harrisonburg",
    "sg:classifiers":[
        {
            "category":"Shopping",
            "subcategory":"Hobbies, Toys, & Games",
            "type":"Retail Goods"
        }
    ],
    "sg:phone":"+1 540 574 2355",
    "sg:postcode":"22801",
    "sg:province":"VA",
    "wof:name":"Toys r US",
    "wof:placetype":"venue"
},
  "geometry": {"coordinates":[-78.839068,38.425155],"type":"Point"}
}