{
  "type": "Feature",
  "properties": {
    "addr:full":"1500 Forest Ave Richmond VA 23229",
    "addr:housenumber":"1500",
    "addr:postcode":"23229",
    "addr:street":"Forest Ave",
    "iso:country":"US",
    "sg:address":"1500 Forest Ave",
    "sg:city":"Richmond",
    "sg:classifiers":[
        {
            "category":"Real Estate",
            "subcategory":"Real Estate Operator",
            "type":"Services"
        }
    ],
    "sg:phone":"+1 804 282 5461",
    "sg:postcode":"23229",
    "sg:province":"VA",
    "sg:tags":[
        "building"
    ],
    "wof:name":"Koger Center The",
    "wof:placetype":"venue"
},
  "geometry": {"coordinates":[-77.544563,37.601106],"type":"Point"}
}