{
  "type": "Feature",
  "properties": {
    "addr:full":"13770 Warwick Blvd Newport News VA 23602",
    "addr:housenumber":"13770",
    "addr:postcode":"23602",
    "addr:street":"Warwick Blvd",
    "iso:country":"US",
    "sg:address":"13770 Warwick Blvd",
    "sg:city":"Newport News",
    "sg:classifiers":[
        {
            "category":"Personal",
            "subcategory":"Beauty Salon",
            "type":"Services"
        }
    ],
    "sg:phone":"+1 757 874 7722",
    "sg:postcode":"23602",
    "sg:province":"VA",
    "wof:name":"Colony Hair Salon",
    "wof:placetype":"venue"
},
  "geometry": {"coordinates":[-76.530281,37.124326],"type":"Point"}
}