{
  "type": "Feature",
  "properties": {
    "iso:country":"US",
    "sg:address":"209 Pennsylvania Ave",
    "sg:city":"Virginia Beach",
    "sg:classifiers":[
        {
            "category":"Wholesale",
            "subcategory":"Hardware",
            "type":"Manufacturing & Wholesale Goods"
        }
    ],
    "sg:phone":"+1 757 499 7822",
    "sg:postcode":"23462",
    "sg:province":"VA",
    "sg:tags":[
        "equipment",
        "air",
        "conditioning",
        "heating"
    ],
    "wof:name":"Breeden & Silver Distribution",
    "wof:placetype":"venue"
},
  "geometry": {"coordinates":[-76.15522199999999,36.843439],"type":"Point"}
}