{
  "type": "Feature",
  "properties": {
    "addr:full":"2815 Melrose Ave NW Roanoke VA 24017",
    "addr:housenumber":"2815",
    "addr:postcode":"24017",
    "addr:street":"Melrose Ave Nw",
    "iso:country":"US",
    "sg:address":"2815 Melrose Ave NW",
    "sg:city":"Roanoke",
    "sg:classifiers":[
        {
            "category":"Building & Trades",
            "subcategory":"Cleaning & Sanitation",
            "type":"Services"
        }
    ],
    "sg:phone":"+1 540 982 8544",
    "sg:postcode":"24017",
    "sg:province":"VA",
    "sg:tags":[
        "maintenance"
    ],
    "wof:name":"Leroys Yard & Building Maint",
    "wof:placetype":"venue"
},
  "geometry": {"coordinates":[-79.981343,37.288456],"type":"Point"}
}