{
  "type": "Feature",
  "properties": {
    "iso:country":"US",
    "sg:address":"2100 Clarendon Blvd # 314",
    "sg:city":"Arlington",
    "sg:classifiers":[
        {
            "category":"Professional",
            "subcategory":"Management & Consulting",
            "type":"Services"
        },
        {
            "category":"Government",
            "subcategory":"Office",
            "type":"Public Place"
        }
    ],
    "sg:phone":"+1 571 228 3260",
    "sg:postcode":"22201",
    "sg:province":"VA",
    "sg:tags":[
        "consultant",
        "resource",
        "human"
    ],
    "sg:website":"http://www.getrealnow.net",
    "wof:name":"Citizen & Consumer Affairs",
    "wof:placetype":"venue"
},
  "geometry": {"coordinates":[-77.08609800000001,38.890579],"type":"Point"}
}