{
  "type": "Feature",
  "properties": {
    "addr:full":"14828 Anderson Ct Woodbridge VA 22193",
    "addr:housenumber":"14828",
    "addr:postcode":"22193",
    "addr:street":"Anderson Ct",
    "iso:country":"US",
    "sg:address":"14828 Anderson Ct",
    "sg:city":"Woodbridge",
    "sg:classifiers":[
        {
            "category":"Building & Trades",
            "subcategory":"Construction",
            "type":"Services"
        }
    ],
    "sg:phone":"+1 703 897 7378",
    "sg:postcode":"22193",
    "sg:province":"VA",
    "sg:tags":[
        "contractor"
    ],
    "wof:name":"B & R Brick Cleaning",
    "wof:placetype":"venue"
},
  "geometry": {"coordinates":[-77.30822499999999,38.631361],"type":"Point"}
}