{
  "type": "Feature",
  "properties": {
    "addr:full":"201 First Colonial Rd Virginia Beach VA 23454",
    "addr:housenumber":"201",
    "addr:postcode":"23454",
    "addr:street":"First Colonial Rd",
    "iso:country":"US",
    "sg:address":"201 First Colonial Rd",
    "sg:city":"Virginia Beach",
    "sg:classifiers":[
        {
            "category":"Professional",
            "type":"Services"
        }
    ],
    "sg:phone":"+1 757 428 2117",
    "sg:postcode":"23454",
    "sg:province":"VA",
    "sg:tags":[
        "establishment"
    ],
    "wof:name":"Funaramics By Jeanette",
    "wof:placetype":"venue"
},
  "geometry": {"coordinates":[-76.02097999999999,36.84614],"type":"Point"}
}