{
  "type": "Feature",
  "properties": {
    "iso:country":"US",
    "sg:address":"3200 Colvin St",
    "sg:city":"Alexandria",
    "sg:classifiers":[
        {
            "category":"Place Of Worship",
            "type":"Public Place"
        }
    ],
    "sg:phone":"+1 703 838 4747",
    "sg:postcode":"22314",
    "sg:province":"VA",
    "sg:tags":[
        "consultant",
        "traffic",
        "parking"
    ],
    "sg:website":"http://www.alexandriava.gov",
    "wof:name":"Alexandria Traffic Division",
    "wof:placetype":"venue"
},
  "geometry": {"coordinates":[-77.08562499999999,38.80702],"type":"Point"}
}