{
  "type": "Feature",
  "properties": {
    "addr:full":"7409 Chatham St Springfield VA 22151",
    "addr:housenumber":"7409",
    "addr:postcode":"22151",
    "addr:street":"Chatham St",
    "iso:country":"US",
    "sg:address":"7409 Chatham St",
    "sg:city":"Springfield",
    "sg:classifiers":[
        {
            "category":"Education",
            "subcategory":"Vocational School",
            "type":"Public Place"
        }
    ],
    "sg:phone":"+1 703 941 2710",
    "sg:postcode":"22151",
    "sg:province":"VA",
    "sg:tags":[
        "consulting",
        "health",
        "care"
    ],
    "wof:name":"Ta ODonnell Associates",
    "wof:placetype":"venue"
},
  "geometry": {"coordinates":[-77.201536,38.804648],"type":"Point"}
}