{
  "type": "Feature",
  "properties": {
    "addr:full":"10118 Dwight Ave Fairfax VA 22032",
    "addr:housenumber":"10118",
    "addr:postcode":"22032",
    "addr:street":"Dwight Ave",
    "iso:country":"US",
    "sg:address":"10118 Dwight Ave",
    "sg:city":"Fairfax",
    "sg:classifiers":[
        {
            "category":"Organizations",
            "subcategory":"Membership Organization",
            "type":"Services"
        }
    ],
    "sg:phone":"+1 703 591 5248",
    "sg:postcode":"22032",
    "sg:province":"VA",
    "wof:name":"Continental Society Daugh",
    "wof:placetype":"venue"
},
  "geometry": {"coordinates":[-77.296702,38.841047],"type":"Point"}
}