{
  "type": "Feature",
  "properties": {
    "addr:full":"333 W Cork St Winchester VA 22601",
    "addr:housenumber":"333",
    "addr:postcode":"22601",
    "addr:street":"W Cork St",
    "iso:country":"US",
    "sg:address":"333 W Cork St",
    "sg:city":"Winchester",
    "sg:classifiers":[
        {
            "category":"Health Services",
            "subcategory":"Clinic",
            "type":"Services"
        }
    ],
    "sg:phone":"+1 540 722 1111",
    "sg:postcode":"22601",
    "sg:province":"VA",
    "sg:tags":[
        "organization",
        "medical",
        "surgical"
    ],
    "wof:name":"Shenandoah Independent Prctc",
    "wof:placetype":"venue"
},
  "geometry": {"coordinates":[-78.171638,39.183222],"type":"Point"}
}