{
  "type": "Feature",
  "properties": {
    "addr:full":"7925 Westpark Dr Mc Lean VA 22102",
    "addr:housenumber":"7925",
    "addr:postcode":"22102",
    "addr:street":"Westpark Dr",
    "iso:country":"US",
    "sg:address":"7925 Westpark Dr",
    "sg:city":"Mc Lean",
    "sg:classifiers":[
        {
            "category":"Insurance",
            "subcategory":"Life Insurance",
            "type":"Services"
        }
    ],
    "sg:phone":"+1 703 506 6845",
    "sg:postcode":"22102",
    "sg:province":"VA",
    "wof:name":"AIG",
    "wof:placetype":"venue"
},
  "geometry": {"coordinates":[-77.22049800000001,38.926158],"type":"Point"}
}