{
  "type": "Feature",
  "properties": {
    "addr:full":"8417 Sudley Rd Manassas VA 20109",
    "addr:housenumber":"8417",
    "addr:postcode":"20109",
    "addr:street":"Sudley Rd",
    "iso:country":"US",
    "sg:address":"8417 Sudley Rd",
    "sg:city":"Manassas",
    "sg:classifiers":[
        {
            "category":"Government",
            "subcategory":"Office",
            "type":"Public Place"
        }
    ],
    "sg:phone":"+1 703 361 5811",
    "sg:postcode":"20109",
    "sg:province":"VA",
    "sg:tags":[
        "armed",
        "force",
        "recruiting"
    ],
    "wof:name":"US Army Recruiting",
    "wof:placetype":"venue"
},
  "geometry": {"coordinates":[-77.5013,38.774291],"type":"Point"}
}