{
  "type": "Feature",
  "properties": {
    "addr:full":"5262 Oaklawn Blvd Hopewell VA 23860",
    "addr:housenumber":"5262",
    "addr:postcode":"23860",
    "addr:street":"Oaklawn Blvd",
    "iso:country":"US",
    "sg:address":"5262 Oaklawn Blvd",
    "sg:city":"Hopewell",
    "sg:classifiers":[
        {
            "category":"Banks & Credit Unions",
            "subcategory":"Bank",
            "type":"Services"
        }
    ],
    "sg:phone":"+1 804 458 9805",
    "sg:postcode":"23860",
    "sg:province":"VA",
    "sg:tags":[
        "personal",
        "institution"
    ],
    "wof:name":"Beneficial",
    "wof:placetype":"venue"
},
  "geometry": {"coordinates":[-77.327499,37.260004],"type":"Point"}
}