{
  "type": "Feature",
  "properties": {
    "addr:full":"512 E Main St Purcellville VA 20134",
    "addr:housenumber":"512",
    "addr:postcode":"20134",
    "addr:street":"E Main St",
    "iso:country":"US",
    "sg:address":"512 E Main St",
    "sg:city":"Purcellville",
    "sg:classifiers":[
        {
            "category":"Professional",
            "type":"Services"
        }
    ],
    "sg:phone":"+1 540 751 0422",
    "sg:postcode":"20134",
    "sg:province":"VA",
    "wof:name":"Dick Kramer Studios",
    "wof:placetype":"venue"
},
  "geometry": {"coordinates":[-77.70807499999999,39.136496],"type":"Point"}
}