{
  "type": "Feature",
  "properties": {
    "addr:full":"7000 Patterson Ave Richmond VA 23226",
    "addr:housenumber":"7000",
    "addr:postcode":"23226",
    "addr:street":"Patterson Ave",
    "iso:country":"US",
    "sg:address":"7000 Patterson Ave",
    "sg:city":"Richmond",
    "sg:classifiers":[
        {
            "category":"Health Services",
            "subcategory":"Doctor",
            "type":"Services"
        }
    ],
    "sg:phone":"+1 804 282 9706",
    "sg:postcode":"23226",
    "sg:province":"VA",
    "sg:tags":[
        "physician",
        "pediatrics",
        "surgeons",
        "manipulative",
        "osteopathic",
        "treatment",
        "surgeon"
    ],
    "wof:name":"Terry, Charles V, Md - Wiley Kirchmier & Terry",
    "wof:placetype":"venue"
},
  "geometry": {"coordinates":[-77.53070099999999,37.5905],"type":"Point"}
}