{
  "type": "Feature",
  "properties": {
    "iso:country":"US",
    "sg:address":"2737 Ridgeview Rd",
    "sg:city":"Powhatan",
    "sg:classifiers":[
        {
            "category":"Wholesale",
            "subcategory":"Furniture",
            "type":"Manufacturing & Wholesale Goods"
        }
    ],
    "sg:phone":"+1 804 403 3003",
    "sg:postcode":"23139",
    "sg:province":"VA",
    "sg:tags":[
        "furnishing",
        "church"
    ],
    "wof:name":"Virginia Church Furniture Co",
    "wof:placetype":"venue"
},
  "geometry": {"coordinates":[-77.851817,37.566921],"type":"Point"}
}