{
  "type": "Feature",
  "properties": {
    "iso:country":"US",
    "sg:address":"2536 Dunham Rd",
    "sg:city":"Richmond",
    "sg:classifiers":[
        {
            "category":"Banks & Credit Unions",
            "subcategory":"Investment Brokerage",
            "type":"Services"
        }
    ],
    "sg:phone":"+1 804 360 3639",
    "sg:postcode":"23233",
    "sg:province":"VA",
    "sg:tags":[
        "advisory"
    ],
    "wof:name":"Potomac Asset Advisors LLC",
    "wof:placetype":"venue"
},
  "geometry": {"coordinates":[-77.61816,37.628002],"type":"Point"}
}