{
  "type": "Feature",
  "properties": {
    "addr:full":"10130 Colvin Run Rd Great Falls VA 22066",
    "addr:housenumber":"10130",
    "addr:postcode":"22066",
    "addr:street":"Colvin Run Rd",
    "iso:country":"US",
    "sg:address":"10130 Colvin Run Rd",
    "sg:city":"Great Falls",
    "sg:classifiers":[
        {
            "category":"Banks & Credit Unions",
            "subcategory":"Investment Brokerage",
            "type":"Services"
        }
    ],
    "sg:phone":"+1 703 438 3307",
    "sg:postcode":"22066",
    "sg:province":"VA",
    "sg:tags":[
        "security"
    ],
    "wof:name":"Royal Advantage Mortgage Inc",
    "wof:placetype":"venue"
},
  "geometry": {"coordinates":[-77.296677,38.973743],"type":"Point"}
}