{
  "type": "Feature",
  "properties": {
    "iso:country":"US",
    "sg:address":"140 Bethel Grange Rd",
    "sg:city":"Winchester",
    "sg:classifiers":[
        {
            "category":"Professional",
            "subcategory":"Computer Services",
            "type":"Services"
        }
    ],
    "sg:phone":"+1 540 662 6019",
    "sg:postcode":"22603",
    "sg:province":"VA",
    "sg:tags":[
        "programing",
        "custom"
    ],
    "wof:name":"Split Pine Studios",
    "wof:placetype":"venue"
},
  "geometry": {"coordinates":[-78.21839300000001,39.22479],"type":"Point"}
}