{
  "type": "Feature",
  "properties": {
    "addr:full":"7005 Jefferson Ave Falls Church VA 22042",
    "addr:housenumber":"7005",
    "addr:postcode":"22042",
    "addr:street":"Jefferson Ave",
    "iso:country":"US",
    "sg:address":"7005 Jefferson Ave",
    "sg:city":"Falls Church",
    "sg:classifiers":[
        {
            "category":"Retail",
            "subcategory":"Repair Shop",
            "type":"Services"
        }
    ],
    "sg:phone":"+1 703 534 5053",
    "sg:postcode":"22042",
    "sg:province":"VA",
    "sg:tags":[
        "equipment",
        "fitness"
    ],
    "wof:name":"Depalma Fitness",
    "wof:placetype":"venue"
},
  "geometry": {"coordinates":[-77.185329,38.870805],"type":"Point"}
}