{
  "type": "Feature",
  "properties": {
    "addr:full":"2650 New Market Rd Richmond VA 23231",
    "addr:housenumber":"2650",
    "addr:postcode":"23231",
    "addr:street":"New Market Rd",
    "iso:country":"US",
    "sg:address":"2650 New Market Rd",
    "sg:city":"Richmond",
    "sg:classifiers":[
        {
            "category":"Food & Beverages",
            "subcategory":"Groceries & Convenience Stores",
            "type":"Retail Goods"
        }
    ],
    "sg:phone":"+1 804 795 1082",
    "sg:postcode":"23231",
    "sg:province":"VA",
    "wof:name":"Fast Mart",
    "wof:placetype":"venue"
},
  "geometry": {"coordinates":[-77.35269599999999,37.444773],"type":"Point"}
}