{
  "type": "Feature",
  "properties": {
    "addr:full":"3201 Rosedale Ave Richmond VA 23230",
    "addr:housenumber":"3201",
    "addr:postcode":"23230",
    "addr:street":"Rosedale Ave",
    "iso:country":"US",
    "sg:address":"3201 Rosedale Ave",
    "sg:city":"Richmond",
    "sg:classifiers":[
        {
            "category":"Manufacturing",
            "subcategory":"Glass & Minerals",
            "type":"Manufacturing & Wholesale Goods"
        },
        {
            "category":"Retail",
            "subcategory":"Auto Repair",
            "type":"Services"
        }
    ],
    "sg:phone":"+1 804 359 4535",
    "sg:postcode":"23230",
    "sg:province":"VA",
    "sg:tags":[
        "plate",
        "window",
        "windshield",
        "glass-auto"
    ],
    "wof:name":"SAFELITE AUTO GLASS",
    "wof:placetype":"venue"
},
  "geometry": {"coordinates":[-77.468819,37.574348],"type":"Point"}
}