{
  "type": "Feature",
  "properties": {
    "addr:full":"3807 Brandon Ave SW Roanoke VA 24018",
    "addr:housenumber":"3807",
    "addr:postcode":"24018",
    "addr:street":"Brandon Ave Sw",
    "iso:country":"US",
    "sg:address":"3807 Brandon Ave SW",
    "sg:city":"Roanoke",
    "sg:classifiers":[
        {
            "category":"Real Estate",
            "subcategory":"Real Estate Agent",
            "type":"Services"
        }
    ],
    "sg:phone":"+1 540 989 3653",
    "sg:postcode":"24018",
    "sg:province":"VA",
    "wof:name":"Csw Assoc",
    "wof:placetype":"venue"
},
  "geometry": {"coordinates":[-80.012343,37.263943],"type":"Point"}
}