{
  "type": "Feature",
  "properties": {
    "addr:full":"320 Carter St Bristol VA 24201",
    "addr:housenumber":"320",
    "addr:postcode":"24201",
    "addr:street":"Carter St",
    "iso:country":"US",
    "sg:address":"320 Carter St",
    "sg:city":"Bristol",
    "sg:classifiers":[
        {
            "category":"Organizations",
            "subcategory":"Religious Organization",
            "type":"Services"
        }
    ],
    "sg:phone":"+1 276 669 1772",
    "sg:postcode":"24201",
    "sg:province":"VA",
    "wof:name":"Trinity United Methdst Church",
    "wof:placetype":"venue"
},
  "geometry": {"coordinates":[-82.19861400000001,36.598059],"type":"Point"}
}