{
  "type": "Feature",
  "properties": {
    "addr:full":"17254 Axselle Dr Montpelier VA 23192",
    "addr:postcode":"17254;23192",
    "addr:street":"Axselle Dr",
    "iso:country":"US",
    "sg:address":"17254 Axselle Dr",
    "sg:city":"Montpelier",
    "sg:classifiers":[
        {
            "category":"Wholesale",
            "subcategory":"Motor Vehicles",
            "type":"Manufacturing & Wholesale Goods"
        }
    ],
    "sg:phone":"+1 540 903 3652",
    "sg:postcode":"23192",
    "sg:province":"VA",
    "wof:name":"Wilder Nat",
    "wof:placetype":"venue"
},
  "geometry": {"coordinates":[-77.717077,37.873317],"type":"Point"}
}