{
  "type": "Feature",
  "properties": {
    "addr:full":"14215 Centreville Sq Centreville VA 20121",
    "addr:housenumber":"14215",
    "addr:postcode":"20121",
    "addr:street":"Centreville Sq",
    "iso:country":"US",
    "sg:address":"14215 Centreville Sq",
    "sg:city":"Centreville",
    "sg:classifiers":[
        {
            "category":"Shopping",
            "subcategory":"Discount & Variety Stores",
            "type":"Retail Goods"
        }
    ],
    "sg:phone":"+1 703 815 8153",
    "sg:postcode":"20121",
    "sg:province":"VA",
    "wof:name":"Dollar Store",
    "wof:placetype":"venue"
},
  "geometry": {"coordinates":[-77.437082,38.837711],"type":"Point"}
}