{
  "type": "Feature",
  "properties": {
    "addr:full":"10040 Whitesel Rd Ashland VA 23005",
    "addr:housenumber":"10040",
    "addr:postcode":"23005",
    "addr:street":"Whitesel Rd",
    "iso:country":"US",
    "sg:address":"10040 Whitesel Rd",
    "sg:city":"Ashland",
    "sg:classifiers":[
        {
            "category":"Mining & Drilling",
            "type":"Manufacturing & Wholesale Goods"
        }
    ],
    "sg:phone":"+1 804 227 3558",
    "sg:postcode":"23005",
    "sg:province":"VA",
    "sg:tags":[
        "oil",
        "gas",
        "producer"
    ],
    "wof:name":"Virginia Natural Gas",
    "wof:placetype":"venue"
},
  "geometry": {"coordinates":[-77.439441,37.705201],"type":"Point"}
}