{
  "type": "Feature",
  "properties": {
    "addr:full":"339 S Main St Woodstock VA 22664",
    "addr:housenumber":"339",
    "addr:postcode":"22664",
    "addr:street":"S Main St",
    "iso:country":"US",
    "sg:address":"339 S Main St",
    "sg:city":"Woodstock",
    "sg:classifiers":[
        {
            "category":"Personal",
            "subcategory":"Beauty Salon",
            "type":"Services"
        }
    ],
    "sg:phone":"+1 540 459 8203",
    "sg:postcode":"22664",
    "sg:province":"VA",
    "sg:tags":[
        "shop"
    ],
    "wof:name":"Hair Gallery",
    "wof:placetype":"venue"
},
  "geometry": {"coordinates":[-78.507869,38.878343],"type":"Point"}
}