{
  "type": "Feature",
  "properties": {
    "iso:country":"US",
    "sg:address":"1995 Browntown Rd",
    "sg:city":"Front Royal",
    "sg:classifiers":[
        {
            "category":"Building & Trades",
            "subcategory":"Construction",
            "type":"Services"
        }
    ],
    "sg:phone":"+1 540 635 8271",
    "sg:postcode":"22630",
    "sg:province":"VA",
    "sg:tags":[
        "carpenter"
    ],
    "wof:name":"Hanna Norman",
    "wof:placetype":"venue"
},
  "geometry": {"coordinates":[-78.231657,38.837871],"type":"Point"}
}