{
  "type": "Feature",
  "properties": {
    "addr:full":"515 Alleghany Ave Lynchburg VA 24501",
    "addr:housenumber":"515",
    "addr:postcode":"24501",
    "addr:street":"Alleghany Ave",
    "iso:country":"US",
    "sg:address":"515 Alleghany Ave",
    "sg:city":"Lynchburg",
    "sg:classifiers":[
        {
            "category":"Wholesale",
            "subcategory":"Hardware",
            "type":"Manufacturing & Wholesale Goods"
        }
    ],
    "sg:phone":"+1 434 845 0400",
    "sg:postcode":"24501",
    "sg:province":"VA",
    "sg:tags":[
        "equipment",
        "air",
        "conditioning",
        "heating"
    ],
    "wof:name":"Aireco Supply",
    "wof:placetype":"venue"
},
  "geometry": {"coordinates":[-79.16849000000001,37.400719],"type":"Point"}
}