{
  "type": "Feature",
  "properties": {
    "addr:full":"104 W Church St Wakefield VA 23888",
    "addr:housenumber":"104",
    "addr:postcode":"23888",
    "addr:street":"W Church St",
    "iso:country":"US",
    "sg:address":"104 W Church St",
    "sg:city":"Wakefield",
    "sg:classifiers":[
        {
            "category":"Organizations",
            "subcategory":"Religious Organization",
            "type":"Services"
        }
    ],
    "sg:phone":"+1 757 899 2007",
    "sg:postcode":"23888",
    "sg:province":"VA",
    "sg:tags":[
        "church"
    ],
    "wof:name":"Wakefield Baptist Church",
    "wof:placetype":"venue"
},
  "geometry": {"coordinates":[-76.987426,36.970566],"type":"Point"}
}