{
  "type": "Feature",
  "properties": {
    "addr:full":"100 E Main St Charlottesville VA 22902",
    "addr:housenumber":"100",
    "addr:postcode":"22902",
    "addr:street":"E Main St",
    "iso:country":"US",
    "sg:address":"100 E Main St",
    "sg:city":"Charlottesville",
    "sg:classifiers":[
        {
            "category":"Shopping",
            "subcategory":"Hobbies, Toys, & Games",
            "type":"Retail Goods"
        }
    ],
    "sg:phone":"+1 434 971 1717",
    "sg:postcode":"22902",
    "sg:province":"VA",
    "sg:tags":[
        "toy",
        "store"
    ],
    "sg:website":"www.alakazamtoys.com/",
    "wof:name":"Alakazam Toys and Gifts",
    "wof:placetype":"venue"
},
  "geometry": {"coordinates":[-78.48156400000001,38.030362],"type":"Point"}
}