{
  "type": "Feature",
  "properties": {
    "addr:full":"8625 Mountainview Ave Marshall VA 20115",
    "addr:housenumber":"8625",
    "addr:postcode":"20115",
    "addr:street":"Mountainview Ave",
    "iso:country":"US",
    "sg:address":"8625 Mountainview Ave",
    "sg:city":"Marshall",
    "sg:classifiers":[
        {
            "category":"Autos & Motor Vehicles",
            "subcategory":"Boat Sales",
            "type":"Retail Goods"
        }
    ],
    "sg:phone":"+1 540 364 2424",
    "sg:postcode":"20115",
    "sg:province":"VA",
    "wof:name":"Sn Marine Mrktg Inc",
    "wof:placetype":"venue"
},
  "geometry": {"coordinates":[-77.85839799999999,38.872249],"type":"Point"}
}