{
  "type": "Feature",
  "properties": {
    "addr:full":"15265 Warwick Blvd Newport News VA 23608",
    "addr:housenumber":"15265",
    "addr:postcode":"23608",
    "addr:street":"Warwick Blvd",
    "iso:country":"US",
    "sg:address":"15265 Warwick Blvd",
    "sg:city":"Newport News",
    "sg:classifiers":[
        {
            "category":"Organizations",
            "subcategory":"Community Association",
            "type":"Services"
        }
    ],
    "sg:phone":"+1 757 877 0999",
    "sg:postcode":"23608",
    "sg:province":"VA",
    "wof:name":"Dav Thrift Stores",
    "wof:placetype":"venue"
},
  "geometry": {"coordinates":[-76.54850399999999,37.143335],"type":"Point"}
}