{
  "type": "Feature",
  "properties": {
    "addr:full":"20426 Cool Fern Sq Ashburn VA 20147",
    "addr:housenumber":"20426",
    "addr:postcode":"20147",
    "addr:street":"Cool Fern Sq",
    "iso:country":"US",
    "sg:address":"20426 Cool Fern Sq",
    "sg:city":"Ashburn",
    "sg:classifiers":[
        {
            "category":"Professional",
            "subcategory":"Art Services",
            "type":"Services"
        }
    ],
    "sg:phone":"+1 703 858 5251",
    "sg:postcode":"20147",
    "sg:province":"VA",
    "sg:tags":[
        "photography",
        "commercial"
    ],
    "wof:name":"Shourya Ray Photography LLC",
    "wof:placetype":"venue"
},
  "geometry": {"coordinates":[-77.471555,39.050053],"type":"Point"}
}