{
  "type": "Feature",
  "properties": {
    "iso:country":"US",
    "sg:address":"124 King William Dr",
    "sg:city":"Williamsburg",
    "sg:classifiers":[
        {
            "category":"Building & Trades",
            "subcategory":"Construction",
            "type":"Services"
        }
    ],
    "sg:phone":"+1 757 220 8347",
    "sg:postcode":"23188",
    "sg:province":"VA",
    "sg:tags":[
        "house"
    ],
    "wof:name":"Honey Dos",
    "wof:placetype":"venue"
},
  "geometry": {"coordinates":[-76.742949,37.318172],"type":"Point"}
}