{
  "type": "Feature",
  "properties": {
    "addr:full":"208 S Main St Bridgewater VA 22812",
    "addr:housenumber":"208",
    "addr:postcode":"22812",
    "addr:street":"S Main St",
    "iso:country":"US",
    "sg:address":"208 S Main St",
    "sg:city":"Bridgewater",
    "sg:classifiers":[
        {
            "category":"Retail",
            "subcategory":"Funeral Services",
            "type":"Services"
        }
    ],
    "sg:phone":"+1 540 828 2542",
    "sg:postcode":"22812",
    "sg:province":"VA",
    "sg:tags":[
        "director"
    ],
    "wof:name":"Johnson Funeral Svc Inc",
    "wof:placetype":"venue"
},
  "geometry": {"coordinates":[-78.9778,38.380987],"type":"Point"}
}