{
  "type": "Feature",
  "properties": {
    "addr:full":"2829 Saratoga Dr Winchester VA 22601",
    "addr:housenumber":"2829",
    "addr:postcode":"22601",
    "addr:street":"Saratoga Dr",
    "iso:country":"US",
    "sg:address":"2829 Saratoga Dr",
    "sg:city":"Winchester",
    "sg:classifiers":[
        {
            "category":"Building & Trades",
            "subcategory":"Landscaping Services",
            "type":"Services"
        }
    ],
    "sg:phone":"+1 540 545 8900",
    "sg:postcode":"22601",
    "sg:province":"VA",
    "sg:tags":[
        "consultant",
        "designer",
        "landscape"
    ],
    "sg:website":"http://www.mcwhorterglensandgardens.com",
    "wof:name":"Mc Whorter Glens & Gardens",
    "wof:placetype":"venue"
},
  "geometry": {"coordinates":[-78.190315,39.14971],"type":"Point"}
}