{
  "type": "Feature",
  "properties": {
    "addr:full":"2346 Plank Rd Fredericksburg VA 22401",
    "addr:housenumber":"2346",
    "addr:postcode":"22401",
    "addr:street":"Plank Rd",
    "iso:country":"US",
    "sg:address":"2346 Plank Rd",
    "sg:city":"Fredericksburg",
    "sg:classifiers":[
        {
            "category":"Home & Garden",
            "subcategory":"Household Appliances",
            "type":"Retail Goods"
        }
    ],
    "sg:phone":"+1 540 368 2789",
    "sg:postcode":"22401",
    "sg:province":"VA",
    "sg:tags":[
        "repair",
        "vacuum",
        "cleaners"
    ],
    "wof:name":"Aerus Electrolux",
    "wof:placetype":"venue"
},
  "geometry": {"coordinates":[-77.49930999999999,38.296246],"type":"Point"}
}