{
  "type": "Feature",
  "properties": {
    "addr:full":"1017 Hull St Richmond VA 23224",
    "addr:housenumber":"1017",
    "addr:postcode":"23224",
    "addr:street":"Hull St",
    "iso:country":"US",
    "sg:address":"1017 Hull St",
    "sg:city":"Richmond",
    "sg:classifiers":[
        {
            "category":"Banks & Credit Unions",
            "subcategory":"Bank",
            "type":"Services"
        }
    ],
    "sg:phone":"+1 804 379 9270",
    "sg:postcode":"23224",
    "sg:province":"VA",
    "sg:tags":[
        "personal",
        "institution"
    ],
    "wof:name":"Beneficial",
    "wof:placetype":"venue"
},
  "geometry": {"coordinates":[-77.443214,37.521606],"type":"Point"}
}