{
  "type": "Feature",
  "properties": {
    "iso:country":"US",
    "sg:address":"1401 Greenbrier Pkwy",
    "sg:city":"Chesapeake",
    "sg:classifiers":[
        {
            "category":"Ice Cream",
            "type":"Food & Drink"
        }
    ],
    "sg:menulink":"http://www.allmenus.com/va/chesapeake/227856-dippin-dots/menu/",
    "sg:phone":"+1 757 578 3448",
    "sg:postcode":"23320",
    "sg:province":"VA",
    "sg:tags":[
        "american"
    ],
    "wof:name":"Dippin' Dots",
    "wof:placetype":"venue"
},
  "geometry": {"coordinates":[-76.22974000000001,36.775074],"type":"Point"}
}