{
  "type": "Feature",
  "properties": {
    "addr:full":"7837 Snow Creek Rd Penhook VA 24137",
    "addr:housenumber":"7837",
    "addr:postcode":"24137",
    "addr:street":"Snow Creek Rd",
    "iso:country":"US",
    "sg:address":"7837 Snow Creek Rd",
    "sg:city":"Penhook",
    "sg:phone":"+1 540 576 2756",
    "sg:postcode":"24137",
    "sg:province":"VA",
    "sg:tags":[
        "farm",
        "field",
        "crop"
    ],
    "wof:name":"Mart Myrl",
    "wof:placetype":"venue"
},
  "geometry": {"coordinates":[-79.722121,36.867689],"type":"Point"}
}