{
  "type": "Feature",
  "properties": {
    "iso:country":"US",
    "sg:address":"301 Davis St",
    "sg:city":"Independence",
    "sg:classifiers":[
        {
            "category":"Government",
            "subcategory":"Post Office",
            "type":"Public Place"
        }
    ],
    "sg:phone":"+1 276 773 2261",
    "sg:postcode":"24348",
    "sg:province":"VA",
    "wof:name":"US Post Office",
    "wof:placetype":"venue"
},
  "geometry": {"coordinates":[-81.146384,36.6235],"type":"Point"}
}