{
  "type": "Feature",
  "properties": {
    "iso:country":"US",
    "sg:address":"1065 Stony Mill Rd",
    "sg:city":"Danville",
    "sg:classifiers":[
        {
            "category":"Organizations",
            "subcategory":"Religious Organization",
            "type":"Services"
        }
    ],
    "sg:phone":"+1 434 822 0822",
    "sg:postcode":"24540",
    "sg:province":"VA",
    "sg:tags":[
        "church"
    ],
    "wof:name":"Danville Bible Church",
    "wof:placetype":"venue"
},
  "geometry": {"coordinates":[-79.539016,36.648224],"type":"Point"}
}