{
  "type": "Feature",
  "properties": {
    "addr:full":"1916 Storm Dr Falls Church VA 22043",
    "addr:housenumber":"1916",
    "addr:postcode":"22043",
    "addr:street":"Storm Dr",
    "iso:country":"US",
    "sg:address":"1916 Storm Dr",
    "sg:city":"Falls Church",
    "sg:classifiers":[
        {
            "category":"Building & Trades",
            "subcategory":"Cleaning & Sanitation",
            "type":"Services"
        }
    ],
    "sg:phone":"+1 703 356 7617",
    "sg:postcode":"22043",
    "sg:province":"VA",
    "sg:tags":[
        "butler",
        "maid"
    ],
    "wof:name":"Imperial Building Maintenance",
    "wof:placetype":"venue"
},
  "geometry": {"coordinates":[-77.19939599999999,38.912584],"type":"Point"}
}