{
  "type": "Feature",
  "properties": {
    "addr:full":"7784 Gunston Plz Lorton VA 22079",
    "addr:housenumber":"7784",
    "addr:postcode":"22079",
    "addr:street":"Gunston Plz",
    "iso:country":"US",
    "sg:address":"7784 Gunston Plz",
    "sg:city":"Lorton",
    "sg:classifiers":[
        {
            "category":"Restaurant",
            "type":"Food & Drink"
        }
    ],
    "sg:phone":"+1 703 550 0002",
    "sg:postcode":"22079",
    "sg:province":"VA",
    "wof:name":"Polo Grill Restaurant & Tap Rm",
    "wof:placetype":"venue"
},
  "geometry": {"coordinates":[-77.209524,38.703689],"type":"Point"}
}