{
  "type": "Feature",
  "properties": {
    "addr:full":"14749 Warwick Blvd Newport News VA 23608",
    "addr:housenumber":"14749",
    "addr:postcode":"23608",
    "addr:street":"Warwick Blvd",
    "iso:country":"US",
    "sg:address":"14749 Warwick Blvd",
    "sg:city":"Newport News",
    "sg:classifiers":[
        {
            "category":"Social Services",
            "subcategory":"Child Care",
            "type":"Services"
        }
    ],
    "sg:phone":"+1 757 989 0860",
    "sg:postcode":"23608",
    "sg:province":"VA",
    "sg:tags":[
        "day"
    ],
    "wof:name":"Gods Time Childcare & Prescho",
    "wof:placetype":"venue"
},
  "geometry": {"coordinates":[-76.54482299999999,37.135031],"type":"Point"}
}