{
  "type": "Feature",
  "properties": {
    "addr:full":"5540 Main St Mount Jackson VA 22842",
    "addr:housenumber":"5540",
    "addr:postcode":"22842",
    "addr:street":"Main St",
    "iso:country":"US",
    "sg:address":"5540 Main St",
    "sg:city":"Mount Jackson",
    "sg:classifiers":[
        {
            "category":"Food & Beverages",
            "subcategory":"Groceries & Convenience Stores",
            "type":"Retail Goods"
        }
    ],
    "sg:phone":"+1 540 477 9624",
    "sg:postcode":"22842",
    "sg:province":"VA",
    "sg:tags":[
        "station",
        "gasoline"
    ],
    "wof:name":"Getgo",
    "wof:placetype":"venue"
},
  "geometry": {"coordinates":[-78.634604,38.753889],"type":"Point"}
}