{
  "type": "Feature",
  "properties": {
    "iso:country":"US",
    "sg:address":"123 Conway Ave",
    "sg:city":"Norfolk",
    "sg:classifiers":[
        {
            "category":"Arts & Performance",
            "subcategory":"Theater",
            "type":"Entertainment"
        }
    ],
    "sg:phone":"+1 757 423 0796",
    "sg:postcode":"23505",
    "sg:province":"VA",
    "sg:tags":[
        "musician"
    ],
    "wof:name":"Mary Hoffenberger",
    "wof:placetype":"venue"
},
  "geometry": {"coordinates":[-76.276985,36.899125],"type":"Point"}
}