{
  "type": "Feature",
  "properties": {
    "iso:country":"US",
    "sg:address":"2817 Mechanicsville Tpke",
    "sg:city":"Richmond",
    "sg:classifiers":[
        {
            "category":"Shopping",
            "subcategory":"Crafts & Fabrics",
            "type":"Retail Goods"
        }
    ],
    "sg:phone":"+1 804 648 3912",
    "sg:postcode":"23223",
    "sg:province":"VA",
    "sg:tags":[
        "florist",
        "supplies-wholesale",
        "manufacturer",
        "florists'",
        "supply"
    ],
    "wof:name":"The Flying Dutchman",
    "wof:placetype":"venue"
},
  "geometry": {"coordinates":[-77.40540300000001,37.563132],"type":"Point"}
}