{
  "type": "Feature",
  "properties": {
    "addr:full":"17258 Raders Church Rd Timberville VA 22853",
    "addr:postcode":"17258;22853",
    "addr:street":"Church Rd",
    "iso:country":"US",
    "sg:address":"17258 Raders Church Rd",
    "sg:city":"Timberville",
    "sg:classifiers":[
        {
            "category":"Building & Trades",
            "subcategory":"Electrical",
            "type":"Services"
        }
    ],
    "sg:phone":"+1 540 896 5775",
    "sg:postcode":"22853",
    "sg:province":"VA",
    "sg:tags":[
        "electrical",
        "contractor"
    ],
    "wof:name":"Able Electric",
    "wof:placetype":"venue"
},
  "geometry": {"coordinates":[-78.777215,38.657867],"type":"Point"}
}