{
  "type": "Feature",
  "properties": {
    "iso:country":"US",
    "sg:address":"5506 Magnolia Ln",
    "sg:city":"Alexandria",
    "sg:classifiers":[
        {
            "category":"Building & Trades",
            "subcategory":"Construction",
            "type":"Services"
        }
    ],
    "sg:phone":"+1 703 578 1959",
    "sg:postcode":"22311",
    "sg:province":"VA",
    "sg:tags":[
        "wallcoverings-installation",
        "wallpaper",
        "painting",
        "contractor"
    ],
    "wof:name":"Ponce Paint Inc",
    "wof:placetype":"venue"
},
  "geometry": {"coordinates":[-77.12353,38.844975],"type":"Point"}
}