{
  "type": "Feature",
  "properties": {
    "addr:full":"28 Moss Ave Hampton VA 23669",
    "addr:housenumber":"28",
    "addr:postcode":"23669",
    "addr:street":"Moss Ave",
    "iso:country":"US",
    "sg:address":"28 Moss Ave",
    "sg:city":"Hampton",
    "sg:classifiers":[
        {
            "category":"Personal",
            "type":"Services"
        }
    ],
    "sg:phone":"+1 757 722 2478",
    "sg:postcode":"23669",
    "sg:province":"VA",
    "wof:name":"Home Work R US",
    "wof:placetype":"venue"
},
  "geometry": {"coordinates":[-76.356854,37.013533],"type":"Point"}
}