{
  "type": "Feature",
  "properties": {
    "addr:full":"805 20th St S Arlington VA 22202",
    "addr:housenumber":"805",
    "addr:postcode":"22202",
    "addr:street":"20Th St S",
    "iso:country":"US",
    "sg:address":"805 20th St S",
    "sg:city":"Arlington",
    "sg:classifiers":[
        {
            "category":"Food & Beverages",
            "subcategory":"Groceries & Convenience Stores",
            "type":"Retail Goods"
        }
    ],
    "sg:phone":"+1 703 920 2040",
    "sg:postcode":"22202",
    "sg:province":"VA",
    "sg:tags":[
        "business",
        "for",
        "private",
        "aircraft",
        "caterer",
        "aviation"
    ],
    "wof:name":"Air Culinarie Inc",
    "wof:placetype":"venue"
},
  "geometry": {"coordinates":[-77.061368,38.855643],"type":"Point"}
}