{
  "type": "Feature",
  "properties": {
    "iso:country":"US",
    "sg:address":"2665 Granite Hill Cir",
    "sg:city":"Richmond",
    "sg:classifiers":[
        {
            "category":"Real Estate",
            "subcategory":"Real Estate Operator",
            "type":"Services"
        }
    ],
    "sg:phone":"+1 804 320 3111",
    "sg:postcode":"23225",
    "sg:province":"VA",
    "sg:tags":[
        "building",
        "apartment"
    ],
    "wof:name":"Forest Ridge Apts",
    "wof:placetype":"venue"
},
  "geometry": {"coordinates":[-77.520692,37.535592],"type":"Point"}
}