{
  "type": "Feature",
  "properties": {
    "iso:country":"US",
    "sg:address":"305 Church St NE",
    "sg:city":"Wise",
    "sg:classifiers":[
        {
            "category":"Food & Beverages",
            "subcategory":"Groceries & Convenience Stores",
            "type":"Retail Goods"
        }
    ],
    "sg:phone":"+1 276 328 6237",
    "sg:postcode":"24293",
    "sg:province":"VA",
    "sg:tags":[
        "grocer"
    ],
    "wof:name":"Pay Less Super Markets",
    "wof:placetype":"venue"
},
  "geometry": {"coordinates":[-82.577979,36.977633],"type":"Point"}
}