{
  "type": "Feature",
  "properties": {
    "addr:full":"12680 Jefferson Ave Newport News VA 23602",
    "addr:housenumber":"12680",
    "addr:postcode":"23602",
    "addr:street":"Jefferson Ave",
    "iso:country":"US",
    "sg:address":"12680 Jefferson Ave",
    "sg:city":"Newport News",
    "sg:classifiers":[
        {
            "category":"Restaurant",
            "type":"Food & Drink"
        }
    ],
    "sg:menulink":"http://www.allmenus.com/va/newport-news/42387-red-lobster/menu/",
    "sg:phone":"+1 757 989 6423",
    "sg:postcode":"23602",
    "sg:province":"VA",
    "sg:tags":[
        "seafood",
        "american"
    ],
    "wof:name":"Red Lobster",
    "wof:placetype":"venue"
},
  "geometry": {"coordinates":[-76.516488,37.134254],"type":"Point"}
}