{
  "type": "Feature",
  "properties": {
    "iso:country":"US",
    "sg:address":"18 W Mercury Blvd",
    "sg:city":"Hampton",
    "sg:classifiers":[
        {
            "category":"Arts & Performance",
            "subcategory":"Theater",
            "type":"Entertainment"
        }
    ],
    "sg:phone":"+1 757 722 9100",
    "sg:postcode":"23669",
    "sg:province":"VA",
    "sg:tags":[
        "group"
    ],
    "wof:name":"Hoshama Music Management Group",
    "wof:placetype":"venue"
},
  "geometry": {"coordinates":[-76.34961300000001,37.044002],"type":"Point"}
}