{
  "type": "Feature",
  "properties": {
    "addr:full":"15104 Spruce Ave Chester VA 23836",
    "addr:housenumber":"15104",
    "addr:postcode":"23836",
    "addr:street":"Spruce Ave",
    "iso:country":"US",
    "sg:address":"15104 Spruce Ave",
    "sg:city":"Chester",
    "sg:classifiers":[
        {
            "category":"Building & Trades",
            "subcategory":"Cleaning & Sanitation",
            "type":"Services"
        }
    ],
    "sg:phone":"+1 804 530 2538",
    "sg:postcode":"23836",
    "sg:province":"VA",
    "sg:tags":[
        "exhaust",
        "kitchen",
        "hood",
        "pressure"
    ],
    "wof:name":"Enon Steam Cleaning",
    "wof:placetype":"venue"
},
  "geometry": {"coordinates":[-77.323402,37.321667],"type":"Point"}
}