{
  "type": "Feature",
  "properties": {
    "addr:full":"3901 Midlands Rd Williamsburg VA 23188",
    "addr:housenumber":"3901",
    "addr:postcode":"23188",
    "addr:street":"Midlands Rd",
    "iso:country":"US",
    "sg:address":"3901 Midlands Rd",
    "sg:city":"Williamsburg",
    "sg:classifiers":[
        {
            "category":"Professional",
            "subcategory":"Accounting & Tax Preparation",
            "type":"Services"
        }
    ],
    "sg:phone":"+1 757 229 1023",
    "sg:postcode":"23188",
    "sg:province":"VA",
    "sg:tags":[
        "accountant"
    ],
    "wof:name":"Lent & Hawthorne Ltd",
    "wof:placetype":"venue"
},
  "geometry": {"coordinates":[-76.74059699999999,37.267543],"type":"Point"}
}