{
  "type": "Feature",
  "properties": {
    "iso:country":"US",
    "sg:address":"596 Central Dr",
    "sg:city":"Virginia Beach",
    "sg:classifiers":[
        {
            "category":"Shopping",
            "subcategory":"Computers & Home Electronics",
            "type":"Retail Goods"
        }
    ],
    "sg:phone":"+1 757 306 8900",
    "sg:postcode":"23454",
    "sg:province":"VA",
    "sg:tags":[
        "repair",
        "networking",
        "sales"
    ],
    "wof:name":"Electronic Solutions",
    "wof:placetype":"venue"
},
  "geometry": {"coordinates":[-76.05905199999999,36.817348],"type":"Point"}
}