{
  "type": "Feature",
  "properties": {
    "iso:country":"US",
    "sg:address":"10481 Lankford Hwy",
    "sg:city":"Temperanceville",
    "sg:classifiers":[
        {
            "category":"Retail",
            "subcategory":"Funeral Services",
            "type":"Services"
        }
    ],
    "sg:phone":"+1 757 824 4001",
    "sg:postcode":"23442",
    "sg:province":"VA",
    "wof:name":"Fox Funeral Home",
    "wof:placetype":"venue"
},
  "geometry": {"coordinates":[-75.55271500000001,37.887277],"type":"Point"}
}