{
  "type": "Feature",
  "properties": {
    "addr:full":"3120 W Cary St Richmond VA 23221",
    "addr:housenumber":"3120",
    "addr:postcode":"23221",
    "addr:street":"W Cary St",
    "iso:country":"US",
    "sg:address":"3120 W Cary St",
    "sg:city":"Richmond",
    "sg:classifiers":[
        {
            "category":"Restaurant",
            "type":"Food & Drink"
        }
    ],
    "sg:menulink":"http://www.allmenus.com/va/richmond/12974-can-can-bistro/menu/",
    "sg:phone":"+1 804 358 7247",
    "sg:postcode":"23221",
    "sg:province":"VA",
    "sg:tags":[
        "french"
    ],
    "wof:name":"Can Can Bistro",
    "wof:placetype":"venue"
},
  "geometry": {"coordinates":[-77.481089,37.553355],"type":"Point"}
}