{
  "type": "Feature",
  "properties": {
    "addr:full":"707 S Pitt St Alexandria VA 22314",
    "addr:housenumber":"707",
    "addr:postcode":"22314",
    "addr:street":"S Pitt St",
    "iso:country":"US",
    "sg:address":"707 S Pitt St",
    "sg:city":"Alexandria",
    "sg:classifiers":[
        {
            "category":"Organizations",
            "subcategory":"Community Association",
            "type":"Services"
        }
    ],
    "sg:phone":"+1 703 549 0747",
    "sg:postcode":"22314",
    "sg:province":"VA",
    "wof:name":"Forest Landowners Tax Council",
    "wof:placetype":"venue"
},
  "geometry": {"coordinates":[-77.04655,38.796802],"type":"Point"}
}