{
  "type": "Feature",
  "properties": {
    "iso:country":"US",
    "sg:address":"1825 Templeton Ln",
    "sg:city":"Virginia Beach",
    "sg:classifiers":[
        {
            "category":"Recreation",
            "type":"Entertainment"
        }
    ],
    "sg:phone":"+1 757 496 2084",
    "sg:postcode":"23454",
    "sg:province":"VA",
    "sg:tags":[
        "club",
        "membership"
    ],
    "wof:name":"National Exchange Club",
    "wof:placetype":"venue"
},
  "geometry": {"coordinates":[-76.028133,36.869576],"type":"Point"}
}