{
  "type": "Feature",
  "properties": {
    "iso:country":"US",
    "sg:address":"3180 Adam Keeling Rd",
    "sg:city":"Virginia Beach",
    "sg:classifiers":[
        {
            "category":"Building & Trades",
            "subcategory":"Plumbing",
            "type":"Services"
        }
    ],
    "sg:phone":"+1 757 481 2680",
    "sg:postcode":"23454",
    "sg:province":"VA",
    "sg:tags":[
        "conditioning",
        "air",
        "system",
        "contractor"
    ],
    "wof:name":"Barry's Gas Burner Svc Inc",
    "wof:placetype":"venue"
},
  "geometry": {"coordinates":[-76.082408,36.89957],"type":"Point"}
}