{
  "type": "Feature",
  "properties": {
    "addr:full":"9093 Mathis Ave Manassas VA 20110",
    "addr:housenumber":"9093",
    "addr:postcode":"20110",
    "addr:street":"Mathis Ave",
    "iso:country":"US",
    "sg:address":"9093 Mathis Ave",
    "sg:city":"Manassas",
    "sg:classifiers":[
        {
            "category":"Autos & Motor Vehicles",
            "subcategory":"Auto Supplies",
            "type":"Retail Goods"
        },
        {
            "category":"Retail",
            "subcategory":"Car Wash",
            "type":"Services"
        },
        {
            "category":"Retail",
            "subcategory":"Auto Repair",
            "type":"Services"
        }
    ],
    "sg:phone":"+1 703 368 2221",
    "sg:postcode":"20110",
    "sg:province":"VA",
    "sg:tags":[
        "body",
        "repairing",
        "automobile",
        "detailing",
        "part",
        "painting"
    ],
    "sg:website":"http://Manassas.maaco.com",
    "wof:name":"Maaco - Manassas",
    "wof:placetype":"venue"
},
  "geometry": {"coordinates":[-77.465068,38.758666],"type":"Point"}
}