{
  "type": "Feature",
  "properties": {
    "iso:country":"US",
    "sg:address":"372 S Independence Blvd",
    "sg:city":"Virginia Beach",
    "sg:classifiers":[
        {
            "category":"Arts & Performance",
            "subcategory":"Theater",
            "type":"Entertainment"
        }
    ],
    "sg:phone":"+1 757 671 8611",
    "sg:postcode":"23452",
    "sg:province":"VA",
    "sg:tags":[
        "band",
        "orchestra"
    ],
    "wof:name":"Va Beach Symphony Orchestra",
    "wof:placetype":"venue"
},
  "geometry": {"coordinates":[-76.13538800000001,36.829287],"type":"Point"}
}