{
  "type": "Feature",
  "properties": {
    "addr:full":"223 N Washington Hwy Ashland VA 23005",
    "addr:housenumber":"223",
    "addr:postcode":"23005",
    "addr:street":"N Washington Hwy",
    "iso:country":"US",
    "sg:address":"223 N Washington Hwy",
    "sg:city":"Ashland",
    "sg:classifiers":[
        {
            "category":"Shopping",
            "subcategory":"Jewelry",
            "type":"Retail Goods"
        }
    ],
    "sg:phone":"+1 804 798 7307",
    "sg:postcode":"23005",
    "sg:province":"VA",
    "sg:tags":[
        "repair",
        "watch",
        "gift",
        "jeweler"
    ],
    "wof:name":"Tompkins Jewelers Inc",
    "wof:placetype":"venue"
},
  "geometry": {"coordinates":[-77.471462,37.759794],"type":"Point"}
}