{
  "type": "Feature",
  "properties": {
    "addr:full":"6775 Springfield Blvd Springfield VA 22150",
    "addr:housenumber":"6775",
    "addr:postcode":"22150",
    "addr:street":"Springfield Blvd",
    "iso:country":"US",
    "sg:address":"6775 Springfield Blvd",
    "sg:city":"Springfield",
    "sg:classifiers":[
        {
            "category":"Shopping",
            "subcategory":"Jewelry",
            "type":"Retail Goods"
        }
    ],
    "sg:phone":"+1 703 924 0001",
    "sg:postcode":"22150",
    "sg:province":"VA",
    "sg:tags":[
        "jeweler"
    ],
    "wof:name":"Diamond Concepts Custom",
    "wof:placetype":"venue"
},
  "geometry": {"coordinates":[-77.183346,38.778067],"type":"Point"}
}