{
  "type": "Feature",
  "properties": {
    "addr:full":"4218 W Broad St Richmond VA 23230",
    "addr:housenumber":"4218",
    "addr:postcode":"23230",
    "addr:street":"W Broad St",
    "iso:country":"US",
    "sg:address":"4218 W Broad St",
    "sg:city":"Richmond",
    "sg:classifiers":[
        {
            "category":"Banks & Credit Unions",
            "subcategory":"Investment Brokerage",
            "type":"Services"
        }
    ],
    "sg:phone":"+1 804 355 0597",
    "sg:postcode":"23230",
    "sg:province":"VA",
    "sg:tags":[
        "advisory",
        "financial"
    ],
    "wof:name":"Family Financial Corp",
    "wof:placetype":"venue"
},
  "geometry": {"coordinates":[-77.485788,37.575279],"type":"Point"}
}