{
  "type": "Feature",
  "properties": {
    "addr:full":"900 28th St S Arlington VA 22202",
    "addr:housenumber":"900",
    "addr:postcode":"22202",
    "addr:street":"28Th St S",
    "iso:country":"US",
    "sg:address":"900 28th St S",
    "sg:city":"Arlington",
    "sg:classifiers":[
        {
            "category":"Building & Trades",
            "subcategory":"Locksmith",
            "type":"Services"
        }
    ],
    "sg:phone":"+1 571 451 0244",
    "sg:postcode":"22202",
    "sg:province":"VA",
    "sg:tags":[
        "key"
    ],
    "wof:name":"24Hrs Car Locksmith",
    "wof:placetype":"venue"
},
  "geometry": {"coordinates":[-77.063013,38.846353],"type":"Point"}
}