{
  "type": "Feature",
  "properties": {
    "addr:full":"10550 Linden Lake Plz Manassas VA 20109",
    "addr:housenumber":"10550",
    "addr:postcode":"20109",
    "addr:street":"Linden Lake Plz",
    "iso:country":"US",
    "sg:address":"10550 Linden Lake Plz",
    "sg:city":"Manassas",
    "sg:classifiers":[
        {
            "category":"Utilities",
            "subcategory":"Telephone",
            "type":"Services"
        }
    ],
    "sg:phone":"+1 703 620 8838",
    "sg:postcode":"20109",
    "sg:province":"VA",
    "sg:tags":[
        "on",
        "text",
        "call",
        "chat",
        "desk",
        "line",
        "outsourced"
    ],
    "wof:name":"IBSI",
    "wof:placetype":"venue"
},
  "geometry": {"coordinates":[-77.51097,38.795339],"type":"Point"}
}