{
  "type": "Feature",
  "properties": {
    "iso:country":"US",
    "sg:address":"13505 Conway Ln",
    "sg:city":"Orange",
    "sg:classifiers":[
        {
            "category":"Professional",
            "subcategory":"Computer Services",
            "type":"Services"
        }
    ],
    "sg:phone":"+1 540 672 9424",
    "sg:postcode":"22960",
    "sg:province":"VA",
    "sg:tags":[
        "programming"
    ],
    "wof:name":"Aquarian Computer Svcs",
    "wof:placetype":"venue"
},
  "geometry": {"coordinates":[-78.136926,38.207952],"type":"Point"}
}