{
  "type": "Feature",
  "properties": {
    "addr:full":"1701 E Nine Mile Rd Highland Springs VA 23075",
    "addr:housenumber":"1701",
    "addr:postcode":"23075",
    "addr:street":"E Nine Mile Rd",
    "iso:country":"US",
    "sg:address":"1701 E Nine Mile Rd",
    "sg:city":"Highland Springs",
    "sg:classifiers":[
        {
            "category":"Organizations",
            "subcategory":"Religious Organization",
            "type":"Services"
        }
    ],
    "sg:phone":"+1 804 737 1981",
    "sg:postcode":"23075",
    "sg:province":"VA",
    "wof:name":"Fair Oak Baptist Church",
    "wof:placetype":"venue"
},
  "geometry": {"coordinates":[-77.31614999999999,37.532742],"type":"Point"}
}