{
  "type": "Feature",
  "properties": {
    "addr:full":"1450 Hoover Rd Woodstock VA 22664",
    "addr:housenumber":"1450",
    "addr:postcode":"22664",
    "addr:street":"Hoover Rd",
    "iso:country":"US",
    "sg:address":"1450 Hoover Rd",
    "sg:city":"Woodstock",
    "sg:classifiers":[
        {
            "category":"Real Estate",
            "subcategory":"Real Estate Agent",
            "type":"Services"
        }
    ],
    "sg:phone":"+1 540 459 8760",
    "sg:postcode":"22664",
    "sg:province":"VA",
    "wof:name":"Countrywide Real Estate Svcs",
    "wof:placetype":"venue"
},
  "geometry": {"coordinates":[-78.52331700000001,38.857785],"type":"Point"}
}