{
  "type": "Feature",
  "properties": {
    "iso:country":"US",
    "sg:address":"2089 Riceville Rd",
    "sg:city":"Java",
    "sg:classifiers":[
        {
            "category":"Retail",
            "subcategory":"Auto Repair",
            "type":"Services"
        }
    ],
    "sg:phone":"+1 434 432 9475",
    "sg:postcode":"24565",
    "sg:province":"VA",
    "sg:tags":[
        "automotive",
        "general"
    ],
    "wof:name":"Jennings Garage",
    "wof:placetype":"venue"
},
  "geometry": {"coordinates":[-79.168342,36.89273],"type":"Point"}
}