{
  "type": "Feature",
  "properties": {
    "addr:full":"1050 N. Stuart St. Arlington VA 22201",
    "addr:housenumber":"1050",
    "addr:postcode":"22201",
    "addr:street":"N. Stuart St.",
    "iso:country":"US",
    "sg:address":"1050 N. Stuart St.",
    "sg:city":"Arlington",
    "sg:classifiers":[
        {
            "category":"Education",
            "subcategory":"Special Training",
            "type":"Public Place"
        },
        {
            "category":"Sports & Exercise",
            "subcategory":"Gym",
            "type":"Entertainment"
        },
        {
            "category":"Personal",
            "type":"Services"
        }
    ],
    "sg:phone":"+1 703 286 5115",
    "sg:postcode":"22201",
    "sg:province":"VA",
    "sg:tags":[
        "trainer",
        "school",
        "cooking",
        "yoga",
        "consultant",
        "instruction",
        "program",
        "fitness",
        "physical"
    ],
    "sg:website":"http://www.cocofitness.com",
    "wof:name":"CocoFitness",
    "wof:placetype":"venue"
},
  "geometry": {"coordinates":[-77.111968,38.883572],"type":"Point"}
}