{
  "type": "Feature",
  "properties": {
    "addr:full":"263 Chelmsford Ct Sterling VA 20165",
    "addr:housenumber":"263",
    "addr:postcode":"20165",
    "addr:street":"Chelmsford Ct",
    "iso:country":"US",
    "sg:address":"263 Chelmsford Ct",
    "sg:city":"Sterling",
    "sg:classifiers":[
        {
            "category":"Professional",
            "type":"Services"
        }
    ],
    "sg:phone":"+1 703 430 5433",
    "sg:postcode":"20165",
    "sg:province":"VA",
    "wof:name":"M Brown",
    "wof:placetype":"venue"
},
  "geometry": {"coordinates":[-77.395985,39.050037],"type":"Point"}
}