{
  "type": "Feature",
  "properties": {
    "addr:full":"352 Robertson Mountain Rd Narrows VA 24124",
    "addr:housenumber":"352",
    "addr:postcode":"24124",
    "addr:street":"Robertson Mountain Rd",
    "iso:country":"US",
    "sg:address":"352 Robertson Mountain Rd",
    "sg:city":"Narrows",
    "sg:classifiers":[
        {
            "category":"Retail",
            "subcategory":"Auto Repair",
            "type":"Services"
        }
    ],
    "sg:phone":"+1 540 726 7427",
    "sg:postcode":"24124",
    "sg:province":"VA",
    "sg:tags":[
        "body",
        "automobile",
        "painting"
    ],
    "wof:name":"Art's Body Shop",
    "wof:placetype":"venue"
},
  "geometry": {"coordinates":[-80.830412,37.362285],"type":"Point"}
}