{
  "type": "Feature",
  "properties": {
    "iso:country":"US",
    "sg:address":"5452 Southpoint Plaza Way",
    "sg:city":"Fredericksburg",
    "sg:classifiers":[
        {
            "category":"Restaurant",
            "type":"Food & Drink"
        }
    ],
    "sg:menulink":"http://www.allmenus.com/va/lee-hill/83423-papa-johns-pizza/menu/",
    "sg:phone":"+1 540 834 4433",
    "sg:postcode":"22407",
    "sg:province":"VA",
    "sg:tags":[
        "american",
        "pizza"
    ],
    "wof:name":"Papa John's Pizza",
    "wof:placetype":"venue"
},
  "geometry": {"coordinates":[-77.50310500000001,38.23161],"type":"Point"}
}