{
  "type": "Feature",
  "properties": {
    "addr:full":"2011 Snow Hill Rd Alton VA 24520",
    "addr:housenumber":"2011",
    "addr:postcode":"24520",
    "addr:street":"Snow Hill Rd",
    "iso:country":"US",
    "sg:address":"2011 Snow Hill Rd",
    "sg:city":"Alton",
    "sg:classifiers":[
        {
            "category":"Home & Garden",
            "subcategory":"Garden Supply",
            "type":"Retail Goods"
        }
    ],
    "sg:phone":"+1 434 753 2818",
    "sg:postcode":"24520",
    "sg:province":"VA",
    "sg:tags":[
        "lawn",
        "mower"
    ],
    "wof:name":"Moneymakers Sandblasting/Weld",
    "wof:placetype":"venue"
},
  "geometry": {"coordinates":[-78.955153,36.591069],"type":"Point"}
}