{
  "type": "Feature",
  "properties": {
    "addr:full":"13402 Kingsman Rd Woodbridge VA 22193",
    "addr:postcode":"13402;22193",
    "addr:street":"Kingsman Rd",
    "iso:country":"US",
    "sg:address":"13402 Kingsman Rd",
    "sg:city":"Woodbridge",
    "sg:classifiers":[
        {
            "category":"Building & Trades",
            "subcategory":"Cleaning & Sanitation",
            "type":"Services"
        }
    ],
    "sg:phone":"+1 703 271 4080",
    "sg:postcode":"22193",
    "sg:province":"VA",
    "sg:tags":[
        "janitor"
    ],
    "wof:name":"Milagro Quality Cleaning Svc",
    "wof:placetype":"venue"
},
  "geometry": {"coordinates":[-77.34659499999999,38.663259],"type":"Point"}
}