{
  "type": "Feature",
  "properties": {
    "addr:full":"2605 Riverside Dr Danville VA 24540",
    "addr:housenumber":"2605",
    "addr:postcode":"24540",
    "addr:street":"Riverside Dr",
    "iso:country":"US",
    "sg:address":"2605 Riverside Dr",
    "sg:city":"Danville",
    "sg:classifiers":[
        {
            "category":"Home & Garden",
            "subcategory":"Building Materials",
            "type":"Retail Goods"
        }
    ],
    "sg:phone":"+1 434 799 5070",
    "sg:postcode":"24540",
    "sg:province":"VA",
    "sg:tags":[
        "insulation",
        "heat"
    ],
    "wof:name":"Mc Cormick Insulation Supply",
    "wof:placetype":"venue"
},
  "geometry": {"coordinates":[-79.414131,36.593191],"type":"Point"}
}