{
  "type": "Feature",
  "properties": {
    "iso:country":"US",
    "sg:address":"228 Creek View Ln",
    "sg:city":"Colonial Beach",
    "sg:classifiers":[
        {
            "category":"Health Services",
            "subcategory":"Clinic",
            "type":"Services"
        }
    ],
    "sg:phone":"+1 804 224 3028",
    "sg:postcode":"22443",
    "sg:province":"VA",
    "sg:tags":[
        "screening"
    ],
    "wof:name":"American Screening Association",
    "wof:placetype":"venue"
},
  "geometry": {"coordinates":[-76.978627,38.249078],"type":"Point"}
}