{
  "type": "Feature",
  "properties": {
    "iso:country":"US",
    "sg:address":"10200 W Broad St",
    "sg:city":"Glen Allen",
    "sg:classifiers":[
        {
            "category":"Retail",
            "subcategory":"Laundry & Dry Cleaning",
            "type":"Services"
        }
    ],
    "sg:phone":"+1 804 527 3299",
    "sg:postcode":"23060",
    "sg:province":"VA",
    "sg:tags":[
        "cleaners"
    ],
    "wof:name":"Puritan Cleaners & Launderers",
    "wof:placetype":"venue"
},
  "geometry": {"coordinates":[-77.578238,37.646288],"type":"Point"}
}