{
  "type": "Feature",
  "properties": {
    "addr:full":"2520 S Pleasant Valley Rd Winchester VA 22601",
    "addr:housenumber":"2520",
    "addr:postcode":"22601",
    "addr:street":"S Pleasant Valley Rd",
    "iso:country":"US",
    "sg:address":"2520 S Pleasant Valley Rd",
    "sg:city":"Winchester",
    "sg:classifiers":[
        {
            "category":"Ice Cream",
            "type":"Food & Drink"
        }
    ],
    "sg:menulink":"http://www.allmenus.com/va/winchester/184461-cold-stone-creamery/menu/",
    "sg:phone":"+1 540 723 0640",
    "sg:postcode":"22601",
    "sg:province":"VA",
    "sg:tags":[
        "smoothy",
        "juice",
        "american"
    ],
    "wof:name":"Cold Stone Creamery",
    "wof:placetype":"venue"
},
  "geometry": {"coordinates":[-78.17562100000001,39.154414],"type":"Point"}
}