{
  "type": "Feature",
  "properties": {
    "iso:country":"US",
    "sg:address":"3506 Mavis Ct",
    "sg:city":"Fairfax",
    "sg:classifiers":[
        {
            "category":"Professional",
            "subcategory":"Business Services",
            "type":"Services"
        }
    ],
    "sg:phone":"+1 703 591 0808",
    "sg:postcode":"22030",
    "sg:province":"VA",
    "wof:name":"Jfa Enterprises LLC",
    "wof:placetype":"venue"
},
  "geometry": {"coordinates":[-77.309884,38.862347],"type":"Point"}
}