{
  "type": "Feature",
  "properties": {
    "iso:country":"US",
    "sg:address":"733 29th St NW",
    "sg:city":"Roanoke",
    "sg:classifiers":[
        {
            "category":"Real Estate",
            "subcategory":"Real Estate Operator",
            "type":"Services"
        }
    ],
    "sg:phone":"+1 540 982 0010",
    "sg:postcode":"24017",
    "sg:province":"VA",
    "sg:tags":[
        "building",
        "apartment"
    ],
    "wof:name":"Shenandoah Village Apartments",
    "wof:placetype":"venue"
},
  "geometry": {"coordinates":[-79.98366900000001,37.285254],"type":"Point"}
}