{
  "type": "Feature",
  "properties": {
    "iso:country":"US",
    "sg:address":"225 N Washington Hwy",
    "sg:city":"Ashland",
    "sg:classifiers":[
        {
            "category":"Professional",
            "subcategory":"Business Services",
            "type":"Services"
        }
    ],
    "sg:phone":"+1 804 752 1650",
    "sg:postcode":"23005",
    "sg:province":"VA",
    "wof:name":"Djs Enterprises LLC",
    "wof:placetype":"venue"
},
  "geometry": {"coordinates":[-77.47146100000001,37.759761],"type":"Point"}
}