{
  "type": "Feature",
  "properties": {
    "iso:country":"US",
    "sg:address":"796 N Main St",
    "sg:city":"Pearisburg",
    "sg:classifiers":[
        {
            "category":"Retail",
            "subcategory":"Auto Repair",
            "type":"Services"
        }
    ],
    "sg:phone":"+1 540 921 3559",
    "sg:postcode":"24134",
    "sg:province":"VA",
    "sg:tags":[
        "body"
    ],
    "wof:name":"Lees Body Shop Inc",
    "wof:placetype":"venue"
},
  "geometry": {"coordinates":[-80.74989100000001,37.333811],"type":"Point"}
}