{
  "type": "Feature",
  "properties": {
    "iso:country":"US",
    "sg:address":"615 S Hicks St",
    "sg:city":"Lawrenceville",
    "sg:classifiers":[
        {
            "category":"Personal",
            "subcategory":"Beauty Salon",
            "type":"Services"
        }
    ],
    "sg:phone":"+1 804 478 4500",
    "sg:postcode":"23868",
    "sg:province":"VA",
    "wof:name":"Hair Attitude",
    "wof:placetype":"venue"
},
  "geometry": {"coordinates":[-77.852069,36.752876],"type":"Point"}
}