{
  "type": "Feature",
  "properties": {
    "addr:full":"700 Flag Stone Way Newport News VA 23608",
    "addr:housenumber":"700",
    "addr:postcode":"23608",
    "addr:street":"Flag Stone Way",
    "iso:country":"US",
    "sg:address":"700 Flag Stone Way",
    "sg:city":"Newport News",
    "sg:classifiers":[
        {
            "category":"Wholesale",
            "subcategory":"Construction Materials",
            "type":"Manufacturing & Wholesale Goods"
        }
    ],
    "sg:phone":"+1 757 989 0500",
    "sg:postcode":"23608",
    "sg:province":"VA",
    "sg:tags":[
        "h",
        "metal",
        "mfg"
    ],
    "wof:name":"Hci/Craftsmen",
    "wof:placetype":"venue"
},
  "geometry": {"coordinates":[-76.53060499999999,37.170365],"type":"Point"}
}