{
  "type": "Feature",
  "properties": {
    "addr:full":"1616 Anderson Rd McLean VA 22102",
    "addr:housenumber":"1616",
    "addr:postcode":"22102",
    "addr:street":"Anderson Rd",
    "iso:country":"US",
    "sg:address":"1616 Anderson Rd",
    "sg:city":"McLean",
    "sg:classifiers":[
        {
            "category":"Professional",
            "subcategory":"Computer Services",
            "type":"Services"
        }
    ],
    "sg:phone":"+1 703 286 0950",
    "sg:postcode":"22102",
    "sg:province":"VA",
    "sg:tags":[
        "weddzilla",
        "bridezilla",
        "wedding-planning",
        "wedding-vendors"
    ],
    "sg:website":"http://www.weddzilla.com",
    "wof:name":"Weddzilla.com",
    "wof:placetype":"venue"
},
  "geometry": {"coordinates":[-77.203823,38.925586],"type":"Point"}
}