{
  "type": "Feature",
  "properties": {
    "iso:country":"US",
    "sg:address":"487 Alabama Dr",
    "sg:city":"Herndon",
    "sg:classifiers":[
        {
            "category":"Communications",
            "type":"Services"
        }
    ],
    "sg:phone":"+1 571 215 8248",
    "sg:postcode":"20170",
    "sg:province":"VA",
    "sg:tags":[
        "communication"
    ],
    "wof:name":"Broadband Links Communications",
    "wof:placetype":"venue"
},
  "geometry": {"coordinates":[-77.38239799999999,38.958339],"type":"Point"}
}