{
  "type": "Feature",
  "properties": {
    "addr:full":"1231 Pleasant View Rd Mount Jackson VA 22842",
    "addr:housenumber":"1231",
    "addr:postcode":"22842",
    "addr:street":"Pleasant View Rd",
    "iso:country":"US",
    "sg:address":"1231 Pleasant View Rd",
    "sg:city":"Mount Jackson",
    "sg:classifiers":[
        {
            "category":"Farming",
            "subcategory":"Dairy Farm",
            "type":"Manufacturing & Wholesale Goods"
        }
    ],
    "sg:phone":"+1 540 477 3707",
    "sg:postcode":"22842",
    "sg:province":"VA",
    "wof:name":"Harry Polk",
    "wof:placetype":"venue"
},
  "geometry": {"coordinates":[-78.671054,38.782184],"type":"Point"}
}