{
  "type": "Feature",
  "properties": {
    "addr:full":"16 Gladeview Dr Fries VA 24330",
    "addr:housenumber":"16",
    "addr:postcode":"fries;24330",
    "addr:street":"Gladeview Dr",
    "iso:country":"US",
    "sg:address":"16 Gladeview Dr",
    "sg:city":"Fries",
    "sg:classifiers":[
        {
            "category":"Professional",
            "type":"Services"
        }
    ],
    "sg:phone":"+1 276 744 7610",
    "sg:postcode":"24330",
    "sg:province":"VA",
    "wof:name":"Jeremy Butterworth",
    "wof:placetype":"venue"
},
  "geometry": {"coordinates":[-80.987354,36.742826],"type":"Point"}
}