{
  "type": "Feature",
  "properties": {
    "addr:full":"10909 Fairchester Dr Fairfax VA 22030",
    "addr:housenumber":"10909",
    "addr:postcode":"22030",
    "addr:street":"Fairchester Dr",
    "iso:country":"US",
    "sg:address":"10909 Fairchester Dr",
    "sg:city":"Fairfax",
    "sg:classifiers":[
        {
            "category":"Professional",
            "subcategory":"Business Services",
            "type":"Services"
        }
    ],
    "sg:phone":"+1 703 218 3274",
    "sg:postcode":"22030",
    "sg:province":"VA",
    "wof:name":"General Home Inspection Co",
    "wof:placetype":"venue"
},
  "geometry": {"coordinates":[-77.322548,38.854285],"type":"Point"}
}