{
  "type": "Feature",
  "properties": {
    "addr:full":"479 McLaws Cir Williamsburg VA 23185",
    "addr:housenumber":"479",
    "addr:postcode":"23185",
    "addr:street":"Mclaws Cir",
    "iso:country":"US",
    "sg:address":"479 McLaws Cir",
    "sg:city":"Williamsburg",
    "sg:classifiers":[
        {
            "category":"Organizations",
            "subcategory":"Professional Association",
            "type":"Services"
        }
    ],
    "sg:phone":"+1 757 229 3113",
    "sg:postcode":"23185",
    "sg:province":"VA",
    "wof:name":"NAACP",
    "wof:placetype":"venue"
},
  "geometry": {"coordinates":[-76.663222,37.248565],"type":"Point"}
}