{
  "type": "Feature",
  "properties": {
    "iso:country":"US",
    "sg:address":"505 W Leigh St",
    "sg:city":"Richmond",
    "sg:classifiers":[
        {
            "category":"Health Services",
            "subcategory":"Doctor",
            "type":"Services"
        }
    ],
    "sg:phone":"+1 804 788 0004",
    "sg:postcode":"23220",
    "sg:province":"VA",
    "sg:tags":[
        "physician",
        "surgeon"
    ],
    "wof:name":"Commonwealth Cardiology Assoc",
    "wof:placetype":"venue"
},
  "geometry": {"coordinates":[-77.444209,37.551384],"type":"Point"}
}