{
  "type": "Feature",
  "properties": {
    "addr:full":"120 Tomahawk Dr Lynchburg VA 24502",
    "addr:housenumber":"120",
    "addr:postcode":"24502",
    "addr:street":"Tomahawk Dr",
    "iso:country":"US",
    "sg:address":"120 Tomahawk Dr",
    "sg:city":"Lynchburg",
    "sg:classifiers":[
        {
            "category":"Professional",
            "type":"Services"
        }
    ],
    "sg:phone":"+1 434 239 6366",
    "sg:postcode":"24502",
    "sg:province":"VA",
    "wof:name":"Delvero Enterprises",
    "wof:placetype":"venue"
},
  "geometry": {"coordinates":[-79.229204,37.369153],"type":"Point"}
}