{
  "type": "Feature",
  "properties": {
    "addr:full":"2130 Germanna Hwy Locust Grove VA 22508",
    "addr:housenumber":"2130",
    "addr:postcode":"22508",
    "addr:street":"Germanna Hwy",
    "iso:country":"US",
    "sg:address":"2130 Germanna Hwy",
    "sg:city":"Locust Grove",
    "sg:classifiers":[
        {
            "category":"Education",
            "subcategory":"College",
            "type":"Public Place"
        }
    ],
    "sg:phone":"+1 540 423 9117",
    "sg:postcode":"22508",
    "sg:province":"VA",
    "sg:tags":[
        "academic",
        "school"
    ],
    "wof:name":"Old Dominion University",
    "wof:placetype":"venue"
},
  "geometry": {"coordinates":[-77.779037,38.376506],"type":"Point"}
}