{
  "type": "Feature",
  "properties": {
    "iso:country":"US",
    "sg:address":"4475 Centerville Rd",
    "sg:city":"Williamsburg",
    "sg:classifiers":[
        {
            "category":"Building & Trades",
            "subcategory":"Construction",
            "type":"Services"
        }
    ],
    "sg:phone":"+1 757 258 9343",
    "sg:postcode":"23188",
    "sg:province":"VA",
    "sg:tags":[
        "house"
    ],
    "wof:name":"Hood & Son Home Improvements",
    "wof:placetype":"venue"
},
  "geometry": {"coordinates":[-76.801225,37.287254],"type":"Point"}
}