{
  "type": "Feature",
  "properties": {
    "addr:full":"44330 Mercure Cir Sterling VA 20166",
    "addr:postcode":"44330;20166",
    "addr:street":"Mercure Cir",
    "iso:country":"US",
    "sg:address":"44330 Mercure Cir",
    "sg:city":"Sterling",
    "sg:classifiers":[
        {
            "category":"Professional",
            "subcategory":"Engineering",
            "type":"Services"
        }
    ],
    "sg:phone":"+1 703 996 0125",
    "sg:postcode":"20166",
    "sg:province":"VA",
    "wof:name":"Granzow Structural Engineers P",
    "wof:placetype":"venue"
},
  "geometry": {"coordinates":[-77.473212,38.985697],"type":"Point"}
}