{
  "type": "Feature",
  "properties": {
    "iso:country":"US",
    "sg:address":"11117 Cutbank Church Rd",
    "sg:city":"Mc Kenney",
    "sg:phone":"+1 804 478 4936",
    "sg:postcode":"23872",
    "sg:province":"VA",
    "sg:tags":[
        "farm",
        "field",
        "crop"
    ],
    "wof:name":"David Dussere",
    "wof:placetype":"venue"
},
  "geometry": {"coordinates":[-77.709701,36.943704],"type":"Point"}
}