{
  "type": "Feature",
  "properties": {
    "addr:full":"44173 Paget Ter Ashburn VA 20147",
    "addr:housenumber":"44173",
    "addr:postcode":"20147",
    "addr:street":"Paget Ter",
    "iso:country":"US",
    "sg:address":"44173 Paget Ter",
    "sg:city":"Ashburn",
    "sg:classifiers":[
        {
            "category":"Professional",
            "subcategory":"Business Services",
            "type":"Services"
        }
    ],
    "sg:phone":"+1 703 689 1226",
    "sg:postcode":"20147",
    "sg:province":"VA",
    "wof:name":"Mayfair Sales Ofc",
    "wof:placetype":"venue"
},
  "geometry": {"coordinates":[-77.47371099999999,39.049696],"type":"Point"}
}