{
  "type": "Feature",
  "properties": {
    "addr:full":"1024 Delf Dr Mc Lean VA 22101",
    "addr:housenumber":"1024",
    "addr:postcode":"22101",
    "addr:street":"Delf Dr",
    "iso:country":"US",
    "sg:address":"1024 Delf Dr",
    "sg:city":"Mc Lean",
    "sg:classifiers":[
        {
            "category":"Professional",
            "subcategory":"Management & Consulting",
            "type":"Services"
        }
    ],
    "sg:phone":"+1 703 848 2682",
    "sg:postcode":"22101",
    "sg:province":"VA",
    "sg:tags":[
        "business"
    ],
    "wof:name":"Andriole Associates",
    "wof:placetype":"venue"
},
  "geometry": {"coordinates":[-77.198651,38.948381],"type":"Point"}
}