{
  "type": "Feature",
  "properties": {
    "addr:full":"1619 Princeton Rd Richmond VA 23227",
    "addr:housenumber":"1619",
    "addr:postcode":"23227",
    "addr:street":"Princeton Rd",
    "iso:country":"US",
    "sg:address":"1619 Princeton Rd",
    "sg:city":"Richmond",
    "sg:classifiers":[
        {
            "category":"Professional",
            "type":"Services"
        }
    ],
    "sg:phone":"+1 804 262 3726",
    "sg:postcode":"23227",
    "sg:province":"VA",
    "sg:tags":[
        "establishment"
    ],
    "wof:name":"Stankus JE",
    "wof:placetype":"venue"
},
  "geometry": {"coordinates":[-77.463953,37.593081],"type":"Point"}
}