{
  "type": "Feature",
  "properties": {
    "iso:country":"US",
    "sg:address":"130 Brooke Ave",
    "sg:city":"Norfolk",
    "sg:classifiers":[
        {
            "category":"Organizations",
            "subcategory":"Religious Organization",
            "type":"Services"
        }
    ],
    "sg:phone":"+1 757 627 8686",
    "sg:postcode":"23510",
    "sg:province":"VA",
    "sg:tags":[
        "church"
    ],
    "sg:website":"www.ummnorva.org",
    "wof:name":"Union Mission",
    "wof:placetype":"venue"
},
  "geometry": {"coordinates":[-76.292348,36.848973],"type":"Point"}
}