{
  "type": "Feature",
  "properties": {
    "addr:full":"129 Skyview Dr Fancy Gap VA 24328",
    "addr:housenumber":"129",
    "addr:postcode":"24328",
    "addr:street":"Skyview Dr",
    "iso:country":"US",
    "sg:address":"129 Skyview Dr",
    "sg:city":"Fancy Gap",
    "sg:classifiers":[
        {
            "category":"Organizations",
            "subcategory":"Religious Organization",
            "type":"Services"
        }
    ],
    "sg:phone":"+1 276 728 2211",
    "sg:postcode":"24328",
    "sg:province":"VA",
    "wof:name":"Skyview Baptist Church",
    "wof:placetype":"venue"
},
  "geometry": {"coordinates":[-80.683702,36.688036],"type":"Point"}
}