{
  "type": "Feature",
  "properties": {
    "addr:full":"9446 Main St Fairfax VA 22031",
    "addr:housenumber":"9446",
    "addr:postcode":"22031",
    "addr:street":"Main St",
    "iso:country":"US",
    "sg:address":"9446 Main St",
    "sg:city":"Fairfax",
    "sg:classifiers":[
        {
            "category":"Shopping",
            "subcategory":"Computers & Home Electronics",
            "type":"Retail Goods"
        }
    ],
    "sg:phone":"+1 703 426 2094",
    "sg:postcode":"22031",
    "sg:province":"VA",
    "wof:name":"Electronics Boutique",
    "wof:placetype":"venue"
},
  "geometry": {"coordinates":[-77.27136299999999,38.841172],"type":"Point"}
}