{
  "type": "Feature",
  "properties": {
    "addr:full":"4524 Melrose Ave NW Roanoke VA 24017",
    "addr:housenumber":"4524",
    "addr:postcode":"24017",
    "addr:street":"Melrose Ave Nw",
    "iso:country":"US",
    "sg:address":"4524 Melrose Ave NW",
    "sg:city":"Roanoke",
    "sg:classifiers":[
        {
            "category":"Autos & Motor Vehicles",
            "subcategory":"Automobile Sales",
            "type":"Retail Goods"
        }
    ],
    "sg:phone":"+1 540 986 3000",
    "sg:postcode":"24017",
    "sg:province":"VA",
    "sg:tags":[
        "truck"
    ],
    "wof:name":"Roanoke Truck Sales",
    "wof:placetype":"venue"
},
  "geometry": {"coordinates":[-80.011145,37.297566],"type":"Point"}
}