{
  "type": "Feature",
  "properties": {
    "addr:full":"4001 N 9th St Ste 108 Arlington VA 22203",
    "addr:housenumber":"4001",
    "addr:postcode":"22203",
    "addr:street":"N 9Th St Ste 108",
    "iso:country":"US",
    "sg:address":"4001 N 9th St Ste 108",
    "sg:city":"Arlington",
    "sg:classifiers":[
        {
            "category":"Sports & Exercise",
            "subcategory":"Gym",
            "type":"Entertainment"
        }
    ],
    "sg:phone":"+1 703 527 9626",
    "sg:postcode":"22203",
    "sg:province":"VA",
    "sg:tags":[
        "pilate"
    ],
    "sg:website":"www.studiobodylogic.com",
    "wof:name":"Studio Body Logic",
    "wof:placetype":"venue"
},
  "geometry": {"coordinates":[-77.108413,38.881474],"type":"Point"}
}