{
  "type": "Feature",
  "properties": {
    "addr:full":"17201 Liberty Hall Dr Glade Spring VA 24340",
    "addr:housenumber":"17201",
    "addr:postcode":"24340",
    "addr:street":"Liberty Hall Dr",
    "iso:country":"US",
    "sg:address":"17201 Liberty Hall Dr",
    "sg:city":"Glade Spring",
    "sg:classifiers":[
        {
            "category":"Government",
            "subcategory":"Office",
            "type":"Public Place"
        }
    ],
    "sg:phone":"+1 276 429 2614",
    "sg:postcode":"24340",
    "sg:province":"VA",
    "sg:tags":[
        "county",
        "program"
    ],
    "wof:name":"Washington County Solid Waste",
    "wof:placetype":"venue"
},
  "geometry": {"coordinates":[-81.78243500000001,36.710282],"type":"Point"}
}