{
  "type": "Feature",
  "properties": {
    "addr:full":"2701 S Oakland St Arlington VA 22206",
    "addr:housenumber":"2701",
    "addr:postcode":"22206",
    "addr:street":"S Oakland St",
    "iso:country":"US",
    "sg:address":"2701 S Oakland St",
    "sg:city":"Arlington",
    "sg:classifiers":[
        {
            "category":"Building & Trades",
            "subcategory":"Cleaning & Sanitation",
            "type":"Services"
        }
    ],
    "sg:phone":"+1 703 379 5006",
    "sg:postcode":"22206",
    "sg:province":"VA",
    "sg:tags":[
        "gutter",
        "residential",
        "contractor",
        "re",
        "window",
        "chimney"
    ],
    "sg:website":"www.winstonsservice.com",
    "wof:name":"Winston's Chimney Service",
    "wof:placetype":"venue"
},
  "geometry": {"coordinates":[-77.089372,38.843912],"type":"Point"}
}