{
  "type": "Feature",
  "properties": {
    "addr:full":"130 S Military Hwy Norfolk VA 23502",
    "addr:housenumber":"130",
    "addr:postcode":"23502",
    "addr:street":"S Military Hwy",
    "iso:country":"US",
    "sg:address":"130 S Military Hwy",
    "sg:city":"Norfolk",
    "sg:classifiers":[
        {
            "category":"Freight",
            "type":"Transportation"
        }
    ],
    "sg:phone":"+1 757 461 8888",
    "sg:postcode":"23502",
    "sg:province":"VA",
    "sg:tags":[
        "mover"
    ],
    "wof:name":"Dun Mar Moving Systems",
    "wof:placetype":"venue"
},
  "geometry": {"coordinates":[-76.210049,36.841459],"type":"Point"}
}