{
  "type": "Feature",
  "properties": {
    "addr:full":"307 Main St Newport News VA 23601",
    "addr:housenumber":"307",
    "addr:postcode":"23601",
    "addr:street":"Main St",
    "iso:country":"US",
    "sg:address":"307 Main St",
    "sg:city":"Newport News",
    "sg:classifiers":[
        {
            "category":"Recreation",
            "type":"Entertainment"
        }
    ],
    "sg:phone":"+1 757 599 4769",
    "sg:postcode":"23601",
    "sg:province":"VA",
    "sg:tags":[
        "amusement"
    ],
    "wof:name":"Peninsula Family Skating Ctr",
    "wof:placetype":"venue"
},
  "geometry": {"coordinates":[-76.45556999999999,37.036867],"type":"Point"}
}