{
  "type": "Feature",
  "properties": {
    "addr:full":"3 Boars Head Pl Charlottesville VA 22903",
    "addr:housenumber":"3",
    "addr:postcode":"22903",
    "addr:street":"Boars Head Pl",
    "iso:country":"US",
    "sg:address":"3 Boars Head Pl",
    "sg:city":"Charlottesville",
    "sg:classifiers":[
        {
            "category":"Professional",
            "subcategory":"Advertising",
            "type":"Services"
        }
    ],
    "sg:phone":"+1 434 977 0239",
    "sg:postcode":"22903",
    "sg:province":"VA",
    "wof:name":"Viacom Sports Marketing LLC",
    "wof:placetype":"venue"
},
  "geometry": {"coordinates":[-78.53923899999999,38.047906],"type":"Point"}
}