{
  "type": "Feature",
  "properties": {
    "iso:country":"US",
    "sg:address":"2526 Wingfield Rd",
    "sg:city":"Norfolk",
    "sg:classifiers":[
        {
            "category":"Real Estate",
            "subcategory":"Real Estate Agent",
            "type":"Services"
        }
    ],
    "sg:phone":"+1 757 587 1590",
    "sg:postcode":"23518",
    "sg:province":"VA",
    "wof:name":"Har-Wood Properties Inc",
    "wof:placetype":"venue"
},
  "geometry": {"coordinates":[-76.20429900000001,36.908016],"type":"Point"}
}