{
  "type": "Feature",
  "properties": {
    "iso:country":"US",
    "sg:address":"198 Mattox Ave",
    "sg:city":"Colonial Beach",
    "sg:classifiers":[
        {
            "category":"Building & Trades",
            "subcategory":"Construction",
            "type":"Services"
        }
    ],
    "sg:phone":"+1 804 224 0880",
    "sg:postcode":"22443",
    "sg:province":"VA",
    "sg:tags":[
        "house"
    ],
    "wof:name":"Bayview Developers Inc",
    "wof:placetype":"venue"
},
  "geometry": {"coordinates":[-76.987154,38.200107],"type":"Point"}
}