{
  "type": "Feature",
  "properties": {
    "iso:country":"US",
    "sg:address":"5900 Fort Ave",
    "sg:city":"Lynchburg",
    "sg:classifiers":[
        {
            "category":"Home & Garden",
            "subcategory":"Carpets & Floor Coverings",
            "type":"Retail Goods"
        }
    ],
    "sg:phone":"+1 434 239 6944",
    "sg:postcode":"24502",
    "sg:province":"VA",
    "sg:tags":[
        "installs",
        "vinyl",
        "flooring"
    ],
    "wof:name":"Carpet Shop Of Lynchburg Inc",
    "wof:placetype":"venue"
},
  "geometry": {"coordinates":[-79.19449899999999,37.372025],"type":"Point"}
}