{
  "type": "Feature",
  "properties": {
    "addr:full":"28 Main St Brodnax VA 23920",
    "addr:housenumber":"28",
    "addr:postcode":"23920",
    "addr:street":"Main St",
    "iso:country":"US",
    "sg:address":"28 Main St",
    "sg:city":"Brodnax",
    "sg:classifiers":[
        {
            "category":"Government",
            "subcategory":"Office",
            "type":"Public Place"
        }
    ],
    "sg:phone":"+1 434 729 3191",
    "sg:postcode":"23920",
    "sg:province":"VA",
    "sg:tags":[
        "village"
    ],
    "wof:name":"Town Of Brodnax",
    "wof:placetype":"venue"
},
  "geometry": {"coordinates":[-78.031898,36.706305],"type":"Point"}
}