{
  "type": "Feature",
  "properties": {
    "addr:full":"1700 Altamont Ave Richmond VA 23230",
    "addr:housenumber":"1700",
    "addr:postcode":"23230",
    "addr:street":"Altamont Ave",
    "iso:country":"US",
    "sg:address":"1700 Altamont Ave",
    "sg:city":"Richmond",
    "sg:classifiers":[
        {
            "category":"Wholesale",
            "subcategory":"Machinery & Supplies",
            "type":"Manufacturing & Wholesale Goods"
        }
    ],
    "sg:phone":"+1 804 358 0534",
    "sg:postcode":"23230",
    "sg:province":"VA",
    "sg:tags":[
        "abrasive"
    ],
    "wof:name":"CAP Coated Abrasive Products",
    "wof:placetype":"venue"
},
  "geometry": {"coordinates":[-77.46685600000001,37.569317],"type":"Point"}
}