{
  "type": "Feature",
  "properties": {
    "addr:full":"1017 W Main St Danville VA 24541",
    "addr:housenumber":"1017",
    "addr:postcode":"24541",
    "addr:street":"W Main St",
    "iso:country":"US",
    "sg:address":"1017 W Main St",
    "sg:city":"Danville",
    "sg:classifiers":[
        {
            "category":"Banks & Credit Unions",
            "subcategory":"Bank",
            "type":"Services"
        }
    ],
    "sg:phone":"+1 434 792 6621",
    "sg:postcode":"24541",
    "sg:province":"VA",
    "sg:tags":[
        "state"
    ],
    "wof:name":"First Virginia Bnk - Southwest",
    "wof:placetype":"venue"
},
  "geometry": {"coordinates":[-79.42978100000001,36.568026],"type":"Point"}
}