{
  "type": "Feature",
  "properties": {
    "addr:full":"21620 Ridgetop Cir Sterling VA 20166",
    "addr:housenumber":"21620",
    "addr:postcode":"20166",
    "addr:street":"Ridgetop Cir",
    "iso:country":"US",
    "sg:address":"21620 Ridgetop Cir",
    "sg:city":"Sterling",
    "sg:classifiers":[
        {
            "category":"Manufacturing",
            "subcategory":"Toys & Sporting Goods",
            "type":"Manufacturing & Wholesale Goods"
        }
    ],
    "sg:phone":"+1 703 433 2540",
    "sg:postcode":"20166",
    "sg:province":"VA",
    "sg:tags":[
        "mfg"
    ],
    "sg:website":"http://www.drmatchett.com",
    "wof:name":"Capitol Rehab",
    "wof:placetype":"venue"
},
  "geometry": {"coordinates":[-77.407112,39.027533],"type":"Point"}
}