{
  "type": "Feature",
  "properties": {
    "addr:full":"2500 Pump Rd Richmond VA 23233",
    "addr:housenumber":"2500",
    "addr:postcode":"23233",
    "addr:street":"Pump Rd",
    "iso:country":"US",
    "sg:address":"2500 Pump Rd",
    "sg:city":"Richmond",
    "sg:classifiers":[
        {
            "category":"Organizations",
            "subcategory":"Religious Organization",
            "type":"Services"
        }
    ],
    "sg:phone":"+1 804 740 7154",
    "sg:postcode":"23233",
    "sg:province":"VA",
    "sg:tags":[
        "church"
    ],
    "wof:name":"Richmond Va FM Group",
    "wof:placetype":"venue"
},
  "geometry": {"coordinates":[-77.610214,37.6307],"type":"Point"}
}