{
  "type": "Feature",
  "properties": {
    "addr:full":"8300 Sudley Rd Ste K19 Manassas VA 20109",
    "addr:housenumber":"8300",
    "addr:postcode":"20109",
    "addr:street":"Sudley Rd Ste K19",
    "iso:country":"US",
    "sg:address":"8300 Sudley Rd Ste K19",
    "sg:city":"Manassas",
    "sg:classifiers":[
        {
            "category":"Shopping",
            "subcategory":"Beauty & Cosmetics",
            "type":"Retail Goods"
        }
    ],
    "sg:phone":"+1 703 369 1102",
    "sg:postcode":"20109",
    "sg:province":"VA",
    "sg:tags":[
        "equipment",
        "perfume",
        "supply"
    ],
    "wof:name":"Merle Norman Cosmetics",
    "wof:placetype":"venue"
},
  "geometry": {"coordinates":[-77.502818,38.774966],"type":"Point"}
}