{
  "type": "Feature",
  "properties": {
    "iso:country":"US",
    "sg:address":"2420 North Kenmore St",
    "sg:city":"Arlington",
    "sg:classifiers":[
        {
            "category":"Park",
            "type":"Public Place"
        },
        {
            "category":"Recreation",
            "type":"Entertainment"
        }
    ],
    "sg:postcode":"22207",
    "sg:province":"VA",
    "sg:tags":[
        "hiking"
    ],
    "sg:website":"www.arlingtonva.us/Departments/P...",
    "wof:name":"Windy Run Park",
    "wof:placetype":"venue"
},
  "geometry": {"coordinates":[-77.09936999999999,38.901553],"type":"Point"}
}