{
  "type": "Feature",
  "properties": {
    "addr:full":"404 Count Fleet Cir Virginia Beach VA 23462",
    "addr:housenumber":"404",
    "addr:postcode":"23462",
    "addr:street":"Count Fleet Cir",
    "iso:country":"US",
    "sg:address":"404 Count Fleet Cir",
    "sg:city":"Virginia Beach",
    "sg:classifiers":[
        {
            "category":"Professional",
            "type":"Services"
        }
    ],
    "sg:phone":"+1 757 497 5232",
    "sg:postcode":"23462",
    "sg:province":"VA",
    "wof:name":"Upwrdcom",
    "wof:placetype":"venue"
},
  "geometry": {"coordinates":[-76.176174,36.824867],"type":"Point"}
}