{
  "type": "Feature",
  "properties": {
    "iso:country":"US",
    "sg:address":"7313 Beverly Park Dr",
    "sg:city":"Springfield",
    "sg:classifiers":[
        {
            "category":"Professional",
            "subcategory":"Business Services",
            "type":"Services"
        },
        {
            "category":"Professional",
            "subcategory":"Management & Consulting",
            "type":"Services"
        }
    ],
    "sg:phone":"+1 703 451 9669",
    "sg:postcode":"22150",
    "sg:province":"VA",
    "sg:tags":[
        "consultant"
    ],
    "wof:name":"Triton Consulting Group Inc",
    "wof:placetype":"venue"
},
  "geometry": {"coordinates":[-77.190917,38.759942],"type":"Point"}
}