{
  "type": "Feature",
  "properties": {
    "iso:country":"US",
    "sg:address":"2206 E Indian River Rd",
    "sg:city":"Norfolk",
    "sg:classifiers":[
        {
            "category":"Banks & Credit Unions",
            "subcategory":"Bank",
            "type":"Services"
        }
    ],
    "sg:phone":"+1 757 545 1053",
    "sg:postcode":"23523",
    "sg:province":"VA",
    "sg:tags":[
        "financing"
    ],
    "wof:name":"C S Parker & Assoc",
    "wof:placetype":"venue"
},
  "geometry": {"coordinates":[-76.255644,36.831219],"type":"Point"}
}