{
  "type": "Feature",
  "properties": {
    "addr:full":"104 Park Hill Ct Sterling VA 20164",
    "addr:housenumber":"104",
    "addr:postcode":"20164",
    "addr:street":"Park Hill Ct",
    "iso:country":"US",
    "sg:address":"104 Park Hill Ct",
    "sg:city":"Sterling",
    "sg:classifiers":[
        {
            "category":"Retail",
            "subcategory":"Repair Shop",
            "type":"Services"
        }
    ],
    "sg:phone":"+1 703 421 7660",
    "sg:postcode":"20164",
    "sg:province":"VA",
    "wof:name":"Potomac Power Washing",
    "wof:placetype":"venue"
},
  "geometry": {"coordinates":[-77.37626299999999,39.032253],"type":"Point"}
}