{
  "type": "Feature",
  "properties": {
    "addr:full":"9607 Warwick Blvd Newport News VA 23601",
    "addr:housenumber":"9607",
    "addr:postcode":"23601",
    "addr:street":"Warwick Blvd",
    "iso:country":"US",
    "sg:address":"9607 Warwick Blvd",
    "sg:city":"Newport News",
    "sg:classifiers":[
        {
            "category":"Restaurant",
            "type":"Food & Drink"
        }
    ],
    "sg:phone":"+1 757 595 2151",
    "sg:postcode":"23601",
    "sg:province":"VA",
    "sg:tags":[
        "eating"
    ],
    "wof:name":"Monty's Restaurant",
    "wof:placetype":"venue"
},
  "geometry": {"coordinates":[-76.455257,37.025334],"type":"Point"}
}