{
  "type": "Feature",
  "properties": {
    "addr:full":"7207 Lockport Pl Lorton VA 22079",
    "addr:housenumber":"7207",
    "addr:postcode":"22079",
    "addr:street":"Lockport Pl",
    "iso:country":"US",
    "sg:address":"7207 Lockport Pl",
    "sg:city":"Lorton",
    "sg:classifiers":[
        {
            "category":"Manufacturing",
            "subcategory":"Glass & Minerals",
            "type":"Manufacturing & Wholesale Goods"
        }
    ],
    "sg:phone":"+1 703 550 7333",
    "sg:postcode":"22079",
    "sg:province":"VA",
    "sg:tags":[
        "mfg",
        "tack",
        "boards",
        "install",
        "chalkboard"
    ],
    "wof:name":"Polyvision Corporation",
    "wof:placetype":"venue"
},
  "geometry": {"coordinates":[-77.193837,38.715035],"type":"Point"}
}