{
  "type": "Feature",
  "properties": {
    "addr:full":"6770 Richmond Hwy Alexandria VA 22306",
    "addr:housenumber":"6770",
    "addr:postcode":"22306",
    "addr:street":"Richmond Hwy",
    "iso:country":"US",
    "sg:address":"6770 Richmond Hwy",
    "sg:city":"Alexandria",
    "sg:phone":"+1 703 660 9214",
    "sg:postcode":"22306",
    "sg:province":"VA",
    "sg:website":"http://www.chipolte.com",
    "wof:name":"Chipotle",
    "wof:placetype":"venue"
},
  "geometry": {"coordinates":[-77.08138099999999,38.771043],"type":"Point"}
}