{
  "type": "Feature",
  "properties": {
    "iso:country":"US",
    "sg:address":"740 Radford St",
    "sg:city":"Christiansburg",
    "sg:classifiers":[
        {
            "category":"Autos & Motor Vehicles",
            "subcategory":"Automobile Sales",
            "type":"Retail Goods"
        }
    ],
    "sg:phone":"+1 540 381 1881",
    "sg:postcode":"24073",
    "sg:province":"VA",
    "sg:tags":[
        "car",
        "used",
        "dealer"
    ],
    "wof:name":"G G E Auto Sales",
    "wof:placetype":"venue"
},
  "geometry": {"coordinates":[-80.422603,37.127494],"type":"Point"}
}