{
  "type": "Feature",
  "properties": {
    "addr:full":"110 New River Rd Christiansburg VA 24073",
    "addr:housenumber":"110",
    "addr:postcode":"24073",
    "addr:street":"New River Rd",
    "iso:country":"US",
    "sg:address":"110 New River Rd",
    "sg:city":"Christiansburg",
    "sg:phone":"+1 540 381 0854",
    "sg:postcode":"24073",
    "sg:province":"VA",
    "sg:website":"http://www.regmovies.com/",
    "wof:name":"Regal Cinema",
    "wof:placetype":"venue"
},
  "geometry": {"coordinates":[-80.42749999999999,37.163295],"type":"Point"}
}