{
  "type": "Feature",
  "properties": {
    "iso:country":"US",
    "sg:address":"10905 Shadow Ln",
    "sg:city":"Fairfax Station",
    "sg:classifiers":[
        {
            "category":"Building & Trades",
            "subcategory":"Construction",
            "type":"Services"
        }
    ],
    "sg:phone":"+1 703 239 8606",
    "sg:postcode":"22039",
    "sg:province":"VA",
    "sg:tags":[
        "tile",
        "dealer"
    ],
    "wof:name":"Brennan Tile Inc",
    "wof:placetype":"venue"
},
  "geometry": {"coordinates":[-77.324916,38.734921],"type":"Point"}
}