{
  "type": "Feature",
  "properties": {
    "iso:country":"US",
    "sg:address":"5253 S Laburnum Ave",
    "sg:city":"Richmond",
    "sg:classifiers":[
        {
            "category":"Shopping",
            "subcategory":"Gifts & Souvenirs",
            "type":"Retail Goods"
        }
    ],
    "sg:phone":"+1 804 222 9334",
    "sg:postcode":"23231",
    "sg:province":"VA",
    "sg:tags":[
        "shop"
    ],
    "wof:name":"Country Keepsakes LTD",
    "wof:placetype":"venue"
},
  "geometry": {"coordinates":[-77.349445,37.512025],"type":"Point"}
}