{
  "type": "Feature",
  "properties": {
    "addr:full":"8523 Oak Chase Cir Fairfax Station VA 22039",
    "addr:housenumber":"8523",
    "addr:postcode":"22039",
    "addr:street":"Oak Chase Cir Fairfax",
    "iso:country":"US",
    "sg:address":"8523 Oak Chase Cir",
    "sg:city":"Fairfax Station",
    "sg:classifiers":[
        {
            "category":"Professional",
            "subcategory":"Lawyer & Legal Services",
            "type":"Services"
        }
    ],
    "sg:phone":"+1 703 969 1177",
    "sg:postcode":"22039",
    "sg:province":"VA",
    "wof:name":"Kissinger Counsultants",
    "wof:placetype":"venue"
},
  "geometry": {"coordinates":[-77.26117499999999,38.725405],"type":"Point"}
}