{
  "type": "Feature",
  "properties": {
    "addr:full":"2709 Campostella Rd Chesapeake VA 23324",
    "addr:housenumber":"2709",
    "addr:postcode":"23324",
    "addr:street":"Campostella Rd",
    "iso:country":"US",
    "sg:address":"2709 Campostella Rd",
    "sg:city":"Chesapeake",
    "sg:classifiers":[
        {
            "category":"Organizations",
            "subcategory":"Religious Organization",
            "type":"Services"
        }
    ],
    "sg:phone":"+1 757 543 2440",
    "sg:postcode":"23324",
    "sg:province":"VA",
    "sg:tags":[
        "church"
    ],
    "wof:name":"Faith House-Deliverance",
    "wof:placetype":"venue"
},
  "geometry": {"coordinates":[-76.25979100000001,36.814612],"type":"Point"}
}