{
  "type": "Feature",
  "properties": {
    "addr:full":"125 S Augusta St Staunton VA 24401",
    "addr:housenumber":"125",
    "addr:postcode":"24401",
    "addr:street":"S Augusta St",
    "iso:country":"US",
    "sg:address":"125 S Augusta St",
    "sg:city":"Staunton",
    "sg:classifiers":[
        {
            "category":"Professional",
            "subcategory":"Lawyer & Legal Services",
            "type":"Services"
        }
    ],
    "sg:phone":"+1 540 885 0199",
    "sg:postcode":"24401",
    "sg:province":"VA",
    "sg:tags":[
        "attorney"
    ],
    "wof:name":"Wharton Aldhizer & Weaver",
    "wof:placetype":"venue"
},
  "geometry": {"coordinates":[-79.07238099999999,38.148421],"type":"Point"}
}