{
  "type": "Feature",
  "properties": {
    "addr:full":"127 Danville Ave Colonial Heights VA 23834",
    "addr:housenumber":"127",
    "addr:postcode":"23834",
    "addr:street":"Danville Ave",
    "iso:country":"US",
    "sg:address":"127 Danville Ave",
    "sg:city":"Colonial Heights",
    "sg:classifiers":[
        {
            "category":"Wholesale",
            "subcategory":"Jewelry",
            "type":"Manufacturing & Wholesale Goods"
        }
    ],
    "sg:phone":"+1 804 526 0870",
    "sg:postcode":"23834",
    "sg:province":"VA",
    "sg:tags":[
        "real",
        "stone",
        "jeweler"
    ],
    "wof:name":"Landmark Associates Inc",
    "wof:placetype":"venue"
},
  "geometry": {"coordinates":[-77.408789,37.246589],"type":"Point"}
}