{
  "type": "Feature",
  "properties": {
    "addr:full":"5315 George Washington Memorial Hwy Grafton VA 23692",
    "addr:housenumber":"5315",
    "addr:postcode":"23692",
    "addr:street":"George Washington Memorial Hwy",
    "iso:country":"US",
    "sg:address":"5315 George Washington Memorial Hwy",
    "sg:city":"Grafton",
    "sg:classifiers":[
        {
            "category":"Education",
            "subcategory":"Dance Studio",
            "type":"Public Place"
        }
    ],
    "sg:phone":"+1 757 898 7619",
    "sg:postcode":"23692",
    "sg:province":"VA",
    "sg:tags":[
        "instruction",
        "dancing"
    ],
    "wof:name":"Margie Williams Studio Of Dnc",
    "wof:placetype":"venue"
},
  "geometry": {"coordinates":[-76.463283,37.15897],"type":"Point"}
}