{
  "type": "Feature",
  "properties": {
    "addr:full":"5019 Wilson Blvd Arlington VA 22203",
    "addr:housenumber":"5019",
    "addr:postcode":"22203",
    "addr:street":"Wilson Blvd",
    "iso:country":"US",
    "sg:address":"5019 Wilson Blvd",
    "sg:city":"Arlington",
    "sg:classifiers":[
        {
            "category":"Restaurant",
            "type":"Food & Drink"
        }
    ],
    "sg:phone":"+1 703 525 6889",
    "sg:postcode":"22203",
    "sg:province":"VA",
    "sg:tags":[
        "pizza"
    ],
    "wof:name":"Two Chefs Pizza",
    "wof:placetype":"venue"
},
  "geometry": {"coordinates":[-77.121803,38.877899],"type":"Point"}
}