{
  "type": "Feature",
  "properties": {
    "addr:full":"2600 Crystal Dr Apt 218 Arlington VA 22202",
    "addr:housenumber":"2600;218",
    "addr:postcode":"22202",
    "addr:street":"Crystal Dr Apt",
    "iso:country":"US",
    "sg:address":"2600 Crystal Dr Apt 218",
    "sg:city":"Arlington",
    "sg:classifiers":[
        {
            "category":"Real Estate",
            "subcategory":"Developer",
            "type":"Services"
        }
    ],
    "sg:phone":"+1 703 671 7505",
    "sg:postcode":"22202",
    "sg:province":"VA",
    "sg:website":"http://www.crystalquarters.com",
    "wof:name":"Crystal Quarters at Water Park",
    "wof:placetype":"venue"
},
  "geometry": {"coordinates":[-77.050652,38.849899],"type":"Point"}
}