{
  "type": "Feature",
  "properties": {
    "iso:country":"US",
    "sg:address":"109 Waterton",
    "sg:city":"Williamsburg",
    "sg:classifiers":[
        {
            "category":"Building & Trades",
            "subcategory":"Construction",
            "type":"Services"
        }
    ],
    "sg:phone":"+1 757 229 6092",
    "sg:postcode":"23188",
    "sg:province":"VA",
    "sg:tags":[
        "siding",
        "contractor"
    ],
    "sg:website":"www.perkins-construction.com",
    "wof:name":"Perkins Construction Co",
    "wof:placetype":"venue"
},
  "geometry": {"coordinates":[-76.793387,37.301639],"type":"Point"}
}