{
  "type": "Feature",
  "properties": {
    "iso:country":"US",
    "sg:address":"2831 Park Center Dr",
    "sg:city":"Alexandria",
    "sg:classifiers":[
        {
            "category":"Mining & Drilling",
            "type":"Manufacturing & Wholesale Goods"
        }
    ],
    "sg:phone":"+1 703 820 3533",
    "sg:postcode":"22302",
    "sg:province":"VA",
    "sg:tags":[
        "ore",
        "gold"
    ],
    "wof:name":"Invest Africa LLC",
    "wof:placetype":"venue"
},
  "geometry": {"coordinates":[-77.103556,38.835862],"type":"Point"}
}