{
  "type": "Feature",
  "properties": {
    "iso:country":"US",
    "sg:address":"2289 River Rd",
    "sg:city":"Stanley",
    "sg:classifiers":[
        {
            "category":"Farming",
            "subcategory":"Poultry Farm",
            "type":"Manufacturing & Wholesale Goods"
        }
    ],
    "sg:phone":"+1 540 778 2783",
    "sg:postcode":"22851",
    "sg:province":"VA",
    "sg:tags":[
        "chicken"
    ],
    "wof:name":"Dovel Farms",
    "wof:placetype":"venue"
},
  "geometry": {"coordinates":[-78.56780999999999,38.560623],"type":"Point"}
}