{
  "type": "Feature",
  "properties": {
    "iso:country":"US",
    "sg:address":"13919 Bayport Landing Rd",
    "sg:city":"Midlothian",
    "sg:classifiers":[
        {
            "category":"Building & Trades",
            "subcategory":"Construction",
            "type":"Services"
        }
    ],
    "sg:phone":"+1 804 739 1674",
    "sg:postcode":"23112",
    "sg:province":"VA",
    "sg:tags":[
        "general",
        "contractor"
    ],
    "wof:name":"Jame G Walters",
    "wof:placetype":"venue"
},
  "geometry": {"coordinates":[-77.666664,37.412315],"type":"Point"}
}