{
  "type": "Feature",
  "properties": {
    "addr:full":"1809 Ruffin Rd Richmond VA 23234",
    "addr:housenumber":"1809",
    "addr:postcode":"23234",
    "addr:street":"Ruffin Rd",
    "iso:country":"US",
    "sg:address":"1809 Ruffin Rd",
    "sg:city":"Richmond",
    "sg:classifiers":[
        {
            "category":"Organizations",
            "subcategory":"Religious Organization",
            "type":"Services"
        }
    ],
    "sg:phone":"+1 804 231 2400",
    "sg:postcode":"23234",
    "sg:province":"VA",
    "wof:name":"Our Daily Bread Ministries",
    "wof:placetype":"venue"
},
  "geometry": {"coordinates":[-77.433134,37.479782],"type":"Point"}
}