{
  "type": "Feature",
  "properties": {
    "addr:full":"2211 Dickens Rd Suite 102 Richmond VA 23230",
    "addr:housenumber":"2211",
    "addr:postcode":"23230",
    "addr:street":"Dickens Rd Suite 102",
    "iso:country":"US",
    "sg:address":"2211 Dickens Rd Suite 102",
    "sg:city":"Richmond",
    "sg:classifiers":[
        {
            "category":"Building & Trades",
            "subcategory":"Construction",
            "type":"Services"
        }
    ],
    "sg:phone":"+1 804 261 9396",
    "sg:postcode":"23230",
    "sg:province":"VA",
    "sg:tags":[
        "equipment",
        "supply",
        "drywall",
        "contractor"
    ],
    "sg:website":"http://www.cookesdrywall.com",
    "wof:name":"Cooke's Drywall Inc",
    "wof:placetype":"venue"
},
  "geometry": {"coordinates":[-77.5107,37.60062],"type":"Point"}
}