{
  "type": "Feature",
  "properties": {
    "iso:country":"US",
    "sg:address":"2401 Lamberts Ave",
    "sg:city":"Richmond",
    "sg:classifiers":[
        {
            "category":"Autos & Motor Vehicles",
            "subcategory":"Automobile Sales",
            "type":"Retail Goods"
        }
    ],
    "sg:phone":"+1 804 270 7215",
    "sg:postcode":"23234",
    "sg:province":"VA",
    "sg:tags":[
        "car",
        "dealer"
    ],
    "wof:name":"Layne's Used Cars Inc",
    "wof:placetype":"venue"
},
  "geometry": {"coordinates":[-77.440727,37.476504],"type":"Point"}
}