{
  "type": "Feature",
  "properties": {
    "addr:full":"206 9th St NW Roanoke VA 24016",
    "addr:housenumber":"206",
    "addr:postcode":"24016",
    "addr:street":"9Th St Nw",
    "iso:country":"US",
    "sg:address":"206 9th St NW",
    "sg:city":"Roanoke",
    "sg:classifiers":[
        {
            "category":"Social Services",
            "subcategory":"Child Care",
            "type":"Services"
        }
    ],
    "sg:phone":"+1 540 342 9491",
    "sg:postcode":"24016",
    "sg:province":"VA",
    "sg:tags":[
        "day"
    ],
    "wof:name":"Tap",
    "wof:placetype":"venue"
},
  "geometry": {"coordinates":[-79.95455200000001,37.277542],"type":"Point"}
}