{
  "type": "Feature",
  "properties": {
    "addr:full":"7122 Forest Hill Ave Richmond VA 23225",
    "addr:housenumber":"7122",
    "addr:postcode":"23225",
    "addr:street":"Forest Hill Ave",
    "iso:country":"US",
    "sg:address":"7122 Forest Hill Ave",
    "sg:city":"Richmond",
    "sg:classifiers":[
        {
            "category":"Building & Trades",
            "subcategory":"Construction",
            "type":"Services"
        }
    ],
    "sg:phone":"+1 804 320 6775",
    "sg:postcode":"23225",
    "sg:province":"VA",
    "sg:tags":[
        "house",
        "industrial"
    ],
    "wof:name":"Virginia Window & Rmdlg Co",
    "wof:placetype":"venue"
},
  "geometry": {"coordinates":[-77.52480300000001,37.537919],"type":"Point"}
}