{
  "type": "Feature",
  "properties": {
    "iso:country":"US",
    "sg:address":"2211 Leeland Dr",
    "sg:city":"Falls Church",
    "sg:classifiers":[
        {
            "category":"Retail",
            "subcategory":"Repair Shop",
            "type":"Services"
        }
    ],
    "sg:phone":"+1 703 538 5464",
    "sg:postcode":"22043",
    "sg:province":"VA",
    "wof:name":"Virginia Floors",
    "wof:placetype":"venue"
},
  "geometry": {"coordinates":[-77.16506800000001,38.900753],"type":"Point"}
}