{
  "type": "Feature",
  "properties": {
    "iso:country":"US",
    "sg:address":"7805 Halyard Ter",
    "sg:city":"Chesterfield",
    "sg:classifiers":[
        {
            "category":"Autos & Motor Vehicles",
            "subcategory":"Automobile Sales",
            "type":"Retail Goods"
        }
    ],
    "sg:phone":"+1 804 230 0826",
    "sg:postcode":"23832",
    "sg:province":"VA",
    "sg:tags":[
        "car",
        "dealer"
    ],
    "wof:name":"Christian Touch Auto Sales Inc",
    "wof:placetype":"venue"
},
  "geometry": {"coordinates":[-77.683513,37.393005],"type":"Point"}
}