{
  "type": "Feature",
  "properties": {
    "iso:country":"US",
    "sg:address":"1805 International Dr",
    "sg:city":"Mc Lean",
    "sg:classifiers":[
        {
            "category":"Shopping",
            "subcategory":"Used Merchandise",
            "type":"Retail Goods"
        }
    ],
    "sg:phone":"+1 703 734 5380",
    "sg:postcode":"22102",
    "sg:province":"VA",
    "wof:name":"HM Designs & Antiques LLC",
    "wof:placetype":"venue"
},
  "geometry": {"coordinates":[-77.22734,38.92459],"type":"Point"}
}