{
  "type": "Feature",
  "properties": {
    "addr:full":"18 Carillon Rd Luray VA 22835",
    "addr:housenumber":"18",
    "addr:postcode":"22835",
    "addr:street":"Carillon Rd",
    "iso:country":"US",
    "sg:address":"18 Carillon Rd",
    "sg:city":"Luray",
    "sg:classifiers":[
        {
            "category":"Organizations",
            "subcategory":"Religious Organization",
            "type":"Services"
        }
    ],
    "sg:phone":"+1 540 743 9452",
    "sg:postcode":"22835",
    "sg:province":"VA",
    "wof:name":"Bethel Baptist Church",
    "wof:placetype":"venue"
},
  "geometry": {"coordinates":[-78.476382,38.664056],"type":"Point"}
}