{
  "type": "Feature",
  "properties": {
    "addr:full":"127 E Washington St Suffolk VA 23434",
    "addr:housenumber":"127",
    "addr:postcode":"23434",
    "addr:street":"E Washington St",
    "iso:country":"US",
    "sg:address":"127 E Washington St",
    "sg:city":"Suffolk",
    "sg:classifiers":[
        {
            "category":"Government",
            "subcategory":"Office",
            "type":"Public Place"
        }
    ],
    "sg:phone":"+1 757 923 3620",
    "sg:postcode":"23434",
    "sg:province":"VA",
    "sg:tags":[
        "village"
    ],
    "wof:name":"Suffolk Industrial Dev Auth",
    "wof:placetype":"venue"
},
  "geometry": {"coordinates":[-76.582703,36.727903],"type":"Point"}
}