{
  "type": "Feature",
  "properties": {
    "iso:country":"US",
    "sg:address":"9274 Old Keene Mill Rd",
    "sg:city":"Burke",
    "sg:classifiers":[
        {
            "category":"Food & Beverages",
            "subcategory":"Groceries & Convenience Stores",
            "type":"Retail Goods"
        }
    ],
    "sg:phone":"+1 703 451 8514",
    "sg:postcode":"22015",
    "sg:province":"VA",
    "sg:tags":[
        "grocer"
    ],
    "wof:name":"Shoppers Food Warehouse MD",
    "wof:placetype":"venue"
},
  "geometry": {"coordinates":[-77.26312799999999,38.775063],"type":"Point"}
}