{
  "type": "Feature",
  "properties": {
    "iso:country":"US",
    "sg:address":"509 Greencastle Ln",
    "sg:city":"Virginia Beach",
    "sg:classifiers":[
        {
            "category":"Professional",
            "type":"Services"
        }
    ],
    "sg:phone":"+1 757 340 5607",
    "sg:postcode":"23452",
    "sg:province":"VA",
    "wof:name":"C B Arnett",
    "wof:placetype":"venue"
},
  "geometry": {"coordinates":[-76.11093,36.849189],"type":"Point"}
}