{
  "type": "Feature",
  "properties": {
    "addr:full":"123 N Main St Amherst VA 24521",
    "addr:housenumber":"123",
    "addr:postcode":"24521",
    "addr:street":"N Main St",
    "iso:country":"US",
    "sg:address":"123 N Main St",
    "sg:city":"Amherst",
    "sg:classifiers":[
        {
            "category":"Insurance",
            "subcategory":"Insurance Agent",
            "type":"Services"
        }
    ],
    "sg:phone":"+1 434 946 7447",
    "sg:postcode":"24521",
    "sg:province":"VA",
    "wof:name":"Farmers Insurance",
    "wof:placetype":"venue"
},
  "geometry": {"coordinates":[-79.048941,37.588478],"type":"Point"}
}