{
  "type": "Feature",
  "properties": {
    "addr:full":"1270 Credle Rd Virginia Beach VA 23454",
    "addr:housenumber":"1270",
    "addr:postcode":"23454",
    "addr:street":"Credle Rd",
    "iso:country":"US",
    "sg:address":"1270 Credle Rd",
    "sg:city":"Virginia Beach",
    "sg:classifiers":[
        {
            "category":"Freight",
            "type":"Transportation"
        }
    ],
    "sg:phone":"+1 757 491 0317",
    "sg:postcode":"23454",
    "sg:province":"VA",
    "sg:tags":[
        "special"
    ],
    "wof:name":"Atlantis Self Storage",
    "wof:placetype":"venue"
},
  "geometry": {"coordinates":[-76.00659,36.820675],"type":"Point"}
}