{
  "type": "Feature",
  "properties": {
    "addr:full":"3640 High St Ste 1D Portsmouth VA 23707",
    "addr:housenumber":"3640",
    "addr:postcode":"23707",
    "addr:street":"High St Ste 1D",
    "iso:country":"US",
    "sg:address":"3640 High St Ste 1D",
    "sg:city":"Portsmouth",
    "sg:classifiers":[
        {
            "category":"Health Services",
            "subcategory":"Podiatrist",
            "type":"Services"
        }
    ],
    "sg:phone":"+1 757 393 1074",
    "sg:postcode":"23707",
    "sg:province":"VA",
    "sg:tags":[
        "physician",
        "surgeons"
    ],
    "wof:name":"Portsmuth Foot Ankle Spcilists",
    "wof:placetype":"venue"
},
  "geometry": {"coordinates":[-76.34880800000001,36.836513],"type":"Point"}
}