{
  "type": "Feature",
  "properties": {
    "iso:country":"US",
    "sg:address":"1816 Todds Ln",
    "sg:city":"Hampton",
    "sg:classifiers":[
        {
            "category":"Personal",
            "type":"Services"
        }
    ],
    "sg:phone":"+1 757 838 2020",
    "sg:postcode":"23666",
    "sg:province":"VA",
    "sg:tags":[
        "program",
        "physical",
        "exercise",
        "fitness"
    ],
    "wof:name":"Life Line Fitness Ctr",
    "wof:placetype":"venue"
},
  "geometry": {"coordinates":[-76.404938,37.041083],"type":"Point"}
}