{
  "type": "Feature",
  "properties": {
    "addr:full":"2702 Charles City Rd Richmond VA 23231",
    "addr:housenumber":"2702",
    "addr:postcode":"23231",
    "addr:street":"Charles City Rd",
    "iso:country":"US",
    "sg:address":"2702 Charles City Rd",
    "sg:city":"Richmond",
    "sg:classifiers":[
        {
            "category":"Education",
            "subcategory":"Dance Studio",
            "type":"Public Place"
        }
    ],
    "sg:phone":"+1 804 222 3728",
    "sg:postcode":"23231",
    "sg:province":"VA",
    "sg:tags":[
        "school",
        "instructor"
    ],
    "wof:name":"Martinique School of Dance",
    "wof:placetype":"venue"
},
  "geometry": {"coordinates":[-77.347593,37.502647],"type":"Point"}
}