{
  "type": "Feature",
  "properties": {
    "iso:country":"US",
    "sg:address":"11831 Shire Ct",
    "sg:city":"Reston",
    "sg:classifiers":[
        {
            "category":"Building & Trades",
            "subcategory":"Landscaping Services",
            "type":"Services"
        }
    ],
    "sg:phone":"+1 703 327 2115",
    "sg:postcode":"20191",
    "sg:province":"VA",
    "wof:name":"Primetime Lawn & Landscape",
    "wof:placetype":"venue"
},
  "geometry": {"coordinates":[-77.36041899999999,38.934578],"type":"Point"}
}