{
  "type": "Feature",
  "properties": {
    "iso:country":"US",
    "sg:address":"938 Decatur St",
    "sg:city":"Chesapeake",
    "sg:classifiers":[
        {
            "category":"Organizations",
            "subcategory":"Religious Organization",
            "type":"Services"
        }
    ],
    "sg:phone":"+1 757 543 0513",
    "sg:postcode":"23324",
    "sg:province":"VA",
    "wof:name":"Bethel Assembly of God",
    "wof:placetype":"venue"
},
  "geometry": {"coordinates":[-76.27642899999999,36.818918],"type":"Point"}
}