{
  "type": "Feature",
  "properties": {
    "addr:full":"7139 Lee Hwy Falls Church VA 22046",
    "addr:housenumber":"7139",
    "addr:postcode":"22046",
    "addr:street":"Lee Hwy",
    "iso:country":"US",
    "sg:address":"7139 Lee Hwy",
    "sg:city":"Falls Church",
    "sg:classifiers":[
        {
            "category":"Home & Garden",
            "subcategory":"Building Materials",
            "type":"Retail Goods"
        },
        {
            "category":"Mining & Drilling",
            "type":"Manufacturing & Wholesale Goods"
        }
    ],
    "sg:phone":"+1 703 532 0169",
    "sg:postcode":"22046",
    "sg:province":"VA",
    "sg:tags":[
        "stone",
        "mar",
        "supply",
        "flagstone",
        "block",
        "masonry",
        "patio"
    ],
    "sg:website":"www.sislersstone.com",
    "wof:name":"Sisler's Inc",
    "wof:placetype":"venue"
},
  "geometry": {"coordinates":[-77.17845800000001,38.879185],"type":"Point"}
}