{
  "type": "Feature",
  "properties": {
    "addr:full":"509 S Taylor St Arlington VA 22204",
    "addr:housenumber":"509",
    "addr:postcode":"22204",
    "addr:street":"S Taylor St",
    "iso:country":"US",
    "sg:address":"509 S Taylor St",
    "sg:city":"Arlington",
    "sg:classifiers":[
        {
            "category":"Building & Trades",
            "subcategory":"Construction",
            "type":"Services"
        }
    ],
    "sg:phone":"+1 703 553 8633",
    "sg:postcode":"22204",
    "sg:province":"VA",
    "sg:tags":[
        "general",
        "contractor"
    ],
    "wof:name":"Arlington Remodeling",
    "wof:placetype":"venue"
},
  "geometry": {"coordinates":[-77.106465,38.864059],"type":"Point"}
}