{
  "type": "Feature",
  "properties": {
    "iso:country":"US",
    "sg:address":"1723 Chesterbrook Vale Ct",
    "sg:city":"Mc Lean",
    "sg:classifiers":[
        {
            "category":"Professional",
            "type":"Services"
        }
    ],
    "sg:phone":"+1 703 442 9495",
    "sg:postcode":"22101",
    "sg:province":"VA",
    "wof:name":"Donn & Linda Spalding",
    "wof:placetype":"venue"
},
  "geometry": {"coordinates":[-77.147171,38.921429],"type":"Point"}
}