{
  "type": "Feature",
  "properties": {
    "iso:country":"US",
    "sg:address":"4732 24th Rd N",
    "sg:city":"Arlington",
    "sg:classifiers":[
        {
            "category":"Health Services",
            "subcategory":"Doctor",
            "type":"Services"
        }
    ],
    "sg:phone":"+1 301 295 3832",
    "sg:postcode":"22207",
    "sg:province":"VA",
    "sg:tags":[
        "physician",
        "surgeon"
    ],
    "wof:name":"Galen Barbour MD",
    "wof:placetype":"venue"
},
  "geometry": {"coordinates":[-77.12548700000001,38.900986],"type":"Point"}
}