{
  "type": "Feature",
  "properties": {
    "iso:country":"US",
    "sg:address":"4731 23rd St N",
    "sg:city":"Arlington",
    "sg:classifiers":[
        {
            "category":"Health Services",
            "subcategory":"Health Practitioner",
            "type":"Services"
        }
    ],
    "sg:phone":"+1 703 527 2166",
    "sg:postcode":"22207",
    "sg:province":"VA",
    "sg:tags":[
        "occupational",
        "therapist"
    ],
    "wof:name":"Moses, Myania",
    "wof:placetype":"venue"
},
  "geometry": {"coordinates":[-77.124347,38.899079],"type":"Point"}
}