{
  "type": "Feature",
  "properties": {
    "iso:country":"US",
    "sg:address":"5602 Brookland Ct",
    "sg:city":"Alexandria",
    "sg:classifiers":[
        {
            "category":"Professional",
            "subcategory":"Business Services",
            "type":"Services"
        }
    ],
    "sg:phone":"+1 703 719 7684",
    "sg:postcode":"22310",
    "sg:province":"VA",
    "sg:tags":[
        "information",
        "bureau",
        "convention"
    ],
    "wof:name":"Anaheim-Orange COUNTY Vcb",
    "wof:placetype":"venue"
},
  "geometry": {"coordinates":[-77.132006,38.785259],"type":"Point"}
}