{
  "type": "Feature",
  "properties": {
    "addr:full":"5109 Leesburg Pike Falls Church VA 22041",
    "addr:housenumber":"5109",
    "addr:postcode":"22041",
    "addr:street":"Leesburg Pike",
    "iso:country":"US",
    "sg:address":"5109 Leesburg Pike",
    "sg:city":"Falls Church",
    "sg:classifiers":[
        {
            "category":"Professional",
            "type":"Services"
        }
    ],
    "sg:phone":"+1 703 681 9781",
    "sg:postcode":"22041",
    "sg:province":"VA",
    "wof:name":"Gpc Dcment Atmtn Prod Svc Daps",
    "wof:placetype":"venue"
},
  "geometry": {"coordinates":[-77.11693200000001,38.845516],"type":"Point"}
}