{
  "type": "Feature",
  "properties": {
    "iso:country":"US",
    "sg:address":"10905 Stacy Run",
    "sg:city":"Fredericksburg",
    "sg:classifiers":[
        {
            "category":"Banks & Credit Unions",
            "subcategory":"Financial Services",
            "type":"Services"
        }
    ],
    "sg:phone":"+1 540 370 4268",
    "sg:postcode":"22408",
    "sg:province":"VA",
    "sg:tags":[
        "investor"
    ],
    "wof:name":"Home Investors of America Inc",
    "wof:placetype":"venue"
},
  "geometry": {"coordinates":[-77.427837,38.258184],"type":"Point"}
}