{
  "type": "Feature",
  "properties": {
    "addr:full":"514 N Main St Hillsville VA 24343",
    "addr:housenumber":"514",
    "addr:postcode":"24343",
    "addr:street":"N Main St",
    "iso:country":"US",
    "sg:address":"514 N Main St",
    "sg:city":"Hillsville",
    "sg:classifiers":[
        {
            "category":"Personal",
            "subcategory":"Beauty Salon",
            "type":"Services"
        }
    ],
    "sg:phone":"+1 276 728 4775",
    "sg:postcode":"24343",
    "sg:province":"VA",
    "wof:name":"Dana's Styling Salon",
    "wof:placetype":"venue"
},
  "geometry": {"coordinates":[-80.73701199999999,36.766177],"type":"Point"}
}