{
  "type": "Feature",
  "properties": {
    "addr:full":"9280 Hornbaker Rd Manassas VA 20109",
    "addr:postcode":"9280;20109",
    "addr:street":"Hornbaker Rd",
    "iso:country":"US",
    "sg:address":"9280 Hornbaker Rd",
    "sg:city":"Manassas",
    "sg:classifiers":[
        {
            "category":"Government",
            "subcategory":"Office",
            "type":"Public Place"
        }
    ],
    "sg:phone":"+1 703 368 0004",
    "sg:postcode":"20109",
    "sg:province":"VA",
    "sg:tags":[
        "dept",
        "transportation"
    ],
    "wof:name":"Virginia Dept Transportation",
    "wof:placetype":"venue"
},
  "geometry": {"coordinates":[-77.533193,38.755845],"type":"Point"}
}