{
  "type": "Feature",
  "properties": {
    "addr:full":"9311 Hardy Cir Smithfield VA 23430",
    "addr:housenumber":"9311",
    "addr:postcode":"23430",
    "addr:street":"Hardy Cir",
    "iso:country":"US",
    "sg:address":"9311 Hardy Cir",
    "sg:city":"Smithfield",
    "sg:classifiers":[
        {
            "category":"Education",
            "subcategory":"School",
            "type":"Public Place"
        }
    ],
    "sg:phone":"+1 757 357 3204",
    "sg:postcode":"23430",
    "sg:province":"VA",
    "sg:website":"www.co.isle-of-wight.va.us",
    "wof:name":"Isle of Wight County of",
    "wof:placetype":"venue"
},
  "geometry": {"coordinates":[-76.634519,37.014429],"type":"Point"}
}