{
  "type": "Feature",
  "properties": {
    "iso:country":"US",
    "sg:address":"4457 Townsend Dr",
    "sg:city":"Cape Charles",
    "sg:classifiers":[
        {
            "category":"Organizations",
            "subcategory":"Religious Organization",
            "type":"Services"
        }
    ],
    "sg:phone":"+1 757 331 4147",
    "sg:postcode":"23310",
    "sg:province":"VA",
    "sg:tags":[
        "clergy"
    ],
    "wof:name":"Rick Kesterson",
    "wof:placetype":"venue"
},
  "geometry": {"coordinates":[-75.95996700000001,37.185492],"type":"Point"}
}