{
  "type": "Feature",
  "properties": {
    "addr:full":"225 Hull Ave Chilhowie VA 24319",
    "addr:housenumber":"225",
    "addr:postcode":"24319",
    "addr:street":"Hull Ave",
    "iso:country":"US",
    "sg:address":"225 Hull Ave",
    "sg:city":"Chilhowie",
    "sg:classifiers":[
        {
            "category":"Personal",
            "subcategory":"Beauty Salon",
            "type":"Services"
        }
    ],
    "sg:phone":"+1 276 646 8107",
    "sg:postcode":"24319",
    "sg:province":"VA",
    "wof:name":"Claudine's Beauty Salon",
    "wof:placetype":"venue"
},
  "geometry": {"coordinates":[-81.682405,36.801414],"type":"Point"}
}