{
  "type": "Feature",
  "properties": {
    "addr:full":"1340 Central Park Blvd Fredericksburg VA 22401",
    "addr:housenumber":"1340",
    "addr:postcode":"22401",
    "addr:street":"Central Park Blvd",
    "iso:country":"US",
    "sg:address":"1340 Central Park Blvd",
    "sg:city":"Fredericksburg",
    "sg:classifiers":[
        {
            "category":"Insurance",
            "subcategory":"Insurance Agent",
            "type":"Services"
        }
    ],
    "sg:phone":"+1 540 548 8344",
    "sg:postcode":"22401",
    "sg:province":"VA",
    "wof:name":"Liberty Mutual 0364",
    "wof:placetype":"venue"
},
  "geometry": {"coordinates":[-77.512794,38.302269],"type":"Point"}
}