{
  "type": "Feature",
  "properties": {
    "iso:country":"US",
    "sg:address":"23 Chestnut Oak Ln",
    "sg:city":"Amissville",
    "sg:classifiers":[
        {
            "category":"Building & Trades",
            "subcategory":"Construction",
            "type":"Services"
        }
    ],
    "sg:phone":"+1 540 222 1013",
    "sg:postcode":"20106",
    "sg:province":"VA",
    "sg:tags":[
        "remodeling",
        "contractor"
    ],
    "wof:name":"Richmar Construction",
    "wof:placetype":"venue"
},
  "geometry": {"coordinates":[-78.026971,38.716774],"type":"Point"}
}