{
  "type": "Feature",
  "properties": {
    "addr:full":"9230 Old Keene Mill Rd Burke VA 22015",
    "addr:housenumber":"9230",
    "addr:postcode":"22015",
    "addr:street":"Old Keene Mill Rd",
    "iso:country":"US",
    "sg:address":"9230 Old Keene Mill Rd",
    "sg:city":"Burke",
    "sg:classifiers":[
        {
            "category":"Shopping",
            "subcategory":"Stationery & Office Supplies",
            "type":"Retail Goods"
        }
    ],
    "sg:phone":"+1 703 440 0359",
    "sg:postcode":"22015",
    "sg:province":"VA",
    "wof:name":"Staples",
    "wof:placetype":"venue"
},
  "geometry": {"coordinates":[-77.26537999999999,38.775886],"type":"Point"}
}