{
  "type": "Feature",
  "properties": {
    "addr:full":"8845 Woodlawn Way Springfield VA 22153",
    "addr:housenumber":"8845",
    "addr:postcode":"22153",
    "addr:street":"Woodlawn Way",
    "iso:country":"US",
    "sg:address":"8845 Woodlawn Way",
    "sg:city":"Springfield",
    "sg:classifiers":[
        {
            "category":"Banks & Credit Unions",
            "subcategory":"Financial Services",
            "type":"Services"
        }
    ],
    "sg:phone":"+1 703 493 9033",
    "sg:postcode":"22153",
    "sg:province":"VA",
    "sg:tags":[
        "trust",
        "investment",
        "real estate"
    ],
    "wof:name":"Little Invstors Stick Together",
    "wof:placetype":"venue"
},
  "geometry": {"coordinates":[-77.249875,38.733961],"type":"Point"}
}