{
  "type": "Feature",
  "properties": {
    "addr:full":"925 Walker Ave Norfolk VA 23523",
    "addr:housenumber":"925",
    "addr:postcode":"23523",
    "addr:street":"Walker Ave",
    "iso:country":"US",
    "sg:address":"925 Walker Ave",
    "sg:city":"Norfolk",
    "sg:classifiers":[
        {
            "category":"Social Services",
            "subcategory":"Child Care",
            "type":"Services"
        }
    ],
    "sg:phone":"+1 757 543 6920",
    "sg:postcode":"23523",
    "sg:province":"VA",
    "sg:tags":[
        "day"
    ],
    "wof:name":"Angels Resting Child Care",
    "wof:placetype":"venue"
},
  "geometry": {"coordinates":[-76.27748200000001,36.826457],"type":"Point"}
}