{
  "type": "Feature",
  "properties": {
    "addr:full":"9865 Old Richmond Rd Keeling VA 24566",
    "addr:housenumber":"9865",
    "addr:postcode":"24566",
    "addr:street":"Old Richmond Rd",
    "iso:country":"US",
    "sg:address":"9865 Old Richmond Rd",
    "sg:city":"Keeling",
    "sg:classifiers":[
        {
            "category":"Organizations",
            "subcategory":"Religious Organization",
            "type":"Services"
        }
    ],
    "sg:phone":"+1 434 792 2822",
    "sg:postcode":"24566",
    "sg:province":"VA",
    "wof:name":"Kentuck Presbyterian Church",
    "wof:placetype":"venue"
},
  "geometry": {"coordinates":[-79.31799599999999,36.682387],"type":"Point"}
}