{
  "type": "Feature",
  "properties": {
    "addr:full":"2031 Madrillon Springs Ct Vienna VA 22182",
    "addr:housenumber":"2031",
    "addr:postcode":"22182",
    "addr:street":"Madrillon Springs Ct",
    "iso:country":"US",
    "sg:address":"2031 Madrillon Springs Ct",
    "sg:city":"Vienna",
    "sg:classifiers":[
        {
            "category":"Professional",
            "subcategory":"Computer Services",
            "type":"Services"
        }
    ],
    "sg:phone":"+1 703 448 9826",
    "sg:postcode":"22182",
    "sg:province":"VA",
    "sg:tags":[
        "consulting"
    ],
    "wof:name":"Cando Consulting",
    "wof:placetype":"venue"
},
  "geometry": {"coordinates":[-77.22644099999999,38.908535],"type":"Point"}
}