{
  "type": "Feature",
  "properties": {
    "addr:full":"2302 W Mercury Blvd Hampton VA 23666",
    "addr:housenumber":"2302",
    "addr:postcode":"23666",
    "addr:street":"W Mercury Blvd",
    "iso:country":"US",
    "sg:address":"2302 W Mercury Blvd",
    "sg:city":"Hampton",
    "sg:classifiers":[
        {
            "category":"Restaurant",
            "type":"Food & Drink"
        }
    ],
    "sg:phone":"+1 757 825 0056",
    "sg:postcode":"23666",
    "sg:province":"VA",
    "sg:tags":[
        "buffet"
    ],
    "wof:name":"Old Country Buffet 84",
    "wof:placetype":"venue"
},
  "geometry": {"coordinates":[-76.405354,37.038229],"type":"Point"}
}