{
  "type": "Feature",
  "properties": {
    "addr:full":"2100 Reston Pkwy Reston VA 20191",
    "addr:housenumber":"2100",
    "addr:postcode":"20191",
    "addr:street":"Reston Pkwy",
    "iso:country":"US",
    "sg:address":"2100 Reston Pkwy",
    "sg:city":"Reston",
    "sg:classifiers":[
        {
            "category":"Professional",
            "subcategory":"Computer Services",
            "type":"Services"
        }
    ],
    "sg:phone":"+1 703 386 9000",
    "sg:postcode":"20191",
    "sg:province":"VA",
    "sg:tags":[
        "development",
        "product",
        "system",
        "integration",
        "it",
        "software"
    ],
    "wof:name":"K&C Technology Corporation",
    "wof:placetype":"venue"
},
  "geometry": {"coordinates":[-77.361316,38.943023],"type":"Point"}
}