{
  "type": "Feature",
  "properties": {
    "iso:country":"US",
    "sg:address":"14705 Saint Germain Dr",
    "sg:city":"Centreville",
    "sg:classifiers":[
        {
            "category":"Professional",
            "subcategory":"Business Services",
            "type":"Services"
        }
    ],
    "sg:phone":"+1 703 335 9981",
    "sg:postcode":"20121",
    "sg:province":"VA",
    "wof:name":"Set You Free Bail Bonds",
    "wof:placetype":"venue"
},
  "geometry": {"coordinates":[-77.449814,38.833304],"type":"Point"}
}