{
  "type": "Feature",
  "properties": {
    "addr:full":"3351 Chesapeake Blvd Norfolk VA 23513",
    "addr:housenumber":"3351",
    "addr:postcode":"23513",
    "addr:street":"Chesapeake Blvd",
    "iso:country":"US",
    "sg:address":"3351 Chesapeake Blvd",
    "sg:city":"Norfolk",
    "sg:classifiers":[
        {
            "category":"Travel",
            "subcategory":"Hotels & Motels",
            "type":"Entertainment"
        }
    ],
    "sg:phone":"+1 757 853 9388",
    "sg:postcode":"23513",
    "sg:province":"VA",
    "wof:name":"Estabrook Inn",
    "wof:placetype":"venue"
},
  "geometry": {"coordinates":[-76.24990200000001,36.878566],"type":"Point"}
}