{
  "type": "Feature",
  "properties": {
    "addr:full":"845 Lacey Spring Rd Harrisonburg VA 22802",
    "addr:housenumber":"845",
    "addr:postcode":"22802",
    "addr:street":"Lacey Spring Rd",
    "iso:country":"US",
    "sg:address":"845 Lacey Spring Rd",
    "sg:city":"Harrisonburg",
    "sg:classifiers":[
        {
            "category":"Professional",
            "type":"Services"
        }
    ],
    "sg:phone":"+1 540 833 5142",
    "sg:postcode":"22802",
    "sg:province":"VA",
    "wof:name":"Moutain View Product Marketing",
    "wof:placetype":"venue"
},
  "geometry": {"coordinates":[-78.78185999999999,38.551896],"type":"Point"}
}