{
  "type": "Feature",
  "properties": {
    "addr:full":"14775 Purcellville Rd Purcellville VA 20132",
    "addr:postcode":"14775;20132",
    "addr:street":"Purcellville Rd",
    "iso:country":"US",
    "sg:address":"14775 Purcellville Rd",
    "sg:city":"Purcellville",
    "sg:classifiers":[
        {
            "category":"Professional",
            "subcategory":"Computer Services",
            "type":"Services"
        }
    ],
    "sg:phone":"+1 540 668 7729",
    "sg:postcode":"20132",
    "sg:province":"VA",
    "sg:tags":[
        "programing",
        "custom"
    ],
    "wof:name":"Dsr Systems Inc",
    "wof:placetype":"venue"
},
  "geometry": {"coordinates":[-77.68904000000001,39.208003],"type":"Point"}
}