{
  "type": "Feature",
  "properties": {
    "addr:full":"1155 N 4th St Wytheville VA 24382",
    "addr:housenumber":"1155",
    "addr:postcode":"24382",
    "addr:street":"N 4Th St",
    "iso:country":"US",
    "sg:address":"1155 N 4th St",
    "sg:city":"Wytheville",
    "sg:classifiers":[
        {
            "category":"Restaurant",
            "type":"Food & Drink"
        }
    ],
    "sg:phone":"+1 276 228 8876",
    "sg:postcode":"24382",
    "sg:province":"VA",
    "wof:name":"Turn One Restaurant",
    "wof:placetype":"venue"
},
  "geometry": {"coordinates":[-81.094363,36.956535],"type":"Point"}
}