{
  "type": "Feature",
  "properties": {
    "addr:full":"6695 Hanson Ln Lorton VA 22079",
    "addr:housenumber":"6695",
    "addr:postcode":"22079",
    "addr:street":"Hanson Ln",
    "iso:country":"US",
    "sg:address":"6695 Hanson Ln",
    "sg:city":"Lorton",
    "sg:classifiers":[
        {
            "category":"Health Services",
            "subcategory":"Doctor",
            "type":"Services"
        }
    ],
    "sg:phone":"+1 703 550 5616",
    "sg:postcode":"22079",
    "sg:province":"VA",
    "sg:tags":[
        "medical"
    ],
    "wof:name":"Radiological Health Center",
    "wof:placetype":"venue"
},
  "geometry": {"coordinates":[-77.17393800000001,38.72922],"type":"Point"}
}