{
  "type": "Feature",
  "properties": {
    "addr:full":"585 Buckner Rd Bumpass VA 23024",
    "addr:housenumber":"585",
    "addr:postcode":"23024",
    "addr:street":"Buckner Rd",
    "iso:country":"US",
    "sg:address":"585 Buckner Rd",
    "sg:city":"Bumpass",
    "sg:classifiers":[
        {
            "category":"Building & Trades",
            "subcategory":"Construction",
            "type":"Services"
        }
    ],
    "sg:phone":"+1 540 872 3524",
    "sg:postcode":"23024",
    "sg:province":"VA",
    "sg:tags":[
        "contractor"
    ],
    "wof:name":"J N Wolfe",
    "wof:placetype":"venue"
},
  "geometry": {"coordinates":[-77.82775100000001,37.891086],"type":"Point"}
}