{
  "type": "Feature",
  "properties": {
    "addr:full":"4454 Majestic Ln Fairfax VA 22033",
    "addr:housenumber":"4454",
    "addr:postcode":"22033",
    "addr:street":"Majestic Ln",
    "iso:country":"US",
    "sg:address":"4454 Majestic Ln",
    "sg:city":"Fairfax",
    "sg:classifiers":[
        {
            "category":"Professional",
            "subcategory":"Engineering",
            "type":"Services"
        },
        {
            "category":"Professional",
            "subcategory":"Management & Consulting",
            "type":"Services"
        }
    ],
    "sg:phone":"+1 703 378 1456",
    "sg:postcode":"22033",
    "sg:province":"VA",
    "sg:tags":[
        "business",
        "engineer"
    ],
    "wof:name":"Spellings & Assoc Inc",
    "wof:placetype":"venue"
},
  "geometry": {"coordinates":[-77.40752999999999,38.87556],"type":"Point"}
}