{
  "type": "Feature",
  "properties": {
    "iso:country":"US",
    "sg:address":"1443 Aldenham Ln",
    "sg:city":"Reston",
    "sg:classifiers":[
        {
            "category":"Building & Trades",
            "subcategory":"Construction",
            "type":"Services"
        }
    ],
    "sg:phone":"+1 703 437 1987",
    "sg:postcode":"20190",
    "sg:province":"VA",
    "sg:tags":[
        "repairing",
        "remodeling",
        "contractor"
    ],
    "wof:name":"Nunn Construction",
    "wof:placetype":"venue"
},
  "geometry": {"coordinates":[-77.32408100000001,38.968859],"type":"Point"}
}