{
  "type": "Feature",
  "properties": {
    "iso:country":"US",
    "sg:address":"3351 Spillway Ln",
    "sg:city":"Mechanicsville",
    "sg:classifiers":[
        {
            "category":"Professional",
            "subcategory":"Computer Services",
            "type":"Services"
        }
    ],
    "sg:phone":"+1 804 779 1036",
    "sg:postcode":"23111",
    "sg:province":"VA",
    "sg:tags":[
        "internet"
    ],
    "wof:name":"Gregory Humphrey",
    "wof:placetype":"venue"
},
  "geometry": {"coordinates":[-77.220671,37.633205],"type":"Point"}
}