{
  "type": "Feature",
  "properties": {
    "addr:full":"5400 Roanoke Ave Alexandria VA 22311",
    "addr:housenumber":"5400",
    "addr:postcode":"22311",
    "addr:street":"Roanoke Ave",
    "iso:country":"US",
    "sg:address":"5400 Roanoke Ave",
    "sg:city":"Alexandria",
    "sg:classifiers":[
        {
            "category":"Museum",
            "subcategory":"Botanical Garden",
            "type":"Entertainment"
        },
        {
            "category":"Recreation",
            "type":"Entertainment"
        }
    ],
    "sg:phone":"+1 703 578 7888",
    "sg:postcode":"22311",
    "sg:province":"VA",
    "sg:tags":[
        "hiking"
    ],
    "sg:website":"www.friendsofwinkler.org/Default...",
    "wof:name":"Winkler Botanical Preserve",
    "wof:placetype":"venue"
},
  "geometry": {"coordinates":[-77.125951,38.827292],"type":"Point"}
}