{
  "type": "Feature",
  "properties": {
    "addr:full":"4213 Lizzie Anne Ln Glen Allen VA 23060",
    "addr:housenumber":"4213",
    "addr:postcode":"23060",
    "addr:street":"Lizzie Anne Ln",
    "iso:country":"US",
    "sg:address":"4213 Lizzie Anne Ln",
    "sg:city":"Glen Allen",
    "sg:classifiers":[
        {
            "category":"Shopping",
            "subcategory":"Gifts & Souvenirs",
            "type":"Retail Goods"
        }
    ],
    "sg:phone":"+1 804 270 4858",
    "sg:postcode":"23060",
    "sg:province":"VA",
    "wof:name":"Gift of Fun Inc",
    "wof:placetype":"venue"
},
  "geometry": {"coordinates":[-77.56723100000001,37.65314],"type":"Point"}
}