{
  "type": "Feature",
  "properties": {
    "addr:full":"438 Whipping Creek Rd Naruna VA 24554",
    "addr:housenumber":"438",
    "addr:postcode":"24554",
    "addr:street":"Whipping Creek Rd",
    "iso:country":"US",
    "sg:address":"438 Whipping Creek Rd",
    "sg:city":"Naruna",
    "sg:classifiers":[
        {
            "category":"Government",
            "subcategory":"Post Office",
            "type":"Public Place"
        }
    ],
    "sg:phone":"+1 434 376 5355",
    "sg:postcode":"24554",
    "sg:province":"VA",
    "wof:name":"US Post Office",
    "wof:placetype":"venue"
},
  "geometry": {"coordinates":[-79.00122,37.105184],"type":"Point"}
}