{
  "type": "Feature",
  "properties": {
    "addr:full":"100 W Mercury Blvd Hampton VA 23669",
    "addr:housenumber":"100",
    "addr:postcode":"23669",
    "addr:street":"W Mercury Blvd",
    "iso:country":"US",
    "sg:address":"100 W Mercury Blvd",
    "sg:city":"Hampton",
    "sg:classifiers":[
        {
            "category":"Banks & Credit Unions",
            "subcategory":"Bank",
            "type":"Services"
        }
    ],
    "sg:phone":"+1 757 726 2888",
    "sg:postcode":"23669",
    "sg:province":"VA",
    "sg:tags":[
        "cashing",
        "check"
    ],
    "wof:name":"Quik Cash 215",
    "wof:placetype":"venue"
},
  "geometry": {"coordinates":[-76.35621999999999,37.043768],"type":"Point"}
}