{
  "type": "Feature",
  "properties": {
    "addr:full":"6411 Rigsby Rd Richmond VA 23226",
    "addr:housenumber":"6411",
    "addr:postcode":"23226",
    "addr:street":"Rigsby Rd",
    "iso:country":"US",
    "sg:address":"6411 Rigsby Rd",
    "sg:city":"Richmond",
    "sg:classifiers":[
        {
            "category":"Shopping",
            "subcategory":"Stationery & Office Supplies",
            "type":"Retail Goods"
        }
    ],
    "sg:phone":"+1 804 282 4130",
    "sg:postcode":"23226",
    "sg:province":"VA",
    "wof:name":"Data Office Supply Inc",
    "wof:placetype":"venue"
},
  "geometry": {"coordinates":[-77.515084,37.596057],"type":"Point"}
}