{
  "type": "Feature",
  "properties": {
    "iso:country":"US",
    "sg:address":"5810 Forest Hill Ave",
    "sg:city":"Richmond",
    "sg:classifiers":[
        {
            "category":"Building & Trades",
            "subcategory":"Construction",
            "type":"Services"
        }
    ],
    "sg:phone":"+1 804 334 0629",
    "sg:postcode":"23225",
    "sg:province":"VA",
    "sg:tags":[
        "pointing",
        "tuck"
    ],
    "wof:name":"Vastukar",
    "wof:placetype":"venue"
},
  "geometry": {"coordinates":[-77.50404,37.530209],"type":"Point"}
}