{
  "type": "Feature",
  "properties": {
    "addr:full":"8031 Poindexter Rd New Kent VA 23124",
    "addr:housenumber":"8031",
    "addr:postcode":"23124",
    "addr:street":"Poindexter Rd",
    "iso:country":"US",
    "sg:address":"8031 Poindexter Rd",
    "sg:city":"New Kent",
    "sg:classifiers":[
        {
            "category":"Building & Trades",
            "subcategory":"Electrical",
            "type":"Services"
        }
    ],
    "sg:phone":"+1 804 932 4447",
    "sg:postcode":"23124",
    "sg:province":"VA",
    "sg:tags":[
        "electrical",
        "contractor"
    ],
    "wof:name":"Brown Sterling C Elec Contr",
    "wof:placetype":"venue"
},
  "geometry": {"coordinates":[-77.032145,37.516893],"type":"Point"}
}