{
  "type": "Feature",
  "properties": {
    "iso:country":"US",
    "sg:address":"18397 Grassland Rd",
    "sg:city":"Culpeper",
    "sg:classifiers":[
        {
            "category":"Professional",
            "type":"Services"
        }
    ],
    "sg:phone":"+1 540 825 1472",
    "sg:postcode":"22701",
    "sg:province":"VA",
    "wof:name":"R L Morris",
    "wof:placetype":"venue"
},
  "geometry": {"coordinates":[-77.972784,38.446913],"type":"Point"}
}