{
  "type": "Feature",
  "properties": {
    "addr:full":"195 Reynolds Ridge Rd Bassett VA 24055",
    "addr:housenumber":"195",
    "addr:postcode":"24055",
    "addr:street":"Reynolds Ridge Rd",
    "iso:country":"US",
    "sg:address":"195 Reynolds Ridge Rd",
    "sg:city":"Bassett",
    "sg:classifiers":[
        {
            "category":"Home & Garden",
            "subcategory":"Building Materials",
            "type":"Retail Goods"
        }
    ],
    "sg:phone":"+1 276 629 2000",
    "sg:postcode":"24055",
    "sg:province":"VA",
    "sg:tags":[
        "windows"
    ],
    "wof:name":"Millennium Siding & Window Co",
    "wof:placetype":"venue"
},
  "geometry": {"coordinates":[-79.932714,36.820655],"type":"Point"}
}