{
  "type": "Feature",
  "properties": {
    "addr:full":"116 Palace Ln Williamsburg VA 23185",
    "addr:housenumber":"116",
    "addr:postcode":"23185",
    "addr:street":"Palace Ln",
    "iso:country":"US",
    "sg:address":"116 Palace Ln",
    "sg:city":"Williamsburg",
    "sg:classifiers":[
        {
            "category":"Education",
            "subcategory":"School",
            "type":"Public Place"
        }
    ],
    "sg:phone":"+1 757 565 2900",
    "sg:postcode":"23185",
    "sg:province":"VA",
    "sg:website":"www.pcsvirginia.com",
    "wof:name":"Providence Classical School",
    "wof:placetype":"venue"
},
  "geometry": {"coordinates":[-76.715298,37.28591],"type":"Point"}
}