{
  "type": "Feature",
  "properties": {
    "addr:full":"1382 Armory Dr Franklin VA 23851",
    "addr:housenumber":"1382",
    "addr:postcode":"23851",
    "addr:street":"Armory Dr",
    "iso:country":"US",
    "sg:address":"1382 Armory Dr",
    "sg:city":"Franklin",
    "sg:classifiers":[
        {
            "category":"Restaurant",
            "type":"Food & Drink"
        }
    ],
    "sg:menulink":"http://www.allmenus.com/va/franklin/36725-famous-uncle-als-hot-dogs/menu/",
    "sg:phone":"+1 757 569 0040",
    "sg:postcode":"23851",
    "sg:province":"VA",
    "sg:tags":[
        "american"
    ],
    "wof:name":"Famous Uncle Al's Hot Dogs",
    "wof:placetype":"venue"
},
  "geometry": {"coordinates":[-76.94940099999999,36.669084],"type":"Point"}
}