{
  "type": "Feature",
  "properties": {
    "iso:country":"US",
    "sg:address":"3213 Spring Dr",
    "sg:city":"Alexandria",
    "sg:classifiers":[
        {
            "category":"Wholesale",
            "subcategory":"Non-durable Goods",
            "type":"Manufacturing & Wholesale Goods"
        }
    ],
    "sg:phone":"+1 703 768 3611",
    "sg:postcode":"22306",
    "sg:province":"VA",
    "wof:name":"Blue Ridge Trading Co",
    "wof:placetype":"venue"
},
  "geometry": {"coordinates":[-77.084292,38.765102],"type":"Point"}
}