{
  "type": "Feature",
  "properties": {
    "iso:country":"US",
    "sg:address":"12829 Jefferson Ave",
    "sg:city":"Newport News",
    "sg:classifiers":[
        {
            "category":"Professional",
            "subcategory":"Engineering",
            "type":"Services"
        }
    ],
    "sg:phone":"+1 757 722 0113",
    "sg:postcode":"23608",
    "sg:province":"VA",
    "sg:tags":[
        "engineer"
    ],
    "sg:website":"www.remsainc.com",
    "wof:name":"Remsa Inc",
    "wof:placetype":"venue"
},
  "geometry": {"coordinates":[-76.523658,37.143134],"type":"Point"}
}