{
  "type": "Feature",
  "properties": {
    "iso:country":"US",
    "sg:address":"805 Live Oak Dr",
    "sg:city":"Chesapeake",
    "sg:classifiers":[
        {
            "category":"Insurance",
            "subcategory":"Insurance Agent",
            "type":"Services"
        }
    ],
    "sg:phone":"+1 757 547 9497",
    "sg:postcode":"23320",
    "sg:province":"VA",
    "wof:name":"Old American Insurance Co",
    "wof:placetype":"venue"
},
  "geometry": {"coordinates":[-76.23142199999999,36.7969],"type":"Point"}
}