{
  "type": "Feature",
  "properties": {
    "iso:country":"US",
    "sg:address":"5955 Free State Rd",
    "sg:city":"Marshall",
    "sg:classifiers":[
        {
            "category":"Building & Trades",
            "subcategory":"Landscaping Services",
            "type":"Services"
        }
    ],
    "sg:phone":"+1 703 661 6770",
    "sg:postcode":"20115",
    "sg:province":"VA",
    "sg:tags":[
        "landscape",
        "contractor"
    ],
    "wof:name":"Tom Payne Inc",
    "wof:placetype":"venue"
},
  "geometry": {"coordinates":[-77.909122,38.794532],"type":"Point"}
}