{
  "type": "Feature",
  "properties": {
    "addr:full":"5659 White Dove Ln Clifton VA 20124",
    "addr:housenumber":"5659",
    "addr:postcode":"20124",
    "addr:street":"White Dove Ln",
    "iso:country":"US",
    "sg:address":"5659 White Dove Ln",
    "sg:city":"Clifton",
    "sg:classifiers":[
        {
            "category":"Building & Trades",
            "subcategory":"Construction",
            "type":"Services"
        }
    ],
    "sg:phone":"+1 703 266 2716",
    "sg:postcode":"20124",
    "sg:province":"VA",
    "sg:tags":[
        "concrete",
        "contractor"
    ],
    "wof:name":"Concrete Raising Inc",
    "wof:placetype":"venue"
},
  "geometry": {"coordinates":[-77.41403699999999,38.835938],"type":"Point"}
}