{
  "type": "Feature",
  "properties": {
    "addr:full":"1321 Victory Blvd Chesapeake VA 23323",
    "addr:housenumber":"1321",
    "addr:postcode":"23323",
    "addr:street":"Victory Blvd",
    "iso:country":"US",
    "sg:address":"1321 Victory Blvd",
    "sg:city":"Chesapeake",
    "sg:classifiers":[
        {
            "category":"Manufacturing",
            "subcategory":"Tools & Machinery",
            "type":"Manufacturing & Wholesale Goods"
        }
    ],
    "sg:phone":"+1 757 485 4690",
    "sg:postcode":"23323",
    "sg:province":"VA",
    "sg:tags":[
        "mfg",
        "watering",
        "equipment",
        "pump",
        "construction",
        "lease"
    ],
    "sg:website":"www.thompsonpump.com",
    "wof:name":"Thompson Pump & Wellpoint Co",
    "wof:placetype":"venue"
},
  "geometry": {"coordinates":[-76.31429799999999,36.795847],"type":"Point"}
}