{
  "type": "Feature",
  "properties": {
    "iso:country":"US",
    "sg:address":"6024 Wensleydale Dr",
    "sg:city":"New Kent",
    "sg:classifiers":[
        {
            "category":"Wholesale",
            "subcategory":"Non-durable Goods",
            "type":"Manufacturing & Wholesale Goods"
        }
    ],
    "sg:phone":"+1 804 932 4541",
    "sg:postcode":"23124",
    "sg:province":"VA",
    "wof:name":"Saltbox Primitive",
    "wof:placetype":"venue"
},
  "geometry": {"coordinates":[-77.110612,37.535124],"type":"Point"}
}