{
  "type": "Feature",
  "properties": {
    "iso:country":"US",
    "sg:address":"11404 Hilbingdon Rd",
    "sg:city":"Henrico",
    "sg:classifiers":[
        {
            "category":"Education",
            "subcategory":"Library",
            "type":"Public Place"
        }
    ],
    "sg:phone":"+1 804 741 3560",
    "sg:postcode":"23238",
    "sg:province":"VA",
    "wof:name":"Family Soluction",
    "wof:placetype":"venue"
},
  "geometry": {"coordinates":[-77.61895800000001,37.612819],"type":"Point"}
}