{
  "type": "Feature",
  "properties": {
    "addr:full":"120 Stillhouse Run Lynchburg VA 24503",
    "addr:housenumber":"120",
    "addr:postcode":"24503",
    "addr:street":"Stillhouse Run",
    "iso:country":"US",
    "sg:address":"120 Stillhouse Run",
    "sg:city":"Lynchburg",
    "sg:classifiers":[
        {
            "category":"Professional",
            "type":"Services"
        }
    ],
    "sg:phone":"+1 434 384 6245",
    "sg:postcode":"24503",
    "sg:province":"VA",
    "sg:tags":[
        "establishment"
    ],
    "wof:name":"Stephen's European Rprdctns",
    "wof:placetype":"venue"
},
  "geometry": {"coordinates":[-79.266935,37.4512],"type":"Point"}
}