{
  "type": "Feature",
  "properties": {
    "addr:full":"203 Edwards Dr Hampton VA 23666",
    "addr:housenumber":"203",
    "addr:postcode":"23666",
    "addr:street":"Edwards Dr",
    "iso:country":"US",
    "sg:address":"203 Edwards Dr",
    "sg:city":"Hampton",
    "sg:classifiers":[
        {
            "category":"Professional",
            "subcategory":"Accounting & Tax Preparation",
            "type":"Services"
        }
    ],
    "sg:phone":"+1 757 838 0373",
    "sg:postcode":"23666",
    "sg:province":"VA",
    "wof:name":"Glascock Tax Service",
    "wof:placetype":"venue"
},
  "geometry": {"coordinates":[-76.422963,37.037316],"type":"Point"}
}