{
  "type": "Feature",
  "properties": {
    "addr:full":"80 Stover St Mc Gaheysville VA 22821",
    "addr:housenumber":"80",
    "addr:postcode":"22821",
    "addr:street":"Stover St",
    "iso:country":"US",
    "sg:address":"80 Stover St",
    "sg:city":"Mc Gaheysville",
    "sg:classifiers":[
        {
            "category":"Government",
            "subcategory":"Fire Station",
            "type":"Public Place"
        }
    ],
    "sg:phone":"+1 540 289 5318",
    "sg:postcode":"22821",
    "sg:province":"VA",
    "sg:tags":[
        "vol",
        "dept"
    ],
    "wof:name":"McGaheysville Vlntr Fire Inc",
    "wof:placetype":"venue"
},
  "geometry": {"coordinates":[-78.944914,38.413938],"type":"Point"}
}