{
  "type": "Feature",
  "properties": {
    "addr:full":"489 McLaws Cir Williamsburg VA 23185",
    "addr:housenumber":"489",
    "addr:postcode":"23185",
    "addr:street":"Mclaws Cir",
    "iso:country":"US",
    "sg:address":"489 McLaws Cir",
    "sg:city":"Williamsburg",
    "sg:classifiers":[
        {
            "category":"Social Services",
            "type":"Services"
        }
    ],
    "sg:phone":"+1 757 220 2766",
    "sg:postcode":"23185",
    "sg:province":"VA",
    "sg:tags":[
        "counselor",
        "marriage",
        "family"
    ],
    "wof:name":"Family Institute Of Virginia",
    "wof:placetype":"venue"
},
  "geometry": {"coordinates":[-76.66264700000001,37.248553],"type":"Point"}
}