{
  "type": "Feature",
  "properties": {
    "addr:full":"310 W Washington St Petersburg VA 23803",
    "addr:housenumber":"310",
    "addr:postcode":"23803",
    "addr:street":"W Washington",
    "iso:country":"US",
    "sg:address":"310 W Washington St",
    "sg:city":"Petersburg",
    "sg:classifiers":[
        {
            "category":"Home & Garden",
            "subcategory":"Building Materials",
            "type":"Retail Goods"
        },
        {
            "category":"Shopping",
            "subcategory":"Hobbies, Toys, & Games",
            "type":"Retail Goods"
        }
    ],
    "sg:phone":"+1 804 732 0854",
    "sg:postcode":"23803",
    "sg:province":"VA",
    "sg:tags":[
        "paint",
        "picture"
    ],
    "wof:name":"Joyner Paint & Frame LLC",
    "wof:placetype":"venue"
},
  "geometry": {"coordinates":[-77.409333,37.226646],"type":"Point"}
}