{
  "type": "Feature",
  "properties": {
    "addr:full":"8258 Richfood Rd Mechanicsville VA 23116",
    "addr:housenumber":"8258",
    "addr:postcode":"23116",
    "addr:street":"Richfood Rd",
    "iso:country":"US",
    "sg:address":"8258 Richfood Rd",
    "sg:city":"Mechanicsville",
    "sg:classifiers":[
        {
            "category":"Personal",
            "type":"Services"
        }
    ],
    "sg:phone":"+1 804 746 6254",
    "sg:postcode":"23116",
    "sg:province":"VA",
    "sg:tags":[
        "car",
        "loading",
        "unloading"
    ],
    "wof:name":"Performance Logistics Group Inc",
    "wof:placetype":"venue"
},
  "geometry": {"coordinates":[-77.40917899999999,37.632364],"type":"Point"}
}