{
  "type": "Feature",
  "properties": {
    "iso:country":"US",
    "sg:address":"600 E Main St",
    "sg:city":"Radford",
    "sg:classifiers":[
        {
            "category":"Health Services",
            "subcategory":"Doctor",
            "type":"Services"
        }
    ],
    "sg:phone":"+1 540 639 9561",
    "sg:postcode":"24141",
    "sg:province":"VA",
    "sg:tags":[
        "clinic"
    ],
    "wof:name":"Gambro Healthcare",
    "wof:placetype":"venue"
},
  "geometry": {"coordinates":[-80.545897,37.137843],"type":"Point"}
}