{
  "type": "Feature",
  "properties": {
    "addr:full":"179 Bucher Run Ln Winchester VA 22602",
    "addr:housenumber":"179",
    "addr:postcode":"22602",
    "addr:street":"Bucher Run Ln",
    "iso:country":"US",
    "sg:address":"179 Bucher Run Ln",
    "sg:city":"Winchester",
    "sg:classifiers":[
        {
            "category":"Building & Trades",
            "subcategory":"Landscaping Services",
            "type":"Services"
        }
    ],
    "sg:phone":"+1 540 877 1956",
    "sg:postcode":"22602",
    "sg:province":"VA",
    "wof:name":"Pine Ridge LLC",
    "wof:placetype":"venue"
},
  "geometry": {"coordinates":[-78.29740700000001,39.210266],"type":"Point"}
}