{
  "type": "Feature",
  "properties": {
    "addr:full":"601 N Vermont St Arlington VA 22203",
    "addr:housenumber":"601",
    "addr:postcode":"22203",
    "addr:street":"N Vermont St",
    "iso:country":"US",
    "sg:address":"601 N Vermont St",
    "sg:city":"Arlington",
    "sg:classifiers":[
        {
            "category":"Organizations",
            "subcategory":"Religious Organization",
            "type":"Services"
        }
    ],
    "sg:phone":"+1 703 527 4766",
    "sg:postcode":"22203",
    "sg:province":"VA",
    "sg:tags":[
        "church"
    ],
    "wof:name":"First Presbyterian Arlington",
    "wof:placetype":"venue"
},
  "geometry": {"coordinates":[-77.114217,38.877983],"type":"Point"}
}