{
  "type": "Feature",
  "properties": {
    "iso:country":"US",
    "sg:address":"753 S Main St",
    "sg:city":"Woodstock",
    "sg:classifiers":[
        {
            "category":"Organizations",
            "subcategory":"Religious Organization",
            "type":"Services"
        }
    ],
    "sg:phone":"+1 540 459 4379",
    "sg:postcode":"22664",
    "sg:province":"VA",
    "wof:name":"New Hope",
    "wof:placetype":"venue"
},
  "geometry": {"coordinates":[-78.513493,38.872043],"type":"Point"}
}