{
  "type": "Feature",
  "properties": {
    "addr:full":"65 Angelo Dr Newport News VA 23608",
    "addr:housenumber":"65",
    "addr:postcode":"23608",
    "addr:street":"Angelo Dr",
    "iso:country":"US",
    "sg:address":"65 Angelo Dr",
    "sg:city":"Newport News",
    "sg:classifiers":[
        {
            "category":"Health Services",
            "subcategory":"Health Practitioner",
            "type":"Services"
        }
    ],
    "sg:phone":"+1 757 877 0302",
    "sg:postcode":"23608",
    "sg:province":"VA",
    "sg:tags":[
        "registered",
        "nurse"
    ],
    "wof:name":"Gloria Engelberger",
    "wof:placetype":"venue"
},
  "geometry": {"coordinates":[-76.57501999999999,37.131531],"type":"Point"}
}