{
  "type": "Feature",
  "properties": {
    "iso:country":"US",
    "sg:address":"15601 Cooks Mill Rd",
    "sg:city":"Lanexa",
    "sg:classifiers":[
        {
            "category":"Organizations",
            "subcategory":"Religious Organization",
            "type":"Services"
        }
    ],
    "sg:phone":"+1 804 966 7011",
    "sg:postcode":"23089",
    "sg:province":"VA",
    "sg:tags":[
        "church"
    ],
    "wof:name":"Second Elam Baptist Church",
    "wof:placetype":"venue"
},
  "geometry": {"coordinates":[-76.89826100000001,37.522447],"type":"Point"}
}