{
  "type": "Feature",
  "properties": {
    "iso:country":"US",
    "sg:address":"2285 Gravel Hill Rd",
    "sg:city":"Troutville",
    "sg:classifiers":[
        {
            "category":"Shopping",
            "subcategory":"Discount & Variety Stores",
            "type":"Retail Goods"
        }
    ],
    "sg:phone":"+1 540 992 4228",
    "sg:postcode":"24175",
    "sg:province":"VA",
    "sg:tags":[
        "merchandise",
        "general"
    ],
    "wof:name":"A 1 Products",
    "wof:placetype":"venue"
},
  "geometry": {"coordinates":[-79.879171,37.459882],"type":"Point"}
}