{
  "type": "Feature",
  "properties": {
    "addr:full":"2201 Montgomery Ave Woodbridge VA 22191",
    "addr:housenumber":"2201",
    "addr:postcode":"22191",
    "addr:street":"Montgomery Ave",
    "iso:country":"US",
    "sg:address":"2201 Montgomery Ave",
    "sg:city":"Woodbridge",
    "sg:classifiers":[
        {
            "category":"Building & Trades",
            "subcategory":"Construction",
            "type":"Services"
        }
    ],
    "sg:phone":"+1 703 490 3146",
    "sg:postcode":"22191",
    "sg:province":"VA",
    "sg:tags":[
        "masonry",
        "contractor"
    ],
    "wof:name":"R L Wilks & Sons Inc",
    "wof:placetype":"venue"
},
  "geometry": {"coordinates":[-77.283247,38.638092],"type":"Point"}
}