{
  "type": "Feature",
  "properties": {
    "iso:country":"US",
    "sg:address":"7521 Granby St",
    "sg:city":"Norfolk",
    "sg:classifiers":[
        {
            "category":"Restaurant",
            "type":"Food & Drink"
        }
    ],
    "sg:phone":"+1 757 423 1000",
    "sg:postcode":"23505",
    "sg:province":"VA",
    "sg:tags":[
        "brew",
        "pub"
    ],
    "sg:website":"http://www.saigaisteakhousesushi.com",
    "wof:name":"Sai Gai Japanese Steak House & Sushi Bar",
    "wof:placetype":"venue"
},
  "geometry": {"coordinates":[-76.273003,36.914131],"type":"Point"}
}