{
  "type": "Feature",
  "properties": {
    "iso:country":"US",
    "sg:address":"807 E Main St",
    "sg:city":"Abingdon",
    "sg:classifiers":[
        {
            "category":"Organizations",
            "subcategory":"Religious Organization",
            "type":"Services"
        }
    ],
    "sg:phone":"+1 276 628 6215",
    "sg:postcode":"24210",
    "sg:province":"VA",
    "sg:tags":[
        "church"
    ],
    "wof:name":"St John Lutheran Church",
    "wof:placetype":"venue"
},
  "geometry": {"coordinates":[-81.94847900000001,36.717817],"type":"Point"}
}