{
  "type": "Feature",
  "properties": {
    "addr:full":"13530 Stonegate Rd Midlothian VA 23113",
    "addr:housenumber":"13530",
    "addr:postcode":"23113",
    "addr:street":"Stonegate Rd",
    "iso:country":"US",
    "sg:address":"13530 Stonegate Rd",
    "sg:city":"Midlothian",
    "sg:classifiers":[
        {
            "category":"Organizations",
            "subcategory":"Membership Organization",
            "type":"Services"
        }
    ],
    "sg:phone":"+1 804 379 7508",
    "sg:postcode":"23113",
    "sg:province":"VA",
    "wof:name":"Micawber Foundation",
    "wof:placetype":"venue"
},
  "geometry": {"coordinates":[-77.650222,37.532627],"type":"Point"}
}