{
  "type": "Feature",
  "properties": {
    "iso:country":"US",
    "sg:address":"7911 Summer Breeze Rd",
    "sg:city":"Pound",
    "sg:classifiers":[
        {
            "category":"Mining & Drilling",
            "type":"Manufacturing & Wholesale Goods"
        }
    ],
    "sg:phone":"+1 276 796 4711",
    "sg:postcode":"24279",
    "sg:province":"VA",
    "sg:tags":[
        "well",
        "gas"
    ],
    "wof:name":"Sowards Energy LLC",
    "wof:placetype":"venue"
},
  "geometry": {"coordinates":[-82.618775,37.108738],"type":"Point"}
}