{
  "type": "Feature",
  "properties": {
    "iso:country":"US",
    "sg:address":"246 Neck-O-Land Rd",
    "sg:city":"Williamsburg",
    "sg:classifiers":[
        {
            "category":"Real Estate",
            "subcategory":"Real Estate Agent",
            "type":"Services"
        }
    ],
    "sg:phone":"+1 757 253 0275",
    "sg:postcode":"23185",
    "sg:province":"VA",
    "wof:name":"R E Gilley Realty",
    "wof:placetype":"venue"
},
  "geometry": {"coordinates":[-76.752162,37.232673],"type":"Point"}
}