{
  "type": "Feature",
  "properties": {
    "addr:full":"1601 N Kent St Arlington VA 22209",
    "addr:housenumber":"1601",
    "addr:postcode":"22209",
    "addr:street":"N Kent St",
    "iso:country":"US",
    "sg:address":"1601 N Kent St",
    "sg:city":"Arlington",
    "sg:classifiers":[
        {
            "category":"Building & Trades",
            "subcategory":"Construction",
            "type":"Services"
        }
    ],
    "sg:phone":"+1 703 248 1661",
    "sg:postcode":"22209",
    "sg:province":"VA",
    "wof:name":"Pae- Berger",
    "wof:placetype":"venue"
},
  "geometry": {"coordinates":[-77.06958299999999,38.897033],"type":"Point"}
}