{
  "type": "Feature",
  "properties": {
    "addr:full":"25897 Flintonbridge Dr Chantilly VA 20152",
    "addr:housenumber":"25897",
    "addr:postcode":"20152",
    "addr:street":"Flintonbridge Dr",
    "iso:country":"US",
    "sg:address":"25897 Flintonbridge Dr",
    "sg:city":"Chantilly",
    "sg:classifiers":[
        {
            "category":"Professional",
            "subcategory":"Accounting & Tax Preparation",
            "type":"Services"
        }
    ],
    "sg:phone":"+1 703 327 5003",
    "sg:postcode":"20152",
    "sg:province":"VA",
    "sg:tags":[
        "project",
        "consulting"
    ],
    "wof:name":"Cjw Consulting",
    "wof:placetype":"venue"
},
  "geometry": {"coordinates":[-77.49500399999999,38.902209],"type":"Point"}
}