{
  "type": "Feature",
  "properties": {
    "addr:full":"6725 27th St N Arlington VA 22213",
    "addr:housenumber":"6725",
    "addr:postcode":"22213",
    "addr:street":"27Th St N",
    "iso:country":"US",
    "sg:address":"6725 27th St N",
    "sg:city":"Arlington",
    "sg:classifiers":[
        {
            "category":"Professional",
            "subcategory":"Art Services",
            "type":"Services"
        }
    ],
    "sg:phone":"+1 703 536 5290",
    "sg:postcode":"22213",
    "sg:province":"VA",
    "sg:tags":[
        "photography",
        "commercial"
    ],
    "wof:name":"Photography By Jon Wilkin",
    "wof:placetype":"venue"
},
  "geometry": {"coordinates":[-77.163263,38.891948],"type":"Point"}
}