{
  "type": "Feature",
  "properties": {
    "addr:full":"1232 Lake Meadow Ln Forest VA 24551",
    "addr:housenumber":"1232",
    "addr:postcode":"24551",
    "addr:street":"Lake Meadow Ln",
    "iso:country":"US",
    "sg:address":"1232 Lake Meadow Ln",
    "sg:city":"Forest",
    "sg:classifiers":[
        {
            "category":"Professional",
            "subcategory":"Management & Consulting",
            "type":"Services"
        }
    ],
    "sg:phone":"+1 434 258 6338",
    "sg:postcode":"24551",
    "sg:province":"VA",
    "sg:tags":[
        "technology"
    ],
    "wof:name":"Ipt Consulting",
    "wof:placetype":"venue"
},
  "geometry": {"coordinates":[-79.31379099999999,37.409118],"type":"Point"}
}