{
  "type": "Feature",
  "properties": {
    "addr:full":"2538 S Crater Rd Petersburg VA 23805",
    "addr:housenumber":"2538",
    "addr:postcode":"23805",
    "addr:street":"S Crater Rd",
    "iso:country":"US",
    "sg:address":"2538 S Crater Rd",
    "sg:city":"Petersburg",
    "sg:classifiers":[
        {
            "category":"Shopping",
            "subcategory":"Florist",
            "type":"Retail Goods"
        }
    ],
    "sg:phone":"+1 804 862 1484",
    "sg:postcode":"23805",
    "sg:province":"VA",
    "sg:tags":[
        "shop",
        "gift"
    ],
    "wof:name":"Barbara's Flowers & Gifts Inc",
    "wof:placetype":"venue"
},
  "geometry": {"coordinates":[-77.37699499999999,37.19792],"type":"Point"}
}