{
  "type": "Feature",
  "properties": {
    "iso:country":"US",
    "sg:address":"8575 King Carter St",
    "sg:city":"Manassas",
    "sg:classifiers":[
        {
            "category":"Professional",
            "subcategory":"Computer Services",
            "type":"Services"
        }
    ],
    "sg:phone":"+1 703 257 0604",
    "sg:postcode":"20110",
    "sg:province":"VA",
    "sg:tags":[
        "communications",
        "system",
        "integration"
    ],
    "wof:name":"Manassas System Integration",
    "wof:placetype":"venue"
},
  "geometry": {"coordinates":[-77.46415399999999,38.771351],"type":"Point"}
}