{
  "type": "Feature",
  "properties": {
    "addr:full":"2138 Wards Rd Lynchburg VA 24502",
    "addr:housenumber":"2138",
    "addr:postcode":"24502",
    "addr:street":"Wards Rd",
    "iso:country":"US",
    "sg:address":"2138 Wards Rd",
    "sg:city":"Lynchburg",
    "sg:classifiers":[
        {
            "category":"Building & Trades",
            "subcategory":"Equipment Rental",
            "type":"Services"
        }
    ],
    "sg:phone":"+1 434 237 0050",
    "sg:postcode":"24502",
    "sg:province":"VA",
    "sg:tags":[
        "leasing",
        "furniture"
    ],
    "wof:name":"Kelly Rentals Inc",
    "wof:placetype":"venue"
},
  "geometry": {"coordinates":[-79.184006,37.371577],"type":"Point"}
}