{
  "type": "Feature",
  "properties": {
    "addr:full":"33 Colony Rd Newport News VA 23602",
    "addr:housenumber":"33",
    "addr:postcode":"23602",
    "addr:street":"Colony Rd",
    "iso:country":"US",
    "sg:address":"33 Colony Rd",
    "sg:city":"Newport News",
    "sg:classifiers":[
        {
            "category":"Retail",
            "subcategory":"Auto Repair",
            "type":"Services"
        }
    ],
    "sg:phone":"+1 757 369 1912",
    "sg:postcode":"23602",
    "sg:province":"VA",
    "sg:tags":[
        "body",
        "automobile",
        "painting"
    ],
    "wof:name":"Thompson's Body Shop",
    "wof:placetype":"venue"
},
  "geometry": {"coordinates":[-76.51481800000001,37.115441],"type":"Point"}
}