{
  "type": "Feature",
  "properties": {
    "iso:country":"US",
    "sg:address":"117 Shooters Ct",
    "sg:city":"Alexandria",
    "sg:classifiers":[
        {
            "category":"Professional",
            "subcategory":"Management & Consulting",
            "type":"Services"
        }
    ],
    "sg:phone":"+1 703 519 4827",
    "sg:postcode":"22314",
    "sg:province":"VA",
    "wof:name":"Bkb International",
    "wof:placetype":"venue"
},
  "geometry": {"coordinates":[-77.06976,38.806949],"type":"Point"}
}