{
  "type": "Feature",
  "properties": {
    "iso:country":"US",
    "sg:address":"1160 Red Rose Ln",
    "sg:city":"Vinton",
    "sg:classifiers":[
        {
            "category":"Building & Trades",
            "subcategory":"Electrical",
            "type":"Services"
        }
    ],
    "sg:phone":"+1 540 890 3026",
    "sg:postcode":"24179",
    "sg:province":"VA",
    "sg:tags":[
        "repair",
        "electrical",
        "contractor"
    ],
    "wof:name":"K W H Communication System",
    "wof:placetype":"venue"
},
  "geometry": {"coordinates":[-79.85086699999999,37.26798],"type":"Point"}
}