{
  "type": "Feature",
  "properties": {
    "addr:full":"3996 Lafayette Blvd Fredericksburg VA 22408",
    "addr:housenumber":"3996",
    "addr:postcode":"22408",
    "addr:street":"Lafayette Blvd",
    "iso:country":"US",
    "sg:address":"3996 Lafayette Blvd",
    "sg:city":"Fredericksburg",
    "sg:classifiers":[
        {
            "category":"Restaurant",
            "type":"Food & Drink"
        }
    ],
    "sg:phone":"+1 540 898 0900",
    "sg:postcode":"22408",
    "sg:province":"VA",
    "sg:tags":[
        "pizza"
    ],
    "wof:name":"Sam's Pizza & Subs",
    "wof:placetype":"venue"
},
  "geometry": {"coordinates":[-77.492245,38.263514],"type":"Point"}
}