{
  "type": "Feature",
  "properties": {
    "addr:full":"4 Loudoun St SE Leesburg VA 20175",
    "addr:housenumber":"4",
    "addr:postcode":"20175",
    "addr:street":"Loudoun St Se",
    "iso:country":"US",
    "sg:address":"4 Loudoun St SE",
    "sg:city":"Leesburg",
    "sg:classifiers":[
        {
            "category":"Professional",
            "subcategory":"Lawyer & Legal Services",
            "type":"Services"
        }
    ],
    "sg:phone":"+1 703 593 5774",
    "sg:postcode":"20175",
    "sg:province":"VA",
    "sg:tags":[
        "attorney",
        "practice",
        "general"
    ],
    "wof:name":"Forrest E White PC",
    "wof:placetype":"venue"
},
  "geometry": {"coordinates":[-77.56504200000001,39.114308],"type":"Point"}
}