{
  "type": "Feature",
  "properties": {
    "addr:full":"104 McPherson Ct Seaford VA 23696",
    "addr:housenumber":"104",
    "addr:postcode":"23696",
    "addr:street":"Mcpherson Ct",
    "iso:country":"US",
    "sg:address":"104 McPherson Ct",
    "sg:city":"Seaford",
    "sg:classifiers":[
        {
            "category":"Retail",
            "subcategory":"Auto Repair",
            "type":"Services"
        }
    ],
    "sg:phone":"+1 757 234 0911",
    "sg:postcode":"23696",
    "sg:province":"VA",
    "sg:tags":[
        "automotive"
    ],
    "wof:name":"Skiffs Creek Towing Inc",
    "wof:placetype":"venue"
},
  "geometry": {"coordinates":[-76.435716,37.192184],"type":"Point"}
}