{
  "type": "Feature",
  "properties": {
    "addr:full":"432 Garrisonville Rd Stafford VA 22554",
    "addr:housenumber":"432",
    "addr:postcode":"22554",
    "addr:street":"Garrisonville Rd",
    "iso:country":"US",
    "sg:address":"432 Garrisonville Rd",
    "sg:city":"Stafford",
    "sg:classifiers":[
        {
            "category":"Restaurant",
            "type":"Food & Drink"
        }
    ],
    "sg:phone":"+1 540 657 5500",
    "sg:postcode":"22554",
    "sg:province":"VA",
    "wof:name":"El Asador Deli Market",
    "wof:placetype":"venue"
},
  "geometry": {"coordinates":[-77.430397,38.474602],"type":"Point"}
}