{
  "type": "Feature",
  "properties": {
    "addr:full":"8296C Old Courthouse Rd Tysons Corner VA 22067",
    "addr:housenumber":"8296c",
    "addr:postcode":"22067",
    "addr:street":"Old Courthouse Rd",
    "iso:country":"US",
    "sg:address":"8296C Old Courthouse Rd",
    "sg:city":"Tysons Corner",
    "sg:classifiers":[
        {
            "category":"Health Services",
            "subcategory":"Clinic",
            "type":"Services"
        }
    ],
    "sg:phone":"+1 703 356 8237",
    "sg:postcode":"22067",
    "sg:province":"VA",
    "sg:tags":[
        "counseling",
        "mental"
    ],
    "wof:name":"Malawista Peter Dr",
    "wof:placetype":"venue"
},
  "geometry": {"coordinates":[-77.231359,38.913917],"type":"Point"}
}