{
  "type": "Feature",
  "properties": {
    "addr:full":"1322 Volunteer Pkwy Bristol VA 37620",
    "addr:housenumber":"1322",
    "addr:postcode":"37620",
    "addr:street":"Volunteer Pkwy",
    "iso:country":"US",
    "sg:address":"1322 Volunteer Pkwy",
    "sg:city":"Bristol",
    "sg:classifiers":[
        {
            "category":"Personal",
            "subcategory":"Barber",
            "type":"Services"
        }
    ],
    "sg:phone":"+1 423 764 2313",
    "sg:postcode":"37620",
    "sg:province":"VA",
    "sg:tags":[
        "shop"
    ],
    "wof:name":"Southside Barber & Style Shop",
    "wof:placetype":"venue"
},
  "geometry": {"coordinates":[-82.20905399999999,36.562494],"type":"Point"}
}