{
  "type": "Feature",
  "properties": {
    "addr:full":"7143 Chestnut Church Rd Mechanicsville VA 23116",
    "addr:housenumber":"7143",
    "addr:postcode":"23116",
    "addr:street":"Chestnut Church Rd",
    "iso:country":"US",
    "sg:address":"7143 Chestnut Church Rd",
    "sg:city":"Mechanicsville",
    "sg:classifiers":[
        {
            "category":"Retail",
            "subcategory":"Auto Repair",
            "type":"Services"
        }
    ],
    "sg:phone":"+1 804 230 8713",
    "sg:postcode":"23116",
    "sg:province":"VA",
    "sg:tags":[
        "automotive"
    ],
    "wof:name":"Atlantic Truck Repair",
    "wof:placetype":"venue"
},
  "geometry": {"coordinates":[-77.342967,37.708693],"type":"Point"}
}