{
  "type": "Feature",
  "properties": {
    "addr:full":"2600 Gayton Grove Rd Richmond VA 23233",
    "addr:housenumber":"2600",
    "addr:postcode":"23233",
    "addr:street":"Gayton Grove Rd",
    "iso:country":"US",
    "sg:address":"2600 Gayton Grove Rd",
    "sg:city":"Richmond",
    "sg:classifiers":[
        {
            "category":"Home & Garden",
            "subcategory":"Building Materials",
            "type":"Retail Goods"
        }
    ],
    "sg:phone":"+1 804 360 4000",
    "sg:postcode":"23233",
    "sg:province":"VA",
    "wof:name":"Tindall Concrete Products",
    "wof:placetype":"venue"
},
  "geometry": {"coordinates":[-77.635209,37.632511],"type":"Point"}
}