{
  "type": "Feature",
  "properties": {
    "iso:country":"US",
    "sg:address":"114 W Broad St",
    "sg:city":"Falls Church",
    "sg:classifiers":[
        {
            "category":"Banks & Credit Unions",
            "subcategory":"Bank",
            "type":"Services"
        }
    ],
    "sg:phone":"+1 703 534 5208",
    "sg:postcode":"22046",
    "sg:province":"VA",
    "sg:tags":[
        "cashing",
        "check"
    ],
    "wof:name":"Check Cashing & Payday Loan",
    "wof:placetype":"venue"
},
  "geometry": {"coordinates":[-77.172021,38.882884],"type":"Point"}
}