{
  "type": "Feature",
  "properties": {
    "addr:full":"2538 Youngs Dr Haymarket VA 20169",
    "addr:housenumber":"2538",
    "addr:postcode":"20169",
    "addr:street":"Youngs Dr",
    "iso:country":"US",
    "sg:address":"2538 Youngs Dr",
    "sg:city":"Haymarket",
    "sg:classifiers":[
        {
            "category":"Manufacturing",
            "subcategory":"Metals",
            "type":"Manufacturing & Wholesale Goods"
        }
    ],
    "sg:phone":"+1 703 754 3316",
    "sg:postcode":"20169",
    "sg:province":"VA",
    "wof:name":"All Blast Sandblasting",
    "wof:placetype":"venue"
},
  "geometry": {"coordinates":[-77.66448699999999,38.903336],"type":"Point"}
}