{
  "type": "Feature",
  "properties": {
    "addr:full":"368 Goods Ln Aroda VA 22709",
    "addr:housenumber":"368",
    "addr:postcode":"22709",
    "addr:street":"Goods Ln",
    "iso:country":"US",
    "sg:address":"368 Goods Ln",
    "sg:city":"Aroda",
    "sg:classifiers":[
        {
            "category":"Retail",
            "subcategory":"Auto Repair",
            "type":"Services"
        }
    ],
    "sg:phone":"+1 540 672 1301",
    "sg:postcode":"22709",
    "sg:province":"VA",
    "sg:tags":[
        "shop",
        "general"
    ],
    "wof:name":"Jims Automotive",
    "wof:placetype":"venue"
},
  "geometry": {"coordinates":[-78.19780799999999,38.338839],"type":"Point"}
}