{
  "type": "Feature",
  "properties": {
    "addr:full":"6738 Celt Rd Stanardsville VA 22973",
    "addr:housenumber":"6738",
    "addr:postcode":"22973",
    "addr:street":"Celt Rd",
    "iso:country":"US",
    "sg:address":"6738 Celt Rd",
    "sg:city":"Stanardsville",
    "sg:classifiers":[
        {
            "category":"Building & Trades",
            "subcategory":"Landscaping Services",
            "type":"Services"
        }
    ],
    "sg:phone":"+1 434 466 6665",
    "sg:postcode":"22973",
    "sg:province":"VA",
    "sg:tags":[
        "lawn",
        "maintenance",
        "grounds"
    ],
    "wof:name":"Greens Keeper Lndscpg & Lawn",
    "wof:placetype":"venue"
},
  "geometry": {"coordinates":[-78.474965,38.229509],"type":"Point"}
}