{
  "type": "Feature",
  "properties": {
    "addr:full":"1148 Volvo Pkwy Chesapeake VA 23320",
    "addr:housenumber":"1148",
    "addr:postcode":"23320",
    "addr:street":"Volvo Pkwy",
    "iso:country":"US",
    "sg:address":"1148 Volvo Pkwy",
    "sg:city":"Chesapeake",
    "sg:classifiers":[
        {
            "category":"Autos & Motor Vehicles",
            "subcategory":"Fuel & Gas Station",
            "type":"Retail Goods"
        }
    ],
    "sg:phone":"+1 757 436 1533",
    "sg:postcode":"23320",
    "sg:province":"VA",
    "sg:tags":[
        "station",
        "gasoline"
    ],
    "wof:name":"Getty",
    "wof:placetype":"venue"
},
  "geometry": {"coordinates":[-76.221971,36.769455],"type":"Point"}
}