{
  "type": "Feature",
  "properties": {
    "addr:full":"1024 Old Quarry Rd Ringgold VA 24586",
    "addr:housenumber":"1024",
    "addr:postcode":"24586",
    "addr:street":"Old Quarry Rd",
    "iso:country":"US",
    "sg:address":"1024 Old Quarry Rd",
    "sg:city":"Ringgold",
    "sg:classifiers":[
        {
            "category":"Professional",
            "subcategory":"Computer Services",
            "type":"Services"
        }
    ],
    "sg:phone":"+1 434 822 7019",
    "sg:postcode":"24586",
    "sg:province":"VA",
    "sg:tags":[
        "programing",
        "custom"
    ],
    "sg:website":"www.iscmall.com",
    "wof:name":"Studio Deluxe Intl",
    "wof:placetype":"venue"
},
  "geometry": {"coordinates":[-79.339736,36.629422],"type":"Point"}
}