{
  "type": "Feature",
  "properties": {
    "addr:full":"11886 Colonial Trl W Spring Grove VA 23881",
    "addr:housenumber":"11886",
    "addr:postcode":"23881",
    "addr:street":"Colonial Trl W",
    "iso:country":"US",
    "sg:address":"11886 Colonial Trl W",
    "sg:city":"Spring Grove",
    "sg:classifiers":[
        {
            "category":"Shopping",
            "subcategory":"Gifts & Souvenirs",
            "type":"Retail Goods"
        }
    ],
    "sg:phone":"+1 757 866 0188",
    "sg:postcode":"23881",
    "sg:province":"VA",
    "sg:tags":[
        "shop"
    ],
    "wof:name":"Cabin Point Gifts Thrifts & Mr",
    "wof:placetype":"venue"
},
  "geometry": {"coordinates":[-77.031778,37.184988],"type":"Point"}
}