{
  "type": "Feature",
  "properties": {
    "addr:full":"700 Amberline Ct Chesapeake VA 23322",
    "addr:housenumber":"700",
    "addr:postcode":"23322",
    "addr:street":"Amberline Ct",
    "iso:country":"US",
    "sg:address":"700 Amberline Ct",
    "sg:city":"Chesapeake",
    "sg:classifiers":[
        {
            "category":"Building & Trades",
            "subcategory":"Cleaning & Sanitation",
            "type":"Services"
        }
    ],
    "sg:phone":"+1 757 436 9306",
    "sg:postcode":"23322",
    "sg:province":"VA",
    "sg:tags":[
        "maintenance"
    ],
    "wof:name":"Lettemicael Cleaning Services",
    "wof:placetype":"venue"
},
  "geometry": {"coordinates":[-76.269426,36.694914],"type":"Point"}
}