{
  "type": "Feature",
  "properties": {
    "addr:full":"1000 N Arlington Mill Dr Arlington VA 22205",
    "addr:housenumber":"1000",
    "addr:postcode":"22205",
    "addr:street":"N Arlington Mill Dr",
    "iso:country":"US",
    "sg:address":"1000 N Arlington Mill Dr",
    "sg:city":"Arlington",
    "sg:classifiers":[
        {
            "category":"Transit Center",
            "subcategory":"Passenger",
            "type":"Transportation"
        },
        {
            "category":"Personal",
            "type":"Services"
        },
        {
            "category":"Professional",
            "subcategory":"Business Services",
            "type":"Services"
        }
    ],
    "sg:phone":"+1 703 994 3931",
    "sg:postcode":"22205",
    "sg:province":"VA",
    "sg:tags":[
        "delivery",
        "towing",
        "courier"
    ],
    "sg:website":"www.driversIncorporated.com",
    "wof:name":"Drivers Incorporated",
    "wof:placetype":"venue"
},
  "geometry": {"coordinates":[-77.137011,38.877014],"type":"Point"}
}