{
  "type": "Feature",
  "properties": {
    "addr:full":"7418 Beulah St Alexandria VA 22315",
    "addr:housenumber":"7418",
    "addr:postcode":"22315",
    "addr:street":"Beulah St",
    "iso:country":"US",
    "sg:address":"7418 Beulah St",
    "sg:city":"Alexandria",
    "sg:classifiers":[
        {
            "category":"Freight",
            "type":"Transportation"
        }
    ],
    "sg:phone":"+1 703 922 9256",
    "sg:postcode":"22315",
    "sg:province":"VA",
    "sg:tags":[
        "operator",
        "local",
        "trucking"
    ],
    "wof:name":"Franklin Trucking",
    "wof:placetype":"venue"
},
  "geometry": {"coordinates":[-77.16328300000001,38.756968],"type":"Point"}
}