{
  "type": "Feature",
  "properties": {
    "addr:full":"1214 County St Portsmouth VA 23704",
    "addr:housenumber":"1214",
    "addr:postcode":"23704",
    "addr:street":"County St",
    "iso:country":"US",
    "sg:address":"1214 County St",
    "sg:city":"Portsmouth",
    "sg:classifiers":[
        {
            "category":"Government",
            "subcategory":"Office",
            "type":"Public Place"
        }
    ],
    "sg:phone":"+1 757 397 8209",
    "sg:postcode":"23704",
    "sg:province":"VA",
    "sg:website":"www.lucaslodge.com",
    "wof:name":"Senator L Louise Lucas",
    "wof:placetype":"venue"
},
  "geometry": {"coordinates":[-76.31385400000001,36.83355],"type":"Point"}
}