{
  "type": "Feature",
  "properties": {
    "addr:full":"401 Princess Anne St Fredericksburg VA 22401",
    "addr:housenumber":"401",
    "addr:postcode":"22401",
    "addr:street":"Princess Anne St",
    "iso:country":"US",
    "sg:address":"401 Princess Anne St",
    "sg:city":"Fredericksburg",
    "sg:classifiers":[
        {
            "category":"Wholesale",
            "subcategory":"Groceries",
            "type":"Manufacturing & Wholesale Goods"
        }
    ],
    "sg:phone":"+1 540 373 8362",
    "sg:postcode":"22401",
    "sg:province":"VA",
    "sg:tags":[
        "food",
        "broker"
    ],
    "wof:name":"Janney Marshall Co",
    "wof:placetype":"venue"
},
  "geometry": {"coordinates":[-77.45721399999999,38.297881],"type":"Point"}
}