{
  "type": "Feature",
  "properties": {
    "addr:full":"3703 Pickett Rd Fairfax VA 22031",
    "addr:housenumber":"3703",
    "addr:postcode":"22031",
    "addr:street":"Pickett Rd",
    "iso:country":"US",
    "sg:address":"3703 Pickett Rd",
    "sg:city":"Fairfax",
    "sg:classifiers":[
        {
            "category":"Home & Garden",
            "subcategory":"Home Furnishings",
            "type":"Retail Goods"
        },
        {
            "category":"Home & Garden",
            "subcategory":"Building Materials",
            "type":"Retail Goods"
        },
        {
            "category":"Building & Trades",
            "subcategory":"Construction",
            "type":"Services"
        },
        {
            "category":"Manufacturing",
            "subcategory":"Building Materials",
            "type":"Manufacturing & Wholesale Goods"
        },
        {
            "category":"Home & Garden",
            "subcategory":"Furniture",
            "type":"Retail Goods"
        }
    ],
    "sg:phone":"+1 703 425 5703",
    "sg:postcode":"22031",
    "sg:province":"VA",
    "sg:tags":[
        "industrial",
        "solid",
        "cabinetmakers-commercial",
        "counter",
        "surface",
        "equipment-household",
        "refacing",
        "resurfacing",
        "maker",
        "cabinet",
        "top",
        "cabinets-refinishing",
        "kitchen"
    ],
    "wof:name":"Professional Cabinetry Inc",
    "wof:placetype":"venue"
},
  "geometry": {"coordinates":[-77.27285000000001,38.849571],"type":"Point"}
}