{
  "type": "Feature",
  "properties": {
    "addr:full":"824 Cherry Ave Charlottesville VA 22903",
    "addr:housenumber":"824",
    "addr:postcode":"22903",
    "addr:street":"Cherry Ave",
    "iso:country":"US",
    "sg:address":"824 Cherry Ave",
    "sg:city":"Charlottesville",
    "sg:classifiers":[
        {
            "category":"Personal",
            "subcategory":"Barber",
            "type":"Services"
        }
    ],
    "sg:phone":"+1 434 977 2887",
    "sg:postcode":"22903",
    "sg:province":"VA",
    "wof:name":"Cherry Avenue Barber Shop",
    "wof:placetype":"venue"
},
  "geometry": {"coordinates":[-78.493167,38.028391],"type":"Point"}
}