{
  "type": "Feature",
  "properties": {
    "iso:country":"US",
    "sg:address":"1800 Azalea Ave",
    "sg:city":"Portsmouth",
    "sg:classifiers":[
        {
            "category":"Organizations",
            "subcategory":"Religious Organization",
            "type":"Services"
        }
    ],
    "sg:phone":"+1 757 397 4398",
    "sg:postcode":"23704",
    "sg:province":"VA",
    "sg:tags":[
        "church"
    ],
    "wof:name":"Macedonia Church God In Christ",
    "wof:placetype":"venue"
},
  "geometry": {"coordinates":[-76.320576,36.824766],"type":"Point"}
}