{
  "type": "Feature",
  "properties": {
    "iso:country":"US",
    "sg:address":"850 Kempsville Rd",
    "sg:city":"Norfolk",
    "sg:classifiers":[
        {
            "category":"Health Services",
            "subcategory":"Doctor",
            "type":"Services"
        }
    ],
    "sg:phone":"+1 757 466 5900",
    "sg:postcode":"23502",
    "sg:province":"VA",
    "sg:tags":[
        "physician"
    ],
    "wof:name":"Smg Norfolk Diagnostic Clinic",
    "wof:placetype":"venue"
},
  "geometry": {"coordinates":[-76.19144,36.849993],"type":"Point"}
}