{
  "type": "Feature",
  "properties": {
    "iso:country":"US",
    "sg:address":"7411 Gatewood Ct",
    "sg:city":"Alexandria",
    "sg:classifiers":[
        {
            "category":"Professional",
            "subcategory":"Management & Consulting",
            "type":"Services"
        }
    ],
    "sg:phone":"+1 703 775 3178",
    "sg:postcode":"22307",
    "sg:province":"VA",
    "wof:name":"George W Handy",
    "wof:placetype":"venue"
},
  "geometry": {"coordinates":[-77.053594,38.756089],"type":"Point"}
}