{
  "type": "Feature",
  "properties": {
    "addr:full":"1450 S Military Hwy Chesapeake VA 23320",
    "addr:housenumber":"1450",
    "addr:postcode":"23320",
    "addr:street":"S Military Hwy",
    "iso:country":"US",
    "sg:address":"1450 S Military Hwy",
    "sg:city":"Chesapeake",
    "sg:classifiers":[
        {
            "category":"Banks & Credit Unions",
            "subcategory":"Bank",
            "type":"Services"
        }
    ],
    "sg:phone":"+1 757 523 2642",
    "sg:postcode":"23320",
    "sg:province":"VA",
    "sg:website":"www.heritagenorfolk.com",
    "wof:name":"Heritage Bank & Trust",
    "wof:placetype":"venue"
},
  "geometry": {"coordinates":[-76.23419,36.797606],"type":"Point"}
}