{
  "type": "Feature",
  "properties": {
    "iso:country":"US",
    "sg:address":"9306 Old Keene Mill Rd",
    "sg:city":"Burke",
    "sg:classifiers":[
        {
            "category":"Retail",
            "subcategory":"Repair Shop",
            "type":"Services"
        }
    ],
    "sg:phone":"+1 703 455 3320",
    "sg:postcode":"22015",
    "sg:province":"VA",
    "wof:name":"Signet TV LLC",
    "wof:placetype":"venue"
},
  "geometry": {"coordinates":[-77.26827299999999,38.776146],"type":"Point"}
}