{
  "type": "Feature",
  "properties": {
    "addr:full":"8560 Center Rd Newington VA 22152",
    "addr:housenumber":"8560",
    "addr:postcode":"22152",
    "addr:street":"Center Rd",
    "iso:country":"US",
    "sg:address":"8560 Center Rd",
    "sg:city":"Newington",
    "sg:classifiers":[
        {
            "category":"Building & Trades",
            "subcategory":"Construction",
            "type":"Services"
        }
    ],
    "sg:phone":"+1 703 339 3383",
    "sg:postcode":"22152",
    "sg:province":"VA",
    "sg:tags":[
        "contractor"
    ],
    "sg:website":"www.colonialmechanical.com",
    "wof:name":"Colonial Mech Corp",
    "wof:placetype":"venue"
},
  "geometry": {"coordinates":[-77.24150400000001,38.787477],"type":"Point"}
}