{
  "type": "Feature",
  "properties": {
    "addr:full":"3300 Old Bridge Rd Woodbridge VA 22192",
    "addr:housenumber":"3300",
    "addr:postcode":"22192",
    "addr:street":"Old Bridge Rd",
    "iso:country":"US",
    "sg:address":"3300 Old Bridge Rd",
    "sg:city":"Woodbridge",
    "sg:classifiers":[
        {
            "category":"Retail",
            "subcategory":"Laundry & Dry Cleaning",
            "type":"Services"
        }
    ],
    "sg:phone":"+1 703 492 4647",
    "sg:postcode":"22192",
    "sg:province":"VA",
    "sg:tags":[
        "drycleaning",
        "plant",
        "cleaners"
    ],
    "wof:name":"Superior Cleaners Inc",
    "wof:placetype":"venue"
},
  "geometry": {"coordinates":[-77.31386500000001,38.684825],"type":"Point"}
}