{
  "type": "Feature",
  "properties": {
    "addr:full":"817 Brooke Rd Virginia Beach VA 23454",
    "addr:housenumber":"817",
    "addr:postcode":"23454",
    "addr:street":"Brooke Rd",
    "iso:country":"US",
    "sg:address":"817 Brooke Rd",
    "sg:city":"Virginia Beach",
    "sg:classifiers":[
        {
            "category":"Professional",
            "subcategory":"Management & Consulting",
            "type":"Services"
        }
    ],
    "sg:phone":"+1 757 496 2102",
    "sg:postcode":"23454",
    "sg:province":"VA",
    "wof:name":"Dana D Barclay Ltd",
    "wof:placetype":"venue"
},
  "geometry": {"coordinates":[-76.049273,36.858899],"type":"Point"}
}