{
  "type": "Feature",
  "properties": {
    "iso:country":"US",
    "sg:address":"9415 Old Burke Lake Rd",
    "sg:city":"Burke",
    "sg:classifiers":[
        {
            "category":"Insurance",
            "subcategory":"Insurance Agent",
            "type":"Services"
        }
    ],
    "sg:phone":"+1 703 978 5700",
    "sg:postcode":"22015",
    "sg:province":"VA",
    "wof:name":"Shields Rudy",
    "wof:placetype":"venue"
},
  "geometry": {"coordinates":[-77.27067700000001,38.794359],"type":"Point"}
}