{
  "type": "Feature",
  "properties": {
    "addr:full":"500 Mountain View Rd Independence VA 24348",
    "addr:housenumber":"500",
    "addr:postcode":"24348",
    "addr:street":"Mountain View Rd",
    "iso:country":"US",
    "sg:address":"500 Mountain View Rd",
    "sg:city":"Independence",
    "sg:classifiers":[
        {
            "category":"Organizations",
            "subcategory":"Religious Organization",
            "type":"Services"
        }
    ],
    "sg:phone":"+1 276 773 3939",
    "sg:postcode":"24348",
    "sg:province":"VA",
    "sg:tags":[
        "church"
    ],
    "wof:name":"Mt View Baptist Church",
    "wof:placetype":"venue"
},
  "geometry": {"coordinates":[-81.187884,36.587519],"type":"Point"}
}