{
  "type": "Feature",
  "properties": {
    "addr:full":"9866 Main St Fairfax VA 22031",
    "addr:housenumber":"9866",
    "addr:postcode":"22031",
    "addr:street":"Main St",
    "iso:country":"US",
    "sg:address":"9866 Main St",
    "sg:city":"Fairfax",
    "sg:classifiers":[
        {
            "category":"Real Estate",
            "subcategory":"Real Estate Operator",
            "type":"Services"
        }
    ],
    "sg:phone":"+1 703 273 3200",
    "sg:postcode":"22031",
    "sg:province":"VA",
    "sg:tags":[
        "building",
        "parks"
    ],
    "wof:name":"Fairfax Square Professional",
    "wof:placetype":"venue"
},
  "geometry": {"coordinates":[-77.289171,38.843501],"type":"Point"}
}