{
  "type": "Feature",
  "properties": {
    "addr:full":"13902 Walney Way Chantilly VA 20151",
    "addr:housenumber":"13902",
    "addr:postcode":"20151",
    "addr:street":"Walney Way",
    "iso:country":"US",
    "sg:address":"13902 Walney Way",
    "sg:city":"Chantilly",
    "sg:classifiers":[
        {
            "category":"Professional",
            "subcategory":"Lawyer & Legal Services",
            "type":"Services"
        }
    ],
    "sg:phone":"+1 703 802 1132",
    "sg:postcode":"20151",
    "sg:province":"VA",
    "wof:name":"Glenn Wainer",
    "wof:placetype":"venue"
},
  "geometry": {"coordinates":[-77.42777100000001,38.868981],"type":"Point"}
}