{
  "type": "Feature",
  "properties": {
    "addr:full":"120 23rd St SE Roanoke VA 24014",
    "addr:housenumber":"120",
    "addr:postcode":"24014",
    "addr:street":"23Rd St Se",
    "iso:country":"US",
    "sg:address":"120 23rd St SE",
    "sg:city":"Roanoke",
    "sg:classifiers":[
        {
            "category":"Professional",
            "subcategory":"Business Services",
            "type":"Services"
        }
    ],
    "sg:phone":"+1 540 343 1111",
    "sg:postcode":"24014",
    "sg:province":"VA",
    "wof:name":"Rockside Design",
    "wof:placetype":"venue"
},
  "geometry": {"coordinates":[-79.944086,37.246651],"type":"Point"}
}