{
  "type": "Feature",
  "properties": {
    "iso:country":"US",
    "sg:address":"1468 Lake James Dr",
    "sg:city":"Virginia Beach",
    "sg:classifiers":[
        {
            "category":"Freight",
            "type":"Transportation"
        }
    ],
    "sg:phone":"+1 757 523 1195",
    "sg:postcode":"23464",
    "sg:province":"VA",
    "wof:name":"Transline Transport Inc",
    "wof:placetype":"venue"
},
  "geometry": {"coordinates":[-76.184798,36.792442],"type":"Point"}
}