{
  "type": "Feature",
  "properties": {
    "addr:full":"14612 Stone Range Dr Centreville VA 20120",
    "addr:housenumber":"14612",
    "addr:postcode":"20120",
    "addr:street":"Stone Range Dr",
    "iso:country":"US",
    "sg:address":"14612 Stone Range Dr",
    "sg:city":"Centreville",
    "sg:classifiers":[
        {
            "category":"Freight",
            "type":"Transportation"
        }
    ],
    "sg:phone":"+1 703 968 7172",
    "sg:postcode":"20120",
    "sg:province":"VA",
    "sg:tags":[
        "trucking"
    ],
    "wof:name":"Economy Hauling",
    "wof:placetype":"venue"
},
  "geometry": {"coordinates":[-77.451722,38.853019],"type":"Point"}
}