{
  "type": "Feature",
  "properties": {
    "addr:full":"288 N Main St Harrisonburg VA 22802",
    "addr:housenumber":"288",
    "addr:postcode":"22802",
    "addr:street":"N Main St",
    "iso:country":"US",
    "sg:address":"288 N Main St",
    "sg:city":"Harrisonburg",
    "sg:classifiers":[
        {
            "category":"Food & Beverages",
            "subcategory":"Groceries & Convenience Stores",
            "type":"Retail Goods"
        }
    ],
    "sg:phone":"+1 540 574 3472",
    "sg:postcode":"22802",
    "sg:province":"VA",
    "wof:name":"Mimi Chuacan",
    "wof:placetype":"venue"
},
  "geometry": {"coordinates":[-78.867969,38.451472],"type":"Point"}
}