{
  "type": "Feature",
  "properties": {
    "iso:country":"US",
    "sg:address":"209 Otey St",
    "sg:city":"Blacksburg",
    "sg:classifiers":[
        {
            "category":"Organizations",
            "subcategory":"Community Association",
            "type":"Services"
        }
    ],
    "sg:phone":"+1 540 953 3904",
    "sg:postcode":"24060",
    "sg:province":"VA",
    "wof:name":"Alliance For Excellence",
    "wof:placetype":"venue"
},
  "geometry": {"coordinates":[-80.415325,37.226933],"type":"Point"}
}