{
  "type": "Feature",
  "properties": {
    "addr:full":"11343 Nuckols Rd Glen Allen VA 23059",
    "addr:housenumber":"11343",
    "addr:postcode":"23059",
    "addr:street":"Nuckols Rd",
    "iso:country":"US",
    "sg:address":"11343 Nuckols Rd",
    "sg:city":"Glen Allen",
    "sg:classifiers":[
        {
            "category":"Personal",
            "subcategory":"Beauty Salon",
            "type":"Services"
        }
    ],
    "sg:phone":"+1 804 967 9976",
    "sg:postcode":"23059",
    "sg:province":"VA",
    "wof:name":"Hair Cuttery",
    "wof:placetype":"venue"
},
  "geometry": {"coordinates":[-77.589399,37.682619],"type":"Point"}
}