{
  "type": "Feature",
  "properties": {
    "addr:full":"13503 Taylorstown Rd Leesburg VA 20176",
    "addr:postcode":"13503;20176",
    "addr:street":"Taylorstown Rd",
    "iso:country":"US",
    "sg:address":"13503 Taylorstown Rd",
    "sg:city":"Leesburg",
    "sg:classifiers":[
        {
            "category":"Building & Trades",
            "subcategory":"Construction",
            "type":"Services"
        }
    ],
    "sg:phone":"+1 703 777 9493",
    "sg:postcode":"20176",
    "sg:province":"VA",
    "sg:tags":[
        "home",
        "improvement"
    ],
    "wof:name":"Myrus Construction",
    "wof:placetype":"venue"
},
  "geometry": {"coordinates":[-77.573178,39.253357],"type":"Point"}
}