{
  "type": "Feature",
  "properties": {
    "addr:full":"6611 Elkhardt Rd Richmond VA 23225",
    "addr:housenumber":"6611",
    "addr:postcode":"23225",
    "addr:street":"Elkhardt Rd",
    "iso:country":"US",
    "sg:address":"6611 Elkhardt Rd",
    "sg:city":"Richmond",
    "sg:classifiers":[
        {
            "category":"Social Services",
            "subcategory":"Child Care",
            "type":"Services"
        }
    ],
    "sg:phone":"+1 804 276 0959",
    "sg:postcode":"23225",
    "sg:province":"VA",
    "sg:tags":[
        "day"
    ],
    "wof:name":"C N I 64",
    "wof:placetype":"venue"
},
  "geometry": {"coordinates":[-77.51669800000001,37.479121],"type":"Point"}
}