{
  "type": "Feature",
  "properties": {
    "addr:full":"4518 Read Mountain Rd Cloverdale VA 24077",
    "addr:housenumber":"4518",
    "addr:postcode":"24077",
    "addr:street":"Read Mountain Rd",
    "iso:country":"US",
    "sg:address":"4518 Read Mountain Rd",
    "sg:city":"Cloverdale",
    "sg:classifiers":[
        {
            "category":"Government",
            "subcategory":"Post Office",
            "type":"Public Place"
        }
    ],
    "sg:phone":"+1 540 992 2334",
    "sg:postcode":"24077",
    "sg:province":"VA",
    "wof:name":"US Post Office",
    "wof:placetype":"venue"
},
  "geometry": {"coordinates":[-79.905587,37.364554],"type":"Point"}
}