{
  "type": "Feature",
  "properties": {
    "iso:country":"US",
    "sg:address":"7214 Hansford Ct",
    "sg:city":"Springfield",
    "sg:classifiers":[
        {
            "category":"Professional",
            "subcategory":"Management & Consulting",
            "type":"Services"
        }
    ],
    "sg:phone":"+1 703 354 8254",
    "sg:postcode":"22151",
    "sg:province":"VA",
    "sg:tags":[
        "international",
        "grocery",
        "store",
        "consultant"
    ],
    "wof:name":"Emerging Markets Institute",
    "wof:placetype":"venue"
},
  "geometry": {"coordinates":[-77.192487,38.810441],"type":"Point"}
}