{
  "type": "Feature",
  "properties": {
    "addr:full":"1496 Teague Dr Mc Lean VA 22101",
    "addr:housenumber":"1496",
    "addr:postcode":"22101",
    "addr:street":"Teague Dr",
    "iso:country":"US",
    "sg:address":"1496 Teague Dr",
    "sg:city":"Mc Lean",
    "sg:classifiers":[
        {
            "category":"Professional",
            "subcategory":"Lawyer & Legal Services",
            "type":"Services"
        }
    ],
    "sg:phone":"+1 703 448 6000",
    "sg:postcode":"22101",
    "sg:province":"VA",
    "wof:name":"Rubin Stephen ESQ",
    "wof:placetype":"venue"
},
  "geometry": {"coordinates":[-77.19411100000001,38.931256],"type":"Point"}
}