{
  "type": "Feature",
  "properties": {
    "iso:country":"US",
    "sg:address":"3176 Summit Square Dr",
    "sg:city":"Oakton",
    "sg:classifiers":[
        {
            "category":"Wholesale",
            "subcategory":"Computers",
            "type":"Manufacturing & Wholesale Goods"
        }
    ],
    "sg:phone":"+1 703 255 7111",
    "sg:postcode":"22124",
    "sg:province":"VA",
    "sg:tags":[
        "communications",
        "datum"
    ],
    "wof:name":"Fibercom Technologies Corp",
    "wof:placetype":"venue"
},
  "geometry": {"coordinates":[-77.299559,38.871882],"type":"Point"}
}