{
  "type": "Feature",
  "properties": {
    "iso:country":"US",
    "sg:address":"1306 Northgate Sq",
    "sg:city":"Reston",
    "sg:classifiers":[
        {
            "category":"Professional",
            "subcategory":"Business Services",
            "type":"Services"
        }
    ],
    "sg:phone":"+1 703 467 8289",
    "sg:postcode":"20190",
    "sg:province":"VA",
    "sg:tags":[
        "mediator"
    ],
    "wof:name":"Karen C Adkins-Hastings",
    "wof:placetype":"venue"
},
  "geometry": {"coordinates":[-77.337125,38.972072],"type":"Point"}
}