{
  "type": "Feature",
  "properties": {
    "addr:full":"813 W Broad St Richmond VA 23220",
    "addr:housenumber":"813",
    "addr:postcode":"23220",
    "addr:street":"W Broad St",
    "iso:country":"US",
    "sg:address":"813 W Broad St",
    "sg:city":"Richmond",
    "sg:classifiers":[
        {
            "category":"Professional",
            "type":"Services"
        }
    ],
    "sg:phone":"+1 804 213 0210",
    "sg:postcode":"23220",
    "sg:province":"VA",
    "sg:tags":[
        "establishment"
    ],
    "wof:name":"Bellona Arsenal Farm",
    "wof:placetype":"venue"
},
  "geometry": {"coordinates":[-77.449084,37.549835],"type":"Point"}
}