{
  "type": "Feature",
  "properties": {
    "addr:full":"37 Leland Rd Rustburg VA 24588",
    "addr:housenumber":"37",
    "addr:postcode":"24588",
    "addr:street":"Leland Rd",
    "iso:country":"US",
    "sg:address":"37 Leland Rd",
    "sg:city":"Rustburg",
    "sg:classifiers":[
        {
            "category":"Building & Trades",
            "subcategory":"Construction",
            "type":"Services"
        }
    ],
    "sg:phone":"+1 434 821 2774",
    "sg:postcode":"24588",
    "sg:province":"VA",
    "sg:tags":[
        "excavation",
        "excavating",
        "contractor"
    ],
    "wof:name":"Counts & Dobyns Excavating Inc",
    "wof:placetype":"venue"
},
  "geometry": {"coordinates":[-79.16462900000001,37.287923],"type":"Point"}
}