{
  "type": "Feature",
  "properties": {
    "addr:full":"10152 Atlee Station Rd Mechanicsville VA 23116",
    "addr:housenumber":"10152",
    "addr:postcode":"23116",
    "addr:street":"Atlee Station Rd",
    "iso:country":"US",
    "sg:address":"10152 Atlee Station Rd",
    "sg:city":"Mechanicsville",
    "sg:classifiers":[
        {
            "category":"Professional",
            "type":"Services"
        }
    ],
    "sg:phone":"+1 804 746 7532",
    "sg:postcode":"23116",
    "sg:province":"VA",
    "wof:name":"Arthur P Graham Rev",
    "wof:placetype":"venue"
},
  "geometry": {"coordinates":[-77.424662,37.678045],"type":"Point"}
}