{
  "type": "Feature",
  "properties": {
    "addr:full":"2241 S Main St Harrisonburg VA 22801",
    "addr:housenumber":"2241",
    "addr:postcode":"22801",
    "addr:street":"S Main St",
    "iso:country":"US",
    "sg:address":"2241 S Main St",
    "sg:city":"Harrisonburg",
    "sg:classifiers":[
        {
            "category":"Restaurant",
            "type":"Food & Drink"
        }
    ],
    "sg:phone":"+1 540 432 6262",
    "sg:postcode":"22801",
    "sg:province":"VA",
    "sg:tags":[
        "eating"
    ],
    "wof:name":"Pupuseria Salvadorena Rstrnt",
    "wof:placetype":"venue"
},
  "geometry": {"coordinates":[-78.89237,38.421807],"type":"Point"}
}