{
  "type": "Feature",
  "properties": {
    "iso:country":"US",
    "sg:address":"4508 Lee Hwy",
    "sg:city":"Arlington",
    "sg:classifiers":[
        {
            "category":"Food & Beverages",
            "subcategory":"Liquor & Beverages",
            "type":"Retail Goods"
        }
    ],
    "sg:phone":"+1 703 525 0990",
    "sg:postcode":"22207",
    "sg:province":"VA",
    "sg:tags":[
        "beer",
        "spirit",
        "wine"
    ],
    "sg:website":"www.arrowine.com",
    "wof:name":"Arrowine",
    "wof:placetype":"venue"
},
  "geometry": {"coordinates":[-77.11810199999999,38.898582],"type":"Point"}
}