{
  "type": "Feature",
  "properties": {
    "addr:full":"2122 Sheep Creek Rd Bedford VA 24523",
    "addr:housenumber":"2122",
    "addr:postcode":"24523",
    "addr:street":"Sheep Creek Rd",
    "iso:country":"US",
    "sg:address":"2122 Sheep Creek Rd",
    "sg:city":"Bedford",
    "sg:classifiers":[
        {
            "category":"Farming",
            "subcategory":"Orchard",
            "type":"Manufacturing & Wholesale Goods"
        }
    ],
    "sg:phone":"+1 540 586 3707",
    "sg:postcode":"24523",
    "sg:province":"VA",
    "sg:tags":[
        "fruit",
        "tree",
        "apple",
        "grower"
    ],
    "sg:website":"www.johnsonsorchards.com",
    "wof:name":"Johnson's Orchard",
    "wof:placetype":"venue"
},
  "geometry": {"coordinates":[-79.623841,37.4004],"type":"Point"}
}