{
  "type": "Feature",
  "properties": {
    "iso:country":"US",
    "sg:address":"150 Little Falls St Suite 100",
    "sg:city":"Falls Church",
    "sg:classifiers":[
        {
            "category":"Professional",
            "subcategory":"Management & Consulting",
            "type":"Services"
        }
    ],
    "sg:phone":"+1 571 482 8801",
    "sg:postcode":"22046",
    "sg:province":"VA",
    "sg:tags":[
        "design",
        "development",
        "content",
        "data",
        "customers",
        "interaction",
        "django",
        "web-services",
        "integration"
    ],
    "sg:website":"http://www.wellfireinteractive.com",
    "wof:name":"Wellfire Interactive",
    "wof:placetype":"venue"
},
  "geometry": {"coordinates":[-77.172977,38.884313],"type":"Point"}
}