{
  "type": "Feature",
  "properties": {
    "iso:country":"US",
    "sg:address":"1372 Old Bridge Rd",
    "sg:city":"Woodbridge",
    "sg:classifiers":[
        {
            "category":"Professional",
            "subcategory":"Engineering",
            "type":"Services"
        }
    ],
    "sg:phone":"+1 703 499 9818",
    "sg:postcode":"22192",
    "sg:province":"VA",
    "sg:tags":[
        "petroleum",
        "engineer"
    ],
    "wof:name":"The Reinforced Earth Company",
    "wof:placetype":"venue"
},
  "geometry": {"coordinates":[-77.26153600000001,38.673199],"type":"Point"}
}