{
  "type": "Feature",
  "properties": {
    "iso:country":"US",
    "sg:address":"1305 Princess Anne St",
    "sg:city":"Fredericksburg",
    "sg:classifiers":[
        {
            "category":"Social Services",
            "subcategory":"Child Care",
            "type":"Services"
        }
    ],
    "sg:phone":"+1 540 371 2420",
    "sg:postcode":"22401",
    "sg:province":"VA",
    "wof:name":"Herbalife Distributor",
    "wof:placetype":"venue"
},
  "geometry": {"coordinates":[-77.46266300000001,38.306612],"type":"Point"}
}