{
  "type": "Feature",
  "properties": {
    "addr:full":"1167 Wildcat Rd Goodview VA 24095",
    "addr:housenumber":"1167",
    "addr:postcode":"24095",
    "addr:street":"Wildcat Rd",
    "iso:country":"US",
    "sg:address":"1167 Wildcat Rd",
    "sg:city":"Goodview",
    "sg:classifiers":[
        {
            "category":"Shopping",
            "subcategory":"Used Merchandise",
            "type":"Retail Goods"
        },
        {
            "category":"Professional",
            "subcategory":"Business Services",
            "type":"Services"
        }
    ],
    "sg:phone":"+1 540 890 6080",
    "sg:postcode":"24095",
    "sg:province":"VA",
    "sg:tags":[
        "auctioneer"
    ],
    "wof:name":"Old Mill Auction Ctr",
    "wof:placetype":"venue"
},
  "geometry": {"coordinates":[-79.78850199999999,37.272315],"type":"Point"}
}