{
  "type": "Feature",
  "properties": {
    "addr:full":"4114 Nine Mile Rd Richmond VA 23223",
    "addr:housenumber":"4114",
    "addr:postcode":"23223",
    "addr:street":"Nine Mile Rd",
    "iso:country":"US",
    "sg:address":"4114 Nine Mile Rd",
    "sg:city":"Richmond",
    "sg:classifiers":[
        {
            "category":"Building & Trades",
            "subcategory":"Construction",
            "type":"Services"
        }
    ],
    "sg:phone":"+1 804 222 6710",
    "sg:postcode":"23223",
    "sg:province":"VA",
    "sg:tags":[
        "hanging",
        "contractor"
    ],
    "wof:name":"Keys Painting Company Inc",
    "wof:placetype":"venue"
},
  "geometry": {"coordinates":[-77.379563,37.540886],"type":"Point"}
}