{
  "type": "Feature",
  "properties": {
    "addr:full":"224 Zion Branch Rd Saluda VA 23149",
    "addr:housenumber":"224",
    "addr:postcode":"23149",
    "addr:street":"Zion Branch Rd",
    "iso:country":"US",
    "sg:address":"224 Zion Branch Rd",
    "sg:city":"Saluda",
    "sg:classifiers":[
        {
            "category":"Organizations",
            "subcategory":"Religious Organization",
            "type":"Services"
        }
    ],
    "sg:phone":"+1 804 758 8266",
    "sg:postcode":"23149",
    "sg:province":"VA",
    "sg:tags":[
        "church"
    ],
    "wof:name":"Zion Branch Baptist Church",
    "wof:placetype":"venue"
},
  "geometry": {"coordinates":[-76.618551,37.621441],"type":"Point"}
}