{
  "type": "Feature",
  "properties": {
    "iso:country":"US",
    "sg:address":"4075 Lowery Rd",
    "sg:city":"Virgilina",
    "sg:classifiers":[
        {
            "category":"Building & Trades",
            "subcategory":"Construction",
            "type":"Services"
        }
    ],
    "sg:phone":"+1 434 585 2257",
    "sg:postcode":"24598",
    "sg:province":"NC",
    "sg:tags":[
        "excavation",
        "contractor"
    ],
    "wof:name":"Cotton Backhoe Service",
    "wof:placetype":"venue"
},
  "geometry": {"coordinates":[-78.81571,36.616435],"type":"Point"}
}