{
  "type": "Feature",
  "properties": {
    "addr:full":"700 Park Ave Norfolk VA 23504",
    "addr:housenumber":"700",
    "addr:postcode":"23504",
    "addr:street":"Park Ave",
    "iso:country":"US",
    "sg:address":"700 Park Ave",
    "sg:city":"Norfolk",
    "sg:classifiers":[
        {
            "category":"Education",
            "subcategory":"College",
            "type":"Public Place"
        }
    ],
    "sg:phone":"+1 757 823 8600",
    "sg:postcode":"23504",
    "sg:province":"VA",
    "sg:tags":[
        "educational",
        "program"
    ],
    "wof:name":"Norfolk State University",
    "wof:placetype":"venue"
},
  "geometry": {"coordinates":[-76.269839,36.847247],"type":"Point"}
}