{
  "type": "Feature",
  "properties": {
    "addr:full":"701 Stokes Dr Roanoke VA 24019",
    "addr:housenumber":"701",
    "addr:postcode":"24019",
    "addr:street":"Stokes Dr",
    "iso:country":"US",
    "sg:address":"701 Stokes Dr",
    "sg:city":"Roanoke",
    "sg:classifiers":[
        {
            "category":"Home & Garden",
            "subcategory":"Building Materials",
            "type":"Retail Goods"
        }
    ],
    "sg:phone":"+1 540 362 4663",
    "sg:postcode":"24019",
    "sg:province":"VA",
    "sg:tags":[
        "door"
    ],
    "wof:name":"Price's Garage Door Svc",
    "wof:placetype":"venue"
},
  "geometry": {"coordinates":[-79.936578,37.330287],"type":"Point"}
}