{
  "type": "Feature",
  "properties": {
    "addr:full":"7607 Evelyn T Butts Ave Norfolk VA 23513",
    "addr:housenumber":"7607",
    "addr:postcode":"23513",
    "addr:street":"Evelyn T Butts Ave",
    "iso:country":"US",
    "sg:address":"7607 Evelyn T Butts Ave",
    "sg:city":"Norfolk",
    "sg:classifiers":[
        {
            "category":"Bus Charters",
            "type":"Transportation"
        }
    ],
    "sg:phone":"+1 757 587 4879",
    "sg:postcode":"23513",
    "sg:province":"VA",
    "wof:name":"Jacobs Bus Company Norfolk",
    "wof:placetype":"venue"
},
  "geometry": {"coordinates":[-76.243538,36.913556],"type":"Point"}
}