{
  "type": "Feature",
  "properties": {
    "iso:country":"US",
    "sg:address":"6926 Westlawn Dr",
    "sg:city":"Falls Church",
    "sg:classifiers":[
        {
            "category":"Building & Trades",
            "subcategory":"Construction",
            "type":"Services"
        }
    ],
    "sg:phone":"+1 703 534 1312",
    "sg:postcode":"22042",
    "sg:province":"VA",
    "sg:tags":[
        "house"
    ],
    "wof:name":"Rv Construction LLC",
    "wof:placetype":"venue"
},
  "geometry": {"coordinates":[-77.186634,38.863584],"type":"Point"}
}