{
  "type": "Feature",
  "properties": {
    "addr:full":"6145 Leesburg Pike Falls Church VA 22041",
    "addr:housenumber":"6145",
    "addr:postcode":"22041",
    "addr:street":"Leesburg Pike",
    "iso:country":"US",
    "sg:address":"6145 Leesburg Pike",
    "sg:city":"Falls Church",
    "sg:classifiers":[
        {
            "category":"Communications",
            "subcategory":"Radio Station",
            "type":"Services"
        }
    ],
    "sg:phone":"+1 703 820 5160",
    "sg:postcode":"22041",
    "sg:province":"VA",
    "sg:tags":[
        "broadcaster",
        "sport"
    ],
    "wof:name":"Greg F Haber",
    "wof:placetype":"venue"
},
  "geometry": {"coordinates":[-77.14395500000001,38.858226],"type":"Point"}
}