{
  "type": "Feature",
  "properties": {
    "iso:country":"US",
    "sg:address":"201 Electric Rd",
    "sg:city":"Salem",
    "sg:classifiers":[
        {
            "category":"Restaurant",
            "type":"Food & Drink"
        }
    ],
    "sg:menulink":"http://www.allmenus.com/va/salem/92954-fuddruckers/menu/",
    "sg:phone":"+1 540 986 2000",
    "sg:postcode":"24153",
    "sg:province":"VA",
    "sg:tags":[
        "burger",
        "american"
    ],
    "wof:name":"Fuddruckers",
    "wof:placetype":"venue"
},
  "geometry": {"coordinates":[-80.02856300000001,37.295505],"type":"Point"}
}