{
  "type": "Feature",
  "properties": {
    "iso:country":"US",
    "sg:address":"506 Madison Ave S",
    "sg:city":"Pulaski",
    "sg:classifiers":[
        {
            "category":"Shopping",
            "type":"Retail Goods"
        }
    ],
    "sg:phone":"+1 540 980 0584",
    "sg:postcode":"24301",
    "sg:province":"VA",
    "sg:tags":[
        "merchandise"
    ],
    "wof:name":"Taylors Thrift Shop",
    "wof:placetype":"venue"
},
  "geometry": {"coordinates":[-80.77784200000001,37.040457],"type":"Point"}
}