{
  "type": "Feature",
  "properties": {
    "addr:full":"1020 E Ocean View Ave Norfolk VA 23503",
    "addr:housenumber":"1020",
    "addr:postcode":"23503",
    "addr:street":"E Ocean View Ave",
    "iso:country":"US",
    "sg:address":"1020 E Ocean View Ave",
    "sg:city":"Norfolk",
    "sg:classifiers":[
        {
            "category":"Travel",
            "subcategory":"Hotels & Motels",
            "type":"Entertainment"
        }
    ],
    "sg:phone":"+1 757 583 9240",
    "sg:postcode":"23503",
    "sg:province":"VA",
    "wof:name":"Macthrift Mtr Inn Chspeake Bay",
    "wof:placetype":"venue"
},
  "geometry": {"coordinates":[-76.240335,36.94729],"type":"Point"}
}