{
  "type": "Feature",
  "properties": {
    "iso:country":"US",
    "sg:address":"68 Fox Glove Ln",
    "sg:city":"Rockbridge Baths",
    "sg:classifiers":[
        {
            "category":"Retail",
            "subcategory":"Animal Services",
            "type":"Services"
        }
    ],
    "sg:phone":"+1 540 348 2058",
    "sg:postcode":"24473",
    "sg:province":"VA",
    "wof:name":"Cocos",
    "wof:placetype":"venue"
},
  "geometry": {"coordinates":[-79.389563,37.929718],"type":"Point"}
}