{
  "type": "Feature",
  "properties": {
    "addr:full":"465 Springpark Pl Herndon VA 20170",
    "addr:housenumber":"465",
    "addr:postcode":"20170",
    "addr:street":"Springpark Pl",
    "iso:country":"US",
    "sg:address":"465 Springpark Pl",
    "sg:city":"Herndon",
    "sg:classifiers":[
        {
            "category":"Professional",
            "subcategory":"Engineering",
            "type":"Services"
        }
    ],
    "sg:phone":"+1 703 742 5700",
    "sg:postcode":"20170",
    "sg:province":"VA",
    "sg:tags":[
        "building",
        "design",
        "industrial",
        "installation"
    ],
    "wof:name":"Pb Constructors Inc",
    "wof:placetype":"venue"
},
  "geometry": {"coordinates":[-77.378322,38.961665],"type":"Point"}
}