{
  "type": "Feature",
  "properties": {
    "addr:full":"481 Lonesome Pine Lancaster VA 22503",
    "addr:housenumber":"481",
    "addr:postcode":"22503",
    "addr:street":"Lonesome Pine",
    "iso:country":"US",
    "sg:address":"481 Lonesome Pine",
    "sg:city":"Lancaster",
    "sg:classifiers":[
        {
            "category":"Shopping",
            "subcategory":"Florist",
            "type":"Retail Goods"
        }
    ],
    "sg:phone":"+1 804 435 0531",
    "sg:postcode":"22503",
    "sg:province":"VA",
    "wof:name":"Greenpoint Nursery Inc",
    "wof:placetype":"venue"
},
  "geometry": {"coordinates":[-76.526566,37.716206],"type":"Point"}
}