{
  "type": "Feature",
  "properties": {
    "addr:full":"3109 Odd Fellows Rd Lynchburg VA 24501",
    "addr:postcode":"24501",
    "addr:street":"Fellows Rd",
    "iso:country":"US",
    "sg:address":"3109 Odd Fellows Rd",
    "sg:city":"Lynchburg",
    "sg:classifiers":[
        {
            "category":"Building & Trades",
            "subcategory":"Plumbing",
            "type":"Services"
        }
    ],
    "sg:phone":"+1 434 528 3626",
    "sg:postcode":"24501",
    "sg:province":"VA",
    "sg:tags":[
        "plumbing",
        "contractor"
    ],
    "wof:name":"Vamac Inc Plumbing Supplies",
    "wof:placetype":"venue"
},
  "geometry": {"coordinates":[-79.15223,37.376721],"type":"Point"}
}