{
  "type": "Feature",
  "properties": {
    "addr:full":"5306 Canter Dr Roanoke VA 24018",
    "addr:housenumber":"5306",
    "addr:postcode":"24018",
    "addr:street":"Canter Dr",
    "iso:country":"US",
    "sg:address":"5306 Canter Dr",
    "sg:city":"Roanoke",
    "sg:classifiers":[
        {
            "category":"Sports & Exercise",
            "subcategory":"Race Track",
            "type":"Entertainment"
        }
    ],
    "sg:phone":"+1 540 989 5184",
    "sg:postcode":"24018",
    "sg:province":"VA",
    "sg:tags":[
        "operation",
        "racing",
        "or"
    ],
    "wof:name":"Dsr Marketing LLC",
    "wof:placetype":"venue"
},
  "geometry": {"coordinates":[-80.02751600000001,37.223202],"type":"Point"}
}