{
  "type": "Feature",
  "properties": {
    "iso:country":"US",
    "sg:address":"8318 Tobin Rd",
    "sg:city":"Annandale",
    "sg:classifiers":[
        {
            "category":"Retail",
            "subcategory":"Repair Shop",
            "type":"Services"
        }
    ],
    "sg:phone":"+1 703 573 4830",
    "sg:postcode":"22003",
    "sg:province":"VA",
    "wof:name":"Duran Cleaning",
    "wof:placetype":"venue"
},
  "geometry": {"coordinates":[-77.23156299999999,38.854097],"type":"Point"}
}