{
  "type": "Feature",
  "properties": {
    "addr:full":"2305 Horseferry Ct Reston VA 20191",
    "addr:housenumber":"2305",
    "addr:postcode":"20191",
    "addr:street":"Horseferry Ct",
    "iso:country":"US",
    "sg:address":"2305 Horseferry Ct",
    "sg:city":"Reston",
    "sg:classifiers":[
        {
            "category":"Professional",
            "subcategory":"Computer Services",
            "type":"Services"
        }
    ],
    "sg:phone":"+1 703 860 5244",
    "sg:postcode":"20191",
    "sg:province":"VA",
    "sg:tags":[
        "consultant"
    ],
    "wof:name":"Net2k",
    "wof:placetype":"venue"
},
  "geometry": {"coordinates":[-77.356477,38.932841],"type":"Point"}
}