{
  "type": "Feature",
  "properties": {
    "addr:full":"35 Patton Ave NE Roanoke VA 24016",
    "addr:housenumber":"35",
    "addr:postcode":"24016",
    "addr:street":"Patton Ave Ne",
    "iso:country":"US",
    "sg:address":"35 Patton Ave NE",
    "sg:city":"Roanoke",
    "sg:classifiers":[
        {
            "category":"Organizations",
            "subcategory":"Community Association",
            "type":"Services"
        }
    ],
    "sg:phone":"+1 540 342 0728",
    "sg:postcode":"24016",
    "sg:province":"VA",
    "wof:name":"Historic Gnsboro Prsrvtion Dst",
    "wof:placetype":"venue"
},
  "geometry": {"coordinates":[-79.93777300000001,37.276897],"type":"Point"}
}