{
  "type": "Feature",
  "properties": {
    "addr:full":"3020 Jefferson Davis Hwy Richmond VA 23234",
    "addr:housenumber":"3020",
    "addr:postcode":"23234",
    "addr:street":"Jefferson Davis Hwy",
    "iso:country":"US",
    "sg:address":"3020 Jefferson Davis Hwy",
    "sg:city":"Richmond",
    "sg:classifiers":[
        {
            "category":"Insurance",
            "subcategory":"Insurance Agent",
            "type":"Services"
        }
    ],
    "sg:phone":"+1 804 230 4100",
    "sg:postcode":"23234",
    "sg:province":"VA",
    "wof:name":"Bradshaw Insurance",
    "wof:placetype":"venue"
},
  "geometry": {"coordinates":[-77.444553,37.481664],"type":"Point"}
}