{
  "type": "Feature",
  "properties": {
    "addr:full":"3207 N Main St Danville VA 24540",
    "addr:housenumber":"3207",
    "addr:postcode":"24540",
    "addr:street":"N Main St",
    "iso:country":"US",
    "sg:address":"3207 N Main St",
    "sg:city":"Danville",
    "sg:classifiers":[
        {
            "category":"Autos & Motor Vehicles",
            "subcategory":"Automobile Sales",
            "type":"Retail Goods"
        }
    ],
    "sg:phone":"+1 434 836 2830",
    "sg:postcode":"24540",
    "sg:province":"VA",
    "sg:tags":[
        "car",
        "dealer"
    ],
    "wof:name":"D & K Auto Sale",
    "wof:placetype":"venue"
},
  "geometry": {"coordinates":[-79.38613599999999,36.637418],"type":"Point"}
}