{
  "type": "Feature",
  "properties": {
    "addr:full":"442 National Ave Winchester VA 22601",
    "addr:housenumber":"442",
    "addr:postcode":"22601",
    "addr:street":"National Ave",
    "iso:country":"US",
    "sg:address":"442 National Ave",
    "sg:city":"Winchester",
    "sg:classifiers":[
        {
            "category":"Shopping",
            "subcategory":"Florist",
            "type":"Retail Goods"
        }
    ],
    "sg:phone":"+1 540 667 1687",
    "sg:postcode":"22601",
    "sg:province":"VA",
    "wof:name":"Smalts Florist Inc",
    "wof:placetype":"venue"
},
  "geometry": {"coordinates":[-78.154701,39.184826],"type":"Point"}
}