{
  "type": "Feature",
  "properties": {
    "addr:full":"3109 W Clay St Richmond VA 23230",
    "addr:housenumber":"3109",
    "addr:postcode":"23230",
    "addr:street":"W Clay St",
    "iso:country":"US",
    "sg:address":"3109 W Clay St",
    "sg:city":"Richmond",
    "sg:classifiers":[
        {
            "category":"Food & Beverages",
            "subcategory":"Groceries & Convenience Stores",
            "type":"Retail Goods"
        }
    ],
    "sg:phone":"+1 804 358 0770",
    "sg:postcode":"23230",
    "sg:province":"VA",
    "wof:name":"7-Eleven",
    "wof:placetype":"venue"
},
  "geometry": {"coordinates":[-77.472854,37.567317],"type":"Point"}
}