{
  "type": "Feature",
  "properties": {
    "iso:country":"US",
    "sg:address":"13372 Packard Dr",
    "sg:city":"Woodbridge",
    "sg:classifiers":[
        {
            "category":"Professional",
            "type":"Services"
        }
    ],
    "sg:phone":"+1 703 878 4439",
    "sg:postcode":"22193",
    "sg:province":"VA",
    "wof:name":"Half Iron Inc",
    "wof:placetype":"venue"
},
  "geometry": {"coordinates":[-77.393845,38.660813],"type":"Point"}
}