{
  "type": "Feature",
  "properties": {
    "iso:country":"US",
    "sg:address":"3212 Skipwith Rd",
    "sg:city":"Richmond",
    "sg:classifiers":[
        {
            "category":"Wholesale",
            "subcategory":"Computers",
            "type":"Manufacturing & Wholesale Goods"
        }
    ],
    "sg:phone":"+1 804 864 9736",
    "sg:postcode":"23294",
    "sg:province":"VA",
    "sg:tags":[
        "rental"
    ],
    "wof:name":"Computer & A/V Rental Inc",
    "wof:placetype":"venue"
},
  "geometry": {"coordinates":[-77.53924499999999,37.629261],"type":"Point"}
}