{
  "type": "Feature",
  "properties": {
    "addr:full":"101 S College Dr Franklin VA 23851",
    "addr:housenumber":"101",
    "addr:postcode":"23851",
    "addr:street":"S College Dr",
    "iso:country":"US",
    "sg:address":"101 S College Dr",
    "sg:city":"Franklin",
    "sg:classifiers":[
        {
            "category":"Government",
            "subcategory":"Office",
            "type":"Public Place"
        }
    ],
    "sg:phone":"+1 757 562 6151",
    "sg:postcode":"23851",
    "sg:province":"VA",
    "sg:tags":[
        "state",
        "program"
    ],
    "wof:name":"Rehabilitative Services Dept",
    "wof:placetype":"venue"
},
  "geometry": {"coordinates":[-76.938712,36.672722],"type":"Point"}
}