{
  "type": "Feature",
  "properties": {
    "iso:country":"US",
    "sg:address":"703 N Mansfield St",
    "sg:city":"Alexandria",
    "sg:classifiers":[
        {
            "category":"Organizations",
            "subcategory":"Religious Organization",
            "type":"Services"
        }
    ],
    "sg:phone":"+1 703 751 0136",
    "sg:postcode":"22304",
    "sg:province":"VA",
    "sg:tags":[
        "lutheran",
        "church"
    ],
    "wof:name":"St Athanasius Lutheran Church",
    "wof:placetype":"venue"
},
  "geometry": {"coordinates":[-77.113654,38.818274],"type":"Point"}
}