{
  "type": "Feature",
  "properties": {
    "iso:country":"US",
    "sg:address":"228 W Locust St",
    "sg:city":"Covington",
    "sg:classifiers":[
        {
            "category":"Professional",
            "subcategory":"Lawyer & Legal Services",
            "type":"Services"
        }
    ],
    "sg:phone":"+1 540 965 9331",
    "sg:postcode":"24426",
    "sg:province":"VA",
    "sg:tags":[
        "attorney"
    ],
    "wof:name":"Pasco & Dascher",
    "wof:placetype":"venue"
},
  "geometry": {"coordinates":[-79.99398100000001,37.792322],"type":"Point"}
}