{
  "type": "Feature",
  "properties": {
    "addr:full":"1302 Longview Dr Woodbridge VA 22191",
    "addr:housenumber":"1302",
    "addr:postcode":"22191",
    "addr:street":"Longview Dr",
    "iso:country":"US",
    "sg:address":"1302 Longview Dr",
    "sg:city":"Woodbridge",
    "sg:classifiers":[
        {
            "category":"Wholesale",
            "subcategory":"Groceries",
            "type":"Manufacturing & Wholesale Goods"
        }
    ],
    "sg:phone":"+1 703 494 2209",
    "sg:postcode":"22191",
    "sg:province":"VA",
    "sg:tags":[
        "confectionery"
    ],
    "wof:name":"Miramel Corp",
    "wof:placetype":"venue"
},
  "geometry": {"coordinates":[-77.258619,38.639558],"type":"Point"}
}