{
  "type": "Feature",
  "properties": {
    "addr:full":"3930 Anderson Hwy Powhatan VA 23139",
    "addr:housenumber":"3930",
    "addr:postcode":"23139",
    "addr:street":"Anderson Hwy",
    "iso:country":"US",
    "sg:address":"3930 Anderson Hwy",
    "sg:city":"Powhatan",
    "sg:classifiers":[
        {
            "category":"Organizations",
            "subcategory":"Non-profit Organization",
            "type":"Services"
        }
    ],
    "sg:phone":"+1 804 598 3351",
    "sg:postcode":"23139",
    "sg:province":"VA",
    "sg:tags":[
        "human"
    ],
    "sg:website":"www.pgcaa.org",
    "wof:name":"Powhatan-Goochland Community",
    "wof:placetype":"venue"
},
  "geometry": {"coordinates":[-77.92215400000001,37.549683],"type":"Point"}
}