{
  "type": "Feature",
  "properties": {
    "addr:full":"18516 Triangle St Triangle VA 22172",
    "addr:housenumber":"18516",
    "addr:postcode":"va 22172",
    "addr:street":"Triangle St",
    "iso:country":"US",
    "sg:address":"18516 Triangle St",
    "sg:city":"Triangle",
    "sg:classifiers":[
        {
            "category":"Retail",
            "subcategory":"Repair Shop",
            "type":"Services"
        }
    ],
    "sg:phone":"+1 703 221 4500",
    "sg:postcode":"22172",
    "sg:province":"VA",
    "sg:tags":[
        "upholsterer"
    ],
    "wof:name":"Quantico Upholstering Co",
    "wof:placetype":"venue"
},
  "geometry": {"coordinates":[-77.332719,38.55109],"type":"Point"}
}