{
  "type": "Feature",
  "properties": {
    "iso:country":"US",
    "sg:address":"407 Myrtle St",
    "sg:city":"Ashland",
    "sg:classifiers":[
        {
            "category":"Organizations",
            "subcategory":"Religious Organization",
            "type":"Services"
        }
    ],
    "sg:phone":"+1 804 798 5769",
    "sg:postcode":"23005",
    "sg:province":"VA",
    "sg:tags":[
        "church"
    ],
    "wof:name":"Ashland Church Of God",
    "wof:placetype":"venue"
},
  "geometry": {"coordinates":[-77.475977,37.756827],"type":"Point"}
}