{
  "type": "Feature",
  "properties": {
    "iso:country":"US",
    "sg:address":"1850 Apple Blossom Dr",
    "sg:city":"Winchester",
    "sg:classifiers":[
        {
            "category":"Shopping",
            "type":"Retail Goods"
        }
    ],
    "sg:phone":"+1 540 535 1160",
    "sg:postcode":"22601",
    "sg:province":"VA",
    "sg:tags":[
        "art",
        "gallery",
        "dealer"
    ],
    "wof:name":"Art Gallery",
    "wof:placetype":"venue"
},
  "geometry": {"coordinates":[-78.162706,39.167041],"type":"Point"}
}