{
  "type": "Feature",
  "properties": {
    "addr:full":"994 Birchwood Rd Axton VA 24054",
    "addr:housenumber":"994",
    "addr:postcode":"24054",
    "addr:street":"Birchwood Rd",
    "iso:country":"US",
    "sg:address":"994 Birchwood Rd",
    "sg:city":"Axton",
    "sg:classifiers":[
        {
            "category":"Manufacturing",
            "subcategory":"Apparel",
            "type":"Manufacturing & Wholesale Goods"
        }
    ],
    "sg:phone":"+1 276 650 3174",
    "sg:postcode":"24054",
    "sg:province":"VA",
    "sg:tags":[
        "mfg"
    ],
    "wof:name":"Janie Draperies Shop",
    "wof:placetype":"venue"
},
  "geometry": {"coordinates":[-79.766211,36.660166],"type":"Point"}
}