{
  "type": "Feature",
  "properties": {
    "iso:country":"US",
    "sg:address":"1527 S Loudoun St",
    "sg:city":"Winchester",
    "sg:classifiers":[
        {
            "category":"Professional",
            "subcategory":"Business Services",
            "type":"Services"
        }
    ],
    "sg:phone":"+1 540 667 8901",
    "sg:postcode":"22601",
    "sg:province":"VA",
    "wof:name":"Home Showcase",
    "wof:placetype":"venue"
},
  "geometry": {"coordinates":[-78.170704,39.170797],"type":"Point"}
}