{
  "type": "Feature",
  "properties": {
    "addr:full":"141 Granby St Norfolk VA 23510",
    "addr:housenumber":"141",
    "addr:postcode":"23510",
    "addr:street":"Granby St",
    "iso:country":"US",
    "sg:address":"141 Granby St",
    "sg:city":"Norfolk",
    "sg:classifiers":[
        {
            "category":"Shopping",
            "subcategory":"Optical Goods",
            "type":"Retail Goods"
        }
    ],
    "sg:phone":"+1 757 627 3937",
    "sg:postcode":"23510",
    "sg:province":"VA",
    "sg:tags":[
        "medical"
    ],
    "wof:name":"Selden Optique Inc",
    "wof:placetype":"venue"
},
  "geometry": {"coordinates":[-76.291518,36.847924],"type":"Point"}
}