{
  "type": "Feature",
  "properties": {
    "addr:full":"5914 Chamberlayne Rd Richmond VA 23227",
    "addr:housenumber":"5914",
    "addr:postcode":"23227",
    "addr:street":"Chamberlayne Rd",
    "iso:country":"US",
    "sg:address":"5914 Chamberlayne Rd",
    "sg:city":"Richmond",
    "sg:classifiers":[
        {
            "category":"Professional",
            "subcategory":"Accounting & Tax Preparation",
            "type":"Services"
        }
    ],
    "sg:phone":"+1 804 264 2263",
    "sg:postcode":"23227",
    "sg:province":"VA",
    "sg:tags":[
        "consulting",
        "management",
        "s"
    ],
    "wof:name":"C Overbey Jr Fincl Plg & CPA",
    "wof:placetype":"venue"
},
  "geometry": {"coordinates":[-77.43813299999999,37.624347],"type":"Point"}
}