{
  "type": "Feature",
  "properties": {
    "iso:country":"US",
    "sg:address":"3105 Letcher Ave",
    "sg:city":"Richmond",
    "sg:classifiers":[
        {
            "category":"Building & Trades",
            "subcategory":"Cleaning & Sanitation",
            "type":"Services"
        }
    ],
    "sg:phone":"+1 804 329 2934",
    "sg:postcode":"23222",
    "sg:province":"VA",
    "sg:tags":[
        "janitor"
    ],
    "wof:name":"Andrew J Clack Janitorial Svc",
    "wof:placetype":"venue"
},
  "geometry": {"coordinates":[-77.422224,37.572489],"type":"Point"}
}