{
  "type": "Feature",
  "properties": {
    "addr:full":"1711 26th St S Arlington VA 22206",
    "addr:housenumber":"1711",
    "addr:postcode":"22206",
    "addr:street":"26Th St S",
    "iso:country":"US",
    "sg:address":"1711 26th St S",
    "sg:city":"Arlington",
    "sg:classifiers":[
        {
            "category":"Professional",
            "type":"Services"
        }
    ],
    "sg:phone":"+1 703 836 8138",
    "sg:postcode":"22206",
    "sg:province":"VA",
    "wof:name":"Park At Arlington",
    "wof:placetype":"venue"
},
  "geometry": {"coordinates":[-77.07512,38.848553],"type":"Point"}
}