{
  "type": "Feature",
  "properties": {
    "addr:full":"3879 Wilcoxson Dr Fairfax VA 22031",
    "addr:housenumber":"3879",
    "addr:postcode":"22031",
    "addr:street":"Wilcoxson Dr",
    "iso:country":"US",
    "sg:address":"3879 Wilcoxson Dr",
    "sg:city":"Fairfax",
    "sg:classifiers":[
        {
            "category":"Professional",
            "subcategory":"Engineering",
            "type":"Services"
        }
    ],
    "sg:phone":"+1 703 503 5048",
    "sg:postcode":"22031",
    "sg:province":"VA",
    "sg:tags":[
        "electronic",
        "engineer"
    ],
    "wof:name":"Peri & Associates",
    "wof:placetype":"venue"
},
  "geometry": {"coordinates":[-77.278847,38.844],"type":"Point"}
}