{
  "type": "Feature",
  "properties": {
    "iso:country":"US",
    "sg:address":"8300 Sudley Rd",
    "sg:city":"Manassas",
    "sg:classifiers":[
        {
            "category":"Shopping",
            "subcategory":"Music",
            "type":"Retail Goods"
        }
    ],
    "sg:phone":"+1 703 631 4964",
    "sg:postcode":"20109",
    "sg:province":"VA",
    "wof:name":"Kemp Mill Music",
    "wof:placetype":"venue"
},
  "geometry": {"coordinates":[-77.501817,38.774311],"type":"Point"}
}