{
  "type": "Feature",
  "properties": {
    "addr:full":"5710 S Laburnum Ave Richmond VA 23231",
    "addr:housenumber":"5710",
    "addr:postcode":"23231",
    "addr:street":"S Laburnum Ave",
    "iso:country":"US",
    "sg:address":"5710 S Laburnum Ave",
    "sg:city":"Richmond",
    "sg:classifiers":[
        {
            "category":"Wholesale",
            "subcategory":"Machinery & Supplies",
            "type":"Manufacturing & Wholesale Goods"
        }
    ],
    "sg:phone":"+1 804 222 1833",
    "sg:postcode":"23231",
    "sg:province":"VA",
    "sg:tags":[
        "industrial"
    ],
    "wof:name":"Stanley Works Inc",
    "wof:placetype":"venue"
},
  "geometry": {"coordinates":[-77.349625,37.504165],"type":"Point"}
}