{
  "type": "Feature",
  "properties": {
    "addr:full":"2730 Hunt Country Ln Charlottesville VA 22901",
    "addr:housenumber":"2730",
    "addr:postcode":"22901",
    "addr:street":"Hunt Country Ln",
    "iso:country":"US",
    "sg:address":"2730 Hunt Country Ln",
    "sg:city":"Charlottesville",
    "sg:classifiers":[
        {
            "category":"Professional",
            "subcategory":"Employment Agencies",
            "type":"Services"
        }
    ],
    "sg:phone":"+1 434 244 2498",
    "sg:postcode":"22901",
    "sg:province":"VA",
    "sg:tags":[
        "workers'",
        "placement",
        "volunteer"
    ],
    "wof:name":"William Freehling Family Foundation 0301",
    "wof:placetype":"venue"
},
  "geometry": {"coordinates":[-78.559506,38.110242],"type":"Point"}
}