{
  "type": "Feature",
  "properties": {
    "addr:full":"3224 New Bridge Rd Virginia Beach VA 23456",
    "addr:housenumber":"3224",
    "addr:postcode":"23456",
    "addr:street":"New Bridge Rd",
    "iso:country":"US",
    "sg:address":"3224 New Bridge Rd",
    "sg:city":"Virginia Beach",
    "sg:classifiers":[
        {
            "category":"Building & Trades",
            "subcategory":"Plumbing",
            "type":"Services"
        }
    ],
    "sg:phone":"+1 757 426 7155",
    "sg:postcode":"23456",
    "sg:province":"VA",
    "sg:tags":[
        "contractor"
    ],
    "wof:name":"Birdsong Service",
    "wof:placetype":"venue"
},
  "geometry": {"coordinates":[-75.998778,36.720412],"type":"Point"}
}