{
  "type": "Feature",
  "properties": {
    "addr:full":"2111 Eisenhower Ave Alexandria VA 22314",
    "addr:housenumber":"2111",
    "addr:postcode":"22314",
    "addr:street":"Eisenhower Ave",
    "iso:country":"US",
    "sg:address":"2111 Eisenhower Ave",
    "sg:city":"Alexandria",
    "sg:classifiers":[
        {
            "category":"Professional",
            "subcategory":"Research",
            "type":"Services"
        }
    ],
    "sg:phone":"+1 703 683 6242",
    "sg:postcode":"22314",
    "sg:province":"VA",
    "sg:tags":[
        "commercial",
        "physical"
    ],
    "wof:name":"Saic",
    "wof:placetype":"venue"
},
  "geometry": {"coordinates":[-77.065849,38.800839],"type":"Point"}
}