{
  "type": "Feature",
  "properties": {
    "addr:full":"173B Keith St Warrenton VA 20186",
    "addr:housenumber":"173b",
    "addr:postcode":"20186",
    "addr:street":"Keith St",
    "iso:country":"US",
    "sg:address":"173B Keith St",
    "sg:city":"Warrenton",
    "sg:classifiers":[
        {
            "category":"Social Services",
            "subcategory":"Child Care",
            "type":"Services"
        }
    ],
    "sg:phone":"+1 540 347 6970",
    "sg:postcode":"20186",
    "sg:province":"VA",
    "sg:tags":[
        "day"
    ],
    "wof:name":"Fauquier Community Child Care Inc",
    "wof:placetype":"venue"
},
  "geometry": {"coordinates":[-77.80059799999999,38.7103],"type":"Point"}
}