{
  "type": "Feature",
  "properties": {
    "addr:full":"405 Yorkshire St Salem VA 24153",
    "addr:housenumber":"405",
    "addr:postcode":"24153",
    "addr:street":"Yorkshire St",
    "iso:country":"US",
    "sg:address":"405 Yorkshire St",
    "sg:city":"Salem",
    "sg:classifiers":[
        {
            "category":"Shopping",
            "subcategory":"Computers & Home Electronics",
            "type":"Retail Goods"
        }
    ],
    "sg:phone":"+1 540 387 4487",
    "sg:postcode":"24153",
    "sg:province":"VA",
    "sg:tags":[
        "equipment",
        "dealer"
    ],
    "wof:name":"Salem Software Svc",
    "wof:placetype":"venue"
},
  "geometry": {"coordinates":[-80.049926,37.273587],"type":"Point"}
}