{
  "type": "Feature",
  "properties": {
    "iso:country":"US",
    "sg:address":"20166 Miller Dr",
    "sg:city":"Culpeper",
    "sg:classifiers":[
        {
            "category":"Insurance",
            "subcategory":"Insurance Agent",
            "type":"Services"
        }
    ],
    "sg:phone":"+1 540 825 7748",
    "sg:postcode":"22701",
    "sg:province":"VA",
    "wof:name":"Robert Y Button III",
    "wof:placetype":"venue"
},
  "geometry": {"coordinates":[-78.035284,38.427136],"type":"Point"}
}