{
  "type": "Feature",
  "properties": {
    "iso:country":"US",
    "sg:address":"1803 E Pembroke Ave",
    "sg:city":"Hampton",
    "sg:classifiers":[
        {
            "category":"Wholesale",
            "subcategory":"Durable Goods & Equipment",
            "type":"Manufacturing & Wholesale Goods"
        }
    ],
    "sg:phone":"+1 757 723 7700",
    "sg:postcode":"23663",
    "sg:province":"VA",
    "wof:name":"Pretty Graphic",
    "wof:placetype":"venue"
},
  "geometry": {"coordinates":[-76.311369,37.038658],"type":"Point"}
}