{
  "type": "Feature",
  "properties": {
    "addr:full":"2101 Mount Vernon Ave Alexandria VA 22301",
    "addr:housenumber":"2101",
    "addr:postcode":"22301",
    "addr:street":"Mount Vernon Ave",
    "iso:country":"US",
    "sg:address":"2101 Mount Vernon Ave",
    "sg:city":"Alexandria",
    "sg:classifiers":[
        {
            "category":"Retail",
            "subcategory":"Repair Shop",
            "type":"Services"
        }
    ],
    "sg:phone":"+1 703 549 6143",
    "sg:postcode":"22301",
    "sg:province":"VA",
    "sg:tags":[
        "watch"
    ],
    "wof:name":"Spurlock Watch & Jewelry",
    "wof:placetype":"venue"
},
  "geometry": {"coordinates":[-77.05851199999999,38.82539],"type":"Point"}
}