{
  "type": "Feature",
  "properties": {
    "addr:full":"406 N 6th Ave Hopewell VA 23860",
    "addr:housenumber":"406",
    "addr:postcode":"23860",
    "addr:street":"N 6Th Ave",
    "iso:country":"US",
    "sg:address":"406 N 6th Ave",
    "sg:city":"Hopewell",
    "sg:classifiers":[
        {
            "category":"Health Services",
            "subcategory":"Doctor",
            "type":"Services"
        }
    ],
    "sg:phone":"+1 804 541 3024",
    "sg:postcode":"23860",
    "sg:province":"VA",
    "sg:tags":[
        "medical"
    ],
    "wof:name":"Southside Head & Neck Surgery",
    "wof:placetype":"venue"
},
  "geometry": {"coordinates":[-77.293094,37.305054],"type":"Point"}
}