{
  "type": "Feature",
  "properties": {
    "addr:full":"2365 Carrsville Hwy Franklin VA 23851",
    "addr:housenumber":"2365",
    "addr:postcode":"23851",
    "addr:street":"Carrsville Hwy",
    "iso:country":"US",
    "sg:address":"2365 Carrsville Hwy",
    "sg:city":"Franklin",
    "sg:phone":"+1 757 562 3400",
    "sg:postcode":"23851",
    "sg:province":"VA",
    "sg:tags":[
        "fuel",
        "oil",
        "gasoline"
    ],
    "wof:name":"Cost Less Oil Co",
    "wof:placetype":"venue"
},
  "geometry": {"coordinates":[-76.88724499999999,36.695147],"type":"Point"}
}