{
  "type": "Feature",
  "properties": {
    "addr:full":"8320 Old Courthouse Rd Vienna VA 22182",
    "addr:housenumber":"8320",
    "addr:postcode":"22182",
    "addr:street":"Old Courthouse Rd",
    "iso:country":"US",
    "sg:address":"8320 Old Courthouse Rd",
    "sg:city":"Vienna",
    "sg:classifiers":[
        {
            "category":"Banks & Credit Unions",
            "subcategory":"Bank",
            "type":"Services"
        }
    ],
    "sg:phone":"+1 703 917 4067",
    "sg:postcode":"22182",
    "sg:province":"VA",
    "sg:tags":[
        "loan",
        "real estate"
    ],
    "wof:name":"Bank United Residential",
    "wof:placetype":"venue"
},
  "geometry": {"coordinates":[-77.23532299999999,38.91527],"type":"Point"}
}