{
  "type": "Feature",
  "properties": {
    "addr:full":"213 River Walk Pkwy Chesapeake VA 23320",
    "addr:housenumber":"213",
    "addr:postcode":"23320",
    "addr:street":"River Walk Pkwy",
    "iso:country":"US",
    "sg:address":"213 River Walk Pkwy",
    "sg:city":"Chesapeake",
    "sg:classifiers":[
        {
            "category":"Health Services",
            "subcategory":"Doctor",
            "type":"Services"
        }
    ],
    "sg:phone":"+1 757 548 1400",
    "sg:postcode":"23320",
    "sg:province":"VA",
    "sg:tags":[
        "physician",
        "surgeon"
    ],
    "wof:name":"Chesapeake Medical Assoc",
    "wof:placetype":"venue"
},
  "geometry": {"coordinates":[-76.258154,36.744117],"type":"Point"}
}