{
  "type": "Feature",
  "properties": {
    "addr:full":"127 W Main St Luray VA 22835",
    "addr:housenumber":"127",
    "addr:postcode":"22835",
    "addr:street":"W Main St",
    "iso:country":"US",
    "sg:address":"127 W Main St",
    "sg:city":"Luray",
    "sg:classifiers":[
        {
            "category":"Government",
            "subcategory":"Court House",
            "type":"Public Place"
        }
    ],
    "sg:phone":"+1 540 843 4913",
    "sg:postcode":"22835",
    "sg:province":"VA",
    "sg:tags":[
        "legal"
    ],
    "wof:name":"Downs Robert A PLC",
    "wof:placetype":"venue"
},
  "geometry": {"coordinates":[-78.463204,38.66549],"type":"Point"}
}