{
  "type": "Feature",
  "properties": {
    "iso:country":"US",
    "sg:address":"1215 E Main St",
    "sg:city":"Waynesboro",
    "sg:classifiers":[
        {
            "category":"Autos & Motor Vehicles",
            "subcategory":"Automobile Sales",
            "type":"Retail Goods"
        }
    ],
    "sg:phone":"+1 540 949 8935",
    "sg:postcode":"22980",
    "sg:province":"VA",
    "sg:tags":[
        "used"
    ],
    "wof:name":"Eastern Gate Motors",
    "wof:placetype":"venue"
},
  "geometry": {"coordinates":[-78.872685,38.064025],"type":"Point"}
}