{
  "type": "Feature",
  "properties": {
    "addr:full":"4924 Shady Side Dr Roanoke VA 24018",
    "addr:housenumber":"4924",
    "addr:postcode":"24018",
    "addr:street":"Shady Side Dr",
    "iso:country":"US",
    "sg:address":"4924 Shady Side Dr",
    "sg:city":"Roanoke",
    "sg:classifiers":[
        {
            "category":"Communications",
            "subcategory":"Film & Video Production",
            "type":"Services"
        },
        {
            "category":"Retail",
            "subcategory":"Event Space",
            "type":"Services"
        },
        {
            "category":"Personal",
            "type":"Services"
        }
    ],
    "sg:phone":"+1 540 772 3200",
    "sg:postcode":"24018",
    "sg:province":"VA",
    "sg:tags":[
        "facility",
        "services-commercial",
        "hall",
        "planning",
        "reception",
        "party",
        "banquet"
    ],
    "wof:name":"Video Records Inc",
    "wof:placetype":"venue"
},
  "geometry": {"coordinates":[-80.009635,37.221103],"type":"Point"}
}