{
  "type": "Feature",
  "properties": {
    "iso:country":"US",
    "sg:address":"12906 Old Stage Rd",
    "sg:city":"Chester",
    "sg:classifiers":[
        {
            "category":"Retail",
            "subcategory":"Repair Shop",
            "type":"Services"
        }
    ],
    "sg:phone":"+1 804 796 3510",
    "sg:postcode":"23836",
    "sg:province":"VA",
    "wof:name":"Amark Corporation",
    "wof:placetype":"venue"
},
  "geometry": {"coordinates":[-77.396928,37.351129],"type":"Point"}
}