{
  "type": "Feature",
  "properties": {
    "addr:full":"1338 Richmond Rd Williamsburg VA 23185",
    "addr:housenumber":"1338",
    "addr:postcode":"23185",
    "addr:street":"Richmond Rd",
    "iso:country":"US",
    "sg:address":"1338 Richmond Rd",
    "sg:city":"Williamsburg",
    "sg:classifiers":[
        {
            "category":"Restaurant",
            "type":"Food & Drink"
        }
    ],
    "sg:menulink":"http://www.allmenus.com/va/williamsburg/55511-marinos-italian-cuisine/menu/",
    "sg:phone":"+1 757 253 1844",
    "sg:postcode":"23185",
    "sg:province":"VA",
    "sg:tags":[
        "italian"
    ],
    "wof:name":"Marino's Italian Cuisine",
    "wof:placetype":"venue"
},
  "geometry": {"coordinates":[-76.719842,37.284162],"type":"Point"}
}