{
  "type": "Feature",
  "properties": {
    "iso:country":"US",
    "sg:address":"10515 Dominion Valley Dr",
    "sg:city":"Fairfax Station",
    "sg:classifiers":[
        {
            "category":"Banks & Credit Unions",
            "subcategory":"Investment Brokerage",
            "type":"Services"
        }
    ],
    "sg:phone":"+1 703 690 4975",
    "sg:postcode":"22039",
    "sg:province":"VA",
    "sg:tags":[
        "security"
    ],
    "wof:name":"Mauricio D Bas Jr MD PC",
    "wof:placetype":"venue"
},
  "geometry": {"coordinates":[-77.311069,38.7361],"type":"Point"}
}