{
  "type": "Feature",
  "properties": {
    "addr:full":"2090 Doe Run Rd Rocky Mount VA 24151",
    "addr:housenumber":"2090",
    "addr:postcode":"24151",
    "addr:street":"Doe Run Rd",
    "iso:country":"US",
    "sg:address":"2090 Doe Run Rd",
    "sg:city":"Rocky Mount",
    "sg:classifiers":[
        {
            "category":"Professional",
            "subcategory":"Business Services",
            "type":"Services"
        }
    ],
    "sg:phone":"+1 540 483 4575",
    "sg:postcode":"24151",
    "sg:province":"VA",
    "sg:tags":[
        "public"
    ],
    "wof:name":"Spy & Associates",
    "wof:placetype":"venue"
},
  "geometry": {"coordinates":[-79.838725,36.976015],"type":"Point"}
}