{
  "type": "Feature",
  "properties": {
    "iso:country":"US",
    "sg:address":"3095 Chipnowak Ct",
    "sg:city":"Oakton",
    "sg:classifiers":[
        {
            "category":"Professional",
            "type":"Services"
        }
    ],
    "sg:phone":"+1 703 716 0022",
    "sg:postcode":"22124",
    "sg:province":"VA",
    "wof:name":"Charles A Tievsky  PLC",
    "wof:placetype":"venue"
},
  "geometry": {"coordinates":[-77.359364,38.894864],"type":"Point"}
}