{
  "type": "Feature",
  "properties": {
    "addr:full":"4500 Southgate Pl Chantilly VA 20151",
    "addr:housenumber":"4500",
    "addr:postcode":"20151",
    "addr:street":"Southgate Pl",
    "iso:country":"US",
    "sg:address":"4500 Southgate Pl",
    "sg:city":"Chantilly",
    "sg:classifiers":[
        {
            "category":"Shopping",
            "subcategory":"Computers & Home Electronics",
            "type":"Retail Goods"
        }
    ],
    "sg:phone":"+1 703 631 4244",
    "sg:postcode":"20151",
    "sg:province":"VA",
    "sg:tags":[
        "company",
        "holding"
    ],
    "wof:name":"Gti",
    "wof:placetype":"venue"
},
  "geometry": {"coordinates":[-77.46278100000001,38.891906],"type":"Point"}
}