{
  "type": "Feature",
  "properties": {
    "addr:full":"1718 Mayfield Dr Roanoke VA 24014",
    "addr:housenumber":"1718",
    "addr:postcode":"24014",
    "addr:street":"Mayfield Dr",
    "iso:country":"US",
    "sg:address":"1718 Mayfield Dr",
    "sg:city":"Roanoke",
    "sg:classifiers":[
        {
            "category":"Real Estate",
            "subcategory":"Real Estate Agent",
            "type":"Services"
        }
    ],
    "sg:phone":"+1 540 427 5900",
    "sg:postcode":"24014",
    "sg:province":"VA",
    "sg:tags":[
        "inspection"
    ],
    "wof:name":"Affordable Home Inspections",
    "wof:placetype":"venue"
},
  "geometry": {"coordinates":[-79.917582,37.233111],"type":"Point"}
}