{
  "type": "Feature",
  "properties": {
    "addr:full":"618 Forest St Charlottesville VA 22903",
    "addr:housenumber":"618",
    "addr:postcode":"22903",
    "addr:street":"Forest St",
    "iso:country":"US",
    "sg:address":"618 Forest St",
    "sg:city":"Charlottesville",
    "sg:classifiers":[
        {
            "category":"Retail",
            "subcategory":"Portrait Studio",
            "type":"Services"
        }
    ],
    "sg:phone":"+1 434 979 1915",
    "sg:postcode":"22903",
    "sg:province":"VA",
    "sg:tags":[
        "photography",
        "store"
    ],
    "sg:website":"www.procameraus.com",
    "wof:name":"Pro Camera Inc",
    "wof:placetype":"venue"
},
  "geometry": {"coordinates":[-78.48761500000001,38.036627],"type":"Point"}
}