{
  "type": "Feature",
  "properties": {
    "addr:full":"6036 Alexander Ave Alexandria VA 22310",
    "addr:housenumber":"6036",
    "addr:postcode":"22310",
    "addr:street":"Alexander Ave",
    "iso:country":"US",
    "sg:address":"6036 Alexander Ave",
    "sg:city":"Alexandria",
    "sg:classifiers":[
        {
            "category":"Professional",
            "subcategory":"Management & Consulting",
            "type":"Services"
        }
    ],
    "sg:phone":"+1 703 922 8365",
    "sg:postcode":"22310",
    "sg:province":"VA",
    "sg:tags":[
        "consultant",
        "business"
    ],
    "wof:name":"Opal Enterprises Inc",
    "wof:placetype":"venue"
},
  "geometry": {"coordinates":[-77.14417299999999,38.768415],"type":"Point"}
}