{
  "type": "Feature",
  "properties": {
    "addr:full":"116 E Main St Orange VA 22960",
    "addr:housenumber":"116",
    "addr:postcode":"22960",
    "addr:street":"E Main St",
    "iso:country":"US",
    "sg:address":"116 E Main St",
    "sg:city":"Orange",
    "sg:classifiers":[
        {
            "category":"Insurance",
            "subcategory":"Insurance Agent",
            "type":"Services"
        }
    ],
    "sg:phone":"+1 540 672 2100",
    "sg:postcode":"22960",
    "sg:province":"VA",
    "wof:name":"State Farm Insurance",
    "wof:placetype":"venue"
},
  "geometry": {"coordinates":[-78.110938,38.245062],"type":"Point"}
}