{
  "type": "Feature",
  "properties": {
    "addr:full":"5246 Duke St Alexandria VA 22304",
    "addr:housenumber":"5246",
    "addr:postcode":"22304",
    "addr:street":"Duke St",
    "iso:country":"US",
    "sg:address":"5246 Duke St",
    "sg:city":"Alexandria",
    "sg:classifiers":[
        {
            "category":"Health Services",
            "subcategory":"Health Practitioner",
            "type":"Services"
        }
    ],
    "sg:phone":"+1 703 751 9681",
    "sg:postcode":"22304",
    "sg:province":"VA",
    "sg:tags":[
        "nurse",
        "registry"
    ],
    "wof:name":"First Assist Inc",
    "wof:placetype":"venue"
},
  "geometry": {"coordinates":[-77.123043,38.812449],"type":"Point"}
}