{
  "type": "Feature",
  "properties": {
    "iso:country":"US",
    "sg:address":"7800 Richmond Hwy",
    "sg:city":"Alexandria",
    "sg:classifiers":[
        {
            "category":"Autos & Motor Vehicles",
            "subcategory":"Motorcycle Sales",
            "type":"Retail Goods"
        }
    ],
    "sg:phone":"+1 703 780 1245",
    "sg:postcode":"22306",
    "sg:province":"VA",
    "wof:name":"Cycle Sport-Alexandria",
    "wof:placetype":"venue"
},
  "geometry": {"coordinates":[-77.083528,38.745653],"type":"Point"}
}