{
  "type": "Feature",
  "properties": {
    "iso:country":"US",
    "sg:address":"5613 Leesburg Pike",
    "sg:city":"Falls Church",
    "sg:classifiers":[
        {
            "category":"Freight",
            "type":"Transportation"
        }
    ],
    "sg:phone":"+1 703 820 1331",
    "sg:postcode":"22041",
    "sg:province":"VA",
    "sg:tags":[
        "operator",
        "local",
        "trucking"
    ],
    "wof:name":"Syramex International Courier",
    "wof:placetype":"venue"
},
  "geometry": {"coordinates":[-77.12504,38.848374],"type":"Point"}
}