{
  "type": "Feature",
  "properties": {
    "addr:full":"3002 Lafayette Ave Richmond VA 23228",
    "addr:housenumber":"3002",
    "addr:postcode":"23228",
    "addr:street":"Lafayette Ave",
    "iso:country":"US",
    "sg:address":"3002 Lafayette Ave",
    "sg:city":"Richmond",
    "sg:classifiers":[
        {
            "category":"Freight",
            "type":"Transportation"
        }
    ],
    "sg:phone":"+1 804 266 9090",
    "sg:postcode":"23228",
    "sg:province":"VA",
    "sg:tags":[
        "mover"
    ],
    "wof:name":"Regency Moving & Storage",
    "wof:placetype":"venue"
},
  "geometry": {"coordinates":[-77.49406500000001,37.615072],"type":"Point"}
}