{
  "type": "Feature",
  "properties": {
    "addr:full":"1426 Seminole Trl Charlottesville VA 22901",
    "addr:housenumber":"1426",
    "addr:postcode":"22901",
    "addr:street":"Seminole Trl",
    "iso:country":"US",
    "sg:address":"1426 Seminole Trl",
    "sg:city":"Charlottesville",
    "sg:classifiers":[
        {
            "category":"Personal",
            "subcategory":"Beauty Salon",
            "type":"Services"
        }
    ],
    "sg:phone":"+1 434 973 2032",
    "sg:postcode":"22901",
    "sg:province":"VA",
    "wof:name":"Marianne's Hair Salon",
    "wof:placetype":"venue"
},
  "geometry": {"coordinates":[-78.477266,38.078276],"type":"Point"}
}