{
  "type": "Feature",
  "properties": {
    "addr:full":"148 Coffee Rd Lynchburg VA 24503",
    "addr:housenumber":"148",
    "addr:postcode":"24503",
    "addr:street":"Coffee Rd",
    "iso:country":"US",
    "sg:address":"148 Coffee Rd",
    "sg:city":"Lynchburg",
    "sg:classifiers":[
        {
            "category":"Building & Trades",
            "subcategory":"Construction",
            "type":"Services"
        }
    ],
    "sg:phone":"+1 434 384 0223",
    "sg:postcode":"24503",
    "sg:province":"VA",
    "sg:tags":[
        "general",
        "contractor"
    ],
    "wof:name":"Anderson Construction Co",
    "wof:placetype":"venue"
},
  "geometry": {"coordinates":[-79.266369,37.447385],"type":"Point"}
}