{
  "type": "Feature",
  "properties": {
    "addr:full":"1419 Union Run Lexington VA 24450",
    "addr:housenumber":"1419",
    "addr:postcode":"24450",
    "addr:street":"Union Run",
    "iso:country":"US",
    "sg:address":"1419 Union Run",
    "sg:city":"Lexington",
    "sg:classifiers":[
        {
            "category":"Building & Trades",
            "subcategory":"Cleaning & Sanitation",
            "type":"Services"
        }
    ],
    "sg:phone":"+1 540 463 9140",
    "sg:postcode":"24450",
    "sg:province":"VA",
    "sg:tags":[
        "maintenance"
    ],
    "wof:name":"Rebeccahs Cleaning",
    "wof:placetype":"venue"
},
  "geometry": {"coordinates":[-79.492593,37.775482],"type":"Point"}
}