{
  "type": "Feature",
  "properties": {
    "addr:full":"1816 Edgehill Dr Alexandria VA 22307",
    "addr:housenumber":"1816",
    "addr:postcode":"22307",
    "addr:street":"Edgehill Dr",
    "iso:country":"US",
    "sg:address":"1816 Edgehill Dr",
    "sg:city":"Alexandria",
    "sg:classifiers":[
        {
            "category":"Health Services",
            "subcategory":"Doctor",
            "type":"Services"
        }
    ],
    "sg:phone":"+1 703 329 1218",
    "sg:postcode":"22307",
    "sg:province":"VA",
    "sg:tags":[
        "medicine",
        "physician",
        "practice",
        "surgeons",
        "family"
    ],
    "wof:name":"Trimber, M.D., P.C., Connell J.",
    "wof:placetype":"venue"
},
  "geometry": {"coordinates":[-77.062044,38.784082],"type":"Point"}
}