{
  "type": "Feature",
  "properties": {
    "addr:full":"6720 Patterson Ave Richmond VA 23226",
    "addr:housenumber":"6720",
    "addr:postcode":"23226",
    "addr:street":"Patterson Ave",
    "iso:country":"US",
    "sg:address":"6720 Patterson Ave",
    "sg:city":"Richmond",
    "sg:classifiers":[
        {
            "category":"Education",
            "subcategory":"Special Training",
            "type":"Public Place"
        }
    ],
    "sg:phone":"+1 804 304 6865",
    "sg:postcode":"23226",
    "sg:province":"VA",
    "sg:tags":[
        "educational"
    ],
    "wof:name":"Med Outcomes",
    "wof:placetype":"venue"
},
  "geometry": {"coordinates":[-77.527461,37.588252],"type":"Point"}
}