{
  "type": "Feature",
  "properties": {
    "addr:full":"2118 W Cary St Richmond VA 23220",
    "addr:housenumber":"2118",
    "addr:postcode":"23220",
    "addr:street":"W Cary St",
    "iso:country":"US",
    "sg:address":"2118 W Cary St",
    "sg:city":"Richmond",
    "sg:classifiers":[
        {
            "category":"Restaurant",
            "type":"Food & Drink"
        }
    ],
    "sg:phone":"+1 804 340 0802",
    "sg:postcode":"23220",
    "sg:province":"VA",
    "sg:tags":[
        "eating"
    ],
    "wof:name":"T Bones Snack Bar",
    "wof:placetype":"venue"
},
  "geometry": {"coordinates":[-77.468734,37.548964],"type":"Point"}
}