{
  "type": "Feature",
  "properties": {
    "addr:full":"400 N King St Hampton VA 23669",
    "addr:housenumber":"400",
    "addr:postcode":"23669",
    "addr:street":"N King St",
    "iso:country":"US",
    "sg:address":"400 N King St",
    "sg:city":"Hampton",
    "sg:classifiers":[
        {
            "category":"Retail",
            "subcategory":"Auto Rental",
            "type":"Services"
        }
    ],
    "sg:phone":"+1 757 722 0552",
    "sg:postcode":"23669",
    "sg:province":"VA",
    "sg:tags":[
        "renting",
        "truck",
        "leasing"
    ],
    "wof:name":"Budget Truck Rental",
    "wof:placetype":"venue"
},
  "geometry": {"coordinates":[-76.34585800000001,37.031501],"type":"Point"}
}