{
  "type": "Feature",
  "properties": {
    "addr:full":"1027 Winward Rd Norfolk VA 23513",
    "addr:housenumber":"1027",
    "addr:postcode":"23513",
    "addr:street":"Winward Rd",
    "iso:country":"US",
    "sg:address":"1027 Winward Rd",
    "sg:city":"Norfolk",
    "sg:classifiers":[
        {
            "category":"Building & Trades",
            "subcategory":"Pest Control",
            "type":"Services"
        }
    ],
    "sg:phone":"+1 757 853 7549",
    "sg:postcode":"23513",
    "sg:province":"VA",
    "sg:tags":[
        "mothproofing"
    ],
    "wof:name":"Grdn Pest Control",
    "wof:placetype":"venue"
},
  "geometry": {"coordinates":[-76.244585,36.893892],"type":"Point"}
}