{
  "type": "Feature",
  "properties": {
    "iso:country":"US",
    "sg:address":"4001 Fair Ridge Dr",
    "sg:city":"Fairfax",
    "sg:classifiers":[
        {
            "category":"Health Services",
            "subcategory":"Doctor",
            "type":"Services"
        }
    ],
    "sg:phone":"+1 703 293 9099",
    "sg:postcode":"22033",
    "sg:province":"VA",
    "sg:tags":[
        "physician",
        "surgeon"
    ],
    "wof:name":"Alison B Selleck PC",
    "wof:placetype":"venue"
},
  "geometry": {"coordinates":[-77.369781,38.87289],"type":"Point"}
}