{
  "type": "Feature",
  "properties": {
    "iso:country":"US",
    "sg:address":"7152 Woodland Dr",
    "sg:city":"Springfield",
    "sg:classifiers":[
        {
            "category":"Social Services",
            "subcategory":"Child Care",
            "type":"Services"
        }
    ],
    "sg:phone":"+1 703 256 9400",
    "sg:postcode":"22151",
    "sg:province":"VA",
    "sg:tags":[
        "school",
        "day"
    ],
    "sg:website":"www.countrywoodland.com",
    "wof:name":"Country Woodland School",
    "wof:placetype":"venue"
},
  "geometry": {"coordinates":[-77.192016,38.809065],"type":"Point"}
}