{
  "type": "Feature",
  "properties": {
    "addr:full":"702 Park Ave NW Norton VA 24273",
    "addr:housenumber":"702",
    "addr:postcode":"24273",
    "addr:street":"Park Ave Nw",
    "iso:country":"US",
    "sg:address":"702 Park Ave NW",
    "sg:city":"Norton",
    "sg:classifiers":[
        {
            "category":"Arts & Performance",
            "subcategory":"Theater",
            "type":"Entertainment"
        }
    ],
    "sg:phone":"+1 276 679 3116",
    "sg:postcode":"24273",
    "sg:province":"VA",
    "wof:name":"Appalshop",
    "wof:placetype":"venue"
},
  "geometry": {"coordinates":[-82.628325,36.934244],"type":"Point"}
}