{
  "type": "Feature",
  "properties": {
    "addr:full":"5714 Oak Knoll Rd Midlothian VA 23112",
    "addr:housenumber":"5714",
    "addr:postcode":"23112",
    "addr:street":"Oak Knoll Rd",
    "iso:country":"US",
    "sg:address":"5714 Oak Knoll Rd",
    "sg:city":"Midlothian",
    "sg:classifiers":[
        {
            "category":"Recreation",
            "type":"Entertainment"
        }
    ],
    "sg:phone":"+1 804 739 0994",
    "sg:postcode":"23112",
    "sg:province":"VA",
    "sg:tags":[
        "instruction",
        "gymnastic"
    ],
    "wof:name":"Tumblebugs",
    "wof:placetype":"venue"
},
  "geometry": {"coordinates":[-77.679529,37.418546],"type":"Point"}
}