{
  "type": "Feature",
  "properties": {
    "addr:full":"1819 Horseback Trl Vienna VA 22182",
    "addr:housenumber":"1819",
    "addr:postcode":"22182",
    "addr:street":"Horseback Trl",
    "iso:country":"US",
    "sg:address":"1819 Horseback Trl",
    "sg:city":"Vienna",
    "sg:classifiers":[
        {
            "category":"Real Estate",
            "subcategory":"Real Estate Agent",
            "type":"Services"
        }
    ],
    "sg:phone":"+1 703 938 1808",
    "sg:postcode":"22182",
    "sg:province":"VA",
    "sg:tags":[
        "development",
        "investor"
    ],
    "wof:name":"Financial General Properties",
    "wof:placetype":"venue"
},
  "geometry": {"coordinates":[-77.30216,38.935888],"type":"Point"}
}