{
  "type": "Feature",
  "properties": {
    "addr:full":"874 Wagon Trail Rd Ridgeway VA 24148",
    "addr:housenumber":"874",
    "addr:postcode":"24148",
    "addr:street":"Wagon Trail Rd",
    "iso:country":"US",
    "sg:address":"874 Wagon Trail Rd",
    "sg:city":"Ridgeway",
    "sg:classifiers":[
        {
            "category":"Personal",
            "subcategory":"Beauty Salon",
            "type":"Services"
        }
    ],
    "sg:phone":"+1 276 957 2272",
    "sg:postcode":"24148",
    "sg:province":"VA",
    "sg:tags":[
        "shop"
    ],
    "wof:name":"Lajuan's Shear Beauty",
    "wof:placetype":"venue"
},
  "geometry": {"coordinates":[-79.988698,36.60787],"type":"Point"}
}