{
  "type": "Feature",
  "properties": {
    "addr:full":"10104 Bushman Drive Oakton VA 22124",
    "addr:housenumber":"10104",
    "addr:postcode":"22124",
    "addr:street":"Bushman Drive",
    "iso:country":"US",
    "sg:address":"10104 Bushman Drive",
    "sg:city":"Oakton",
    "sg:classifiers":[
        {
            "category":"Professional",
            "subcategory":"Computer Services",
            "type":"Services"
        }
    ],
    "sg:phone":"+1 800 833 9796",
    "sg:postcode":"22124",
    "sg:province":"VA",
    "sg:tags":[
        "enterprise-2-0",
        "social-media",
        "productivity"
    ],
    "sg:website":"http://infovark.com",
    "wof:name":"Infovark",
    "wof:placetype":"venue"
},
  "geometry": {"coordinates":[-77.29431700000001,38.875771],"type":"Point"}
}