{
  "type": "Feature",
  "properties": {
    "iso:country":"US",
    "sg:address":"737 Helmsdale Way",
    "sg:city":"Chesapeake",
    "sg:classifiers":[
        {
            "category":"Professional",
            "type":"Services"
        }
    ],
    "sg:phone":"+1 757 410 3449",
    "sg:postcode":"23320",
    "sg:province":"VA",
    "sg:tags":[
        "establishment"
    ],
    "wof:name":"Allbritton RL",
    "wof:placetype":"venue"
},
  "geometry": {"coordinates":[-76.264252,36.748391],"type":"Point"}
}