{
  "type": "Feature",
  "properties": {
    "addr:full":"4003 W Main St Salem VA 24153",
    "addr:housenumber":"4003",
    "addr:postcode":"24153",
    "addr:street":"W Main St",
    "iso:country":"US",
    "sg:address":"4003 W Main St",
    "sg:city":"Salem",
    "sg:classifiers":[
        {
            "category":"Recreation",
            "subcategory":"Amusement Park",
            "type":"Entertainment"
        }
    ],
    "sg:phone":"+1 540 380 2305",
    "sg:postcode":"24153",
    "sg:province":"VA",
    "wof:name":"Al Salem Enterprises",
    "wof:placetype":"venue"
},
  "geometry": {"coordinates":[-80.134096,37.27405],"type":"Point"}
}