{
  "type": "Feature",
  "properties": {
    "iso:country":"US",
    "sg:address":"2416 26th Rd S",
    "sg:city":"Arlington",
    "sg:classifiers":[
        {
            "category":"Taxi",
            "type":"Transportation"
        },
        {
            "category":"Professional",
            "subcategory":"Business Services",
            "type":"Services"
        },
        {
            "category":"Government",
            "subcategory":"Post Office",
            "type":"Public Place"
        }
    ],
    "sg:phone":"+1 703 271 8628",
    "sg:postcode":"22206",
    "sg:province":"VA",
    "sg:tags":[
        "delivery",
        "messenger",
        "courier"
    ],
    "wof:name":"Atlas Express Courier",
    "wof:placetype":"venue"
},
  "geometry": {"coordinates":[-77.07759799999999,38.845373],"type":"Point"}
}