{
  "type": "Feature",
  "properties": {
    "addr:full":"5181 N Lee Hwy Arlington VA 22207",
    "addr:housenumber":"5181",
    "addr:postcode":"22207",
    "addr:street":"N Lee Hwy",
    "iso:country":"US",
    "sg:address":"5181 N Lee Hwy",
    "sg:city":"Arlington",
    "sg:classifiers":[
        {
            "category":"Professional",
            "subcategory":"Engineering",
            "type":"Services"
        }
    ],
    "sg:phone":"+1 703 631 5775",
    "sg:postcode":"22207",
    "sg:province":"VA",
    "sg:tags":[
        "engineer"
    ],
    "wof:name":"Frazier Consultants Inc",
    "wof:placetype":"venue"
},
  "geometry": {"coordinates":[-77.132881,38.896453],"type":"Point"}
}