{
  "type": "Feature",
  "properties": {
    "iso:country":"US",
    "sg:address":"810 Caroline St",
    "sg:city":"Fredericksburg",
    "sg:classifiers":[
        {
            "category":"Shopping",
            "subcategory":"Gifts & Souvenirs",
            "type":"Retail Goods"
        }
    ],
    "sg:phone":"+1 540 373 4110",
    "sg:postcode":"22401",
    "sg:province":"VA",
    "sg:tags":[
        "shop",
        "novelty"
    ],
    "sg:website":"www.ihscelti.com",
    "wof:name":"Celtic Connection Lc",
    "wof:placetype":"venue"
},
  "geometry": {"coordinates":[-77.458808,38.302257],"type":"Point"}
}