{
  "type": "Feature",
  "properties": {
    "iso:country":"US",
    "sg:address":"16 Molly Cir",
    "sg:city":"Martinsville",
    "sg:classifiers":[
        {
            "category":"Real Estate",
            "subcategory":"Real Estate Operator",
            "type":"Services"
        }
    ],
    "sg:phone":"+1 276 638 4431",
    "sg:postcode":"24112",
    "sg:province":"VA",
    "sg:tags":[
        "apartment"
    ],
    "wof:name":"Wellington Manor",
    "wof:placetype":"venue"
},
  "geometry": {"coordinates":[-79.79234,36.681886],"type":"Point"}
}