{
  "type": "Feature",
  "properties": {
    "addr:full":"23202 Airport St Petersburg VA 23803",
    "addr:housenumber":"23202",
    "addr:postcode":"23803",
    "addr:street":"Airport St",
    "iso:country":"US",
    "sg:address":"23202 Airport St",
    "sg:city":"Petersburg",
    "sg:classifiers":[
        {
            "category":"Wholesale",
            "subcategory":"Office Equipment",
            "type":"Manufacturing & Wholesale Goods"
        }
    ],
    "sg:phone":"+1 804 861 8454",
    "sg:postcode":"23803",
    "sg:province":"VA",
    "sg:tags":[
        "register",
        "cash",
        "supply"
    ],
    "wof:name":"Southside Business Machine Co",
    "wof:placetype":"venue"
},
  "geometry": {"coordinates":[-77.504122,37.193286],"type":"Point"}
}