{
  "type": "Feature",
  "properties": {
    "addr:full":"197 Broadview Ave Warrenton VA 20186",
    "addr:housenumber":"197",
    "addr:postcode":"20186",
    "addr:street":"Broadview Ave",
    "iso:country":"US",
    "sg:address":"197 Broadview Ave",
    "sg:city":"Warrenton",
    "sg:classifiers":[
        {
            "category":"Building & Trades",
            "subcategory":"Construction",
            "type":"Services"
        }
    ],
    "sg:phone":"+1 540 347 0027",
    "sg:postcode":"20186",
    "sg:province":"VA",
    "sg:tags":[
        "contractor"
    ],
    "sg:website":"www.sublettservices.com",
    "wof:name":"Sublett Services Lcc",
    "wof:placetype":"venue"
},
  "geometry": {"coordinates":[-77.80538199999999,38.72223],"type":"Point"}
}