{
  "type": "Feature",
  "properties": {
    "addr:full":"242 Millwood Ave Winchester VA 22601",
    "addr:housenumber":"242",
    "addr:postcode":"22601",
    "addr:street":"Millwood Ave",
    "iso:country":"US",
    "sg:address":"242 Millwood Ave",
    "sg:city":"Winchester",
    "sg:classifiers":[
        {
            "category":"Restaurant",
            "type":"Food & Drink"
        }
    ],
    "sg:phone":"+1 540 535 2055",
    "sg:postcode":"22601",
    "sg:province":"VA",
    "sg:website":"www.cantinaditalia.com",
    "wof:name":"Cantina D'Italia",
    "wof:placetype":"venue"
},
  "geometry": {"coordinates":[-78.164796,39.172546],"type":"Point"}
}