{
  "type": "Feature",
  "properties": {
    "addr:full":"4524 N Lee Hwy Arlington VA 22207",
    "addr:housenumber":"4524",
    "addr:postcode":"22207",
    "addr:street":"N Lee Hwy",
    "iso:country":"US",
    "sg:address":"4524 N Lee Hwy",
    "sg:city":"Arlington",
    "sg:classifiers":[
        {
            "category":"Shopping",
            "subcategory":"Books",
            "type":"Retail Goods"
        }
    ],
    "sg:phone":"+1 703 522 2047",
    "sg:postcode":"22207",
    "sg:province":"VA",
    "sg:tags":[
        "store"
    ],
    "wof:name":"Imagination Station",
    "wof:placetype":"venue"
},
  "geometry": {"coordinates":[-77.119043,38.898496],"type":"Point"}
}