{
  "type": "Feature",
  "properties": {
    "addr:full":"900 Bland Blvd Newport News VA 23602",
    "addr:housenumber":"900",
    "addr:postcode":"23602",
    "addr:street":"Bland Blvd",
    "iso:country":"US",
    "sg:address":"900 Bland Blvd",
    "sg:city":"Newport News",
    "sg:classifiers":[
        {
            "category":"Restaurant",
            "type":"Food & Drink"
        }
    ],
    "sg:phone":"+1 757 988 0506",
    "sg:postcode":"23602",
    "sg:province":"VA",
    "sg:tags":[
        "fast"
    ],
    "wof:name":"Burger King",
    "wof:placetype":"venue"
},
  "geometry": {"coordinates":[-76.510215,37.128337],"type":"Point"}
}