{
  "type": "Feature",
  "properties": {
    "iso:country":"US",
    "sg:address":"403 S Main St",
    "sg:city":"Woodstock",
    "sg:classifiers":[
        {
            "category":"Freight",
            "type":"Transportation"
        }
    ],
    "sg:phone":"+1 540 459 4555",
    "sg:postcode":"22664",
    "sg:province":"VA",
    "sg:tags":[
        "trucking"
    ],
    "wof:name":"Trans Service Assoc Inc",
    "wof:placetype":"venue"
},
  "geometry": {"coordinates":[-78.507999,38.878173],"type":"Point"}
}