{
  "type": "Feature",
  "properties": {
    "iso:country":"US",
    "sg:address":"12144 Kain Rd",
    "sg:city":"Glen Allen",
    "sg:classifiers":[
        {
            "category":"Building & Trades",
            "subcategory":"Construction",
            "type":"Services"
        }
    ],
    "sg:phone":"+1 804 360 8331",
    "sg:postcode":"23059",
    "sg:province":"VA",
    "sg:tags":[
        "concrete",
        "contractor"
    ],
    "wof:name":"Jesus H Lopez Concrete",
    "wof:placetype":"venue"
},
  "geometry": {"coordinates":[-77.616812,37.666579],"type":"Point"}
}