{
  "type": "Feature",
  "properties": {
    "addr:full":"5001 W Broad St Richmond VA 23230",
    "addr:housenumber":"5001",
    "addr:postcode":"23230",
    "addr:street":"W Broad St",
    "iso:country":"US",
    "sg:address":"5001 W Broad St",
    "sg:city":"Richmond",
    "sg:classifiers":[
        {
            "category":"Government",
            "subcategory":"Office",
            "type":"Public Place"
        }
    ],
    "sg:phone":"+1 804 662 7365",
    "sg:postcode":"23230",
    "sg:province":"VA",
    "sg:tags":[
        "village"
    ],
    "wof:name":"Richmond Capital Area ASAP",
    "wof:placetype":"venue"
},
  "geometry": {"coordinates":[-77.498357,37.585533],"type":"Point"}
}