{
  "type": "Feature",
  "properties": {
    "addr:full":"13412 Jefferson Davis Hwy Woodbridge VA 22191",
    "addr:housenumber":"13412",
    "addr:postcode":"22191",
    "addr:street":"Jefferson Davis Hwy",
    "iso:country":"US",
    "sg:address":"13412 Jefferson Davis Hwy",
    "sg:city":"Woodbridge",
    "sg:classifiers":[
        {
            "category":"Professional",
            "type":"Services"
        }
    ],
    "sg:phone":"+1 703 491 7975",
    "sg:postcode":"22191",
    "sg:province":"VA",
    "sg:tags":[
        "establishment"
    ],
    "wof:name":"Myung Shin Corp",
    "wof:placetype":"venue"
},
  "geometry": {"coordinates":[-77.247006,38.661715],"type":"Point"}
}