{
  "type": "Feature",
  "properties": {
    "iso:country":"US",
    "sg:address":"16644 Mountain Rd",
    "sg:city":"Montpelier",
    "sg:classifiers":[
        {
            "category":"Professional",
            "subcategory":"Business Services",
            "type":"Services"
        }
    ],
    "sg:phone":"+1 804 883 3005",
    "sg:postcode":"23192",
    "sg:province":"VA",
    "wof:name":"Keith Rathbone Pt & Assoc Inc",
    "wof:placetype":"venue"
},
  "geometry": {"coordinates":[-77.664293,37.814085],"type":"Point"}
}