{
  "type": "Feature",
  "properties": {
    "addr:full":"13565 Cobra Dr Herndon VA 20171",
    "addr:housenumber":"13565",
    "addr:postcode":"20171",
    "addr:street":"Cobra Dr",
    "iso:country":"US",
    "sg:address":"13565 Cobra Dr",
    "sg:city":"Herndon",
    "sg:classifiers":[
        {
            "category":"Professional",
            "subcategory":"Management & Consulting",
            "type":"Services"
        }
    ],
    "sg:phone":"+1 703 481 4300",
    "sg:postcode":"20171",
    "sg:province":"VA",
    "sg:tags":[
        "support",
        "administrative"
    ],
    "wof:name":"Marson Corporation",
    "wof:placetype":"venue"
},
  "geometry": {"coordinates":[-77.40948299999999,38.920978],"type":"Point"}
}