{
  "type": "Feature",
  "properties": {
    "iso:country":"US",
    "sg:address":"2139 S Oxford St",
    "sg:city":"Arlington",
    "sg:classifiers":[
        {
            "category":"Building & Trades",
            "subcategory":"Landscaping Services",
            "type":"Services"
        }
    ],
    "sg:phone":"+1 703 778 6618",
    "sg:postcode":"22204",
    "sg:province":"VA",
    "wof:name":"C & J Lawn Landscaping & Janitorial Services",
    "wof:placetype":"venue"
},
  "geometry": {"coordinates":[-77.091607,38.848746],"type":"Point"}
}