{
  "type": "Feature",
  "properties": {
    "iso:country":"US",
    "sg:address":"107 Minuet Dr",
    "sg:city":"Covington",
    "sg:classifiers":[
        {
            "category":"Organizations",
            "subcategory":"Religious Organization",
            "type":"Services"
        }
    ],
    "sg:phone":"+1 540 962 3032",
    "sg:postcode":"24426",
    "sg:province":"VA",
    "sg:tags":[
        "church"
    ],
    "wof:name":"Mt Pleasant United Methodist",
    "wof:placetype":"venue"
},
  "geometry": {"coordinates":[-80.00041299999999,37.825608],"type":"Point"}
}