{
  "type": "Feature",
  "properties": {
    "iso:country":"US",
    "sg:address":"836 Reece Rd SW",
    "sg:city":"Willis",
    "sg:classifiers":[
        {
            "category":"Organizations",
            "subcategory":"Religious Organization",
            "type":"Services"
        }
    ],
    "sg:phone":"+1 540 789 7730",
    "sg:postcode":"24380",
    "sg:province":"VA",
    "sg:tags":[
        "church"
    ],
    "wof:name":"Myra Fork Baptist Church",
    "wof:placetype":"venue"
},
  "geometry": {"coordinates":[-80.547202,36.838647],"type":"Point"}
}