{
  "type": "Feature",
  "properties": {
    "addr:full":"137 Spring St Herndon VA 20170",
    "addr:housenumber":"137",
    "addr:postcode":"20170",
    "addr:street":"Spring St",
    "iso:country":"US",
    "sg:address":"137 Spring St",
    "sg:city":"Herndon",
    "sg:classifiers":[
        {
            "category":"Building & Trades",
            "subcategory":"Construction",
            "type":"Services"
        }
    ],
    "sg:phone":"+1 703 974 4774",
    "sg:postcode":"20170",
    "sg:province":"VA",
    "sg:tags":[
        "house"
    ],
    "wof:name":"Lone Star Development Inc",
    "wof:placetype":"venue"
},
  "geometry": {"coordinates":[-77.374291,38.958788],"type":"Point"}
}