{
  "type": "Feature",
  "properties": {
    "addr:full":"13540 Waterford Pl Midlothian VA 23112",
    "addr:housenumber":"13540",
    "addr:postcode":"23112",
    "addr:street":"Waterford Pl",
    "iso:country":"US",
    "sg:address":"13540 Waterford Pl",
    "sg:city":"Midlothian",
    "sg:classifiers":[
        {
            "category":"Personal",
            "subcategory":"Beauty Salon",
            "type":"Services"
        }
    ],
    "sg:phone":"+1 804 744 5100",
    "sg:postcode":"23112",
    "sg:province":"VA",
    "sg:tags":[
        "shop"
    ],
    "wof:name":"Waterford Hair",
    "wof:placetype":"venue"
},
  "geometry": {"coordinates":[-77.64775299999999,37.450938],"type":"Point"}
}