{
  "type": "Feature",
  "properties": {
    "addr:full":"11610 Busy St Richmond VA 23236",
    "addr:postcode":"11610;23236",
    "addr:street":"Busy St",
    "iso:country":"US",
    "sg:address":"11610 Busy St",
    "sg:city":"Richmond",
    "sg:classifiers":[
        {
            "category":"Insurance",
            "subcategory":"Insurance Agent",
            "type":"Services"
        }
    ],
    "sg:phone":"+1 804 794 3300",
    "sg:postcode":"23236",
    "sg:province":"VA",
    "wof:name":"Mike Mc Caffery Insurance",
    "wof:placetype":"venue"
},
  "geometry": {"coordinates":[-77.610393,37.502441],"type":"Point"}
}