{
  "type": "Feature",
  "properties": {
    "iso:country":"US",
    "sg:address":"601 Madison St",
    "sg:city":"Alexandria",
    "sg:classifiers":[
        {
            "category":"Manufacturing",
            "subcategory":"Tools & Machinery",
            "type":"Manufacturing & Wholesale Goods"
        },
        {
            "category":"Wholesale",
            "subcategory":"Auto Parts",
            "type":"Manufacturing & Wholesale Goods"
        }
    ],
    "sg:phone":"+1 703 549 9266",
    "sg:postcode":"22314",
    "sg:province":"VA",
    "sg:tags":[
        "power",
        "supply",
        "transmission",
        "automobile",
        "mfg",
        "equipment"
    ],
    "wof:name":"Allison Transmission",
    "wof:placetype":"venue"
},
  "geometry": {"coordinates":[-77.045265,38.813019],"type":"Point"}
}