{
  "type": "Feature",
  "properties": {
    "addr:full":"350 Mary Gray Ln Staunton VA 24401",
    "addr:housenumber":"350",
    "addr:postcode":"24401",
    "addr:street":"Mary Gray Ln",
    "iso:country":"US",
    "sg:address":"350 Mary Gray Ln",
    "sg:city":"Staunton",
    "sg:classifiers":[
        {
            "category":"Education",
            "subcategory":"Special Training",
            "type":"Public Place"
        }
    ],
    "sg:phone":"+1 540 885 5778",
    "sg:postcode":"24401",
    "sg:province":"VA",
    "wof:name":"Frances Lamb Piano Studio",
    "wof:placetype":"venue"
},
  "geometry": {"coordinates":[-79.058559,38.130555],"type":"Point"}
}