{
  "type": "Feature",
  "properties": {
    "iso:country":"US",
    "sg:address":"321 N Washington St",
    "sg:city":"Falls Church",
    "sg:classifiers":[
        {
            "category":"Health Services",
            "subcategory":"Doctor",
            "type":"Services"
        }
    ],
    "sg:phone":"+1 703 534 4700",
    "sg:postcode":"22046",
    "sg:province":"VA",
    "sg:tags":[
        "dentist"
    ],
    "wof:name":"Ralph E Gallimore DDS",
    "wof:placetype":"venue"
},
  "geometry": {"coordinates":[-77.168302,38.884351],"type":"Point"}
}