{
  "type": "Feature",
  "properties": {
    "addr:full":"2623 Volunteer Pkwy Bristol VA 37620",
    "addr:housenumber":"2623",
    "addr:postcode":"37620",
    "addr:street":"Volunteer Pkwy",
    "iso:country":"US",
    "sg:address":"2623 Volunteer Pkwy",
    "sg:city":"Bristol",
    "sg:classifiers":[
        {
            "category":"Travel",
            "subcategory":"Campground",
            "type":"Entertainment"
        }
    ],
    "sg:phone":"+1 423 652 2267",
    "sg:postcode":"37620",
    "sg:province":"VA",
    "sg:website":"www.thundervalleycampground.com",
    "wof:name":"Thunder Valley Campground",
    "wof:placetype":"venue"
},
  "geometry": {"coordinates":[-82.255055,36.525718],"type":"Point"}
}