{
  "type": "Feature",
  "properties": {
    "addr:full":"4616 Candlelight Ct Glen Allen VA 23060",
    "addr:housenumber":"4616",
    "addr:postcode":"23060",
    "addr:street":"Candlelight Ct",
    "iso:country":"US",
    "sg:address":"4616 Candlelight Ct",
    "sg:city":"Glen Allen",
    "sg:classifiers":[
        {
            "category":"Wholesale",
            "subcategory":"Chemicals & Plastics",
            "type":"Manufacturing & Wholesale Goods"
        }
    ],
    "sg:phone":"+1 804 747 4249",
    "sg:postcode":"23060",
    "sg:province":"VA",
    "wof:name":"S I Concrete Systems",
    "wof:placetype":"venue"
},
  "geometry": {"coordinates":[-77.544782,37.653258],"type":"Point"}
}