{
  "type": "Feature",
  "properties": {
    "iso:country":"US",
    "sg:address":"5222 Beaver Dam Rd",
    "sg:city":"Waverly",
    "sg:classifiers":[
        {
            "category":"Real Estate",
            "subcategory":"Real Estate Operator",
            "type":"Services"
        }
    ],
    "sg:phone":"+1 804 834 2377",
    "sg:postcode":"23890",
    "sg:province":"VA",
    "sg:tags":[
        "property",
        "lessor"
    ],
    "wof:name":"R Westbrook",
    "wof:placetype":"venue"
},
  "geometry": {"coordinates":[-77.070695,37.049015],"type":"Point"}
}