{
  "type": "Feature",
  "properties": {
    "addr:full":"3166 S Terry's Bridge Rd Scottsburg VA 24589",
    "addr:housenumber":"3166",
    "addr:postcode":"24589",
    "addr:street":"S Terry'S Bridge Rd",
    "iso:country":"US",
    "sg:address":"3166 S Terry's Bridge Rd",
    "sg:city":"Scottsburg",
    "sg:classifiers":[
        {
            "category":"Retail",
            "subcategory":"Auto Repair",
            "type":"Services"
        }
    ],
    "sg:phone":"+1 434 454 7301",
    "sg:postcode":"24589",
    "sg:province":"VA",
    "sg:tags":[
        "body",
        "automobile",
        "painting"
    ],
    "wof:name":"Moore's Body Shop",
    "wof:placetype":"venue"
},
  "geometry": {"coordinates":[-78.802133,36.754815],"type":"Point"}
}