{
  "type": "Feature",
  "properties": {
    "iso:country":"US",
    "sg:address":"715 S Washington St",
    "sg:city":"Alexandria",
    "sg:classifiers":[
        {
            "category":"Professional",
            "subcategory":"Management & Consulting",
            "type":"Services"
        }
    ],
    "sg:phone":"+1 703 299 9060",
    "sg:postcode":"22314",
    "sg:province":"VA",
    "sg:tags":[
        "training"
    ],
    "wof:name":"SL Associates",
    "wof:placetype":"venue"
},
  "geometry": {"coordinates":[-77.048734,38.797188],"type":"Point"}
}