{
  "type": "Feature",
  "properties": {
    "iso:country":"US",
    "sg:address":"813 Toms Creek Rd",
    "sg:city":"Blacksburg",
    "sg:classifiers":[
        {
            "category":"Education",
            "subcategory":"School",
            "type":"Public Place"
        }
    ],
    "sg:phone":"+1 540 951 5726",
    "sg:postcode":"24060",
    "sg:province":"VA",
    "wof:name":"Montgomery County Dist",
    "wof:placetype":"venue"
},
  "geometry": {"coordinates":[-80.42658299999999,37.236072],"type":"Point"}
}