{
  "type": "Feature",
  "properties": {
    "iso:country":"US",
    "sg:address":"703 Oakland Ave",
    "sg:city":"Hampton",
    "sg:classifiers":[
        {
            "category":"Building & Trades",
            "subcategory":"Construction",
            "type":"Services"
        }
    ],
    "sg:phone":"+1 757 771 5845",
    "sg:postcode":"23663",
    "sg:province":"VA",
    "sg:tags":[
        "handyman"
    ],
    "wof:name":"Legacy Conservation",
    "wof:placetype":"venue"
},
  "geometry": {"coordinates":[-76.324409,37.030391],"type":"Point"}
}