{
  "type": "Feature",
  "properties": {
    "iso:country":"US",
    "sg:address":"9942 Midlothian Tpke",
    "sg:city":"Richmond",
    "sg:classifiers":[
        {
            "category":"Personal",
            "subcategory":"Beauty Salon",
            "type":"Services"
        }
    ],
    "sg:phone":"+1 804 320 1733",
    "sg:postcode":"23235",
    "sg:province":"VA",
    "sg:tags":[
        "shop"
    ],
    "wof:name":"Robious Nails",
    "wof:placetype":"venue"
},
  "geometry": {"coordinates":[-77.577026,37.504276],"type":"Point"}
}