{
  "type": "Feature",
  "properties": {
    "iso:country":"US",
    "sg:address":"12490 Warwick Blvd",
    "sg:city":"Newport News",
    "sg:classifiers":[
        {
            "category":"Shopping",
            "subcategory":"Clothing, Apparel, & Fashions",
            "type":"Retail Goods"
        }
    ],
    "sg:phone":"+1 757 596 0228",
    "sg:postcode":"23606",
    "sg:province":"VA",
    "wof:name":"Talbots 245",
    "wof:placetype":"venue"
},
  "geometry": {"coordinates":[-76.493906,37.074244],"type":"Point"}
}