{
  "type": "Feature",
  "properties": {
    "addr:full":"1080 Riverside Dr Danville VA 24540",
    "addr:housenumber":"1080",
    "addr:postcode":"24540",
    "addr:street":"Riverside Dr",
    "iso:country":"US",
    "sg:address":"1080 Riverside Dr",
    "sg:city":"Danville",
    "sg:classifiers":[
        {
            "category":"Autos & Motor Vehicles",
            "subcategory":"Automobile Sales",
            "type":"Retail Goods"
        }
    ],
    "sg:phone":"+1 434 793 5922",
    "sg:postcode":"24540",
    "sg:province":"VA",
    "sg:tags":[
        "car",
        "used",
        "dealer"
    ],
    "wof:name":"Fitzgerald's Auto Sales",
    "wof:placetype":"venue"
},
  "geometry": {"coordinates":[-79.401824,36.596558],"type":"Point"}
}