{
  "type": "Feature",
  "properties": {
    "iso:country":"US",
    "sg:address":"2618 Nevada Ave",
    "sg:city":"Norfolk",
    "sg:classifiers":[
        {
            "category":"Building & Trades",
            "subcategory":"Electrical",
            "type":"Services"
        }
    ],
    "sg:phone":"+1 757 855 4545",
    "sg:postcode":"23513",
    "sg:province":"VA",
    "sg:tags":[
        "electrical",
        "contractor"
    ],
    "wof:name":"Residential Service Co Inc",
    "wof:placetype":"venue"
},
  "geometry": {"coordinates":[-76.24705,36.871839],"type":"Point"}
}