{
  "type": "Feature",
  "properties": {
    "addr:full":"2776 Hydraulic Rd Charlottesville VA 22901",
    "addr:housenumber":"2776",
    "addr:postcode":"22901",
    "addr:street":"Hydraulic Rd",
    "iso:country":"US",
    "sg:address":"2776 Hydraulic Rd",
    "sg:city":"Charlottesville",
    "sg:classifiers":[
        {
            "category":"Professional",
            "subcategory":"Accounting & Tax Preparation",
            "type":"Services"
        }
    ],
    "sg:phone":"+1 434 978 2864",
    "sg:postcode":"22901",
    "sg:province":"VA",
    "sg:tags":[
        "accountant"
    ],
    "wof:name":"William N Keyseear CPA",
    "wof:placetype":"venue"
},
  "geometry": {"coordinates":[-78.498474,38.074626],"type":"Point"}
}