{
  "type": "Feature",
  "properties": {
    "addr:full":"7500 Leesburg Pike Falls Church VA 22043",
    "addr:housenumber":"7500",
    "addr:postcode":"22043",
    "addr:street":"Leesburg Pike",
    "iso:country":"US",
    "sg:address":"7500 Leesburg Pike",
    "sg:city":"Falls Church",
    "sg:classifiers":[
        {
            "category":"Building & Trades",
            "subcategory":"Locksmith",
            "type":"Services"
        }
    ],
    "sg:phone":"+1 571 730 0735",
    "sg:postcode":"22043",
    "sg:province":"VA",
    "sg:tags":[
        "key"
    ],
    "wof:name":"Leesburg Pike 24 Hour Locksmith",
    "wof:placetype":"venue"
},
  "geometry": {"coordinates":[-77.203022,38.903007],"type":"Point"}
}