{
  "type": "Feature",
  "properties": {
    "iso:country":"US",
    "sg:address":"1600 Duke St",
    "sg:city":"Alexandria",
    "sg:classifiers":[
        {
            "category":"Government",
            "subcategory":"Office",
            "type":"Public Place"
        }
    ],
    "sg:phone":"+1 703 683 2680",
    "sg:postcode":"22314",
    "sg:province":"VA",
    "wof:name":"Vitetta",
    "wof:placetype":"venue"
},
  "geometry": {"coordinates":[-77.05951,38.80432],"type":"Point"}
}