{
  "type": "Feature",
  "properties": {
    "iso:country":"US",
    "sg:address":"4040 Postal Dr",
    "sg:city":"Roanoke",
    "sg:classifiers":[
        {
            "category":"Health Services",
            "subcategory":"Doctor",
            "type":"Services"
        }
    ],
    "sg:phone":"+1 540 772 4453",
    "sg:postcode":"24018",
    "sg:province":"VA",
    "sg:tags":[
        "medical"
    ],
    "wof:name":"Kunkle Arthur A MD",
    "wof:placetype":"venue"
},
  "geometry": {"coordinates":[-80.01114800000001,37.234619],"type":"Point"}
}