{
  "type": "Feature",
  "properties": {
    "iso:country":"US",
    "sg:address":"8570 Executive Park Ave",
    "sg:city":"Fairfax",
    "sg:classifiers":[
        {
            "category":"Utilities",
            "subcategory":"Water",
            "type":"Services"
        }
    ],
    "sg:phone":"+1 703 698 5800",
    "sg:postcode":"22031",
    "sg:province":"VA",
    "sg:tags":[
        "company",
        "sewage"
    ],
    "sg:website":"www.fcwa.org",
    "wof:name":"Fairfax County Water Authority",
    "wof:placetype":"venue"
},
  "geometry": {"coordinates":[-77.23853800000001,38.867651],"type":"Point"}
}