{
  "type": "Feature",
  "properties": {
    "addr:full":"2922 Annandale Rd Falls Church VA 22042",
    "addr:housenumber":"2922",
    "addr:postcode":"22042",
    "addr:street":"Annandale Rd",
    "iso:country":"US",
    "sg:address":"2922 Annandale Rd",
    "sg:city":"Falls Church",
    "sg:classifiers":[
        {
            "category":"Restaurant",
            "type":"Food & Drink"
        }
    ],
    "sg:phone":"+1 703 538 8888",
    "sg:postcode":"22042",
    "sg:province":"VA",
    "wof:name":"Majestic Restaurant",
    "wof:placetype":"venue"
},
  "geometry": {"coordinates":[-77.174559,38.871607],"type":"Point"}
}