{
  "type": "Feature",
  "properties": {
    "addr:full":"580 Peregrine St Virginia Beach VA 23462",
    "addr:housenumber":"580",
    "addr:postcode":"23462",
    "addr:street":"Peregrine St",
    "iso:country":"US",
    "sg:address":"580 Peregrine St",
    "sg:city":"Virginia Beach",
    "sg:classifiers":[
        {
            "category":"Professional",
            "subcategory":"Business Services",
            "type":"Services"
        }
    ],
    "sg:phone":"+1 757 717 1890",
    "sg:postcode":"23462",
    "sg:province":"VA",
    "wof:name":"Vynture Solutions",
    "wof:placetype":"venue"
},
  "geometry": {"coordinates":[-76.159565,36.851999],"type":"Point"}
}