{
  "type": "Feature",
  "properties": {
    "addr:full":"20 N Union St Petersburg VA 23803",
    "addr:housenumber":"20",
    "addr:postcode":"23803",
    "addr:street":"N Union",
    "iso:country":"US",
    "sg:address":"20 N Union St",
    "sg:city":"Petersburg",
    "sg:classifiers":[
        {
            "category":"Retail",
            "subcategory":"Car Wash",
            "type":"Services"
        }
    ],
    "sg:phone":"+1 804 732 3400",
    "sg:postcode":"23803",
    "sg:province":"VA",
    "sg:tags":[
        "automobile",
        "detail",
        "clean"
    ],
    "wof:name":"We Detail",
    "wof:placetype":"venue"
},
  "geometry": {"coordinates":[-77.405117,37.228382],"type":"Point"}
}