{
  "type": "Feature",
  "properties": {
    "addr:full":"102 Executive Dr Sterling VA 20166",
    "addr:housenumber":"102",
    "addr:postcode":"20166",
    "addr:street":"Executive Dr",
    "iso:country":"US",
    "sg:address":"102 Executive Dr",
    "sg:city":"Sterling",
    "sg:classifiers":[
        {
            "category":"Professional",
            "subcategory":"Business Services",
            "type":"Services"
        }
    ],
    "sg:phone":"+1 703 319 0286",
    "sg:postcode":"20166",
    "sg:province":"VA",
    "sg:tags":[
        "network",
        "integration"
    ],
    "wof:name":"Ipath Technologies",
    "wof:placetype":"venue"
},
  "geometry": {"coordinates":[-77.444954,38.985541],"type":"Point"}
}