{
  "type": "Feature",
  "properties": {
    "iso:country":"US",
    "sg:address":"345 W Duke of Gloucester St",
    "sg:city":"Williamsburg",
    "sg:classifiers":[
        {
            "category":"Shopping",
            "subcategory":"Books",
            "type":"Retail Goods"
        }
    ],
    "sg:phone":"+1 757 221 2480",
    "sg:postcode":"23185",
    "sg:province":"VA",
    "sg:tags":[
        "text",
        "school",
        "college",
        "supply"
    ],
    "wof:name":"William & Mary Bookstore",
    "wof:placetype":"venue"
},
  "geometry": {"coordinates":[-76.704654,37.271079],"type":"Point"}
}