{
  "type": "Feature",
  "properties": {
    "iso:country":"US",
    "sg:address":"424 W 25th St",
    "sg:city":"Norfolk",
    "sg:classifiers":[
        {
            "category":"Wholesale",
            "subcategory":"Machinery & Supplies",
            "type":"Manufacturing & Wholesale Goods"
        }
    ],
    "sg:phone":"+1 757 625 2525",
    "sg:postcode":"23517",
    "sg:province":"VA",
    "sg:tags":[
        "tool"
    ],
    "wof:name":"Bryan Electric Co",
    "wof:placetype":"venue"
},
  "geometry": {"coordinates":[-76.290015,36.872169],"type":"Point"}
}