{
  "type": "Feature",
  "properties": {
    "addr:full":"16 Catherine Ln Stafford VA 22554",
    "addr:housenumber":"16",
    "addr:postcode":"22554",
    "addr:street":"Catherine Ln",
    "iso:country":"US",
    "sg:address":"16 Catherine Ln",
    "sg:city":"Stafford",
    "sg:classifiers":[
        {
            "category":"Freight",
            "type":"Transportation"
        }
    ],
    "sg:phone":"+1 540 295 4123",
    "sg:postcode":"22554",
    "sg:province":"VA",
    "sg:tags":[
        "over",
        "hauling",
        "road"
    ],
    "wof:name":"Dimensions Trucking Inc",
    "wof:placetype":"venue"
},
  "geometry": {"coordinates":[-77.44927300000001,38.459863],"type":"Point"}
}