{
  "type": "Feature",
  "properties": {
    "addr:full":"195 Farrier Ln Winchester VA 22602",
    "addr:housenumber":"195",
    "addr:postcode":"22602",
    "addr:street":"Farrier Ln",
    "iso:country":"US",
    "sg:address":"195 Farrier Ln",
    "sg:city":"Winchester",
    "sg:classifiers":[
        {
            "category":"Shopping",
            "subcategory":"Gifts & Souvenirs",
            "type":"Retail Goods"
        }
    ],
    "sg:phone":"+1 540 877 9933",
    "sg:postcode":"22602",
    "sg:province":"VA",
    "wof:name":"A Touch Of Virginia",
    "wof:placetype":"venue"
},
  "geometry": {"coordinates":[-78.253694,39.194962],"type":"Point"}
}