{
  "type": "Feature",
  "properties": {
    "iso:country":"US",
    "sg:address":"1940 Duke St Ste 200",
    "sg:city":"Alexandria",
    "sg:classifiers":[
        {
            "category":"Professional",
            "subcategory":"Computer Services",
            "type":"Services"
        }
    ],
    "sg:phone":"+1 703 486 5680",
    "sg:postcode":"22314",
    "sg:province":"VA",
    "sg:tags":[
        "cd-rom",
        "software"
    ],
    "wof:name":"Engineering Software & Network Services",
    "wof:placetype":"venue"
},
  "geometry": {"coordinates":[-77.06157,38.80455],"type":"Point"}
}