{
  "type": "Feature",
  "properties": {
    "iso:country":"US",
    "sg:address":"801 S Pitt St",
    "sg:city":"Alexandria",
    "sg:classifiers":[
        {
            "category":"Personal",
            "type":"Services"
        }
    ],
    "sg:phone":"+1 703 519 9600",
    "sg:postcode":"22314",
    "sg:province":"VA",
    "sg:tags":[
        "therapist",
        "massage"
    ],
    "wof:name":"Luna Massage Therapy",
    "wof:placetype":"venue"
},
  "geometry": {"coordinates":[-77.046688,38.79559],"type":"Point"}
}