{
  "type": "Feature",
  "properties": {
    "iso:country":"US",
    "sg:address":"33392 Lee Hwy",
    "sg:city":"Glade Spring",
    "sg:classifiers":[
        {
            "category":"Retail",
            "subcategory":"Auto Repair",
            "type":"Services"
        }
    ],
    "sg:phone":"+1 276 429 5967",
    "sg:postcode":"24340",
    "sg:province":"VA",
    "sg:tags":[
        "wrecker"
    ],
    "wof:name":"Apache Towing & Recovery",
    "wof:placetype":"venue"
},
  "geometry": {"coordinates":[-81.78098199999999,36.769377],"type":"Point"}
}