{
  "type": "Feature",
  "properties": {
    "addr:full":"1310 Evergreen Ct Virginia Beach VA 23453",
    "addr:housenumber":"1310",
    "addr:postcode":"23453",
    "addr:street":"Evergreen Ct",
    "iso:country":"US",
    "sg:address":"1310 Evergreen Ct",
    "sg:city":"Virginia Beach",
    "sg:classifiers":[
        {
            "category":"Building & Trades",
            "subcategory":"Construction",
            "type":"Services"
        }
    ],
    "sg:phone":"+1 757 368 8216",
    "sg:postcode":"23453",
    "sg:province":"VA",
    "sg:tags":[
        "contractor"
    ],
    "wof:name":"Gutierrez Drywall",
    "wof:placetype":"venue"
},
  "geometry": {"coordinates":[-76.09049899999999,36.794753],"type":"Point"}
}