{
  "type": "Feature",
  "properties": {
    "addr:full":"770 Roanoke Rd Daleville VA 24083",
    "addr:housenumber":"770",
    "addr:postcode":"24083",
    "addr:street":"Roanoke Rd",
    "iso:country":"US",
    "sg:address":"770 Roanoke Rd",
    "sg:city":"Daleville",
    "sg:classifiers":[
        {
            "category":"Manufacturing",
            "subcategory":"Lumber",
            "type":"Manufacturing & Wholesale Goods"
        }
    ],
    "sg:phone":"+1 540 992 3771",
    "sg:postcode":"24083",
    "sg:province":"VA",
    "sg:tags":[
        "government"
    ],
    "wof:name":"Forestry Dept",
    "wof:placetype":"venue"
},
  "geometry": {"coordinates":[-79.908115,37.396889],"type":"Point"}
}