{
  "type": "Feature",
  "properties": {
    "iso:country":"US",
    "sg:address":"4030 Allen's Mill Rd",
    "sg:city":"Scottsburg",
    "sg:classifiers":[
        {
            "category":"Retail",
            "subcategory":"Repair Shop",
            "type":"Services"
        },
        {
            "category":"Building & Trades",
            "subcategory":"Construction",
            "type":"Services"
        }
    ],
    "sg:phone":"+1 434 454 7978",
    "sg:postcode":"24589",
    "sg:province":"VA",
    "sg:tags":[
        "welding",
        "contractor"
    ],
    "wof:name":"Tommy's Welding & Fabrication",
    "wof:placetype":"venue"
},
  "geometry": {"coordinates":[-78.74081,36.750323],"type":"Point"}
}