{
  "type": "Feature",
  "properties": {
    "addr:full":"4607 Newcomb Pl Alexandria VA 22304",
    "addr:housenumber":"4607",
    "addr:postcode":"22304",
    "addr:street":"Newcomb Pl",
    "iso:country":"US",
    "sg:address":"4607 Newcomb Pl",
    "sg:city":"Alexandria",
    "sg:classifiers":[
        {
            "category":"Professional",
            "subcategory":"Lawyer & Legal Services",
            "type":"Services"
        }
    ],
    "sg:phone":"+1 703 751 5318",
    "sg:postcode":"22304",
    "sg:province":"VA",
    "wof:name":"Roche Brien A Lwyr",
    "wof:placetype":"venue"
},
  "geometry": {"coordinates":[-77.110703,38.8214],"type":"Point"}
}