{
  "type": "Feature",
  "properties": {
    "iso:country":"US",
    "sg:address":"1965 Logan Manor Dr 100",
    "sg:city":"Reston",
    "sg:classifiers":[
        {
            "category":"Home & Garden",
            "subcategory":"Garden Supply",
            "type":"Retail Goods"
        }
    ],
    "sg:phone":"+1 301 933 4833",
    "sg:postcode":"20190",
    "sg:province":"VA",
    "sg:tags":[
        "tree",
        "christmas"
    ],
    "wof:name":"Seasonal Evergreen Company",
    "wof:placetype":"venue"
},
  "geometry": {"coordinates":[-77.367043,38.957781],"type":"Point"}
}