{
  "type": "Feature",
  "properties": {
    "addr:full":"2900 Yadkin Rd Chesapeake VA 23323",
    "addr:housenumber":"2900",
    "addr:postcode":"23323",
    "addr:street":"Yadkin Rd",
    "iso:country":"US",
    "sg:address":"2900 Yadkin Rd",
    "sg:city":"Chesapeake",
    "sg:classifiers":[
        {
            "category":"Manufacturing",
            "subcategory":"Tools & Machinery",
            "type":"Manufacturing & Wholesale Goods"
        }
    ],
    "sg:phone":"+1 757 487 8879",
    "sg:postcode":"23323",
    "sg:province":"VA",
    "sg:tags":[
        "machine",
        "shop"
    ],
    "wof:name":"R & L Machine Shop Inc",
    "wof:placetype":"venue"
},
  "geometry": {"coordinates":[-76.35240400000001,36.765676],"type":"Point"}
}