{
  "type": "Feature",
  "properties": {
    "addr:full":"2100 Green Watch Way Reston VA 20191",
    "addr:housenumber":"2100",
    "addr:postcode":"20191",
    "addr:street":"Green Watch Way",
    "iso:country":"US",
    "sg:address":"2100 Green Watch Way",
    "sg:city":"Reston",
    "sg:classifiers":[
        {
            "category":"Wholesale",
            "subcategory":"Computers",
            "type":"Manufacturing & Wholesale Goods"
        }
    ],
    "sg:phone":"+1 703 390 9380",
    "sg:postcode":"20191",
    "sg:province":"VA",
    "wof:name":"SMK Soft Inc",
    "wof:placetype":"venue"
},
  "geometry": {"coordinates":[-77.347859,38.93486],"type":"Point"}
}