{
  "type": "Feature",
  "properties": {
    "addr:full":"45850 Edwards Ter Sterling VA 20166",
    "addr:housenumber":"45850",
    "addr:postcode":"20166",
    "addr:street":"Edwards Ter",
    "iso:country":"US",
    "sg:address":"45850 Edwards Ter",
    "sg:city":"Sterling",
    "sg:classifiers":[
        {
            "category":"Professional",
            "type":"Services"
        }
    ],
    "sg:phone":"+1 703 406 1559",
    "sg:postcode":"20166",
    "sg:province":"VA",
    "wof:name":"It2m Inc",
    "wof:placetype":"venue"
},
  "geometry": {"coordinates":[-77.41370499999999,39.032841],"type":"Point"}
}