{
  "type": "Feature",
  "properties": {
    "addr:full":"4020 Bonney Rd Virginia Beach VA 23452",
    "addr:postcode":"4020;23452",
    "addr:street":"Bonney Rd",
    "iso:country":"US",
    "sg:address":"4020 Bonney Rd",
    "sg:city":"Virginia Beach",
    "sg:classifiers":[
        {
            "category":"Retail",
            "subcategory":"Laundry & Dry Cleaning",
            "type":"Services"
        }
    ],
    "sg:phone":"+1 757 747 6400",
    "sg:postcode":"23452",
    "sg:province":"VA",
    "sg:tags":[
        "cleaners"
    ],
    "wof:name":"Bonney Cleaners",
    "wof:placetype":"venue"
},
  "geometry": {"coordinates":[-76.115188,36.838491],"type":"Point"}
}