{
  "type": "Feature",
  "properties": {
    "addr:full":"6824 Forest Hill Ave Richmond VA 23225",
    "addr:housenumber":"6824",
    "addr:postcode":"23225",
    "addr:street":"Forest Hill Ave",
    "iso:country":"US",
    "sg:address":"6824 Forest Hill Ave",
    "sg:city":"Richmond",
    "sg:classifiers":[
        {
            "category":"Food & Beverages",
            "subcategory":"Groceries & Convenience Stores",
            "type":"Retail Goods"
        }
    ],
    "sg:phone":"+1 804 320 7252",
    "sg:postcode":"23225",
    "sg:province":"VA",
    "wof:name":"7-Eleven",
    "wof:placetype":"venue"
},
  "geometry": {"coordinates":[-77.521112,37.538167],"type":"Point"}
}