{
  "type": "Feature",
  "properties": {
    "iso:country":"US",
    "sg:address":"14209 Spruce Ave",
    "sg:city":"Chester",
    "sg:classifiers":[
        {
            "category":"Building & Trades",
            "subcategory":"Construction",
            "type":"Services"
        }
    ],
    "sg:phone":"+1 804 712 8350",
    "sg:postcode":"23836",
    "sg:province":"VA",
    "sg:tags":[
        "house"
    ],
    "wof:name":"Buisset Home Repair",
    "wof:placetype":"venue"
},
  "geometry": {"coordinates":[-77.31514799999999,37.330446],"type":"Point"}
}