{
  "type": "Feature",
  "properties": {
    "addr:full":"717 E Main St Purcellville VA 20132",
    "addr:housenumber":"717",
    "addr:postcode":"20132",
    "addr:street":"E Main St",
    "iso:country":"US",
    "sg:address":"717 E Main St",
    "sg:city":"Purcellville",
    "sg:classifiers":[
        {
            "category":"Real Estate",
            "subcategory":"Real Estate Operator",
            "type":"Services"
        }
    ],
    "sg:phone":"+1 540 338 6219",
    "sg:postcode":"20132",
    "sg:province":"VA",
    "sg:tags":[
        "mall",
        "shopping",
        "center"
    ],
    "wof:name":"Loudoun Valley Shopping Ctr",
    "wof:placetype":"venue"
},
  "geometry": {"coordinates":[-77.705775,39.136584],"type":"Point"}
}