{
  "type": "Feature",
  "properties": {
    "iso:country":"US",
    "sg:address":"2606 S Oxford St",
    "sg:city":"Arlington",
    "sg:classifiers":[
        {
            "category":"Shopping",
            "subcategory":"Pets & Pet Supplies",
            "type":"Retail Goods"
        },
        {
            "category":"Retail",
            "subcategory":"Pet Boarding",
            "type":"Services"
        }
    ],
    "sg:phone":"+1 703 845 3647",
    "sg:postcode":"22206",
    "sg:province":"VA",
    "sg:tags":[
        "walker",
        "boarding/pet",
        "dog",
        "groomers",
        "sitting"
    ],
    "sg:website":"www.wagmoredogs.com",
    "wof:name":"Wag More Dogs",
    "wof:placetype":"venue"
},
  "geometry": {"coordinates":[-77.092174,38.845512],"type":"Point"}
}