{
  "type": "Feature",
  "properties": {
    "addr:full":"1207 Fenwick Dr Lynchburg VA 24502",
    "addr:housenumber":"1207",
    "addr:postcode":"24502",
    "addr:street":"Fenwick Dr",
    "iso:country":"US",
    "sg:address":"1207 Fenwick Dr",
    "sg:city":"Lynchburg",
    "sg:classifiers":[
        {
            "category":"Professional",
            "type":"Services"
        }
    ],
    "sg:phone":"+1 434 237 6466",
    "sg:postcode":"24502",
    "sg:province":"VA",
    "sg:website":"www.vacul.org",
    "wof:name":"Virginia Credit Union Svc Inc",
    "wof:placetype":"venue"
},
  "geometry": {"coordinates":[-79.19613,37.366685],"type":"Point"}
}