{
  "type": "Feature",
  "properties": {
    "addr:full":"11700 Lake Falls Dr Chester VA 23831",
    "addr:housenumber":"11700",
    "addr:postcode":"23831",
    "addr:street":"Lake Falls Dr",
    "iso:country":"US",
    "sg:address":"11700 Lake Falls Dr",
    "sg:city":"Chester",
    "sg:classifiers":[
        {
            "category":"Professional",
            "subcategory":"Management & Consulting",
            "type":"Services"
        }
    ],
    "sg:phone":"+1 804 931 3638",
    "sg:postcode":"23831",
    "sg:province":"VA",
    "wof:name":"Radigan Quality Research Inc",
    "wof:placetype":"venue"
},
  "geometry": {"coordinates":[-77.489014,37.358354],"type":"Point"}
}