{
  "type": "Feature",
  "properties": {
    "addr:full":"2451 Roanoke St Christiansburg VA 24073",
    "addr:housenumber":"2451",
    "addr:postcode":"24073",
    "addr:street":"Roanoke St",
    "iso:country":"US",
    "sg:address":"2451 Roanoke St",
    "sg:city":"Christiansburg",
    "sg:classifiers":[
        {
            "category":"Retail",
            "subcategory":"Auto Rental",
            "type":"Services"
        }
    ],
    "sg:phone":"+1 540 382 5541",
    "sg:postcode":"24073",
    "sg:province":"VA",
    "sg:tags":[
        "repair",
        "re",
        "general",
        "equipment",
        "trailer",
        "utility"
    ],
    "wof:name":"U-Haul",
    "wof:placetype":"venue"
},
  "geometry": {"coordinates":[-80.359832,37.136691],"type":"Point"}
}