{
  "type": "Feature",
  "properties": {
    "addr:full":"6062 Indian River Rd Virginia Beach VA 23464",
    "addr:housenumber":"6062",
    "addr:postcode":"23464",
    "addr:street":"Indian River Rd",
    "iso:country":"US",
    "sg:address":"6062 Indian River Rd",
    "sg:city":"Virginia Beach",
    "sg:classifiers":[
        {
            "category":"Real Estate",
            "subcategory":"Real Estate Operator",
            "type":"Services"
        }
    ],
    "sg:phone":"+1 757 366 5222",
    "sg:postcode":"23464",
    "sg:province":"VA",
    "sg:tags":[
        "building",
        "nonresidential"
    ],
    "wof:name":"Atlas Properties Lcc",
    "wof:placetype":"venue"
},
  "geometry": {"coordinates":[-76.204267,36.811891],"type":"Point"}
}