{
  "type": "Feature",
  "properties": {
    "addr:full":"1423 W Main St Richmond VA 23220",
    "addr:housenumber":"1423",
    "addr:postcode":"23220",
    "addr:street":"W Main St",
    "iso:country":"US",
    "sg:address":"1423 W Main St",
    "sg:city":"Richmond",
    "sg:classifiers":[
        {
            "category":"Shopping",
            "subcategory":"Used Merchandise",
            "type":"Retail Goods"
        }
    ],
    "sg:phone":"+1 804 355 0254",
    "sg:postcode":"23220",
    "sg:province":"VA",
    "sg:tags":[
        "store"
    ],
    "wof:name":"Adams Antiques",
    "wof:placetype":"venue"
},
  "geometry": {"coordinates":[-77.459452,37.546847],"type":"Point"}
}