{
  "type": "Feature",
  "properties": {
    "iso:country":"US",
    "sg:address":"156 Shamokin Springs Trl",
    "sg:city":"Wintergreen",
    "sg:classifiers":[
        {
            "category":"Professional",
            "type":"Services"
        }
    ],
    "sg:phone":"+1 434 325 7503",
    "sg:postcode":"22958",
    "sg:province":"VA",
    "sg:tags":[
        "establishment"
    ],
    "wof:name":"Feldman & Feldman",
    "wof:placetype":"venue"
},
  "geometry": {"coordinates":[-78.935849,37.93106],"type":"Point"}
}