{
  "type": "Feature",
  "properties": {
    "iso:country":"US",
    "sg:address":"12153 Hooe Rd",
    "sg:city":"Bristow",
    "sg:classifiers":[
        {
            "category":"Retail",
            "subcategory":"Auto Repair",
            "type":"Services"
        }
    ],
    "sg:phone":"+1 703 369 3003",
    "sg:postcode":"20136",
    "sg:province":"VA",
    "sg:tags":[
        "department",
        "maintenance",
        "vehicle"
    ],
    "wof:name":"Fleet Management",
    "wof:placetype":"venue"
},
  "geometry": {"coordinates":[-77.515272,38.690234],"type":"Point"}
}