{
  "type": "Feature",
  "properties": {
    "addr:full":"2309 Haversham Close Virginia Beach VA 23454",
    "addr:housenumber":"2309",
    "addr:postcode":"23454",
    "addr:street":"Haversham Close",
    "iso:country":"US",
    "sg:address":"2309 Haversham Close",
    "sg:city":"Virginia Beach",
    "sg:classifiers":[
        {
            "category":"Health Services",
            "subcategory":"Doctor",
            "type":"Services"
        }
    ],
    "sg:phone":"+1 757 496 2784",
    "sg:postcode":"23454",
    "sg:province":"VA",
    "sg:tags":[
        "physician",
        "surgeon"
    ],
    "wof:name":"George R Payne MD",
    "wof:placetype":"venue"
},
  "geometry": {"coordinates":[-76.048985,36.89881],"type":"Point"}
}