{
  "type": "Feature",
  "properties": {
    "addr:full":"21755 Flora Springs Ter Ashburn VA 20147",
    "addr:housenumber":"21755",
    "addr:postcode":"20147",
    "addr:street":"Flora Springs Ter",
    "iso:country":"US",
    "sg:address":"21755 Flora Springs Ter",
    "sg:city":"Ashburn",
    "sg:classifiers":[
        {
            "category":"Shopping",
            "subcategory":"Catalog Store",
            "type":"Retail Goods"
        }
    ],
    "sg:phone":"+1 703 624 4925",
    "sg:postcode":"20147",
    "sg:province":"VA",
    "sg:tags":[
        "house",
        "mail"
    ],
    "wof:name":"Pepper Berry",
    "wof:placetype":"venue"
},
  "geometry": {"coordinates":[-77.4911,39.01425],"type":"Point"}
}