{
  "type": "Feature",
  "properties": {
    "addr:full":"4141 Duke St Alexandria VA 22304",
    "addr:housenumber":"4141",
    "addr:postcode":"22304",
    "addr:street":"Duke St",
    "iso:country":"US",
    "sg:address":"4141 Duke St",
    "sg:city":"Alexandria",
    "sg:classifiers":[
        {
            "category":"Health Services",
            "subcategory":"Doctor",
            "type":"Services"
        }
    ],
    "sg:phone":"+1 703 461 3556",
    "sg:postcode":"22304",
    "sg:province":"VA",
    "sg:tags":[
        "physician",
        "surgeon"
    ],
    "wof:name":"Mendez, Ramon E, Md - Washington Nephrology Assoc",
    "wof:placetype":"venue"
},
  "geometry": {"coordinates":[-77.103396,38.811459],"type":"Point"}
}