{
  "type": "Feature",
  "properties": {
    "iso:country":"US",
    "sg:address":"611 S Carlin Springs Rd",
    "sg:city":"Arlington",
    "sg:classifiers":[
        {
            "category":"Health Services",
            "subcategory":"Doctor",
            "type":"Services"
        }
    ],
    "sg:phone":"+1 703 671 1992",
    "sg:postcode":"22204",
    "sg:province":"VA",
    "wof:name":"Crossland Stanley G MD",
    "wof:placetype":"venue"
},
  "geometry": {"coordinates":[-77.12809799999999,38.860401],"type":"Point"}
}