{
  "type": "Feature",
  "properties": {
    "addr:full":"302 Gaines Ct SW Leesburg VA 20175",
    "addr:housenumber":"302",
    "addr:postcode":"20175",
    "addr:street":"Gaines Ct Sw",
    "iso:country":"US",
    "sg:address":"302 Gaines Ct SW",
    "sg:city":"Leesburg",
    "sg:classifiers":[
        {
            "category":"Professional",
            "subcategory":"Management & Consulting",
            "type":"Services"
        }
    ],
    "sg:phone":"+1 703 737 7847",
    "sg:postcode":"20175",
    "sg:province":"VA",
    "sg:tags":[
        "business"
    ],
    "wof:name":"LDM Consulting Services L L C",
    "wof:placetype":"venue"
},
  "geometry": {"coordinates":[-77.59565000000001,39.0863],"type":"Point"}
}