{
  "type": "Feature",
  "properties": {
    "iso:country":"US",
    "sg:address":"4900 Whitmell School Rd",
    "sg:city":"Dry Fork",
    "sg:classifiers":[
        {
            "category":"Home & Garden",
            "subcategory":"Mobile Homes",
            "type":"Retail Goods"
        }
    ],
    "sg:phone":"+1 434 724 1154",
    "sg:postcode":"24549",
    "sg:province":"VA",
    "wof:name":"Country Vlg Mobile Home Sales",
    "wof:placetype":"venue"
},
  "geometry": {"coordinates":[-79.51286399999999,36.676106],"type":"Point"}
}