{
  "type": "Feature",
  "properties": {
    "addr:full":"11160 S Lakes Dr Reston VA 20191",
    "addr:housenumber":"11160",
    "addr:postcode":"20191",
    "addr:street":"S Lakes Dr",
    "iso:country":"US",
    "sg:address":"11160 S Lakes Dr",
    "sg:city":"Reston",
    "sg:classifiers":[
        {
            "category":"Professional",
            "subcategory":"Advertising",
            "type":"Services"
        }
    ],
    "sg:phone":"+1 703 476 9200",
    "sg:postcode":"20191",
    "sg:province":"VA",
    "sg:tags":[
        "mailing",
        "shipping"
    ],
    "wof:name":"UPS Store",
    "wof:placetype":"venue"
},
  "geometry": {"coordinates":[-77.330196,38.9374],"type":"Point"}
}