{
  "type": "Feature",
  "properties": {
    "addr:full":"7 Waterford Ct Williamsburg VA 23188",
    "addr:housenumber":"7",
    "addr:postcode":"23188",
    "addr:street":"Waterford Ct",
    "iso:country":"US",
    "sg:address":"7 Waterford Ct",
    "sg:city":"Williamsburg",
    "sg:classifiers":[
        {
            "category":"Wholesale",
            "subcategory":"Non-durable Goods",
            "type":"Manufacturing & Wholesale Goods"
        }
    ],
    "sg:phone":"+1 757 565 0455",
    "sg:postcode":"23188",
    "sg:province":"VA",
    "sg:tags":[
        "advertising"
    ],
    "wof:name":"Creative Specialty Promotions",
    "wof:placetype":"venue"
},
  "geometry": {"coordinates":[-76.76197999999999,37.302104],"type":"Point"}
}