{
  "type": "Feature",
  "properties": {
    "iso:country":"US",
    "sg:address":"252 Little Bay Rd",
    "sg:city":"White Stone",
    "sg:classifiers":[
        {
            "category":"Building & Trades",
            "subcategory":"Electrical",
            "type":"Services"
        }
    ],
    "sg:phone":"+1 804 435 3936",
    "sg:postcode":"22578",
    "sg:province":"VA",
    "sg:tags":[
        "electric",
        "contractor"
    ],
    "wof:name":"Joseph B Elbourn & Son",
    "wof:placetype":"venue"
},
  "geometry": {"coordinates":[-76.380872,37.644041],"type":"Point"}
}