{
  "type": "Feature",
  "properties": {
    "iso:country":"US",
    "sg:address":"300 S Main St",
    "sg:city":"Blacksburg",
    "sg:classifiers":[
        {
            "category":"Government",
            "subcategory":"Office",
            "type":"Public Place"
        }
    ],
    "sg:phone":"+1 540 961 1119",
    "sg:postcode":"24060",
    "sg:province":"VA",
    "sg:tags":[
        "govt",
        "city"
    ],
    "wof:name":"City Utility Svc",
    "wof:placetype":"venue"
},
  "geometry": {"coordinates":[-80.41246099999999,37.227934],"type":"Point"}
}