{
  "type": "Feature",
  "properties": {
    "addr:full":"909 N McKinley Rd Arlington VA 22205",
    "addr:housenumber":"909",
    "addr:postcode":"22205",
    "addr:street":"N Mckinley Rd",
    "iso:country":"US",
    "sg:address":"909 N McKinley Rd",
    "sg:city":"Arlington",
    "sg:classifiers":[
        {
            "category":"Real Estate",
            "subcategory":"Real Estate Agent",
            "type":"Services"
        }
    ],
    "sg:phone":"+1 703 532 4065",
    "sg:postcode":"22205",
    "sg:province":"VA",
    "wof:name":"Choudary Chatha Realtor",
    "wof:placetype":"venue"
},
  "geometry": {"coordinates":[-77.14575499999999,38.87654],"type":"Point"}
}