{
  "type": "Feature",
  "properties": {
    "addr:full":"9556 Windsor Shade Dr Ashland VA 23005",
    "addr:housenumber":"9556",
    "addr:postcode":"23005",
    "addr:street":"Windsor Shade Dr",
    "iso:country":"US",
    "sg:address":"9556 Windsor Shade Dr",
    "sg:city":"Ashland",
    "sg:classifiers":[
        {
            "category":"Professional",
            "type":"Services"
        }
    ],
    "sg:phone":"+1 804 550 0311",
    "sg:postcode":"23005",
    "sg:province":"VA",
    "wof:name":"Eleanor Shumaker",
    "wof:placetype":"venue"
},
  "geometry": {"coordinates":[-77.43485800000001,37.693915],"type":"Point"}
}