{
  "type": "Feature",
  "properties": {
    "addr:full":"14324 Little Rocky Mountain Ct Centreville VA 20120",
    "addr:housenumber":"14324",
    "addr:postcode":"20120",
    "addr:street":"Little Rocky Mountain Ct",
    "iso:country":"US",
    "sg:address":"14324 Little Rocky Mountain Ct",
    "sg:city":"Centreville",
    "sg:classifiers":[
        {
            "category":"Building & Trades",
            "subcategory":"Construction",
            "type":"Services"
        }
    ],
    "sg:phone":"+1 703 830 2421",
    "sg:postcode":"20120",
    "sg:province":"VA",
    "sg:tags":[
        "contractor"
    ],
    "wof:name":"Zalokar Sheet Metal",
    "wof:placetype":"venue"
},
  "geometry": {"coordinates":[-77.44123399999999,38.844084],"type":"Point"}
}