{
  "type": "Feature",
  "properties": {
    "addr:full":"710 7th St Portsmouth VA 23704",
    "addr:housenumber":"710",
    "addr:postcode":"23704",
    "addr:street":"7Th St",
    "iso:country":"US",
    "sg:address":"710 7th St",
    "sg:city":"Portsmouth",
    "sg:classifiers":[
        {
            "category":"Freight",
            "type":"Transportation"
        }
    ],
    "sg:phone":"+1 757 397 1248",
    "sg:postcode":"23704",
    "sg:province":"VA",
    "sg:tags":[
        "storage",
        "interstate",
        "moving",
        "local"
    ],
    "wof:name":"Harrisons Moving & Storage Co",
    "wof:placetype":"venue"
},
  "geometry": {"coordinates":[-76.30215099999999,36.822475],"type":"Point"}
}