{
  "type": "Feature",
  "properties": {
    "addr:full":"228 N Edgewood St Arlington VA 22201",
    "addr:housenumber":"228",
    "addr:postcode":"22201",
    "addr:street":"N Edgewood St",
    "iso:country":"US",
    "sg:address":"228 N Edgewood St",
    "sg:city":"Arlington",
    "sg:classifiers":[
        {
            "category":"Professional",
            "subcategory":"Business Services",
            "type":"Services"
        }
    ],
    "sg:phone":"+1 703 528 5451",
    "sg:postcode":"22201",
    "sg:province":"VA",
    "wof:name":"Creative Design Solutions",
    "wof:placetype":"venue"
},
  "geometry": {"coordinates":[-77.090194,38.87838],"type":"Point"}
}