{
  "type": "Feature",
  "properties": {
    "addr:full":"5150 State Park Rd Dublin VA 24084",
    "addr:housenumber":"5150",
    "addr:postcode":"24084",
    "addr:street":"State Park Rd",
    "iso:country":"US",
    "sg:address":"5150 State Park Rd",
    "sg:city":"Dublin",
    "sg:classifiers":[
        {
            "category":"Autos & Motor Vehicles",
            "subcategory":"Fuel & Gas Station",
            "type":"Retail Goods"
        }
    ],
    "sg:phone":"+1 540 674 4552",
    "sg:postcode":"24084",
    "sg:province":"VA",
    "sg:tags":[
        "station",
        "gasoline"
    ],
    "wof:name":"Lancer Travel Plaza",
    "wof:placetype":"venue"
},
  "geometry": {"coordinates":[-80.650741,37.086893],"type":"Point"}
}