{
  "type": "Feature",
  "properties": {
    "addr:full":"24414 Musselwhite Dr Waverly VA 23891",
    "addr:postcode":"24414;23891",
    "addr:street":"Musselwhite Dr",
    "iso:country":"US",
    "sg:address":"24414 Musselwhite Dr",
    "sg:city":"Waverly",
    "sg:classifiers":[
        {
            "category":"Health Services",
            "subcategory":"Clinic",
            "type":"Services"
        }
    ],
    "sg:phone":"+1 804 834 3671",
    "sg:postcode":"23891",
    "sg:province":"VA",
    "wof:name":"Prison Health Svc",
    "wof:placetype":"venue"
},
  "geometry": {"coordinates":[-77.220418,37.03998],"type":"Point"}
}