{
  "type": "Feature",
  "properties": {
    "addr:full":"7700 Little River Tpke Annandale VA 22003",
    "addr:housenumber":"7700",
    "addr:postcode":"22003",
    "addr:street":"Little River Tpke",
    "iso:country":"US",
    "sg:address":"7700 Little River Tpke",
    "sg:city":"Annandale",
    "sg:classifiers":[
        {
            "category":"Banks & Credit Unions",
            "subcategory":"Bank",
            "type":"Services"
        }
    ],
    "sg:phone":"+1 703 642 1001",
    "sg:postcode":"22003",
    "sg:province":"VA",
    "sg:tags":[
        "loan",
        "real estate"
    ],
    "wof:name":"American Trust Mortgage",
    "wof:placetype":"venue"
},
  "geometry": {"coordinates":[-77.214642,38.833487],"type":"Point"}
}