{
  "type": "Feature",
  "properties": {
    "addr:full":"2001 S Main St Blacksburg VA 24060",
    "addr:housenumber":"2001",
    "addr:postcode":"24060",
    "addr:street":"S Main St",
    "iso:country":"US",
    "sg:address":"2001 S Main St",
    "sg:city":"Blacksburg",
    "sg:classifiers":[
        {
            "category":"Wholesale",
            "subcategory":"Non-durable Goods",
            "type":"Manufacturing & Wholesale Goods"
        }
    ],
    "sg:phone":"+1 540 953 7030",
    "sg:postcode":"24060",
    "sg:province":"VA",
    "wof:name":"Energy Savers VA Inc",
    "wof:placetype":"venue"
},
  "geometry": {"coordinates":[-80.398737,37.205797],"type":"Point"}
}