{
  "type": "Feature",
  "properties": {
    "addr:full":"11138 Marsh Rd Bealeton VA 22712",
    "addr:housenumber":"11138",
    "addr:postcode":"22712",
    "addr:street":"Marsh Rd",
    "iso:country":"US",
    "sg:address":"11138 Marsh Rd",
    "sg:city":"Bealeton",
    "sg:classifiers":[
        {
            "category":"Education",
            "subcategory":"School",
            "type":"Public Place"
        }
    ],
    "sg:phone":"+1 540 439 3207",
    "sg:postcode":"22712",
    "sg:province":"VA",
    "sg:tags":[
        "high",
        "middle",
        "elementary"
    ],
    "sg:website":"www.fauquiercounty.gov",
    "wof:name":"Fauquier County of",
    "wof:placetype":"venue"
},
  "geometry": {"coordinates":[-77.765331,38.57598],"type":"Point"}
}