{
  "type": "Feature",
  "properties": {
    "addr:full":"316 Brook Park Pl Forest VA 24551",
    "addr:housenumber":"316",
    "addr:postcode":"24551",
    "addr:street":"Brook Park Pl",
    "iso:country":"US",
    "sg:address":"316 Brook Park Pl",
    "sg:city":"Forest",
    "sg:classifiers":[
        {
            "category":"Building & Trades",
            "subcategory":"Electrical",
            "type":"Services"
        }
    ],
    "sg:phone":"+1 434 385 1997",
    "sg:postcode":"24551",
    "sg:province":"VA",
    "sg:tags":[
        "electrical",
        "contractor"
    ],
    "wof:name":"T C Electric",
    "wof:placetype":"venue"
},
  "geometry": {"coordinates":[-79.250165,37.369033],"type":"Point"}
}