{
  "type": "Feature",
  "properties": {
    "addr:full":"4301 Old River Trl Powhatan VA 23139",
    "addr:housenumber":"4301",
    "addr:postcode":"23139",
    "addr:street":"Old River Trl",
    "iso:country":"US",
    "sg:address":"4301 Old River Trl",
    "sg:city":"Powhatan",
    "sg:classifiers":[
        {
            "category":"Wholesale",
            "subcategory":"Machinery & Supplies",
            "type":"Manufacturing & Wholesale Goods"
        },
        {
            "category":"Food & Beverages",
            "subcategory":"Dairy",
            "type":"Retail Goods"
        }
    ],
    "sg:phone":"+1 804 598 4686",
    "sg:postcode":"23139",
    "sg:province":"VA",
    "sg:tags":[
        "equipment"
    ],
    "wof:name":"Moyer Farm & Dairy Supply Inc",
    "wof:placetype":"venue"
},
  "geometry": {"coordinates":[-77.943398,37.660818],"type":"Point"}
}