{
  "type": "Feature",
  "properties": {
    "addr:full":"Rosslyn Metro Center Mall 1700 N Moore St Level 2, Ste 235 Arlington VA 22209",
    "addr:housenumber":"1700;2 ste 235",
    "addr:postcode":"22209",
    "addr:street":"N Moore St Level",
    "iso:country":"US",
    "sg:address":"Rosslyn Metro Center Mall 1700 N Moore St Level 2, Ste 235",
    "sg:city":"Arlington",
    "sg:classifiers":[
        {
            "category":"Local Transit",
            "type":"Transportation"
        }
    ],
    "sg:phone":"+1 703 525 1995",
    "sg:postcode":"22209",
    "sg:province":"VA",
    "sg:tags":[
        "public"
    ],
    "sg:website":"www.commuterpage.com/stores.htm",
    "wof:name":"Commuter Store",
    "wof:placetype":"venue"
},
  "geometry": {"coordinates":[-77.07171,38.895509],"type":"Point"}
}