{
  "type": "Feature",
  "properties": {
    "addr:full":"15540 Lee Hwy Bristol VA 24202",
    "addr:housenumber":"15540",
    "addr:postcode":"24202",
    "addr:street":"Lee Hwy",
    "iso:country":"US",
    "sg:address":"15540 Lee Hwy",
    "sg:city":"Bristol",
    "sg:classifiers":[
        {
            "category":"Organizations",
            "subcategory":"Religious Organization",
            "type":"Services"
        }
    ],
    "sg:phone":"+1 276 628 9472",
    "sg:postcode":"24202",
    "sg:province":"VA",
    "wof:name":"Grace Chapel",
    "wof:placetype":"venue"
},
  "geometry": {"coordinates":[-82.07996300000001,36.656199],"type":"Point"}
}