{
  "type": "Feature",
  "properties": {
    "iso:country":"US",
    "sg:address":"325 Burr Oak Rd",
    "sg:city":"Lynchburg",
    "sg:classifiers":[
        {
            "category":"Building & Trades",
            "subcategory":"Construction",
            "type":"Services"
        }
    ],
    "sg:phone":"+1 434 525 5536",
    "sg:postcode":"24502",
    "sg:province":"VA",
    "sg:tags":[
        "house"
    ],
    "wof:name":"Snipes Construction Inc",
    "wof:placetype":"venue"
},
  "geometry": {"coordinates":[-79.26864999999999,37.29409],"type":"Point"}
}