{
  "type": "Feature",
  "properties": {
    "addr:full":"123 Three Cedars Ln Fredericksburg VA 22407",
    "addr:housenumber":"123",
    "addr:postcode":"22407",
    "addr:street":"Three Cedars Ln",
    "iso:country":"US",
    "sg:address":"123 Three Cedars Ln",
    "sg:city":"Fredericksburg",
    "sg:classifiers":[
        {
            "category":"Education",
            "subcategory":"Dance Studio",
            "type":"Public Place"
        }
    ],
    "sg:phone":"+1 540 891 8128",
    "sg:postcode":"22407",
    "sg:province":"VA",
    "sg:tags":[
        "business"
    ],
    "wof:name":"Wilbert Wormley Jr",
    "wof:placetype":"venue"
},
  "geometry": {"coordinates":[-77.53673999999999,38.229659],"type":"Point"}
}