{
  "type": "Feature",
  "properties": {
    "addr:full":"8402 Gravel Hill Rd Catawba VA 24070",
    "addr:housenumber":"8402",
    "addr:postcode":"24070",
    "addr:street":"Gravel Hill Rd",
    "iso:country":"US",
    "sg:address":"8402 Gravel Hill Rd",
    "sg:city":"Catawba",
    "sg:classifiers":[
        {
            "category":"Health Services",
            "subcategory":"Doctor",
            "type":"Services"
        }
    ],
    "sg:phone":"+1 540 384 6041",
    "sg:postcode":"24070",
    "sg:province":"VA",
    "sg:tags":[
        "physician",
        "surgeon"
    ],
    "wof:name":"Georges Julie Clnc",
    "wof:placetype":"venue"
},
  "geometry": {"coordinates":[-80.255376,37.330511],"type":"Point"}
}