{
  "type": "Feature",
  "properties": {
    "addr:full":"1912 Opitz Blvd Woodbridge VA 22191",
    "addr:housenumber":"1912",
    "addr:postcode":"22191",
    "addr:street":"Opitz Blvd",
    "iso:country":"US",
    "sg:address":"1912 Opitz Blvd",
    "sg:city":"Woodbridge",
    "sg:classifiers":[
        {
            "category":"Health Services",
            "subcategory":"Doctor",
            "type":"Services"
        }
    ],
    "sg:phone":"+1 703 492 6726",
    "sg:postcode":"22191",
    "sg:province":"VA",
    "sg:tags":[
        "physician",
        "surgeon"
    ],
    "wof:name":"Sanjeev Kohli MD",
    "wof:placetype":"venue"
},
  "geometry": {"coordinates":[-77.273955,38.634728],"type":"Point"}
}