{
  "type": "Feature",
  "properties": {
    "iso:country":"US",
    "sg:address":"1595 Spring Hill Rd",
    "sg:city":"Vienna",
    "sg:classifiers":[
        {
            "category":"Manufacturing",
            "subcategory":"Tools & Machinery",
            "type":"Manufacturing & Wholesale Goods"
        }
    ],
    "sg:phone":"+1 703 245 4544",
    "sg:postcode":"22182",
    "sg:province":"VA",
    "sg:tags":[
        "manufacture",
        "transfer",
        "product",
        "asynchronous",
        "mode"
    ],
    "wof:name":"Marconi Communications Inc",
    "wof:placetype":"venue"
},
  "geometry": {"coordinates":[-77.24470599999999,38.927041],"type":"Point"}
}