{
  "type": "Feature",
  "properties": {
    "addr:full":"1330 Roanoke Rd Daleville VA 24083",
    "addr:housenumber":"1330",
    "addr:postcode":"24083",
    "addr:street":"Roanoke Rd",
    "iso:country":"US",
    "sg:address":"1330 Roanoke Rd",
    "sg:city":"Daleville",
    "sg:classifiers":[
        {
            "category":"Professional",
            "subcategory":"Engineering",
            "type":"Services"
        }
    ],
    "sg:phone":"+1 540 966 4283",
    "sg:postcode":"24083",
    "sg:province":"VA",
    "sg:tags":[
        "engineer"
    ],
    "wof:name":"JPR Engineering Inc",
    "wof:placetype":"venue"
},
  "geometry": {"coordinates":[-79.912916,37.403879],"type":"Point"}
}