{
  "type": "Feature",
  "properties": {
    "addr:full":"5539 N Lee Hwy Arlington VA 22207",
    "addr:housenumber":"5539",
    "addr:postcode":"22207",
    "addr:street":"N Lee Hwy",
    "iso:country":"US",
    "sg:address":"5539 N Lee Hwy",
    "sg:city":"Arlington",
    "sg:classifiers":[
        {
            "category":"Building & Trades",
            "subcategory":"Construction",
            "type":"Services"
        }
    ],
    "sg:phone":"+1 703 534 7730",
    "sg:postcode":"22207",
    "sg:province":"VA",
    "sg:tags":[
        "general",
        "contractor"
    ],
    "wof:name":"Potomac Custom Builders",
    "wof:placetype":"venue"
},
  "geometry": {"coordinates":[-77.139957,38.89591],"type":"Point"}
}