{
  "type": "Feature",
  "properties": {
    "iso:country":"US",
    "sg:address":"1118 Snider St",
    "sg:city":"Marion",
    "sg:classifiers":[
        {
            "category":"Professional",
            "type":"Services"
        }
    ],
    "sg:phone":"+1 276 783 2844",
    "sg:postcode":"24354",
    "sg:province":"VA",
    "sg:tags":[
        "establishment"
    ],
    "wof:name":"NHLI",
    "wof:placetype":"venue"
},
  "geometry": {"coordinates":[-81.506579,36.851074],"type":"Point"}
}