{
  "type": "Feature",
  "properties": {
    "iso:country":"US",
    "sg:address":"2908 W Cary St",
    "sg:city":"Richmond",
    "sg:classifiers":[
        {
            "category":"Cinema",
            "subcategory":"Movie Theater",
            "type":"Entertainment"
        }
    ],
    "sg:phone":"+1 804 353 9911",
    "sg:postcode":"23221",
    "sg:province":"VA",
    "wof:name":"Byrd Theatre",
    "wof:placetype":"venue"
},
  "geometry": {"coordinates":[-77.478706,37.552527],"type":"Point"}
}