{
  "type": "Feature",
  "properties": {
    "addr:full":"616 24th St S Arlington VA 22202",
    "addr:housenumber":"616",
    "addr:postcode":"22202",
    "addr:street":"24Th St S",
    "iso:country":"US",
    "sg:address":"616 24th St S",
    "sg:city":"Arlington",
    "sg:classifiers":[
        {
            "category":"Professional",
            "subcategory":"Art Services",
            "type":"Services"
        }
    ],
    "sg:phone":"+1 703 838 8584",
    "sg:postcode":"22202",
    "sg:province":"VA",
    "sg:tags":[
        "consultant",
        "designer",
        "lighting"
    ],
    "sg:website":"http://www.dcaproductions.com",
    "wof:name":"Dca Productions",
    "wof:placetype":"venue"
},
  "geometry": {"coordinates":[-77.055626,38.852342],"type":"Point"}
}