{
  "type": "Feature",
  "properties": {
    "addr:full":"474 Clarke Ln Heathsville VA 22473",
    "addr:housenumber":"474",
    "addr:postcode":"22473",
    "addr:street":"Clarke Ln",
    "iso:country":"US",
    "sg:address":"474 Clarke Ln",
    "sg:city":"Heathsville",
    "sg:classifiers":[
        {
            "category":"Building & Trades",
            "subcategory":"Plumbing",
            "type":"Services"
        }
    ],
    "sg:phone":"+1 804 580 4103",
    "sg:postcode":"22473",
    "sg:province":"VA",
    "sg:tags":[
        "conditioning",
        "air",
        "system",
        "contractor"
    ],
    "wof:name":"T N Sherwood Co",
    "wof:placetype":"venue"
},
  "geometry": {"coordinates":[-76.434038,37.968716],"type":"Point"}
}