{
  "type": "Feature",
  "properties": {
    "addr:full":"1201 Hollins Rd Richmond VA 23229",
    "addr:housenumber":"1201",
    "addr:postcode":"23229",
    "addr:street":"Hollins Rd",
    "iso:country":"US",
    "sg:address":"1201 Hollins Rd",
    "sg:city":"Richmond",
    "sg:classifiers":[
        {
            "category":"Wholesale",
            "subcategory":"Machinery & Supplies",
            "type":"Manufacturing & Wholesale Goods"
        }
    ],
    "sg:phone":"+1 804 343 1900",
    "sg:postcode":"23229",
    "sg:province":"VA",
    "sg:tags":[
        "equipment"
    ],
    "wof:name":"Chesapeake Contracting Group",
    "wof:placetype":"venue"
},
  "geometry": {"coordinates":[-77.540004,37.595583],"type":"Point"}
}