{
  "type": "Feature",
  "properties": {
    "addr:full":"11120 Lake Jackson Dr Manassas VA 20111",
    "addr:housenumber":"11120",
    "addr:postcode":"20111",
    "addr:street":"Lake Jackson Dr",
    "iso:country":"US",
    "sg:address":"11120 Lake Jackson Dr",
    "sg:city":"Manassas",
    "sg:classifiers":[
        {
            "category":"Personal",
            "type":"Services"
        }
    ],
    "sg:phone":"+1 703 855 0410",
    "sg:postcode":"20111",
    "sg:province":"VA",
    "wof:name":"A Sense of Touch Inc",
    "wof:placetype":"venue"
},
  "geometry": {"coordinates":[-77.445581,38.710869],"type":"Point"}
}