{
  "type": "Feature",
  "properties": {
    "iso:country":"US",
    "sg:address":"46 S Glebe Rd",
    "sg:city":"Arlington",
    "sg:classifiers":[
        {
            "category":"Health Services",
            "subcategory":"Health Practitioner",
            "type":"Services"
        },
        {
            "category":"Health Services",
            "subcategory":"Chiropractor",
            "type":"Services"
        }
    ],
    "sg:phone":"+1 703 521 0644",
    "sg:postcode":"22204",
    "sg:province":"VA",
    "sg:tags":[
        "acupuncture",
        "therapy",
        "physical"
    ],
    "sg:website":"www.advhealthctr.com",
    "wof:name":"Dr. Louis J Ziegler, DC",
    "wof:placetype":"venue"
},
  "geometry": {"coordinates":[-77.0998,38.869701],"type":"Point"}
}