{
  "type": "Feature",
  "properties": {
    "addr:full":"16515 Childress Hollow Rd Abingdon VA 24210",
    "addr:housenumber":"16515",
    "addr:postcode":"24210",
    "addr:street":"Childress Hollow Rd",
    "iso:country":"US",
    "sg:address":"16515 Childress Hollow Rd",
    "sg:city":"Abingdon",
    "sg:classifiers":[
        {
            "category":"Farming",
            "subcategory":"Livestock Farm",
            "type":"Manufacturing & Wholesale Goods"
        }
    ],
    "sg:phone":"+1 276 628 8389",
    "sg:postcode":"24210",
    "sg:province":"VA",
    "sg:tags":[
        "beef",
        "feedlot",
        "cattle"
    ],
    "wof:name":"Edith Long",
    "wof:placetype":"venue"
},
  "geometry": {"coordinates":[-82.083716,36.707929],"type":"Point"}
}