{
  "type": "Feature",
  "properties": {
    "addr:full":"2228 Jadwyn Rd Maurertown VA 22644",
    "addr:housenumber":"2228",
    "addr:postcode":"22644",
    "addr:street":"Jadwyn Rd",
    "iso:country":"US",
    "sg:address":"2228 Jadwyn Rd",
    "sg:city":"Maurertown",
    "sg:classifiers":[
        {
            "category":"Building & Trades",
            "subcategory":"Construction",
            "type":"Services"
        }
    ],
    "sg:phone":"+1 540 459 4455",
    "sg:postcode":"22644",
    "sg:province":"VA",
    "sg:tags":[
        "house",
        "nonresidential"
    ],
    "wof:name":"Alta Construction Services",
    "wof:placetype":"venue"
},
  "geometry": {"coordinates":[-78.514385,38.928256],"type":"Point"}
}