{
  "type": "Feature",
  "properties": {
    "iso:country":"US",
    "sg:address":"6401 Backlick Rd",
    "sg:city":"Springfield",
    "sg:classifiers":[
        {
            "category":"Utilities",
            "subcategory":"Telephone",
            "type":"Services"
        },
        {
            "category":"Shopping",
            "subcategory":"Mobile Phones",
            "type":"Retail Goods"
        },
        {
            "category":"Manufacturing",
            "subcategory":"Electronics",
            "type":"Manufacturing & Wholesale Goods"
        },
        {
            "category":"Shopping",
            "subcategory":"Computers & Home Electronics",
            "type":"Retail Goods"
        },
        {
            "category":"Communications",
            "type":"Services"
        }
    ],
    "sg:phone":"+1 703 451 8575",
    "sg:postcode":"22150",
    "sg:province":"VA",
    "sg:tags":[
        "sound",
        "television",
        "theater",
        "supply",
        "system",
        "equipment",
        "radio",
        "cellular",
        "telecommunications-equipment",
        "consumer",
        "store"
    ],
    "sg:website":"http://www.radioshack.com",
    "wof:name":"RadioShack",
    "wof:placetype":"venue"
},
  "geometry": {"coordinates":[-77.18506600000001,38.78088],"type":"Point"}
}