{
  "type": "Feature",
  "properties": {
    "addr:full":"328 Main St Newport News VA 23601",
    "addr:housenumber":"328",
    "addr:postcode":"23601",
    "addr:street":"Main St",
    "iso:country":"US",
    "sg:address":"328 Main St",
    "sg:city":"Newport News",
    "sg:classifiers":[
        {
            "category":"Health Services",
            "subcategory":"Doctor",
            "type":"Services"
        }
    ],
    "sg:phone":"+1 757 594 3511",
    "sg:postcode":"23601",
    "sg:province":"VA",
    "sg:tags":[
        "medical"
    ],
    "wof:name":"Paul J Meyers",
    "wof:placetype":"venue"
},
  "geometry": {"coordinates":[-76.45566599999999,37.036611],"type":"Point"}
}