{
  "type": "Feature",
  "properties": {
    "addr:full":"848 Thompson Dr Abingdon VA 24210",
    "addr:housenumber":"848",
    "addr:postcode":"24210",
    "addr:street":"Thompson Dr",
    "iso:country":"US",
    "sg:address":"848 Thompson Dr",
    "sg:city":"Abingdon",
    "sg:classifiers":[
        {
            "category":"Education",
            "subcategory":"Vocational School",
            "type":"Public Place"
        }
    ],
    "sg:phone":"+1 276 676 1948",
    "sg:postcode":"24210",
    "sg:province":"VA",
    "sg:tags":[
        "technical",
        "trade"
    ],
    "sg:website":"www.wcskillcenter.org",
    "wof:name":"Washington Co Adult Skill Ctr",
    "wof:placetype":"venue"
},
  "geometry": {"coordinates":[-81.951184,36.719679],"type":"Point"}
}