{
  "type": "Feature",
  "properties": {
    "addr:full":"1700 Todds Ln Hampton VA 23666",
    "addr:housenumber":"1700",
    "addr:postcode":"23666",
    "addr:street":"Todds Ln",
    "iso:country":"US",
    "sg:address":"1700 Todds Ln",
    "sg:city":"Hampton",
    "sg:classifiers":[
        {
            "category":"Food & Beverages",
            "subcategory":"Groceries & Convenience Stores",
            "type":"Retail Goods"
        }
    ],
    "sg:phone":"+1 757 826 7608",
    "sg:postcode":"23666",
    "sg:province":"VA",
    "sg:tags":[
        "station",
        "gas"
    ],
    "wof:name":"Miller Mart 9",
    "wof:placetype":"venue"
},
  "geometry": {"coordinates":[-76.40928099999999,37.039949],"type":"Point"}
}