{
  "type": "Feature",
  "properties": {
    "addr:full":"101 Elm Ave SE Roanoke VA 24013",
    "addr:housenumber":"101",
    "addr:postcode":"24013",
    "addr:street":"Elm Ave Se",
    "iso:country":"US",
    "sg:address":"101 Elm Ave SE",
    "sg:city":"Roanoke",
    "sg:classifiers":[
        {
            "category":"Health Services",
            "subcategory":"Doctor",
            "type":"Services"
        }
    ],
    "sg:phone":"+1 540 890 0400",
    "sg:postcode":"24013",
    "sg:province":"VA",
    "sg:tags":[
        "medical"
    ],
    "wof:name":"William P Smales MD",
    "wof:placetype":"venue"
},
  "geometry": {"coordinates":[-79.93880299999999,37.266815],"type":"Point"}
}