{
  "type": "Feature",
  "properties": {
    "iso:country":"US",
    "sg:address":"5443 Sheffield Ct",
    "sg:city":"Alexandria",
    "sg:phone":"+1 703 820 0501",
    "sg:postcode":"22311",
    "sg:province":"VA",
    "wof:name":"Home Cooking",
    "wof:placetype":"venue"
},
  "geometry": {"coordinates":[-77.125968,38.826786],"type":"Point"}
}