{
  "type": "Feature",
  "properties": {
    "addr:full":"1411 Lake Forest Dr Portsmouth VA 23701",
    "addr:housenumber":"1411",
    "addr:postcode":"23701",
    "addr:street":"Lake Forest Dr",
    "iso:country":"US",
    "sg:address":"1411 Lake Forest Dr",
    "sg:city":"Portsmouth",
    "sg:classifiers":[
        {
            "category":"Utilities",
            "subcategory":"Refuse",
            "type":"Services"
        }
    ],
    "sg:phone":"+1 757 465 2567",
    "sg:postcode":"23701",
    "sg:province":"VA",
    "sg:tags":[
        "system"
    ],
    "wof:name":"S & M Hauling",
    "wof:placetype":"venue"
},
  "geometry": {"coordinates":[-76.376789,36.795648],"type":"Point"}
}