{
  "type": "Feature",
  "properties": {
    "addr:full":"10826 Warwick Blvd Newport News VA 23601",
    "addr:housenumber":"10826",
    "addr:postcode":"23601",
    "addr:street":"Warwick Blvd",
    "iso:country":"US",
    "sg:address":"10826 Warwick Blvd",
    "sg:city":"Newport News",
    "sg:classifiers":[
        {
            "category":"Personal",
            "subcategory":"Beauty Salon",
            "type":"Services"
        }
    ],
    "sg:phone":"+1 757 595 2887",
    "sg:postcode":"23601",
    "sg:province":"VA",
    "sg:tags":[
        "shop"
    ],
    "wof:name":"Village Stylist",
    "wof:placetype":"venue"
},
  "geometry": {"coordinates":[-76.468211,37.039135],"type":"Point"}
}