{
  "type": "Feature",
  "properties": {
    "iso:country":"US",
    "sg:address":"1103 Ivy Pl",
    "sg:city":"Forest",
    "sg:classifiers":[
        {
            "category":"Insurance",
            "subcategory":"Insurance Agent",
            "type":"Services"
        }
    ],
    "sg:phone":"+1 434 832 7090",
    "sg:postcode":"24551",
    "sg:province":"VA",
    "wof:name":"Investors Financial Group",
    "wof:placetype":"venue"
},
  "geometry": {"coordinates":[-79.32696199999999,37.397293],"type":"Point"}
}