{
  "type": "Feature",
  "properties": {
    "addr:full":"15121 Farm Creek Dr Woodbridge VA 22191",
    "addr:housenumber":"15121",
    "addr:postcode":"22191",
    "addr:street":"Farm Creek Dr",
    "iso:country":"US",
    "sg:address":"15121 Farm Creek Dr",
    "sg:city":"Woodbridge",
    "sg:classifiers":[
        {
            "category":"Freight",
            "type":"Transportation"
        }
    ],
    "sg:phone":"+1 703 491 1004",
    "sg:postcode":"22191",
    "sg:province":"VA",
    "sg:tags":[
        "mover"
    ],
    "wof:name":"Bekins Moving & Storage",
    "wof:placetype":"venue"
},
  "geometry": {"coordinates":[-77.25447699999999,38.618841],"type":"Point"}
}