{
  "type": "Feature",
  "properties": {
    "addr:full":"1202 Salem Ave SW Roanoke VA 24016",
    "addr:housenumber":"1202",
    "addr:postcode":"24016",
    "addr:street":"Salem Ave Sw",
    "iso:country":"US",
    "sg:address":"1202 Salem Ave SW",
    "sg:city":"Roanoke",
    "sg:classifiers":[
        {
            "category":"Retail",
            "subcategory":"Car Wash",
            "type":"Services"
        }
    ],
    "sg:phone":"+1 540 342 7771",
    "sg:postcode":"24016",
    "sg:province":"VA",
    "sg:tags":[
        "polishing",
        "washing"
    ],
    "wof:name":"Howard's Detailing & Car Care",
    "wof:placetype":"venue"
},
  "geometry": {"coordinates":[-79.962125,37.274014],"type":"Point"}
}