{
  "type": "Feature",
  "properties": {
    "addr:full":"504 Lee Ct Sterling VA 20164",
    "addr:housenumber":"504",
    "addr:postcode":"20164",
    "addr:street":"Lee Ct",
    "iso:country":"US",
    "sg:address":"504 Lee Ct",
    "sg:city":"Sterling",
    "sg:classifiers":[
        {
            "category":"Building & Trades",
            "subcategory":"Construction",
            "type":"Services"
        }
    ],
    "sg:phone":"+1 703 266 2752",
    "sg:postcode":"20164",
    "sg:province":"VA",
    "sg:tags":[
        "general",
        "contractor"
    ],
    "wof:name":"Katchmark Construction",
    "wof:placetype":"venue"
},
  "geometry": {"coordinates":[-77.394801,38.99409],"type":"Point"}
}