{
  "type": "Feature",
  "properties": {
    "addr:full":"961 Acorn Dr Harrisonburg VA 22802",
    "addr:housenumber":"961",
    "addr:postcode":"22802",
    "addr:street":"Acorn Dr",
    "iso:country":"US",
    "sg:address":"961 Acorn Dr",
    "sg:city":"Harrisonburg",
    "sg:classifiers":[
        {
            "category":"Utilities",
            "subcategory":"Telephone",
            "type":"Services"
        }
    ],
    "sg:phone":"+1 540 437 4200",
    "sg:postcode":"22802",
    "sg:province":"VA",
    "sg:tags":[
        "tv",
        "internet",
        "cable",
        "provider"
    ],
    "wof:name":"NTC Communication LLC",
    "wof:placetype":"venue"
},
  "geometry": {"coordinates":[-78.869024,38.475791],"type":"Point"}
}