{
  "type": "Feature",
  "properties": {
    "addr:full":"491 Carlisle Dr Herndon VA 20170",
    "addr:housenumber":"491",
    "addr:postcode":"20170",
    "addr:street":"Carlisle Dr",
    "iso:country":"US",
    "sg:address":"491 Carlisle Dr",
    "sg:city":"Herndon",
    "sg:classifiers":[
        {
            "category":"Insurance",
            "subcategory":"Insurance Agent",
            "type":"Services"
        }
    ],
    "sg:phone":"+1 703 478 9703",
    "sg:postcode":"20170",
    "sg:province":"VA",
    "wof:name":"New York Life Insurance Co",
    "wof:placetype":"venue"
},
  "geometry": {"coordinates":[-77.36909799999999,38.965833],"type":"Point"}
}