{
  "type": "Feature",
  "properties": {
    "iso:country":"US",
    "sg:address":"5729 Mill Creek Rd",
    "sg:city":"Luray",
    "sg:classifiers":[
        {
            "category":"Building & Trades",
            "subcategory":"Landscaping Services",
            "type":"Services"
        }
    ],
    "sg:phone":"+1 540 778 4577",
    "sg:postcode":"22835",
    "sg:province":"VA",
    "sg:tags":[
        "lawn",
        "maintenance",
        "grounds"
    ],
    "wof:name":"Professional Edge",
    "wof:placetype":"venue"
},
  "geometry": {"coordinates":[-78.50451200000001,38.613787],"type":"Point"}
}