{
  "type": "Feature",
  "properties": {
    "iso:country":"US",
    "sg:address":"1552 Potomac Greens Dr",
    "sg:city":"Alexandria",
    "sg:classifiers":[
        {
            "category":"Shopping",
            "subcategory":"Clothing, Apparel, & Fashions",
            "type":"Retail Goods"
        }
    ],
    "sg:phone":"+1 703 706 9009",
    "sg:postcode":"22314",
    "sg:province":"VA",
    "sg:tags":[
        "children's",
        "clothing"
    ],
    "wof:name":"Tutto Bambini",
    "wof:placetype":"venue"
},
  "geometry": {"coordinates":[-77.04704599999999,38.82366],"type":"Point"}
}