{
  "type": "Feature",
  "properties": {
    "addr:full":"9500 Three Chopt Rd Richmond VA 23229",
    "addr:housenumber":"9500",
    "addr:postcode":"23229",
    "addr:street":"Three Chopt Rd",
    "iso:country":"US",
    "sg:address":"9500 Three Chopt Rd",
    "sg:city":"Richmond",
    "sg:classifiers":[
        {
            "category":"Organizations",
            "subcategory":"Religious Organization",
            "type":"Services"
        }
    ],
    "sg:phone":"+1 804 346 4673",
    "sg:postcode":"23229",
    "sg:province":"VA",
    "wof:name":"Hermitage Road Church Christ",
    "wof:placetype":"venue"
},
  "geometry": {"coordinates":[-77.570409,37.620004],"type":"Point"}
}