{
  "type": "Feature",
  "properties": {
    "addr:full":"45 Pine Rd Langley Afb VA 23665",
    "addr:housenumber":"45",
    "addr:postcode":"23665",
    "addr:street":"Pine Rd",
    "iso:country":"US",
    "sg:address":"45 Pine Rd",
    "sg:city":"Langley Afb",
    "sg:classifiers":[
        {
            "category":"Health Services",
            "subcategory":"Doctor",
            "type":"Services"
        }
    ],
    "sg:phone":"+1 757 764 6840",
    "sg:postcode":"23665",
    "sg:province":"VA",
    "sg:tags":[
        "physician",
        "surgeon"
    ],
    "wof:name":"Nikolche Naumovski MD",
    "wof:placetype":"venue"
},
  "geometry": {"coordinates":[-76.355867,37.074263],"type":"Point"}
}