{
  "type": "Feature",
  "properties": {
    "iso:country":"US",
    "sg:address":"10411 Hall Industrial Dr",
    "sg:city":"Fredericksburg",
    "sg:classifiers":[
        {
            "category":"Bus Charters",
            "type":"Transportation"
        }
    ],
    "sg:phone":"+1 540 898 6959",
    "sg:postcode":"22408",
    "sg:province":"VA",
    "sg:tags":[
        "rental"
    ],
    "wof:name":"Martz Group",
    "wof:placetype":"venue"
},
  "geometry": {"coordinates":[-77.49989600000001,38.194697],"type":"Point"}
}