{
  "type": "Feature",
  "properties": {
    "addr:full":"43838 Kittiwake Dr Leesburg VA 20176",
    "addr:postcode":"43838;20176",
    "addr:street":"Kittiwake Dr",
    "iso:country":"US",
    "sg:address":"43838 Kittiwake Dr",
    "sg:city":"Leesburg",
    "sg:classifiers":[
        {
            "category":"Professional",
            "type":"Services"
        }
    ],
    "sg:phone":"+1 571 333 9735",
    "sg:postcode":"20176",
    "sg:province":"VA",
    "sg:tags":[
        "establishment"
    ],
    "wof:name":"Ravi & Ravi",
    "wof:placetype":"venue"
},
  "geometry": {"coordinates":[-77.483307,39.083346],"type":"Point"}
}