{
  "type": "Feature",
  "properties": {
    "addr:full":"217 Lakeshore Dr Fredericksburg VA 22405",
    "addr:housenumber":"217",
    "addr:postcode":"22405",
    "addr:street":"Lakeshore Dr",
    "iso:country":"US",
    "sg:address":"217 Lakeshore Dr",
    "sg:city":"Fredericksburg",
    "sg:classifiers":[
        {
            "category":"Building & Trades",
            "subcategory":"Construction",
            "type":"Services"
        }
    ],
    "sg:phone":"+1 540 372 9947",
    "sg:postcode":"22405",
    "sg:province":"VA",
    "sg:tags":[
        "general",
        "contractor"
    ],
    "wof:name":"John Janney Builder Inc",
    "wof:placetype":"venue"
},
  "geometry": {"coordinates":[-77.424739,38.286319],"type":"Point"}
}