{
  "type": "Feature",
  "properties": {
    "iso:country":"US",
    "sg:address":"5008 Fable Ave",
    "sg:city":"Portsmouth",
    "sg:classifiers":[
        {
            "category":"Real Estate",
            "subcategory":"Architect",
            "type":"Services"
        }
    ],
    "sg:phone":"+1 757 483 3507",
    "sg:postcode":"23703",
    "sg:province":"VA",
    "sg:tags":[
        "architectural"
    ],
    "wof:name":"Terra Architectural Desig",
    "wof:placetype":"venue"
},
  "geometry": {"coordinates":[-76.381029,36.843292],"type":"Point"}
}