{
  "type": "Feature",
  "properties": {
    "addr:full":"612 S Sycamore St Petersburg VA 23803",
    "addr:housenumber":"612",
    "addr:postcode":"23803",
    "addr:street":"S Sycamore",
    "iso:country":"US",
    "sg:address":"612 S Sycamore St",
    "sg:city":"Petersburg",
    "sg:classifiers":[
        {
            "category":"Health Services",
            "subcategory":"Doctor",
            "type":"Services"
        }
    ],
    "sg:phone":"+1 804 861 5555",
    "sg:postcode":"23803",
    "sg:province":"VA",
    "sg:tags":[
        "physician",
        "surgeon"
    ],
    "wof:name":"Petersburg Dermatology PC",
    "wof:placetype":"venue"
},
  "geometry": {"coordinates":[-77.399807,37.218318],"type":"Point"}
}