{
  "type": "Feature",
  "properties": {
    "addr:full":"1600 Oliver Hill Way Richmond VA 23219",
    "addr:housenumber":"1600",
    "addr:postcode":"23219",
    "addr:street":"Oliver Hill Way",
    "iso:country":"US",
    "sg:address":"1600 Oliver Hill Way",
    "sg:city":"Richmond",
    "sg:classifiers":[
        {
            "category":"Professional",
            "subcategory":"Employment Agencies",
            "type":"Services"
        },
        {
            "category":"Professional",
            "subcategory":"Lawyer & Legal Services",
            "type":"Services"
        }
    ],
    "sg:phone":"+1 804 646 2914",
    "sg:postcode":"23219",
    "sg:province":"VA",
    "sg:tags":[
        "convention",
        "secretarial",
        "reporters-court"
    ],
    "sg:website":"http://www.richmondgov.com",
    "wof:name":"Social Services Dept",
    "wof:placetype":"venue"
},
  "geometry": {"coordinates":[-77.42414100000001,37.548222],"type":"Point"}
}