{
  "type": "Feature",
  "properties": {
    "iso:country":"US",
    "sg:address":"609 Lynnhaven Pkwy",
    "sg:city":"Virginia Beach",
    "sg:classifiers":[
        {
            "category":"Banks & Credit Unions",
            "subcategory":"Bank",
            "type":"Services"
        }
    ],
    "sg:phone":"+1 757 306 9270",
    "sg:postcode":"23452",
    "sg:province":"VA",
    "sg:tags":[
        "loan",
        "real estate"
    ],
    "wof:name":"Standard Capital",
    "wof:placetype":"venue"
},
  "geometry": {"coordinates":[-76.067233,36.824069],"type":"Point"}
}