{
  "type": "Feature",
  "properties": {
    "iso:country":"US",
    "sg:address":"487 Jefferson Dr W",
    "sg:city":"Palmyra",
    "sg:classifiers":[
        {
            "category":"Shopping",
            "subcategory":"Gifts & Souvenirs",
            "type":"Retail Goods"
        }
    ],
    "sg:phone":"+1 434 589 2800",
    "sg:postcode":"22963",
    "sg:province":"VA",
    "wof:name":"Shicks Cards & Collectibles",
    "wof:placetype":"venue"
},
  "geometry": {"coordinates":[-78.344876,37.923693],"type":"Point"}
}