{
  "type": "Feature",
  "properties": {
    "addr:full":"3038 Waterlick Rd Lynchburg VA 24502",
    "addr:housenumber":"3038",
    "addr:postcode":"24502",
    "addr:street":"Waterlick Rd",
    "iso:country":"US",
    "sg:address":"3038 Waterlick Rd",
    "sg:city":"Lynchburg",
    "sg:classifiers":[
        {
            "category":"Professional",
            "subcategory":"Accounting & Tax Preparation",
            "type":"Services"
        }
    ],
    "sg:phone":"+1 434 237 3500",
    "sg:postcode":"24502",
    "sg:province":"VA",
    "sg:tags":[
        "accountant"
    ],
    "wof:name":"Shackleford & Werthman CPA",
    "wof:placetype":"venue"
},
  "geometry": {"coordinates":[-79.242634,37.327859],"type":"Point"}
}