{
  "type": "Feature",
  "properties": {
    "iso:country":"US",
    "sg:address":"18307 Jefferson Davis Hwy",
    "sg:city":"Triangle",
    "sg:classifiers":[
        {
            "category":"Retail",
            "subcategory":"Auto Repair",
            "type":"Services"
        }
    ],
    "sg:phone":"+1 703 221 3367",
    "sg:postcode":"22172",
    "sg:province":"VA",
    "sg:tags":[
        "automotive"
    ],
    "wof:name":"Quality Auto RPR Transmissions",
    "wof:placetype":"venue"
},
  "geometry": {"coordinates":[-77.332472,38.555172],"type":"Point"}
}