{
  "type": "Feature",
  "properties": {
    "addr:full":"8390 Terminal Rd Ste F Lorton VA 22079",
    "addr:housenumber":"8390",
    "addr:postcode":"22079",
    "addr:street":"Terminal Rd Ste F",
    "iso:country":"US",
    "sg:address":"8390 Terminal Rd Ste F",
    "sg:city":"Lorton",
    "sg:classifiers":[
        {
            "category":"Manufacturing",
            "subcategory":"Electronics",
            "type":"Manufacturing & Wholesale Goods"
        },
        {
            "category":"Professional",
            "subcategory":"Printing & Photocopies",
            "type":"Services"
        }
    ],
    "sg:phone":"+1 703 550 7700",
    "sg:postcode":"22079",
    "sg:province":"VA",
    "sg:tags":[
        "printers-equipment",
        "services-commercial",
        "duplicating",
        "copying",
        "supply"
    ],
    "sg:website":"http://www.accessprint.com",
    "wof:name":"Access Printing Co",
    "wof:placetype":"venue"
},
  "geometry": {"coordinates":[-77.195516,38.728161],"type":"Point"}
}