{
  "type": "Feature",
  "properties": {
    "addr:full":"RR 1 Box 195 Haysi VA 24256",
    "addr:housenumber":"195",
    "addr:postcode":"haysi;24256",
    "addr:street":"Rr 1 Box",
    "iso:country":"US",
    "sg:address":"RR 1 Box 195",
    "sg:city":"Haysi",
    "sg:classifiers":[
        {
            "category":"Communications",
            "subcategory":"Film & Video Production",
            "type":"Services"
        }
    ],
    "sg:phone":"+1 276 835 8431",
    "sg:postcode":"24256",
    "sg:province":"VA",
    "sg:tags":[
        "photographer",
        "aerial"
    ],
    "wof:name":"Davis Vidio Aerial Photo",
    "wof:placetype":"venue"
},
  "geometry": {"coordinates":[-82.31869500000001,37.226761],"type":"Point"}
}