{
  "type": "Feature",
  "properties": {
    "addr:full":"5335 Ritchie Rd Bealeton VA 22712",
    "addr:housenumber":"5335",
    "addr:postcode":"22712",
    "addr:street":"Ritchie Rd",
    "iso:country":"US",
    "sg:address":"5335 Ritchie Rd",
    "sg:city":"Bealeton",
    "sg:classifiers":[
        {
            "category":"Building & Trades",
            "subcategory":"Construction",
            "type":"Services"
        }
    ],
    "sg:phone":"+1 540 439 6900",
    "sg:postcode":"22712",
    "sg:province":"VA",
    "sg:tags":[
        "contractor"
    ],
    "wof:name":"Firesafe Chimney Systems Inc",
    "wof:placetype":"venue"
},
  "geometry": {"coordinates":[-77.72935099999999,38.543352],"type":"Point"}
}