{
  "type": "Feature",
  "properties": {
    "addr:full":"8610 Prince George Dr Disputanta VA 23842",
    "addr:housenumber":"8610",
    "addr:postcode":"23842",
    "addr:street":"Prince George Dr",
    "iso:country":"US",
    "sg:address":"8610 Prince George Dr",
    "sg:city":"Disputanta",
    "sg:classifiers":[
        {
            "category":"Building & Trades",
            "subcategory":"Construction",
            "type":"Services"
        }
    ],
    "sg:phone":"+1 804 733 4503",
    "sg:postcode":"23842",
    "sg:province":"VA",
    "sg:tags":[
        "roofing",
        "contractor"
    ],
    "wof:name":"Tri Square Builders",
    "wof:placetype":"venue"
},
  "geometry": {"coordinates":[-77.26073,37.195224],"type":"Point"}
}