{
  "type": "Feature",
  "properties": {
    "addr:full":"18296 Tioga Dr Abingdon VA 24211",
    "addr:housenumber":"18296",
    "addr:postcode":"24211",
    "addr:street":"Tioga Dr",
    "iso:country":"US",
    "sg:address":"18296 Tioga Dr",
    "sg:city":"Abingdon",
    "sg:classifiers":[
        {
            "category":"Retail",
            "subcategory":"Auto Rental",
            "type":"Services"
        }
    ],
    "sg:phone":"+1 276 623 2437",
    "sg:postcode":"24211",
    "sg:province":"VA",
    "sg:tags":[
        "equipment",
        "car",
        "passenger"
    ],
    "wof:name":"Rent Smart",
    "wof:placetype":"venue"
},
  "geometry": {"coordinates":[-82.034485,36.621888],"type":"Point"}
}