{
  "type": "Feature",
  "properties": {
    "addr:full":"1950 Old Gallows Rd Vienna VA 22182",
    "addr:housenumber":"1950",
    "addr:postcode":"22182",
    "addr:street":"Old Gallows Rd",
    "iso:country":"US",
    "sg:address":"1950 Old Gallows Rd",
    "sg:city":"Vienna",
    "sg:classifiers":[
        {
            "category":"Professional",
            "subcategory":"Lawyer & Legal Services",
            "type":"Services"
        }
    ],
    "sg:phone":"+1 703 356 4960",
    "sg:postcode":"22182",
    "sg:province":"VA",
    "wof:name":"Property & Estate Law",
    "wof:placetype":"venue"
},
  "geometry": {"coordinates":[-77.223266,38.911309],"type":"Point"}
}