{
  "type": "Feature",
  "properties": {
    "iso:country":"US",
    "sg:address":"813 W 39th St",
    "sg:city":"Norfolk",
    "sg:classifiers":[
        {
            "category":"Building & Trades",
            "subcategory":"Construction",
            "type":"Services"
        }
    ],
    "sg:phone":"+1 757 440 0015",
    "sg:postcode":"23508",
    "sg:province":"VA",
    "sg:tags":[
        "general",
        "contractor"
    ],
    "wof:name":"Renovations & Innovations",
    "wof:placetype":"venue"
},
  "geometry": {"coordinates":[-76.29787,36.880619],"type":"Point"}
}