{
  "type": "Feature",
  "properties": {
    "iso:country":"US",
    "sg:address":"1821 Spruce St",
    "sg:city":"Martinsville",
    "sg:classifiers":[
        {
            "category":"Building & Trades",
            "subcategory":"Construction",
            "type":"Services"
        }
    ],
    "sg:phone":"+1 276 632 7276",
    "sg:postcode":"24112",
    "sg:province":"VA",
    "sg:tags":[
        "fire",
        "restoration",
        "damage"
    ],
    "wof:name":"Servpro",
    "wof:placetype":"venue"
},
  "geometry": {"coordinates":[-79.83967199999999,36.669783],"type":"Point"}
}