{
  "type": "Feature",
  "properties": {
    "addr:full":"1205 State St Radford VA 24141",
    "addr:housenumber":"1205",
    "addr:postcode":"24141",
    "addr:street":"State St",
    "iso:country":"US",
    "sg:address":"1205 State St",
    "sg:city":"Radford",
    "sg:classifiers":[
        {
            "category":"Building & Trades",
            "subcategory":"Construction",
            "type":"Services"
        }
    ],
    "sg:phone":"+1 540 639 2511",
    "sg:postcode":"24141",
    "sg:province":"VA",
    "sg:tags":[
        "residential",
        "painting"
    ],
    "wof:name":"Painting By Bill Vinion",
    "wof:placetype":"venue"
},
  "geometry": {"coordinates":[-80.56632399999999,37.124227],"type":"Point"}
}