{
  "type": "Feature",
  "properties": {
    "addr:full":"2 Lower Tuckahoe Rd E Richmond VA 23238",
    "addr:housenumber":"2",
    "addr:postcode":"23238",
    "addr:street":"Lower Tuckahoe Rd E",
    "iso:country":"US",
    "sg:address":"2 Lower Tuckahoe Rd E",
    "sg:city":"Richmond",
    "sg:classifiers":[
        {
            "category":"Professional",
            "subcategory":"Engineering",
            "type":"Services"
        }
    ],
    "sg:phone":"+1 804 784 2300",
    "sg:postcode":"23238",
    "sg:province":"VA",
    "sg:tags":[
        "equipment",
        "supply"
    ],
    "wof:name":"Metray Inc",
    "wof:placetype":"venue"
},
  "geometry": {"coordinates":[-77.64122,37.584061],"type":"Point"}
}