{
  "type": "Feature",
  "properties": {
    "iso:country":"US",
    "sg:address":"505 Huntmar Park Dr",
    "sg:city":"Herndon",
    "sg:classifiers":[
        {
            "category":"Professional",
            "subcategory":"Computer Services",
            "type":"Services"
        }
    ],
    "sg:phone":"+1 703 708 1900",
    "sg:postcode":"20170",
    "sg:province":"VA",
    "sg:tags":[
        "consulting",
        "management",
        "datum"
    ],
    "wof:name":"Sungard",
    "wof:placetype":"venue"
},
  "geometry": {"coordinates":[-77.380326,38.964377],"type":"Point"}
}