{
  "type": "Feature",
  "properties": {
    "iso:country":"US",
    "sg:address":"8035 Sudley Rd",
    "sg:city":"Manassas",
    "sg:classifiers":[
        {
            "category":"Shopping",
            "subcategory":"Hobbies, Toys, & Games",
            "type":"Retail Goods"
        }
    ],
    "sg:phone":"+1 703 330 3559",
    "sg:postcode":"20109",
    "sg:province":"VA",
    "wof:name":"Game Stop Corp",
    "wof:placetype":"venue"
},
  "geometry": {"coordinates":[-77.511635,38.782463],"type":"Point"}
}