{
  "type": "Feature",
  "properties": {
    "addr:full":"201 King St Ste 202 Alexandria VA 22314",
    "addr:housenumber":"201",
    "addr:postcode":"22314",
    "addr:street":"King St Ste 202",
    "iso:country":"US",
    "sg:address":"201 King St Ste 202",
    "sg:city":"Alexandria",
    "sg:classifiers":[
        {
            "category":"Professional",
            "subcategory":"Management & Consulting",
            "type":"Services"
        }
    ],
    "sg:phone":"+1 703 229 4444",
    "sg:postcode":"22314",
    "sg:province":"VA",
    "sg:tags":[
        "counselor",
        "relation",
        "public"
    ],
    "wof:name":"Endeavour Global Strategies",
    "wof:placetype":"venue"
},
  "geometry": {"coordinates":[-77.041481,38.804371],"type":"Point"}
}