{
  "type": "Feature",
  "properties": {
    "addr:full":"1101 Azalea Ave Richmond VA 23227",
    "addr:housenumber":"1101",
    "addr:postcode":"23227",
    "addr:street":"Azalea Ave",
    "iso:country":"US",
    "sg:address":"1101 Azalea Ave",
    "sg:city":"Richmond",
    "sg:classifiers":[
        {
            "category":"Banks & Credit Unions",
            "subcategory":"Bank",
            "type":"Services"
        },
        {
            "category":"Banks & Credit Unions",
            "subcategory":"Financial Services",
            "type":"Services"
        }
    ],
    "sg:phone":"+1 804 264 5990",
    "sg:postcode":"23227",
    "sg:province":"VA",
    "sg:tags":[
        "loan",
        "financing"
    ],
    "sg:website":"http://www.SunTrust.com",
    "wof:name":"SunTrust Bank - Azalea Avenue",
    "wof:placetype":"venue"
},
  "geometry": {"coordinates":[-77.45153000000001,37.601662],"type":"Point"}
}