{
  "type": "Feature",
  "properties": {
    "addr:full":"3301 Manor Grove Cir Glen Allen VA 23059",
    "addr:housenumber":"3301",
    "addr:postcode":"23059",
    "addr:street":"Manor Grove Cir",
    "iso:country":"US",
    "sg:address":"3301 Manor Grove Cir",
    "sg:city":"Glen Allen",
    "sg:classifiers":[
        {
            "category":"Professional",
            "type":"Services"
        }
    ],
    "sg:phone":"+1 804 249 4001",
    "sg:postcode":"23059",
    "sg:province":"VA",
    "wof:name":"Manor At Hunton Park",
    "wof:placetype":"venue"
},
  "geometry": {"coordinates":[-77.522502,37.684758],"type":"Point"}
}