{
  "type": "Feature",
  "properties": {
    "addr:full":"172 Winding Way Rd Lynchburg VA 24502",
    "addr:housenumber":"172",
    "addr:postcode":"24502",
    "addr:street":"Winding Way Rd",
    "iso:country":"US",
    "sg:address":"172 Winding Way Rd",
    "sg:city":"Lynchburg",
    "sg:classifiers":[
        {
            "category":"Professional",
            "subcategory":"Employment Agencies",
            "type":"Services"
        }
    ],
    "sg:phone":"+1 434 237 6775",
    "sg:postcode":"24502",
    "sg:province":"VA",
    "sg:tags":[
        "help",
        "supply"
    ],
    "wof:name":"Saami Shaibani Dr",
    "wof:placetype":"venue"
},
  "geometry": {"coordinates":[-79.25665100000001,37.35365],"type":"Point"}
}