{
  "type": "Feature",
  "properties": {
    "addr:full":"3312 Croft St Norfolk VA 23513",
    "addr:housenumber":"3312",
    "addr:postcode":"23513",
    "addr:street":"Croft St",
    "iso:country":"US",
    "sg:address":"3312 Croft St",
    "sg:city":"Norfolk",
    "sg:classifiers":[
        {
            "category":"Freight",
            "type":"Transportation"
        }
    ],
    "sg:phone":"+1 757 857 1001",
    "sg:postcode":"23513",
    "sg:province":"VA",
    "sg:tags":[
        "storage",
        "outlet"
    ],
    "wof:name":"Armadillo Mini Storage",
    "wof:placetype":"venue"
},
  "geometry": {"coordinates":[-76.217662,36.884479],"type":"Point"}
}