{
  "type": "Feature",
  "properties": {
    "addr:full":"2701 E Parham Rd Richmond VA 23228",
    "addr:housenumber":"2701",
    "addr:postcode":"23228",
    "addr:street":"E Parham Rd",
    "iso:country":"US",
    "sg:address":"2701 E Parham Rd",
    "sg:city":"Richmond",
    "sg:classifiers":[
        {
            "category":"Freight",
            "type":"Transportation"
        }
    ],
    "sg:phone":"+1 804 264 7867",
    "sg:postcode":"23228",
    "sg:province":"VA",
    "sg:tags":[
        "commercial",
        "storage"
    ],
    "wof:name":"Parham Road Self Storage",
    "wof:placetype":"venue"
},
  "geometry": {"coordinates":[-77.495822,37.636635],"type":"Point"}
}