{
  "type": "Feature",
  "properties": {
    "addr:full":"4805 Stonecroft Blvd Chantilly VA 20151",
    "addr:housenumber":"4805",
    "addr:postcode":"20151",
    "addr:street":"Stonecroft Blvd",
    "iso:country":"US",
    "sg:address":"4805 Stonecroft Blvd",
    "sg:city":"Chantilly",
    "sg:classifiers":[
        {
            "category":"Professional",
            "type":"Services"
        }
    ],
    "sg:phone":"+1 703 858 9919",
    "sg:postcode":"20151",
    "sg:province":"VA",
    "sg:tags":[
        "establishment"
    ],
    "wof:name":"Mark Winkler Co",
    "wof:placetype":"venue"
},
  "geometry": {"coordinates":[-77.46101400000001,38.882067],"type":"Point"}
}