{
  "type": "Feature",
  "properties": {
    "addr:full":"4914 Radford Ave Richmond VA 23230",
    "addr:housenumber":"4914",
    "addr:postcode":"23230",
    "addr:street":"Radford Ave",
    "iso:country":"US",
    "sg:address":"4914 Radford Ave",
    "sg:city":"Richmond",
    "sg:classifiers":[
        {
            "category":"Professional",
            "subcategory":"Employment Agencies",
            "type":"Services"
        }
    ],
    "sg:phone":"+1 804 353 3388",
    "sg:postcode":"23230",
    "sg:province":"VA",
    "sg:tags":[
        "help",
        "supply"
    ],
    "wof:name":"Kelly Services",
    "wof:placetype":"venue"
},
  "geometry": {"coordinates":[-77.495755,37.581105],"type":"Point"}
}