{
  "type": "Feature",
  "properties": {
    "addr:full":"13290 Worth Ave Woodbridge VA 22192",
    "addr:housenumber":"13290",
    "addr:postcode":"22192",
    "addr:street":"Worth Ave",
    "iso:country":"US",
    "sg:address":"13290 Worth Ave",
    "sg:city":"Woodbridge",
    "sg:classifiers":[
        {
            "category":"Organizations",
            "subcategory":"Professional Association",
            "type":"Services"
        }
    ],
    "sg:phone":"+1 703 494 5216",
    "sg:postcode":"22192",
    "sg:province":"VA",
    "wof:name":"Smoketown Road Association",
    "wof:placetype":"venue"
},
  "geometry": {"coordinates":[-77.295062,38.648283],"type":"Point"}
}