{
  "type": "Feature",
  "properties": {
    "addr:full":"6101 Belle Dr Crozet VA 22932",
    "addr:housenumber":"6101",
    "addr:postcode":"22932",
    "addr:street":"Belle Dr",
    "iso:country":"US",
    "sg:address":"6101 Belle Dr",
    "sg:city":"Crozet",
    "sg:classifiers":[
        {
            "category":"Building & Trades",
            "subcategory":"Construction",
            "type":"Services"
        }
    ],
    "sg:phone":"+1 434 823 1221",
    "sg:postcode":"22932",
    "sg:province":"VA",
    "sg:tags":[
        "house"
    ],
    "wof:name":"Mercury Construction Service",
    "wof:placetype":"venue"
},
  "geometry": {"coordinates":[-78.711579,38.073398],"type":"Point"}
}