{
  "type": "Feature",
  "properties": {
    "addr:full":"36634 N Fork Rd Purcellville VA 20132",
    "addr:housenumber":"36634",
    "addr:postcode":"20132",
    "addr:street":"N Fork Rd",
    "iso:country":"US",
    "sg:address":"36634 N Fork Rd",
    "sg:city":"Purcellville",
    "sg:classifiers":[
        {
            "category":"Real Estate",
            "subcategory":"Real Estate Agent",
            "type":"Services"
        }
    ],
    "sg:phone":"+1 540 338 8388",
    "sg:postcode":"20132",
    "sg:province":"VA",
    "wof:name":"Blue Haron Realty",
    "wof:placetype":"venue"
},
  "geometry": {"coordinates":[-77.72479199999999,39.067946],"type":"Point"}
}