{
  "type": "Feature",
  "properties": {
    "addr:full":"2325 Dulles Corner Blvd 5th Floor Herndon VA 20171",
    "addr:housenumber":"2325",
    "addr:postcode":"20171",
    "addr:street":"Dulles Corner Blvd 5Th Floor",
    "iso:country":"US",
    "sg:address":"2325 Dulles Corner Blvd 5th Floor",
    "sg:city":"Herndon",
    "sg:classifiers":[
        {
            "category":"Professional",
            "subcategory":"Business Services",
            "type":"Services"
        }
    ],
    "sg:phone":"+1 703 788 6534",
    "sg:postcode":"20171",
    "sg:province":"VA",
    "sg:tags":[
        "low-latency-network",
        "mobile-backhaul",
        "wirelesss-backhaul",
        "saas",
        "content-distribution",
        "frequency-trading",
        "high-frequency-trading"
    ],
    "sg:website":"http://www.cfnservices.com",
    "wof:name":"CFN Services",
    "wof:placetype":"venue"
},
  "geometry": {"coordinates":[-77.42274,38.9598],"type":"Point"}
}