{
  "type": "Feature",
  "properties": {
    "addr:full":"517 N Fillmore Ave Sterling VA 20164",
    "addr:housenumber":"517",
    "addr:postcode":"20164",
    "addr:street":"N Fillmore Ave",
    "iso:country":"US",
    "sg:address":"517 N Fillmore Ave",
    "sg:city":"Sterling",
    "sg:classifiers":[
        {
            "category":"Professional",
            "type":"Services"
        }
    ],
    "sg:phone":"+1 703 444 1058",
    "sg:postcode":"20164",
    "sg:province":"VA",
    "wof:name":"Beyond Bronze",
    "wof:placetype":"venue"
},
  "geometry": {"coordinates":[-77.39405499999999,39.004041],"type":"Point"}
}