{
  "type": "Feature",
  "properties": {
    "addr:full":"1221 E Broad St Richmond VA 23219",
    "addr:housenumber":"1221",
    "addr:postcode":"23219",
    "addr:street":"E Broad St",
    "iso:country":"US",
    "sg:address":"1221 E Broad St",
    "sg:city":"Richmond",
    "sg:classifiers":[
        {
            "category":"Government",
            "subcategory":"Office",
            "type":"Public Place"
        }
    ],
    "sg:phone":"+1 804 786 2801",
    "sg:postcode":"23219",
    "sg:province":"VA",
    "sg:tags":[
        "state",
        "program"
    ],
    "wof:name":"Transportation Dept Gen Info",
    "wof:placetype":"venue"
},
  "geometry": {"coordinates":[-77.430097,37.538408],"type":"Point"}
}