{
  "type": "Feature",
  "properties": {
    "iso:country":"US",
    "sg:address":"5587 Roundtree Dr",
    "sg:city":"Woodbridge",
    "sg:classifiers":[
        {
            "category":"Professional",
            "subcategory":"Computer Services",
            "type":"Services"
        }
    ],
    "sg:phone":"+1 571 264 8571",
    "sg:postcode":"22193",
    "sg:province":"VA",
    "sg:tags":[
        "consulting"
    ],
    "wof:name":"Visionnet Technologies Inc",
    "wof:placetype":"venue"
},
  "geometry": {"coordinates":[-77.377099,38.646768],"type":"Point"}
}