{
  "type": "Feature",
  "properties": {
    "addr:full":"12727 Oak Lake Ct Midlothian VA 23112",
    "addr:housenumber":"12727",
    "addr:postcode":"23112",
    "addr:street":"Oak Lake Ct",
    "iso:country":"US",
    "sg:address":"12727 Oak Lake Ct",
    "sg:city":"Midlothian",
    "sg:classifiers":[
        {
            "category":"Building & Trades",
            "subcategory":"Equipment Rental",
            "type":"Services"
        }
    ],
    "sg:phone":"+1 804 744 0316",
    "sg:postcode":"23112",
    "sg:province":"VA",
    "wof:name":"Prime Energy",
    "wof:placetype":"venue"
},
  "geometry": {"coordinates":[-77.630348,37.456834],"type":"Point"}
}