{
  "type": "Feature",
  "properties": {
    "addr:full":"549 S Birdneck Rd Virginia Beach VA 23451",
    "addr:housenumber":"549",
    "addr:postcode":"23451",
    "addr:street":"S Birdneck Rd",
    "iso:country":"US",
    "sg:address":"549 S Birdneck Rd",
    "sg:city":"Virginia Beach",
    "sg:classifiers":[
        {
            "category":"Retail",
            "subcategory":"Auto Repair",
            "type":"Services"
        }
    ],
    "sg:phone":"+1 757 425 8011",
    "sg:postcode":"23451",
    "sg:province":"VA",
    "sg:tags":[
        "body",
        "automotive",
        "painting",
        "automobile"
    ],
    "wof:name":"Auto Elite Collision Center",
    "wof:placetype":"venue"
},
  "geometry": {"coordinates":[-75.999858,36.823182],"type":"Point"}
}