{
  "type": "Feature",
  "properties": {
    "iso:country":"US",
    "sg:address":"122 W Pembroke Ave",
    "sg:city":"Hampton",
    "sg:classifiers":[
        {
            "category":"Retail",
            "subcategory":"Auto Repair",
            "type":"Services"
        }
    ],
    "sg:phone":"+1 757 723 0078",
    "sg:postcode":"23669",
    "sg:province":"VA",
    "sg:tags":[
        "body",
        "automobile",
        "painting"
    ],
    "wof:name":"Dinh Auto Sales & Body Shop",
    "wof:placetype":"venue"
},
  "geometry": {"coordinates":[-76.34929200000001,37.029513],"type":"Point"}
}