{
  "type": "Feature",
  "properties": {
    "addr:full":"1200 W Main St Wytheville VA 24382",
    "addr:housenumber":"1200",
    "addr:postcode":"24382",
    "addr:street":"W Main St",
    "iso:country":"US",
    "sg:address":"1200 W Main St",
    "sg:city":"Wytheville",
    "sg:classifiers":[
        {
            "category":"Manufacturing",
            "subcategory":"Retail Goods",
            "type":"Manufacturing & Wholesale Goods"
        }
    ],
    "sg:phone":"+1 276 223 1214",
    "sg:postcode":"24382",
    "sg:province":"VA",
    "sg:tags":[
        "manufacturer"
    ],
    "wof:name":"Oak Hall Industries",
    "wof:placetype":"venue"
},
  "geometry": {"coordinates":[-81.093964,36.941865],"type":"Point"}
}