{
  "type": "Feature",
  "properties": {
    "addr:full":"2551 Freeman St Hopewell VA 23860",
    "addr:housenumber":"2551",
    "addr:postcode":"23860",
    "addr:street":"Freeman St",
    "iso:country":"US",
    "sg:address":"2551 Freeman St",
    "sg:city":"Hopewell",
    "sg:classifiers":[
        {
            "category":"Shopping",
            "subcategory":"Clothing, Apparel, & Fashions",
            "type":"Retail Goods"
        }
    ],
    "sg:phone":"+1 804 458 1523",
    "sg:postcode":"23860",
    "sg:province":"VA",
    "wof:name":"Custom Designs",
    "wof:placetype":"venue"
},
  "geometry": {"coordinates":[-77.295275,37.281595],"type":"Point"}
}