{
  "type": "Feature",
  "properties": {
    "iso:country":"US",
    "sg:address":"1701 Scaup Ct",
    "sg:city":"Chesapeake",
    "sg:classifiers":[
        {
            "category":"Shopping",
            "subcategory":"Discount & Variety Stores",
            "type":"Retail Goods"
        }
    ],
    "sg:phone":"+1 757 543 7696",
    "sg:postcode":"23320",
    "sg:province":"VA",
    "wof:name":"Homestead Retailors",
    "wof:placetype":"venue"
},
  "geometry": {"coordinates":[-76.27392999999999,36.77712],"type":"Point"}
}