{
  "type": "Feature",
  "properties": {
    "iso:country":"US",
    "sg:address":"5644 Shoulders Hill Rd",
    "sg:city":"Suffolk",
    "sg:classifiers":[
        {
            "category":"Retail",
            "subcategory":"Auto Repair",
            "type":"Services"
        }
    ],
    "sg:phone":"+1 757 483 3367",
    "sg:postcode":"23435",
    "sg:province":"VA",
    "sg:tags":[
        "automobile",
        "top",
        "upholstery"
    ],
    "wof:name":"Tim's Upholstery",
    "wof:placetype":"venue"
},
  "geometry": {"coordinates":[-76.464035,36.860148],"type":"Point"}
}