{
  "type": "Feature",
  "properties": {
    "addr:full":"5327 Queensberry Ave Springfield VA 22151",
    "addr:housenumber":"5327",
    "addr:postcode":"22151",
    "addr:street":"Queensberry Ave",
    "iso:country":"US",
    "sg:address":"5327 Queensberry Ave",
    "sg:city":"Springfield",
    "sg:classifiers":[
        {
            "category":"Professional",
            "subcategory":"Accounting & Tax Preparation",
            "type":"Services"
        }
    ],
    "sg:phone":"+1 703 321 0357",
    "sg:postcode":"22151",
    "sg:province":"VA",
    "wof:name":"Draffin & Assoc Inc",
    "wof:placetype":"venue"
},
  "geometry": {"coordinates":[-77.220888,38.805226],"type":"Point"}
}