{
  "type": "Feature",
  "properties": {
    "addr:full":"26 S King St Leesburg VA 20175",
    "addr:housenumber":"26",
    "addr:postcode":"20175",
    "addr:street":"S King St",
    "iso:country":"US",
    "sg:address":"26 S King St",
    "sg:city":"Leesburg",
    "sg:classifiers":[
        {
            "category":"Shopping",
            "type":"Retail Goods"
        }
    ],
    "sg:phone":"+1 703 777 0720",
    "sg:postcode":"20175",
    "sg:province":"VA",
    "sg:tags":[
        "merchandise"
    ],
    "wof:name":"Loudoun Quilt Shop",
    "wof:placetype":"venue"
},
  "geometry": {"coordinates":[-77.56457399999999,39.115121],"type":"Point"}
}