{
  "type": "Feature",
  "properties": {
    "addr:full":"4917 Colonial Ave Roanoke VA 24018",
    "addr:housenumber":"4917",
    "addr:postcode":"24018",
    "addr:street":"Colonial Ave",
    "iso:country":"US",
    "sg:address":"4917 Colonial Ave",
    "sg:city":"Roanoke",
    "sg:classifiers":[
        {
            "category":"Building & Trades",
            "subcategory":"Construction",
            "type":"Services"
        }
    ],
    "sg:phone":"+1 540 725 7641",
    "sg:postcode":"24018",
    "sg:province":"VA",
    "sg:tags":[
        "floor"
    ],
    "wof:name":"Industrial Floor Systems Inc",
    "wof:placetype":"venue"
},
  "geometry": {"coordinates":[-80.011332,37.223591],"type":"Point"}
}