{
  "type": "Feature",
  "properties": {
    "addr:full":"242 Gala Dr Roanoke VA 24019",
    "addr:housenumber":"242",
    "addr:postcode":"24019",
    "addr:street":"Gala Dr",
    "iso:country":"US",
    "sg:address":"242 Gala Dr",
    "sg:city":"Roanoke",
    "sg:classifiers":[
        {
            "category":"Wholesale",
            "subcategory":"Electrical",
            "type":"Manufacturing & Wholesale Goods"
        }
    ],
    "sg:phone":"+1 540 977 6811",
    "sg:postcode":"24019",
    "sg:province":"VA",
    "sg:tags":[
        "transmission",
        "equipment",
        "power"
    ],
    "wof:name":"Rockwell Automation",
    "wof:placetype":"venue"
},
  "geometry": {"coordinates":[-79.87755,37.335265],"type":"Point"}
}