{
  "type": "Feature",
  "properties": {
    "addr:full":"5723 S Laburnum Ave Richmond VA 23231",
    "addr:housenumber":"5723",
    "addr:postcode":"23231",
    "addr:street":"S Laburnum Ave",
    "iso:country":"US",
    "sg:address":"5723 S Laburnum Ave",
    "sg:city":"Richmond",
    "sg:classifiers":[
        {
            "category":"Building & Trades",
            "subcategory":"Cleaning & Sanitation",
            "type":"Services"
        }
    ],
    "sg:phone":"+1 804 222 9059",
    "sg:postcode":"23231",
    "sg:province":"VA",
    "sg:tags":[
        "janitor"
    ],
    "wof:name":"PBM Premier Building",
    "wof:placetype":"venue"
},
  "geometry": {"coordinates":[-77.349349,37.507723],"type":"Point"}
}