{
  "type": "Feature",
  "properties": {
    "iso:country":"US",
    "sg:address":"966 Cam Real S",
    "sg:city":"Virginia Beach",
    "sg:classifiers":[
        {
            "category":"Shopping",
            "type":"Retail Goods"
        }
    ],
    "sg:phone":"+1 757 426 8911",
    "sg:postcode":"23456",
    "sg:province":"VA",
    "sg:tags":[
        "enforcement",
        "law",
        "merchandise",
        "supply"
    ],
    "wof:name":"Protective Material Company",
    "wof:placetype":"venue"
},
  "geometry": {"coordinates":[-75.986637,36.74572],"type":"Point"}
}