{
  "type": "Feature",
  "properties": {
    "addr:full":"6167 Strasburg Dr Centreville VA 20121",
    "addr:housenumber":"6167",
    "addr:postcode":"20121",
    "addr:street":"Strasburg Dr",
    "iso:country":"US",
    "sg:address":"6167 Strasburg Dr",
    "sg:city":"Centreville",
    "sg:classifiers":[
        {
            "category":"Building & Trades",
            "subcategory":"Construction",
            "type":"Services"
        }
    ],
    "sg:phone":"+1 703 338 3204",
    "sg:postcode":"20121",
    "sg:province":"VA",
    "sg:tags":[
        "painting",
        "contractor"
    ],
    "wof:name":"Carlos Perez",
    "wof:placetype":"venue"
},
  "geometry": {"coordinates":[-77.443775,38.834596],"type":"Point"}
}