{
  "type": "Feature",
  "properties": {
    "addr:full":"2215 Plank Rd Fredericksburg VA 22401",
    "addr:housenumber":"2215",
    "addr:postcode":"22401",
    "addr:street":"Plank Rd",
    "iso:country":"US",
    "sg:address":"2215 Plank Rd",
    "sg:city":"Fredericksburg",
    "sg:classifiers":[
        {
            "category":"Health Services",
            "subcategory":"Podiatrist",
            "type":"Services"
        }
    ],
    "sg:phone":"+1 540 371 2724",
    "sg:postcode":"22401",
    "sg:province":"VA",
    "wof:name":"Rappahannoch Foot & Ankle Spec",
    "wof:placetype":"venue"
},
  "geometry": {"coordinates":[-77.496809,38.296187],"type":"Point"}
}