{
  "type": "Feature",
  "properties": {
    "addr:full":"1117-L East Market Street Charlottesville VA 22902",
    "addr:housenumber":"1117-l",
    "addr:postcode":"22902",
    "addr:street":"East Market Street",
    "iso:country":"US",
    "sg:address":"1117-L East Market Street",
    "sg:city":"Charlottesville",
    "sg:classifiers":[
        {
            "category":"Restaurant",
            "type":"Food & Drink"
        }
    ],
    "sg:phone":"+1 434 971 7720",
    "sg:postcode":"22902",
    "sg:province":"VA",
    "sg:website":"www.apimentocatering.com/",
    "wof:name":"A Pimento Catering",
    "wof:placetype":"venue"
},
  "geometry": {"coordinates":[-78.471797,38.028179],"type":"Point"}
}