{
  "type": "Feature",
  "properties": {
    "iso:country":"US",
    "sg:address":"31492 Baylor Rd",
    "sg:city":"Hanover",
    "sg:classifiers":[
        {
            "category":"Social Services",
            "subcategory":"Child Care",
            "type":"Services"
        }
    ],
    "sg:phone":"+1 804 994 2244",
    "sg:postcode":"23069",
    "sg:province":"VA",
    "sg:tags":[
        "day"
    ],
    "wof:name":"Carters Child Day Center",
    "wof:placetype":"venue"
},
  "geometry": {"coordinates":[-77.37146199999999,37.829855],"type":"Point"}
}