{
  "type": "Feature",
  "properties": {
    "iso:country":"US",
    "sg:address":"2715 Monticello Ave",
    "sg:city":"Norfolk",
    "sg:classifiers":[
        {
            "category":"Autos & Motor Vehicles",
            "subcategory":"Auto Supplies",
            "type":"Retail Goods"
        }
    ],
    "sg:phone":"+1 757 624 8472",
    "sg:postcode":"23517",
    "sg:province":"VA",
    "wof:name":"Express Tires & Rims Inc",
    "wof:placetype":"venue"
},
  "geometry": {"coordinates":[-76.281948,36.872018],"type":"Point"}
}