{
  "type": "Feature",
  "properties": {
    "addr:full":"16 Howard Pl Sterling VA 20164",
    "addr:housenumber":"16",
    "addr:postcode":"20164",
    "addr:street":"Howard Pl",
    "iso:country":"US",
    "sg:address":"16 Howard Pl",
    "sg:city":"Sterling",
    "sg:classifiers":[
        {
            "category":"Wholesale",
            "subcategory":"Electrical",
            "type":"Manufacturing & Wholesale Goods"
        }
    ],
    "sg:phone":"+1 703 406 9777",
    "sg:postcode":"20164",
    "sg:province":"VA",
    "sg:tags":[
        "comm",
        "system",
        "microwave"
    ],
    "wof:name":"Secontel",
    "wof:placetype":"venue"
},
  "geometry": {"coordinates":[-77.37653299999999,39.036449],"type":"Point"}
}