{
  "type": "Feature",
  "properties": {
    "iso:country":"US",
    "sg:address":"1102 Waterstone Ct",
    "sg:city":"Chesapeake",
    "sg:classifiers":[
        {
            "category":"Health Services",
            "subcategory":"Health Practitioner",
            "type":"Services"
        }
    ],
    "sg:phone":"+1 757 831 4718",
    "sg:postcode":"23320",
    "sg:province":"VA",
    "wof:name":"Costal Surgical Assistants",
    "wof:placetype":"venue"
},
  "geometry": {"coordinates":[-76.24426099999999,36.756981],"type":"Point"}
}