{
  "type": "Feature",
  "properties": {
    "iso:country":"US",
    "sg:address":"609 Geranium Rd",
    "sg:city":"Ruckersville",
    "sg:classifiers":[
        {
            "category":"Building & Trades",
            "subcategory":"Cleaning & Sanitation",
            "type":"Services"
        }
    ],
    "sg:phone":"+1 434 985 8892",
    "sg:postcode":"22968",
    "sg:province":"VA",
    "sg:tags":[
        "janitor"
    ],
    "wof:name":"Extreme Cleaning Svc",
    "wof:placetype":"venue"
},
  "geometry": {"coordinates":[-78.428293,38.257687],"type":"Point"}
}