{
  "type": "Feature",
  "properties": {
    "addr:full":"2223 W Grace St Richmond VA 23220",
    "addr:housenumber":"2223",
    "addr:postcode":"23220",
    "addr:street":"W Grace St",
    "iso:country":"US",
    "sg:address":"2223 W Grace St",
    "sg:city":"Richmond",
    "sg:classifiers":[
        {
            "category":"Health Services",
            "subcategory":"Nursing And Care Facility",
            "type":"Services"
        }
    ],
    "sg:phone":"+1 804 355 9636",
    "sg:postcode":"23220",
    "sg:province":"VA",
    "sg:tags":[
        "home",
        "convalescent"
    ],
    "wof:name":"Nel Brook West Rest Home",
    "wof:placetype":"venue"
},
  "geometry": {"coordinates":[-77.46422699999999,37.557496],"type":"Point"}
}