{
  "type": "Feature",
  "properties": {
    "iso:country":"US",
    "sg:address":"1030 S Jefferson St Ste G100",
    "sg:city":"Roanoke",
    "sg:classifiers":[
        {
            "category":"Health Services",
            "subcategory":"Doctor",
            "type":"Services"
        }
    ],
    "sg:phone":"+1 540 985 8526",
    "sg:postcode":"24016",
    "sg:province":"VA",
    "sg:tags":[
        "physician",
        "psychologist",
        "neurology",
        "surgeons",
        "surgeon"
    ],
    "wof:name":"Carilion Sleep Ctr",
    "wof:placetype":"venue"
},
  "geometry": {"coordinates":[-79.941327,37.26407],"type":"Point"}
}