{
  "type": "Feature",
  "properties": {
    "iso:country":"US",
    "sg:address":"412 Lynn St",
    "sg:city":"Danville",
    "sg:classifiers":[
        {
            "category":"Retail",
            "subcategory":"Repair Shop",
            "type":"Services"
        }
    ],
    "sg:phone":"+1 434 799 3979",
    "sg:postcode":"24541",
    "sg:province":"VA",
    "sg:tags":[
        "refinishing",
        "furniture"
    ],
    "wof:name":"A-1 Furniture Refinishing",
    "wof:placetype":"venue"
},
  "geometry": {"coordinates":[-79.38896,36.585226],"type":"Point"}
}