{
  "type": "Feature",
  "properties": {
    "iso:country":"US",
    "sg:address":"700 S Main St",
    "sg:city":"Emporia",
    "sg:classifiers":[
        {
            "category":"Taxi",
            "type":"Transportation"
        }
    ],
    "sg:phone":"+1 434 348 9321",
    "sg:postcode":"23847",
    "sg:province":"VA",
    "sg:tags":[
        "taxicab"
    ],
    "wof:name":"Southside Taxi",
    "wof:placetype":"venue"
},
  "geometry": {"coordinates":[-77.547674,36.678199],"type":"Point"}
}