{
  "type": "Feature",
  "properties": {
    "addr:full":"16 Church Ave SW Roanoke VA 24011",
    "addr:housenumber":"16",
    "addr:postcode":"24011",
    "addr:street":"Church Ave Sw",
    "iso:country":"US",
    "sg:address":"16 Church Ave SW",
    "sg:city":"Roanoke",
    "sg:classifiers":[
        {
            "category":"Health Services",
            "subcategory":"Chiropractor",
            "type":"Services"
        }
    ],
    "sg:phone":"+1 540 344 1055",
    "sg:postcode":"24011",
    "sg:province":"VA",
    "sg:tags":[
        "personal"
    ],
    "wof:name":"Oasis Chiropractic & Massage",
    "wof:placetype":"venue"
},
  "geometry": {"coordinates":[-79.942215,37.270467],"type":"Point"}
}