{
  "type": "Feature",
  "properties": {
    "addr:full":"8217 Hidden Valley Rd Abingdon VA 24210",
    "addr:housenumber":"8217",
    "addr:postcode":"24210",
    "addr:street":"Hidden Valley Rd",
    "iso:country":"US",
    "sg:address":"8217 Hidden Valley Rd",
    "sg:city":"Abingdon",
    "sg:classifiers":[
        {
            "category":"Autos & Motor Vehicles",
            "subcategory":"Automobile Sales",
            "type":"Retail Goods"
        }
    ],
    "sg:phone":"+1 276 628 8352",
    "sg:postcode":"24210",
    "sg:province":"VA",
    "sg:tags":[
        "car",
        "used",
        "dealer"
    ],
    "wof:name":"Bill's Body Shop & Auto Sales",
    "wof:placetype":"venue"
},
  "geometry": {"coordinates":[-82.09544,36.825435],"type":"Point"}
}