{
  "type": "Feature",
  "properties": {
    "iso:country":"US",
    "sg:address":"2203 Arlington Chase Rd",
    "sg:city":"Cape Charles",
    "sg:classifiers":[
        {
            "category":"Real Estate",
            "subcategory":"Architect",
            "type":"Services"
        }
    ],
    "sg:phone":"+1 757 331 2919",
    "sg:postcode":"23310",
    "sg:province":"VA",
    "wof:name":"Robert M Trower",
    "wof:placetype":"venue"
},
  "geometry": {"coordinates":[-76.00271499999999,37.227421],"type":"Point"}
}