{
  "type": "Feature",
  "properties": {
    "iso:country":"US",
    "sg:address":"28132 Gregory Rd",
    "sg:city":"Ruther Glen",
    "sg:classifiers":[
        {
            "category":"Autos & Motor Vehicles",
            "subcategory":"Auto Supplies",
            "type":"Retail Goods"
        }
    ],
    "sg:phone":"+1 804 994 9123",
    "sg:postcode":"22546",
    "sg:province":"VA",
    "wof:name":"Lone Star Trailer & Hitch",
    "wof:placetype":"venue"
},
  "geometry": {"coordinates":[-77.36707800000001,37.876879],"type":"Point"}
}