{
  "type": "Feature",
  "properties": {
    "addr:full":"3521 Ellwood Ave Richmond VA 23221",
    "addr:housenumber":"3521",
    "addr:postcode":"23221",
    "addr:street":"Ellwood Ave",
    "iso:country":"US",
    "sg:address":"3521 Ellwood Ave",
    "sg:city":"Richmond",
    "sg:classifiers":[
        {
            "category":"Personal",
            "type":"Services"
        }
    ],
    "sg:phone":"+1 804 358 4141",
    "sg:postcode":"23221",
    "sg:province":"VA",
    "sg:tags":[
        "shop",
        "beauty"
    ],
    "wof:name":"Salon Haley",
    "wof:placetype":"venue"
},
  "geometry": {"coordinates":[-77.48784000000001,37.55694],"type":"Point"}
}