{
  "type": "Feature",
  "properties": {
    "addr:full":"201 E Main St Charlottesville VA 22902",
    "addr:housenumber":"201",
    "addr:postcode":"22902",
    "addr:street":"E Main St",
    "iso:country":"US",
    "sg:address":"201 E Main St",
    "sg:city":"Charlottesville",
    "sg:classifiers":[
        {
            "category":"Food & Beverages",
            "subcategory":"Specialty",
            "type":"Retail Goods"
        }
    ],
    "sg:phone":"+1 434 984 2665",
    "sg:postcode":"22902",
    "sg:province":"VA",
    "sg:tags":[
        "medical"
    ],
    "wof:name":"Sunrise Herb Shoppe",
    "wof:placetype":"venue"
},
  "geometry": {"coordinates":[-78.48003,38.030254],"type":"Point"}
}