{
  "type": "Feature",
  "properties": {
    "addr:full":"170 Rugby Rd Charlottesville VA 22903",
    "addr:housenumber":"170",
    "addr:postcode":"22903",
    "addr:street":"Rugby Rd",
    "iso:country":"US",
    "sg:address":"170 Rugby Rd",
    "sg:city":"Charlottesville",
    "sg:classifiers":[
        {
            "category":"Education",
            "subcategory":"College",
            "type":"Public Place"
        }
    ],
    "sg:phone":"+1 434 924 5965",
    "sg:postcode":"22903",
    "sg:province":"VA",
    "wof:name":"VA Graduate Marine Science",
    "wof:placetype":"venue"
},
  "geometry": {"coordinates":[-78.50196699999999,38.039435],"type":"Point"}
}