{
  "type": "Feature",
  "properties": {
    "iso:country":"US",
    "sg:address":"3080 Airline Blvd",
    "sg:city":"Portsmouth",
    "sg:classifiers":[
        {
            "category":"Manufacturing",
            "subcategory":"Furniture",
            "type":"Manufacturing & Wholesale Goods"
        }
    ],
    "sg:phone":"+1 757 488 9126",
    "sg:postcode":"23701",
    "sg:province":"VA",
    "wof:name":"Unclaimed Freight Co",
    "wof:placetype":"venue"
},
  "geometry": {"coordinates":[-76.370237,36.808792],"type":"Point"}
}