{
  "type": "Feature",
  "properties": {
    "iso:country":"US",
    "sg:address":"6017 James D Hagood Hwy",
    "sg:city":"Scottsburg",
    "sg:classifiers":[
        {
            "category":"Utilities",
            "subcategory":"Mobile Phone",
            "type":"Services"
        }
    ],
    "sg:phone":"+1 434 454 6829",
    "sg:postcode":"24589",
    "sg:province":"VA",
    "sg:tags":[
        "telephone",
        "cellular"
    ],
    "wof:name":"Alltel Communications",
    "wof:placetype":"venue"
},
  "geometry": {"coordinates":[-78.828783,36.763221],"type":"Point"}
}