{
  "type": "Feature",
  "properties": {
    "addr:full":"2501 Manchester St Blacksburg VA 24060",
    "addr:housenumber":"2501",
    "addr:postcode":"24060",
    "addr:street":"Manchester St",
    "iso:country":"US",
    "sg:address":"2501 Manchester St",
    "sg:city":"Blacksburg",
    "sg:classifiers":[
        {
            "category":"Organizations",
            "subcategory":"Religious Organization",
            "type":"Services"
        }
    ],
    "sg:phone":"+1 540 552 0960",
    "sg:postcode":"24060",
    "sg:province":"VA",
    "wof:name":"Taylor Harold Wm Pastor",
    "wof:placetype":"venue"
},
  "geometry": {"coordinates":[-80.449867,37.218153],"type":"Point"}
}