{
  "type": "Feature",
  "properties": {
    "addr:full":"3418 Stoney Creek Rd Edinburg VA 22824",
    "addr:housenumber":"3418",
    "addr:postcode":"22824",
    "addr:street":"Stoney Creek Rd",
    "iso:country":"US",
    "sg:address":"3418 Stoney Creek Rd",
    "sg:city":"Edinburg",
    "sg:classifiers":[
        {
            "category":"Restaurant",
            "type":"Food & Drink"
        }
    ],
    "sg:phone":"+1 540 984 4022",
    "sg:postcode":"22824",
    "sg:province":"VA",
    "sg:tags":[
        "banquet",
        "rooms"
    ],
    "wof:name":"Stoney Creek Banquet Hall",
    "wof:placetype":"venue"
},
  "geometry": {"coordinates":[-78.627897,38.865268],"type":"Point"}
}