{
  "type": "Feature",
  "properties": {
    "addr:full":"305 Leeward Way Newport News VA 23601",
    "addr:housenumber":"305",
    "addr:postcode":"23601",
    "addr:street":"Leeward Way",
    "iso:country":"US",
    "sg:address":"305 Leeward Way",
    "sg:city":"Newport News",
    "sg:classifiers":[
        {
            "category":"Professional",
            "type":"Services"
        }
    ],
    "sg:phone":"+1 757 223 1746",
    "sg:postcode":"23601",
    "sg:province":"VA",
    "wof:name":"Albert W & Rosemary S Hall",
    "wof:placetype":"venue"
},
  "geometry": {"coordinates":[-76.45131000000001,37.094218],"type":"Point"}
}