{
  "type": "Feature",
  "properties": {
    "iso:country":"US",
    "sg:address":"719 Broad Bay Cove",
    "sg:city":"Newport News",
    "sg:classifiers":[
        {
            "category":"Professional",
            "subcategory":"Management & Consulting",
            "type":"Services"
        }
    ],
    "sg:phone":"+1 757 877 4771",
    "sg:postcode":"23602",
    "sg:province":"VA",
    "sg:tags":[
        "business"
    ],
    "wof:name":"Klein & Assoc",
    "wof:placetype":"venue"
},
  "geometry": {"coordinates":[-76.474199,37.11484],"type":"Point"}
}