{
  "type": "Feature",
  "properties": {
    "addr:full":"105 Wheely Cir Yorktown VA 23692",
    "addr:housenumber":"105",
    "addr:postcode":"23692",
    "addr:street":"Wheely Cir",
    "iso:country":"US",
    "sg:address":"105 Wheely Cir",
    "sg:city":"Yorktown",
    "sg:classifiers":[
        {
            "category":"Professional",
            "subcategory":"Employment Agencies",
            "type":"Services"
        }
    ],
    "sg:phone":"+1 757 898 9348",
    "sg:postcode":"23692",
    "sg:province":"VA",
    "sg:tags":[
        "help",
        "supply"
    ],
    "wof:name":"Sweet Dreams Vending",
    "wof:placetype":"venue"
},
  "geometry": {"coordinates":[-76.483177,37.176307],"type":"Point"}
}