{
  "type": "Feature",
  "properties": {
    "addr:full":"2713 Griffin Ave Richmond VA 23222",
    "addr:housenumber":"2713",
    "addr:postcode":"23222",
    "addr:street":"Griffin Ave",
    "iso:country":"US",
    "sg:address":"2713 Griffin Ave",
    "sg:city":"Richmond",
    "sg:classifiers":[
        {
            "category":"Professional",
            "subcategory":"Business Services",
            "type":"Services"
        }
    ],
    "sg:phone":"+1 804 321 9328",
    "sg:postcode":"23222",
    "sg:province":"VA",
    "wof:name":"Str Enterprises Inc",
    "wof:placetype":"venue"
},
  "geometry": {"coordinates":[-77.43761600000001,37.568533],"type":"Point"}
}