{
  "type": "Feature",
  "properties": {
    "iso:country":"US",
    "sg:address":"1961 Chain Bridge Rd",
    "sg:city":"Mc Lean",
    "sg:classifiers":[
        {
            "category":"Personal",
            "type":"Services"
        }
    ],
    "sg:phone":"+1 703 847 0066",
    "sg:postcode":"22102",
    "sg:province":"VA",
    "wof:name":"Smalls Formal Wear",
    "wof:placetype":"venue"
},
  "geometry": {"coordinates":[-77.226226,38.919716],"type":"Point"}
}