{
  "type": "Feature",
  "properties": {
    "addr:full":"14150 Bowling Green Rd Windsor VA 23487",
    "addr:housenumber":"14150",
    "addr:postcode":"23487",
    "addr:street":"Bowling Green Rd",
    "iso:country":"US",
    "sg:address":"14150 Bowling Green Rd",
    "sg:city":"Windsor",
    "sg:classifiers":[
        {
            "category":"Home & Garden",
            "subcategory":"Garden Supply",
            "type":"Retail Goods"
        }
    ],
    "sg:phone":"+1 757 357 6872",
    "sg:postcode":"23487",
    "sg:province":"VA",
    "sg:tags":[
        "fuel",
        "dealer"
    ],
    "wof:name":"James River Mulch and Fire WD",
    "wof:placetype":"venue"
},
  "geometry": {"coordinates":[-76.68732799999999,36.896725],"type":"Point"}
}