{
  "type": "Feature",
  "properties": {
    "iso:country":"US",
    "sg:address":"7904 Greenebrook Ct",
    "sg:city":"Fairfax Station",
    "sg:classifiers":[
        {
            "category":"Utilities",
            "subcategory":"Telephone",
            "type":"Services"
        }
    ],
    "sg:phone":"+1 703 690 2200",
    "sg:postcode":"22039",
    "sg:province":"VA",
    "sg:tags":[
        "communications",
        "computer",
        "related"
    ],
    "wof:name":"Augusto Cuzzi Assoc",
    "wof:placetype":"venue"
},
  "geometry": {"coordinates":[-77.273117,38.740267],"type":"Point"}
}