{
  "type": "Feature",
  "properties": {
    "iso:country":"US",
    "sg:address":"348 Barcelona Dr",
    "sg:city":"Chesapeake",
    "sg:classifiers":[
        {
            "category":"Retail",
            "subcategory":"Repair Shop",
            "type":"Services"
        }
    ],
    "sg:phone":"+1 757 410 1374",
    "sg:postcode":"23322",
    "sg:province":"VA",
    "sg:tags":[
        "dry",
        "equipment",
        "machinery",
        "related",
        "cleaning"
    ],
    "wof:name":"Tidewater Mechanical Svc Co",
    "wof:placetype":"venue"
},
  "geometry": {"coordinates":[-76.27722799999999,36.708971],"type":"Point"}
}