{
  "type": "Feature",
  "properties": {
    "iso:country":"US",
    "sg:address":"154 S Rosemont Rd",
    "sg:city":"Virginia Beach",
    "sg:classifiers":[
        {
            "category":"Home & Garden",
            "subcategory":"Household Appliances",
            "type":"Retail Goods"
        }
    ],
    "sg:phone":"+1 757 340 3520",
    "sg:postcode":"23452",
    "sg:province":"VA",
    "sg:tags":[
        "sales"
    ],
    "wof:name":"Maytag Home Appliance Center",
    "wof:placetype":"venue"
},
  "geometry": {"coordinates":[-76.09569500000001,36.835442],"type":"Point"}
}