{
  "type": "Feature",
  "properties": {
    "addr:full":"2069 W Main St Salem VA 24153",
    "addr:housenumber":"2069",
    "addr:postcode":"24153",
    "addr:street":"W Main St",
    "iso:country":"US",
    "sg:address":"2069 W Main St",
    "sg:city":"Salem",
    "sg:classifiers":[
        {
            "category":"Food & Beverages",
            "subcategory":"Groceries & Convenience Stores",
            "type":"Retail Goods"
        }
    ],
    "sg:phone":"+1 540 389 8615",
    "sg:postcode":"24153",
    "sg:province":"VA",
    "wof:name":"Eagle Discount Tobacco",
    "wof:placetype":"venue"
},
  "geometry": {"coordinates":[-80.095252,37.287683],"type":"Point"}
}