{
  "type": "Feature",
  "properties": {
    "iso:country":"US",
    "sg:address":"328 Summit Point Dr",
    "sg:city":"Front Royal",
    "sg:classifiers":[
        {
            "category":"Shopping",
            "subcategory":"Used Merchandise",
            "type":"Retail Goods"
        }
    ],
    "sg:phone":"+1 540 635 2757",
    "sg:postcode":"22630",
    "sg:province":"VA",
    "sg:tags":[
        "shop",
        "thrift"
    ],
    "wof:name":"Look 4 Less",
    "wof:placetype":"venue"
},
  "geometry": {"coordinates":[-78.135563,38.870982],"type":"Point"}
}