{
  "type": "Feature",
  "properties": {
    "addr:full":"1224 W Main St Charlottesville VA 22903",
    "addr:housenumber":"1224",
    "addr:postcode":"22903",
    "addr:street":"W Main St",
    "iso:country":"US",
    "sg:address":"1224 W Main St",
    "sg:city":"Charlottesville",
    "sg:classifiers":[
        {
            "category":"Social Services",
            "type":"Services"
        }
    ],
    "sg:phone":"+1 434 295 8514",
    "sg:postcode":"22903",
    "sg:province":"VA",
    "sg:tags":[
        "counseling"
    ],
    "wof:name":"Leonard Carter LPC",
    "wof:placetype":"venue"
},
  "geometry": {"coordinates":[-78.49701899999999,38.032976],"type":"Point"}
}