{
  "type": "Feature",
  "properties": {
    "addr:full":"8630 Walcott Ct Manassas VA 20111",
    "addr:postcode":"8630;20111",
    "addr:street":"Walcott Ct",
    "iso:country":"US",
    "sg:address":"8630 Walcott Ct",
    "sg:city":"Manassas",
    "sg:classifiers":[
        {
            "category":"Professional",
            "subcategory":"Art Services",
            "type":"Services"
        }
    ],
    "sg:phone":"+1 703 392 9971",
    "sg:postcode":"20111",
    "sg:province":"VA",
    "sg:tags":[
        "production",
        "film"
    ],
    "wof:name":"Rosebiani Jano",
    "wof:placetype":"venue"
},
  "geometry": {"coordinates":[-77.45698,38.778029],"type":"Point"}
}