{
  "type": "Feature",
  "properties": {
    "iso:country":"US",
    "sg:address":"5850 Oak Grove Pl",
    "sg:city":"Dublin",
    "sg:classifiers":[
        {
            "category":"Organizations",
            "subcategory":"Religious Organization",
            "type":"Services"
        }
    ],
    "sg:phone":"+1 540 674 4131",
    "sg:postcode":"24084",
    "sg:province":"VA",
    "sg:tags":[
        "church"
    ],
    "sg:website":"www.appconf.org",
    "wof:name":"Appalachian Conference Church",
    "wof:placetype":"venue"
},
  "geometry": {"coordinates":[-80.672831,37.114297],"type":"Point"}
}