{
  "type": "Feature",
  "properties": {
    "iso:country":"US",
    "sg:address":"880 N Military Hwy",
    "sg:city":"Norfolk",
    "sg:classifiers":[
        {
            "category":"Shopping",
            "subcategory":"Clothing, Apparel, & Fashions",
            "type":"Retail Goods"
        }
    ],
    "sg:phone":"+1 757 466 8656",
    "sg:postcode":"23502",
    "sg:province":"VA",
    "wof:name":"Ashley Store",
    "wof:placetype":"venue"
},
  "geometry": {"coordinates":[-76.209799,36.851842],"type":"Point"}
}