{
  "type": "Feature",
  "properties": {
    "iso:country":"US",
    "sg:address":"8156 Woodland Ct",
    "sg:city":"Dunn Loring",
    "sg:classifiers":[
        {
            "category":"Retail",
            "subcategory":"Repair Shop",
            "type":"Services"
        }
    ],
    "sg:phone":"+1 703 527 9057",
    "sg:postcode":"22027",
    "sg:province":"VA",
    "wof:name":"Sonshine Cleaning Service",
    "wof:placetype":"venue"
},
  "geometry": {"coordinates":[-77.227158,38.892299],"type":"Point"}
}