{
  "type": "Feature",
  "properties": {
    "addr:full":"64 S Airport Dr Highland Springs VA 23075",
    "addr:housenumber":"64",
    "addr:postcode":"23075",
    "addr:street":"S Airport Dr",
    "iso:country":"US",
    "sg:address":"64 S Airport Dr",
    "sg:city":"Highland Springs",
    "sg:classifiers":[
        {
            "category":"Retail",
            "subcategory":"Laundry & Dry Cleaning",
            "type":"Services"
        }
    ],
    "sg:phone":"+1 804 737 7504",
    "sg:postcode":"23075",
    "sg:province":"VA",
    "sg:tags":[
        "drycleaning",
        "plant"
    ],
    "wof:name":"Spring Cleaner",
    "wof:placetype":"venue"
},
  "geometry": {"coordinates":[-77.319858,37.537468],"type":"Point"}
}