{
  "type": "Feature",
  "properties": {
    "addr:full":"128 S Main St Stuart VA 24171",
    "addr:housenumber":"128",
    "addr:postcode":"24171",
    "addr:street":"S Main St",
    "iso:country":"US",
    "sg:address":"128 S Main St",
    "sg:city":"Stuart",
    "sg:classifiers":[
        {
            "category":"Personal",
            "type":"Services"
        }
    ],
    "sg:phone":"+1 276 694 5566",
    "sg:postcode":"24171",
    "sg:province":"VA",
    "sg:tags":[
        "program",
        "physical",
        "exercise",
        "fitness"
    ],
    "wof:name":"Nautilus & Fitness",
    "wof:placetype":"venue"
},
  "geometry": {"coordinates":[-80.269842,36.638044],"type":"Point"}
}