{
  "type": "Feature",
  "properties": {
    "addr:full":"16 Carpenter Ln Harrisonburg VA 22801",
    "addr:housenumber":"16",
    "addr:postcode":"22801",
    "addr:street":"Carpenter Ln",
    "iso:country":"US",
    "sg:address":"16 Carpenter Ln",
    "sg:city":"Harrisonburg",
    "sg:classifiers":[
        {
            "category":"Autos & Motor Vehicles",
            "subcategory":"Automobile Sales",
            "type":"Retail Goods"
        }
    ],
    "sg:phone":"+1 540 433 1334",
    "sg:postcode":"22801",
    "sg:province":"VA",
    "sg:tags":[
        "car",
        "dealer"
    ],
    "wof:name":"Valley View Motors",
    "wof:placetype":"venue"
},
  "geometry": {"coordinates":[-78.91623800000001,38.393866],"type":"Point"}
}