{
  "type": "Feature",
  "properties": {
    "iso:country":"US",
    "sg:address":"2810 Belle Ave NE",
    "sg:city":"Roanoke",
    "sg:classifiers":[
        {
            "category":"Manufacturing",
            "subcategory":"Leather Goods",
            "type":"Manufacturing & Wholesale Goods"
        }
    ],
    "sg:phone":"+1 540 345 7267",
    "sg:postcode":"24012",
    "sg:province":"VA",
    "sg:tags":[
        "saddlery",
        "harness"
    ],
    "wof:name":"G & D Mfg",
    "wof:placetype":"venue"
},
  "geometry": {"coordinates":[-79.895309,37.291686],"type":"Point"}
}