{
  "type": "Feature",
  "properties": {
    "iso:country":"US",
    "sg:address":"4640 13th St N",
    "sg:city":"Arlington",
    "sg:classifiers":[
        {
            "category":"Utilities",
            "type":"Services"
        }
    ],
    "sg:phone":"+1 703 528 6445",
    "sg:postcode":"22207",
    "sg:province":"VA",
    "sg:tags":[
        "energy",
        "company",
        "renewable"
    ],
    "wof:name":"Verdant Power LLC",
    "wof:placetype":"venue"
},
  "geometry": {"coordinates":[-77.119039,38.886623],"type":"Point"}
}