{
  "type": "Feature",
  "properties": {
    "addr:full":"183A Keith St Warrenton VA 20186",
    "addr:housenumber":"183a",
    "addr:postcode":"20186",
    "addr:street":"Keith St",
    "iso:country":"US",
    "sg:address":"183A Keith St",
    "sg:city":"Warrenton",
    "sg:classifiers":[
        {
            "category":"Banks & Credit Unions",
            "subcategory":"Investment Brokerage",
            "type":"Services"
        }
    ],
    "sg:phone":"+1 540 351 1717",
    "sg:postcode":"20186",
    "sg:province":"VA",
    "sg:tags":[
        "investing"
    ],
    "wof:name":"Burleson Jon L CPA",
    "wof:placetype":"venue"
},
  "geometry": {"coordinates":[-77.800291,38.710739],"type":"Point"}
}