{
  "type": "Feature",
  "properties": {
    "iso:country":"US",
    "sg:address":"8548 McGrath Rd",
    "sg:city":"Manassas",
    "sg:classifiers":[
        {
            "category":"Building & Trades",
            "subcategory":"Equipment Rental",
            "type":"Services"
        }
    ],
    "sg:phone":"+1 703 369 1082",
    "sg:postcode":"20112",
    "sg:province":"VA",
    "wof:name":"Holmarc Corp",
    "wof:placetype":"venue"
},
  "geometry": {"coordinates":[-77.457399,38.70186],"type":"Point"}
}