{
  "type": "Feature",
  "properties": {
    "addr:full":"2845 N Armistead Ave Hampton VA 23666",
    "addr:housenumber":"2845",
    "addr:postcode":"23666",
    "addr:street":"N Armistead Ave",
    "iso:country":"US",
    "sg:address":"2845 N Armistead Ave",
    "sg:city":"Hampton",
    "sg:classifiers":[
        {
            "category":"Professional",
            "subcategory":"Advertising",
            "type":"Services"
        }
    ],
    "sg:phone":"+1 757 265 2148",
    "sg:postcode":"23666",
    "sg:province":"VA",
    "sg:tags":[
        "specialty"
    ],
    "wof:name":"Racetalklive.Com Inc",
    "wof:placetype":"venue"
},
  "geometry": {"coordinates":[-76.38449900000001,37.069099],"type":"Point"}
}