{
  "type": "Feature",
  "properties": {
    "addr:full":"6828 Commerce St Springfield VA 22150",
    "addr:housenumber":"6828",
    "addr:postcode":"22150",
    "addr:street":"Commerce St",
    "iso:country":"US",
    "sg:address":"6828 Commerce St",
    "sg:city":"Springfield",
    "sg:classifiers":[
        {
            "category":"Professional",
            "subcategory":"Lawyer & Legal Services",
            "type":"Services"
        }
    ],
    "sg:phone":"+1 703 448 9663",
    "sg:postcode":"22150",
    "sg:province":"VA",
    "sg:tags":[
        "attorney"
    ],
    "wof:name":"Elizabeth S York",
    "wof:placetype":"venue"
},
  "geometry": {"coordinates":[-77.184558,38.782348],"type":"Point"}
}