{
  "type": "Feature",
  "properties": {
    "addr:full":"7621 George Washington Memorial Hwy Yorktown VA 23692",
    "addr:housenumber":"7621",
    "addr:postcode":"23692",
    "addr:street":"George Washington Memorial Hwy",
    "iso:country":"US",
    "sg:address":"7621 George Washington Memorial Hwy",
    "sg:city":"Yorktown",
    "sg:classifiers":[
        {
            "category":"Insurance",
            "subcategory":"Insurance Agent",
            "type":"Services"
        }
    ],
    "sg:phone":"+1 757 872 4790",
    "sg:postcode":"23692",
    "sg:province":"VA",
    "wof:name":"Hendrix Insurance Agency",
    "wof:placetype":"venue"
},
  "geometry": {"coordinates":[-76.484675,37.184809],"type":"Point"}
}