{
  "type": "Feature",
  "properties": {
    "iso:country":"US",
    "sg:address":"4412 Ketcham Dr",
    "sg:city":"Chesterfield",
    "sg:classifiers":[
        {
            "category":"Building & Trades",
            "subcategory":"Construction",
            "type":"Services"
        }
    ],
    "sg:phone":"+1 804 675 2651",
    "sg:postcode":"23832",
    "sg:province":"VA",
    "sg:tags":[
        "hanging",
        "contractor"
    ],
    "wof:name":"Gonzalez Painting",
    "wof:placetype":"venue"
},
  "geometry": {"coordinates":[-77.528408,37.450807],"type":"Point"}
}