{
  "type": "Feature",
  "properties": {
    "addr:full":"7369 McWhorter Pl Annandale VA 22003",
    "addr:housenumber":"7369",
    "addr:postcode":"22003",
    "addr:street":"Mcwhorter Pl",
    "iso:country":"US",
    "sg:address":"7369 McWhorter Pl",
    "sg:city":"Annandale",
    "sg:classifiers":[
        {
            "category":"Social Services",
            "type":"Services"
        }
    ],
    "sg:phone":"+1 703 914 2673",
    "sg:postcode":"22003",
    "sg:province":"VA",
    "wof:name":"Camille Grosso",
    "wof:placetype":"venue"
},
  "geometry": {"coordinates":[-77.199123,38.828742],"type":"Point"}
}