{
  "type": "Feature",
  "properties": {
    "iso:country":"US",
    "sg:address":"33531 Chincoteague Rd",
    "sg:city":"Chincoteague",
    "sg:classifiers":[
        {
            "category":"Manufacturing",
            "subcategory":"Tools & Machinery",
            "type":"Manufacturing & Wholesale Goods"
        }
    ],
    "sg:phone":"+1 757 824 0590",
    "sg:postcode":"23337",
    "sg:province":"VA",
    "sg:tags":[
        "aeronautical",
        "system",
        "nautical"
    ],
    "wof:name":"Lockheed Martin",
    "wof:placetype":"venue"
},
  "geometry": {"coordinates":[-75.487149,37.92532],"type":"Point"}
}