{
  "type": "Feature",
  "properties": {
    "iso:country":"US",
    "sg:address":"3108 Cool Stream Dr",
    "sg:city":"Richmond",
    "sg:classifiers":[
        {
            "category":"Professional",
            "subcategory":"Computer Services",
            "type":"Services"
        }
    ],
    "sg:phone":"+1 410 276 4600",
    "sg:postcode":"23233",
    "sg:province":"VA",
    "sg:tags":[
        "design",
        "system"
    ],
    "wof:name":"Glows In The Dark Studios",
    "wof:placetype":"venue"
},
  "geometry": {"coordinates":[-77.61386899999999,37.640179],"type":"Point"}
}