{
  "type": "Feature",
  "properties": {
    "iso:country":"US",
    "sg:address":"12429 Eden Ln",
    "sg:city":"Woodbridge",
    "sg:classifiers":[
        {
            "category":"Professional",
            "subcategory":"Accounting & Tax Preparation",
            "type":"Services"
        }
    ],
    "sg:phone":"+1 703 385 1837",
    "sg:postcode":"22192",
    "sg:province":"VA",
    "wof:name":"A Perfect Balance of Virginia",
    "wof:placetype":"venue"
},
  "geometry": {"coordinates":[-77.333934,38.684364],"type":"Point"}
}