{
  "type": "Feature",
  "properties": {
    "addr:full":"410 N 4th Ave Hopewell VA 23860",
    "addr:housenumber":"410",
    "addr:postcode":"23860",
    "addr:street":"N 4Th Ave",
    "iso:country":"US",
    "sg:address":"410 N 4th Ave",
    "sg:city":"Hopewell",
    "sg:classifiers":[
        {
            "category":"Building & Trades",
            "subcategory":"Construction",
            "type":"Services"
        }
    ],
    "sg:phone":"+1 804 541 2228",
    "sg:postcode":"23860",
    "sg:province":"VA",
    "sg:tags":[
        "house"
    ],
    "wof:name":"Clore GI Gen Contr",
    "wof:placetype":"venue"
},
  "geometry": {"coordinates":[-77.291286,37.304886],"type":"Point"}
}