{
  "type": "Feature",
  "properties": {
    "addr:full":"2424 Number Ten Ln Chesapeake VA 23323",
    "addr:housenumber":"2424",
    "addr:postcode":"23323",
    "addr:street":"Number Ten Ln",
    "iso:country":"US",
    "sg:address":"2424 Number Ten Ln",
    "sg:city":"Chesapeake",
    "sg:classifiers":[
        {
            "category":"Building & Trades",
            "subcategory":"Construction",
            "type":"Services"
        }
    ],
    "sg:phone":"+1 757 424 1731",
    "sg:postcode":"23323",
    "sg:province":"VA",
    "sg:tags":[
        "house"
    ],
    "wof:name":"Perry Construction Inc",
    "wof:placetype":"venue"
},
  "geometry": {"coordinates":[-76.333652,36.696855],"type":"Point"}
}