{
  "type": "Feature",
  "properties": {
    "addr:full":"5501 Stanfield Rd Spotsylvania VA 22551",
    "addr:housenumber":"5501",
    "addr:postcode":"22551",
    "addr:street":"Stanfield Rd",
    "iso:country":"US",
    "sg:address":"5501 Stanfield Rd",
    "sg:city":"Spotsylvania",
    "sg:classifiers":[
        {
            "category":"Building & Trades",
            "subcategory":"Construction",
            "type":"Services"
        }
    ],
    "sg:phone":"+1 540 582 5501",
    "sg:postcode":"22551",
    "sg:province":"VA",
    "sg:tags":[
        "contractor"
    ],
    "wof:name":"S Hosey Fence Co",
    "wof:placetype":"venue"
},
  "geometry": {"coordinates":[-77.567046,38.105012],"type":"Point"}
}