{
  "type": "Feature",
  "properties": {
    "addr:full":"526 N Main St Bridgewater VA 22812",
    "addr:housenumber":"526",
    "addr:postcode":"22812",
    "addr:street":"N Main St",
    "iso:country":"US",
    "sg:address":"526 N Main St",
    "sg:city":"Bridgewater",
    "sg:classifiers":[
        {
            "category":"Autos & Motor Vehicles",
            "subcategory":"Automobile Sales",
            "type":"Retail Goods"
        }
    ],
    "sg:phone":"+1 540 828 6954",
    "sg:postcode":"22812",
    "sg:province":"VA",
    "sg:tags":[
        "used"
    ],
    "wof:name":"Rhodes Auto Sales",
    "wof:placetype":"venue"
},
  "geometry": {"coordinates":[-78.96762,38.389326],"type":"Point"}
}