{
  "type": "Feature",
  "properties": {
    "addr:full":"3900 Bradwater St Fairfax VA 22031",
    "addr:housenumber":"3900",
    "addr:postcode":"22031",
    "addr:street":"Bradwater St",
    "iso:country":"US",
    "sg:address":"3900 Bradwater St",
    "sg:city":"Fairfax",
    "sg:classifiers":[
        {
            "category":"Professional",
            "subcategory":"Business Services",
            "type":"Services"
        }
    ],
    "sg:phone":"+1 703 426 0723",
    "sg:postcode":"22031",
    "sg:province":"VA",
    "sg:tags":[
        "representation"
    ],
    "wof:name":"Castel Systems Inc",
    "wof:placetype":"venue"
},
  "geometry": {"coordinates":[-77.27798199999999,38.841974],"type":"Point"}
}