{
  "type": "Feature",
  "properties": {
    "addr:full":"7705 Goodview Rd Goodview VA 24095",
    "addr:housenumber":"7705",
    "addr:postcode":"24095",
    "addr:street":"Goodview Rd",
    "iso:country":"US",
    "sg:address":"7705 Goodview Rd",
    "sg:city":"Goodview",
    "sg:classifiers":[
        {
            "category":"Food & Beverages",
            "subcategory":"Groceries & Convenience Stores",
            "type":"Retail Goods"
        }
    ],
    "sg:phone":"+1 540 890 5319",
    "sg:postcode":"24095",
    "sg:province":"VA",
    "sg:tags":[
        "grocer"
    ],
    "wof:name":"Goodview Grocery",
    "wof:placetype":"venue"
},
  "geometry": {"coordinates":[-79.72186000000001,37.214328],"type":"Point"}
}