{
  "type": "Feature",
  "properties": {
    "addr:full":"6840 Anderson Mill Rd Chatham VA 24531",
    "addr:housenumber":"6840",
    "addr:postcode":"24531",
    "addr:street":"Anderson Mill Rd",
    "iso:country":"US",
    "sg:address":"6840 Anderson Mill Rd",
    "sg:city":"Chatham",
    "sg:classifiers":[
        {
            "category":"Building & Trades",
            "subcategory":"Landscaping Services",
            "type":"Services"
        }
    ],
    "sg:phone":"+1 434 432 3210",
    "sg:postcode":"24531",
    "sg:province":"VA",
    "wof:name":"Troys Lawn Care",
    "wof:placetype":"venue"
},
  "geometry": {"coordinates":[-79.50822100000001,36.881196],"type":"Point"}
}