{
  "type": "Feature",
  "properties": {
    "addr:full":"225 N Main St Hillsville VA 24343",
    "addr:housenumber":"225",
    "addr:postcode":"24343",
    "addr:street":"N Main St",
    "iso:country":"US",
    "sg:address":"225 N Main St",
    "sg:city":"Hillsville",
    "sg:classifiers":[
        {
            "category":"Shopping",
            "subcategory":"Used Merchandise",
            "type":"Retail Goods"
        },
        {
            "category":"Shopping",
            "subcategory":"Bicycles & Sporting Goods",
            "type":"Retail Goods"
        }
    ],
    "sg:phone":"+1 276 728 5241",
    "sg:postcode":"24343",
    "sg:province":"VA",
    "sg:tags":[
        "gun",
        "gunsmith"
    ],
    "wof:name":"Stagecoach Station Gun Shop",
    "wof:placetype":"venue"
},
  "geometry": {"coordinates":[-80.736043,36.764774],"type":"Point"}
}