{
  "type": "Feature",
  "properties": {
    "addr:full":"32 Bridge St S Martinsville VA 24112",
    "addr:housenumber":"32",
    "addr:postcode":"24112",
    "addr:street":"Bridge St S Martinsville",
    "iso:country":"US",
    "sg:address":"32 Bridge St S",
    "sg:city":"Martinsville",
    "sg:classifiers":[
        {
            "category":"Government",
            "subcategory":"Jail",
            "type":"Public Place"
        }
    ],
    "sg:phone":"+1 276 666 2304",
    "sg:postcode":"24112",
    "sg:province":"VA",
    "sg:tags":[
        "govt",
        "state",
        "institution"
    ],
    "wof:name":"Virginia Corrections Dept",
    "wof:placetype":"venue"
},
  "geometry": {"coordinates":[-79.87369700000001,36.689874],"type":"Point"}
}