{
  "type": "Feature",
  "properties": {
    "iso:country":"US",
    "sg:address":"619 E Constance Rd",
    "sg:city":"Suffolk",
    "sg:classifiers":[
        {
            "category":"Education",
            "subcategory":"Dance Studio",
            "type":"Public Place"
        },
        {
            "category":"Recreation",
            "type":"Entertainment"
        }
    ],
    "sg:phone":"+1 757 923 5150",
    "sg:postcode":"23434",
    "sg:province":"VA",
    "sg:tags":[
        "fitness",
        "instruction",
        "dancing",
        "physical",
        "facility"
    ],
    "sg:website":"www.tttgym.com",
    "wof:name":"Triple T Sports Center",
    "wof:placetype":"venue"
},
  "geometry": {"coordinates":[-76.564204,36.738573],"type":"Point"}
}