{
  "type": "Feature",
  "properties": {
    "addr:full":"4203 de Haven Dr Chantilly VA 20151",
    "addr:housenumber":"4203",
    "addr:postcode":"20151",
    "addr:street":"De Haven Dr",
    "iso:country":"US",
    "sg:address":"4203 de Haven Dr",
    "sg:city":"Chantilly",
    "sg:classifiers":[
        {
            "category":"Professional",
            "subcategory":"Computer Services",
            "type":"Services"
        }
    ],
    "sg:phone":"+1 703 577 5862",
    "sg:postcode":"20151",
    "sg:province":"VA",
    "sg:tags":[
        "information",
        "system"
    ],
    "wof:name":"On Call Gurus",
    "wof:placetype":"venue"
},
  "geometry": {"coordinates":[-77.42238500000001,38.881897],"type":"Point"}
}