{
  "type": "Feature",
  "properties": {
    "addr:full":"128 S Lynnhaven Rd Virginia Beach VA 23452",
    "addr:housenumber":"128",
    "addr:postcode":"23452",
    "addr:street":"S Lynnhaven Rd",
    "iso:country":"US",
    "sg:address":"128 S Lynnhaven Rd",
    "sg:city":"Virginia Beach",
    "sg:classifiers":[
        {
            "category":"Real Estate",
            "subcategory":"Developer",
            "type":"Services"
        }
    ],
    "sg:phone":"+1 757 340 8084",
    "sg:postcode":"23452",
    "sg:province":"VA",
    "wof:name":"O & R Inc",
    "wof:placetype":"venue"
},
  "geometry": {"coordinates":[-76.067108,36.838194],"type":"Point"}
}