{
  "type": "Feature",
  "properties": {
    "addr:full":"416 Stonewall St Franklin VA 23851",
    "addr:housenumber":"416",
    "addr:postcode":"23851",
    "addr:street":"Stonewall St",
    "iso:country":"US",
    "sg:address":"416 Stonewall St",
    "sg:city":"Franklin",
    "sg:classifiers":[
        {
            "category":"Organizations",
            "subcategory":"Religious Organization",
            "type":"Services"
        }
    ],
    "sg:phone":"+1 757 569 9808",
    "sg:postcode":"23851",
    "sg:province":"VA",
    "sg:tags":[
        "church"
    ],
    "wof:name":"New Mount Zion Baptist Church",
    "wof:placetype":"venue"
},
  "geometry": {"coordinates":[-76.932069,36.668642],"type":"Point"}
}