{
  "type": "Feature",
  "properties": {
    "addr:full":"394 E Midland Trl Lexington VA 24450",
    "addr:housenumber":"394",
    "addr:postcode":"24450",
    "addr:street":"E Midland Trl",
    "iso:country":"US",
    "sg:address":"394 E Midland Trl",
    "sg:city":"Lexington",
    "sg:classifiers":[
        {
            "category":"Retail",
            "subcategory":"Auto Repair",
            "type":"Services"
        }
    ],
    "sg:phone":"+1 540 464 4112",
    "sg:postcode":"24450",
    "sg:province":"VA",
    "sg:tags":[
        "body"
    ],
    "wof:name":"County Line Collision",
    "wof:placetype":"venue"
},
  "geometry": {"coordinates":[-79.43185200000001,37.773684],"type":"Point"}
}