{
  "type": "Feature",
  "properties": {
    "addr:full":"1343 Lee Hwy Bristol VA 24201",
    "addr:housenumber":"1343",
    "addr:postcode":"24201",
    "addr:street":"Lee Hwy",
    "iso:country":"US",
    "sg:address":"1343 Lee Hwy",
    "sg:city":"Bristol",
    "sg:classifiers":[
        {
            "category":"Food & Beverages",
            "subcategory":"Fruits & Vegetables",
            "type":"Retail Goods"
        }
    ],
    "sg:phone":"+1 276 466 6103",
    "sg:postcode":"24201",
    "sg:province":"VA",
    "sg:tags":[
        "produce"
    ],
    "wof:name":"J R S Produce",
    "wof:placetype":"venue"
},
  "geometry": {"coordinates":[-82.17356599999999,36.611504],"type":"Point"}
}