{
  "type": "Feature",
  "properties": {
    "iso:country":"US",
    "sg:address":"728 High St",
    "sg:city":"Portsmouth",
    "sg:classifiers":[
        {
            "category":"Building & Trades",
            "subcategory":"Construction",
            "type":"Services"
        }
    ],
    "sg:phone":"+1 757 399 6238",
    "sg:postcode":"23704",
    "sg:province":"VA",
    "sg:tags":[
        "general",
        "contractor"
    ],
    "wof:name":"Largo Construction Inc",
    "wof:placetype":"venue"
},
  "geometry": {"coordinates":[-76.30595700000001,36.83531],"type":"Point"}
}