{
  "type": "Feature",
  "properties": {
    "addr:full":"637 Pine Ave Waynesboro VA 22980",
    "addr:housenumber":"637",
    "addr:postcode":"22980",
    "addr:street":"Pine Ave",
    "iso:country":"US",
    "sg:address":"637 Pine Ave",
    "sg:city":"Waynesboro",
    "sg:classifiers":[
        {
            "category":"Real Estate",
            "subcategory":"Real Estate Agent",
            "type":"Services"
        }
    ],
    "sg:phone":"+1 540 942 7294",
    "sg:postcode":"22980",
    "sg:province":"VA",
    "sg:tags":[
        "appraisal"
    ],
    "wof:name":"Cross County Appraisal Inc",
    "wof:placetype":"venue"
},
  "geometry": {"coordinates":[-78.89841300000001,38.064084],"type":"Point"}
}