{
  "type": "Feature",
  "properties": {
    "iso:country":"US",
    "sg:address":"32 Meadville Dr",
    "sg:city":"Onancock",
    "sg:classifiers":[
        {
            "category":"Wholesale",
            "subcategory":"Plants",
            "type":"Manufacturing & Wholesale Goods"
        }
    ],
    "sg:phone":"+1 757 787 4410",
    "sg:postcode":"23417",
    "sg:province":"VA",
    "sg:tags":[
        "florist"
    ],
    "wof:name":"Chelsea Farms Dried Flowers",
    "wof:placetype":"venue"
},
  "geometry": {"coordinates":[-75.753078,37.707225],"type":"Point"}
}