{
  "type": "Feature",
  "properties": {
    "iso:country":"US",
    "sg:address":"1635 N George Mason Dr",
    "sg:city":"Arlington",
    "sg:classifiers":[
        {
            "category":"Health Services",
            "subcategory":"Doctor",
            "type":"Services"
        }
    ],
    "sg:phone":"+1 703 528 0623",
    "sg:postcode":"22205",
    "sg:province":"VA",
    "sg:tags":[
        "podiatrist"
    ],
    "wof:name":"Rosenthal Kenneth Y DPM",
    "wof:placetype":"venue"
},
  "geometry": {"coordinates":[-77.128197,38.8881],"type":"Point"}
}