{
  "type": "Feature",
  "properties": {
    "iso:country":"US",
    "sg:address":"227 Starling Ave",
    "sg:city":"Martinsville",
    "sg:classifiers":[
        {
            "category":"Professional",
            "subcategory":"Lawyer & Legal Services",
            "type":"Services"
        }
    ],
    "sg:phone":"+1 276 632 2056",
    "sg:postcode":"24112",
    "sg:province":"VA",
    "sg:tags":[
        "attorney"
    ],
    "wof:name":"John W Swezey Law Office",
    "wof:placetype":"venue"
},
  "geometry": {"coordinates":[-79.865942,36.684941],"type":"Point"}
}