{
  "type": "Feature",
  "properties": {
    "iso:country":"US",
    "sg:address":"5657 Columbia Pike Ste 200",
    "sg:city":"Falls Church",
    "sg:classifiers":[
        {
            "category":"Professional",
            "subcategory":"Lawyer & Legal Services",
            "type":"Services"
        }
    ],
    "sg:phone":"+1 703 379 9446",
    "sg:postcode":"22041",
    "sg:province":"VA",
    "wof:name":"Salvado & Salvado P C",
    "wof:placetype":"venue"
},
  "geometry": {"coordinates":[-77.12449599999999,38.852501],"type":"Point"}
}