{
  "type": "Feature",
  "properties": {
    "iso:country":"US",
    "sg:address":"8300 Old Courthouse Rd Ste 220",
    "sg:city":"Vienna",
    "sg:classifiers":[
        {
            "category":"Health Services",
            "subcategory":"Doctor",
            "type":"Services"
        }
    ],
    "sg:phone":"+1 571 297 4730",
    "sg:postcode":"22182",
    "sg:province":"VA",
    "sg:tags":[
        "medicine",
        "sport"
    ],
    "wof:name":"The Tao of Wellness",
    "wof:placetype":"venue"
},
  "geometry": {"coordinates":[-77.23124900000001,38.914222],"type":"Point"}
}