{
  "type": "Feature",
  "properties": {
    "addr:full":"1120 N Vermont St Arlington VA 22201",
    "addr:housenumber":"1120",
    "addr:postcode":"22201",
    "addr:street":"N Vermont St",
    "iso:country":"US",
    "sg:address":"1120 N Vermont St",
    "sg:city":"Arlington",
    "sg:classifiers":[
        {
            "category":"Museum",
            "type":"Entertainment"
        }
    ],
    "sg:phone":"+1 703 557 0613",
    "sg:postcode":"22201",
    "sg:province":"VA",
    "sg:website":"http://www.nps.gov",
    "wof:name":"Us Robert E Lee Memorial",
    "wof:placetype":"venue"
},
  "geometry": {"coordinates":[-77.11494,38.883691],"type":"Point"}
}