{
  "type": "Feature",
  "properties": {
    "iso:country":"US",
    "sg:address":"40 Ballard Rd",
    "sg:city":"Newport News",
    "sg:classifiers":[
        {
            "category":"Organizations",
            "subcategory":"Religious Organization",
            "type":"Services"
        }
    ],
    "sg:phone":"+1 757 596 9682",
    "sg:postcode":"23601",
    "sg:province":"VA",
    "wof:name":"Bethany Gospel Chapel",
    "wof:placetype":"venue"
},
  "geometry": {"coordinates":[-76.463545,37.065139],"type":"Point"}
}