{
  "type": "Feature",
  "properties": {
    "addr:full":"8701 Hull Street Rd Richmond VA 23236",
    "addr:housenumber":"8701",
    "addr:postcode":"23236",
    "addr:street":"Hull Street Rd",
    "iso:country":"US",
    "sg:address":"8701 Hull Street Rd",
    "sg:city":"Richmond",
    "sg:classifiers":[
        {
            "category":"Building & Trades",
            "subcategory":"Construction",
            "type":"Services"
        }
    ],
    "sg:phone":"+1 804 675 1112",
    "sg:postcode":"23236",
    "sg:province":"VA",
    "sg:tags":[
        "excavating",
        "contractor"
    ],
    "wof:name":"Gleghorn Excavating Inc",
    "wof:placetype":"venue"
},
  "geometry": {"coordinates":[-77.559631,37.451854],"type":"Point"}
}