{
  "type": "Feature",
  "properties": {
    "addr:full":"8327 Sudley Rd Manassas VA 20109",
    "addr:housenumber":"8327",
    "addr:postcode":"20109",
    "addr:street":"Sudley Rd",
    "iso:country":"US",
    "sg:address":"8327 Sudley Rd",
    "sg:city":"Manassas",
    "sg:classifiers":[
        {
            "category":"Home & Garden",
            "subcategory":"Home Furnishings",
            "type":"Retail Goods"
        }
    ],
    "sg:phone":"+1 703 361 9650",
    "sg:postcode":"20109",
    "sg:province":"VA",
    "sg:tags":[
        "venetian",
        "blind"
    ],
    "wof:name":"Next Day Blinds",
    "wof:placetype":"venue"
},
  "geometry": {"coordinates":[-77.5013,38.774291],"type":"Point"}
}