{
  "type": "Feature",
  "properties": {
    "addr:full":"2460 Rivermont Ave Lynchburg VA 24503",
    "addr:housenumber":"2460",
    "addr:postcode":"24503",
    "addr:street":"Rivermont Ave",
    "iso:country":"US",
    "sg:address":"2460 Rivermont Ave",
    "sg:city":"Lynchburg",
    "sg:classifiers":[
        {
            "category":"Arts & Performance",
            "subcategory":"Theater",
            "type":"Entertainment"
        }
    ],
    "sg:phone":"+1 434 845 6540",
    "sg:postcode":"24503",
    "sg:province":"VA",
    "sg:tags":[
        "band",
        "orchestra"
    ],
    "wof:name":"Olde Stuff Band",
    "wof:placetype":"venue"
},
  "geometry": {"coordinates":[-79.16916000000001,37.435399],"type":"Point"}
}