{
  "type": "Feature",
  "properties": {
    "iso:country":"US",
    "sg:address":"10700 Beach Mill Rd",
    "sg:city":"Great Falls",
    "sg:classifiers":[
        {
            "category":"Professional",
            "type":"Services"
        }
    ],
    "sg:phone":"+1 703 450 5373",
    "sg:postcode":"22066",
    "sg:province":"VA",
    "wof:name":"Simmons & Simmons LLC",
    "wof:placetype":"venue"
},
  "geometry": {"coordinates":[-77.317233,39.029924],"type":"Point"}
}