{
  "type": "Feature",
  "properties": {
    "iso:country":"US",
    "sg:address":"208 Golden Oak Ct",
    "sg:city":"Virginia Beach",
    "sg:classifiers":[
        {
            "category":"Real Estate",
            "subcategory":"Real Estate Services",
            "type":"Services"
        }
    ],
    "sg:phone":"+1 757 498 8999",
    "sg:postcode":"23452",
    "sg:province":"VA",
    "sg:tags":[
        "company",
        "title"
    ],
    "wof:name":"Tidewater Settlement Svc",
    "wof:placetype":"venue"
},
  "geometry": {"coordinates":[-76.070801,36.832963],"type":"Point"}
}