{
  "type": "Feature",
  "properties": {
    "addr:full":"1160 Millwood Pike Winchester VA 22602",
    "addr:housenumber":"1160",
    "addr:postcode":"22602",
    "addr:street":"Millwood Pike",
    "iso:country":"US",
    "sg:address":"1160 Millwood Pike",
    "sg:city":"Winchester",
    "sg:classifiers":[
        {
            "category":"Autos & Motor Vehicles",
            "subcategory":"Motorcycle Sales",
            "type":"Retail Goods"
        }
    ],
    "sg:phone":"+1 540 662 4468",
    "sg:postcode":"22602",
    "sg:province":"VA",
    "sg:tags":[
        "scooter",
        "parts",
        "accessory"
    ],
    "sg:website":"www.hdwinchester.com",
    "wof:name":"Winchester Harley Davidson",
    "wof:placetype":"venue"
},
  "geometry": {"coordinates":[-78.149,39.158446],"type":"Point"}
}