{
  "type": "Feature",
  "properties": {
    "addr:full":"7611 Somerset Crossing Dr Gainesville VA 20156",
    "addr:housenumber":"7611",
    "addr:postcode":"20156",
    "addr:street":"Somerset Crossing Dr",
    "iso:country":"US",
    "sg:address":"7611 Somerset Crossing Dr",
    "sg:city":"Gainesville",
    "sg:classifiers":[
        {
            "category":"Restaurant",
            "type":"Food & Drink"
        }
    ],
    "sg:phone":"+1 703 753 2597",
    "sg:postcode":"20156",
    "sg:province":"VA",
    "sg:tags":[
        "seafood"
    ],
    "sg:website":"www.bonefishgrill.com",
    "wof:name":"Bonefish Grill",
    "wof:placetype":"venue"
},
  "geometry": {"coordinates":[-77.63069400000001,38.792528],"type":"Point"}
}