{
  "type": "Feature",
  "properties": {
    "iso:country":"US",
    "sg:address":"900 Commonwealth Pl",
    "sg:city":"Virginia Beach",
    "sg:classifiers":[
        {
            "category":"Building & Trades",
            "subcategory":"Electrical",
            "type":"Services"
        }
    ],
    "sg:phone":"+1 757 361 0207",
    "sg:postcode":"23464",
    "sg:province":"VA",
    "wof:name":"Priority Wire & Cable Inc",
    "wof:placetype":"venue"
},
  "geometry": {"coordinates":[-76.20476499999999,36.810553],"type":"Point"}
}