{
  "type": "Feature",
  "properties": {
    "iso:country":"US",
    "sg:address":"4713 Ewell Rd",
    "sg:city":"Fredericksburg",
    "sg:classifiers":[
        {
            "category":"Wholesale",
            "subcategory":"Auto Parts",
            "type":"Manufacturing & Wholesale Goods"
        }
    ],
    "sg:phone":"+1 540 373 6766",
    "sg:postcode":"22408",
    "sg:province":"VA",
    "sg:tags":[
        "equipment",
        "towing"
    ],
    "wof:name":"Ashby's Garage",
    "wof:placetype":"venue"
},
  "geometry": {"coordinates":[-77.502855,38.253243],"type":"Point"}
}