{
  "type": "Feature",
  "properties": {
    "addr:full":"11264 Circle Loop King George VA 22485",
    "addr:housenumber":"11264",
    "addr:postcode":"22485",
    "addr:street":"Circle Loop",
    "iso:country":"US",
    "sg:address":"11264 Circle Loop",
    "sg:city":"King George",
    "sg:classifiers":[
        {
            "category":"Autos & Motor Vehicles",
            "subcategory":"Automobile Sales",
            "type":"Retail Goods"
        }
    ],
    "sg:phone":"+1 540 775 3672",
    "sg:postcode":"22485",
    "sg:province":"VA",
    "sg:tags":[
        "used"
    ],
    "wof:name":"B&J Auto Sales",
    "wof:placetype":"venue"
},
  "geometry": {"coordinates":[-77.149788,38.261263],"type":"Point"}
}