{
  "type": "Feature",
  "properties": {
    "iso:country":"US",
    "sg:address":"5002 Airport Rd NW",
    "sg:city":"Roanoke",
    "sg:classifiers":[
        {
            "category":"Real Estate",
            "subcategory":"Real Estate Operator",
            "type":"Services"
        }
    ],
    "sg:phone":"+1 540 366 4270",
    "sg:postcode":"24012",
    "sg:province":"VA",
    "sg:tags":[
        "building",
        "nonresidential"
    ],
    "wof:name":"Crossroads Mall",
    "wof:placetype":"venue"
},
  "geometry": {"coordinates":[-79.955409,37.318029],"type":"Point"}
}