{
  "type": "Feature",
  "properties": {
    "addr:full":"3262 Gallows Rd Fairfax VA 22031",
    "addr:housenumber":"3262",
    "addr:postcode":"22031",
    "addr:street":"Gallows Rd",
    "iso:country":"US",
    "sg:address":"3262 Gallows Rd",
    "sg:city":"Fairfax",
    "sg:classifiers":[
        {
            "category":"Building & Trades",
            "subcategory":"Construction",
            "type":"Services"
        }
    ],
    "sg:phone":"+1 703 641 9851",
    "sg:postcode":"22031",
    "sg:province":"VA",
    "sg:tags":[
        "plastering",
        "contractor"
    ],
    "wof:name":"MDT Redecoration & Repairs",
    "wof:placetype":"venue"
},
  "geometry": {"coordinates":[-77.22664399999999,38.860363],"type":"Point"}
}