{
  "type": "Feature",
  "properties": {
    "addr:full":"3728 Cook Blvd Chesapeake VA 23323",
    "addr:housenumber":"3728",
    "addr:postcode":"23323",
    "addr:street":"Cook Blvd",
    "iso:country":"US",
    "sg:address":"3728 Cook Blvd",
    "sg:city":"Chesapeake",
    "sg:classifiers":[
        {
            "category":"Shopping",
            "subcategory":"Used Merchandise",
            "type":"Retail Goods"
        },
        {
            "category":"Shopping",
            "subcategory":"Gifts & Souvenirs",
            "type":"Retail Goods"
        }
    ],
    "sg:phone":"+1 757 487 1815",
    "sg:postcode":"23323",
    "sg:province":"VA",
    "sg:tags":[
        "shop",
        "historical",
        "reproduction"
    ],
    "wof:name":"Tuckahoe Trading Co LLC",
    "wof:placetype":"venue"
},
  "geometry": {"coordinates":[-76.381935,36.782943],"type":"Point"}
}