{
  "type": "Feature",
  "properties": {
    "iso:country":"US",
    "sg:address":"625 E Laburnum Ave",
    "sg:city":"Richmond",
    "sg:classifiers":[
        {
            "category":"Food & Beverages",
            "subcategory":"Groceries & Convenience Stores",
            "type":"Retail Goods"
        },
        {
            "category":"Banks & Credit Unions",
            "subcategory":"Bank",
            "type":"Services"
        }
    ],
    "sg:phone":"+1 804 329 1916",
    "sg:postcode":"23222",
    "sg:province":"VA",
    "sg:tags":[
        "loan",
        "broker"
    ],
    "wof:name":"The Market Place 7",
    "wof:placetype":"venue"
},
  "geometry": {"coordinates":[-77.423872,37.585589],"type":"Point"}
}