{
  "type": "Feature",
  "properties": {
    "addr:full":"2419 Royall Ave Richmond VA 23224",
    "addr:housenumber":"2419",
    "addr:postcode":"23224",
    "addr:street":"Royall Ave",
    "iso:country":"US",
    "sg:address":"2419 Royall Ave",
    "sg:city":"Richmond",
    "sg:classifiers":[
        {
            "category":"Recreation",
            "type":"Entertainment"
        }
    ],
    "sg:phone":"+1 804 232 6417",
    "sg:postcode":"23224",
    "sg:province":"VA",
    "wof:name":"Ruffin Road Community Center",
    "wof:placetype":"venue"
},
  "geometry": {"coordinates":[-77.443731,37.495267],"type":"Point"}
}