{
  "type": "Feature",
  "properties": {
    "iso:country":"US",
    "sg:address":"5188 Cleveland St",
    "sg:city":"Virginia Beach",
    "sg:classifiers":[
        {
            "category":"Home & Garden",
            "subcategory":"Building Materials",
            "type":"Retail Goods"
        }
    ],
    "sg:phone":"+1 757 490 0165",
    "sg:postcode":"23462",
    "sg:province":"VA",
    "sg:tags":[
        "windows"
    ],
    "wof:name":"J D Childress Mfg Co",
    "wof:placetype":"venue"
},
  "geometry": {"coordinates":[-76.15960699999999,36.842143],"type":"Point"}
}