{
  "type": "Feature",
  "properties": {
    "iso:country":"US",
    "sg:address":"4300 Portsmouth Blvd",
    "sg:city":"Chesapeake",
    "sg:classifiers":[
        {
            "category":"Shopping",
            "type":"Retail Goods"
        }
    ],
    "sg:phone":"+1 757 465 8836",
    "sg:postcode":"23321",
    "sg:province":"VA",
    "sg:tags":[
        "pet",
        "shop"
    ],
    "wof:name":"Scales & Tails Pet Store",
    "wof:placetype":"venue"
},
  "geometry": {"coordinates":[-76.419353,36.822191],"type":"Point"}
}