{
  "type": "Feature",
  "properties": {
    "addr:full":"11913 Main St Fredericksburg VA 22408",
    "addr:housenumber":"11913",
    "addr:postcode":"22408",
    "addr:street":"Main St",
    "iso:country":"US",
    "sg:address":"11913 Main St",
    "sg:city":"Fredericksburg",
    "sg:classifiers":[
        {
            "category":"Professional",
            "subcategory":"Computer Services",
            "type":"Services"
        }
    ],
    "sg:phone":"+1 540 368 8106",
    "sg:postcode":"22408",
    "sg:province":"VA",
    "sg:tags":[
        "related"
    ],
    "wof:name":"Jrm Technologies",
    "wof:placetype":"venue"
},
  "geometry": {"coordinates":[-77.44829799999999,38.278829],"type":"Point"}
}