{
  "type": "Feature",
  "properties": {
    "iso:country":"US",
    "sg:address":"109 Bridgewood Ct",
    "sg:city":"Stafford",
    "sg:classifiers":[
        {
            "category":"Social Services",
            "subcategory":"Adult Care",
            "type":"Services"
        }
    ],
    "sg:phone":"+1 703 864 2462",
    "sg:postcode":"22554",
    "sg:province":"VA",
    "sg:tags":[
        "residential"
    ],
    "wof:name":"Hides Home Inc",
    "wof:placetype":"venue"
},
  "geometry": {"coordinates":[-77.38735200000001,38.487859],"type":"Point"}
}