{
  "type": "Feature",
  "properties": {
    "addr:full":"5448 Blacksburg Rd Troutville VA 24175",
    "addr:housenumber":"5448",
    "addr:postcode":"24175",
    "addr:street":"Blacksburg Rd",
    "iso:country":"US",
    "sg:address":"5448 Blacksburg Rd",
    "sg:city":"Troutville",
    "sg:classifiers":[
        {
            "category":"Food & Beverages",
            "subcategory":"Meat & Fish",
            "type":"Retail Goods"
        },
        {
            "category":"Farming",
            "subcategory":"Farm",
            "type":"Manufacturing & Wholesale Goods"
        }
    ],
    "sg:phone":"+1 540 992 2297",
    "sg:postcode":"24175",
    "sg:province":"VA",
    "sg:tags":[
        "prepared",
        "general",
        "ham",
        "crop",
        "mfg"
    ],
    "wof:name":"Etzler John L Country Hams",
    "wof:placetype":"venue"
},
  "geometry": {"coordinates":[-79.953497,37.454433],"type":"Point"}
}