{
  "type": "Feature",
  "properties": {
    "addr:full":"2100 Richmond Rd Williamsburg VA 23185",
    "addr:housenumber":"2100",
    "addr:postcode":"23185",
    "addr:street":"Richmond Rd",
    "iso:country":"US",
    "sg:address":"2100 Richmond Rd",
    "sg:city":"Williamsburg",
    "sg:classifiers":[
        {
            "category":"Restaurant",
            "type":"Food & Drink"
        }
    ],
    "sg:menulink":"http://www.allmenus.com/va/williamsburg/54731-red-lobster/menu/",
    "sg:phone":"+1 757 221 8127",
    "sg:postcode":"23185",
    "sg:province":"VA",
    "sg:tags":[
        "seafood",
        "american"
    ],
    "wof:name":"Red Lobster",
    "wof:placetype":"venue"
},
  "geometry": {"coordinates":[-76.727654,37.299979],"type":"Point"}
}