{
  "type": "Feature",
  "properties": {
    "addr:full":"1104 Atlantic Dr Stafford VA 22554",
    "addr:housenumber":"1104",
    "addr:postcode":"22554",
    "addr:street":"Atlantic Dr",
    "iso:country":"US",
    "sg:address":"1104 Atlantic Dr",
    "sg:city":"Stafford",
    "sg:classifiers":[
        {
            "category":"Professional",
            "subcategory":"Management & Consulting",
            "type":"Services"
        }
    ],
    "sg:phone":"+1 540 659 7270",
    "sg:postcode":"22554",
    "sg:province":"VA",
    "sg:tags":[
        "business"
    ],
    "wof:name":"Ae Systems Inc",
    "wof:placetype":"venue"
},
  "geometry": {"coordinates":[-77.39079700000001,38.462228],"type":"Point"}
}