{
  "type": "Feature",
  "properties": {
    "addr:full":"1562 N Franklin St Christiansburg VA 24073",
    "addr:housenumber":"1562",
    "addr:postcode":"24073",
    "addr:street":"N Franklin St",
    "iso:country":"US",
    "sg:address":"1562 N Franklin St",
    "sg:city":"Christiansburg",
    "sg:classifiers":[
        {
            "category":"Banks & Credit Unions",
            "subcategory":"Bank",
            "type":"Services"
        }
    ],
    "sg:phone":"+1 540 381 1707",
    "sg:postcode":"24073",
    "sg:province":"VA",
    "sg:tags":[
        "mortgage"
    ],
    "wof:name":"Avco Financial",
    "wof:placetype":"venue"
},
  "geometry": {"coordinates":[-80.41482600000001,37.150661],"type":"Point"}
}