{
  "type": "Feature",
  "properties": {
    "addr:full":"13523 Bannacker Pl Herndon VA 20171",
    "addr:housenumber":"13523",
    "addr:postcode":"20171",
    "addr:street":"Bannacker Pl",
    "iso:country":"US",
    "sg:address":"13523 Bannacker Pl",
    "sg:city":"Herndon",
    "sg:classifiers":[
        {
            "category":"Banks & Credit Unions",
            "subcategory":"Bank",
            "type":"Services"
        }
    ],
    "sg:phone":"+1 703 561 0352",
    "sg:postcode":"20171",
    "sg:province":"VA",
    "sg:tags":[
        "foreign"
    ],
    "wof:name":"D&D International Inc",
    "wof:placetype":"venue"
},
  "geometry": {"coordinates":[-77.414472,38.947623],"type":"Point"}
}