{
  "type": "Feature",
  "properties": {
    "addr:full":"310 Central Rd Fredericksburg VA 22401",
    "addr:housenumber":"310",
    "addr:postcode":"22401",
    "addr:street":"Central Rd",
    "iso:country":"US",
    "sg:address":"310 Central Rd",
    "sg:city":"Fredericksburg",
    "sg:classifiers":[
        {
            "category":"Wholesale",
            "subcategory":"Electrical",
            "type":"Manufacturing & Wholesale Goods"
        }
    ],
    "sg:phone":"+1 540 899 8845",
    "sg:postcode":"22401",
    "sg:province":"VA",
    "sg:tags":[
        "television"
    ],
    "wof:name":"Edge Teck",
    "wof:placetype":"venue"
},
  "geometry": {"coordinates":[-77.47264800000001,38.286703],"type":"Point"}
}