{
  "type": "Feature",
  "properties": {
    "addr:full":"16495 15th St Dahlgren VA 22485",
    "addr:housenumber":"16495",
    "addr:postcode":"22485",
    "addr:street":"15Th St",
    "iso:country":"US",
    "sg:address":"16495 15th St",
    "sg:city":"Dahlgren",
    "sg:classifiers":[
        {
            "category":"Education",
            "subcategory":"School",
            "type":"Public Place"
        }
    ],
    "sg:phone":"+1 540 663 3322",
    "sg:postcode":"22485",
    "sg:province":"VA",
    "sg:website":"www.kgcs.k12.va.us",
    "wof:name":"Potomac Elementary School",
    "wof:placetype":"venue"
},
  "geometry": {"coordinates":[-77.052021,38.335352],"type":"Point"}
}