{
  "type": "Feature",
  "properties": {
    "iso:country":"US",
    "sg:address":"7750 Gunston Plz",
    "sg:city":"Lorton",
    "sg:classifiers":[
        {
            "category":"Retail",
            "subcategory":"Laundry & Dry Cleaning",
            "type":"Services"
        }
    ],
    "sg:phone":"+1 703 550 8255",
    "sg:postcode":"22079",
    "sg:province":"VA",
    "sg:tags":[
        "drycleaning",
        "plant"
    ],
    "wof:name":"Town Cleaners",
    "wof:placetype":"venue"
},
  "geometry": {"coordinates":[-77.20945,38.703732],"type":"Point"}
}