{
  "type": "Feature",
  "properties": {
    "addr:full":"3311 20th St N Arlington VA 22207",
    "addr:housenumber":"3311",
    "addr:postcode":"22207",
    "addr:street":"20Th St N",
    "iso:country":"US",
    "sg:address":"3311 20th St N",
    "sg:city":"Arlington",
    "sg:classifiers":[
        {
            "category":"Professional",
            "subcategory":"Lawyer & Legal Services",
            "type":"Services"
        }
    ],
    "sg:phone":"+1 571 527 0223",
    "sg:postcode":"22207",
    "sg:province":"VA",
    "sg:tags":[
        "plan"
    ],
    "wof:name":"Richardson Lloyd Esq",
    "wof:placetype":"venue"
},
  "geometry": {"coordinates":[-77.101311,38.894377],"type":"Point"}
}