{
  "type": "Feature",
  "properties": {
    "addr:full":"5130 Woodmere Dr Centreville VA 20120",
    "addr:housenumber":"5130",
    "addr:postcode":"20120",
    "addr:street":"Woodmere Dr",
    "iso:country":"US",
    "sg:address":"5130 Woodmere Dr",
    "sg:city":"Centreville",
    "sg:classifiers":[
        {
            "category":"Social Services",
            "subcategory":"Child Care",
            "type":"Services"
        }
    ],
    "sg:phone":"+1 703 818 3380",
    "sg:postcode":"20120",
    "sg:province":"VA",
    "sg:tags":[
        "day"
    ],
    "wof:name":"La Petite Academy 894",
    "wof:placetype":"venue"
},
  "geometry": {"coordinates":[-77.445874,38.866683],"type":"Point"}
}