{
  "type": "Feature",
  "properties": {
    "iso:country":"US",
    "sg:address":"2069 Mountain View Rd",
    "sg:city":"Vinton",
    "sg:classifiers":[
        {
            "category":"Organizations",
            "subcategory":"Religious Organization",
            "type":"Services"
        }
    ],
    "sg:phone":"+1 540 890 6560",
    "sg:postcode":"24179",
    "sg:province":"VA",
    "sg:tags":[
        "clergy"
    ],
    "wof:name":"Douglas Chubb",
    "wof:placetype":"venue"
},
  "geometry": {"coordinates":[-79.86109999999999,37.290436],"type":"Point"}
}