{
  "type": "Feature",
  "properties": {
    "addr:full":"101 W Washington St Galax VA 24333",
    "addr:housenumber":"101",
    "addr:postcode":"24333",
    "addr:street":"W Washington St",
    "iso:country":"US",
    "sg:address":"101 W Washington St",
    "sg:city":"Galax",
    "sg:classifiers":[
        {
            "category":"Organizations",
            "subcategory":"Religious Organization",
            "type":"Services"
        }
    ],
    "sg:phone":"+1 276 236 3031",
    "sg:postcode":"24333",
    "sg:province":"VA",
    "sg:tags":[
        "school"
    ],
    "wof:name":"New Hrvest Christn Worship Ctr",
    "wof:placetype":"venue"
},
  "geometry": {"coordinates":[-80.925521,36.663634],"type":"Point"}
}