{
  "type": "Feature",
  "properties": {
    "addr:full":"305 Tanyard Rd Rocky Mount VA 24151",
    "addr:housenumber":"305",
    "addr:postcode":"24151",
    "addr:street":"Tanyard Rd",
    "iso:country":"US",
    "sg:address":"305 Tanyard Rd",
    "sg:city":"Rocky Mount",
    "sg:classifiers":[
        {
            "category":"Government",
            "subcategory":"Office",
            "type":"Public Place"
        }
    ],
    "sg:phone":"+1 540 483 4957",
    "sg:postcode":"24151",
    "sg:province":"VA",
    "sg:tags":[
        "transportation"
    ],
    "wof:name":"Rocky Mount Customer Svc Ctr",
    "wof:placetype":"venue"
},
  "geometry": {"coordinates":[-79.882695,37.00155],"type":"Point"}
}