{
  "type": "Feature",
  "properties": {
    "addr:full":"104 Lee St Appomattox VA 24522",
    "addr:housenumber":"104",
    "addr:postcode":"24522",
    "addr:street":"Lee St",
    "iso:country":"US",
    "sg:address":"104 Lee St",
    "sg:city":"Appomattox",
    "sg:classifiers":[
        {
            "category":"Insurance",
            "subcategory":"Insurance Agent",
            "type":"Services"
        }
    ],
    "sg:phone":"+1 434 352 3516",
    "sg:postcode":"24522",
    "sg:province":"VA",
    "wof:name":"Lee Street Insurance",
    "wof:placetype":"venue"
},
  "geometry": {"coordinates":[-78.82832000000001,37.354705],"type":"Point"}
}