{
  "type": "Feature",
  "properties": {
    "addr:full":"21430 Timberlake Rd Lynchburg VA 24502",
    "addr:housenumber":"21430",
    "addr:postcode":"24502",
    "addr:street":"Timberlake Rd",
    "iso:country":"US",
    "sg:address":"21430 Timberlake Rd",
    "sg:city":"Lynchburg",
    "sg:classifiers":[
        {
            "category":"Manufacturing",
            "subcategory":"Printing",
            "type":"Manufacturing & Wholesale Goods"
        }
    ],
    "sg:phone":"+1 434 239 3072",
    "sg:postcode":"24502",
    "sg:province":"VA",
    "sg:tags":[
        "newspaper"
    ],
    "wof:name":"Bingo Bugle",
    "wof:placetype":"venue"
},
  "geometry": {"coordinates":[-79.246172,37.329343],"type":"Point"}
}