{
  "type": "Feature",
  "properties": {
    "iso:country":"US",
    "sg:address":"3129 Amador Dr",
    "sg:city":"Virginia Beach",
    "sg:classifiers":[
        {
            "category":"Building & Trades",
            "subcategory":"Construction",
            "type":"Services"
        }
    ],
    "sg:phone":"+1 757 493 9645",
    "sg:postcode":"23456",
    "sg:province":"VA",
    "sg:tags":[
        "home",
        "improvement"
    ],
    "sg:website":"www.atlanticbuild.com",
    "wof:name":"Atlantic Building & Remodeling",
    "wof:placetype":"venue"
},
  "geometry": {"coordinates":[-76.078233,36.737113],"type":"Point"}
}