{
  "type": "Feature",
  "properties": {
    "addr:full":"14472 Golden Oak Rd Centreville VA 20121",
    "addr:housenumber":"14472",
    "addr:postcode":"20121",
    "addr:street":"Golden Oak Rd",
    "iso:country":"US",
    "sg:address":"14472 Golden Oak Rd",
    "sg:city":"Centreville",
    "sg:classifiers":[
        {
            "category":"Education",
            "subcategory":"Special Training",
            "type":"Public Place"
        }
    ],
    "sg:phone":"+1 571 522 6588",
    "sg:postcode":"20121",
    "sg:province":"VA",
    "sg:tags":[
        "teaching",
        "educational"
    ],
    "wof:name":"Udai S Negi",
    "wof:placetype":"venue"
},
  "geometry": {"coordinates":[-77.445599,38.834167],"type":"Point"}
}