{
  "type": "Feature",
  "properties": {
    "addr:full":"3109 Hanover Ave Richmond VA 23221",
    "addr:housenumber":"3109",
    "addr:postcode":"23221",
    "addr:street":"Hanover Ave",
    "iso:country":"US",
    "sg:address":"3109 Hanover Ave",
    "sg:city":"Richmond",
    "sg:classifiers":[
        {
            "category":"Professional",
            "subcategory":"Art Services",
            "type":"Services"
        }
    ],
    "sg:phone":"+1 804 359 2925",
    "sg:postcode":"23221",
    "sg:province":"VA",
    "sg:tags":[
        "commercial",
        "design"
    ],
    "wof:name":"Govoni Jean & Partners Inc",
    "wof:placetype":"venue"
},
  "geometry": {"coordinates":[-77.47887900000001,37.557799],"type":"Point"}
}