{
  "type": "Feature",
  "properties": {
    "addr:full":"6308 Battle Rock Dr Clifton VA 20124",
    "addr:housenumber":"6308",
    "addr:postcode":"20124",
    "addr:street":"Battle Rock Dr",
    "iso:country":"US",
    "sg:address":"6308 Battle Rock Dr",
    "sg:city":"Clifton",
    "sg:classifiers":[
        {
            "category":"Wholesale",
            "subcategory":"Computers",
            "type":"Manufacturing & Wholesale Goods"
        }
    ],
    "sg:phone":"+1 703 815 9044",
    "sg:postcode":"20124",
    "sg:province":"VA",
    "wof:name":"HP",
    "wof:placetype":"venue"
},
  "geometry": {"coordinates":[-77.416854,38.816714],"type":"Point"}
}