{
  "type": "Feature",
  "properties": {
    "addr:full":"1024 King St Alexandria VA 22314",
    "addr:housenumber":"1024",
    "addr:postcode":"22314",
    "addr:street":"King St",
    "iso:country":"US",
    "sg:address":"1024 King St",
    "sg:city":"Alexandria",
    "sg:classifiers":[
        {
            "category":"Home & Garden",
            "subcategory":"Furniture",
            "type":"Retail Goods"
        }
    ],
    "sg:phone":"+1 703 838 0520",
    "sg:postcode":"22314",
    "sg:province":"VA",
    "wof:name":"Chinoiserie",
    "wof:placetype":"venue"
},
  "geometry": {"coordinates":[-77.051175,38.805516],"type":"Point"}
}