{
  "type": "Feature",
  "properties": {
    "iso:country":"US",
    "sg:address":"1612 Cutty Sark Rd",
    "sg:city":"Virginia Beach",
    "sg:classifiers":[
        {
            "category":"Health Services",
            "subcategory":"Doctor",
            "type":"Services"
        }
    ],
    "sg:phone":"+1 757 481 7964",
    "sg:postcode":"23454",
    "sg:province":"VA",
    "sg:tags":[
        "dentist"
    ],
    "wof:name":"David E Rowe DDS",
    "wof:placetype":"venue"
},
  "geometry": {"coordinates":[-76.03215299999999,36.887897],"type":"Point"}
}