{
  "type": "Feature",
  "properties": {
    "addr:full":"4660 Straightstone Rd Long Island VA 24557",
    "addr:housenumber":"4660",
    "addr:postcode":"24557",
    "addr:street":"Straightstone Rd",
    "iso:country":"US",
    "sg:address":"4660 Straightstone Rd",
    "sg:city":"Long Island",
    "sg:classifiers":[
        {
            "category":"Organizations",
            "subcategory":"Religious Organization",
            "type":"Services"
        }
    ],
    "sg:phone":"+1 434 335 5528",
    "sg:postcode":"24557",
    "sg:province":"VA",
    "wof:name":"Straightstone Baptist Church",
    "wof:placetype":"venue"
},
  "geometry": {"coordinates":[-79.14515299999999,37.018057],"type":"Point"}
}