{
  "type": "Feature",
  "properties": {
    "addr:full":"43050 Elk Pl Chantilly VA 20152",
    "addr:housenumber":"43050",
    "addr:postcode":"20152",
    "addr:street":"Elk Pl",
    "iso:country":"US",
    "sg:address":"43050 Elk Pl",
    "sg:city":"Chantilly",
    "sg:classifiers":[
        {
            "category":"Building & Trades",
            "subcategory":"Construction",
            "type":"Services"
        }
    ],
    "sg:phone":"+1 571 259 4240",
    "sg:postcode":"20152",
    "sg:province":"VA",
    "sg:tags":[
        "general",
        "contractor"
    ],
    "wof:name":"Gould Construction Co LLC",
    "wof:placetype":"venue"
},
  "geometry": {"coordinates":[-77.51131599999999,38.921942],"type":"Point"}
}