{
  "type": "Feature",
  "properties": {
    "addr:full":"5505 Robin Hood Rd Norfolk VA 23513",
    "addr:housenumber":"5505",
    "addr:postcode":"23513",
    "addr:street":"Robin Hood Rd",
    "iso:country":"US",
    "sg:address":"5505 Robin Hood Rd",
    "sg:city":"Norfolk",
    "sg:classifiers":[
        {
            "category":"Banks & Credit Unions",
            "subcategory":"Bank",
            "type":"Services"
        }
    ],
    "sg:phone":"+1 757 857 0077",
    "sg:postcode":"23513",
    "sg:province":"VA",
    "sg:tags":[
        "personal",
        "mortgage"
    ],
    "wof:name":"EquiCredit",
    "wof:placetype":"venue"
},
  "geometry": {"coordinates":[-76.216066,36.882242],"type":"Point"}
}