{
  "type": "Feature",
  "properties": {
    "addr:full":"10648 Lee Jackson Hwy Big Island VA 24526",
    "addr:housenumber":"10648",
    "addr:postcode":"24526",
    "addr:street":"Lee Jackson Hwy",
    "iso:country":"US",
    "sg:address":"10648 Lee Jackson Hwy",
    "sg:city":"Big Island",
    "sg:classifiers":[
        {
            "category":"Restaurant",
            "type":"Food & Drink"
        }
    ],
    "sg:phone":"+1 434 299 7118",
    "sg:postcode":"24526",
    "sg:province":"VA",
    "wof:name":"Islander Market & Deli",
    "wof:placetype":"venue"
},
  "geometry": {"coordinates":[-79.35939999999999,37.533043],"type":"Point"}
}