{
  "type": "Feature",
  "properties": {
    "iso:country":"US",
    "sg:address":"11703 Brocks Gap Rd",
    "sg:city":"Fulks Run",
    "sg:classifiers":[
        {
            "category":"Personal",
            "subcategory":"Beauty Salon",
            "type":"Services"
        }
    ],
    "sg:phone":"+1 540 896 9110",
    "sg:postcode":"22830",
    "sg:province":"VA",
    "sg:tags":[
        "shop"
    ],
    "wof:name":"Tammy's Cuts & Style",
    "wof:placetype":"venue"
},
  "geometry": {"coordinates":[-78.906792,38.660399],"type":"Point"}
}