{
  "type": "Feature",
  "properties": {
    "addr:full":"10066 Stonewall Jackson Rd Woodford VA 22580",
    "addr:housenumber":"10066",
    "addr:postcode":"22580",
    "addr:street":"Stonewall Jackson Rd",
    "iso:country":"US",
    "sg:address":"10066 Stonewall Jackson Rd",
    "sg:city":"Woodford",
    "sg:classifiers":[
        {
            "category":"Professional",
            "type":"Services"
        }
    ],
    "sg:phone":"+1 804 633 5201",
    "sg:postcode":"22580",
    "sg:province":"VA",
    "wof:name":"Earl L Smith",
    "wof:placetype":"venue"
},
  "geometry": {"coordinates":[-77.47049800000001,38.126859],"type":"Point"}
}