{
  "type": "Feature",
  "properties": {
    "addr:full":"7120 Richmond Hwy Alexandria VA 22306",
    "addr:housenumber":"7120",
    "addr:postcode":"22306",
    "addr:street":"Richmond Hwy",
    "iso:country":"US",
    "sg:address":"7120 Richmond Hwy",
    "sg:city":"Alexandria",
    "sg:classifiers":[
        {
            "category":"Organizations",
            "subcategory":"Community Association",
            "type":"Services"
        }
    ],
    "sg:phone":"+1 703 660 8734",
    "sg:postcode":"22306",
    "sg:province":"VA",
    "sg:tags":[
        "fraternal"
    ],
    "wof:name":"Elks Lodge",
    "wof:placetype":"venue"
},
  "geometry": {"coordinates":[-77.084187,38.761922],"type":"Point"}
}