{
  "type": "Feature",
  "properties": {
    "addr:full":"1749 Granby St NE Roanoke VA 24012",
    "addr:housenumber":"1749",
    "addr:postcode":"24012",
    "addr:street":"Granby St Ne",
    "iso:country":"US",
    "sg:address":"1749 Granby St NE",
    "sg:city":"Roanoke",
    "sg:classifiers":[
        {
            "category":"Retail",
            "subcategory":"Auto Repair",
            "type":"Services"
        }
    ],
    "sg:phone":"+1 540 982 3663",
    "sg:postcode":"24012",
    "sg:province":"VA",
    "sg:tags":[
        "wrecker"
    ],
    "wof:name":"Wood's Towing & Recovery",
    "wof:placetype":"venue"
},
  "geometry": {"coordinates":[-79.902728,37.303131],"type":"Point"}
}