{
  "type": "Feature",
  "properties": {
    "addr:full":"114 Production Dr Yorktown VA 23693",
    "addr:housenumber":"114",
    "addr:postcode":"23693",
    "addr:street":"Production Dr",
    "iso:country":"US",
    "sg:address":"114 Production Dr",
    "sg:city":"Yorktown",
    "sg:classifiers":[
        {
            "category":"Home & Garden",
            "subcategory":"Household Appliances",
            "type":"Retail Goods"
        }
    ],
    "sg:phone":"+1 757 342 5048",
    "sg:postcode":"23693",
    "sg:province":"VA",
    "sg:tags":[
        "air",
        "heating",
        "sales",
        "conditioning"
    ],
    "wof:name":"JD Triplett Co",
    "wof:placetype":"venue"
},
  "geometry": {"coordinates":[-76.458021,37.111159],"type":"Point"}
}