{
  "type": "Feature",
  "properties": {
    "addr:full":"302 N Oak St Falls Church VA 22046",
    "addr:housenumber":"302",
    "addr:postcode":"22046",
    "addr:street":"N Oak St",
    "iso:country":"US",
    "sg:address":"302 N Oak St",
    "sg:city":"Falls Church",
    "sg:classifiers":[
        {
            "category":"Professional",
            "subcategory":"Lawyer & Legal Services",
            "type":"Services"
        }
    ],
    "sg:phone":"+1 703 625 3029",
    "sg:postcode":"22046",
    "sg:province":"VA",
    "sg:tags":[
        "consulting",
        "management"
    ],
    "wof:name":"John A Macevoy Esq",
    "wof:placetype":"venue"
},
  "geometry": {"coordinates":[-77.177306,38.890665],"type":"Point"}
}