{
  "type": "Feature",
  "properties": {
    "iso:country":"US",
    "sg:address":"146 W Shirley Ave",
    "sg:city":"Warrenton",
    "sg:classifiers":[
        {
            "category":"Restaurant",
            "type":"Food & Drink"
        }
    ],
    "sg:menulink":"http://www.allmenus.com/va/center/238530-tippys-taco-house/menu/",
    "sg:phone":"+1 540 349 2330",
    "sg:postcode":"20186",
    "sg:province":"VA",
    "sg:tags":[
        "american",
        "mexican",
        "tex-mex"
    ],
    "wof:name":"Tippy's Taco House",
    "wof:placetype":"venue"
},
  "geometry": {"coordinates":[-77.803247,38.711164],"type":"Point"}
}