{
  "type": "Feature",
  "properties": {
    "addr:full":"3992 Newmans Neck Rd Heathsville VA 22473",
    "addr:housenumber":"3992",
    "addr:postcode":"22473",
    "addr:street":"Newmans Neck Rd",
    "iso:country":"US",
    "sg:address":"3992 Newmans Neck Rd",
    "sg:city":"Heathsville",
    "sg:classifiers":[
        {
            "category":"Building & Trades",
            "subcategory":"Construction",
            "type":"Services"
        }
    ],
    "sg:phone":"+1 804 580 6161",
    "sg:postcode":"22473",
    "sg:province":"VA",
    "sg:tags":[
        "maker",
        "cabinet"
    ],
    "wof:name":"Riverside Cabinets",
    "wof:placetype":"venue"
},
  "geometry": {"coordinates":[-76.406459,37.958409],"type":"Point"}
}