{
  "type": "Feature",
  "properties": {
    "addr:full":"2706 Hungary Spring Rd Richmond VA 23294",
    "addr:postcode":"2706;23294",
    "addr:street":"Spring Rd",
    "iso:country":"US",
    "sg:address":"2706 Hungary Spring Rd",
    "sg:city":"Richmond",
    "sg:classifiers":[
        {
            "category":"Professional",
            "type":"Services"
        }
    ],
    "sg:phone":"+1 804 935 6786",
    "sg:postcode":"23294",
    "sg:province":"VA",
    "wof:name":"Charles McIntosh & Son",
    "wof:placetype":"venue"
},
  "geometry": {"coordinates":[-77.52670999999999,37.622102],"type":"Point"}
}