{
  "type": "Feature",
  "properties": {
    "addr:full":"10320 Nassawadox Way Ashland VA 23005",
    "addr:housenumber":"10320",
    "addr:postcode":"23005",
    "addr:street":"Nassawadox Way",
    "iso:country":"US",
    "sg:address":"10320 Nassawadox Way",
    "sg:city":"Ashland",
    "sg:classifiers":[
        {
            "category":"Professional",
            "subcategory":"Art Services",
            "type":"Services"
        }
    ],
    "sg:phone":"+1 804 550 9560",
    "sg:postcode":"23005",
    "sg:province":"VA",
    "sg:tags":[
        "commercial",
        "design"
    ],
    "wof:name":"Digishop Corp",
    "wof:placetype":"venue"
},
  "geometry": {"coordinates":[-77.425132,37.68947],"type":"Point"}
}