{
  "type": "Feature",
  "properties": {
    "addr:full":"1873 Laurel Grove Rd Sutherlin VA 24594",
    "addr:housenumber":"1873",
    "addr:postcode":"24594",
    "addr:street":"Laurel Grove Rd",
    "iso:country":"US",
    "sg:address":"1873 Laurel Grove Rd",
    "sg:city":"Sutherlin",
    "sg:classifiers":[
        {
            "category":"Building & Trades",
            "subcategory":"Plumbing",
            "type":"Services"
        }
    ],
    "sg:phone":"+1 434 822 5773",
    "sg:postcode":"24594",
    "sg:province":"VA",
    "sg:tags":[
        "conditioning",
        "air",
        "system",
        "contractor"
    ],
    "wof:name":"Performance Heating & Air Cond",
    "wof:placetype":"venue"
},
  "geometry": {"coordinates":[-79.204376,36.67933],"type":"Point"}
}