{
  "type": "Feature",
  "properties": {
    "addr:full":"2275 S Quincy St Arlington VA 22204",
    "addr:housenumber":"2275",
    "addr:postcode":"22204",
    "addr:street":"S Quincy St",
    "iso:country":"US",
    "sg:address":"2275 S Quincy St",
    "sg:city":"Arlington",
    "sg:classifiers":[
        {
            "category":"Communications",
            "subcategory":"Television Station",
            "type":"Services"
        }
    ],
    "sg:phone":"+1 703 998 2895",
    "sg:postcode":"22204",
    "sg:province":"VA",
    "wof:name":"W E T A T V Channel 26account",
    "wof:placetype":"venue"
},
  "geometry": {"coordinates":[-77.093096,38.848028],"type":"Point"}
}