{
  "type": "Feature",
  "properties": {
    "iso:country":"US",
    "sg:address":"224 W Lee Ave",
    "sg:city":"Vinton",
    "sg:classifiers":[
        {
            "category":"Building & Trades",
            "subcategory":"Pest Control",
            "type":"Services"
        }
    ],
    "sg:phone":"+1 540 342 5828",
    "sg:postcode":"24179",
    "sg:province":"VA",
    "wof:name":"B & C Exterminators Inc",
    "wof:placetype":"venue"
},
  "geometry": {"coordinates":[-79.89957,37.280546],"type":"Point"}
}