{
  "type": "Feature",
  "properties": {
    "iso:country":"US",
    "sg:address":"21113 Chesterfield Ave",
    "sg:city":"Petersburg",
    "sg:classifiers":[
        {
            "category":"Restaurant",
            "type":"Food & Drink"
        }
    ],
    "sg:phone":"+1 804 526 2716",
    "sg:postcode":"23803",
    "sg:province":"VA",
    "sg:tags":[
        "delicatessen"
    ],
    "wof:name":"Bast Of Virginia",
    "wof:placetype":"venue"
},
  "geometry": {"coordinates":[-77.423923,37.236151],"type":"Point"}
}