{
  "type": "Feature",
  "properties": {
    "addr:full":"9544 Woodman Rd Henrico VA 23228",
    "addr:housenumber":"9544",
    "addr:postcode":"23228",
    "addr:street":"Woodman Rd",
    "iso:country":"US",
    "sg:address":"9544 Woodman Rd",
    "sg:city":"Henrico",
    "sg:classifiers":[
        {
            "category":"Shopping",
            "subcategory":"Pharmacy",
            "type":"Retail Goods"
        }
    ],
    "sg:phone":"+1 804 266 9704",
    "sg:postcode":"23228",
    "sg:province":"VA",
    "wof:name":"Rite Aid",
    "wof:placetype":"venue"
},
  "geometry": {"coordinates":[-77.494336,37.643414],"type":"Point"}
}