{
  "type": "Feature",
  "properties": {
    "addr:full":"7415 Oldhams Rd Kinsale VA 22488",
    "addr:housenumber":"7415",
    "addr:postcode":"22488",
    "addr:street":"Oldhams Rd",
    "iso:country":"US",
    "sg:address":"7415 Oldhams Rd",
    "sg:city":"Kinsale",
    "sg:classifiers":[
        {
            "category":"Restaurant",
            "type":"Food & Drink"
        }
    ],
    "sg:phone":"+1 804 472 4200",
    "sg:postcode":"22488",
    "sg:province":"VA",
    "sg:tags":[
        "style",
        "family"
    ],
    "sg:website":"http://www.thebackdraft.com",
    "wof:name":"Rag",
    "wof:placetype":"venue"
},
  "geometry": {"coordinates":[-76.613511,38.023031],"type":"Point"}
}