{
  "type": "Feature",
  "properties": {
    "addr:full":"1320 Old Chain Bridge Rd Mc Lean VA 22101",
    "addr:housenumber":"1320",
    "addr:postcode":"22101",
    "addr:street":"Old Chain Bridge Rd Mc Lean",
    "iso:country":"US",
    "sg:address":"1320 Old Chain Bridge Rd",
    "sg:city":"Mc Lean",
    "sg:classifiers":[
        {
            "category":"Deli",
            "type":"Food & Drink"
        }
    ],
    "sg:phone":"+1 703 847 9600",
    "sg:postcode":"22101",
    "sg:province":"VA",
    "wof:name":"Madison Deli",
    "wof:placetype":"venue"
},
  "geometry": {"coordinates":[-77.176697,38.9398],"type":"Point"}
}