{
  "type": "Feature",
  "properties": {
    "iso:country":"US",
    "sg:address":"2300 N Clarendon Blvd",
    "sg:city":"Arlington",
    "sg:classifiers":[
        {
            "category":"Building & Trades",
            "subcategory":"Electrical",
            "type":"Services"
        }
    ],
    "sg:phone":"+1 703 465 2842",
    "sg:postcode":"22201",
    "sg:province":"VA",
    "sg:tags":[
        "electrical",
        "contractor"
    ],
    "wof:name":"Sharp Electronics",
    "wof:placetype":"venue"
},
  "geometry": {"coordinates":[-77.08649200000001,38.890408],"type":"Point"}
}