{
  "type": "Feature",
  "properties": {
    "addr:full":"9525 Braddock Rd Fairfax VA 22032",
    "addr:housenumber":"9525",
    "addr:postcode":"22032",
    "addr:street":"Braddock Rd",
    "iso:country":"US",
    "sg:address":"9525 Braddock Rd",
    "sg:city":"Fairfax",
    "sg:classifiers":[
        {
            "category":"Food & Beverages",
            "subcategory":"Groceries & Convenience Stores",
            "type":"Retail Goods"
        }
    ],
    "sg:phone":"+1 703 978 4604",
    "sg:postcode":"22032",
    "sg:province":"VA",
    "wof:name":"Safeway",
    "wof:placetype":"venue"
},
  "geometry": {"coordinates":[-77.276062,38.818918],"type":"Point"}
}