{
  "type": "Feature",
  "properties": {
    "addr:full":"15 Watling St Urbanna VA 23175",
    "addr:housenumber":"15",
    "addr:postcode":"23175",
    "addr:street":"Watling St",
    "iso:country":"US",
    "sg:address":"15 Watling St",
    "sg:city":"Urbanna",
    "sg:classifiers":[
        {
            "category":"Recreation",
            "subcategory":"Marina",
            "type":"Entertainment"
        }
    ],
    "sg:phone":"+1 804 758 2342",
    "sg:postcode":"23175",
    "sg:province":"VA",
    "wof:name":"Urbanna Yachting Ctr",
    "wof:placetype":"venue"
},
  "geometry": {"coordinates":[-76.5728,37.634052],"type":"Point"}
}