{
  "type": "Feature",
  "properties": {
    "addr:full":"1040 Cowford Rd Halifax VA 24558",
    "addr:housenumber":"1040",
    "addr:postcode":"24558",
    "addr:street":"Cowford Rd",
    "iso:country":"US",
    "sg:address":"1040 Cowford Rd",
    "sg:city":"Halifax",
    "sg:classifiers":[
        {
            "category":"Social Services",
            "subcategory":"Child Care",
            "type":"Services"
        }
    ],
    "sg:phone":"+1 434 476 5030",
    "sg:postcode":"24558",
    "sg:province":"VA",
    "wof:name":"Tri-County Community Action",
    "wof:placetype":"venue"
},
  "geometry": {"coordinates":[-78.920771,36.768664],"type":"Point"}
}