{
  "type": "Feature",
  "properties": {
    "addr:full":"2900 S Columbia Pike Arlington VA 22204",
    "addr:housenumber":"2900",
    "addr:postcode":"22204",
    "addr:street":"S Columbia Pike",
    "iso:country":"US",
    "sg:address":"2900 S Columbia Pike",
    "sg:city":"Arlington",
    "sg:classifiers":[
        {
            "category":"Restaurant",
            "type":"Food & Drink"
        }
    ],
    "sg:phone":"+1 703 920 2404",
    "sg:postcode":"22204",
    "sg:province":"VA",
    "wof:name":"Blanka Restaurant",
    "wof:placetype":"venue"
},
  "geometry": {"coordinates":[-77.08792699999999,38.862331],"type":"Point"}
}