{
  "type": "Feature",
  "properties": {
    "iso:country":"US",
    "sg:address":"512 Devils Bottom Rd",
    "sg:city":"Lancaster",
    "sg:classifiers":[
        {
            "category":"Building & Trades",
            "subcategory":"Construction",
            "type":"Services"
        }
    ],
    "sg:phone":"+1 804 436 9600",
    "sg:postcode":"22503",
    "sg:province":"VA",
    "sg:tags":[
        "contractor"
    ],
    "wof:name":"Bayside Seamless Gutters",
    "wof:placetype":"venue"
},
  "geometry": {"coordinates":[-76.42153399999999,37.748585],"type":"Point"}
}