{
  "type": "Feature",
  "properties": {
    "addr:full":"1012 Blythewood Ln Suffolk VA 23434",
    "addr:housenumber":"1012",
    "addr:postcode":"23434",
    "addr:street":"Blythewood Ln",
    "iso:country":"US",
    "sg:address":"1012 Blythewood Ln",
    "sg:city":"Suffolk",
    "sg:classifiers":[
        {
            "category":"Building & Trades",
            "subcategory":"Construction",
            "type":"Services"
        }
    ],
    "sg:phone":"+1 757 539 4695",
    "sg:postcode":"23434",
    "sg:province":"VA",
    "sg:tags":[
        "house"
    ],
    "wof:name":"Skyline Construction",
    "wof:placetype":"venue"
},
  "geometry": {"coordinates":[-76.559673,36.72164],"type":"Point"}
}