{
  "type": "Feature",
  "properties": {
    "iso:country":"US",
    "sg:address":"1201 Palmerton Dr",
    "sg:city":"Newport News",
    "sg:classifiers":[
        {
            "category":"Organizations",
            "subcategory":"Community Association",
            "type":"Services"
        }
    ],
    "sg:phone":"+1 757 874 1588",
    "sg:postcode":"23602",
    "sg:province":"VA",
    "wof:name":"Kiwanis International",
    "wof:placetype":"venue"
},
  "geometry": {"coordinates":[-76.506591,37.151048],"type":"Point"}
}