{
  "type": "Feature",
  "properties": {
    "addr:full":"2410 Williamson Rd NE Roanoke VA 24012",
    "addr:housenumber":"2410",
    "addr:postcode":"24012",
    "addr:street":"Williamson Rd Ne",
    "iso:country":"US",
    "sg:address":"2410 Williamson Rd NE",
    "sg:city":"Roanoke",
    "sg:classifiers":[
        {
            "category":"Restaurant",
            "type":"Food & Drink"
        }
    ],
    "sg:phone":"+1 540 563 0112",
    "sg:postcode":"24012",
    "sg:province":"VA",
    "sg:tags":[
        "motel"
    ],
    "wof:name":"Affordable Efficiency Inn",
    "wof:placetype":"venue"
},
  "geometry": {"coordinates":[-79.935919,37.294169],"type":"Point"}
}