{
  "type": "Feature",
  "properties": {
    "addr:full":"17744 Main St Dumfries VA 22026",
    "addr:housenumber":"17744",
    "addr:postcode":"22026",
    "addr:street":"Main St",
    "iso:country":"US",
    "sg:address":"17744 Main St",
    "sg:city":"Dumfries",
    "sg:classifiers":[
        {
            "category":"Personal",
            "subcategory":"Barber",
            "type":"Services"
        }
    ],
    "sg:phone":"+1 703 221 0097",
    "sg:postcode":"22026",
    "sg:province":"VA",
    "wof:name":"Unique II Barber Shop",
    "wof:placetype":"venue"
},
  "geometry": {"coordinates":[-77.327068,38.567463],"type":"Point"}
}