{
  "type": "Feature",
  "properties": {
    "addr:full":"8001 Brook Rd Richmond VA 23227",
    "addr:housenumber":"8001",
    "addr:postcode":"23227",
    "addr:street":"Brook Rd",
    "iso:country":"US",
    "sg:address":"8001 Brook Rd",
    "sg:city":"Richmond",
    "sg:classifiers":[
        {
            "category":"Restaurant",
            "type":"Food & Drink"
        }
    ],
    "sg:phone":"+1 804 553 4474",
    "sg:postcode":"23227",
    "sg:province":"VA",
    "sg:tags":[
        "out"
    ],
    "wof:name":"Dominic's Of New York",
    "wof:placetype":"venue"
},
  "geometry": {"coordinates":[-77.458517,37.630844],"type":"Point"}
}