{
  "type": "Feature",
  "properties": {
    "addr:full":"1576 N Colonial Ter Arlington VA 22209",
    "addr:housenumber":"1576",
    "addr:postcode":"22209",
    "addr:street":"N Colonial Ter",
    "iso:country":"US",
    "sg:address":"1576 N Colonial Ter",
    "sg:city":"Arlington",
    "sg:classifiers":[
        {
            "category":"Professional",
            "subcategory":"Computer Services",
            "type":"Services"
        }
    ],
    "sg:phone":"+1 703 908 0878",
    "sg:postcode":"22209",
    "sg:province":"VA",
    "sg:tags":[
        "information",
        "consulting",
        "management",
        "technology"
    ],
    "wof:name":"Planitech LLC",
    "wof:placetype":"venue"
},
  "geometry": {"coordinates":[-77.074962,38.89791],"type":"Point"}
}