{
  "type": "Feature",
  "properties": {
    "addr:full":"226 Dockside Dr Hampton VA 23669",
    "addr:housenumber":"226",
    "addr:postcode":"23669",
    "addr:street":"Dockside Dr",
    "iso:country":"US",
    "sg:address":"226 Dockside Dr",
    "sg:city":"Hampton",
    "sg:classifiers":[
        {
            "category":"Health Services",
            "subcategory":"Optometrist",
            "type":"Services"
        }
    ],
    "sg:phone":"+1 757 314 8037",
    "sg:postcode":"23669",
    "sg:province":"VA",
    "wof:name":"Thomas A Neal Od",
    "wof:placetype":"venue"
},
  "geometry": {"coordinates":[-76.338285,37.038427],"type":"Point"}
}