{
  "type": "Feature",
  "properties": {
    "addr:full":"3544 S Jefferson St Falls Church VA 22041",
    "addr:housenumber":"3544",
    "addr:postcode":"22041",
    "addr:street":"S Jefferson St",
    "iso:country":"US",
    "sg:address":"3544 S Jefferson St",
    "sg:city":"Falls Church",
    "sg:classifiers":[
        {
            "category":"Personal",
            "subcategory":"Beauty Salon",
            "type":"Services"
        }
    ],
    "sg:phone":"+1 703 820 5500",
    "sg:postcode":"22041",
    "sg:province":"VA",
    "sg:tags":[
        "shop"
    ],
    "wof:name":"Great Clips",
    "wof:placetype":"venue"
},
  "geometry": {"coordinates":[-77.118071,38.849073],"type":"Point"}
}