{
  "type": "Feature",
  "properties": {
    "addr:full":"11106 Lee Hwy Fairfax VA 22030",
    "addr:housenumber":"11106",
    "addr:postcode":"22030",
    "addr:street":"Lee Hwy",
    "iso:country":"US",
    "sg:address":"11106 Lee Hwy",
    "sg:city":"Fairfax",
    "sg:classifiers":[
        {
            "category":"Home & Garden",
            "subcategory":"Furniture",
            "type":"Retail Goods"
        }
    ],
    "sg:phone":"+1 703 352 5111",
    "sg:postcode":"22030",
    "sg:province":"VA",
    "wof:name":"Futons By Ellen",
    "wof:placetype":"venue"
},
  "geometry": {"coordinates":[-77.32856200000001,38.852237],"type":"Point"}
}