{
  "type": "Feature",
  "properties": {
    "addr:full":"6720 Circle Creek Dr Boones Mill VA 24065",
    "addr:housenumber":"6720",
    "addr:postcode":"24065",
    "addr:street":"Circle Creek Dr",
    "iso:country":"US",
    "sg:address":"6720 Circle Creek Dr",
    "sg:city":"Boones Mill",
    "sg:classifiers":[
        {
            "category":"Building & Trades",
            "subcategory":"Construction",
            "type":"Services"
        }
    ],
    "sg:phone":"+1 540 774 4341",
    "sg:postcode":"24065",
    "sg:province":"VA",
    "sg:tags":[
        "contractor"
    ],
    "wof:name":"All N1 Contracting Inc",
    "wof:placetype":"venue"
},
  "geometry": {"coordinates":[-79.941115,37.167866],"type":"Point"}
}