{
  "type": "Feature",
  "properties": {
    "iso:country":"US",
    "sg:address":"2150 Jennings St",
    "sg:city":"Woodbridge",
    "sg:classifiers":[
        {
            "category":"Professional",
            "subcategory":"Computer Services",
            "type":"Services"
        }
    ],
    "sg:phone":"+1 703 580 9088",
    "sg:postcode":"22191",
    "sg:province":"VA",
    "sg:tags":[
        "programing",
        "custom"
    ],
    "wof:name":"Straycom Technical",
    "wof:placetype":"venue"
},
  "geometry": {"coordinates":[-77.27624299999999,38.599557],"type":"Point"}
}