{
  "type": "Feature",
  "properties": {
    "iso:country":"US",
    "sg:address":"7801 Westpark Dr",
    "sg:city":"Mc Lean",
    "sg:classifiers":[
        {
            "category":"Real Estate",
            "subcategory":"Developer",
            "type":"Services"
        }
    ],
    "sg:phone":"+1 703 893 9444",
    "sg:postcode":"22102",
    "sg:province":"VA",
    "wof:name":"Homart Development Co",
    "wof:placetype":"venue"
},
  "geometry": {"coordinates":[-77.218873,38.921248],"type":"Point"}
}