{
  "type": "Feature",
  "properties": {
    "iso:country":"US",
    "sg:address":"2336 E Little Creek Rd",
    "sg:city":"Norfolk",
    "sg:classifiers":[
        {
            "category":"Banks & Credit Unions",
            "subcategory":"Bank",
            "type":"Services"
        }
    ],
    "sg:phone":"+1 757 587 4200",
    "sg:postcode":"23518",
    "sg:province":"VA",
    "wof:name":"Branch Bnkg Tr Co of Virginia",
    "wof:placetype":"venue"
},
  "geometry": {"coordinates":[-76.21692899999999,36.915195],"type":"Point"}
}