{
  "type": "Feature",
  "properties": {
    "addr:full":"1 Dogleg Rd Palmyra VA 22963",
    "addr:housenumber":"1",
    "addr:postcode":"22963",
    "addr:street":"Dogleg Rd",
    "iso:country":"US",
    "sg:address":"1 Dogleg Rd",
    "sg:city":"Palmyra",
    "sg:classifiers":[
        {
            "category":"Professional",
            "subcategory":"Business Services",
            "type":"Services"
        }
    ],
    "sg:phone":"+1 434 589 5470",
    "sg:postcode":"22963",
    "sg:province":"VA",
    "wof:name":"CMS Copyright Svc",
    "wof:placetype":"venue"
},
  "geometry": {"coordinates":[-78.31124199999999,37.906217],"type":"Point"}
}