{
  "type": "Feature",
  "properties": {
    "iso:country":"US",
    "sg:address":"219 5th St",
    "sg:city":"Clarksville",
    "sg:classifiers":[
        {
            "category":"Organizations",
            "subcategory":"Religious Organization",
            "type":"Services"
        }
    ],
    "sg:phone":"+1 434 374 8050",
    "sg:postcode":"23927",
    "sg:province":"VA",
    "sg:tags":[
        "church"
    ],
    "wof:name":"Jamieson Memorial Methodist",
    "wof:placetype":"venue"
},
  "geometry": {"coordinates":[-78.55665500000001,36.622889],"type":"Point"}
}