{
  "type": "Feature",
  "properties": {
    "iso:country":"US",
    "sg:address":"1901 Zinzer Rd",
    "sg:city":"Hampton",
    "sg:classifiers":[
        {
            "category":"Health Services",
            "subcategory":"Health Practitioner",
            "type":"Services"
        }
    ],
    "sg:phone":"+1 757 850 1456",
    "sg:postcode":"23663",
    "sg:province":"VA",
    "sg:tags":[
        "assistant",
        "medical"
    ],
    "wof:name":"Poe Veilka",
    "wof:placetype":"venue"
},
  "geometry": {"coordinates":[-76.30417199999999,37.049689],"type":"Point"}
}