{
  "type": "Feature",
  "properties": {
    "addr:full":"272 Waterloo St Warrenton VA 20186",
    "addr:housenumber":"272",
    "addr:postcode":"20186",
    "addr:street":"Waterloo St",
    "iso:country":"US",
    "sg:address":"272 Waterloo St",
    "sg:city":"Warrenton",
    "sg:classifiers":[
        {
            "category":"Shopping",
            "subcategory":"Gifts & Souvenirs",
            "type":"Retail Goods"
        }
    ],
    "sg:phone":"+1 540 347 4188",
    "sg:postcode":"20186",
    "sg:province":"VA",
    "sg:tags":[
        "cards",
        "greeting"
    ],
    "wof:name":"Ribbons Inc",
    "wof:placetype":"venue"
},
  "geometry": {"coordinates":[-77.80509000000001,38.716835],"type":"Point"}
}