{
  "type": "Feature",
  "properties": {
    "iso:country":"US",
    "sg:address":"12201 Jefferson Davis Hwy",
    "sg:city":"Chester",
    "sg:classifiers":[
        {
            "category":"Retail",
            "subcategory":"Auto Repair",
            "type":"Services"
        }
    ],
    "sg:phone":"+1 804 751 0999",
    "sg:postcode":"23831",
    "sg:province":"VA",
    "sg:tags":[
        "automobile",
        "lubrication",
        "automotive"
    ],
    "sg:website":"www.jiffylube.com",
    "wof:name":"Jiffy Lube",
    "wof:placetype":"venue"
},
  "geometry": {"coordinates":[-77.41462799999999,37.358487],"type":"Point"}
}