{
  "type": "Feature",
  "properties": {
    "iso:country":"US",
    "sg:address":"12021 Southern Points Dr",
    "sg:city":"Chesterfield",
    "sg:classifiers":[
        {
            "category":"Professional",
            "subcategory":"Accounting & Tax Preparation",
            "type":"Services"
        }
    ],
    "sg:phone":"+1 804 908 5436",
    "sg:postcode":"23838",
    "sg:province":"VA",
    "wof:name":"Wiglesworth Accounting Svcs",
    "wof:placetype":"venue"
},
  "geometry": {"coordinates":[-77.678197,37.340185],"type":"Point"}
}