{
  "type": "Feature",
  "properties": {
    "addr:full":"2277 Westover Ave SW Roanoke VA 24015",
    "addr:housenumber":"2277",
    "addr:postcode":"24015",
    "addr:street":"Westover Ave Sw",
    "iso:country":"US",
    "sg:address":"2277 Westover Ave SW",
    "sg:city":"Roanoke",
    "sg:classifiers":[
        {
            "category":"Real Estate",
            "subcategory":"Real Estate Services",
            "type":"Services"
        },
        {
            "category":"Professional",
            "subcategory":"Business Services",
            "type":"Services"
        },
        {
            "category":"Real Estate",
            "subcategory":"Surveying",
            "type":"Services"
        }
    ],
    "sg:phone":"+1 540 491 9988",
    "sg:postcode":"24015",
    "sg:province":"VA",
    "sg:tags":[
        "commercial",
        "appraisers-business",
        "industrial",
        "appraisers-commercial",
        "appraiser"
    ],
    "wof:name":"Thompson Valuation & Consulting, Inc.",
    "wof:placetype":"venue"
},
  "geometry": {"coordinates":[-79.985,37.265872],"type":"Point"}
}