{
  "type": "Feature",
  "properties": {
    "iso:country":"US",
    "sg:address":"10208 Ashbrooke Ct",
    "sg:city":"Oakton",
    "sg:classifiers":[
        {
            "category":"Restaurant",
            "type":"Food & Drink"
        }
    ],
    "sg:phone":"+1 703 281 5157",
    "sg:postcode":"22124",
    "sg:province":"VA",
    "sg:tags":[
        "eating"
    ],
    "wof:name":"White Spot (north)",
    "wof:placetype":"venue"
},
  "geometry": {"coordinates":[-77.297279,38.875614],"type":"Point"}
}