{
  "type": "Feature",
  "properties": {
    "iso:country":"US",
    "sg:address":"995 J Clyde Morris Blvd",
    "sg:city":"Newport News",
    "sg:classifiers":[
        {
            "category":"Food & Beverages",
            "subcategory":"Groceries & Convenience Stores",
            "type":"Retail Goods"
        }
    ],
    "sg:phone":"+1 757 595 1551",
    "sg:postcode":"23601",
    "sg:province":"VA",
    "sg:tags":[
        "station",
        "gas"
    ],
    "wof:name":"Miller Mart 12",
    "wof:placetype":"venue"
},
  "geometry": {"coordinates":[-76.45922400000001,37.094973],"type":"Point"}
}