{
  "type": "Feature",
  "properties": {
    "iso:country":"US",
    "sg:address":"11 Mohawk Dr",
    "sg:city":"Portsmouth",
    "sg:classifiers":[
        {
            "category":"Building & Trades",
            "subcategory":"Construction",
            "type":"Services"
        }
    ],
    "sg:phone":"+1 757 235 4150",
    "sg:postcode":"23701",
    "sg:province":"VA",
    "sg:tags":[
        "resurfacing",
        "laying",
        "refinishing",
        "floor"
    ],
    "wof:name":"Seamster Flooring",
    "wof:placetype":"venue"
},
  "geometry": {"coordinates":[-76.36311000000001,36.813275],"type":"Point"}
}