{
  "type": "Feature",
  "properties": {
    "addr:full":"12480 Crain Hwy Newburg MD 20664",
    "addr:housenumber":"12480",
    "addr:postcode":"20664",
    "addr:street":"Crain Hwy",
    "iso:country":"US",
    "sg:address":"12480 Crain Hwy",
    "sg:city":"Newburg",
    "sg:classifiers":[
        {
            "category":"Travel",
            "subcategory":"Travel Agent",
            "type":"Entertainment"
        }
    ],
    "sg:phone":"+1 301 259 2500",
    "sg:postcode":"20664",
    "sg:province":"MD",
    "sg:tags":[
        "information",
        "tourist"
    ],
    "sg:website":"www.mdwelcome.org",
    "wof:name":"Crain Memorial Welcome Ctr",
    "wof:placetype":"venue"
},
  "geometry": {"coordinates":[-76.959006,38.372281],"type":"Point"}
}