{
  "type": "Feature",
  "properties": {
    "addr:full":"3805 Dunstan Ct Chesapeake VA 23322",
    "addr:housenumber":"3805",
    "addr:postcode":"23322",
    "addr:street":"Dunstan Ct",
    "iso:country":"US",
    "sg:address":"3805 Dunstan Ct",
    "sg:city":"Chesapeake",
    "sg:classifiers":[
        {
            "category":"Professional",
            "type":"Services"
        }
    ],
    "sg:phone":"+1 757 421 4451",
    "sg:postcode":"23322",
    "sg:province":"VA",
    "wof:name":"Seniors Planning Services Inc",
    "wof:placetype":"venue"
},
  "geometry": {"coordinates":[-76.24594500000001,36.576073],"type":"Point"}
}