{
  "type": "Feature",
  "properties": {
    "addr:full":"20597 Cornstalk Ter Ashburn VA 20147",
    "addr:postcode":"20597;20147",
    "addr:street":"Cornstalk Ter",
    "iso:country":"US",
    "sg:address":"20597 Cornstalk Ter",
    "sg:city":"Ashburn",
    "sg:classifiers":[
        {
            "category":"Professional",
            "subcategory":"Computer Services",
            "type":"Services"
        }
    ],
    "sg:phone":"+1 703 723 2144",
    "sg:postcode":"20147",
    "sg:province":"VA",
    "sg:tags":[
        "programing",
        "custom"
    ],
    "wof:name":"Sunforge",
    "wof:placetype":"venue"
},
  "geometry": {"coordinates":[-77.475441,39.046711],"type":"Point"}
}