{
  "type": "Feature",
  "properties": {
    "iso:country":"US",
    "sg:address":"5703 Waters Edge Landing Ct",
    "sg:city":"Burke",
    "sg:classifiers":[
        {
            "category":"Professional",
            "subcategory":"Management & Consulting",
            "type":"Services"
        }
    ],
    "sg:phone":"+1 703 250 3994",
    "sg:postcode":"22015",
    "sg:province":"VA",
    "wof:name":"Smyth Water Planning Solutions",
    "wof:placetype":"venue"
},
  "geometry": {"coordinates":[-77.31085400000001,38.794271],"type":"Point"}
}