{
  "type": "Feature",
  "properties": {
    "addr:full":"2230 E Parham Rd Richmond VA 23228",
    "addr:housenumber":"2230",
    "addr:postcode":"23228",
    "addr:street":"E Parham Rd",
    "iso:country":"US",
    "sg:address":"2230 E Parham Rd",
    "sg:city":"Richmond",
    "sg:classifiers":[
        {
            "category":"Organizations",
            "subcategory":"Religious Organization",
            "type":"Services"
        }
    ],
    "sg:phone":"+1 804 553 4090",
    "sg:postcode":"23228",
    "sg:province":"VA",
    "wof:name":"Good News Jail Prison Ministry",
    "wof:placetype":"venue"
},
  "geometry": {"coordinates":[-77.49128399999999,37.639993],"type":"Point"}
}