{
  "type": "Feature",
  "properties": {
    "iso:country":"US",
    "sg:address":"2401 S Columbia Pike",
    "sg:city":"Arlington",
    "sg:classifiers":[
        {
            "category":"Restaurant",
            "type":"Food & Drink"
        }
    ],
    "sg:phone":"+1 703 920 4732",
    "sg:postcode":"22204",
    "sg:province":"VA",
    "sg:tags":[
        "eating"
    ],
    "wof:name":"Cafe Laluna",
    "wof:placetype":"venue"
},
  "geometry": {"coordinates":[-77.08410000000001,38.863305],"type":"Point"}
}