{
  "type": "Feature",
  "properties": {
    "addr:full":"101 Seminole Dr Madison Heights VA 24572",
    "addr:housenumber":"101",
    "addr:postcode":"24572",
    "addr:street":"Seminole Dr",
    "iso:country":"US",
    "sg:address":"101 Seminole Dr",
    "sg:city":"Madison Heights",
    "sg:classifiers":[
        {
            "category":"Organizations",
            "subcategory":"Religious Organization",
            "type":"Services"
        }
    ],
    "sg:phone":"+1 434 528 4286",
    "sg:postcode":"24572",
    "sg:province":"VA",
    "wof:name":"Open Door Baptist Church",
    "wof:placetype":"venue"
},
  "geometry": {"coordinates":[-79.12053299999999,37.439092],"type":"Point"}
}