{
  "type": "Feature",
  "properties": {
    "addr:full":"1120 Pine Heights Trl Halifax VA 24558",
    "addr:housenumber":"1120",
    "addr:postcode":"24558",
    "addr:street":"Pine Heights Trl",
    "iso:country":"US",
    "sg:address":"1120 Pine Heights Trl",
    "sg:city":"Halifax",
    "sg:classifiers":[
        {
            "category":"Manufacturing",
            "subcategory":"Lumber",
            "type":"Manufacturing & Wholesale Goods"
        }
    ],
    "sg:phone":"+1 434 476 6245",
    "sg:postcode":"24558",
    "sg:province":"VA",
    "sg:tags":[
        "logging"
    ],
    "wof:name":"Edmondson Logging",
    "wof:placetype":"venue"
},
  "geometry": {"coordinates":[-79.00063400000001,36.760072],"type":"Point"}
}