{
  "type": "Feature",
  "properties": {
    "iso:country":"US",
    "sg:address":"6125 Algona Ct",
    "sg:city":"Alexandria",
    "sg:classifiers":[
        {
            "category":"Professional",
            "subcategory":"Computer Services",
            "type":"Services"
        }
    ],
    "sg:phone":"+1 703 960 2500",
    "sg:postcode":"22310",
    "sg:province":"VA",
    "sg:tags":[
        "internet"
    ],
    "wof:name":"Merak Mail Server",
    "wof:placetype":"venue"
},
  "geometry": {"coordinates":[-77.09634200000001,38.784197],"type":"Point"}
}