{
  "type": "Feature",
  "properties": {
    "iso:country":"US",
    "sg:address":"606 Chesapeake Dr",
    "sg:city":"White Stone",
    "sg:classifiers":[
        {
            "category":"Professional",
            "subcategory":"Business Services",
            "type":"Services"
        }
    ],
    "sg:phone":"+1 804 435 2300",
    "sg:postcode":"22578",
    "sg:province":"VA",
    "sg:tags":[
        "interior",
        "consultant",
        "design",
        "decorator"
    ],
    "wof:name":"Miller Mc Cann Intl",
    "wof:placetype":"venue"
},
  "geometry": {"coordinates":[-76.38725599999999,37.646858],"type":"Point"}
}