{
  "type": "Feature",
  "properties": {
    "addr:full":"37 Fillmore St Arlington VA 22201",
    "addr:housenumber":"37",
    "addr:postcode":"22201",
    "addr:street":"Fillmore St",
    "iso:country":"US",
    "sg:address":"37 Fillmore St",
    "sg:city":"Arlington",
    "sg:classifiers":[
        {
            "category":"Insurance",
            "subcategory":"Hazard Insurance",
            "type":"Services"
        }
    ],
    "sg:phone":"+1 703 351 9494",
    "sg:postcode":"22201",
    "sg:province":"VA",
    "sg:website":"www.cmrinsure.com",
    "wof:name":"CMR Insurance Agency",
    "wof:placetype":"venue"
},
  "geometry": {"coordinates":[-77.08973899999999,38.874339],"type":"Point"}
}