{
  "type": "Feature",
  "properties": {
    "addr:full":"220 Hollywood Farm Rd Fredericksburg VA 22405",
    "addr:housenumber":"220",
    "addr:postcode":"22405",
    "addr:street":"Hollywood Farm Rd",
    "iso:country":"US",
    "sg:address":"220 Hollywood Farm Rd",
    "sg:city":"Fredericksburg",
    "sg:classifiers":[
        {
            "category":"Building & Trades",
            "subcategory":"Landscaping Services",
            "type":"Services"
        }
    ],
    "sg:phone":"+1 540 371 3420",
    "sg:postcode":"22405",
    "sg:province":"VA",
    "wof:name":"Butler & Son Landscaping",
    "wof:placetype":"venue"
},
  "geometry": {"coordinates":[-77.35762099999999,38.275569],"type":"Point"}
}