{
  "type": "Feature",
  "properties": {
    "iso:country":"US",
    "sg:address":"5602 General Washington Dr",
    "sg:city":"Alexandria",
    "sg:classifiers":[
        {
            "category":"Home & Garden",
            "subcategory":"Home Furnishings",
            "type":"Retail Goods"
        }
    ],
    "sg:phone":"+1 703 354 6616",
    "sg:postcode":"22312",
    "sg:province":"VA",
    "sg:tags":[
        "window",
        "covering"
    ],
    "wof:name":"Maritas Design",
    "wof:placetype":"venue"
},
  "geometry": {"coordinates":[-77.164236,38.798396],"type":"Point"}
}