{
  "type": "Feature",
  "properties": {
    "iso:country":"US",
    "sg:address":"427 Ruritan Dr",
    "sg:city":"Emporia",
    "sg:classifiers":[
        {
            "category":"Organizations",
            "subcategory":"Religious Organization",
            "type":"Services"
        }
    ],
    "sg:phone":"+1 434 634 4281",
    "sg:postcode":"23847",
    "sg:province":"VA",
    "sg:tags":[
        "church"
    ],
    "wof:name":"First Christian Church Inc",
    "wof:placetype":"venue"
},
  "geometry": {"coordinates":[-77.565549,36.716832],"type":"Point"}
}