{
  "type": "Feature",
  "properties": {
    "addr:full":"14870 Lightner Rd Haymarket VA 20169",
    "addr:postcode":"14870;20169",
    "addr:street":"Lightner Rd",
    "iso:country":"US",
    "sg:address":"14870 Lightner Rd",
    "sg:city":"Haymarket",
    "sg:classifiers":[
        {
            "category":"Building & Trades",
            "subcategory":"Construction",
            "type":"Services"
        }
    ],
    "sg:phone":"+1 703 753 3360",
    "sg:postcode":"20169",
    "sg:province":"VA",
    "sg:tags":[
        "contractor"
    ],
    "wof:name":"Branch Highways",
    "wof:placetype":"venue"
},
  "geometry": {"coordinates":[-77.63261,38.836316],"type":"Point"}
}