{
  "type": "Feature",
  "properties": {
    "iso:country":"US",
    "sg:address":"47382 Westwood Pl",
    "sg:city":"Sterling",
    "sg:classifiers":[
        {
            "category":"Banks & Credit Unions",
            "subcategory":"Bank",
            "type":"Services"
        }
    ],
    "sg:phone":"+1 571 434 0920",
    "sg:postcode":"20165",
    "sg:province":"VA",
    "sg:tags":[
        "loan",
        "real estate"
    ],
    "wof:name":"Power Plus Mort Inc",
    "wof:placetype":"venue"
},
  "geometry": {"coordinates":[-77.359364,39.037631],"type":"Point"}
}