{
  "type": "Feature",
  "properties": {
    "addr:full":"1087 Kane St Norfolk VA 23513",
    "addr:housenumber":"1087",
    "addr:postcode":"23513",
    "addr:street":"Kane St",
    "iso:country":"US",
    "sg:address":"1087 Kane St",
    "sg:city":"Norfolk",
    "sg:classifiers":[
        {
            "category":"Retail",
            "subcategory":"Car Wash",
            "type":"Services"
        }
    ],
    "sg:phone":"+1 757 285 6837",
    "sg:postcode":"23513",
    "sg:province":"VA",
    "wof:name":"Shaw Water Work Power Washing",
    "wof:placetype":"venue"
},
  "geometry": {"coordinates":[-76.240937,36.906906],"type":"Point"}
}