{
  "type": "Feature",
  "properties": {
    "addr:full":"13920 Noblewood Plz Woodbridge VA 22193",
    "addr:housenumber":"13920",
    "addr:postcode":"22193",
    "addr:street":"Noblewood Plz",
    "iso:country":"US",
    "sg:address":"13920 Noblewood Plz",
    "sg:city":"Woodbridge",
    "sg:classifiers":[
        {
            "category":"Banks & Credit Unions",
            "subcategory":"Bank",
            "type":"Services"
        }
    ],
    "sg:phone":"+1 703 533 6348",
    "sg:postcode":"22193",
    "sg:province":"VA",
    "sg:tags":[
        "state"
    ],
    "wof:name":"First Virginia",
    "wof:placetype":"venue"
},
  "geometry": {"coordinates":[-77.315676,38.651888],"type":"Point"}
}