{
  "type": "Feature",
  "properties": {
    "iso:country":"US",
    "sg:address":"14240 Sullyfield Cir",
    "sg:city":"Chantilly",
    "sg:classifiers":[
        {
            "category":"Building & Trades",
            "subcategory":"Electrical",
            "type":"Services"
        }
    ],
    "sg:phone":"+1 703 968 4089",
    "sg:postcode":"20151",
    "sg:province":"VA",
    "sg:tags":[
        "security",
        "electrical",
        "system",
        "contractor"
    ],
    "wof:name":"Argus Electronic Systems Inc",
    "wof:placetype":"venue"
},
  "geometry": {"coordinates":[-77.438204,38.894317],"type":"Point"}
}