{
  "type": "Feature",
  "properties": {
    "iso:country":"US",
    "sg:address":"12706 Sabastian Dr",
    "sg:city":"Fairfax",
    "sg:classifiers":[
        {
            "category":"Professional",
            "type":"Services"
        }
    ],
    "sg:phone":"+1 703 830 2197",
    "sg:postcode":"22030",
    "sg:province":"VA",
    "wof:name":"Jennifer Wheeler",
    "wof:placetype":"venue"
},
  "geometry": {"coordinates":[-77.387851,38.845445],"type":"Point"}
}