{
  "type": "Feature",
  "properties": {
    "addr:full":"8407 Richmond Hwy Alexandria VA 22309",
    "addr:housenumber":"8407",
    "addr:postcode":"22309",
    "addr:street":"Richmond Hwy",
    "iso:country":"US",
    "sg:address":"8407 Richmond Hwy",
    "sg:city":"Alexandria",
    "sg:classifiers":[
        {
            "category":"Social Services",
            "type":"Services"
        }
    ],
    "sg:phone":"+1 703 799 2293",
    "sg:postcode":"22309",
    "sg:province":"VA",
    "sg:tags":[
        "shelter",
        "housing",
        "provides",
        "emergency"
    ],
    "sg:website":"www.newhopehousing.org",
    "wof:name":"New Hope Housing Inc",
    "wof:placetype":"venue"
},
  "geometry": {"coordinates":[-77.10991799999999,38.728111],"type":"Point"}
}