{
  "type": "Feature",
  "properties": {
    "addr:full":"14462 Jefferson Davis Hwy Woodbridge VA 22191",
    "addr:housenumber":"14462",
    "addr:postcode":"22191",
    "addr:street":"Jefferson Davis Hwy",
    "iso:country":"US",
    "sg:address":"14462 Jefferson Davis Hwy",
    "sg:city":"Woodbridge",
    "sg:classifiers":[
        {
            "category":"Shopping",
            "subcategory":"Clothing, Apparel, & Fashions",
            "type":"Retail Goods"
        }
    ],
    "sg:phone":"+1 703 491 9966",
    "sg:postcode":"22191",
    "sg:province":"VA",
    "wof:name":"Bag N Wear",
    "wof:placetype":"venue"
},
  "geometry": {"coordinates":[-77.267839,38.638988],"type":"Point"}
}