{
  "type": "Feature",
  "properties": {
    "iso:country":"US",
    "sg:address":"12913 Alton Sq",
    "sg:city":"Herndon",
    "sg:classifiers":[
        {
            "category":"Professional",
            "subcategory":"Business Services",
            "type":"Services"
        }
    ],
    "sg:phone":"+1 703 437 0457",
    "sg:postcode":"20170",
    "sg:province":"VA",
    "sg:tags":[
        "lecture",
        "bureau",
        "seminar"
    ],
    "wof:name":"PMA Worldwide",
    "wof:placetype":"venue"
},
  "geometry": {"coordinates":[-77.394982,38.956206],"type":"Point"}
}