{
  "type": "Feature",
  "properties": {
    "iso:country":"US",
    "sg:address":"900 Natural Resources Dr",
    "sg:city":"Charlottesville",
    "sg:classifiers":[
        {
            "category":"Government",
            "subcategory":"Office",
            "type":"Public Place"
        }
    ],
    "sg:phone":"+1 434 951 6310",
    "sg:postcode":"22903",
    "sg:province":"VA",
    "sg:tags":[
        "govt",
        "state",
        "utility"
    ],
    "wof:name":"Mines Minerals & Energy Dept",
    "wof:placetype":"venue"
},
  "geometry": {"coordinates":[-78.531932,38.022443],"type":"Point"}
}