{
  "type": "Feature",
  "properties": {
    "addr:full":"17311 Brandy Rd Culpeper VA 22701",
    "addr:housenumber":"17311",
    "addr:postcode":"22701",
    "addr:street":"Brandy Rd",
    "iso:country":"US",
    "sg:address":"17311 Brandy Rd",
    "sg:city":"Culpeper",
    "sg:classifiers":[
        {
            "category":"Building & Trades",
            "subcategory":"Construction",
            "type":"Services"
        }
    ],
    "sg:phone":"+1 540 825 0600",
    "sg:postcode":"22701",
    "sg:province":"VA",
    "sg:tags":[
        "contractor"
    ],
    "wof:name":"MICA Of Virginia",
    "wof:placetype":"venue"
},
  "geometry": {"coordinates":[-77.928219,38.491794],"type":"Point"}
}