{
  "type": "Feature",
  "properties": {
    "addr:full":"14511 Lee Jackson Memorial Hwy Chantilly VA 20151",
    "addr:housenumber":"14511",
    "addr:postcode":"20151",
    "addr:street":"Lee Jackson Memorial Hwy",
    "iso:country":"US",
    "sg:address":"14511 Lee Jackson Memorial Hwy",
    "sg:city":"Chantilly",
    "sg:classifiers":[
        {
            "category":"Restaurant",
            "type":"Food & Drink"
        }
    ],
    "sg:menulink":"http://www.allmenus.com/va/sully/24777-thai-basil/menu/",
    "sg:phone":"+1 703 631 8277",
    "sg:postcode":"20151",
    "sg:province":"VA",
    "sg:tags":[
        "thai",
        "asian"
    ],
    "wof:name":"Thai Basil",
    "wof:placetype":"venue"
},
  "geometry": {"coordinates":[-77.448143,38.900944],"type":"Point"}
}