{
  "type": "Feature",
  "properties": {
    "addr:full":"20315 Sheffield Pl Petersburg VA 23803",
    "addr:housenumber":"20315",
    "addr:postcode":"23803",
    "addr:street":"Sheffield Pl",
    "iso:country":"US",
    "sg:address":"20315 Sheffield Pl",
    "sg:city":"Petersburg",
    "sg:classifiers":[
        {
            "category":"Organizations",
            "subcategory":"Religious Organization",
            "type":"Services"
        }
    ],
    "sg:phone":"+1 804 526 8304",
    "sg:postcode":"23803",
    "sg:province":"VA",
    "sg:tags":[
        "clergy"
    ],
    "wof:name":"Rebecca B Griffin",
    "wof:placetype":"venue"
},
  "geometry": {"coordinates":[-77.423124,37.244913],"type":"Point"}
}