{
  "type": "Feature",
  "properties": {
    "addr:full":"9401 Battle St Manassas VA 20110",
    "addr:housenumber":"9401",
    "addr:postcode":"20110",
    "addr:street":"Battle St",
    "iso:country":"US",
    "sg:address":"9401 Battle St",
    "sg:city":"Manassas",
    "sg:classifiers":[
        {
            "category":"Professional",
            "subcategory":"Lawyer & Legal Services",
            "type":"Services"
        }
    ],
    "sg:phone":"+1 703 365 2442",
    "sg:postcode":"20110",
    "sg:province":"VA",
    "wof:name":"Chandler & Mc Getrick",
    "wof:placetype":"venue"
},
  "geometry": {"coordinates":[-77.47246800000001,38.751051],"type":"Point"}
}