{
  "type": "Feature",
  "properties": {
    "iso:country":"US",
    "sg:address":"6704 Old McLean Village Dr",
    "sg:city":"Mc Lean",
    "sg:classifiers":[
        {
            "category":"Professional",
            "subcategory":"Management & Consulting",
            "type":"Services"
        }
    ],
    "sg:phone":"+1 703 734 3501",
    "sg:postcode":"22101",
    "sg:province":"VA",
    "wof:name":"William H Power",
    "wof:placetype":"venue"
},
  "geometry": {"coordinates":[-77.175809,38.936987],"type":"Point"}
}