{
  "type": "Feature",
  "properties": {
    "addr:full":"5239 Ranchcrest Dr Roanoke VA 24018",
    "addr:housenumber":"5239",
    "addr:postcode":"24018",
    "addr:street":"Ranchcrest Dr",
    "iso:country":"US",
    "sg:address":"5239 Ranchcrest Dr",
    "sg:city":"Roanoke",
    "sg:classifiers":[
        {
            "category":"Professional",
            "subcategory":"Management & Consulting",
            "type":"Services"
        }
    ],
    "sg:phone":"+1 540 989 1666",
    "sg:postcode":"24018",
    "sg:province":"VA",
    "sg:tags":[
        "consultant",
        "resource",
        "human"
    ],
    "wof:name":"J B Freedom Co",
    "wof:placetype":"venue"
},
  "geometry": {"coordinates":[-80.012086,37.215924],"type":"Point"}
}