{
  "type": "Feature",
  "properties": {
    "iso:country":"US",
    "sg:address":"800 S Main St",
    "sg:city":"Harrisonburg",
    "sg:classifiers":[
        {
            "category":"Professional",
            "subcategory":"Accounting & Tax Preparation",
            "type":"Services"
        }
    ],
    "sg:phone":"+1 540 568 3084",
    "sg:postcode":"22801",
    "sg:province":"VA",
    "wof:name":"James Madison University",
    "wof:placetype":"venue"
},
  "geometry": {"coordinates":[-78.87412999999999,38.441438],"type":"Point"}
}