{
  "type": "Feature",
  "properties": {
    "iso:country":"US",
    "sg:address":"985 Poquoson Ave",
    "sg:city":"Poquoson",
    "sg:classifiers":[
        {
            "category":"Education",
            "subcategory":"School",
            "type":"Public Place"
        }
    ],
    "sg:phone":"+1 757 868 6031",
    "sg:postcode":"23662",
    "sg:province":"VA",
    "sg:tags":[
        "executive"
    ],
    "wof:name":"Poquoson Middle School",
    "wof:placetype":"venue"
},
  "geometry": {"coordinates":[-76.366488,37.128312],"type":"Point"}
}