{
  "type": "Feature",
  "properties": {
    "addr:full":"9403 East St Manassas VA 20110",
    "addr:housenumber":"9403",
    "addr:postcode":"20110",
    "addr:street":"East St",
    "iso:country":"US",
    "sg:address":"9403 East St",
    "sg:city":"Manassas",
    "sg:classifiers":[
        {
            "category":"Restaurant",
            "type":"Food & Drink"
        }
    ],
    "sg:phone":"+1 703 368 5647",
    "sg:postcode":"20110",
    "sg:province":"VA",
    "sg:tags":[
        "eating"
    ],
    "wof:name":"Maries Cafe",
    "wof:placetype":"venue"
},
  "geometry": {"coordinates":[-77.470609,38.751283],"type":"Point"}
}