{
  "type": "Feature",
  "properties": {
    "addr:full":"9631 Cosby Mill Rd Quinton VA 23141",
    "addr:housenumber":"9631",
    "addr:postcode":"23141",
    "addr:street":"Cosby Mill Rd",
    "iso:country":"US",
    "sg:address":"9631 Cosby Mill Rd",
    "sg:city":"Quinton",
    "sg:classifiers":[
        {
            "category":"Building & Trades",
            "subcategory":"Construction",
            "type":"Services"
        }
    ],
    "sg:phone":"+1 804 932 8975",
    "sg:postcode":"23141",
    "sg:province":"VA",
    "sg:tags":[
        "house"
    ],
    "wof:name":"Jones Construction Co",
    "wof:placetype":"venue"
},
  "geometry": {"coordinates":[-77.162008,37.548202],"type":"Point"}
}