{
  "type": "Feature",
  "properties": {
    "addr:full":"6518 Berkshire Dr Alexandria VA 22310",
    "addr:housenumber":"6518",
    "addr:postcode":"22310",
    "addr:street":"Berkshire Dr",
    "iso:country":"US",
    "sg:address":"6518 Berkshire Dr",
    "sg:city":"Alexandria",
    "sg:classifiers":[
        {
            "category":"Professional",
            "type":"Services"
        }
    ],
    "sg:phone":"+1 703 329 3015",
    "sg:postcode":"22310",
    "sg:province":"VA",
    "wof:name":"Bryan Frassmann",
    "wof:placetype":"venue"
},
  "geometry": {"coordinates":[-77.09578399999999,38.776754],"type":"Point"}
}