{
  "type": "Feature",
  "properties": {
    "addr:full":"2323 Memorial Ave Lynchburg VA 24501",
    "addr:housenumber":"2323",
    "addr:postcode":"24501",
    "addr:street":"Memorial Ave",
    "iso:country":"US",
    "sg:address":"2323 Memorial Ave",
    "sg:city":"Lynchburg",
    "sg:classifiers":[
        {
            "category":"Wholesale",
            "subcategory":"Machinery & Supplies",
            "type":"Manufacturing & Wholesale Goods"
        },
        {
            "category":"Shopping",
            "subcategory":"Beauty & Cosmetics",
            "type":"Retail Goods"
        }
    ],
    "sg:phone":"+1 434 528 9689",
    "sg:postcode":"24501",
    "sg:province":"VA",
    "sg:tags":[
        "salon",
        "miscellaneous",
        "store"
    ],
    "wof:name":"A Plus Beauty Supply",
    "wof:placetype":"venue"
},
  "geometry": {"coordinates":[-79.167226,37.403697],"type":"Point"}
}