{
  "type": "Feature",
  "properties": {
    "addr:full":"5377 Telephone Rd Warrenton VA 20187",
    "addr:housenumber":"5377",
    "addr:postcode":"20187",
    "addr:street":"Telephone Rd",
    "iso:country":"US",
    "sg:address":"5377 Telephone Rd",
    "sg:city":"Warrenton",
    "sg:classifiers":[
        {
            "category":"Autos & Motor Vehicles",
            "subcategory":"Automobile Sales",
            "type":"Retail Goods"
        }
    ],
    "sg:phone":"+1 540 347 3005",
    "sg:postcode":"20187",
    "sg:province":"VA",
    "sg:tags":[
        "truck"
    ],
    "wof:name":"Wright Truck Sales",
    "wof:placetype":"venue"
},
  "geometry": {"coordinates":[-77.733158,38.760674],"type":"Point"}
}