{
  "type": "Feature",
  "properties": {
    "addr:full":"8529 Pappas Way Annandale VA 22003",
    "addr:housenumber":"8529",
    "addr:postcode":"22003",
    "addr:street":"Pappas Way",
    "iso:country":"US",
    "sg:address":"8529 Pappas Way",
    "sg:city":"Annandale",
    "sg:classifiers":[
        {
            "category":"Professional",
            "subcategory":"Management & Consulting",
            "type":"Services"
        }
    ],
    "sg:phone":"+1 703 978 4684",
    "sg:postcode":"22003",
    "sg:province":"VA",
    "sg:tags":[
        "consultant"
    ],
    "wof:name":"Carl's Consulting",
    "wof:placetype":"venue"
},
  "geometry": {"coordinates":[-77.241079,38.822185],"type":"Point"}
}