{
  "type": "Feature",
  "properties": {
    "addr:full":"6862 Elm St Mc Lean VA 22101",
    "addr:housenumber":"6862",
    "addr:postcode":"22101",
    "addr:street":"Elm St Mc Lean",
    "iso:country":"US",
    "sg:address":"6862 Elm St",
    "sg:city":"Mc Lean",
    "sg:classifiers":[
        {
            "category":"Real Estate",
            "subcategory":"Real Estate Services",
            "type":"Services"
        }
    ],
    "sg:phone":"+1 703 790 9150",
    "sg:postcode":"22101",
    "sg:province":"VA",
    "sg:tags":[
        "company",
        "title"
    ],
    "wof:name":"Equitable Title & Escrow",
    "wof:placetype":"venue"
},
  "geometry": {"coordinates":[-77.181415,38.937093],"type":"Point"}
}