{
  "type": "Feature",
  "properties": {
    "iso:country":"US",
    "sg:address":"10 Alphus St",
    "sg:city":"Poquoson",
    "sg:classifiers":[
        {
            "category":"Retail",
            "subcategory":"Auto Repair",
            "type":"Services"
        }
    ],
    "sg:phone":"+1 757 874 7895",
    "sg:postcode":"23662",
    "sg:province":"VA",
    "sg:tags":[
        "repairing",
        "automobile"
    ],
    "wof:name":"Cawley's Service Ctr",
    "wof:placetype":"venue"
},
  "geometry": {"coordinates":[-76.39201799999999,37.122437],"type":"Point"}
}