{
  "type": "Feature",
  "properties": {
    "addr:full":"4300 Wilson Blvd Arlington VA 22203",
    "addr:housenumber":"4300",
    "addr:postcode":"22203",
    "addr:street":"Wilson Blvd",
    "iso:country":"US",
    "sg:address":"4300 Wilson Blvd",
    "sg:city":"Arlington",
    "sg:classifiers":[
        {
            "category":"Restaurant",
            "type":"Food & Drink"
        }
    ],
    "sg:phone":"+1 866 377 7216",
    "sg:postcode":"22203",
    "sg:province":"VA",
    "sg:tags":[
        "thai"
    ],
    "sg:website":"http://www.1genthaicuisine.com",
    "wof:name":"1 Gen Thai",
    "wof:placetype":"venue"
},
  "geometry": {"coordinates":[-77.112488,38.880058],"type":"Point"}
}