{
  "type": "Feature",
  "properties": {
    "iso:country":"US",
    "sg:address":"437 Catlett Mountain Rd",
    "sg:city":"Front Royal",
    "sg:classifiers":[
        {
            "category":"Building & Trades",
            "subcategory":"Construction",
            "type":"Services"
        }
    ],
    "sg:phone":"+1 703 237 3720",
    "sg:postcode":"22630",
    "sg:province":"VA",
    "sg:tags":[
        "painter"
    ],
    "wof:name":"Gray's Superior Painters",
    "wof:placetype":"venue"
},
  "geometry": {"coordinates":[-78.237334,38.917323],"type":"Point"}
}