{
  "type": "Feature",
  "properties": {
    "addr:full":"2186 John Wayland Hwy Harrisonburg VA 22801",
    "addr:housenumber":"2186",
    "addr:postcode":"22801",
    "addr:street":"John Wayland Hwy",
    "iso:country":"US",
    "sg:address":"2186 John Wayland Hwy",
    "sg:city":"Harrisonburg",
    "sg:classifiers":[
        {
            "category":"Professional",
            "subcategory":"Accounting & Tax Preparation",
            "type":"Services"
        },
        {
            "category":"Banks & Credit Unions",
            "subcategory":"Financial Services",
            "type":"Services"
        }
    ],
    "sg:phone":"+1 540 801 0153",
    "sg:postcode":"22801",
    "sg:province":"VA",
    "sg:tags":[
        "return",
        "preparation-business",
        "taxes-consultants",
        "loan",
        "reporting",
        "representative",
        "alternative",
        "bookkeeping"
    ],
    "sg:website":"http://www.hrblock.com",
    "wof:name":"H&R Block",
    "wof:placetype":"venue"
},
  "geometry": {"coordinates":[-78.90913999999999,38.430615],"type":"Point"}
}