{
  "type": "Feature",
  "properties": {
    "addr:full":"5 Leahs Trce Hampton VA 23666",
    "addr:housenumber":"5",
    "addr:postcode":"23666",
    "addr:street":"Leahs Trce",
    "iso:country":"US",
    "sg:address":"5 Leahs Trce",
    "sg:city":"Hampton",
    "sg:classifiers":[
        {
            "category":"Building & Trades",
            "subcategory":"Construction",
            "type":"Services"
        }
    ],
    "sg:phone":"+1 757 827 0719",
    "sg:postcode":"23666",
    "sg:province":"VA",
    "sg:tags":[
        "general",
        "contractor"
    ],
    "wof:name":"All Doors Installed By Todd",
    "wof:placetype":"venue"
},
  "geometry": {"coordinates":[-76.443483,37.036434],"type":"Point"}
}