{
  "type": "Feature",
  "properties": {
    "addr:full":"2120 Grandy Ave Norfolk VA 23504",
    "addr:housenumber":"2120",
    "addr:postcode":"23504",
    "addr:street":"Grandy Ave",
    "iso:country":"US",
    "sg:address":"2120 Grandy Ave",
    "sg:city":"Norfolk",
    "sg:classifiers":[
        {
            "category":"Building & Trades",
            "subcategory":"Plumbing",
            "type":"Services"
        }
    ],
    "sg:phone":"+1 757 640 8891",
    "sg:postcode":"23504",
    "sg:province":"VA",
    "sg:tags":[
        "plumbing",
        "contractor",
        "work",
        "heating",
        "mechanical"
    ],
    "wof:name":"Myers Plumbing & Heating Co",
    "wof:placetype":"venue"
},
  "geometry": {"coordinates":[-76.249301,36.861759],"type":"Point"}
}