{
  "type": "Feature",
  "properties": {
    "addr:full":"11869 Dunlop Ct Reston VA 20191",
    "addr:housenumber":"11869",
    "addr:postcode":"20191",
    "addr:street":"Dunlop Ct",
    "iso:country":"US",
    "sg:address":"11869 Dunlop Ct",
    "sg:city":"Reston",
    "sg:classifiers":[
        {
            "category":"Building & Trades",
            "subcategory":"Plumbing",
            "type":"Services"
        }
    ],
    "sg:phone":"+1 703 476 0191",
    "sg:postcode":"20191",
    "sg:province":"VA",
    "sg:tags":[
        "water",
        "heater",
        "repair"
    ],
    "sg:website":"http://www.daystarrplumbing.com",
    "wof:name":"Daystarr Plumbing",
    "wof:placetype":"venue"
},
  "geometry": {"coordinates":[-77.355903,38.93179],"type":"Point"}
}