{
  "type": "Feature",
  "properties": {
    "addr:full":"11620 W Broad St Henrico VA 23233",
    "addr:housenumber":"11620",
    "addr:postcode":"23233",
    "addr:street":"W Broad St",
    "iso:country":"US",
    "sg:address":"11620 W Broad St",
    "sg:city":"Henrico",
    "sg:classifiers":[
        {
            "category":"Shopping",
            "subcategory":"Optical Goods",
            "type":"Retail Goods"
        },
        {
            "category":"Health Services",
            "subcategory":"Optometrist",
            "type":"Services"
        },
        {
            "category":"Health Services",
            "subcategory":"Doctor",
            "type":"Services"
        },
        {
            "category":"Shopping",
            "subcategory":"Optician",
            "type":"Retail Goods"
        }
    ],
    "sg:phone":"+1 804 360 7040",
    "sg:postcode":"23233",
    "sg:province":"VA",
    "sg:tags":[
        "lens",
        "eyeglass",
        "surgeon",
        "contact",
        "physician"
    ],
    "wof:name":"Jonathan Stoller & Assoc",
    "wof:placetype":"venue"
},
  "geometry": {"coordinates":[-77.61372299999999,37.651767],"type":"Point"}
}