{
  "type": "Feature",
  "properties": {
    "addr:full":"4179 Peaks Rd Bedford VA 24523",
    "addr:housenumber":"4179",
    "addr:postcode":"24523",
    "addr:street":"Peaks Rd",
    "iso:country":"US",
    "sg:address":"4179 Peaks Rd",
    "sg:city":"Bedford",
    "sg:classifiers":[
        {
            "category":"Retail",
            "subcategory":"Auto Repair",
            "type":"Services"
        }
    ],
    "sg:phone":"+1 540 586 2975",
    "sg:postcode":"24523",
    "sg:province":"VA",
    "sg:tags":[
        "alternator",
        "rebuild",
        "starter"
    ],
    "wof:name":"Carter Rebuilder",
    "wof:placetype":"venue"
},
  "geometry": {"coordinates":[-79.550444,37.386289],"type":"Point"}
}