{
  "type": "Feature",
  "properties": {
    "addr:full":"101 Keesling Ave NW Salem VA 24153",
    "addr:housenumber":"101",
    "addr:postcode":"24153",
    "addr:street":"Keesling Ave Nw",
    "iso:country":"US",
    "sg:address":"101 Keesling Ave NW",
    "sg:city":"Salem",
    "sg:classifiers":[
        {
            "category":"Organizations",
            "subcategory":"Religious Organization",
            "type":"Services"
        }
    ],
    "sg:phone":"+1 540 387 1311",
    "sg:postcode":"24153",
    "sg:province":"VA",
    "wof:name":"New Hope Presbyterian Church",
    "wof:placetype":"venue"
},
  "geometry": {"coordinates":[-80.10811200000001,37.282658],"type":"Point"}
}