{
  "type": "Feature",
  "properties": {
    "addr:full":"7204 University Dr Richmond VA 23229",
    "addr:housenumber":"7204",
    "addr:postcode":"23229",
    "addr:street":"University Dr",
    "iso:country":"US",
    "sg:address":"7204 University Dr",
    "sg:city":"Richmond",
    "sg:classifiers":[
        {
            "category":"Professional",
            "subcategory":"Management & Consulting",
            "type":"Services"
        }
    ],
    "sg:phone":"+1 804 282 9299",
    "sg:postcode":"23229",
    "sg:province":"VA",
    "wof:name":"Kinton Stllngs Mktg Media Cons",
    "wof:placetype":"venue"
},
  "geometry": {"coordinates":[-77.552424,37.577121],"type":"Point"}
}