{
  "type": "Feature",
  "properties": {
    "addr:full":"1011 Falls Ridge Rd Christiansburg VA 24073",
    "addr:housenumber":"1011",
    "addr:postcode":"24073",
    "addr:street":"Falls Ridge Rd",
    "iso:country":"US",
    "sg:address":"1011 Falls Ridge Rd",
    "sg:city":"Christiansburg",
    "sg:classifiers":[
        {
            "category":"Banks & Credit Unions",
            "subcategory":"Bank",
            "type":"Services"
        },
        {
            "category":"Shopping",
            "subcategory":"Used Merchandise",
            "type":"Retail Goods"
        }
    ],
    "sg:phone":"+1 540 382 2873",
    "sg:postcode":"24073",
    "sg:province":"VA",
    "sg:tags":[
        "shop",
        "second",
        "resale",
        "hand"
    ],
    "sg:website":"http://www.endangered.com",
    "wof:name":"Endangered Species Inc",
    "wof:placetype":"venue"
},
  "geometry": {"coordinates":[-80.32537600000001,37.193923],"type":"Point"}
}