{
  "type": "Feature",
  "properties": {
    "addr:full":"355 Shady Grove Rd Martinsville VA 24112",
    "addr:housenumber":"355",
    "addr:postcode":"24112",
    "addr:street":"Shady Grove Rd",
    "iso:country":"US",
    "sg:address":"355 Shady Grove Rd",
    "sg:city":"Martinsville",
    "sg:classifiers":[
        {
            "category":"Professional",
            "type":"Services"
        }
    ],
    "sg:phone":"+1 276 632 8681",
    "sg:postcode":"24112",
    "sg:province":"VA",
    "wof:name":"Bread of Life Mission",
    "wof:placetype":"venue"
},
  "geometry": {"coordinates":[-79.813485,36.805649],"type":"Point"}
}