{
  "type": "Feature",
  "properties": {
    "iso:country":"US",
    "sg:address":"1 N 5th St",
    "sg:city":"Richmond",
    "sg:classifiers":[
        {
            "category":"Professional",
            "subcategory":"Lawyer & Legal Services",
            "type":"Services"
        }
    ],
    "sg:phone":"+1 804 780 0880",
    "sg:postcode":"23219",
    "sg:province":"VA",
    "sg:tags":[
        "attorney"
    ],
    "sg:website":"www.ellysonlaw.com",
    "wof:name":"William G Ellyson",
    "wof:placetype":"venue"
},
  "geometry": {"coordinates":[-77.43908399999999,37.54123],"type":"Point"}
}