{
  "type": "Feature",
  "properties": {
    "addr:full":"1230 Firehouse Dr Louisa VA 23093",
    "addr:housenumber":"1230",
    "addr:postcode":"23093",
    "addr:street":"Firehouse Dr",
    "iso:country":"US",
    "sg:address":"1230 Firehouse Dr",
    "sg:city":"Louisa",
    "sg:classifiers":[
        {
            "category":"Organizations",
            "subcategory":"Religious Organization",
            "type":"Services"
        }
    ],
    "sg:phone":"+1 540 967 0796",
    "sg:postcode":"23093",
    "sg:province":"VA",
    "wof:name":"Blue Rdge Shores Baptst Church",
    "wof:placetype":"venue"
},
  "geometry": {"coordinates":[-78.031756,38.098907],"type":"Point"}
}