{
  "type": "Feature",
  "properties": {
    "addr:full":"19240 Leesville Rd Lynchburg VA 24502",
    "addr:postcode":"19240;24502",
    "addr:street":"Leesville Rd",
    "iso:country":"US",
    "sg:address":"19240 Leesville Rd",
    "sg:city":"Lynchburg",
    "sg:classifiers":[
        {
            "category":"Building & Trades",
            "subcategory":"Construction",
            "type":"Services"
        }
    ],
    "sg:phone":"+1 434 239 1261",
    "sg:postcode":"24502",
    "sg:province":"VA",
    "sg:tags":[
        "excavating",
        "grading"
    ],
    "wof:name":"Marshall Schmitt Inc",
    "wof:placetype":"venue"
},
  "geometry": {"coordinates":[-79.22983000000001,37.323784],"type":"Point"}
}