{
  "type": "Feature",
  "properties": {
    "addr:full":"105 S Pantops Dr Charlottesville VA 22911",
    "addr:housenumber":"105",
    "addr:postcode":"22911",
    "addr:street":"S Pantops Dr",
    "iso:country":"US",
    "sg:address":"105 S Pantops Dr",
    "sg:city":"Charlottesville",
    "sg:classifiers":[
        {
            "category":"Professional",
            "subcategory":"Computer Services",
            "type":"Services"
        }
    ],
    "sg:phone":"+1 434 984 1112",
    "sg:postcode":"22911",
    "sg:province":"VA",
    "sg:tags":[
        "consultant",
        "designer"
    ],
    "wof:name":"Dominion Digital",
    "wof:placetype":"venue"
},
  "geometry": {"coordinates":[-78.455079,38.03164],"type":"Point"}
}