{
  "type": "Feature",
  "properties": {
    "iso:country":"US",
    "sg:address":"493 Crowell Ln",
    "sg:city":"Lynchburg",
    "sg:classifiers":[
        {
            "category":"Professional",
            "subcategory":"Computer Services",
            "type":"Services"
        }
    ],
    "sg:phone":"+1 434 239 3049",
    "sg:postcode":"24502",
    "sg:province":"VA",
    "sg:tags":[
        "repair"
    ],
    "wof:name":"Porta-Tech Svc",
    "wof:placetype":"venue"
},
  "geometry": {"coordinates":[-79.23884700000001,37.331348],"type":"Point"}
}