{
  "type": "Feature",
  "properties": {
    "addr:full":"10650 Page Ave Fairfax VA 22030",
    "addr:housenumber":"10650",
    "addr:postcode":"22030",
    "addr:street":"Page Ave",
    "iso:country":"US",
    "sg:address":"10650 Page Ave",
    "sg:city":"Fairfax",
    "sg:classifiers":[
        {
            "category":"Education",
            "subcategory":"School",
            "type":"Public Place"
        },
        {
            "category":"Government",
            "subcategory":"Jail",
            "type":"Public Place"
        }
    ],
    "sg:phone":"+1 703 246 2844",
    "sg:postcode":"22030",
    "sg:province":"VA",
    "sg:tags":[
        "county",
        "govt",
        "institution"
    ],
    "wof:name":"Juvenile Detention Center",
    "wof:placetype":"venue"
},
  "geometry": {"coordinates":[-77.311468,38.845737],"type":"Point"}
}