{
  "type": "Feature",
  "properties": {
    "iso:country":"US",
    "sg:address":"3452 Lyrac St",
    "sg:city":"Oakton",
    "sg:classifiers":[
        {
            "category":"Professional",
            "subcategory":"Testing Lab",
            "type":"Services"
        }
    ],
    "sg:phone":"+1 703 758 8381",
    "sg:postcode":"22124",
    "sg:province":"VA",
    "sg:tags":[
        "laboratory"
    ],
    "wof:name":"Trent Severn",
    "wof:placetype":"venue"
},
  "geometry": {"coordinates":[-77.35645100000001,38.883123],"type":"Point"}
}