{
  "type": "Feature",
  "properties": {
    "iso:country":"US",
    "sg:address":"1912 Woodford Rd Ste 100",
    "sg:city":"Vienna",
    "sg:classifiers":[
        {
            "category":"Communications",
            "subcategory":"Newspaper",
            "type":"Services"
        }
    ],
    "sg:phone":"+1 703 847 4741",
    "sg:postcode":"22182",
    "sg:province":"VA",
    "sg:tags":[
        "print",
        "medium"
    ],
    "wof:name":"The Bureau of National Affairs Inc",
    "wof:placetype":"venue"
},
  "geometry": {"coordinates":[-77.233299,38.914398],"type":"Point"}
}