{
  "type": "Feature",
  "properties": {
    "addr:full":"3600 Greenmoor Ct Chesapeake VA 23322",
    "addr:housenumber":"3600",
    "addr:postcode":"23322",
    "addr:street":"Greenmoor Ct",
    "iso:country":"US",
    "sg:address":"3600 Greenmoor Ct",
    "sg:city":"Chesapeake",
    "sg:classifiers":[
        {
            "category":"Professional",
            "subcategory":"Management & Consulting",
            "type":"Services"
        }
    ],
    "sg:phone":"+1 757 421 4614",
    "sg:postcode":"23322",
    "sg:province":"VA",
    "sg:tags":[
        "business"
    ],
    "wof:name":"Marable Assoc Consulting",
    "wof:placetype":"venue"
},
  "geometry": {"coordinates":[-76.267149,36.595345],"type":"Point"}
}