{
  "type": "Feature",
  "properties": {
    "iso:country":"US",
    "sg:address":"7778 Bracken Ct",
    "sg:city":"Manassas",
    "sg:classifiers":[
        {
            "category":"Building & Trades",
            "subcategory":"Construction",
            "type":"Services"
        }
    ],
    "sg:phone":"+1 703 257 1686",
    "sg:postcode":"20111",
    "sg:province":"VA",
    "sg:tags":[
        "carpentry",
        "contractor"
    ],
    "wof:name":"J J L Carpentry Inc",
    "wof:placetype":"venue"
},
  "geometry": {"coordinates":[-77.434776,38.719995],"type":"Point"}
}