{
  "type": "Feature",
  "properties": {
    "iso:country":"US",
    "sg:address":"7012 Maple Tree Ln",
    "sg:city":"Springfield",
    "sg:classifiers":[
        {
            "category":"Organizations",
            "subcategory":"Religious Organization",
            "type":"Services"
        }
    ],
    "sg:phone":"+1 703 451 7076",
    "sg:postcode":"22152",
    "sg:province":"VA",
    "wof:name":"Jones  Juliana",
    "wof:placetype":"venue"
},
  "geometry": {"coordinates":[-77.222049,38.763257],"type":"Point"}
}