{
  "type": "Feature",
  "properties": {
    "addr:full":"11703 Chester Rd Chester VA 23831",
    "addr:housenumber":"11703",
    "addr:postcode":"23831",
    "addr:street":"Chester Rd",
    "iso:country":"US",
    "sg:address":"11703 Chester Rd",
    "sg:city":"Chester",
    "sg:classifiers":[
        {
            "category":"Health Services",
            "subcategory":"Doctor",
            "type":"Services"
        }
    ],
    "sg:phone":"+1 804 748 2225",
    "sg:postcode":"23831",
    "sg:province":"VA",
    "sg:tags":[
        "dentist"
    ],
    "wof:name":"Reed D Prugh DDS",
    "wof:placetype":"venue"
},
  "geometry": {"coordinates":[-77.443147,37.363293],"type":"Point"}
}