{
  "type": "Feature",
  "properties": {
    "iso:country":"US",
    "sg:address":"1305 False Creek Way",
    "sg:city":"Chesapeake",
    "sg:classifiers":[
        {
            "category":"Professional",
            "subcategory":"Business Services",
            "type":"Services"
        }
    ],
    "sg:phone":"+1 757 410 4498",
    "sg:postcode":"23322",
    "sg:province":"VA",
    "wof:name":"Design By Mony",
    "wof:placetype":"venue"
},
  "geometry": {"coordinates":[-76.287576,36.724579],"type":"Point"}
}