{
  "type": "Feature",
  "properties": {
    "addr:full":"5431 Potomac Ave NW Washington MD 20016",
    "addr:housenumber":"5431",
    "addr:postcode":"20016",
    "addr:street":"Potomac Ave Nw",
    "iso:country":"US",
    "sg:address":"5431 Potomac Ave NW",
    "sg:city":"Washington",
    "sg:classifiers":[
        {
            "category":"Health Services",
            "subcategory":"Doctor",
            "type":"Services"
        }
    ],
    "sg:phone":"+1 202 784 3400",
    "sg:postcode":"20016",
    "sg:province":"MD",
    "sg:tags":[
        "physician",
        "surgeon"
    ],
    "wof:name":"Susan M Ascher MD",
    "wof:placetype":"venue"
},
  "geometry": {"coordinates":[-77.10938400000001,38.927908],"type":"Point"}
}