{
  "type": "Feature",
  "properties": {
    "addr:full":"117 S Court St Luray VA 22835",
    "addr:housenumber":"117",
    "addr:postcode":"22835",
    "addr:street":"S Court St",
    "iso:country":"US",
    "sg:address":"117 S Court St",
    "sg:city":"Luray",
    "sg:classifiers":[
        {
            "category":"Government",
            "subcategory":"Office",
            "type":"Public Place"
        }
    ],
    "sg:phone":"+1 540 743 1003",
    "sg:postcode":"22835",
    "sg:province":"VA",
    "wof:name":"Page County Comprehensive Svc",
    "wof:placetype":"venue"
},
  "geometry": {"coordinates":[-78.464512,38.664179],"type":"Point"}
}