{
  "type": "Feature",
  "properties": {
    "addr:full":"8492 Centreville Rd Manassas VA 20111",
    "addr:housenumber":"8492",
    "addr:postcode":"20111",
    "addr:street":"Centreville Rd",
    "iso:country":"US",
    "sg:address":"8492 Centreville Rd",
    "sg:city":"Manassas",
    "sg:classifiers":[
        {
            "category":"Building & Trades",
            "subcategory":"Equipment Rental",
            "type":"Services"
        }
    ],
    "sg:phone":"+1 703 257 4692",
    "sg:postcode":"20111",
    "sg:province":"VA",
    "sg:tags":[
        "leasing"
    ],
    "wof:name":"Aaarons",
    "wof:placetype":"venue"
},
  "geometry": {"coordinates":[-77.45266700000001,38.772114],"type":"Point"}
}