{
  "type": "Feature",
  "properties": {
    "addr:full":"311 Old Virginia St Urbanna VA 23175",
    "addr:housenumber":"311",
    "addr:postcode":"23175",
    "addr:street":"Old Virginia St",
    "iso:country":"US",
    "sg:address":"311 Old Virginia St",
    "sg:city":"Urbanna",
    "sg:classifiers":[
        {
            "category":"Shopping",
            "subcategory":"Clothing, Apparel, & Fashions",
            "type":"Retail Goods"
        }
    ],
    "sg:phone":"+1 804 758 3756",
    "sg:postcode":"23175",
    "sg:province":"VA",
    "sg:website":"www.cyndysbynn.com",
    "wof:name":"Cyndy's Bynn",
    "wof:placetype":"venue"
},
  "geometry": {"coordinates":[-76.662395,37.67086],"type":"Point"}
}