{
  "type": "Feature",
  "properties": {
    "addr:full":"5046 Richmond Rd Keswick VA 22947",
    "addr:housenumber":"5046",
    "addr:postcode":"22947",
    "addr:street":"Richmond Rd",
    "iso:country":"US",
    "sg:address":"5046 Richmond Rd",
    "sg:city":"Keswick",
    "sg:classifiers":[
        {
            "category":"Building & Trades",
            "subcategory":"Construction",
            "type":"Services"
        }
    ],
    "sg:phone":"+1 434 293 6793",
    "sg:postcode":"22947",
    "sg:province":"VA",
    "sg:tags":[
        "contractor"
    ],
    "wof:name":"CM Contracting of VA Inc",
    "wof:placetype":"venue"
},
  "geometry": {"coordinates":[-78.32618600000001,37.986302],"type":"Point"}
}