{
  "type": "Feature",
  "properties": {
    "iso:country":"US",
    "sg:address":"4413 Wishart Rd",
    "sg:city":"Virginia Beach",
    "sg:classifiers":[
        {
            "category":"Organizations",
            "subcategory":"Religious Organization",
            "type":"Services"
        }
    ],
    "sg:phone":"+1 757 464 4941",
    "sg:postcode":"23455",
    "sg:province":"VA",
    "sg:tags":[
        "church"
    ],
    "sg:website":"www.vbfcn.org",
    "wof:name":"First Church Of The Nazarene",
    "wof:placetype":"venue"
},
  "geometry": {"coordinates":[-76.126116,36.874517],"type":"Point"}
}