{
  "type": "Feature",
  "properties": {
    "iso:country":"US",
    "sg:address":"2007 15th St N Ste 1",
    "sg:city":"Arlington",
    "sg:classifiers":[
        {
            "category":"Professional",
            "subcategory":"Lawyer & Legal Services",
            "type":"Services"
        }
    ],
    "sg:phone":"+1 703 248 0348",
    "sg:postcode":"22201",
    "sg:province":"VA",
    "wof:name":"Harr Karla Lwyr",
    "wof:placetype":"venue"
},
  "geometry": {"coordinates":[-77.08229799999999,38.890999],"type":"Point"}
}