{
  "type": "Feature",
  "properties": {
    "addr:full":"8300 Sudley Rd Manassas VA 20109",
    "addr:housenumber":"8300",
    "addr:postcode":"20109",
    "addr:street":"Sudley Rd",
    "iso:country":"US",
    "sg:address":"8300 Sudley Rd",
    "sg:city":"Manassas",
    "sg:classifiers":[
        {
            "category":"Shopping",
            "subcategory":"Clothing, Apparel, & Fashions",
            "type":"Retail Goods"
        }
    ],
    "sg:phone":"+1 703 335 2790",
    "sg:postcode":"20109",
    "sg:province":"VA",
    "wof:name":"Limited",
    "wof:placetype":"venue"
},
  "geometry": {"coordinates":[-77.501817,38.774311],"type":"Point"}
}