{
  "type": "Feature",
  "properties": {
    "addr:full":"12132 Paige Rd Woodford VA 22580",
    "addr:housenumber":"12132",
    "addr:postcode":"22580",
    "addr:street":"Paige Rd",
    "iso:country":"US",
    "sg:address":"12132 Paige Rd",
    "sg:city":"Woodford",
    "sg:phone":"+1 804 448 2848",
    "sg:postcode":"22580",
    "sg:province":"VA",
    "wof:name":"Edward G Thornton",
    "wof:placetype":"venue"
},
  "geometry": {"coordinates":[-77.43521800000001,38.074955],"type":"Point"}
}