{
  "type": "Feature",
  "properties": {
    "addr:full":"750 Miller Dr SE Leesburg VA 20175",
    "addr:housenumber":"750",
    "addr:postcode":"20175",
    "addr:street":"Miller Dr Se",
    "iso:country":"US",
    "sg:address":"750 Miller Dr SE",
    "sg:city":"Leesburg",
    "sg:classifiers":[
        {
            "category":"Autos & Motor Vehicles",
            "subcategory":"Automobile Sales",
            "type":"Retail Goods"
        }
    ],
    "sg:phone":"+1 703 669 3611",
    "sg:postcode":"20175",
    "sg:province":"VA",
    "wof:name":"Mid Atlantic Money",
    "wof:placetype":"venue"
},
  "geometry": {"coordinates":[-77.555932,39.082748],"type":"Point"}
}