{
  "type": "Feature",
  "properties": {
    "iso:country":"US",
    "sg:address":"505 E Main St",
    "sg:city":"Radford",
    "sg:classifiers":[
        {
            "category":"Retail",
            "subcategory":"Car Wash",
            "type":"Services"
        }
    ],
    "sg:phone":"+1 540 731 8303",
    "sg:postcode":"24141",
    "sg:province":"VA",
    "sg:tags":[
        "carwash"
    ],
    "wof:name":"Radford Universal Car Care",
    "wof:placetype":"venue"
},
  "geometry": {"coordinates":[-80.543102,37.136187],"type":"Point"}
}