{
  "type": "Feature",
  "properties": {
    "addr:full":"820 University City Blvd Blacksburg VA 24060",
    "addr:housenumber":"820",
    "addr:postcode":"24060",
    "addr:street":"University City Blvd",
    "iso:country":"US",
    "sg:address":"820 University City Blvd",
    "sg:city":"Blacksburg",
    "sg:classifiers":[
        {
            "category":"Health Services",
            "subcategory":"Doctor",
            "type":"Services"
        }
    ],
    "sg:phone":"+1 540 961 5288",
    "sg:postcode":"24060",
    "sg:province":"VA",
    "sg:tags":[
        "physician",
        "surgeon"
    ],
    "wof:name":"Medical Associates Of Sw Va",
    "wof:placetype":"venue"
},
  "geometry": {"coordinates":[-80.433769,37.235357],"type":"Point"}
}