{
  "type": "Feature",
  "properties": {
    "iso:country":"US",
    "sg:address":"4309 Brighton Ln",
    "sg:city":"Chesapeake",
    "sg:classifiers":[
        {
            "category":"Home & Garden",
            "subcategory":"Building Materials",
            "type":"Retail Goods"
        }
    ],
    "sg:phone":"+1 757 484 4814",
    "sg:postcode":"23321",
    "sg:province":"VA",
    "sg:tags":[
        "windows"
    ],
    "wof:name":"Window King Of America",
    "wof:placetype":"venue"
},
  "geometry": {"coordinates":[-76.409955,36.849679],"type":"Point"}
}