{
  "type": "Feature",
  "properties": {
    "addr:full":"5704 W Broad St Richmond VA 23230",
    "addr:housenumber":"5704",
    "addr:postcode":"23230",
    "addr:street":"W Broad St",
    "iso:country":"US",
    "sg:address":"5704 W Broad St",
    "sg:city":"Richmond",
    "sg:classifiers":[
        {
            "category":"Shopping",
            "type":"Retail Goods"
        }
    ],
    "sg:phone":"+1 804 672 0137",
    "sg:postcode":"23230",
    "sg:province":"VA",
    "sg:tags":[
        "pet",
        "food",
        "supply"
    ],
    "wof:name":"Petsmart",
    "wof:placetype":"venue"
},
  "geometry": {"coordinates":[-77.503716,37.590144],"type":"Point"}
}