{
  "type": "Feature",
  "properties": {
    "iso:country":"US",
    "sg:address":"2100 Mount Vernon Ave",
    "sg:city":"Alexandria",
    "sg:classifiers":[
        {
            "category":"Personal",
            "subcategory":"Beauty Salon",
            "type":"Services"
        }
    ],
    "sg:phone":"+1 703 683 2400",
    "sg:postcode":"22301",
    "sg:province":"VA",
    "sg:tags":[
        "hair"
    ],
    "sg:website":"www.annewelshsalon.com/",
    "wof:name":"Anne Welsh Salon",
    "wof:placetype":"venue"
},
  "geometry": {"coordinates":[-77.058742,38.824841],"type":"Point"}
}