{
  "type": "Feature",
  "properties": {
    "addr:full":"725 King St Alexandria VA 22314",
    "addr:housenumber":"725",
    "addr:postcode":"22314",
    "addr:street":"King St",
    "iso:country":"US",
    "sg:address":"725 King St",
    "sg:city":"Alexandria",
    "sg:classifiers":[
        {
            "category":"Restaurant",
            "type":"Food & Drink"
        }
    ],
    "sg:phone":"+1 703 548 8500",
    "sg:postcode":"22314",
    "sg:province":"VA",
    "sg:tags":[
        "pizza",
        "italian"
    ],
    "sg:website":"http://www.bertuccis.com",
    "wof:name":"Bertucci's",
    "wof:placetype":"venue"
},
  "geometry": {"coordinates":[-77.04728900000001,38.805123],"type":"Point"}
}