{
  "type": "Feature",
  "properties": {
    "iso:country":"US",
    "sg:address":"23 S 13th St",
    "sg:city":"Richmond",
    "sg:classifiers":[
        {
            "category":"Government",
            "subcategory":"Court House",
            "type":"Public Place"
        }
    ],
    "sg:phone":"+1 804 646 3448",
    "sg:postcode":"23219",
    "sg:province":"VA",
    "sg:tags":[
        "counsel",
        "prosecution",
        "legal"
    ],
    "wof:name":"City Attorney- Assistant",
    "wof:placetype":"venue"
},
  "geometry": {"coordinates":[-77.4332,37.535948],"type":"Point"}
}