{
  "type": "Feature",
  "properties": {
    "addr:full":"109 N Main St Woodstock VA 22664",
    "addr:housenumber":"109",
    "addr:postcode":"22664",
    "addr:street":"N Main St",
    "iso:country":"US",
    "sg:address":"109 N Main St",
    "sg:city":"Woodstock",
    "sg:classifiers":[
        {
            "category":"Professional",
            "subcategory":"Lawyer & Legal Services",
            "type":"Services"
        }
    ],
    "sg:phone":"+1 540 459 4941",
    "sg:postcode":"22664",
    "sg:province":"VA",
    "sg:tags":[
        "attorney",
        "practice"
    ],
    "wof:name":"Old Dominion Local Probation L",
    "wof:placetype":"venue"
},
  "geometry": {"coordinates":[-78.505269,38.881854],"type":"Point"}
}