{
  "type": "Feature",
  "properties": {
    "addr:full":"9275 Shelton Pointe Dr Mechanicsville VA 23116",
    "addr:housenumber":"9275",
    "addr:postcode":"23116",
    "addr:street":"Shelton Pointe Dr",
    "iso:country":"US",
    "sg:address":"9275 Shelton Pointe Dr",
    "sg:city":"Mechanicsville",
    "sg:classifiers":[
        {
            "category":"Professional",
            "type":"Services"
        }
    ],
    "sg:phone":"+1 804 559 7325",
    "sg:postcode":"23116",
    "sg:province":"VA",
    "wof:name":"Fred W Brumbaugh",
    "wof:placetype":"venue"
},
  "geometry": {"coordinates":[-77.343565,37.659298],"type":"Point"}
}