{
  "type": "Feature",
  "properties": {
    "iso:country":"US",
    "sg:address":"1741 Pimmit Dr",
    "sg:city":"Falls Church",
    "sg:classifiers":[
        {
            "category":"Professional",
            "type":"Services"
        }
    ],
    "sg:phone":"+1 703 883 0534",
    "sg:postcode":"22043",
    "sg:province":"VA",
    "wof:name":"Pradeep Gupta",
    "wof:placetype":"venue"
},
  "geometry": {"coordinates":[-77.1969,38.920551],"type":"Point"}
}