{
  "type": "Feature",
  "properties": {
    "addr:full":"2754 Alleghany Spring Rd Shawsville VA 24162",
    "addr:housenumber":"2754",
    "addr:postcode":"24162",
    "addr:street":"Alleghany Spring Rd",
    "iso:country":"US",
    "sg:address":"2754 Alleghany Spring Rd",
    "sg:city":"Shawsville",
    "sg:classifiers":[
        {
            "category":"Building & Trades",
            "subcategory":"Landscaping Services",
            "type":"Services"
        }
    ],
    "sg:phone":"+1 540 268 2082",
    "sg:postcode":"24162",
    "sg:province":"VA",
    "wof:name":"Sisson Lawn & Landscaping",
    "wof:placetype":"venue"
},
  "geometry": {"coordinates":[-80.25492,37.108622],"type":"Point"}
}