{
  "type": "Feature",
  "properties": {
    "iso:country":"US",
    "sg:address":"18209 Richmond Tpke",
    "sg:city":"Milford",
    "sg:classifiers":[
        {
            "category":"Autos & Motor Vehicles",
            "subcategory":"Auto Supplies",
            "type":"Retail Goods"
        }
    ],
    "sg:phone":"+1 804 633 5289",
    "sg:postcode":"22514",
    "sg:province":"VA",
    "sg:tags":[
        "tire"
    ],
    "wof:name":"Winding Brook Automotive",
    "wof:placetype":"venue"
},
  "geometry": {"coordinates":[-77.334515,38.010295],"type":"Point"}
}