{
  "type": "Feature",
  "properties": {
    "iso:country":"US",
    "sg:address":"321 London Bridge Rd",
    "sg:city":"Virginia Beach",
    "sg:classifiers":[
        {
            "category":"Retail",
            "subcategory":"Repair Shop",
            "type":"Services"
        }
    ],
    "sg:phone":"+1 757 340 8651",
    "sg:postcode":"23454",
    "sg:province":"VA",
    "wof:name":"Harris Upholstery",
    "wof:placetype":"venue"
},
  "geometry": {"coordinates":[-76.05185899999999,36.832252],"type":"Point"}
}