{
  "type": "Feature",
  "properties": {
    "addr:full":"5321 Jessup Ln Woodbridge VA 22193",
    "addr:housenumber":"5321",
    "addr:postcode":"22193",
    "addr:street":"Jessup Ln",
    "iso:country":"US",
    "sg:address":"5321 Jessup Ln",
    "sg:city":"Woodbridge",
    "sg:classifiers":[
        {
            "category":"Education",
            "subcategory":"Vocational School",
            "type":"Public Place"
        }
    ],
    "sg:phone":"+1 703 980 7044",
    "sg:postcode":"22193",
    "sg:province":"VA",
    "sg:tags":[
        "computer"
    ],
    "wof:name":"Etcon",
    "wof:placetype":"venue"
},
  "geometry": {"coordinates":[-77.36735299999999,38.630782],"type":"Point"}
}