{
  "type": "Feature",
  "properties": {
    "addr:full":"9220 Brook Rd Glen Allen VA 23060",
    "addr:housenumber":"9220",
    "addr:postcode":"23060",
    "addr:street":"Brook Rd",
    "iso:country":"US",
    "sg:address":"9220 Brook Rd",
    "sg:city":"Glen Allen",
    "sg:classifiers":[
        {
            "category":"Wholesale",
            "subcategory":"Non-durable Goods",
            "type":"Manufacturing & Wholesale Goods"
        }
    ],
    "sg:phone":"+1 804 545 1000",
    "sg:postcode":"23060",
    "sg:province":"VA",
    "sg:tags":[
        "product",
        "promotional",
        "advertising",
        "specialty"
    ],
    "sg:website":"www.turnkeywow.com",
    "wof:name":"Turnkey Promotions Inc",
    "wof:placetype":"venue"
},
  "geometry": {"coordinates":[-77.459789,37.651682],"type":"Point"}
}