{
  "type": "Feature",
  "properties": {
    "addr:full":"101 N Columbus St Alexandria VA 22314",
    "addr:housenumber":"101",
    "addr:postcode":"22314",
    "addr:street":"N Columbus St",
    "iso:country":"US",
    "sg:address":"101 N Columbus St",
    "sg:city":"Alexandria",
    "sg:classifiers":[
        {
            "category":"Real Estate",
            "subcategory":"Real Estate Agent",
            "type":"Services"
        }
    ],
    "sg:phone":"+1 703 548 1810",
    "sg:postcode":"22314",
    "sg:province":"VA",
    "wof:name":"Rjk Builders Inc",
    "wof:placetype":"venue"
},
  "geometry": {"coordinates":[-77.047867,38.806342],"type":"Point"}
}