{
  "type": "Feature",
  "properties": {
    "iso:country":"US",
    "sg:address":"3899 Burnt Chimney Rd",
    "sg:city":"Wirtz",
    "sg:classifiers":[
        {
            "category":"Farming",
            "subcategory":"Farm & Veterinary Services",
            "type":"Manufacturing & Wholesale Goods"
        }
    ],
    "sg:phone":"+1 540 721 2503",
    "sg:postcode":"24184",
    "sg:province":"VA",
    "sg:tags":[
        "livestock"
    ],
    "wof:name":"Crossroads Angus Farm",
    "wof:placetype":"venue"
},
  "geometry": {"coordinates":[-79.753287,37.087375],"type":"Point"}
}