{
  "type": "Feature",
  "properties": {
    "iso:country":"US",
    "sg:address":"13037 Lee Jackson Memorial Hwy",
    "sg:city":"Fairfax",
    "sg:classifiers":[
        {
            "category":"Structure",
            "subcategory":"Office Building",
            "type":"Public Place"
        }
    ],
    "sg:phone":"+1 703 631 9200",
    "sg:postcode":"22033",
    "sg:province":"VA",
    "sg:tags":[
        "park"
    ],
    "wof:name":"Prudential Preferred Properties Virginia Area",
    "wof:placetype":"venue"
},
  "geometry": {"coordinates":[-77.397732,38.880901],"type":"Point"}
}