{
  "type": "Feature",
  "properties": {
    "addr:full":"1604 Spring Hill Rd Ste 400 Vienna VA 22182",
    "addr:housenumber":"1604",
    "addr:postcode":"22182",
    "addr:street":"Spring Hill Rd Ste 400",
    "iso:country":"US",
    "sg:address":"1604 Spring Hill Rd Ste 400",
    "sg:city":"Vienna",
    "sg:classifiers":[
        {
            "category":"Professional",
            "subcategory":"Employment Agencies",
            "type":"Services"
        }
    ],
    "sg:phone":"+1 703 749 2223",
    "sg:postcode":"22182",
    "sg:province":"VA",
    "wof:name":"Gcs Inc",
    "wof:placetype":"venue"
},
  "geometry": {"coordinates":[-77.24214499999999,38.928058],"type":"Point"}
}