{
  "type": "Feature",
  "properties": {
    "addr:full":"806 Jamison Ave SE Roanoke VA 24013",
    "addr:housenumber":"806",
    "addr:postcode":"24013",
    "addr:street":"Jamison Ave Se",
    "iso:country":"US",
    "sg:address":"806 Jamison Ave SE",
    "sg:city":"Roanoke",
    "sg:classifiers":[
        {
            "category":"Organizations",
            "subcategory":"Religious Organization",
            "type":"Services"
        }
    ],
    "sg:phone":"+1 540 344 4444",
    "sg:postcode":"24013",
    "sg:province":"VA",
    "wof:name":"Metroplitan Cmnty Church",
    "wof:placetype":"venue"
},
  "geometry": {"coordinates":[-79.928872,37.269246],"type":"Point"}
}