{
  "type": "Feature",
  "properties": {
    "iso:country":"US",
    "sg:address":"3935 Callaway Rd",
    "sg:city":"Rocky Mount",
    "sg:classifiers":[
        {
            "category":"Professional",
            "subcategory":"Computer Services",
            "type":"Services"
        }
    ],
    "sg:phone":"+1 540 483 7355",
    "sg:postcode":"24151",
    "sg:province":"VA",
    "sg:tags":[
        "datum"
    ],
    "wof:name":"Mac & More Design",
    "wof:placetype":"venue"
},
  "geometry": {"coordinates":[-79.980463,37.038443],"type":"Point"}
}