{
  "type": "Feature",
  "properties": {
    "addr:full":"100 Myers Dr Charlottesville VA 22901",
    "addr:housenumber":"100",
    "addr:postcode":"22901",
    "addr:street":"Myers Dr",
    "iso:country":"US",
    "sg:address":"100 Myers Dr",
    "sg:city":"Charlottesville",
    "sg:classifiers":[
        {
            "category":"Autos & Motor Vehicles",
            "subcategory":"Automobile Sales",
            "type":"Retail Goods"
        }
    ],
    "sg:phone":"+1 434 951 1000",
    "sg:postcode":"22901",
    "sg:province":"VA",
    "sg:tags":[
        "car",
        "dealer"
    ],
    "sg:website":"www.colonialautocenter.com",
    "wof:name":"Colonial Auto Ctr",
    "wof:placetype":"venue"
},
  "geometry": {"coordinates":[-78.472369,38.085876],"type":"Point"}
}