{
  "type": "Feature",
  "properties": {
    "addr:full":"1126 E Stuart Dr Galax VA 24333",
    "addr:housenumber":"1126",
    "addr:postcode":"24333",
    "addr:street":"E Stuart Dr",
    "iso:country":"US",
    "sg:address":"1126 E Stuart Dr",
    "sg:city":"Galax",
    "sg:classifiers":[
        {
            "category":"Shopping",
            "subcategory":"Bicycles & Sporting Goods",
            "type":"Retail Goods"
        }
    ],
    "sg:phone":"+1 276 236 9962",
    "sg:postcode":"24333",
    "sg:province":"VA",
    "wof:name":"Hibbett Sporting Goods Inc",
    "wof:placetype":"venue"
},
  "geometry": {"coordinates":[-80.881677,36.690377],"type":"Point"}
}