{
  "type": "Feature",
  "properties": {
    "addr:full":"113 Cannon Cir Winchester VA 22602",
    "addr:housenumber":"113",
    "addr:postcode":"22602",
    "addr:street":"Cannon Cir",
    "iso:country":"US",
    "sg:address":"113 Cannon Cir",
    "sg:city":"Winchester",
    "sg:classifiers":[
        {
            "category":"Real Estate",
            "subcategory":"Real Estate Agent",
            "type":"Services"
        }
    ],
    "sg:phone":"+1 540 539 4908",
    "sg:postcode":"22602",
    "sg:province":"VA",
    "wof:name":"Alan Shogren Real Estate",
    "wof:placetype":"venue"
},
  "geometry": {"coordinates":[-78.110488,39.183094],"type":"Point"}
}