{
  "type": "Feature",
  "properties": {
    "iso:country":"US",
    "sg:address":"2612 Jefferson Davis Hwy",
    "sg:city":"Stafford",
    "sg:classifiers":[
        {
            "category":"Personal",
            "subcategory":"Beauty Salon",
            "type":"Services"
        }
    ],
    "sg:phone":"+1 540 288 8505",
    "sg:postcode":"22554",
    "sg:province":"VA",
    "sg:tags":[
        "shop",
        "barber"
    ],
    "wof:name":"Slammin Cuts & Styles",
    "wof:placetype":"venue"
},
  "geometry": {"coordinates":[-77.40194200000001,38.445857],"type":"Point"}
}