{
  "type": "Feature",
  "properties": {
    "addr:full":"44299 Ladiesburg Pl Ashburn VA 20147",
    "addr:postcode":"44299;20147",
    "addr:street":"Ladiesburg Pl",
    "iso:country":"US",
    "sg:address":"44299 Ladiesburg Pl",
    "sg:city":"Ashburn",
    "sg:classifiers":[
        {
            "category":"Shopping",
            "type":"Retail Goods"
        }
    ],
    "sg:phone":"+1 703 729 4578",
    "sg:postcode":"20147",
    "sg:province":"VA",
    "sg:tags":[
        "merchandise"
    ],
    "wof:name":"Patricia M Whittle",
    "wof:placetype":"venue"
},
  "geometry": {"coordinates":[-77.46852800000001,39.040938],"type":"Point"}
}