{
  "type": "Feature",
  "properties": {
    "addr:full":"8115 E Boulevard Dr Alexandria VA 22308",
    "addr:housenumber":"8115 e",
    "addr:postcode":"22308",
    "addr:street":"Boulevard Dr",
    "iso:country":"US",
    "sg:address":"8115 E Boulevard Dr",
    "sg:city":"Alexandria",
    "sg:classifiers":[
        {
            "category":"Professional",
            "type":"Services"
        }
    ],
    "sg:phone":"+1 703 660 6563",
    "sg:postcode":"22308",
    "sg:province":"VA",
    "wof:name":"Roger Garrett",
    "wof:placetype":"venue"
},
  "geometry": {"coordinates":[-77.046448,38.735852],"type":"Point"}
}