{
  "type": "Feature",
  "properties": {
    "iso:country":"US",
    "sg:address":"11332 Northwest Ln",
    "sg:city":"Rockville",
    "sg:classifiers":[
        {
            "category":"Recreation",
            "type":"Entertainment"
        }
    ],
    "sg:phone":"+1 804 749 4344",
    "sg:postcode":"23146",
    "sg:province":"VA",
    "sg:tags":[
        "riding",
        "academy"
    ],
    "wof:name":"Clarke's Barn",
    "wof:placetype":"venue"
},
  "geometry": {"coordinates":[-77.73972000000001,37.720179],"type":"Point"}
}