{
  "type": "Feature",
  "properties": {
    "addr:full":"2504 Sedgewick Pl Dumfries VA 22026",
    "addr:housenumber":"2504",
    "addr:postcode":"22026",
    "addr:street":"Sedgewick Pl",
    "iso:country":"US",
    "sg:address":"2504 Sedgewick Pl",
    "sg:city":"Dumfries",
    "sg:classifiers":[
        {
            "category":"Professional",
            "type":"Services"
        }
    ],
    "sg:phone":"+1 703 441 3282",
    "sg:postcode":"22026",
    "sg:province":"VA",
    "wof:name":"Livewire Sp",
    "wof:placetype":"venue"
},
  "geometry": {"coordinates":[-77.327631,38.559906],"type":"Point"}
}