{
  "type": "Feature",
  "properties": {
    "addr:full":"5420 Wycklow Ct Alexandria VA 22304",
    "addr:housenumber":"5420",
    "addr:postcode":"22304",
    "addr:street":"Wycklow Ct",
    "iso:country":"US",
    "sg:address":"5420 Wycklow Ct",
    "sg:city":"Alexandria",
    "sg:classifiers":[
        {
            "category":"Shopping",
            "subcategory":"Used Merchandise",
            "type":"Retail Goods"
        }
    ],
    "sg:phone":"+1 703 933 2664",
    "sg:postcode":"22304",
    "sg:province":"VA",
    "wof:name":"Antique Finder",
    "wof:placetype":"venue"
},
  "geometry": {"coordinates":[-77.121532,38.824586],"type":"Point"}
}