{
  "type": "Feature",
  "properties": {
    "addr:full":"5905 W Broad St Richmond VA 23230",
    "addr:housenumber":"5905",
    "addr:postcode":"23230",
    "addr:street":"W Broad St",
    "iso:country":"US",
    "sg:address":"5905 W Broad St",
    "sg:city":"Richmond",
    "sg:classifiers":[
        {
            "category":"Insurance",
            "subcategory":"Insurance Agent",
            "type":"Services"
        },
        {
            "category":"Insurance",
            "subcategory":"Hazard Insurance",
            "type":"Services"
        },
        {
            "category":"Insurance",
            "subcategory":"Title Insurance",
            "type":"Services"
        },
        {
            "category":"Insurance",
            "subcategory":"Life Insurance",
            "type":"Services"
        }
    ],
    "sg:phone":"+1 804 285 2091",
    "sg:postcode":"23230",
    "sg:province":"VA",
    "sg:tags":[
        "business",
        "auto",
        "commercial",
        "homeowner",
        "motorcycle",
        "renter"
    ],
    "wof:name":"Allstate Insurance Company - Brenda Tribble",
    "wof:placetype":"venue"
},
  "geometry": {"coordinates":[-77.50594100000001,37.59178],"type":"Point"}
}