{
  "type": "Feature",
  "properties": {
    "addr:full":"457 Sandy Creek Rd Danville VA 24540",
    "addr:housenumber":"457",
    "addr:postcode":"24540",
    "addr:street":"Sandy Creek Rd",
    "iso:country":"US",
    "sg:address":"457 Sandy Creek Rd",
    "sg:city":"Danville",
    "sg:classifiers":[
        {
            "category":"Building & Trades",
            "subcategory":"Plumbing",
            "type":"Services"
        }
    ],
    "sg:phone":"+1 434 685 5708",
    "sg:postcode":"24540",
    "sg:province":"VA",
    "sg:tags":[
        "air",
        "heating",
        "conditioning",
        "contractor"
    ],
    "wof:name":"Mark Fore Heating & AC",
    "wof:placetype":"venue"
},
  "geometry": {"coordinates":[-79.47089,36.672092],"type":"Point"}
}