{
  "type": "Feature",
  "properties": {
    "addr:full":"4009 Oak Dr Chesapeake VA 23321",
    "addr:housenumber":"4009",
    "addr:postcode":"23321",
    "addr:street":"Oak Dr",
    "iso:country":"US",
    "sg:address":"4009 Oak Dr",
    "sg:city":"Chesapeake",
    "sg:classifiers":[
        {
            "category":"Professional",
            "subcategory":"Business Services",
            "type":"Services"
        }
    ],
    "sg:phone":"+1 757 638 1724",
    "sg:postcode":"23321",
    "sg:province":"VA",
    "wof:name":"Joyce Technology Service Inc",
    "wof:placetype":"venue"
},
  "geometry": {"coordinates":[-76.400391,36.850665],"type":"Point"}
}