{
  "type": "Feature",
  "properties": {
    "addr:full":"13301 Midlothian Tpke Midlothian VA 23113",
    "addr:housenumber":"13301",
    "addr:postcode":"23113",
    "addr:street":"Midlothian Tpke",
    "iso:country":"US",
    "sg:address":"13301 Midlothian Tpke",
    "sg:city":"Midlothian",
    "sg:classifiers":[
        {
            "category":"Health Services",
            "subcategory":"Doctor",
            "type":"Services"
        }
    ],
    "sg:phone":"+1 804 379 0875",
    "sg:postcode":"23113",
    "sg:province":"VA",
    "sg:tags":[
        "dentist"
    ],
    "wof:name":"Stephen K Payne DDS",
    "wof:placetype":"venue"
},
  "geometry": {"coordinates":[-77.644519,37.502396],"type":"Point"}
}