{
  "type": "Feature",
  "properties": {
    "iso:country":"US",
    "sg:address":"6306 Prospect Ter",
    "sg:city":"Alexandria",
    "sg:classifiers":[
        {
            "category":"Building & Trades",
            "subcategory":"Construction",
            "type":"Services"
        }
    ],
    "sg:phone":"+1 703 675 9108",
    "sg:postcode":"22310",
    "sg:province":"VA",
    "sg:tags":[
        "floor",
        "laying",
        "contractor"
    ],
    "wof:name":"North West Hardwood Floors",
    "wof:placetype":"venue"
},
  "geometry": {"coordinates":[-77.10034899999999,38.779408],"type":"Point"}
}