{
  "type": "Feature",
  "properties": {
    "addr:full":"6000 Skipwith Rd Skipwith VA 23968",
    "addr:postcode":"6000;23968",
    "addr:street":"Skipwith Rd",
    "iso:country":"US",
    "sg:address":"6000 Skipwith Rd",
    "sg:city":"Skipwith",
    "sg:classifiers":[
        {
            "category":"Government",
            "subcategory":"Post Office",
            "type":"Public Place"
        }
    ],
    "sg:phone":"+1 434 372 3460",
    "sg:postcode":"23968",
    "sg:province":"VA",
    "wof:name":"US Post Office",
    "wof:placetype":"venue"
},
  "geometry": {"coordinates":[-78.490908,36.69453],"type":"Point"}
}