{
  "type": "Feature",
  "properties": {
    "addr:full":"1183 Warrenton Rd Fredericksburg VA 22406",
    "addr:housenumber":"1183",
    "addr:postcode":"22406",
    "addr:street":"Warrenton Rd",
    "iso:country":"US",
    "sg:address":"1183 Warrenton Rd",
    "sg:city":"Fredericksburg",
    "sg:classifiers":[
        {
            "category":"Shopping",
            "subcategory":"Used Merchandise",
            "type":"Retail Goods"
        }
    ],
    "sg:phone":"+1 540 752 9688",
    "sg:postcode":"22406",
    "sg:province":"VA",
    "sg:tags":[
        "antique"
    ],
    "wof:name":"Patooties",
    "wof:placetype":"venue"
},
  "geometry": {"coordinates":[-77.523263,38.36836],"type":"Point"}
}