{
  "type": "Feature",
  "properties": {
    "iso:country":"US",
    "sg:address":"13 Sidney Pl",
    "sg:city":"Newport News",
    "sg:classifiers":[
        {
            "category":"Professional",
            "subcategory":"Engineering",
            "type":"Services"
        }
    ],
    "sg:phone":"+1 757 595 7486",
    "sg:postcode":"23601",
    "sg:province":"VA",
    "wof:name":"Brett Design & Drafting",
    "wof:placetype":"venue"
},
  "geometry": {"coordinates":[-76.457115,37.037877],"type":"Point"}
}