{
  "type": "Feature",
  "properties": {
    "iso:country":"US",
    "sg:address":"1025 Derrymore Rd",
    "sg:city":"Richmond",
    "sg:classifiers":[
        {
            "category":"Building & Trades",
            "subcategory":"Construction",
            "type":"Services"
        }
    ],
    "sg:phone":"+1 804 745 0288",
    "sg:postcode":"23225",
    "sg:province":"VA",
    "sg:tags":[
        "house"
    ],
    "wof:name":"Rj Construction Co",
    "wof:placetype":"venue"
},
  "geometry": {"coordinates":[-77.506803,37.49245],"type":"Point"}
}