{
  "type": "Feature",
  "properties": {
    "addr:full":"899 E Fincastle St Tazewell VA 24651",
    "addr:housenumber":"899",
    "addr:postcode":"24651",
    "addr:street":"E Fincastle St",
    "iso:country":"US",
    "sg:address":"899 E Fincastle St",
    "sg:city":"Tazewell",
    "sg:classifiers":[
        {
            "category":"Restaurant",
            "type":"Food & Drink"
        }
    ],
    "sg:menulink":"http://www.allmenus.com/va/southern/199977-long-john-silvers/menu/",
    "sg:phone":"+1 276 988 9043",
    "sg:postcode":"24651",
    "sg:province":"VA",
    "sg:tags":[
        "seafood",
        "american"
    ],
    "wof:name":"Long John Silver's",
    "wof:placetype":"venue"
},
  "geometry": {"coordinates":[-81.493329,37.130336],"type":"Point"}
}