{
  "type": "Feature",
  "properties": {
    "iso:country":"US",
    "sg:address":"3406 Orange Ave NE",
    "sg:city":"Roanoke",
    "sg:classifiers":[
        {
            "category":"Home & Garden",
            "subcategory":"Building Materials",
            "type":"Retail Goods"
        }
    ],
    "sg:phone":"+1 540 343 8109",
    "sg:postcode":"24012",
    "sg:province":"VA",
    "wof:name":"Contractor Yard Inc",
    "wof:placetype":"venue"
},
  "geometry": {"coordinates":[-79.893507,37.301711],"type":"Point"}
}