{
  "type": "Feature",
  "properties": {
    "addr:full":"211 England St Ashland VA 23005",
    "addr:housenumber":"211",
    "addr:postcode":"23005",
    "addr:street":"England St",
    "iso:country":"US",
    "sg:address":"211 England St",
    "sg:city":"Ashland",
    "sg:classifiers":[
        {
            "category":"Professional",
            "subcategory":"Lawyer & Legal Services",
            "type":"Services"
        }
    ],
    "sg:phone":"+1 804 798 3232",
    "sg:postcode":"23005",
    "sg:province":"VA",
    "sg:tags":[
        "attorney"
    ],
    "wof:name":"Derrick E Rosser PC",
    "wof:placetype":"venue"
},
  "geometry": {"coordinates":[-77.479879,37.758771],"type":"Point"}
}