{
  "type": "Feature",
  "properties": {
    "addr:full":"4101 Kensington Ave Richmond VA 23221",
    "addr:housenumber":"4101",
    "addr:postcode":"23221",
    "addr:street":"Kensington Ave",
    "iso:country":"US",
    "sg:address":"4101 Kensington Ave",
    "sg:city":"Richmond",
    "sg:classifiers":[
        {
            "category":"Professional",
            "subcategory":"Business Services",
            "type":"Services"
        }
    ],
    "sg:phone":"+1 804 358 9972",
    "sg:postcode":"23221",
    "sg:province":"VA",
    "wof:name":"Kensington Associates LLC",
    "wof:placetype":"venue"
},
  "geometry": {"coordinates":[-77.49177899999999,37.565819],"type":"Point"}
}