{
  "type": "Feature",
  "properties": {
    "addr:full":"620 Creekside Ln Faber VA 22938",
    "addr:housenumber":"620",
    "addr:postcode":"22938",
    "addr:street":"Creekside Ln",
    "iso:country":"US",
    "sg:address":"620 Creekside Ln",
    "sg:city":"Faber",
    "sg:classifiers":[
        {
            "category":"Professional",
            "subcategory":"Art Services",
            "type":"Services"
        }
    ],
    "sg:phone":"+1 434 361 1963",
    "sg:postcode":"22938",
    "sg:province":"VA",
    "sg:tags":[
        "commercial",
        "design"
    ],
    "wof:name":"Elliot Serelda Graphics",
    "wof:placetype":"venue"
},
  "geometry": {"coordinates":[-78.833477,37.863256],"type":"Point"}
}