{
  "type": "Feature",
  "properties": {
    "iso:country":"US",
    "sg:address":"228 Madison St",
    "sg:city":"Hamilton",
    "sg:classifiers":[
        {
            "category":"Professional",
            "subcategory":"Accounting & Tax Preparation",
            "type":"Services"
        }
    ],
    "sg:phone":"+1 540 338 2447",
    "sg:postcode":"20158",
    "sg:province":"VA",
    "wof:name":"Gregory H Edmondson",
    "wof:placetype":"venue"
},
  "geometry": {"coordinates":[-77.67396599999999,39.132026],"type":"Point"}
}