{
  "type": "Feature",
  "properties": {
    "iso:country":"US",
    "sg:address":"300 Blue Ridge St",
    "sg:city":"Martinsville",
    "sg:classifiers":[
        {
            "category":"Social Services",
            "subcategory":"Job Training",
            "type":"Services"
        }
    ],
    "sg:phone":"+1 276 638 2278",
    "sg:postcode":"24112",
    "sg:province":"VA",
    "sg:tags":[
        "rehabilitation"
    ],
    "wof:name":"Sun Dance Rehabilitation",
    "wof:placetype":"venue"
},
  "geometry": {"coordinates":[-79.84395600000001,36.688646],"type":"Point"}
}