{
  "type": "Feature",
  "properties": {
    "addr:full":"10203 Steuben Dr Glen Allen VA 23060",
    "addr:housenumber":"10203",
    "addr:postcode":"23060",
    "addr:street":"Steuben Dr",
    "iso:country":"US",
    "sg:address":"10203 Steuben Dr",
    "sg:city":"Glen Allen",
    "sg:classifiers":[
        {
            "category":"Utilities",
            "subcategory":"Telephone",
            "type":"Services"
        }
    ],
    "sg:phone":"+1 804 501 0250",
    "sg:postcode":"23060",
    "sg:province":"VA",
    "sg:tags":[
        "telecommunication"
    ],
    "wof:name":"Mactec Inc",
    "wof:placetype":"venue"
},
  "geometry": {"coordinates":[-77.50998199999999,37.659155],"type":"Point"}
}