{
  "type": "Feature",
  "properties": {
    "iso:country":"US",
    "sg:address":"2400 Capistrano St",
    "sg:city":"Blacksburg",
    "sg:classifiers":[
        {
            "category":"Professional",
            "subcategory":"Art Services",
            "type":"Services"
        }
    ],
    "sg:phone":"+1 540 951 3351",
    "sg:postcode":"24060",
    "sg:province":"VA",
    "sg:tags":[
        "photography",
        "commercial"
    ],
    "wof:name":"Richard C Griffiths",
    "wof:placetype":"venue"
},
  "geometry": {"coordinates":[-80.45144000000001,37.221096],"type":"Point"}
}