{
  "type": "Feature",
  "properties": {
    "iso:country":"US",
    "sg:address":"190 S Whiting St",
    "sg:city":"Alexandria",
    "sg:classifiers":[
        {
            "category":"Autos & Motor Vehicles",
            "subcategory":"Fuel & Gas Station",
            "type":"Retail Goods"
        }
    ],
    "sg:phone":"+1 703 751 9499",
    "sg:postcode":"22304",
    "sg:province":"VA",
    "sg:tags":[
        "station",
        "gasoline",
        "oil"
    ],
    "wof:name":"Landmarks Towers Mobil",
    "wof:placetype":"venue"
},
  "geometry": {"coordinates":[-77.137046,38.812246],"type":"Point"}
}