{
  "type": "Feature",
  "properties": {
    "addr:full":"124 Hamlin Dr Fredericksburg VA 22405",
    "addr:housenumber":"124",
    "addr:postcode":"22405",
    "addr:street":"Hamlin Dr",
    "iso:country":"US",
    "sg:address":"124 Hamlin Dr",
    "sg:city":"Fredericksburg",
    "sg:classifiers":[
        {
            "category":"Organizations",
            "subcategory":"Religious Organization",
            "type":"Services"
        }
    ],
    "sg:phone":"+1 540 372 7281",
    "sg:postcode":"22405",
    "sg:province":"VA",
    "wof:name":"William H Bell",
    "wof:placetype":"venue"
},
  "geometry": {"coordinates":[-77.438222,38.31745],"type":"Point"}
}