{
  "type": "Feature",
  "properties": {
    "iso:country":"US",
    "sg:address":"27480 Fairfield Dr",
    "sg:city":"Onancock",
    "sg:classifiers":[
        {
            "category":"Shopping",
            "subcategory":"Catalog Store",
            "type":"Retail Goods"
        }
    ],
    "sg:phone":"+1 757 787 2824",
    "sg:postcode":"23417",
    "sg:province":"VA",
    "sg:tags":[
        "mail",
        "house"
    ],
    "wof:name":"Chesapeake Herb Farm",
    "wof:placetype":"venue"
},
  "geometry": {"coordinates":[-75.81422999999999,37.666738],"type":"Point"}
}