{
  "type": "Feature",
  "properties": {
    "iso:country":"US",
    "sg:address":"5903 Kingsford Rd",
    "sg:city":"Springfield",
    "sg:classifiers":[
        {
            "category":"Government",
            "subcategory":"Office",
            "type":"Public Place"
        }
    ],
    "sg:phone":"+1 703 451 1655",
    "sg:postcode":"22152",
    "sg:province":"VA",
    "sg:tags":[
        "consultant",
        "national",
        "education",
        "security",
        "specialist"
    ],
    "wof:name":"Industrial Security Services",
    "wof:placetype":"venue"
},
  "geometry": {"coordinates":[-77.231951,38.79053],"type":"Point"}
}