{
  "type": "Feature",
  "properties": {
    "addr:full":"1510 E Ridge Rd Richmond VA 23229",
    "addr:housenumber":"1510",
    "addr:postcode":"23229",
    "addr:street":"E Ridge Rd",
    "iso:country":"US",
    "sg:address":"1510 E Ridge Rd",
    "sg:city":"Richmond",
    "sg:classifiers":[
        {
            "category":"Cinema",
            "subcategory":"Movie Theater",
            "type":"Entertainment"
        }
    ],
    "sg:phone":"+1 804 282 0335",
    "sg:postcode":"23229",
    "sg:province":"VA",
    "wof:name":"Willow Lawn Cinemas 4",
    "wof:placetype":"venue"
},
  "geometry": {"coordinates":[-77.562625,37.601974],"type":"Point"}
}