{
  "type": "Feature",
  "properties": {
    "addr:full":"701 Greyledge Blvd Chester VA 23836",
    "addr:housenumber":"701",
    "addr:postcode":"23836",
    "addr:street":"Greyledge Blvd",
    "iso:country":"US",
    "sg:address":"701 Greyledge Blvd",
    "sg:city":"Chester",
    "sg:classifiers":[
        {
            "category":"Recreation",
            "type":"Entertainment"
        }
    ],
    "sg:phone":"+1 804 530 1119",
    "sg:postcode":"23836",
    "sg:province":"VA",
    "sg:tags":[
        "pool",
        "swimming"
    ],
    "wof:name":"Southbend Pool",
    "wof:placetype":"venue"
},
  "geometry": {"coordinates":[-77.351338,37.335232],"type":"Point"}
}