{
  "type": "Feature",
  "properties": {
    "addr:full":"305 Memorial Ave Hopewell VA 23860",
    "addr:housenumber":"305",
    "addr:postcode":"23860",
    "addr:street":"Memorial Ave",
    "iso:country":"US",
    "sg:address":"305 Memorial Ave",
    "sg:city":"Hopewell",
    "sg:classifiers":[
        {
            "category":"Organizations",
            "subcategory":"Religious Organization",
            "type":"Services"
        }
    ],
    "sg:phone":"+1 804 452 1444",
    "sg:postcode":"23860",
    "sg:province":"VA",
    "sg:tags":[
        "clergy"
    ],
    "wof:name":"J Bruce Catron",
    "wof:placetype":"venue"
},
  "geometry": {"coordinates":[-77.29525,37.303424],"type":"Point"}
}