{
  "type": "Feature",
  "properties": {
    "iso:country":"US",
    "sg:address":"2811 Cherry Hill Rd",
    "sg:city":"Dumfries",
    "sg:classifiers":[
        {
            "category":"Manufacturing",
            "subcategory":"Retail Goods",
            "type":"Manufacturing & Wholesale Goods"
        }
    ],
    "sg:phone":"+1 703 441 8849",
    "sg:postcode":"22026",
    "sg:province":"VA",
    "sg:tags":[
        "product",
        "mfg"
    ],
    "wof:name":"A Touch of Silk Inc",
    "wof:placetype":"venue"
},
  "geometry": {"coordinates":[-77.297225,38.574847],"type":"Point"}
}