{
  "type": "Feature",
  "properties": {
    "iso:country":"US",
    "sg:address":"1420 Seminole Trl",
    "sg:city":"Charlottesville",
    "sg:classifiers":[
        {
            "category":"Restaurant",
            "type":"Food & Drink"
        }
    ],
    "sg:phone":"+1 434 973 1177",
    "sg:postcode":"22901",
    "sg:province":"VA",
    "wof:name":"Copacabana Brazilian Intl",
    "wof:placetype":"venue"
},
  "geometry": {"coordinates":[-78.477199,38.078371],"type":"Point"}
}