{
  "type": "Feature",
  "properties": {
    "addr:full":"1137 Gauguin Dr Virginia Beach VA 23454",
    "addr:housenumber":"1137",
    "addr:postcode":"23454",
    "addr:street":"Gauguin Dr",
    "iso:country":"US",
    "sg:address":"1137 Gauguin Dr",
    "sg:city":"Virginia Beach",
    "sg:classifiers":[
        {
            "category":"Manufacturing",
            "subcategory":"Printing",
            "type":"Manufacturing & Wholesale Goods"
        }
    ],
    "sg:phone":"+1 757 426 6630",
    "sg:postcode":"23454",
    "sg:province":"VA",
    "sg:tags":[
        "newspaper"
    ],
    "wof:name":"Soccer Rag",
    "wof:placetype":"venue"
},
  "geometry": {"coordinates":[-75.99266799999999,36.780356],"type":"Point"}
}