{
  "type": "Feature",
  "properties": {
    "iso:country":"US",
    "sg:address":"8904 Playground Cir",
    "sg:city":"Richmond",
    "sg:classifiers":[
        {
            "category":"Restaurant",
            "type":"Food & Drink"
        }
    ],
    "sg:phone":"+1 804 714 1990",
    "sg:postcode":"23237",
    "sg:province":"VA",
    "wof:name":"Maria S Italian Restauran",
    "wof:placetype":"venue"
},
  "geometry": {"coordinates":[-77.498867,37.395289],"type":"Point"}
}