{
  "type": "Feature",
  "properties": {
    "addr:full":"2010 Redman Rd Richmond VA 23226",
    "addr:housenumber":"2010",
    "addr:postcode":"23226",
    "addr:street":"Redman Rd",
    "iso:country":"US",
    "sg:address":"2010 Redman Rd",
    "sg:city":"Richmond",
    "sg:classifiers":[
        {
            "category":"Professional",
            "type":"Services"
        }
    ],
    "sg:phone":"+1 804 303 1609",
    "sg:postcode":"23226",
    "sg:province":"VA",
    "sg:tags":[
        "establishment"
    ],
    "wof:name":"Moscoso Josearturo",
    "wof:placetype":"venue"
},
  "geometry": {"coordinates":[-77.517303,37.598092],"type":"Point"}
}