{
  "type": "Feature",
  "properties": {
    "iso:country":"US",
    "sg:address":"5428 Hope Park Rd",
    "sg:city":"Fairfax",
    "sg:classifiers":[
        {
            "category":"Building & Trades",
            "subcategory":"Cleaning & Sanitation",
            "type":"Services"
        }
    ],
    "sg:phone":"+1 703 830 2891",
    "sg:postcode":"22030",
    "sg:province":"VA",
    "sg:tags":[
        "maintenance"
    ],
    "wof:name":"Trammel Cleaning Service",
    "wof:placetype":"venue"
},
  "geometry": {"coordinates":[-77.366288,38.824726],"type":"Point"}
}