{
  "type": "Feature",
  "properties": {
    "addr:full":"590 Westside Blvd NW Roanoke VA 24017",
    "addr:housenumber":"590",
    "addr:postcode":"24017",
    "addr:street":"Westside Blvd Nw",
    "iso:country":"US",
    "sg:address":"590 Westside Blvd NW",
    "sg:city":"Roanoke",
    "sg:classifiers":[
        {
            "category":"Recreation",
            "type":"Entertainment"
        }
    ],
    "sg:phone":"+1 540 344 7511",
    "sg:postcode":"24017",
    "sg:province":"VA",
    "sg:tags":[
        "center"
    ],
    "wof:name":"Wilmont Recreation Club",
    "wof:placetype":"venue"
},
  "geometry": {"coordinates":[-80.00623400000001,37.281623],"type":"Point"}
}