{
  "type": "Feature",
  "properties": {
    "iso:country":"US",
    "sg:address":"9050 Little Joselyn Dr",
    "sg:city":"Mechanicsville",
    "sg:classifiers":[
        {
            "category":"Professional",
            "type":"Services"
        }
    ],
    "sg:phone":"+1 804 550 0444",
    "sg:postcode":"23116",
    "sg:province":"VA",
    "wof:name":"Acuscrip Network Inc",
    "wof:placetype":"venue"
},
  "geometry": {"coordinates":[-77.407588,37.689801],"type":"Point"}
}