{
  "type": "Feature",
  "properties": {
    "addr:full":"8697 Sudley Rd Manassas VA 20110",
    "addr:housenumber":"8697",
    "addr:postcode":"20110",
    "addr:street":"Sudley Rd",
    "iso:country":"US",
    "sg:address":"8697 Sudley Rd",
    "sg:city":"Manassas",
    "sg:classifiers":[
        {
            "category":"Restaurant",
            "type":"Food & Drink"
        }
    ],
    "sg:menulink":"http://www.allmenus.com/va/manassas/236531-guapos-restaurant/menu/",
    "sg:phone":"+1 703 361 0088",
    "sg:postcode":"20110",
    "sg:province":"VA",
    "sg:tags":[
        "mexican"
    ],
    "wof:name":"Guapo's Restaurant",
    "wof:placetype":"venue"
},
  "geometry": {"coordinates":[-77.48878000000001,38.769314],"type":"Point"}
}