{
  "type": "Feature",
  "properties": {
    "addr:full":"525 S Wayne Ave Waynesboro VA 22980",
    "addr:housenumber":"525",
    "addr:postcode":"22980",
    "addr:street":"S Wayne Ave",
    "iso:country":"US",
    "sg:address":"525 S Wayne Ave",
    "sg:city":"Waynesboro",
    "sg:classifiers":[
        {
            "category":"Shopping",
            "subcategory":"Hobbies, Toys, & Games",
            "type":"Retail Goods"
        }
    ],
    "sg:phone":"+1 540 949 5828",
    "sg:postcode":"22980",
    "sg:province":"VA",
    "sg:tags":[
        "model",
        "supply"
    ],
    "wof:name":"Valley Games & Hobbies",
    "wof:placetype":"venue"
},
  "geometry": {"coordinates":[-78.892839,38.063247],"type":"Point"}
}