{
  "type": "Feature",
  "properties": {
    "iso:country":"US",
    "sg:address":"1 Cardinal Dr",
    "sg:city":"Clinchco",
    "sg:classifiers":[
        {
            "category":"Education",
            "subcategory":"School",
            "type":"Public Place"
        }
    ],
    "sg:phone":"+1 276 835 8671",
    "sg:postcode":"24201",
    "sg:province":"VA",
    "wof:name":"Clinchco Elementary School",
    "wof:placetype":"venue"
},
  "geometry": {"coordinates":[-82.128466,36.617459],"type":"Point"}
}