{
  "type": "Feature",
  "properties": {
    "addr:full":"3439 Carlin Springs Rd Baileys Crossrds VA 22041",
    "addr:housenumber":"3439",
    "addr:postcode":"crossrds;22041",
    "addr:street":"Carlin Springs Rd",
    "iso:country":"US",
    "sg:address":"3439 Carlin Springs Rd",
    "sg:city":"Baileys Crossrds",
    "sg:classifiers":[
        {
            "category":"Autos & Motor Vehicles",
            "subcategory":"Auto Supplies",
            "type":"Retail Goods"
        }
    ],
    "sg:phone":"+1 703 845 7000",
    "sg:postcode":"22041",
    "sg:province":"VA",
    "sg:tags":[
        "automobile",
        "parts"
    ],
    "wof:name":"J K Auto Parts Inc",
    "wof:placetype":"venue"
},
  "geometry": {"coordinates":[-77.123696,38.850025],"type":"Point"}
}