{
  "type": "Feature",
  "properties": {
    "addr:full":"2465 Centreville Rd Herndon VA 20171",
    "addr:housenumber":"2465",
    "addr:postcode":"20171",
    "addr:street":"Centreville Rd",
    "iso:country":"US",
    "sg:address":"2465 Centreville Rd",
    "sg:city":"Herndon",
    "sg:classifiers":[
        {
            "category":"Insurance",
            "subcategory":"Insurance Agent",
            "type":"Services"
        }
    ],
    "sg:phone":"+1 703 713 3900",
    "sg:postcode":"20171",
    "sg:province":"VA",
    "wof:name":"State Farm Insurance",
    "wof:placetype":"venue"
},
  "geometry": {"coordinates":[-77.413753,38.948501],"type":"Point"}
}