{
  "type": "Feature",
  "properties": {
    "addr:full":"48 W Boscawen St Winchester VA 22601",
    "addr:housenumber":"48",
    "addr:postcode":"22601",
    "addr:street":"W Boscawen St",
    "iso:country":"US",
    "sg:address":"48 W Boscawen St",
    "sg:city":"Winchester",
    "sg:classifiers":[
        {
            "category":"Mining & Drilling",
            "type":"Manufacturing & Wholesale Goods"
        }
    ],
    "sg:phone":"+1 540 678 1490",
    "sg:postcode":"22601",
    "sg:province":"VA",
    "sg:tags":[
        "company"
    ],
    "wof:name":"Unimin Corp",
    "wof:placetype":"venue"
},
  "geometry": {"coordinates":[-78.16583199999999,39.18413],"type":"Point"}
}