{
  "type": "Feature",
  "properties": {
    "iso:country":"US",
    "sg:address":"4308 Backlick Rd",
    "sg:city":"Annandale",
    "sg:classifiers":[
        {
            "category":"Restaurant",
            "type":"Food & Drink"
        }
    ],
    "sg:menulink":"http://www.allmenus.com/va/mason/48331-sorak-garden/menu/",
    "sg:phone":"+1 703 916 7600",
    "sg:postcode":"22003",
    "sg:province":"VA",
    "sg:tags":[
        "korean",
        "asian"
    ],
    "wof:name":"Sorak Garden",
    "wof:placetype":"venue"
},
  "geometry": {"coordinates":[-77.194447,38.83003],"type":"Point"}
}