{
  "type": "Feature",
  "properties": {
    "addr:full":"216 S Patrick St Alexandria VA 22314",
    "addr:housenumber":"216",
    "addr:postcode":"22314",
    "addr:street":"S Patrick St",
    "iso:country":"US",
    "sg:address":"216 S Patrick St",
    "sg:city":"Alexandria",
    "sg:classifiers":[
        {
            "category":"Professional",
            "subcategory":"Lawyer & Legal Services",
            "type":"Services"
        }
    ],
    "sg:phone":"+1 703 549 0446",
    "sg:postcode":"22314",
    "sg:province":"VA",
    "wof:name":"Lowe & Carlo",
    "wof:placetype":"venue"
},
  "geometry": {"coordinates":[-77.05068199999999,38.803274],"type":"Point"}
}