{
  "type": "Feature",
  "properties": {
    "addr:full":"824 Smith St Martinsville VA 24112",
    "addr:housenumber":"824",
    "addr:postcode":"24112",
    "addr:street":"Smith St",
    "iso:country":"US",
    "sg:address":"824 Smith St",
    "sg:city":"Martinsville",
    "sg:classifiers":[
        {
            "category":"Organizations",
            "subcategory":"Religious Organization",
            "type":"Services"
        }
    ],
    "sg:phone":"+1 276 632 9329",
    "sg:postcode":"24112",
    "sg:province":"VA",
    "sg:tags":[
        "church"
    ],
    "wof:name":"Seventh Day Adventist Church",
    "wof:placetype":"venue"
},
  "geometry": {"coordinates":[-79.889774,36.693931],"type":"Point"}
}