{
  "type": "Feature",
  "properties": {
    "iso:country":"US",
    "sg:address":"14747 Hackwood St",
    "sg:city":"Woodbridge",
    "sg:classifiers":[
        {
            "category":"Professional",
            "subcategory":"Detective & Security Services",
            "type":"Services"
        }
    ],
    "sg:phone":"+1 703 624 4872",
    "sg:postcode":"22191",
    "sg:province":"VA",
    "sg:tags":[
        "car"
    ],
    "wof:name":"Vuss Security Inc",
    "wof:placetype":"venue"
},
  "geometry": {"coordinates":[-77.25552399999999,38.632522],"type":"Point"}
}