{
  "type": "Feature",
  "properties": {
    "addr:full":"210 7th St Salem VA 24153",
    "addr:housenumber":"210",
    "addr:postcode":"24153",
    "addr:street":"7Th St",
    "iso:country":"US",
    "sg:address":"210 7th St",
    "sg:city":"Salem",
    "sg:classifiers":[
        {
            "category":"Professional",
            "subcategory":"Accounting & Tax Preparation",
            "type":"Services"
        }
    ],
    "sg:phone":"+1 540 389 0072",
    "sg:postcode":"24153",
    "sg:province":"VA",
    "sg:tags":[
        "accountant"
    ],
    "wof:name":"Jack K Hatfield Inc",
    "wof:placetype":"venue"
},
  "geometry": {"coordinates":[-80.052606,37.283069],"type":"Point"}
}