{
  "type": "Feature",
  "properties": {
    "addr:full":"45706 Elmwood Ct Sterling VA 20166",
    "addr:housenumber":"45706",
    "addr:postcode":"20166",
    "addr:street":"Elmwood Ct",
    "iso:country":"US",
    "sg:address":"45706 Elmwood Ct",
    "sg:city":"Sterling",
    "sg:classifiers":[
        {
            "category":"Retail",
            "subcategory":"Auto Repair",
            "type":"Services"
        }
    ],
    "sg:phone":"+1 703 444 4669",
    "sg:postcode":"20166",
    "sg:province":"VA",
    "sg:tags":[
        "body",
        "automobile",
        "painting"
    ],
    "wof:name":"Platinum Auto Body Inc",
    "wof:placetype":"venue"
},
  "geometry": {"coordinates":[-77.418588,39.02149],"type":"Point"}
}