{
  "type": "Feature",
  "properties": {
    "addr:full":"5784 S Lee Hwy Natural Bridge VA 24578",
    "addr:housenumber":"5784",
    "addr:postcode":"24578",
    "addr:street":"S Lee Hwy",
    "iso:country":"US",
    "sg:address":"5784 S Lee Hwy",
    "sg:city":"Natural Bridge",
    "sg:classifiers":[
        {
            "category":"Museum",
            "subcategory":"Botanical Garden",
            "type":"Entertainment"
        }
    ],
    "sg:phone":"+1 540 291 2420",
    "sg:postcode":"24578",
    "sg:province":"VA",
    "sg:tags":[
        "zoo"
    ],
    "wof:name":"Natural Bridge Zoological Park",
    "wof:placetype":"venue"
},
  "geometry": {"coordinates":[-79.524781,37.6489],"type":"Point"}
}