{
  "type": "Feature",
  "properties": {
    "iso:country":"US",
    "sg:address":"908 Lake Village Dr",
    "sg:city":"Chesapeake",
    "sg:classifiers":[
        {
            "category":"Real Estate",
            "subcategory":"Real Estate Operator",
            "type":"Services"
        }
    ],
    "sg:phone":"+1 757 487 5122",
    "sg:postcode":"23323",
    "sg:province":"VA",
    "sg:tags":[
        "building",
        "apartment"
    ],
    "sg:website":"www.lawsoncompanies.com",
    "wof:name":"Lake Village Apartments",
    "wof:placetype":"venue"
},
  "geometry": {"coordinates":[-76.32912,36.77774],"type":"Point"}
}