{
  "type": "Feature",
  "properties": {
    "iso:country":"US",
    "sg:address":"1905 Chain Bridge Rd",
    "sg:city":"Mc Lean",
    "sg:classifiers":[
        {
            "category":"Home & Garden",
            "subcategory":"Household Appliances",
            "type":"Retail Goods"
        }
    ],
    "sg:phone":"+1 703 893 6112",
    "sg:postcode":"22102",
    "sg:province":"VA",
    "sg:tags":[
        "c"
    ],
    "wof:name":"Circuit City",
    "wof:placetype":"venue"
},
  "geometry": {"coordinates":[-77.220196,38.920139],"type":"Point"}
}