{
  "type": "Feature",
  "properties": {
    "addr:full":"11281 Air Park Rd Ashland VA 23005",
    "addr:housenumber":"11281",
    "addr:postcode":"23005",
    "addr:street":"Air Park Rd",
    "iso:country":"US",
    "sg:address":"11281 Air Park Rd",
    "sg:city":"Ashland",
    "sg:classifiers":[
        {
            "category":"Building & Trades",
            "subcategory":"Construction",
            "type":"Services"
        }
    ],
    "sg:phone":"+1 804 752 6032",
    "sg:postcode":"23005",
    "sg:province":"VA",
    "sg:tags":[
        "general",
        "contractor"
    ],
    "wof:name":"Bell Mejia Engrg & Constr",
    "wof:placetype":"venue"
},
  "geometry": {"coordinates":[-77.44627,37.708917],"type":"Point"}
}