{
  "type": "Feature",
  "properties": {
    "addr:full":"830 W Lee Hwy Chilhowie VA 24319",
    "addr:housenumber":"830",
    "addr:postcode":"24319",
    "addr:street":"W Lee Hwy",
    "iso:country":"US",
    "sg:address":"830 W Lee Hwy",
    "sg:city":"Chilhowie",
    "sg:classifiers":[
        {
            "category":"Restaurant",
            "type":"Food & Drink"
        }
    ],
    "sg:phone":"+1 276 646 5052",
    "sg:postcode":"24319",
    "sg:province":"VA",
    "sg:tags":[
        "eating"
    ],
    "wof:name":"C Js Pizza",
    "wof:placetype":"venue"
},
  "geometry": {"coordinates":[-81.689015,36.793935],"type":"Point"}
}