{
  "type": "Feature",
  "properties": {
    "iso:country":"US",
    "sg:address":"5213 Ampthill Dr",
    "sg:city":"Alexandria",
    "sg:classifiers":[
        {
            "category":"Shopping",
            "subcategory":"Bicycles & Sporting Goods",
            "type":"Retail Goods"
        }
    ],
    "sg:phone":"+1 800 221 5378",
    "sg:postcode":"22312",
    "sg:province":"VA",
    "sg:tags":[
        "tent"
    ],
    "wof:name":"Tent & Structure International Inc",
    "wof:placetype":"venue"
},
  "geometry": {"coordinates":[-77.161108,38.811421],"type":"Point"}
}