{
  "type": "Feature",
  "properties": {
    "iso:country":"US",
    "sg:address":"4238 Wilson Blvd",
    "sg:city":"Arlington",
    "sg:classifiers":[
        {
            "category":"Shopping",
            "subcategory":"Optician",
            "type":"Retail Goods"
        },
        {
            "category":"Personal",
            "subcategory":"Shoe Repair & Shine",
            "type":"Services"
        }
    ],
    "sg:phone":"+1 703 522 1852",
    "sg:postcode":"22203",
    "sg:province":"VA",
    "sg:tags":[
        "eyewear",
        "sunglass"
    ],
    "sg:website":"www2.sunglasshut.com",
    "wof:name":"Sunglass Hut",
    "wof:placetype":"venue"
},
  "geometry": {"coordinates":[-77.111524,38.87986],"type":"Point"}
}