{
  "type": "Feature",
  "properties": {
    "addr:full":"6533 Peters Creek Rd NW Roanoke VA 24019",
    "addr:housenumber":"6533",
    "addr:postcode":"24019",
    "addr:street":"Peters Creek Rd Nw",
    "iso:country":"US",
    "sg:address":"6533 Peters Creek Rd NW",
    "sg:city":"Roanoke",
    "sg:classifiers":[
        {
            "category":"Education",
            "subcategory":"School",
            "type":"Public Place"
        }
    ],
    "sg:phone":"+1 540 561 8165",
    "sg:postcode":"24019",
    "sg:province":"VA",
    "sg:website":"www.rcs.k12.va.us",
    "wof:name":"Burlington Elementary School",
    "wof:placetype":"venue"
},
  "geometry": {"coordinates":[-79.960751,37.344869],"type":"Point"}
}