{
  "type": "Feature",
  "properties": {
    "iso:country":"US",
    "sg:address":"3540 Main St",
    "sg:city":"Toms Brook",
    "sg:classifiers":[
        {
            "category":"Retail",
            "subcategory":"Auto Repair",
            "type":"Services"
        }
    ],
    "sg:phone":"+1 540 436 3490",
    "sg:postcode":"22660",
    "sg:province":"VA",
    "sg:tags":[
        "wrecker"
    ],
    "wof:name":"Toms Brook Svc Ctr",
    "wof:placetype":"venue"
},
  "geometry": {"coordinates":[-78.43674900000001,38.948336],"type":"Point"}
}