{
  "type": "Feature",
  "properties": {
    "iso:country":"US",
    "sg:address":"5600 Brickell Rd",
    "sg:city":"Norfolk",
    "sg:classifiers":[
        {
            "category":"Personal",
            "subcategory":"Beauty Salon",
            "type":"Services"
        }
    ],
    "sg:phone":"+1 757 461 3993",
    "sg:postcode":"23502",
    "sg:province":"VA",
    "wof:name":"Simply Hair",
    "wof:placetype":"venue"
},
  "geometry": {"coordinates":[-76.21137899999999,36.853908],"type":"Point"}
}