{
  "type": "Feature",
  "properties": {
    "iso:country":"US",
    "sg:address":"718 Kelly Hill Rd",
    "sg:city":"Atkins",
    "sg:classifiers":[
        {
            "category":"Professional",
            "subcategory":"Business Services",
            "type":"Services"
        }
    ],
    "sg:phone":"+1 276 783 8398",
    "sg:postcode":"24311",
    "sg:province":"VA",
    "wof:name":"Halls Auction",
    "wof:placetype":"venue"
},
  "geometry": {"coordinates":[-81.44642399999999,36.839655],"type":"Point"}
}