{
  "type": "Feature",
  "properties": {
    "addr:full":"5620 Teterling Ct Chester VA 23831",
    "addr:housenumber":"5620",
    "addr:postcode":"23831",
    "addr:street":"Teterling Ct",
    "iso:country":"US",
    "sg:address":"5620 Teterling Ct",
    "sg:city":"Chester",
    "sg:phone":"+1 804 748 4810",
    "sg:postcode":"23831",
    "sg:province":"VA",
    "sg:tags":[
        "farm",
        "field",
        "crop"
    ],
    "wof:name":"Ralph Dunn",
    "wof:placetype":"venue"
},
  "geometry": {"coordinates":[-77.468085,37.354385],"type":"Point"}
}