{
  "type": "Feature",
  "properties": {
    "addr:full":"2353 Lanier Rd Rockville VA 23146",
    "addr:housenumber":"2353",
    "addr:postcode":"23146",
    "addr:street":"Lanier Rd",
    "iso:country":"US",
    "sg:address":"2353 Lanier Rd",
    "sg:city":"Rockville",
    "sg:classifiers":[
        {
            "category":"Utilities",
            "subcategory":"Refuse",
            "type":"Services"
        }
    ],
    "sg:phone":"+1 804 749 8344",
    "sg:postcode":"23146",
    "sg:province":"VA",
    "sg:tags":[
        "material",
        "system"
    ],
    "wof:name":"United States Filter Corp",
    "wof:placetype":"venue"
},
  "geometry": {"coordinates":[-77.66423399999999,37.700565],"type":"Point"}
}