{
  "type": "Feature",
  "properties": {
    "iso:country":"US",
    "sg:address":"6212 Little River Tpke",
    "sg:city":"Alexandria",
    "sg:classifiers":[
        {
            "category":"Shopping",
            "subcategory":"Clothing, Apparel, & Fashions",
            "type":"Retail Goods"
        }
    ],
    "sg:phone":"+1 703 333 5953",
    "sg:postcode":"22312",
    "sg:province":"VA",
    "wof:name":"Fashion Lafama",
    "wof:placetype":"venue"
},
  "geometry": {"coordinates":[-77.141935,38.817918],"type":"Point"}
}