{
  "type": "Feature",
  "properties": {
    "addr:full":"2018 Lakeside Dr Lynchburg VA 24501",
    "addr:housenumber":"2018",
    "addr:postcode":"24501",
    "addr:street":"Lakeside Dr",
    "iso:country":"US",
    "sg:address":"2018 Lakeside Dr",
    "sg:city":"Lynchburg",
    "sg:classifiers":[
        {
            "category":"Autos & Motor Vehicles",
            "subcategory":"Automobile Sales",
            "type":"Retail Goods"
        }
    ],
    "sg:phone":"+1 434 385 1033",
    "sg:postcode":"24501",
    "sg:province":"VA",
    "sg:tags":[
        "car",
        "used",
        "dealer"
    ],
    "wof:name":"New To U Auto",
    "wof:placetype":"venue"
},
  "geometry": {"coordinates":[-79.20007099999999,37.401658],"type":"Point"}
}