{
  "type": "Feature",
  "properties": {
    "addr:full":"2420 Woodrow St Lynchburg VA 24501",
    "addr:housenumber":"2420",
    "addr:postcode":"24501",
    "addr:street":"Woodrow St",
    "iso:country":"US",
    "sg:address":"2420 Woodrow St",
    "sg:city":"Lynchburg",
    "sg:classifiers":[
        {
            "category":"Health Services",
            "subcategory":"Clinic",
            "type":"Services"
        }
    ],
    "sg:phone":"+1 434 847 8031",
    "sg:postcode":"24501",
    "sg:province":"VA",
    "sg:tags":[
        "specialty",
        "outpatient"
    ],
    "wof:name":"Hudson House",
    "wof:placetype":"venue"
},
  "geometry": {"coordinates":[-79.13740799999999,37.378584],"type":"Point"}
}