{
  "type": "Feature",
  "properties": {
    "iso:country":"US",
    "sg:address":"105 Falls Ave",
    "sg:city":"Falls Church",
    "sg:classifiers":[
        {
            "category":"Retail",
            "subcategory":"Auto Repair",
            "type":"Services"
        }
    ],
    "sg:phone":"+1 703 533 1107",
    "sg:postcode":"22046",
    "sg:province":"VA",
    "sg:tags":[
        "general"
    ],
    "wof:name":"Beachs Automotive Service",
    "wof:placetype":"venue"
},
  "geometry": {"coordinates":[-77.18575199999999,38.892814],"type":"Point"}
}