{
  "type": "Feature",
  "properties": {
    "addr:full":"3839 Irvington Rd Irvington VA 22480",
    "addr:housenumber":"3839",
    "addr:postcode":"22480",
    "addr:street":"Irvington Rd",
    "iso:country":"US",
    "sg:address":"3839 Irvington Rd",
    "sg:city":"Irvington",
    "sg:classifiers":[
        {
            "category":"Building & Trades",
            "subcategory":"Construction",
            "type":"Services"
        }
    ],
    "sg:phone":"+1 804 438 5141",
    "sg:postcode":"22480",
    "sg:province":"VA",
    "sg:tags":[
        "contractor"
    ],
    "wof:name":"Plus 3 Drywall Inc",
    "wof:placetype":"venue"
},
  "geometry": {"coordinates":[-76.415379,37.66907],"type":"Point"}
}