{
  "type": "Feature",
  "properties": {
    "addr:full":"2491 N Harrison St Arlington VA 22207",
    "addr:housenumber":"2491",
    "addr:postcode":"22207",
    "addr:street":"N Harrison St",
    "iso:country":"US",
    "sg:address":"2491 N Harrison St",
    "sg:city":"Arlington",
    "sg:classifiers":[
        {
            "category":"Professional",
            "subcategory":"Accounting & Tax Preparation",
            "type":"Services"
        },
        {
            "category":"Banks & Credit Unions",
            "subcategory":"Financial Services",
            "type":"Services"
        }
    ],
    "sg:phone":"+1 703 536 4110",
    "sg:postcode":"22207",
    "sg:province":"VA",
    "sg:tags":[
        "return",
        "preparation-business",
        "taxes-consultants",
        "loan",
        "reporting",
        "representative",
        "alternative",
        "bookkeeping"
    ],
    "sg:website":"http://www.hrblock.com",
    "wof:name":"H&R Block",
    "wof:placetype":"venue"
},
  "geometry": {"coordinates":[-77.138473,38.8968],"type":"Point"}
}