{
  "type": "Feature",
  "properties": {
    "addr:full":"404 Sharon Dr Newport News VA 23602",
    "addr:housenumber":"404",
    "addr:postcode":"23602",
    "addr:street":"Sharon Dr",
    "iso:country":"US",
    "sg:address":"404 Sharon Dr",
    "sg:city":"Newport News",
    "sg:classifiers":[
        {
            "category":"Organizations",
            "subcategory":"Religious Organization",
            "type":"Services"
        }
    ],
    "sg:phone":"+1 757 875 1900",
    "sg:postcode":"23602",
    "sg:province":"VA",
    "sg:tags":[
        "pentecostal",
        "church"
    ],
    "wof:name":"Virginia Dst HM Ministries",
    "wof:placetype":"venue"
},
  "geometry": {"coordinates":[-76.52051299999999,37.1173],"type":"Point"}
}