{
  "type": "Feature",
  "properties": {
    "addr:full":"429 Winding Way Bracey VA 23919",
    "addr:housenumber":"429",
    "addr:postcode":"23919",
    "addr:street":"Winding Way",
    "iso:country":"US",
    "sg:address":"429 Winding Way",
    "sg:city":"Bracey",
    "sg:classifiers":[
        {
            "category":"Professional",
            "type":"Services"
        }
    ],
    "sg:phone":"+1 434 636 2052",
    "sg:postcode":"23919",
    "sg:province":"VA",
    "sg:tags":[
        "establishment"
    ],
    "wof:name":"Fenner",
    "wof:placetype":"venue"
},
  "geometry": {"coordinates":[-78.067033,36.560519],"type":"Point"}
}