{
  "type": "Feature",
  "properties": {
    "addr:full":"3445 Periwinkle Ln Roanoke VA 24014",
    "addr:housenumber":"3445",
    "addr:postcode":"24014",
    "addr:street":"Periwinkle Ln",
    "iso:country":"US",
    "sg:address":"3445 Periwinkle Ln",
    "sg:city":"Roanoke",
    "sg:classifiers":[
        {
            "category":"Retail",
            "subcategory":"Auto Repair",
            "type":"Services"
        }
    ],
    "sg:phone":"+1 540 334 1311",
    "sg:postcode":"24014",
    "sg:province":"VA",
    "sg:tags":[
        "body"
    ],
    "wof:name":"B&C Auto Body",
    "wof:placetype":"venue"
},
  "geometry": {"coordinates":[-79.905669,37.226617],"type":"Point"}
}