{
  "type": "Feature",
  "properties": {
    "iso:country":"US",
    "sg:address":"3903 9th St S",
    "sg:city":"Arlington",
    "sg:classifiers":[
        {
            "category":"Building & Trades",
            "subcategory":"Construction",
            "type":"Services"
        }
    ],
    "sg:phone":"+1 703 979 3278",
    "sg:postcode":"22204",
    "sg:province":"VA",
    "sg:tags":[
        "contractor",
        "nonresidential"
    ],
    "wof:name":"T K Conable Contractor",
    "wof:placetype":"venue"
},
  "geometry": {"coordinates":[-77.09778900000001,38.861179],"type":"Point"}
}