{
  "type": "Feature",
  "properties": {
    "addr:full":"42046 Cherish Ct Aldie VA 20105",
    "addr:housenumber":"42046",
    "addr:postcode":"20105",
    "addr:street":"Cherish Ct",
    "iso:country":"US",
    "sg:address":"42046 Cherish Ct",
    "sg:city":"Aldie",
    "sg:classifiers":[
        {
            "category":"Building & Trades",
            "subcategory":"Construction",
            "type":"Services"
        }
    ],
    "sg:phone":"+1 703 327 3435",
    "sg:postcode":"20105",
    "sg:province":"VA",
    "sg:tags":[
        "contractor"
    ],
    "wof:name":"Akran Inc",
    "wof:placetype":"venue"
},
  "geometry": {"coordinates":[-77.54867400000001,38.915257],"type":"Point"}
}