{
  "type": "Feature",
  "properties": {
    "iso:country":"US",
    "sg:address":"512 Diane Ln",
    "sg:city":"Richmond",
    "sg:classifiers":[
        {
            "category":"Building & Trades",
            "subcategory":"Construction",
            "type":"Services"
        }
    ],
    "sg:phone":"+1 804 515 0725",
    "sg:postcode":"23227",
    "sg:province":"VA",
    "sg:tags":[
        "house"
    ],
    "wof:name":"Adaptable Home Designs",
    "wof:placetype":"venue"
},
  "geometry": {"coordinates":[-77.433543,37.636097],"type":"Point"}
}