{
  "type": "Feature",
  "properties": {
    "iso:country":"US",
    "sg:address":"9962 Brook Rd",
    "sg:city":"Glen Allen",
    "sg:classifiers":[
        {
            "category":"Professional",
            "subcategory":"Advertising",
            "type":"Services"
        }
    ],
    "sg:phone":"+1 804 565 9565",
    "sg:postcode":"23059",
    "sg:province":"VA",
    "sg:tags":[
        "mailing",
        "shipping"
    ],
    "wof:name":"UPS Store",
    "wof:placetype":"venue"
},
  "geometry": {"coordinates":[-77.46096300000001,37.671357],"type":"Point"}
}