{
  "type": "Feature",
  "properties": {
    "addr:full":"1800 Parkway Ln Richmond VA 23225",
    "addr:housenumber":"1800",
    "addr:postcode":"23225",
    "addr:street":"Parkway Ln",
    "iso:country":"US",
    "sg:address":"1800 Parkway Ln",
    "sg:city":"Richmond",
    "sg:classifiers":[
        {
            "category":"Organizations",
            "subcategory":"Religious Organization",
            "type":"Services"
        }
    ],
    "sg:phone":"+1 804 745 0709",
    "sg:postcode":"23225",
    "sg:province":"VA",
    "sg:tags":[
        "church"
    ],
    "wof:name":"Chinese Baptist Church",
    "wof:placetype":"venue"
},
  "geometry": {"coordinates":[-77.52244,37.481172],"type":"Point"}
}