{
  "type": "Feature",
  "properties": {
    "addr:full":"3120 Hatcher St Alexandria VA 22303",
    "addr:housenumber":"3120",
    "addr:postcode":"22303",
    "addr:street":"Hatcher St",
    "iso:country":"US",
    "sg:address":"3120 Hatcher St",
    "sg:city":"Alexandria",
    "sg:classifiers":[
        {
            "category":"Professional",
            "subcategory":"Management & Consulting",
            "type":"Services"
        }
    ],
    "sg:phone":"+1 703 960 5353",
    "sg:postcode":"22303",
    "sg:province":"VA",
    "wof:name":"Shadow Fax Medical Legal Consu",
    "wof:placetype":"venue"
},
  "geometry": {"coordinates":[-77.085854,38.797045],"type":"Point"}
}