{
  "type": "Feature",
  "properties": {
    "iso:country":"US",
    "sg:address":"5227 Winter View Dr",
    "sg:city":"Alexandria",
    "sg:classifiers":[
        {
            "category":"Professional",
            "type":"Services"
        }
    ],
    "sg:phone":"+1 703 504 6928",
    "sg:postcode":"22312",
    "sg:province":"VA",
    "wof:name":"Admirality House",
    "wof:placetype":"venue"
},
  "geometry": {"coordinates":[-77.148427,38.808165],"type":"Point"}
}