{
  "type": "Feature",
  "properties": {
    "addr:full":"210 N Main St Amherst VA 24521",
    "addr:housenumber":"210",
    "addr:postcode":"24521",
    "addr:street":"N Main St",
    "iso:country":"US",
    "sg:address":"210 N Main St",
    "sg:city":"Amherst",
    "sg:classifiers":[
        {
            "category":"Government",
            "subcategory":"Office",
            "type":"Public Place"
        }
    ],
    "sg:phone":"+1 434 946 5218",
    "sg:postcode":"24521",
    "sg:province":"VA",
    "sg:tags":[
        "state",
        "program"
    ],
    "wof:name":"Motor Vehicles Dept-License",
    "wof:placetype":"venue"
},
  "geometry": {"coordinates":[-79.045045,37.589411],"type":"Point"}
}