{
  "type": "Feature",
  "properties": {
    "iso:country":"US",
    "sg:address":"44 Irvington Rd",
    "sg:city":"Kilmarnock",
    "sg:classifiers":[
        {
            "category":"Organizations",
            "subcategory":"Membership Organization",
            "type":"Services"
        }
    ],
    "sg:phone":"+1 804 435 0822",
    "sg:postcode":"22482",
    "sg:province":"VA",
    "sg:tags":[
        "society",
        "humane"
    ],
    "wof:name":"Animal Welfare League Inc",
    "wof:placetype":"venue"
},
  "geometry": {"coordinates":[-76.38140199999999,37.709601],"type":"Point"}
}