{
  "type": "Feature",
  "properties": {
    "addr:full":"8614 Westwood Center Dr Vienna VA 22182",
    "addr:housenumber":"8614",
    "addr:postcode":"22182",
    "addr:street":"Westwood Center Dr",
    "iso:country":"US",
    "sg:address":"8614 Westwood Center Dr",
    "sg:city":"Vienna",
    "sg:classifiers":[
        {
            "category":"Shopping",
            "subcategory":"Computers & Home Electronics",
            "type":"Retail Goods"
        },
        {
            "category":"Professional",
            "subcategory":"Computer Services",
            "type":"Services"
        }
    ],
    "sg:phone":"+1 703 916 1770",
    "sg:postcode":"22182",
    "sg:province":"VA",
    "sg:tags":[
        "website",
        "development",
        "software",
        "related",
        "internet"
    ],
    "wof:name":"Systems Integration & Mgmt",
    "wof:placetype":"venue"
},
  "geometry": {"coordinates":[-77.24814000000001,38.928888],"type":"Point"}
}