{
  "type": "Feature",
  "properties": {
    "addr:full":"405 Walnut Ave SW Roanoke VA 24016",
    "addr:housenumber":"405",
    "addr:postcode":"24016",
    "addr:street":"Walnut Ave Sw",
    "iso:country":"US",
    "sg:address":"405 Walnut Ave SW",
    "sg:city":"Roanoke",
    "sg:classifiers":[
        {
            "category":"Home & Garden",
            "subcategory":"Home Furnishings",
            "type":"Retail Goods"
        }
    ],
    "sg:phone":"+1 540 343 4279",
    "sg:postcode":"24016",
    "sg:province":"VA",
    "wof:name":"Tailored Designs",
    "wof:placetype":"venue"
},
  "geometry": {"coordinates":[-79.951003,37.262589],"type":"Point"}
}