{
  "type": "Feature",
  "properties": {
    "iso:country":"US",
    "sg:address":"1451 Dolley Madison Blvd",
    "sg:city":"Mc Lean",
    "sg:classifiers":[
        {
            "category":"Wholesale",
            "subcategory":"Medical Equipment & Supplies",
            "type":"Manufacturing & Wholesale Goods"
        }
    ],
    "sg:phone":"+1 703 356 2564",
    "sg:postcode":"22101",
    "sg:province":"VA",
    "sg:tags":[
        "physician",
        "surgeon"
    ],
    "sg:website":"www.carerehab.com",
    "wof:name":"Care Rehab",
    "wof:placetype":"venue"
},
  "geometry": {"coordinates":[-77.183695,38.937628],"type":"Point"}
}