{
  "type": "Feature",
  "properties": {
    "addr:full":"5809 Lancelot Dr Virginia Beach VA 23464",
    "addr:housenumber":"5809",
    "addr:postcode":"23464",
    "addr:street":"Lancelot Dr",
    "iso:country":"US",
    "sg:address":"5809 Lancelot Dr",
    "sg:city":"Virginia Beach",
    "sg:classifiers":[
        {
            "category":"Health Services",
            "subcategory":"Clinic",
            "type":"Services"
        }
    ],
    "sg:phone":"+1 757 366 0411",
    "sg:postcode":"23464",
    "sg:province":"VA",
    "sg:tags":[
        "physician",
        "assistant"
    ],
    "wof:name":"Priscilla Serrano",
    "wof:placetype":"venue"
},
  "geometry": {"coordinates":[-76.19364899999999,36.825839],"type":"Point"}
}