{
  "type": "Feature",
  "properties": {
    "iso:country":"US",
    "sg:address":"7221 Old Keene Mill Rd",
    "sg:city":"Springfield",
    "sg:classifiers":[
        {
            "category":"Retail",
            "subcategory":"Self-service Laundry",
            "type":"Services"
        }
    ],
    "sg:phone":"+1 703 569 4842",
    "sg:postcode":"22150",
    "sg:province":"VA",
    "sg:tags":[
        "coin"
    ],
    "wof:name":"Keene Mill Cleaners",
    "wof:placetype":"venue"
},
  "geometry": {"coordinates":[-77.194703,38.777575],"type":"Point"}
}