{
  "type": "Feature",
  "properties": {
    "addr:full":"12318 Washington Brice Rd Fairfax VA 22033",
    "addr:housenumber":"12318",
    "addr:postcode":"22033",
    "addr:street":"Washington Brice Rd",
    "iso:country":"US",
    "sg:address":"12318 Washington Brice Rd",
    "sg:city":"Fairfax",
    "sg:classifiers":[
        {
            "category":"Professional",
            "subcategory":"Accounting & Tax Preparation",
            "type":"Services"
        }
    ],
    "sg:phone":"+1 703 716 0210",
    "sg:postcode":"22033",
    "sg:province":"VA",
    "sg:tags":[
        "return",
        "filing"
    ],
    "wof:name":"Blue & Grey Assoc",
    "wof:placetype":"venue"
},
  "geometry": {"coordinates":[-77.371692,38.879542],"type":"Point"}
}