{
  "type": "Feature",
  "properties": {
    "iso:country":"US",
    "sg:address":"2120 Washington Blvd Ste 100",
    "sg:city":"Arlington",
    "sg:classifiers":[
        {
            "category":"Shopping",
            "subcategory":"Stationery & Office Supplies",
            "type":"Retail Goods"
        }
    ],
    "sg:phone":"+1 703 271 1185",
    "sg:postcode":"22204",
    "sg:province":"VA",
    "sg:tags":[
        "equipment"
    ],
    "sg:website":"www.konica.com",
    "wof:name":"Konica Business Machines Government Marketing",
    "wof:placetype":"venue"
},
  "geometry": {"coordinates":[-77.09699999999999,38.860001],"type":"Point"}
}