{
  "type": "Feature",
  "properties": {
    "iso:country":"US",
    "sg:address":"4605 Liberton Ct",
    "sg:city":"Chesapeake",
    "sg:classifiers":[
        {
            "category":"Building & Trades",
            "subcategory":"Construction",
            "type":"Services"
        }
    ],
    "sg:phone":"+1 757 483 2924",
    "sg:postcode":"23321",
    "sg:province":"VA",
    "sg:tags":[
        "equipment",
        "systems-repairing",
        "contractor",
        "specialty",
        "heating"
    ],
    "wof:name":"Genesis Mechanical",
    "wof:placetype":"venue"
},
  "geometry": {"coordinates":[-76.413158,36.86301],"type":"Point"}
}