{
  "type": "Feature",
  "properties": {
    "iso:country":"US",
    "sg:address":"4533 Rothwell Dr",
    "sg:city":"Virginia Beach",
    "sg:classifiers":[
        {
            "category":"Building & Trades",
            "subcategory":"Construction",
            "type":"Services"
        }
    ],
    "sg:phone":"+1 757 467 3333",
    "sg:postcode":"23456",
    "sg:province":"VA",
    "sg:tags":[
        "house"
    ],
    "wof:name":"Wright Construction Company",
    "wof:placetype":"venue"
},
  "geometry": {"coordinates":[-76.136539,36.791074],"type":"Point"}
}