{
  "type": "Feature",
  "properties": {
    "addr:full":"4523 E Little Creek Rd Norfolk VA 23518",
    "addr:housenumber":"4523",
    "addr:postcode":"23518",
    "addr:street":"E Little Creek Rd",
    "iso:country":"US",
    "sg:address":"4523 E Little Creek Rd",
    "sg:city":"Norfolk",
    "sg:classifiers":[
        {
            "category":"Professional",
            "type":"Services"
        }
    ],
    "sg:phone":"+1 757 480 5941",
    "sg:postcode":"23518",
    "sg:province":"VA",
    "wof:name":"Nationwide Money Svc",
    "wof:placetype":"venue"
},
  "geometry": {"coordinates":[-76.19021499999999,36.918709],"type":"Point"}
}