{
  "type": "Feature",
  "properties": {
    "addr:full":"11787 Mente Rd Manassas VA 20112",
    "addr:postcode":"11787;20112",
    "addr:street":"Mente Rd",
    "iso:country":"US",
    "sg:address":"11787 Mente Rd",
    "sg:city":"Manassas",
    "sg:classifiers":[
        {
            "category":"Building & Trades",
            "subcategory":"Construction",
            "type":"Services"
        }
    ],
    "sg:phone":"+1 703 257 1581",
    "sg:postcode":"20112",
    "sg:province":"VA",
    "sg:tags":[
        "contractor",
        "painting",
        "hanging"
    ],
    "wof:name":"Browns Qlty Painting",
    "wof:placetype":"venue"
},
  "geometry": {"coordinates":[-77.464078,38.699857],"type":"Point"}
}