{
  "type": "Feature",
  "properties": {
    "addr:full":"1316 E Bayview Blvd Norfolk VA 23503",
    "addr:housenumber":"1316",
    "addr:postcode":"23503",
    "addr:street":"E Bayview Blvd",
    "iso:country":"US",
    "sg:address":"1316 E Bayview Blvd",
    "sg:city":"Norfolk",
    "sg:classifiers":[
        {
            "category":"Building & Trades",
            "subcategory":"Construction",
            "type":"Services"
        }
    ],
    "sg:phone":"+1 757 587 4986",
    "sg:postcode":"23503",
    "sg:province":"VA",
    "sg:tags":[
        "hanging",
        "contractor"
    ],
    "wof:name":"Stafford Painting",
    "wof:placetype":"venue"
},
  "geometry": {"coordinates":[-76.240886,36.934208],"type":"Point"}
}