{
  "type": "Feature",
  "properties": {
    "iso:country":"US",
    "sg:address":"106 S Franklin St",
    "sg:city":"Christiansburg",
    "sg:classifiers":[
        {
            "category":"Health Services",
            "subcategory":"Doctor",
            "type":"Services"
        }
    ],
    "sg:phone":"+1 540 381 2013",
    "sg:postcode":"24073",
    "sg:province":"VA",
    "sg:tags":[
        "physician",
        "surgeon"
    ],
    "wof:name":"NRV Eye Ctr",
    "wof:placetype":"venue"
},
  "geometry": {"coordinates":[-80.407628,37.129025],"type":"Point"}
}