{
  "type": "Feature",
  "properties": {
    "iso:country":"US",
    "sg:address":"5062 Golf Club Rd",
    "sg:city":"Danville",
    "sg:classifiers":[
        {
            "category":"Building & Trades",
            "subcategory":"Construction",
            "type":"Services"
        }
    ],
    "sg:phone":"+1 434 797 1291",
    "sg:postcode":"24540",
    "sg:province":"VA",
    "sg:tags":[
        "tile",
        "dealer",
        "contractor"
    ],
    "wof:name":"White's Tile & Marble Co",
    "wof:placetype":"venue"
},
  "geometry": {"coordinates":[-79.46063599999999,36.63258],"type":"Point"}
}