{
  "type": "Feature",
  "properties": {
    "addr:full":"75 Commonwealth Ct Clarksville VA 23927",
    "addr:housenumber":"75",
    "addr:postcode":"23927",
    "addr:street":"Commonwealth Ct",
    "iso:country":"US",
    "sg:address":"75 Commonwealth Ct",
    "sg:city":"Clarksville",
    "sg:classifiers":[
        {
            "category":"Professional",
            "subcategory":"Business Services",
            "type":"Services"
        }
    ],
    "sg:phone":"+1 434 374 4239",
    "sg:postcode":"23927",
    "sg:province":"VA",
    "wof:name":"CDM Enterprises Inc",
    "wof:placetype":"venue"
},
  "geometry": {"coordinates":[-78.55882,36.650374],"type":"Point"}
}