{
  "type": "Feature",
  "properties": {
    "addr:full":"360 W Main St Lebanon VA 24266",
    "addr:housenumber":"360",
    "addr:postcode":"24266",
    "addr:street":"W Main St",
    "iso:country":"US",
    "sg:address":"360 W Main St",
    "sg:city":"Lebanon",
    "sg:classifiers":[
        {
            "category":"Health Services",
            "subcategory":"Doctor",
            "type":"Services"
        }
    ],
    "sg:phone":"+1 276 889 0035",
    "sg:postcode":"24266",
    "sg:province":"VA",
    "sg:tags":[
        "physician",
        "surgeon"
    ],
    "wof:name":"Javed & Assoc Medical Clnc",
    "wof:placetype":"venue"
},
  "geometry": {"coordinates":[-82.08951500000001,36.899833],"type":"Point"}
}