{
  "type": "Feature",
  "properties": {
    "iso:country":"US",
    "sg:address":"12095 Fair Oaks Mall",
    "sg:city":"Fairfax",
    "sg:classifiers":[
        {
            "category":"Home & Garden",
            "subcategory":"Furniture",
            "type":"Retail Goods"
        }
    ],
    "sg:phone":"+1 703 591 6868",
    "sg:postcode":"22033",
    "sg:province":"VA",
    "sg:website":"www.bombaycompany.com",
    "wof:name":"Bombay Co",
    "wof:placetype":"venue"
},
  "geometry": {"coordinates":[-77.358043,38.860773],"type":"Point"}
}