{
  "type": "Feature",
  "properties": {
    "iso:country":"US",
    "sg:address":"816 S Veitch St",
    "sg:city":"Arlington",
    "sg:classifiers":[
        {
            "category":"Professional",
            "subcategory":"Art Services",
            "type":"Services"
        }
    ],
    "sg:phone":"+1 703 856 6802",
    "sg:postcode":"22204",
    "sg:province":"VA",
    "sg:tags":[
        "graphic",
        "design"
    ],
    "wof:name":"Binti Designs LLC",
    "wof:placetype":"venue"
},
  "geometry": {"coordinates":[-77.08156099999999,38.86528],"type":"Point"}
}