{
  "type": "Feature",
  "properties": {
    "iso:country":"US",
    "sg:address":"210 East Rd",
    "sg:city":"Portsmouth",
    "sg:classifiers":[
        {
            "category":"Professional",
            "subcategory":"Lawyer & Legal Services",
            "type":"Services"
        }
    ],
    "sg:phone":"+1 757 399 8105",
    "sg:postcode":"23707",
    "sg:province":"VA",
    "wof:name":"Goldcrest Properties",
    "wof:placetype":"venue"
},
  "geometry": {"coordinates":[-76.350295,36.842959],"type":"Point"}
}