{
  "type": "Feature",
  "properties": {
    "addr:full":"603 W Main St Smithfield VA 23430",
    "addr:housenumber":"603",
    "addr:postcode":"23430",
    "addr:street":"W Main St",
    "iso:country":"US",
    "sg:address":"603 W Main St",
    "sg:city":"Smithfield",
    "sg:classifiers":[
        {
            "category":"Food & Beverages",
            "subcategory":"Groceries & Convenience Stores",
            "type":"Retail Goods"
        }
    ],
    "sg:phone":"+1 757 357 5558",
    "sg:postcode":"23430",
    "sg:province":"VA",
    "sg:website":"www.exxon.com",
    "wof:name":"Tom & Jerry's Exxon",
    "wof:placetype":"venue"
},
  "geometry": {"coordinates":[-76.64156699999999,36.976779],"type":"Point"}
}