{
  "type": "Feature",
  "properties": {
    "addr:full":"2 Wyatt Ct Sterling VA 20165",
    "addr:housenumber":"2",
    "addr:postcode":"20165",
    "addr:street":"Wyatt Ct",
    "iso:country":"US",
    "sg:address":"2 Wyatt Ct",
    "sg:city":"Sterling",
    "sg:classifiers":[
        {
            "category":"Airline",
            "type":"Transportation"
        }
    ],
    "sg:phone":"+1 703 421 3575",
    "sg:postcode":"20165",
    "sg:province":"VA",
    "sg:tags":[
        "nonscheduled",
        "air"
    ],
    "wof:name":"Creative Jets",
    "wof:placetype":"venue"
},
  "geometry": {"coordinates":[-77.421711,39.047779],"type":"Point"}
}