{
  "type": "Feature",
  "properties": {
    "addr:full":"125 Armory Rd Galax VA 24333",
    "addr:housenumber":"125",
    "addr:postcode":"24333",
    "addr:street":"Armory Rd",
    "iso:country":"US",
    "sg:address":"125 Armory Rd",
    "sg:city":"Galax",
    "sg:classifiers":[
        {
            "category":"Government",
            "subcategory":"Office",
            "type":"Public Place"
        }
    ],
    "sg:phone":"+1 276 236 3124",
    "sg:postcode":"24333",
    "sg:province":"VA",
    "sg:tags":[
        "national",
        "security"
    ],
    "wof:name":"United States Dept of Army",
    "wof:placetype":"venue"
},
  "geometry": {"coordinates":[-80.93855499999999,36.659563],"type":"Point"}
}