{
  "type": "Feature",
  "properties": {
    "addr:full":"35091 Paxson Rd Round Hill VA 20141",
    "addr:postcode":"35091;20141",
    "addr:street":"Paxson Rd",
    "iso:country":"US",
    "sg:address":"35091 Paxson Rd",
    "sg:city":"Round Hill",
    "sg:classifiers":[
        {
            "category":"Farming",
            "subcategory":"Livestock Farm",
            "type":"Manufacturing & Wholesale Goods"
        }
    ],
    "sg:phone":"+1 540 554 8193",
    "sg:postcode":"20141",
    "sg:province":"VA",
    "sg:tags":[
        "beef",
        "feedlot",
        "cattle"
    ],
    "wof:name":"Sullystone Farm",
    "wof:placetype":"venue"
},
  "geometry": {"coordinates":[-77.794708,39.098325],"type":"Point"}
}