{
  "type": "Feature",
  "properties": {
    "iso:country":"US",
    "sg:address":"728 Baker Ln",
    "sg:city":"Winchester",
    "sg:classifiers":[
        {
            "category":"Home & Garden",
            "subcategory":"Building Materials",
            "type":"Retail Goods"
        }
    ],
    "sg:phone":"+1 540 667 5155",
    "sg:postcode":"22603",
    "sg:province":"VA",
    "sg:tags":[
        "glass",
        "window",
        "plate"
    ],
    "wof:name":"Mack Kerns' Glass & Mirror Inc",
    "wof:placetype":"venue"
},
  "geometry": {"coordinates":[-78.14348699999999,39.191931],"type":"Point"}
}