{
  "type": "Feature",
  "properties": {
    "addr:full":"33 Glade Ct Altavista VA 24517",
    "addr:housenumber":"33",
    "addr:postcode":"24517",
    "addr:street":"Glade Ct",
    "iso:country":"US",
    "sg:address":"33 Glade Ct",
    "sg:city":"Altavista",
    "sg:classifiers":[
        {
            "category":"Professional",
            "subcategory":"Management & Consulting",
            "type":"Services"
        }
    ],
    "sg:phone":"+1 434 369 4679",
    "sg:postcode":"24517",
    "sg:province":"VA",
    "sg:tags":[
        "consultant"
    ],
    "wof:name":"Tuthill Associates",
    "wof:placetype":"venue"
},
  "geometry": {"coordinates":[-79.313377,37.129979],"type":"Point"}
}