{
  "type": "Feature",
  "properties": {
    "iso:country":"US",
    "sg:address":"1502 Hamilton Dr",
    "sg:city":"Lynchburg",
    "sg:classifiers":[
        {
            "category":"Restaurant",
            "type":"Food & Drink"
        }
    ],
    "sg:phone":"+1 434 384 1927",
    "sg:postcode":"24503",
    "sg:province":"VA",
    "sg:tags":[
        "eating"
    ],
    "wof:name":"Cooks Alley Catering",
    "wof:placetype":"venue"
},
  "geometry": {"coordinates":[-79.204384,37.442287],"type":"Point"}
}