{
  "type": "Feature",
  "properties": {
    "addr:full":"440 Nursery Purcellville VA 20132",
    "addr:housenumber":"440",
    "addr:postcode":"20132",
    "addr:street":"Nursery",
    "iso:country":"US",
    "sg:address":"440 Nursery",
    "sg:city":"Purcellville",
    "sg:classifiers":[
        {
            "category":"Education",
            "subcategory":"School",
            "type":"Public Place"
        }
    ],
    "sg:phone":"+1 540 338 6870",
    "sg:postcode":"20132",
    "sg:province":"VA",
    "wof:name":"Louden Elementary",
    "wof:placetype":"venue"
},
  "geometry": {"coordinates":[-77.720029,39.131035],"type":"Point"}
}