{
  "type": "Feature",
  "properties": {
    "iso:country":"US",
    "sg:address":"4211 W Mercury Blvd",
    "sg:city":"Hampton",
    "sg:classifiers":[
        {
            "category":"Cinema",
            "subcategory":"Movie Rental",
            "type":"Entertainment"
        }
    ],
    "sg:phone":"+1 757 827 8763",
    "sg:postcode":"23666",
    "sg:province":"VA",
    "sg:tags":[
        "video",
        "tape"
    ],
    "wof:name":"Video Store II",
    "wof:placetype":"venue"
},
  "geometry": {"coordinates":[-76.42765900000001,37.027741],"type":"Point"}
}