{
  "type": "Feature",
  "properties": {
    "addr:full":"43345 Nicklaus Ln Chantilly VA 20152",
    "addr:postcode":"43345;20152",
    "addr:street":"Nicklaus Ln",
    "iso:country":"US",
    "sg:address":"43345 Nicklaus Ln",
    "sg:city":"Chantilly",
    "sg:classifiers":[
        {
            "category":"Social Services",
            "subcategory":"Child Care",
            "type":"Services"
        }
    ],
    "sg:phone":"+1 540 454 8636",
    "sg:postcode":"20152",
    "sg:province":"VA",
    "sg:tags":[
        "day"
    ],
    "wof:name":"Laila's Home Daycare",
    "wof:placetype":"venue"
},
  "geometry": {"coordinates":[-77.50305,38.895057],"type":"Point"}
}