{
  "type": "Feature",
  "properties": {
    "iso:country":"US",
    "sg:address":"23197 Governor Harrison Pkwy",
    "sg:city":"Freeman",
    "sg:classifiers":[
        {
            "category":"Home & Garden",
            "subcategory":"Mobile Homes",
            "type":"Retail Goods"
        },
        {
            "category":"Manufacturing",
            "subcategory":"Buildings",
            "type":"Manufacturing & Wholesale Goods"
        }
    ],
    "sg:phone":"+1 434 336 0070",
    "sg:postcode":"23856",
    "sg:province":"VA",
    "sg:tags":[
        "prefab"
    ],
    "wof:name":"Superior Homes",
    "wof:placetype":"venue"
},
  "geometry": {"coordinates":[-77.65655700000001,36.75735],"type":"Point"}
}