{
  "type": "Feature",
  "properties": {
    "iso:country":"US",
    "sg:address":"1487 Chain Bridge Rd Ste 100",
    "sg:city":"McLean",
    "sg:classifiers":[
        {
            "category":"Building & Trades",
            "subcategory":"Construction",
            "type":"Services"
        }
    ],
    "sg:phone":"+1 703 442 3200",
    "sg:postcode":"22101",
    "sg:province":"VA",
    "sg:tags":[
        "interior",
        "design"
    ],
    "sg:website":"www.hughesdes.com",
    "wof:name":"Hughes Design Associates",
    "wof:placetype":"venue"
},
  "geometry": {"coordinates":[-77.181015,38.931088],"type":"Point"}
}