{
  "type": "Feature",
  "properties": {
    "addr:full":"138 Windy Pines Rd Front Royal VA 22630",
    "addr:housenumber":"138",
    "addr:postcode":"22630",
    "addr:street":"Windy Pines Rd",
    "iso:country":"US",
    "sg:address":"138 Windy Pines Rd",
    "sg:city":"Front Royal",
    "sg:phone":"+1 540 636 6849",
    "sg:postcode":"22630",
    "sg:province":"VA",
    "sg:tags":[
        "communications",
        "telegraph"
    ],
    "wof:name":"Byways Unlimited LLC",
    "wof:placetype":"venue"
},
  "geometry": {"coordinates":[-78.26912900000001,38.874971],"type":"Point"}
}