{
  "type": "Feature",
  "properties": {
    "iso:country":"US",
    "sg:address":"1700 N Moore St",
    "sg:city":"Arlington",
    "sg:classifiers":[
        {
            "category":"Food & Beverages",
            "subcategory":"Specialty",
            "type":"Retail Goods"
        },
        {
            "category":"Coffee & Tea",
            "type":"Food & Drink"
        },
        {
            "category":"Bakery",
            "type":"Food & Drink"
        },
        {
            "category":"Deli",
            "type":"Food & Drink"
        }
    ],
    "sg:phone":"+1 703 524 8900",
    "sg:postcode":"22209",
    "sg:province":"VA",
    "sg:website":"www.tivolirestaurant.net",
    "wof:name":"Tivoli Restaurant",
    "wof:placetype":"venue"
},
  "geometry": {"coordinates":[-77.07150300000001,38.8951],"type":"Point"}
}