{
  "type": "Feature",
  "properties": {
    "addr:full":"12491 Church Rd Richmond VA 23233",
    "addr:housenumber":"12491",
    "addr:postcode":"23233",
    "addr:street":"Church Rd",
    "iso:country":"US",
    "sg:address":"12491 Church Rd",
    "sg:city":"Richmond",
    "sg:classifiers":[
        {
            "category":"Government",
            "subcategory":"Fire Station",
            "type":"Public Place"
        }
    ],
    "sg:phone":"+1 804 501 4901",
    "sg:postcode":"23233",
    "sg:province":"VA",
    "sg:tags":[
        "protection"
    ],
    "wof:name":"Fire Station 13",
    "wof:placetype":"venue"
},
  "geometry": {"coordinates":[-77.633988,37.637105],"type":"Point"}
}