{
  "type": "Feature",
  "properties": {
    "iso:country":"US",
    "sg:address":"7849 Azalea Garden Rd",
    "sg:city":"Norfolk",
    "sg:classifiers":[
        {
            "category":"Professional",
            "subcategory":"Business Services",
            "type":"Services"
        }
    ],
    "sg:phone":"+1 757 587 0007",
    "sg:postcode":"23518",
    "sg:province":"VA",
    "sg:tags":[
        "process",
        "serving"
    ],
    "wof:name":"Ba International Inc",
    "wof:placetype":"venue"
},
  "geometry": {"coordinates":[-76.21166100000001,36.9143],"type":"Point"}
}