{
  "type": "Feature",
  "properties": {
    "iso:country":"US",
    "sg:address":"320 Hospital Dr",
    "sg:city":"Martinsville",
    "sg:classifiers":[
        {
            "category":"Restaurant",
            "type":"Food & Drink"
        }
    ],
    "sg:phone":"+1 276 666 7637",
    "sg:postcode":"24112",
    "sg:province":"VA",
    "sg:tags":[
        "eating"
    ],
    "wof:name":"Marriott",
    "wof:placetype":"venue"
},
  "geometry": {"coordinates":[-79.865137,36.698079],"type":"Point"}
}