{
  "type": "Feature",
  "properties": {
    "addr:full":"2149 Ferguson Rd Ringgold VA 24586",
    "addr:housenumber":"2149",
    "addr:postcode":"24586",
    "addr:street":"Ferguson Rd",
    "iso:country":"US",
    "sg:address":"2149 Ferguson Rd",
    "sg:city":"Ringgold",
    "sg:classifiers":[
        {
            "category":"Farming",
            "subcategory":"Farm",
            "type":"Manufacturing & Wholesale Goods"
        }
    ],
    "sg:phone":"+1 434 822 8708",
    "sg:postcode":"24586",
    "sg:province":"VA",
    "sg:tags":[
        "crop",
        "general"
    ],
    "wof:name":"Scott Lynch",
    "wof:placetype":"venue"
},
  "geometry": {"coordinates":[-79.28796199999999,36.634677],"type":"Point"}
}