{
  "type": "Feature",
  "properties": {
    "iso:country":"US",
    "sg:address":"61 Meadow Ln",
    "sg:city":"Collinsville",
    "sg:classifiers":[
        {
            "category":"Social Services",
            "subcategory":"Child Care",
            "type":"Services"
        }
    ],
    "sg:phone":"+1 276 647 5722",
    "sg:postcode":"24078",
    "sg:province":"VA",
    "wof:name":"Bright Beginnings Child Ctr",
    "wof:placetype":"venue"
},
  "geometry": {"coordinates":[-79.911299,36.723638],"type":"Point"}
}