{
  "type": "Feature",
  "properties": {
    "addr:full":"2971 Valley Ave Winchester VA 22601",
    "addr:housenumber":"2971",
    "addr:postcode":"22601",
    "addr:street":"Valley Ave",
    "iso:country":"US",
    "sg:address":"2971 Valley Ave",
    "sg:city":"Winchester",
    "sg:classifiers":[
        {
            "category":"Professional",
            "type":"Services"
        }
    ],
    "sg:phone":"+1 540 450 2753",
    "sg:postcode":"22601",
    "sg:province":"VA",
    "sg:tags":[
        "establishment"
    ],
    "wof:name":"Contract Solutions",
    "wof:placetype":"venue"
},
  "geometry": {"coordinates":[-78.189317,39.146292],"type":"Point"}
}