{
  "type": "Feature",
  "properties": {
    "addr:full":"107 Main St Appomattox VA 24531",
    "addr:housenumber":"107",
    "addr:postcode":"24531",
    "addr:street":"Main St",
    "iso:country":"US",
    "sg:address":"107 Main St",
    "sg:city":"Appomattox",
    "sg:classifiers":[
        {
            "category":"Wholesale",
            "subcategory":"Farm Supplies",
            "type":"Manufacturing & Wholesale Goods"
        }
    ],
    "sg:phone":"+1 434 352 7298",
    "sg:postcode":"24531",
    "sg:province":"VA",
    "wof:name":"Coleman & Sons Inc",
    "wof:placetype":"venue"
},
  "geometry": {"coordinates":[-79.396649,36.830121],"type":"Point"}
}