{
  "type": "Feature",
  "properties": {
    "addr:full":"1177 N Main St Marion VA 24354",
    "addr:housenumber":"1177",
    "addr:postcode":"24354",
    "addr:street":"N Main St",
    "iso:country":"US",
    "sg:address":"1177 N Main St",
    "sg:city":"Marion",
    "sg:classifiers":[
        {
            "category":"Government",
            "subcategory":"Office",
            "type":"Public Place"
        }
    ],
    "sg:phone":"+1 276 783 2215",
    "sg:postcode":"24354",
    "sg:province":"VA",
    "sg:tags":[
        "executive"
    ],
    "wof:name":"Alcoholic Beverage Ctrl 135",
    "wof:placetype":"venue"
},
  "geometry": {"coordinates":[-81.501712,36.844054],"type":"Point"}
}