{
  "type": "Feature",
  "properties": {
    "addr:full":"1057 Edwards Ferry Rd NE Leesburg VA 20176",
    "addr:housenumber":"1057",
    "addr:postcode":"20176",
    "addr:street":"Edwards Ferry Rd Ne",
    "iso:country":"US",
    "sg:address":"1057 Edwards Ferry Rd NE",
    "sg:city":"Leesburg",
    "sg:classifiers":[
        {
            "category":"Banks & Credit Unions",
            "subcategory":"Financial Services",
            "type":"Services"
        }
    ],
    "sg:phone":"+1 571 258 1610",
    "sg:postcode":"20176",
    "sg:province":"VA",
    "sg:tags":[
        "company",
        "holding"
    ],
    "wof:name":"Bayside Holding Co Inc",
    "wof:placetype":"venue"
},
  "geometry": {"coordinates":[-77.537891,39.113536],"type":"Point"}
}