{
  "type": "Feature",
  "properties": {
    "iso:country":"US",
    "sg:address":"9001 Braddock Rd",
    "sg:city":"Springfield",
    "sg:classifiers":[
        {
            "category":"Wholesale",
            "subcategory":"Durable Goods & Equipment",
            "type":"Manufacturing & Wholesale Goods"
        }
    ],
    "sg:phone":"+1 703 323 8880",
    "sg:postcode":"22151",
    "sg:province":"VA",
    "sg:tags":[
        "fire",
        "extinguisher"
    ],
    "wof:name":"A-Advance Mobile Fire Prtctn",
    "wof:placetype":"venue"
},
  "geometry": {"coordinates":[-77.253015,38.810601],"type":"Point"}
}