{
  "type": "Feature",
  "properties": {
    "iso:country":"US",
    "sg:address":"36 Briolette Ct",
    "sg:city":"Fincastle",
    "sg:classifiers":[
        {
            "category":"Freight",
            "type":"Transportation"
        }
    ],
    "sg:phone":"+1 540 992 2346",
    "sg:postcode":"24090",
    "sg:province":"VA",
    "sg:tags":[
        "operator",
        "local",
        "trucking"
    ],
    "wof:name":"Montgomery Trucking",
    "wof:placetype":"venue"
},
  "geometry": {"coordinates":[-79.79914599999999,37.468049],"type":"Point"}
}