{
  "type": "Feature",
  "properties": {
    "addr:full":"40 Crescent St Front Royal VA 22630",
    "addr:housenumber":"40",
    "addr:postcode":"22630",
    "addr:street":"Crescent St",
    "iso:country":"US",
    "sg:address":"40 Crescent St",
    "sg:city":"Front Royal",
    "sg:classifiers":[
        {
            "category":"Education",
            "subcategory":"School",
            "type":"Public Place"
        }
    ],
    "sg:phone":"+1 540 635 4188",
    "sg:postcode":"22630",
    "sg:province":"VA",
    "wof:name":"E W Morrison Primary School",
    "wof:placetype":"venue"
},
  "geometry": {"coordinates":[-78.19181399999999,38.91959],"type":"Point"}
}