{
  "type": "Feature",
  "properties": {
    "iso:country":"US",
    "sg:address":"13721 Jefferson Davis Hwy",
    "sg:city":"Woodbridge",
    "sg:classifiers":[
        {
            "category":"Manufacturing",
            "subcategory":"Metals",
            "type":"Manufacturing & Wholesale Goods"
        }
    ],
    "sg:phone":"+1 703 675 5924",
    "sg:postcode":"22191",
    "sg:province":"VA",
    "sg:tags":[
        "metalwork",
        "sheet",
        "mfg"
    ],
    "wof:name":"Brothers Ductwork Inc",
    "wof:placetype":"venue"
},
  "geometry": {"coordinates":[-77.25338000000001,38.654005],"type":"Point"}
}