{
  "type": "Feature",
  "properties": {
    "addr:full":"23411 Autopilot Dr Sterling VA 20166",
    "addr:housenumber":"23411",
    "addr:postcode":"20166",
    "addr:street":"Autopilot Dr",
    "iso:country":"US",
    "sg:address":"23411 Autopilot Dr",
    "sg:city":"Sterling",
    "sg:classifiers":[
        {
            "category":"Local Transit",
            "type":"Transportation"
        }
    ],
    "sg:phone":"+1 703 661 1331",
    "sg:postcode":"20166",
    "sg:province":"VA",
    "sg:tags":[
        "limousine"
    ],
    "wof:name":"U S Sedan Svc Inc",
    "wof:placetype":"venue"
},
  "geometry": {"coordinates":[-77.44961000000001,38.971289],"type":"Point"}
}