{
  "type": "Feature",
  "properties": {
    "iso:country":"US",
    "sg:address":"1220 Graylyn Rd",
    "sg:city":"Virginia Beach",
    "sg:classifiers":[
        {
            "category":"Professional",
            "type":"Services"
        }
    ],
    "sg:phone":"+1 757 313 7652",
    "sg:postcode":"23464",
    "sg:province":"VA",
    "sg:tags":[
        "establishment"
    ],
    "wof:name":"Davidson & Davidson",
    "wof:placetype":"venue"
},
  "geometry": {"coordinates":[-76.149783,36.780215],"type":"Point"}
}