{
  "type": "Feature",
  "properties": {
    "iso:country":"US",
    "sg:address":"250 S Wayne Ave",
    "sg:city":"Waynesboro",
    "sg:classifiers":[
        {
            "category":"Government",
            "subcategory":"Police Station",
            "type":"Public Place"
        }
    ],
    "sg:phone":"+1 540 942 6675",
    "sg:postcode":"22980",
    "sg:province":"VA",
    "sg:tags":[
        "department"
    ],
    "wof:name":"Waynesboro Police Dept",
    "wof:placetype":"venue"
},
  "geometry": {"coordinates":[-78.889957,38.066947],"type":"Point"}
}