{
  "type": "Feature",
  "properties": {
    "addr:full":"397 Little Neck Rd Virginia Beach VA 23452",
    "addr:housenumber":"397",
    "addr:postcode":"23452",
    "addr:street":"Little Neck Rd",
    "iso:country":"US",
    "sg:address":"397 Little Neck Rd",
    "sg:city":"Virginia Beach",
    "sg:classifiers":[
        {
            "category":"Personal",
            "type":"Services"
        }
    ],
    "sg:phone":"+1 757 340 2564",
    "sg:postcode":"23452",
    "sg:province":"VA",
    "sg:tags":[
        "credit",
        "debt",
        "counseling"
    ],
    "wof:name":"Harbour Credit Counseling Svc",
    "wof:placetype":"venue"
},
  "geometry": {"coordinates":[-76.091407,36.84378],"type":"Point"}
}