{
  "type": "Feature",
  "properties": {
    "addr:full":"250 W Lee Hwy Warrenton VA 20186",
    "addr:housenumber":"250",
    "addr:postcode":"20186",
    "addr:street":"W Lee Hwy",
    "iso:country":"US",
    "sg:address":"250 W Lee Hwy",
    "sg:city":"Warrenton",
    "sg:classifiers":[
        {
            "category":"Shopping",
            "subcategory":"Clothing, Apparel, & Fashions",
            "type":"Retail Goods"
        }
    ],
    "sg:phone":"+1 540 341 2700",
    "sg:postcode":"20186",
    "sg:province":"VA",
    "sg:tags":[
        "costume"
    ],
    "wof:name":"Masters Costumes",
    "wof:placetype":"venue"
},
  "geometry": {"coordinates":[-77.799519,38.728531],"type":"Point"}
}