{
  "type": "Feature",
  "properties": {
    "addr:full":"6747 Lea Berry Way Haymarket VA 20169",
    "addr:housenumber":"6747",
    "addr:postcode":"20169",
    "addr:street":"Lea Berry Way",
    "iso:country":"US",
    "sg:address":"6747 Lea Berry Way",
    "sg:city":"Haymarket",
    "sg:classifiers":[
        {
            "category":"Food & Beverages",
            "subcategory":"Bakery",
            "type":"Retail Goods"
        }
    ],
    "sg:phone":"+1 703 753 1115",
    "sg:postcode":"20169",
    "sg:province":"VA",
    "sg:tags":[
        "sandwich"
    ],
    "sg:website":"www.subway.com",
    "wof:name":"Subway",
    "wof:placetype":"venue"
},
  "geometry": {"coordinates":[-77.64149399999999,38.814311],"type":"Point"}
}