{
  "type": "Feature",
  "properties": {
    "iso:country":"US",
    "sg:address":"1407 Oakwood Ave",
    "sg:city":"Richmond",
    "sg:classifiers":[
        {
            "category":"Building & Trades",
            "subcategory":"Cleaning & Sanitation",
            "type":"Services"
        }
    ],
    "sg:phone":"+1 804 226 9038",
    "sg:postcode":"23223",
    "sg:province":"VA",
    "sg:tags":[
        "janitor"
    ],
    "wof:name":"Mike's Cleaning Svc",
    "wof:placetype":"venue"
},
  "geometry": {"coordinates":[-77.39954299999999,37.533961],"type":"Point"}
}