{
  "type": "Feature",
  "properties": {
    "addr:full":"1001 S Glebe Rd Arlington VA 22204",
    "addr:housenumber":"1001",
    "addr:postcode":"22204",
    "addr:street":"S Glebe Rd",
    "iso:country":"US",
    "sg:address":"1001 S Glebe Rd",
    "sg:city":"Arlington",
    "sg:classifiers":[
        {
            "category":"Autos & Motor Vehicles",
            "subcategory":"Fuel & Gas Station",
            "type":"Retail Goods"
        },
        {
            "category":"Autos & Motor Vehicles",
            "subcategory":"Auto Supplies",
            "type":"Retail Goods"
        },
        {
            "category":"Retail",
            "subcategory":"Auto Repair",
            "type":"Services"
        }
    ],
    "sg:phone":"+1 703 979 0667",
    "sg:postcode":"22204",
    "sg:province":"VA",
    "sg:tags":[
        "exhaust",
        "oil",
        "tire",
        "automobile",
        "system",
        "accessory",
        "lube",
        "part",
        "brake",
        "muffler"
    ],
    "sg:website":"http://www.midaswashingtondc.com",
    "wof:name":"Midas",
    "wof:placetype":"venue"
},
  "geometry": {"coordinates":[-77.09198000000001,38.861259],"type":"Point"}
}