{
  "type": "Feature",
  "properties": {
    "addr:full":"11801 Boydton Plank Rd Dinwiddie VA 23841",
    "addr:housenumber":"11801",
    "addr:postcode":"23841",
    "addr:street":"Boydton Plank Rd",
    "iso:country":"US",
    "sg:address":"11801 Boydton Plank Rd",
    "sg:city":"Dinwiddie",
    "sg:classifiers":[
        {
            "category":"Autos & Motor Vehicles",
            "subcategory":"Auto Supplies",
            "type":"Retail Goods"
        }
    ],
    "sg:phone":"+1 804 469 3200",
    "sg:postcode":"23841",
    "sg:province":"VA",
    "sg:tags":[
        "tire"
    ],
    "wof:name":"Number One Tires",
    "wof:placetype":"venue"
},
  "geometry": {"coordinates":[-77.56159,37.104241],"type":"Point"}
}