{
  "type": "Feature",
  "properties": {
    "iso:country":"US",
    "sg:address":"5200 Newbys Bridge Rd",
    "sg:city":"Chesterfield",
    "sg:classifiers":[
        {
            "category":"Organizations",
            "subcategory":"Religious Organization",
            "type":"Services"
        }
    ],
    "sg:phone":"+1 804 276 5803",
    "sg:postcode":"23832",
    "sg:province":"VA",
    "wof:name":"Friendship Baptist Church",
    "wof:placetype":"venue"
},
  "geometry": {"coordinates":[-77.549874,37.432767],"type":"Point"}
}