{
  "type": "Feature",
  "properties": {
    "addr:full":"406 W Broad St Richmond VA 23220",
    "addr:housenumber":"406",
    "addr:postcode":"23220",
    "addr:street":"W Broad St",
    "iso:country":"US",
    "sg:address":"406 W Broad St",
    "sg:city":"Richmond",
    "sg:classifiers":[
        {
            "category":"Professional",
            "subcategory":"Lawyer & Legal Services",
            "type":"Services"
        }
    ],
    "sg:phone":"+1 804 780 0400",
    "sg:postcode":"23220",
    "sg:province":"VA",
    "wof:name":"Lawyers Closing Service",
    "wof:placetype":"venue"
},
  "geometry": {"coordinates":[-77.44624,37.548217],"type":"Point"}
}