{
  "type": "Feature",
  "properties": {
    "addr:full":"1510 N 28th St Richmond VA 23223",
    "addr:housenumber":"1510",
    "addr:postcode":"23223",
    "addr:street":"N 28Th St",
    "iso:country":"US",
    "sg:address":"1510 N 28th St",
    "sg:city":"Richmond",
    "sg:classifiers":[
        {
            "category":"Health Services",
            "subcategory":"Doctor",
            "type":"Services"
        }
    ],
    "sg:phone":"+1 804 440 8425",
    "sg:postcode":"23223",
    "sg:province":"VA",
    "sg:tags":[
        "medical"
    ],
    "wof:name":"Barrington H Bowser MD",
    "wof:placetype":"venue"
},
  "geometry": {"coordinates":[-77.405514,37.541111],"type":"Point"}
}