{
  "type": "Feature",
  "properties": {
    "addr:full":"9500 Barlow Rd Fort Belvoir VA 22060",
    "addr:housenumber":"9500",
    "addr:postcode":"22060",
    "addr:street":"Barlow Rd",
    "iso:country":"US",
    "sg:address":"9500 Barlow Rd",
    "sg:city":"Fort Belvoir",
    "sg:classifiers":[
        {
            "category":"Social Services",
            "subcategory":"Child Care",
            "type":"Services"
        }
    ],
    "sg:phone":"+1 703 805 3339",
    "sg:postcode":"22060",
    "sg:province":"VA",
    "sg:tags":[
        "day"
    ],
    "wof:name":"Child Development Center",
    "wof:placetype":"venue"
},
  "geometry": {"coordinates":[-77.131153,38.698761],"type":"Point"}
}