{
  "type": "Feature",
  "properties": {
    "addr:full":"4107 Lafayette Blvd Fredericksburg VA 22408",
    "addr:housenumber":"4107",
    "addr:postcode":"22408",
    "addr:street":"Lafayette Blvd",
    "iso:country":"US",
    "sg:address":"4107 Lafayette Blvd",
    "sg:city":"Fredericksburg",
    "sg:classifiers":[
        {
            "category":"Insurance",
            "subcategory":"Insurance Agent",
            "type":"Services"
        }
    ],
    "sg:phone":"+1 703 891 0112",
    "sg:postcode":"22408",
    "sg:province":"VA",
    "wof:name":"Cost Containment Group Inc",
    "wof:placetype":"venue"
},
  "geometry": {"coordinates":[-77.49234800000001,38.26249],"type":"Point"}
}