{
  "type": "Feature",
  "properties": {
    "addr:full":"3376 Virginia Beach Blvd Virginia Beach VA 23452",
    "addr:housenumber":"3376",
    "addr:postcode":"23452",
    "addr:street":"Virginia Beach Blvd",
    "iso:country":"US",
    "sg:address":"3376 Virginia Beach Blvd",
    "sg:city":"Virginia Beach",
    "sg:classifiers":[
        {
            "category":"Shopping",
            "subcategory":"Pharmacy",
            "type":"Retail Goods"
        }
    ],
    "sg:phone":"+1 757 340 6935",
    "sg:postcode":"23452",
    "sg:province":"VA",
    "wof:name":"Walgreens",
    "wof:placetype":"venue"
},
  "geometry": {"coordinates":[-76.090176,36.841752],"type":"Point"}
}