{
  "type": "Feature",
  "properties": {
    "addr:full":"307 Maple Ave W Ste H Vienna VA 22180",
    "addr:housenumber":"307",
    "addr:postcode":"22180",
    "addr:street":"Maple Ave W Ste H",
    "iso:country":"US",
    "sg:address":"307 Maple Ave W Ste H",
    "sg:city":"Vienna",
    "sg:classifiers":[
        {
            "category":"Health Services",
            "subcategory":"Doctor",
            "type":"Services"
        },
        {
            "category":"Health Services",
            "subcategory":"Dentist",
            "type":"Services"
        }
    ],
    "sg:phone":"+1 703 938 5920",
    "sg:postcode":"22180",
    "sg:province":"VA",
    "sg:tags":[
        "dentists-oral",
        "maxillofacial",
        "dental",
        "surgeons",
        "physician",
        "clinic",
        "dentists-endodontists",
        "surgery",
        "oral"
    ],
    "wof:name":"Albert A Citron Dmd",
    "wof:placetype":"venue"
},
  "geometry": {"coordinates":[-77.269575,38.898057],"type":"Point"}
}