{
  "type": "Feature",
  "properties": {
    "addr:full":"9009 Archwind Ct Richmond VA 23236",
    "addr:housenumber":"9009",
    "addr:postcode":"23236",
    "addr:street":"Archwind Ct",
    "iso:country":"US",
    "sg:address":"9009 Archwind Ct",
    "sg:city":"Richmond",
    "sg:classifiers":[
        {
            "category":"Food & Beverages",
            "subcategory":"Liquor & Beverages",
            "type":"Retail Goods"
        }
    ],
    "sg:phone":"+1 804 675 2581",
    "sg:postcode":"23236",
    "sg:province":"VA",
    "sg:tags":[
        "alcoholic"
    ],
    "wof:name":"Jay T Wine",
    "wof:placetype":"venue"
},
  "geometry": {"coordinates":[-77.56805799999999,37.483463],"type":"Point"}
}