{
  "type": "Feature",
  "properties": {
    "addr:full":"2802 Hawthorne Ave Richmond VA 23222",
    "addr:housenumber":"2802",
    "addr:postcode":"23222",
    "addr:street":"Hawthorne Ave",
    "iso:country":"US",
    "sg:address":"2802 Hawthorne Ave",
    "sg:city":"Richmond",
    "sg:classifiers":[
        {
            "category":"Banks & Credit Unions",
            "subcategory":"Bank",
            "type":"Services"
        }
    ],
    "sg:phone":"+1 804 321 3155",
    "sg:postcode":"23222",
    "sg:province":"VA",
    "sg:tags":[
        "mortgage"
    ],
    "wof:name":"US Mortgage Reductin",
    "wof:placetype":"venue"
},
  "geometry": {"coordinates":[-77.441247,37.567516],"type":"Point"}
}