{
  "type": "Feature",
  "properties": {
    "addr:full":"3516 Plank Rd Fredericksburg VA 22407",
    "addr:housenumber":"3516",
    "addr:postcode":"22407",
    "addr:street":"Plank Rd",
    "iso:country":"US",
    "sg:address":"3516 Plank Rd",
    "sg:city":"Fredericksburg",
    "sg:classifiers":[
        {
            "category":"Social Services",
            "subcategory":"Job Training",
            "type":"Services"
        }
    ],
    "sg:phone":"+1 540 786 9951",
    "sg:postcode":"22407",
    "sg:province":"VA",
    "sg:tags":[
        "career",
        "counseling",
        "vocational"
    ],
    "wof:name":"Career Computers",
    "wof:placetype":"venue"
},
  "geometry": {"coordinates":[-77.519885,38.29348],"type":"Point"}
}