{
  "type": "Feature",
  "properties": {
    "addr:full":"12420 Warwick Blvd Newport News VA 23606",
    "addr:housenumber":"12420",
    "addr:postcode":"23606",
    "addr:street":"Warwick Blvd",
    "iso:country":"US",
    "sg:address":"12420 Warwick Blvd",
    "sg:city":"Newport News",
    "sg:classifiers":[
        {
            "category":"Wholesale",
            "subcategory":"Scrap",
            "type":"Manufacturing & Wholesale Goods"
        }
    ],
    "sg:phone":"+1 757 599 6500",
    "sg:postcode":"23606",
    "sg:province":"VA",
    "sg:tags":[
        "recycling",
        "center"
    ],
    "wof:name":"Lions Eyeglass Recycling Ctr",
    "wof:placetype":"venue"
},
  "geometry": {"coordinates":[-76.49196999999999,37.066565],"type":"Point"}
}