{
  "type": "Feature",
  "properties": {
    "addr:full":"12088 Hacksneck Rd Hacksneck VA 23358",
    "addr:housenumber":"12088",
    "addr:postcode":"23358",
    "addr:street":"Hacksneck Rd",
    "iso:country":"US",
    "sg:address":"12088 Hacksneck Rd",
    "sg:city":"Hacksneck",
    "sg:classifiers":[
        {
            "category":"Government",
            "subcategory":"Post Office",
            "type":"Public Place"
        }
    ],
    "sg:phone":"+1 757 442 2070",
    "sg:postcode":"23358",
    "sg:province":"VA",
    "wof:name":"US Post Office",
    "wof:placetype":"venue"
},
  "geometry": {"coordinates":[-75.87129899999999,37.64221],"type":"Point"}
}