{
  "type": "Feature",
  "properties": {
    "addr:full":"15217 Illinois Rd Woodbridge VA 22191",
    "addr:housenumber":"15217",
    "addr:postcode":"22191",
    "addr:street":"Illinois Rd",
    "iso:country":"US",
    "sg:address":"15217 Illinois Rd",
    "sg:city":"Woodbridge",
    "sg:classifiers":[
        {
            "category":"Professional",
            "subcategory":"Business Services",
            "type":"Services"
        }
    ],
    "sg:phone":"+1 703 497 6900",
    "sg:postcode":"22191",
    "sg:province":"VA",
    "wof:name":"Abundant Living",
    "wof:placetype":"venue"
},
  "geometry": {"coordinates":[-77.256629,38.620893],"type":"Point"}
}