{
  "type": "Feature",
  "properties": {
    "iso:country":"US",
    "sg:address":"801 Boush St",
    "sg:city":"Norfolk",
    "sg:classifiers":[
        {
            "category":"Government",
            "subcategory":"Office",
            "type":"Public Place"
        }
    ],
    "sg:phone":"+1 757 625 6161",
    "sg:postcode":"23510",
    "sg:province":"VA",
    "sg:tags":[
        "village"
    ],
    "sg:website":"www.hope-house.org",
    "wof:name":"Hope House Foundation",
    "wof:placetype":"venue"
},
  "geometry": {"coordinates":[-76.290938,36.85717],"type":"Point"}
}