{
  "type": "Feature",
  "properties": {
    "addr:full":"4709 Randolph Ct Annandale VA 22003",
    "addr:housenumber":"4709",
    "addr:postcode":"22003",
    "addr:street":"Randolph Ct",
    "iso:country":"US",
    "sg:address":"4709 Randolph Ct",
    "sg:city":"Annandale",
    "sg:classifiers":[
        {
            "category":"Professional",
            "subcategory":"Management & Consulting",
            "type":"Services"
        }
    ],
    "sg:phone":"+1 703 642 5856",
    "sg:postcode":"22003",
    "sg:province":"VA",
    "sg:tags":[
        "logistics"
    ],
    "wof:name":"James P Davidson",
    "wof:placetype":"venue"
},
  "geometry": {"coordinates":[-77.17553599999999,38.822044],"type":"Point"}
}