{
  "type": "Feature",
  "properties": {
    "iso:country":"US",
    "sg:address":"1140 5th St",
    "sg:city":"Bristol",
    "sg:classifiers":[
        {
            "category":"Manufacturing",
            "subcategory":"Tools & Machinery",
            "type":"Manufacturing & Wholesale Goods"
        }
    ],
    "sg:phone":"+1 423 764 6828",
    "sg:postcode":"37620",
    "sg:province":"VA",
    "sg:tags":[
        "shop",
        "mfg",
        "expansion",
        "machine",
        "joint",
        "fitting",
        "steam"
    ],
    "wof:name":"Bristol Machine & Engineering",
    "wof:placetype":"venue"
},
  "geometry": {"coordinates":[-82.173592,36.582077],"type":"Point"}
}