{
  "type": "Feature",
  "properties": {
    "addr:full":"934 W Little Creek Rd Norfolk VA 23505",
    "addr:housenumber":"934",
    "addr:postcode":"23505",
    "addr:street":"W Little Creek Rd",
    "iso:country":"US",
    "sg:address":"934 W Little Creek Rd",
    "sg:city":"Norfolk",
    "sg:classifiers":[
        {
            "category":"Organizations",
            "subcategory":"Religious Organization",
            "type":"Services"
        }
    ],
    "sg:phone":"+1 757 423 8469",
    "sg:postcode":"23505",
    "sg:province":"VA",
    "sg:website":"www.newmtp.org",
    "wof:name":"Mount Pleasant Baptist Church",
    "wof:placetype":"venue"
},
  "geometry": {"coordinates":[-76.291127,36.916249],"type":"Point"}
}