{
  "type": "Feature",
  "properties": {
    "iso:country":"US",
    "sg:address":"80 Farmers Dr",
    "sg:city":"Moneta",
    "sg:classifiers":[
        {
            "category":"Professional",
            "subcategory":"Advertising",
            "type":"Services"
        }
    ],
    "sg:phone":"+1 540 721 1950",
    "sg:postcode":"24112",
    "sg:province":"VA",
    "wof:name":"Gibson Media Design Inc",
    "wof:placetype":"venue"
},
  "geometry": {"coordinates":[-79.98436,36.677997],"type":"Point"}
}