{
  "type": "Feature",
  "properties": {
    "iso:country":"US",
    "sg:address":"2005 Bedford Ln",
    "sg:city":"Alexandria",
    "sg:classifiers":[
        {
            "category":"Professional",
            "subcategory":"Business Services",
            "type":"Services"
        }
    ],
    "sg:phone":"+1 703 765 8195",
    "sg:postcode":"22307",
    "sg:province":"VA",
    "wof:name":"Ronald E Ullrich",
    "wof:placetype":"venue"
},
  "geometry": {"coordinates":[-77.065327,38.759409],"type":"Point"}
}