{
  "type": "Feature",
  "properties": {
    "addr:full":"2614 Sewells Point Rd Norfolk VA 23513",
    "addr:postcode":"2614;23513",
    "addr:street":"Sewells Point Rd",
    "iso:country":"US",
    "sg:address":"2614 Sewells Point Rd",
    "sg:city":"Norfolk",
    "sg:classifiers":[
        {
            "category":"Organizations",
            "subcategory":"Religious Organization",
            "type":"Services"
        }
    ],
    "sg:phone":"+1 757 853 5051",
    "sg:postcode":"23513",
    "sg:province":"VA",
    "wof:name":"New Hope Church Deliverance",
    "wof:placetype":"venue"
},
  "geometry": {"coordinates":[-76.232361,36.87351],"type":"Point"}
}