{
  "type": "Feature",
  "properties": {
    "iso:country":"US",
    "sg:address":"3237 History Dr",
    "sg:city":"Oakton",
    "sg:classifiers":[
        {
            "category":"Professional",
            "subcategory":"Computer Services",
            "type":"Services"
        }
    ],
    "sg:phone":"+1 703 620 1910",
    "sg:postcode":"22124",
    "sg:province":"VA",
    "sg:tags":[
        "prepackaged",
        "software"
    ],
    "sg:website":"www.tarkir.net",
    "wof:name":"Modern Software Development",
    "wof:placetype":"venue"
},
  "geometry": {"coordinates":[-77.346369,38.882433],"type":"Point"}
}