{
  "type": "Feature",
  "properties": {
    "iso:country":"US",
    "sg:address":"405 Glenn Dr",
    "sg:city":"Sterling",
    "sg:classifiers":[
        {
            "category":"Restaurant",
            "type":"Food & Drink"
        }
    ],
    "sg:phone":"+1 703 450 6666",
    "sg:postcode":"20164",
    "sg:province":"VA",
    "sg:tags":[
        "catering"
    ],
    "wof:name":"Celebrtion Ctrg Special Events",
    "wof:placetype":"venue"
},
  "geometry": {"coordinates":[-77.42677999999999,38.996357],"type":"Point"}
}