{
  "type": "Feature",
  "properties": {
    "iso:country":"US",
    "sg:address":"3636 Moore St",
    "sg:city":"Hampton",
    "sg:classifiers":[
        {
            "category":"Restaurant",
            "type":"Food & Drink"
        }
    ],
    "sg:phone":"+1 757 723 6695",
    "sg:postcode":"23661",
    "sg:province":"VA",
    "sg:tags":[
        "eating"
    ],
    "wof:name":"Two Guys Caterers Inc",
    "wof:placetype":"venue"
},
  "geometry": {"coordinates":[-76.36248399999999,37.017834],"type":"Point"}
}