{
  "type": "Feature",
  "properties": {
    "addr:full":"4104 Yerkes Pl Annandale VA 22003",
    "addr:housenumber":"4104",
    "addr:postcode":"22003",
    "addr:street":"Yerkes Pl",
    "iso:country":"US",
    "sg:address":"4104 Yerkes Pl",
    "sg:city":"Annandale",
    "sg:classifiers":[
        {
            "category":"Professional",
            "subcategory":"Business Services",
            "type":"Services"
        }
    ],
    "sg:phone":"+1 703 323 8749",
    "sg:postcode":"22003",
    "sg:province":"VA",
    "sg:tags":[
        "arabic",
        "linguist"
    ],
    "wof:name":"Mongia T Dambowic",
    "wof:placetype":"venue"
},
  "geometry": {"coordinates":[-77.251583,38.835184],"type":"Point"}
}