{
  "type": "Feature",
  "properties": {
    "addr:full":"8016 Centreville Rd Manassas Park VA 20111",
    "addr:housenumber":"8016",
    "addr:postcode":"20111",
    "addr:street":"Centreville Rd;Park",
    "iso:country":"US",
    "sg:address":"8016 Centreville Rd",
    "sg:city":"Manassas Park",
    "sg:classifiers":[
        {
            "category":"Autos & Motor Vehicles",
            "subcategory":"Automobile Sales",
            "type":"Retail Goods"
        }
    ],
    "sg:phone":"+1 703 368 6311",
    "sg:postcode":"20111",
    "sg:province":"VA",
    "sg:tags":[
        "car",
        "used",
        "dealer"
    ],
    "wof:name":"Exotic Motor Carriages",
    "wof:placetype":"venue"
},
  "geometry": {"coordinates":[-77.45035,38.781835],"type":"Point"}
}