{
  "type": "Feature",
  "properties": {
    "iso:country":"US",
    "sg:address":"10500 Patterson Ave",
    "sg:city":"Richmond",
    "sg:classifiers":[
        {
            "category":"Home & Garden",
            "subcategory":"Furniture",
            "type":"Retail Goods"
        }
    ],
    "sg:phone":"+1 804 740 3124",
    "sg:postcode":"23238",
    "sg:province":"VA",
    "wof:name":"Virginia Wayside Furniture Inc",
    "wof:placetype":"venue"
},
  "geometry": {"coordinates":[-77.60527399999999,37.59694],"type":"Point"}
}