{
  "type": "Feature",
  "properties": {
    "addr:full":"175 Gibson Dr Christiansburg VA 24073",
    "addr:housenumber":"175",
    "addr:postcode":"24073",
    "addr:street":"Gibson Dr",
    "iso:country":"US",
    "sg:address":"175 Gibson Dr",
    "sg:city":"Christiansburg",
    "sg:classifiers":[
        {
            "category":"Professional",
            "subcategory":"Management & Consulting",
            "type":"Services"
        }
    ],
    "sg:phone":"+1 540 382 3538",
    "sg:postcode":"24073",
    "sg:province":"VA",
    "sg:tags":[
        "retail",
        "direct",
        "sales"
    ],
    "wof:name":"Enhanced Living Inc",
    "wof:placetype":"venue"
},
  "geometry": {"coordinates":[-80.43140200000001,37.154059],"type":"Point"}
}