{
  "type": "Feature",
  "properties": {
    "addr:full":"4307 Old Hundred Rd Chester VA 23831",
    "addr:housenumber":"4307",
    "addr:postcode":"23831",
    "addr:street":"Old Hundred Rd",
    "iso:country":"US",
    "sg:address":"4307 Old Hundred Rd",
    "sg:city":"Chester",
    "sg:classifiers":[
        {
            "category":"Shopping",
            "subcategory":"Used Merchandise",
            "type":"Retail Goods"
        }
    ],
    "sg:phone":"+1 804 706 9500",
    "sg:postcode":"23831",
    "sg:province":"VA",
    "wof:name":"French Garden Antiques",
    "wof:placetype":"venue"
},
  "geometry": {"coordinates":[-77.44746000000001,37.354895],"type":"Point"}
}