{
  "type": "Feature",
  "properties": {
    "addr:full":"6710 Hopewell Ave Springfield VA 22151",
    "addr:housenumber":"6710",
    "addr:postcode":"22151",
    "addr:street":"Hopewell Ave",
    "iso:country":"US",
    "sg:address":"6710 Hopewell Ave",
    "sg:city":"Springfield",
    "sg:classifiers":[
        {
            "category":"Building & Trades",
            "subcategory":"Construction",
            "type":"Services"
        }
    ],
    "sg:phone":"+1 703 256 0022",
    "sg:postcode":"22151",
    "sg:province":"VA",
    "sg:tags":[
        "hanging",
        "contractor"
    ],
    "wof:name":"Best Choice Painting",
    "wof:placetype":"venue"
},
  "geometry": {"coordinates":[-77.176158,38.802781],"type":"Point"}
}