{
  "type": "Feature",
  "properties": {
    "iso:country":"US",
    "sg:address":"363 Warrenton Rd",
    "sg:city":"Fredericksburg",
    "sg:classifiers":[
        {
            "category":"Cinema",
            "subcategory":"Movie Rental",
            "type":"Entertainment"
        }
    ],
    "sg:phone":"+1 540 368 8077",
    "sg:postcode":"22405",
    "sg:province":"VA",
    "sg:tags":[
        "video",
        "tape"
    ],
    "wof:name":"Richmond Video Outlet LLC",
    "wof:placetype":"venue"
},
  "geometry": {"coordinates":[-77.48817099999999,38.338297],"type":"Point"}
}