{
  "type": "Feature",
  "properties": {
    "addr:full":"2702 Key Blvd Arlington VA 22201",
    "addr:housenumber":"2702",
    "addr:postcode":"22201",
    "addr:street":"Key Blvd",
    "iso:country":"US",
    "sg:address":"2702 Key Blvd",
    "sg:city":"Arlington",
    "sg:classifiers":[
        {
            "category":"Professional",
            "subcategory":"Lawyer & Legal Services",
            "type":"Services"
        }
    ],
    "sg:phone":"+1 703 525 9010",
    "sg:postcode":"22201",
    "sg:province":"VA",
    "wof:name":"Muse Robert Atty",
    "wof:placetype":"venue"
},
  "geometry": {"coordinates":[-77.0921,38.892076],"type":"Point"}
}