{
  "type": "Feature",
  "properties": {
    "addr:full":"8157 Elm Dr Mechanicsville VA 23111",
    "addr:housenumber":"8157",
    "addr:postcode":"23111",
    "addr:street":"Elm Dr",
    "iso:country":"US",
    "sg:address":"8157 Elm Dr",
    "sg:city":"Mechanicsville",
    "sg:classifiers":[
        {
            "category":"Building & Trades",
            "subcategory":"Plumbing",
            "type":"Services"
        }
    ],
    "sg:phone":"+1 804 746 9231",
    "sg:postcode":"23111",
    "sg:province":"VA",
    "sg:tags":[
        "plumbing",
        "contractor"
    ],
    "wof:name":"Herman W Allen Inc",
    "wof:placetype":"venue"
},
  "geometry": {"coordinates":[-77.381047,37.6016],"type":"Point"}
}