{
  "type": "Feature",
  "properties": {
    "addr:full":"7144 Old Dominion Dr Mc Lean VA 22101",
    "addr:housenumber":"7144",
    "addr:postcode":"22101",
    "addr:street":"Old Dominion Dr",
    "iso:country":"US",
    "sg:address":"7144 Old Dominion Dr",
    "sg:city":"Mc Lean",
    "sg:classifiers":[
        {
            "category":"Organizations",
            "subcategory":"Religious Organization",
            "type":"Services"
        }
    ],
    "sg:phone":"+1 703 893 8651",
    "sg:postcode":"22101",
    "sg:province":"VA",
    "wof:name":"McLean Korean Presbt Church",
    "wof:placetype":"venue"
},
  "geometry": {"coordinates":[-77.193528,38.940594],"type":"Point"}
}