{
  "type": "Feature",
  "properties": {
    "iso:country":"US",
    "sg:address":"439 Lam's Xing",
    "sg:city":"Elkton",
    "sg:phone":"+1 540 298 8242",
    "sg:postcode":"22827",
    "sg:province":"VA",
    "sg:tags":[
        "farm",
        "corn",
        "bean"
    ],
    "wof:name":"William Lam",
    "wof:placetype":"venue"
},
  "geometry": {"coordinates":[-78.58964,38.460845],"type":"Point"}
}