{
  "type": "Feature",
  "properties": {
    "iso:country":"US",
    "sg:address":"5 Whitaker Ct",
    "sg:city":"Williamsburg",
    "sg:phone":"+1 757 258 9536",
    "sg:postcode":"23188",
    "sg:province":"VA",
    "sg:tags":[
        "product",
        "petroleum"
    ],
    "wof:name":"Texpar Energy LLC",
    "wof:placetype":"venue"
},
  "geometry": {"coordinates":[-76.768933,37.304642],"type":"Point"}
}