{
  "type": "Feature",
  "properties": {
    "iso:country":"US",
    "sg:address":"528 N Main St",
    "sg:city":"Hillsville",
    "sg:classifiers":[
        {
            "category":"Organizations",
            "subcategory":"Non-profit Organization",
            "type":"Services"
        }
    ],
    "sg:phone":"+1 276 728 5564",
    "sg:postcode":"24343",
    "sg:province":"VA",
    "sg:tags":[
        "info",
        "addiction",
        "abuse",
        "treatment",
        "drug"
    ],
    "wof:name":"Drug Test Resource",
    "wof:placetype":"venue"
},
  "geometry": {"coordinates":[-80.736971,36.766084],"type":"Point"}
}