{
  "type": "Feature",
  "properties": {
    "addr:full":"3075 S Ox Rd Edinburg VA 22824",
    "addr:housenumber":"3075",
    "addr:postcode":"22824",
    "addr:street":"S Ox Rd",
    "iso:country":"US",
    "sg:address":"3075 S Ox Rd",
    "sg:city":"Edinburg",
    "sg:classifiers":[
        {
            "category":"Utilities",
            "subcategory":"Telephone",
            "type":"Services"
        }
    ],
    "sg:phone":"+1 540 984 5251",
    "sg:postcode":"22824",
    "sg:province":"VA",
    "sg:tags":[
        "communications"
    ],
    "wof:name":"Shentel",
    "wof:placetype":"venue"
},
  "geometry": {"coordinates":[-78.56665099999999,38.840981],"type":"Point"}
}