{
  "type": "Feature",
  "properties": {
    "iso:country":"US",
    "sg:address":"540 Loblolly Ln",
    "sg:city":"Charlottesville",
    "sg:classifiers":[
        {
            "category":"Restaurant",
            "type":"Food & Drink"
        }
    ],
    "sg:phone":"+1 434 979 2879",
    "sg:postcode":"22903",
    "sg:province":"VA",
    "wof:name":"Sloans Restaurant",
    "wof:placetype":"venue"
},
  "geometry": {"coordinates":[-78.603931,38.050051],"type":"Point"}
}