{
  "type": "Feature",
  "properties": {
    "addr:full":"5771 Thomas Jefferson Rd Forest VA 24551",
    "addr:housenumber":"5771",
    "addr:postcode":"24551",
    "addr:street":"Thomas Jefferson Rd",
    "iso:country":"US",
    "sg:address":"5771 Thomas Jefferson Rd",
    "sg:city":"Forest",
    "sg:classifiers":[
        {
            "category":"Wholesale",
            "subcategory":"Motor Vehicles",
            "type":"Manufacturing & Wholesale Goods"
        }
    ],
    "sg:phone":"+1 434 525 0015",
    "sg:postcode":"24551",
    "sg:province":"VA",
    "wof:name":"Parker John",
    "wof:placetype":"venue"
},
  "geometry": {"coordinates":[-79.312681,37.31169],"type":"Point"}
}