{
  "type": "Feature",
  "properties": {
    "addr:full":"8501 Barrington Ct Springfield VA 22152",
    "addr:housenumber":"8501",
    "addr:postcode":"22152",
    "addr:street":"Barrington Ct",
    "iso:country":"US",
    "sg:address":"8501 Barrington Ct",
    "sg:city":"Springfield",
    "sg:classifiers":[
        {
            "category":"Professional",
            "subcategory":"Art Services",
            "type":"Services"
        }
    ],
    "sg:phone":"+1 571 332 3370",
    "sg:postcode":"22152",
    "sg:province":"VA",
    "sg:tags":[
        "commercial",
        "design"
    ],
    "wof:name":"Visual Emotion Studios",
    "wof:placetype":"venue"
},
  "geometry": {"coordinates":[-77.23971,38.79286],"type":"Point"}
}