{
  "type": "Feature",
  "properties": {
    "addr:full":"82 Pilgrims Way Bentonville VA 22610",
    "addr:housenumber":"82",
    "addr:postcode":"22610",
    "addr:street":"Pilgrims Way",
    "iso:country":"US",
    "sg:address":"82 Pilgrims Way",
    "sg:city":"Bentonville",
    "sg:classifiers":[
        {
            "category":"Communications",
            "type":"Services"
        }
    ],
    "sg:phone":"+1 540 635 4194",
    "sg:postcode":"22610",
    "sg:province":"VA",
    "sg:tags":[
        "communication"
    ],
    "wof:name":"Shenandoah Communications",
    "wof:placetype":"venue"
},
  "geometry": {"coordinates":[-78.33973400000001,38.851133],"type":"Point"}
}