{
  "type": "Feature",
  "properties": {
    "addr:full":"8196 Terminal Rd Lorton VA 22079",
    "addr:housenumber":"8196",
    "addr:postcode":"22079",
    "addr:street":"Terminal Rd",
    "iso:country":"US",
    "sg:address":"8196 Terminal Rd",
    "sg:city":"Lorton",
    "sg:classifiers":[
        {
            "category":"Autos & Motor Vehicles",
            "subcategory":"Auto Supplies",
            "type":"Retail Goods"
        },
        {
            "category":"Wholesale",
            "subcategory":"Auto Parts",
            "type":"Manufacturing & Wholesale Goods"
        }
    ],
    "sg:phone":"+1 703 339 8300",
    "sg:postcode":"22079",
    "sg:province":"VA",
    "sg:tags":[
        "automobile"
    ],
    "wof:name":"Fairfax Auto Parts",
    "wof:placetype":"venue"
},
  "geometry": {"coordinates":[-77.189859,38.735141],"type":"Point"}
}