{
  "type": "Feature",
  "properties": {
    "addr:full":"10114 Giles Run Rd Lorton VA 22079",
    "addr:housenumber":"10114",
    "addr:postcode":"22079",
    "addr:street":"Giles Run Rd",
    "iso:country":"US",
    "sg:address":"10114 Giles Run Rd",
    "sg:city":"Lorton",
    "sg:classifiers":[
        {
            "category":"Wholesale",
            "subcategory":"Auto Parts",
            "type":"Manufacturing & Wholesale Goods"
        }
    ],
    "sg:phone":"+1 703 339 9886",
    "sg:postcode":"22079",
    "sg:province":"VA",
    "sg:tags":[
        "used"
    ],
    "wof:name":"Central Core & Auto Salvage",
    "wof:placetype":"venue"
},
  "geometry": {"coordinates":[-77.224591,38.68076],"type":"Point"}
}