{
  "type": "Feature",
  "properties": {
    "iso:country":"US",
    "sg:address":"1098 Crute Ln",
    "sg:city":"Scottsburg",
    "sg:classifiers":[
        {
            "category":"Recreation",
            "type":"Entertainment"
        }
    ],
    "sg:phone":"+1 434 454 7833",
    "sg:postcode":"24589",
    "sg:province":"VA",
    "sg:tags":[
        "club",
        "membership",
        "sport"
    ],
    "wof:name":"Bethel Community Ruritan Club",
    "wof:placetype":"venue"
},
  "geometry": {"coordinates":[-78.845929,36.775765],"type":"Point"}
}