{
  "type": "Feature",
  "properties": {
    "iso:country":"US",
    "sg:address":"1516 Holland Rd",
    "sg:city":"Suffolk",
    "sg:classifiers":[
        {
            "category":"Restaurant",
            "type":"Food & Drink"
        }
    ],
    "sg:menulink":"http://www.allmenus.com/va/suffolk/166163-arbys/menu/",
    "sg:phone":"+1 757 539 0651",
    "sg:postcode":"23434",
    "sg:province":"VA",
    "sg:tags":[
        "burger",
        "american"
    ],
    "wof:name":"Arby's",
    "wof:placetype":"venue"
},
  "geometry": {"coordinates":[-76.636785,36.723936],"type":"Point"}
}