{
  "type": "Feature",
  "properties": {
    "iso:country":"US",
    "sg:address":"4702 Olde Forge Ct",
    "sg:city":"Fairfax",
    "sg:classifiers":[
        {
            "category":"Real Estate",
            "subcategory":"Real Estate Agent",
            "type":"Services"
        }
    ],
    "sg:phone":"+1 703 978 5982",
    "sg:postcode":"22032",
    "sg:province":"VA",
    "wof:name":"James Lynn Enterprises",
    "wof:placetype":"venue"
},
  "geometry": {"coordinates":[-77.27795,38.822567],"type":"Point"}
}