{
  "type": "Feature",
  "properties": {
    "addr:full":"5200 Lakeside Ave Richmond VA 23228",
    "addr:housenumber":"5200",
    "addr:postcode":"23228",
    "addr:street":"Lakeside Ave",
    "iso:country":"US",
    "sg:address":"5200 Lakeside Ave",
    "sg:city":"Richmond",
    "sg:classifiers":[
        {
            "category":"Restaurant",
            "type":"Food & Drink"
        }
    ],
    "sg:phone":"+1 804 262 8775",
    "sg:postcode":"23228",
    "sg:province":"VA",
    "sg:tags":[
        "eating"
    ],
    "wof:name":"Roys",
    "wof:placetype":"venue"
},
  "geometry": {"coordinates":[-77.467125,37.600057],"type":"Point"}
}