{
  "type": "Feature",
  "properties": {
    "addr:full":"3239 Cismont Ct Occoquan VA 22192",
    "addr:housenumber":"3239",
    "addr:postcode":"22192",
    "addr:street":"Cismont Ct",
    "iso:country":"US",
    "sg:address":"3239 Cismont Ct",
    "sg:city":"Occoquan",
    "sg:classifiers":[
        {
            "category":"Shopping",
            "subcategory":"Clothing, Apparel, & Fashions",
            "type":"Retail Goods"
        }
    ],
    "sg:phone":"+1 703 494 7756",
    "sg:postcode":"22192",
    "sg:province":"VA",
    "sg:tags":[
        "theatrical",
        "costume"
    ],
    "wof:name":"Fashions In Action Inc",
    "wof:placetype":"venue"
},
  "geometry": {"coordinates":[-77.30352999999999,38.671089],"type":"Point"}
}