{
  "type": "Feature",
  "properties": {
    "iso:country":"US",
    "sg:address":"1851 N Scott St",
    "sg:city":"Arlington",
    "sg:classifiers":[
        {
            "category":"Real Estate",
            "subcategory":"Real Estate Operator",
            "type":"Services"
        }
    ],
    "sg:phone":"+1 703 243 9031",
    "sg:postcode":"22209",
    "sg:province":"VA",
    "sg:tags":[
        "apartment"
    ],
    "wof:name":"Rosslyn Heights Inc",
    "wof:placetype":"venue"
},
  "geometry": {"coordinates":[-77.07947,38.896336],"type":"Point"}
}