{
  "type": "Feature",
  "properties": {
    "iso:country":"US",
    "sg:address":"6052 Providence Rd",
    "sg:city":"Virginia Beach",
    "sg:classifiers":[
        {
            "category":"Insurance",
            "subcategory":"Insurance Agent",
            "type":"Services"
        }
    ],
    "sg:phone":"+1 757 523 1020",
    "sg:postcode":"23464",
    "sg:province":"VA",
    "wof:name":"Primerica",
    "wof:placetype":"venue"
},
  "geometry": {"coordinates":[-76.202905,36.812924],"type":"Point"}
}