{
  "type": "Feature",
  "properties": {
    "addr:full":"5075 Mineral Spring Rd Suffolk VA 23438",
    "addr:housenumber":"5075",
    "addr:postcode":"23438",
    "addr:street":"Mineral Spring Rd",
    "iso:country":"US",
    "sg:address":"5075 Mineral Spring Rd",
    "sg:city":"Suffolk",
    "sg:classifiers":[
        {
            "category":"Building & Trades",
            "subcategory":"Electrical",
            "type":"Services"
        }
    ],
    "sg:phone":"+1 757 986 4042",
    "sg:postcode":"23438",
    "sg:province":"VA",
    "sg:tags":[
        "electrical",
        "contractor"
    ],
    "wof:name":"White Electric",
    "wof:placetype":"venue"
},
  "geometry": {"coordinates":[-76.692831,36.595397],"type":"Point"}
}