{
  "type": "Feature",
  "properties": {
    "iso:country":"US",
    "sg:address":"7015 Old Keene Mill Rd",
    "sg:city":"Springfield",
    "sg:classifiers":[
        {
            "category":"Professional",
            "subcategory":"Lawyer & Legal Services",
            "type":"Services"
        }
    ],
    "sg:phone":"+1 703 569 0400",
    "sg:postcode":"22150",
    "sg:province":"VA",
    "wof:name":"Altman Somers & Woods",
    "wof:placetype":"venue"
},
  "geometry": {"coordinates":[-77.186089,38.779025],"type":"Point"}
}