{
  "type": "Feature",
  "properties": {
    "addr:full":"955 2nd St SE Charlottesville VA 22902",
    "addr:housenumber":"955",
    "addr:postcode":"22902",
    "addr:street":"2Nd St Se",
    "iso:country":"US",
    "sg:address":"955 2nd St SE",
    "sg:city":"Charlottesville",
    "sg:classifiers":[
        {
            "category":"Professional",
            "subcategory":"Computer Services",
            "type":"Services"
        }
    ],
    "sg:phone":"+1 434 817 0252",
    "sg:postcode":"22902",
    "sg:province":"VA",
    "sg:tags":[
        "repair"
    ],
    "sg:website":"www.seacominc.com",
    "wof:name":"Seacom Inc",
    "wof:placetype":"venue"
},
  "geometry": {"coordinates":[-78.476552,38.03781],"type":"Point"}
}