{
  "type": "Feature",
  "properties": {
    "addr:full":"6505 Leisure Ter Richmond VA 23237",
    "addr:housenumber":"6505",
    "addr:postcode":"23237",
    "addr:street":"Leisure Ter",
    "iso:country":"US",
    "sg:address":"6505 Leisure Ter",
    "sg:city":"Richmond",
    "sg:classifiers":[
        {
            "category":"Professional",
            "subcategory":"Management & Consulting",
            "type":"Services"
        }
    ],
    "sg:phone":"+1 804 275 4804",
    "sg:postcode":"23237",
    "sg:province":"VA",
    "sg:tags":[
        "architectural"
    ],
    "wof:name":"Conley Design Group Inc",
    "wof:placetype":"venue"
},
  "geometry": {"coordinates":[-77.501521,37.393511],"type":"Point"}
}