{
  "type": "Feature",
  "properties": {
    "iso:country":"US",
    "sg:address":"10 Woodland Dr",
    "sg:city":"Bristol",
    "sg:classifiers":[
        {
            "category":"Personal",
            "type":"Services"
        }
    ],
    "sg:phone":"+1 276 466 1978",
    "sg:postcode":"24201",
    "sg:province":"VA",
    "sg:tags":[
        "animal"
    ],
    "wof:name":"Doggywalkercom Inc",
    "wof:placetype":"venue"
},
  "geometry": {"coordinates":[-82.17815299999999,36.616629],"type":"Point"}
}