{
  "type": "Feature",
  "properties": {
    "addr:full":"1133 Kingwood Ave Norfolk VA 23502",
    "addr:housenumber":"1133",
    "addr:postcode":"23502",
    "addr:street":"Kingwood Ave",
    "iso:country":"US",
    "sg:address":"1133 Kingwood Ave",
    "sg:city":"Norfolk",
    "sg:classifiers":[
        {
            "category":"Manufacturing",
            "subcategory":"Food",
            "type":"Manufacturing & Wholesale Goods"
        },
        {
            "category":"Food & Beverages",
            "subcategory":"Fruits & Vegetables",
            "type":"Retail Goods"
        }
    ],
    "sg:phone":"+1 757 853 9095",
    "sg:postcode":"23502",
    "sg:province":"VA",
    "sg:tags":[
        "produce",
        "mfg"
    ],
    "wof:name":"Hampton Roads Produce Distribu",
    "wof:placetype":"venue"
},
  "geometry": {"coordinates":[-76.238226,36.858903],"type":"Point"}
}