{
  "type": "Feature",
  "properties": {
    "iso:country":"US",
    "sg:address":"1300 Quincy St",
    "sg:city":"Alexandria",
    "sg:classifiers":[
        {
            "category":"Organizations",
            "subcategory":"Community Association",
            "type":"Services"
        }
    ],
    "sg:phone":"+1 703 778 2459",
    "sg:postcode":"22302",
    "sg:province":"VA",
    "wof:name":"Wash-Lee Crew Boosters",
    "wof:placetype":"venue"
},
  "geometry": {"coordinates":[-77.08146499999999,38.823841],"type":"Point"}
}