{
  "type": "Feature",
  "properties": {
    "addr:full":"3600 S Glebe Rd Ste 140 Arlington VA 22202",
    "addr:housenumber":"3600",
    "addr:postcode":"22202",
    "addr:street":"S Glebe Rd Ste 140",
    "iso:country":"US",
    "sg:address":"3600 S Glebe Rd Ste 140",
    "sg:city":"Arlington",
    "sg:classifiers":[
        {
            "category":"Freight",
            "type":"Transportation"
        },
        {
            "category":"Professional",
            "subcategory":"Lawyer & Legal Services",
            "type":"Services"
        },
        {
            "category":"Professional",
            "subcategory":"Printing & Photocopies",
            "type":"Services"
        }
    ],
    "sg:phone":"+1 703 418 3727",
    "sg:postcode":"22202",
    "sg:province":"VA",
    "sg:tags":[
        "notary",
        "shipping"
    ],
    "sg:website":"www.fedex.com/us/office/",
    "wof:name":"FedEx Office Print & Ship Center",
    "wof:placetype":"venue"
},
  "geometry": {"coordinates":[-77.051239,38.842382],"type":"Point"}
}