{
  "type": "Feature",
  "properties": {
    "addr:full":"899 Hillside Ave Harrisonburg VA 22802",
    "addr:housenumber":"899",
    "addr:postcode":"22802",
    "addr:street":"Hillside Ave",
    "iso:country":"US",
    "sg:address":"899 Hillside Ave",
    "sg:city":"Harrisonburg",
    "sg:classifiers":[
        {
            "category":"Building & Trades",
            "subcategory":"Construction",
            "type":"Services"
        }
    ],
    "sg:phone":"+1 540 433 5987",
    "sg:postcode":"22802",
    "sg:province":"VA",
    "sg:tags":[
        "builder",
        "operative"
    ],
    "wof:name":"Raymont Enterprises",
    "wof:placetype":"venue"
},
  "geometry": {"coordinates":[-78.616924,38.418079],"type":"Point"}
}