{
  "type": "Feature",
  "properties": {
    "addr:full":"8306 Sir Lionel Pl Richmond VA 23237",
    "addr:housenumber":"8306",
    "addr:postcode":"23237",
    "addr:street":"Sir Lionel Pl",
    "iso:country":"US",
    "sg:address":"8306 Sir Lionel Pl",
    "sg:city":"Richmond",
    "sg:classifiers":[
        {
            "category":"Professional",
            "subcategory":"Business Services",
            "type":"Services"
        }
    ],
    "sg:phone":"+1 804 545 2835",
    "sg:postcode":"23237",
    "sg:province":"VA",
    "sg:tags":[
        "inspection"
    ],
    "wof:name":"River City Inspections",
    "wof:placetype":"venue"
},
  "geometry": {"coordinates":[-77.478196,37.402386],"type":"Point"}
}