{
  "type": "Feature",
  "properties": {
    "iso:country":"US",
    "sg:address":"2802 Atlantic Ave",
    "sg:city":"Virginia Beach",
    "sg:classifiers":[
        {
            "category":"Travel",
            "subcategory":"Hotels & Motels",
            "type":"Entertainment"
        }
    ],
    "sg:phone":"+1 757 428 3434",
    "sg:postcode":"23451",
    "sg:province":"VA",
    "sg:tags":[
        "operation"
    ],
    "wof:name":"Wynnwood Inn & Suites",
    "wof:placetype":"venue"
},
  "geometry": {"coordinates":[-75.97799500000001,36.858329],"type":"Point"}
}