{
  "type": "Feature",
  "properties": {
    "iso:country":"US",
    "sg:address":"1770 Rocky Ford Rd",
    "sg:city":"Powhatan",
    "sg:classifiers":[
        {
            "category":"Personal",
            "subcategory":"Beauty Salon",
            "type":"Services"
        }
    ],
    "sg:phone":"+1 804 598 3358",
    "sg:postcode":"23139",
    "sg:province":"VA",
    "sg:tags":[
        "shop"
    ],
    "wof:name":"Jameson Rabbit Farm",
    "wof:placetype":"venue"
},
  "geometry": {"coordinates":[-77.89081299999999,37.519182],"type":"Point"}
}