{
  "type": "Feature",
  "properties": {
    "addr:full":"515 Crickett Ln Pearisburg VA 24134",
    "addr:housenumber":"515",
    "addr:postcode":"24134",
    "addr:street":"Crickett Ln",
    "iso:country":"US",
    "sg:address":"515 Crickett Ln",
    "sg:city":"Pearisburg",
    "sg:classifiers":[
        {
            "category":"Building & Trades",
            "subcategory":"Construction",
            "type":"Services"
        }
    ],
    "sg:phone":"+1 540 921 3052",
    "sg:postcode":"24134",
    "sg:province":"VA",
    "sg:tags":[
        "contractor"
    ],
    "wof:name":"Cantrall Martin Construction",
    "wof:placetype":"venue"
},
  "geometry": {"coordinates":[-80.696572,37.329587],"type":"Point"}
}