{
  "type": "Feature",
  "properties": {
    "iso:country":"US",
    "sg:address":"4128 Innslake Dr",
    "sg:city":"Glen Allen",
    "sg:classifiers":[
        {
            "category":"Insurance",
            "subcategory":"Insurance Agent",
            "type":"Services"
        }
    ],
    "sg:phone":"+1 804 747 5300",
    "sg:postcode":"23060",
    "sg:province":"VA",
    "sg:tags":[
        "brokerage",
        "agency"
    ],
    "wof:name":"Kennedy Partridge & Associates",
    "wof:placetype":"venue"
},
  "geometry": {"coordinates":[-77.57839300000001,37.64983],"type":"Point"}
}