{
  "type": "Feature",
  "properties": {
    "iso:country":"US",
    "sg:address":"1016 Wilson Rd",
    "sg:city":"Norfolk",
    "sg:classifiers":[
        {
            "category":"Personal",
            "subcategory":"Barber",
            "type":"Services"
        }
    ],
    "sg:phone":"+1 757 545 9627",
    "sg:postcode":"23523",
    "sg:province":"VA",
    "sg:tags":[
        "shop"
    ],
    "wof:name":"Jenkins Barber Shop",
    "wof:placetype":"venue"
},
  "geometry": {"coordinates":[-76.263777,36.831888],"type":"Point"}
}