{
  "type": "Feature",
  "properties": {
    "addr:full":"202 E Oak St Alexandria VA 22301",
    "addr:housenumber":"202",
    "addr:postcode":"22301",
    "addr:street":"E Oak St",
    "iso:country":"US",
    "sg:address":"202 E Oak St",
    "sg:city":"Alexandria",
    "sg:classifiers":[
        {
            "category":"Retail",
            "subcategory":"Portrait Studio",
            "type":"Services"
        },
        {
            "category":"Professional",
            "subcategory":"Art Services",
            "type":"Services"
        }
    ],
    "sg:phone":"+1 703 548 1921",
    "sg:postcode":"22301",
    "sg:province":"VA",
    "sg:tags":[
        "rental",
        "photographers-portrait",
        "photographic",
        "darkroom"
    ],
    "wof:name":"Mcfarland Photograph Inc",
    "wof:placetype":"venue"
},
  "geometry": {"coordinates":[-77.058454,38.813043],"type":"Point"}
}