{
  "type": "Feature",
  "properties": {
    "iso:country":"US",
    "sg:address":"417 County St",
    "sg:city":"Portsmouth",
    "sg:classifiers":[
        {
            "category":"Restaurant",
            "type":"Food & Drink"
        }
    ],
    "sg:phone":"+1 757 399 8060",
    "sg:postcode":"23704",
    "sg:province":"VA",
    "wof:name":"Bob's BBQ & Country Cookin",
    "wof:placetype":"venue"
},
  "geometry": {"coordinates":[-76.302099,36.833679],"type":"Point"}
}