{
  "type": "Feature",
  "properties": {
    "addr:full":"711 Dominion Sq Shopping Ctr Culpeper VA 22701",
    "addr:housenumber":"711",
    "addr:postcode":"22701",
    "addr:street":"Dominion Sq Shopping Ctr",
    "iso:country":"US",
    "sg:address":"711 Dominion Sq Shopping Ctr",
    "sg:city":"Culpeper",
    "sg:classifiers":[
        {
            "category":"Restaurant",
            "type":"Food & Drink"
        }
    ],
    "sg:menulink":"http://www.allmenus.com/va/east-fairfax/147606-subway/menu/",
    "sg:phone":"+1 540 825 8018",
    "sg:postcode":"22701",
    "sg:province":"VA",
    "sg:tags":[
        "american",
        "sandwich"
    ],
    "wof:name":"Subway",
    "wof:placetype":"venue"
},
  "geometry": {"coordinates":[-77.976112,38.48183],"type":"Point"}
}