{
  "type": "Feature",
  "properties": {
    "addr:full":"203 Cooper Ct Newport News VA 23602",
    "addr:housenumber":"203",
    "addr:postcode":"23602",
    "addr:street":"Cooper Ct",
    "iso:country":"US",
    "sg:address":"203 Cooper Ct",
    "sg:city":"Newport News",
    "sg:classifiers":[
        {
            "category":"Freight",
            "type":"Transportation"
        }
    ],
    "sg:phone":"+1 757 890 6161",
    "sg:postcode":"23602",
    "sg:province":"VA",
    "wof:name":"Moving Images Videography",
    "wof:placetype":"venue"
},
  "geometry": {"coordinates":[-76.52739699999999,37.109567],"type":"Point"}
}