{
  "type": "Feature",
  "properties": {
    "addr:full":"167 W Shirley Ave Warrenton VA 20186",
    "addr:housenumber":"167",
    "addr:postcode":"20186",
    "addr:street":"W Shirley Ave",
    "iso:country":"US",
    "sg:address":"167 W Shirley Ave",
    "sg:city":"Warrenton",
    "sg:classifiers":[
        {
            "category":"Government",
            "subcategory":"Fire Station",
            "type":"Public Place"
        }
    ],
    "sg:phone":"+1 540 000 1111",
    "sg:postcode":"20186",
    "sg:province":"VA",
    "sg:tags":[
        "county",
        "protection"
    ],
    "wof:name":"Fauquier Fire Dept",
    "wof:placetype":"venue"
},
  "geometry": {"coordinates":[-77.805151,38.7125],"type":"Point"}
}