{
  "type": "Feature",
  "properties": {
    "iso:country":"US",
    "sg:address":"56 Robinson Dr",
    "sg:city":"Newport News",
    "sg:classifiers":[
        {
            "category":"Professional",
            "type":"Services"
        }
    ],
    "sg:phone":"+1 757 596 4192",
    "sg:postcode":"23601",
    "sg:province":"VA",
    "wof:name":"Jtw Inc",
    "wof:placetype":"venue"
},
  "geometry": {"coordinates":[-76.46707499999999,37.073488],"type":"Point"}
}