{
  "type": "Feature",
  "properties": {
    "iso:country":"US",
    "sg:address":"6730 N Lee Hwy",
    "sg:city":"Arlington",
    "sg:classifiers":[
        {
            "category":"Autos & Motor Vehicles",
            "subcategory":"Fuel & Gas Station",
            "type":"Retail Goods"
        }
    ],
    "sg:phone":"+1 703 237 4226",
    "sg:postcode":"22205",
    "sg:province":"VA",
    "sg:tags":[
        "oil"
    ],
    "sg:website":"www.exxonmobile.com",
    "wof:name":"Washington Lee Exxon",
    "wof:placetype":"venue"
},
  "geometry": {"coordinates":[-77.160231,38.888591],"type":"Point"}
}