{
  "type": "Feature",
  "properties": {
    "iso:country":"US",
    "sg:address":"611 S Carlin Springs Rd",
    "sg:city":"Arlington",
    "sg:classifiers":[
        {
            "category":"Professional",
            "subcategory":"Management & Consulting",
            "type":"Services"
        },
        {
            "category":"Professional",
            "subcategory":"Engineering",
            "type":"Services"
        }
    ],
    "sg:phone":"+1 571 431 6175",
    "sg:postcode":"22204",
    "sg:province":"VA",
    "sg:tags":[
        "science",
        "consultant",
        "engineer",
        "academic"
    ],
    "wof:name":"Washington Dermtology Consultants",
    "wof:placetype":"venue"
},
  "geometry": {"coordinates":[-77.12770399999999,38.860125],"type":"Point"}
}