{
  "type": "Feature",
  "properties": {
    "addr:full":"1604 Shrewsbury Ct Virginia Beach VA 23456",
    "addr:housenumber":"1604",
    "addr:postcode":"23456",
    "addr:street":"Shrewsbury Ct",
    "iso:country":"US",
    "sg:address":"1604 Shrewsbury Ct",
    "sg:city":"Virginia Beach",
    "sg:classifiers":[
        {
            "category":"Building & Trades",
            "subcategory":"Cleaning & Sanitation",
            "type":"Services"
        }
    ],
    "sg:phone":"+1 757 228 5742",
    "sg:postcode":"23456",
    "sg:province":"VA",
    "wof:name":"Hospitality Janitorial Svcs",
    "wof:placetype":"venue"
},
  "geometry": {"coordinates":[-76.139447,36.792278],"type":"Point"}
}