{
  "type": "Feature",
  "properties": {
    "addr:full":"3031 Valley Ave Winchester VA 22601",
    "addr:housenumber":"3031",
    "addr:postcode":"22601",
    "addr:street":"Valley Ave",
    "iso:country":"US",
    "sg:address":"3031 Valley Ave",
    "sg:city":"Winchester",
    "sg:classifiers":[
        {
            "category":"Wholesale",
            "subcategory":"Sporting Goods",
            "type":"Manufacturing & Wholesale Goods"
        }
    ],
    "sg:phone":"+1 540 662 3310",
    "sg:postcode":"22601",
    "sg:province":"VA",
    "sg:tags":[
        "equipment",
        "billiard",
        "supply"
    ],
    "sg:website":"www.robbiesbilliards.com",
    "wof:name":"Robbies Billiards Sales & Svc",
    "wof:placetype":"venue"
},
  "geometry": {"coordinates":[-78.18957399999999,39.144965],"type":"Point"}
}