{
  "type": "Feature",
  "properties": {
    "addr:full":"2905 Patterson Ave Richmond VA 23221",
    "addr:housenumber":"2905",
    "addr:postcode":"23221",
    "addr:street":"Patterson Ave",
    "iso:country":"US",
    "sg:address":"2905 Patterson Ave",
    "sg:city":"Richmond",
    "sg:classifiers":[
        {
            "category":"Restaurant",
            "type":"Food & Drink"
        }
    ],
    "sg:menulink":"http://www.allmenus.com/va/richmond/12958-banditos/menu/",
    "sg:phone":"+1 804 354 9999",
    "sg:postcode":"23221",
    "sg:province":"VA",
    "sg:tags":[
        "mexican"
    ],
    "wof:name":"Bandito's",
    "wof:placetype":"venue"
},
  "geometry": {"coordinates":[-77.47333,37.559944],"type":"Point"}
}