{
  "type": "Feature",
  "properties": {
    "addr:full":"113 W Bank St Petersburg VA 23803",
    "addr:housenumber":"113",
    "addr:postcode":"23803",
    "addr:street":"W Bank St",
    "iso:country":"US",
    "sg:address":"113 W Bank St",
    "sg:city":"Petersburg",
    "sg:classifiers":[
        {
            "category":"Wholesale",
            "subcategory":"Construction Materials",
            "type":"Manufacturing & Wholesale Goods"
        }
    ],
    "sg:phone":"+1 804 732 8810",
    "sg:postcode":"23803",
    "sg:province":"VA",
    "wof:name":"Appomattox Tile Art Inc",
    "wof:placetype":"venue"
},
  "geometry": {"coordinates":[-77.405888,37.231808],"type":"Point"}
}