{
  "type": "Feature",
  "properties": {
    "iso:country":"US",
    "sg:address":"426 W Main St",
    "sg:city":"Salem",
    "sg:classifiers":[
        {
            "category":"Health Services",
            "subcategory":"Doctor",
            "type":"Services"
        }
    ],
    "sg:phone":"+1 540 389 7348",
    "sg:postcode":"24153",
    "sg:province":"VA",
    "sg:tags":[
        "physician",
        "surgeon",
        "medical"
    ],
    "wof:name":"Daniel T Drysdale MD",
    "wof:placetype":"venue"
},
  "geometry": {"coordinates":[-80.06651599999999,37.291182],"type":"Point"}
}