{
  "type": "Feature",
  "properties": {
    "addr:full":"10125 Lakehaven Ct Burke VA 22015",
    "addr:housenumber":"10125",
    "addr:postcode":"22015",
    "addr:street":"Lakehaven Ct",
    "iso:country":"US",
    "sg:address":"10125 Lakehaven Ct",
    "sg:city":"Burke",
    "sg:classifiers":[
        {
            "category":"Organizations",
            "subcategory":"Religious Organization",
            "type":"Services"
        }
    ],
    "sg:phone":"+1 703 503 4579",
    "sg:postcode":"22015",
    "sg:province":"VA",
    "wof:name":"Accotink Unitairn Univrslt Ch",
    "wof:placetype":"venue"
},
  "geometry": {"coordinates":[-77.296621,38.774394],"type":"Point"}
}