{
  "type": "Feature",
  "properties": {
    "addr:full":"2544 Bainbridge Blvd Ste C Chesapeake VA 23324",
    "addr:housenumber":"2544",
    "addr:postcode":"23324",
    "addr:street":"Bainbridge Blvd Ste C",
    "iso:country":"US",
    "sg:address":"2544 Bainbridge Blvd Ste C",
    "sg:city":"Chesapeake",
    "sg:classifiers":[
        {
            "category":"Restaurant",
            "type":"Food & Drink"
        }
    ],
    "sg:phone":"+1 757 545 7200",
    "sg:postcode":"23324",
    "sg:province":"VA",
    "sg:tags":[
        "asian",
        "chinese",
        "pan"
    ],
    "wof:name":"China Ocean Restaurant",
    "wof:placetype":"venue"
},
  "geometry": {"coordinates":[-76.27667099999999,36.79874],"type":"Point"}
}