{
  "type": "Feature",
  "properties": {
    "addr:full":"632 Charles St Staunton VA 24401",
    "addr:housenumber":"632",
    "addr:postcode":"24401",
    "addr:street":"Charles St",
    "iso:country":"US",
    "sg:address":"632 Charles St",
    "sg:city":"Staunton",
    "sg:classifiers":[
        {
            "category":"Shopping",
            "subcategory":"Florist",
            "type":"Retail Goods"
        }
    ],
    "sg:phone":"+1 540 885 1571",
    "sg:postcode":"24401",
    "sg:province":"VA",
    "wof:name":"Flowers By Jay",
    "wof:placetype":"venue"
},
  "geometry": {"coordinates":[-79.070031,38.137172],"type":"Point"}
}