{
  "type": "Feature",
  "properties": {
    "addr:full":"864 W 40th St Norfolk VA 23508",
    "addr:housenumber":"864",
    "addr:postcode":"23508",
    "addr:street":"W 40Th St",
    "iso:country":"US",
    "sg:address":"864 W 40th St",
    "sg:city":"Norfolk",
    "sg:classifiers":[
        {
            "category":"Building & Trades",
            "subcategory":"Construction",
            "type":"Services"
        }
    ],
    "sg:phone":"+1 757 489 7181",
    "sg:postcode":"23508",
    "sg:province":"VA",
    "sg:tags":[
        "home",
        "improvement"
    ],
    "wof:name":"Cullifer Construction Svc",
    "wof:placetype":"venue"
},
  "geometry": {"coordinates":[-76.29602199999999,36.88154],"type":"Point"}
}