{
  "type": "Feature",
  "properties": {
    "iso:country":"US",
    "sg:address":"3455 N Glebe Rd",
    "sg:city":"Arlington",
    "sg:classifiers":[
        {
            "category":"Organizations",
            "subcategory":"Religious Organization",
            "type":"Services"
        }
    ],
    "sg:phone":"+1 703 538 7000",
    "sg:postcode":"22207",
    "sg:province":"VA",
    "sg:tags":[
        "church"
    ],
    "sg:website":"www.memorialbaptistchurch.org",
    "wof:name":"Memorial Baptist Church Inc",
    "wof:placetype":"venue"
},
  "geometry": {"coordinates":[-77.13559100000001,38.914148],"type":"Point"}
}