{
  "type": "Feature",
  "properties": {
    "iso:country":"US",
    "sg:address":"14662 Moneta Rd",
    "sg:city":"Moneta",
    "sg:classifiers":[
        {
            "category":"Manufacturing",
            "subcategory":"Glass & Minerals",
            "type":"Manufacturing & Wholesale Goods"
        }
    ],
    "sg:phone":"+1 540 890 8910",
    "sg:postcode":"24121",
    "sg:province":"VA",
    "sg:tags":[
        "refractory"
    ],
    "wof:name":"Emlex Construction Co Inc",
    "wof:placetype":"venue"
},
  "geometry": {"coordinates":[-79.635946,37.165712],"type":"Point"}
}