{
  "type": "Feature",
  "properties": {
    "addr:full":"603 Wormley Creek Dr Yorktown VA 23692",
    "addr:housenumber":"603",
    "addr:postcode":"23692",
    "addr:street":"Wormley Creek Dr",
    "iso:country":"US",
    "sg:address":"603 Wormley Creek Dr",
    "sg:city":"Yorktown",
    "sg:classifiers":[
        {
            "category":"Social Services",
            "type":"Services"
        }
    ],
    "sg:phone":"+1 757 898 9022",
    "sg:postcode":"23692",
    "sg:province":"VA",
    "sg:tags":[
        "counselor",
        "marriage",
        "family"
    ],
    "wof:name":"Tipton K Sheets",
    "wof:placetype":"venue"
},
  "geometry": {"coordinates":[-76.48054500000001,37.209179],"type":"Point"}
}