{
  "type": "Feature",
  "properties": {
    "addr:full":"22601 Davis Dr Sterling VA 20164",
    "addr:housenumber":"22601",
    "addr:postcode":"20164",
    "addr:street":"Davis Dr",
    "iso:country":"US",
    "sg:address":"22601 Davis Dr",
    "sg:city":"Sterling",
    "sg:classifiers":[
        {
            "category":"Professional",
            "subcategory":"Advertising",
            "type":"Services"
        }
    ],
    "sg:phone":"+1 703 787 7708",
    "sg:postcode":"20164",
    "sg:province":"VA",
    "wof:name":"Power Pact LLC",
    "wof:placetype":"venue"
},
  "geometry": {"coordinates":[-77.417934,38.991471],"type":"Point"}
}