{
  "type": "Feature",
  "properties": {
    "addr:full":"14745 Dogwood Park Ln Haymarket VA 20169",
    "addr:housenumber":"14745",
    "addr:postcode":"20169",
    "addr:street":"Dogwood Park Ln",
    "iso:country":"US",
    "sg:address":"14745 Dogwood Park Ln",
    "sg:city":"Haymarket",
    "sg:classifiers":[
        {
            "category":"Building & Trades",
            "subcategory":"Construction",
            "type":"Services"
        }
    ],
    "sg:phone":"+1 571 261 1321",
    "sg:postcode":"20169",
    "sg:province":"VA",
    "sg:tags":[
        "house"
    ],
    "wof:name":"Oak Ridge Builders",
    "wof:placetype":"venue"
},
  "geometry": {"coordinates":[-77.631141,38.811553],"type":"Point"}
}