{
  "type": "Feature",
  "properties": {
    "iso:country":"US",
    "sg:address":"32319 Constitution Hwy",
    "sg:city":"Locust Grove",
    "sg:classifiers":[
        {
            "category":"Autos & Motor Vehicles",
            "subcategory":"Automobile Sales",
            "type":"Retail Goods"
        }
    ],
    "sg:phone":"+1 540 854 5600",
    "sg:postcode":"22508",
    "sg:province":"VA",
    "sg:tags":[
        "car",
        "used",
        "dealer"
    ],
    "wof:name":"Battlefield Auto Sales & Srvc",
    "wof:placetype":"venue"
},
  "geometry": {"coordinates":[-77.804418,38.30632],"type":"Point"}
}