{
  "type": "Feature",
  "properties": {
    "iso:country":"US",
    "sg:address":"26053 Parks Rd",
    "sg:city":"Parksley",
    "sg:classifiers":[
        {
            "category":"Farming",
            "subcategory":"Poultry Farm",
            "type":"Manufacturing & Wholesale Goods"
        }
    ],
    "sg:phone":"+1 757 787 3778",
    "sg:postcode":"23421",
    "sg:province":"VA",
    "sg:tags":[
        "hatchery"
    ],
    "wof:name":"Corbin Farm",
    "wof:placetype":"venue"
},
  "geometry": {"coordinates":[-75.62772,37.737753],"type":"Point"}
}