{
  "type": "Feature",
  "properties": {
    "addr:full":"9300 Mackenzie Meadow Ct Nokesville VA 20181",
    "addr:housenumber":"9300",
    "addr:postcode":"20181",
    "addr:street":"Mackenzie Meadow Ct",
    "iso:country":"US",
    "sg:address":"9300 Mackenzie Meadow Ct",
    "sg:city":"Nokesville",
    "sg:classifiers":[
        {
            "category":"Building & Trades",
            "subcategory":"Construction",
            "type":"Services"
        }
    ],
    "sg:phone":"+1 703 754 4746",
    "sg:postcode":"20181",
    "sg:province":"VA",
    "sg:tags":[
        "system",
        "specialty",
        "heating",
        "contractor",
        "air conditioning"
    ],
    "wof:name":"Advanced Air Conditiong & Heat",
    "wof:placetype":"venue"
},
  "geometry": {"coordinates":[-77.64122999999999,38.754611],"type":"Point"}
}