{
  "type": "Feature",
  "properties": {
    "addr:full":"14918 Kamputa Dr Centreville VA 20120",
    "addr:housenumber":"14918",
    "addr:postcode":"20120",
    "addr:street":"Kamputa Dr",
    "iso:country":"US",
    "sg:address":"14918 Kamputa Dr",
    "sg:city":"Centreville",
    "sg:classifiers":[
        {
            "category":"Professional",
            "subcategory":"Computer Services",
            "type":"Services"
        }
    ],
    "sg:phone":"+1 703 222 3217",
    "sg:postcode":"20120",
    "sg:province":"VA",
    "sg:tags":[
        "development",
        "consulting",
        "software"
    ],
    "wof:name":"Coral Computer Inc",
    "wof:placetype":"venue"
},
  "geometry": {"coordinates":[-77.46429500000001,38.854463],"type":"Point"}
}