{
  "type": "Feature",
  "properties": {
    "iso:country":"US",
    "sg:address":"2 Cardinal Park Dr SE",
    "sg:city":"Leesburg",
    "sg:classifiers":[
        {
            "category":"Organizations",
            "subcategory":"Religious Organization",
            "type":"Services"
        }
    ],
    "sg:phone":"+1 703 771 1534",
    "sg:postcode":"20175",
    "sg:province":"VA",
    "sg:tags":[
        "church"
    ],
    "sg:website":"www.potomachills.com",
    "wof:name":"Potomac Hills Community Church",
    "wof:placetype":"venue"
},
  "geometry": {"coordinates":[-77.541675,39.098188],"type":"Point"}
}