{
  "type": "Feature",
  "properties": {
    "iso:country":"US",
    "sg:address":"4310 Rivermont Dr",
    "sg:city":"Front Royal",
    "sg:classifiers":[
        {
            "category":"Retail",
            "subcategory":"Veterinary Services",
            "type":"Services"
        }
    ],
    "sg:phone":"+1 540 635 4176",
    "sg:postcode":"22630",
    "sg:province":"VA",
    "sg:tags":[
        "veterinarian"
    ],
    "wof:name":"Warren County Veterinary Clnc",
    "wof:placetype":"venue"
},
  "geometry": {"coordinates":[-78.212918,38.903772],"type":"Point"}
}