{
  "type": "Feature",
  "properties": {
    "addr:full":"22800 Indian Creek Dr Sterling VA 20166",
    "addr:housenumber":"22800",
    "addr:postcode":"20166",
    "addr:street":"Indian Creek Dr",
    "iso:country":"US",
    "sg:address":"22800 Indian Creek Dr",
    "sg:city":"Sterling",
    "sg:classifiers":[
        {
            "category":"Freight",
            "type":"Transportation"
        }
    ],
    "sg:phone":"+1 703 834 1313",
    "sg:postcode":"20166",
    "sg:province":"VA",
    "sg:tags":[
        "moving",
        "storage"
    ],
    "wof:name":"Relocation Systems LLc",
    "wof:placetype":"venue"
},
  "geometry": {"coordinates":[-77.433482,38.986278],"type":"Point"}
}