{
  "type": "Feature",
  "properties": {
    "addr:full":"9100 Bethia Rd Chesterfield VA 23832",
    "addr:housenumber":"9100",
    "addr:postcode":"23832",
    "addr:street":"Bethia Rd",
    "iso:country":"US",
    "sg:address":"9100 Bethia Rd",
    "sg:city":"Chesterfield",
    "sg:classifiers":[
        {
            "category":"Building & Trades",
            "subcategory":"Construction",
            "type":"Services"
        }
    ],
    "sg:phone":"+1 804 739 3244",
    "sg:postcode":"23832",
    "sg:province":"VA",
    "sg:tags":[
        "contractor"
    ],
    "wof:name":"Contract Building Service Inc",
    "wof:placetype":"venue"
},
  "geometry": {"coordinates":[-77.672275,37.38197],"type":"Point"}
}