{
  "type": "Feature",
  "properties": {
    "iso:country":"US",
    "sg:address":"3413 Manning Rd",
    "sg:city":"Suffolk",
    "sg:classifiers":[
        {
            "category":"Professional",
            "subcategory":"Testing Lab",
            "type":"Services"
        }
    ],
    "sg:phone":"+1 757 986 3254",
    "sg:postcode":"23434",
    "sg:province":"VA",
    "sg:tags":[
        "soil",
        "engineering",
        "sampling"
    ],
    "wof:name":"Enviro Drill Inc",
    "wof:placetype":"venue"
},
  "geometry": {"coordinates":[-76.692427,36.648281],"type":"Point"}
}