{
  "type": "Feature",
  "properties": {
    "addr:full":"681 Village Hwy Rustburg VA 24588",
    "addr:housenumber":"681",
    "addr:postcode":"24588",
    "addr:street":"Village Hwy",
    "iso:country":"US",
    "sg:address":"681 Village Hwy",
    "sg:city":"Rustburg",
    "sg:classifiers":[
        {
            "category":"Organizations",
            "subcategory":"Religious Organization",
            "type":"Services"
        }
    ],
    "sg:phone":"+1 434 332 5992",
    "sg:postcode":"24588",
    "sg:province":"VA",
    "sg:tags":[
        "church"
    ],
    "wof:name":"Rustburg Presbyterian Church",
    "wof:placetype":"venue"
},
  "geometry": {"coordinates":[-79.102998,37.275627],"type":"Point"}
}