{
  "type": "Feature",
  "properties": {
    "iso:country":"US",
    "sg:address":"100 Duke St",
    "sg:city":"Alexandria",
    "sg:classifiers":[
        {
            "category":"Communications",
            "subcategory":"Radio Station",
            "type":"Services"
        }
    ],
    "sg:phone":"+1 703 684 3507",
    "sg:postcode":"22314",
    "sg:province":"VA",
    "sg:tags":[
        "educational"
    ],
    "wof:name":"Ana Rico",
    "wof:placetype":"venue"
},
  "geometry": {"coordinates":[-77.04196899999999,38.802091],"type":"Point"}
}