{
  "type": "Feature",
  "properties": {
    "addr:full":"7457 Mill Swamp Rd Ivor VA 23866",
    "addr:housenumber":"7457",
    "addr:postcode":"23866",
    "addr:street":"Mill Swamp Rd",
    "iso:country":"US",
    "sg:address":"7457 Mill Swamp Rd",
    "sg:city":"Ivor",
    "sg:classifiers":[
        {
            "category":"Building & Trades",
            "subcategory":"Plumbing",
            "type":"Services"
        }
    ],
    "sg:phone":"+1 757 357 6856",
    "sg:postcode":"23866",
    "sg:province":"VA",
    "sg:tags":[
        "contractor"
    ],
    "wof:name":"Fabian Tobin",
    "wof:placetype":"venue"
},
  "geometry": {"coordinates":[-76.791853,37.002385],"type":"Point"}
}