{
  "type": "Feature",
  "properties": {
    "addr:full":"5857 Leesburg Pike Falls Church VA 22041",
    "addr:housenumber":"5857",
    "addr:postcode":"22041",
    "addr:street":"Leesburg Pike",
    "iso:country":"US",
    "sg:address":"5857 Leesburg Pike",
    "sg:city":"Falls Church",
    "sg:classifiers":[
        {
            "category":"Shopping",
            "subcategory":"Computers & Home Electronics",
            "type":"Retail Goods"
        }
    ],
    "sg:phone":"+1 703 845 8707",
    "sg:postcode":"22041",
    "sg:province":"VA",
    "sg:tags":[
        "high",
        "fidelity",
        "stereophonic"
    ],
    "wof:name":"Tweeter",
    "wof:placetype":"venue"
},
  "geometry": {"coordinates":[-77.132599,38.852008],"type":"Point"}
}