{
  "type": "Feature",
  "properties": {
    "addr:full":"510 Cardinal Glen Cir Sterling VA 20164",
    "addr:housenumber":"510",
    "addr:postcode":"20164",
    "addr:street":"Cardinal Glen Cir",
    "iso:country":"US",
    "sg:address":"510 Cardinal Glen Cir",
    "sg:city":"Sterling",
    "sg:classifiers":[
        {
            "category":"Organizations",
            "subcategory":"Professional Association",
            "type":"Services"
        }
    ],
    "sg:phone":"+1 703 421 8575",
    "sg:postcode":"20164",
    "sg:province":"VA",
    "wof:name":"Sterling Oxford House",
    "wof:placetype":"venue"
},
  "geometry": {"coordinates":[-77.383645,39.022688],"type":"Point"}
}