{
  "type": "Feature",
  "properties": {
    "addr:full":"11153 Goldfish Ln Broadway VA 22815",
    "addr:housenumber":"11153",
    "addr:postcode":"22815",
    "addr:street":"Goldfish Ln",
    "iso:country":"US",
    "sg:address":"11153 Goldfish Ln",
    "sg:city":"Broadway",
    "sg:classifiers":[
        {
            "category":"Home & Garden",
            "subcategory":"Hardware",
            "type":"Retail Goods"
        }
    ],
    "sg:phone":"+1 540 896 5212",
    "sg:postcode":"22815",
    "sg:province":"VA",
    "sg:tags":[
        "tool",
        "used"
    ],
    "wof:name":"Jones Enterprises",
    "wof:placetype":"venue"
},
  "geometry": {"coordinates":[-78.768535,38.583483],"type":"Point"}
}