{
  "type": "Feature",
  "properties": {
    "iso:country":"US",
    "sg:address":"385 Reflections Dr",
    "sg:city":"Virginia Beach",
    "sg:classifiers":[
        {
            "category":"Local Transit",
            "type":"Transportation"
        }
    ],
    "sg:phone":"+1 757 631 4870",
    "sg:postcode":"23452",
    "sg:province":"VA",
    "sg:tags":[
        "passenger"
    ],
    "wof:name":"Toms Limo Service",
    "wof:placetype":"venue"
},
  "geometry": {"coordinates":[-76.075126,36.829355],"type":"Point"}
}