{
  "type": "Feature",
  "properties": {
    "addr:full":"6518 Greenleaf St Springfield VA 22150",
    "addr:housenumber":"6518",
    "addr:postcode":"22150",
    "addr:street":"Greenleaf St",
    "iso:country":"US",
    "sg:address":"6518 Greenleaf St",
    "sg:city":"Springfield",
    "sg:classifiers":[
        {
            "category":"Local Transit",
            "type":"Transportation"
        }
    ],
    "sg:phone":"+1 703 313 0012",
    "sg:postcode":"22150",
    "sg:province":"VA",
    "sg:tags":[
        "passenger"
    ],
    "wof:name":"L & S Sedans Inc",
    "wof:placetype":"venue"
},
  "geometry": {"coordinates":[-77.165846,38.773827],"type":"Point"}
}