{
  "type": "Feature",
  "properties": {
    "iso:country":"US",
    "sg:address":"3305 Graham Rd",
    "sg:city":"Falls Church",
    "sg:classifiers":[
        {
            "category":"Organizations",
            "subcategory":"Religious Organization",
            "type":"Services"
        }
    ],
    "sg:phone":"+1 703 560 0853",
    "sg:postcode":"22042",
    "sg:province":"VA",
    "wof:name":"Society For Rlgous Orgnzations",
    "wof:placetype":"venue"
},
  "geometry": {"coordinates":[-77.19175199999999,38.858933],"type":"Point"}
}