{
  "type": "Feature",
  "properties": {
    "iso:country":"US",
    "sg:address":"17295 Lee Hwy",
    "sg:city":"Abingdon",
    "sg:classifiers":[
        {
            "category":"Manufacturing",
            "subcategory":"Tools & Machinery",
            "type":"Manufacturing & Wholesale Goods"
        }
    ],
    "sg:phone":"+1 276 628 6113",
    "sg:postcode":"24210",
    "sg:province":"VA",
    "sg:tags":[
        "shop",
        "die",
        "machine",
        "special",
        "mfg"
    ],
    "wof:name":"Lilly's Die-Tool & Mfg Corp",
    "wof:placetype":"venue"
},
  "geometry": {"coordinates":[-82.055267,36.671513],"type":"Point"}
}