{
  "type": "Feature",
  "properties": {
    "iso:country":"US",
    "sg:address":"2002 Lakewinds Dr",
    "sg:city":"Reston",
    "sg:classifiers":[
        {
            "category":"Real Estate",
            "subcategory":"Real Estate Agent",
            "type":"Services"
        }
    ],
    "sg:phone":"+1 703 620 6437",
    "sg:postcode":"20191",
    "sg:province":"VA",
    "wof:name":"Whispering Waves LP",
    "wof:placetype":"venue"
},
  "geometry": {"coordinates":[-77.33470699999999,38.935705],"type":"Point"}
}