{
  "type": "Feature",
  "properties": {
    "addr:full":"17 Bedford Rd Newport News VA 23601",
    "addr:housenumber":"17",
    "addr:postcode":"23601",
    "addr:street":"Bedford Rd",
    "iso:country":"US",
    "sg:address":"17 Bedford Rd",
    "sg:city":"Newport News",
    "sg:classifiers":[
        {
            "category":"Building & Trades",
            "subcategory":"Construction",
            "type":"Services"
        }
    ],
    "sg:phone":"+1 757 508 7752",
    "sg:postcode":"23601",
    "sg:province":"VA",
    "sg:tags":[
        "contractor"
    ],
    "wof:name":"Thomas & Fields Roofing Svc",
    "wof:placetype":"venue"
},
  "geometry": {"coordinates":[-76.46333199999999,37.067139],"type":"Point"}
}