{
  "type": "Feature",
  "properties": {
    "iso:country":"US",
    "sg:address":"2142 Haycock Rd",
    "sg:city":"Falls Church",
    "sg:classifiers":[
        {
            "category":"Professional",
            "subcategory":"Advertising",
            "type":"Services"
        }
    ],
    "sg:phone":"+1 703 241 2510",
    "sg:postcode":"22043",
    "sg:province":"VA",
    "sg:tags":[
        "agency"
    ],
    "wof:name":"Beckon Call Inc",
    "wof:placetype":"venue"
},
  "geometry": {"coordinates":[-77.171178,38.903651],"type":"Point"}
}