{
  "type": "Feature",
  "properties": {
    "addr:full":"7416 Evelyn T Butts Ave Norfolk VA 23513",
    "addr:housenumber":"7416",
    "addr:postcode":"23513",
    "addr:street":"Evelyn T Butts Ave",
    "iso:country":"US",
    "sg:address":"7416 Evelyn T Butts Ave",
    "sg:city":"Norfolk",
    "sg:classifiers":[
        {
            "category":"Organizations",
            "subcategory":"Religious Organization",
            "type":"Services"
        }
    ],
    "sg:phone":"+1 757 853 2439",
    "sg:postcode":"23513",
    "sg:province":"VA",
    "sg:tags":[
        "church"
    ],
    "wof:name":"Endtime United Church Of Jesus",
    "wof:placetype":"venue"
},
  "geometry": {"coordinates":[-76.243106,36.911433],"type":"Point"}
}