{
  "type": "Feature",
  "properties": {
    "addr:full":"6718 Holford Ln Springfield VA 22152",
    "addr:housenumber":"6718",
    "addr:postcode":"22152",
    "addr:street":"Holford Ln",
    "iso:country":"US",
    "sg:address":"6718 Holford Ln",
    "sg:city":"Springfield",
    "sg:classifiers":[
        {
            "category":"Professional",
            "subcategory":"Business Services",
            "type":"Services"
        }
    ],
    "sg:phone":"+1 703 451 5302",
    "sg:postcode":"22152",
    "sg:province":"VA",
    "wof:name":"Ouellette Herta",
    "wof:placetype":"venue"
},
  "geometry": {"coordinates":[-77.23563300000001,38.768206],"type":"Point"}
}