{
  "type": "Feature",
  "properties": {
    "addr:full":"92 Stoney Dr Deltaville VA 23070",
    "addr:housenumber":"92",
    "addr:postcode":"23070",
    "addr:street":"Stoney Dr",
    "iso:country":"US",
    "sg:address":"92 Stoney Dr",
    "sg:city":"Deltaville",
    "sg:classifiers":[
        {
            "category":"Professional",
            "type":"Services"
        }
    ],
    "sg:phone":"+1 804 776 6541",
    "sg:postcode":"23070",
    "sg:province":"VA",
    "sg:tags":[
        "establishment"
    ],
    "wof:name":"Docks Unlimited",
    "wof:placetype":"venue"
},
  "geometry": {"coordinates":[-76.384281,37.569477],"type":"Point"}
}