{
  "type": "Feature",
  "properties": {
    "addr:full":"110 Creekside Ln Winchester VA 22602",
    "addr:housenumber":"110",
    "addr:postcode":"22602",
    "addr:street":"Creekside Ln",
    "iso:country":"US",
    "sg:address":"110 Creekside Ln",
    "sg:city":"Winchester",
    "sg:classifiers":[
        {
            "category":"Personal",
            "subcategory":"Beauty Salon",
            "type":"Services"
        }
    ],
    "sg:phone":"+1 540 662 5056",
    "sg:postcode":"22602",
    "sg:province":"VA",
    "sg:tags":[
        "shop"
    ],
    "wof:name":"Visage",
    "wof:placetype":"venue"
},
  "geometry": {"coordinates":[-78.19105999999999,39.140455],"type":"Point"}
}