{
  "type": "Feature",
  "properties": {
    "iso:country":"US",
    "sg:address":"101 E Main St",
    "sg:city":"Marion",
    "sg:classifiers":[
        {
            "category":"Insurance",
            "subcategory":"Insurance Agent",
            "type":"Services"
        }
    ],
    "sg:phone":"+1 276 783 6646",
    "sg:postcode":"24354",
    "sg:province":"VA",
    "wof:name":"Hometown Investment Svc",
    "wof:placetype":"venue"
},
  "geometry": {"coordinates":[-81.51961799999999,36.832924],"type":"Point"}
}