{
  "type": "Feature",
  "properties": {
    "addr:full":"7 Clear Water Ct Charlottesville VA 22942",
    "addr:housenumber":"7",
    "addr:postcode":"22942",
    "addr:street":"Clear Water Ct",
    "iso:country":"US",
    "sg:address":"7 Clear Water Ct",
    "sg:city":"Charlottesville",
    "sg:classifiers":[
        {
            "category":"Building & Trades",
            "subcategory":"Landscaping Services",
            "type":"Services"
        }
    ],
    "sg:phone":"+1 434 242 2102",
    "sg:postcode":"22942",
    "sg:province":"VA",
    "sg:tags":[
        "lawn",
        "maintenance",
        "grounds"
    ],
    "wof:name":"Faithful Service",
    "wof:placetype":"venue"
},
  "geometry": {"coordinates":[-78.238055,38.071372],"type":"Point"}
}