{
  "type": "Feature",
  "properties": {
    "addr:full":"3601 Terminal Ave Newport News VA 23607",
    "addr:housenumber":"3601",
    "addr:postcode":"23607",
    "addr:street":"Terminal Ave",
    "iso:country":"US",
    "sg:address":"3601 Terminal Ave",
    "sg:city":"Newport News",
    "sg:classifiers":[
        {
            "category":"Railroad",
            "type":"Transportation"
        }
    ],
    "sg:phone":"+1 757 380 5000",
    "sg:postcode":"23607",
    "sg:province":"VA",
    "sg:tags":[
        "operator",
        "line"
    ],
    "wof:name":"CSX Transportation Inc",
    "wof:placetype":"venue"
},
  "geometry": {"coordinates":[-76.426755,36.98493],"type":"Point"}
}