{
  "type": "Feature",
  "properties": {
    "addr:full":"4301 S Columbia Pike Arlington VA 22204",
    "addr:housenumber":"4301",
    "addr:postcode":"22204",
    "addr:street":"S Columbia Pike",
    "iso:country":"US",
    "sg:address":"4301 S Columbia Pike",
    "sg:city":"Arlington",
    "sg:classifiers":[
        {
            "category":"Professional",
            "subcategory":"Management & Consulting",
            "type":"Services"
        }
    ],
    "sg:phone":"+1 703 271 0599",
    "sg:postcode":"22204",
    "sg:province":"VA",
    "wof:name":"Jack & John Swallow & Assoc",
    "wof:placetype":"venue"
},
  "geometry": {"coordinates":[-77.104298,38.857924],"type":"Point"}
}