{
  "type": "Feature",
  "properties": {
    "iso:country":"US",
    "sg:address":"412 Dorchester Rd",
    "sg:city":"Falls Church",
    "sg:classifiers":[
        {
            "category":"Arts & Performance",
            "subcategory":"Theater",
            "type":"Entertainment"
        }
    ],
    "sg:phone":"+1 703 536 3107",
    "sg:postcode":"22046",
    "sg:province":"VA",
    "sg:tags":[
        "group"
    ],
    "wof:name":"Opus 3 Trio Inc",
    "wof:placetype":"venue"
},
  "geometry": {"coordinates":[-77.17058299999999,38.892174],"type":"Point"}
}