{
  "type": "Feature",
  "properties": {
    "addr:full":"11674 Smith Mountain Lake Pkwy Huddleston VA 24104",
    "addr:housenumber":"11674",
    "addr:postcode":"24104",
    "addr:street":"Smith Mountain Lake Pkwy",
    "iso:country":"US",
    "sg:address":"11674 Smith Mountain Lake Pkwy",
    "sg:city":"Huddleston",
    "sg:classifiers":[
        {
            "category":"Food & Beverages",
            "subcategory":"Groceries & Convenience Stores",
            "type":"Retail Goods"
        }
    ],
    "sg:phone":"+1 540 297 6857",
    "sg:postcode":"24104",
    "sg:province":"VA",
    "sg:tags":[
        "grocer"
    ],
    "wof:name":"White House Corner Store",
    "wof:placetype":"venue"
},
  "geometry": {"coordinates":[-79.571288,37.115055],"type":"Point"}
}