{
  "type": "Feature",
  "properties": {
    "iso:country":"US",
    "sg:address":"2110 Olympic Ct",
    "sg:city":"Richmond",
    "sg:classifiers":[
        {
            "category":"Shopping",
            "type":"Retail Goods"
        }
    ],
    "sg:phone":"+1 804 560 1771",
    "sg:postcode":"23235",
    "sg:province":"VA",
    "sg:tags":[
        "religious"
    ],
    "wof:name":"Thee Master's Touch",
    "wof:placetype":"venue"
},
  "geometry": {"coordinates":[-77.593396,37.522295],"type":"Point"}
}