{
  "type": "Feature",
  "properties": {
    "addr:full":"3248 Jefferson Davis Hwy Stafford VA 22554",
    "addr:housenumber":"3248",
    "addr:postcode":"22554",
    "addr:street":"Jefferson Davis Hwy",
    "iso:country":"US",
    "sg:address":"3248 Jefferson Davis Hwy",
    "sg:city":"Stafford",
    "sg:classifiers":[
        {
            "category":"Organizations",
            "subcategory":"Religious Organization",
            "type":"Services"
        }
    ],
    "sg:phone":"+1 540 657 8406",
    "sg:postcode":"22554",
    "sg:province":"VA",
    "sg:tags":[
        "church"
    ],
    "wof:name":"Living Water AME Church",
    "wof:placetype":"venue"
},
  "geometry": {"coordinates":[-77.391541,38.476035],"type":"Point"}
}