{
  "type": "Feature",
  "properties": {
    "addr:full":"8717 Wadebrook Ter Springfield VA 22153",
    "addr:housenumber":"8717",
    "addr:postcode":"22153",
    "addr:street":"Wadebrook Ter",
    "iso:country":"US",
    "sg:address":"8717 Wadebrook Ter",
    "sg:city":"Springfield",
    "sg:classifiers":[
        {
            "category":"Real Estate",
            "subcategory":"Real Estate Services",
            "type":"Services"
        },
        {
            "category":"Real Estate",
            "subcategory":"Real Estate Agent",
            "type":"Services"
        }
    ],
    "sg:phone":"+1 703 629 3721",
    "sg:postcode":"22153",
    "sg:province":"VA",
    "sg:tags":[
        "management"
    ],
    "wof:name":"Metropolitan Property Mgmt",
    "wof:placetype":"venue"
},
  "geometry": {"coordinates":[-77.211066,38.721291],"type":"Point"}
}