{
  "type": "Feature",
  "properties": {
    "addr:full":"7505 Leesburg Pike Falls Church VA 22043",
    "addr:housenumber":"7505",
    "addr:postcode":"22043",
    "addr:street":"Leesburg Pike",
    "iso:country":"US",
    "sg:address":"7505 Leesburg Pike",
    "sg:city":"Falls Church",
    "sg:classifiers":[
        {
            "category":"Home & Garden",
            "subcategory":"Building Materials",
            "type":"Retail Goods"
        }
    ],
    "sg:phone":"+1 703 847 5772",
    "sg:postcode":"22043",
    "sg:province":"VA",
    "sg:tags":[
        "windows"
    ],
    "wof:name":"Pella Window Store",
    "wof:placetype":"venue"
},
  "geometry": {"coordinates":[-77.204055,38.903381],"type":"Point"}
}