{
  "type": "Feature",
  "properties": {
    "addr:full":"412 N Jordan St Alexandria VA 22304",
    "addr:housenumber":"412",
    "addr:postcode":"22304",
    "addr:street":"N Jordan St",
    "iso:country":"US",
    "sg:address":"412 N Jordan St",
    "sg:city":"Alexandria",
    "sg:classifiers":[
        {
            "category":"Organizations",
            "subcategory":"Religious Organization",
            "type":"Services"
        }
    ],
    "sg:phone":"+1 703 370 3771",
    "sg:postcode":"22304",
    "sg:province":"VA",
    "sg:tags":[
        "clergy"
    ],
    "wof:name":"Patricia A Jones",
    "wof:placetype":"venue"
},
  "geometry": {"coordinates":[-77.108006,38.817778],"type":"Point"}
}