{
  "type": "Feature",
  "properties": {
    "iso:country":"US",
    "sg:address":"5885 Trinity Pkwy",
    "sg:city":"Centreville",
    "sg:classifiers":[
        {
            "category":"Organizations",
            "subcategory":"Religious Organization",
            "type":"Services"
        }
    ],
    "sg:phone":"+1 703 266 2274",
    "sg:postcode":"20120",
    "sg:province":"VA",
    "wof:name":"Trinity Centre One LLC",
    "wof:placetype":"venue"
},
  "geometry": {"coordinates":[-77.44114,38.840546],"type":"Point"}
}