{
  "type": "Feature",
  "properties": {
    "addr:full":"328 Three Oaks Rd Wirtz VA 24184",
    "addr:housenumber":"328",
    "addr:postcode":"24184",
    "addr:street":"Three Oaks Rd",
    "iso:country":"US",
    "sg:address":"328 Three Oaks Rd",
    "sg:city":"Wirtz",
    "sg:classifiers":[
        {
            "category":"Building & Trades",
            "subcategory":"Construction",
            "type":"Services"
        }
    ],
    "sg:phone":"+1 540 721 8950",
    "sg:postcode":"24184",
    "sg:province":"VA",
    "sg:tags":[
        "contractor"
    ],
    "wof:name":"Smith Bros",
    "wof:placetype":"venue"
},
  "geometry": {"coordinates":[-79.779353,37.072486],"type":"Point"}
}