{
  "type": "Feature",
  "properties": {
    "addr:full":"554 Railroad Dr Marion VA 24354",
    "addr:housenumber":"554",
    "addr:postcode":"24354",
    "addr:street":"Railroad Dr",
    "iso:country":"US",
    "sg:address":"554 Railroad Dr",
    "sg:city":"Marion",
    "sg:classifiers":[
        {
            "category":"Building & Trades",
            "subcategory":"Plumbing",
            "type":"Services"
        }
    ],
    "sg:phone":"+1 276 783 4833",
    "sg:postcode":"24354",
    "sg:province":"VA",
    "sg:tags":[
        "contractor"
    ],
    "wof:name":"Custom Air Inc",
    "wof:placetype":"venue"
},
  "geometry": {"coordinates":[-81.570111,36.812583],"type":"Point"}
}