{
  "type": "Feature",
  "properties": {
    "addr:full":"2500 N Quantico St Arlington VA 22207",
    "addr:housenumber":"2500",
    "addr:postcode":"22207",
    "addr:street":"N Quantico St",
    "iso:country":"US",
    "sg:address":"2500 N Quantico St",
    "sg:city":"Arlington",
    "sg:classifiers":[
        {
            "category":"Professional",
            "subcategory":"Lawyer & Legal Services",
            "type":"Services"
        }
    ],
    "sg:phone":"+1 703 241 1227",
    "sg:postcode":"22207",
    "sg:province":"VA",
    "wof:name":"Donald C Weinberg PC",
    "wof:placetype":"venue"
},
  "geometry": {"coordinates":[-77.153834,38.893722],"type":"Point"}
}