{
  "type": "Feature",
  "properties": {
    "iso:country":"US",
    "sg:address":"7013 Manchester Blvd",
    "sg:city":"Franconia",
    "sg:classifiers":[
        {
            "category":"Restaurant",
            "type":"Food & Drink"
        }
    ],
    "sg:menulink":"http://www.allmenus.com/va/lee/163664-roy-rogers/menu/",
    "sg:phone":"+1 703 719 5980",
    "sg:postcode":"22310",
    "sg:province":"VA",
    "sg:tags":[
        "american"
    ],
    "wof:name":"Roy Rogers",
    "wof:placetype":"venue"
},
  "geometry": {"coordinates":[-77.15378800000001,38.764662],"type":"Point"}
}