{
  "type": "Feature",
  "properties": {
    "iso:country":"US",
    "sg:address":"124 Amherst St",
    "sg:city":"Winchester",
    "sg:classifiers":[
        {
            "category":"Social Services",
            "type":"Services"
        }
    ],
    "sg:phone":"+1 540 722 6130",
    "sg:postcode":"22601",
    "sg:province":"VA",
    "wof:name":"Stephanie Tracy",
    "wof:placetype":"venue"
},
  "geometry": {"coordinates":[-78.16719500000001,39.185568],"type":"Point"}
}