{
  "type": "Feature",
  "properties": {
    "addr:full":"395 Thomas Jefferson Hwy Charlotte Ct Hse VA 23923",
    "addr:housenumber":"395",
    "addr:postcode":"23923",
    "addr:street":"Thomas Jefferson Hwy Charlotte Ct",
    "iso:country":"US",
    "sg:address":"395 Thomas Jefferson Hwy",
    "sg:city":"Charlotte Ct Hse",
    "sg:classifiers":[
        {
            "category":"Social Services",
            "type":"Services"
        }
    ],
    "sg:phone":"+1 434 542 5607",
    "sg:postcode":"23923",
    "sg:province":"VA",
    "sg:tags":[
        "organization",
        "welfare"
    ],
    "wof:name":"Charter Oak Ctr",
    "wof:placetype":"venue"
},
  "geometry": {"coordinates":[-78.636155,37.070147],"type":"Point"}
}