{
  "type": "Feature",
  "properties": {
    "addr:full":"362 W Broad St Falls Church VA 22046",
    "addr:housenumber":"362",
    "addr:postcode":"22046",
    "addr:street":"W Broad St",
    "iso:country":"US",
    "sg:address":"362 W Broad St",
    "sg:city":"Falls Church",
    "sg:classifiers":[
        {
            "category":"Shopping",
            "subcategory":"Clothing, Apparel, & Fashions",
            "type":"Retail Goods"
        }
    ],
    "sg:phone":"+1 703 237 0010",
    "sg:postcode":"22046",
    "sg:province":"VA",
    "wof:name":"Bridal Visions",
    "wof:placetype":"venue"
},
  "geometry": {"coordinates":[-77.17411,38.884122],"type":"Point"}
}