{
  "type": "Feature",
  "properties": {
    "iso:country":"US",
    "sg:address":"2000 Peninsula Rd",
    "sg:city":"Virginia Beach",
    "sg:classifiers":[
        {
            "category":"Building & Trades",
            "subcategory":"Construction",
            "type":"Services"
        }
    ],
    "sg:phone":"+1 757 422 4378",
    "sg:postcode":"23451",
    "sg:province":"VA",
    "sg:tags":[
        "house"
    ],
    "wof:name":"Cjm Home Improvements",
    "wof:placetype":"venue"
},
  "geometry": {"coordinates":[-76.05690199999999,36.905383],"type":"Point"}
}