{
  "type": "Feature",
  "properties": {
    "addr:full":"3212 Victory Blvd Portsmouth VA 23702",
    "addr:housenumber":"3212",
    "addr:postcode":"23702",
    "addr:street":"Victory Blvd",
    "iso:country":"US",
    "sg:address":"3212 Victory Blvd",
    "sg:city":"Portsmouth",
    "sg:classifiers":[
        {
            "category":"Shopping",
            "subcategory":"Pharmacy",
            "type":"Retail Goods"
        }
    ],
    "sg:phone":"+1 757 485 1046",
    "sg:postcode":"23702",
    "sg:province":"VA",
    "sg:tags":[
        "drug",
        "store"
    ],
    "wof:name":"Medicine Shoppe The",
    "wof:placetype":"venue"
},
  "geometry": {"coordinates":[-76.348415,36.797421],"type":"Point"}
}