{
  "type": "Feature",
  "properties": {
    "addr:full":"18 E Washington St Middleburg VA 20117",
    "addr:housenumber":"18",
    "addr:postcode":"20117",
    "addr:street":"E Washington St",
    "iso:country":"US",
    "sg:address":"18 E Washington St",
    "sg:city":"Middleburg",
    "sg:classifiers":[
        {
            "category":"Real Estate",
            "subcategory":"Real Estate Agent",
            "type":"Services"
        }
    ],
    "sg:phone":"+1 540 687 3700",
    "sg:postcode":"20117",
    "sg:province":"VA",
    "sg:website":"www.whitecorealestate.com",
    "wof:name":"White & Co Real Estate Inc",
    "wof:placetype":"venue"
},
  "geometry": {"coordinates":[-77.73435600000001,38.969343],"type":"Point"}
}