{
  "type": "Feature",
  "properties": {
    "addr:full":"327 Main St South Boston VA 24592",
    "addr:housenumber":"327",
    "addr:postcode":"24592",
    "addr:street":"Main St",
    "iso:country":"US",
    "sg:address":"327 Main St",
    "sg:city":"South Boston",
    "sg:classifiers":[
        {
            "category":"Wholesale",
            "subcategory":"Electrical",
            "type":"Manufacturing & Wholesale Goods"
        }
    ],
    "sg:phone":"+1 434 572 4945",
    "sg:postcode":"24592",
    "sg:province":"VA",
    "sg:tags":[
        "electric",
        "motor"
    ],
    "wof:name":"Randolph John Motor Inn",
    "wof:placetype":"venue"
},
  "geometry": {"coordinates":[-78.901309,36.697471],"type":"Point"}
}