{
  "type": "Feature",
  "properties": {
    "iso:country":"US",
    "sg:address":"1435 Crossways Blvd",
    "sg:city":"Chesapeake",
    "sg:classifiers":[
        {
            "category":"Professional",
            "subcategory":"Engineering",
            "type":"Services"
        },
        {
            "category":"Professional",
            "subcategory":"Management & Consulting",
            "type":"Services"
        }
    ],
    "sg:phone":"+1 757 366 8731",
    "sg:postcode":"23320",
    "sg:province":"VA",
    "sg:tags":[
        "environmental",
        "computer",
        "engineer"
    ],
    "sg:website":"www.ensafe.com",
    "wof:name":"Ensafe Inc",
    "wof:placetype":"venue"
},
  "geometry": {"coordinates":[-76.245716,36.775783],"type":"Point"}
}