{
  "type": "Feature",
  "properties": {
    "addr:full":"12144 Washington Hwy Ashland VA 23005",
    "addr:housenumber":"12144",
    "addr:postcode":"23005",
    "addr:street":"Washington Hwy",
    "iso:country":"US",
    "sg:address":"12144 Washington Hwy",
    "sg:city":"Ashland",
    "sg:classifiers":[
        {
            "category":"Home & Garden",
            "subcategory":"Building Materials",
            "type":"Retail Goods"
        }
    ],
    "sg:phone":"+1 804 798 1514",
    "sg:postcode":"23005",
    "sg:province":"VA",
    "wof:name":"Carter Lumber",
    "wof:placetype":"venue"
},
  "geometry": {"coordinates":[-77.471052,37.73607],"type":"Point"}
}