{
  "type": "Feature",
  "properties": {
    "iso:country":"US",
    "sg:address":"1828 Memorial Ave SW",
    "sg:city":"Roanoke",
    "sg:classifiers":[
        {
            "category":"Food & Beverages",
            "subcategory":"Groceries & Convenience Stores",
            "type":"Retail Goods"
        }
    ],
    "sg:phone":"+1 540 982 7736",
    "sg:postcode":"24015",
    "sg:province":"VA",
    "sg:tags":[
        "product"
    ],
    "wof:name":"Stop In Food Stores, Inc.",
    "wof:placetype":"venue"
},
  "geometry": {"coordinates":[-79.97475900000001,37.266024],"type":"Point"}
}