{
  "type": "Feature",
  "properties": {
    "addr:full":"925 Graceland Ct Powhatan VA 23139",
    "addr:housenumber":"925",
    "addr:postcode":"23139",
    "addr:street":"Graceland Ct",
    "iso:country":"US",
    "sg:address":"925 Graceland Ct",
    "sg:city":"Powhatan",
    "sg:classifiers":[
        {
            "category":"Utilities",
            "subcategory":"Telephone",
            "type":"Services"
        }
    ],
    "sg:phone":"+1 804 839 0786",
    "sg:postcode":"23139",
    "sg:province":"VA",
    "sg:tags":[
        "internet"
    ],
    "wof:name":"Lighthouse Websnet LLC",
    "wof:placetype":"venue"
},
  "geometry": {"coordinates":[-77.820598,37.46321],"type":"Point"}
}