{
  "type": "Feature",
  "properties": {
    "iso:country":"US",
    "sg:address":"143 Washington St",
    "sg:city":"Warrenton",
    "sg:classifiers":[
        {
            "category":"Home & Garden",
            "subcategory":"Garden Supply",
            "type":"Retail Goods"
        },
        {
            "category":"Arts & Performance",
            "subcategory":"Arts Center",
            "type":"Entertainment"
        }
    ],
    "sg:phone":"+1 540 347 7100",
    "sg:postcode":"20186",
    "sg:province":"VA",
    "sg:tags":[
        "nursery",
        "gardening"
    ],
    "wof:name":"Warrenton Farmers Cooperative",
    "wof:placetype":"venue"
},
  "geometry": {"coordinates":[-77.793404,38.7076],"type":"Point"}
}