{
  "type": "Feature",
  "properties": {
    "addr:full":"3906 Greensboro Rd Ridgeway VA 24148",
    "addr:housenumber":"3906",
    "addr:postcode":"24148",
    "addr:street":"Greensboro Rd",
    "iso:country":"US",
    "sg:address":"3906 Greensboro Rd",
    "sg:city":"Ridgeway",
    "sg:classifiers":[
        {
            "category":"Food & Beverages",
            "subcategory":"Groceries & Convenience Stores",
            "type":"Retail Goods"
        }
    ],
    "sg:phone":"+1 276 632 1584",
    "sg:postcode":"24148",
    "sg:province":"VA",
    "wof:name":"Ideal Market",
    "wof:placetype":"venue"
},
  "geometry": {"coordinates":[-79.85969900000001,36.638002],"type":"Point"}
}