{
  "type": "Feature",
  "properties": {
    "addr:full":"2603 E Main St Richmond VA 23223",
    "addr:housenumber":"2603",
    "addr:postcode":"23223",
    "addr:street":"E Main St",
    "iso:country":"US",
    "sg:address":"2603 E Main St",
    "sg:city":"Richmond",
    "sg:classifiers":[
        {
            "category":"Restaurant",
            "type":"Food & Drink"
        }
    ],
    "sg:menulink":"http://www.allmenus.com/va/richmond/285199-millies-diner/menu/",
    "sg:phone":"+1 804 643 5512",
    "sg:postcode":"23223",
    "sg:province":"VA",
    "sg:tags":[
        "new",
        "american"
    ],
    "wof:name":"Millie's Diner",
    "wof:placetype":"venue"
},
  "geometry": {"coordinates":[-77.420329,37.528382],"type":"Point"}
}