{
  "type": "Feature",
  "properties": {
    "addr:full":"10705 Tiffin Ct Fairfax Station VA 22039",
    "addr:housenumber":"10705",
    "addr:postcode":"22039",
    "addr:street":"Tiffin Ct",
    "iso:country":"US",
    "sg:address":"10705 Tiffin Ct",
    "sg:city":"Fairfax Station",
    "sg:classifiers":[
        {
            "category":"Education",
            "subcategory":"School",
            "type":"Public Place"
        }
    ],
    "sg:phone":"+1 703 978 7905",
    "sg:postcode":"22039",
    "sg:province":"VA",
    "wof:name":"New World Bilingual Insti",
    "wof:placetype":"venue"
},
  "geometry": {"coordinates":[-77.315226,38.767696],"type":"Point"}
}