{
  "type": "Feature",
  "properties": {
    "addr:full":"1216 Perth Rd Nathalie VA 24577",
    "addr:housenumber":"1216",
    "addr:postcode":"24577",
    "addr:street":"Perth Rd",
    "iso:country":"US",
    "sg:address":"1216 Perth Rd",
    "sg:city":"Nathalie",
    "sg:classifiers":[
        {
            "category":"Restaurant",
            "type":"Food & Drink"
        }
    ],
    "sg:phone":"+1 434 376 3645",
    "sg:postcode":"24577",
    "sg:province":"VA",
    "sg:tags":[
        "independent",
        "family"
    ],
    "wof:name":"Grannys Restaurant",
    "wof:placetype":"venue"
},
  "geometry": {"coordinates":[-78.983851,37.011374],"type":"Point"}
}