{
  "type": "Feature",
  "properties": {
    "iso:country":"US",
    "sg:address":"1401 Overbrook Rd",
    "sg:city":"Richmond",
    "sg:classifiers":[
        {
            "category":"Recreation",
            "type":"Entertainment"
        },
        {
            "category":"Sports & Exercise",
            "subcategory":"Gym",
            "type":"Entertainment"
        }
    ],
    "sg:phone":"+1 804 358 0251",
    "sg:postcode":"23220",
    "sg:province":"VA",
    "sg:tags":[
        "fitness",
        "physical",
        "gymnasium",
        "facility"
    ],
    "wof:name":"Citywide Boxing Club",
    "wof:placetype":"venue"
},
  "geometry": {"coordinates":[-77.454539,37.56534],"type":"Point"}
}