{
  "type": "Feature",
  "properties": {
    "addr:full":"1132 W Broad St Falls Church VA 22046",
    "addr:housenumber":"1132",
    "addr:postcode":"22046",
    "addr:street":"W Broad St",
    "iso:country":"US",
    "sg:address":"1132 W Broad St",
    "sg:city":"Falls Church",
    "sg:classifiers":[
        {
            "category":"Retail",
            "subcategory":"Auto Repair",
            "type":"Services"
        }
    ],
    "sg:phone":"+1 703 532 3500",
    "sg:postcode":"22046",
    "sg:province":"VA",
    "sg:tags":[
        "general"
    ],
    "wof:name":"Valvoline Express Care",
    "wof:placetype":"venue"
},
  "geometry": {"coordinates":[-77.187136,38.892556],"type":"Point"}
}