{
  "type": "Feature",
  "properties": {
    "iso:country":"US",
    "sg:address":"2064 Link Puryear Rd",
    "sg:city":"South Boston",
    "sg:classifiers":[
        {
            "category":"Building & Trades",
            "subcategory":"Construction",
            "type":"Services"
        }
    ],
    "sg:phone":"+1 434 575 2392",
    "sg:postcode":"24592",
    "sg:province":"NC",
    "sg:tags":[
        "contractor"
    ],
    "wof:name":"Mid-Atlantic Insulating Servic",
    "wof:placetype":"venue"
},
  "geometry": {"coordinates":[-78.948263,36.625819],"type":"Point"}
}