{
  "type": "Feature",
  "properties": {
    "addr:full":"2800 W Main St Salem VA 24153",
    "addr:housenumber":"2800",
    "addr:postcode":"24153",
    "addr:street":"W Main St",
    "iso:country":"US",
    "sg:address":"2800 W Main St",
    "sg:city":"Salem",
    "sg:classifiers":[
        {
            "category":"Wholesale",
            "subcategory":"Durable Goods & Equipment",
            "type":"Manufacturing & Wholesale Goods"
        }
    ],
    "sg:phone":"+1 540 375 3808",
    "sg:postcode":"24153",
    "sg:province":"VA",
    "wof:name":"Salem Candle Supply",
    "wof:placetype":"venue"
},
  "geometry": {"coordinates":[-80.108369,37.281694],"type":"Point"}
}