{
  "type": "Feature",
  "properties": {
    "addr:full":"9320 Lee Ave Manassas VA 20110",
    "addr:housenumber":"9320",
    "addr:postcode":"20110",
    "addr:street":"Lee Ave",
    "iso:country":"US",
    "sg:address":"9320 Lee Ave",
    "sg:city":"Manassas",
    "sg:classifiers":[
        {
            "category":"Government",
            "subcategory":"Office",
            "type":"Public Place"
        }
    ],
    "sg:phone":"+1 703 792 6420",
    "sg:postcode":"20110",
    "sg:province":"VA",
    "wof:name":"Prince William Adult Detention",
    "wof:placetype":"venue"
},
  "geometry": {"coordinates":[-77.478549,38.751817],"type":"Point"}
}