{
  "type": "Feature",
  "properties": {
    "addr:full":"1500 King College Rd Bristol VA 37620",
    "addr:housenumber":"1500",
    "addr:postcode":"37620",
    "addr:street":"King College Rd",
    "iso:country":"US",
    "sg:address":"1500 King College Rd",
    "sg:city":"Bristol",
    "sg:classifiers":[
        {
            "category":"Food & Beverages",
            "subcategory":"Groceries & Convenience Stores",
            "type":"Retail Goods"
        }
    ],
    "sg:phone":"+1 423 968 7923",
    "sg:postcode":"37620",
    "sg:province":"VA",
    "sg:tags":[
        "grocer"
    ],
    "wof:name":"King College Mart",
    "wof:placetype":"venue"
},
  "geometry": {"coordinates":[-82.15218,36.585052],"type":"Point"}
}