{
  "type": "Feature",
  "properties": {
    "addr:full":"4004 Cedarwood Ln Williamsburg VA 23188",
    "addr:housenumber":"4004",
    "addr:postcode":"23188",
    "addr:street":"Cedarwood Ln",
    "iso:country":"US",
    "sg:address":"4004 Cedarwood Ln",
    "sg:city":"Williamsburg",
    "sg:classifiers":[
        {
            "category":"Building & Trades",
            "subcategory":"Construction",
            "type":"Services"
        }
    ],
    "sg:phone":"+1 757 229 0814",
    "sg:postcode":"23188",
    "sg:province":"VA",
    "sg:tags":[
        "house"
    ],
    "wof:name":"Bruce Home Improvement",
    "wof:placetype":"venue"
},
  "geometry": {"coordinates":[-76.780801,37.281421],"type":"Point"}
}