{
  "type": "Feature",
  "properties": {
    "addr:full":"231 E Church St Martinsville VA 24112",
    "addr:housenumber":"231",
    "addr:postcode":"24112",
    "addr:street":"E Church St",
    "iso:country":"US",
    "sg:address":"231 E Church St",
    "sg:city":"Martinsville",
    "sg:classifiers":[
        {
            "category":"Banks & Credit Unions",
            "subcategory":"Bank",
            "type":"Services"
        }
    ],
    "sg:phone":"+1 276 666 0528",
    "sg:postcode":"24112",
    "sg:province":"VA",
    "wof:name":"Fidelity Bank",
    "wof:placetype":"venue"
},
  "geometry": {"coordinates":[-79.868043,36.689859],"type":"Point"}
}