{
  "type": "Feature",
  "properties": {
    "iso:country":"US",
    "sg:address":"6105 Covered Bridge Rd",
    "sg:city":"Burke",
    "sg:classifiers":[
        {
            "category":"Food & Beverages",
            "subcategory":"Specialty",
            "type":"Retail Goods"
        }
    ],
    "sg:phone":"+1 703 978 4907",
    "sg:postcode":"22015",
    "sg:province":"VA",
    "wof:name":"K&Y Foods Inc",
    "wof:placetype":"venue"
},
  "geometry": {"coordinates":[-77.274665,38.785029],"type":"Point"}
}