{
  "type": "Feature",
  "properties": {
    "addr:full":"510 Research Rd Richmond VA 23236",
    "addr:housenumber":"510",
    "addr:postcode":"23236",
    "addr:street":"Research Rd",
    "iso:country":"US",
    "sg:address":"510 Research Rd",
    "sg:city":"Richmond",
    "sg:classifiers":[
        {
            "category":"Shopping",
            "subcategory":"Pets & Pet Supplies",
            "type":"Retail Goods"
        }
    ],
    "sg:phone":"+1 804 794 7698",
    "sg:postcode":"23236",
    "sg:province":"VA",
    "sg:tags":[
        "furnishing",
        "dog",
        "store",
        "cat"
    ],
    "wof:name":"Pets",
    "wof:placetype":"venue"
},
  "geometry": {"coordinates":[-77.60105,37.499539],"type":"Point"}
}