{
  "type": "Feature",
  "properties": {
    "addr:full":"1431 Candlewood St Fredericksburg VA 22407",
    "addr:housenumber":"1431",
    "addr:postcode":"22407",
    "addr:street":"Candlewood St",
    "iso:country":"US",
    "sg:address":"1431 Candlewood St",
    "sg:city":"Fredericksburg",
    "sg:classifiers":[
        {
            "category":"Professional",
            "subcategory":"Management & Consulting",
            "type":"Services"
        }
    ],
    "sg:phone":"+1 540 786 2428",
    "sg:postcode":"22407",
    "sg:province":"VA",
    "sg:tags":[
        "enforcement",
        "law"
    ],
    "wof:name":"Richard R Weart",
    "wof:placetype":"venue"
},
  "geometry": {"coordinates":[-77.533467,38.298143],"type":"Point"}
}