{
  "type": "Feature",
  "properties": {
    "iso:country":"US",
    "sg:address":"5317 Denver Dr",
    "sg:city":"Virginia Beach",
    "sg:classifiers":[
        {
            "category":"Health Services",
            "subcategory":"Doctor",
            "type":"Services"
        }
    ],
    "sg:phone":"+1 757 479 4866",
    "sg:postcode":"23464",
    "sg:province":"VA",
    "sg:tags":[
        "ophthalmic"
    ],
    "wof:name":"Raquel D White",
    "wof:placetype":"venue"
},
  "geometry": {"coordinates":[-76.18530199999999,36.774764],"type":"Point"}
}