{
  "type": "Feature",
  "properties": {
    "addr:full":"24 Woodland Dr Staunton VA 24401",
    "addr:housenumber":"24",
    "addr:postcode":"24401",
    "addr:street":"Woodland Dr",
    "iso:country":"US",
    "sg:address":"24 Woodland Dr",
    "sg:city":"Staunton",
    "sg:classifiers":[
        {
            "category":"Health Services",
            "subcategory":"Doctor",
            "type":"Services"
        }
    ],
    "sg:phone":"+1 540 886 8905",
    "sg:postcode":"24401",
    "sg:province":"VA",
    "sg:tags":[
        "medical"
    ],
    "wof:name":"Malcolm Tenney Dr",
    "wof:placetype":"venue"
},
  "geometry": {"coordinates":[-79.059704,38.169582],"type":"Point"}
}