{
  "type": "Feature",
  "properties": {
    "addr:full":"9 S Commerce Ave Front Royal VA 22630",
    "addr:housenumber":"9",
    "addr:postcode":"22630",
    "addr:street":"S Commerce Ave",
    "iso:country":"US",
    "sg:address":"9 S Commerce Ave",
    "sg:city":"Front Royal",
    "sg:classifiers":[
        {
            "category":"Autos & Motor Vehicles",
            "subcategory":"Automobile Sales",
            "type":"Retail Goods"
        }
    ],
    "sg:phone":"+1 540 635 2156",
    "sg:postcode":"22630",
    "sg:province":"VA",
    "sg:tags":[
        "car",
        "dealer"
    ],
    "wof:name":"Jack Evans Chevrolet Cadillac",
    "wof:placetype":"venue"
},
  "geometry": {"coordinates":[-78.186728,38.917117],"type":"Point"}
}