{
  "type": "Feature",
  "properties": {
    "iso:country":"US",
    "sg:address":"8549 Old Dominion Dr",
    "sg:city":"Mc Lean",
    "sg:classifiers":[
        {
            "category":"Banks & Credit Unions",
            "subcategory":"Investment Brokerage",
            "type":"Services"
        },
        {
            "category":"Building & Trades",
            "subcategory":"Equipment Rental",
            "type":"Services"
        }
    ],
    "sg:phone":"+1 703 448 3330",
    "sg:postcode":"22102",
    "sg:province":"VA",
    "sg:tags":[
        "banking",
        "leasing"
    ],
    "wof:name":"Anderson Funding Group Ltd",
    "wof:placetype":"venue"
},
  "geometry": {"coordinates":[-77.24087299999999,38.961436],"type":"Point"}
}