{
  "type": "Feature",
  "properties": {
    "addr:full":"11402 Jefferson Davis Hwy Chester VA 23831",
    "addr:housenumber":"11402",
    "addr:postcode":"23831",
    "addr:street":"Jefferson Davis Hwy",
    "iso:country":"US",
    "sg:address":"11402 Jefferson Davis Hwy",
    "sg:city":"Chester",
    "sg:classifiers":[
        {
            "category":"Sports & Exercise",
            "subcategory":"Golf",
            "type":"Entertainment"
        }
    ],
    "sg:phone":"+1 804 751 9800",
    "sg:postcode":"23831",
    "sg:province":"VA",
    "sg:tags":[
        "course",
        "public"
    ],
    "wof:name":"Holiday Golf Driving Range",
    "wof:placetype":"venue"
},
  "geometry": {"coordinates":[-77.418401,37.371618],"type":"Point"}
}