{
  "type": "Feature",
  "properties": {
    "iso:country":"US",
    "sg:address":"23035 Douglas Ct",
    "sg:city":"Sterling",
    "sg:classifiers":[
        {
            "category":"Insurance",
            "subcategory":"Insurance Agent",
            "type":"Services"
        }
    ],
    "sg:phone":"+1 703 834 3120",
    "sg:postcode":"20166",
    "sg:province":"VA",
    "sg:tags":[
        "agency"
    ],
    "wof:name":"Downs & Associates Inc",
    "wof:placetype":"venue"
},
  "geometry": {"coordinates":[-77.414996,38.977968],"type":"Point"}
}