{
  "type": "Feature",
  "properties": {
    "addr:full":"1401 N Glebe Rd Arlington VA 22207",
    "addr:housenumber":"1401",
    "addr:postcode":"22207",
    "addr:street":"N Glebe Rd",
    "iso:country":"US",
    "sg:address":"1401 N Glebe Rd",
    "sg:city":"Arlington",
    "sg:classifiers":[
        {
            "category":"Building & Trades",
            "subcategory":"Construction",
            "type":"Services"
        }
    ],
    "sg:phone":"+1 703 522 3093",
    "sg:postcode":"22207",
    "sg:province":"VA",
    "sg:tags":[
        "house",
        "nonresidential"
    ],
    "wof:name":"Walker Construction",
    "wof:placetype":"venue"
},
  "geometry": {"coordinates":[-77.11872099999999,38.888533],"type":"Point"}
}