{
  "type": "Feature",
  "properties": {
    "iso:country":"US",
    "sg:address":"10325 Warwick Blvd",
    "sg:city":"Newport News",
    "sg:classifiers":[
        {
            "category":"Personal",
            "type":"Services"
        }
    ],
    "sg:phone":"+1 757 596 0951",
    "sg:postcode":"23601",
    "sg:province":"VA",
    "sg:tags":[
        "wear",
        "formal"
    ],
    "wof:name":"Beecroft & Bull LTD",
    "wof:placetype":"venue"
},
  "geometry": {"coordinates":[-76.462408,37.033468],"type":"Point"}
}