{
  "type": "Feature",
  "properties": {
    "addr:full":"11600 New Bond St Fredericksburg VA 22408",
    "addr:housenumber":"11600",
    "addr:postcode":"22408",
    "addr:street":"New Bond St",
    "iso:country":"US",
    "sg:address":"11600 New Bond St",
    "sg:city":"Fredericksburg",
    "sg:classifiers":[
        {
            "category":"Professional",
            "subcategory":"Management & Consulting",
            "type":"Services"
        }
    ],
    "sg:phone":"+1 540 891 0360",
    "sg:postcode":"22408",
    "sg:province":"VA",
    "sg:tags":[
        "communication",
        "consultant"
    ],
    "wof:name":"Dinkle Telecommunication Inc",
    "wof:placetype":"venue"
},
  "geometry": {"coordinates":[-77.503691,38.275417],"type":"Point"}
}