{
  "type": "Feature",
  "properties": {
    "addr:full":"24788 Shells Way Aldie VA 20152",
    "addr:housenumber":"24788",
    "addr:postcode":"20152",
    "addr:street":"Shells Way",
    "iso:country":"US",
    "sg:address":"24788 Shells Way",
    "sg:city":"Aldie",
    "sg:classifiers":[
        {
            "category":"Professional",
            "subcategory":"Management & Consulting",
            "type":"Services"
        }
    ],
    "sg:phone":"+1 703 542 5928",
    "sg:postcode":"20152",
    "sg:province":"VA",
    "sg:tags":[
        "pharmaceutical",
        "consultant"
    ],
    "wof:name":"Business Research Services",
    "wof:placetype":"venue"
},
  "geometry": {"coordinates":[-77.55406000000001,38.930799],"type":"Point"}
}