{
  "type": "Feature",
  "properties": {
    "addr:full":"4455 Starling Ct Woodbridge VA 22193",
    "addr:housenumber":"4455",
    "addr:postcode":"22193",
    "addr:street":"Starling Ct",
    "iso:country":"US",
    "sg:address":"4455 Starling Ct",
    "sg:city":"Woodbridge",
    "sg:classifiers":[
        {
            "category":"Personal",
            "type":"Services"
        }
    ],
    "sg:phone":"+1 703 878 3545",
    "sg:postcode":"22193",
    "sg:province":"VA",
    "wof:name":"Golden Fingers Mssg Thrp LLC",
    "wof:placetype":"venue"
},
  "geometry": {"coordinates":[-77.34481,38.629701],"type":"Point"}
}