{
  "type": "Feature",
  "properties": {
    "addr:full":"10330 Main St Fairfax VA 22030",
    "addr:housenumber":"10330",
    "addr:postcode":"22030",
    "addr:street":"Main St",
    "iso:country":"US",
    "sg:address":"10330 Main St",
    "sg:city":"Fairfax",
    "sg:classifiers":[
        {
            "category":"Education",
            "subcategory":"Special Training",
            "type":"Public Place"
        }
    ],
    "sg:phone":"+1 703 383 9641",
    "sg:postcode":"22030",
    "sg:province":"VA",
    "sg:tags":[
        "tutoring"
    ],
    "sg:website":"www.escore.com",
    "wof:name":"Score! Educational Ctr",
    "wof:placetype":"venue"
},
  "geometry": {"coordinates":[-77.302252,38.845316],"type":"Point"}
}