{
  "type": "Feature",
  "properties": {
    "iso:country":"US",
    "sg:address":"6401 Centralia Rd",
    "sg:city":"Chesterfield",
    "sg:classifiers":[
        {
            "category":"Food & Beverages",
            "subcategory":"Groceries & Convenience Stores",
            "type":"Retail Goods"
        }
    ],
    "sg:phone":"+1 804 796 1120",
    "sg:postcode":"23832",
    "sg:province":"VA",
    "sg:tags":[
        "equipment"
    ],
    "wof:name":"Ukrops Super Market 490",
    "wof:placetype":"venue"
},
  "geometry": {"coordinates":[-77.499259,37.373703],"type":"Point"}
}