{
  "type": "Feature",
  "properties": {
    "addr:full":"2000 N Clarendon Blvd Arlington VA 22201",
    "addr:housenumber":"2000",
    "addr:postcode":"22201",
    "addr:street":"N Clarendon Blvd",
    "iso:country":"US",
    "sg:address":"2000 N Clarendon Blvd",
    "sg:city":"Arlington",
    "sg:classifiers":[
        {
            "category":"Professional",
            "subcategory":"Research",
            "type":"Services"
        }
    ],
    "sg:phone":"+1 703 243 2100",
    "sg:postcode":"22201",
    "sg:province":"VA",
    "sg:tags":[
        "educational"
    ],
    "sg:website":"www.ers.org",
    "wof:name":"Educational Research Service",
    "wof:placetype":"venue"
},
  "geometry": {"coordinates":[-77.08394800000001,38.891482],"type":"Point"}
}