{
  "type": "Feature",
  "properties": {
    "iso:country":"US",
    "sg:address":"274 Parkway Ln S",
    "sg:city":"Floyd",
    "sg:classifiers":[
        {
            "category":"Building & Trades",
            "subcategory":"Construction",
            "type":"Services"
        }
    ],
    "sg:phone":"+1 540 382 1056",
    "sg:postcode":"24091",
    "sg:province":"VA",
    "sg:tags":[
        "designer"
    ],
    "wof:name":"Journey Designs LLC",
    "wof:placetype":"venue"
},
  "geometry": {"coordinates":[-80.31750599999999,36.90261],"type":"Point"}
}