{
  "type": "Feature",
  "properties": {
    "addr:full":"1157 Kesler Rd Front Royal VA 22630",
    "addr:housenumber":"1157",
    "addr:postcode":"22630",
    "addr:street":"Kesler Rd",
    "iso:country":"US",
    "sg:address":"1157 Kesler Rd",
    "sg:city":"Front Royal",
    "sg:classifiers":[
        {
            "category":"Farming",
            "subcategory":"Farm",
            "type":"Manufacturing & Wholesale Goods"
        }
    ],
    "sg:phone":"+1 540 635 3693",
    "sg:postcode":"22630",
    "sg:province":"VA",
    "wof:name":"Riverview Farms",
    "wof:placetype":"venue"
},
  "geometry": {"coordinates":[-78.214136,38.943107],"type":"Point"}
}