{
  "type": "Feature",
  "properties": {
    "addr:full":"2320 Cherry Hill Farm Charlottesville VA 22903",
    "addr:housenumber":"2320",
    "addr:postcode":"22903",
    "addr:street":"Cherry Hill",
    "iso:country":"US",
    "sg:address":"2320 Cherry Hill Farm",
    "sg:city":"Charlottesville",
    "sg:classifiers":[
        {
            "category":"Farming",
            "subcategory":"Farm",
            "type":"Manufacturing & Wholesale Goods"
        }
    ],
    "sg:phone":"+1 434 295 5885",
    "sg:postcode":"22903",
    "sg:province":"VA",
    "wof:name":"Cherry Hill Farm",
    "wof:placetype":"venue"
},
  "geometry": {"coordinates":[-78.574151,38.04702],"type":"Point"}
}