{
  "type": "Feature",
  "properties": {
    "addr:full":"38978 Goose Creek Ln Leesburg VA 20175",
    "addr:housenumber":"38978",
    "addr:postcode":"20175",
    "addr:street":"Goose Creek Ln",
    "iso:country":"US",
    "sg:address":"38978 Goose Creek Ln",
    "sg:city":"Leesburg",
    "sg:classifiers":[
        {
            "category":"Farming",
            "subcategory":"Farm",
            "type":"Manufacturing & Wholesale Goods"
        }
    ],
    "sg:phone":"+1 703 777 3312",
    "sg:postcode":"20175",
    "sg:province":"VA",
    "sg:tags":[
        "crop",
        "general"
    ],
    "wof:name":"Old Orchard Farm",
    "wof:placetype":"venue"
},
  "geometry": {"coordinates":[-77.656026,39.036979],"type":"Point"}
}