{
  "type": "Feature",
  "properties": {
    "iso:country":"US",
    "sg:address":"6505 Cavalier Dr",
    "sg:city":"Alexandria",
    "sg:classifiers":[
        {
            "category":"Professional",
            "subcategory":"Engineering",
            "type":"Services"
        }
    ],
    "sg:phone":"+1 434 432 1063",
    "sg:postcode":"22307",
    "sg:province":"VA",
    "wof:name":"Medaglia Engineering Corp",
    "wof:placetype":"venue"
},
  "geometry": {"coordinates":[-77.06912,38.777645],"type":"Point"}
}