{
  "type": "Feature",
  "properties": {
    "addr:full":"106 Wadsworth St Radford VA 24141",
    "addr:housenumber":"106",
    "addr:postcode":"24141",
    "addr:street":"Wadsworth St",
    "iso:country":"US",
    "sg:address":"106 Wadsworth St",
    "sg:city":"Radford",
    "sg:classifiers":[
        {
            "category":"Health Services",
            "subcategory":"Doctor",
            "type":"Services"
        }
    ],
    "sg:phone":"+1 540 639 9023",
    "sg:postcode":"24141",
    "sg:province":"VA",
    "sg:tags":[
        "physician",
        "surgeon"
    ],
    "wof:name":"Southwestern Va Ear Nose",
    "wof:placetype":"venue"
},
  "geometry": {"coordinates":[-80.57869100000001,37.131792],"type":"Point"}
}