{
  "type": "Feature",
  "properties": {
    "iso:country":"US",
    "sg:address":"317 Riverside Dr",
    "sg:city":"Yorktown",
    "sg:classifiers":[
        {
            "category":"Professional",
            "subcategory":"Management & Consulting",
            "type":"Services"
        }
    ],
    "sg:phone":"+1 757 989 5398",
    "sg:postcode":"23692",
    "sg:province":"VA",
    "sg:tags":[
        "organization",
        "image"
    ],
    "wof:name":"Shaw Sandra S",
    "wof:placetype":"venue"
},
  "geometry": {"coordinates":[-76.441737,37.144978],"type":"Point"}
}