{
  "type": "Feature",
  "properties": {
    "addr:full":"3057 Nutley St Ste 151 Fairfax VA 22031",
    "addr:housenumber":"3057",
    "addr:postcode":"22031",
    "addr:street":"Nutley St Ste 151",
    "iso:country":"US",
    "sg:address":"3057 Nutley St Ste 151",
    "sg:city":"Fairfax",
    "sg:classifiers":[
        {
            "category":"Retail",
            "subcategory":"Repair Shop",
            "type":"Services"
        }
    ],
    "sg:phone":"+1 703 319 7600",
    "sg:postcode":"22031",
    "sg:province":"VA",
    "sg:tags":[
        "television",
        "radio-service"
    ],
    "wof:name":"High Tech Tv",
    "wof:placetype":"venue"
},
  "geometry": {"coordinates":[-77.263138,38.869099],"type":"Point"}
}