{
  "type": "Feature",
  "properties": {
    "iso:country":"US",
    "sg:address":"A FREE SERVICE",
    "sg:city":"Richmond",
    "sg:classifiers":[
        {
            "category":"Insurance",
            "subcategory":"Hazard Insurance",
            "type":"Services"
        }
    ],
    "sg:phone":"+1 206 600 2360",
    "sg:postcode":"23234",
    "sg:province":"VA",
    "sg:website":"http://bestinsurancequotes.synthasite.com/get-quotes.php",
    "wof:name":"Best Insurance Quotes",
    "wof:placetype":"venue"
},
  "geometry": {"coordinates":[-77.486771,37.460474],"type":"Point"}
}