{
  "type": "Feature",
  "properties": {
    "addr:full":"770 Winding Way Rd Lynchburg VA 24502",
    "addr:housenumber":"770",
    "addr:postcode":"24502",
    "addr:street":"Winding Way Rd",
    "iso:country":"US",
    "sg:address":"770 Winding Way Rd",
    "sg:city":"Lynchburg",
    "sg:classifiers":[
        {
            "category":"Health Services",
            "subcategory":"Doctor",
            "type":"Services"
        }
    ],
    "sg:phone":"+1 434 832 0632",
    "sg:postcode":"24502",
    "sg:province":"VA",
    "sg:tags":[
        "medical"
    ],
    "wof:name":"Drs Resourcing Design",
    "wof:placetype":"venue"
},
  "geometry": {"coordinates":[-79.254971,37.354384],"type":"Point"}
}