{
  "type": "Feature",
  "properties": {
    "iso:country":"US",
    "sg:address":"405 S Parliament Dr",
    "sg:city":"Virginia Beach",
    "sg:classifiers":[
        {
            "category":"Social Services",
            "type":"Services"
        }
    ],
    "sg:phone":"+1 757 490 9627",
    "sg:postcode":"23462",
    "sg:province":"VA",
    "sg:website":"www.fightms.com",
    "wof:name":"National Multiple Sclerosis",
    "wof:placetype":"venue"
},
  "geometry": {"coordinates":[-76.16944100000001,36.827795],"type":"Point"}
}