{
  "type": "Feature",
  "properties": {
    "addr:full":"124 Campbell Ave SW Roanoke VA 24011",
    "addr:housenumber":"124",
    "addr:postcode":"24011",
    "addr:street":"Campbell Ave Sw",
    "iso:country":"US",
    "sg:address":"124 Campbell Ave SW",
    "sg:city":"Roanoke",
    "sg:classifiers":[
        {
            "category":"Personal",
            "type":"Services"
        }
    ],
    "sg:phone":"+1 540 342 4334",
    "sg:postcode":"24011",
    "sg:province":"VA",
    "sg:tags":[
        "control",
        "weight"
    ],
    "wof:name":"Health Unlimited",
    "wof:placetype":"venue"
},
  "geometry": {"coordinates":[-79.943934,37.271657],"type":"Point"}
}