{
  "type": "Feature",
  "properties": {
    "iso:country":"US",
    "sg:address":"137 Fleming St",
    "sg:city":"Fredericksburg",
    "sg:classifiers":[
        {
            "category":"Autos & Motor Vehicles",
            "subcategory":"Auto Supplies",
            "type":"Retail Goods"
        },
        {
            "category":"Retail",
            "subcategory":"Auto Repair",
            "type":"Services"
        }
    ],
    "sg:phone":"+1 540 604 5843",
    "sg:postcode":"22408",
    "sg:province":"VA",
    "sg:tags":[
        "tire"
    ],
    "wof:name":"Action Mobile and Auto TRUCK Repair",
    "wof:placetype":"venue"
},
  "geometry": {"coordinates":[-77.49684999999999,38.263297],"type":"Point"}
}