{
  "type": "Feature",
  "properties": {
    "addr:full":"22490 Penola Rd Ruther Glen VA 22546",
    "addr:housenumber":"22490",
    "addr:postcode":"22546",
    "addr:street":"Penola Rd",
    "iso:country":"US",
    "sg:address":"22490 Penola Rd",
    "sg:city":"Ruther Glen",
    "sg:classifiers":[
        {
            "category":"Building & Trades",
            "subcategory":"Construction",
            "type":"Services"
        }
    ],
    "sg:phone":"+1 804 633 7888",
    "sg:postcode":"22546",
    "sg:province":"VA",
    "sg:tags":[
        "heavy"
    ],
    "wof:name":"Mattaponi Springs Golf Club",
    "wof:placetype":"venue"
},
  "geometry": {"coordinates":[-77.365236,37.953764],"type":"Point"}
}