{
  "type": "Feature",
  "properties": {
    "addr:full":"1190 N Laburnum Ave Richmond VA 23223",
    "addr:housenumber":"1190",
    "addr:postcode":"23223",
    "addr:street":"N Laburnum Ave",
    "iso:country":"US",
    "sg:address":"1190 N Laburnum Ave",
    "sg:city":"Richmond",
    "sg:classifiers":[
        {
            "category":"Restaurant",
            "type":"Food & Drink"
        }
    ],
    "sg:phone":"+1 804 643 4903",
    "sg:postcode":"23223",
    "sg:province":"VA",
    "wof:name":"Cafe 297",
    "wof:placetype":"venue"
},
  "geometry": {"coordinates":[-77.37483,37.559903],"type":"Point"}
}