{
  "type": "Feature",
  "properties": {
    "addr:full":"3117 W Clay St Richmond VA 23230",
    "addr:housenumber":"3117",
    "addr:postcode":"23230",
    "addr:street":"W Clay St",
    "iso:country":"US",
    "sg:address":"3117 W Clay St",
    "sg:city":"Richmond",
    "sg:classifiers":[
        {
            "category":"Education",
            "subcategory":"Vocational School",
            "type":"Public Place"
        }
    ],
    "sg:phone":"+1 804 358 3111",
    "sg:postcode":"23230",
    "sg:province":"VA",
    "sg:tags":[
        "training",
        "computer"
    ],
    "wof:name":"ACT Certified Consultants-Va",
    "wof:placetype":"venue"
},
  "geometry": {"coordinates":[-77.472791,37.567251],"type":"Point"}
}