{
  "type": "Feature",
  "properties": {
    "iso:country":"US",
    "sg:address":"20430 Virgil H Goode Hwy",
    "sg:city":"Rocky Mount",
    "sg:classifiers":[
        {
            "category":"Restaurant",
            "type":"Food & Drink"
        },
        {
            "category":"Ice Cream",
            "type":"Food & Drink"
        }
    ],
    "sg:menulink":"http://www.allmenus.com/va/boone/192606-dairy-queen/menu/",
    "sg:phone":"+1 540 334 2977",
    "sg:postcode":"24151",
    "sg:province":"VA",
    "sg:tags":[
        "burger",
        "american",
        "ice",
        "cream"
    ],
    "wof:name":"Dairy Queen",
    "wof:placetype":"venue"
},
  "geometry": {"coordinates":[-79.900301,37.072385],"type":"Point"}
}