{
  "type": "Feature",
  "properties": {
    "addr:full":"241 Gimlet Ridge Rd Bentonville VA 22610",
    "addr:housenumber":"241",
    "addr:postcode":"22610",
    "addr:street":"Gimlet Ridge Rd",
    "iso:country":"US",
    "sg:address":"241 Gimlet Ridge Rd",
    "sg:city":"Bentonville",
    "sg:classifiers":[
        {
            "category":"Real Estate",
            "subcategory":"Real Estate Agent",
            "type":"Services"
        }
    ],
    "sg:phone":"+1 540 635 8429",
    "sg:postcode":"22610",
    "sg:province":"VA",
    "wof:name":"Gimlet Ridge Property Owners",
    "wof:placetype":"venue"
},
  "geometry": {"coordinates":[-78.275131,38.812216],"type":"Point"}
}