{
  "type": "Feature",
  "properties": {
    "iso:country":"US",
    "sg:address":"953 Boughton Way",
    "sg:city":"Virginia Beach",
    "sg:classifiers":[
        {
            "category":"Building & Trades",
            "subcategory":"Construction",
            "type":"Services"
        }
    ],
    "sg:phone":"+1 757 468 6400",
    "sg:postcode":"23453",
    "sg:province":"VA",
    "sg:tags":[
        "hanging",
        "contractor"
    ],
    "wof:name":"Lemaster Painting",
    "wof:placetype":"venue"
},
  "geometry": {"coordinates":[-76.067868,36.807209],"type":"Point"}
}