{
  "type": "Feature",
  "properties": {
    "addr:full":"890 Forrest St Charlottesville VA 22903",
    "addr:housenumber":"890",
    "addr:postcode":"22903",
    "addr:street":"Forrest St",
    "iso:country":"US",
    "sg:address":"890 Forrest St",
    "sg:city":"Charlottesville",
    "sg:classifiers":[
        {
            "category":"Government",
            "subcategory":"Office",
            "type":"Public Place"
        }
    ],
    "sg:phone":"+1 434 924 6832",
    "sg:postcode":"22903",
    "sg:province":"VA",
    "sg:tags":[
        "national",
        "security"
    ],
    "wof:name":"Air Force Rotc",
    "wof:placetype":"venue"
},
  "geometry": {"coordinates":[-78.48622899999999,38.037628],"type":"Point"}
}