{
  "type": "Feature",
  "properties": {
    "iso:country":"US",
    "sg:address":"1420 N Parham Rd",
    "sg:city":"Richmond",
    "sg:classifiers":[
        {
            "category":"Restaurant",
            "type":"Food & Drink"
        }
    ],
    "sg:menulink":"http://www.allmenus.com/va/tuckahoe/147799-subway/menu/",
    "sg:phone":"+1 804 740 3487",
    "sg:postcode":"23229",
    "sg:province":"VA",
    "sg:tags":[
        "american",
        "sandwich"
    ],
    "wof:name":"Subway",
    "wof:placetype":"venue"
},
  "geometry": {"coordinates":[-77.563902,37.600272],"type":"Point"}
}