{
  "type": "Feature",
  "properties": {
    "addr:full":"8648 Burnside Ct Manassas VA 20111",
    "addr:housenumber":"8648",
    "addr:postcode":"20111",
    "addr:street":"Burnside Ct",
    "iso:country":"US",
    "sg:address":"8648 Burnside Ct",
    "sg:city":"Manassas",
    "sg:classifiers":[
        {
            "category":"Recreation",
            "type":"Entertainment"
        }
    ],
    "sg:phone":"+1 703 330 8765",
    "sg:postcode":"20111",
    "sg:province":"VA",
    "sg:tags":[
        "club",
        "membership"
    ],
    "wof:name":"Outlook Recreation Association",
    "wof:placetype":"venue"
},
  "geometry": {"coordinates":[-77.44739800000001,38.769301],"type":"Point"}
}