{
  "type": "Feature",
  "properties": {
    "iso:country":"US",
    "sg:address":"1104 Amherst St",
    "sg:city":"Winchester",
    "sg:classifiers":[
        {
            "category":"Insurance",
            "subcategory":"Insurance Agent",
            "type":"Services"
        }
    ],
    "sg:phone":"+1 540 662 3865",
    "sg:postcode":"22601",
    "sg:province":"VA",
    "wof:name":"F & M J Amherst Insurance",
    "wof:placetype":"venue"
},
  "geometry": {"coordinates":[-78.181697,39.189586],"type":"Point"}
}