{
  "type": "Feature",
  "properties": {
    "addr:full":"636 Main St Dillwyn VA 23938",
    "addr:housenumber":"636",
    "addr:postcode":"23938",
    "addr:street":"Main St",
    "iso:country":"US",
    "sg:address":"636 Main St",
    "sg:city":"Dillwyn",
    "sg:classifiers":[
        {
            "category":"Personal",
            "subcategory":"Beauty Salon",
            "type":"Services"
        }
    ],
    "sg:phone":"+1 434 983 2719",
    "sg:postcode":"23938",
    "sg:province":"VA",
    "wof:name":"Faye's Beauty Salon",
    "wof:placetype":"venue"
},
  "geometry": {"coordinates":[-77.886955,36.861068],"type":"Point"}
}