{
  "type": "Feature",
  "properties": {
    "addr:full":"17 S Sheppard St Richmond VA 23221",
    "addr:housenumber":"17",
    "addr:postcode":"23221",
    "addr:street":"S Sheppard St",
    "iso:country":"US",
    "sg:address":"17 S Sheppard St",
    "sg:city":"Richmond",
    "sg:classifiers":[
        {
            "category":"Insurance",
            "subcategory":"Insurance Agent",
            "type":"Services"
        }
    ],
    "sg:phone":"+1 804 358 9116",
    "sg:postcode":"23221",
    "sg:province":"VA",
    "sg:tags":[
        "adjuster"
    ],
    "wof:name":"B H Johnson Assoc Inc",
    "wof:placetype":"venue"
},
  "geometry": {"coordinates":[-77.478669,37.552647],"type":"Point"}
}