{
  "type": "Feature",
  "properties": {
    "addr:full":"365 Burnett Rd Woodlawn VA 24381",
    "addr:housenumber":"365",
    "addr:postcode":"24381",
    "addr:street":"Burnett Rd",
    "iso:country":"US",
    "sg:address":"365 Burnett Rd",
    "sg:city":"Woodlawn",
    "sg:classifiers":[
        {
            "category":"Farming",
            "subcategory":"Livestock Farm",
            "type":"Manufacturing & Wholesale Goods"
        }
    ],
    "sg:phone":"+1 276 728 3403",
    "sg:postcode":"24381",
    "sg:province":"VA",
    "sg:tags":[
        "beef",
        "feedlot",
        "cattle"
    ],
    "wof:name":"Burnett Farm",
    "wof:placetype":"venue"
},
  "geometry": {"coordinates":[-80.875361,36.780669],"type":"Point"}
}