{
  "type": "Feature",
  "properties": {
    "addr:full":"2700 Azalea Garden Rd Norfolk VA 23513",
    "addr:housenumber":"2700",
    "addr:postcode":"23513",
    "addr:street":"Azalea Garden Rd",
    "iso:country":"US",
    "sg:address":"2700 Azalea Garden Rd",
    "sg:city":"Norfolk",
    "sg:classifiers":[
        {
            "category":"Food & Beverages",
            "subcategory":"Groceries & Convenience Stores",
            "type":"Retail Goods"
        }
    ],
    "sg:phone":"+1 757 857 1600",
    "sg:postcode":"23513",
    "sg:province":"VA",
    "wof:name":"Fat Phillys Food & Grill",
    "wof:placetype":"venue"
},
  "geometry": {"coordinates":[-76.226719,36.879343],"type":"Point"}
}