{
  "type": "Feature",
  "properties": {
    "iso:country":"US",
    "sg:address":"534 W 24th St",
    "sg:city":"Norfolk",
    "sg:classifiers":[
        {
            "category":"Building & Trades",
            "subcategory":"Construction",
            "type":"Services"
        }
    ],
    "sg:phone":"+1 757 455 5866",
    "sg:postcode":"23517",
    "sg:province":"VA",
    "sg:tags":[
        "concrete",
        "contractor"
    ],
    "wof:name":"Concrete Works",
    "wof:placetype":"venue"
},
  "geometry": {"coordinates":[-76.291935,36.871921],"type":"Point"}
}