{
  "type": "Feature",
  "properties": {
    "addr:full":"2690 Bridge Rd Suffolk VA 23435",
    "addr:housenumber":"2690",
    "addr:postcode":"23435",
    "addr:street":"Bridge Rd",
    "iso:country":"US",
    "sg:address":"2690 Bridge Rd",
    "sg:city":"Suffolk",
    "sg:classifiers":[
        {
            "category":"Retail",
            "subcategory":"Funeral Services",
            "type":"Services"
        }
    ],
    "sg:phone":"+1 757 483 4392",
    "sg:postcode":"23435",
    "sg:province":"VA",
    "sg:tags":[
        "cemetery"
    ],
    "wof:name":"Bennetts Creek Chapel",
    "wof:placetype":"venue"
},
  "geometry": {"coordinates":[-76.49140199999999,36.879002],"type":"Point"}
}