{
  "type": "Feature",
  "properties": {
    "addr:full":"759 Dutch Rd Suffolk VA 23437",
    "addr:housenumber":"759",
    "addr:postcode":"23437",
    "addr:street":"Dutch Rd",
    "iso:country":"US",
    "sg:address":"759 Dutch Rd",
    "sg:city":"Suffolk",
    "sg:classifiers":[
        {
            "category":"Professional",
            "type":"Services"
        }
    ],
    "sg:phone":"+1 757 657 9911",
    "sg:postcode":"23437",
    "sg:province":"VA",
    "wof:name":"Bfp",
    "wof:placetype":"venue"
},
  "geometry": {"coordinates":[-76.766876,36.668402],"type":"Point"}
}