{
  "type": "Feature",
  "properties": {
    "iso:country":"US",
    "sg:address":"2447 Sugar Mill Way",
    "sg:city":"Herndon",
    "sg:classifiers":[
        {
            "category":"Professional",
            "subcategory":"Computer Services",
            "type":"Services"
        }
    ],
    "sg:phone":"+1 703 855 8975",
    "sg:postcode":"20171",
    "sg:province":"VA",
    "sg:tags":[
        "application",
        "programming",
        "software"
    ],
    "wof:name":"American Federal Services Inc",
    "wof:placetype":"venue"
},
  "geometry": {"coordinates":[-77.404597,38.946462],"type":"Point"}
}