{
  "type": "Feature",
  "properties": {
    "addr:full":"563 Neff Ave Harrisonburg VA 22801",
    "addr:housenumber":"563",
    "addr:postcode":"22801",
    "addr:street":"Neff Ave",
    "iso:country":"US",
    "sg:address":"563 Neff Ave",
    "sg:city":"Harrisonburg",
    "sg:classifiers":[
        {
            "category":"Shopping",
            "subcategory":"Pharmacy",
            "type":"Retail Goods"
        }
    ],
    "sg:phone":"+1 540 434 2372",
    "sg:postcode":"22801",
    "sg:province":"VA",
    "wof:name":"Williamson Hughes Pharmacy",
    "wof:placetype":"venue"
},
  "geometry": {"coordinates":[-78.855767,38.426161],"type":"Point"}
}