{
  "type": "Feature",
  "properties": {
    "iso:country":"US",
    "sg:address":"10096 James Monroe Hwy",
    "sg:city":"Culpeper",
    "sg:classifiers":[
        {
            "category":"Shopping",
            "subcategory":"Bicycles & Sporting Goods",
            "type":"Retail Goods"
        }
    ],
    "sg:phone":"+1 540 547 2110",
    "sg:postcode":"22701",
    "sg:province":"VA",
    "wof:name":"Sport Shop",
    "wof:placetype":"venue"
},
  "geometry": {"coordinates":[-78.062021,38.455335],"type":"Point"}
}