{
  "type": "Feature",
  "properties": {
    "iso:country":"US",
    "sg:address":"13758 Royal Red Ter",
    "sg:city":"Chantilly",
    "sg:classifiers":[
        {
            "category":"Professional",
            "subcategory":"Management & Consulting",
            "type":"Services"
        }
    ],
    "sg:phone":"+1 703 322 4468",
    "sg:postcode":"20151",
    "sg:province":"VA",
    "wof:name":"Graystar Associates LLC",
    "wof:placetype":"venue"
},
  "geometry": {"coordinates":[-77.424244,38.869313],"type":"Point"}
}