{
  "type": "Feature",
  "properties": {
    "addr:full":"209 N Belmont Ave Richmond VA 23221",
    "addr:housenumber":"209",
    "addr:postcode":"23221",
    "addr:street":"N Belmont Ave",
    "iso:country":"US",
    "sg:address":"209 N Belmont Ave",
    "sg:city":"Richmond",
    "sg:classifiers":[
        {
            "category":"Professional",
            "subcategory":"Lawyer & Legal Services",
            "type":"Services"
        }
    ],
    "sg:phone":"+1 804 278 8902",
    "sg:postcode":"23221",
    "sg:province":"VA",
    "wof:name":"Michael A Montgomery Lawyer",
    "wof:placetype":"venue"
},
  "geometry": {"coordinates":[-77.47752,37.557289],"type":"Point"}
}