{
  "type": "Feature",
  "properties": {
    "addr:full":"102 Wall St S Abingdon VA 24210",
    "addr:housenumber":"102",
    "addr:postcode":"24210",
    "addr:street":"Wall St S",
    "iso:country":"US",
    "sg:address":"102 Wall St S",
    "sg:city":"Abingdon",
    "sg:classifiers":[
        {
            "category":"Banks & Credit Unions",
            "subcategory":"Bank",
            "type":"Services"
        }
    ],
    "sg:phone":"+1 276 628 7376",
    "sg:postcode":"24210",
    "sg:province":"VA",
    "wof:name":"First Bank Of Virginia",
    "wof:placetype":"venue"
},
  "geometry": {"coordinates":[-81.97995,36.70806],"type":"Point"}
}