{
  "type": "Feature",
  "properties": {
    "iso:country":"US",
    "sg:address":"7424 Gainesville Vlg Sq",
    "sg:city":"Gainesville",
    "sg:classifiers":[
        {
            "category":"Personal",
            "subcategory":"Nail Salon",
            "type":"Services"
        }
    ],
    "sg:phone":"+1 703 754 2009",
    "sg:postcode":"20155",
    "sg:province":"VA",
    "wof:name":"C & T Nails",
    "wof:placetype":"venue"
},
  "geometry": {"coordinates":[-77.613602,38.7962],"type":"Point"}
}