{
  "type": "Feature",
  "properties": {
    "iso:country":"US",
    "sg:address":"630 High St",
    "sg:city":"Portsmouth",
    "sg:classifiers":[
        {
            "category":"Home & Garden",
            "subcategory":"Home Furnishings",
            "type":"Retail Goods"
        }
    ],
    "sg:phone":"+1 757 397 5588",
    "sg:postcode":"23704",
    "sg:province":"VA",
    "sg:tags":[
        "sewing"
    ],
    "wof:name":"Ma Maison LLC",
    "wof:placetype":"venue"
},
  "geometry": {"coordinates":[-76.305018,36.835312],"type":"Point"}
}