{
  "type": "Feature",
  "properties": {
    "iso:country":"US",
    "sg:address":"9041 W Broad St",
    "sg:city":"Richmond",
    "sg:classifiers":[
        {
            "category":"Personal",
            "subcategory":"Beauty Salon",
            "type":"Services"
        }
    ],
    "sg:phone":"+1 804 270 2095",
    "sg:postcode":"23294",
    "sg:province":"VA",
    "sg:tags":[
        "school"
    ],
    "wof:name":"Empire Beauty School",
    "wof:placetype":"venue"
},
  "geometry": {"coordinates":[-77.54993,37.636371],"type":"Point"}
}