{
  "type": "Feature",
  "properties": {
    "iso:country":"US",
    "sg:address":"7209 Jefferson Davis Hwy",
    "sg:city":"Richmond",
    "sg:classifiers":[
        {
            "category":"Professional",
            "type":"Services"
        }
    ],
    "sg:phone":"+1 804 279 9281",
    "sg:postcode":"23237",
    "sg:province":"VA",
    "sg:tags":[
        "establishment"
    ],
    "wof:name":"Almancem",
    "wof:placetype":"venue"
},
  "geometry": {"coordinates":[-77.43902199999999,37.426838],"type":"Point"}
}