{
  "type": "Feature",
  "properties": {
    "addr:full":"5840 Anthony Dr Woodbridge VA 22193",
    "addr:housenumber":"5840",
    "addr:postcode":"22193",
    "addr:street":"Anthony Dr",
    "iso:country":"US",
    "sg:address":"5840 Anthony Dr",
    "sg:city":"Woodbridge",
    "sg:classifiers":[
        {
            "category":"Retail",
            "subcategory":"Repair Shop",
            "type":"Services"
        }
    ],
    "sg:phone":"+1 703 878 3486",
    "sg:postcode":"22193",
    "sg:province":"VA",
    "wof:name":"Flower Fresh Home Cleaning",
    "wof:placetype":"venue"
},
  "geometry": {"coordinates":[-77.385468,38.640266],"type":"Point"}
}