{
  "type": "Feature",
  "properties": {
    "addr:full":"2901 Charles City Rd Richmond VA 23231",
    "addr:housenumber":"2901",
    "addr:postcode":"23231",
    "addr:street":"Charles City Rd",
    "iso:country":"US",
    "sg:address":"2901 Charles City Rd",
    "sg:city":"Richmond",
    "sg:classifiers":[
        {
            "category":"Manufacturing",
            "subcategory":"Printing",
            "type":"Manufacturing & Wholesale Goods"
        }
    ],
    "sg:phone":"+1 804 771 3884",
    "sg:postcode":"23231",
    "sg:province":"VA",
    "sg:tags":[
        "lithographic",
        "commercial",
        "photocopying"
    ],
    "wof:name":"Dominion Virginia Power",
    "wof:placetype":"venue"
},
  "geometry": {"coordinates":[-77.34067400000001,37.499137],"type":"Point"}
}