{
  "type": "Feature",
  "properties": {
    "addr:full":"16 N Franklin St Christiansburg VA 24073",
    "addr:housenumber":"16",
    "addr:postcode":"24073",
    "addr:street":"N Franklin St",
    "iso:country":"US",
    "sg:address":"16 N Franklin St",
    "sg:city":"Christiansburg",
    "sg:classifiers":[
        {
            "category":"Shopping",
            "subcategory":"Pharmacy",
            "type":"Retail Goods"
        }
    ],
    "sg:phone":"+1 540 382 1212",
    "sg:postcode":"24073",
    "sg:province":"VA",
    "wof:name":"Medicine Shoppe Pharmacy",
    "wof:placetype":"venue"
},
  "geometry": {"coordinates":[-80.41059799999999,37.131054],"type":"Point"}
}