{
  "type": "Feature",
  "properties": {
    "addr:full":"5711 Richmond Rd Williamsburg VA 23188",
    "addr:housenumber":"5711",
    "addr:postcode":"23188",
    "addr:street":"Richmond Rd",
    "iso:country":"US",
    "sg:address":"5711 Richmond Rd",
    "sg:city":"Williamsburg",
    "sg:classifiers":[
        {
            "category":"Shopping",
            "subcategory":"Clothing, Apparel, & Fashions",
            "type":"Retail Goods"
        }
    ],
    "sg:phone":"+1 757 258 1039",
    "sg:postcode":"23188",
    "sg:province":"VA",
    "sg:tags":[
        "item",
        "boutique"
    ],
    "wof:name":"Claire's",
    "wof:placetype":"venue"
},
  "geometry": {"coordinates":[-76.735344,37.319365],"type":"Point"}
}