{
  "type": "Feature",
  "properties": {
    "addr:full":"5532 Hempstead Way Springfield VA 22151",
    "addr:housenumber":"5532",
    "addr:postcode":"22151",
    "addr:street":"Hempstead Way",
    "iso:country":"US",
    "sg:address":"5532 Hempstead Way",
    "sg:city":"Springfield",
    "sg:classifiers":[
        {
            "category":"Professional",
            "subcategory":"Business Services",
            "type":"Services"
        }
    ],
    "sg:phone":"+1 703 750 3431",
    "sg:postcode":"22151",
    "sg:province":"VA",
    "sg:tags":[
        "development",
        "application",
        "computer",
        "software"
    ],
    "wof:name":"Accolade Solutions Inc",
    "wof:placetype":"venue"
},
  "geometry": {"coordinates":[-77.18638799999999,38.79993],"type":"Point"}
}