{
  "type": "Feature",
  "properties": {
    "addr:full":"316 Flatwoods Rd Marion VA 24354",
    "addr:housenumber":"316",
    "addr:postcode":"24354",
    "addr:street":"Flatwoods Rd",
    "iso:country":"US",
    "sg:address":"316 Flatwoods Rd",
    "sg:city":"Marion",
    "sg:classifiers":[
        {
            "category":"Freight",
            "type":"Transportation"
        }
    ],
    "sg:phone":"+1 276 783 3022",
    "sg:postcode":"24354",
    "sg:province":"VA",
    "sg:tags":[
        "operator",
        "local",
        "trucking"
    ],
    "wof:name":"First Choice Fencing",
    "wof:placetype":"venue"
},
  "geometry": {"coordinates":[-81.564374,36.76222],"type":"Point"}
}