{
  "type": "Feature",
  "properties": {
    "addr:full":"874 N Jackson St Arlington VA 22201",
    "addr:housenumber":"874",
    "addr:postcode":"22201",
    "addr:street":"N Jackson St",
    "iso:country":"US",
    "sg:address":"874 N Jackson St",
    "sg:city":"Arlington",
    "sg:classifiers":[
        {
            "category":"Professional",
            "subcategory":"Lawyer & Legal Services",
            "type":"Services"
        }
    ],
    "sg:phone":"+1 703 524 5682",
    "sg:postcode":"22201",
    "sg:province":"VA",
    "wof:name":"Gish Brian R Lwyr",
    "wof:placetype":"venue"
},
  "geometry": {"coordinates":[-77.09901000000001,38.883222],"type":"Point"}
}