{
  "type": "Feature",
  "properties": {
    "addr:full":"7040 Jefferson Davis Hwy Richmond VA 23237",
    "addr:housenumber":"7040",
    "addr:postcode":"23237",
    "addr:street":"Jefferson Davis Hwy",
    "iso:country":"US",
    "sg:address":"7040 Jefferson Davis Hwy",
    "sg:city":"Richmond",
    "sg:classifiers":[
        {
            "category":"Wholesale",
            "subcategory":"Machinery & Supplies",
            "type":"Manufacturing & Wholesale Goods"
        }
    ],
    "sg:phone":"+1 804 743 0453",
    "sg:postcode":"23237",
    "sg:province":"VA",
    "sg:tags":[
        "rope"
    ],
    "wof:name":"Torrence Rope & Sling",
    "wof:placetype":"venue"
},
  "geometry": {"coordinates":[-77.43962000000001,37.427998],"type":"Point"}
}