{
  "type": "Feature",
  "properties": {
    "addr:full":"2233 Tacketts Mill Dr Woodbridge VA 22192",
    "addr:housenumber":"2233",
    "addr:postcode":"22192",
    "addr:street":"Tacketts Mill Dr",
    "iso:country":"US",
    "sg:address":"2233 Tacketts Mill Dr",
    "sg:city":"Woodbridge",
    "sg:classifiers":[
        {
            "category":"Professional",
            "type":"Services"
        }
    ],
    "sg:phone":"+1 703 497 0568",
    "sg:postcode":"22192",
    "sg:province":"VA",
    "wof:name":"Chalet",
    "wof:placetype":"venue"
},
  "geometry": {"coordinates":[-77.277855,38.675626],"type":"Point"}
}