{
  "type": "Feature",
  "properties": {
    "addr:full":"6525 Greenway Dr Blue Ridge VA 24019",
    "addr:housenumber":"6525",
    "addr:postcode":"24019",
    "addr:street":"Greenway Dr",
    "iso:country":"US",
    "sg:address":"6525 Greenway Dr",
    "sg:city":"Blue Ridge",
    "sg:classifiers":[
        {
            "category":"Real Estate",
            "subcategory":"Real Estate Operator",
            "type":"Services"
        }
    ],
    "sg:phone":"+1 540 366 8243",
    "sg:postcode":"24019",
    "sg:province":"VA",
    "sg:tags":[
        "building",
        "apartment"
    ],
    "wof:name":"Bent Creek I",
    "wof:placetype":"venue"
},
  "geometry": {"coordinates":[-79.951716,37.335862],"type":"Point"}
}