{
  "type": "Feature",
  "properties": {
    "iso:country":"US",
    "sg:address":"624 Ben Bow Dr",
    "sg:city":"Virginia Beach",
    "sg:classifiers":[
        {
            "category":"Building & Trades",
            "subcategory":"Construction",
            "type":"Services"
        }
    ],
    "sg:phone":"+1 757 420 8028",
    "sg:postcode":"23464",
    "sg:province":"VA",
    "sg:tags":[
        "house"
    ],
    "wof:name":"Cannady & Son Inc",
    "wof:placetype":"venue"
},
  "geometry": {"coordinates":[-76.174111,36.821745],"type":"Point"}
}