{
  "type": "Feature",
  "properties": {
    "addr:full":"1347 Chesapeake Ave Chesapeake VA 23324",
    "addr:housenumber":"1347",
    "addr:postcode":"23324",
    "addr:street":"Chesapeake Ave",
    "iso:country":"US",
    "sg:address":"1347 Chesapeake Ave",
    "sg:city":"Chesapeake",
    "sg:classifiers":[
        {
            "category":"Social Services",
            "subcategory":"Child Care",
            "type":"Services"
        }
    ],
    "sg:phone":"+1 757 543 8443",
    "sg:postcode":"23324",
    "sg:province":"VA",
    "sg:tags":[
        "day"
    ],
    "wof:name":"Rita Wilson",
    "wof:placetype":"venue"
},
  "geometry": {"coordinates":[-76.271451,36.813596],"type":"Point"}
}