{
  "type": "Feature",
  "properties": {
    "addr:full":"2017 Brier Cliff Cres Chesapeake VA 23320",
    "addr:housenumber":"2017",
    "addr:postcode":"23320",
    "addr:street":"Brier Cliff Cres",
    "iso:country":"US",
    "sg:address":"2017 Brier Cliff Cres",
    "sg:city":"Chesapeake",
    "sg:classifiers":[
        {
            "category":"Professional",
            "subcategory":"Computer Services",
            "type":"Services"
        }
    ],
    "sg:phone":"+1 757 479 5226",
    "sg:postcode":"23320",
    "sg:province":"VA",
    "sg:tags":[
        "prepackaged",
        "software"
    ],
    "wof:name":"Confidence Software Design",
    "wof:placetype":"venue"
},
  "geometry": {"coordinates":[-76.190253,36.758529],"type":"Point"}
}