{
  "type": "Feature",
  "properties": {
    "iso:country":"US",
    "sg:address":"6446 Muster Ct",
    "sg:city":"Centreville",
    "sg:classifiers":[
        {
            "category":"Professional",
            "type":"Services"
        }
    ],
    "sg:phone":"+1 703 815 2173",
    "sg:postcode":"20121",
    "sg:province":"VA",
    "wof:name":"Grin N Bear It",
    "wof:placetype":"venue"
},
  "geometry": {"coordinates":[-77.447416,38.822063],"type":"Point"}
}