{
  "type": "Feature",
  "properties": {
    "addr:full":"12605 Hogans Dr Chester VA 23836",
    "addr:housenumber":"12605",
    "addr:postcode":"23836",
    "addr:street":"Hogans Dr",
    "iso:country":"US",
    "sg:address":"12605 Hogans Dr",
    "sg:city":"Chester",
    "sg:classifiers":[
        {
            "category":"Home & Garden",
            "subcategory":"Home Furnishings",
            "type":"Retail Goods"
        }
    ],
    "sg:phone":"+1 804 530 5073",
    "sg:postcode":"23836",
    "sg:province":"VA",
    "sg:tags":[
        "venetian",
        "blind"
    ],
    "wof:name":"Blinds To You",
    "wof:placetype":"venue"
},
  "geometry": {"coordinates":[-77.357202,37.357044],"type":"Point"}
}