{
  "type": "Feature",
  "properties": {
    "addr:full":"760 Amanda Ct Culpeper VA 22701",
    "addr:housenumber":"760",
    "addr:postcode":"22701",
    "addr:street":"Amanda Ct",
    "iso:country":"US",
    "sg:address":"760 Amanda Ct",
    "sg:city":"Culpeper",
    "sg:classifiers":[
        {
            "category":"Social Services",
            "subcategory":"Child Care",
            "type":"Services"
        }
    ],
    "sg:phone":"+1 540 825 1125",
    "sg:postcode":"22701",
    "sg:province":"VA",
    "sg:tags":[
        "day"
    ],
    "wof:name":"Harley Robin Family Day Home",
    "wof:placetype":"venue"
},
  "geometry": {"coordinates":[-77.98391599999999,38.487352],"type":"Point"}
}