{
  "type": "Feature",
  "properties": {
    "addr:full":"2400 N Franklin St Christiansburg VA 24073",
    "addr:housenumber":"2400",
    "addr:postcode":"24073",
    "addr:street":"N Franklin St",
    "iso:country":"US",
    "sg:address":"2400 N Franklin St",
    "sg:city":"Christiansburg",
    "sg:classifiers":[
        {
            "category":"Utilities",
            "subcategory":"Mobile Phone",
            "type":"Services"
        },
        {
            "category":"Utilities",
            "subcategory":"Telephone",
            "type":"Services"
        }
    ],
    "sg:phone":"+1 540 381 0436",
    "sg:postcode":"24073",
    "sg:province":"VA",
    "sg:tags":[
        "equipment",
        "cellular",
        "supplies-rental"
    ],
    "sg:website":"http://www.walmart.com",
    "wof:name":"Wal-Mart - Connect Center",
    "wof:placetype":"venue"
},
  "geometry": {"coordinates":[-80.42291299999999,37.161659],"type":"Point"}
}