{
  "type": "Feature",
  "properties": {
    "addr:full":"204 Melwood Ln Richmond VA 23229",
    "addr:housenumber":"204",
    "addr:postcode":"23229",
    "addr:street":"Melwood Ln",
    "iso:country":"US",
    "sg:address":"204 Melwood Ln",
    "sg:city":"Richmond",
    "sg:classifiers":[
        {
            "category":"Professional",
            "subcategory":"Management & Consulting",
            "type":"Services"
        }
    ],
    "sg:phone":"+1 804 282 1355",
    "sg:postcode":"23229",
    "sg:province":"VA",
    "sg:tags":[
        "public",
        "relations"
    ],
    "wof:name":"Susanne Gregory MPH",
    "wof:placetype":"venue"
},
  "geometry": {"coordinates":[-77.563682,37.58045],"type":"Point"}
}