{
  "type": "Feature",
  "properties": {
    "addr:full":"745 Halifax Rd Danville VA 24540",
    "addr:housenumber":"745",
    "addr:postcode":"24540",
    "addr:street":"Halifax Rd",
    "iso:country":"US",
    "sg:address":"745 Halifax Rd",
    "sg:city":"Danville",
    "sg:classifiers":[
        {
            "category":"Railroad",
            "type":"Transportation"
        }
    ],
    "sg:phone":"+1 434 797 6380",
    "sg:postcode":"24540",
    "sg:province":"VA",
    "sg:tags":[
        "operator",
        "line"
    ],
    "wof:name":"Norfolk Southern Corporation",
    "wof:placetype":"venue"
},
  "geometry": {"coordinates":[-79.36998800000001,36.589534],"type":"Point"}
}