{
  "type": "Feature",
  "properties": {
    "addr:full":"521 Hardy Rd Vinton VA 24179",
    "addr:housenumber":"521",
    "addr:postcode":"24179",
    "addr:street":"Hardy Rd",
    "iso:country":"US",
    "sg:address":"521 Hardy Rd",
    "sg:city":"Vinton",
    "sg:classifiers":[
        {
            "category":"Retail",
            "subcategory":"Veterinary Services",
            "type":"Services"
        }
    ],
    "sg:phone":"+1 540 345 5653",
    "sg:postcode":"24179",
    "sg:province":"VA",
    "wof:name":"Hardy Rd Companion Animal Hosp",
    "wof:placetype":"venue"
},
  "geometry": {"coordinates":[-79.89371800000001,37.273633],"type":"Point"}
}