{
  "type": "Feature",
  "properties": {
    "addr:full":"523 Shell Rd Hampton VA 23661",
    "addr:housenumber":"523",
    "addr:postcode":"23661",
    "addr:street":"Shell Rd",
    "iso:country":"US",
    "sg:address":"523 Shell Rd",
    "sg:city":"Hampton",
    "sg:classifiers":[
        {
            "category":"Autos & Motor Vehicles",
            "subcategory":"Fuel & Gas Station",
            "type":"Retail Goods"
        }
    ],
    "sg:phone":"+1 757 643 4381",
    "sg:postcode":"23661",
    "sg:province":"VA",
    "sg:tags":[
        "station",
        "gasoline"
    ],
    "wof:name":"Shell Road Auto Center",
    "wof:placetype":"venue"
},
  "geometry": {"coordinates":[-76.405413,36.998111],"type":"Point"}
}