{
  "type": "Feature",
  "properties": {
    "addr:full":"111 Dogwood Dr Newport News VA 23606",
    "addr:housenumber":"111",
    "addr:postcode":"23606",
    "addr:street":"Dogwood Dr",
    "iso:country":"US",
    "sg:address":"111 Dogwood Dr",
    "sg:city":"Newport News",
    "sg:classifiers":[
        {
            "category":"Banks & Credit Unions",
            "subcategory":"Financial Services",
            "type":"Services"
        }
    ],
    "sg:phone":"+1 757 596 7062",
    "sg:postcode":"23606",
    "sg:province":"VA",
    "sg:tags":[
        "trust",
        "management"
    ],
    "wof:name":"Mackel Nelson Family Ltd",
    "wof:placetype":"venue"
},
  "geometry": {"coordinates":[-76.495401,37.052334],"type":"Point"}
}