{
  "type": "Feature",
  "properties": {
    "addr:full":"829 Maryland Ave Salem VA 24153",
    "addr:housenumber":"829",
    "addr:postcode":"24153",
    "addr:street":"Maryland Ave",
    "iso:country":"US",
    "sg:address":"829 Maryland Ave",
    "sg:city":"Salem",
    "sg:classifiers":[
        {
            "category":"Shopping",
            "subcategory":"Used Merchandise",
            "type":"Retail Goods"
        }
    ],
    "sg:phone":"+1 540 389 3754",
    "sg:postcode":"24153",
    "sg:province":"VA",
    "wof:name":"Lighthouse Antq Collectibles",
    "wof:placetype":"venue"
},
  "geometry": {"coordinates":[-80.046153,37.290163],"type":"Point"}
}