{
  "type": "Feature",
  "properties": {
    "iso:country":"US",
    "sg:address":"332 Fairfax St",
    "sg:city":"Radford",
    "sg:classifiers":[
        {
            "category":"Real Estate",
            "subcategory":"Real Estate Operator",
            "type":"Services"
        }
    ],
    "sg:phone":"+1 540 731 1786",
    "sg:postcode":"24141",
    "sg:province":"VA",
    "sg:tags":[
        "apartment",
        "complex"
    ],
    "wof:name":"Fairfax Village Apartments",
    "wof:placetype":"venue"
},
  "geometry": {"coordinates":[-80.542395,37.13257],"type":"Point"}
}