{
  "type": "Feature",
  "properties": {
    "addr:full":"5638 Club Ln Roanoke VA 24018",
    "addr:housenumber":"5638",
    "addr:postcode":"24018",
    "addr:street":"Club Ln",
    "iso:country":"US",
    "sg:address":"5638 Club Ln",
    "sg:city":"Roanoke",
    "sg:classifiers":[
        {
            "category":"Manufacturing",
            "subcategory":"Signs",
            "type":"Manufacturing & Wholesale Goods"
        }
    ],
    "sg:phone":"+1 540 774 8345",
    "sg:postcode":"24018",
    "sg:province":"VA",
    "wof:name":"Bob Kinsey Enterprise Signs",
    "wof:placetype":"venue"
},
  "geometry": {"coordinates":[-80.040424,37.25763],"type":"Point"}
}