{
  "type": "Feature",
  "properties": {
    "iso:country":"US",
    "sg:address":"205 Keith St",
    "sg:city":"Warrenton",
    "sg:classifiers":[
        {
            "category":"Personal",
            "subcategory":"Beauty Salon",
            "type":"Services"
        }
    ],
    "sg:phone":"+1 540 347 7787",
    "sg:postcode":"20186",
    "sg:province":"VA",
    "wof:name":"Warrenton Paza Hair Designs",
    "wof:placetype":"venue"
},
  "geometry": {"coordinates":[-77.801,38.709937],"type":"Point"}
}