{
  "type": "Feature",
  "properties": {
    "addr:full":"310 Chesapeake Dr White Stone VA 22578",
    "addr:housenumber":"310",
    "addr:postcode":"22578",
    "addr:street":"Chesapeake Dr White Stone",
    "iso:country":"US",
    "sg:address":"310 Chesapeake Dr",
    "sg:city":"White Stone",
    "sg:classifiers":[
        {
            "category":"Real Estate",
            "subcategory":"Developer",
            "type":"Services"
        },
        {
            "category":"Real Estate",
            "subcategory":"Real Estate Agent",
            "type":"Services"
        }
    ],
    "sg:phone":"+1 805 898 9418",
    "sg:postcode":"22578",
    "sg:province":"VA",
    "wof:name":"Merry Point Development Co",
    "wof:placetype":"venue"
},
  "geometry": {"coordinates":[-76.39260899999999,37.650727],"type":"Point"}
}