{
  "type": "Feature",
  "properties": {
    "iso:country":"US",
    "sg:address":"3463 W Cary St",
    "sg:city":"Richmond",
    "sg:classifiers":[
        {
            "category":"Manufacturing",
            "subcategory":"Building Materials",
            "type":"Manufacturing & Wholesale Goods"
        },
        {
            "category":"Home & Garden",
            "subcategory":"Furniture",
            "type":"Retail Goods"
        }
    ],
    "sg:phone":"+1 804 342 1055",
    "sg:postcode":"23221",
    "sg:province":"VA",
    "sg:tags":[
        "cabinet",
        "all",
        "wood",
        "cabinetry",
        "custom"
    ],
    "wof:name":"Carytown Cabinetry Company",
    "wof:placetype":"venue"
},
  "geometry": {"coordinates":[-77.485975,37.55493],"type":"Point"}
}