{
  "type": "Feature",
  "properties": {
    "addr:full":"907 Clay St Lynchburg VA 24504",
    "addr:housenumber":"907",
    "addr:postcode":"24504",
    "addr:street":"Clay St",
    "iso:country":"US",
    "sg:address":"907 Clay St",
    "sg:city":"Lynchburg",
    "sg:classifiers":[
        {
            "category":"Government",
            "subcategory":"Office",
            "type":"Public Place"
        }
    ],
    "sg:phone":"+1 434 847 1301",
    "sg:postcode":"24504",
    "sg:province":"VA",
    "sg:tags":[
        "village"
    ],
    "wof:name":"Lynchburg Sheriff Office",
    "wof:placetype":"venue"
},
  "geometry": {"coordinates":[-79.144364,37.412502],"type":"Point"}
}