{
  "type": "Feature",
  "properties": {
    "addr:full":"1822 E Franklin St Richmond VA 23223",
    "addr:housenumber":"1822",
    "addr:postcode":"23223",
    "addr:street":"E Franklin St",
    "iso:country":"US",
    "sg:address":"1822 E Franklin St",
    "sg:city":"Richmond",
    "sg:classifiers":[
        {
            "category":"Wholesale",
            "subcategory":"Home Furnishings",
            "type":"Manufacturing & Wholesale Goods"
        }
    ],
    "sg:phone":"+1 804 643 6023",
    "sg:postcode":"23223",
    "sg:province":"VA",
    "sg:tags":[
        "curtain",
        "drapery"
    ],
    "wof:name":"Challenger Products",
    "wof:placetype":"venue"
},
  "geometry": {"coordinates":[-77.426052,37.533404],"type":"Point"}
}