{
  "type": "Feature",
  "properties": {
    "iso:country":"US",
    "sg:address":"815 Slaters Ln",
    "sg:city":"Alexandria",
    "sg:classifiers":[
        {
            "category":"Professional",
            "subcategory":"Advertising",
            "type":"Services"
        }
    ],
    "sg:phone":"+1 703 519 0651",
    "sg:postcode":"22314",
    "sg:province":"VA",
    "sg:tags":[
        "dvd",
        "cassette",
        "duplicating",
        "cd"
    ],
    "wof:name":"Cold Harbor Films, Lc",
    "wof:placetype":"venue"
},
  "geometry": {"coordinates":[-77.04727200000001,38.82144],"type":"Point"}
}