{
  "type": "Feature",
  "properties": {
    "addr:full":"708 S Main St Lexington VA 24450",
    "addr:housenumber":"708",
    "addr:postcode":"24450",
    "addr:street":"S Main St",
    "iso:country":"US",
    "sg:address":"708 S Main St",
    "sg:city":"Lexington",
    "sg:classifiers":[
        {
            "category":"Banks & Credit Unions",
            "subcategory":"Bank",
            "type":"Services"
        }
    ],
    "sg:phone":"+1 540 463 8228",
    "sg:postcode":"24450",
    "sg:province":"VA",
    "wof:name":"Crestar Bank",
    "wof:placetype":"venue"
},
  "geometry": {"coordinates":[-79.450182,37.774407],"type":"Point"}
}