{
  "type": "Feature",
  "properties": {
    "addr:full":"4 E Main St Christiansburg VA 24073",
    "addr:housenumber":"4",
    "addr:postcode":"24073",
    "addr:street":"E Main St",
    "iso:country":"US",
    "sg:address":"4 E Main St",
    "sg:city":"Christiansburg",
    "sg:classifiers":[
        {
            "category":"Government",
            "subcategory":"Office",
            "type":"Public Place"
        }
    ],
    "sg:phone":"+1 540 382 5750",
    "sg:postcode":"24073",
    "sg:province":"VA",
    "wof:name":"Montgomery Cnty Planning Dept",
    "wof:placetype":"venue"
},
  "geometry": {"coordinates":[-80.40863400000001,37.130081],"type":"Point"}
}