{
  "type": "Feature",
  "properties": {
    "iso:country":"US",
    "sg:address":"4316 Wheeler Ave",
    "sg:city":"Alexandria",
    "sg:classifiers":[
        {
            "category":"Arts & Performance",
            "subcategory":"Theater",
            "type":"Entertainment"
        }
    ],
    "sg:phone":"+1 703 823 3303",
    "sg:postcode":"22304",
    "sg:province":"VA",
    "sg:tags":[
        "equipment",
        "theatrical",
        "supply"
    ],
    "sg:website":"www.aemitchell.com",
    "wof:name":"A E Mitchell & Co Inc",
    "wof:placetype":"venue"
},
  "geometry": {"coordinates":[-77.109115,38.807491],"type":"Point"}
}