{
  "type": "Feature",
  "properties": {
    "iso:country":"US",
    "sg:address":"1206 W Main St",
    "sg:city":"Danville",
    "sg:classifiers":[
        {
            "category":"Social Services",
            "type":"Services"
        }
    ],
    "sg:phone":"+1 434 792 6078",
    "sg:postcode":"24541",
    "sg:province":"VA",
    "sg:tags":[
        "organization",
        "welfare"
    ],
    "wof:name":"Goodwill Industries",
    "wof:placetype":"venue"
},
  "geometry": {"coordinates":[-79.431431,36.567726],"type":"Point"}
}