{
  "type": "Feature",
  "properties": {
    "iso:country":"US",
    "sg:address":"1300 Courthouse Rd",
    "sg:city":"Stafford",
    "sg:classifiers":[
        {
            "category":"Government",
            "subcategory":"Office",
            "type":"Public Place"
        }
    ],
    "sg:phone":"+1 540 658 4124",
    "sg:postcode":"22554",
    "sg:province":"VA",
    "wof:name":"Stafford County Commissioner",
    "wof:placetype":"venue"
},
  "geometry": {"coordinates":[-77.408197,38.422047],"type":"Point"}
}