{
  "type": "Feature",
  "properties": {
    "addr:full":"485 Johnstown Rd Chesapeake VA 23322",
    "addr:housenumber":"485",
    "addr:postcode":"23322",
    "addr:street":"Johnstown Rd",
    "iso:country":"US",
    "sg:address":"485 Johnstown Rd",
    "sg:city":"Chesapeake",
    "sg:classifiers":[
        {
            "category":"Real Estate",
            "subcategory":"Real Estate Agent",
            "type":"Services"
        },
        {
            "category":"Professional",
            "subcategory":"Business Services",
            "type":"Services"
        }
    ],
    "sg:phone":"+1 757 548 3181",
    "sg:postcode":"23322",
    "sg:province":"VA",
    "sg:tags":[
        "appraiser"
    ],
    "wof:name":"Virginia Appraisal Company",
    "wof:placetype":"venue"
},
  "geometry": {"coordinates":[-76.24209399999999,36.707032],"type":"Point"}
}