{
  "type": "Feature",
  "properties": {
    "addr:full":"1304 Tatemstown Rd Chesapeake VA 23325",
    "addr:housenumber":"1304",
    "addr:postcode":"23325",
    "addr:street":"Tatemstown Rd",
    "iso:country":"US",
    "sg:address":"1304 Tatemstown Rd",
    "sg:city":"Chesapeake",
    "sg:classifiers":[
        {
            "category":"Personal",
            "subcategory":"Beauty Salon",
            "type":"Services"
        }
    ],
    "sg:phone":"+1 757 543 3079",
    "sg:postcode":"23325",
    "sg:province":"VA",
    "sg:tags":[
        "shop"
    ],
    "wof:name":"Pamper Thyself",
    "wof:placetype":"venue"
},
  "geometry": {"coordinates":[-76.249413,36.824075],"type":"Point"}
}