{
  "type": "Feature",
  "properties": {
    "addr:full":"11284 Old Telegraph Rd Ashland VA 23005",
    "addr:housenumber":"11284",
    "addr:postcode":"23005",
    "addr:street":"Old Telegraph Rd",
    "iso:country":"US",
    "sg:address":"11284 Old Telegraph Rd",
    "sg:city":"Ashland",
    "sg:classifiers":[
        {
            "category":"Building & Trades",
            "subcategory":"Construction",
            "type":"Services"
        }
    ],
    "sg:phone":"+1 804 752 3424",
    "sg:postcode":"23005",
    "sg:province":"VA",
    "sg:tags":[
        "residential"
    ],
    "wof:name":"S K Williams Inc",
    "wof:placetype":"venue"
},
  "geometry": {"coordinates":[-77.46728899999999,37.712851],"type":"Point"}
}