{
  "type": "Feature",
  "properties": {
    "iso:country":"US",
    "sg:address":"20533 Warburton Bay Sq",
    "sg:city":"Sterling",
    "sg:classifiers":[
        {
            "category":"Professional",
            "subcategory":"Management & Consulting",
            "type":"Services"
        }
    ],
    "sg:phone":"+1 703 404 1906",
    "sg:postcode":"20165",
    "sg:province":"VA",
    "sg:tags":[
        "marketing",
        "rep"
    ],
    "wof:name":"DC Orbit LLC",
    "wof:placetype":"venue"
},
  "geometry": {"coordinates":[-77.35065400000001,39.046416],"type":"Point"}
}