{
  "type": "Feature",
  "properties": {
    "addr:full":"5101 Fleming Dr Annandale VA 22003",
    "addr:housenumber":"5101",
    "addr:postcode":"22003",
    "addr:street":"Fleming Dr",
    "iso:country":"US",
    "sg:address":"5101 Fleming Dr",
    "sg:city":"Annandale",
    "sg:classifiers":[
        {
            "category":"Organizations",
            "subcategory":"Religious Organization",
            "type":"Services"
        }
    ],
    "sg:phone":"+1 703 764 8906",
    "sg:postcode":"22003",
    "sg:province":"VA",
    "wof:name":"Islamic Unity of Afghanis",
    "wof:placetype":"venue"
},
  "geometry": {"coordinates":[-77.248893,38.813164],"type":"Point"}
}