{
  "type": "Feature",
  "properties": {
    "addr:full":"1313 E Main St Ste 240 Richmond VA 23219",
    "addr:housenumber":"1313",
    "addr:postcode":"23219",
    "addr:street":"E Main St Ste 240",
    "iso:country":"US",
    "sg:address":"1313 E Main St Ste 240",
    "sg:city":"Richmond",
    "sg:classifiers":[
        {
            "category":"Professional",
            "subcategory":"Engineering",
            "type":"Services"
        }
    ],
    "sg:phone":"+1 804 320 6900",
    "sg:postcode":"23219",
    "sg:province":"VA",
    "sg:tags":[
        "consultant",
        "energy",
        "conservation"
    ],
    "sg:website":"http://www.compassenergy.net",
    "wof:name":"Compass Energy Services Inc",
    "wof:placetype":"venue"
},
  "geometry": {"coordinates":[-77.432648,37.535978],"type":"Point"}
}