{
  "type": "Feature",
  "properties": {
    "iso:country":"US",
    "sg:address":"777 Poquoson Ave",
    "sg:city":"Poquoson",
    "sg:classifiers":[
        {
            "category":"Retail",
            "subcategory":"Portrait Studio",
            "type":"Services"
        }
    ],
    "sg:phone":"+1 757 868 1281",
    "sg:postcode":"23662",
    "sg:province":"VA",
    "sg:tags":[
        "photo"
    ],
    "wof:name":"Photographic Images Inc",
    "wof:placetype":"venue"
},
  "geometry": {"coordinates":[-76.379947,37.132454],"type":"Point"}
}