{
  "type": "Feature",
  "properties": {
    "iso:country":"US",
    "sg:address":"1902 Plank Rd",
    "sg:city":"Fredericksburg",
    "sg:classifiers":[
        {
            "category":"Real Estate",
            "subcategory":"Developer",
            "type":"Services"
        }
    ],
    "sg:phone":"+1 540 373 9104",
    "sg:postcode":"22401",
    "sg:province":"VA",
    "sg:tags":[
        "cemetery"
    ],
    "wof:name":"Oak Hill Cemetery Co Inc",
    "wof:placetype":"venue"
},
  "geometry": {"coordinates":[-77.49148599999999,38.29584],"type":"Point"}
}