{
  "type": "Feature",
  "properties": {
    "addr:full":"629 Cedar Creek Grade Winchester VA 22601",
    "addr:housenumber":"629",
    "addr:postcode":"22601",
    "addr:street":"Cedar Creek Grade",
    "iso:country":"US",
    "sg:address":"629 Cedar Creek Grade",
    "sg:city":"Winchester",
    "sg:classifiers":[
        {
            "category":"Professional",
            "subcategory":"Business Services",
            "type":"Services"
        }
    ],
    "sg:phone":"+1 540 665 8057",
    "sg:postcode":"22601",
    "sg:province":"VA",
    "sg:tags":[
        "company",
        "holding"
    ],
    "wof:name":"Amsec Enterprises LLC",
    "wof:placetype":"venue"
},
  "geometry": {"coordinates":[-78.188096,39.162991],"type":"Point"}
}