{
  "type": "Feature",
  "properties": {
    "iso:country":"US",
    "sg:address":"4604 Pinecrest Office Park Dr Office Par",
    "sg:city":"Alexandria",
    "sg:classifiers":[
        {
            "category":"Banks & Credit Unions",
            "subcategory":"Investment Brokerage",
            "type":"Services"
        },
        {
            "category":"Insurance",
            "subcategory":"Hazard Insurance",
            "type":"Services"
        }
    ],
    "sg:phone":"+1 703 354 3501",
    "sg:postcode":"22312",
    "sg:province":"VA",
    "sg:tags":[
        "commercial",
        "agent",
        "business",
        "resume"
    ],
    "sg:website":"http://www.ashcraft-assoc.com",
    "wof:name":"Ashcraft Associates Insurance Agency",
    "wof:placetype":"venue"
},
  "geometry": {"coordinates":[-77.161007,38.824055],"type":"Point"}
}