{
  "type": "Feature",
  "properties": {
    "iso:country":"US",
    "sg:address":"245 First Colonial Rd",
    "sg:city":"Virginia Beach",
    "sg:classifiers":[
        {
            "category":"Education",
            "subcategory":"Vocational School",
            "type":"Public Place"
        }
    ],
    "sg:phone":"+1 757 425 0728",
    "sg:postcode":"23454",
    "sg:province":"VA",
    "sg:tags":[
        "training",
        "computer",
        "consulting"
    ],
    "wof:name":"Technotraining Inc",
    "wof:placetype":"venue"
},
  "geometry": {"coordinates":[-76.021068,36.846404],"type":"Point"}
}