{
  "type": "Feature",
  "properties": {
    "iso:country":"US",
    "sg:address":"202 Loyal Ln",
    "sg:city":"Newport News",
    "sg:classifiers":[
        {
            "category":"Professional",
            "subcategory":"Computer Services",
            "type":"Services"
        }
    ],
    "sg:phone":"+1 757 369 2857",
    "sg:postcode":"23602",
    "sg:province":"VA",
    "wof:name":"Oncall Computer Repair",
    "wof:placetype":"venue"
},
  "geometry": {"coordinates":[-76.547527,37.108596],"type":"Point"}
}