{
  "type": "Feature",
  "properties": {
    "iso:country":"US",
    "sg:address":"11418 Lilting Ln",
    "sg:city":"Fairfax Station",
    "sg:classifiers":[
        {
            "category":"Professional",
            "subcategory":"Accounting & Tax Preparation",
            "type":"Services"
        }
    ],
    "sg:phone":"+1 703 917 7490",
    "sg:postcode":"22039",
    "sg:province":"VA",
    "wof:name":"Phyllis Hunter",
    "wof:placetype":"venue"
},
  "geometry": {"coordinates":[-77.342643,38.770417],"type":"Point"}
}