{
  "type": "Feature",
  "properties": {
    "addr:full":"1203 S Main St Culpeper VA 22701",
    "addr:housenumber":"1203",
    "addr:postcode":"22701",
    "addr:street":"S Main St",
    "iso:country":"US",
    "sg:address":"1203 S Main St",
    "sg:city":"Culpeper",
    "sg:classifiers":[
        {
            "category":"Autos & Motor Vehicles",
            "subcategory":"Auto Supplies",
            "type":"Retail Goods"
        },
        {
            "category":"Wholesale",
            "subcategory":"Auto Parts",
            "type":"Manufacturing & Wholesale Goods"
        }
    ],
    "sg:phone":"+1 540 825 5250",
    "sg:postcode":"22701",
    "sg:province":"VA",
    "sg:tags":[
        "automobile"
    ],
    "wof:name":"Fisher Auto Parts Inc",
    "wof:placetype":"venue"
},
  "geometry": {"coordinates":[-77.99866299999999,38.466214],"type":"Point"}
}