{
  "type": "Feature",
  "properties": {
    "iso:country":"US",
    "sg:address":"2200 Mount Pleasant Rd",
    "sg:city":"Chesapeake",
    "sg:classifiers":[
        {
            "category":"Organizations",
            "subcategory":"Religious Organization",
            "type":"Services"
        }
    ],
    "sg:phone":"+1 757 482 0915",
    "sg:postcode":"23322",
    "sg:province":"VA",
    "wof:name":"St Thomas AME Zion Church",
    "wof:placetype":"venue"
},
  "geometry": {"coordinates":[-76.141679,36.7141],"type":"Point"}
}