{
  "type": "Feature",
  "properties": {
    "iso:country":"US",
    "sg:address":"2415 N Dearing St",
    "sg:city":"Alexandria",
    "sg:classifiers":[
        {
            "category":"Professional",
            "subcategory":"Management & Consulting",
            "type":"Services"
        }
    ],
    "sg:phone":"+1 703 820 0718",
    "sg:postcode":"22302",
    "sg:province":"VA",
    "sg:tags":[
        "business"
    ],
    "wof:name":"Service Excellence Group",
    "wof:placetype":"venue"
},
  "geometry": {"coordinates":[-77.093757,38.830314],"type":"Point"}
}