{
  "type": "Feature",
  "properties": {
    "addr:full":"18160 Constitution Hwy Orange VA 22960",
    "addr:housenumber":"18160",
    "addr:postcode":"22960",
    "addr:street":"Constitution Hwy",
    "iso:country":"US",
    "sg:address":"18160 Constitution Hwy",
    "sg:city":"Orange",
    "sg:classifiers":[
        {
            "category":"Food & Beverages",
            "subcategory":"Groceries & Convenience Stores",
            "type":"Retail Goods"
        }
    ],
    "sg:phone":"+1 540 672 5411",
    "sg:postcode":"22960",
    "sg:province":"VA",
    "wof:name":"Gas & Stuff",
    "wof:placetype":"venue"
},
  "geometry": {"coordinates":[-78.055989,38.242965],"type":"Point"}
}