{
  "type": "Feature",
  "properties": {
    "iso:country":"US",
    "sg:address":"4601B Pinecrest Office Park Dr",
    "sg:city":"Alexandria",
    "sg:classifiers":[
        {
            "category":"Professional",
            "subcategory":"Lawyer & Legal Services",
            "type":"Services"
        }
    ],
    "sg:phone":"+1 703 914 1155",
    "sg:postcode":"22312",
    "sg:province":"VA",
    "sg:tags":[
        "attorney",
        "law",
        "immigration",
        "plan"
    ],
    "wof:name":"Chun & Associates",
    "wof:placetype":"venue"
},
  "geometry": {"coordinates":[-77.161186,38.824219],"type":"Point"}
}