{
  "type": "Feature",
  "properties": {
    "iso:country":"US",
    "sg:address":"613 W Main St",
    "sg:city":"Wise",
    "sg:classifiers":[
        {
            "category":"Home & Garden",
            "subcategory":"Building Materials",
            "type":"Retail Goods"
        }
    ],
    "sg:phone":"+1 276 328 5046",
    "sg:postcode":"24293",
    "sg:province":"VA",
    "sg:tags":[
        "glass",
        "window",
        "plate"
    ],
    "wof:name":"Wise Glass & Mirror Inc",
    "wof:placetype":"venue"
},
  "geometry": {"coordinates":[-82.58791600000001,36.985167],"type":"Point"}
}