{
  "type": "Feature",
  "properties": {
    "addr:full":"5708 Ridgedale Dr Woodbridge VA 22193",
    "addr:housenumber":"5708",
    "addr:postcode":"22193",
    "addr:street":"Ridgedale Dr",
    "iso:country":"US",
    "sg:address":"5708 Ridgedale Dr",
    "sg:city":"Woodbridge",
    "sg:classifiers":[
        {
            "category":"Travel",
            "subcategory":"Travel Agent",
            "type":"Entertainment"
        }
    ],
    "sg:phone":"+1 703 670 7030",
    "sg:postcode":"22193",
    "sg:province":"VA",
    "sg:tags":[
        "agency",
        "bureau"
    ],
    "wof:name":"Cavero Group Inc",
    "wof:placetype":"venue"
},
  "geometry": {"coordinates":[-77.378918,38.652158],"type":"Point"}
}