{
  "type": "Feature",
  "properties": {
    "iso:country":"US",
    "sg:address":"3211 10th St N",
    "sg:city":"Arlington",
    "sg:classifiers":[
        {
            "category":"Retail",
            "subcategory":"Auto Repair",
            "type":"Services"
        }
    ],
    "sg:phone":"+1 703 243 6800",
    "sg:postcode":"22201",
    "sg:province":"VA",
    "sg:tags":[
        "repairing",
        "automobile"
    ],
    "wof:name":"J C Auto Bahn",
    "wof:placetype":"venue"
},
  "geometry": {"coordinates":[-77.097252,38.884569],"type":"Point"}
}