{
  "type": "Feature",
  "properties": {
    "addr:full":"4501 Wyatts Mill Rd Jarratt VA 23867",
    "addr:housenumber":"4501",
    "addr:postcode":"23867",
    "addr:street":"Wyatts Mill Rd",
    "iso:country":"US",
    "sg:address":"4501 Wyatts Mill Rd",
    "sg:city":"Jarratt",
    "sg:classifiers":[
        {
            "category":"Retail",
            "subcategory":"Auto Repair",
            "type":"Services"
        }
    ],
    "sg:phone":"+1 434 348 3559",
    "sg:postcode":"23867",
    "sg:province":"VA",
    "sg:tags":[
        "automotive"
    ],
    "wof:name":"R C Electric",
    "wof:placetype":"venue"
},
  "geometry": {"coordinates":[-77.55781899999999,36.829841],"type":"Point"}
}