{
  "type": "Feature",
  "properties": {
    "iso:country":"US",
    "sg:address":"2695 Fox Mountain Rd",
    "sg:city":"Elkton",
    "sg:classifiers":[
        {
            "category":"Building & Trades",
            "subcategory":"Construction",
            "type":"Services"
        }
    ],
    "sg:phone":"+1 540 298 2213",
    "sg:postcode":"22827",
    "sg:province":"VA",
    "sg:tags":[
        "house"
    ],
    "wof:name":"Bendanco Const Inc",
    "wof:placetype":"venue"
},
  "geometry": {"coordinates":[-78.574127,38.421176],"type":"Point"}
}