{
  "type": "Feature",
  "properties": {
    "addr:full":"201 S Glebe Rd Arlington VA 22204",
    "addr:housenumber":"201",
    "addr:postcode":"22204",
    "addr:street":"S Glebe Rd",
    "iso:country":"US",
    "sg:address":"201 S Glebe Rd",
    "sg:city":"Arlington",
    "sg:classifiers":[
        {
            "category":"Food & Beverages",
            "subcategory":"Groceries & Convenience Stores",
            "type":"Retail Goods"
        }
    ],
    "sg:phone":"+1 703 271 0646",
    "sg:postcode":"22204",
    "sg:province":"VA",
    "wof:name":"7-Eleven Food Stores",
    "wof:placetype":"venue"
},
  "geometry": {"coordinates":[-77.09760300000001,38.868401],"type":"Point"}
}