{
  "type": "Feature",
  "properties": {
    "iso:country":"US",
    "sg:address":"5522 Chesterfield Dr",
    "sg:city":"Richmond",
    "sg:classifiers":[
        {
            "category":"Retail",
            "subcategory":"Repair Shop",
            "type":"Services"
        }
    ],
    "sg:phone":"+1 540 982 7557",
    "sg:postcode":"23224",
    "sg:province":"VA",
    "sg:tags":[
        "related"
    ],
    "wof:name":"Henry's Mobile Repair Svc",
    "wof:placetype":"venue"
},
  "geometry": {"coordinates":[-77.49436300000001,37.487609],"type":"Point"}
}