{
  "type": "Feature",
  "properties": {
    "addr:full":"17336 Pickwick Dr Purcellville VA 20132",
    "addr:housenumber":"17336",
    "addr:postcode":"20132",
    "addr:street":"Pickwick Dr",
    "iso:country":"US",
    "sg:address":"17336 Pickwick Dr",
    "sg:city":"Purcellville",
    "sg:classifiers":[
        {
            "category":"Health Services",
            "subcategory":"Chiropractor",
            "type":"Services"
        }
    ],
    "sg:phone":"+1 540 338 0005",
    "sg:postcode":"20132",
    "sg:province":"VA",
    "wof:name":"Peter M Daddio DC",
    "wof:placetype":"venue"
},
  "geometry": {"coordinates":[-77.69695299999999,39.140472],"type":"Point"}
}