{
  "type": "Feature",
  "properties": {
    "iso:country":"US",
    "sg:address":"505 Southview Ter",
    "sg:city":"Christiansburg",
    "sg:classifiers":[
        {
            "category":"Banks & Credit Unions",
            "subcategory":"Financial Services",
            "type":"Services"
        }
    ],
    "sg:phone":"+1 540 382 8148",
    "sg:postcode":"24073",
    "sg:province":"VA",
    "sg:tags":[
        "management",
        "open",
        "investment"
    ],
    "wof:name":"Southview Management Co",
    "wof:placetype":"venue"
},
  "geometry": {"coordinates":[-80.390933,37.126649],"type":"Point"}
}