{
  "type": "Feature",
  "properties": {
    "addr:full":"203 3rd St Grottoes VA 24441",
    "addr:housenumber":"203",
    "addr:postcode":"24441",
    "addr:street":"3Rd St",
    "iso:country":"US",
    "sg:address":"203 3rd St",
    "sg:city":"Grottoes",
    "sg:classifiers":[
        {
            "category":"Personal",
            "subcategory":"Beauty Salon",
            "type":"Services"
        }
    ],
    "sg:phone":"+1 540 249 3003",
    "sg:postcode":"24441",
    "sg:province":"VA",
    "wof:name":"Andria's Elite Hair & Tanning",
    "wof:placetype":"venue"
},
  "geometry": {"coordinates":[-78.826706,38.262549],"type":"Point"}
}