{
  "type": "Feature",
  "properties": {
    "iso:country":"US",
    "sg:address":"512 Powell Ave E",
    "sg:city":"Big Stone Gap",
    "sg:classifiers":[
        {
            "category":"Health Services",
            "subcategory":"Optometrist",
            "type":"Services"
        }
    ],
    "sg:phone":"+1 276 523 2424",
    "sg:postcode":"24219",
    "sg:province":"VA",
    "wof:name":"Rob O D Sawyer",
    "wof:placetype":"venue"
},
  "geometry": {"coordinates":[-82.77615400000001,36.86994],"type":"Point"}
}