{
  "type": "Feature",
  "properties": {
    "iso:country":"US",
    "sg:address":"8905 Mathis Ave",
    "sg:city":"Manassas",
    "sg:classifiers":[
        {
            "category":"Autos & Motor Vehicles",
            "subcategory":"Automobile Sales",
            "type":"Retail Goods"
        }
    ],
    "sg:phone":"+1 703 330 8733",
    "sg:postcode":"20110",
    "sg:province":"VA",
    "sg:tags":[
        "car",
        "used"
    ],
    "wof:name":"Toy Store",
    "wof:placetype":"venue"
},
  "geometry": {"coordinates":[-77.46288300000001,38.76096],"type":"Point"}
}