{
  "type": "Feature",
  "properties": {
    "iso:country":"US",
    "sg:address":"1112 Azalea Garden Rd",
    "sg:city":"Norfolk",
    "sg:classifiers":[
        {
            "category":"Government",
            "subcategory":"Office",
            "type":"Public Place"
        }
    ],
    "sg:phone":"+1 757 441 5803",
    "sg:postcode":"23502",
    "sg:province":"VA",
    "sg:tags":[
        "village"
    ],
    "wof:name":"Norfolk Radio & Electronics",
    "wof:placetype":"venue"
},
  "geometry": {"coordinates":[-76.232511,36.856678],"type":"Point"}
}