{
  "type": "Feature",
  "properties": {
    "addr:full":"2526 Trophy Ln Reston VA 20191",
    "addr:housenumber":"2526",
    "addr:postcode":"20191",
    "addr:street":"Trophy Ln",
    "iso:country":"US",
    "sg:address":"2526 Trophy Ln",
    "sg:city":"Reston",
    "sg:classifiers":[
        {
            "category":"Shopping",
            "subcategory":"Computers & Home Electronics",
            "type":"Retail Goods"
        }
    ],
    "sg:phone":"+1 703 716 9090",
    "sg:postcode":"20191",
    "sg:province":"VA",
    "wof:name":"Delta Sales",
    "wof:placetype":"venue"
},
  "geometry": {"coordinates":[-77.364358,38.924844],"type":"Point"}
}