{
  "type": "Feature",
  "properties": {
    "iso:country":"US",
    "sg:address":"4009 Stowe Dr",
    "sg:city":"Richmond",
    "sg:classifiers":[
        {
            "category":"Building & Trades",
            "subcategory":"Construction",
            "type":"Services"
        }
    ],
    "sg:phone":"+1 804 304 2507",
    "sg:postcode":"23234",
    "sg:province":"VA",
    "sg:tags":[
        "dry wall",
        "contractor"
    ],
    "wof:name":"Wall Doctor",
    "wof:placetype":"venue"
},
  "geometry": {"coordinates":[-77.471982,37.465236],"type":"Point"}
}