{
  "type": "Feature",
  "properties": {
    "addr:full":"6719 Mallard Lake Dr Roanoke VA 24018",
    "addr:housenumber":"6719",
    "addr:postcode":"24018",
    "addr:street":"Mallard Lake Dr",
    "iso:country":"US",
    "sg:address":"6719 Mallard Lake Dr",
    "sg:city":"Roanoke",
    "sg:classifiers":[
        {
            "category":"Banks & Credit Unions",
            "subcategory":"Financial Services",
            "type":"Services"
        }
    ],
    "sg:phone":"+1 540 774 6018",
    "sg:postcode":"24018",
    "sg:province":"VA",
    "sg:tags":[
        "investor"
    ],
    "wof:name":"Clement Investment Properties",
    "wof:placetype":"venue"
},
  "geometry": {"coordinates":[-80.03845699999999,37.189815],"type":"Point"}
}