{
  "type": "Feature",
  "properties": {
    "addr:full":"6704 Emporia Ct Springfield VA 22152",
    "addr:housenumber":"6704",
    "addr:postcode":"22152",
    "addr:street":"Emporia Ct",
    "iso:country":"US",
    "sg:address":"6704 Emporia Ct",
    "sg:city":"Springfield",
    "sg:classifiers":[
        {
            "category":"Building & Trades",
            "subcategory":"Construction",
            "type":"Services"
        }
    ],
    "sg:phone":"+1 703 451 1717",
    "sg:postcode":"22152",
    "sg:province":"VA",
    "sg:tags":[
        "house"
    ],
    "wof:name":"Alw Home Improvements",
    "wof:placetype":"venue"
},
  "geometry": {"coordinates":[-77.224034,38.77216],"type":"Point"}
}