{
  "type": "Feature",
  "properties": {
    "addr:full":"1800 Bayberry Ct Ste 103 Richmond VA 23226",
    "addr:housenumber":"1800",
    "addr:postcode":"23226",
    "addr:street":"Bayberry Ct Ste 103",
    "iso:country":"US",
    "sg:address":"1800 Bayberry Ct Ste 103",
    "sg:city":"Richmond",
    "sg:classifiers":[
        {
            "category":"Professional",
            "subcategory":"Management & Consulting",
            "type":"Services"
        },
        {
            "category":"Banks & Credit Unions",
            "subcategory":"Financial Services",
            "type":"Services"
        }
    ],
    "sg:phone":"+1 804 484 1400",
    "sg:postcode":"23226",
    "sg:province":"VA",
    "sg:tags":[
        "consultant",
        "financing",
        "planning"
    ],
    "sg:website":"http://www.tfscapital.com",
    "wof:name":"T F S Capital",
    "wof:placetype":"venue"
},
  "geometry": {"coordinates":[-77.53147199999999,37.606785],"type":"Point"}
}