{
  "type": "Feature",
  "properties": {
    "addr:full":"4238 Wilson Blvd Ste 1222 Arlington VA 22203",
    "addr:housenumber":"4238;1222",
    "addr:postcode":"22203",
    "addr:street":"Wilson Blvd Ste",
    "iso:country":"US",
    "sg:address":"4238 Wilson Blvd Ste 1222",
    "sg:city":"Arlington",
    "sg:classifiers":[
        {
            "category":"Utilities",
            "subcategory":"Mobile Phone",
            "type":"Services"
        },
        {
            "category":"Shopping",
            "subcategory":"Mobile Phones",
            "type":"Retail Goods"
        },
        {
            "category":"Utilities",
            "subcategory":"Telephone",
            "type":"Services"
        },
        {
            "category":"Professional",
            "subcategory":"Computer Services",
            "type":"Services"
        }
    ],
    "sg:phone":"+1 703 243 7832",
    "sg:postcode":"22203",
    "sg:province":"VA",
    "sg:tags":[
        "telecommunication",
        "supply",
        "communication",
        "system",
        "wireless",
        "equipment",
        "cellular"
    ],
    "sg:website":"http://clickserve.dartsearch.net/link/click?lid=43000000308049899",
    "wof:name":"T-Mobile",
    "wof:placetype":"venue"
},
  "geometry": {"coordinates":[-77.111557,38.880051],"type":"Point"}
}