{
  "type": "Feature",
  "properties": {
    "iso:country":"US",
    "sg:address":"537 E Moreell Cir",
    "sg:city":"Norfolk",
    "sg:classifiers":[
        {
            "category":"Shopping",
            "subcategory":"Computers & Home Electronics",
            "type":"Retail Goods"
        }
    ],
    "sg:phone":"+1 757 216 8285",
    "sg:postcode":"23505",
    "sg:province":"VA",
    "sg:tags":[
        "resellers",
        "system",
        "value"
    ],
    "wof:name":"Ess",
    "wof:placetype":"venue"
},
  "geometry": {"coordinates":[-76.30914799999999,36.925717],"type":"Point"}
}