{
  "type": "Feature",
  "properties": {
    "addr:full":"4217 Mechanicsville Tpke Mechanicsville VA 23111",
    "addr:housenumber":"4217",
    "addr:postcode":"23111",
    "addr:street":"Mechanicsville Tpke",
    "iso:country":"US",
    "sg:address":"4217 Mechanicsville Tpke",
    "sg:city":"Mechanicsville",
    "sg:classifiers":[
        {
            "category":"Autos & Motor Vehicles",
            "subcategory":"Boat Sales",
            "type":"Retail Goods"
        }
    ],
    "sg:phone":"+1 804 779 2727",
    "sg:postcode":"23111",
    "sg:province":"VA",
    "sg:tags":[
        "repair"
    ],
    "wof:name":"Arvis Marine",
    "wof:placetype":"venue"
},
  "geometry": {"coordinates":[-77.244018,37.647479],"type":"Point"}
}