{
  "type": "Feature",
  "properties": {
    "addr:full":"722 Grant St Herndon VA 20170",
    "addr:housenumber":"722",
    "addr:postcode":"20170",
    "addr:street":"Grant St",
    "iso:country":"US",
    "sg:address":"722 Grant St",
    "sg:city":"Herndon",
    "sg:classifiers":[
        {
            "category":"Health Services",
            "subcategory":"Doctor",
            "type":"Services"
        }
    ],
    "sg:phone":"+1 703 642 8722",
    "sg:postcode":"20170",
    "sg:province":"VA",
    "sg:tags":[
        "physician",
        "surgeon"
    ],
    "wof:name":"Dr Daniel Lee",
    "wof:placetype":"venue"
},
  "geometry": {"coordinates":[-77.379245,38.969601],"type":"Point"}
}