{
  "type": "Feature",
  "properties": {
    "iso:country":"US",
    "sg:address":"4029 Rolling Rd",
    "sg:city":"Scottsville",
    "sg:classifiers":[
        {
            "category":"Professional",
            "subcategory":"Management & Consulting",
            "type":"Services"
        }
    ],
    "sg:phone":"+1 434 296 3335",
    "sg:postcode":"24590",
    "sg:province":"VA",
    "sg:tags":[
        "business"
    ],
    "wof:name":"J W K International Corp",
    "wof:placetype":"venue"
},
  "geometry": {"coordinates":[-78.4482,37.924891],"type":"Point"}
}