{
  "type": "Feature",
  "properties": {
    "addr:full":"562 Seatons Ln West Point VA 23181",
    "addr:housenumber":"562",
    "addr:postcode":"23181",
    "addr:street":"Seatons Ln",
    "iso:country":"US",
    "sg:address":"562 Seatons Ln",
    "sg:city":"West Point",
    "sg:classifiers":[
        {
            "category":"Professional",
            "subcategory":"Advertising",
            "type":"Services"
        }
    ],
    "sg:phone":"+1 804 843 3368",
    "sg:postcode":"23181",
    "sg:province":"VA",
    "sg:tags":[
        "agency"
    ],
    "wof:name":"Young & Rubicam Inc",
    "wof:placetype":"venue"
},
  "geometry": {"coordinates":[-76.88453199999999,37.593613],"type":"Point"}
}