{
  "type": "Feature",
  "properties": {
    "addr:full":"3915 New Market Rd Richmond VA 23231",
    "addr:housenumber":"3915",
    "addr:postcode":"23231",
    "addr:street":"New Market Rd",
    "iso:country":"US",
    "sg:address":"3915 New Market Rd",
    "sg:city":"Richmond",
    "sg:classifiers":[
        {
            "category":"Personal",
            "subcategory":"Beauty Salon",
            "type":"Services"
        }
    ],
    "sg:phone":"+1 804 795 1805",
    "sg:postcode":"23231",
    "sg:province":"VA",
    "sg:tags":[
        "shop"
    ],
    "wof:name":"Cindy's Hair Matters",
    "wof:placetype":"venue"
},
  "geometry": {"coordinates":[-77.307327,37.427379],"type":"Point"}
}