{
  "type": "Feature",
  "properties": {
    "addr:full":"135 Buckingham Cir Charlottesville VA 22903",
    "addr:housenumber":"135",
    "addr:postcode":"22903",
    "addr:street":"Buckingham Cir",
    "iso:country":"US",
    "sg:address":"135 Buckingham Cir",
    "sg:city":"Charlottesville",
    "sg:classifiers":[
        {
            "category":"Building & Trades",
            "subcategory":"Construction",
            "type":"Services"
        }
    ],
    "sg:phone":"+1 434 971 8243",
    "sg:postcode":"22903",
    "sg:province":"VA",
    "sg:tags":[
        "contractor"
    ],
    "wof:name":"J Herring Masonry",
    "wof:placetype":"venue"
},
  "geometry": {"coordinates":[-78.53121,38.027014],"type":"Point"}
}