{
  "type": "Feature",
  "properties": {
    "iso:country":"US",
    "sg:address":"2707 Westminister Pl",
    "sg:city":"Alexandria",
    "sg:classifiers":[
        {
            "category":"Professional",
            "subcategory":"Lawyer & Legal Services",
            "type":"Services"
        }
    ],
    "sg:phone":"+1 703 548 3754",
    "sg:postcode":"22305",
    "sg:province":"VA",
    "wof:name":"Pro Ethics Ltd",
    "wof:placetype":"venue"
},
  "geometry": {"coordinates":[-77.072399,38.82957],"type":"Point"}
}