{
  "type": "Feature",
  "properties": {
    "addr:full":"99 Bell Ave Pulaski VA 24301",
    "addr:housenumber":"99",
    "addr:postcode":"24301",
    "addr:street":"Bell Ave",
    "iso:country":"US",
    "sg:address":"99 Bell Ave",
    "sg:city":"Pulaski",
    "sg:classifiers":[
        {
            "category":"Personal",
            "subcategory":"Beauty Salon",
            "type":"Services"
        }
    ],
    "sg:phone":"+1 540 980 3530",
    "sg:postcode":"24301",
    "sg:province":"VA",
    "wof:name":"Kim's Family Hair Care",
    "wof:placetype":"venue"
},
  "geometry": {"coordinates":[-80.770044,37.047647],"type":"Point"}
}