{
  "type": "Feature",
  "properties": {
    "iso:country":"US",
    "sg:address":"3714 Campbell Ave",
    "sg:city":"Lynchburg",
    "sg:classifiers":[
        {
            "category":"Building & Trades",
            "subcategory":"Pest Control",
            "type":"Services"
        }
    ],
    "sg:phone":"+1 434 846 2747",
    "sg:postcode":"24501",
    "sg:province":"VA",
    "sg:tags":[
        "repellent",
        "bird",
        "barrier"
    ],
    "wof:name":"Dodson Bros Extermination Co",
    "wof:placetype":"venue"
},
  "geometry": {"coordinates":[-79.13588,37.381312],"type":"Point"}
}