{
  "type": "Feature",
  "properties": {
    "iso:country":"US",
    "sg:address":"14800 Washington St",
    "sg:city":"Haymarket",
    "sg:classifiers":[
        {
            "category":"Social Services",
            "subcategory":"Child Care",
            "type":"Services"
        }
    ],
    "sg:phone":"+1 703 753 9561",
    "sg:postcode":"20169",
    "sg:province":"VA",
    "sg:tags":[
        "elementary",
        "kindergarten",
        "school",
        "academic"
    ],
    "sg:website":"www.haymarketbaptistchurch.org",
    "wof:name":"Haymarket Baptist Pre-School",
    "wof:placetype":"venue"
},
  "geometry": {"coordinates":[-77.632896,38.8106],"type":"Point"}
}