{
  "type": "Feature",
  "properties": {
    "addr:full":"10301 Midlothian Tpke Richmond VA 23235",
    "addr:housenumber":"10301",
    "addr:postcode":"23235",
    "addr:street":"Midlothian Tpke",
    "iso:country":"US",
    "sg:address":"10301 Midlothian Tpke",
    "sg:city":"Richmond",
    "sg:classifiers":[
        {
            "category":"Restaurant",
            "type":"Food & Drink"
        }
    ],
    "sg:menulink":"http://www.allmenus.com/va/clover-hill/272823-tgi-fridays/menu/",
    "sg:phone":"+1 804 330 0203",
    "sg:postcode":"23235",
    "sg:province":"VA",
    "sg:tags":[
        "american"
    ],
    "wof:name":"TGI Friday's",
    "wof:placetype":"venue"
},
  "geometry": {"coordinates":[-77.58615899999999,37.506578],"type":"Point"}
}