{
  "type": "Feature",
  "properties": {
    "addr:full":"221 S Loudoun St Strasburg VA 22657",
    "addr:housenumber":"221",
    "addr:postcode":"22657",
    "addr:street":"S Loudoun St",
    "iso:country":"US",
    "sg:address":"221 S Loudoun St",
    "sg:city":"Strasburg",
    "sg:classifiers":[
        {
            "category":"Government",
            "subcategory":"Office",
            "type":"Public Place"
        }
    ],
    "sg:phone":"+1 540 722 2115",
    "sg:postcode":"22657",
    "sg:province":"VA",
    "sg:tags":[
        "management"
    ],
    "wof:name":"Steve Nicholson",
    "wof:placetype":"venue"
},
  "geometry": {"coordinates":[-78.35067100000001,38.985158],"type":"Point"}
}