{
  "type": "Feature",
  "properties": {
    "iso:country":"US",
    "sg:address":"3556 Brambleton Ave",
    "sg:city":"Roanoke",
    "sg:classifiers":[
        {
            "category":"Home & Garden",
            "subcategory":"Carpets & Floor Coverings",
            "type":"Retail Goods"
        }
    ],
    "sg:phone":"+1 540 772 3055",
    "sg:postcode":"24018",
    "sg:province":"VA",
    "wof:name":"Elite Flooring Inc",
    "wof:placetype":"venue"
},
  "geometry": {"coordinates":[-80.00075200000001,37.237304],"type":"Point"}
}