{
  "type": "Feature",
  "properties": {
    "addr:full":"1872 Rio Hill Ctr Charlottesville VA 22901",
    "addr:housenumber":"1872",
    "addr:postcode":"22901",
    "addr:street":"Rio Hill",
    "iso:country":"US",
    "sg:address":"1872 Rio Hill Ctr",
    "sg:city":"Charlottesville",
    "sg:classifiers":[
        {
            "category":"Shopping",
            "subcategory":"Clothing, Apparel, & Fashions",
            "type":"Retail Goods"
        }
    ],
    "sg:phone":"+1 434 973 9686",
    "sg:postcode":"22901",
    "sg:province":"VA",
    "sg:tags":[
        "accessory"
    ],
    "wof:name":"Dress Barn the",
    "wof:placetype":"venue"
},
  "geometry": {"coordinates":[-78.471199,38.0877],"type":"Point"}
}