{
  "type": "Feature",
  "properties": {
    "addr:full":"11032 Oakton Rd Oakton VA 22124",
    "addr:housenumber":"11032",
    "addr:postcode":"22124",
    "addr:street":"Oakton Rd",
    "iso:country":"US",
    "sg:address":"11032 Oakton Rd",
    "sg:city":"Oakton",
    "sg:classifiers":[
        {
            "category":"Organizations",
            "subcategory":"Religious Organization",
            "type":"Services"
        }
    ],
    "sg:phone":"+1 703 385 8516",
    "sg:postcode":"22124",
    "sg:province":"VA",
    "sg:tags":[
        "church"
    ],
    "wof:name":"Korean Fellowship Baptist Chr",
    "wof:placetype":"venue"
},
  "geometry": {"coordinates":[-77.328422,38.870419],"type":"Point"}
}