{
  "type": "Feature",
  "properties": {
    "iso:country":"US",
    "sg:address":"8503 Middle Run Dr",
    "sg:city":"Springfield",
    "sg:classifiers":[
        {
            "category":"Professional",
            "type":"Services"
        }
    ],
    "sg:phone":"+1 703 644 3169",
    "sg:postcode":"22153",
    "sg:province":"VA",
    "wof:name":"Steve Hudson",
    "wof:placetype":"venue"
},
  "geometry": {"coordinates":[-77.238429,38.745703],"type":"Point"}
}