{
  "type": "Feature",
  "properties": {
    "addr:full":"34150 Parker Rd Locust Grove VA 22508",
    "addr:housenumber":"34150",
    "addr:postcode":"22508",
    "addr:street":"Parker Rd",
    "iso:country":"US",
    "sg:address":"34150 Parker Rd",
    "sg:city":"Locust Grove",
    "sg:classifiers":[
        {
            "category":"Manufacturing",
            "subcategory":"Furniture",
            "type":"Manufacturing & Wholesale Goods"
        },
        {
            "category":"Home & Garden",
            "subcategory":"Furniture",
            "type":"Retail Goods"
        }
    ],
    "sg:phone":"+1 540 854 0097",
    "sg:postcode":"22508",
    "sg:province":"VA",
    "sg:tags":[
        "household",
        "wood",
        "cabinet",
        "mfg"
    ],
    "wof:name":"Williams Cabinet Co",
    "wof:placetype":"venue"
},
  "geometry": {"coordinates":[-77.782076,38.290777],"type":"Point"}
}