{
  "type": "Feature",
  "properties": {
    "addr:full":"9410 Wellington Rd Manassas VA 20110",
    "addr:housenumber":"9410",
    "addr:postcode":"20110",
    "addr:street":"Wellington Rd",
    "iso:country":"US",
    "sg:address":"9410 Wellington Rd",
    "sg:city":"Manassas",
    "sg:classifiers":[
        {
            "category":"Retail",
            "subcategory":"Repair Shop",
            "type":"Services"
        }
    ],
    "sg:phone":"+1 703 366 3691",
    "sg:postcode":"20110",
    "sg:province":"VA",
    "sg:tags":[
        "broadcast",
        "satellite",
        "direct"
    ],
    "wof:name":"Ace Dish",
    "wof:placetype":"venue"
},
  "geometry": {"coordinates":[-77.490385,38.74958],"type":"Point"}
}