{
  "type": "Feature",
  "properties": {
    "iso:country":"US",
    "sg:address":"8150 Leesburg Pike Ste 1230",
    "sg:city":"Vienna",
    "sg:classifiers":[
        {
            "category":"Banks & Credit Unions",
            "subcategory":"Financial Services",
            "type":"Services"
        }
    ],
    "sg:phone":"+1 703 288 9650",
    "sg:postcode":"22182",
    "sg:province":"VA",
    "sg:tags":[
        "broker",
        "mortgage"
    ],
    "wof:name":"Pinnacle Financial Corp",
    "wof:placetype":"venue"
},
  "geometry": {"coordinates":[-77.22668,38.916169],"type":"Point"}
}