{
  "type": "Feature",
  "properties": {
    "addr:full":"11401 Vaughan Rd Petersburg VA 23805",
    "addr:housenumber":"11401",
    "addr:postcode":"23805",
    "addr:street":"Vaughan Rd",
    "iso:country":"US",
    "sg:address":"11401 Vaughan Rd",
    "sg:city":"Petersburg",
    "sg:classifiers":[
        {
            "category":"Farming",
            "subcategory":"Livestock Farm",
            "type":"Manufacturing & Wholesale Goods"
        }
    ],
    "sg:phone":"+1 804 733 3813",
    "sg:postcode":"23805",
    "sg:province":"VA",
    "sg:tags":[
        "beef",
        "feedlot",
        "cattle"
    ],
    "wof:name":"Ramon Zitta",
    "wof:placetype":"venue"
},
  "geometry": {"coordinates":[-77.473197,37.116519],"type":"Point"}
}