{
  "type": "Feature",
  "properties": {
    "iso:country":"US",
    "sg:address":"104 Courtland Dr",
    "sg:city":"Vinton",
    "sg:classifiers":[
        {
            "category":"Building & Trades",
            "subcategory":"Landscaping Services",
            "type":"Services"
        }
    ],
    "sg:phone":"+1 540 890 5532",
    "sg:postcode":"24179",
    "sg:province":"VA",
    "sg:tags":[
        "mowing"
    ],
    "wof:name":"Debos Mowing & Lawn Care",
    "wof:placetype":"venue"
},
  "geometry": {"coordinates":[-79.767895,37.301855],"type":"Point"}
}