{
  "type": "Feature",
  "properties": {
    "addr:full":"2032 N Taylor St Arlington VA 22207",
    "addr:housenumber":"2032",
    "addr:postcode":"22207",
    "addr:street":"N Taylor St",
    "iso:country":"US",
    "sg:address":"2032 N Taylor St",
    "sg:city":"Arlington",
    "sg:classifiers":[
        {
            "category":"Government",
            "subcategory":"Office",
            "type":"Public Place"
        }
    ],
    "sg:phone":"+1 703 525 5747",
    "sg:postcode":"22207",
    "sg:province":"VA",
    "sg:tags":[
        "international",
        "affairs"
    ],
    "wof:name":"Miw",
    "wof:placetype":"venue"
},
  "geometry": {"coordinates":[-77.113375,38.895156],"type":"Point"}
}