{
  "type": "Feature",
  "properties": {
    "iso:country":"US",
    "sg:address":"320 King St Ste 5",
    "sg:city":"Alexandria",
    "sg:classifiers":[
        {
            "category":"Banks & Credit Unions",
            "subcategory":"Financial Services",
            "type":"Services"
        },
        {
            "category":"Insurance",
            "subcategory":"Title Insurance",
            "type":"Services"
        },
        {
            "category":"Real Estate",
            "subcategory":"Real Estate Services",
            "type":"Services"
        }
    ],
    "sg:phone":"+1 703 842 7525",
    "sg:postcode":"22314",
    "sg:province":"VA",
    "sg:tags":[
        "escrow"
    ],
    "wof:name":"Absolute Title & Escrow",
    "wof:placetype":"venue"
},
  "geometry": {"coordinates":[-77.042761,38.804527],"type":"Point"}
}