{
  "type": "Feature",
  "properties": {
    "addr:full":"1710 Maple Shade Ln Richmond VA 23227",
    "addr:housenumber":"1710",
    "addr:postcode":"23227",
    "addr:street":"Maple Shade Ln",
    "iso:country":"US",
    "sg:address":"1710 Maple Shade Ln",
    "sg:city":"Richmond",
    "sg:classifiers":[
        {
            "category":"Professional",
            "subcategory":"Management & Consulting",
            "type":"Services"
        }
    ],
    "sg:phone":"+1 804 340 0034",
    "sg:postcode":"23227",
    "sg:province":"VA",
    "sg:tags":[
        "consultant",
        "business"
    ],
    "wof:name":"Jaymar Consulting Inc",
    "wof:placetype":"venue"
},
  "geometry": {"coordinates":[-77.463444,37.582012],"type":"Point"}
}