{
  "type": "Feature",
  "properties": {
    "addr:full":"512 Warrick Rd Chesapeake VA 23322",
    "addr:housenumber":"512",
    "addr:postcode":"23322",
    "addr:street":"Warrick Rd",
    "iso:country":"US",
    "sg:address":"512 Warrick Rd",
    "sg:city":"Chesapeake",
    "sg:classifiers":[
        {
            "category":"Building & Trades",
            "subcategory":"Construction",
            "type":"Services"
        }
    ],
    "sg:phone":"+1 757 436 9476",
    "sg:postcode":"23322",
    "sg:province":"VA",
    "sg:tags":[
        "house"
    ],
    "wof:name":"Gary E Royse Sr",
    "wof:placetype":"venue"
},
  "geometry": {"coordinates":[-76.268314,36.7033],"type":"Point"}
}