{
  "type": "Feature",
  "properties": {
    "addr:full":"1120 Chestnut Mountain Dr Vinton VA 24179",
    "addr:housenumber":"1120",
    "addr:postcode":"24179",
    "addr:street":"Chestnut Mountain Dr",
    "iso:country":"US",
    "sg:address":"1120 Chestnut Mountain Dr",
    "sg:city":"Vinton",
    "sg:classifiers":[
        {
            "category":"Building & Trades",
            "subcategory":"Construction",
            "type":"Services"
        }
    ],
    "sg:phone":"+1 540 890 4100",
    "sg:postcode":"24179",
    "sg:province":"VA",
    "sg:tags":[
        "contractor"
    ],
    "wof:name":"Wade Construction",
    "wof:placetype":"venue"
},
  "geometry": {"coordinates":[-79.84998899999999,37.275913],"type":"Point"}
}