{
  "type": "Feature",
  "properties": {
    "iso:country":"US",
    "sg:address":"8348 US Hwy 29",
    "sg:city":"Blairs",
    "sg:phone":"+1 434 836 0173",
    "sg:postcode":"24527",
    "sg:province":"VA",
    "sg:tags":[
        "farm",
        "tobacco"
    ],
    "wof:name":"Randy Yates",
    "wof:placetype":"venue"
},
  "geometry": {"coordinates":[-79.37873999999999,36.715647],"type":"Point"}
}