{
  "type": "Feature",
  "properties": {
    "addr:full":"1204 Birdneck Lake Dr Virginia Beach VA 23451",
    "addr:housenumber":"1204",
    "addr:postcode":"23451",
    "addr:street":"Birdneck Lake Dr",
    "iso:country":"US",
    "sg:address":"1204 Birdneck Lake Dr",
    "sg:city":"Virginia Beach",
    "sg:classifiers":[
        {
            "category":"Shopping",
            "subcategory":"Beauty & Cosmetics",
            "type":"Retail Goods"
        }
    ],
    "sg:phone":"+1 757 437 2292",
    "sg:postcode":"23451",
    "sg:province":"VA",
    "sg:tags":[
        "food",
        "merchandise"
    ],
    "wof:name":"Arbonne International",
    "wof:placetype":"venue"
},
  "geometry": {"coordinates":[-75.989317,36.806274],"type":"Point"}
}