{
  "type": "Feature",
  "properties": {
    "addr:full":"701 Church St Blackstone VA 23824",
    "addr:housenumber":"701",
    "addr:postcode":"23824",
    "addr:street":"Church St",
    "iso:country":"US",
    "sg:address":"701 Church St",
    "sg:city":"Blackstone",
    "sg:classifiers":[
        {
            "category":"Real Estate",
            "subcategory":"Real Estate Operator",
            "type":"Services"
        }
    ],
    "sg:phone":"+1 434 292 5989",
    "sg:postcode":"23824",
    "sg:province":"VA",
    "sg:tags":[
        "apartment"
    ],
    "wof:name":"Magnolia Place",
    "wof:placetype":"venue"
},
  "geometry": {"coordinates":[-78.01158599999999,37.078274],"type":"Point"}
}