{
  "type": "Feature",
  "properties": {
    "addr:full":"9011 Arboretum Pkwy Richmond VA 23236",
    "addr:postcode":"9011;23236",
    "addr:street":"Arboretum Pkwy",
    "iso:country":"US",
    "sg:address":"9011 Arboretum Pkwy",
    "sg:city":"Richmond",
    "sg:classifiers":[
        {
            "category":"Utilities",
            "subcategory":"Mobile Phone",
            "type":"Services"
        }
    ],
    "sg:phone":"+1 804 327 5335",
    "sg:postcode":"23236",
    "sg:province":"VA",
    "sg:tags":[
        "telephone",
        "cellular"
    ],
    "wof:name":"United States Cellular Corp",
    "wof:placetype":"venue"
},
  "geometry": {"coordinates":[-77.56544599999999,37.492111],"type":"Point"}
}