{
  "type": "Feature",
  "properties": {
    "iso:country":"US",
    "sg:address":"157 Plaza Rd SW",
    "sg:city":"Wise",
    "sg:classifiers":[
        {
            "category":"Banks & Credit Unions",
            "subcategory":"Bank",
            "type":"Services"
        }
    ],
    "sg:phone":"+1 276 679 0842",
    "sg:postcode":"24293",
    "sg:province":"VA",
    "sg:tags":[
        "personal",
        "financing",
        "institution"
    ],
    "wof:name":"American General Finance Corp",
    "wof:placetype":"venue"
},
  "geometry": {"coordinates":[-82.597055,36.970945],"type":"Point"}
}