{
  "type": "Feature",
  "properties": {
    "iso:country":"US",
    "sg:address":"17218 Pittman Rd",
    "sg:city":"Boykins",
    "sg:classifiers":[
        {
            "category":"Organizations",
            "subcategory":"Religious Organization",
            "type":"Services"
        }
    ],
    "sg:phone":"+1 757 654 0880",
    "sg:postcode":"23827",
    "sg:province":"VA",
    "sg:tags":[
        "church"
    ],
    "wof:name":"New Day Christian Ctr",
    "wof:placetype":"venue"
},
  "geometry": {"coordinates":[-77.214608,36.578491],"type":"Point"}
}