{
  "type": "Feature",
  "properties": {
    "addr:full":"3114 Knox St Portsmouth VA 23704",
    "addr:housenumber":"3114",
    "addr:postcode":"23704",
    "addr:street":"Knox St",
    "iso:country":"US",
    "sg:address":"3114 Knox St",
    "sg:city":"Portsmouth",
    "sg:classifiers":[
        {
            "category":"Organizations",
            "subcategory":"Religious Organization",
            "type":"Services"
        }
    ],
    "sg:phone":"+1 757 399 5464",
    "sg:postcode":"23704",
    "sg:province":"VA",
    "sg:tags":[
        "clergy"
    ],
    "wof:name":"Joseph L Faulk",
    "wof:placetype":"venue"
},
  "geometry": {"coordinates":[-76.330169,36.819095],"type":"Point"}
}