{
  "type": "Feature",
  "properties": {
    "addr:full":"419 Yale Dr Hampton VA 23666",
    "addr:housenumber":"419",
    "addr:postcode":"23666",
    "addr:street":"Yale Dr",
    "iso:country":"US",
    "sg:address":"419 Yale Dr",
    "sg:city":"Hampton",
    "sg:classifiers":[
        {
            "category":"Manufacturing",
            "subcategory":"Retail Goods",
            "type":"Manufacturing & Wholesale Goods"
        }
    ],
    "sg:phone":"+1 757 826 2700",
    "sg:postcode":"23666",
    "sg:province":"VA",
    "sg:tags":[
        "product",
        "mfg"
    ],
    "wof:name":"Design Svc",
    "wof:placetype":"venue"
},
  "geometry": {"coordinates":[-76.422996,37.030197],"type":"Point"}
}