{
  "type": "Feature",
  "properties": {
    "iso:country":"US",
    "sg:address":"4050 Riverside Dr",
    "sg:city":"Danville",
    "sg:classifiers":[
        {
            "category":"Autos & Motor Vehicles",
            "subcategory":"Automobile Sales",
            "type":"Retail Goods"
        }
    ],
    "sg:phone":"+1 434 793 7901",
    "sg:postcode":"24541",
    "sg:province":"VA",
    "sg:tags":[
        "car",
        "dealer"
    ],
    "sg:website":"www.johnhoover.com",
    "wof:name":"John Hoover Honda",
    "wof:placetype":"venue"
},
  "geometry": {"coordinates":[-79.438582,36.58074],"type":"Point"}
}