{
  "type": "Feature",
  "properties": {
    "iso:country":"US",
    "sg:address":"936 Independence Blvd",
    "sg:city":"Virginia Beach",
    "sg:classifiers":[
        {
            "category":"Education",
            "subcategory":"Library",
            "type":"Public Place"
        }
    ],
    "sg:phone":"+1 757 460 7518",
    "sg:postcode":"23455",
    "sg:province":"VA",
    "sg:tags":[
        "executive"
    ],
    "wof:name":"Public Libraries",
    "wof:placetype":"venue"
},
  "geometry": {"coordinates":[-76.132859,36.868156],"type":"Point"}
}