{
  "type": "Feature",
  "properties": {
    "addr:full":"150 Hunts Neck Rd Poquoson VA 23662",
    "addr:housenumber":"150",
    "addr:postcode":"23662",
    "addr:street":"Hunts Neck Rd",
    "iso:country":"US",
    "sg:address":"150 Hunts Neck Rd",
    "sg:city":"Poquoson",
    "sg:classifiers":[
        {
            "category":"Building & Trades",
            "subcategory":"Construction",
            "type":"Services"
        }
    ],
    "sg:phone":"+1 757 868 8374",
    "sg:postcode":"23662",
    "sg:province":"VA",
    "sg:tags":[
        "house"
    ],
    "wof:name":"Paul Morse Sr Home Repair Inc",
    "wof:placetype":"venue"
},
  "geometry": {"coordinates":[-76.39553600000001,37.146678],"type":"Point"}
}