{
  "type": "Feature",
  "properties": {
    "addr:full":"15735 Porterfield Hwy Abingdon VA 24210",
    "addr:housenumber":"15735",
    "addr:postcode":"24210",
    "addr:street":"Porterfield Hwy",
    "iso:country":"US",
    "sg:address":"15735 Porterfield Hwy",
    "sg:city":"Abingdon",
    "sg:classifiers":[
        {
            "category":"Food & Beverages",
            "subcategory":"Candy",
            "type":"Retail Goods"
        }
    ],
    "sg:phone":"+1 276 676 0441",
    "sg:postcode":"24210",
    "sg:province":"VA",
    "sg:tags":[
        "confectionery"
    ],
    "wof:name":"Wholesale House Tobacco Outlet",
    "wof:placetype":"venue"
},
  "geometry": {"coordinates":[-82.016824,36.723034],"type":"Point"}
}