{
  "type": "Feature",
  "properties": {
    "addr:full":"136 Kempsville Rd Chesapeake VA 23320",
    "addr:housenumber":"136",
    "addr:postcode":"23320",
    "addr:street":"Kempsville Rd",
    "iso:country":"US",
    "sg:address":"136 Kempsville Rd",
    "sg:city":"Chesapeake",
    "sg:classifiers":[
        {
            "category":"Banks & Credit Unions",
            "subcategory":"Investment Brokerage",
            "type":"Services"
        }
    ],
    "sg:phone":"+1 757 547 8257",
    "sg:postcode":"23320",
    "sg:province":"VA",
    "sg:tags":[
        "advisory"
    ],
    "wof:name":"Advantage Investing Inc",
    "wof:placetype":"venue"
},
  "geometry": {"coordinates":[-76.23897100000001,36.733281],"type":"Point"}
}