{
  "type": "Feature",
  "properties": {
    "addr:full":"101 Charwood Dr Abingdon VA 24210",
    "addr:housenumber":"101",
    "addr:postcode":"24210",
    "addr:street":"Charwood Dr",
    "iso:country":"US",
    "sg:address":"101 Charwood Dr",
    "sg:city":"Abingdon",
    "sg:classifiers":[
        {
            "category":"Insurance",
            "subcategory":"Insurance Agent",
            "type":"Services"
        }
    ],
    "sg:phone":"+1 276 628 6970",
    "sg:postcode":"24210",
    "sg:province":"VA",
    "wof:name":"C R Gregory Insurance",
    "wof:placetype":"venue"
},
  "geometry": {"coordinates":[-82.005381,36.702504],"type":"Point"}
}