{
  "type": "Feature",
  "properties": {
    "addr:full":"2610 Fairystone Park Hwy Bassett VA 24055",
    "addr:housenumber":"2610",
    "addr:postcode":"24055",
    "addr:street":"Fairystone Park Hwy",
    "iso:country":"US",
    "sg:address":"2610 Fairystone Park Hwy",
    "sg:city":"Bassett",
    "sg:classifiers":[
        {
            "category":"Retail",
            "subcategory":"Auto Repair",
            "type":"Services"
        }
    ],
    "sg:phone":"+1 276 629 9070",
    "sg:postcode":"24055",
    "sg:province":"VA",
    "sg:tags":[
        "repairing",
        "automobile"
    ],
    "wof:name":"Elliott's Garage",
    "wof:placetype":"venue"
},
  "geometry": {"coordinates":[-79.978554,36.752935],"type":"Point"}
}