{
  "type": "Feature",
  "properties": {
    "addr:full":"210 Franklin Rd SW Roanoke VA 24011",
    "addr:housenumber":"210",
    "addr:postcode":"24011",
    "addr:street":"Franklin Rd Sw",
    "iso:country":"US",
    "sg:address":"210 Franklin Rd SW",
    "sg:city":"Roanoke",
    "sg:classifiers":[
        {
            "category":"Building & Trades",
            "subcategory":"Plumbing",
            "type":"Services"
        }
    ],
    "sg:phone":"+1 540 342 5242",
    "sg:postcode":"24011",
    "sg:province":"VA",
    "sg:tags":[
        "heating",
        "contractor"
    ],
    "wof:name":"Northern Management Svc Inc",
    "wof:placetype":"venue"
},
  "geometry": {"coordinates":[-79.944739,37.268692],"type":"Point"}
}