{
  "type": "Feature",
  "properties": {
    "addr:full":"11835 Fair Oaks Mall Fairfax VA 22033",
    "addr:housenumber":"11835",
    "addr:postcode":"22033",
    "addr:street":"Fair Oaks Mall",
    "iso:country":"US",
    "sg:address":"11835 Fair Oaks Mall",
    "sg:city":"Fairfax",
    "sg:classifiers":[
        {
            "category":"Home & Garden",
            "subcategory":"Furniture",
            "type":"Retail Goods"
        }
    ],
    "sg:phone":"+1 703 383 1990",
    "sg:postcode":"22033",
    "sg:province":"VA",
    "sg:tags":[
        "mattress"
    ],
    "wof:name":"Select Comfort Corp",
    "wof:placetype":"venue"
},
  "geometry": {"coordinates":[-77.35777400000001,38.860849],"type":"Point"}
}