{
  "type": "Feature",
  "properties": {
    "iso:country":"US",
    "sg:address":"473 US Hwy 23",
    "sg:city":"Weber City",
    "sg:classifiers":[
        {
            "category":"Utilities",
            "subcategory":"Fuel Oil & Lpg",
            "type":"Services"
        }
    ],
    "sg:phone":"+1 276 386 6241",
    "sg:postcode":"24290",
    "sg:province":"VA",
    "sg:tags":[
        "dealer"
    ],
    "wof:name":"Begley Rick Coal & Cnstr",
    "wof:placetype":"venue"
},
  "geometry": {"coordinates":[-82.553757,36.62855],"type":"Point"}
}