{
  "type": "Feature",
  "properties": {
    "iso:country":"US",
    "sg:address":"5006 Pheasant Ridge Rd",
    "sg:city":"Fairfax",
    "sg:classifiers":[
        {
            "category":"Shopping",
            "subcategory":"Bicycles & Sporting Goods",
            "type":"Retail Goods"
        }
    ],
    "sg:phone":"+1 703 988 9670",
    "sg:postcode":"22030",
    "sg:province":"VA",
    "sg:tags":[
        "equipment",
        "golf",
        "supply"
    ],
    "wof:name":"Caddie",
    "wof:placetype":"venue"
},
  "geometry": {"coordinates":[-77.370999,38.841269],"type":"Point"}
}