{
  "type": "Feature",
  "properties": {
    "iso:country":"US",
    "sg:address":"4312 Merlyn Walk Pl",
    "sg:city":"Newport News",
    "sg:classifiers":[
        {
            "category":"Building & Trades",
            "subcategory":"Construction",
            "type":"Services"
        }
    ],
    "sg:phone":"+1 757 872 0636",
    "sg:postcode":"23602",
    "sg:province":"VA",
    "sg:tags":[
        "handyman"
    ],
    "wof:name":"House To House Handyman Svc",
    "wof:placetype":"venue"
},
  "geometry": {"coordinates":[-76.53743,37.124851],"type":"Point"}
}