{
  "type": "Feature",
  "properties": {
    "addr:full":"2100 Station Rd Richmond VA 23234",
    "addr:housenumber":"2100",
    "addr:postcode":"23234",
    "addr:street":"Station Rd",
    "iso:country":"US",
    "sg:address":"2100 Station Rd",
    "sg:city":"Richmond",
    "sg:classifiers":[
        {
            "category":"Government",
            "subcategory":"Office",
            "type":"Public Place"
        }
    ],
    "sg:phone":"+1 804 275 0063",
    "sg:postcode":"23234",
    "sg:province":"VA",
    "wof:name":"Chesterfield County Sewage",
    "wof:placetype":"venue"
},
  "geometry": {"coordinates":[-77.436352,37.441411],"type":"Point"}
}