{
  "type": "Feature",
  "properties": {
    "addr:full":"5804 Saint George Ave Crozet VA 22932",
    "addr:housenumber":"5804",
    "addr:postcode":"22932",
    "addr:street":"Saint George Ave",
    "iso:country":"US",
    "sg:address":"5804 Saint George Ave",
    "sg:city":"Crozet",
    "sg:classifiers":[
        {
            "category":"Organizations",
            "subcategory":"Professional Association",
            "type":"Services"
        }
    ],
    "sg:phone":"+1 434 823 5171",
    "sg:postcode":"22932",
    "sg:province":"VA",
    "sg:tags":[
        "religious",
        "business"
    ],
    "sg:website":"www.crozetchurch.org",
    "wof:name":"Crozet Baptist Church",
    "wof:placetype":"venue"
},
  "geometry": {"coordinates":[-78.70246,38.07349],"type":"Point"}
}