{
  "type": "Feature",
  "properties": {
    "addr:full":"601 W 34th St Richmond VA 23225",
    "addr:housenumber":"601",
    "addr:postcode":"23225",
    "addr:street":"W 34Th St",
    "iso:country":"US",
    "sg:address":"601 W 34th St",
    "sg:city":"Richmond",
    "sg:classifiers":[
        {
            "category":"Personal",
            "type":"Services"
        }
    ],
    "sg:phone":"+1 804 440 5344",
    "sg:postcode":"23225",
    "sg:province":"VA",
    "sg:tags":[
        "consultant",
        "wedding"
    ],
    "wof:name":"At Any Event",
    "wof:placetype":"venue"
},
  "geometry": {"coordinates":[-77.47020500000001,37.517897],"type":"Point"}
}