{
  "type": "Feature",
  "properties": {
    "addr:full":"610 Sycamore St Glade Spring VA 24340",
    "addr:housenumber":"610",
    "addr:postcode":"24340",
    "addr:street":"Sycamore St",
    "iso:country":"US",
    "sg:address":"610 Sycamore St",
    "sg:city":"Glade Spring",
    "sg:classifiers":[
        {
            "category":"Professional",
            "subcategory":"Business Services",
            "type":"Services"
        }
    ],
    "sg:phone":"+1 276 429 4469",
    "sg:postcode":"24340",
    "sg:province":"VA",
    "sg:tags":[
        "translation"
    ],
    "wof:name":"Gail Orr",
    "wof:placetype":"venue"
},
  "geometry": {"coordinates":[-81.775991,36.785809],"type":"Point"}
}