{
  "type": "Feature",
  "properties": {
    "addr:full":"21 Haney Rd Waynesboro VA 22968",
    "addr:housenumber":"21",
    "addr:postcode":"22968",
    "addr:street":"Haney Rd",
    "iso:country":"US",
    "sg:address":"21 Haney Rd",
    "sg:city":"Waynesboro",
    "sg:classifiers":[
        {
            "category":"Banks & Credit Unions",
            "subcategory":"Investment Brokerage",
            "type":"Services"
        }
    ],
    "sg:phone":"+1 540 943 7665",
    "sg:postcode":"22968",
    "sg:province":"VA",
    "sg:tags":[
        "consultant",
        "planning",
        "financial"
    ],
    "wof:name":"American Express Financial Adv",
    "wof:placetype":"venue"
},
  "geometry": {"coordinates":[-78.39692100000001,38.260464],"type":"Point"}
}