{
  "type": "Feature",
  "properties": {
    "iso:country":"US",
    "sg:address":"413 Watkins St",
    "sg:city":"Emporia",
    "sg:classifiers":[
        {
            "category":"Building & Trades",
            "subcategory":"Landscaping Services",
            "type":"Services"
        }
    ],
    "sg:phone":"+1 434 348 0666",
    "sg:postcode":"23847",
    "sg:province":"VA",
    "sg:tags":[
        "tree"
    ],
    "wof:name":"Coker's Tree Svc",
    "wof:placetype":"venue"
},
  "geometry": {"coordinates":[-77.551636,36.683153],"type":"Point"}
}