{
  "type": "Feature",
  "properties": {
    "addr:full":"104 Morton St Franklin VA 23851",
    "addr:housenumber":"104",
    "addr:postcode":"23851",
    "addr:street":"Morton St",
    "iso:country":"US",
    "sg:address":"104 Morton St",
    "sg:city":"Franklin",
    "sg:classifiers":[
        {
            "category":"Personal",
            "subcategory":"Beauty Salon",
            "type":"Services"
        }
    ],
    "sg:phone":"+1 757 562 5939",
    "sg:postcode":"23851",
    "sg:province":"VA",
    "wof:name":"JMJ Hair",
    "wof:placetype":"venue"
},
  "geometry": {"coordinates":[-76.920179,36.663569],"type":"Point"}
}