{
  "type": "Feature",
  "properties": {
    "iso:country":"US",
    "sg:address":"6515 George Washington Memorial Hwy",
    "sg:city":"Yorktown",
    "sg:classifiers":[
        {
            "category":"Professional",
            "subcategory":"Accounting & Tax Preparation",
            "type":"Services"
        }
    ],
    "sg:phone":"+1 757 890 6000",
    "sg:postcode":"23692",
    "sg:province":"VA",
    "sg:tags":[
        "accountant",
        "return"
    ],
    "wof:name":"Alta Accounting Co",
    "wof:placetype":"venue"
},
  "geometry": {"coordinates":[-76.47377299999999,37.171292],"type":"Point"}
}