{
  "type": "Feature",
  "properties": {
    "addr:full":"1710 S Taylor St Arlington VA 22204",
    "addr:housenumber":"1710",
    "addr:postcode":"22204",
    "addr:street":"S Taylor St",
    "iso:country":"US",
    "sg:address":"1710 S Taylor St",
    "sg:city":"Arlington",
    "sg:classifiers":[
        {
            "category":"Education",
            "subcategory":"Special Training",
            "type":"Public Place"
        }
    ],
    "sg:phone":"+1 703 521 8900",
    "sg:postcode":"22204",
    "sg:province":"VA",
    "sg:tags":[
        "tutoring"
    ],
    "wof:name":"The Greenbrier Learning",
    "wof:placetype":"venue"
},
  "geometry": {"coordinates":[-77.100403,38.851898],"type":"Point"}
}