{
  "type": "Feature",
  "properties": {
    "iso:country":"US",
    "sg:address":"11300 Washington Hwy",
    "sg:city":"Ashland",
    "sg:classifiers":[
        {
            "category":"Wholesale",
            "subcategory":"Motor Vehicles",
            "type":"Manufacturing & Wholesale Goods"
        },
        {
            "category":"Personal",
            "type":"Services"
        },
        {
            "category":"Wholesale",
            "subcategory":"Scrap",
            "type":"Manufacturing & Wholesale Goods"
        }
    ],
    "sg:phone":"+1 804 798 5086",
    "sg:postcode":"23005",
    "sg:province":"VA",
    "sg:tags":[
        "automobile",
        "towing",
        "truck",
        "wrecking",
        "transporter"
    ],
    "wof:name":"ACE Towing & Recovery",
    "wof:placetype":"venue"
},
  "geometry": {"coordinates":[-77.46723900000001,37.712498],"type":"Point"}
}