{
  "type": "Feature",
  "properties": {
    "iso:country":"US",
    "sg:address":"702 N Parham Rd",
    "sg:city":"Richmond",
    "sg:classifiers":[
        {
            "category":"Health Services",
            "subcategory":"Hospital",
            "type":"Services"
        }
    ],
    "sg:phone":"+1 804 747 5656",
    "sg:postcode":"23229",
    "sg:province":"VA",
    "sg:tags":[
        "general"
    ],
    "wof:name":"Columbia HCA",
    "wof:placetype":"venue"
},
  "geometry": {"coordinates":[-77.572267,37.588718],"type":"Point"}
}