{
  "type": "Feature",
  "properties": {
    "iso:country":"US",
    "sg:address":"14654 Thomas Nelson Hwy",
    "sg:city":"Lovingston",
    "sg:classifiers":[
        {
            "category":"Organizations",
            "subcategory":"Religious Organization",
            "type":"Services"
        }
    ],
    "sg:phone":"+1 434 263 8842",
    "sg:postcode":"22949",
    "sg:province":"VA",
    "sg:tags":[
        "church"
    ],
    "wof:name":"Ridgecrest Baptist Church",
    "wof:placetype":"venue"
},
  "geometry": {"coordinates":[-78.836259,37.828399],"type":"Point"}
}