{
  "type": "Feature",
  "properties": {
    "addr:full":"7520 Aspenpark Rd Lorton VA 22079",
    "addr:housenumber":"7520",
    "addr:postcode":"22079",
    "addr:street":"Aspenpark Rd",
    "iso:country":"US",
    "sg:address":"7520 Aspenpark Rd",
    "sg:city":"Lorton",
    "sg:classifiers":[
        {
            "category":"Manufacturing",
            "subcategory":"Chemicals & Compounds",
            "type":"Manufacturing & Wholesale Goods"
        }
    ],
    "sg:phone":"+1 703 980 7168",
    "sg:postcode":"22079",
    "sg:province":"VA",
    "sg:tags":[
        "preparation",
        "pharmaceutical",
        "mfg"
    ],
    "wof:name":"Tech Farm Solutions",
    "wof:placetype":"venue"
},
  "geometry": {"coordinates":[-77.20181100000001,38.710273],"type":"Point"}
}