{
  "type": "Feature",
  "properties": {
    "addr:full":"1826 E Nine Mile Rd Highland Springs VA 23075",
    "addr:housenumber":"1826",
    "addr:postcode":"23075",
    "addr:street":"E Nine Mile Rd",
    "iso:country":"US",
    "sg:address":"1826 E Nine Mile Rd",
    "sg:city":"Highland Springs",
    "sg:classifiers":[
        {
            "category":"Autos & Motor Vehicles",
            "subcategory":"Auto Supplies",
            "type":"Retail Goods"
        }
    ],
    "sg:phone":"+1 804 737 5700",
    "sg:postcode":"23075",
    "sg:province":"VA",
    "wof:name":"South Auto Parts",
    "wof:placetype":"venue"
},
  "geometry": {"coordinates":[-77.313354,37.53078],"type":"Point"}
}