{
  "type": "Feature",
  "properties": {
    "addr:full":"2 Macirvin Dr Newport News VA 23606",
    "addr:housenumber":"2",
    "addr:postcode":"23606",
    "addr:street":"Macirvin Dr",
    "iso:country":"US",
    "sg:address":"2 Macirvin Dr",
    "sg:city":"Newport News",
    "sg:classifiers":[
        {
            "category":"Organizations",
            "subcategory":"Professional Association",
            "type":"Services"
        }
    ],
    "sg:phone":"+1 757 599 3575",
    "sg:postcode":"23606",
    "sg:province":"VA",
    "sg:tags":[
        "business"
    ],
    "wof:name":"Chamber Music Soc of Virginia",
    "wof:placetype":"venue"
},
  "geometry": {"coordinates":[-76.51296000000001,37.065763],"type":"Point"}
}