{
  "type": "Feature",
  "properties": {
    "addr:full":"3448 Herbert St Norfolk VA 23513",
    "addr:housenumber":"3448",
    "addr:postcode":"23513",
    "addr:street":"Herbert St",
    "iso:country":"US",
    "sg:address":"3448 Herbert St",
    "sg:city":"Norfolk",
    "sg:classifiers":[
        {
            "category":"Professional",
            "subcategory":"Computer Services",
            "type":"Services"
        }
    ],
    "sg:phone":"+1 757 852 9142",
    "sg:postcode":"23513",
    "sg:province":"VA",
    "sg:tags":[
        "web",
        "consumer",
        "information"
    ],
    "wof:name":"Wwwacestimatescom",
    "wof:placetype":"venue"
},
  "geometry": {"coordinates":[-76.231211,36.886113],"type":"Point"}
}