{
  "type": "Feature",
  "properties": {
    "iso:country":"US",
    "sg:address":"3192 Beechland Rd",
    "sg:city":"Elberon",
    "sg:phone":"+1 757 294 3043",
    "sg:postcode":"23846",
    "sg:province":"VA",
    "sg:tags":[
        "farm",
        "wheat"
    ],
    "wof:name":"Beechland Farms Inc",
    "wof:placetype":"venue"
},
  "geometry": {"coordinates":[-76.818335,37.089701],"type":"Point"}
}