{
  "type": "Feature",
  "properties": {
    "addr:full":"8124 Shore Dr Norfolk VA 23518",
    "addr:housenumber":"8124",
    "addr:postcode":"23518",
    "addr:street":"Shore Dr",
    "iso:country":"US",
    "sg:address":"8124 Shore Dr",
    "sg:city":"Norfolk",
    "sg:classifiers":[
        {
            "category":"Personal",
            "subcategory":"Beauty Salon",
            "type":"Services"
        }
    ],
    "sg:phone":"+1 757 583 3483",
    "sg:postcode":"23518",
    "sg:province":"VA",
    "wof:name":"East Beach Tanning & Nails",
    "wof:placetype":"venue"
},
  "geometry": {"coordinates":[-76.192117,36.921947],"type":"Point"}
}