{
  "type": "Feature",
  "properties": {
    "addr:full":"11916 Hull Street Rd Midlothian VA 23112",
    "addr:housenumber":"11916",
    "addr:postcode":"23112",
    "addr:street":"Hull Street Rd",
    "iso:country":"US",
    "sg:address":"11916 Hull Street Rd",
    "sg:city":"Midlothian",
    "sg:classifiers":[
        {
            "category":"Building & Trades",
            "subcategory":"Construction",
            "type":"Services"
        }
    ],
    "sg:phone":"+1 804 744 8797",
    "sg:postcode":"23112",
    "sg:province":"VA",
    "sg:tags":[
        "house",
        "improvement",
        "home"
    ],
    "wof:name":"M B I Home Improvement",
    "wof:placetype":"venue"
},
  "geometry": {"coordinates":[-77.614512,37.43242],"type":"Point"}
}