{
  "type": "Feature",
  "properties": {
    "addr:full":"2300 Hermitage Rd Richmond VA 23220",
    "addr:housenumber":"2300",
    "addr:postcode":"23220",
    "addr:street":"Hermitage Rd",
    "iso:country":"US",
    "sg:address":"2300 Hermitage Rd",
    "sg:city":"Richmond",
    "sg:classifiers":[
        {
            "category":"Building & Trades",
            "subcategory":"Construction",
            "type":"Services"
        }
    ],
    "sg:phone":"+1 804 355 2115",
    "sg:postcode":"23220",
    "sg:province":"VA",
    "sg:tags":[
        "contractor"
    ],
    "wof:name":"City Tin & Copper",
    "wof:placetype":"venue"
},
  "geometry": {"coordinates":[-77.460576,37.563926],"type":"Point"}
}