{
  "type": "Feature",
  "properties": {
    "addr:full":"11171 Balls Ford Rd Manassas VA 20109",
    "addr:housenumber":"11171",
    "addr:postcode":"20109",
    "addr:street":"Balls Ford Rd",
    "iso:country":"US",
    "sg:address":"11171 Balls Ford Rd",
    "sg:city":"Manassas",
    "sg:classifiers":[
        {
            "category":"Food & Beverages",
            "subcategory":"Groceries & Convenience Stores",
            "type":"Retail Goods"
        }
    ],
    "sg:phone":"+1 703 365 0797",
    "sg:postcode":"20109",
    "sg:province":"VA",
    "wof:name":"7-Eleven Inc",
    "wof:placetype":"venue"
},
  "geometry": {"coordinates":[-77.528099,38.797401],"type":"Point"}
}