{
  "type": "Feature",
  "properties": {
    "addr:full":"1343 Towne Sq Blvd NW Roanoke VA 24012",
    "addr:housenumber":"1343",
    "addr:postcode":"24012",
    "addr:street":"Towne Sq Blvd Nw",
    "iso:country":"US",
    "sg:address":"1343 Towne Sq Blvd NW",
    "sg:city":"Roanoke",
    "sg:classifiers":[
        {
            "category":"Banks & Credit Unions",
            "subcategory":"Bank",
            "type":"Services"
        }
    ],
    "sg:phone":"+1 540 366 3147",
    "sg:postcode":"24012",
    "sg:province":"VA",
    "sg:tags":[
        "cashing",
        "personal",
        "check",
        "institution"
    ],
    "wof:name":"Advance America",
    "wof:placetype":"venue"
},
  "geometry": {"coordinates":[-79.961242,37.319133],"type":"Point"}
}