{
  "type": "Feature",
  "properties": {
    "addr:full":"6579 Edsall Rd Springfield VA 22151",
    "addr:housenumber":"6579",
    "addr:postcode":"22151",
    "addr:street":"Edsall Rd",
    "iso:country":"US",
    "sg:address":"6579 Edsall Rd",
    "sg:city":"Springfield",
    "sg:classifiers":[
        {
            "category":"Building & Trades",
            "subcategory":"Plumbing",
            "type":"Services"
        }
    ],
    "sg:phone":"+1 703 941 6733",
    "sg:postcode":"22151",
    "sg:province":"VA",
    "sg:tags":[
        "a",
        "c",
        "contractor"
    ],
    "wof:name":"Acx",
    "wof:placetype":"venue"
},
  "geometry": {"coordinates":[-77.170665,38.80608],"type":"Point"}
}