{
  "type": "Feature",
  "properties": {
    "iso:country":"US",
    "sg:address":"1003 N 25th St",
    "sg:city":"Richmond",
    "sg:classifiers":[
        {
            "category":"Personal",
            "subcategory":"Shoe Repair & Shine",
            "type":"Services"
        }
    ],
    "sg:phone":"+1 804 643 9713",
    "sg:postcode":"23223",
    "sg:province":"VA",
    "sg:tags":[
        "repairing",
        "parlor",
        "boot"
    ],
    "wof:name":"Jefferson's Shoe Repair",
    "wof:placetype":"venue"
},
  "geometry": {"coordinates":[-77.412334,37.538413],"type":"Point"}
}