{
  "type": "Feature",
  "properties": {
    "addr:full":"6172 Skyview Cir Dublin VA 24084",
    "addr:housenumber":"6172",
    "addr:postcode":"24084",
    "addr:street":"Skyview Cir",
    "iso:country":"US",
    "sg:address":"6172 Skyview Cir",
    "sg:city":"Dublin",
    "sg:classifiers":[
        {
            "category":"Building & Trades",
            "subcategory":"Electrical",
            "type":"Services"
        }
    ],
    "sg:phone":"+1 540 674 8796",
    "sg:postcode":"24084",
    "sg:province":"VA",
    "sg:tags":[
        "electrical",
        "contractor"
    ],
    "wof:name":"Christians Electrical Svc LLC",
    "wof:placetype":"venue"
},
  "geometry": {"coordinates":[-80.694677,37.123863],"type":"Point"}
}