{
  "type": "Feature",
  "properties": {
    "addr:full":"1326 W Main St Salem VA 24153",
    "addr:housenumber":"1326",
    "addr:postcode":"24153",
    "addr:street":"W Main St",
    "iso:country":"US",
    "sg:address":"1326 W Main St",
    "sg:city":"Salem",
    "sg:classifiers":[
        {
            "category":"Professional",
            "subcategory":"Business Services",
            "type":"Services"
        }
    ],
    "sg:phone":"+1 540 375 3830",
    "sg:postcode":"24153",
    "sg:province":"VA",
    "sg:tags":[
        "embroidery"
    ],
    "wof:name":"Hometown Creations Co",
    "wof:placetype":"venue"
},
  "geometry": {"coordinates":[-80.07981700000001,37.289571],"type":"Point"}
}