{
  "type": "Feature",
  "properties": {
    "addr:full":"1400 S Hayes St Arlington VA 22202",
    "addr:housenumber":"1400",
    "addr:postcode":"22202",
    "addr:street":"S Hayes St",
    "iso:country":"US",
    "sg:address":"1400 S Hayes St",
    "sg:city":"Arlington",
    "sg:classifiers":[
        {
            "category":"Shopping",
            "subcategory":"Clothing, Apparel, & Fashions",
            "type":"Retail Goods"
        }
    ],
    "sg:phone":"+1 703 415 1121",
    "sg:postcode":"22202",
    "sg:province":"VA",
    "sg:website":"shop.nordstrom.com/c/nordstrom-rack",
    "wof:name":"Nordstrom Rack",
    "wof:placetype":"venue"
},
  "geometry": {"coordinates":[-77.058128,38.86223],"type":"Point"}
}