{
  "type": "Feature",
  "properties": {
    "addr:full":"9601 Amberdale Dr Richmond VA 23236",
    "addr:housenumber":"9601",
    "addr:postcode":"23236",
    "addr:street":"Amberdale Dr",
    "iso:country":"US",
    "sg:address":"9601 Amberdale Dr",
    "sg:city":"Richmond",
    "sg:classifiers":[
        {
            "category":"Banks & Credit Unions",
            "subcategory":"Bank",
            "type":"Services"
        },
        {
            "category":"Banks & Credit Unions",
            "subcategory":"Financial Services",
            "type":"Services"
        }
    ],
    "sg:phone":"+1 804 276 3436",
    "sg:postcode":"23236",
    "sg:province":"VA",
    "sg:tags":[
        "commercial",
        "loan",
        "saving",
        "mortgage"
    ],
    "sg:website":"https://www.wachovia.com/?DCMP=KNL-CPS-DS-Directory-0703&HBX_PK=Banks&HBX_OU=71",
    "wof:name":"Wachovia Bank",
    "wof:placetype":"venue"
},
  "geometry": {"coordinates":[-77.572472,37.44725],"type":"Point"}
}