{
  "type": "Feature",
  "properties": {
    "addr:full":"1272 Bishop Hill Rd Charlottesville VA 22902",
    "addr:housenumber":"1272",
    "addr:postcode":"22902",
    "addr:street":"Bishop Hill Rd",
    "iso:country":"US",
    "sg:address":"1272 Bishop Hill Rd",
    "sg:city":"Charlottesville",
    "sg:classifiers":[
        {
            "category":"Real Estate",
            "subcategory":"Architect",
            "type":"Services"
        }
    ],
    "sg:phone":"+1 434 977 7574",
    "sg:postcode":"22902",
    "sg:province":"VA",
    "sg:tags":[
        "architectural"
    ],
    "wof:name":"Howard Murry James",
    "wof:placetype":"venue"
},
  "geometry": {"coordinates":[-78.456495,37.974786],"type":"Point"}
}