{
  "type": "Feature",
  "properties": {
    "iso:country":"US",
    "sg:address":"7011 Forest Hill Ave",
    "sg:city":"Richmond",
    "sg:classifiers":[
        {
            "category":"Wholesale",
            "subcategory":"Medical Equipment & Supplies",
            "type":"Manufacturing & Wholesale Goods"
        },
        {
            "category":"Health Services",
            "subcategory":"Doctor",
            "type":"Services"
        }
    ],
    "sg:phone":"+1 804 560 4479",
    "sg:postcode":"23225",
    "sg:province":"VA",
    "sg:tags":[
        "physician",
        "surgeon",
        "merchandise"
    ],
    "wof:name":"Health Solutions Inc",
    "wof:placetype":"venue"
},
  "geometry": {"coordinates":[-77.527666,37.537557],"type":"Point"}
}