{
  "type": "Feature",
  "properties": {
    "addr:full":"36959 Basswood Ct Purcellville VA 20132",
    "addr:postcode":"36959;20132",
    "addr:street":"Basswood Ct",
    "iso:country":"US",
    "sg:address":"36959 Basswood Ct",
    "sg:city":"Purcellville",
    "sg:classifiers":[
        {
            "category":"Professional",
            "subcategory":"Business Services",
            "type":"Services"
        }
    ],
    "sg:phone":"+1 703 648 4053",
    "sg:postcode":"20132",
    "sg:province":"VA",
    "wof:name":"U F G S",
    "wof:placetype":"venue"
},
  "geometry": {"coordinates":[-77.726213,39.127057],"type":"Point"}
}