{
  "type": "Feature",
  "properties": {
    "iso:country":"US",
    "sg:address":"736 Warrenton Rd",
    "sg:city":"Fredericksburg",
    "sg:classifiers":[
        {
            "category":"Shopping",
            "subcategory":"Pharmacy",
            "type":"Retail Goods"
        }
    ],
    "sg:phone":"+1 540 371 2627",
    "sg:postcode":"22406",
    "sg:province":"VA",
    "sg:tags":[
        "drug",
        "store"
    ],
    "wof:name":"CVS",
    "wof:placetype":"venue"
},
  "geometry": {"coordinates":[-77.503981,38.350171],"type":"Point"}
}