{
  "type": "Feature",
  "properties": {
    "iso:country":"US",
    "sg:address":"911 King St",
    "sg:city":"Alexandria",
    "sg:classifiers":[
        {
            "category":"Restaurant",
            "type":"Food & Drink"
        }
    ],
    "sg:menulink":"http://www.allmenus.com/va/alexandria/260011-the-majestic/menu/",
    "sg:phone":"+1 703 837 9117",
    "sg:postcode":"22314",
    "sg:province":"VA",
    "sg:tags":[
        "american"
    ],
    "wof:name":"The Majestic",
    "wof:placetype":"venue"
},
  "geometry": {"coordinates":[-77.04958600000001,38.805498],"type":"Point"}
}