{
  "type": "Feature",
  "properties": {
    "addr:full":"7116 Kerr Dr Springfield VA 22150",
    "addr:housenumber":"7116",
    "addr:postcode":"22150",
    "addr:street":"Kerr Dr",
    "iso:country":"US",
    "sg:address":"7116 Kerr Dr",
    "sg:city":"Springfield",
    "sg:classifiers":[
        {
            "category":"Freight",
            "type":"Transportation"
        }
    ],
    "sg:phone":"+1 703 451 2918",
    "sg:postcode":"22150",
    "sg:province":"VA",
    "sg:tags":[
        "operator",
        "local",
        "trucking"
    ],
    "wof:name":"Fjj Trucking",
    "wof:placetype":"venue"
},
  "geometry": {"coordinates":[-77.192443,38.795159],"type":"Point"}
}