{
  "type": "Feature",
  "properties": {
    "addr:full":"1503 Dulcimer Ct Vienna VA 22182",
    "addr:housenumber":"1503",
    "addr:postcode":"22182",
    "addr:street":"Dulcimer Ct",
    "iso:country":"US",
    "sg:address":"1503 Dulcimer Ct",
    "sg:city":"Vienna",
    "sg:classifiers":[
        {
            "category":"Professional",
            "subcategory":"Business Services",
            "type":"Services"
        }
    ],
    "sg:phone":"+1 703 938 3289",
    "sg:postcode":"22182",
    "sg:province":"VA",
    "wof:name":"Frank Almaguer",
    "wof:placetype":"venue"
},
  "geometry": {"coordinates":[-77.27155999999999,38.943964],"type":"Point"}
}