{
  "type": "Feature",
  "properties": {
    "addr:full":"1910 Byrd Ave Richmond VA 23230",
    "addr:housenumber":"1910",
    "addr:postcode":"23230",
    "addr:street":"Byrd Ave",
    "iso:country":"US",
    "sg:address":"1910 Byrd Ave",
    "sg:city":"Richmond",
    "sg:classifiers":[
        {
            "category":"Insurance",
            "subcategory":"Insurance Agent",
            "type":"Services"
        }
    ],
    "sg:phone":"+1 804 288 0400",
    "sg:postcode":"23230",
    "sg:province":"VA",
    "wof:name":"Associated Risk Management",
    "wof:placetype":"venue"
},
  "geometry": {"coordinates":[-77.50065499999999,37.584695],"type":"Point"}
}