{
  "type": "Feature",
  "properties": {
    "addr:full":"1966 E Pembroke Ave Hampton VA 23663",
    "addr:housenumber":"1966",
    "addr:postcode":"23663",
    "addr:street":"E Pembroke Ave",
    "iso:country":"US",
    "sg:address":"1966 E Pembroke Ave",
    "sg:city":"Hampton",
    "sg:classifiers":[
        {
            "category":"Restaurant",
            "type":"Food & Drink"
        }
    ],
    "sg:menulink":"http://www.allmenus.com/va/hampton/71904-pizza-hut/menu/",
    "sg:phone":"+1 757 723 2200",
    "sg:postcode":"23663",
    "sg:province":"VA",
    "sg:tags":[
        "american",
        "pizza"
    ],
    "wof:name":"Pizza Hut",
    "wof:placetype":"venue"
},
  "geometry": {"coordinates":[-76.305708,37.03946],"type":"Point"}
}