{
  "type": "Feature",
  "properties": {
    "addr:full":"1253 Prophet Rd Goode VA 24556",
    "addr:housenumber":"1253",
    "addr:postcode":"24556",
    "addr:street":"Prophet Rd",
    "iso:country":"US",
    "sg:address":"1253 Prophet Rd",
    "sg:city":"Goode",
    "sg:classifiers":[
        {
            "category":"Shopping",
            "type":"Retail Goods"
        }
    ],
    "sg:phone":"+1 540 587 9577",
    "sg:postcode":"24556",
    "sg:province":"VA",
    "sg:tags":[
        "cosmetic",
        "perfume"
    ],
    "wof:name":"Mary Kay Cosmetics",
    "wof:placetype":"venue"
},
  "geometry": {"coordinates":[-79.39174800000001,37.349654],"type":"Point"}
}