{
  "type": "Feature",
  "properties": {
    "addr:full":"1825 Waters Edge Dr Penhook VA 24137",
    "addr:housenumber":"1825",
    "addr:postcode":"24137",
    "addr:street":"Waters Edge Dr",
    "iso:country":"US",
    "sg:address":"1825 Waters Edge Dr",
    "sg:city":"Penhook",
    "sg:classifiers":[
        {
            "category":"Recreation",
            "type":"Entertainment"
        }
    ],
    "sg:phone":"+1 540 576 2714",
    "sg:postcode":"24137",
    "sg:province":"VA",
    "sg:tags":[
        "stable"
    ],
    "wof:name":"Waters Edge Equestrian Center",
    "wof:placetype":"venue"
},
  "geometry": {"coordinates":[-79.617216,37.020267],"type":"Point"}
}