{
  "type": "Feature",
  "properties": {
    "iso:country":"US",
    "sg:address":"4860 Indian Valley Rd",
    "sg:city":"Radford",
    "sg:classifiers":[
        {
            "category":"Retail",
            "subcategory":"Animal Services",
            "type":"Services"
        }
    ],
    "sg:phone":"+1 540 382 7252",
    "sg:postcode":"24141",
    "sg:province":"VA",
    "wof:name":"Timber Ridge Stables",
    "wof:placetype":"venue"
},
  "geometry": {"coordinates":[-80.52755500000001,37.036259],"type":"Point"}
}