{
  "type": "Feature",
  "properties": {
    "iso:country":"US",
    "sg:address":"20575 Shadow Woods Ct",
    "sg:city":"Sterling",
    "sg:classifiers":[
        {
            "category":"Professional",
            "subcategory":"Business Services",
            "type":"Services"
        }
    ],
    "sg:phone":"+1 703 404 3327",
    "sg:postcode":"20165",
    "sg:province":"VA",
    "wof:name":"Material Differences",
    "wof:placetype":"venue"
},
  "geometry": {"coordinates":[-77.39857499999999,39.04485],"type":"Point"}
}