{
  "type": "Feature",
  "properties": {
    "addr:full":"908 King St Alexandria VA 22314",
    "addr:housenumber":"908",
    "addr:postcode":"22314",
    "addr:street":"King St",
    "iso:country":"US",
    "sg:address":"908 King St",
    "sg:city":"Alexandria",
    "sg:classifiers":[
        {
            "category":"Organizations",
            "subcategory":"Non-profit Organization",
            "type":"Services"
        },
        {
            "category":"Organizations",
            "subcategory":"Membership Organization",
            "type":"Services"
        }
    ],
    "sg:phone":"+1 703 836 9595",
    "sg:postcode":"22314",
    "sg:province":"VA",
    "sg:tags":[
        "group",
        "advocacy"
    ],
    "sg:website":"www.amprogress.com",
    "wof:name":"Americans For Medical Progress",
    "wof:placetype":"venue"
},
  "geometry": {"coordinates":[-77.050231,38.805397],"type":"Point"}
}