{
  "type": "Feature",
  "properties": {
    "addr:full":"2111 Eisenhower Ave Alexandria VA 22314",
    "addr:housenumber":"2111",
    "addr:postcode":"22314",
    "addr:street":"Eisenhower Ave",
    "iso:country":"US",
    "sg:address":"2111 Eisenhower Ave",
    "sg:city":"Alexandria",
    "sg:classifiers":[
        {
            "category":"Real Estate",
            "subcategory":"Real Estate Agent",
            "type":"Services"
        }
    ],
    "sg:phone":"+1 703 299 3506",
    "sg:postcode":"22314",
    "sg:province":"VA",
    "wof:name":"Commercial Real Estate Assoc",
    "wof:placetype":"venue"
},
  "geometry": {"coordinates":[-77.065849,38.800839],"type":"Point"}
}