{
  "type": "Feature",
  "properties": {
    "addr:full":"1559 Laskin Rd Virginia Beach VA 23451",
    "addr:housenumber":"1559",
    "addr:postcode":"23451",
    "addr:street":"Laskin Rd",
    "iso:country":"US",
    "sg:address":"1559 Laskin Rd",
    "sg:city":"Virginia Beach",
    "sg:classifiers":[
        {
            "category":"Wholesale",
            "subcategory":"Metals & Minerals",
            "type":"Manufacturing & Wholesale Goods"
        }
    ],
    "sg:phone":"+1 757 425 1104",
    "sg:postcode":"23451",
    "sg:province":"VA",
    "sg:tags":[
        "steel",
        "prefabricated",
        "building"
    ],
    "wof:name":"Power Built",
    "wof:placetype":"venue"
},
  "geometry": {"coordinates":[-76.019093,36.851434],"type":"Point"}
}