{
  "type": "Feature",
  "properties": {
    "addr:full":"1119 Thompson Cir Newport News VA 23604",
    "addr:housenumber":"1119",
    "addr:postcode":"23604",
    "addr:street":"Thompson Cir",
    "iso:country":"US",
    "sg:address":"1119 Thompson Cir",
    "sg:city":"Newport News",
    "sg:classifiers":[
        {
            "category":"Building & Trades",
            "subcategory":"Cleaning & Sanitation",
            "type":"Services"
        }
    ],
    "sg:phone":"+1 757 888 1098",
    "sg:postcode":"23604",
    "sg:province":"VA",
    "sg:tags":[
        "house"
    ],
    "wof:name":"High Tech Houseclean-Ing",
    "wof:placetype":"venue"
},
  "geometry": {"coordinates":[-76.571389,37.148318],"type":"Point"}
}