{
  "type": "Feature",
  "properties": {
    "addr:full":"9520 Richmond Hwy Lorton VA 22079",
    "addr:housenumber":"9520",
    "addr:postcode":"22079",
    "addr:street":"Richmond Hwy",
    "iso:country":"US",
    "sg:address":"9520 Richmond Hwy",
    "sg:city":"Lorton",
    "sg:classifiers":[
        {
            "category":"Education",
            "subcategory":"Library",
            "type":"Public Place"
        }
    ],
    "sg:phone":"+1 703 339 7385",
    "sg:postcode":"22079",
    "sg:province":"VA",
    "wof:name":"Public Library Systems",
    "wof:placetype":"venue"
},
  "geometry": {"coordinates":[-77.212879,38.698634],"type":"Point"}
}