{
  "type": "Feature",
  "properties": {
    "iso:country":"US",
    "sg:address":"5955 Kingstowne Towne Ctr",
    "sg:city":"Alexandria",
    "sg:classifiers":[
        {
            "category":"Restaurant",
            "type":"Food & Drink"
        }
    ],
    "sg:menulink":"http://www.allmenus.com/va/lee/222058-chipotle/menu/",
    "sg:phone":"+1 703 924 6018",
    "sg:postcode":"22315",
    "sg:province":"VA",
    "sg:tags":[
        "mexican"
    ],
    "wof:name":"Chipotle",
    "wof:placetype":"venue"
},
  "geometry": {"coordinates":[-77.139928,38.769908],"type":"Point"}
}