{
  "type": "Feature",
  "properties": {
    "iso:country":"US",
    "sg:address":"8550 Lee Hwy",
    "sg:city":"Fairfax",
    "sg:classifiers":[
        {
            "category":"Health Services",
            "subcategory":"Podiatrist",
            "type":"Services"
        }
    ],
    "sg:phone":"+1 703 560 3773",
    "sg:postcode":"22031",
    "sg:province":"VA",
    "wof:name":"Capital Podiatry Assoc",
    "wof:placetype":"venue"
},
  "geometry": {"coordinates":[-77.24189,38.873381],"type":"Point"}
}