{
  "type": "Feature",
  "properties": {
    "iso:country":"US",
    "sg:address":"301 Maple Ave W",
    "sg:city":"Vienna",
    "sg:classifiers":[
        {
            "category":"Health Services",
            "subcategory":"Doctor",
            "type":"Services"
        }
    ],
    "sg:phone":"+1 703 255 9850",
    "sg:postcode":"22180",
    "sg:province":"VA",
    "sg:tags":[
        "physician",
        "surgeon"
    ],
    "wof:name":"Zaid Khalil MD",
    "wof:placetype":"venue"
},
  "geometry": {"coordinates":[-77.270535,38.897324],"type":"Point"}
}