{
  "type": "Feature",
  "properties": {
    "addr:full":"24186 Eagle Site Dr Abingdon VA 24211",
    "addr:housenumber":"24186",
    "addr:postcode":"24211",
    "addr:street":"Eagle Site Dr",
    "iso:country":"US",
    "sg:address":"24186 Eagle Site Dr",
    "sg:city":"Abingdon",
    "sg:classifiers":[
        {
            "category":"Building & Trades",
            "subcategory":"Construction",
            "type":"Services"
        }
    ],
    "sg:phone":"+1 276 623 0492",
    "sg:postcode":"24211",
    "sg:province":"VA",
    "sg:tags":[
        "residential"
    ],
    "wof:name":"Bill French Building",
    "wof:placetype":"venue"
},
  "geometry": {"coordinates":[-81.93274700000001,36.646601],"type":"Point"}
}