{
  "type": "Feature",
  "properties": {
    "addr:full":"5701 Duke St Alexandria VA 22304",
    "addr:housenumber":"5701",
    "addr:postcode":"22304",
    "addr:street":"Duke St",
    "iso:country":"US",
    "sg:address":"5701 Duke St",
    "sg:city":"Alexandria",
    "sg:classifiers":[
        {
            "category":"Autos & Motor Vehicles",
            "subcategory":"Auto Supplies",
            "type":"Retail Goods"
        }
    ],
    "sg:phone":"+1 703 354 2034",
    "sg:postcode":"22304",
    "sg:province":"VA",
    "sg:tags":[
        "tire"
    ],
    "wof:name":"Goodyear Auto Svc Ctr",
    "wof:placetype":"venue"
},
  "geometry": {"coordinates":[-77.129864,38.814326],"type":"Point"}
}