{
  "type": "Feature",
  "properties": {
    "addr:full":"400A Fairway Ave Charlottesville VA 22902",
    "addr:housenumber":"400a",
    "addr:postcode":"22902",
    "addr:street":"Fairway Ave",
    "iso:country":"US",
    "sg:address":"400A Fairway Ave",
    "sg:city":"Charlottesville",
    "sg:classifiers":[
        {
            "category":"Professional",
            "subcategory":"Accounting & Tax Preparation",
            "type":"Services"
        }
    ],
    "sg:phone":"+1 434 979 3500",
    "sg:postcode":"22902",
    "sg:province":"VA",
    "sg:tags":[
        "return",
        "preparation-business"
    ],
    "wof:name":"Bessie Tax Service",
    "wof:placetype":"venue"
},
  "geometry": {"coordinates":[-78.463814,38.028389],"type":"Point"}
}