{
  "type": "Feature",
  "properties": {
    "addr:full":"22377 Belmont Ridge Rd Ashburn VA 20148",
    "addr:housenumber":"22377",
    "addr:postcode":"20148",
    "addr:street":"Belmont Ridge Rd",
    "iso:country":"US",
    "sg:address":"22377 Belmont Ridge Rd",
    "sg:city":"Ashburn",
    "sg:classifiers":[
        {
            "category":"Organizations",
            "subcategory":"Professional Association",
            "type":"Services"
        }
    ],
    "sg:phone":"+1 703 858 0784",
    "sg:postcode":"20148",
    "sg:province":"VA",
    "wof:name":"National Recreation & Park",
    "wof:placetype":"venue"
},
  "geometry": {"coordinates":[-77.52871500000001,38.99795],"type":"Point"}
}