{
  "type": "Feature",
  "properties": {
    "addr:full":"5002 Airport Rd NW Roanoke VA 24012",
    "addr:housenumber":"5002",
    "addr:postcode":"24012",
    "addr:street":"Airport Rd Nw",
    "iso:country":"US",
    "sg:address":"5002 Airport Rd NW",
    "sg:city":"Roanoke",
    "sg:classifiers":[
        {
            "category":"Insurance",
            "subcategory":"Insurance Agent",
            "type":"Services"
        }
    ],
    "sg:phone":"+1 540 265 0259",
    "sg:postcode":"24012",
    "sg:province":"VA",
    "wof:name":"Rogers Insurance",
    "wof:placetype":"venue"
},
  "geometry": {"coordinates":[-79.955409,37.318029],"type":"Point"}
}