{
  "type": "Feature",
  "properties": {
    "addr:full":"46444 Montgomery Pl Sterling VA 20165",
    "addr:housenumber":"46444",
    "addr:postcode":"20165",
    "addr:street":"Montgomery Pl",
    "iso:country":"US",
    "sg:address":"46444 Montgomery Pl",
    "sg:city":"Sterling",
    "sg:classifiers":[
        {
            "category":"Home & Garden",
            "subcategory":"Home Furnishings",
            "type":"Retail Goods"
        }
    ],
    "sg:phone":"+1 703 421 6112",
    "sg:postcode":"20165",
    "sg:province":"VA",
    "sg:tags":[
        "venetian",
        "blind"
    ],
    "wof:name":"Potomac Blinds",
    "wof:placetype":"venue"
},
  "geometry": {"coordinates":[-77.391593,39.042288],"type":"Point"}
}