{
  "type": "Feature",
  "properties": {
    "addr:full":"1709 Royal Park Ct Virginia Beach VA 23454",
    "addr:housenumber":"1709",
    "addr:postcode":"23454",
    "addr:street":"Royal Park Ct",
    "iso:country":"US",
    "sg:address":"1709 Royal Park Ct",
    "sg:city":"Virginia Beach",
    "sg:classifiers":[
        {
            "category":"Travel",
            "subcategory":"Travel Agent",
            "type":"Entertainment"
        }
    ],
    "sg:phone":"+1 757 412 0240",
    "sg:postcode":"23454",
    "sg:province":"VA",
    "sg:tags":[
        "operator",
        "tour"
    ],
    "wof:name":"Tours With Glenda",
    "wof:placetype":"venue"
},
  "geometry": {"coordinates":[-76.024141,36.860432],"type":"Point"}
}