{
  "type": "Feature",
  "properties": {
    "iso:country":"US",
    "sg:address":"4909 Government Rd",
    "sg:city":"Richmond",
    "sg:classifiers":[
        {
            "category":"Organizations",
            "subcategory":"Religious Organization",
            "type":"Services"
        }
    ],
    "sg:phone":"+1 804 652 4600",
    "sg:postcode":"23231",
    "sg:province":"VA",
    "sg:tags":[
        "church"
    ],
    "wof:name":"Greater Works Evangelistic Min",
    "wof:placetype":"venue"
},
  "geometry": {"coordinates":[-77.39495100000001,37.515752],"type":"Point"}
}