{
  "type": "Feature",
  "properties": {
    "addr:full":"180 Dumfries Dr Dumfries VA 22026",
    "addr:housenumber":"180",
    "addr:postcode":"22026",
    "addr:street":"Dumfries Dr",
    "iso:country":"US",
    "sg:address":"180 Dumfries Dr",
    "sg:city":"Dumfries",
    "sg:classifiers":[
        {
            "category":"Insurance",
            "subcategory":"Insurance Agent",
            "type":"Services"
        }
    ],
    "sg:phone":"+1 703 221 9200",
    "sg:postcode":"22026",
    "sg:province":"VA",
    "wof:name":"State Farm Insurance",
    "wof:placetype":"venue"
},
  "geometry": {"coordinates":[-77.32182299999999,38.576648],"type":"Point"}
}