{
  "type": "Feature",
  "properties": {
    "addr:full":"2815 Wild Turkey Run Christiansburg VA 24073",
    "addr:housenumber":"2815",
    "addr:postcode":"24073",
    "addr:street":"Wild Turkey Run",
    "iso:country":"US",
    "sg:address":"2815 Wild Turkey Run",
    "sg:city":"Christiansburg",
    "sg:classifiers":[
        {
            "category":"Farming",
            "subcategory":"Livestock Farm",
            "type":"Manufacturing & Wholesale Goods"
        },
        {
            "category":"Recreation",
            "type":"Entertainment"
        }
    ],
    "sg:phone":"+1 540 381 6233",
    "sg:postcode":"24073",
    "sg:province":"VA",
    "sg:tags":[
        "equine",
        "stable"
    ],
    "wof:name":"Laurel Springs Farm Inc",
    "wof:placetype":"venue"
},
  "geometry": {"coordinates":[-80.412532,37.095647],"type":"Point"}
}