{
  "type": "Feature",
  "properties": {
    "addr:full":"121 Church Ave SW Roanoke VA 24011",
    "addr:housenumber":"121",
    "addr:postcode":"24011",
    "addr:street":"Church Ave Sw",
    "iso:country":"US",
    "sg:address":"121 Church Ave SW",
    "sg:city":"Roanoke",
    "sg:classifiers":[
        {
            "category":"Parking",
            "type":"Transportation"
        }
    ],
    "sg:phone":"+1 540 981 1311",
    "sg:postcode":"24011",
    "sg:province":"VA",
    "sg:tags":[
        "garage"
    ],
    "wof:name":"Allright Parking",
    "wof:placetype":"venue"
},
  "geometry": {"coordinates":[-79.943826,37.270648],"type":"Point"}
}