{
  "type": "Feature",
  "properties": {
    "addr:full":"307 Chesapeake Dr Great Falls VA 22066",
    "addr:housenumber":"307",
    "addr:postcode":"22066",
    "addr:street":"Chesapeake Dr",
    "iso:country":"US",
    "sg:address":"307 Chesapeake Dr",
    "sg:city":"Great Falls",
    "sg:classifiers":[
        {
            "category":"Organizations",
            "subcategory":"Political Organization",
            "type":"Services"
        },
        {
            "category":"Organizations",
            "subcategory":"Professional Association",
            "type":"Services"
        }
    ],
    "sg:phone":"+1 703 759 4441",
    "sg:postcode":"22066",
    "sg:province":"VA",
    "wof:name":"Foreign Policy Association",
    "wof:placetype":"venue"
},
  "geometry": {"coordinates":[-77.277193,39.019358],"type":"Point"}
}