{
  "type": "Feature",
  "properties": {
    "iso:country":"US",
    "sg:address":"46631 Spectrum Way",
    "sg:city":"Sterling",
    "sg:classifiers":[
        {
            "category":"Professional",
            "subcategory":"Computer Services",
            "type":"Services"
        }
    ],
    "sg:phone":"+1 703 450 3818",
    "sg:postcode":"20164",
    "sg:province":"VA",
    "sg:tags":[
        "reseller",
        "system",
        "value"
    ],
    "wof:name":"Loudoun Technology Inc",
    "wof:placetype":"venue"
},
  "geometry": {"coordinates":[-77.3857,39.029784],"type":"Point"}
}