{
  "type": "Feature",
  "properties": {
    "addr:full":"940 Prescelly Pl Charlottesville VA 22901",
    "addr:housenumber":"940",
    "addr:postcode":"22901",
    "addr:street":"Prescelly Pl",
    "iso:country":"US",
    "sg:address":"940 Prescelly Pl",
    "sg:city":"Charlottesville",
    "sg:classifiers":[
        {
            "category":"Organizations",
            "subcategory":"Community Association",
            "type":"Services"
        }
    ],
    "sg:phone":"+1 434 979 9797",
    "sg:postcode":"22901",
    "sg:province":"VA",
    "wof:name":"Stone Henge Homeowners Inc",
    "wof:placetype":"venue"
},
  "geometry": {"coordinates":[-78.466734,38.050666],"type":"Point"}
}