{
  "type": "Feature",
  "properties": {
    "addr:full":"2214 Ivy Rd Ste 106 Charlottesville VA 22903",
    "addr:housenumber":"2214",
    "addr:postcode":"22903",
    "addr:street":"Ivy Rd Ste 106",
    "iso:country":"US",
    "sg:address":"2214 Ivy Rd Ste 106",
    "sg:city":"Charlottesville",
    "sg:classifiers":[
        {
            "category":"Health Services",
            "subcategory":"Doctor",
            "type":"Services"
        }
    ],
    "sg:phone":"+1 434 295 6880",
    "sg:postcode":"22903",
    "sg:province":"VA",
    "sg:tags":[
        "surgeon",
        "oral"
    ],
    "sg:website":"www.cvillesmile.com",
    "wof:name":"Nicoletti Darlene DDS",
    "wof:placetype":"venue"
},
  "geometry": {"coordinates":[-78.5159,38.044998],"type":"Point"}
}