{
  "type": "Feature",
  "properties": {
    "iso:country":"US",
    "sg:address":"224 Fawcetts Run Ln",
    "sg:city":"Winchester",
    "sg:classifiers":[
        {
            "category":"Insurance",
            "subcategory":"Insurance Agent",
            "type":"Services"
        }
    ],
    "sg:phone":"+1 540 869 7312",
    "sg:postcode":"22602",
    "sg:province":"VA",
    "wof:name":"Federated Insurance Co",
    "wof:placetype":"venue"
},
  "geometry": {"coordinates":[-78.3048,39.110544],"type":"Point"}
}