{
  "type": "Feature",
  "properties": {
    "iso:country":"US",
    "sg:address":"6237 Jefferson Davis Hwy",
    "sg:city":"Spotsylvania",
    "sg:classifiers":[
        {
            "category":"Autos & Motor Vehicles",
            "subcategory":"Automobile Sales",
            "type":"Retail Goods"
        }
    ],
    "sg:phone":"+1 540 582 8151",
    "sg:postcode":"22580",
    "sg:province":"VA",
    "wof:name":"Tri Force Auto Sales",
    "wof:placetype":"venue"
},
  "geometry": {"coordinates":[-77.521575,38.129951],"type":"Point"}
}