{
  "type": "Feature",
  "properties": {
    "addr:full":"100 Kirk Ave SE Roanoke VA 24011",
    "addr:housenumber":"100",
    "addr:postcode":"24011",
    "addr:street":"Kirk Ave Se",
    "iso:country":"US",
    "sg:address":"100 Kirk Ave SE",
    "sg:city":"Roanoke",
    "sg:classifiers":[
        {
            "category":"Professional",
            "subcategory":"Computer Services",
            "type":"Services"
        }
    ],
    "sg:phone":"+1 540 344 1001",
    "sg:postcode":"24011",
    "sg:province":"VA",
    "sg:tags":[
        "support",
        "technology"
    ],
    "wof:name":"Bit By Bit LLC",
    "wof:placetype":"venue"
},
  "geometry": {"coordinates":[-79.93858299999999,37.271125],"type":"Point"}
}