{
  "type": "Feature",
  "properties": {
    "iso:country":"US",
    "sg:address":"1640 Huguenot Rd",
    "sg:city":"Midlothian",
    "sg:classifiers":[
        {
            "category":"Professional",
            "subcategory":"Management & Consulting",
            "type":"Services"
        }
    ],
    "sg:phone":"+1 804 379 9244",
    "sg:postcode":"23113",
    "sg:province":"VA",
    "sg:tags":[
        "business"
    ],
    "wof:name":"Actuarial Consulting Grou",
    "wof:placetype":"venue"
},
  "geometry": {"coordinates":[-77.61521399999999,37.514562],"type":"Point"}
}