{
  "type": "Feature",
  "properties": {
    "addr:full":"1165 N Independence Ave Independence VA 24348",
    "addr:housenumber":"1165",
    "addr:postcode":"24348",
    "addr:street":"N Independence Ave",
    "iso:country":"US",
    "sg:address":"1165 N Independence Ave",
    "sg:city":"Independence",
    "sg:classifiers":[
        {
            "category":"Personal",
            "subcategory":"Beauty Salon",
            "type":"Services"
        }
    ],
    "sg:phone":"+1 276 773 2110",
    "sg:postcode":"24348",
    "sg:province":"VA",
    "wof:name":"Studio 21 Family Hair Care Ctr",
    "wof:placetype":"venue"
},
  "geometry": {"coordinates":[-81.16482600000001,36.64163],"type":"Point"}
}