{
  "type": "Feature",
  "properties": {
    "addr:full":"3539 S George Mason Dr Alexandria VA 22302",
    "addr:housenumber":"3539",
    "addr:postcode":"22302",
    "addr:street":"S George Mason Dr",
    "iso:country":"US",
    "sg:address":"3539 S George Mason Dr",
    "sg:city":"Alexandria",
    "sg:classifiers":[
        {
            "category":"Shopping",
            "type":"Retail Goods"
        },
        {
            "category":"Organizations",
            "subcategory":"Non-profit Organization",
            "type":"Services"
        }
    ],
    "sg:phone":"+1 703 430 6557",
    "sg:postcode":"22302",
    "sg:province":"VA",
    "sg:tags":[
        "supply",
        "fund",
        "games",
        "merchandise",
        "raising"
    ],
    "wof:name":"Colvin Run Citizens Association",
    "wof:placetype":"venue"
},
  "geometry": {"coordinates":[-77.113643,38.846881],"type":"Point"}
}