{
  "type": "Feature",
  "properties": {
    "iso:country":"US",
    "sg:address":"5933 Bush Hill Dr",
    "sg:city":"Alexandria",
    "sg:classifiers":[
        {
            "category":"Real Estate",
            "subcategory":"Real Estate Services",
            "type":"Services"
        }
    ],
    "sg:phone":"+1 703 971 9478",
    "sg:postcode":"22310",
    "sg:province":"VA",
    "sg:tags":[
        "buyer",
        "broker"
    ],
    "wof:name":"Jmc Land",
    "wof:placetype":"venue"
},
  "geometry": {"coordinates":[-77.12219399999999,38.788668],"type":"Point"}
}