{
  "type": "Feature",
  "properties": {
    "addr:full":"10228 US Hwy 23 Pound VA 24279",
    "addr:housenumber":"10228",
    "addr:postcode":"24279",
    "addr:street":"Us Hwy 23",
    "iso:country":"US",
    "sg:address":"10228 US Hwy 23",
    "sg:city":"Pound",
    "sg:classifiers":[
        {
            "category":"Professional",
            "subcategory":"Accounting & Tax Preparation",
            "type":"Services"
        }
    ],
    "sg:phone":"+1 276 796 5259",
    "sg:postcode":"24279",
    "sg:province":"VA",
    "sg:tags":[
        "return",
        "filing"
    ],
    "wof:name":"Business Accounting Svc",
    "wof:placetype":"venue"
},
  "geometry": {"coordinates":[-82.599833,37.095417],"type":"Point"}
}