{
  "type": "Feature",
  "properties": {
    "addr:full":"10404 Lakeridge Pkwy Ashland VA 23005",
    "addr:housenumber":"10404",
    "addr:postcode":"23005",
    "addr:street":"Lakeridge Pkwy",
    "iso:country":"US",
    "sg:address":"10404 Lakeridge Pkwy",
    "sg:city":"Ashland",
    "sg:classifiers":[
        {
            "category":"Freight",
            "type":"Transportation"
        }
    ],
    "sg:phone":"+1 804 550 2044",
    "sg:postcode":"23005",
    "sg:province":"VA",
    "wof:name":"USF Processors Inc",
    "wof:placetype":"venue"
},
  "geometry": {"coordinates":[-77.453784,37.695519],"type":"Point"}
}