{
  "type": "Feature",
  "properties": {
    "iso:country":"US",
    "sg:address":"9009 Captains Row",
    "sg:city":"Alexandria",
    "sg:classifiers":[
        {
            "category":"Professional",
            "subcategory":"Engineering",
            "type":"Services"
        }
    ],
    "sg:phone":"+1 703 780 1946",
    "sg:postcode":"22308",
    "sg:province":"VA",
    "sg:tags":[
        "computer",
        "system"
    ],
    "wof:name":"Burtek International Corp",
    "wof:placetype":"venue"
},
  "geometry": {"coordinates":[-77.07105900000001,38.713257],"type":"Point"}
}