{
  "type": "Feature",
  "properties": {
    "iso:country":"US",
    "sg:address":"8489 Chesapeake Blvd",
    "sg:city":"Norfolk",
    "sg:classifiers":[
        {
            "category":"Food & Beverages",
            "subcategory":"Groceries & Convenience Stores",
            "type":"Retail Goods"
        }
    ],
    "sg:phone":"+1 757 587 7507",
    "sg:postcode":"23518",
    "sg:province":"VA",
    "wof:name":"7-Eleven",
    "wof:placetype":"venue"
},
  "geometry": {"coordinates":[-76.243887,36.929141],"type":"Point"}
}