{
  "type": "Feature",
  "properties": {
    "iso:country":"US",
    "sg:address":"12416 Ox Hill Rd",
    "sg:city":"Fairfax",
    "sg:classifiers":[
        {
            "category":"Real Estate",
            "subcategory":"Real Estate Agent",
            "type":"Services"
        }
    ],
    "sg:phone":"+1 703 758 8325",
    "sg:postcode":"22033",
    "sg:province":"VA",
    "wof:name":"Teck Realty",
    "wof:placetype":"venue"
},
  "geometry": {"coordinates":[-77.37835699999999,38.879064],"type":"Point"}
}