{
  "type": "Feature",
  "properties": {
    "addr:full":"1636 9th St SE Roanoke VA 24013",
    "addr:housenumber":"1636",
    "addr:postcode":"24013",
    "addr:street":"9Th St Se",
    "iso:country":"US",
    "sg:address":"1636 9th St SE",
    "sg:city":"Roanoke",
    "sg:classifiers":[
        {
            "category":"Professional",
            "subcategory":"Computer Services",
            "type":"Services"
        }
    ],
    "sg:phone":"+1 540 342 9680",
    "sg:postcode":"24013",
    "sg:province":"VA",
    "sg:tags":[
        "related"
    ],
    "wof:name":"Aim Sports LLC",
    "wof:placetype":"venue"
},
  "geometry": {"coordinates":[-79.925051,37.259288],"type":"Point"}
}