{
  "type": "Feature",
  "properties": {
    "addr:full":"106 Whitney Pl NE Leesburg VA 20176",
    "addr:housenumber":"106",
    "addr:postcode":"20176",
    "addr:street":"Whitney Pl Ne",
    "iso:country":"US",
    "sg:address":"106 Whitney Pl NE",
    "sg:city":"Leesburg",
    "sg:classifiers":[
        {
            "category":"Professional",
            "subcategory":"Business Services",
            "type":"Services"
        }
    ],
    "sg:phone":"+1 703 431 8055",
    "sg:postcode":"20176",
    "sg:province":"VA",
    "wof:name":"Basic Living Designs",
    "wof:placetype":"venue"
},
  "geometry": {"coordinates":[-77.558127,39.122054],"type":"Point"}
}