{
  "type": "Feature",
  "properties": {
    "addr:full":"13022 James Madison Hwy Orange VA 22960",
    "addr:housenumber":"13022",
    "addr:postcode":"22960",
    "addr:street":"James Madison Hwy",
    "iso:country":"US",
    "sg:address":"13022 James Madison Hwy",
    "sg:city":"Orange",
    "sg:classifiers":[
        {
            "category":"Local Transit",
            "type":"Transportation"
        }
    ],
    "sg:phone":"+1 540 672 1117",
    "sg:postcode":"22960",
    "sg:province":"VA",
    "wof:name":"Greyhound Bus Information",
    "wof:placetype":"venue"
},
  "geometry": {"coordinates":[-78.117794,38.227686],"type":"Point"}
}