{
  "type": "Feature",
  "properties": {
    "addr:full":"3518 N Nottingham St Arlington VA 22207",
    "addr:housenumber":"3518",
    "addr:postcode":"22207",
    "addr:street":"N Nottingham St",
    "iso:country":"US",
    "sg:address":"3518 N Nottingham St",
    "sg:city":"Arlington",
    "sg:classifiers":[
        {
            "category":"Organizations",
            "subcategory":"Membership Organization",
            "type":"Services"
        }
    ],
    "sg:phone":"+1 703 241 7533",
    "sg:postcode":"22207",
    "sg:province":"VA",
    "sg:tags":[
        "environmental",
        "ecological",
        "conservation"
    ],
    "sg:website":"http://www.rarecenter.org",
    "wof:name":"Rare Center",
    "wof:placetype":"venue"
},
  "geometry": {"coordinates":[-77.153119,38.905308],"type":"Point"}
}