{
  "type": "Feature",
  "properties": {
    "addr:full":"4322 Dale Blvd Woodbridge VA 22193",
    "addr:housenumber":"4322",
    "addr:postcode":"22193",
    "addr:street":"Dale Blvd",
    "iso:country":"US",
    "sg:address":"4322 Dale Blvd",
    "sg:city":"Woodbridge",
    "sg:classifiers":[
        {
            "category":"Building & Trades",
            "subcategory":"Cleaning & Sanitation",
            "type":"Services"
        }
    ],
    "sg:phone":"+1 703 583 4111",
    "sg:postcode":"22193",
    "sg:province":"VA",
    "sg:tags":[
        "butler",
        "maid"
    ],
    "wof:name":"Maid Pro",
    "wof:placetype":"venue"
},
  "geometry": {"coordinates":[-77.33957100000001,38.647808],"type":"Point"}
}