{
  "type": "Feature",
  "properties": {
    "iso:country":"US",
    "sg:address":"8198 Euclid Ct",
    "sg:city":"Manassas Park",
    "sg:classifiers":[
        {
            "category":"Home & Garden",
            "subcategory":"Furniture",
            "type":"Retail Goods"
        }
    ],
    "sg:phone":"+1 703 369 4455",
    "sg:postcode":"20111",
    "sg:province":"VA",
    "sg:tags":[
        "top",
        "counter"
    ],
    "wof:name":"Heartwood Solid Surfaces Inc",
    "wof:placetype":"venue"
},
  "geometry": {"coordinates":[-77.439792,38.779098],"type":"Point"}
}