{
  "type": "Feature",
  "properties": {
    "addr:full":"2 W Marshall St Middleburg VA 20118",
    "addr:housenumber":"2",
    "addr:postcode":"20118",
    "addr:street":"W Marshall St",
    "iso:country":"US",
    "sg:address":"2 W Marshall St",
    "sg:city":"Middleburg",
    "sg:classifiers":[
        {
            "category":"Shopping",
            "type":"Retail Goods"
        },
        {
            "category":"Restaurant",
            "type":"Food & Drink"
        }
    ],
    "sg:phone":"+1 540 687 5282",
    "sg:postcode":"20118",
    "sg:province":"VA",
    "sg:tags":[
        "art",
        "grocery",
        "eating",
        "gallery",
        "dealer"
    ],
    "wof:name":"Mosby's Tavern",
    "wof:placetype":"venue"
},
  "geometry": {"coordinates":[-77.7372,38.969246],"type":"Point"}
}