{
  "type": "Feature",
  "properties": {
    "addr:full":"6926 Peters Creek Rd Roanoke VA 24019",
    "addr:housenumber":"6926",
    "addr:postcode":"24019",
    "addr:street":"Peters Creek Rd",
    "iso:country":"US",
    "sg:address":"6926 Peters Creek Rd",
    "sg:city":"Roanoke",
    "sg:classifiers":[
        {
            "category":"Organizations",
            "subcategory":"Community Association",
            "type":"Services"
        }
    ],
    "sg:phone":"+1 540 772 0000",
    "sg:postcode":"24019",
    "sg:province":"VA",
    "wof:name":"Oakcliff Homeowners' Association, Inc.",
    "wof:placetype":"venue"
},
  "geometry": {"coordinates":[-79.957212,37.346154],"type":"Point"}
}