{
  "type": "Feature",
  "properties": {
    "iso:country":"US",
    "sg:address":"6011 Williamsburg Rd",
    "sg:city":"Alexandria",
    "sg:classifiers":[
        {
            "category":"Professional",
            "subcategory":"Management & Consulting",
            "type":"Services"
        }
    ],
    "sg:phone":"+1 703 855 2584",
    "sg:postcode":"22303",
    "sg:province":"VA",
    "sg:tags":[
        "business"
    ],
    "wof:name":"Dawn Wyse Design Consultant",
    "wof:placetype":"venue"
},
  "geometry": {"coordinates":[-77.07822899999999,38.787879],"type":"Point"}
}