{
  "type": "Feature",
  "properties": {
    "iso:country":"US",
    "sg:address":"3708 N Woodstock St",
    "sg:city":"Arlington",
    "sg:classifiers":[
        {
            "category":"Building & Trades",
            "subcategory":"Cleaning & Sanitation",
            "type":"Services"
        }
    ],
    "sg:phone":"+1 703 534 3131",
    "sg:postcode":"22207",
    "sg:province":"VA",
    "sg:tags":[
        "maintenance"
    ],
    "wof:name":"Columbia Cleaning Services",
    "wof:placetype":"venue"
},
  "geometry": {"coordinates":[-77.131683,38.916759],"type":"Point"}
}