{
  "type": "Feature",
  "properties": {
    "addr:full":"1800 Norris Ln Richmond VA 23226",
    "addr:housenumber":"1800",
    "addr:postcode":"23226",
    "addr:street":"Norris Ln",
    "iso:country":"US",
    "sg:address":"1800 Norris Ln",
    "sg:city":"Richmond",
    "sg:classifiers":[
        {
            "category":"Building & Trades",
            "subcategory":"Construction",
            "type":"Services"
        }
    ],
    "sg:phone":"+1 804 285 3393",
    "sg:postcode":"23226",
    "sg:province":"VA",
    "wof:name":"A J Carpenter",
    "wof:placetype":"venue"
},
  "geometry": {"coordinates":[-77.50961100000001,37.589298],"type":"Point"}
}