{
  "type": "Feature",
  "properties": {
    "iso:country":"US",
    "sg:address":"14240 Sullyfield Cir",
    "sg:city":"Chantilly",
    "sg:classifiers":[
        {
            "category":"Retail",
            "subcategory":"Auto Repair",
            "type":"Services"
        }
    ],
    "sg:phone":"+1 703 263 2011",
    "sg:postcode":"20151",
    "sg:province":"VA",
    "sg:tags":[
        "transmission",
        "general"
    ],
    "wof:name":"Japanese Auto Work",
    "wof:placetype":"venue"
},
  "geometry": {"coordinates":[-77.438204,38.894317],"type":"Point"}
}