{
  "type": "Feature",
  "properties": {
    "addr:full":"901 E Byrd St Ste 500 Richmond VA 23219",
    "addr:housenumber":"901",
    "addr:postcode":"23219",
    "addr:street":"E Byrd St Ste 500",
    "iso:country":"US",
    "sg:address":"901 E Byrd St Ste 500",
    "sg:city":"Richmond",
    "sg:classifiers":[
        {
            "category":"Banks & Credit Unions",
            "subcategory":"Bank",
            "type":"Services"
        },
        {
            "category":"Banks & Credit Unions",
            "subcategory":"Financial Services",
            "type":"Services"
        }
    ],
    "sg:phone":"+1 804 649 2311",
    "sg:postcode":"23219",
    "sg:province":"VA",
    "sg:tags":[
        "commercial",
        "loan",
        "saving",
        "mortgage"
    ],
    "sg:website":"http://www.wachoviabank.com",
    "wof:name":"Wachovia",
    "wof:placetype":"venue"
},
  "geometry": {"coordinates":[-77.438911,37.535782],"type":"Point"}
}