{
  "type": "Feature",
  "properties": {
    "iso:country":"US",
    "sg:address":"752 Walker Rd",
    "sg:city":"Great Falls",
    "sg:classifiers":[
        {
            "category":"Professional",
            "type":"Services"
        }
    ],
    "sg:phone":"+1 703 759 0420",
    "sg:postcode":"22066",
    "sg:province":"VA",
    "sg:tags":[
        "establishment"
    ],
    "sg:website":"www.the-elementsinc.com",
    "wof:name":"Elements",
    "wof:placetype":"venue"
},
  "geometry": {"coordinates":[-77.28846900000001,38.996029],"type":"Point"}
}