{
  "type": "Feature",
  "properties": {
    "addr:full":"8096 Elm Dr Mechanicsville VA 23111",
    "addr:housenumber":"8096",
    "addr:postcode":"23111",
    "addr:street":"Elm Dr",
    "iso:country":"US",
    "sg:address":"8096 Elm Dr",
    "sg:city":"Mechanicsville",
    "sg:classifiers":[
        {
            "category":"Insurance",
            "subcategory":"Insurance Agent",
            "type":"Services"
        }
    ],
    "sg:phone":"+1 804 559 1200",
    "sg:postcode":"23111",
    "sg:province":"VA",
    "wof:name":"John R Stech Jr Insurance",
    "wof:placetype":"venue"
},
  "geometry": {"coordinates":[-77.378715,37.600095],"type":"Point"}
}