{
  "type": "Feature",
  "properties": {
    "iso:country":"US",
    "sg:address":"2946 Chain Bridge Rd",
    "sg:city":"Oakton",
    "sg:classifiers":[
        {
            "category":"Shopping",
            "subcategory":"Gifts & Souvenirs",
            "type":"Retail Goods"
        }
    ],
    "sg:phone":"+1 703 255 3101",
    "sg:postcode":"22124",
    "sg:province":"VA",
    "wof:name":"Balloons",
    "wof:placetype":"venue"
},
  "geometry": {"coordinates":[-77.301835,38.880424],"type":"Point"}
}