{
  "type": "Feature",
  "properties": {
    "addr:full":"1128 W Olney Rd Norfolk VA 23507",
    "addr:housenumber":"1128",
    "addr:postcode":"23507",
    "addr:street":"W Olney Rd",
    "iso:country":"US",
    "sg:address":"1128 W Olney Rd",
    "sg:city":"Norfolk",
    "sg:classifiers":[
        {
            "category":"Freight",
            "type":"Transportation"
        }
    ],
    "sg:phone":"+1 757 466 1170",
    "sg:postcode":"23507",
    "sg:province":"VA",
    "sg:website":"www.cvinternational.com",
    "wof:name":"C V Intl Inc",
    "wof:placetype":"venue"
},
  "geometry": {"coordinates":[-76.30741999999999,36.863899],"type":"Point"}
}