{
  "type": "Feature",
  "properties": {
    "iso:country":"US",
    "sg:address":"215 Roanoke St",
    "sg:city":"Christiansburg",
    "sg:classifiers":[
        {
            "category":"Government",
            "subcategory":"Office",
            "type":"Public Place"
        }
    ],
    "sg:phone":"+1 540 382 5790",
    "sg:postcode":"24073",
    "sg:province":"VA",
    "sg:tags":[
        "executive"
    ],
    "wof:name":"Montgomery County EXT Svc",
    "wof:placetype":"venue"
},
  "geometry": {"coordinates":[-80.403768,37.130182],"type":"Point"}
}