{
  "type": "Feature",
  "properties": {
    "addr:full":"7002 Little River Tpke Annandale VA 22003",
    "addr:housenumber":"7002",
    "addr:postcode":"22003",
    "addr:street":"Little River Tpke",
    "iso:country":"US",
    "sg:address":"7002 Little River Tpke",
    "sg:city":"Annandale",
    "sg:classifiers":[
        {
            "category":"Health Services",
            "subcategory":"Doctor",
            "type":"Services"
        }
    ],
    "sg:phone":"+1 703 642 2288",
    "sg:postcode":"22003",
    "sg:province":"VA",
    "sg:tags":[
        "physician",
        "surgeon"
    ],
    "wof:name":"Hyung L Kim MD",
    "wof:placetype":"venue"
},
  "geometry": {"coordinates":[-77.18625400000001,38.828816],"type":"Point"}
}