{
  "type": "Feature",
  "properties": {
    "addr:full":"63 Monacan Ct Lexington VA 24450",
    "addr:housenumber":"63",
    "addr:postcode":"24450",
    "addr:street":"Monacan Ct",
    "iso:country":"US",
    "sg:address":"63 Monacan Ct",
    "sg:city":"Lexington",
    "sg:classifiers":[
        {
            "category":"Social Services",
            "subcategory":"Job Training",
            "type":"Services"
        }
    ],
    "sg:phone":"+1 540 000 1111",
    "sg:postcode":"24450",
    "sg:province":"VA",
    "sg:tags":[
        "rehabilitation"
    ],
    "wof:name":"Alcoholics Anonymous",
    "wof:placetype":"venue"
},
  "geometry": {"coordinates":[-79.47511799999999,37.812401],"type":"Point"}
}