{
  "type": "Feature",
  "properties": {
    "addr:full":"2601 Jefferson Ave Newport News VA 23607",
    "addr:housenumber":"2601",
    "addr:postcode":"23607",
    "addr:street":"Jefferson Ave",
    "iso:country":"US",
    "sg:address":"2601 Jefferson Ave",
    "sg:city":"Newport News",
    "sg:classifiers":[
        {
            "category":"Restaurant",
            "type":"Food & Drink"
        }
    ],
    "sg:phone":"+1 757 380 8735",
    "sg:postcode":"23607",
    "sg:province":"VA",
    "sg:tags":[
        "eating"
    ],
    "wof:name":"McDonalds",
    "wof:placetype":"venue"
},
  "geometry": {"coordinates":[-76.42187699999999,36.982713],"type":"Point"}
}