{
  "type": "Feature",
  "properties": {
    "iso:country":"US",
    "sg:address":"6969 Richmond Hwy",
    "sg:city":"Alexandria",
    "sg:classifiers":[
        {
            "category":"Professional",
            "type":"Services"
        }
    ],
    "sg:phone":"+1 703 721 0217",
    "sg:postcode":"22306",
    "sg:province":"VA",
    "wof:name":"Davis Ebo",
    "wof:placetype":"venue"
},
  "geometry": {"coordinates":[-77.083536,38.766743],"type":"Point"}
}