{
  "type": "Feature",
  "properties": {
    "addr:full":"237 Park St SE Abingdon VA 24210",
    "addr:housenumber":"237",
    "addr:postcode":"24210",
    "addr:street":"Park St Se",
    "iso:country":"US",
    "sg:address":"237 Park St SE",
    "sg:city":"Abingdon",
    "sg:classifiers":[
        {
            "category":"Professional",
            "subcategory":"Employment Agencies",
            "type":"Services"
        }
    ],
    "sg:phone":"+1 276 676 2401",
    "sg:postcode":"24210",
    "sg:province":"VA",
    "sg:tags":[
        "help",
        "supply"
    ],
    "wof:name":"Washington Cnty Lf Saving Crew",
    "wof:placetype":"venue"
},
  "geometry": {"coordinates":[-81.96832499999999,36.711638],"type":"Point"}
}