{
  "type": "Feature",
  "properties": {
    "iso:country":"US",
    "sg:address":"409 Trents Ferry Rd",
    "sg:city":"Lynchburg",
    "sg:classifiers":[
        {
            "category":"Real Estate",
            "subcategory":"Real Estate Agent",
            "type":"Services"
        }
    ],
    "sg:phone":"+1 434 384 2500",
    "sg:postcode":"24503",
    "sg:province":"VA",
    "wof:name":"Trent Realty Holdings LLC",
    "wof:placetype":"venue"
},
  "geometry": {"coordinates":[-79.20650999999999,37.464716],"type":"Point"}
}