{
  "type": "Feature",
  "properties": {
    "addr:full":"900 Maple Ave E Vienna VA 22180",
    "addr:housenumber":"900",
    "addr:postcode":"22180",
    "addr:street":"Maple Ave E",
    "iso:country":"US",
    "sg:address":"900 Maple Ave E",
    "sg:city":"Vienna",
    "sg:classifiers":[
        {
            "category":"Education",
            "subcategory":"Preschool",
            "type":"Public Place"
        },
        {
            "category":"Education",
            "subcategory":"School",
            "type":"Public Place"
        }
    ],
    "sg:phone":"+1 703 938 3588",
    "sg:postcode":"22180",
    "sg:province":"VA",
    "sg:tags":[
        "elementary"
    ],
    "sg:website":"www.fbmeekins.org",
    "wof:name":"Meekins Cooperative Pre School",
    "wof:placetype":"venue"
},
  "geometry": {"coordinates":[-77.251099,38.9105],"type":"Point"}
}