{
  "type": "Feature",
  "properties": {
    "iso:country":"US",
    "sg:address":"4625 Shore Dr",
    "sg:city":"Virginia Beach",
    "sg:classifiers":[
        {
            "category":"Food & Beverages",
            "subcategory":"Groceries & Convenience Stores",
            "type":"Retail Goods"
        }
    ],
    "sg:phone":"+1 757 460 0343",
    "sg:postcode":"23455",
    "sg:province":"VA",
    "sg:tags":[
        "grocer"
    ],
    "wof:name":"Kroger",
    "wof:placetype":"venue"
},
  "geometry": {"coordinates":[-76.13082300000001,36.903608],"type":"Point"}
}