{
  "type": "Feature",
  "properties": {
    "addr:full":"424 Maple Ave E Vienna VA 22180",
    "addr:housenumber":"424",
    "addr:postcode":"22180",
    "addr:street":"Maple Ave E",
    "iso:country":"US",
    "sg:address":"424 Maple Ave E",
    "sg:city":"Vienna",
    "sg:classifiers":[
        {
            "category":"Personal",
            "subcategory":"Tanning Parlor",
            "type":"Services"
        }
    ],
    "sg:phone":"+1 703 319 0119",
    "sg:postcode":"22180",
    "sg:province":"VA",
    "wof:name":"Kapalua Bay Tanning Salon",
    "wof:placetype":"venue"
},
  "geometry": {"coordinates":[-77.256488,38.908518],"type":"Point"}
}