{
  "type": "Feature",
  "properties": {
    "addr:full":"8695 Sandy Beach Ln King George VA 22485",
    "addr:housenumber":"8695",
    "addr:postcode":"22485",
    "addr:street":"Sandy Beach Ln",
    "iso:country":"US",
    "sg:address":"8695 Sandy Beach Ln",
    "sg:city":"King George",
    "sg:classifiers":[
        {
            "category":"Professional",
            "subcategory":"Business Services",
            "type":"Services"
        }
    ],
    "sg:phone":"+1 540 775 0771",
    "sg:postcode":"22485",
    "sg:province":"VA",
    "wof:name":"Monmouth North Ltd Partnership",
    "wof:placetype":"venue"
},
  "geometry": {"coordinates":[-77.016644,38.29136],"type":"Point"}
}