{
  "type": "Feature",
  "properties": {
    "iso:country":"US",
    "sg:address":"10223 Timber Ridge Dr",
    "sg:city":"Ashland",
    "sg:classifiers":[
        {
            "category":"Wholesale",
            "subcategory":"Machinery & Supplies",
            "type":"Manufacturing & Wholesale Goods"
        }
    ],
    "sg:phone":"+1 804 550 2747",
    "sg:postcode":"23005",
    "sg:province":"VA",
    "sg:tags":[
        "chemical",
        "to",
        "industry",
        "cleaning"
    ],
    "wof:name":"Chemtec of VA",
    "wof:placetype":"venue"
},
  "geometry": {"coordinates":[-77.455229,37.699766],"type":"Point"}
}