{
  "type": "Feature",
  "properties": {
    "addr:full":"3502 Mechanicsville Pike Richmond VA 23223",
    "addr:housenumber":"3502",
    "addr:postcode":"23223",
    "addr:street":"Mechanicsville Pike",
    "iso:country":"US",
    "sg:address":"3502 Mechanicsville Pike",
    "sg:city":"Richmond",
    "sg:classifiers":[
        {
            "category":"Insurance",
            "subcategory":"Insurance Agent",
            "type":"Services"
        }
    ],
    "sg:phone":"+1 804 321 0737",
    "sg:postcode":"23223",
    "sg:province":"VA",
    "wof:name":"M & M Insurance",
    "wof:placetype":"venue"
},
  "geometry": {"coordinates":[-77.398217,37.574142],"type":"Point"}
}