{
  "type": "Feature",
  "properties": {
    "iso:country":"US",
    "sg:address":"1421 Prince St",
    "sg:city":"Alexandria",
    "sg:classifiers":[
        {
            "category":"Professional",
            "subcategory":"Computer Services",
            "type":"Services"
        }
    ],
    "sg:phone":"+1 703 548 2255",
    "sg:postcode":"22314",
    "sg:province":"VA",
    "wof:name":"Visionary Integration Pro",
    "wof:placetype":"venue"
},
  "geometry": {"coordinates":[-77.05632900000001,38.805167],"type":"Point"}
}