{
  "type": "Feature",
  "properties": {
    "addr:full":"485 Parkersburg Tpke Staunton VA 24401",
    "addr:housenumber":"485",
    "addr:postcode":"24401",
    "addr:street":"Parkersburg Tpke",
    "iso:country":"US",
    "sg:address":"485 Parkersburg Tpke",
    "sg:city":"Staunton",
    "sg:classifiers":[
        {
            "category":"Building & Trades",
            "subcategory":"Landscaping Services",
            "type":"Services"
        }
    ],
    "sg:phone":"+1 540 885 0618",
    "sg:postcode":"24401",
    "sg:province":"VA",
    "sg:tags":[
        "lawn"
    ],
    "wof:name":"Brubecks Grader & Lawn Svcs",
    "wof:placetype":"venue"
},
  "geometry": {"coordinates":[-79.129389,38.154129],"type":"Point"}
}