{
  "type": "Feature",
  "properties": {
    "iso:country":"US",
    "sg:address":"7008 Alicent Ct",
    "sg:city":"Mc Lean",
    "sg:classifiers":[
        {
            "category":"Professional",
            "subcategory":"Computer Services",
            "type":"Services"
        }
    ],
    "sg:phone":"+1 571 331 6273",
    "sg:postcode":"22101",
    "sg:province":"VA",
    "sg:tags":[
        "consulting"
    ],
    "wof:name":"Advanced Modeling Concepts",
    "wof:placetype":"venue"
},
  "geometry": {"coordinates":[-77.18528000000001,38.927494],"type":"Point"}
}