{
  "type": "Feature",
  "properties": {
    "iso:country":"US",
    "sg:address":"11209 Leadbetter Rd",
    "sg:city":"Ashland",
    "sg:classifiers":[
        {
            "category":"Manufacturing",
            "subcategory":"Rubber & Plastics",
            "type":"Manufacturing & Wholesale Goods"
        }
    ],
    "sg:phone":"+1 804 752 2646",
    "sg:postcode":"23005",
    "sg:province":"VA",
    "sg:tags":[
        "tube",
        "tire",
        "mfg"
    ],
    "wof:name":"Firestone",
    "wof:placetype":"venue"
},
  "geometry": {"coordinates":[-77.443394,37.709228],"type":"Point"}
}