{
  "type": "Feature",
  "properties": {
    "addr:full":"512 Raton Ct Chesapeake VA 23323",
    "addr:housenumber":"512",
    "addr:postcode":"23323",
    "addr:street":"Raton Ct",
    "iso:country":"US",
    "sg:address":"512 Raton Ct",
    "sg:city":"Chesapeake",
    "sg:classifiers":[
        {
            "category":"Building & Trades",
            "subcategory":"Construction",
            "type":"Services"
        }
    ],
    "sg:phone":"+1 757 485 4972",
    "sg:postcode":"23323",
    "sg:province":"VA",
    "sg:tags":[
        "house"
    ],
    "wof:name":"Mapp Building Co",
    "wof:placetype":"venue"
},
  "geometry": {"coordinates":[-76.32720500000001,36.726284],"type":"Point"}
}