{
  "type": "Feature",
  "properties": {
    "iso:country":"US",
    "sg:address":"2024 Greenville Ave",
    "sg:city":"Staunton",
    "sg:classifiers":[
        {
            "category":"Retail",
            "subcategory":"Repair Shop",
            "type":"Services"
        }
    ],
    "sg:phone":"+1 540 886 7461",
    "sg:postcode":"24401",
    "sg:province":"VA",
    "sg:tags":[
        "sharpening"
    ],
    "wof:name":"Valley Sharp Shop",
    "wof:placetype":"venue"
},
  "geometry": {"coordinates":[-79.06357800000001,38.128575],"type":"Point"}
}