{
  "type": "Feature",
  "properties": {
    "iso:country":"US",
    "sg:address":"181 Old Airport Rd",
    "sg:city":"Bristol",
    "sg:classifiers":[
        {
            "category":"Freight",
            "type":"Transportation"
        }
    ],
    "sg:phone":"+1 276 466 1080",
    "sg:postcode":"24201",
    "sg:province":"VA",
    "sg:tags":[
        "special"
    ],
    "wof:name":"C & C Mini Storage Buildings",
    "wof:placetype":"venue"
},
  "geometry": {"coordinates":[-82.13730200000001,36.613113],"type":"Point"}
}