{
  "type": "Feature",
  "properties": {
    "addr:full":"14362 New Towne Haven Ln Carrollton VA 23314",
    "addr:housenumber":"14362",
    "addr:postcode":"23314",
    "addr:street":"New Towne Haven Ln",
    "iso:country":"US",
    "sg:address":"14362 New Towne Haven Ln",
    "sg:city":"Carrollton",
    "sg:classifiers":[
        {
            "category":"Education",
            "subcategory":"Library",
            "type":"Public Place"
        }
    ],
    "sg:phone":"+1 757 238 2641",
    "sg:postcode":"23314",
    "sg:province":"VA",
    "wof:name":"Black Water Region Library Sys",
    "wof:placetype":"venue"
},
  "geometry": {"coordinates":[-76.555947,36.938707],"type":"Point"}
}