{
  "type": "Feature",
  "properties": {
    "addr:full":"6453 James Madison Pkwy King George VA 22485",
    "addr:housenumber":"6453",
    "addr:postcode":"22485",
    "addr:street":"James Madison Pkwy",
    "iso:country":"US",
    "sg:address":"6453 James Madison Pkwy",
    "sg:city":"King George",
    "sg:classifiers":[
        {
            "category":"Autos & Motor Vehicles",
            "subcategory":"Automobile Sales",
            "type":"Retail Goods"
        }
    ],
    "sg:phone":"+1 540 775 1062",
    "sg:postcode":"22485",
    "sg:province":"VA",
    "wof:name":"Supplies & Parts",
    "wof:placetype":"venue"
},
  "geometry": {"coordinates":[-77.095366,38.322788],"type":"Point"}
}