{
  "type": "Feature",
  "properties": {
    "addr:full":"5500 Riverside Dr Richmond VA 23225",
    "addr:housenumber":"5500",
    "addr:postcode":"23225",
    "addr:street":"Riverside Dr",
    "iso:country":"US",
    "sg:address":"5500 Riverside Dr",
    "sg:city":"Richmond",
    "sg:classifiers":[
        {
            "category":"Professional",
            "subcategory":"Lawyer & Legal Services",
            "type":"Services"
        }
    ],
    "sg:phone":"+1 804 232 4778",
    "sg:postcode":"23225",
    "sg:province":"VA",
    "wof:name":"Virkler Paul Attorney At Law",
    "wof:placetype":"venue"
},
  "geometry": {"coordinates":[-77.497379,37.534037],"type":"Point"}
}