{
  "type": "Feature",
  "properties": {
    "addr:full":"9404 Tunstall Rd New Kent VA 23124",
    "addr:housenumber":"9404",
    "addr:postcode":"23124",
    "addr:street":"Tunstall Rd",
    "iso:country":"US",
    "sg:address":"9404 Tunstall Rd",
    "sg:city":"New Kent",
    "sg:classifiers":[
        {
            "category":"Building & Trades",
            "subcategory":"Construction",
            "type":"Services"
        }
    ],
    "sg:phone":"+1 804 338 3727",
    "sg:postcode":"23124",
    "sg:province":"VA",
    "sg:tags":[
        "floor",
        "installing",
        "covering"
    ],
    "wof:name":"Lacy & Clarke Floorcovering",
    "wof:placetype":"venue"
},
  "geometry": {"coordinates":[-77.114842,37.535109],"type":"Point"}
}