{
  "type": "Feature",
  "properties": {
    "addr:full":"7464 Zachary Taylor Hwy Unionville VA 22567",
    "addr:housenumber":"7464",
    "addr:postcode":"22567",
    "addr:street":"Zachary Taylor Hwy",
    "iso:country":"US",
    "sg:address":"7464 Zachary Taylor Hwy",
    "sg:city":"Unionville",
    "sg:classifiers":[
        {
            "category":"Building & Trades",
            "subcategory":"Construction",
            "type":"Services"
        }
    ],
    "sg:phone":"+1 540 854 5606",
    "sg:postcode":"22567",
    "sg:province":"VA",
    "sg:tags":[
        "marking",
        "maintenance",
        "parking"
    ],
    "wof:name":"F & H Paving Inc",
    "wof:placetype":"venue"
},
  "geometry": {"coordinates":[-77.956402,38.296862],"type":"Point"}
}