{
  "type": "Feature",
  "properties": {
    "addr:full":"6225 Brandon Ave Springfield VA 22150",
    "addr:housenumber":"6225",
    "addr:postcode":"22150",
    "addr:street":"Brandon Ave",
    "iso:country":"US",
    "sg:address":"6225 Brandon Ave",
    "sg:city":"Springfield",
    "sg:classifiers":[
        {
            "category":"Banks & Credit Unions",
            "subcategory":"Investment Brokerage",
            "type":"Services"
        },
        {
            "category":"Professional",
            "type":"Services"
        }
    ],
    "sg:phone":"+1 703 866 3814",
    "sg:postcode":"22150",
    "sg:province":"VA",
    "sg:tags":[
        "security"
    ],
    "wof:name":"Aegis Capitol",
    "wof:placetype":"venue"
},
  "geometry": {"coordinates":[-77.18199,38.784626],"type":"Point"}
}