{
  "type": "Feature",
  "properties": {
    "addr:full":"6400 Arlington Blvd Falls Church VA 22042",
    "addr:housenumber":"6400",
    "addr:postcode":"22042",
    "addr:street":"Arlington Blvd",
    "iso:country":"US",
    "sg:address":"6400 Arlington Blvd",
    "sg:city":"Falls Church",
    "sg:classifiers":[
        {
            "category":"Organizations",
            "subcategory":"Community Association",
            "type":"Services"
        }
    ],
    "sg:phone":"+1 703 532 5005",
    "sg:postcode":"22042",
    "sg:province":"VA",
    "wof:name":"Kpa Management",
    "wof:placetype":"venue"
},
  "geometry": {"coordinates":[-77.16013100000001,38.872136],"type":"Point"}
}