{
  "type": "Feature",
  "properties": {
    "addr:full":"980 S Military Hwy Virginia Beach VA 23464",
    "addr:housenumber":"980",
    "addr:postcode":"23464",
    "addr:street":"S Military Hwy",
    "iso:country":"US",
    "sg:address":"980 S Military Hwy",
    "sg:city":"Virginia Beach",
    "sg:classifiers":[
        {
            "category":"Autos & Motor Vehicles",
            "subcategory":"Recreational Vehicle Sales",
            "type":"Retail Goods"
        },
        {
            "category":"Building & Trades",
            "subcategory":"Construction",
            "type":"Services"
        }
    ],
    "sg:phone":"+1 757 420 6816",
    "sg:postcode":"23464",
    "sg:province":"VA",
    "sg:tags":[
        "supply"
    ],
    "wof:name":"Leonard Buildings & Truck ACC",
    "wof:placetype":"venue"
},
  "geometry": {"coordinates":[-76.217102,36.812405],"type":"Point"}
}