{
  "type": "Feature",
  "properties": {
    "addr:full":"9656 Blake Ln Fairfax VA 22031",
    "addr:housenumber":"9656",
    "addr:postcode":"22031",
    "addr:street":"Blake Ln",
    "iso:country":"US",
    "sg:address":"9656 Blake Ln",
    "sg:city":"Fairfax",
    "sg:classifiers":[
        {
            "category":"Shopping",
            "subcategory":"Computers & Home Electronics",
            "type":"Retail Goods"
        }
    ],
    "sg:phone":"+1 703 938 0161",
    "sg:postcode":"22031",
    "sg:province":"VA",
    "sg:tags":[
        "software"
    ],
    "sg:website":"www.arkoinc.com",
    "wof:name":"Arko Inc",
    "wof:placetype":"venue"
},
  "geometry": {"coordinates":[-77.281227,38.87315],"type":"Point"}
}