{
  "type": "Feature",
  "properties": {
    "addr:full":"2405 Ownby Ln Richmond VA 23220",
    "addr:housenumber":"2405",
    "addr:postcode":"23220",
    "addr:street":"Ownby Ln",
    "iso:country":"US",
    "sg:address":"2405 Ownby Ln",
    "sg:city":"Richmond",
    "sg:classifiers":[
        {
            "category":"Wholesale",
            "subcategory":"Construction Materials",
            "type":"Manufacturing & Wholesale Goods"
        },
        {
            "category":"Wholesale",
            "subcategory":"Hardware",
            "type":"Manufacturing & Wholesale Goods"
        }
    ],
    "sg:phone":"+1 804 358 9308",
    "sg:postcode":"23220",
    "sg:province":"VA",
    "sg:tags":[
        "fixture",
        "bathroom",
        "door",
        "builder",
        "frame"
    ],
    "wof:name":"Architectural Hardware Inc",
    "wof:placetype":"venue"
},
  "geometry": {"coordinates":[-77.457617,37.563482],"type":"Point"}
}