{
  "type": "Feature",
  "properties": {
    "addr:full":"125 Kristin Ct Yorktown VA 23692",
    "addr:housenumber":"125",
    "addr:postcode":"23692",
    "addr:street":"Kristin Ct",
    "iso:country":"US",
    "sg:address":"125 Kristin Ct",
    "sg:city":"Yorktown",
    "sg:classifiers":[
        {
            "category":"Social Services",
            "type":"Services"
        }
    ],
    "sg:phone":"+1 757 833 6091",
    "sg:postcode":"23692",
    "sg:province":"VA",
    "sg:tags":[
        "individual",
        "family"
    ],
    "wof:name":"Cynthia M Komisarz",
    "wof:placetype":"venue"
},
  "geometry": {"coordinates":[-76.464872,37.171683],"type":"Point"}
}