{
  "type": "Feature",
  "properties": {
    "addr:full":"2413 Ridge Road Dr Alexandria VA 22302",
    "addr:housenumber":"2413",
    "addr:postcode":"22302",
    "addr:street":"Ridge Road Dr",
    "iso:country":"US",
    "sg:address":"2413 Ridge Road Dr",
    "sg:city":"Alexandria",
    "sg:classifiers":[
        {
            "category":"Professional",
            "type":"Services"
        }
    ],
    "sg:phone":"+1 703 683 1746",
    "sg:postcode":"22302",
    "sg:province":"VA",
    "sg:tags":[
        "jockey",
        "disc"
    ],
    "sg:website":"http://www.supermusicservices.com",
    "wof:name":"Supermusic Services Inc",
    "wof:placetype":"venue"
},
  "geometry": {"coordinates":[-77.07594,38.825644],"type":"Point"}
}