{
  "type": "Feature",
  "properties": {
    "addr:full":"600 Airport Rd Winchester VA 22602",
    "addr:housenumber":"600",
    "addr:postcode":"22602",
    "addr:street":"Airport Rd",
    "iso:country":"US",
    "sg:address":"600 Airport Rd",
    "sg:city":"Winchester",
    "sg:classifiers":[
        {
            "category":"Building & Trades",
            "subcategory":"Cleaning & Sanitation",
            "type":"Services"
        }
    ],
    "sg:phone":"+1 540 533 5727",
    "sg:postcode":"22602",
    "sg:province":"VA",
    "sg:tags":[
        "maintenance"
    ],
    "wof:name":"Giant Construction",
    "wof:placetype":"venue"
},
  "geometry": {"coordinates":[-78.14361599999999,39.139224],"type":"Point"}
}