{
  "type": "Feature",
  "properties": {
    "iso:country":"US",
    "sg:address":"14729 Saint Germain Dr",
    "sg:city":"Centreville",
    "sg:classifiers":[
        {
            "category":"Professional",
            "subcategory":"Business Services",
            "type":"Services"
        }
    ],
    "sg:phone":"+1 703 263 0199",
    "sg:postcode":"20121",
    "sg:province":"VA",
    "wof:name":"Mpc & Assoc Inc",
    "wof:placetype":"venue"
},
  "geometry": {"coordinates":[-77.450943,38.827363],"type":"Point"}
}