{
  "type": "Feature",
  "properties": {
    "iso:country":"US",
    "sg:address":"2317 W Broad St",
    "sg:city":"Richmond",
    "sg:classifiers":[
        {
            "category":"Building & Trades",
            "subcategory":"Plumbing",
            "type":"Services"
        }
    ],
    "sg:phone":"+1 804 254 0516",
    "sg:postcode":"23220",
    "sg:province":"VA",
    "sg:tags":[
        "conditioning",
        "air",
        "system",
        "contractor"
    ],
    "wof:name":"Sonny's Services Inc",
    "wof:placetype":"venue"
},
  "geometry": {"coordinates":[-77.464968,37.559221],"type":"Point"}
}