{
  "type": "Feature",
  "properties": {
    "iso:country":"US",
    "sg:address":"11333 Edenderry Dr",
    "sg:city":"Fairfax",
    "sg:classifiers":[
        {
            "category":"Professional",
            "subcategory":"Management & Consulting",
            "type":"Services"
        }
    ],
    "sg:phone":"+1 703 273 8016",
    "sg:postcode":"22030",
    "sg:province":"VA",
    "sg:tags":[
        "resource",
        "human"
    ],
    "wof:name":"Howard C Beattie",
    "wof:placetype":"venue"
},
  "geometry": {"coordinates":[-77.338841,38.827951],"type":"Point"}
}