{
  "type": "Feature",
  "properties": {
    "addr:full":"1901 Beauregard St Alexandria VA 22311",
    "addr:housenumber":"1901",
    "addr:postcode":"22311",
    "addr:street":"Beauregard St",
    "iso:country":"US",
    "sg:address":"1901 Beauregard St",
    "sg:city":"Alexandria",
    "sg:classifiers":[
        {
            "category":"Professional",
            "subcategory":"Computer Services",
            "type":"Services"
        }
    ],
    "sg:phone":"+1 703 931 0505",
    "sg:postcode":"22311",
    "sg:province":"VA",
    "sg:tags":[
        "programing",
        "custom"
    ],
    "wof:name":"Sonalysts Inc",
    "wof:placetype":"venue"
},
  "geometry": {"coordinates":[-77.11979599999999,38.833773],"type":"Point"}
}