{
  "type": "Feature",
  "properties": {
    "iso:country":"US",
    "sg:address":"2952 Chain Bridge Rd K",
    "sg:city":"Oakton",
    "sg:classifiers":[
        {
            "category":"Arena",
            "subcategory":"Sports Club",
            "type":"Entertainment"
        }
    ],
    "sg:phone":"+1 703 255 9554",
    "sg:postcode":"22124",
    "sg:province":"VA",
    "sg:tags":[
        "martial art",
        "instruction"
    ],
    "wof:name":"Mountain Kim Martial Arts",
    "wof:placetype":"venue"
},
  "geometry": {"coordinates":[-77.301715,38.880594],"type":"Point"}
}