{
  "type": "Feature",
  "properties": {
    "addr:full":"2905 Princess Anne Cres Chesapeake VA 23321",
    "addr:housenumber":"2905",
    "addr:postcode":"23321",
    "addr:street":"Princess;Cres",
    "iso:country":"US",
    "sg:address":"2905 Princess Anne Cres",
    "sg:city":"Chesapeake",
    "sg:classifiers":[
        {
            "category":"Organizations",
            "subcategory":"Religious Organization",
            "type":"Services"
        }
    ],
    "sg:phone":"+1 757 686 1566",
    "sg:postcode":"23321",
    "sg:province":"VA",
    "wof:name":"Society For Relief Preachers",
    "wof:placetype":"venue"
},
  "geometry": {"coordinates":[-76.404141,36.841912],"type":"Point"}
}