{
  "type": "Feature",
  "properties": {
    "iso:country":"US",
    "sg:address":"191 Rowland Creek Ln",
    "sg:city":"Marion",
    "sg:classifiers":[
        {
            "category":"Building & Trades",
            "subcategory":"Plumbing",
            "type":"Services"
        }
    ],
    "sg:phone":"+1 276 783 7509",
    "sg:postcode":"24354",
    "sg:province":"VA",
    "sg:tags":[
        "heating",
        "contractor"
    ],
    "wof:name":"Jack Owens Plumbing & Heating",
    "wof:placetype":"venue"
},
  "geometry": {"coordinates":[-81.563664,36.743049],"type":"Point"}
}