{
  "type": "Feature",
  "properties": {
    "addr:full":"5445 Glenside Dr Richmond VA 23228",
    "addr:housenumber":"5445",
    "addr:postcode":"23228",
    "addr:street":"Glenside Dr",
    "iso:country":"US",
    "sg:address":"5445 Glenside Dr",
    "sg:city":"Richmond",
    "sg:classifiers":[
        {
            "category":"Professional",
            "subcategory":"Employment Agencies",
            "type":"Services"
        }
    ],
    "sg:phone":"+1 804 484 3400",
    "sg:postcode":"23228",
    "sg:province":"VA",
    "sg:tags":[
        "help",
        "supply"
    ],
    "wof:name":"Onsite Environment",
    "wof:placetype":"venue"
},
  "geometry": {"coordinates":[-77.516104,37.609207],"type":"Point"}
}