{
  "type": "Feature",
  "properties": {
    "addr:full":"51 W del Ray Ave Alexandria VA 22301",
    "addr:housenumber":"51",
    "addr:postcode":"22301",
    "addr:street":"W Del Ray Ave",
    "iso:country":"US",
    "sg:address":"51 W del Ray Ave",
    "sg:city":"Alexandria",
    "sg:classifiers":[
        {
            "category":"Real Estate",
            "subcategory":"Architect",
            "type":"Services"
        }
    ],
    "sg:phone":"+1 703 548 3116",
    "sg:postcode":"22301",
    "sg:province":"VA",
    "wof:name":"Cobalt Design Group",
    "wof:placetype":"venue"
},
  "geometry": {"coordinates":[-77.06527699999999,38.826394],"type":"Point"}
}