{
  "type": "Feature",
  "properties": {
    "iso:country":"US",
    "sg:address":"1522 Edgemont Ave",
    "sg:city":"Bristol",
    "sg:classifiers":[
        {
            "category":"Health Services",
            "subcategory":"Doctor",
            "type":"Services"
        }
    ],
    "sg:phone":"+1 423 764 7100",
    "sg:postcode":"37620",
    "sg:province":"VA",
    "sg:tags":[
        "dentist"
    ],
    "wof:name":"Stephanie A Snelson DDS",
    "wof:placetype":"venue"
},
  "geometry": {"coordinates":[-82.184516,36.578374],"type":"Point"}
}