{
  "type": "Feature",
  "properties": {
    "addr:full":"12912 Plaza Dr Richmond VA 23233",
    "addr:housenumber":"12912",
    "addr:postcode":"23233",
    "addr:street":"Plaza Dr",
    "iso:country":"US",
    "sg:address":"12912 Plaza Dr",
    "sg:city":"Richmond",
    "sg:classifiers":[
        {
            "category":"Professional",
            "type":"Services"
        }
    ],
    "sg:phone":"+1 804 784 4323",
    "sg:postcode":"23233",
    "sg:province":"VA",
    "wof:name":"BT and T LLC",
    "wof:placetype":"venue"
},
  "geometry": {"coordinates":[-77.67831200000001,37.67175],"type":"Point"}
}