{
  "type": "Feature",
  "properties": {
    "addr:full":"7278 Enterprise St Chincoteague VA 23337",
    "addr:housenumber":"7278",
    "addr:postcode":"23337",
    "addr:street":"Enterprise St",
    "iso:country":"US",
    "sg:address":"7278 Enterprise St",
    "sg:city":"Chincoteague",
    "sg:classifiers":[
        {
            "category":"Professional",
            "subcategory":"Research",
            "type":"Services"
        }
    ],
    "sg:phone":"+1 757 824 5636",
    "sg:postcode":"23337",
    "sg:province":"VA",
    "sg:tags":[
        "organization",
        "noncommercial"
    ],
    "wof:name":"Wallops Island Mar Science Ctr",
    "wof:placetype":"venue"
},
  "geometry": {"coordinates":[-75.482511,37.935412],"type":"Point"}
}