{
  "type": "Feature",
  "properties": {
    "addr:full":"12010 Sunset Hills Rd Reston VA 20190",
    "addr:housenumber":"12010",
    "addr:postcode":"20190",
    "addr:street":"Sunset Hills Rd",
    "iso:country":"US",
    "sg:address":"12010 Sunset Hills Rd",
    "sg:city":"Reston",
    "sg:classifiers":[
        {
            "category":"Shopping",
            "subcategory":"Computers & Home Electronics",
            "type":"Retail Goods"
        }
    ],
    "sg:phone":"+1 703 736 3500",
    "sg:postcode":"20190",
    "sg:province":"VA",
    "sg:tags":[
        "software"
    ],
    "wof:name":"Integrated Chipware",
    "wof:placetype":"venue"
},
  "geometry": {"coordinates":[-77.360719,38.953635],"type":"Point"}
}