{
  "type": "Feature",
  "properties": {
    "iso:country":"US",
    "sg:address":"625 N Loudoun St",
    "sg:city":"Winchester",
    "sg:classifiers":[
        {
            "category":"Professional",
            "type":"Services"
        }
    ],
    "sg:phone":"+1 540 450 1594",
    "sg:postcode":"22601",
    "sg:province":"VA",
    "wof:name":"Mike & Lous",
    "wof:placetype":"venue"
},
  "geometry": {"coordinates":[-78.161568,39.194936],"type":"Point"}
}