{
  "type": "Feature",
  "properties": {
    "iso:country":"US",
    "sg:address":"1317 Vincent Pl",
    "sg:city":"Mc Lean",
    "sg:classifiers":[
        {
            "category":"Professional",
            "type":"Services"
        },
        {
            "category":"Professional",
            "subcategory":"Management & Consulting",
            "type":"Services"
        }
    ],
    "sg:phone":"+1 703 448 9640",
    "sg:postcode":"22101",
    "sg:province":"VA",
    "sg:tags":[
        "establishment",
        "hospital",
        "health",
        "consultant"
    ],
    "sg:website":"www.tgtg.com",
    "wof:name":"Global Telemedicine Group The",
    "wof:placetype":"venue"
},
  "geometry": {"coordinates":[-77.180684,38.936658],"type":"Point"}
}