{
  "type": "Feature",
  "properties": {
    "iso:country":"US",
    "sg:address":"1132 Powhatan St",
    "sg:city":"Alexandria",
    "sg:classifiers":[
        {
            "category":"Education",
            "subcategory":"Special Training",
            "type":"Public Place"
        }
    ],
    "sg:phone":"+1 703 684 6940",
    "sg:postcode":"22314",
    "sg:province":"VA",
    "sg:tags":[
        "instructor",
        "language"
    ],
    "wof:name":"Romanian Language Culture Svcs",
    "wof:placetype":"venue"
},
  "geometry": {"coordinates":[-77.047431,38.818246],"type":"Point"}
}