{
  "type": "Feature",
  "properties": {
    "addr:full":"19808 US Hwy 29 Chatham VA 24531",
    "addr:housenumber":"19808",
    "addr:postcode":"24531",
    "addr:street":"Us Hwy 29",
    "iso:country":"US",
    "sg:address":"19808 US Hwy 29",
    "sg:city":"Chatham",
    "sg:classifiers":[
        {
            "category":"Shopping",
            "subcategory":"Clothing, Apparel, & Fashions",
            "type":"Retail Goods"
        }
    ],
    "sg:phone":"+1 434 432 3711",
    "sg:postcode":"24531",
    "sg:province":"VA",
    "wof:name":"Marlene's Dress Shop",
    "wof:placetype":"venue"
},
  "geometry": {"coordinates":[-79.402642,36.86512],"type":"Point"}
}