{
  "type": "Feature",
  "properties": {
    "iso:country":"US",
    "sg:address":"431 Winterhaven Dr",
    "sg:city":"Newport News",
    "sg:classifiers":[
        {
            "category":"Organizations",
            "subcategory":"Community Association",
            "type":"Services"
        }
    ],
    "sg:phone":"+1 757 930 1440",
    "sg:postcode":"23606",
    "sg:province":"VA",
    "wof:name":"James L Hale Chapter",
    "wof:placetype":"venue"
},
  "geometry": {"coordinates":[-76.492919,37.083388],"type":"Point"}
}