{
  "type": "Feature",
  "properties": {
    "iso:country":"US",
    "sg:address":"465 Toms Rd",
    "sg:city":"Waynesboro",
    "sg:classifiers":[
        {
            "category":"Wholesale",
            "subcategory":"Hardware",
            "type":"Manufacturing & Wholesale Goods"
        }
    ],
    "sg:phone":"+1 540 949 7571",
    "sg:postcode":"22923",
    "sg:province":"VA",
    "sg:tags":[
        "parts",
        "refrigerating"
    ],
    "wof:name":"Comer's Service Co",
    "wof:placetype":"venue"
},
  "geometry": {"coordinates":[-78.346797,38.230703],"type":"Point"}
}