{
  "type": "Feature",
  "properties": {
    "iso:country":"US",
    "sg:address":"3303 Arbor Ter",
    "sg:city":"Charlottesville",
    "sg:classifiers":[
        {
            "category":"Professional",
            "subcategory":"Management & Consulting",
            "type":"Services"
        }
    ],
    "sg:phone":"+1 434 972 7278",
    "sg:postcode":"22911",
    "sg:province":"VA",
    "sg:tags":[
        "public",
        "relations"
    ],
    "wof:name":"Four Leaf Public Relations LLC",
    "wof:placetype":"venue"
},
  "geometry": {"coordinates":[-78.43022499999999,38.127156],"type":"Point"}
}