{
  "type": "Feature",
  "properties": {
    "iso:country":"US",
    "sg:address":"5795 Burke Towne Ct",
    "sg:city":"Burke",
    "sg:classifiers":[
        {
            "category":"Wholesale",
            "subcategory":"Auto Parts",
            "type":"Manufacturing & Wholesale Goods"
        }
    ],
    "sg:phone":"+1 703 323 1554",
    "sg:postcode":"22015",
    "sg:province":"VA",
    "wof:name":"Mhg International Inc",
    "wof:placetype":"venue"
},
  "geometry": {"coordinates":[-77.275665,38.793295],"type":"Point"}
}