{
  "type": "Feature",
  "properties": {
    "addr:full":"475 Deal Pl Amissville VA 20106",
    "addr:housenumber":"475",
    "addr:postcode":"20106",
    "addr:street":"Deal Pl",
    "iso:country":"US",
    "sg:address":"475 Deal Pl",
    "sg:city":"Amissville",
    "sg:classifiers":[
        {
            "category":"Manufacturing",
            "subcategory":"Signs",
            "type":"Manufacturing & Wholesale Goods"
        }
    ],
    "sg:phone":"+1 540 341 2728",
    "sg:postcode":"20106",
    "sg:province":"VA",
    "wof:name":"About Signs",
    "wof:placetype":"venue"
},
  "geometry": {"coordinates":[-77.932438,38.690929],"type":"Point"}
}