{
  "type": "Feature",
  "properties": {
    "addr:full":"5911 2nd St N Arlington VA 22203",
    "addr:housenumber":"5911",
    "addr:postcode":"22203",
    "addr:street":"2Nd St N",
    "iso:country":"US",
    "sg:address":"5911 2nd St N",
    "sg:city":"Arlington",
    "sg:classifiers":[
        {
            "category":"Professional",
            "subcategory":"Secretarial Services",
            "type":"Services"
        }
    ],
    "sg:phone":"+1 703 528 5403",
    "sg:postcode":"22203",
    "sg:province":"VA",
    "sg:tags":[
        "reporting"
    ],
    "wof:name":"Me/Word Processing",
    "wof:placetype":"venue"
},
  "geometry": {"coordinates":[-77.13598500000001,38.867847],"type":"Point"}
}