{
  "type": "Feature",
  "properties": {
    "addr:full":"3809 Laramie Pl Alexandria VA 22309",
    "addr:housenumber":"3809",
    "addr:postcode":"22309",
    "addr:street":"Laramie Pl",
    "iso:country":"US",
    "sg:address":"3809 Laramie Pl",
    "sg:city":"Alexandria",
    "sg:classifiers":[
        {
            "category":"Building & Trades",
            "subcategory":"Cleaning & Sanitation",
            "type":"Services"
        }
    ],
    "sg:phone":"+1 703 799 4100",
    "sg:postcode":"22309",
    "sg:province":"VA",
    "sg:tags":[
        "maintenance"
    ],
    "wof:name":"Window Wrestlers",
    "wof:placetype":"venue"
},
  "geometry": {"coordinates":[-77.09716400000001,38.741585],"type":"Point"}
}