{
  "type": "Feature",
  "properties": {
    "addr:full":"8116 Lake Pleasant Dr Springfield VA 22153",
    "addr:housenumber":"8116",
    "addr:postcode":"22153",
    "addr:street":"Lake Pleasant Dr",
    "iso:country":"US",
    "sg:address":"8116 Lake Pleasant Dr",
    "sg:city":"Springfield",
    "sg:classifiers":[
        {
            "category":"Organizations",
            "subcategory":"Membership Organization",
            "type":"Services"
        }
    ],
    "sg:phone":"+1 703 866 6345",
    "sg:postcode":"22153",
    "sg:province":"VA",
    "wof:name":"Free Muslim Assoc",
    "wof:placetype":"venue"
},
  "geometry": {"coordinates":[-77.218518,38.735588],"type":"Point"}
}