{
  "type": "Feature",
  "properties": {
    "iso:country":"US",
    "sg:address":"111 Wiggington Rd",
    "sg:city":"Lynchburg",
    "sg:classifiers":[
        {
            "category":"Communications",
            "type":"Services"
        }
    ],
    "sg:phone":"+1 434 385 4548",
    "sg:postcode":"24502",
    "sg:province":"VA",
    "sg:tags":[
        "communication"
    ],
    "wof:name":"Ionian Communications",
    "wof:placetype":"venue"
},
  "geometry": {"coordinates":[-79.22073,37.406904],"type":"Point"}
}