{
  "type": "Feature",
  "properties": {
    "iso:country":"US",
    "sg:address":"925 Harris St",
    "sg:city":"Charlottesville",
    "sg:classifiers":[
        {
            "category":"Retail",
            "subcategory":"Repair Shop",
            "type":"Services"
        },
        {
            "category":"Home & Garden",
            "subcategory":"Garden Supply",
            "type":"Retail Goods"
        }
    ],
    "sg:phone":"+1 434 296 3249",
    "sg:postcode":"22903",
    "sg:province":"VA",
    "sg:tags":[
        "lawn"
    ],
    "wof:name":"Becker's LLC",
    "wof:placetype":"venue"
},
  "geometry": {"coordinates":[-78.482287,38.038009],"type":"Point"}
}