{
  "type": "Feature",
  "properties": {
    "iso:country":"US",
    "sg:address":"3420 Pump Rd",
    "sg:city":"Richmond",
    "sg:classifiers":[
        {
            "category":"Professional",
            "subcategory":"Business Services",
            "type":"Services"
        }
    ],
    "sg:phone":"+1 804 360 9626",
    "sg:postcode":"23233",
    "sg:province":"VA",
    "wof:name":"American Print & Mail",
    "wof:placetype":"venue"
},
  "geometry": {"coordinates":[-77.614288,37.648209],"type":"Point"}
}