{
  "type": "Feature",
  "properties": {
    "addr:full":"3867 Colony Ln Roanoke VA 24018",
    "addr:housenumber":"3867",
    "addr:postcode":"24018",
    "addr:street":"Colony Ln",
    "iso:country":"US",
    "sg:address":"3867 Colony Ln",
    "sg:city":"Roanoke",
    "sg:classifiers":[
        {
            "category":"Building & Trades",
            "subcategory":"Construction",
            "type":"Services"
        }
    ],
    "sg:phone":"+1 540 774 2166",
    "sg:postcode":"24018",
    "sg:province":"VA",
    "sg:tags":[
        "house"
    ],
    "wof:name":"Brooks & Company",
    "wof:placetype":"venue"
},
  "geometry": {"coordinates":[-79.992893,37.225598],"type":"Point"}
}