{
  "type": "Feature",
  "properties": {
    "addr:full":"1674 Iroquois Trl Bedford VA 24523",
    "addr:housenumber":"1674",
    "addr:postcode":"24523",
    "addr:street":"Iroquois Trl",
    "iso:country":"US",
    "sg:address":"1674 Iroquois Trl",
    "sg:city":"Bedford",
    "sg:classifiers":[
        {
            "category":"Professional",
            "type":"Services"
        }
    ],
    "sg:phone":"+1 540 586 5610",
    "sg:postcode":"24523",
    "sg:province":"VA",
    "wof:name":"Stevick",
    "wof:placetype":"venue"
},
  "geometry": {"coordinates":[-79.458292,37.424628],"type":"Point"}
}