{
  "type": "Feature",
  "properties": {
    "addr:full":"6625 Electric Ave Warrenton VA 20187",
    "addr:housenumber":"6625",
    "addr:postcode":"20187",
    "addr:street":"Electric Ave",
    "iso:country":"US",
    "sg:address":"6625 Electric Ave",
    "sg:city":"Warrenton",
    "sg:classifiers":[
        {
            "category":"Real Estate",
            "subcategory":"Real Estate Agent",
            "type":"Services"
        }
    ],
    "sg:phone":"+1 540 428 1882",
    "sg:postcode":"20187",
    "sg:province":"VA",
    "wof:name":"Lewis & Clark",
    "wof:placetype":"venue"
},
  "geometry": {"coordinates":[-77.721609,38.765995],"type":"Point"}
}