{
  "type": "Feature",
  "properties": {
    "addr:full":"20789 Great Falls Plz Sterling VA 20165",
    "addr:housenumber":"20789",
    "addr:postcode":"20165",
    "addr:street":"Plz",
    "iso:country":"US",
    "sg:address":"20789 Great Falls Plz",
    "sg:city":"Sterling",
    "sg:classifiers":[
        {
            "category":"Cinema",
            "subcategory":"Movie Rental",
            "type":"Entertainment"
        }
    ],
    "sg:phone":"+1 703 450 1661",
    "sg:postcode":"20165",
    "sg:province":"VA",
    "sg:tags":[
        "video",
        "tape"
    ],
    "wof:name":"Video Warehouse",
    "wof:placetype":"venue"
},
  "geometry": {"coordinates":[-77.357916,39.040244],"type":"Point"}
}