{
  "type": "Feature",
  "properties": {
    "iso:country":"US",
    "sg:address":"13541 E Boundary Rd",
    "sg:city":"Midlothian",
    "sg:classifiers":[
        {
            "category":"Professional",
            "subcategory":"Employment Agencies",
            "type":"Services"
        }
    ],
    "sg:phone":"+1 804 359 1392",
    "sg:postcode":"23112",
    "sg:province":"VA",
    "sg:tags":[
        "help",
        "supply"
    ],
    "wof:name":"Trojan Labor",
    "wof:placetype":"venue"
},
  "geometry": {"coordinates":[-77.646444,37.448046],"type":"Point"}
}