{
  "type": "Feature",
  "properties": {
    "iso:country":"US",
    "sg:address":"1902 Old Stage Rd",
    "sg:city":"Lawrenceville",
    "sg:classifiers":[
        {
            "category":"Wholesale",
            "subcategory":"Farm Supplies",
            "type":"Manufacturing & Wholesale Goods"
        }
    ],
    "sg:phone":"+1 434 848 4373",
    "sg:postcode":"23868",
    "sg:province":"VA",
    "sg:tags":[
        "livestock"
    ],
    "wof:name":"Theresa Carpenter",
    "wof:placetype":"venue"
},
  "geometry": {"coordinates":[-77.764442,36.807179],"type":"Point"}
}