{
  "type": "Feature",
  "properties": {
    "addr:full":"4004 Margaret Cir Virginia Beach VA 23456",
    "addr:housenumber":"4004",
    "addr:postcode":"23456",
    "addr:street":"Margaret Cir",
    "iso:country":"US",
    "sg:address":"4004 Margaret Cir",
    "sg:city":"Virginia Beach",
    "sg:classifiers":[
        {
            "category":"Professional",
            "subcategory":"Management & Consulting",
            "type":"Services"
        }
    ],
    "sg:phone":"+1 757 430 3118",
    "sg:postcode":"23456",
    "sg:province":"VA",
    "wof:name":"Monaco Capital Mangement LL",
    "wof:placetype":"venue"
},
  "geometry": {"coordinates":[-76.12326299999999,36.766272],"type":"Point"}
}