{
  "type": "Feature",
  "properties": {
    "addr:full":"2003 Gallows Tree Ct Vienna VA 22182",
    "addr:housenumber":"2003",
    "addr:postcode":"22182",
    "addr:street":"Gallows Tree Ct",
    "iso:country":"US",
    "sg:address":"2003 Gallows Tree Ct",
    "sg:city":"Vienna",
    "sg:classifiers":[
        {
            "category":"Government",
            "subcategory":"Office",
            "type":"Public Place"
        }
    ],
    "sg:phone":"+1 703 963 1043",
    "sg:postcode":"22182",
    "sg:province":"VA",
    "sg:tags":[
        "security",
        "consulting"
    ],
    "wof:name":"Strategic Security Systems LLC",
    "wof:placetype":"venue"
},
  "geometry": {"coordinates":[-77.22476899999999,38.907992],"type":"Point"}
}