{
  "type": "Feature",
  "properties": {
    "addr:full":"122 W 21st St Norfolk VA 23517",
    "addr:housenumber":"122",
    "addr:postcode":"23517",
    "addr:street":"W 21St St",
    "iso:country":"US",
    "sg:address":"122 W 21st St",
    "sg:city":"Norfolk",
    "sg:classifiers":[
        {
            "category":"Shopping",
            "subcategory":"Used Merchandise",
            "type":"Retail Goods"
        }
    ],
    "sg:phone":"+1 757 622 0414",
    "sg:postcode":"23517",
    "sg:province":"VA",
    "sg:tags":[
        "antique"
    ],
    "wof:name":"Richard Levin's Garfield's",
    "wof:placetype":"venue"
},
  "geometry": {"coordinates":[-76.286123,36.867791],"type":"Point"}
}