{
  "type": "Feature",
  "properties": {
    "iso:country":"US",
    "sg:address":"5523 Woodrow Ter",
    "sg:city":"Richmond",
    "sg:classifiers":[
        {
            "category":"Building & Trades",
            "subcategory":"Construction",
            "type":"Services"
        }
    ],
    "sg:phone":"+1 804 264 6845",
    "sg:postcode":"23228",
    "sg:province":"VA",
    "sg:tags":[
        "contractor"
    ],
    "wof:name":"Richmond Residential Roofing",
    "wof:placetype":"venue"
},
  "geometry": {"coordinates":[-77.48115900000001,37.605963],"type":"Point"}
}