{
  "type": "Feature",
  "properties": {
    "iso:country":"US",
    "sg:address":"3608 Canal Turn Ct",
    "sg:city":"Suffolk",
    "sg:classifiers":[
        {
            "category":"Building & Trades",
            "subcategory":"Landscaping Services",
            "type":"Services"
        }
    ],
    "sg:phone":"+1 757 686 4847",
    "sg:postcode":"23435",
    "sg:province":"VA",
    "wof:name":"Hickmans Lawn Maintenance",
    "wof:placetype":"venue"
},
  "geometry": {"coordinates":[-76.466821,36.848726],"type":"Point"}
}