{
  "type": "Feature",
  "properties": {
    "addr:full":"6630 Jefferson St Haymarket VA 20169",
    "addr:housenumber":"6630",
    "addr:postcode":"20169",
    "addr:street":"Jefferson St",
    "iso:country":"US",
    "sg:address":"6630 Jefferson St",
    "sg:city":"Haymarket",
    "sg:classifiers":[
        {
            "category":"Building & Trades",
            "subcategory":"Construction",
            "type":"Services"
        }
    ],
    "sg:phone":"+1 703 551 2200",
    "sg:postcode":"20169",
    "sg:province":"VA",
    "sg:tags":[
        "general",
        "contractor"
    ],
    "sg:website":"www.dominionconstruction.com",
    "wof:name":"Dominion Construction Inc",
    "wof:placetype":"venue"
},
  "geometry": {"coordinates":[-77.634795,38.814749],"type":"Point"}
}