{
  "type": "Feature",
  "properties": {
    "iso:country":"US",
    "sg:address":"207 Braeburn Dr",
    "sg:city":"Winchester",
    "sg:classifiers":[
        {
            "category":"Building & Trades",
            "subcategory":"Cleaning & Sanitation",
            "type":"Services"
        }
    ],
    "sg:phone":"+1 540 667 3064",
    "sg:postcode":"22601",
    "sg:province":"VA",
    "sg:tags":[
        "janitor"
    ],
    "wof:name":"Complete Cleaning Svc",
    "wof:placetype":"venue"
},
  "geometry": {"coordinates":[-78.136494,39.191086],"type":"Point"}
}