{
  "type": "Feature",
  "properties": {
    "addr:full":"21455 Chestnut Ln Zuni VA 23898",
    "addr:housenumber":"21455",
    "addr:postcode":"23898",
    "addr:street":"Chestnut Ln",
    "iso:country":"US",
    "sg:address":"21455 Chestnut Ln",
    "sg:city":"Zuni",
    "sg:classifiers":[
        {
            "category":"Education",
            "subcategory":"School",
            "type":"Public Place"
        }
    ],
    "sg:phone":"+1 757 242 9237",
    "sg:postcode":"23898",
    "sg:province":"VA",
    "wof:name":"Cypress Spring Farm Oee",
    "wof:placetype":"venue"
},
  "geometry": {"coordinates":[-76.84261600000001,36.842561],"type":"Point"}
}