{
  "type": "Feature",
  "properties": {
    "addr:full":"6 Harrop Parrish Ct Williamsburg VA 23188",
    "addr:housenumber":"6",
    "addr:postcode":"23188",
    "addr:street":"Harrop Parrish Ct",
    "iso:country":"US",
    "sg:address":"6 Harrop Parrish Ct",
    "sg:city":"Williamsburg",
    "sg:classifiers":[
        {
            "category":"Manufacturing",
            "subcategory":"Metals",
            "type":"Manufacturing & Wholesale Goods"
        }
    ],
    "sg:phone":"+1 757 259 2464",
    "sg:postcode":"23188",
    "sg:province":"VA",
    "sg:tags":[
        "hardware",
        "mfg"
    ],
    "wof:name":"Sargent Greenleaf Inc",
    "wof:placetype":"venue"
},
  "geometry": {"coordinates":[-76.775564,37.2988],"type":"Point"}
}