{
  "type": "Feature",
  "properties": {
    "iso:country":"US",
    "sg:address":"110 Battlefield Blvd N",
    "sg:city":"Chesapeake",
    "sg:classifiers":[
        {
            "category":"Manufacturing",
            "subcategory":"Paper Products",
            "type":"Manufacturing & Wholesale Goods"
        }
    ],
    "sg:phone":"+1 757 547 5478",
    "sg:postcode":"23320",
    "sg:province":"VA",
    "sg:tags":[
        "label"
    ],
    "sg:website":"www.designsincva.com",
    "wof:name":"De Signs Inc",
    "wof:placetype":"venue"
},
  "geometry": {"coordinates":[-76.24049599999999,36.722325],"type":"Point"}
}