{
  "type": "Feature",
  "properties": {
    "addr:full":"2120 John Rolfe Pkwy Richmond VA 23233",
    "addr:housenumber":"2120",
    "addr:postcode":"23233",
    "addr:street":"John Rolfe Pkwy",
    "iso:country":"US",
    "sg:address":"2120 John Rolfe Pkwy",
    "sg:city":"Richmond",
    "sg:classifiers":[
        {
            "category":"Restaurant",
            "type":"Food & Drink"
        }
    ],
    "sg:menulink":"http://www.allmenus.com/va/tuckahoe/192042-wendys/menu/",
    "sg:phone":"+1 804 364 1991",
    "sg:postcode":"23233",
    "sg:province":"VA",
    "sg:tags":[
        "burger",
        "american",
        "soup"
    ],
    "wof:name":"Wendy's",
    "wof:placetype":"venue"
},
  "geometry": {"coordinates":[-77.623965,37.621105],"type":"Point"}
}