{
  "type": "Feature",
  "properties": {
    "addr:full":"733 W Cary St Richmond VA 23220",
    "addr:housenumber":"733",
    "addr:postcode":"23220",
    "addr:street":"W Cary St",
    "iso:country":"US",
    "sg:address":"733 W Cary St",
    "sg:city":"Richmond",
    "sg:classifiers":[
        {
            "category":"Restaurant",
            "type":"Food & Drink"
        }
    ],
    "sg:phone":"+1 804 644 6676",
    "sg:postcode":"23220",
    "sg:province":"VA",
    "sg:tags":[
        "style",
        "american",
        "family"
    ],
    "wof:name":"Mojo's",
    "wof:placetype":"venue"
},
  "geometry": {"coordinates":[-77.450754,37.544493],"type":"Point"}
}