{
  "type": "Feature",
  "properties": {
    "addr:full":"4111 11th Pl N Arlington VA 22201",
    "addr:housenumber":"4111",
    "addr:postcode":"22201",
    "addr:street":"11Th Pl N",
    "iso:country":"US",
    "sg:address":"4111 11th Pl N",
    "sg:city":"Arlington",
    "sg:classifiers":[
        {
            "category":"Communications",
            "type":"Services"
        }
    ],
    "sg:phone":"+1 703 625 4029",
    "sg:postcode":"22201",
    "sg:province":"VA",
    "wof:name":"Digital Democracy",
    "wof:placetype":"venue"
},
  "geometry": {"coordinates":[-77.110411,38.884816],"type":"Point"}
}