{
  "type": "Feature",
  "properties": {
    "iso:country":"US",
    "sg:address":"44136 Merrywood Ct",
    "sg:city":"Ashburn",
    "sg:classifiers":[
        {
            "category":"Personal",
            "subcategory":"Beauty Salon",
            "type":"Services"
        }
    ],
    "sg:phone":"+1 703 723 1915",
    "sg:postcode":"20147",
    "sg:province":"VA",
    "sg:tags":[
        "shop"
    ],
    "wof:name":"Denise Johnston",
    "wof:placetype":"venue"
},
  "geometry": {"coordinates":[-77.474321,39.026336],"type":"Point"}
}