{
  "type": "Feature",
  "properties": {
    "addr:full":"1750 Tysons Blvd Mc Lean VA 22102",
    "addr:housenumber":"1750",
    "addr:postcode":"22102",
    "addr:street":"Tysons Blvd Mc Lean",
    "iso:country":"US",
    "sg:address":"1750 Tysons Blvd",
    "sg:city":"Mc Lean",
    "sg:classifiers":[
        {
            "category":"Professional",
            "subcategory":"Lawyer & Legal Services",
            "type":"Services"
        }
    ],
    "sg:phone":"+1 703 712 5068",
    "sg:postcode":"22102",
    "sg:province":"VA",
    "wof:name":"Neff Laurie F Atty",
    "wof:placetype":"venue"
},
  "geometry": {"coordinates":[-77.222244,38.92333],"type":"Point"}
}