{
  "type": "Feature",
  "properties": {
    "iso:country":"US",
    "sg:address":"4174 Mount Laurel Rd",
    "sg:city":"Williamsburg",
    "sg:classifiers":[
        {
            "category":"Building & Trades",
            "subcategory":"Landscaping Services",
            "type":"Services"
        }
    ],
    "sg:phone":"+1 757 566 1579",
    "sg:postcode":"23188",
    "sg:province":"VA",
    "sg:tags":[
        "landscape",
        "contractor"
    ],
    "wof:name":"Belden Landscapes",
    "wof:placetype":"venue"
},
  "geometry": {"coordinates":[-76.773295,37.403638],"type":"Point"}
}