{
  "type": "Feature",
  "properties": {
    "addr:full":"4508 Starkey Rd Roanoke VA 24018",
    "addr:housenumber":"4508",
    "addr:postcode":"24018",
    "addr:street":"Starkey Rd",
    "iso:country":"US",
    "sg:address":"4508 Starkey Rd",
    "sg:city":"Roanoke",
    "sg:classifiers":[
        {
            "category":"Recreation",
            "type":"Entertainment"
        }
    ],
    "sg:phone":"+1 540 989 5758",
    "sg:postcode":"24018",
    "sg:province":"VA",
    "sg:tags":[
        "club",
        "membership"
    ],
    "wof:name":"Roanoke Wellness and Athc CLB",
    "wof:placetype":"venue"
},
  "geometry": {"coordinates":[-79.984442,37.223761],"type":"Point"}
}