{
  "type": "Feature",
  "properties": {
    "addr:full":"3505 Bus Center Dr Chesapeake VA 23323",
    "addr:postcode":"3505;23323",
    "addr:street":"Center Dr",
    "iso:country":"US",
    "sg:address":"3505 Bus Center Dr",
    "sg:city":"Chesapeake",
    "sg:classifiers":[
        {
            "category":"Building & Trades",
            "subcategory":"Construction",
            "type":"Services"
        }
    ],
    "sg:phone":"+1 757 485 0400",
    "sg:postcode":"23323",
    "sg:province":"VA",
    "sg:tags":[
        "sandblasting"
    ],
    "wof:name":"Mid Atlantic Coatings Inc",
    "wof:placetype":"venue"
},
  "geometry": {"coordinates":[-76.35994700000001,36.786313],"type":"Point"}
}