{
  "type": "Feature",
  "properties": {
    "iso:country":"US",
    "sg:address":"4305 Backlick Rd",
    "sg:city":"Annandale",
    "sg:classifiers":[
        {
            "category":"Shopping",
            "subcategory":"Clothing, Apparel, & Fashions",
            "type":"Retail Goods"
        }
    ],
    "sg:phone":"+1 703 256 8644",
    "sg:postcode":"22003",
    "sg:province":"VA",
    "sg:tags":[
        "alterations-clothing"
    ],
    "sg:website":"http://www.zipweb.com/?businessName=AlanUdallDds/",
    "wof:name":"Francis Tailors",
    "wof:placetype":"venue"
},
  "geometry": {"coordinates":[-77.19435900000001,38.8302],"type":"Point"}
}