{
  "type": "Feature",
  "properties": {
    "iso:country":"US",
    "sg:address":"4024 W Broad St",
    "sg:city":"Richmond",
    "sg:classifiers":[
        {
            "category":"Autos & Motor Vehicles",
            "subcategory":"Fuel & Gas Station",
            "type":"Retail Goods"
        }
    ],
    "sg:phone":"+1 804 353 9940",
    "sg:postcode":"23230",
    "sg:province":"VA",
    "sg:tags":[
        "oil"
    ],
    "wof:name":"Rennie's",
    "wof:placetype":"venue"
},
  "geometry": {"coordinates":[-77.483594,37.573413],"type":"Point"}
}