{
  "type": "Feature",
  "properties": {
    "addr:full":"422 Crawford St Portsmouth VA 23704",
    "addr:housenumber":"422",
    "addr:postcode":"23704",
    "addr:street":"Crawford St",
    "iso:country":"US",
    "sg:address":"422 Crawford St",
    "sg:city":"Portsmouth",
    "sg:classifiers":[
        {
            "category":"Professional",
            "subcategory":"Lawyer & Legal Services",
            "type":"Services"
        }
    ],
    "sg:phone":"+1 757 397 0003",
    "sg:postcode":"23704",
    "sg:province":"VA",
    "sg:tags":[
        "attorney"
    ],
    "wof:name":"Holley & Massie",
    "wof:placetype":"venue"
},
  "geometry": {"coordinates":[-76.29801999999999,36.83763],"type":"Point"}
}