{
  "type": "Feature",
  "properties": {
    "iso:country":"US",
    "sg:address":"13850 Rembrandt Way",
    "sg:city":"Chantilly",
    "sg:classifiers":[
        {
            "category":"Professional",
            "subcategory":"Computer Services",
            "type":"Services"
        }
    ],
    "sg:phone":"+1 703 861 7131",
    "sg:postcode":"20151",
    "sg:province":"VA",
    "sg:tags":[
        "consulting",
        "it",
        "solution"
    ],
    "wof:name":"Sk Consulting",
    "wof:placetype":"venue"
},
  "geometry": {"coordinates":[-77.425321,38.900138],"type":"Point"}
}