{
  "type": "Feature",
  "properties": {
    "addr:full":"11213 Lee Hwy Ste L Fairfax VA 22030",
    "addr:housenumber":"11213",
    "addr:postcode":"22030",
    "addr:street":"Lee Hwy Ste L",
    "iso:country":"US",
    "sg:address":"11213 Lee Hwy Ste L",
    "sg:city":"Fairfax",
    "sg:classifiers":[
        {
            "category":"Utilities",
            "subcategory":"Mobile Phone",
            "type":"Services"
        }
    ],
    "sg:phone":"+1 703 352 0203",
    "sg:postcode":"22030",
    "sg:province":"VA",
    "sg:tags":[
        "telephone",
        "cellular"
    ],
    "wof:name":"Sprint- Adcomm Digital",
    "wof:placetype":"venue"
},
  "geometry": {"coordinates":[-77.332751,38.851606],"type":"Point"}
}