{
  "type": "Feature",
  "properties": {
    "addr:full":"3923 Hull Street Rd Richmond VA 23224",
    "addr:housenumber":"3923",
    "addr:postcode":"23224",
    "addr:street":"Hull Street Rd",
    "iso:country":"US",
    "sg:address":"3923 Hull Street Rd",
    "sg:city":"Richmond",
    "sg:classifiers":[
        {
            "category":"Food & Beverages",
            "subcategory":"Groceries & Convenience Stores",
            "type":"Retail Goods"
        }
    ],
    "sg:phone":"+1 804 440 1555",
    "sg:postcode":"23224",
    "sg:province":"VA",
    "wof:name":"Buggy Jamaican Grocery",
    "wof:placetype":"venue"
},
  "geometry": {"coordinates":[-77.47237199999999,37.502959],"type":"Point"}
}