{
  "type": "Feature",
  "properties": {
    "iso:country":"US",
    "sg:address":"120 W Main St",
    "sg:city":"Floyd",
    "sg:classifiers":[
        {
            "category":"Professional",
            "subcategory":"Accounting & Tax Preparation",
            "type":"Services"
        }
    ],
    "sg:phone":"+1 540 745 3818",
    "sg:postcode":"24091",
    "sg:province":"VA",
    "sg:tags":[
        "accountant"
    ],
    "wof:name":"Michael J Hatcher",
    "wof:placetype":"venue"
},
  "geometry": {"coordinates":[-80.321046,36.911078],"type":"Point"}
}