{
  "type": "Feature",
  "properties": {
    "addr:full":"45925 Maries Rd Sterling VA 20166",
    "addr:postcode":"45925;20166",
    "addr:street":"Maries Rd",
    "iso:country":"US",
    "sg:address":"45925 Maries Rd",
    "sg:city":"Sterling",
    "sg:classifiers":[
        {
            "category":"Professional",
            "subcategory":"Computer Services",
            "type":"Services"
        }
    ],
    "sg:phone":"+1 703 421 8100",
    "sg:postcode":"20166",
    "sg:province":"VA",
    "sg:tags":[
        "consultant",
        "designer"
    ],
    "sg:website":"www.inlinecorp.com",
    "wof:name":"Inline Corp",
    "wof:placetype":"venue"
},
  "geometry": {"coordinates":[-77.40894299999999,39.020621],"type":"Point"}
}