{
  "type": "Feature",
  "properties": {
    "addr:full":"16401 Chickahominy Bluff Rd Williamsburg VA 23185",
    "addr:housenumber":"16401",
    "addr:postcode":"23185",
    "addr:street":"Chickahominy Bluff Rd",
    "iso:country":"US",
    "sg:address":"16401 Chickahominy Bluff Rd",
    "sg:city":"Williamsburg",
    "sg:classifiers":[
        {
            "category":"Organizations",
            "subcategory":"Religious Organization",
            "type":"Services"
        }
    ],
    "sg:phone":"+1 757 565 3142",
    "sg:postcode":"23185",
    "sg:province":"VA",
    "sg:tags":[
        "church"
    ],
    "wof:name":"Grove Christian Outreach Ctr",
    "wof:placetype":"venue"
},
  "geometry": {"coordinates":[-76.88235899999999,37.262265],"type":"Point"}
}