{
  "type": "Feature",
  "properties": {
    "iso:country":"US",
    "sg:address":"230 Bull Run Rd",
    "sg:city":"Bassett",
    "sg:classifiers":[
        {
            "category":"Organizations",
            "subcategory":"Religious Organization",
            "type":"Services"
        }
    ],
    "sg:phone":"+1 276 673 1005",
    "sg:postcode":"24055",
    "sg:province":"VA",
    "sg:tags":[
        "church"
    ],
    "wof:name":"Riverview Primitive Baptist Ch",
    "wof:placetype":"venue"
},
  "geometry": {"coordinates":[-80.043763,36.682204],"type":"Point"}
}