{
  "type": "Feature",
  "properties": {
    "addr:full":"205 Morven Park Rd NW Leesburg VA 20176",
    "addr:housenumber":"205",
    "addr:postcode":"20176",
    "addr:street":"Morven Park Rd Nw",
    "iso:country":"US",
    "sg:address":"205 Morven Park Rd NW",
    "sg:city":"Leesburg",
    "sg:classifiers":[
        {
            "category":"Professional",
            "subcategory":"Management & Consulting",
            "type":"Services"
        },
        {
            "category":"Professional",
            "subcategory":"Engineering",
            "type":"Services"
        }
    ],
    "sg:phone":"+1 703 669 8691",
    "sg:postcode":"20176",
    "sg:province":"VA",
    "sg:tags":[
        "environmental",
        "ecological",
        "engineer",
        "consultant"
    ],
    "wof:name":"Tomtoxiccom",
    "wof:placetype":"venue"
},
  "geometry": {"coordinates":[-77.57209,39.123692],"type":"Point"}
}