{
  "type": "Feature",
  "properties": {
    "addr:full":"3816 Old Gun Rd W Midlothian VA 23113",
    "addr:housenumber":"3816",
    "addr:postcode":"23113",
    "addr:street":"Old Gun Rd W",
    "iso:country":"US",
    "sg:address":"3816 Old Gun Rd W",
    "sg:city":"Midlothian",
    "sg:classifiers":[
        {
            "category":"Health Services",
            "subcategory":"Clinic",
            "type":"Services"
        }
    ],
    "sg:phone":"+1 804 320 1483",
    "sg:postcode":"23113",
    "sg:province":"VA",
    "wof:name":"Wkg & J",
    "wof:placetype":"venue"
},
  "geometry": {"coordinates":[-77.614441,37.554424],"type":"Point"}
}