{
  "type": "Feature",
  "properties": {
    "iso:country":"US",
    "sg:address":"552 Central Dr",
    "sg:city":"Virginia Beach",
    "sg:classifiers":[
        {
            "category":"Home & Garden",
            "subcategory":"Home Furnishings",
            "type":"Retail Goods"
        }
    ],
    "sg:phone":"+1 757 481 5805",
    "sg:postcode":"23454",
    "sg:province":"VA",
    "sg:tags":[
        "venetian",
        "blind"
    ],
    "sg:website":"www.aaablinds.com",
    "wof:name":"AAA Blind & Shade Factory",
    "wof:placetype":"venue"
},
  "geometry": {"coordinates":[-76.059011,36.824025],"type":"Point"}
}