{
  "type": "Feature",
  "properties": {
    "iso:country":"US",
    "sg:address":"909 Gardens Blvd",
    "sg:city":"Charlottesville",
    "sg:classifiers":[
        {
            "category":"Shopping",
            "subcategory":"Bicycles & Sporting Goods",
            "type":"Retail Goods"
        }
    ],
    "sg:phone":"+1 434 964 9200",
    "sg:postcode":"22901",
    "sg:province":"VA",
    "sg:tags":[
        "equipment",
        "diver",
        "diva",
        "supply"
    ],
    "wof:name":"Dive Connections Inc",
    "wof:placetype":"venue"
},
  "geometry": {"coordinates":[-78.470737,38.084836],"type":"Point"}
}