{
  "type": "Feature",
  "properties": {
    "iso:country":"US",
    "sg:address":"113 Hopewell Rd",
    "sg:city":"Clear Brook",
    "sg:classifiers":[
        {
            "category":"Shopping",
            "subcategory":"Gifts & Souvenirs",
            "type":"Retail Goods"
        }
    ],
    "sg:phone":"+1 540 665 2094",
    "sg:postcode":"22624",
    "sg:province":"VA",
    "sg:tags":[
        "collectible"
    ],
    "wof:name":"D & S Racing Collectibles",
    "wof:placetype":"venue"
},
  "geometry": {"coordinates":[-78.132987,39.259753],"type":"Point"}
}