{
  "type": "Feature",
  "properties": {
    "addr:full":"5100 Leesburg Pike Ste 301 Alexandria VA 22302",
    "addr:housenumber":"5100",
    "addr:postcode":"22302",
    "addr:street":"Leesburg Pike Ste 301",
    "iso:country":"US",
    "sg:address":"5100 Leesburg Pike Ste 301",
    "sg:city":"Alexandria",
    "sg:classifiers":[
        {
            "category":"Real Estate",
            "subcategory":"Real Estate Services",
            "type":"Services"
        }
    ],
    "sg:phone":"+1 703 933 3090",
    "sg:postcode":"22302",
    "sg:province":"VA",
    "sg:website":"www.TheSettlementGroup.com",
    "wof:name":"The Settlement Group Inc",
    "wof:placetype":"venue"
},
  "geometry": {"coordinates":[-77.11508000000001,38.845459],"type":"Point"}
}