{
  "type": "Feature",
  "properties": {
    "iso:country":"US",
    "sg:address":"5451 Rosehaven Ct",
    "sg:city":"Warrenton",
    "sg:classifiers":[
        {
            "category":"Real Estate",
            "subcategory":"Real Estate Operator",
            "type":"Services"
        }
    ],
    "sg:phone":"+1 540 349 0700",
    "sg:postcode":"20187",
    "sg:province":"VA",
    "sg:tags":[
        "building",
        "nonresidential"
    ],
    "wof:name":"Handford Properties LLC",
    "wof:placetype":"venue"
},
  "geometry": {"coordinates":[-77.735913,38.764506],"type":"Point"}
}