{
  "type": "Feature",
  "properties": {
    "addr:full":"11835 US Hwy 15 Clarksville VA 23927",
    "addr:housenumber":"11835",
    "addr:postcode":"23927",
    "addr:street":"Us Hwy 15",
    "iso:country":"US",
    "sg:address":"11835 US Hwy 15",
    "sg:city":"Clarksville",
    "sg:classifiers":[
        {
            "category":"Restaurant",
            "type":"Food & Drink"
        }
    ],
    "sg:phone":"+1 434 374 2507",
    "sg:postcode":"23927",
    "sg:province":"VA",
    "sg:tags":[
        "eating"
    ],
    "wof:name":"Lil Hobys Cafe",
    "wof:placetype":"venue"
},
  "geometry": {"coordinates":[-78.55258499999999,36.600296],"type":"Point"}
}