{
  "type": "Feature",
  "properties": {
    "addr:full":"18471 Spring Lake Rd Abingdon VA 24210",
    "addr:housenumber":"18471",
    "addr:postcode":"24210",
    "addr:street":"Spring Lake Rd",
    "iso:country":"US",
    "sg:address":"18471 Spring Lake Rd",
    "sg:city":"Abingdon",
    "sg:classifiers":[
        {
            "category":"Wholesale",
            "subcategory":"Motor Vehicles",
            "type":"Manufacturing & Wholesale Goods"
        }
    ],
    "sg:phone":"+1 276 628 1995",
    "sg:postcode":"24210",
    "sg:province":"VA",
    "sg:tags":[
        "auction",
        "automobile"
    ],
    "wof:name":"Va Tn Auto Auction",
    "wof:placetype":"venue"
},
  "geometry": {"coordinates":[-82.03701599999999,36.729587],"type":"Point"}
}