{
  "type": "Feature",
  "properties": {
    "addr:full":"2016 S Glebe Rd Arlington VA 22204",
    "addr:housenumber":"2016",
    "addr:postcode":"22204",
    "addr:street":"S Glebe Rd",
    "iso:country":"US",
    "sg:address":"2016 S Glebe Rd",
    "sg:city":"Arlington",
    "sg:classifiers":[
        {
            "category":"Autos & Motor Vehicles",
            "subcategory":"Automobile Sales",
            "type":"Retail Goods"
        },
        {
            "category":"Local Transit",
            "type":"Transportation"
        }
    ],
    "sg:phone":"+1 703 922 4022",
    "sg:postcode":"22204",
    "sg:province":"VA",
    "sg:tags":[
        "shuttle",
        "limo"
    ],
    "wof:name":"Atlas Express",
    "wof:placetype":"venue"
},
  "geometry": {"coordinates":[-77.08630700000001,38.852222],"type":"Point"}
}