{
  "type": "Feature",
  "properties": {
    "iso:country":"US",
    "sg:address":"3600 Warbro Rd",
    "sg:city":"Midlothian",
    "sg:classifiers":[
        {
            "category":"Building & Trades",
            "subcategory":"Construction",
            "type":"Services"
        }
    ],
    "sg:phone":"+1 804 744 1135",
    "sg:postcode":"23112",
    "sg:province":"VA",
    "sg:tags":[
        "paving",
        "contractor"
    ],
    "wof:name":"APAC-Va Inc",
    "wof:placetype":"venue"
},
  "geometry": {"coordinates":[-77.62130399999999,37.435173],"type":"Point"}
}