{
  "type": "Feature",
  "properties": {
    "addr:full":"16149 Apple Blossom Ln Timberville VA 22853",
    "addr:housenumber":"16149",
    "addr:postcode":"22853",
    "addr:street":"Apple Blossom Ln",
    "iso:country":"US",
    "sg:address":"16149 Apple Blossom Ln",
    "sg:city":"Timberville",
    "sg:classifiers":[
        {
            "category":"Manufacturing",
            "subcategory":"Wood Products",
            "type":"Manufacturing & Wholesale Goods"
        }
    ],
    "sg:phone":"+1 540 896 8563",
    "sg:postcode":"22853",
    "sg:province":"VA",
    "sg:tags":[
        "mfg"
    ],
    "wof:name":"Pallets 4u LLC",
    "wof:placetype":"venue"
},
  "geometry": {"coordinates":[-78.7392,38.630862],"type":"Point"}
}