{
  "type": "Feature",
  "properties": {
    "addr:full":"181 Blairs Ct Blairs VA 24527",
    "addr:housenumber":"181",
    "addr:postcode":"24527",
    "addr:street":"Blairs Ct Blairs",
    "iso:country":"US",
    "sg:address":"181 Blairs Ct",
    "sg:city":"Blairs",
    "sg:classifiers":[
        {
            "category":"Real Estate",
            "subcategory":"Real Estate Operator",
            "type":"Services"
        }
    ],
    "sg:phone":"+1 434 836 4593",
    "sg:postcode":"24527",
    "sg:province":"VA",
    "sg:tags":[
        "mobile",
        "home",
        "site"
    ],
    "wof:name":"Rolling Hills Mobile Home Park",
    "wof:placetype":"venue"
},
  "geometry": {"coordinates":[-79.374123,36.679348],"type":"Point"}
}