{
  "type": "Feature",
  "properties": {
    "iso:country":"US",
    "sg:address":"3628 Annandale Rd",
    "sg:city":"Annandale",
    "sg:classifiers":[
        {
            "category":"Social Services",
            "subcategory":"Child Care",
            "type":"Services"
        }
    ],
    "sg:phone":"+1 703 849 0737",
    "sg:postcode":"22003",
    "sg:province":"VA",
    "sg:tags":[
        "day"
    ],
    "wof:name":"Rosy's Family Day Care",
    "wof:placetype":"venue"
},
  "geometry": {"coordinates":[-77.202123,38.845296],"type":"Point"}
}