{
  "type": "Feature",
  "properties": {
    "addr:full":"501 Winamack Ct Midlothian VA 23114",
    "addr:housenumber":"501",
    "addr:postcode":"23114",
    "addr:street":"Winamack Ct",
    "iso:country":"US",
    "sg:address":"501 Winamack Ct",
    "sg:city":"Midlothian",
    "sg:classifiers":[
        {
            "category":"Professional",
            "type":"Services"
        }
    ],
    "sg:phone":"+1 804 794 7329",
    "sg:postcode":"23114",
    "sg:province":"VA",
    "wof:name":"Ipath",
    "wof:placetype":"venue"
},
  "geometry": {"coordinates":[-77.64026,37.491406],"type":"Point"}
}