{
  "type": "Feature",
  "properties": {
    "addr:full":"1815 S Loudoun St Winchester VA 22601",
    "addr:housenumber":"1815",
    "addr:postcode":"22601",
    "addr:street":"S Loudoun St",
    "iso:country":"US",
    "sg:address":"1815 S Loudoun St",
    "sg:city":"Winchester",
    "sg:classifiers":[
        {
            "category":"Shopping",
            "subcategory":"Used Merchandise",
            "type":"Retail Goods"
        }
    ],
    "sg:phone":"+1 540 662 4643",
    "sg:postcode":"22601",
    "sg:province":"VA",
    "wof:name":"Winchester Antq & Collectibles",
    "wof:placetype":"venue"
},
  "geometry": {"coordinates":[-78.171724,39.166822],"type":"Point"}
}