{
  "type": "Feature",
  "properties": {
    "addr:full":"7662 Greenwood Way Nokesville VA 20181",
    "addr:housenumber":"7662",
    "addr:postcode":"20181",
    "addr:street":"Greenwood Way",
    "iso:country":"US",
    "sg:address":"7662 Greenwood Way",
    "sg:city":"Nokesville",
    "sg:classifiers":[
        {
            "category":"Manufacturing",
            "subcategory":"Tools & Machinery",
            "type":"Manufacturing & Wholesale Goods"
        }
    ],
    "sg:phone":"+1 703 753 4282",
    "sg:postcode":"20181",
    "sg:province":"VA",
    "sg:tags":[
        "photographic",
        "mfg"
    ],
    "wof:name":"Park Products East Inc",
    "wof:placetype":"venue"
},
  "geometry": {"coordinates":[-77.67003200000001,38.720572],"type":"Point"}
}