{
  "type": "Feature",
  "properties": {
    "addr:full":"9516 Jefferson Ave Newport News VA 23605",
    "addr:housenumber":"9516",
    "addr:postcode":"23605",
    "addr:street":"Jefferson Ave",
    "iso:country":"US",
    "sg:address":"9516 Jefferson Ave",
    "sg:city":"Newport News",
    "sg:classifiers":[
        {
            "category":"Recreation",
            "type":"Entertainment"
        }
    ],
    "sg:phone":"+1 757 591 0626",
    "sg:postcode":"23605",
    "sg:province":"VA",
    "wof:name":"Wilcox Indoor Archery Range",
    "wof:placetype":"venue"
},
  "geometry": {"coordinates":[-76.45000899999999,37.028332],"type":"Point"}
}