{
  "type": "Feature",
  "properties": {
    "addr:full":"111 Whitney Pl NE Leesburg VA 20176",
    "addr:housenumber":"111",
    "addr:postcode":"20176",
    "addr:street":"Whitney Pl Ne",
    "iso:country":"US",
    "sg:address":"111 Whitney Pl NE",
    "sg:city":"Leesburg",
    "sg:classifiers":[
        {
            "category":"Professional",
            "subcategory":"Management & Consulting",
            "type":"Services"
        }
    ],
    "sg:phone":"+1 703 779 0682",
    "sg:postcode":"20176",
    "sg:province":"VA",
    "wof:name":"Legin Inc",
    "wof:placetype":"venue"
},
  "geometry": {"coordinates":[-77.558099,39.121904],"type":"Point"}
}