{
  "type": "Feature",
  "properties": {
    "iso:country":"US",
    "sg:address":"13 Charleston Ct",
    "sg:city":"Stafford",
    "sg:classifiers":[
        {
            "category":"Professional",
            "type":"Services"
        }
    ],
    "sg:phone":"+1 540 720 9405",
    "sg:postcode":"22554",
    "sg:province":"VA",
    "wof:name":"W G Brunkow Consulting",
    "wof:placetype":"venue"
},
  "geometry": {"coordinates":[-77.441052,38.462195],"type":"Point"}
}