{
  "type": "Feature",
  "properties": {
    "addr:full":"7311 Sudley Rd Manassas VA 20109",
    "addr:housenumber":"7311",
    "addr:postcode":"20109",
    "addr:street":"Sudley Rd",
    "iso:country":"US",
    "sg:address":"7311 Sudley Rd",
    "sg:city":"Manassas",
    "sg:classifiers":[
        {
            "category":"Restaurant",
            "type":"Food & Drink"
        }
    ],
    "sg:menulink":"http://www.allmenus.com/va/gainesville/222070-chipotle/menu/",
    "sg:phone":"+1 703 365 0213",
    "sg:postcode":"20109",
    "sg:province":"VA",
    "sg:tags":[
        "mexican"
    ],
    "wof:name":"Chipotle",
    "wof:placetype":"venue"
},
  "geometry": {"coordinates":[-77.51742400000001,38.796474],"type":"Point"}
}