{
  "type": "Feature",
  "properties": {
    "iso:country":"US",
    "sg:address":"5815 Jacksons Oak Ct",
    "sg:city":"Burke",
    "sg:classifiers":[
        {
            "category":"Organizations",
            "subcategory":"Membership Organization",
            "type":"Services"
        }
    ],
    "sg:phone":"+1 703 503 8270",
    "sg:postcode":"22015",
    "sg:province":"VA",
    "wof:name":"Federally Employed Women",
    "wof:placetype":"venue"
},
  "geometry": {"coordinates":[-77.31980799999999,38.795164],"type":"Point"}
}