{
  "type": "Feature",
  "properties": {
    "addr:full":"1105 Alverser Dr Midlothian VA 23113",
    "addr:housenumber":"1105",
    "addr:postcode":"23113",
    "addr:street":"Alverser Dr",
    "iso:country":"US",
    "sg:address":"1105 Alverser Dr",
    "sg:city":"Midlothian",
    "sg:classifiers":[
        {
            "category":"Shopping",
            "subcategory":"Bicycles & Sporting Goods",
            "type":"Retail Goods"
        }
    ],
    "sg:phone":"+1 804 379 8333",
    "sg:postcode":"23113",
    "sg:province":"VA",
    "sg:tags":[
        "equipment",
        "golf",
        "supply"
    ],
    "wof:name":"Richmond Golf Center",
    "wof:placetype":"venue"
},
  "geometry": {"coordinates":[-77.61785,37.506365],"type":"Point"}
}