{
  "type": "Feature",
  "properties": {
    "iso:country":"US",
    "sg:address":"3910 Terrace Dr",
    "sg:city":"Annandale",
    "sg:classifiers":[
        {
            "category":"Recreation",
            "type":"Entertainment"
        },
        {
            "category":"Professional",
            "subcategory":"Art Services",
            "type":"Services"
        }
    ],
    "sg:phone":"+1 703 941 1171",
    "sg:postcode":"22003",
    "sg:province":"VA",
    "sg:tags":[
        "graphic",
        "de",
        "commercial",
        "designer"
    ],
    "wof:name":"Shinder & Associates",
    "wof:placetype":"venue"
},
  "geometry": {"coordinates":[-77.188519,38.836426],"type":"Point"}
}