{
  "type": "Feature",
  "properties": {
    "addr:full":"44029 Tavern Dr Ashburn VA 20147",
    "addr:housenumber":"44029",
    "addr:postcode":"20147",
    "addr:street":"Tavern Dr",
    "iso:country":"US",
    "sg:address":"44029 Tavern Dr",
    "sg:city":"Ashburn",
    "sg:classifiers":[
        {
            "category":"Building & Trades",
            "subcategory":"Construction",
            "type":"Services"
        }
    ],
    "sg:phone":"+1 202 421 0132",
    "sg:postcode":"20147",
    "sg:province":"VA",
    "sg:tags":[
        "management"
    ],
    "wof:name":"Alliance Services",
    "wof:placetype":"venue"
},
  "geometry": {"coordinates":[-77.47607499999999,39.039564],"type":"Point"}
}