{
  "type": "Feature",
  "properties": {
    "iso:country":"US",
    "sg:address":"101 E 29th St",
    "sg:city":"Buena Vista",
    "sg:classifiers":[
        {
            "category":"Social Services",
            "subcategory":"Job Training",
            "type":"Services"
        }
    ],
    "sg:phone":"+1 540 261 2870",
    "sg:postcode":"24416",
    "sg:province":"VA",
    "sg:tags":[
        "rehabilitation"
    ],
    "wof:name":"Rockbridge Area Community Svc",
    "wof:placetype":"venue"
},
  "geometry": {"coordinates":[-79.34842999999999,37.743902],"type":"Point"}
}