{
  "type": "Feature",
  "properties": {
    "addr:full":"52 Brent Point Rd Stafford VA 22554",
    "addr:housenumber":"52",
    "addr:postcode":"22554",
    "addr:street":"Brent Point Rd",
    "iso:country":"US",
    "sg:address":"52 Brent Point Rd",
    "sg:city":"Stafford",
    "sg:classifiers":[
        {
            "category":"Retail",
            "subcategory":"Repair Shop",
            "type":"Services"
        }
    ],
    "sg:phone":"+1 540 659 6396",
    "sg:postcode":"22554",
    "sg:province":"VA",
    "sg:tags":[
        "lock",
        "locksmith"
    ],
    "wof:name":"Century Locksmith",
    "wof:placetype":"venue"
},
  "geometry": {"coordinates":[-77.34786800000001,38.455999],"type":"Point"}
}