{
  "type": "Feature",
  "properties": {
    "addr:full":"2416 Rosedown Dr Reston VA 20191",
    "addr:housenumber":"2416",
    "addr:postcode":"20191",
    "addr:street":"Rosedown Dr",
    "iso:country":"US",
    "sg:address":"2416 Rosedown Dr",
    "sg:city":"Reston",
    "sg:classifiers":[
        {
            "category":"Professional",
            "type":"Services"
        }
    ],
    "sg:phone":"+1 703 476 6618",
    "sg:postcode":"20191",
    "sg:province":"VA",
    "wof:name":"Financial Services Limited",
    "wof:placetype":"venue"
},
  "geometry": {"coordinates":[-77.38055900000001,38.939872],"type":"Point"}
}