{
  "type": "Feature",
  "properties": {
    "addr:full":"23206 Airport St Petersburg VA 23803",
    "addr:housenumber":"23206",
    "addr:postcode":"23803",
    "addr:street":"Airport St",
    "iso:country":"US",
    "sg:address":"23206 Airport St",
    "sg:city":"Petersburg",
    "sg:classifiers":[
        {
            "category":"Professional",
            "subcategory":"Lawyer & Legal Services",
            "type":"Services"
        }
    ],
    "sg:phone":"+1 804 732 1900",
    "sg:postcode":"23803",
    "sg:province":"VA",
    "wof:name":"Rebecca J Bryant",
    "wof:placetype":"venue"
},
  "geometry": {"coordinates":[-77.504006,37.193273],"type":"Point"}
}