{
  "type": "Feature",
  "properties": {
    "addr:full":"14 Campbell Ave SW Roanoke VA 24011",
    "addr:housenumber":"14",
    "addr:postcode":"24011",
    "addr:street":"Campbell Ave Sw",
    "iso:country":"US",
    "sg:address":"14 Campbell Ave SW",
    "sg:city":"Roanoke",
    "sg:classifiers":[
        {
            "category":"Recreation",
            "type":"Entertainment"
        }
    ],
    "sg:phone":"+1 540 343 4500",
    "sg:postcode":"24011",
    "sg:province":"VA",
    "sg:tags":[
        "club",
        "hockey"
    ],
    "sg:website":"www.roanokeexpress.com",
    "wof:name":"Roanoke Express Hockey Club",
    "wof:placetype":"venue"
},
  "geometry": {"coordinates":[-79.94217999999999,37.27178],"type":"Point"}
}