{
  "type": "Feature",
  "properties": {
    "addr:full":"574 Elon Rd Madison Heights VA 24572",
    "addr:housenumber":"574",
    "addr:postcode":"24572",
    "addr:street":"Elon Rd",
    "iso:country":"US",
    "sg:address":"574 Elon Rd",
    "sg:city":"Madison Heights",
    "sg:classifiers":[
        {
            "category":"Professional",
            "subcategory":"Accounting & Tax Preparation",
            "type":"Services"
        }
    ],
    "sg:phone":"+1 434 929 1251",
    "sg:postcode":"24572",
    "sg:province":"VA",
    "wof:name":"Linda B Eubank",
    "wof:placetype":"venue"
},
  "geometry": {"coordinates":[-79.13292800000001,37.466053],"type":"Point"}
}