{
  "type": "Feature",
  "properties": {
    "iso:country":"US",
    "sg:address":"12009 Bradley Forest Rd",
    "sg:city":"Manassas",
    "sg:classifiers":[
        {
            "category":"Cinema",
            "subcategory":"Movie Rental",
            "type":"Entertainment"
        }
    ],
    "sg:phone":"+1 703 330 1186",
    "sg:postcode":"20112",
    "sg:province":"VA",
    "sg:tags":[
        "video",
        "tape"
    ],
    "wof:name":"Video Man Inc",
    "wof:placetype":"venue"
},
  "geometry": {"coordinates":[-77.47685300000001,38.694044],"type":"Point"}
}