{
  "type": "Feature",
  "properties": {
    "addr:full":"401 W Brookland Park Blvd Richmond VA 23222",
    "addr:housenumber":"401",
    "addr:postcode":"23222",
    "addr:street":"W Brookland Park Blvd",
    "iso:country":"US",
    "sg:address":"401 W Brookland Park Blvd",
    "sg:city":"Richmond",
    "sg:classifiers":[
        {
            "category":"Shopping",
            "subcategory":"Florist",
            "type":"Retail Goods"
        }
    ],
    "sg:phone":"+1 804 321 6418",
    "sg:postcode":"23222",
    "sg:province":"VA",
    "sg:website":"www.bouquetsbysylvia.com",
    "wof:name":"Bouquets By Sylvia",
    "wof:placetype":"venue"
},
  "geometry": {"coordinates":[-77.438599,37.571768],"type":"Point"}
}