{
  "type": "Feature",
  "properties": {
    "addr:full":"14535 Minnieville Rd Woodbridge VA 22193",
    "addr:housenumber":"14535",
    "addr:postcode":"22193",
    "addr:street":"Minnieville Rd",
    "iso:country":"US",
    "sg:address":"14535 Minnieville Rd",
    "sg:city":"Woodbridge",
    "sg:classifiers":[
        {
            "category":"Food & Beverages",
            "subcategory":"Bakery",
            "type":"Retail Goods"
        }
    ],
    "sg:phone":"+1 703 670 2344",
    "sg:postcode":"22193",
    "sg:province":"VA",
    "sg:tags":[
        "baker"
    ],
    "wof:name":"Ruby's & Chopy's Cakes",
    "wof:placetype":"venue"
},
  "geometry": {"coordinates":[-77.361527,38.633943],"type":"Point"}
}