{
  "type": "Feature",
  "properties": {
    "addr:full":"1300 N Wilson Blvd Arlington VA 22209",
    "addr:housenumber":"1300",
    "addr:postcode":"22209",
    "addr:street":"N Wilson Blvd",
    "iso:country":"US",
    "sg:address":"1300 N Wilson Blvd",
    "sg:city":"Arlington",
    "sg:classifiers":[
        {
            "category":"Wholesale",
            "subcategory":"Chemicals & Plastics",
            "type":"Manufacturing & Wholesale Goods"
        }
    ],
    "sg:phone":"+1 703 524 7700",
    "sg:postcode":"22209",
    "sg:province":"VA",
    "wof:name":"Eastman Chemical Company",
    "wof:placetype":"venue"
},
  "geometry": {"coordinates":[-77.073132,38.894819],"type":"Point"}
}