{
  "type": "Feature",
  "properties": {
    "iso:country":"US",
    "sg:address":"6828 Commerce St",
    "sg:city":"Springfield",
    "sg:classifiers":[
        {
            "category":"Banks & Credit Unions",
            "subcategory":"Investment Brokerage",
            "type":"Services"
        },
        {
            "category":"Professional",
            "subcategory":"Business Services",
            "type":"Services"
        }
    ],
    "sg:phone":"+1 703 451 8890",
    "sg:postcode":"22150",
    "sg:province":"VA",
    "sg:tags":[
        "advisory",
        "financial"
    ],
    "wof:name":"Englert & Assoc",
    "wof:placetype":"venue"
},
  "geometry": {"coordinates":[-77.184558,38.782348],"type":"Point"}
}