{
  "type": "Feature",
  "properties": {
    "addr:full":"13613 Genito Rd Midlothian VA 23112",
    "addr:housenumber":"13613",
    "addr:postcode":"23112",
    "addr:street":"Genito Rd",
    "iso:country":"US",
    "sg:address":"13613 Genito Rd",
    "sg:city":"Midlothian",
    "sg:classifiers":[
        {
            "category":"Personal",
            "subcategory":"Beauty Salon",
            "type":"Services"
        }
    ],
    "sg:phone":"+1 804 744 7001",
    "sg:postcode":"23112",
    "sg:province":"VA",
    "wof:name":"Tresses Salon",
    "wof:placetype":"venue"
},
  "geometry": {"coordinates":[-77.649828,37.449788],"type":"Point"}
}