{
  "type": "Feature",
  "properties": {
    "iso:country":"US",
    "sg:address":"2616 Airline Blvd",
    "sg:city":"Portsmouth",
    "sg:classifiers":[
        {
            "category":"Wholesale",
            "subcategory":"Non-durable Goods",
            "type":"Manufacturing & Wholesale Goods"
        }
    ],
    "sg:phone":"+1 757 397 8469",
    "sg:postcode":"23701",
    "sg:province":"VA",
    "sg:tags":[
        "merchandise-wholesale"
    ],
    "wof:name":"Royal Son Imports",
    "wof:placetype":"venue"
},
  "geometry": {"coordinates":[-76.360525,36.812178],"type":"Point"}
}