{
  "type": "Feature",
  "properties": {
    "addr:full":"1204 N Royal Ave Front Royal VA 22630",
    "addr:housenumber":"1204",
    "addr:postcode":"22630",
    "addr:street":"N Royal Ave",
    "iso:country":"US",
    "sg:address":"1204 N Royal Ave",
    "sg:city":"Front Royal",
    "sg:classifiers":[
        {
            "category":"Restaurant",
            "type":"Food & Drink"
        }
    ],
    "sg:phone":"+1 540 635 6468",
    "sg:postcode":"22630",
    "sg:province":"VA",
    "sg:tags":[
        "eating"
    ],
    "wof:name":"Arbys",
    "wof:placetype":"venue"
},
  "geometry": {"coordinates":[-78.19454,38.933327],"type":"Point"}
}