{
  "type": "Feature",
  "properties": {
    "addr:full":"632 Front St Lovingston VA 22949",
    "addr:housenumber":"632",
    "addr:postcode":"22949",
    "addr:street":"Front St",
    "iso:country":"US",
    "sg:address":"632 Front St",
    "sg:city":"Lovingston",
    "sg:classifiers":[
        {
            "category":"Organizations",
            "subcategory":"Religious Organization",
            "type":"Services"
        }
    ],
    "sg:phone":"+1 434 263 4008",
    "sg:postcode":"22949",
    "sg:province":"VA",
    "sg:tags":[
        "church"
    ],
    "wof:name":"St Mary's Catholic Church",
    "wof:placetype":"venue"
},
  "geometry": {"coordinates":[-78.870525,37.761657],"type":"Point"}
}