{
  "type": "Feature",
  "properties": {
    "addr:full":"426 Booher Dr Bristol VA 37620",
    "addr:housenumber":"426",
    "addr:postcode":"37620",
    "addr:street":"Booher Dr",
    "iso:country":"US",
    "sg:address":"426 Booher Dr",
    "sg:city":"Bristol",
    "sg:classifiers":[
        {
            "category":"Manufacturing",
            "subcategory":"Leather Goods",
            "type":"Manufacturing & Wholesale Goods"
        }
    ],
    "sg:phone":"+1 423 878 5709",
    "sg:postcode":"37620",
    "sg:province":"VA",
    "sg:tags":[
        "box",
        "jewelry",
        "mfg"
    ],
    "wof:name":"Jims Woodworking",
    "wof:placetype":"venue"
},
  "geometry": {"coordinates":[-82.15159,36.539173],"type":"Point"}
}