{
  "type": "Feature",
  "properties": {
    "addr:full":"1763 Ivy Oak Sq Reston VA 20190",
    "addr:housenumber":"1763",
    "addr:postcode":"20190",
    "addr:street":"Ivy Oak Sq",
    "iso:country":"US",
    "sg:address":"1763 Ivy Oak Sq",
    "sg:city":"Reston",
    "sg:classifiers":[
        {
            "category":"Professional",
            "subcategory":"Management & Consulting",
            "type":"Services"
        }
    ],
    "sg:phone":"+1 703 464 1230",
    "sg:postcode":"20190",
    "sg:province":"VA",
    "sg:tags":[
        "marketing",
        "consultant"
    ],
    "wof:name":"Unified Marketing",
    "wof:placetype":"venue"
},
  "geometry": {"coordinates":[-77.348376,38.95776],"type":"Point"}
}