{
  "type": "Feature",
  "properties": {
    "addr:full":"505 Seaford Rd Seaford VA 23696",
    "addr:housenumber":"505",
    "addr:postcode":"23696",
    "addr:street":"Seaford Rd",
    "iso:country":"US",
    "sg:address":"505 Seaford Rd",
    "sg:city":"Seaford",
    "sg:classifiers":[
        {
            "category":"Building & Trades",
            "subcategory":"Construction",
            "type":"Services"
        }
    ],
    "sg:phone":"+1 757 890 9274",
    "sg:postcode":"23696",
    "sg:province":"VA",
    "sg:tags":[
        "dry wall",
        "contractor"
    ],
    "wof:name":"Webster Drywall Plastering",
    "wof:placetype":"venue"
},
  "geometry": {"coordinates":[-76.454824,37.184089],"type":"Point"}
}