{
  "type": "Feature",
  "properties": {
    "addr:full":"325 Brunswick Dr Brodnax VA 23920",
    "addr:housenumber":"325",
    "addr:postcode":"brodnax;23920",
    "addr:street":"Brunswick Dr",
    "iso:country":"US",
    "sg:address":"325 Brunswick Dr",
    "sg:city":"Brodnax",
    "sg:classifiers":[
        {
            "category":"Communications",
            "type":"Services"
        }
    ],
    "sg:phone":"+1 434 949 0059",
    "sg:postcode":"23920",
    "sg:province":"VA",
    "wof:name":"Grigg Communications",
    "wof:placetype":"venue"
},
  "geometry": {"coordinates":[-77.959413,36.812198],"type":"Point"}
}