{
  "type": "Feature",
  "properties": {
    "addr:full":"22212 Sugarbush Ln Abingdon VA 24211",
    "addr:housenumber":"22212",
    "addr:postcode":"24211",
    "addr:street":"Sugarbush Ln",
    "iso:country":"US",
    "sg:address":"22212 Sugarbush Ln",
    "sg:city":"Abingdon",
    "sg:classifiers":[
        {
            "category":"Recreation",
            "type":"Entertainment"
        }
    ],
    "sg:phone":"+1 276 628 6353",
    "sg:postcode":"24211",
    "sg:province":"VA",
    "sg:tags":[
        "balloon"
    ],
    "wof:name":"Balloon Virginia Inc",
    "wof:placetype":"venue"
},
  "geometry": {"coordinates":[-81.970268,36.636377],"type":"Point"}
}