{
  "type": "Feature",
  "properties": {
    "iso:country":"US",
    "sg:address":"7119 Beulah St",
    "sg:city":"Alexandria",
    "sg:classifiers":[
        {
            "category":"Organizations",
            "subcategory":"Religious Organization",
            "type":"Services"
        }
    ],
    "sg:phone":"+1 703 971 9835",
    "sg:postcode":"22315",
    "sg:province":"VA",
    "sg:tags":[
        "church"
    ],
    "wof:name":"Beulah Park",
    "wof:placetype":"venue"
},
  "geometry": {"coordinates":[-77.157844,38.761887],"type":"Point"}
}