{
  "type": "Feature",
  "properties": {
    "iso:country":"US",
    "sg:address":"1621 E Market St",
    "sg:city":"Harrisonburg",
    "sg:classifiers":[
        {
            "category":"Shopping",
            "subcategory":"Books",
            "type":"Retail Goods"
        }
    ],
    "sg:phone":"+1 540 433 2421",
    "sg:postcode":"22801",
    "sg:province":"VA",
    "wof:name":"Family Christian Stores 420",
    "wof:placetype":"venue"
},
  "geometry": {"coordinates":[-78.846777,38.434354],"type":"Point"}
}