{
  "type": "Feature",
  "properties": {
    "addr:full":"3360 S Military Hwy Chesapeake VA 23323",
    "addr:housenumber":"3360",
    "addr:postcode":"23323",
    "addr:street":"S Military Hwy",
    "iso:country":"US",
    "sg:address":"3360 S Military Hwy",
    "sg:city":"Chesapeake",
    "sg:classifiers":[
        {
            "category":"Restaurant",
            "type":"Food & Drink"
        }
    ],
    "sg:menulink":"http://www.allmenus.com/va/chesapeake/83391-papa-johns-pizza/menu/",
    "sg:phone":"+1 757 485 7200",
    "sg:postcode":"23323",
    "sg:province":"VA",
    "sg:tags":[
        "american",
        "pizza"
    ],
    "wof:name":"Papa John's Pizza",
    "wof:placetype":"venue"
},
  "geometry": {"coordinates":[-76.340917,36.771919],"type":"Point"}
}