{
  "type": "Feature",
  "properties": {
    "iso:country":"US",
    "sg:address":"3402 Kimball Rd",
    "sg:city":"Luray",
    "sg:classifiers":[
        {
            "category":"Travel",
            "subcategory":"Resort",
            "type":"Entertainment"
        },
        {
            "category":"Recreation",
            "subcategory":"Campground",
            "type":"Entertainment"
        }
    ],
    "sg:phone":"+1 540 743 7222",
    "sg:postcode":"22835",
    "sg:province":"VA",
    "sg:tags":[
        "recreational",
        "park",
        "vehicle"
    ],
    "wof:name":"Country Waye Rv Resort",
    "wof:placetype":"venue"
},
  "geometry": {"coordinates":[-78.440365,38.701455],"type":"Point"}
}