{
  "type": "Feature",
  "properties": {
    "iso:country":"US",
    "sg:address":"4604 Mill Park Dr",
    "sg:city":"Glen Allen",
    "sg:classifiers":[
        {
            "category":"Health Services",
            "subcategory":"Clinic",
            "type":"Services"
        }
    ],
    "sg:phone":"+1 804 364 6109",
    "sg:postcode":"23060",
    "sg:province":"VA",
    "sg:tags":[
        "practitioner",
        "mental"
    ],
    "wof:name":"Linda C Kane",
    "wof:placetype":"venue"
},
  "geometry": {"coordinates":[-77.542085,37.651152],"type":"Point"}
}