{
  "type": "Feature",
  "properties": {
    "addr:full":"4817 Virginia Beach Blvd Virginia Beach VA 23462",
    "addr:housenumber":"4817",
    "addr:postcode":"23462",
    "addr:street":"Virginia Beach Blvd",
    "iso:country":"US",
    "sg:address":"4817 Virginia Beach Blvd",
    "sg:city":"Virginia Beach",
    "sg:classifiers":[
        {
            "category":"Shopping",
            "subcategory":"Crafts & Fabrics",
            "type":"Retail Goods"
        }
    ],
    "sg:phone":"+1 757 497 3771",
    "sg:postcode":"23462",
    "sg:province":"VA",
    "sg:tags":[
        "shop",
        "store"
    ],
    "wof:name":"Hancock Fabrics Inc",
    "wof:placetype":"venue"
},
  "geometry": {"coordinates":[-76.14256399999999,36.843474],"type":"Point"}
}