{
  "type": "Feature",
  "properties": {
    "iso:country":"US",
    "sg:address":"7177 Gray Ct",
    "sg:city":"Warrenton",
    "sg:classifiers":[
        {
            "category":"Restaurant",
            "type":"Food & Drink"
        }
    ],
    "sg:phone":"+1 540 349 9117",
    "sg:postcode":"20187",
    "sg:province":"VA",
    "sg:tags":[
        "eating"
    ],
    "wof:name":"Colleen S Kitchen",
    "wof:placetype":"venue"
},
  "geometry": {"coordinates":[-77.73172,38.740451],"type":"Point"}
}