{
  "type": "Feature",
  "properties": {
    "addr:full":"521 N Main St Woodstock VA 22664",
    "addr:housenumber":"521",
    "addr:postcode":"22664",
    "addr:street":"N Main St",
    "iso:country":"US",
    "sg:address":"521 N Main St",
    "sg:city":"Woodstock",
    "sg:classifiers":[
        {
            "category":"Shopping",
            "subcategory":"Gifts & Souvenirs",
            "type":"Retail Goods"
        }
    ],
    "sg:phone":"+1 540 459 4908",
    "sg:postcode":"22664",
    "sg:province":"VA",
    "wof:name":"Baskets Of Distinction",
    "wof:placetype":"venue"
},
  "geometry": {"coordinates":[-78.501673,38.886507],"type":"Point"}
}