{
  "type": "Feature",
  "properties": {
    "addr:full":"21 S Kent St Winchester VA 22601",
    "addr:housenumber":"21",
    "addr:postcode":"22601",
    "addr:street":"S Kent St",
    "iso:country":"US",
    "sg:address":"21 S Kent St",
    "sg:city":"Winchester",
    "sg:classifiers":[
        {
            "category":"Professional",
            "subcategory":"Computer Services",
            "type":"Services"
        }
    ],
    "sg:phone":"+1 540 722 6060",
    "sg:postcode":"22601",
    "sg:province":"VA",
    "sg:tags":[
        "home",
        "consulting",
        "page",
        "dev",
        "internet"
    ],
    "sg:website":"www.highered.org",
    "wof:name":"Highered.Org Inc",
    "wof:placetype":"venue"
},
  "geometry": {"coordinates":[-78.162853,39.183193],"type":"Point"}
}