{
  "type": "Feature",
  "properties": {
    "addr:full":"2901 N Key Blvd Arlington VA 22201",
    "addr:housenumber":"2901",
    "addr:postcode":"22201",
    "addr:street":"N Key Blvd",
    "iso:country":"US",
    "sg:address":"2901 N Key Blvd",
    "sg:city":"Arlington",
    "sg:classifiers":[
        {
            "category":"Banks & Credit Unions",
            "subcategory":"Financial Services",
            "type":"Services"
        }
    ],
    "sg:phone":"+1 703 527 2933",
    "sg:postcode":"22201",
    "sg:province":"VA",
    "sg:tags":[
        "investor"
    ],
    "wof:name":"Key Realty & Investments LLC",
    "wof:placetype":"venue"
},
  "geometry": {"coordinates":[-77.09524999999999,38.891013],"type":"Point"}
}