{
  "type": "Feature",
  "properties": {
    "addr:full":"3531 Airline Blvd Portsmouth VA 23701",
    "addr:housenumber":"3531",
    "addr:postcode":"23701",
    "addr:street":"Airline Blvd",
    "iso:country":"US",
    "sg:address":"3531 Airline Blvd",
    "sg:city":"Portsmouth",
    "sg:classifiers":[
        {
            "category":"Shopping",
            "subcategory":"Pharmacy",
            "type":"Retail Goods"
        }
    ],
    "sg:phone":"+1 757 488 2880",
    "sg:postcode":"23701",
    "sg:province":"VA",
    "sg:website":"www.eckerd.com",
    "wof:name":"Eckerd",
    "wof:placetype":"venue"
},
  "geometry": {"coordinates":[-76.384269,36.80441],"type":"Point"}
}