{
  "type": "Feature",
  "properties": {
    "iso:country":"US",
    "sg:address":"4201 Lafayette Center Dr",
    "sg:city":"Chantilly",
    "sg:classifiers":[
        {
            "category":"Professional",
            "subcategory":"Research",
            "type":"Services"
        }
    ],
    "sg:phone":"+1 703 222 9001",
    "sg:postcode":"20151",
    "sg:province":"VA",
    "sg:tags":[
        "foundation",
        "philanthropic"
    ],
    "wof:name":"New Horizon Foundation",
    "wof:placetype":"venue"
},
  "geometry": {"coordinates":[-77.47575500000001,38.905664],"type":"Point"}
}