{
  "type": "Feature",
  "properties": {
    "addr:full":"6612 Van Buren Ave Richmond VA 23226",
    "addr:housenumber":"6612",
    "addr:postcode":"23226",
    "addr:street":"Van Buren Ave",
    "iso:country":"US",
    "sg:address":"6612 Van Buren Ave",
    "sg:city":"Richmond",
    "sg:classifiers":[
        {
            "category":"Building & Trades",
            "subcategory":"Cleaning & Sanitation",
            "type":"Services"
        }
    ],
    "sg:phone":"+1 804 285 1759",
    "sg:postcode":"23226",
    "sg:province":"VA",
    "sg:tags":[
        "window"
    ],
    "wof:name":"We Do Windows",
    "wof:placetype":"venue"
},
  "geometry": {"coordinates":[-77.526601,37.588972],"type":"Point"}
}