{
  "type": "Feature",
  "properties": {
    "addr:full":"2063 Huguenot Rd Richmond VA 23235",
    "addr:housenumber":"2063",
    "addr:postcode":"23235",
    "addr:street":"Huguenot Rd",
    "iso:country":"US",
    "sg:address":"2063 Huguenot Rd",
    "sg:city":"Richmond",
    "sg:classifiers":[
        {
            "category":"Fast Food",
            "type":"Food & Drink"
        },
        {
            "category":"Restaurant",
            "type":"Food & Drink"
        }
    ],
    "sg:phone":"+1 804 272 4500",
    "sg:postcode":"23235",
    "sg:province":"VA",
    "sg:tags":[
        "style",
        "hamburger",
        "family",
        "house",
        "dog",
        "hot",
        "barbecue",
        "steak"
    ],
    "sg:website":"http://www.outbacksteakhouse.com",
    "wof:name":"Outback Steakhouse",
    "wof:placetype":"venue"
},
  "geometry": {"coordinates":[-77.614013,37.521211],"type":"Point"}
}