{
  "type": "Feature",
  "properties": {
    "iso:country":"US",
    "sg:address":"4801 Valley View Blvd NW",
    "sg:city":"Roanoke",
    "sg:classifiers":[
        {
            "category":"Coffee & Tea",
            "type":"Food & Drink"
        }
    ],
    "sg:menulink":"http://www.allmenus.com/va/roanoke/112095-starbucks-coffee/menu/",
    "sg:phone":"+1 540 366 1957",
    "sg:postcode":"24012",
    "sg:province":"VA",
    "sg:tags":[
        "american"
    ],
    "wof:name":"Starbucks Coffee",
    "wof:placetype":"venue"
},
  "geometry": {"coordinates":[-79.958657,37.302941],"type":"Point"}
}