{
  "type": "Feature",
  "properties": {
    "addr:full":"3152 Ramesses Ct Herndon VA 20171",
    "addr:housenumber":"3152",
    "addr:postcode":"20171",
    "addr:street":"Ramesses Ct",
    "iso:country":"US",
    "sg:address":"3152 Ramesses Ct",
    "sg:city":"Herndon",
    "sg:classifiers":[
        {
            "category":"Professional",
            "subcategory":"Management & Consulting",
            "type":"Services"
        }
    ],
    "sg:phone":"+1 703 904 0991",
    "sg:postcode":"20171",
    "sg:province":"VA",
    "wof:name":"Z Dimensional Marketing Inc",
    "wof:placetype":"venue"
},
  "geometry": {"coordinates":[-77.416206,38.91882],"type":"Point"}
}