{
  "type": "Feature",
  "properties": {
    "addr:full":"18490 Blue Ridge Mountain Rd Bluemont VA 20135",
    "addr:housenumber":"18490",
    "addr:postcode":"20135",
    "addr:street":"Blue Ridge Mountain Rd",
    "iso:country":"US",
    "sg:address":"18490 Blue Ridge Mountain Rd",
    "sg:city":"Bluemont",
    "sg:classifiers":[
        {
            "category":"Professional",
            "subcategory":"Management & Consulting",
            "type":"Services"
        }
    ],
    "sg:phone":"+1 540 554 2619",
    "sg:postcode":"20135",
    "sg:province":"VA",
    "sg:tags":[
        "business"
    ],
    "wof:name":"Robert McElwaine Co",
    "wof:placetype":"venue"
},
  "geometry": {"coordinates":[-77.8811,39.077784],"type":"Point"}
}