{
  "type": "Feature",
  "properties": {
    "addr:full":"4440 Springfield Rd Glen Allen VA 23060",
    "addr:housenumber":"4440",
    "addr:postcode":"23060",
    "addr:street":"Springfield Rd",
    "iso:country":"US",
    "sg:address":"4440 Springfield Rd",
    "sg:city":"Glen Allen",
    "sg:classifiers":[
        {
            "category":"Health Services",
            "subcategory":"Doctor",
            "type":"Services"
        }
    ],
    "sg:phone":"+1 804 217 9820",
    "sg:postcode":"23060",
    "sg:province":"VA",
    "wof:name":"Dhakar DDS Surya",
    "wof:placetype":"venue"
},
  "geometry": {"coordinates":[-77.560787,37.649396],"type":"Point"}
}