{
  "type": "Feature",
  "properties": {
    "iso:country":"US",
    "sg:address":"1201 Mall Dr",
    "sg:city":"Richmond",
    "sg:classifiers":[
        {
            "category":"Home & Garden",
            "subcategory":"Furniture",
            "type":"Retail Goods"
        }
    ],
    "sg:phone":"+1 804 379 0987",
    "sg:postcode":"23235",
    "sg:province":"VA",
    "sg:tags":[
        "baby",
        "accessory"
    ],
    "wof:name":"USA Baby",
    "wof:placetype":"venue"
},
  "geometry": {"coordinates":[-77.606538,37.50828],"type":"Point"}
}