{
  "type": "Feature",
  "properties": {
    "iso:country":"US",
    "sg:address":"1324 Profit Ct",
    "sg:city":"Woodbridge",
    "sg:classifiers":[
        {
            "category":"Retail",
            "subcategory":"Repair Shop",
            "type":"Services"
        }
    ],
    "sg:phone":"+1 703 490 9998",
    "sg:postcode":"22191",
    "sg:province":"VA",
    "sg:tags":[
        "refinishing",
        "furniture"
    ],
    "sg:website":"www.finaltouch.biz",
    "wof:name":"C R Final Touch Inc",
    "wof:placetype":"venue"
},
  "geometry": {"coordinates":[-77.253483,38.629565],"type":"Point"}
}