{
  "type": "Feature",
  "properties": {
    "addr:full":"9623 W Broad St Glen Allen VA 23060",
    "addr:housenumber":"9623",
    "addr:postcode":"23060",
    "addr:street":"W Broad St",
    "iso:country":"US",
    "sg:address":"9623 W Broad St",
    "sg:city":"Glen Allen",
    "sg:classifiers":[
        {
            "category":"Retail",
            "subcategory":"Laundry & Dry Cleaning",
            "type":"Services"
        }
    ],
    "sg:phone":"+1 804 273 0591",
    "sg:postcode":"23060",
    "sg:province":"VA",
    "sg:tags":[
        "cleaners"
    ],
    "wof:name":"Ireland Cleaners",
    "wof:placetype":"venue"
},
  "geometry": {"coordinates":[-77.564288,37.642031],"type":"Point"}
}