{
  "type": "Feature",
  "properties": {
    "addr:full":"10200 Westford Dr Vienna VA 22182",
    "addr:housenumber":"10200",
    "addr:postcode":"22182",
    "addr:street":"Westford Dr",
    "iso:country":"US",
    "sg:address":"10200 Westford Dr",
    "sg:city":"Vienna",
    "sg:classifiers":[
        {
            "category":"Professional",
            "subcategory":"Computer Services",
            "type":"Services"
        }
    ],
    "sg:phone":"+1 703 850 4489",
    "sg:postcode":"22182",
    "sg:province":"VA",
    "sg:tags":[
        "consultant",
        "designer"
    ],
    "sg:website":"www.cygnet.org",
    "wof:name":"Cygnet Computing Svc",
    "wof:placetype":"venue"
},
  "geometry": {"coordinates":[-77.29772800000001,38.958672],"type":"Point"}
}