{
  "type": "Feature",
  "properties": {
    "addr:full":"105 Junction Dr Ashland VA 23005",
    "addr:housenumber":"105",
    "addr:postcode":"23005",
    "addr:street":"Junction Dr",
    "iso:country":"US",
    "sg:address":"105 Junction Dr",
    "sg:city":"Ashland",
    "sg:classifiers":[
        {
            "category":"Restaurant",
            "type":"Food & Drink"
        }
    ],
    "sg:phone":"+1 804 798 9259",
    "sg:postcode":"23005",
    "sg:province":"VA",
    "sg:tags":[
        "eating"
    ],
    "wof:name":"Lafatas Italian Restaurant &G",
    "wof:placetype":"venue"
},
  "geometry": {"coordinates":[-77.467367,37.756062],"type":"Point"}
}