{
  "type": "Feature",
  "properties": {
    "iso:country":"US",
    "sg:address":"407 Crown View Dr",
    "sg:city":"Alexandria",
    "sg:classifiers":[
        {
            "category":"Organizations",
            "subcategory":"Labor Organization",
            "type":"Services"
        }
    ],
    "sg:phone":"+1 703 751 1239",
    "sg:postcode":"22314",
    "sg:province":"VA",
    "sg:tags":[
        "consultant",
        "relation"
    ],
    "wof:name":"D N A Technology Consulting Services L L C",
    "wof:placetype":"venue"
},
  "geometry": {"coordinates":[-77.077989,38.812262],"type":"Point"}
}