{
  "type": "Feature",
  "properties": {
    "iso:country":"US",
    "sg:address":"8425 Richmond Ave",
    "sg:city":"Alexandria",
    "sg:classifiers":[
        {
            "category":"Building & Trades",
            "subcategory":"Construction",
            "type":"Services"
        }
    ],
    "sg:phone":"+1 703 780 2428",
    "sg:postcode":"22309",
    "sg:province":"VA",
    "sg:tags":[
        "house"
    ],
    "wof:name":"All Star Home Improvement",
    "wof:placetype":"venue"
},
  "geometry": {"coordinates":[-77.10356400000001,38.725042],"type":"Point"}
}