{
  "type": "Feature",
  "properties": {
    "addr:full":"7700 Progress Ct Gainesville VA 20155",
    "addr:housenumber":"7700",
    "addr:postcode":"20155",
    "addr:street":"Progress Ct",
    "iso:country":"US",
    "sg:address":"7700 Progress Ct",
    "sg:city":"Gainesville",
    "sg:classifiers":[
        {
            "category":"Retail",
            "subcategory":"Auto Rental",
            "type":"Services"
        }
    ],
    "sg:phone":"+1 703 753 0136",
    "sg:postcode":"20155",
    "sg:province":"VA",
    "sg:tags":[
        "car"
    ],
    "wof:name":"Hertz Rent A Car",
    "wof:placetype":"venue"
},
  "geometry": {"coordinates":[-77.592066,38.792033],"type":"Point"}
}