{
  "type": "Feature",
  "properties": {
    "iso:country":"US",
    "sg:address":"101 S Davis Ave",
    "sg:city":"Richmond",
    "sg:classifiers":[
        {
            "category":"Local Transit",
            "type":"Transportation"
        }
    ],
    "sg:phone":"+1 804 254 4785",
    "sg:postcode":"23220",
    "sg:province":"VA",
    "sg:tags":[
        "bus",
        "line"
    ],
    "sg:website":"www.ridegrtc.com",
    "wof:name":"GRTC",
    "wof:placetype":"venue"
},
  "geometry": {"coordinates":[-77.473522,37.548747],"type":"Point"}
}