{
  "type": "Feature",
  "properties": {
    "iso:country":"US",
    "sg:address":"501 S Main St",
    "sg:city":"Lexington",
    "sg:classifiers":[
        {
            "category":"Travel",
            "subcategory":"Hotels & Motels",
            "type":"Entertainment"
        }
    ],
    "sg:phone":"+1 540 463 2567",
    "sg:postcode":"24450",
    "sg:province":"VA",
    "sg:tags":[
        "breakfast",
        "accommodation",
        "bed"
    ],
    "sg:website":"www.magnoliahouseinn.com",
    "wof:name":"Magnolia House Bed & Breakfast",
    "wof:placetype":"venue"
},
  "geometry": {"coordinates":[-79.447367,37.77979],"type":"Point"}
}