{
  "type": "Feature",
  "properties": {
    "addr:full":"5829 21st St N Arlington VA 22205",
    "addr:housenumber":"5829",
    "addr:postcode":"22205",
    "addr:street":"21St St N",
    "iso:country":"US",
    "sg:address":"5829 21st St N",
    "sg:city":"Arlington",
    "sg:classifiers":[
        {
            "category":"Building & Trades",
            "subcategory":"Construction",
            "type":"Services"
        }
    ],
    "sg:phone":"+1 703 531 1050",
    "sg:postcode":"22205",
    "sg:province":"VA",
    "sg:tags":[
        "residential"
    ],
    "wof:name":"Yeonas & Ellis LLC",
    "wof:placetype":"venue"
},
  "geometry": {"coordinates":[-77.142636,38.889923],"type":"Point"}
}