{
  "type": "Feature",
  "properties": {
    "iso:country":"US",
    "sg:address":"114 S Main St",
    "sg:city":"Bridgewater",
    "sg:classifiers":[
        {
            "category":"Health Services",
            "subcategory":"Doctor",
            "type":"Services"
        }
    ],
    "sg:phone":"+1 540 828 2529",
    "sg:postcode":"22812",
    "sg:province":"VA",
    "sg:tags":[
        "medical"
    ],
    "wof:name":"Thompson James MD PC",
    "wof:placetype":"venue"
},
  "geometry": {"coordinates":[-78.976788,38.381932],"type":"Point"}
}