{
  "type": "Feature",
  "properties": {
    "iso:country":"US",
    "sg:address":"1929 Coliseum Dr",
    "sg:city":"Hampton",
    "sg:classifiers":[
        {
            "category":"Shopping",
            "subcategory":"Computers & Home Electronics",
            "type":"Retail Goods"
        }
    ],
    "sg:phone":"+1 757 838 7050",
    "sg:postcode":"23666",
    "sg:province":"VA",
    "sg:tags":[
        "equipment",
        "dealer"
    ],
    "wof:name":"Action Custom Computers",
    "wof:placetype":"venue"
},
  "geometry": {"coordinates":[-76.38847199999999,37.041561],"type":"Point"}
}