{
  "type": "Feature",
  "properties": {
    "iso:country":"US",
    "sg:address":"406 Rainbow Dr",
    "sg:city":"Staunton",
    "sg:classifiers":[
        {
            "category":"Building & Trades",
            "subcategory":"Construction",
            "type":"Services"
        }
    ],
    "sg:phone":"+1 540 337 6550",
    "sg:postcode":"24401",
    "sg:province":"VA",
    "sg:tags":[
        "house"
    ],
    "wof:name":"Decker Construction",
    "wof:placetype":"venue"
},
  "geometry": {"coordinates":[-79.050057,38.177389],"type":"Point"}
}