{
  "type": "Feature",
  "properties": {
    "addr:full":"210 S Jefferson St Roanoke VA 24011",
    "addr:housenumber":"210",
    "addr:postcode":"24011",
    "addr:street":"S Jefferson St",
    "iso:country":"US",
    "sg:address":"210 S Jefferson St",
    "sg:city":"Roanoke",
    "sg:classifiers":[
        {
            "category":"Banks & Credit Unions",
            "subcategory":"Bank",
            "type":"Services"
        }
    ],
    "sg:phone":"+1 540 983 1550",
    "sg:postcode":"24011",
    "sg:province":"VA",
    "sg:tags":[
        "pr",
        "datum",
        "national",
        "commercial",
        "security"
    ],
    "wof:name":"National Bank of Commerce",
    "wof:placetype":"venue"
},
  "geometry": {"coordinates":[-79.940494,37.271233],"type":"Point"}
}