{
  "type": "Feature",
  "properties": {
    "addr:full":"625 Slaters Ln Ste 300 Alexandria VA 22314",
    "addr:housenumber":"625",
    "addr:postcode":"22314",
    "addr:street":"Slaters Ln Ste 300",
    "iso:country":"US",
    "sg:address":"625 Slaters Ln Ste 300",
    "sg:city":"Alexandria",
    "sg:classifiers":[
        {
            "category":"Building & Trades",
            "subcategory":"Construction",
            "type":"Services"
        },
        {
            "category":"Real Estate",
            "subcategory":"Architect",
            "type":"Services"
        }
    ],
    "sg:phone":"+1 703 836 7766",
    "sg:postcode":"22314",
    "sg:province":"VA",
    "sg:tags":[
        "interior",
        "design"
    ],
    "wof:name":"Wisnewski Blair & Associates Ltd",
    "wof:placetype":"venue"
},
  "geometry": {"coordinates":[-77.042603,38.8218],"type":"Point"}
}