{
  "type": "Feature",
  "properties": {
    "addr:full":"817 Union Forge Ln Chesapeake VA 23322",
    "addr:housenumber":"817",
    "addr:postcode":"23322",
    "addr:street":"Union Forge Ln",
    "iso:country":"US",
    "sg:address":"817 Union Forge Ln",
    "sg:city":"Chesapeake",
    "sg:classifiers":[
        {
            "category":"Professional",
            "subcategory":"Management & Consulting",
            "type":"Services"
        }
    ],
    "sg:phone":"+1 757 410 3338",
    "sg:postcode":"23322",
    "sg:province":"VA",
    "sg:tags":[
        "business"
    ],
    "wof:name":"East Coast Test & Balance Inc",
    "wof:placetype":"venue"
},
  "geometry": {"coordinates":[-76.24499400000001,36.695725],"type":"Point"}
}