{
  "type": "Feature",
  "properties": {
    "addr:full":"615 Elden St Herndon VA 20170",
    "addr:housenumber":"615",
    "addr:postcode":"20170",
    "addr:street":"Elden St",
    "iso:country":"US",
    "sg:address":"615 Elden St",
    "sg:city":"Herndon",
    "sg:classifiers":[
        {
            "category":"Retail",
            "subcategory":"Laundry & Dry Cleaning",
            "type":"Services"
        }
    ],
    "sg:phone":"+1 703 481 1305",
    "sg:postcode":"20170",
    "sg:province":"VA",
    "sg:tags":[
        "drycleaning",
        "plant"
    ],
    "wof:name":"Viking Cleaners",
    "wof:placetype":"venue"
},
  "geometry": {"coordinates":[-77.383386,38.96957],"type":"Point"}
}