{
  "type": "Feature",
  "properties": {
    "addr:full":"7 Cedar Cir Williamsburg VA 23188",
    "addr:housenumber":"7",
    "addr:postcode":"23188",
    "addr:street":"Cedar Cir",
    "iso:country":"US",
    "sg:address":"7 Cedar Cir",
    "sg:city":"Williamsburg",
    "sg:classifiers":[
        {
            "category":"Building & Trades",
            "subcategory":"Construction",
            "type":"Services"
        }
    ],
    "sg:phone":"+1 757 565 4022",
    "sg:postcode":"23188",
    "sg:province":"VA",
    "sg:tags":[
        "home",
        "improvement"
    ],
    "wof:name":"Cook's Home Repair",
    "wof:placetype":"venue"
},
  "geometry": {"coordinates":[-76.761719,37.33959],"type":"Point"}
}