{
  "type": "Feature",
  "properties": {
    "addr:full":"3897 Main St Chincoteague VA 23336",
    "addr:housenumber":"3897",
    "addr:postcode":"23336",
    "addr:street":"Main St",
    "iso:country":"US",
    "sg:address":"3897 Main St",
    "sg:city":"Chincoteague",
    "sg:classifiers":[
        {
            "category":"Health Services",
            "subcategory":"Doctor",
            "type":"Services"
        }
    ],
    "sg:phone":"+1 757 336 5116",
    "sg:postcode":"23336",
    "sg:province":"VA",
    "sg:tags":[
        "dentist"
    ],
    "wof:name":"William W Baczek DDS",
    "wof:placetype":"venue"
},
  "geometry": {"coordinates":[-75.37962,37.932295],"type":"Point"}
}