{
  "type": "Feature",
  "properties": {
    "iso:country":"US",
    "sg:address":"13826 Lee Hwy",
    "sg:city":"Centreville",
    "sg:classifiers":[
        {
            "category":"Real Estate",
            "subcategory":"Real Estate Agent",
            "type":"Services"
        }
    ],
    "sg:phone":"+1 703 897 5050",
    "sg:postcode":"20120",
    "sg:province":"VA",
    "wof:name":"Herman Mason",
    "wof:placetype":"venue"
},
  "geometry": {"coordinates":[-77.426193,38.838943],"type":"Point"}
}