{
  "type": "Feature",
  "properties": {
    "addr:full":"9704 Olde Milbrooke Way Glen Allen VA 23060",
    "addr:housenumber":"9704",
    "addr:postcode":"23060",
    "addr:street":"Olde Milbrooke Way",
    "iso:country":"US",
    "sg:address":"9704 Olde Milbrooke Way",
    "sg:city":"Glen Allen",
    "sg:classifiers":[
        {
            "category":"Shopping",
            "subcategory":"Computers & Home Electronics",
            "type":"Retail Goods"
        }
    ],
    "sg:phone":"+1 804 965 0597",
    "sg:postcode":"23060",
    "sg:province":"VA",
    "wof:name":"Planetside Computer Services",
    "wof:placetype":"venue"
},
  "geometry": {"coordinates":[-77.556741,37.667046],"type":"Point"}
}