{
  "type": "Feature",
  "properties": {
    "addr:full":"6315 Beulah St Franconia VA 22310",
    "addr:housenumber":"6315",
    "addr:postcode":"22310",
    "addr:street":"Beulah St",
    "iso:country":"US",
    "sg:address":"6315 Beulah St",
    "sg:city":"Franconia",
    "sg:classifiers":[
        {
            "category":"Organizations",
            "subcategory":"Religious Organization",
            "type":"Services"
        }
    ],
    "sg:phone":"+1 703 971 3984",
    "sg:postcode":"22310",
    "sg:province":"VA",
    "sg:tags":[
        "church"
    ],
    "wof:name":"Franconia Alliance Church",
    "wof:placetype":"venue"
},
  "geometry": {"coordinates":[-77.14591799999999,38.780395],"type":"Point"}
}