{
  "type": "Feature",
  "properties": {
    "addr:full":"4516 Leonard Pkwy Richmond VA 23221",
    "addr:housenumber":"4516",
    "addr:postcode":"23221",
    "addr:street":"Leonard Pkwy",
    "iso:country":"US",
    "sg:address":"4516 Leonard Pkwy",
    "sg:city":"Richmond",
    "sg:classifiers":[
        {
            "category":"Building & Trades",
            "subcategory":"Landscaping Services",
            "type":"Services"
        }
    ],
    "sg:phone":"+1 804 358 2154",
    "sg:postcode":"23221",
    "sg:province":"VA",
    "sg:tags":[
        "landscape"
    ],
    "wof:name":"Historic Landscape Preser",
    "wof:placetype":"venue"
},
  "geometry": {"coordinates":[-77.49679,37.568631],"type":"Point"}
}