{
  "type": "Feature",
  "properties": {
    "iso:country":"US",
    "sg:address":"10915 Hull Street Rd",
    "sg:city":"Midlothian",
    "sg:classifiers":[
        {
            "category":"Health Services",
            "subcategory":"Doctor",
            "type":"Services"
        }
    ],
    "sg:phone":"+1 804 346 0600",
    "sg:postcode":"23112",
    "sg:province":"VA",
    "sg:tags":[
        "physician",
        "surgeon"
    ],
    "wof:name":"Advanced Pain Ctr Of Richmond",
    "wof:placetype":"venue"
},
  "geometry": {"coordinates":[-77.59508099999999,37.438971],"type":"Point"}
}