{
  "type": "Feature",
  "properties": {
    "addr:full":"16270 Pinopolis Rd Capron VA 23829",
    "addr:housenumber":"16270",
    "addr:postcode":"23829",
    "addr:street":"Pinopolis Rd",
    "iso:country":"US",
    "sg:address":"16270 Pinopolis Rd",
    "sg:city":"Capron",
    "sg:classifiers":[
        {
            "category":"Farming",
            "subcategory":"Farm",
            "type":"Manufacturing & Wholesale Goods"
        }
    ],
    "sg:phone":"+1 434 658 4927",
    "sg:postcode":"23829",
    "sg:province":"VA",
    "sg:tags":[
        "crop",
        "general"
    ],
    "wof:name":"Bain Brothers",
    "wof:placetype":"venue"
},
  "geometry": {"coordinates":[-77.227389,36.677564],"type":"Point"}
}