{
  "type": "Feature",
  "properties": {
    "iso:country":"US",
    "sg:address":"3624 Rolridge Rd",
    "sg:city":"Richmond",
    "sg:classifiers":[
        {
            "category":"Banks & Credit Unions",
            "subcategory":"Investment Brokerage",
            "type":"Services"
        }
    ],
    "sg:phone":"+1 804 360 8092",
    "sg:postcode":"23233",
    "sg:province":"VA",
    "sg:tags":[
        "consultant",
        "financing"
    ],
    "wof:name":"JHL Financial Consulting Inc",
    "wof:placetype":"venue"
},
  "geometry": {"coordinates":[-77.642235,37.643605],"type":"Point"}
}