{
  "type": "Feature",
  "properties": {
    "iso:country":"US",
    "sg:address":"3320 6th St S",
    "sg:city":"Arlington",
    "sg:classifiers":[
        {
            "category":"Social Services",
            "type":"Services"
        }
    ],
    "sg:phone":"+1 703 486 4244",
    "sg:postcode":"22204",
    "sg:province":"VA",
    "wof:name":"Women In Transition 2000",
    "wof:placetype":"venue"
},
  "geometry": {"coordinates":[-77.094376,38.866487],"type":"Point"}
}