{
  "type": "Feature",
  "properties": {
    "iso:country":"US",
    "sg:address":"6250 Circle Dr",
    "sg:city":"Chincoteague",
    "sg:classifiers":[
        {
            "category":"Professional",
            "subcategory":"Computer Services",
            "type":"Services"
        }
    ],
    "sg:phone":"+1 757 894 2642",
    "sg:postcode":"23336",
    "sg:province":"VA",
    "sg:tags":[
        "datum"
    ],
    "wof:name":"Rising Tide",
    "wof:placetype":"venue"
},
  "geometry": {"coordinates":[-75.355757,37.933796],"type":"Point"}
}