{
  "type": "Feature",
  "properties": {
    "addr:full":"2938 River Rd W Goochland VA 23063",
    "addr:housenumber":"2938",
    "addr:postcode":"23063",
    "addr:street":"River Rd W Goochland",
    "iso:country":"US",
    "sg:address":"2938 River Rd W",
    "sg:city":"Goochland",
    "sg:classifiers":[
        {
            "category":"Government",
            "subcategory":"Office",
            "type":"Public Place"
        }
    ],
    "sg:phone":"+1 804 556 5359",
    "sg:postcode":"23063",
    "sg:province":"VA",
    "sg:tags":[
        "county",
        "program",
        "adm"
    ],
    "wof:name":"Goochland County Economic Dev",
    "wof:placetype":"venue"
},
  "geometry": {"coordinates":[-77.885306,37.684397],"type":"Point"}
}