{
  "type": "Feature",
  "properties": {
    "addr:full":"1326 Clarke Ave SW Roanoke VA 24016",
    "addr:housenumber":"1326",
    "addr:postcode":"24016",
    "addr:street":"Clarke Ave Sw",
    "iso:country":"US",
    "sg:address":"1326 Clarke Ave SW",
    "sg:city":"Roanoke",
    "sg:classifiers":[
        {
            "category":"Building & Trades",
            "subcategory":"Landscaping Services",
            "type":"Services"
        }
    ],
    "sg:phone":"+1 540 985 5117",
    "sg:postcode":"24016",
    "sg:province":"VA",
    "sg:tags":[
        "landscape"
    ],
    "wof:name":"Rainbow Luscious Landscaping",
    "wof:placetype":"venue"
},
  "geometry": {"coordinates":[-79.943134,37.259506],"type":"Point"}
}