{
  "type": "Feature",
  "properties": {
    "addr:full":"141 Warren St Norfolk VA 23505",
    "addr:housenumber":"141",
    "addr:postcode":"23505",
    "addr:street":"Warren St",
    "iso:country":"US",
    "sg:address":"141 Warren St",
    "sg:city":"Norfolk",
    "sg:classifiers":[
        {
            "category":"Shopping",
            "subcategory":"Gifts & Souvenirs",
            "type":"Retail Goods"
        }
    ],
    "sg:phone":"+1 757 583 5888",
    "sg:postcode":"23505",
    "sg:province":"VA",
    "wof:name":"Beautiful Gifts Inc",
    "wof:placetype":"venue"
},
  "geometry": {"coordinates":[-76.277173,36.90927],"type":"Point"}
}