{
  "type": "Feature",
  "properties": {
    "iso:country":"US",
    "sg:address":"4703 Nine Mile Rd",
    "sg:city":"Richmond",
    "sg:classifiers":[
        {
            "category":"Restaurant",
            "type":"Food & Drink"
        }
    ],
    "sg:phone":"+1 804 226 4848",
    "sg:postcode":"23223",
    "sg:province":"VA",
    "sg:tags":[
        "eating"
    ],
    "wof:name":"China Kingdom Inc",
    "wof:placetype":"venue"
},
  "geometry": {"coordinates":[-77.370059,37.544062],"type":"Point"}
}