{
  "type": "Feature",
  "properties": {
    "iso:country":"US",
    "sg:address":"1901 W Hundred Rd",
    "sg:city":"Chester",
    "sg:classifiers":[
        {
            "category":"Restaurant",
            "type":"Food & Drink"
        }
    ],
    "sg:menulink":"http://www.allmenus.com/va/bermuda/155047-hardees/menu/",
    "sg:phone":"+1 804 748 4892",
    "sg:postcode":"23836",
    "sg:province":"VA",
    "sg:tags":[
        "burger",
        "american"
    ],
    "wof:name":"Hardee's",
    "wof:placetype":"venue"
},
  "geometry": {"coordinates":[-77.397265,37.353282],"type":"Point"}
}