{
  "type": "Feature",
  "properties": {
    "addr:full":"12780 Flat Meadow Ln Herndon VA 20171",
    "addr:housenumber":"12780 flat",
    "addr:postcode":"20171",
    "addr:street":"Meadow Ln",
    "iso:country":"US",
    "sg:address":"12780 Flat Meadow Ln",
    "sg:city":"Herndon",
    "sg:classifiers":[
        {
            "category":"Wholesale",
            "subcategory":"Books, Periodicals, & Newspapers",
            "type":"Manufacturing & Wholesale Goods"
        }
    ],
    "sg:phone":"+1 703 648 0354",
    "sg:postcode":"20171",
    "sg:province":"VA",
    "wof:name":"Silver Burdett Ginn Inc",
    "wof:placetype":"venue"
},
  "geometry": {"coordinates":[-77.391488,38.911979],"type":"Point"}
}