{
  "type": "Feature",
  "properties": {
    "addr:full":"1225 E Washington Ave Vinton VA 24179",
    "addr:housenumber":"1225",
    "addr:postcode":"24179",
    "addr:street":"E Washington Ave",
    "iso:country":"US",
    "sg:address":"1225 E Washington Ave",
    "sg:city":"Vinton",
    "sg:classifiers":[
        {
            "category":"Shopping",
            "type":"Retail Goods"
        }
    ],
    "sg:phone":"+1 540 345 1443",
    "sg:postcode":"24179",
    "sg:province":"VA",
    "sg:tags":[
        "repair",
        "merchandise"
    ],
    "wof:name":"Abel Office Systems",
    "wof:placetype":"venue"
},
  "geometry": {"coordinates":[-79.877402,37.277523],"type":"Point"}
}