{
  "type": "Feature",
  "properties": {
    "iso:country":"US",
    "sg:address":"1009 W Washington St",
    "sg:city":"Suffolk",
    "sg:classifiers":[
        {
            "category":"Shopping",
            "subcategory":"Stationery & Office Supplies",
            "type":"Retail Goods"
        }
    ],
    "sg:phone":"+1 757 934 8950",
    "sg:postcode":"23434",
    "sg:province":"VA",
    "sg:tags":[
        "stationer"
    ],
    "wof:name":"Treasured Memories",
    "wof:placetype":"venue"
},
  "geometry": {"coordinates":[-76.599204,36.730731],"type":"Point"}
}