{
  "type": "Feature",
  "properties": {
    "addr:full":"1417 University Ave Charlottesville VA 22903",
    "addr:housenumber":"1417",
    "addr:postcode":"22903",
    "addr:street":"University Ave",
    "iso:country":"US",
    "sg:address":"1417 University Ave",
    "sg:city":"Charlottesville",
    "sg:classifiers":[
        {
            "category":"Shopping",
            "subcategory":"Computers & Home Electronics",
            "type":"Retail Goods"
        }
    ],
    "sg:phone":"+1 434 293 7005",
    "sg:postcode":"22903",
    "sg:province":"VA",
    "sg:tags":[
        "equipment",
        "satellite",
        "system"
    ],
    "wof:name":"Satellite Ballroom",
    "wof:placetype":"venue"
},
  "geometry": {"coordinates":[-78.49995699999999,38.034304],"type":"Point"}
}