{
  "type": "Feature",
  "properties": {
    "addr:full":"3479 James Madison Hwy Gordonsville VA 22942",
    "addr:housenumber":"3479",
    "addr:postcode":"22942",
    "addr:street":"James Madison Hwy",
    "iso:country":"US",
    "sg:address":"3479 James Madison Hwy",
    "sg:city":"Gordonsville",
    "sg:classifiers":[
        {
            "category":"Personal",
            "type":"Services"
        }
    ],
    "sg:phone":"+1 540 832 2917",
    "sg:postcode":"22942",
    "sg:province":"VA",
    "sg:tags":[
        "therapist",
        "massage"
    ],
    "wof:name":"Inside Out Wellness",
    "wof:placetype":"venue"
},
  "geometry": {"coordinates":[-78.18135700000001,38.082835],"type":"Point"}
}