{
  "type": "Feature",
  "properties": {
    "addr:full":"109 Perry St Petersburg VA 23803",
    "addr:housenumber":"109",
    "addr:postcode":"23803",
    "addr:street":"Perry St",
    "iso:country":"US",
    "sg:address":"109 Perry St",
    "sg:city":"Petersburg",
    "sg:classifiers":[
        {
            "category":"Shopping",
            "subcategory":"Crafts & Fabrics",
            "type":"Retail Goods"
        }
    ],
    "sg:phone":"+1 804 796 9656",
    "sg:postcode":"23803",
    "sg:province":"VA",
    "sg:tags":[
        "shop"
    ],
    "wof:name":"Waubridge Specialty Fabrics",
    "wof:placetype":"venue"
},
  "geometry": {"coordinates":[-77.408816,37.225078],"type":"Point"}
}