{
  "type": "Feature",
  "properties": {
    "addr:full":"4237 Bethlehem Church Rd NE Pilot VA 24138",
    "addr:housenumber":"4237",
    "addr:postcode":"24138",
    "addr:street":"Bethlehem Church Rd Ne",
    "iso:country":"US",
    "sg:address":"4237 Bethlehem Church Rd NE",
    "sg:city":"Pilot",
    "sg:classifiers":[
        {
            "category":"Building & Trades",
            "subcategory":"Construction",
            "type":"Services"
        }
    ],
    "sg:phone":"+1 540 651 3478",
    "sg:postcode":"24138",
    "sg:province":"VA",
    "sg:tags":[
        "house"
    ],
    "wof:name":"Construction Inc",
    "wof:placetype":"venue"
},
  "geometry": {"coordinates":[-80.33341299999999,37.01789],"type":"Point"}
}