{
  "type": "Feature",
  "properties": {
    "iso:country":"US",
    "sg:address":"125 Arena St",
    "sg:city":"Williamsburg",
    "sg:classifiers":[
        {
            "category":"Real Estate",
            "subcategory":"Real Estate Agent",
            "type":"Services"
        }
    ],
    "sg:phone":"+1 757 564 0345",
    "sg:postcode":"23185",
    "sg:province":"VA",
    "wof:name":"Lisa Genakos Realtor",
    "wof:placetype":"venue"
},
  "geometry": {"coordinates":[-76.78125300000001,37.246026],"type":"Point"}
}