{
  "type": "Feature",
  "properties": {
    "addr:full":"400 Holiday Ct Ste 103 Warrenton VA 20186",
    "addr:housenumber":"400",
    "addr:postcode":"20186",
    "addr:street":"Holiday Ct Ste 103",
    "iso:country":"US",
    "sg:address":"400 Holiday Ct Ste 103",
    "sg:city":"Warrenton",
    "sg:classifiers":[
        {
            "category":"Banks & Credit Unions",
            "subcategory":"Financial Services",
            "type":"Services"
        }
    ],
    "sg:phone":"+1 540 341 0035",
    "sg:postcode":"20186",
    "sg:province":"VA",
    "sg:tags":[
        "broker",
        "mortgage"
    ],
    "wof:name":"The Settlement Co",
    "wof:placetype":"venue"
},
  "geometry": {"coordinates":[-77.78407900000001,38.721168],"type":"Point"}
}