{
  "type": "Feature",
  "properties": {
    "addr:full":"2170 Huguenot Trl Powhatan VA 23139",
    "addr:housenumber":"2170",
    "addr:postcode":"23139",
    "addr:street":"Huguenot Trl",
    "iso:country":"US",
    "sg:address":"2170 Huguenot Trl",
    "sg:city":"Powhatan",
    "sg:classifiers":[
        {
            "category":"Recreation",
            "type":"Entertainment"
        }
    ],
    "sg:phone":"+1 804 897 1421",
    "sg:postcode":"23139",
    "sg:province":"VA",
    "sg:tags":[
        "stable"
    ],
    "wof:name":"Cottonglen Inc",
    "wof:placetype":"venue"
},
  "geometry": {"coordinates":[-77.79521800000001,37.594636],"type":"Point"}
}