{
  "type": "Feature",
  "properties": {
    "addr:full":"13622 Mount Zion Church Rd Culpeper VA 22701",
    "addr:housenumber":"13622",
    "addr:postcode":"22701",
    "addr:street":"Mount Zion Church Rd",
    "iso:country":"US",
    "sg:address":"13622 Mount Zion Church Rd",
    "sg:city":"Culpeper",
    "sg:classifiers":[
        {
            "category":"Building & Trades",
            "subcategory":"Construction",
            "type":"Services"
        }
    ],
    "sg:phone":"+1 540 829 4675",
    "sg:postcode":"22701",
    "sg:province":"VA",
    "sg:tags":[
        "house",
        "improvement",
        "home"
    ],
    "wof:name":"Wright Home Improvement",
    "wof:placetype":"venue"
},
  "geometry": {"coordinates":[-77.966323,38.515257],"type":"Point"}
}