{
  "type": "Feature",
  "properties": {
    "addr:full":"1100 Milnwood Rd Farmville VA 23901",
    "addr:housenumber":"1100",
    "addr:postcode":"23901",
    "addr:street":"Milnwood Rd",
    "iso:country":"US",
    "sg:address":"1100 Milnwood Rd",
    "sg:city":"Farmville",
    "sg:classifiers":[
        {
            "category":"Real Estate",
            "subcategory":"Real Estate Operator",
            "type":"Services"
        }
    ],
    "sg:phone":"+1 434 392 9510",
    "sg:postcode":"23901",
    "sg:province":"VA",
    "sg:tags":[
        "building",
        "apartment"
    ],
    "wof:name":"Milnwood Village Apartments",
    "wof:placetype":"venue"
},
  "geometry": {"coordinates":[-78.38426800000001,37.283813],"type":"Point"}
}