{
  "type": "Feature",
  "properties": {
    "iso:country":"US",
    "sg:address":"17485 Bowling Green Rd",
    "sg:city":"Smithfield",
    "sg:classifiers":[
        {
            "category":"Freight",
            "type":"Transportation"
        }
    ],
    "sg:phone":"+1 757 357 7025",
    "sg:postcode":"23430",
    "sg:province":"VA",
    "sg:tags":[
        "hauling",
        "contract",
        "trucking"
    ],
    "wof:name":"R A Matney Trucking",
    "wof:placetype":"venue"
},
  "geometry": {"coordinates":[-76.62195800000001,36.917386],"type":"Point"}
}