{
  "type": "Feature",
  "properties": {
    "addr:full":"9208 Claytonia Ln Annandale VA 22003",
    "addr:housenumber":"9208",
    "addr:postcode":"22003",
    "addr:street":"Claytonia Ln",
    "iso:country":"US",
    "sg:address":"9208 Claytonia Ln",
    "sg:city":"Annandale",
    "sg:classifiers":[
        {
            "category":"Wholesale",
            "subcategory":"Electrical",
            "type":"Manufacturing & Wholesale Goods"
        }
    ],
    "sg:phone":"+1 703 573 3165",
    "sg:postcode":"22003",
    "sg:province":"VA",
    "sg:tags":[
        "electronic",
        "component"
    ],
    "wof:name":"Ects Inc",
    "wof:placetype":"venue"
},
  "geometry": {"coordinates":[-77.262967,38.812297],"type":"Point"}
}