{
  "type": "Feature",
  "properties": {
    "iso:country":"US",
    "sg:address":"9117 Dickey Dr",
    "sg:city":"Mechanicsville",
    "sg:classifiers":[
        {
            "category":"Insurance",
            "subcategory":"Insurance Agent",
            "type":"Services"
        }
    ],
    "sg:phone":"+1 804 427 6804",
    "sg:postcode":"23116",
    "sg:province":"VA",
    "wof:name":"Don Long State Farm Insurance",
    "wof:placetype":"venue"
},
  "geometry": {"coordinates":[-77.405699,37.649625],"type":"Point"}
}