{
  "type": "Feature",
  "properties": {
    "iso:country":"US",
    "sg:address":"2139 Coliseum Dr",
    "sg:city":"Hampton",
    "sg:classifiers":[
        {
            "category":"Retail",
            "subcategory":"Laundry & Dry Cleaning",
            "type":"Services"
        }
    ],
    "sg:phone":"+1 757 826 9407",
    "sg:postcode":"23666",
    "sg:province":"VA",
    "sg:tags":[
        "cleaners"
    ],
    "wof:name":"Classic Cleaners",
    "wof:placetype":"venue"
},
  "geometry": {"coordinates":[-76.391649,37.049274],"type":"Point"}
}