{
  "type": "Feature",
  "properties": {
    "iso:country":"US",
    "sg:address":"103 Clifton St",
    "sg:city":"Lynchburg",
    "sg:classifiers":[
        {
            "category":"Health Services",
            "subcategory":"Clinic",
            "type":"Services"
        }
    ],
    "sg:phone":"+1 434 947 3954",
    "sg:postcode":"24501",
    "sg:province":"VA",
    "sg:tags":[
        "medical",
        "kidney",
        "dialysis",
        "center"
    ],
    "wof:name":"Lynchburg Dialysis Facility",
    "wof:placetype":"venue"
},
  "geometry": {"coordinates":[-79.180583,37.415697],"type":"Point"}
}