{
  "type": "Feature",
  "properties": {
    "iso:country":"US",
    "sg:address":"2140 Glencourse Ln",
    "sg:city":"Reston",
    "sg:classifiers":[
        {
            "category":"Professional",
            "subcategory":"Computer Services",
            "type":"Services"
        }
    ],
    "sg:phone":"+1 703 758 9520",
    "sg:postcode":"20191",
    "sg:province":"VA",
    "sg:tags":[
        "datum"
    ],
    "wof:name":"Cpncom Inc",
    "wof:placetype":"venue"
},
  "geometry": {"coordinates":[-77.345736,38.937658],"type":"Point"}
}