{
  "type": "Feature",
  "properties": {
    "addr:full":"11001 Warwick Blvd Newport News VA 23601",
    "addr:housenumber":"11001",
    "addr:postcode":"23601",
    "addr:street":"Warwick Blvd",
    "iso:country":"US",
    "sg:address":"11001 Warwick Blvd",
    "sg:city":"Newport News",
    "sg:classifiers":[
        {
            "category":"Professional",
            "type":"Services"
        }
    ],
    "sg:phone":"+1 757 988 8900",
    "sg:postcode":"23601",
    "sg:province":"VA",
    "sg:tags":[
        "establishment"
    ],
    "wof:name":"Deep Solutions",
    "wof:placetype":"venue"
},
  "geometry": {"coordinates":[-76.47364899999999,37.044652],"type":"Point"}
}