{
  "type": "Feature",
  "properties": {
    "iso:country":"US",
    "sg:address":"118 E Grayson St",
    "sg:city":"Galax",
    "sg:classifiers":[
        {
            "category":"Manufacturing",
            "subcategory":"Tools & Machinery",
            "type":"Manufacturing & Wholesale Goods"
        }
    ],
    "sg:phone":"+1 276 236 2772",
    "sg:postcode":"24333",
    "sg:province":"VA",
    "sg:tags":[
        "machine",
        "shop"
    ],
    "wof:name":"Star Machine Shop",
    "wof:placetype":"venue"
},
  "geometry": {"coordinates":[-80.924015,36.661981],"type":"Point"}
}