{
  "type": "Feature",
  "properties": {
    "addr:full":"5711 Courthouse Rd Chesterfield VA 23832",
    "addr:housenumber":"5711",
    "addr:postcode":"23832",
    "addr:street":"Courthouse Rd",
    "iso:country":"US",
    "sg:address":"5711 Courthouse Rd",
    "sg:city":"Chesterfield",
    "sg:classifiers":[
        {
            "category":"Organizations",
            "subcategory":"Religious Organization",
            "type":"Services"
        }
    ],
    "sg:phone":"+1 804 675 2183",
    "sg:postcode":"23832",
    "sg:province":"VA",
    "sg:tags":[
        "church"
    ],
    "wof:name":"Faith Heritage",
    "wof:placetype":"venue"
},
  "geometry": {"coordinates":[-77.570723,37.418285],"type":"Point"}
}