{
  "type": "Feature",
  "properties": {
    "iso:country":"US",
    "sg:address":"241 Maple Dr",
    "sg:city":"Collinsville",
    "sg:classifiers":[
        {
            "category":"Organizations",
            "subcategory":"Religious Organization",
            "type":"Services"
        }
    ],
    "sg:phone":"+1 276 647 1818",
    "sg:postcode":"24078",
    "sg:province":"VA",
    "wof:name":"Gospel Rd Baptist Ch",
    "wof:placetype":"venue"
},
  "geometry": {"coordinates":[-79.91049099999999,36.72062],"type":"Point"}
}