{
  "type": "Feature",
  "properties": {
    "iso:country":"US",
    "sg:address":"601 Marblethorpe Rd",
    "sg:city":"Richmond",
    "sg:classifiers":[
        {
            "category":"Building & Trades",
            "subcategory":"Construction",
            "type":"Services"
        }
    ],
    "sg:phone":"+1 804 794 9433",
    "sg:postcode":"23236",
    "sg:province":"VA",
    "sg:tags":[
        "house"
    ],
    "wof:name":"Replacement S Independent",
    "wof:placetype":"venue"
},
  "geometry": {"coordinates":[-77.589861,37.482983],"type":"Point"}
}