{
  "type": "Feature",
  "properties": {
    "addr:full":"957 W 21st St Norfolk VA 23517",
    "addr:housenumber":"957",
    "addr:postcode":"23517",
    "addr:street":"W 21St St",
    "iso:country":"US",
    "sg:address":"957 W 21st St",
    "sg:city":"Norfolk",
    "sg:classifiers":[
        {
            "category":"Health Services",
            "subcategory":"Doctor",
            "type":"Services"
        }
    ],
    "sg:phone":"+1 757 461 1688",
    "sg:postcode":"23517",
    "sg:province":"VA",
    "sg:tags":[
        "physician",
        "surgeon"
    ],
    "wof:name":"Orthopaedic Associates Of Va",
    "wof:placetype":"venue"
},
  "geometry": {"coordinates":[-76.299263,36.87193],"type":"Point"}
}