{
  "type": "Feature",
  "properties": {
    "addr:full":"530 Huntmar Park Dr Herndon VA 20170",
    "addr:housenumber":"530",
    "addr:postcode":"20170",
    "addr:street":"Huntmar Park Dr",
    "iso:country":"US",
    "sg:address":"530 Huntmar Park Dr",
    "sg:city":"Herndon",
    "sg:classifiers":[
        {
            "category":"Social Services",
            "subcategory":"Child Care",
            "type":"Services"
        }
    ],
    "sg:phone":"+1 703 471 2821",
    "sg:postcode":"20170",
    "sg:province":"VA",
    "wof:name":"Federal Children Ctr Doi",
    "wof:placetype":"venue"
},
  "geometry": {"coordinates":[-77.380461,38.963739],"type":"Point"}
}