{
  "type": "Feature",
  "properties": {
    "addr:full":"10805 Fournier Dr Fairfax Station VA 22039",
    "addr:housenumber":"10805",
    "addr:postcode":"22039",
    "addr:street":"Fournier Dr",
    "iso:country":"US",
    "sg:address":"10805 Fournier Dr",
    "sg:city":"Fairfax Station",
    "sg:classifiers":[
        {
            "category":"Shopping",
            "subcategory":"Clothing, Apparel, & Fashions",
            "type":"Retail Goods"
        }
    ],
    "sg:phone":"+1 703 426 2503",
    "sg:postcode":"22039",
    "sg:province":"VA",
    "wof:name":"Samias Fashion Inc",
    "wof:placetype":"venue"
},
  "geometry": {"coordinates":[-77.319737,38.786061],"type":"Point"}
}