{
  "type": "Feature",
  "properties": {
    "addr:full":"9981 Lickinghole Rd Ashland VA 23005",
    "addr:postcode":"9981;23005",
    "addr:street":"Lickinghole Rd",
    "iso:country":"US",
    "sg:address":"9981 Lickinghole Rd",
    "sg:city":"Ashland",
    "sg:classifiers":[
        {
            "category":"Sports & Exercise",
            "subcategory":"Gym",
            "type":"Entertainment"
        }
    ],
    "sg:phone":"+1 804 752 6610",
    "sg:postcode":"23005",
    "sg:province":"VA",
    "sg:tags":[
        "fitness",
        "facility"
    ],
    "wof:name":"All American Fitness Center",
    "wof:placetype":"venue"
},
  "geometry": {"coordinates":[-77.437934,37.70237],"type":"Point"}
}