{
  "type": "Feature",
  "properties": {
    "addr:full":"2817 Otsego Dr Herndon VA 20171",
    "addr:postcode":"2817;20171",
    "addr:street":"Otsego Dr",
    "iso:country":"US",
    "sg:address":"2817 Otsego Dr",
    "sg:city":"Herndon",
    "sg:classifiers":[
        {
            "category":"Professional",
            "subcategory":"Advertising",
            "type":"Services"
        }
    ],
    "sg:phone":"+1 703 620 6410",
    "sg:postcode":"20171",
    "sg:province":"VA",
    "sg:tags":[
        "sales",
        "specialty"
    ],
    "wof:name":"Rose Promotions Inc",
    "wof:placetype":"venue"
},
  "geometry": {"coordinates":[-77.383318,38.919611],"type":"Point"}
}