{
  "type": "Feature",
  "properties": {
    "addr:full":"7118 Freshaire Dr Springfield VA 22153",
    "addr:housenumber":"7118",
    "addr:postcode":"22153",
    "addr:street":"Freshaire Dr",
    "iso:country":"US",
    "sg:address":"7118 Freshaire Dr",
    "sg:city":"Springfield",
    "sg:classifiers":[
        {
            "category":"Home & Garden",
            "subcategory":"Carpets & Floor Coverings",
            "type":"Retail Goods"
        }
    ],
    "sg:phone":"+1 703 866 0553",
    "sg:postcode":"22153",
    "sg:province":"VA",
    "sg:tags":[
        "laying",
        "contractor"
    ],
    "wof:name":"Interior Creations Inc",
    "wof:placetype":"venue"
},
  "geometry": {"coordinates":[-77.255183,38.75996],"type":"Point"}
}