{
  "type": "Feature",
  "properties": {
    "addr:full":"5270 Claridge Dr Chesterfield VA 23832",
    "addr:housenumber":"5270",
    "addr:postcode":"23832",
    "addr:street":"Claridge Dr",
    "iso:country":"US",
    "sg:address":"5270 Claridge Dr",
    "sg:city":"Chesterfield",
    "sg:classifiers":[
        {
            "category":"Professional",
            "subcategory":"Accounting & Tax Preparation",
            "type":"Services"
        }
    ],
    "sg:phone":"+1 804 675 4437",
    "sg:postcode":"23832",
    "sg:province":"VA",
    "sg:tags":[
        "bookkeeping",
        "general"
    ],
    "wof:name":"Cobbs Bookkeeping & Tax Servi",
    "wof:placetype":"venue"
},
  "geometry": {"coordinates":[-77.572962,37.427623],"type":"Point"}
}