{
  "type": "Feature",
  "properties": {
    "addr:full":"901 W Broad St Waynesboro VA 22980",
    "addr:housenumber":"901",
    "addr:postcode":"22980",
    "addr:street":"W Broad St",
    "iso:country":"US",
    "sg:address":"901 W Broad St",
    "sg:city":"Waynesboro",
    "sg:classifiers":[
        {
            "category":"Building & Trades",
            "subcategory":"Equipment Rental",
            "type":"Services"
        }
    ],
    "sg:phone":"+1 540 942 2450",
    "sg:postcode":"22980",
    "sg:province":"VA",
    "sg:tags":[
        "appliance",
        "electronic",
        "furniture"
    ],
    "wof:name":"Ace T V Rentals",
    "wof:placetype":"venue"
},
  "geometry": {"coordinates":[-78.894519,38.070982],"type":"Point"}
}