{
  "type": "Feature",
  "properties": {
    "iso:country":"US",
    "sg:address":"1702 S Main St",
    "sg:city":"Blacksburg",
    "sg:classifiers":[
        {
            "category":"Shopping",
            "subcategory":"Gifts & Souvenirs",
            "type":"Retail Goods"
        }
    ],
    "sg:phone":"+1 540 953 3452",
    "sg:postcode":"24060",
    "sg:province":"VA",
    "sg:tags":[
        "shop"
    ],
    "sg:website":"www.for-the-birds.com",
    "wof:name":"For The Birds Inc",
    "wof:placetype":"venue"
},
  "geometry": {"coordinates":[-80.399787,37.211126],"type":"Point"}
}