{
  "type": "Feature",
  "properties": {
    "addr:full":"1805 Larkwood Ct Chesapeake VA 23321",
    "addr:housenumber":"1805",
    "addr:postcode":"23321",
    "addr:street":"Larkwood Ct",
    "iso:country":"US",
    "sg:address":"1805 Larkwood Ct",
    "sg:city":"Chesapeake",
    "sg:classifiers":[
        {
            "category":"Building & Trades",
            "subcategory":"Electrical",
            "type":"Services"
        }
    ],
    "sg:phone":"+1 757 672 6881",
    "sg:postcode":"23321",
    "sg:province":"VA",
    "sg:tags":[
        "electrical",
        "contractor"
    ],
    "wof:name":"McG Electrical Systems Inc",
    "wof:placetype":"venue"
},
  "geometry": {"coordinates":[-76.44049800000001,36.806277],"type":"Point"}
}