{
  "type": "Feature",
  "properties": {
    "addr:full":"7396 Hungarytown Rd Blackstone VA 23824",
    "addr:housenumber":"7396",
    "addr:postcode":"23824",
    "addr:street":"Hungarytown Rd",
    "iso:country":"US",
    "sg:address":"7396 Hungarytown Rd",
    "sg:city":"Blackstone",
    "sg:phone":"+1 434 645 1018",
    "sg:postcode":"23824",
    "sg:province":"VA",
    "sg:tags":[
        "farm",
        "field",
        "crop"
    ],
    "wof:name":"Als Lawn and Garden Center",
    "wof:placetype":"venue"
},
  "geometry": {"coordinates":[-78.11543,37.07297],"type":"Point"}
}