{
  "type": "Feature",
  "properties": {
    "iso:country":"US",
    "sg:address":"11325 Sunset Hills Rd",
    "sg:city":"Reston",
    "sg:classifiers":[
        {
            "category":"Health Services",
            "subcategory":"Doctor",
            "type":"Services"
        }
    ],
    "sg:phone":"+1 703 437 8811",
    "sg:postcode":"20190",
    "sg:province":"VA",
    "wof:name":"Drs Novick Hartz & Hall PC",
    "wof:placetype":"venue"
},
  "geometry": {"coordinates":[-77.338534,38.950688],"type":"Point"}
}