{
  "type": "Feature",
  "properties": {
    "iso:country":"US",
    "sg:address":"4207 Corcoran St",
    "sg:city":"Alexandria",
    "sg:classifiers":[
        {
            "category":"Professional",
            "subcategory":"Management & Consulting",
            "type":"Services"
        }
    ],
    "sg:phone":"+1 703 780 8157",
    "sg:postcode":"22309",
    "sg:province":"VA",
    "sg:tags":[
        "processing",
        "business"
    ],
    "wof:name":"Wingfield Multimedia Systems",
    "wof:placetype":"venue"
},
  "geometry": {"coordinates":[-77.107534,38.743146],"type":"Point"}
}