{
  "type": "Feature",
  "properties": {
    "addr:full":"113 S Hill Ave South Hill VA 23970",
    "addr:housenumber":"113",
    "addr:postcode":"23970",
    "addr:street":"S Hill Ave",
    "iso:country":"US",
    "sg:address":"113 S Hill Ave",
    "sg:city":"South Hill",
    "sg:classifiers":[
        {
            "category":"Farming",
            "subcategory":"Farm & Veterinary Services",
            "type":"Manufacturing & Wholesale Goods"
        }
    ],
    "sg:phone":"+1 434 447 6633",
    "sg:postcode":"23970",
    "sg:province":"VA",
    "sg:tags":[
        "control",
        "weed"
    ],
    "wof:name":"Lake Gaston Weed Control Cncl",
    "wof:placetype":"venue"
},
  "geometry": {"coordinates":[-78.130735,36.724545],"type":"Point"}
}