{
  "type": "Feature",
  "properties": {
    "iso:country":"US",
    "sg:address":"7732 Gromwell Ct",
    "sg:city":"Springfield",
    "sg:classifiers":[
        {
            "category":"Professional",
            "subcategory":"Management & Consulting",
            "type":"Services"
        }
    ],
    "sg:phone":"+1 703 866 7621",
    "sg:postcode":"22152",
    "sg:province":"VA",
    "sg:tags":[
        "retail",
        "direct",
        "sales"
    ],
    "wof:name":"Playtex Products Inc",
    "wof:placetype":"venue"
},
  "geometry": {"coordinates":[-77.20948199999999,38.76636],"type":"Point"}
}