{
  "type": "Feature",
  "properties": {
    "iso:country":"US",
    "sg:address":"2557 Huntington Dr",
    "sg:city":"Herndon",
    "sg:classifiers":[
        {
            "category":"Real Estate",
            "subcategory":"Real Estate Agent",
            "type":"Services"
        }
    ],
    "sg:phone":"+1 703 860 0385",
    "sg:postcode":"20171",
    "sg:province":"VA",
    "wof:name":"Northern Virginia Title Escrow",
    "wof:placetype":"venue"
},
  "geometry": {"coordinates":[-77.377662,38.93137],"type":"Point"}
}