{
  "type": "Feature",
  "properties": {
    "addr:full":"4435 N Pershing Dr Arlington VA 22203",
    "addr:housenumber":"4435",
    "addr:postcode":"22203",
    "addr:street":"N Pershing Dr",
    "iso:country":"US",
    "sg:address":"4435 N Pershing Dr",
    "sg:city":"Arlington",
    "sg:classifiers":[
        {
            "category":"Health Services",
            "subcategory":"Nursing And Care Facility",
            "type":"Services"
        }
    ],
    "sg:phone":"+1 703 528 3775",
    "sg:postcode":"22203",
    "sg:province":"VA",
    "wof:name":"Home Care Partners Inc",
    "wof:placetype":"venue"
},
  "geometry": {"coordinates":[-77.109301,38.871048],"type":"Point"}
}