{
  "type": "Feature",
  "properties": {
    "iso:country":"US",
    "sg:address":"5901 Queen's Mill Cir",
    "sg:city":"Fredericksburg",
    "sg:classifiers":[
        {
            "category":"Professional",
            "subcategory":"Management & Consulting",
            "type":"Services"
        }
    ],
    "sg:phone":"+1 540 898 1295",
    "sg:postcode":"22407",
    "sg:province":"VA",
    "sg:tags":[
        "retail",
        "direct",
        "sales"
    ],
    "wof:name":"Carol Washburn",
    "wof:placetype":"venue"
},
  "geometry": {"coordinates":[-77.530131,38.26574],"type":"Point"}
}