{
  "type": "Feature",
  "properties": {
    "iso:country":"US",
    "sg:address":"801 Fairmont Ave",
    "sg:city":"Winchester",
    "sg:classifiers":[
        {
            "category":"Professional",
            "type":"Services"
        }
    ],
    "sg:phone":"+1 540 667 5630",
    "sg:postcode":"22601",
    "sg:province":"VA",
    "wof:name":"Continental Commisary Co",
    "wof:placetype":"venue"
},
  "geometry": {"coordinates":[-78.165609,39.19504],"type":"Point"}
}