{
  "type": "Feature",
  "properties": {
    "addr:full":"3640 Dam Neck Rd Virginia Beach VA 23453",
    "addr:housenumber":"3640",
    "addr:postcode":"23453",
    "addr:street":"Dam Neck Rd",
    "iso:country":"US",
    "sg:address":"3640 Dam Neck Rd",
    "sg:city":"Virginia Beach",
    "sg:classifiers":[
        {
            "category":"Wholesale",
            "subcategory":"Farm Supplies",
            "type":"Manufacturing & Wholesale Goods"
        }
    ],
    "sg:phone":"+1 757 474 2019",
    "sg:postcode":"23453",
    "sg:province":"VA",
    "sg:tags":[
        "raw",
        "product",
        "material"
    ],
    "wof:name":"Peanuts Etc",
    "wof:placetype":"venue"
},
  "geometry": {"coordinates":[-76.090379,36.776378],"type":"Point"}
}