{
  "type": "Feature",
  "properties": {
    "iso:country":"US",
    "sg:address":"1529 Old William St",
    "sg:city":"Fredericksburg",
    "sg:classifiers":[
        {
            "category":"Shopping",
            "type":"Retail Goods"
        }
    ],
    "sg:phone":"+1 540 373 8651",
    "sg:postcode":"22401",
    "sg:province":"VA",
    "sg:tags":[
        "monument"
    ],
    "wof:name":"Carroll Memorials",
    "wof:placetype":"venue"
},
  "geometry": {"coordinates":[-77.480445,38.295404],"type":"Point"}
}