{
  "type": "Feature",
  "properties": {
    "iso:country":"US",
    "sg:address":"3033 Wilson Blvd",
    "sg:city":"Arlington",
    "sg:classifiers":[
        {
            "category":"Banks & Credit Unions",
            "subcategory":"Bank",
            "type":"Services"
        }
    ],
    "sg:phone":"+1 703 524 8100",
    "sg:postcode":"22201",
    "sg:province":"VA",
    "wof:name":"James Monroe Bank",
    "wof:placetype":"venue"
},
  "geometry": {"coordinates":[-77.094498,38.887798],"type":"Point"}
}