{
  "type": "Feature",
  "properties": {
    "addr:full":"31 Oertel Dr Farmville VA 23901",
    "addr:housenumber":"31",
    "addr:postcode":"23901",
    "addr:street":"Oertel Dr",
    "iso:country":"US",
    "sg:address":"31 Oertel Dr",
    "sg:city":"Farmville",
    "sg:classifiers":[
        {
            "category":"Building & Trades",
            "subcategory":"Construction",
            "type":"Services"
        }
    ],
    "sg:phone":"+1 434 392 6290",
    "sg:postcode":"23901",
    "sg:province":"VA",
    "sg:tags":[
        "hanging",
        "contractor"
    ],
    "wof:name":"Wallworks",
    "wof:placetype":"venue"
},
  "geometry": {"coordinates":[-78.407179,37.370119],"type":"Point"}
}