{
  "type": "Feature",
  "properties": {
    "iso:country":"US",
    "sg:address":"15450 Hillsboro Rd",
    "sg:city":"Purcellville",
    "sg:classifiers":[
        {
            "category":"Building & Trades",
            "subcategory":"Construction",
            "type":"Services"
        }
    ],
    "sg:phone":"+1 571 220 2350",
    "sg:postcode":"20132",
    "sg:province":"VA",
    "sg:tags":[
        "house"
    ],
    "wof:name":"Gps Systems Inc",
    "wof:placetype":"venue"
},
  "geometry": {"coordinates":[-77.71990099999999,39.189526],"type":"Point"}
}