{
  "type": "Feature",
  "properties": {
    "addr:full":"11740 W Broad St Richmond VA 23233",
    "addr:housenumber":"11740",
    "addr:postcode":"23233",
    "addr:street":"W Broad St",
    "iso:country":"US",
    "sg:address":"11740 W Broad St",
    "sg:city":"Richmond",
    "sg:classifiers":[
        {
            "category":"Retail",
            "subcategory":"Veterinary Services",
            "type":"Services"
        }
    ],
    "sg:phone":"+1 804 364 0224",
    "sg:postcode":"23233",
    "sg:province":"VA",
    "sg:tags":[
        "veterinarian"
    ],
    "wof:name":"Banfield The Pet Hospital",
    "wof:placetype":"venue"
},
  "geometry": {"coordinates":[-77.618956,37.652614],"type":"Point"}
}