{
  "type": "Feature",
  "properties": {
    "addr:full":"3005 Greenway Ave Richmond VA 23228",
    "addr:housenumber":"3005",
    "addr:postcode":"23228",
    "addr:street":"Greenway Ave",
    "iso:country":"US",
    "sg:address":"3005 Greenway Ave",
    "sg:city":"Richmond",
    "sg:classifiers":[
        {
            "category":"Building & Trades",
            "subcategory":"Construction",
            "type":"Services"
        }
    ],
    "sg:phone":"+1 804 264 8079",
    "sg:postcode":"23228",
    "sg:province":"VA",
    "sg:tags":[
        "hanging",
        "contractor"
    ],
    "wof:name":"Foster L R Painting Contractor",
    "wof:placetype":"venue"
},
  "geometry": {"coordinates":[-77.488862,37.604468],"type":"Point"}
}