{
  "type": "Feature",
  "properties": {
    "addr:full":"1853 Nester Rd Thaxton VA 24174",
    "addr:housenumber":"1853",
    "addr:postcode":"24174",
    "addr:street":"Nester Rd",
    "iso:country":"US",
    "sg:address":"1853 Nester Rd",
    "sg:city":"Thaxton",
    "sg:classifiers":[
        {
            "category":"Education",
            "subcategory":"School",
            "type":"Public Place"
        }
    ],
    "sg:phone":"+1 540 586 1440",
    "sg:postcode":"24174",
    "sg:province":"VA",
    "wof:name":"Danny Ray Creasy",
    "wof:placetype":"venue"
},
  "geometry": {"coordinates":[-79.667271,37.346827],"type":"Point"}
}