{
  "type": "Feature",
  "properties": {
    "addr:full":"38673 Charles Town Pike Waterford VA 20134",
    "addr:housenumber":"38673",
    "addr:postcode":"20134",
    "addr:street":"Charles Town Pike",
    "iso:country":"US",
    "sg:address":"38673 Charles Town Pike",
    "sg:city":"Waterford",
    "sg:classifiers":[
        {
            "category":"Building & Trades",
            "subcategory":"Landscaping Services",
            "type":"Services"
        }
    ],
    "sg:phone":"+1 540 882 9009",
    "sg:postcode":"20134",
    "sg:province":"VA",
    "sg:tags":[
        "designer",
        "landscape"
    ],
    "wof:name":"Metes & Bounds",
    "wof:placetype":"venue"
},
  "geometry": {"coordinates":[-77.67124800000001,39.187803],"type":"Point"}
}