{
  "type": "Feature",
  "properties": {
    "addr:full":"43258 Clearnight Ter Ashburn VA 20147",
    "addr:housenumber":"43258",
    "addr:postcode":"20147",
    "addr:street":"Clearnight Ter",
    "iso:country":"US",
    "sg:address":"43258 Clearnight Ter",
    "sg:city":"Ashburn",
    "sg:classifiers":[
        {
            "category":"Professional",
            "subcategory":"Management & Consulting",
            "type":"Services"
        }
    ],
    "sg:phone":"+1 703 729 7806",
    "sg:postcode":"20147",
    "sg:province":"VA",
    "sg:tags":[
        "business"
    ],
    "wof:name":"Advanced Business Solutions",
    "wof:placetype":"venue"
},
  "geometry": {"coordinates":[-77.505307,39.040845],"type":"Point"}
}