{
  "type": "Feature",
  "properties": {
    "iso:country":"US",
    "sg:address":"115 Saint Home Pl",
    "sg:city":"Rustburg",
    "sg:classifiers":[
        {
            "category":"Building & Trades",
            "subcategory":"Cleaning & Sanitation",
            "type":"Services"
        }
    ],
    "sg:phone":"+1 434 332 6646",
    "sg:postcode":"24588",
    "sg:province":"VA",
    "sg:tags":[
        "janitor"
    ],
    "wof:name":"Mr C's Professional Cleaning",
    "wof:placetype":"venue"
},
  "geometry": {"coordinates":[-79.111598,37.24226],"type":"Point"}
}