{
  "type": "Feature",
  "properties": {
    "iso:country":"US",
    "sg:address":"800 3rd St Ste 100",
    "sg:city":"Herndon",
    "sg:classifiers":[
        {
            "category":"Taxi",
            "type":"Transportation"
        }
    ],
    "sg:phone":"+1 703 707 9121",
    "sg:postcode":"20170",
    "sg:province":"VA",
    "wof:name":"Washington Dulles Flyer Inc",
    "wof:placetype":"venue"
},
  "geometry": {"coordinates":[-77.38194300000001,38.980541],"type":"Point"}
}