{
  "type": "Feature",
  "properties": {
    "addr:full":"5288 Dawes Ave Alexandria VA 22311",
    "addr:housenumber":"5288",
    "addr:postcode":"22311",
    "addr:street":"Dawes Ave",
    "iso:country":"US",
    "sg:address":"5288 Dawes Ave",
    "sg:city":"Alexandria",
    "sg:classifiers":[
        {
            "category":"Health Services",
            "subcategory":"Doctor",
            "type":"Services"
        }
    ],
    "sg:phone":"+1 703 671 6060",
    "sg:postcode":"22311",
    "sg:province":"VA",
    "sg:tags":[
        "surgeon",
        "oral"
    ],
    "wof:name":"Anderson David C DDS",
    "wof:placetype":"venue"
},
  "geometry": {"coordinates":[-77.120903,38.839699],"type":"Point"}
}