{
  "type": "Feature",
  "properties": {
    "iso:country":"US",
    "sg:address":"200 Gentry Ave",
    "sg:city":"Alexandria",
    "sg:classifiers":[
        {
            "category":"Professional",
            "subcategory":"Management & Consulting",
            "type":"Services"
        }
    ],
    "sg:phone":"+1 703 739 0606",
    "sg:postcode":"22305",
    "sg:province":"VA",
    "sg:tags":[
        "promotion",
        "board"
    ],
    "wof:name":"Murphy Mini",
    "wof:placetype":"venue"
},
  "geometry": {"coordinates":[-77.06447799999999,38.833211],"type":"Point"}
}