{
  "type": "Feature",
  "properties": {
    "addr:full":"250 Glebe Rd Daleville VA 24083",
    "addr:housenumber":"250",
    "addr:postcode":"24083",
    "addr:street":"Glebe Rd",
    "iso:country":"US",
    "sg:address":"250 Glebe Rd",
    "sg:city":"Daleville",
    "sg:classifiers":[
        {
            "category":"Health Services",
            "subcategory":"Nursing And Care Facility",
            "type":"Services"
        }
    ],
    "sg:phone":"+1 540 992 6711",
    "sg:postcode":"24083",
    "sg:province":"VA",
    "sg:tags":[
        "home",
        "convalescent"
    ],
    "wof:name":"Glebe",
    "wof:placetype":"venue"
},
  "geometry": {"coordinates":[-79.913704,37.420667],"type":"Point"}
}