{
  "type": "Feature",
  "properties": {
    "iso:country":"US",
    "sg:address":"8 Butler Farm Rd",
    "sg:city":"Hampton",
    "sg:classifiers":[
        {
            "category":"Retail",
            "subcategory":"Animal Services",
            "type":"Services"
        }
    ],
    "sg:phone":"+1 757 865 0511",
    "sg:postcode":"23666",
    "sg:province":"VA",
    "sg:tags":[
        "shelter"
    ],
    "wof:name":"Animal Aid Society",
    "wof:placetype":"venue"
},
  "geometry": {"coordinates":[-76.38979399999999,37.064063],"type":"Point"}
}