{
  "type": "Feature",
  "properties": {
    "addr:full":"109 Basalt Dr Fredericksburg VA 22406",
    "addr:housenumber":"109",
    "addr:postcode":"22406",
    "addr:street":"Basalt Dr",
    "iso:country":"US",
    "sg:address":"109 Basalt Dr",
    "sg:city":"Fredericksburg",
    "sg:classifiers":[
        {
            "category":"Retail",
            "subcategory":"Auto Repair",
            "type":"Services"
        }
    ],
    "sg:phone":"+1 703 536 0370",
    "sg:postcode":"22406",
    "sg:province":"VA",
    "sg:tags":[
        "wrecker"
    ],
    "wof:name":"Accurate Towing",
    "wof:placetype":"venue"
},
  "geometry": {"coordinates":[-77.53445499999999,38.363853],"type":"Point"}
}