{
  "type": "Feature",
  "properties": {
    "addr:full":"12701 Gordon Blvd Woodbridge VA 22192",
    "addr:housenumber":"12701",
    "addr:postcode":"22192",
    "addr:street":"Gordon Blvd",
    "iso:country":"US",
    "sg:address":"12701 Gordon Blvd",
    "sg:city":"Woodbridge",
    "sg:classifiers":[
        {
            "category":"Marine",
            "type":"Transportation"
        }
    ],
    "sg:phone":"+1 540 720 0800",
    "sg:postcode":"22192",
    "sg:province":"VA",
    "sg:tags":[
        "surveyor"
    ],
    "wof:name":"True Heading Marine Surveying",
    "wof:placetype":"venue"
},
  "geometry": {"coordinates":[-77.254909,38.675022],"type":"Point"}
}