{
  "type": "Feature",
  "properties": {
    "iso:country":"US",
    "sg:address":"7022 Old Cabin Ln",
    "sg:city":"Gloucester",
    "sg:classifiers":[
        {
            "category":"Freight",
            "type":"Transportation"
        }
    ],
    "sg:phone":"+1 804 693 3195",
    "sg:postcode":"23061",
    "sg:province":"VA",
    "sg:tags":[
        "operator",
        "mobile",
        "trucking",
        "home"
    ],
    "wof:name":"D & S Mobile Home Movers",
    "wof:placetype":"venue"
},
  "geometry": {"coordinates":[-76.511257,37.477675],"type":"Point"}
}