{
  "type": "Feature",
  "properties": {
    "addr:full":"4077 Main St Chincoteague VA 23336",
    "addr:housenumber":"4077",
    "addr:postcode":"23336",
    "addr:street":"Main St",
    "iso:country":"US",
    "sg:address":"4077 Main St",
    "sg:city":"Chincoteague",
    "sg:classifiers":[
        {
            "category":"Education",
            "subcategory":"Library",
            "type":"Public Place"
        }
    ],
    "sg:phone":"+1 757 336 3460",
    "sg:postcode":"23336",
    "sg:province":"VA",
    "wof:name":"Island Library",
    "wof:placetype":"venue"
},
  "geometry": {"coordinates":[-75.376216,37.934331],"type":"Point"}
}