{
  "type": "Feature",
  "properties": {
    "addr:full":"444 Floyd Hwy S Floyd VA 24091",
    "addr:housenumber":"444",
    "addr:postcode":"24091",
    "addr:street":"Floyd Hwy S",
    "iso:country":"US",
    "sg:address":"444 Floyd Hwy S",
    "sg:city":"Floyd",
    "sg:classifiers":[
        {
            "category":"Organizations",
            "subcategory":"Community Association",
            "type":"Services"
        }
    ],
    "sg:phone":"+1 540 745 2475",
    "sg:postcode":"24091",
    "sg:province":"VA",
    "wof:name":"Lodge 2300 - Floyd",
    "wof:placetype":"venue"
},
  "geometry": {"coordinates":[-80.337014,36.909074],"type":"Point"}
}