{
  "type": "Feature",
  "properties": {
    "addr:full":"128 Colony Rd Madison Heights VA 24572",
    "addr:housenumber":"128",
    "addr:postcode":"24572",
    "addr:street":"Colony Rd",
    "iso:country":"US",
    "sg:address":"128 Colony Rd",
    "sg:city":"Madison Heights",
    "sg:classifiers":[
        {
            "category":"Retail",
            "subcategory":"Auto Repair",
            "type":"Services"
        }
    ],
    "sg:phone":"+1 434 528 5995",
    "sg:postcode":"24572",
    "sg:province":"VA",
    "sg:tags":[
        "repairing",
        "automobile"
    ],
    "wof:name":"Marshall Automotive & Mobility",
    "wof:placetype":"venue"
},
  "geometry": {"coordinates":[-79.12981600000001,37.425628],"type":"Point"}
}