{
  "type": "Feature",
  "properties": {
    "iso:country":"US",
    "sg:address":"3601 Seaford Rd",
    "sg:city":"Seaford",
    "sg:classifiers":[
        {
            "category":"Professional",
            "subcategory":"Business Services",
            "type":"Services"
        }
    ],
    "sg:phone":"+1 757 898 7424",
    "sg:postcode":"23696",
    "sg:province":"VA",
    "sg:tags":[
        "barricade"
    ],
    "wof:name":"Barricade Rentals Inc",
    "wof:placetype":"venue"
},
  "geometry": {"coordinates":[-76.411484,37.189446],"type":"Point"}
}