{
  "type": "Feature",
  "properties": {
    "addr:full":"1745 S Jefferson Davis Hwy Arlington VA 22202",
    "addr:housenumber":"1745",
    "addr:postcode":"22202",
    "addr:street":"S Jefferson Davis Hwy",
    "iso:country":"US",
    "sg:address":"1745 S Jefferson Davis Hwy",
    "sg:city":"Arlington",
    "sg:classifiers":[
        {
            "category":"Professional",
            "subcategory":"Business Services",
            "type":"Services"
        }
    ],
    "sg:phone":"+1 703 416 1950",
    "sg:postcode":"22202",
    "sg:province":"VA",
    "wof:name":"Sheehan Brian",
    "wof:placetype":"venue"
},
  "geometry": {"coordinates":[-77.051917,38.85965],"type":"Point"}
}