{
  "type": "Feature",
  "properties": {
    "addr:full":"6969 Richmond Hwy Ste 201 Alexandria VA 22306",
    "addr:housenumber":"6969",
    "addr:postcode":"22306",
    "addr:street":"Richmond Hwy Ste 201",
    "iso:country":"US",
    "sg:address":"6969 Richmond Hwy Ste 201",
    "sg:city":"Alexandria",
    "sg:classifiers":[
        {
            "category":"Health Services",
            "subcategory":"Clinic",
            "type":"Services"
        }
    ],
    "sg:phone":"+1 703 768 7351",
    "sg:postcode":"22306",
    "sg:province":"VA",
    "sg:tags":[
        "medical",
        "welfare"
    ],
    "wof:name":"Mofrankal Health Care Svc",
    "wof:placetype":"venue"
},
  "geometry": {"coordinates":[-77.083679,38.766289],"type":"Point"}
}