{
  "type": "Feature",
  "properties": {
    "iso:country":"US",
    "sg:address":"3200 Commerce St",
    "sg:city":"Blacksburg",
    "sg:classifiers":[
        {
            "category":"Professional",
            "subcategory":"Testing Lab",
            "type":"Services"
        }
    ],
    "sg:phone":"+1 540 951 4234",
    "sg:postcode":"24060",
    "sg:province":"VA",
    "sg:tags":[
        "soil"
    ],
    "sg:website":"www.simonassoc.com",
    "wof:name":"Simon & Assoc Inc",
    "wof:placetype":"venue"
},
  "geometry": {"coordinates":[-80.39328399999999,37.194455],"type":"Point"}
}