{
  "type": "Feature",
  "properties": {
    "addr:full":"310 Montgomery St Alexandria VA 22314",
    "addr:housenumber":"310",
    "addr:postcode":"22314",
    "addr:street":"Montgomery St",
    "iso:country":"US",
    "sg:address":"310 Montgomery St",
    "sg:city":"Alexandria",
    "sg:classifiers":[
        {
            "category":"Organizations",
            "subcategory":"Professional Association",
            "type":"Services"
        }
    ],
    "sg:phone":"+1 703 549 4432",
    "sg:postcode":"22314",
    "sg:province":"VA",
    "wof:name":"Health Industry Distributors",
    "wof:placetype":"venue"
},
  "geometry": {"coordinates":[-77.041608,38.813635],"type":"Point"}
}