{
  "type": "Feature",
  "properties": {
    "iso:country":"US",
    "sg:address":"225 Ritter Rd",
    "sg:city":"Winchester",
    "sg:phone":"+1 540 869 5033",
    "sg:postcode":"22602",
    "sg:province":"VA",
    "sg:tags":[
        "equipment",
        "station"
    ],
    "wof:name":"Rappahannock Petroleum Svc",
    "wof:placetype":"venue"
},
  "geometry": {"coordinates":[-78.137799,39.084984],"type":"Point"}
}