{
  "type": "Feature",
  "properties": {
    "addr:full":"8400 Franconia Rd Richmond VA 23227",
    "addr:housenumber":"8400",
    "addr:postcode":"23227",
    "addr:street":"Franconia Rd",
    "iso:country":"US",
    "sg:address":"8400 Franconia Rd",
    "sg:city":"Richmond",
    "sg:classifiers":[
        {
            "category":"Freight",
            "type":"Transportation"
        }
    ],
    "sg:phone":"+1 804 615 8523",
    "sg:postcode":"23227",
    "sg:province":"VA",
    "sg:tags":[
        "delivery"
    ],
    "wof:name":"Central Delivery Svc",
    "wof:placetype":"venue"
},
  "geometry": {"coordinates":[-77.43952299999999,37.639707],"type":"Point"}
}