{
  "type": "Feature",
  "properties": {
    "addr:full":"3920 Pender Dr Fairfax VA 22030",
    "addr:housenumber":"3920",
    "addr:postcode":"22030",
    "addr:street":"Pender Dr",
    "iso:country":"US",
    "sg:address":"3920 Pender Dr",
    "sg:city":"Fairfax",
    "sg:classifiers":[
        {
            "category":"Government",
            "subcategory":"Office",
            "type":"Public Place"
        }
    ],
    "sg:phone":"+1 703 302 7997",
    "sg:postcode":"22030",
    "sg:province":"VA",
    "sg:tags":[
        "telecommunication"
    ],
    "wof:name":"Diplomatic Telecommunications",
    "wof:placetype":"venue"
},
  "geometry": {"coordinates":[-77.33365999999999,38.86028],"type":"Point"}
}