{
  "type": "Feature",
  "properties": {
    "addr:full":"2800 N Parham Rd Richmond VA 23294",
    "addr:housenumber":"2800",
    "addr:postcode":"23294",
    "addr:street":"N Parham Rd",
    "iso:country":"US",
    "sg:address":"2800 N Parham Rd",
    "sg:city":"Richmond",
    "sg:classifiers":[
        {
            "category":"Professional",
            "subcategory":"Accounting & Tax Preparation",
            "type":"Services"
        }
    ],
    "sg:phone":"+1 804 270 5900",
    "sg:postcode":"23294",
    "sg:province":"VA",
    "wof:name":"Parham Road Cleaners",
    "wof:placetype":"venue"
},
  "geometry": {"coordinates":[-77.545354,37.628692],"type":"Point"}
}