{
  "type": "Feature",
  "properties": {
    "addr:full":"18237 Richmond Tpke Milford VA 22514",
    "addr:housenumber":"18237",
    "addr:postcode":"22514",
    "addr:street":"Richmond Tpke",
    "iso:country":"US",
    "sg:address":"18237 Richmond Tpke",
    "sg:city":"Milford",
    "sg:classifiers":[
        {
            "category":"Insurance",
            "subcategory":"Insurance Agent",
            "type":"Services"
        }
    ],
    "sg:phone":"+1 804 633 9825",
    "sg:postcode":"22514",
    "sg:province":"VA",
    "wof:name":"Caroline County Farm Bureau",
    "wof:placetype":"venue"
},
  "geometry": {"coordinates":[-77.335481,38.011815],"type":"Point"}
}