{
  "type": "Feature",
  "properties": {
    "addr:full":"504 Marston Dr Chesapeake VA 23322",
    "addr:housenumber":"504",
    "addr:postcode":"23322",
    "addr:street":"Marston Dr",
    "iso:country":"US",
    "sg:address":"504 Marston Dr",
    "sg:city":"Chesapeake",
    "sg:classifiers":[
        {
            "category":"Arts & Performance",
            "subcategory":"Theater",
            "type":"Entertainment"
        }
    ],
    "sg:phone":"+1 757 482 0967",
    "sg:postcode":"23322",
    "sg:province":"VA",
    "sg:tags":[
        "group"
    ],
    "wof:name":"Sterling Enterprises",
    "wof:placetype":"venue"
},
  "geometry": {"coordinates":[-76.209913,36.687195],"type":"Point"}
}