{
  "type": "Feature",
  "properties": {
    "addr:full":"4725 Rugby Rd Virginia Beach VA 23464",
    "addr:housenumber":"4725",
    "addr:postcode":"23464",
    "addr:street":"Rugby Rd",
    "iso:country":"US",
    "sg:address":"4725 Rugby Rd",
    "sg:city":"Virginia Beach",
    "sg:classifiers":[
        {
            "category":"Professional",
            "subcategory":"Accounting & Tax Preparation",
            "type":"Services"
        }
    ],
    "sg:phone":"+1 757 495 5728",
    "sg:postcode":"23464",
    "sg:province":"VA",
    "sg:tags":[
        "return"
    ],
    "wof:name":"A OK Tax Service",
    "wof:placetype":"venue"
},
  "geometry": {"coordinates":[-76.154754,36.790082],"type":"Point"}
}