{
  "type": "Feature",
  "properties": {
    "iso:country":"US",
    "sg:address":"913 Winstead St",
    "sg:city":"Great Falls",
    "sg:classifiers":[
        {
            "category":"Professional",
            "subcategory":"Research",
            "type":"Services"
        }
    ],
    "sg:phone":"+1 703 438 0882",
    "sg:postcode":"22066",
    "sg:province":"VA",
    "sg:tags":[
        "commercial",
        "physical"
    ],
    "wof:name":"Jase Inc",
    "wof:placetype":"venue"
},
  "geometry": {"coordinates":[-77.293626,38.984701],"type":"Point"}
}