{
  "type": "Feature",
  "properties": {
    "addr:full":"P.O. Box 40875 Arlington VA 22204",
    "addr:housenumber":"p.o. box 40875",
    "addr:postcode":"22204",
    "iso:country":"US",
    "sg:address":"P.O. Box 40875",
    "sg:city":"Arlington",
    "sg:classifiers":[
        {
            "category":"Professional",
            "subcategory":"Computer Services",
            "type":"Services"
        }
    ],
    "sg:postcode":"22204",
    "sg:province":"VA",
    "sg:tags":[
        "fsbo",
        "real-estate",
        "homes",
        "washington-dc",
        "maryland",
        "virginia",
        "for-sale-by-owner"
    ],
    "sg:website":"http://www.fsboTheDistrict.com",
    "wof:name":"fsboTheDistrict",
    "wof:placetype":"venue"
},
  "geometry": {"coordinates":[-77.10086800000001,38.860335],"type":"Point"}
}