{
  "type": "Feature",
  "properties": {
    "addr:full":"13106 Woolwine Hwy Woolwine VA 24185",
    "addr:housenumber":"13106",
    "addr:postcode":"24185",
    "addr:street":"Woolwine Hwy",
    "iso:country":"US",
    "sg:address":"13106 Woolwine Hwy",
    "sg:city":"Woolwine",
    "sg:classifiers":[
        {
            "category":"Freight",
            "type":"Transportation"
        }
    ],
    "sg:phone":"+1 276 930 1146",
    "sg:postcode":"24185",
    "sg:province":"VA",
    "sg:tags":[
        "operator",
        "local",
        "trucking"
    ],
    "wof:name":"Ja Worley Trucking Inc",
    "wof:placetype":"venue"
},
  "geometry": {"coordinates":[-80.31966,36.81068],"type":"Point"}
}