{
  "type": "Feature",
  "properties": {
    "iso:country":"US",
    "sg:address":"7223 Nathan Ct",
    "sg:city":"Manassas",
    "sg:classifiers":[
        {
            "category":"Organizations",
            "subcategory":"Religious Organization",
            "type":"Services"
        }
    ],
    "sg:phone":"+1 703 335 2670",
    "sg:postcode":"20109",
    "sg:province":"VA",
    "wof:name":"Unity Christian Outreach",
    "wof:placetype":"venue"
},
  "geometry": {"coordinates":[-77.52215200000001,38.799874],"type":"Point"}
}