{
  "type": "Feature",
  "properties": {
    "addr:full":"10020 Iron Bridge Rd Chesterfield VA 23832",
    "addr:housenumber":"10020",
    "addr:postcode":"23832",
    "addr:street":"Iron Bridge Rd",
    "iso:country":"US",
    "sg:address":"10020 Iron Bridge Rd",
    "sg:city":"Chesterfield",
    "sg:classifiers":[
        {
            "category":"Government",
            "subcategory":"Office",
            "type":"Public Place"
        }
    ],
    "sg:phone":"+1 804 796 1479",
    "sg:postcode":"23832",
    "sg:province":"VA",
    "wof:name":"Magnolia Grange Museum House",
    "wof:placetype":"venue"
},
  "geometry": {"coordinates":[-77.50806,37.375725],"type":"Point"}
}