{
  "type": "Feature",
  "properties": {
    "addr:full":"6400 Brandon Ave Springfield VA 22150",
    "addr:housenumber":"6400",
    "addr:postcode":"22150",
    "addr:street":"Brandon Ave",
    "iso:country":"US",
    "sg:address":"6400 Brandon Ave",
    "sg:city":"Springfield",
    "sg:classifiers":[
        {
            "category":"Professional",
            "type":"Services"
        }
    ],
    "sg:phone":"+1 703 451 9806",
    "sg:postcode":"22150",
    "sg:province":"VA",
    "sg:tags":[
        "establishment"
    ],
    "wof:name":"Town Center",
    "wof:placetype":"venue"
},
  "geometry": {"coordinates":[-77.18249,38.77943],"type":"Point"}
}