{
  "type": "Feature",
  "properties": {
    "iso:country":"US",
    "sg:address":"212 Fort Collier Rd",
    "sg:city":"Winchester",
    "sg:classifiers":[
        {
            "category":"Wholesale",
            "subcategory":"Electrical",
            "type":"Manufacturing & Wholesale Goods"
        }
    ],
    "sg:phone":"+1 540 678 9000",
    "sg:postcode":"22603",
    "sg:province":"VA",
    "sg:tags":[
        "equipment",
        "electric",
        "supply"
    ],
    "sg:website":"www.eeco-net.com",
    "wof:name":"Electrical Equipment Co",
    "wof:placetype":"venue"
},
  "geometry": {"coordinates":[-78.147806,39.195685],"type":"Point"}
}