{
  "type": "Feature",
  "properties": {
    "addr:full":"302 Washington Ave SW Roanoke VA 24016",
    "addr:housenumber":"302",
    "addr:postcode":"24016",
    "addr:street":"Washington Ave Sw",
    "iso:country":"US",
    "sg:address":"302 Washington Ave SW",
    "sg:city":"Roanoke",
    "sg:classifiers":[
        {
            "category":"Professional",
            "subcategory":"Lawyer & Legal Services",
            "type":"Services"
        }
    ],
    "sg:phone":"+1 540 344 7600",
    "sg:postcode":"24016",
    "sg:province":"VA",
    "wof:name":"David O Williamson",
    "wof:placetype":"venue"
},
  "geometry": {"coordinates":[-79.946584,37.263783],"type":"Point"}
}