{
  "type": "Feature",
  "properties": {
    "iso:country":"US",
    "sg:address":"1619 Logan St",
    "sg:city":"Richmond",
    "sg:classifiers":[
        {
            "category":"Building & Trades",
            "subcategory":"Plumbing",
            "type":"Services"
        }
    ],
    "sg:phone":"+1 804 272 2626",
    "sg:postcode":"23235",
    "sg:province":"VA",
    "sg:tags":[
        "septic"
    ],
    "wof:name":"Anytime Pumping",
    "wof:placetype":"venue"
},
  "geometry": {"coordinates":[-77.554485,37.520785],"type":"Point"}
}