{
  "type": "Feature",
  "properties": {
    "addr:full":"1221 Culbert Dr Marion VA 24354",
    "addr:housenumber":"1221",
    "addr:postcode":"24354",
    "addr:street":"Culbert Dr",
    "iso:country":"US",
    "sg:address":"1221 Culbert Dr",
    "sg:city":"Marion",
    "sg:classifiers":[
        {
            "category":"Building & Trades",
            "subcategory":"Electrical",
            "type":"Services"
        }
    ],
    "sg:phone":"+1 276 783 3854",
    "sg:postcode":"24354",
    "sg:province":"VA",
    "sg:tags":[
        "electrical",
        "contractor"
    ],
    "wof:name":"Mountain Empire Electric",
    "wof:placetype":"venue"
},
  "geometry": {"coordinates":[-81.501496,36.850568],"type":"Point"}
}