{
  "type": "Feature",
  "properties": {
    "addr:full":"315 Reneau Way Herndon VA 20170",
    "addr:housenumber":"315",
    "addr:postcode":"20170",
    "addr:street":"Reneau Way",
    "iso:country":"US",
    "sg:address":"315 Reneau Way",
    "sg:city":"Herndon",
    "sg:classifiers":[
        {
            "category":"Professional",
            "subcategory":"Computer Services",
            "type":"Services"
        }
    ],
    "sg:phone":"+1 703 759 2658",
    "sg:postcode":"20170",
    "sg:province":"VA",
    "sg:tags":[
        "consultant",
        "designer"
    ],
    "wof:name":"Advanced Computer Svc",
    "wof:placetype":"venue"
},
  "geometry": {"coordinates":[-77.371061,38.970025],"type":"Point"}
}