{
  "type": "Feature",
  "properties": {
    "iso:country":"US",
    "sg:address":"200 W Forest Trl",
    "sg:city":"South Boston",
    "sg:classifiers":[
        {
            "category":"Health Services",
            "subcategory":"Doctor",
            "type":"Services"
        }
    ],
    "sg:phone":"+1 434 572 3323",
    "sg:postcode":"24592",
    "sg:province":"VA",
    "sg:tags":[
        "physician",
        "surgeon"
    ],
    "wof:name":"Souza & Assoc",
    "wof:placetype":"venue"
},
  "geometry": {"coordinates":[-78.946546,36.740147],"type":"Point"}
}