{
  "type": "Feature",
  "properties": {
    "iso:country":"US",
    "sg:address":"430 Bybee Rd",
    "sg:city":"Louisa",
    "sg:classifiers":[
        {
            "category":"Building & Trades",
            "subcategory":"Landscaping Services",
            "type":"Services"
        }
    ],
    "sg:phone":"+1 434 589 4574",
    "sg:postcode":"23093",
    "sg:province":"VA",
    "wof:name":"Johnson Landscape Inc La",
    "wof:placetype":"venue"
},
  "geometry": {"coordinates":[-78.198784,37.959526],"type":"Point"}
}