{
  "type": "Feature",
  "properties": {
    "iso:country":"US",
    "sg:address":"5810 Kingstowne Center",
    "sg:city":"Alexandria",
    "sg:classifiers":[
        {
            "category":"Professional",
            "subcategory":"Computer Services",
            "type":"Services"
        }
    ],
    "sg:phone":"+1 703 973 2892",
    "sg:postcode":"22315",
    "sg:province":"VA",
    "sg:tags":[
        "consultant",
        "it"
    ],
    "wof:name":"H & L Consultants Group LLC",
    "wof:placetype":"venue"
},
  "geometry": {"coordinates":[-77.135544,38.774997],"type":"Point"}
}