{
  "type": "Feature",
  "properties": {
    "iso:country":"US",
    "sg:address":"3604 Canoe Birch Ct",
    "sg:city":"Fairfax",
    "sg:classifiers":[
        {
            "category":"Professional",
            "subcategory":"Computer Services",
            "type":"Services"
        }
    ],
    "sg:phone":"+1 703 464 0384",
    "sg:postcode":"22033",
    "sg:province":"VA",
    "sg:tags":[
        "prepackaged",
        "software"
    ],
    "wof:name":"Business Optmum Sftwr Solution",
    "wof:placetype":"venue"
},
  "geometry": {"coordinates":[-77.413641,38.895923],"type":"Point"}
}