{
  "type": "Feature",
  "properties": {
    "addr:full":"406 8th St NE Charlottesville VA 22902",
    "addr:housenumber":"406",
    "addr:postcode":"22902",
    "addr:street":"8Th St Ne",
    "iso:country":"US",
    "sg:address":"406 8th St NE",
    "sg:city":"Charlottesville",
    "sg:classifiers":[
        {
            "category":"Insurance",
            "subcategory":"Insurance Agent",
            "type":"Services"
        }
    ],
    "sg:phone":"+1 434 971 5647",
    "sg:postcode":"22902",
    "sg:province":"VA",
    "wof:name":"MAS Insurance Svc Inc",
    "wof:placetype":"venue"
},
  "geometry": {"coordinates":[-78.474779,38.03232],"type":"Point"}
}