{
  "type": "Feature",
  "properties": {
    "addr:full":"2040 Coliseum Dr Hampton VA 23666",
    "addr:housenumber":"2040",
    "addr:postcode":"23666",
    "addr:street":"Coliseum Dr",
    "iso:country":"US",
    "sg:address":"2040 Coliseum Dr",
    "sg:city":"Hampton",
    "sg:classifiers":[
        {
            "category":"Personal",
            "subcategory":"Beauty Salon",
            "type":"Services"
        }
    ],
    "sg:phone":"+1 757 825 0817",
    "sg:postcode":"23666",
    "sg:province":"VA",
    "sg:tags":[
        "shop"
    ],
    "sg:website":"www.supercuts.com",
    "wof:name":"Supercuts",
    "wof:placetype":"venue"
},
  "geometry": {"coordinates":[-76.389707,37.044418],"type":"Point"}
}