{
  "type": "Feature",
  "properties": {
    "iso:country":"US",
    "sg:address":"800 Adams St",
    "sg:city":"Fredericksburg",
    "sg:classifiers":[
        {
            "category":"Shopping",
            "subcategory":"Used Merchandise",
            "type":"Retail Goods"
        }
    ],
    "sg:phone":"+1 540 374 1838",
    "sg:postcode":"22401",
    "sg:province":"VA",
    "wof:name":"Empty Nest",
    "wof:placetype":"venue"
},
  "geometry": {"coordinates":[-77.47662699999999,38.296209],"type":"Point"}
}