{
  "type": "Feature",
  "properties": {
    "iso:country":"US",
    "sg:address":"403 Judges Ct",
    "sg:city":"Newport News",
    "sg:classifiers":[
        {
            "category":"Health Services",
            "subcategory":"Health Practitioner",
            "type":"Services"
        }
    ],
    "sg:phone":"+1 757 886 1511",
    "sg:postcode":"23608",
    "sg:province":"VA",
    "sg:tags":[
        "registered",
        "nurse"
    ],
    "wof:name":"Kathleen M Calby",
    "wof:placetype":"venue"
},
  "geometry": {"coordinates":[-76.533382,37.141328],"type":"Point"}
}