{
  "type": "Feature",
  "properties": {
    "iso:country":"US",
    "sg:address":"9624 Jefferson Davis Hwy",
    "sg:city":"Richmond",
    "sg:classifiers":[
        {
            "category":"Restaurant",
            "type":"Food & Drink"
        }
    ],
    "sg:phone":"+1 804 271 9255",
    "sg:postcode":"23237",
    "sg:province":"VA",
    "sg:tags":[
        "eating"
    ],
    "wof:name":"Cancun Restaurant",
    "wof:placetype":"venue"
},
  "geometry": {"coordinates":[-77.42913299999999,37.393782],"type":"Point"}
}