{
  "type": "Feature",
  "properties": {
    "iso:country":"US",
    "sg:address":"2460 Harmony Dr",
    "sg:city":"Charlottesville",
    "sg:classifiers":[
        {
            "category":"Professional",
            "type":"Services"
        }
    ],
    "sg:phone":"+1 434 979 9502",
    "sg:postcode":"22901",
    "sg:province":"VA",
    "wof:name":"Thomas & Susan Likowski",
    "wof:placetype":"venue"
},
  "geometry": {"coordinates":[-78.57970299999999,38.103035],"type":"Point"}
}