{
  "type": "Feature",
  "properties": {
    "iso:country":"US",
    "sg:address":"701 Berkley Ct",
    "sg:city":"Virginia Beach",
    "sg:classifiers":[
        {
            "category":"Education",
            "subcategory":"Special Training",
            "type":"Public Place"
        }
    ],
    "sg:phone":"+1 757 486 8433",
    "sg:postcode":"23452",
    "sg:province":"VA",
    "wof:name":"Innovative Education Inc",
    "wof:placetype":"venue"
},
  "geometry": {"coordinates":[-76.09224399999999,36.858337],"type":"Point"}
}