{
  "type": "Feature",
  "properties": {
    "addr:full":"14114 Lee Hwy Centreville VA 20120",
    "addr:housenumber":"14114",
    "addr:postcode":"20120",
    "addr:street":"Lee Hwy",
    "iso:country":"US",
    "sg:address":"14114 Lee Hwy",
    "sg:city":"Centreville",
    "sg:classifiers":[
        {
            "category":"Recreation",
            "type":"Entertainment"
        }
    ],
    "sg:phone":"+1 703 266 8888",
    "sg:postcode":"20120",
    "sg:province":"VA",
    "sg:tags":[
        "parlor",
        "billiard",
        "restaurant"
    ],
    "sg:website":"http://www.fasteddies.com",
    "wof:name":"Fast Eddie's Sports & Billiards",
    "wof:placetype":"venue"
},
  "geometry": {"coordinates":[-77.434735,38.83876],"type":"Point"}
}