{
  "type": "Feature",
  "properties": {
    "addr:full":"5520 Starboard Ct Fairfax VA 22032",
    "addr:housenumber":"5520",
    "addr:postcode":"22032",
    "addr:street":"Starboard Ct",
    "iso:country":"US",
    "sg:address":"5520 Starboard Ct",
    "sg:city":"Fairfax",
    "sg:classifiers":[
        {
            "category":"Professional",
            "subcategory":"Management & Consulting",
            "type":"Services"
        }
    ],
    "sg:phone":"+1 703 323 0738",
    "sg:postcode":"22032",
    "sg:province":"VA",
    "wof:name":"Frenzinger Thomas W",
    "wof:placetype":"venue"
},
  "geometry": {"coordinates":[-77.29146799999999,38.80184],"type":"Point"}
}