{
  "type": "Feature",
  "properties": {
    "addr:full":"4105 Forty Two Rd Clifton Forge VA 24422",
    "addr:housenumber":"4105",
    "addr:postcode":"forge;24422",
    "addr:street":"Forty Two Rd",
    "iso:country":"US",
    "sg:address":"4105 Forty Two Rd",
    "sg:city":"Clifton Forge",
    "sg:classifiers":[
        {
            "category":"Farming",
            "subcategory":"Nursery",
            "type":"Manufacturing & Wholesale Goods"
        }
    ],
    "sg:phone":"+1 540 863 9551",
    "sg:postcode":"24422",
    "sg:province":"VA",
    "sg:tags":[
        "ornamental"
    ],
    "wof:name":"Old Longdale Greenhouse",
    "wof:placetype":"venue"
},
  "geometry": {"coordinates":[-79.741713,37.849658],"type":"Point"}
}