{
  "type": "Feature",
  "properties": {
    "addr:full":"1840 International Dr McLean VA 22101",
    "addr:housenumber":"1840",
    "addr:postcode":"22101",
    "addr:street":"International Dr",
    "iso:country":"US",
    "sg:address":"1840 International Dr",
    "sg:city":"McLean",
    "sg:classifiers":[
        {
            "category":"Building & Trades",
            "subcategory":"Locksmith",
            "type":"Services"
        }
    ],
    "sg:phone":"+1 571 297 3407",
    "sg:postcode":"22101",
    "sg:province":"VA",
    "sg:tags":[
        "key"
    ],
    "wof:name":"Locksmith & Locks-24 7 Emergency",
    "wof:placetype":"venue"
},
  "geometry": {"coordinates":[-77.226332,38.919122],"type":"Point"}
}