{
  "type": "Feature",
  "properties": {
    "addr:full":"1860 Stratford Park Pl Reston VA 20190",
    "addr:housenumber":"1860",
    "addr:postcode":"20190",
    "addr:street":"Stratford Park Pl",
    "iso:country":"US",
    "sg:address":"1860 Stratford Park Pl",
    "sg:city":"Reston",
    "sg:classifiers":[
        {
            "category":"Building & Trades",
            "subcategory":"Construction",
            "type":"Services"
        }
    ],
    "sg:phone":"+1 703 437 6100",
    "sg:postcode":"20190",
    "sg:province":"VA",
    "sg:tags":[
        "contractor"
    ],
    "wof:name":"Nova Tile",
    "wof:placetype":"venue"
},
  "geometry": {"coordinates":[-77.353264,38.958017],"type":"Point"}
}