{
  "type": "Feature",
  "properties": {
    "addr:full":"50 Featherbed Ln Winchester VA 22601",
    "addr:housenumber":"50",
    "addr:postcode":"22601",
    "addr:street":"Featherbed Ln",
    "iso:country":"US",
    "sg:address":"50 Featherbed Ln",
    "sg:city":"Winchester",
    "sg:classifiers":[
        {
            "category":"Restaurant",
            "type":"Food & Drink"
        }
    ],
    "sg:menulink":"http://www.allmenus.com/va/winchester/257299-red-hot-and-blue/menu/",
    "sg:phone":"+1 540 678 3000",
    "sg:postcode":"22601",
    "sg:province":"VA",
    "sg:tags":[
        "barbecue",
        "american"
    ],
    "wof:name":"Red Hot And Blue",
    "wof:placetype":"venue"
},
  "geometry": {"coordinates":[-78.170666,39.165272],"type":"Point"}
}