{
  "type": "Feature",
  "properties": {
    "addr:full":"1057 Paradise Rd Alton VA 24520",
    "addr:housenumber":"1057",
    "addr:postcode":"24520",
    "addr:street":"Paradise Rd",
    "iso:country":"US",
    "sg:address":"1057 Paradise Rd",
    "sg:city":"Alton",
    "sg:classifiers":[
        {
            "category":"Building & Trades",
            "subcategory":"Landscaping Services",
            "type":"Services"
        }
    ],
    "sg:phone":"+1 434 575 5616",
    "sg:postcode":"24520",
    "sg:province":"VA",
    "wof:name":"Talbott Tree Service",
    "wof:placetype":"venue"
},
  "geometry": {"coordinates":[-78.937001,36.604635],"type":"Point"}
}