{
  "type": "Feature",
  "properties": {
    "addr:full":"2606 Walmsley Blvd Richmond VA 23234",
    "addr:housenumber":"2606",
    "addr:postcode":"23234",
    "addr:street":"Walmsley Blvd",
    "iso:country":"US",
    "sg:address":"2606 Walmsley Blvd",
    "sg:city":"Richmond",
    "sg:classifiers":[
        {
            "category":"Retail",
            "subcategory":"Self-service Laundry",
            "type":"Services"
        }
    ],
    "sg:phone":"+1 804 271 7576",
    "sg:postcode":"23234",
    "sg:province":"VA",
    "sg:tags":[
        "coin"
    ],
    "wof:name":"Jefferson Cleaners & Laundry",
    "wof:placetype":"venue"
},
  "geometry": {"coordinates":[-77.44239899999999,37.460993],"type":"Point"}
}