{
  "type": "Feature",
  "properties": {
    "addr:full":"1803 S Meadow St Richmond VA 23220",
    "addr:housenumber":"1803",
    "addr:postcode":"23220",
    "addr:street":"S Meadow St",
    "iso:country":"US",
    "sg:address":"1803 S Meadow St",
    "sg:city":"Richmond",
    "sg:classifiers":[
        {
            "category":"Manufacturing",
            "subcategory":"Tools & Machinery",
            "type":"Manufacturing & Wholesale Goods"
        }
    ],
    "sg:phone":"+1 804 358 8701",
    "sg:postcode":"23220",
    "sg:province":"VA",
    "sg:tags":[
        "transformer",
        "mfg"
    ],
    "wof:name":"Straight Forward Accessories",
    "wof:placetype":"venue"
},
  "geometry": {"coordinates":[-77.473726,37.531899],"type":"Point"}
}