{
  "type": "Feature",
  "properties": {
    "addr:full":"4201 John Marr Dr Ste 211 Annandale VA 22003",
    "addr:housenumber":"4201",
    "addr:postcode":"22003",
    "addr:street":"John Marr Dr Ste 211",
    "iso:country":"US",
    "sg:address":"4201 John Marr Dr Ste 211",
    "sg:city":"Annandale",
    "sg:classifiers":[
        {
            "category":"Insurance",
            "subcategory":"Hazard Insurance",
            "type":"Services"
        }
    ],
    "sg:phone":"+1 703 941 0151",
    "sg:postcode":"22003",
    "sg:province":"VA",
    "sg:tags":[
        "commercial",
        "business"
    ],
    "wof:name":"Able Water Works",
    "wof:placetype":"venue"
},
  "geometry": {"coordinates":[-77.18974300000001,38.83297],"type":"Point"}
}