{
  "type": "Feature",
  "properties": {
    "addr:full":"156 Laurel Hill Rd Verona VA 24482",
    "addr:housenumber":"156",
    "addr:postcode":"24482",
    "addr:street":"Laurel Hill Rd",
    "iso:country":"US",
    "sg:address":"156 Laurel Hill Rd",
    "sg:city":"Verona",
    "sg:classifiers":[
        {
            "category":"Professional",
            "subcategory":"Engineering",
            "type":"Services"
        }
    ],
    "sg:phone":"+1 540 248 7407",
    "sg:postcode":"24482",
    "sg:province":"VA",
    "sg:tags":[
        "engineer"
    ],
    "wof:name":"B W Hamrick Engineering",
    "wof:placetype":"venue"
},
  "geometry": {"coordinates":[-79.00826499999999,38.202258],"type":"Point"}
}