{
  "type": "Feature",
  "properties": {
    "addr:full":"3045 Shore Dr Virginia Beach VA 23451",
    "addr:housenumber":"3045",
    "addr:postcode":"23451",
    "addr:street":"Shore Dr",
    "iso:country":"US",
    "sg:address":"3045 Shore Dr",
    "sg:city":"Virginia Beach",
    "sg:classifiers":[
        {
            "category":"Restaurant",
            "type":"Food & Drink"
        }
    ],
    "sg:phone":"+1 757 481 2718",
    "sg:postcode":"23451",
    "sg:province":"VA",
    "sg:tags":[
        "fast"
    ],
    "wof:name":"Famous Uncle Als Restaurant",
    "wof:placetype":"venue"
},
  "geometry": {"coordinates":[-76.078744,36.910302],"type":"Point"}
}