{
  "type": "Feature",
  "properties": {
    "iso:country":"US",
    "sg:address":"6623 Old Dominion Dr",
    "sg:city":"Mc Lean",
    "sg:classifiers":[
        {
            "category":"Building & Trades",
            "subcategory":"Construction",
            "type":"Services"
        }
    ],
    "sg:phone":"+1 703 734 9050",
    "sg:postcode":"22101",
    "sg:province":"VA",
    "sg:tags":[
        "house"
    ],
    "wof:name":"Bowa Builders Inc",
    "wof:placetype":"venue"
},
  "geometry": {"coordinates":[-77.16997499999999,38.929742],"type":"Point"}
}