{
  "type": "Feature",
  "properties": {
    "addr:full":"13512 Riverbelle Way Midlothian VA 23113",
    "addr:housenumber":"13512",
    "addr:postcode":"23113",
    "addr:street":"Riverbelle Way",
    "iso:country":"US",
    "sg:address":"13512 Riverbelle Way",
    "sg:city":"Midlothian",
    "sg:classifiers":[
        {
            "category":"Shopping",
            "subcategory":"Computers & Home Electronics",
            "type":"Retail Goods"
        }
    ],
    "sg:phone":"+1 804 794 9089",
    "sg:postcode":"23113",
    "sg:province":"VA",
    "wof:name":"Blaylock Enterprises",
    "wof:placetype":"venue"
},
  "geometry": {"coordinates":[-77.64502299999999,37.553988],"type":"Point"}
}