{
  "type": "Feature",
  "properties": {
    "iso:country":"US",
    "sg:address":"7609 Wildwood Ct",
    "sg:city":"Lorton",
    "sg:classifiers":[
        {
            "category":"Education",
            "subcategory":"Special Training",
            "type":"Public Place"
        }
    ],
    "sg:phone":"+1 703 550 3433",
    "sg:postcode":"22079",
    "sg:province":"VA",
    "wof:name":"Fiftee Carat Music Inc",
    "wof:placetype":"venue"
},
  "geometry": {"coordinates":[-77.20553700000001,38.707702],"type":"Point"}
}