{
  "type": "Feature",
  "properties": {
    "iso:country":"US",
    "sg:address":"2505 Kecoughtan Rd",
    "sg:city":"Hampton",
    "sg:classifiers":[
        {
            "category":"Personal",
            "subcategory":"Beauty Salon",
            "type":"Services"
        }
    ],
    "sg:phone":"+1 757 722 4032",
    "sg:postcode":"23661",
    "sg:province":"VA",
    "wof:name":"Sussex Total Beauty & Tanning",
    "wof:placetype":"venue"
},
  "geometry": {"coordinates":[-76.377275,37.003445],"type":"Point"}
}