{
  "type": "Feature",
  "properties": {
    "addr:full":"2202 Hollins Mill Rd Lynchburg VA 24503",
    "addr:housenumber":"2202",
    "addr:postcode":"24503",
    "addr:street":"Hollins Mill Rd",
    "iso:country":"US",
    "sg:address":"2202 Hollins Mill Rd",
    "sg:city":"Lynchburg",
    "sg:classifiers":[
        {
            "category":"Wholesale",
            "subcategory":"Machinery & Supplies",
            "type":"Manufacturing & Wholesale Goods"
        },
        {
            "category":"Building & Trades",
            "subcategory":"Construction",
            "type":"Services"
        }
    ],
    "sg:phone":"+1 434 846 7711",
    "sg:postcode":"24503",
    "sg:province":"VA",
    "sg:tags":[
        "equipment",
        "industrial",
        "elevator",
        "repair"
    ],
    "wof:name":"Otis Elevator Company",
    "wof:placetype":"venue"
},
  "geometry": {"coordinates":[-79.16457699999999,37.432365],"type":"Point"}
}