{
  "type": "Feature",
  "properties": {
    "addr:full":"2126 Butylo Rd Laneview VA 22504",
    "addr:housenumber":"2126",
    "addr:postcode":"22504",
    "addr:street":"Butylo Rd",
    "iso:country":"US",
    "sg:address":"2126 Butylo Rd",
    "sg:city":"Laneview",
    "sg:classifiers":[
        {
            "category":"Professional",
            "type":"Services"
        }
    ],
    "sg:phone":"+1 804 443 3588",
    "sg:postcode":"22504",
    "sg:province":"VA",
    "wof:name":"J Douglas Davis",
    "wof:placetype":"venue"
},
  "geometry": {"coordinates":[-76.688969,37.770922],"type":"Point"}
}