{
  "type": "Feature",
  "properties": {
    "addr:full":"22455 Davis Dr Sterling VA 20164",
    "addr:housenumber":"22455",
    "addr:postcode":"20164",
    "addr:street":"Davis Dr",
    "iso:country":"US",
    "sg:address":"22455 Davis Dr",
    "sg:city":"Sterling",
    "sg:classifiers":[
        {
            "category":"Building & Trades",
            "subcategory":"Construction",
            "type":"Services"
        }
    ],
    "sg:phone":"+1 703 868 7699",
    "sg:postcode":"20164",
    "sg:province":"VA",
    "sg:tags":[
        "contracting",
        "general"
    ],
    "wof:name":"Team Construction LLC",
    "wof:placetype":"venue"
},
  "geometry": {"coordinates":[-77.42506299999999,38.996912],"type":"Point"}
}