{
  "type": "Feature",
  "properties": {
    "addr:full":"9240 Hampton Hunt Dr Fairfax Station VA 22039",
    "addr:housenumber":"9240",
    "addr:postcode":"22039",
    "addr:street":"Hampton Hunt Dr",
    "iso:country":"US",
    "sg:address":"9240 Hampton Hunt Dr",
    "sg:city":"Fairfax Station",
    "sg:classifiers":[
        {
            "category":"Professional",
            "type":"Services"
        }
    ],
    "sg:phone":"+1 703 493 9116",
    "sg:postcode":"22039",
    "sg:province":"VA",
    "wof:name":"Pronan Inc",
    "wof:placetype":"venue"
},
  "geometry": {"coordinates":[-77.29266200000001,38.712699],"type":"Point"}
}