{
  "type": "Feature",
  "properties": {
    "addr:full":"8615 Sanford Dr Richmond VA 23228",
    "addr:housenumber":"8615",
    "addr:postcode":"23228",
    "addr:street":"Sanford Dr",
    "iso:country":"US",
    "sg:address":"8615 Sanford Dr",
    "sg:city":"Richmond",
    "sg:classifiers":[
        {
            "category":"Manufacturing",
            "subcategory":"Retail Goods",
            "type":"Manufacturing & Wholesale Goods"
        }
    ],
    "sg:phone":"+1 804 262 3914",
    "sg:postcode":"23228",
    "sg:province":"VA",
    "sg:tags":[
        "marking",
        "printing",
        "commercial",
        "devices",
        "mfg"
    ],
    "wof:name":"Screen Print City",
    "wof:placetype":"venue"
},
  "geometry": {"coordinates":[-77.502673,37.628136],"type":"Point"}
}