{
  "type": "Feature",
  "properties": {
    "addr:full":"311 Cameron St Alexandria VA 22314",
    "addr:housenumber":"311",
    "addr:postcode":"22314",
    "addr:street":"Cameron St",
    "iso:country":"US",
    "sg:address":"311 Cameron St",
    "sg:city":"Alexandria",
    "sg:classifiers":[
        {
            "category":"Shopping",
            "subcategory":"Florist",
            "type":"Retail Goods"
        }
    ],
    "sg:phone":"+1 703 548 3111",
    "sg:postcode":"22314",
    "sg:province":"VA",
    "wof:name":"Wisteria",
    "wof:placetype":"venue"
},
  "geometry": {"coordinates":[-77.043284,38.805833],"type":"Point"}
}