{
  "type": "Feature",
  "properties": {
    "iso:country":"US",
    "sg:address":"1 Bainbridge Ave",
    "sg:city":"Hampton",
    "sg:classifiers":[
        {
            "category":"Real Estate",
            "subcategory":"Real Estate Operator",
            "type":"Services"
        }
    ],
    "sg:phone":"+1 757 723 3111",
    "sg:postcode":"23663",
    "sg:province":"VA",
    "sg:tags":[
        "apartment"
    ],
    "wof:name":"John's Creek Apartments",
    "wof:placetype":"venue"
},
  "geometry": {"coordinates":[-76.324123,37.020519],"type":"Point"}
}