{
  "type": "Feature",
  "properties": {
    "addr:full":"42395 Ryan Rd Ste 112B Ashburn VA 20148",
    "addr:housenumber":"42395",
    "addr:postcode":"20148",
    "addr:street":"Ryan Rd Ste 112B",
    "iso:country":"US",
    "sg:address":"42395 Ryan Rd Ste 112B",
    "sg:city":"Ashburn",
    "sg:classifiers":[
        {
            "category":"Communications",
            "subcategory":"News Services",
            "type":"Services"
        },
        {
            "category":"Transit Center",
            "subcategory":"Freight",
            "type":"Transportation"
        },
        {
            "category":"Professional",
            "subcategory":"Business Services",
            "type":"Services"
        },
        {
            "category":"Professional",
            "subcategory":"Printing & Photocopies",
            "type":"Services"
        },
        {
            "category":"Government",
            "subcategory":"Post Office",
            "type":"Public Place"
        }
    ],
    "sg:phone":"+1 703 957 4545",
    "sg:postcode":"20148",
    "sg:province":"VA",
    "sg:tags":[
        "cargo",
        "fax",
        "transparency",
        "package",
        "color",
        "express",
        "duplicating",
        "shipping",
        "mailbox-rental",
        "air",
        "copying",
        "mail",
        "print",
        "notary",
        "receiving",
        "photographic"
    ],
    "sg:website":"http://www.upsstore.com",
    "wof:name":"The UPS Store",
    "wof:placetype":"venue"
},
  "geometry": {"coordinates":[-77.53682499999999,38.986718],"type":"Point"}
}