{
  "type": "Feature",
  "properties": {
    "addr:full":"8245 Crestridge Rd Fairfax Station VA 22039",
    "addr:housenumber":"8245",
    "addr:postcode":"22039",
    "addr:street":"Crestridge Rd",
    "iso:country":"US",
    "sg:address":"8245 Crestridge Rd",
    "sg:city":"Fairfax Station",
    "sg:classifiers":[
        {
            "category":"Restaurant",
            "type":"Food & Drink"
        }
    ],
    "sg:phone":"+1 703 503 9882",
    "sg:postcode":"22039",
    "sg:province":"VA",
    "sg:tags":[
        "marketing",
        "sales"
    ],
    "wof:name":"World Cuisine LLC",
    "wof:placetype":"venue"
},
  "geometry": {"coordinates":[-77.342569,38.731378],"type":"Point"}
}