{
  "type": "Feature",
  "properties": {
    "iso:country":"US",
    "sg:address":"724 S Lee St",
    "sg:city":"Alexandria",
    "sg:classifiers":[
        {
            "category":"Professional",
            "subcategory":"Management & Consulting",
            "type":"Services"
        }
    ],
    "sg:phone":"+1 703 837 8356",
    "sg:postcode":"22314",
    "sg:province":"VA",
    "sg:tags":[
        "business"
    ],
    "wof:name":"2000 Group Inc",
    "wof:placetype":"venue"
},
  "geometry": {"coordinates":[-77.043094,38.796592],"type":"Point"}
}