{
  "type": "Feature",
  "properties": {
    "iso:country":"US",
    "sg:address":"3753 Centerview Dr",
    "sg:city":"Chantilly",
    "sg:classifiers":[
        {
            "category":"Education",
            "subcategory":"School",
            "type":"Public Place"
        }
    ],
    "sg:phone":"+1 703 397 0555",
    "sg:postcode":"20151",
    "sg:province":"VA",
    "wof:name":"Chesterbrook Academy",
    "wof:placetype":"venue"
},
  "geometry": {"coordinates":[-77.42833,38.900828],"type":"Point"}
}