{
  "type": "Feature",
  "properties": {
    "iso:country":"US",
    "sg:address":"1100 Dryden Ln",
    "sg:city":"Charlottesville",
    "sg:classifiers":[
        {
            "category":"Real Estate",
            "subcategory":"Real Estate Agent",
            "type":"Services"
        }
    ],
    "sg:phone":"+1 434 296 9860",
    "sg:postcode":"22903",
    "sg:province":"VA",
    "sg:website":"www.ashcroftonline.com",
    "wof:name":"Brian W Chase Realtor",
    "wof:placetype":"venue"
},
  "geometry": {"coordinates":[-78.538431,38.051705],"type":"Point"}
}