{
  "type": "Feature",
  "properties": {
    "addr:full":"221 Bollingbrook St Petersburg VA 23803",
    "addr:housenumber":"221",
    "addr:postcode":"23803",
    "addr:street":"Bollingbrook St",
    "iso:country":"US",
    "sg:address":"221 Bollingbrook St",
    "sg:city":"Petersburg",
    "sg:classifiers":[
        {
            "category":"Freight",
            "type":"Transportation"
        }
    ],
    "sg:phone":"+1 804 733 8121",
    "sg:postcode":"23803",
    "sg:province":"VA",
    "sg:tags":[
        "moving",
        "mover",
        "storage",
        "household"
    ],
    "wof:name":"L A Sheffield Transfer & Stge",
    "wof:placetype":"venue"
},
  "geometry": {"coordinates":[-77.40029,37.232897],"type":"Point"}
}