{
  "type": "Feature",
  "properties": {
    "addr:full":"305 Destroyer Cove Stafford VA 22554",
    "addr:housenumber":"305",
    "addr:postcode":"22554",
    "addr:street":"Destroyer Cove",
    "iso:country":"US",
    "sg:address":"305 Destroyer Cove",
    "sg:city":"Stafford",
    "sg:classifiers":[
        {
            "category":"Professional",
            "type":"Services"
        }
    ],
    "sg:phone":"+1 540 720 0289",
    "sg:postcode":"22554",
    "sg:province":"VA",
    "wof:name":"William Muccullough",
    "wof:placetype":"venue"
},
  "geometry": {"coordinates":[-77.37308299999999,38.444999],"type":"Point"}
}