{
  "type": "Feature",
  "properties": {
    "addr:full":"1600 Anderson Rd Mc Lean VA 22102",
    "addr:housenumber":"1600",
    "addr:postcode":"22102",
    "addr:street":"Anderson Rd",
    "iso:country":"US",
    "sg:address":"1600 Anderson Rd",
    "sg:city":"Mc Lean",
    "sg:classifiers":[
        {
            "category":"Real Estate",
            "subcategory":"Real Estate Services",
            "type":"Services"
        }
    ],
    "sg:phone":"+1 301 625 6703",
    "sg:postcode":"22102",
    "sg:province":"VA",
    "sg:tags":[
        "management",
        "property"
    ],
    "wof:name":"West Farm Associates",
    "wof:placetype":"venue"
},
  "geometry": {"coordinates":[-77.204803,38.9259],"type":"Point"}
}