{
  "type": "Feature",
  "properties": {
    "iso:country":"US",
    "sg:address":"2028 Madrillon Springs Ct",
    "sg:city":"Vienna",
    "sg:classifiers":[
        {
            "category":"Professional",
            "subcategory":"Management & Consulting",
            "type":"Services"
        }
    ],
    "sg:phone":"+1 703 827 8631",
    "sg:postcode":"22182",
    "sg:province":"VA",
    "sg:tags":[
        "educational",
        "teacher"
    ],
    "wof:name":"Radmila Carmichael",
    "wof:placetype":"venue"
},
  "geometry": {"coordinates":[-77.226585,38.908578],"type":"Point"}
}