{
  "type": "Feature",
  "properties": {
    "iso:country":"US",
    "sg:address":"271 Hill Point Rd",
    "sg:city":"Richmond",
    "sg:classifiers":[
        {
            "category":"Wholesale",
            "subcategory":"Stationery",
            "type":"Manufacturing & Wholesale Goods"
        }
    ],
    "sg:phone":"+1 804 784 3620",
    "sg:postcode":"23238",
    "sg:province":"VA",
    "sg:tags":[
        "business",
        "form",
        "supply"
    ],
    "wof:name":"Safeguard Business Systems",
    "wof:placetype":"venue"
},
  "geometry": {"coordinates":[-77.63270199999999,37.578997],"type":"Point"}
}