{
  "type": "Feature",
  "properties": {
    "addr:full":"1501 Willis Rd Richmond VA 23237",
    "addr:housenumber":"1501",
    "addr:postcode":"23237",
    "addr:street":"Willis Rd",
    "iso:country":"US",
    "sg:address":"1501 Willis Rd",
    "sg:city":"Richmond",
    "sg:classifiers":[
        {
            "category":"Professional",
            "subcategory":"Accounting & Tax Preparation",
            "type":"Services"
        }
    ],
    "sg:phone":"+1 804 714 2500",
    "sg:postcode":"23237",
    "sg:province":"VA",
    "sg:tags":[
        "accountant"
    ],
    "wof:name":"D H Assoc",
    "wof:placetype":"venue"
},
  "geometry": {"coordinates":[-77.412081,37.403818],"type":"Point"}
}