{
  "type": "Feature",
  "properties": {
    "iso:country":"US",
    "sg:address":"646 S Antioch Rd",
    "sg:city":"Luray",
    "sg:classifiers":[
        {
            "category":"Farming",
            "subcategory":"Poultry Farm",
            "type":"Manufacturing & Wholesale Goods"
        }
    ],
    "sg:phone":"+1 540 743 3901",
    "sg:postcode":"22835",
    "sg:province":"VA",
    "sg:tags":[
        "chicken"
    ],
    "wof:name":"Cheryl Sours",
    "wof:placetype":"venue"
},
  "geometry": {"coordinates":[-78.429728,38.654335],"type":"Point"}
}