{
  "type": "Feature",
  "properties": {
    "addr:full":"4001 Old Halifax Rd South Boston NC 24592",
    "addr:housenumber":"4001",
    "addr:postcode":"24592",
    "addr:street":"Old Halifax Rd",
    "iso:country":"US",
    "sg:address":"4001 Old Halifax Rd",
    "sg:city":"South Boston",
    "sg:classifiers":[
        {
            "category":"Banks & Credit Unions",
            "subcategory":"Bank",
            "type":"Services"
        }
    ],
    "sg:phone":"+1 434 572 3496",
    "sg:postcode":"24592",
    "sg:province":"NC",
    "sg:tags":[
        "cashing",
        "personal",
        "check",
        "institution"
    ],
    "wof:name":"Advance America",
    "wof:placetype":"venue"
},
  "geometry": {"coordinates":[-78.91679000000001,36.73538],"type":"Point"}
}