{
  "type": "Feature",
  "properties": {
    "addr:full":"10705 Courthouse Rd Fredericksburg VA 22407",
    "addr:housenumber":"10705",
    "addr:postcode":"22407",
    "addr:street":"Courthouse Rd",
    "iso:country":"US",
    "sg:address":"10705 Courthouse Rd",
    "sg:city":"Fredericksburg",
    "sg:classifiers":[
        {
            "category":"Retail",
            "subcategory":"Funeral Services",
            "type":"Services"
        }
    ],
    "sg:phone":"+1 540 834 4035",
    "sg:postcode":"22407",
    "sg:province":"VA",
    "wof:name":"Sensible Alternatives",
    "wof:placetype":"venue"
},
  "geometry": {"coordinates":[-77.515214,38.246644],"type":"Point"}
}