{
  "type": "Feature",
  "properties": {
    "addr:full":"904 E Church St Martinsville VA 24112",
    "addr:housenumber":"904",
    "addr:postcode":"24112",
    "addr:street":"E Church St",
    "iso:country":"US",
    "sg:address":"904 E Church St",
    "sg:city":"Martinsville",
    "sg:classifiers":[
        {
            "category":"Autos & Motor Vehicles",
            "subcategory":"Auto Supplies",
            "type":"Retail Goods"
        }
    ],
    "sg:phone":"+1 276 638 7050",
    "sg:postcode":"24112",
    "sg:province":"VA",
    "sg:tags":[
        "tire"
    ],
    "wof:name":"Long Mile Tire",
    "wof:placetype":"venue"
},
  "geometry": {"coordinates":[-79.853308,36.692008],"type":"Point"}
}