{
  "type": "Feature",
  "properties": {
    "iso:country":"US",
    "sg:address":"2700 Goodes Bridge Rd",
    "sg:city":"Richmond",
    "sg:classifiers":[
        {
            "category":"Building & Trades",
            "subcategory":"Construction",
            "type":"Services"
        }
    ],
    "sg:phone":"+1 804 276 5555",
    "sg:postcode":"23224",
    "sg:province":"VA",
    "sg:tags":[
        "roofing",
        "contractor"
    ],
    "sg:website":"www.serviceroofing.com",
    "wof:name":"Whitley Service Roofing",
    "wof:placetype":"venue"
},
  "geometry": {"coordinates":[-77.52201100000001,37.469298],"type":"Point"}
}