{
  "type": "Feature",
  "properties": {
    "addr:full":"8428 Quarry Rd Manassas VA 20110",
    "addr:housenumber":"8428",
    "addr:postcode":"20110",
    "addr:street":"Quarry Rd",
    "iso:country":"US",
    "sg:address":"8428 Quarry Rd",
    "sg:city":"Manassas",
    "sg:classifiers":[
        {
            "category":"Building & Trades",
            "subcategory":"Electrical",
            "type":"Services"
        }
    ],
    "sg:phone":"+1 703 393 7525",
    "sg:postcode":"20110",
    "sg:province":"VA",
    "sg:tags":[
        "interior",
        "electrical",
        "renovation",
        "contractor"
    ],
    "wof:name":"Esco",
    "wof:placetype":"venue"
},
  "geometry": {"coordinates":[-77.45206899999999,38.755544],"type":"Point"}
}