{
  "type": "Feature",
  "properties": {
    "addr:full":"3508 Mountain Rd Haymarket VA 20169",
    "addr:housenumber":"3508",
    "addr:postcode":"20169",
    "addr:street":"Mountain Rd",
    "iso:country":"US",
    "sg:address":"3508 Mountain Rd",
    "sg:city":"Haymarket",
    "sg:classifiers":[
        {
            "category":"Professional",
            "subcategory":"Management & Consulting",
            "type":"Services"
        }
    ],
    "sg:phone":"+1 703 753 7013",
    "sg:postcode":"20169",
    "sg:province":"VA",
    "sg:tags":[
        "information",
        "technology"
    ],
    "wof:name":"Management Innovations Ltd",
    "wof:placetype":"venue"
},
  "geometry": {"coordinates":[-77.673929,38.881381],"type":"Point"}
}