{
  "type": "Feature",
  "properties": {
    "iso:country":"US",
    "sg:address":"10852 Warwick Blvd",
    "sg:city":"Newport News",
    "sg:classifiers":[
        {
            "category":"Shopping",
            "subcategory":"Florist",
            "type":"Retail Goods"
        }
    ],
    "sg:phone":"+1 757 591 0674",
    "sg:postcode":"23601",
    "sg:province":"VA",
    "sg:tags":[
        "antique",
        "novelty",
        "gift"
    ],
    "wof:name":"Celebrity Wholesale",
    "wof:placetype":"venue"
},
  "geometry": {"coordinates":[-76.46743499999999,37.037922],"type":"Point"}
}