{
  "type": "Feature",
  "properties": {
    "addr:full":"3816 Franklin Rd SW Roanoke VA 24014",
    "addr:housenumber":"3816",
    "addr:postcode":"24014",
    "addr:street":"Franklin Rd Sw",
    "iso:country":"US",
    "sg:address":"3816 Franklin Rd SW",
    "sg:city":"Roanoke",
    "sg:classifiers":[
        {
            "category":"Travel",
            "subcategory":"Hotels & Motels",
            "type":"Entertainment"
        }
    ],
    "sg:phone":"+1 540 989 4000",
    "sg:postcode":"24014",
    "sg:province":"VA",
    "wof:name":"Hampton Inn",
    "wof:placetype":"venue"
},
  "geometry": {"coordinates":[-79.971206,37.233632],"type":"Point"}
}