{
  "type": "Feature",
  "properties": {
    "addr:full":"517 Bryan Dr Vinton VA 24179",
    "addr:housenumber":"517",
    "addr:postcode":"24179",
    "addr:street":"Bryan Dr",
    "iso:country":"US",
    "sg:address":"517 Bryan Dr",
    "sg:city":"Vinton",
    "sg:classifiers":[
        {
            "category":"Building & Trades",
            "subcategory":"Construction",
            "type":"Services"
        }
    ],
    "sg:phone":"+1 540 345 2322",
    "sg:postcode":"24179",
    "sg:province":"VA",
    "sg:tags":[
        "house"
    ],
    "wof:name":"Tingler Construction & Imprvs",
    "wof:placetype":"venue"
},
  "geometry": {"coordinates":[-79.87776599999999,37.26908],"type":"Point"}
}