{
  "type": "Feature",
  "properties": {
    "iso:country":"US",
    "sg:address":"13940 Tall Timber Ct",
    "sg:city":"Gainesville",
    "sg:classifiers":[
        {
            "category":"Building & Trades",
            "subcategory":"Landscaping Services",
            "type":"Services"
        }
    ],
    "sg:phone":"+1 703 753 2125",
    "sg:postcode":"20155",
    "sg:province":"VA",
    "wof:name":"Nicks Lawn Service",
    "wof:placetype":"venue"
},
  "geometry": {"coordinates":[-77.603314,38.775507],"type":"Point"}
}