{
  "type": "Feature",
  "properties": {
    "addr:full":"15 Catoctin Cir SE Leesburg VA 20175",
    "addr:housenumber":"15",
    "addr:postcode":"20175",
    "addr:street":"Catoctin Cir Se",
    "iso:country":"US",
    "sg:address":"15 Catoctin Cir SE",
    "sg:city":"Leesburg",
    "sg:classifiers":[
        {
            "category":"Communications",
            "type":"Services"
        }
    ],
    "sg:phone":"+1 703 478 1110",
    "sg:postcode":"20175",
    "sg:province":"VA",
    "wof:name":"Communication Services Assoc",
    "wof:placetype":"venue"
},
  "geometry": {"coordinates":[-77.56686500000001,39.107182],"type":"Point"}
}