{
  "type": "Feature",
  "properties": {
    "addr:full":"10104 Scout Dr Fairfax VA 22030",
    "addr:housenumber":"10104",
    "addr:postcode":"22030",
    "addr:street":"Scout Dr",
    "iso:country":"US",
    "sg:address":"10104 Scout Dr",
    "sg:city":"Fairfax",
    "sg:classifiers":[
        {
            "category":"Communications",
            "type":"Services"
        },
        {
            "category":"Organizations",
            "subcategory":"Community Association",
            "type":"Services"
        }
    ],
    "sg:phone":"+1 703 352 2637",
    "sg:postcode":"22030",
    "sg:province":"VA",
    "wof:name":"E W Communications Inc",
    "wof:placetype":"venue"
},
  "geometry": {"coordinates":[-77.295934,38.867551],"type":"Point"}
}