{
  "type": "Feature",
  "properties": {
    "addr:full":"2121 N Culpeper St Arlington VA 22207",
    "addr:housenumber":"2121",
    "addr:postcode":"22207",
    "addr:street":"N Culpeper St",
    "iso:country":"US",
    "sg:address":"2121 N Culpeper St",
    "sg:city":"Arlington",
    "sg:classifiers":[
        {
            "category":"Social Services",
            "type":"Services"
        }
    ],
    "sg:phone":"+1 703 228 4839",
    "sg:postcode":"22207",
    "sg:province":"VA",
    "sg:tags":[
        "executive"
    ],
    "wof:name":"Arlington Co Senior Center",
    "wof:placetype":"venue"
},
  "geometry": {"coordinates":[-77.12721500000001,38.896222],"type":"Point"}
}