{
  "type": "Feature",
  "properties": {
    "addr:full":"1500 N Main St Blacksburg VA 24060",
    "addr:housenumber":"1500",
    "addr:postcode":"24060",
    "addr:street":"N Main St",
    "iso:country":"US",
    "sg:address":"1500 N Main St",
    "sg:city":"Blacksburg",
    "sg:classifiers":[
        {
            "category":"Insurance",
            "subcategory":"Insurance Agent",
            "type":"Services"
        }
    ],
    "sg:phone":"+1 540 953 2300",
    "sg:postcode":"24060",
    "sg:province":"VA",
    "wof:name":"State Farm Insurance",
    "wof:placetype":"venue"
},
  "geometry": {"coordinates":[-80.41248,37.249481],"type":"Point"}
}