{
  "type": "Feature",
  "properties": {
    "iso:country":"US",
    "sg:address":"3013 Milford Ln",
    "sg:city":"Virginia Beach",
    "sg:classifiers":[
        {
            "category":"Professional",
            "subcategory":"Business Services",
            "type":"Services"
        }
    ],
    "sg:phone":"+1 757 486 5814",
    "sg:postcode":"23452",
    "sg:province":"VA",
    "wof:name":"Jsm Group Inc",
    "wof:placetype":"venue"
},
  "geometry": {"coordinates":[-76.079376,36.848371],"type":"Point"}
}