{
  "type": "Feature",
  "properties": {
    "addr:full":"5405 Murdock Ct Virginia Beach VA 23464",
    "addr:housenumber":"5405",
    "addr:postcode":"23464",
    "addr:street":"Murdock Ct",
    "iso:country":"US",
    "sg:address":"5405 Murdock Ct",
    "sg:city":"Virginia Beach",
    "sg:classifiers":[
        {
            "category":"Building & Trades",
            "subcategory":"Electrical",
            "type":"Services"
        }
    ],
    "sg:phone":"+1 757 479 3333",
    "sg:postcode":"23464",
    "sg:province":"VA",
    "sg:tags":[
        "electrical",
        "contractor"
    ],
    "wof:name":"Kenneys Electric",
    "wof:placetype":"venue"
},
  "geometry": {"coordinates":[-76.176372,36.779967],"type":"Point"}
}