{
  "type": "Feature",
  "properties": {
    "addr:full":"12411 Chapel Rd Clifton VA 20124",
    "addr:housenumber":"12411",
    "addr:postcode":"20124",
    "addr:street":"Chapel Rd",
    "iso:country":"US",
    "sg:address":"12411 Chapel Rd",
    "sg:city":"Clifton",
    "sg:classifiers":[
        {
            "category":"Building & Trades",
            "subcategory":"Construction",
            "type":"Services"
        }
    ],
    "sg:phone":"+1 703 968 5877",
    "sg:postcode":"20124",
    "sg:province":"VA",
    "sg:tags":[
        "home",
        "general",
        "contractor"
    ],
    "wof:name":"Kuemmerle Steven W Development",
    "wof:placetype":"venue"
},
  "geometry": {"coordinates":[-77.372902,38.778894],"type":"Point"}
}