{
  "type": "Feature",
  "properties": {
    "addr:full":"1308 Meadow Lake Rd Virginia Beach VA 23454",
    "addr:housenumber":"1308",
    "addr:postcode":"23454",
    "addr:street":"Meadow Lake Rd",
    "iso:country":"US",
    "sg:address":"1308 Meadow Lake Rd",
    "sg:city":"Virginia Beach",
    "sg:classifiers":[
        {
            "category":"Real Estate",
            "subcategory":"Real Estate Agent",
            "type":"Services"
        }
    ],
    "sg:phone":"+1 757 481 1800",
    "sg:postcode":"23454",
    "sg:province":"VA",
    "sg:tags":[
        "inspection"
    ],
    "wof:name":"Gregory Termite Moisture & Pst",
    "wof:placetype":"venue"
},
  "geometry": {"coordinates":[-76.047303,36.873367],"type":"Point"}
}