{
  "type": "Feature",
  "properties": {
    "addr:full":"115 S Main St Bridgewater VA 22812",
    "addr:housenumber":"115",
    "addr:postcode":"22812",
    "addr:street":"S Main St",
    "iso:country":"US",
    "sg:address":"115 S Main St",
    "sg:city":"Bridgewater",
    "sg:classifiers":[
        {
            "category":"Real Estate",
            "subcategory":"Real Estate Operator",
            "type":"Services"
        }
    ],
    "sg:phone":"+1 540 828 6218",
    "sg:postcode":"22812",
    "sg:province":"VA",
    "sg:tags":[
        "property",
        "lessor"
    ],
    "wof:name":"Shadowlawn LLC",
    "wof:placetype":"venue"
},
  "geometry": {"coordinates":[-78.976904,38.382027],"type":"Point"}
}