{
  "type": "Feature",
  "properties": {
    "addr:full":"5623 Gasburg Rd Gasburg VA 23887",
    "addr:housenumber":"5623",
    "addr:postcode":"23887",
    "addr:street":"Gasburg Rd",
    "iso:country":"US",
    "sg:address":"5623 Gasburg Rd",
    "sg:city":"Gasburg",
    "sg:classifiers":[
        {
            "category":"Restaurant",
            "type":"Food & Drink"
        }
    ],
    "sg:phone":"+1 434 577 3179",
    "sg:postcode":"23887",
    "sg:province":"VA",
    "sg:tags":[
        "lounge"
    ],
    "wof:name":"Raven Rest Spt Bar & Lounge",
    "wof:placetype":"venue"
},
  "geometry": {"coordinates":[-77.871831,36.561414],"type":"Point"}
}