{
  "type": "Feature",
  "properties": {
    "iso:country":"US",
    "sg:address":"1810 Stafford Ave",
    "sg:city":"Fredericksburg",
    "sg:classifiers":[
        {
            "category":"Building & Trades",
            "subcategory":"Construction",
            "type":"Services"
        }
    ],
    "sg:phone":"+1 540 368 0480",
    "sg:postcode":"22401",
    "sg:province":"VA",
    "sg:tags":[
        "home",
        "builder"
    ],
    "wof:name":"Superior Settlement Svc LLC",
    "wof:placetype":"venue"
},
  "geometry": {"coordinates":[-77.481275,38.302271],"type":"Point"}
}