{
  "type": "Feature",
  "properties": {
    "iso:country":"US",
    "sg:address":"279 White St NE",
    "sg:city":"Abingdon",
    "sg:classifiers":[
        {
            "category":"Professional",
            "subcategory":"Research",
            "type":"Services"
        }
    ],
    "sg:phone":"+1 276 676 2702",
    "sg:postcode":"24210",
    "sg:province":"VA",
    "sg:tags":[
        "laboratory"
    ],
    "wof:name":"Tanner White Laboratory",
    "wof:placetype":"venue"
},
  "geometry": {"coordinates":[-81.966633,36.715659],"type":"Point"}
}