{
  "type": "Feature",
  "properties": {
    "iso:country":"US",
    "sg:address":"18259 Westinghouse Rd",
    "sg:city":"Abingdon",
    "sg:classifiers":[
        {
            "category":"Real Estate",
            "subcategory":"Real Estate Agent",
            "type":"Services"
        }
    ],
    "sg:phone":"+1 276 623 4300",
    "sg:postcode":"24210",
    "sg:province":"VA",
    "wof:name":"Paramont VA Realty",
    "wof:placetype":"venue"
},
  "geometry": {"coordinates":[-82.054479,36.683816],"type":"Point"}
}