{
  "type": "Feature",
  "properties": {
    "iso:country":"US",
    "sg:address":"8367 Fairystone Park Hwy",
    "sg:city":"Bassett",
    "sg:classifiers":[
        {
            "category":"Building & Trades",
            "subcategory":"Construction",
            "type":"Services"
        }
    ],
    "sg:phone":"+1 276 629 3075",
    "sg:postcode":"24055",
    "sg:province":"VA",
    "sg:tags":[
        "residential"
    ],
    "wof:name":"Washburn Contractors",
    "wof:placetype":"venue"
},
  "geometry": {"coordinates":[-80.065568,36.752692],"type":"Point"}
}