{
  "type": "Feature",
  "properties": {
    "iso:country":"US",
    "sg:address":"8806 Pear Tree Village Ct",
    "sg:city":"Alexandria",
    "sg:classifiers":[
        {
            "category":"Retail",
            "subcategory":"Laundry & Dry Cleaning",
            "type":"Services"
        }
    ],
    "sg:phone":"+1 703 360 7744",
    "sg:postcode":"22309",
    "sg:province":"VA",
    "sg:tags":[
        "cleaner",
        "drapery",
        "curtain"
    ],
    "sg:website":"http://www.classicleaners.com",
    "wof:name":"Classicleaners",
    "wof:placetype":"venue"
},
  "geometry": {"coordinates":[-77.12561700000001,38.72003],"type":"Point"}
}