{
  "type": "Feature",
  "properties": {
    "addr:full":"980 Creek Rd Emporia VA 23847",
    "addr:housenumber":"980",
    "addr:postcode":"23847",
    "addr:street":"Creek Rd",
    "iso:country":"US",
    "sg:address":"980 Creek Rd",
    "sg:city":"Emporia",
    "sg:classifiers":[
        {
            "category":"Government",
            "subcategory":"Office",
            "type":"Public Place"
        }
    ],
    "sg:phone":"+1 434 348 3379",
    "sg:postcode":"23847",
    "sg:province":"VA",
    "sg:tags":[
        "county",
        "program"
    ],
    "wof:name":"Greensville County Sanitary",
    "wof:placetype":"venue"
},
  "geometry": {"coordinates":[-77.449359,36.556325],"type":"Point"}
}