{
  "type": "Feature",
  "properties": {
    "addr:full":"6001 Wilkinson Rd Richmond VA 23227",
    "addr:housenumber":"6001",
    "addr:postcode":"23227",
    "addr:street":"Wilkinson Rd",
    "iso:country":"US",
    "sg:address":"6001 Wilkinson Rd",
    "sg:city":"Richmond",
    "sg:classifiers":[
        {
            "category":"Communications",
            "subcategory":"Radio Station",
            "type":"Services"
        }
    ],
    "sg:phone":"+1 804 264 1047",
    "sg:postcode":"23227",
    "sg:province":"VA",
    "sg:tags":[
        "broadcast"
    ],
    "wof:name":"W D Y L - FM",
    "wof:placetype":"venue"
},
  "geometry": {"coordinates":[-77.42567,37.619633],"type":"Point"}
}