{
  "type": "Feature",
  "properties": {
    "addr:full":"950 Avon Rd Afton VA 22920",
    "addr:housenumber":"950",
    "addr:postcode":"22920",
    "addr:street":"Avon Rd",
    "iso:country":"US",
    "sg:address":"950 Avon Rd",
    "sg:city":"Afton",
    "sg:classifiers":[
        {
            "category":"Travel",
            "subcategory":"Hotels & Motels",
            "type":"Entertainment"
        }
    ],
    "sg:phone":"+1 540 456 8300",
    "sg:postcode":"22920",
    "sg:province":"VA",
    "sg:tags":[
        "resort"
    ],
    "sg:website":"www.rentalsatwintergreen.com",
    "wof:name":"Resort Reservations-Wntrgrn",
    "wof:placetype":"venue"
},
  "geometry": {"coordinates":[-78.83382899999999,37.987599],"type":"Point"}
}