{
  "type": "Feature",
  "properties": {
    "addr:full":"9532 Flatwood Ln Catlett VA 20119",
    "addr:housenumber":"9532",
    "addr:postcode":"20119",
    "addr:street":"Flatwood Ln",
    "iso:country":"US",
    "sg:address":"9532 Flatwood Ln",
    "sg:city":"Catlett",
    "sg:classifiers":[
        {
            "category":"Retail",
            "subcategory":"Repair Shop",
            "type":"Services"
        }
    ],
    "sg:phone":"+1 703 304 7276",
    "sg:postcode":"20119",
    "sg:province":"VA",
    "sg:tags":[
        "equipment",
        "dental",
        "refinishing"
    ],
    "wof:name":"Earls Dental Repair Svc",
    "wof:placetype":"venue"
},
  "geometry": {"coordinates":[-77.62214299999999,38.638012],"type":"Point"}
}