{
  "type": "Feature",
  "properties": {
    "addr:full":"7865 Jordantown Rd Vinton VA 24179",
    "addr:housenumber":"7865",
    "addr:postcode":"24179",
    "addr:street":"Jordantown Rd",
    "iso:country":"US",
    "sg:address":"7865 Jordantown Rd",
    "sg:city":"Vinton",
    "sg:classifiers":[
        {
            "category":"Food & Beverages",
            "subcategory":"Groceries & Convenience Stores",
            "type":"Retail Goods"
        }
    ],
    "sg:phone":"+1 540 890 2619",
    "sg:postcode":"24179",
    "sg:province":"VA",
    "wof:name":"Getty Food Mart",
    "wof:placetype":"venue"
},
  "geometry": {"coordinates":[-79.792638,37.270338],"type":"Point"}
}