{
  "type": "Feature",
  "properties": {
    "iso:country":"US",
    "sg:address":"12000 Wyndham Lake Dr",
    "sg:city":"Glen Allen",
    "sg:classifiers":[
        {
            "category":"Professional",
            "subcategory":"Accounting & Tax Preparation",
            "type":"Services"
        }
    ],
    "sg:phone":"+1 804 360 4770",
    "sg:postcode":"23059",
    "sg:province":"VA",
    "sg:tags":[
        "accountant"
    ],
    "wof:name":"Michael R Anliker CPA PC",
    "wof:placetype":"venue"
},
  "geometry": {"coordinates":[-77.613017,37.691289],"type":"Point"}
}