{
  "type": "Feature",
  "properties": {
    "addr:full":"1976 Munden Point Rd Virginia Beach VA 23457",
    "addr:housenumber":"1976",
    "addr:postcode":"23457",
    "addr:street":"Munden Point Rd",
    "iso:country":"US",
    "sg:address":"1976 Munden Point Rd",
    "sg:city":"Virginia Beach",
    "sg:classifiers":[
        {
            "category":"Professional",
            "subcategory":"Computer Services",
            "type":"Services"
        }
    ],
    "sg:phone":"+1 757 426 6704",
    "sg:postcode":"23457",
    "sg:province":"VA",
    "sg:tags":[
        "research"
    ],
    "wof:name":"Sirius-Beta Corporation",
    "wof:placetype":"venue"
},
  "geometry": {"coordinates":[-76.02570299999999,36.578507],"type":"Point"}
}