{
  "type": "Feature",
  "properties": {
    "iso:country":"US",
    "sg:address":"2484 N Landing Rd",
    "sg:city":"Virginia Beach",
    "sg:classifiers":[
        {
            "category":"Restaurant",
            "type":"Food & Drink"
        }
    ],
    "sg:phone":"+1 757 563 2577",
    "sg:postcode":"23456",
    "sg:province":"VA",
    "sg:tags":[
        "eating",
        "banquet",
        "rooms"
    ],
    "sg:website":"www.peterssushi.com",
    "wof:name":"Peter's Sushi Cafe",
    "wof:placetype":"venue"
},
  "geometry": {"coordinates":[-76.058628,36.74872],"type":"Point"}
}