{
  "type": "Feature",
  "properties": {
    "iso:country":"US",
    "sg:address":"2007 W Broad St",
    "sg:city":"Richmond",
    "sg:classifiers":[
        {
            "category":"Insurance",
            "subcategory":"Insurance Agent",
            "type":"Services"
        }
    ],
    "sg:phone":"+1 804 359 2474",
    "sg:postcode":"23220",
    "sg:province":"VA",
    "wof:name":"N H Bradley Insurance Agency",
    "wof:placetype":"venue"
},
  "geometry": {"coordinates":[-77.462467,37.557736],"type":"Point"}
}