{
  "type": "Feature",
  "properties": {
    "addr:full":"1006 Emerald Dr Alexandria VA 22308",
    "addr:housenumber":"1006",
    "addr:postcode":"22308",
    "addr:street":"Emerald Dr",
    "iso:country":"US",
    "sg:address":"1006 Emerald Dr",
    "sg:city":"Alexandria",
    "sg:classifiers":[
        {
            "category":"Professional",
            "subcategory":"Business Services",
            "type":"Services"
        }
    ],
    "sg:phone":"+1 703 360 8507",
    "sg:postcode":"22308",
    "sg:province":"VA",
    "wof:name":"Innisbrook Wraps",
    "wof:placetype":"venue"
},
  "geometry": {"coordinates":[-77.050292,38.719738],"type":"Point"}
}