{
  "type": "Feature",
  "properties": {
    "iso:country":"US",
    "sg:address":"5501 Courtney Ave",
    "sg:city":"Alexandria",
    "sg:classifiers":[
        {
            "category":"Utilities",
            "subcategory":"Refuse",
            "type":"Services"
        }
    ],
    "sg:phone":"+1 703 370 8124",
    "sg:postcode":"22304",
    "sg:province":"VA",
    "sg:tags":[
        "lubricating",
        "system",
        "mfg"
    ],
    "wof:name":"U S Filter Recovery Services",
    "wof:placetype":"venue"
},
  "geometry": {"coordinates":[-77.13212,38.802389],"type":"Point"}
}