{
  "type": "Feature",
  "properties": {
    "iso:country":"US",
    "sg:address":"525 E Market St",
    "sg:city":"Leesburg",
    "sg:classifiers":[
        {
            "category":"Restaurant",
            "type":"Food & Drink"
        }
    ],
    "sg:phone":"+1 703 443 0488",
    "sg:postcode":"20176",
    "sg:province":"VA",
    "sg:tags":[
        "management"
    ],
    "wof:name":"New Kids Inc",
    "wof:placetype":"venue"
},
  "geometry": {"coordinates":[-77.553256,39.109212],"type":"Point"}
}