{
  "type": "Feature",
  "properties": {
    "iso:country":"US",
    "sg:address":"5915 Highdale Cir",
    "sg:city":"Alexandria",
    "sg:classifiers":[
        {
            "category":"Professional",
            "subcategory":"Business Services",
            "type":"Services"
        }
    ],
    "sg:phone":"+1 703 971 8354",
    "sg:postcode":"22310",
    "sg:province":"VA",
    "wof:name":"Msy Design",
    "wof:placetype":"venue"
},
  "geometry": {"coordinates":[-77.13850499999999,38.790165],"type":"Point"}
}