{
  "type": "Feature",
  "properties": {
    "iso:country":"US",
    "sg:address":"1412 Lockett Ridge Rd",
    "sg:city":"Midlothian",
    "sg:classifiers":[
        {
            "category":"Real Estate",
            "subcategory":"Real Estate Services",
            "type":"Services"
        },
        {
            "category":"Real Estate",
            "subcategory":"Real Estate Agent",
            "type":"Services"
        }
    ],
    "sg:phone":"+1 804 794 4003",
    "sg:postcode":"23114",
    "sg:province":"VA",
    "sg:tags":[
        "buyer",
        "broker"
    ],
    "wof:name":"Newkirk Anneg Real Estate",
    "wof:placetype":"venue"
},
  "geometry": {"coordinates":[-77.620699,37.47129],"type":"Point"}
}