{
  "type": "Feature",
  "properties": {
    "iso:country":"US",
    "sg:address":"211 Wilson Ave",
    "sg:city":"Blacksburg",
    "sg:classifiers":[
        {
            "category":"Recreation",
            "type":"Entertainment"
        }
    ],
    "sg:phone":"+1 540 552 6969",
    "sg:postcode":"24060",
    "sg:province":"VA",
    "wof:name":"Miller Off Main St Galleries",
    "wof:placetype":"venue"
},
  "geometry": {"coordinates":[-80.41358700000001,37.233078],"type":"Point"}
}