{
  "type": "Feature",
  "properties": {
    "addr:full":"6468 Lake Meadow Dr Burke VA 22015",
    "addr:housenumber":"6468",
    "addr:postcode":"22015",
    "addr:street":"Lake Meadow Dr",
    "iso:country":"US",
    "sg:address":"6468 Lake Meadow Dr",
    "sg:city":"Burke",
    "sg:classifiers":[
        {
            "category":"Professional",
            "subcategory":"Computer Services",
            "type":"Services"
        }
    ],
    "sg:phone":"+1 703 862 6200",
    "sg:postcode":"22015",
    "sg:province":"VA",
    "sg:tags":[
        "related"
    ],
    "wof:name":"Internet Applications Dev",
    "wof:placetype":"venue"
},
  "geometry": {"coordinates":[-77.29242600000001,38.777986],"type":"Point"}
}