{
  "type": "Feature",
  "properties": {
    "addr:full":"317 Church Ave SW Roanoke VA 24016",
    "addr:housenumber":"317",
    "addr:postcode":"24016",
    "addr:street":"Church Ave Sw",
    "iso:country":"US",
    "sg:address":"317 Church Ave SW",
    "sg:city":"Roanoke",
    "sg:classifiers":[
        {
            "category":"Health Services",
            "subcategory":"Hospital",
            "type":"Services"
        }
    ],
    "sg:phone":"+1 540 853 2946",
    "sg:postcode":"24016",
    "sg:province":"VA",
    "wof:name":"Prison Health Services",
    "wof:placetype":"venue"
},
  "geometry": {"coordinates":[-79.946568,37.27044],"type":"Point"}
}