{
  "type": "Feature",
  "properties": {
    "addr:full":"500 Cypress St Bristol VA 37620",
    "addr:housenumber":"500",
    "addr:postcode":"37620",
    "addr:street":"Cypress St",
    "iso:country":"US",
    "sg:address":"500 Cypress St",
    "sg:city":"Bristol",
    "sg:classifiers":[
        {
            "category":"Education",
            "subcategory":"School",
            "type":"Public Place"
        }
    ],
    "sg:phone":"+1 423 652 9280",
    "sg:postcode":"37620",
    "sg:province":"VA",
    "wof:name":"Fairmount Elementary School",
    "wof:placetype":"venue"
},
  "geometry": {"coordinates":[-82.16922099999999,36.587934],"type":"Point"}
}