{
  "type": "Feature",
  "properties": {
    "addr:full":"4333 Alta Vista Dr Fairfax VA 22030",
    "addr:housenumber":"4333",
    "addr:postcode":"22030",
    "addr:street":"Alta Vista Dr",
    "iso:country":"US",
    "sg:address":"4333 Alta Vista Dr",
    "sg:city":"Fairfax",
    "sg:classifiers":[
        {
            "category":"Building & Trades",
            "subcategory":"Construction",
            "type":"Services"
        }
    ],
    "sg:phone":"+1 703 273 7787",
    "sg:postcode":"22030",
    "sg:province":"VA",
    "sg:tags":[
        "house"
    ],
    "wof:name":"Ch Construction Co Inc",
    "wof:placetype":"venue"
},
  "geometry": {"coordinates":[-77.324,38.842082],"type":"Point"}
}