{
  "type": "Feature",
  "properties": {
    "addr:full":"151 W King St Strasburg VA 22657",
    "addr:housenumber":"151",
    "addr:postcode":"22657",
    "addr:street":"W King St",
    "iso:country":"US",
    "sg:address":"151 W King St",
    "sg:city":"Strasburg",
    "sg:classifiers":[
        {
            "category":"Recreation",
            "type":"Entertainment"
        }
    ],
    "sg:phone":"+1 540 465 5757",
    "sg:postcode":"22657",
    "sg:province":"VA",
    "wof:name":"Half Moon Beach Park Inc",
    "wof:placetype":"venue"
},
  "geometry": {"coordinates":[-78.362876,38.989439],"type":"Point"}
}