{
  "type": "Feature",
  "properties": {
    "addr:full":"1391 Ryland Dr Forest VA 24551",
    "addr:housenumber":"1391",
    "addr:postcode":"24551",
    "addr:street":"Ryland Dr",
    "iso:country":"US",
    "sg:address":"1391 Ryland Dr",
    "sg:city":"Forest",
    "sg:classifiers":[
        {
            "category":"Retail",
            "subcategory":"Repair Shop",
            "type":"Services"
        }
    ],
    "sg:phone":"+1 434 525 0564",
    "sg:postcode":"24551",
    "sg:province":"VA",
    "sg:tags":[
        "welding"
    ],
    "wof:name":"Brown Farm & Repair",
    "wof:placetype":"venue"
},
  "geometry": {"coordinates":[-79.293182,37.307318],"type":"Point"}
}