{
  "type": "Feature",
  "properties": {
    "iso:country":"US",
    "sg:address":"160 James Rd",
    "sg:city":"Danville",
    "sg:classifiers":[
        {
            "category":"Retail",
            "subcategory":"Auto Repair",
            "type":"Services"
        }
    ],
    "sg:phone":"+1 434 822 0744",
    "sg:postcode":"24541",
    "sg:province":"VA",
    "sg:tags":[
        "repairing",
        "automobile"
    ],
    "wof:name":"Butch's Auto Repair",
    "wof:placetype":"venue"
},
  "geometry": {"coordinates":[-79.46422,36.59884],"type":"Point"}
}