{
  "type": "Feature",
  "properties": {
    "addr:full":"508 Wenonah Ave Pearisburg VA 24134",
    "addr:housenumber":"508",
    "addr:postcode":"24134",
    "addr:street":"Wenonah Ave",
    "iso:country":"US",
    "sg:address":"508 Wenonah Ave",
    "sg:city":"Pearisburg",
    "sg:classifiers":[
        {
            "category":"Personal",
            "subcategory":"Beauty Salon",
            "type":"Services"
        }
    ],
    "sg:phone":"+1 540 921 1988",
    "sg:postcode":"24134",
    "sg:province":"VA",
    "wof:name":"Family Hair Salon & Gift Shop",
    "wof:placetype":"venue"
},
  "geometry": {"coordinates":[-80.73468200000001,37.326461],"type":"Point"}
}