{
  "type": "Feature",
  "properties": {
    "addr:full":"535 Landmark Rd Wirtz VA 24184",
    "addr:housenumber":"535",
    "addr:postcode":"24184",
    "addr:street":"Landmark Rd",
    "iso:country":"US",
    "sg:address":"535 Landmark Rd",
    "sg:city":"Wirtz",
    "sg:classifiers":[
        {
            "category":"Building & Trades",
            "subcategory":"Construction",
            "type":"Services"
        }
    ],
    "sg:phone":"+1 540 721 1977",
    "sg:postcode":"24184",
    "sg:province":"VA",
    "sg:tags":[
        "contractor",
        "mason"
    ],
    "wof:name":"Kc Mansory",
    "wof:placetype":"venue"
},
  "geometry": {"coordinates":[-79.831782,37.121871],"type":"Point"}
}