{
  "type": "Feature",
  "properties": {
    "addr:full":"6800 Industrial Rd Springfield VA 22151",
    "addr:housenumber":"6800",
    "addr:postcode":"22151",
    "addr:street":"Industrial Rd",
    "iso:country":"US",
    "sg:address":"6800 Industrial Rd",
    "sg:city":"Springfield",
    "sg:classifiers":[
        {
            "category":"Wholesale",
            "subcategory":"Machinery & Supplies",
            "type":"Manufacturing & Wholesale Goods"
        }
    ],
    "sg:phone":"+1 703 658 6400",
    "sg:postcode":"22151",
    "sg:province":"VA",
    "sg:tags":[
        "fire",
        "department",
        "equipment"
    ],
    "wof:name":"Solutions Safety Svc",
    "wof:placetype":"venue"
},
  "geometry": {"coordinates":[-77.179113,38.798598],"type":"Point"}
}