{
  "type": "Feature",
  "properties": {
    "addr:full":"272 Burnetts Way Suffolk VA 23434",
    "addr:housenumber":"272",
    "addr:postcode":"23434",
    "addr:street":"Burnetts Way",
    "iso:country":"US",
    "sg:address":"272 Burnetts Way",
    "sg:city":"Suffolk",
    "sg:classifiers":[
        {
            "category":"Professional",
            "subcategory":"Business Services",
            "type":"Services"
        }
    ],
    "sg:phone":"+1 757 934 3208",
    "sg:postcode":"23434",
    "sg:province":"VA",
    "wof:name":"AZ Sales & Rentals",
    "wof:placetype":"venue"
},
  "geometry": {"coordinates":[-76.582318,36.770025],"type":"Point"}
}