{
  "type": "Feature",
  "properties": {
    "addr:full":"2665 River Rd Virginia Beach VA 23454",
    "addr:housenumber":"2665",
    "addr:postcode":"23454",
    "addr:street":"River Rd",
    "iso:country":"US",
    "sg:address":"2665 River Rd",
    "sg:city":"Virginia Beach",
    "sg:classifiers":[
        {
            "category":"Professional",
            "subcategory":"Engineering",
            "type":"Services"
        }
    ],
    "sg:phone":"+1 757 481 7890",
    "sg:postcode":"23454",
    "sg:province":"VA",
    "wof:name":"Bridges Lewish H Jr",
    "wof:placetype":"venue"
},
  "geometry": {"coordinates":[-76.05797099999999,36.890418],"type":"Point"}
}