{
  "type": "Feature",
  "properties": {
    "addr:full":"810 Kempsville Rd Chesapeake VA 23320",
    "addr:housenumber":"810",
    "addr:postcode":"23320",
    "addr:street":"Kempsville Rd",
    "iso:country":"US",
    "sg:address":"810 Kempsville Rd",
    "sg:city":"Chesapeake",
    "sg:classifiers":[
        {
            "category":"Organizations",
            "subcategory":"Non-profit Organization",
            "type":"Services"
        }
    ],
    "sg:phone":"+1 757 495 8706",
    "sg:postcode":"23320",
    "sg:province":"VA",
    "wof:name":"Diversified Industrial Concept",
    "wof:placetype":"venue"
},
  "geometry": {"coordinates":[-76.212951,36.746444],"type":"Point"}
}