{
  "type": "Feature",
  "properties": {
    "iso:country":"US",
    "sg:address":"936 S Church St",
    "sg:city":"Smithfield",
    "sg:classifiers":[
        {
            "category":"Organizations",
            "subcategory":"Labor Organization",
            "type":"Services"
        }
    ],
    "sg:phone":"+1 757 357 4916",
    "sg:postcode":"23430",
    "sg:province":"VA",
    "wof:name":"Food Processors",
    "wof:placetype":"venue"
},
  "geometry": {"coordinates":[-76.61251799999999,36.978438],"type":"Point"}
}