{
  "type": "Feature",
  "properties": {
    "iso:country":"US",
    "sg:address":"215 S Jefferson St",
    "sg:city":"Roanoke",
    "sg:classifiers":[
        {
            "category":"Sports & Exercise",
            "subcategory":"Gym",
            "type":"Entertainment"
        }
    ],
    "sg:phone":"+1 540 224 5678",
    "sg:postcode":"24011",
    "sg:province":"VA",
    "sg:tags":[
        "club",
        "health",
        "studio",
        "gymnasium"
    ],
    "wof:name":"Zoom Fitness On The Go",
    "wof:placetype":"venue"
},
  "geometry": {"coordinates":[-79.94064299999999,37.271263],"type":"Point"}
}