{
  "type": "Feature",
  "properties": {
    "addr:full":"4194 Innslake Dr Glen Allen VA 23060",
    "addr:housenumber":"4194",
    "addr:postcode":"23060",
    "addr:street":"Innslake Dr",
    "iso:country":"US",
    "sg:address":"4194 Innslake Dr",
    "sg:city":"Glen Allen",
    "sg:classifiers":[
        {
            "category":"Professional",
            "subcategory":"Computer Services",
            "type":"Services"
        }
    ],
    "sg:phone":"+1 804 346 1200",
    "sg:postcode":"23060",
    "sg:province":"VA",
    "sg:tags":[
        "project",
        "presentation",
        "animation",
        "including",
        "modeling"
    ],
    "wof:name":"Cornerstone Imaging",
    "wof:placetype":"venue"
},
  "geometry": {"coordinates":[-77.579573,37.651292],"type":"Point"}
}