{
  "type": "Feature",
  "properties": {
    "addr:full":"470 George Dean Dr Charlottesville VA 22903",
    "addr:housenumber":"470",
    "addr:postcode":"22903",
    "addr:street":"George Dean Dr",
    "iso:country":"US",
    "sg:address":"470 George Dean Dr",
    "sg:city":"Charlottesville",
    "sg:classifiers":[
        {
            "category":"Manufacturing",
            "subcategory":"Lumber",
            "type":"Manufacturing & Wholesale Goods"
        }
    ],
    "sg:phone":"+1 434 977 5193",
    "sg:postcode":"22903",
    "sg:province":"VA",
    "sg:tags":[
        "government"
    ],
    "wof:name":"Forestry Dept",
    "wof:placetype":"venue"
},
  "geometry": {"coordinates":[-78.532939,38.025202],"type":"Point"}
}