{
  "type": "Feature",
  "properties": {
    "addr:full":"3175 Summit Square Dr Oakton VA 22124",
    "addr:housenumber":"3175",
    "addr:postcode":"22124",
    "addr:street":"Summit Square Dr",
    "iso:country":"US",
    "sg:address":"3175 Summit Square Dr",
    "sg:city":"Oakton",
    "sg:classifiers":[
        {
            "category":"Professional",
            "subcategory":"Business Services",
            "type":"Services"
        }
    ],
    "sg:phone":"+1 703 974 5438",
    "sg:postcode":"22124",
    "sg:province":"VA",
    "wof:name":"Verizon",
    "wof:placetype":"venue"
},
  "geometry": {"coordinates":[-77.299481,38.872172],"type":"Point"}
}