{
  "type": "Feature",
  "properties": {
    "iso:country":"US",
    "sg:address":"14328 Eastview Dr",
    "sg:city":"King George",
    "sg:classifiers":[
        {
            "category":"Utilities",
            "subcategory":"Refuse",
            "type":"Services"
        }
    ],
    "sg:phone":"+1 540 775 4888",
    "sg:postcode":"22485",
    "sg:province":"VA",
    "sg:tags":[
        "garbage",
        "collection"
    ],
    "wof:name":"King George Disposal",
    "wof:placetype":"venue"
},
  "geometry": {"coordinates":[-77.096317,38.219244],"type":"Point"}
}