{
  "type": "Feature",
  "properties": {
    "addr:full":"319 Brown St Petersburg VA 23803",
    "addr:housenumber":"319",
    "addr:postcode":"23803",
    "addr:street":"Brown St",
    "iso:country":"US",
    "sg:address":"319 Brown St",
    "sg:city":"Petersburg",
    "sg:classifiers":[
        {
            "category":"Professional",
            "type":"Services"
        }
    ],
    "sg:phone":"+1 804 733 4974",
    "sg:postcode":"23803",
    "sg:province":"VA",
    "sg:tags":[
        "establishment"
    ],
    "wof:name":"Precon Inc",
    "wof:placetype":"venue"
},
  "geometry": {"coordinates":[-77.406182,37.224214],"type":"Point"}
}