{
  "type": "Feature",
  "properties": {
    "addr:full":"1791 Cambridge Dr Richmond VA 23238",
    "addr:housenumber":"1791",
    "addr:postcode":"23238",
    "addr:street":"Cambridge Dr",
    "iso:country":"US",
    "sg:address":"1791 Cambridge Dr",
    "sg:city":"Richmond",
    "sg:classifiers":[
        {
            "category":"Organizations",
            "subcategory":"Religious Organization",
            "type":"Services"
        }
    ],
    "sg:phone":"+1 804 740 6551",
    "sg:postcode":"23238",
    "sg:province":"VA",
    "sg:tags":[
        "church"
    ],
    "sg:website":"www.hopechurchrichmond.org",
    "wof:name":"Hope Church",
    "wof:placetype":"venue"
},
  "geometry": {"coordinates":[-77.63473399999999,37.615259],"type":"Point"}
}