{
  "type": "Feature",
  "properties": {
    "iso:country":"US",
    "sg:address":"14368 Chastine Dr",
    "sg:city":"King George",
    "sg:classifiers":[
        {
            "category":"Recreation",
            "type":"Entertainment"
        }
    ],
    "sg:phone":"+1 540 785 1848",
    "sg:postcode":"22485",
    "sg:province":"VA",
    "sg:tags":[
        "animal"
    ],
    "wof:name":"Veleskiev Equestrian Center",
    "wof:placetype":"venue"
},
  "geometry": {"coordinates":[-77.099374,38.210712],"type":"Point"}
}