{
  "type": "Feature",
  "properties": {
    "addr:full":"913 S Main St Woodstock VA 22664",
    "addr:housenumber":"913",
    "addr:postcode":"22664",
    "addr:street":"S Main St",
    "iso:country":"US",
    "sg:address":"913 S Main St",
    "sg:city":"Woodstock",
    "sg:classifiers":[
        {
            "category":"Professional",
            "type":"Services"
        },
        {
            "category":"Deli",
            "type":"Food & Drink"
        },
        {
            "category":"Restaurant",
            "type":"Food & Drink"
        },
        {
            "category":"Fast Food",
            "type":"Food & Drink"
        }
    ],
    "sg:phone":"+1 540 459 3744",
    "sg:postcode":"22664",
    "sg:province":"VA",
    "sg:tags":[
        "house",
        "delicatessen",
        "take",
        "caterer",
        "barbecue",
        "steak"
    ],
    "sg:website":"http://www.shafferscatering.com",
    "wof:name":"Shaffer's",
    "wof:placetype":"venue"
},
  "geometry": {"coordinates":[-78.517211,38.867856],"type":"Point"}
}