{
  "type": "Feature",
  "properties": {
    "addr:full":"201 Moore Ave SE Vienna VA 22180",
    "addr:housenumber":"201",
    "addr:postcode":"22180",
    "addr:street":"Moore Ave Se",
    "iso:country":"US",
    "sg:address":"201 Moore Ave SE",
    "sg:city":"Vienna",
    "sg:classifiers":[
        {
            "category":"Building & Trades",
            "subcategory":"Construction",
            "type":"Services"
        }
    ],
    "sg:phone":"+1 703 242 1654",
    "sg:postcode":"22180",
    "sg:province":"VA",
    "sg:tags":[
        "house"
    ],
    "wof:name":"Oscars Improvement",
    "wof:placetype":"venue"
},
  "geometry": {"coordinates":[-77.25301399999999,38.898855],"type":"Point"}
}