{
  "type": "Feature",
  "properties": {
    "addr:full":"769 N Main St Emporia VA 23847",
    "addr:housenumber":"769",
    "addr:postcode":"23847",
    "addr:street":"N Main St",
    "iso:country":"US",
    "sg:address":"769 N Main St",
    "sg:city":"Emporia",
    "sg:classifiers":[
        {
            "category":"Restaurant",
            "type":"Food & Drink"
        }
    ],
    "sg:phone":"+1 434 348 8700",
    "sg:postcode":"23847",
    "sg:province":"VA",
    "wof:name":"Country Skillet",
    "wof:placetype":"venue"
},
  "geometry": {"coordinates":[-77.533507,36.708248],"type":"Point"}
}