{
  "type": "Feature",
  "properties": {
    "addr:full":"118 N Alfred St Alexandria VA 22314",
    "addr:housenumber":"118",
    "addr:postcode":"22314",
    "addr:street":"N Alfred St",
    "iso:country":"US",
    "sg:address":"118 N Alfred St",
    "sg:city":"Alexandria",
    "sg:classifiers":[
        {
            "category":"Professional",
            "subcategory":"Lawyer & Legal Services",
            "type":"Services"
        }
    ],
    "sg:phone":"+1 703 548 0110",
    "sg:postcode":"22314",
    "sg:province":"VA",
    "sg:tags":[
        "attorney",
        "practice"
    ],
    "wof:name":"A Able Alexandria Law Firm",
    "wof:placetype":"venue"
},
  "geometry": {"coordinates":[-77.049136,38.805568],"type":"Point"}
}