{
  "type": "Feature",
  "properties": {
    "iso:country":"US",
    "sg:address":"8036 Grandview Ct",
    "sg:city":"Springfield",
    "sg:classifiers":[
        {
            "category":"Building & Trades",
            "subcategory":"Construction",
            "type":"Services"
        }
    ],
    "sg:phone":"+1 703 690 0151",
    "sg:postcode":"22153",
    "sg:province":"VA",
    "sg:tags":[
        "hanging",
        "contractor"
    ],
    "wof:name":"Talys Painting Company",
    "wof:placetype":"venue"
},
  "geometry": {"coordinates":[-77.225497,38.732455],"type":"Point"}
}