{
  "type": "Feature",
  "properties": {
    "addr:full":"1317 Dasher Ln Reston VA 20190",
    "addr:housenumber":"1317",
    "addr:postcode":"20190",
    "addr:street":"Dasher Ln",
    "iso:country":"US",
    "sg:address":"1317 Dasher Ln",
    "sg:city":"Reston",
    "sg:classifiers":[
        {
            "category":"Banks & Credit Unions",
            "subcategory":"Financial Services",
            "type":"Services"
        }
    ],
    "sg:phone":"+1 703 759 4543",
    "sg:postcode":"20190",
    "sg:province":"VA",
    "sg:tags":[
        "investor"
    ],
    "wof:name":"Sca Investments LLC",
    "wof:placetype":"venue"
},
  "geometry": {"coordinates":[-77.317044,38.971166],"type":"Point"}
}