{
  "type": "Feature",
  "properties": {
    "iso:country":"US",
    "sg:address":"2981 S Military Hwy",
    "sg:city":"Chesapeake",
    "sg:classifiers":[
        {
            "category":"Shopping",
            "subcategory":"Used Merchandise",
            "type":"Retail Goods"
        },
        {
            "category":"Professional",
            "subcategory":"Business Services",
            "type":"Services"
        }
    ],
    "sg:phone":"+1 757 487 1583",
    "sg:postcode":"23323",
    "sg:province":"VA",
    "sg:tags":[
        "flea",
        "market"
    ],
    "wof:name":"Dave's Variety",
    "wof:placetype":"venue"
},
  "geometry": {"coordinates":[-76.32295999999999,36.772983],"type":"Point"}
}