{
  "type": "Feature",
  "properties": {
    "iso:country":"US",
    "sg:address":"2627 Westhaven Pl",
    "sg:city":"Lynchburg",
    "sg:classifiers":[
        {
            "category":"Organizations",
            "subcategory":"Religious Organization",
            "type":"Services"
        }
    ],
    "sg:phone":"+1 434 384 5433",
    "sg:postcode":"24501",
    "sg:province":"VA",
    "wof:name":"Word Missionary Church",
    "wof:placetype":"venue"
},
  "geometry": {"coordinates":[-79.198905,37.41471],"type":"Point"}
}