{
  "type": "Feature",
  "properties": {
    "addr:full":"200 Southgate Sq Colonial Heights VA 23834",
    "addr:housenumber":"200",
    "addr:postcode":"23834",
    "addr:street":"Southgate Sq",
    "iso:country":"US",
    "sg:address":"200 Southgate Sq",
    "sg:city":"Colonial Heights",
    "sg:classifiers":[
        {
            "category":"Restaurant",
            "type":"Food & Drink"
        }
    ],
    "sg:menulink":"http://www.allmenus.com/va/colonial-heights/285599-chinamens-buffet/menu/",
    "sg:phone":"+1 804 520 4280",
    "sg:postcode":"23834",
    "sg:province":"VA",
    "sg:tags":[
        "asian",
        "chinese"
    ],
    "wof:name":"Chinamen's Buffet",
    "wof:placetype":"venue"
},
  "geometry": {"coordinates":[-77.390832,37.248241],"type":"Point"}
}