{
  "type": "Feature",
  "properties": {
    "addr:full":"1336 N Great Neck Rd Virginia Beach VA 23454",
    "addr:housenumber":"1336",
    "addr:postcode":"23454",
    "addr:street":"N Great Neck Rd",
    "iso:country":"US",
    "sg:address":"1336 N Great Neck Rd",
    "sg:city":"Virginia Beach",
    "sg:classifiers":[
        {
            "category":"Restaurant",
            "type":"Food & Drink"
        }
    ],
    "sg:phone":"+1 757 412 4752",
    "sg:postcode":"23454",
    "sg:province":"VA",
    "wof:name":"Isla",
    "wof:placetype":"venue"
},
  "geometry": {"coordinates":[-76.03980199999999,36.87573],"type":"Point"}
}