{
  "type": "Feature",
  "properties": {
    "addr:full":"2644 Ringgold Depot Rd Sutherlin VA 24594",
    "addr:housenumber":"2644",
    "addr:postcode":"24594",
    "addr:street":"Ringgold Depot Rd",
    "iso:country":"US",
    "sg:address":"2644 Ringgold Depot Rd",
    "sg:city":"Sutherlin",
    "sg:classifiers":[
        {
            "category":"Professional",
            "type":"Services"
        }
    ],
    "sg:phone":"+1 434 822 7525",
    "sg:postcode":"24594",
    "sg:province":"VA",
    "wof:name":"John W Epps Jr",
    "wof:placetype":"venue"
},
  "geometry": {"coordinates":[-79.27417,36.593263],"type":"Point"}
}