{
  "type": "Feature",
  "properties": {
    "iso:country":"US",
    "sg:address":"10518 Acacia Ln",
    "sg:city":"Fairfax",
    "sg:classifiers":[
        {
            "category":"Professional",
            "subcategory":"Management & Consulting",
            "type":"Services"
        }
    ],
    "sg:phone":"+1 703 250 9760",
    "sg:postcode":"22032",
    "sg:province":"VA",
    "sg:tags":[
        "information",
        "technology",
        "telecommunication",
        "consultant"
    ],
    "wof:name":"Vision Networks Inc",
    "wof:placetype":"venue"
},
  "geometry": {"coordinates":[-77.310762,38.805927],"type":"Point"}
}