{
  "type": "Feature",
  "properties": {
    "addr:full":"28348 Eleys Ford Rd Richardsville VA 22736",
    "addr:postcode":"28348;22736",
    "addr:street":"Eleys Ford Rd",
    "iso:country":"US",
    "sg:address":"28348 Eleys Ford Rd",
    "sg:city":"Richardsville",
    "sg:classifiers":[
        {
            "category":"Organizations",
            "subcategory":"Religious Organization",
            "type":"Services"
        }
    ],
    "sg:phone":"+1 540 399 1248",
    "sg:postcode":"22736",
    "sg:province":"VA",
    "wof:name":"Oakland Baptist Church",
    "wof:placetype":"venue"
},
  "geometry": {"coordinates":[-77.740939,38.404415],"type":"Point"}
}