{
  "type": "Feature",
  "properties": {
    "addr:full":"1 S Armistead Ave Hampton VA 23669",
    "addr:housenumber":"1",
    "addr:postcode":"23669",
    "addr:street":"S Armistead Ave",
    "iso:country":"US",
    "sg:address":"1 S Armistead Ave",
    "sg:city":"Hampton",
    "sg:classifiers":[
        {
            "category":"Government",
            "subcategory":"Office",
            "type":"Public Place"
        }
    ],
    "sg:phone":"+1 757 727 1111",
    "sg:postcode":"23669",
    "sg:province":"VA",
    "sg:tags":[
        "village"
    ],
    "wof:name":"Hampton Redevelopment/Housing",
    "wof:placetype":"venue"
},
  "geometry": {"coordinates":[-76.34959000000001,37.025037],"type":"Point"}
}