{
  "type": "Feature",
  "properties": {
    "addr:full":"1202 Prince Edward St Fredericksburg VA 22401",
    "addr:housenumber":"1202",
    "addr:postcode":"22401",
    "addr:street":"Prince Edward St",
    "iso:country":"US",
    "sg:address":"1202 Prince Edward St",
    "sg:city":"Fredericksburg",
    "sg:classifiers":[
        {
            "category":"Real Estate",
            "subcategory":"Real Estate Agent",
            "type":"Services"
        }
    ],
    "sg:phone":"+1 540 373 4076",
    "sg:postcode":"22401",
    "sg:province":"VA",
    "wof:name":"Grenn Realty Inc",
    "wof:placetype":"venue"
},
  "geometry": {"coordinates":[-77.46460999999999,38.305331],"type":"Point"}
}