{
  "type": "Feature",
  "properties": {
    "addr:full":"3625 N Military Hwy Norfolk VA 23518",
    "addr:housenumber":"3625",
    "addr:postcode":"23518",
    "addr:street":"N Military Hwy",
    "iso:country":"US",
    "sg:address":"3625 N Military Hwy",
    "sg:city":"Norfolk",
    "sg:classifiers":[
        {
            "category":"Autos & Motor Vehicles",
            "subcategory":"Automobile Sales",
            "type":"Retail Goods"
        }
    ],
    "sg:phone":"+1 757 853 1600",
    "sg:postcode":"23518",
    "sg:province":"VA",
    "sg:tags":[
        "used"
    ],
    "wof:name":"South Beach Motors Inc",
    "wof:placetype":"venue"
},
  "geometry": {"coordinates":[-76.222786,36.893807],"type":"Point"}
}