{
  "type": "Feature",
  "properties": {
    "addr:full":"9602 Waterford Dr Manassas VA 20110",
    "addr:housenumber":"9602",
    "addr:postcode":"20110",
    "addr:street":"Waterford Dr",
    "iso:country":"US",
    "sg:address":"9602 Waterford Dr",
    "sg:city":"Manassas",
    "sg:classifiers":[
        {
            "category":"Building & Trades",
            "subcategory":"Construction",
            "type":"Services"
        }
    ],
    "sg:phone":"+1 703 365 0800",
    "sg:postcode":"20110",
    "sg:province":"VA",
    "sg:tags":[
        "house"
    ],
    "wof:name":"Master Builders and Home Imprv",
    "wof:placetype":"venue"
},
  "geometry": {"coordinates":[-77.48729400000001,38.733087],"type":"Point"}
}