{
  "type": "Feature",
  "properties": {
    "iso:country":"US",
    "sg:address":"17190 Kings Hwy",
    "sg:city":"Montross",
    "sg:classifiers":[
        {
            "category":"Professional",
            "subcategory":"Accounting & Tax Preparation",
            "type":"Services"
        }
    ],
    "sg:phone":"+1 804 493 9897",
    "sg:postcode":"22520",
    "sg:province":"VA",
    "sg:tags":[
        "accountant"
    ],
    "wof:name":"Alice Payne Accounting Tax Svc",
    "wof:placetype":"venue"
},
  "geometry": {"coordinates":[-76.804034,38.09363],"type":"Point"}
}