{
  "type": "Feature",
  "properties": {
    "addr:full":"3725 Acosta Rd Fairfax VA 22031",
    "addr:housenumber":"3725",
    "addr:postcode":"22031",
    "addr:street":"Acosta Rd",
    "iso:country":"US",
    "sg:address":"3725 Acosta Rd",
    "sg:city":"Fairfax",
    "sg:classifiers":[
        {
            "category":"Professional",
            "subcategory":"Management & Consulting",
            "type":"Services"
        }
    ],
    "sg:phone":"+1 703 591 8559",
    "sg:postcode":"22031",
    "sg:province":"VA",
    "sg:tags":[
        "business"
    ],
    "wof:name":"Boyd Consulting Services Inc",
    "wof:placetype":"venue"
},
  "geometry": {"coordinates":[-77.268253,38.846799],"type":"Point"}
}