{
  "type": "Feature",
  "properties": {
    "iso:country":"US",
    "sg:address":"25848 Natures Ln",
    "sg:city":"Chantilly",
    "sg:classifiers":[
        {
            "category":"Wholesale",
            "subcategory":"Books, Periodicals, & Newspapers",
            "type":"Manufacturing & Wholesale Goods"
        }
    ],
    "sg:phone":"+1 703 327 2132",
    "sg:postcode":"20152",
    "sg:province":"VA",
    "wof:name":"Mags4salecom",
    "wof:placetype":"venue"
},
  "geometry": {"coordinates":[-77.496831,38.901766],"type":"Point"}
}