{
  "type": "Feature",
  "properties": {
    "iso:country":"US",
    "sg:address":"3312 Fall Hill Ave",
    "sg:city":"Fredericksburg",
    "sg:classifiers":[
        {
            "category":"Health Services",
            "subcategory":"Doctor",
            "type":"Services"
        }
    ],
    "sg:phone":"+1 540 349 1028",
    "sg:postcode":"22401",
    "sg:province":"VA",
    "sg:tags":[
        "physician",
        "surgeon"
    ],
    "wof:name":"Plastic Surgery Svc-Frdrcksbrg",
    "wof:placetype":"venue"
},
  "geometry": {"coordinates":[-77.492256,38.31581],"type":"Point"}
}