{
  "type": "Feature",
  "properties": {
    "addr:full":"2020 Brambleton Ave SW Roanoke VA 24015",
    "addr:housenumber":"2020",
    "addr:postcode":"24015",
    "addr:street":"Brambleton Ave Sw",
    "iso:country":"US",
    "sg:address":"2020 Brambleton Ave SW",
    "sg:city":"Roanoke",
    "sg:classifiers":[
        {
            "category":"Professional",
            "subcategory":"Computer Services",
            "type":"Services"
        },
        {
            "category":"Shopping",
            "subcategory":"Computers & Home Electronics",
            "type":"Retail Goods"
        }
    ],
    "sg:phone":"+1 540 857 3055",
    "sg:postcode":"24015",
    "sg:province":"VA",
    "sg:tags":[
        "sales"
    ],
    "wof:name":"Computer Pros Inc",
    "wof:placetype":"venue"
},
  "geometry": {"coordinates":[-79.96861800000001,37.256676],"type":"Point"}
}