{
  "type": "Feature",
  "properties": {
    "addr:full":"2778 Washington Blvd Arlington VA 22201",
    "addr:housenumber":"2778",
    "addr:postcode":"22201",
    "addr:street":"Washington Blvd",
    "iso:country":"US",
    "sg:address":"2778 Washington Blvd",
    "sg:city":"Arlington",
    "sg:classifiers":[
        {
            "category":"Health Services",
            "subcategory":"Doctor",
            "type":"Services"
        }
    ],
    "sg:phone":"+1 703 469 2225",
    "sg:postcode":"22201",
    "sg:province":"VA",
    "sg:tags":[
        "orthopedist"
    ],
    "wof:name":"Spine Doctors",
    "wof:placetype":"venue"
},
  "geometry": {"coordinates":[-77.091296,38.881739],"type":"Point"}
}