{
  "type": "Feature",
  "properties": {
    "addr:full":"2400 Charles City Rd Richmond VA 23231",
    "addr:housenumber":"2400",
    "addr:postcode":"23231",
    "addr:street":"Charles City Rd",
    "iso:country":"US",
    "sg:address":"2400 Charles City Rd",
    "sg:city":"Richmond",
    "sg:classifiers":[
        {
            "category":"Professional",
            "subcategory":"Management & Consulting",
            "type":"Services"
        }
    ],
    "sg:phone":"+1 804 222 5100",
    "sg:postcode":"23231",
    "sg:province":"VA",
    "sg:tags":[
        "break",
        "coffee",
        "supply"
    ],
    "sg:website":"www.diamondsprings.com",
    "wof:name":"Diamond Springs",
    "wof:placetype":"venue"
},
  "geometry": {"coordinates":[-77.35392299999999,37.506032],"type":"Point"}
}