{
  "type": "Feature",
  "properties": {
    "iso:country":"US",
    "sg:address":"4313 Cary Street Rd",
    "sg:city":"Richmond",
    "sg:classifiers":[
        {
            "category":"Professional",
            "subcategory":"Business Services",
            "type":"Services"
        }
    ],
    "sg:phone":"+1 804 359 3100",
    "sg:postcode":"23221",
    "sg:province":"VA",
    "sg:tags":[
        "interior",
        "consultant",
        "design",
        "decorator"
    ],
    "wof:name":"Suellen Gregory Interior Dsgn",
    "wof:placetype":"venue"
},
  "geometry": {"coordinates":[-77.50013300000001,37.561345],"type":"Point"}
}