{
  "type": "Feature",
  "properties": {
    "addr:full":"5341 Woodbury Woods Pl Fairfax VA 22032",
    "addr:housenumber":"5341",
    "addr:postcode":"22032",
    "addr:street":"Woodbury Woods Pl",
    "iso:country":"US",
    "sg:address":"5341 Woodbury Woods Pl",
    "sg:city":"Fairfax",
    "sg:classifiers":[
        {
            "category":"Professional",
            "subcategory":"Employment Agencies",
            "type":"Services"
        }
    ],
    "sg:phone":"+1 703 764 2747",
    "sg:postcode":"22032",
    "sg:province":"VA",
    "sg:tags":[
        "laboratory",
        "assistant"
    ],
    "wof:name":"Brent Mueler",
    "wof:placetype":"venue"
},
  "geometry": {"coordinates":[-77.30754399999999,38.807994],"type":"Point"}
}