{
  "type": "Feature",
  "properties": {
    "addr:full":"2301 Willis Rd Richmond VA 23237",
    "addr:housenumber":"2301",
    "addr:postcode":"23237",
    "addr:street":"Willis Rd",
    "iso:country":"US",
    "sg:address":"2301 Willis Rd",
    "sg:city":"Richmond",
    "sg:classifiers":[
        {
            "category":"Travel",
            "subcategory":"Hotels & Motels",
            "type":"Entertainment"
        }
    ],
    "sg:phone":"+1 804 271 6081",
    "sg:postcode":"23237",
    "sg:province":"VA",
    "wof:name":"VIP Motor Inn",
    "wof:placetype":"venue"
},
  "geometry": {"coordinates":[-77.425084,37.401266],"type":"Point"}
}