{
  "type": "Feature",
  "properties": {
    "addr:full":"222 W 21st St Norfolk VA 23517",
    "addr:housenumber":"222",
    "addr:postcode":"23517",
    "addr:street":"W 21St St",
    "iso:country":"US",
    "sg:address":"222 W 21st St",
    "sg:city":"Norfolk",
    "sg:classifiers":[
        {
            "category":"Restaurant",
            "type":"Food & Drink"
        }
    ],
    "sg:phone":"+1 757 626 3232",
    "sg:postcode":"23517",
    "sg:province":"VA",
    "sg:tags":[
        "eating"
    ],
    "wof:name":"21st Street Deli",
    "wof:placetype":"venue"
},
  "geometry": {"coordinates":[-76.287988,36.868317],"type":"Point"}
}