{
  "type": "Feature",
  "properties": {
    "iso:country":"US",
    "sg:address":"7328 Auburn St",
    "sg:city":"Annandale",
    "sg:classifiers":[
        {
            "category":"Retail",
            "subcategory":"Laundry & Dry Cleaning",
            "type":"Services"
        }
    ],
    "sg:phone":"+1 703 256 9805",
    "sg:postcode":"22003",
    "sg:province":"VA",
    "sg:tags":[
        "rug",
        "carpet"
    ],
    "wof:name":"Custom Color Carpet Care",
    "wof:placetype":"venue"
},
  "geometry": {"coordinates":[-77.197345,38.820824],"type":"Point"}
}