{
  "type": "Feature",
  "properties": {
    "addr:full":"8397 Terminal Rd Lorton VA 22079",
    "addr:housenumber":"8397",
    "addr:postcode":"22079",
    "addr:street":"Terminal Rd",
    "iso:country":"US",
    "sg:address":"8397 Terminal Rd",
    "sg:city":"Lorton",
    "sg:classifiers":[
        {
            "category":"Wholesale",
            "subcategory":"Construction Materials",
            "type":"Manufacturing & Wholesale Goods"
        },
        {
            "category":"Home & Garden",
            "subcategory":"Building Materials",
            "type":"Retail Goods"
        }
    ],
    "sg:phone":"+1 703 550 0895",
    "sg:postcode":"22079",
    "sg:province":"VA",
    "sg:tags":[
        "siding"
    ],
    "wof:name":"Alside Supply Center",
    "wof:placetype":"venue"
},
  "geometry": {"coordinates":[-77.190308,38.734272],"type":"Point"}
}