{
  "type": "Feature",
  "properties": {
    "addr:full":"1920 Centerville Tpke Virginia Beach VA 23464",
    "addr:housenumber":"1920",
    "addr:postcode":"23464",
    "addr:street":"Centerville Tpke",
    "iso:country":"US",
    "sg:address":"1920 Centerville Tpke",
    "sg:city":"Virginia Beach",
    "sg:classifiers":[
        {
            "category":"Health Services",
            "subcategory":"Chiropractor",
            "type":"Services"
        }
    ],
    "sg:phone":"+1 757 479 0626",
    "sg:postcode":"23464",
    "sg:province":"VA",
    "wof:name":"Family Chiropractic Clinic",
    "wof:placetype":"venue"
},
  "geometry": {"coordinates":[-76.19210099999999,36.780359],"type":"Point"}
}