{
  "type": "Feature",
  "properties": {
    "addr:full":"4500 Progress Rd Norfolk VA 23502",
    "addr:housenumber":"4500",
    "addr:postcode":"23502",
    "addr:street":"Progress Rd",
    "iso:country":"US",
    "sg:address":"4500 Progress Rd",
    "sg:city":"Norfolk",
    "sg:classifiers":[
        {
            "category":"Wholesale",
            "subcategory":"Sporting Goods",
            "type":"Manufacturing & Wholesale Goods"
        }
    ],
    "sg:phone":"+1 757 858 2200",
    "sg:postcode":"23502",
    "sg:province":"VA",
    "sg:tags":[
        "equipment",
        "pool",
        "swimming"
    ],
    "wof:name":"Superior Pool Products",
    "wof:placetype":"venue"
},
  "geometry": {"coordinates":[-76.23153600000001,36.865516],"type":"Point"}
}