{
  "type": "Feature",
  "properties": {
    "addr:full":"1014 Bill Tuck Hwy South Boston VA 24592",
    "addr:housenumber":"1014",
    "addr:postcode":"24592",
    "addr:street":"Bill Tuck Hwy",
    "iso:country":"US",
    "sg:address":"1014 Bill Tuck Hwy",
    "sg:city":"South Boston",
    "sg:classifiers":[
        {
            "category":"Food & Beverages",
            "subcategory":"Groceries & Convenience Stores",
            "type":"Retail Goods"
        }
    ],
    "sg:phone":"+1 434 572 2277",
    "sg:postcode":"24592",
    "sg:province":"VA",
    "wof:name":"Zip Mart",
    "wof:placetype":"venue"
},
  "geometry": {"coordinates":[-78.897865,36.687616],"type":"Point"}
}