{
  "type": "Feature",
  "properties": {
    "iso:country":"US",
    "sg:address":"1800 N Veitch St",
    "sg:city":"Arlington",
    "sg:classifiers":[
        {
            "category":"Professional",
            "type":"Services"
        }
    ],
    "sg:phone":"+1 703 248 0900",
    "sg:postcode":"22201",
    "sg:province":"VA",
    "wof:name":"E-Clarity LLC",
    "wof:placetype":"venue"
},
  "geometry": {"coordinates":[-77.086389,38.895488],"type":"Point"}
}