{
  "type": "Feature",
  "properties": {
    "addr:full":"8060 Valley Pike Middletown VA 22645",
    "addr:housenumber":"8060",
    "addr:postcode":"22645",
    "addr:street":"Valley Pike",
    "iso:country":"US",
    "sg:address":"8060 Valley Pike",
    "sg:city":"Middletown",
    "sg:classifiers":[
        {
            "category":"Professional",
            "subcategory":"Accounting & Tax Preparation",
            "type":"Services"
        }
    ],
    "sg:phone":"+1 540 869 3955",
    "sg:postcode":"22645",
    "sg:province":"VA",
    "wof:name":"Professionally Yours",
    "wof:placetype":"venue"
},
  "geometry": {"coordinates":[-78.288087,39.021948],"type":"Point"}
}