{
  "type": "Feature",
  "properties": {
    "iso:country":"US",
    "sg:address":"9414 Cello Ct",
    "sg:city":"Vienna",
    "sg:classifiers":[
        {
            "category":"Professional",
            "type":"Services"
        }
    ],
    "sg:phone":"+1 703 281 4845",
    "sg:postcode":"22182",
    "sg:province":"VA",
    "wof:name":"Noel Firth",
    "wof:placetype":"venue"
},
  "geometry": {"coordinates":[-77.27240500000001,38.946905],"type":"Point"}
}