{
  "type": "Feature",
  "properties": {
    "addr:full":"11701 Harvestdale Dr Fredericksburg VA 22407",
    "addr:housenumber":"11701",
    "addr:postcode":"22407",
    "addr:street":"Harvestdale Dr",
    "iso:country":"US",
    "sg:address":"11701 Harvestdale Dr",
    "sg:city":"Fredericksburg",
    "sg:classifiers":[
        {
            "category":"Social Services",
            "type":"Services"
        }
    ],
    "sg:phone":"+1 540 786 6300",
    "sg:postcode":"22407",
    "sg:province":"VA",
    "sg:tags":[
        "counseling"
    ],
    "wof:name":"Elizabeth Healy Mack",
    "wof:placetype":"venue"
},
  "geometry": {"coordinates":[-77.587115,38.279092],"type":"Point"}
}