{
  "type": "Feature",
  "properties": {
    "addr:full":"5148 Leesburg Pike Alexandria VA 22302",
    "addr:housenumber":"5148",
    "addr:postcode":"22302",
    "addr:street":"Leesburg Pike",
    "iso:country":"US",
    "sg:address":"5148 Leesburg Pike",
    "sg:city":"Alexandria",
    "sg:classifiers":[
        {
            "category":"Personal",
            "type":"Services"
        }
    ],
    "sg:phone":"+1 703 575 8000",
    "sg:postcode":"22302",
    "sg:province":"VA",
    "wof:name":"Permanent Makeup Clinic",
    "wof:placetype":"venue"
},
  "geometry": {"coordinates":[-77.116838,38.845639],"type":"Point"}
}