{
  "type": "Feature",
  "properties": {
    "addr:full":"4115 Usher Ave Alexandria VA 22304",
    "addr:housenumber":"4115",
    "addr:postcode":"22304",
    "addr:street":"Usher Ave",
    "iso:country":"US",
    "sg:address":"4115 Usher Ave",
    "sg:city":"Alexandria",
    "sg:classifiers":[
        {
            "category":"Building & Trades",
            "subcategory":"Plumbing",
            "type":"Services"
        }
    ],
    "sg:phone":"+1 703 370 5780",
    "sg:postcode":"22304",
    "sg:province":"VA",
    "sg:tags":[
        "contractor"
    ],
    "wof:name":"Y B Leaky",
    "wof:placetype":"venue"
},
  "geometry": {"coordinates":[-77.102783,38.810432],"type":"Point"}
}