{
  "type": "Feature",
  "properties": {
    "addr:full":"4118 W Broad St Ste A Richmond VA 23230",
    "addr:housenumber":"4118",
    "addr:postcode":"23230",
    "addr:street":"W Broad St Ste A",
    "iso:country":"US",
    "sg:address":"4118 W Broad St Ste A",
    "sg:city":"Richmond",
    "sg:classifiers":[
        {
            "category":"Wholesale",
            "subcategory":"Office Equipment",
            "type":"Manufacturing & Wholesale Goods"
        },
        {
            "category":"Professional",
            "subcategory":"Accounting & Tax Preparation",
            "type":"Services"
        }
    ],
    "sg:phone":"+1 804 353 8388",
    "sg:postcode":"23230",
    "sg:province":"VA",
    "sg:tags":[
        "machine",
        "bookkeeping",
        "return",
        "supply"
    ],
    "sg:website":"http://www.thompsoninvestmenttaxservice.com/",
    "wof:name":"Thompson's Investment & Tax",
    "wof:placetype":"venue"
},
  "geometry": {"coordinates":[-77.48403399999999,37.573833],"type":"Point"}
}