{
  "type": "Feature",
  "properties": {
    "iso:country":"US",
    "sg:address":"2121 Oak Leaf Ct",
    "sg:city":"Powhatan",
    "sg:classifiers":[
        {
            "category":"Manufacturing",
            "subcategory":"Tools & Machinery",
            "type":"Manufacturing & Wholesale Goods"
        }
    ],
    "sg:phone":"+1 804 598 6833",
    "sg:postcode":"23139",
    "sg:province":"VA",
    "sg:tags":[
        "protection",
        "system",
        "power"
    ],
    "wof:name":"Critical & Emergency Power Sys",
    "wof:placetype":"venue"
},
  "geometry": {"coordinates":[-77.783103,37.53843],"type":"Point"}
}