{
  "type": "Feature",
  "properties": {
    "iso:country":"US",
    "sg:address":"222 W 21st St",
    "sg:city":"Norfolk",
    "sg:classifiers":[
        {
            "category":"Freight",
            "type":"Transportation"
        }
    ],
    "sg:phone":"+1 757 626 0065",
    "sg:postcode":"23517",
    "sg:province":"VA",
    "sg:tags":[
        "packaging",
        "shipping"
    ],
    "wof:name":"Pak Mail",
    "wof:placetype":"venue"
},
  "geometry": {"coordinates":[-76.287988,36.868317],"type":"Point"}
}