{
  "type": "Feature",
  "properties": {
    "addr:full":"4401 Crossings Blvd Hopewell VA 23875",
    "addr:housenumber":"4401",
    "addr:postcode":"23875",
    "addr:street":"Crossings Blvd",
    "iso:country":"US",
    "sg:address":"4401 Crossings Blvd",
    "sg:city":"Hopewell",
    "sg:classifiers":[
        {
            "category":"Government",
            "subcategory":"Office",
            "type":"Public Place"
        }
    ],
    "sg:phone":"+1 804 458 3450",
    "sg:postcode":"23875",
    "sg:province":"VA",
    "sg:tags":[
        "state",
        "program"
    ],
    "wof:name":"Motor Vehicle Dept",
    "wof:placetype":"venue"
},
  "geometry": {"coordinates":[-77.324564,37.256868],"type":"Point"}
}