{
  "type": "Feature",
  "properties": {
    "addr:full":"44110 Ashburn Village Blvd #184 Ashburn VA 20147",
    "addr:housenumber":"44110",
    "addr:postcode":"20147",
    "addr:street":"Ashburn Village Blvd # 184",
    "iso:country":"US",
    "sg:address":"44110 Ashburn Village Blvd #184",
    "sg:city":"Ashburn",
    "sg:classifiers":[
        {
            "category":"Shopping",
            "subcategory":"Hobbies, Toys, & Games",
            "type":"Retail Goods"
        },
        {
            "category":"Banks & Credit Unions",
            "subcategory":"Investment Brokerage",
            "type":"Services"
        },
        {
            "category":"Shopping",
            "type":"Retail Goods"
        },
        {
            "category":"Shopping",
            "subcategory":"Computers & Home Electronics",
            "type":"Retail Goods"
        }
    ],
    "sg:phone":"+1 703 729 7709",
    "sg:postcode":"20147",
    "sg:province":"VA",
    "sg:tags":[
        "games-wholesale",
        "dvd",
        "sale",
        "dvds-rental",
        "tape",
        "video",
        "supplies-wholesale",
        "merchandise",
        "manufacturer"
    ],
    "sg:website":"http://www.blockbuster.com",
    "wof:name":"Blockbuster",
    "wof:placetype":"venue"
},
  "geometry": {"coordinates":[-77.49321,39.011509],"type":"Point"}
}