{
  "type": "Feature",
  "properties": {
    "addr:full":"11232 Harbor Ct Reston VA 20191",
    "addr:housenumber":"11232",
    "addr:postcode":"20191",
    "addr:street":"Harbor Ct",
    "iso:country":"US",
    "sg:address":"11232 Harbor Ct",
    "sg:city":"Reston",
    "sg:classifiers":[
        {
            "category":"Building & Trades",
            "subcategory":"Construction",
            "type":"Services"
        }
    ],
    "sg:phone":"+1 703 391 9555",
    "sg:postcode":"20191",
    "sg:province":"VA",
    "sg:tags":[
        "hanging",
        "contractor"
    ],
    "wof:name":"Richard H Painter",
    "wof:placetype":"venue"
},
  "geometry": {"coordinates":[-77.33065999999999,38.937366],"type":"Point"}
}