{
  "type": "Feature",
  "properties": {
    "iso:country":"US",
    "sg:address":"111 Browns Ln",
    "sg:city":"Yorktown",
    "sg:classifiers":[
        {
            "category":"Organizations",
            "subcategory":"Religious Organization",
            "type":"Services"
        }
    ],
    "sg:phone":"+1 757 888 9622",
    "sg:postcode":"23690",
    "sg:province":"VA",
    "sg:tags":[
        "church"
    ],
    "wof:name":"Kingdom Hall Of Jehovah",
    "wof:placetype":"venue"
},
  "geometry": {"coordinates":[-76.557367,37.226467],"type":"Point"}
}