{
  "type": "Feature",
  "properties": {
    "iso:country":"US",
    "sg:address":"203 Douglas St",
    "sg:city":"Bristol",
    "sg:classifiers":[
        {
            "category":"Recreation",
            "subcategory":"Amusement Park",
            "type":"Entertainment"
        }
    ],
    "sg:phone":"+1 276 466 3027",
    "sg:postcode":"24201",
    "sg:province":"VA",
    "sg:tags":[
        "device"
    ],
    "wof:name":"Lark Amusement Inc",
    "wof:placetype":"venue"
},
  "geometry": {"coordinates":[-82.196969,36.597473],"type":"Point"}
}