{
  "type": "Feature",
  "properties": {
    "addr:full":"508 Division St Norlina VA 27563",
    "addr:housenumber":"508",
    "addr:postcode":"27563",
    "addr:street":"Division St",
    "iso:country":"US",
    "sg:address":"508 Division St",
    "sg:city":"Norlina",
    "sg:classifiers":[
        {
            "category":"Building & Trades",
            "subcategory":"Plumbing",
            "type":"Services"
        }
    ],
    "sg:phone":"+1 252 456 3398",
    "sg:postcode":"27563",
    "sg:province":"VA",
    "sg:tags":[
        "contractor"
    ],
    "wof:name":"Bolton Plumbing & Maintenance",
    "wof:placetype":"venue"
},
  "geometry": {"coordinates":[-78.192821,36.442049],"type":"Point"}
}