{
  "type": "Feature",
  "properties": {
    "iso:country":"US",
    "sg:address":"865 W 39th St",
    "sg:city":"Norfolk",
    "sg:classifiers":[
        {
            "category":"Manufacturing",
            "subcategory":"Metals",
            "type":"Manufacturing & Wholesale Goods"
        }
    ],
    "sg:phone":"+1 757 423 8600",
    "sg:postcode":"23508",
    "sg:province":"VA",
    "sg:tags":[
        "coating"
    ],
    "sg:website":"www.asconorfolk.com",
    "wof:name":"American Stripping Co",
    "wof:placetype":"venue"
},
  "geometry": {"coordinates":[-76.296031,36.880683],"type":"Point"}
}