{
  "type": "Feature",
  "properties": {
    "addr:full":"6494 Main St Middleburg VA 20198",
    "addr:housenumber":"6494",
    "addr:postcode":"20198",
    "addr:street":"Main St",
    "iso:country":"US",
    "sg:address":"6494 Main St",
    "sg:city":"Middleburg",
    "sg:classifiers":[
        {
            "category":"Banks & Credit Unions",
            "subcategory":"Investment Brokerage",
            "type":"Services"
        }
    ],
    "sg:phone":"+1 540 253 5955",
    "sg:postcode":"20198",
    "sg:province":"VA",
    "sg:tags":[
        "security"
    ],
    "wof:name":"Cambridge Asset Management",
    "wof:placetype":"venue"
},
  "geometry": {"coordinates":[-77.775929,38.862546],"type":"Point"}
}