{
  "type": "Feature",
  "properties": {
    "iso:country":"US",
    "sg:address":"3620 Oakland Rd",
    "sg:city":"Louisa",
    "sg:classifiers":[
        {
            "category":"Building & Trades",
            "subcategory":"Plumbing",
            "type":"Services"
        }
    ],
    "sg:phone":"+1 540 967 9564",
    "sg:postcode":"23093",
    "sg:province":"VA",
    "sg:tags":[
        "conditioning",
        "air",
        "system",
        "contractor"
    ],
    "wof:name":"Lloyd S Heating Cooling",
    "wof:placetype":"venue"
},
  "geometry": {"coordinates":[-78.03679200000001,38.088981],"type":"Point"}
}