{
  "type": "Feature",
  "properties": {
    "addr:full":"101 South St SE Leesburg VA 20175",
    "addr:housenumber":"101",
    "addr:postcode":"20175",
    "addr:street":"South St Se",
    "iso:country":"US",
    "sg:address":"101 South St SE",
    "sg:city":"Leesburg",
    "sg:classifiers":[
        {
            "category":"Professional",
            "subcategory":"Engineering",
            "type":"Services"
        }
    ],
    "sg:phone":"+1 703 443 2400",
    "sg:postcode":"20175",
    "sg:province":"VA",
    "sg:tags":[
        "civil",
        "engineer"
    ],
    "wof:name":"Bowman Consulting Group, Ltd.",
    "wof:placetype":"venue"
},
  "geometry": {"coordinates":[-77.564148,39.112492],"type":"Point"}
}