{
  "type": "Feature",
  "properties": {
    "iso:country":"US",
    "sg:address":"1000 Suburban Village Loop",
    "sg:city":"Richmond",
    "sg:classifiers":[
        {
            "category":"Real Estate",
            "subcategory":"Real Estate Operator",
            "type":"Services"
        }
    ],
    "sg:phone":"+1 804 272 0480",
    "sg:postcode":"23235",
    "sg:province":"VA",
    "sg:tags":[
        "mobile",
        "home",
        "community"
    ],
    "wof:name":"Suburban Mobile Village",
    "wof:placetype":"venue"
},
  "geometry": {"coordinates":[-77.57911300000001,37.506913],"type":"Point"}
}