{
  "type": "Feature",
  "properties": {
    "addr:full":"13131 Marcey Creek Rd Herndon VA 20171",
    "addr:housenumber":"13131",
    "addr:postcode":"20171",
    "addr:street":"Marcey Creek Rd",
    "iso:country":"US",
    "sg:address":"13131 Marcey Creek Rd",
    "sg:city":"Herndon",
    "sg:classifiers":[
        {
            "category":"Professional",
            "subcategory":"Computer Services",
            "type":"Services"
        }
    ],
    "sg:phone":"+1 703 481 0352",
    "sg:postcode":"20171",
    "sg:province":"VA",
    "sg:tags":[
        "consulting",
        "it",
        "solution"
    ],
    "wof:name":"Cytek",
    "wof:placetype":"venue"
},
  "geometry": {"coordinates":[-77.397964,38.947211],"type":"Point"}
}