{
  "type": "Feature",
  "properties": {
    "addr:full":"202 S Columbus St Alexandria VA 22314",
    "addr:housenumber":"202",
    "addr:postcode":"22314",
    "addr:street":"S Columbus St",
    "iso:country":"US",
    "sg:address":"202 S Columbus St",
    "sg:city":"Alexandria",
    "sg:classifiers":[
        {
            "category":"Retail",
            "subcategory":"Repair Shop",
            "type":"Services"
        },
        {
            "category":"Building & Trades",
            "subcategory":"Construction",
            "type":"Services"
        },
        {
            "category":"Building & Trades",
            "subcategory":"Electrical",
            "type":"Services"
        }
    ],
    "sg:phone":"+1 703 340 1949",
    "sg:postcode":"22314",
    "sg:province":"VA",
    "sg:tags":[
        "industrial",
        "electrician",
        "electric",
        "appliance",
        "specialty",
        "heating",
        "contractors-commercial",
        "maintenance",
        "small",
        "home",
        "contractor"
    ],
    "wof:name":"Murphy Family Electric",
    "wof:placetype":"venue"
},
  "geometry": {"coordinates":[-77.048345,38.804039],"type":"Point"}
}