{
  "type": "Feature",
  "properties": {
    "addr:full":"11130 Dennis W Kerns Pkwy King George VA 22485",
    "addr:housenumber":"11130",
    "addr:postcode":"22485",
    "addr:street":"Dennis W Kerns Pkwy",
    "iso:country":"US",
    "sg:address":"11130 Dennis W Kerns Pkwy",
    "sg:city":"King George",
    "sg:classifiers":[
        {
            "category":"Manufacturing",
            "subcategory":"Glass & Minerals",
            "type":"Manufacturing & Wholesale Goods"
        }
    ],
    "sg:phone":"+1 540 775 7801",
    "sg:postcode":"22485",
    "sg:province":"VA",
    "sg:tags":[
        "product",
        "mfg"
    ],
    "sg:website":"www.americanglassind.com",
    "wof:name":"American Glass Industries",
    "wof:placetype":"venue"
},
  "geometry": {"coordinates":[-77.301922,38.26296],"type":"Point"}
}