{
  "type": "Feature",
  "properties": {
    "addr:full":"11747 W Broad St Richmond VA 23233",
    "addr:housenumber":"11747",
    "addr:postcode":"23233",
    "addr:street":"W Broad St",
    "iso:country":"US",
    "sg:address":"11747 W Broad St",
    "sg:city":"Richmond",
    "sg:classifiers":[
        {
            "category":"Home & Garden",
            "subcategory":"Home Furnishings",
            "type":"Retail Goods"
        }
    ],
    "sg:phone":"+1 804 360 2283",
    "sg:postcode":"23233",
    "sg:province":"VA",
    "sg:tags":[
        "lighting",
        "fixture"
    ],
    "wof:name":"House Of Lighting Inc",
    "wof:placetype":"venue"
},
  "geometry": {"coordinates":[-77.61882900000001,37.652584],"type":"Point"}
}