{
  "type": "Feature",
  "properties": {
    "iso:country":"US",
    "sg:address":"14405 Richards Run Ln",
    "sg:city":"Purcellville",
    "sg:classifiers":[
        {
            "category":"Professional",
            "subcategory":"Computer Services",
            "type":"Services"
        }
    ],
    "sg:phone":"+1 540 668 6849",
    "sg:postcode":"20132",
    "sg:province":"VA",
    "sg:tags":[
        "technical",
        "assistance",
        "support"
    ],
    "sg:website":"http://www.bimmers.com",
    "wof:name":"Bimmers Co Inc",
    "wof:placetype":"venue"
},
  "geometry": {"coordinates":[-77.674938,39.218556],"type":"Point"}
}