{
  "type": "Feature",
  "properties": {
    "addr:full":"4552 Revere Dr Virginia Beach VA 23456",
    "addr:housenumber":"4552",
    "addr:postcode":"23456",
    "addr:street":"Revere Dr",
    "iso:country":"US",
    "sg:address":"4552 Revere Dr",
    "sg:city":"Virginia Beach",
    "sg:classifiers":[
        {
            "category":"Retail",
            "subcategory":"Auto Repair",
            "type":"Services"
        }
    ],
    "sg:phone":"+1 757 495 7666",
    "sg:postcode":"23456",
    "sg:province":"VA",
    "sg:tags":[
        "general"
    ],
    "wof:name":"Spiveys Automotive Service",
    "wof:placetype":"venue"
},
  "geometry": {"coordinates":[-76.14162,36.795026],"type":"Point"}
}