{
  "type": "Feature",
  "properties": {
    "addr:full":"4239 Leedstown Rd Colonial Beach VA 22443",
    "addr:housenumber":"4239",
    "addr:postcode":"22443",
    "addr:street":"Leedstown Rd",
    "iso:country":"US",
    "sg:address":"4239 Leedstown Rd",
    "sg:city":"Colonial Beach",
    "sg:classifiers":[
        {
            "category":"Building & Trades",
            "subcategory":"Landscaping Services",
            "type":"Services"
        }
    ],
    "sg:phone":"+1 804 214 9302",
    "sg:postcode":"22443",
    "sg:province":"VA",
    "wof:name":"C Tre Entertainment Inc",
    "wof:placetype":"venue"
},
  "geometry": {"coordinates":[-77.01586,38.132875],"type":"Point"}
}