{
  "type": "Feature",
  "properties": {
    "iso:country":"US",
    "sg:address":"6842 Elm St",
    "sg:city":"Mc Lean",
    "sg:classifiers":[
        {
            "category":"Banks & Credit Unions",
            "subcategory":"Investment Brokerage",
            "type":"Services"
        }
    ],
    "sg:phone":"+1 703 556 9060",
    "sg:postcode":"22101",
    "sg:province":"VA",
    "sg:tags":[
        "advisory",
        "financial"
    ],
    "wof:name":"Epiphany Advisors",
    "wof:placetype":"venue"
},
  "geometry": {"coordinates":[-77.179205,38.935516],"type":"Point"}
}