{
  "type": "Feature",
  "properties": {
    "iso:country":"US",
    "sg:address":"10420 Heather Greens Cir",
    "sg:city":"Spotsylvania",
    "sg:classifiers":[
        {
            "category":"Building & Trades",
            "subcategory":"Plumbing",
            "type":"Services"
        }
    ],
    "sg:phone":"+1 540 710 6934",
    "sg:postcode":"22553",
    "sg:province":"VA",
    "sg:tags":[
        "contractor"
    ],
    "wof:name":"Eddies Plumbing Company",
    "wof:placetype":"venue"
},
  "geometry": {"coordinates":[-77.554013,38.239687],"type":"Point"}
}