{
  "type": "Feature",
  "properties": {
    "addr:full":"305 Bluefish Ln Virginia Beach VA 23456",
    "addr:housenumber":"305",
    "addr:postcode":"23456",
    "addr:street":"Bluefish Ln",
    "iso:country":"US",
    "sg:address":"305 Bluefish Ln",
    "sg:city":"Virginia Beach",
    "sg:classifiers":[
        {
            "category":"Shopping",
            "subcategory":"Clothing, Apparel, & Fashions",
            "type":"Retail Goods"
        }
    ],
    "sg:phone":"+1 757 468 2885",
    "sg:postcode":"23456",
    "sg:province":"VA",
    "wof:name":"WEI Wig Corp",
    "wof:placetype":"venue"
},
  "geometry": {"coordinates":[-75.949552,36.752785],"type":"Point"}
}