{
  "type": "Feature",
  "properties": {
    "addr:full":"741 Wadsworth Dr Richmond VA 23236",
    "addr:housenumber":"741",
    "addr:postcode":"23236",
    "addr:street":"Wadsworth Dr",
    "iso:country":"US",
    "sg:address":"741 Wadsworth Dr",
    "sg:city":"Richmond",
    "sg:classifiers":[
        {
            "category":"Wholesale",
            "subcategory":"Vending Machines",
            "type":"Manufacturing & Wholesale Goods"
        }
    ],
    "sg:phone":"+1 804 330 0660",
    "sg:postcode":"23236",
    "sg:province":"VA",
    "wof:name":"All In One Vending",
    "wof:placetype":"venue"
},
  "geometry": {"coordinates":[-77.563478,37.487204],"type":"Point"}
}