{
  "type": "Feature",
  "properties": {
    "addr:full":"239 South St Front Royal VA 22630",
    "addr:housenumber":"239",
    "addr:postcode":"22630",
    "addr:street":"South St",
    "iso:country":"US",
    "sg:address":"239 South St",
    "sg:city":"Front Royal",
    "sg:classifiers":[
        {
            "category":"Social Services",
            "type":"Services"
        }
    ],
    "sg:phone":"+1 540 635 2333",
    "sg:postcode":"22630",
    "sg:province":"VA",
    "sg:tags":[
        "organization",
        "welfare"
    ],
    "wof:name":"American Red Cross",
    "wof:placetype":"venue"
},
  "geometry": {"coordinates":[-78.191247,38.911717],"type":"Point"}
}