{
  "type": "Feature",
  "properties": {
    "addr:full":"8041 Sherwood Crossing Pl 20 Apt 204 Mechanicsville VA 23111",
    "addr:housenumber":"8041;20",
    "addr:postcode":"23111",
    "addr:street":"Sherwood Crossing Pl;204",
    "iso:country":"US",
    "sg:address":"8041 Sherwood Crossing Pl 20 Apt 204",
    "sg:city":"Mechanicsville",
    "sg:classifiers":[
        {
            "category":"Professional",
            "subcategory":"Advertising",
            "type":"Services"
        }
    ],
    "sg:phone":"+1 804 247 1112",
    "sg:postcode":"23111",
    "sg:province":"VA",
    "sg:tags":[
        "promotion",
        "sale"
    ],
    "wof:name":"Laura Santee",
    "wof:placetype":"venue"
},
  "geometry": {"coordinates":[-77.344872,37.617015],"type":"Point"}
}