{
  "type": "Feature",
  "properties": {
    "iso:country":"US",
    "sg:address":"521 N Quincy St",
    "sg:city":"Arlington",
    "sg:classifiers":[
        {
            "category":"Health Services",
            "subcategory":"Clinic",
            "type":"Services"
        }
    ],
    "sg:phone":"+1 703 920 1440",
    "sg:postcode":"22203",
    "sg:province":"VA",
    "sg:tags":[
        "counseling",
        "mental"
    ],
    "sg:website":"www.vanguardservices.org/demeter...",
    "wof:name":"Demeter House",
    "wof:placetype":"venue"
},
  "geometry": {"coordinates":[-77.107651,38.876986],"type":"Point"}
}