{
  "type": "Feature",
  "properties": {
    "addr:full":"114 OAKGROVE RD. #102 Sterling VA 20166",
    "addr:housenumber":"114",
    "addr:postcode":"20166",
    "addr:street":"Oakgrove Rd. # 102",
    "iso:country":"US",
    "sg:address":"114 OAKGROVE RD. #102",
    "sg:city":"Sterling",
    "sg:classifiers":[
        {
            "category":"Professional",
            "subcategory":"Computer Services",
            "type":"Services"
        },
        {
            "category":"Internet Cafe",
            "subcategory":"None",
            "type":"Food & Drink"
        }
    ],
    "sg:phone":"+1 703 478 0880",
    "sg:postcode":"20166",
    "sg:province":"VA",
    "sg:tags":[
        "product",
        "software"
    ],
    "sg:website":"http://www.bikinikaratebabes.com",
    "wof:name":"Creative Edge Studios Inc",
    "wof:placetype":"venue"
},
  "geometry": {"coordinates":[-77.433273,38.9902],"type":"Point"}
}