{
  "type": "Feature",
  "properties": {
    "addr:full":"106 Mountain Ave SW Roanoke VA 24016",
    "addr:housenumber":"106",
    "addr:postcode":"24016",
    "addr:street":"Mountain Ave Sw",
    "iso:country":"US",
    "sg:address":"106 Mountain Ave SW",
    "sg:city":"Roanoke",
    "sg:classifiers":[
        {
            "category":"Professional",
            "subcategory":"Art Services",
            "type":"Services"
        }
    ],
    "sg:phone":"+1 540 343 7411",
    "sg:postcode":"24016",
    "sg:province":"VA",
    "sg:tags":[
        "commercial",
        "design"
    ],
    "wof:name":"Katie Wallace Design",
    "wof:placetype":"venue"
},
  "geometry": {"coordinates":[-79.943612,37.265725],"type":"Point"}
}