{
  "type": "Feature",
  "properties": {
    "addr:full":"301 Shenandoah St SE Leesburg VA 20175",
    "addr:housenumber":"301",
    "addr:postcode":"20175",
    "addr:street":"Shenandoah St Se",
    "iso:country":"US",
    "sg:address":"301 Shenandoah St SE",
    "sg:city":"Leesburg",
    "sg:classifiers":[
        {
            "category":"Organizations",
            "subcategory":"Membership Organization",
            "type":"Services"
        }
    ],
    "sg:phone":"+1 571 233 7603",
    "sg:postcode":"20175",
    "sg:province":"VA",
    "wof:name":"Rasofed Inc",
    "wof:placetype":"venue"
},
  "geometry": {"coordinates":[-77.560232,39.104338],"type":"Point"}
}