{
  "type": "Feature",
  "properties": {
    "addr:full":"2300 Westmoreland St Richmond VA 23230",
    "addr:housenumber":"2300",
    "addr:postcode":"23230",
    "addr:street":"Westmoreland St",
    "iso:country":"US",
    "sg:address":"2300 Westmoreland St",
    "sg:city":"Richmond",
    "sg:classifiers":[
        {
            "category":"Building & Trades",
            "subcategory":"Plumbing",
            "type":"Services"
        }
    ],
    "sg:phone":"+1 804 355 0651",
    "sg:postcode":"23230",
    "sg:province":"VA",
    "sg:tags":[
        "conditioning",
        "air",
        "system",
        "contractor"
    ],
    "wof:name":"Carrier Mid-Atlantic",
    "wof:placetype":"venue"
},
  "geometry": {"coordinates":[-77.486875,37.586878],"type":"Point"}
}