{
  "type": "Feature",
  "properties": {
    "addr:full":"6030 Corland Ct Mc Lean VA 22101",
    "addr:housenumber":"6030",
    "addr:postcode":"22101",
    "addr:street":"Corland Ct Mc Lean",
    "iso:country":"US",
    "sg:address":"6030 Corland Ct",
    "sg:city":"Mc Lean",
    "sg:classifiers":[
        {
            "category":"Professional",
            "subcategory":"Business Services",
            "type":"Services"
        }
    ],
    "sg:phone":"+1 703 533 3455",
    "sg:postcode":"22101",
    "sg:province":"VA",
    "wof:name":"Buttercup Enterprises LLC",
    "wof:placetype":"venue"
},
  "geometry": {"coordinates":[-77.143263,38.918906],"type":"Point"}
}