{
  "type": "Feature",
  "properties": {
    "iso:country":"US",
    "sg:address":"205 Taylor St",
    "sg:city":"Colonial Beach",
    "sg:classifiers":[
        {
            "category":"Restaurant",
            "type":"Food & Drink"
        }
    ],
    "sg:phone":"+1 804 224 8433",
    "sg:postcode":"22443",
    "sg:province":"VA",
    "wof:name":"High Tides On The Potomac",
    "wof:placetype":"venue"
},
  "geometry": {"coordinates":[-76.961837,38.252476],"type":"Point"}
}