{
  "type": "Feature",
  "properties": {
    "iso:country":"US",
    "sg:address":"1544 Laskin Rd",
    "sg:city":"Virginia Beach",
    "sg:classifiers":[
        {
            "category":"Shopping",
            "subcategory":"Shoes",
            "type":"Retail Goods"
        }
    ],
    "sg:phone":"+1 757 422 5220",
    "sg:postcode":"23451",
    "sg:province":"VA",
    "sg:website":"www.shoesforgirls.com",
    "wof:name":"Amy's-A Shoe Scene",
    "wof:placetype":"venue"
},
  "geometry": {"coordinates":[-76.01863299999999,36.851383],"type":"Point"}
}