{
  "type": "Feature",
  "properties": {
    "addr:full":"16 S King St Leesburg VA 20175",
    "addr:housenumber":"16",
    "addr:postcode":"20175",
    "addr:street":"S King St",
    "iso:country":"US",
    "sg:address":"16 S King St",
    "sg:city":"Leesburg",
    "sg:classifiers":[
        {
            "category":"Shopping",
            "subcategory":"Jewelry",
            "type":"Retail Goods"
        }
    ],
    "sg:phone":"+1 703 777 7805",
    "sg:postcode":"20175",
    "sg:province":"VA",
    "sg:tags":[
        "jeweler"
    ],
    "wof:name":"Mary Adams",
    "wof:placetype":"venue"
},
  "geometry": {"coordinates":[-77.56452899999999,39.115246],"type":"Point"}
}