{
  "type": "Feature",
  "properties": {
    "addr:full":"482 Bradley St SW Abingdon VA 24210",
    "addr:housenumber":"482",
    "addr:postcode":"24210",
    "addr:street":"Bradley St Sw",
    "iso:country":"US",
    "sg:address":"482 Bradley St SW",
    "sg:city":"Abingdon",
    "sg:classifiers":[
        {
            "category":"Social Services",
            "subcategory":"Adult Care",
            "type":"Services"
        }
    ],
    "sg:phone":"+1 276 628 7709",
    "sg:postcode":"24210",
    "sg:province":"VA",
    "sg:tags":[
        "residential"
    ],
    "wof:name":"Renaissance House",
    "wof:placetype":"venue"
},
  "geometry": {"coordinates":[-81.98683,36.703212],"type":"Point"}
}