{
  "type": "Feature",
  "properties": {
    "addr:full":"304 Farmingdale Ln Blacksburg VA 24060",
    "addr:housenumber":"304",
    "addr:postcode":"24060",
    "addr:street":"Farmingdale Ln",
    "iso:country":"US",
    "sg:address":"304 Farmingdale Ln",
    "sg:city":"Blacksburg",
    "sg:classifiers":[
        {
            "category":"Professional",
            "type":"Services"
        }
    ],
    "sg:phone":"+1 540 552 3789",
    "sg:postcode":"24060",
    "sg:province":"VA",
    "wof:name":"Jimmy L Shaver",
    "wof:placetype":"venue"
},
  "geometry": {"coordinates":[-80.421004,37.270591],"type":"Point"}
}