{
  "type": "Feature",
  "properties": {
    "addr:full":"5714 Little Falls Rd Arlington VA 22207",
    "addr:housenumber":"5714",
    "addr:postcode":"22207",
    "addr:street":"Little Falls Rd",
    "iso:country":"US",
    "sg:address":"5714 Little Falls Rd",
    "sg:city":"Arlington",
    "sg:classifiers":[
        {
            "category":"Banks & Credit Unions",
            "subcategory":"Investment Brokerage",
            "type":"Services"
        }
    ],
    "sg:phone":"+1 703 536 3100",
    "sg:postcode":"22207",
    "sg:province":"VA",
    "sg:tags":[
        "investing"
    ],
    "wof:name":"Robert P McCabe CFP",
    "wof:placetype":"venue"
},
  "geometry": {"coordinates":[-77.14702699999999,38.901876],"type":"Point"}
}