{
  "type": "Feature",
  "properties": {
    "addr:full":"1100 Jefferson St Lynchburg VA 24504",
    "addr:housenumber":"1100",
    "addr:postcode":"24504",
    "addr:street":"Jefferson St",
    "iso:country":"US",
    "sg:address":"1100 Jefferson St",
    "sg:city":"Lynchburg",
    "sg:classifiers":[
        {
            "category":"Building & Trades",
            "subcategory":"Equipment Rental",
            "type":"Services"
        }
    ],
    "sg:phone":"+1 434 846 1583",
    "sg:postcode":"24504",
    "sg:province":"VA",
    "sg:tags":[
        "camping"
    ],
    "wof:name":"Party Rentals Inc",
    "wof:placetype":"venue"
},
  "geometry": {"coordinates":[-79.13822999999999,37.413343],"type":"Point"}
}