{
  "type": "Feature",
  "properties": {
    "iso:country":"US",
    "sg:address":"8410 Staples Mill Rd",
    "sg:city":"Richmond",
    "sg:classifiers":[
        {
            "category":"Shopping",
            "subcategory":"Tobacco",
            "type":"Retail Goods"
        }
    ],
    "sg:phone":"+1 804 266 2200",
    "sg:postcode":"23228",
    "sg:province":"VA",
    "sg:tags":[
        "shop"
    ],
    "wof:name":"Cigarette Depot",
    "wof:placetype":"venue"
},
  "geometry": {"coordinates":[-77.50510199999999,37.626763],"type":"Point"}
}