{
  "type": "Feature",
  "properties": {
    "addr:full":"304 Turner Rd Richmond VA 23236",
    "addr:housenumber":"304",
    "addr:postcode":"23236",
    "addr:street":"Turner Rd",
    "iso:country":"US",
    "sg:address":"304 Turner Rd",
    "sg:city":"Richmond",
    "sg:classifiers":[
        {
            "category":"Social Services",
            "type":"Services"
        }
    ],
    "sg:phone":"+1 804 675 0316",
    "sg:postcode":"23236",
    "sg:province":"VA",
    "sg:tags":[
        "youth",
        "organization",
        "center"
    ],
    "wof:name":"Changing Fazes Youth & Family",
    "wof:placetype":"venue"
},
  "geometry": {"coordinates":[-77.53633499999999,37.496333],"type":"Point"}
}