{
  "type": "Feature",
  "properties": {
    "iso:country":"US",
    "sg:address":"24134 Stewart Town Ln",
    "sg:city":"Aldie",
    "sg:classifiers":[
        {
            "category":"Organizations",
            "subcategory":"Religious Organization",
            "type":"Services"
        }
    ],
    "sg:phone":"+1 703 327 6754",
    "sg:postcode":"20105",
    "sg:province":"VA",
    "sg:tags":[
        "clergy"
    ],
    "wof:name":"James M Stewart Rev",
    "wof:placetype":"venue"
},
  "geometry": {"coordinates":[-77.64972299999999,38.951262],"type":"Point"}
}