{
  "type": "Feature",
  "properties": {
    "iso:country":"US",
    "sg:address":"107 E Church St",
    "sg:city":"Martinsville",
    "sg:classifiers":[
        {
            "category":"Home & Garden",
            "subcategory":"Furniture",
            "type":"Retail Goods"
        }
    ],
    "sg:phone":"+1 276 632 2575",
    "sg:postcode":"24112",
    "sg:province":"VA",
    "wof:name":"Lane Furniture Outlet",
    "wof:placetype":"venue"
},
  "geometry": {"coordinates":[-79.871297,36.690578],"type":"Point"}
}