{
  "type": "Feature",
  "properties": {
    "iso:country":"US",
    "sg:address":"9113 Beachway Ln",
    "sg:city":"Springfield",
    "sg:classifiers":[
        {
            "category":"Autos & Motor Vehicles",
            "subcategory":"Fuel & Gas Station",
            "type":"Retail Goods"
        }
    ],
    "sg:phone":"+1 703 451 6229",
    "sg:postcode":"22153",
    "sg:province":"VA",
    "sg:tags":[
        "station",
        "gasoline"
    ],
    "wof:name":"Hillandale Exon",
    "wof:placetype":"venue"
},
  "geometry": {"coordinates":[-77.26090499999999,38.758513],"type":"Point"}
}