{
  "type": "Feature",
  "properties": {
    "addr:full":"3915 Sunnymeade Rd Rustburg VA 24588",
    "addr:housenumber":"3915",
    "addr:postcode":"24588",
    "addr:street":"Sunnymeade Rd",
    "iso:country":"US",
    "sg:address":"3915 Sunnymeade Rd",
    "sg:city":"Rustburg",
    "sg:classifiers":[
        {
            "category":"Professional",
            "subcategory":"Testing Lab",
            "type":"Services"
        },
        {
            "category":"Manufacturing",
            "subcategory":"Tools & Machinery",
            "type":"Manufacturing & Wholesale Goods"
        }
    ],
    "sg:phone":"+1 434 846 0244",
    "sg:postcode":"24588",
    "sg:province":"VA",
    "sg:tags":[
        "shock",
        "apparatus",
        "vibration"
    ],
    "wof:name":"Dynamic Testing Inc",
    "wof:placetype":"venue"
},
  "geometry": {"coordinates":[-79.120532,37.328333],"type":"Point"}
}