{
  "type": "Feature",
  "properties": {
    "addr:full":"6354 Blackbear Trl Mechanicsville VA 23116",
    "addr:postcode":"6354;23116",
    "addr:street":"Blackbear Trl",
    "iso:country":"US",
    "sg:address":"6354 Blackbear Trl",
    "sg:city":"Mechanicsville",
    "sg:classifiers":[
        {
            "category":"Building & Trades",
            "subcategory":"Construction",
            "type":"Services"
        }
    ],
    "sg:phone":"+1 804 746 2777",
    "sg:postcode":"23116",
    "sg:province":"VA",
    "sg:tags":[
        "house"
    ],
    "wof:name":"Sun Construction Inc",
    "wof:placetype":"venue"
},
  "geometry": {"coordinates":[-77.32275,37.695758],"type":"Point"}
}