{
  "type": "Feature",
  "properties": {
    "iso:country":"US",
    "sg:address":"8045 Jefferson Davis Hwy",
    "sg:city":"Richmond",
    "sg:classifiers":[
        {
            "category":"Retail",
            "subcategory":"Repair Shop",
            "type":"Services"
        }
    ],
    "sg:phone":"+1 804 743 8200",
    "sg:postcode":"23237",
    "sg:province":"VA",
    "sg:tags":[
        "boat",
        "supply"
    ],
    "wof:name":"Bruces Boat Supplies & Service",
    "wof:placetype":"venue"
},
  "geometry": {"coordinates":[-77.435896,37.415746],"type":"Point"}
}