{
  "type": "Feature",
  "properties": {
    "addr:full":"3690 King St Alexandria VA 22302",
    "addr:housenumber":"3690",
    "addr:postcode":"22302",
    "addr:street":"King St",
    "iso:country":"US",
    "sg:address":"3690 King St",
    "sg:city":"Alexandria",
    "sg:classifiers":[
        {
            "category":"Shopping",
            "subcategory":"Optical Goods",
            "type":"Retail Goods"
        },
        {
            "category":"Health Services",
            "subcategory":"Doctor",
            "type":"Services"
        }
    ],
    "sg:phone":"+1 410 265 6084",
    "sg:postcode":"22302",
    "sg:province":"VA",
    "sg:tags":[
        "medical",
        "optician",
        "eyewear"
    ],
    "wof:name":"United Optical",
    "wof:placetype":"venue"
},
  "geometry": {"coordinates":[-77.091797,38.830101],"type":"Point"}
}