{
  "type": "Feature",
  "properties": {
    "addr:full":"257 Ridge McIntire Rd Charlottesville VA 22903",
    "addr:housenumber":"257",
    "addr:postcode":"22903",
    "addr:street":"Ridge Mcintire Rd",
    "iso:country":"US",
    "sg:address":"257 Ridge McIntire Rd",
    "sg:city":"Charlottesville",
    "sg:classifiers":[
        {
            "category":"Banks & Credit Unions",
            "subcategory":"Bank",
            "type":"Services"
        }
    ],
    "sg:phone":"+1 434 296 2956",
    "sg:postcode":"22903",
    "sg:province":"VA",
    "sg:tags":[
        "personal",
        "commercial",
        "institution"
    ],
    "wof:name":"Pioneer Bank",
    "wof:placetype":"venue"
},
  "geometry": {"coordinates":[-78.485158,38.031736],"type":"Point"}
}