{
  "type": "Feature",
  "properties": {
    "iso:country":"US",
    "sg:address":"2232 Wakerobin Ln",
    "sg:city":"Reston",
    "sg:classifiers":[
        {
            "category":"Recreation",
            "type":"Entertainment"
        }
    ],
    "sg:phone":"+1 703 620 6480",
    "sg:postcode":"20191",
    "sg:province":"VA",
    "sg:tags":[
        "club",
        "membership"
    ],
    "wof:name":"Redbirds Girls Softball Club",
    "wof:placetype":"venue"
},
  "geometry": {"coordinates":[-77.336077,38.92928],"type":"Point"}
}