{
  "type": "Feature",
  "properties": {
    "iso:country":"US",
    "sg:address":"5739 Hull Street Rd",
    "sg:city":"Richmond",
    "sg:classifiers":[
        {
            "category":"Professional",
            "subcategory":"Accounting & Tax Preparation",
            "type":"Services"
        }
    ],
    "sg:phone":"+1 804 674 7475",
    "sg:postcode":"23224",
    "sg:province":"VA",
    "sg:tags":[
        "return",
        "filing"
    ],
    "wof:name":"Exito Inc",
    "wof:placetype":"venue"
},
  "geometry": {"coordinates":[-77.499878,37.484675],"type":"Point"}
}