{
  "type": "Feature",
  "properties": {
    "iso:country":"US",
    "sg:address":"147 Canterbury Run",
    "sg:city":"Newport News",
    "sg:classifiers":[
        {
            "category":"Wholesale",
            "subcategory":"Sporting Goods",
            "type":"Manufacturing & Wholesale Goods"
        }
    ],
    "sg:phone":"+1 757 877 8831",
    "sg:postcode":"23602",
    "sg:province":"VA",
    "sg:tags":[
        "lur",
        "fishing"
    ],
    "wof:name":"Performance Lures",
    "wof:placetype":"venue"
},
  "geometry": {"coordinates":[-76.542329,37.120497],"type":"Point"}
}