{
  "type": "Feature",
  "properties": {
    "addr:full":"2509 Pittston Rd Fredericksburg VA 22408",
    "addr:housenumber":"2509",
    "addr:postcode":"22408",
    "addr:street":"Pittston Rd",
    "iso:country":"US",
    "sg:address":"2509 Pittston Rd",
    "sg:city":"Fredericksburg",
    "sg:classifiers":[
        {
            "category":"Personal",
            "type":"Services"
        }
    ],
    "sg:phone":"+1 540 374 1611",
    "sg:postcode":"22408",
    "sg:province":"VA",
    "wof:name":"Stephen J Hodak",
    "wof:placetype":"venue"
},
  "geometry": {"coordinates":[-77.41678400000001,38.239624],"type":"Point"}
}