{
  "type": "Feature",
  "properties": {
    "iso:country":"US",
    "sg:address":"4135 Virginia Beach Blvd",
    "sg:city":"Virginia Beach",
    "sg:classifiers":[
        {
            "category":"Food & Beverages",
            "subcategory":"Bakery",
            "type":"Retail Goods"
        }
    ],
    "sg:phone":"+1 757 463 2253",
    "sg:postcode":"23452",
    "sg:province":"VA",
    "sg:tags":[
        "baker"
    ],
    "wof:name":"Custom Cake Shoppe Ltd",
    "wof:placetype":"venue"
},
  "geometry": {"coordinates":[-76.11661700000001,36.842513],"type":"Point"}
}