{
  "type": "Feature",
  "properties": {
    "addr:full":"6030 Woolridge Rd Moseley VA 23120",
    "addr:postcode":"6030;23120",
    "addr:street":"Woolridge Rd",
    "iso:country":"US",
    "sg:address":"6030 Woolridge Rd",
    "sg:city":"Moseley",
    "sg:classifiers":[
        {
            "category":"Manufacturing",
            "subcategory":"Tools & Machinery",
            "type":"Manufacturing & Wholesale Goods"
        }
    ],
    "sg:phone":"+1 804 739 0921",
    "sg:postcode":"23120",
    "sg:province":"VA",
    "sg:tags":[
        "speed",
        "mfg"
    ],
    "wof:name":"Textron Power Transmission",
    "wof:placetype":"venue"
},
  "geometry": {"coordinates":[-77.709962,37.41964],"type":"Point"}
}