{
  "type": "Feature",
  "properties": {
    "iso:country":"US",
    "sg:address":"2364 Great Neck Cir",
    "sg:city":"Virginia Beach",
    "sg:classifiers":[
        {
            "category":"Professional",
            "subcategory":"Business Services",
            "type":"Services"
        }
    ],
    "sg:phone":"+1 757 481 6655",
    "sg:postcode":"23454",
    "sg:province":"VA",
    "sg:tags":[
        "interior",
        "consultant",
        "design",
        "decorator"
    ],
    "wof:name":"Weirich Interior Design LLC",
    "wof:placetype":"venue"
},
  "geometry": {"coordinates":[-76.050071,36.880693],"type":"Point"}
}