{
  "type": "Feature",
  "properties": {
    "addr:full":"1383 Dow St Christiansburg VA 24073",
    "addr:housenumber":"1383",
    "addr:postcode":"24073",
    "addr:street":"Dow St",
    "iso:country":"US",
    "sg:address":"1383 Dow St",
    "sg:city":"Christiansburg",
    "sg:classifiers":[
        {
            "category":"Retail",
            "subcategory":"Laundry & Dry Cleaning",
            "type":"Services"
        }
    ],
    "sg:phone":"+1 540 382 2101",
    "sg:postcode":"24073",
    "sg:province":"VA",
    "sg:tags":[
        "drycleaning",
        "plant"
    ],
    "wof:name":"Pharis Cleaners",
    "wof:placetype":"venue"
},
  "geometry": {"coordinates":[-80.43499199999999,37.122336],"type":"Point"}
}