{
  "type": "Feature",
  "properties": {
    "addr:full":"3342 Melrose Ave NW Roanoke VA 24017",
    "addr:housenumber":"3342",
    "addr:postcode":"24017",
    "addr:street":"Melrose Ave Nw",
    "iso:country":"US",
    "sg:address":"3342 Melrose Ave NW",
    "sg:city":"Roanoke",
    "sg:classifiers":[
        {
            "category":"Shopping",
            "subcategory":"Catalog Store",
            "type":"Retail Goods"
        }
    ],
    "sg:phone":"+1 540 345 7640",
    "sg:postcode":"24017",
    "sg:province":"VA",
    "sg:tags":[
        "fulfill",
        "order"
    ],
    "wof:name":"Quality Fulfillment Services",
    "wof:placetype":"venue"
},
  "geometry": {"coordinates":[-79.99052399999999,37.291331],"type":"Point"}
}