{
  "type": "Feature",
  "properties": {
    "iso:country":"US",
    "sg:address":"4215 W Hundred Rd",
    "sg:city":"Chester",
    "sg:classifiers":[
        {
            "category":"Retail",
            "subcategory":"Auto Repair",
            "type":"Services"
        }
    ],
    "sg:phone":"+1 804 748 7405",
    "sg:postcode":"23831",
    "sg:province":"VA",
    "sg:tags":[
        "muffler",
        "exhaust",
        "system"
    ],
    "wof:name":"Chester Muffler & Brake Ctr",
    "wof:placetype":"venue"
},
  "geometry": {"coordinates":[-77.44354,37.357116],"type":"Point"}
}