{
  "type": "Feature",
  "properties": {
    "iso:country":"US",
    "sg:address":"200 E Cary St",
    "sg:city":"Richmond",
    "sg:classifiers":[
        {
            "category":"Professional",
            "subcategory":"Lawyer & Legal Services",
            "type":"Services"
        }
    ],
    "sg:phone":"+1 804 771 9680",
    "sg:postcode":"23219",
    "sg:province":"VA",
    "sg:tags":[
        "trust",
        "living",
        "planning",
        "probate",
        "estate"
    ],
    "wof:name":"Another Chance To Excel",
    "wof:placetype":"venue"
},
  "geometry": {"coordinates":[-77.44338999999999,37.54113],"type":"Point"}
}