{
  "type": "Feature",
  "properties": {
    "iso:country":"US",
    "sg:address":"146 Patrick St SE",
    "sg:city":"Vienna",
    "sg:classifiers":[
        {
            "category":"Building & Trades",
            "subcategory":"Construction",
            "type":"Services"
        }
    ],
    "sg:phone":"+1 703 573 6738",
    "sg:postcode":"22180",
    "sg:province":"VA",
    "sg:tags":[
        "house"
    ],
    "wof:name":"Jaad Construction Inc",
    "wof:placetype":"venue"
},
  "geometry": {"coordinates":[-77.24400300000001,38.888646],"type":"Point"}
}