{
  "type": "Feature",
  "properties": {
    "iso:country":"US",
    "sg:address":"169 Broadview Ave",
    "sg:city":"Warrenton",
    "sg:classifiers":[
        {
            "category":"Manufacturing",
            "subcategory":"Printing",
            "type":"Manufacturing & Wholesale Goods"
        }
    ],
    "sg:phone":"+1 540 341 4277",
    "sg:postcode":"20186",
    "sg:province":"VA",
    "sg:tags":[
        "printer"
    ],
    "wof:name":"TCG Printing & Mailing",
    "wof:placetype":"venue"
},
  "geometry": {"coordinates":[-77.806826,38.719774],"type":"Point"}
}