{
  "type": "Feature",
  "properties": {
    "iso:country":"US",
    "sg:address":"5510 Cherokee Ave",
    "sg:city":"Alexandria",
    "sg:classifiers":[
        {
            "category":"Real Estate",
            "subcategory":"Architect",
            "type":"Services"
        }
    ],
    "sg:phone":"+1 703 256 3344",
    "sg:postcode":"22312",
    "sg:province":"VA",
    "sg:tags":[
        "architectural"
    ],
    "wof:name":"Clark Nexsen",
    "wof:placetype":"venue"
},
  "geometry": {"coordinates":[-77.165696,38.804136],"type":"Point"}
}