{
  "type": "Feature",
  "properties": {
    "addr:full":"26460 Smiths Ferry Rd Franklin VA 23851",
    "addr:postcode":"26460;23851",
    "addr:street":"Smiths Ferry Rd",
    "iso:country":"US",
    "sg:address":"26460 Smiths Ferry Rd",
    "sg:city":"Franklin",
    "sg:classifiers":[
        {
            "category":"Professional",
            "type":"Services"
        }
    ],
    "sg:phone":"+1 757 562 7033",
    "sg:postcode":"23851",
    "sg:province":"VA",
    "sg:tags":[
        "establishment"
    ],
    "wof:name":"Mosena Enterprises Inc",
    "wof:placetype":"venue"
},
  "geometry": {"coordinates":[-76.94734,36.655791],"type":"Point"}
}