{
  "type": "Feature",
  "properties": {
    "iso:country":"US",
    "sg:address":"828 Main St",
    "sg:city":"Lynchburg",
    "sg:classifiers":[
        {
            "category":"Organizations",
            "subcategory":"Religious Organization",
            "type":"Services"
        }
    ],
    "sg:phone":"+1 434 847 7888",
    "sg:postcode":"24504",
    "sg:province":"VA",
    "sg:tags":[
        "church"
    ],
    "wof:name":"Charles Billingsley Concert",
    "wof:placetype":"venue"
},
  "geometry": {"coordinates":[-79.142408,37.415132],"type":"Point"}
}