{
  "type": "Feature",
  "properties": {
    "addr:full":"401 Old Waterford Rd NW Leesburg VA 20176",
    "addr:housenumber":"401",
    "addr:postcode":"20176",
    "addr:street":"Old Waterford Rd Nw",
    "iso:country":"US",
    "sg:address":"401 Old Waterford Rd NW",
    "sg:city":"Leesburg",
    "sg:classifiers":[
        {
            "category":"Organizations",
            "subcategory":"Membership Organization",
            "type":"Services"
        }
    ],
    "sg:phone":"+1 703 777 9668",
    "sg:postcode":"20176",
    "sg:province":"VA",
    "sg:tags":[
        "military",
        "veteran"
    ],
    "wof:name":"Vfw Post 1177",
    "wof:placetype":"venue"
},
  "geometry": {"coordinates":[-77.568443,39.123348],"type":"Point"}
}