{
  "type": "Feature",
  "properties": {
    "addr:full":"549 Almond Dr Newport News VA 23601",
    "addr:housenumber":"549",
    "addr:postcode":"23601",
    "addr:street":"Almond Dr",
    "iso:country":"US",
    "sg:address":"549 Almond Dr",
    "sg:city":"Newport News",
    "sg:classifiers":[
        {
            "category":"Professional",
            "subcategory":"Art Services",
            "type":"Services"
        }
    ],
    "sg:phone":"+1 757 599 0018",
    "sg:postcode":"23601",
    "sg:province":"VA",
    "sg:tags":[
        "graphic",
        "designer"
    ],
    "wof:name":"Image By Design",
    "wof:placetype":"venue"
},
  "geometry": {"coordinates":[-76.45182,37.051291],"type":"Point"}
}