{
  "type": "Feature",
  "properties": {
    "addr:full":"34 Old Fox Hill Rd Hampton VA 23669",
    "addr:housenumber":"34",
    "addr:postcode":"23669",
    "addr:street":"Old Fox Hill Rd",
    "iso:country":"US",
    "sg:address":"34 Old Fox Hill Rd",
    "sg:city":"Hampton",
    "sg:classifiers":[
        {
            "category":"Building & Trades",
            "subcategory":"Construction",
            "type":"Services"
        }
    ],
    "sg:phone":"+1 757 303 8813",
    "sg:postcode":"23669",
    "sg:province":"VA",
    "sg:tags":[
        "concrete",
        "contractor"
    ],
    "wof:name":"T & T Concrete",
    "wof:placetype":"venue"
},
  "geometry": {"coordinates":[-76.34483,37.045802],"type":"Point"}
}