{
  "type": "Feature",
  "properties": {
    "addr:full":"24 Reeves Rd Mount Solon VA 22843",
    "addr:housenumber":"24",
    "addr:postcode":"22843",
    "addr:street":"Reeves Rd",
    "iso:country":"US",
    "sg:address":"24 Reeves Rd",
    "sg:city":"Mount Solon",
    "sg:classifiers":[
        {
            "category":"Farming",
            "subcategory":"Dairy Farm",
            "type":"Manufacturing & Wholesale Goods"
        }
    ],
    "sg:phone":"+1 540 350 2460",
    "sg:postcode":"22843",
    "sg:province":"VA",
    "sg:tags":[
        "corn",
        "wheat"
    ],
    "wof:name":"Wine Lyndon",
    "wof:placetype":"venue"
},
  "geometry": {"coordinates":[-79.05734,38.36645],"type":"Point"}
}