{
  "type": "Feature",
  "properties": {
    "addr:full":"421 7th St West Point VA 23181",
    "addr:housenumber":"421",
    "addr:postcode":"23181",
    "addr:street":"7Th St",
    "iso:country":"US",
    "sg:address":"421 7th St",
    "sg:city":"West Point",
    "sg:classifiers":[
        {
            "category":"Government",
            "subcategory":"Fire Station",
            "type":"Public Place"
        }
    ],
    "sg:phone":"+1 804 843 4865",
    "sg:postcode":"23181",
    "sg:province":"VA",
    "sg:tags":[
        "dept",
        "v"
    ],
    "wof:name":"West Point Vol Fire & Rescue",
    "wof:placetype":"venue"
},
  "geometry": {"coordinates":[-76.795027,37.532153],"type":"Point"}
}