{
  "type": "Feature",
  "properties": {
    "iso:country":"US",
    "sg:address":"1181 First Colonial Rd",
    "sg:city":"Virginia Beach",
    "sg:classifiers":[
        {
            "category":"Health Services",
            "subcategory":"Doctor",
            "type":"Services"
        }
    ],
    "sg:phone":"+1 757 425 1600",
    "sg:postcode":"23454",
    "sg:province":"VA",
    "sg:tags":[
        "gynecology",
        "obstetric"
    ],
    "wof:name":"Virginia Beach Ob & Gyn PC",
    "wof:placetype":"venue"
},
  "geometry": {"coordinates":[-76.029731,36.866673],"type":"Point"}
}