{
  "type": "Feature",
  "properties": {
    "addr:full":"3330 S Crater Rd Petersburg VA 23805",
    "addr:housenumber":"3330",
    "addr:postcode":"23805",
    "addr:street":"S Crater Rd",
    "iso:country":"US",
    "sg:address":"3330 S Crater Rd",
    "sg:city":"Petersburg",
    "sg:classifiers":[
        {
            "category":"Restaurant",
            "type":"Food & Drink"
        }
    ],
    "sg:menulink":"http://www.allmenus.com/va/petersburg/101038-captain-ds-seafood/menu/",
    "sg:phone":"+1 804 862 8520",
    "sg:postcode":"23805",
    "sg:province":"VA",
    "sg:tags":[
        "seafood",
        "american"
    ],
    "wof:name":"Captain D's Seafood",
    "wof:placetype":"venue"
},
  "geometry": {"coordinates":[-77.36793900000001,37.182617],"type":"Point"}
}