{
  "type": "Feature",
  "properties": {
    "addr:full":"263 Sandy Dr Lynchburg VA 24502",
    "addr:housenumber":"263",
    "addr:postcode":"24502",
    "addr:street":"Sandy Dr",
    "iso:country":"US",
    "sg:address":"263 Sandy Dr",
    "sg:city":"Lynchburg",
    "sg:classifiers":[
        {
            "category":"Insurance",
            "subcategory":"Insurance Agent",
            "type":"Services"
        }
    ],
    "sg:phone":"+1 434 525 5200",
    "sg:postcode":"24502",
    "sg:province":"VA",
    "wof:name":"Insurance Financial Ser",
    "wof:placetype":"venue"
},
  "geometry": {"coordinates":[-79.27525300000001,37.302983],"type":"Point"}
}