{
  "type": "Feature",
  "properties": {
    "iso:country":"US",
    "sg:address":"12100 Sunset Hills Rd",
    "sg:city":"Reston",
    "sg:classifiers":[
        {
            "category":"Wholesale",
            "subcategory":"Computers",
            "type":"Manufacturing & Wholesale Goods"
        }
    ],
    "sg:phone":"+1 703 481 0050",
    "sg:postcode":"20190",
    "sg:province":"VA",
    "sg:tags":[
        "software"
    ],
    "wof:name":"Eg Solutions LLC",
    "wof:placetype":"venue"
},
  "geometry": {"coordinates":[-77.36805699999999,38.954792],"type":"Point"}
}