{
  "type": "Feature",
  "properties": {
    "addr:full":"5663 Jordantown Rd Vinton VA 24179",
    "addr:housenumber":"5663",
    "addr:postcode":"24179",
    "addr:street":"Jordantown Rd",
    "iso:country":"US",
    "sg:address":"5663 Jordantown Rd",
    "sg:city":"Vinton",
    "sg:classifiers":[
        {
            "category":"Organizations",
            "subcategory":"Religious Organization",
            "type":"Services"
        }
    ],
    "sg:phone":"+1 540 890 6414",
    "sg:postcode":"24179",
    "sg:province":"VA",
    "wof:name":"Jordantown Church Of God",
    "wof:placetype":"venue"
},
  "geometry": {"coordinates":[-79.769988,37.29199],"type":"Point"}
}