{
  "type": "Feature",
  "properties": {
    "iso:country":"US",
    "sg:address":"1648 Beaver Dam Rd",
    "sg:city":"Buchanan",
    "sg:classifiers":[
        {
            "category":"Farming",
            "subcategory":"Dairy Farm",
            "type":"Manufacturing & Wholesale Goods"
        }
    ],
    "sg:phone":"+1 540 254 1930",
    "sg:postcode":"24066",
    "sg:province":"VA",
    "wof:name":"Marshall Brothers Dairy",
    "wof:placetype":"venue"
},
  "geometry": {"coordinates":[-79.77046799999999,37.518489],"type":"Point"}
}