{
  "type": "Feature",
  "properties": {
    "iso:country":"US",
    "sg:address":"5600 Cox Rd",
    "sg:city":"Glen Allen",
    "sg:classifiers":[
        {
            "category":"Professional",
            "subcategory":"Business Services",
            "type":"Services"
        }
    ],
    "sg:phone":"+1 804 967 1000",
    "sg:postcode":"23060",
    "sg:province":"VA",
    "sg:tags":[
        "cards",
        "credit"
    ],
    "wof:name":"Capital One Financial Corp",
    "wof:placetype":"venue"
},
  "geometry": {"coordinates":[-77.566979,37.672426],"type":"Point"}
}