{
  "type": "Feature",
  "properties": {
    "iso:country":"US",
    "sg:address":"125 Greene Dr",
    "sg:city":"Yorktown",
    "sg:classifiers":[
        {
            "category":"Manufacturing",
            "subcategory":"Tools & Machinery",
            "type":"Manufacturing & Wholesale Goods"
        }
    ],
    "sg:phone":"+1 757 898 7844",
    "sg:postcode":"23692",
    "sg:province":"VA",
    "sg:tags":[
        "machine",
        "shop"
    ],
    "wof:name":"Automated Machine & Technology",
    "wof:placetype":"venue"
},
  "geometry": {"coordinates":[-76.484731,37.181272],"type":"Point"}
}