{
  "type": "Feature",
  "properties": {
    "addr:full":"11626 Wards Rd Rustburg VA 24588",
    "addr:housenumber":"11626",
    "addr:postcode":"24588",
    "addr:street":"Wards Rd",
    "iso:country":"US",
    "sg:address":"11626 Wards Rd",
    "sg:city":"Rustburg",
    "sg:classifiers":[
        {
            "category":"Personal",
            "subcategory":"Beauty Salon",
            "type":"Services"
        }
    ],
    "sg:phone":"+1 434 821 4770",
    "sg:postcode":"24588",
    "sg:province":"VA",
    "wof:name":"Vera's Back To Basic Beauty",
    "wof:placetype":"venue"
},
  "geometry": {"coordinates":[-79.16807300000001,37.288516],"type":"Point"}
}