{
  "type": "Feature",
  "properties": {
    "iso:country":"US",
    "sg:address":"1709 Cole Blvd",
    "sg:city":"Glen Allen",
    "sg:classifiers":[
        {
            "category":"Social Services",
            "subcategory":"Child Care",
            "type":"Services"
        }
    ],
    "sg:phone":"+1 804 266 6668",
    "sg:postcode":"23060",
    "sg:province":"VA",
    "sg:tags":[
        "day"
    ],
    "wof:name":"Greenwood Preschool",
    "wof:placetype":"venue"
},
  "geometry": {"coordinates":[-77.470934,37.653901],"type":"Point"}
}