{
  "type": "Feature",
  "properties": {
    "addr:full":"1650 Darbytown Rd Henrico VA 23231",
    "addr:housenumber":"1650",
    "addr:postcode":"23231",
    "addr:street":"Darbytown Rd",
    "iso:country":"US",
    "sg:address":"1650 Darbytown Rd",
    "sg:city":"Henrico",
    "sg:classifiers":[
        {
            "category":"Home & Garden",
            "subcategory":"Building Materials",
            "type":"Retail Goods"
        },
        {
            "category":"Building & Trades",
            "subcategory":"Construction",
            "type":"Services"
        },
        {
            "category":"Manufacturing",
            "subcategory":"Building Materials",
            "type":"Manufacturing & Wholesale Goods"
        }
    ],
    "sg:phone":"+1 804 222 6770",
    "sg:postcode":"23231",
    "sg:province":"VA",
    "sg:tags":[
        "product",
        "products-wholesale",
        "contractor",
        "concrete",
        "staining",
        "manufacturer"
    ],
    "wof:name":"Structural Concrete Products",
    "wof:placetype":"venue"
},
  "geometry": {"coordinates":[-77.38413199999999,37.506489],"type":"Point"}
}