{
  "type": "Feature",
  "properties": {
    "iso:country":"US",
    "sg:address":"6767 Forest Hill Ave Ste 204",
    "sg:city":"Richmond",
    "sg:classifiers":[
        {
            "category":"Professional",
            "subcategory":"Engineering",
            "type":"Services"
        },
        {
            "category":"Professional",
            "subcategory":"Business Services",
            "type":"Services"
        },
        {
            "category":"Professional",
            "subcategory":"Management & Consulting",
            "type":"Services"
        }
    ],
    "sg:phone":"+1 804 323 3835",
    "sg:postcode":"23225",
    "sg:province":"VA",
    "sg:tags":[
        "engineer",
        "consultant",
        "ecological",
        "coach",
        "environmental"
    ],
    "sg:website":"http://www.blueskiesassociates.com",
    "wof:name":"Blueskies Environmental Associates Inc",
    "wof:placetype":"venue"
},
  "geometry": {"coordinates":[-77.518959,37.537891],"type":"Point"}
}