{
  "type": "Feature",
  "properties": {
    "iso:country":"US",
    "sg:address":"756 Stell Ln",
    "sg:city":"Virginia Beach",
    "sg:classifiers":[
        {
            "category":"Building & Trades",
            "subcategory":"Plumbing",
            "type":"Services"
        }
    ],
    "sg:phone":"+1 757 473 3483",
    "sg:postcode":"23455",
    "sg:province":"VA",
    "sg:tags":[
        "contractor"
    ],
    "wof:name":"Affordable Plumbing Sewers",
    "wof:placetype":"venue"
},
  "geometry": {"coordinates":[-76.143794,36.861223],"type":"Point"}
}