{
  "type": "Feature",
  "properties": {
    "iso:country":"US",
    "sg:address":"160 Newtown Rd",
    "sg:city":"Virginia Beach",
    "sg:classifiers":[
        {
            "category":"Banks & Credit Unions",
            "subcategory":"Bank",
            "type":"Services"
        }
    ],
    "sg:phone":"+1 757 463 5100",
    "sg:postcode":"23462",
    "sg:province":"VA",
    "sg:tags":[
        "loan",
        "real estate"
    ],
    "wof:name":"First Security Mortgage",
    "wof:placetype":"venue"
},
  "geometry": {"coordinates":[-76.185744,36.843044],"type":"Point"}
}