{
  "type": "Feature",
  "properties": {
    "iso:country":"US",
    "sg:address":"604 Wilson St",
    "sg:city":"Danville",
    "sg:classifiers":[
        {
            "category":"Building & Trades",
            "subcategory":"Electrical",
            "type":"Services"
        }
    ],
    "sg:phone":"+1 434 799 3591",
    "sg:postcode":"24541",
    "sg:province":"VA",
    "sg:tags":[
        "electric",
        "contractor"
    ],
    "wof:name":"Motley Electric Corp",
    "wof:placetype":"venue"
},
  "geometry": {"coordinates":[-79.39209099999999,36.583216],"type":"Point"}
}