{
  "type": "Feature",
  "properties": {
    "addr:full":"1304 Turnmill Dr Richmond VA 23235",
    "addr:housenumber":"1304",
    "addr:postcode":"23235",
    "addr:street":"Turnmill Dr",
    "iso:country":"US",
    "sg:address":"1304 Turnmill Dr",
    "sg:city":"Richmond",
    "sg:classifiers":[
        {
            "category":"Shopping",
            "subcategory":"Clothing, Apparel, & Fashions",
            "type":"Retail Goods"
        }
    ],
    "sg:phone":"+1 804 745 3971",
    "sg:postcode":"23235",
    "sg:province":"VA",
    "sg:tags":[
        "merchandise"
    ],
    "wof:name":"Spectra Lasers of Virginia",
    "wof:placetype":"venue"
},
  "geometry": {"coordinates":[-77.54096800000001,37.483158],"type":"Point"}
}