{
  "type": "Feature",
  "properties": {
    "iso:country":"US",
    "sg:address":"1715 N Wilson Blvd",
    "sg:city":"Arlington",
    "sg:classifiers":[
        {
            "category":"Retail",
            "subcategory":"Laundry & Dry Cleaning",
            "type":"Services"
        }
    ],
    "sg:phone":"+1 703 465 5066",
    "sg:postcode":"22209",
    "sg:province":"VA",
    "sg:tags":[
        "drycleaning",
        "plant"
    ],
    "wof:name":"Bergmann Inc",
    "wof:placetype":"venue"
},
  "geometry": {"coordinates":[-77.08027199999999,38.893243],"type":"Point"}
}