{
  "type": "Feature",
  "properties": {
    "addr:full":"639 Nickland Dr Evington VA 24550",
    "addr:housenumber":"639",
    "addr:postcode":"24550",
    "addr:street":"Nickland Dr",
    "iso:country":"US",
    "sg:address":"639 Nickland Dr",
    "sg:city":"Evington",
    "sg:classifiers":[
        {
            "category":"Building & Trades",
            "subcategory":"Construction",
            "type":"Services"
        }
    ],
    "sg:phone":"+1 434 821 4606",
    "sg:postcode":"24550",
    "sg:province":"VA",
    "sg:tags":[
        "residential"
    ],
    "wof:name":"Scott Wade Builder",
    "wof:placetype":"venue"
},
  "geometry": {"coordinates":[-79.194879,37.191319],"type":"Point"}
}