{
  "type": "Feature",
  "properties": {
    "addr:full":"6845 Elm St Ste 708 Mc Lean VA 22101",
    "addr:housenumber":"6845",
    "addr:postcode":"22101",
    "addr:street":"Elm St Ste 708 Mc Lean",
    "iso:country":"US",
    "sg:address":"6845 Elm St Ste 708",
    "sg:city":"Mc Lean",
    "sg:classifiers":[
        {
            "category":"Health Services",
            "subcategory":"Doctor",
            "type":"Services"
        }
    ],
    "sg:phone":"+1 703 893 1111",
    "sg:postcode":"22101",
    "sg:province":"VA",
    "sg:tags":[
        "surgeon",
        "cosmetic"
    ],
    "wof:name":"Duda Gloria MD",
    "wof:placetype":"venue"
},
  "geometry": {"coordinates":[-77.180801,38.9366],"type":"Point"}
}