{
  "type": "Feature",
  "properties": {
    "addr:full":"4037 Taylor Rd Chesapeake VA 23321",
    "addr:housenumber":"4037",
    "addr:postcode":"23321",
    "addr:street":"Taylor Rd",
    "iso:country":"US",
    "sg:address":"4037 Taylor Rd",
    "sg:city":"Chesapeake",
    "sg:classifiers":[
        {
            "category":"Health Services",
            "subcategory":"Doctor",
            "type":"Services"
        }
    ],
    "sg:phone":"+1 757 484 0216",
    "sg:postcode":"23321",
    "sg:province":"VA",
    "sg:tags":[
        "medical"
    ],
    "wof:name":"Damle Anant",
    "wof:placetype":"venue"
},
  "geometry": {"coordinates":[-76.404501,36.862843],"type":"Point"}
}