{
  "type": "Feature",
  "properties": {
    "addr:full":"862 S Hill Ave South Hill VA 23970",
    "addr:housenumber":"862",
    "addr:postcode":"23970",
    "addr:street":"S Hill Ave",
    "iso:country":"US",
    "sg:address":"862 S Hill Ave",
    "sg:city":"South Hill",
    "sg:classifiers":[
        {
            "category":"Insurance",
            "subcategory":"Insurance Agent",
            "type":"Services"
        }
    ],
    "sg:phone":"+1 434 955 2720",
    "sg:postcode":"23970",
    "sg:province":"VA",
    "wof:name":"Wootten Insurance Inc",
    "wof:placetype":"venue"
},
  "geometry": {"coordinates":[-78.133095,36.718781],"type":"Point"}
}