{
  "type": "Feature",
  "properties": {
    "addr:full":"2210 Ellett Rd Christiansburg VA 24073",
    "addr:housenumber":"2210",
    "addr:postcode":"24073",
    "addr:street":"Ellett Rd",
    "iso:country":"US",
    "sg:address":"2210 Ellett Rd",
    "sg:city":"Christiansburg",
    "sg:classifiers":[
        {
            "category":"Building & Trades",
            "subcategory":"Landscaping Services",
            "type":"Services"
        }
    ],
    "sg:phone":"+1 540 381 0448",
    "sg:postcode":"24073",
    "sg:province":"VA",
    "wof:name":"Mill Brook Landscaping Inc",
    "wof:placetype":"venue"
},
  "geometry": {"coordinates":[-80.37602800000001,37.173502],"type":"Point"}
}