{
  "type": "Feature",
  "properties": {
    "addr:full":"201 Bulldog Dr Chesapeake VA 23320",
    "addr:housenumber":"201",
    "addr:postcode":"23320",
    "addr:street":"Bulldog Dr",
    "iso:country":"US",
    "sg:address":"201 Bulldog Dr",
    "sg:city":"Chesapeake",
    "sg:classifiers":[
        {
            "category":"Building & Trades",
            "subcategory":"Equipment Rental",
            "type":"Services"
        }
    ],
    "sg:phone":"+1 757 436 7600",
    "sg:postcode":"23320",
    "sg:province":"VA",
    "sg:tags":[
        "contractor"
    ],
    "sg:website":"www.unitedrentals.com",
    "wof:name":"United Rentals Aerial Equip",
    "wof:placetype":"venue"
},
  "geometry": {"coordinates":[-76.25738699999999,36.770851],"type":"Point"}
}