{
  "type": "Feature",
  "properties": {
    "addr:full":"11919 Freedom Dr Ste A Reston VA 20190",
    "addr:housenumber":"11919",
    "addr:postcode":"20190",
    "addr:street":"Freedom Dr Ste A",
    "iso:country":"US",
    "sg:address":"11919 Freedom Dr Ste A",
    "sg:city":"Reston",
    "sg:classifiers":[
        {
            "category":"Government",
            "subcategory":"Embassy",
            "type":"Public Place"
        },
        {
            "category":"Retail",
            "subcategory":"Photofinishing",
            "type":"Services"
        },
        {
            "category":"Professional",
            "subcategory":"Printing & Photocopies",
            "type":"Services"
        }
    ],
    "sg:phone":"+1 703 742 0235",
    "sg:postcode":"20190",
    "sg:province":"VA",
    "sg:tags":[
        "information",
        "laboratories-commercial",
        "finishing-custom",
        "visa",
        "passport",
        "photo",
        "laboratory",
        "finishing"
    ],
    "sg:website":"http://www.motophoto.com",
    "wof:name":"Moto Photo",
    "wof:placetype":"venue"
},
  "geometry": {"coordinates":[-77.356888,38.959572],"type":"Point"}
}