{
  "type": "Feature",
  "properties": {
    "iso:country":"US",
    "sg:address":"24095 Gum Spring Rd",
    "sg:city":"Sterling",
    "sg:classifiers":[
        {
            "category":"Shopping",
            "subcategory":"Used Merchandise",
            "type":"Retail Goods"
        }
    ],
    "sg:phone":"+1 703 996 8887",
    "sg:postcode":"20166",
    "sg:province":"VA",
    "wof:name":"Three Sisters Antiques",
    "wof:placetype":"venue"
},
  "geometry": {"coordinates":[-77.53698199999999,38.949004],"type":"Point"}
}