{
  "type": "Feature",
  "properties": {
    "addr:full":"8720 Waterford Rd Alexandria VA 22308",
    "addr:housenumber":"8720",
    "addr:postcode":"22308",
    "addr:street":"Waterford Rd",
    "iso:country":"US",
    "sg:address":"8720 Waterford Rd",
    "sg:city":"Alexandria",
    "sg:classifiers":[
        {
            "category":"Professional",
            "subcategory":"Computer Services",
            "type":"Services"
        }
    ],
    "sg:phone":"+1 703 472 5048",
    "sg:postcode":"22308",
    "sg:province":"VA",
    "sg:tags":[
        "related"
    ],
    "wof:name":"Webster Consulting LLC",
    "wof:placetype":"venue"
},
  "geometry": {"coordinates":[-77.073269,38.720227],"type":"Point"}
}