{
  "type": "Feature",
  "properties": {
    "addr:full":"5632 Tournament Dr Haymarket VA 20169",
    "addr:housenumber":"5632",
    "addr:postcode":"20169",
    "addr:street":"Tournament Dr",
    "iso:country":"US",
    "sg:address":"5632 Tournament Dr",
    "sg:city":"Haymarket",
    "sg:classifiers":[
        {
            "category":"Banks & Credit Unions",
            "subcategory":"Investment Brokerage",
            "type":"Services"
        }
    ],
    "sg:phone":"+1 703 754 6019",
    "sg:postcode":"20169",
    "sg:province":"VA",
    "sg:tags":[
        "investing"
    ],
    "wof:name":"Fox Financial Services",
    "wof:placetype":"venue"
},
  "geometry": {"coordinates":[-77.626701,38.8354],"type":"Point"}
}