{
  "type": "Feature",
  "properties": {
    "iso:country":"US",
    "sg:address":"13904 Melton Pl",
    "sg:city":"Centreville",
    "sg:classifiers":[
        {
            "category":"Professional",
            "subcategory":"Business Services",
            "type":"Services"
        }
    ],
    "sg:phone":"+1 703 802 3611",
    "sg:postcode":"20120",
    "sg:province":"VA",
    "wof:name":"Interiors By Kymberly",
    "wof:placetype":"venue"
},
  "geometry": {"coordinates":[-77.428163,38.846643],"type":"Point"}
}