{
  "type": "Feature",
  "properties": {
    "addr:full":"1153 N Military Hwy Norfolk VA 23502",
    "addr:housenumber":"1153",
    "addr:postcode":"23502",
    "addr:street":"N Military Hwy",
    "iso:country":"US",
    "sg:address":"1153 N Military Hwy",
    "sg:city":"Norfolk",
    "sg:classifiers":[
        {
            "category":"Coffee & Tea",
            "type":"Food & Drink"
        }
    ],
    "sg:menulink":"http://www.allmenus.com/va/norfolk/112060-starbucks-coffee/menu/",
    "sg:phone":"+1 757 455 6504",
    "sg:postcode":"23502",
    "sg:province":"VA",
    "sg:tags":[
        "american"
    ],
    "wof:name":"Starbucks Coffee",
    "wof:placetype":"venue"
},
  "geometry": {"coordinates":[-76.210497,36.863103],"type":"Point"}
}