{
  "type": "Feature",
  "properties": {
    "addr:full":"1995 Jude's Ferry Rd Powhatan VA 23139",
    "addr:housenumber":"1995",
    "addr:postcode":"23139",
    "addr:street":"Jude'S Ferry Rd",
    "iso:country":"US",
    "sg:address":"1995 Jude's Ferry Rd",
    "sg:city":"Powhatan",
    "sg:classifiers":[
        {
            "category":"Building & Trades",
            "subcategory":"Construction",
            "type":"Services"
        }
    ],
    "sg:phone":"+1 804 598 5255",
    "sg:postcode":"23139",
    "sg:province":"VA",
    "sg:tags":[
        "house"
    ],
    "wof:name":"Haddon Builders",
    "wof:placetype":"venue"
},
  "geometry": {"coordinates":[-77.802103,37.5268],"type":"Point"}
}