{
  "type": "Feature",
  "properties": {
    "iso:country":"US",
    "sg:address":"3276 Willow Glen Dr",
    "sg:city":"Herndon",
    "sg:classifiers":[
        {
            "category":"Real Estate",
            "subcategory":"Architect",
            "type":"Services"
        }
    ],
    "sg:phone":"+1 703 648 3112",
    "sg:postcode":"20171",
    "sg:province":"VA",
    "sg:tags":[
        "architectural"
    ],
    "wof:name":"Tah Architects",
    "wof:placetype":"venue"
},
  "geometry": {"coordinates":[-77.38887,38.904129],"type":"Point"}
}