{
  "type": "Feature",
  "properties": {
    "addr:full":"135 Ruben Ct Danville VA 24541",
    "addr:housenumber":"135",
    "addr:postcode":"24541",
    "addr:street":"Ruben Ct",
    "iso:country":"US",
    "sg:address":"135 Ruben Ct",
    "sg:city":"Danville",
    "sg:classifiers":[
        {
            "category":"Building & Trades",
            "subcategory":"Construction",
            "type":"Services"
        }
    ],
    "sg:phone":"+1 434 822 1964",
    "sg:postcode":"24541",
    "sg:province":"VA",
    "sg:tags":[
        "contractor"
    ],
    "wof:name":"River Town Tile Co",
    "wof:placetype":"venue"
},
  "geometry": {"coordinates":[-79.44513499999999,36.595507],"type":"Point"}
}