{
  "type": "Feature",
  "properties": {
    "iso:country":"US",
    "sg:address":"5723 Wooden Hawk Ln",
    "sg:city":"Burke",
    "sg:classifiers":[
        {
            "category":"Professional",
            "subcategory":"Computer Services",
            "type":"Services"
        }
    ],
    "sg:phone":"+1 703 978 5392",
    "sg:postcode":"22015",
    "sg:province":"VA",
    "sg:tags":[
        "programing",
        "custom"
    ],
    "wof:name":"Computer Constructs",
    "wof:placetype":"venue"
},
  "geometry": {"coordinates":[-77.28870499999999,38.795123],"type":"Point"}
}