{
  "type": "Feature",
  "properties": {
    "addr:full":"9621 Hastings Mill Dr Glen Allen VA 23060",
    "addr:housenumber":"9621",
    "addr:postcode":"23060",
    "addr:street":"Hastings Mill Dr",
    "iso:country":"US",
    "sg:address":"9621 Hastings Mill Dr",
    "sg:city":"Glen Allen",
    "sg:classifiers":[
        {
            "category":"Professional",
            "subcategory":"Advertising",
            "type":"Services"
        }
    ],
    "sg:phone":"+1 804 755 7543",
    "sg:postcode":"23060",
    "sg:province":"VA",
    "wof:name":"Kellys Advertising",
    "wof:placetype":"venue"
},
  "geometry": {"coordinates":[-77.52453,37.647375],"type":"Point"}
}