{
  "type": "Feature",
  "properties": {
    "addr:full":"5706 Hopkins Rd Richmond VA 23234",
    "addr:housenumber":"5706",
    "addr:postcode":"23234",
    "addr:street":"Hopkins Rd",
    "iso:country":"US",
    "sg:address":"5706 Hopkins Rd",
    "sg:city":"Richmond",
    "sg:classifiers":[
        {
            "category":"Home & Garden",
            "subcategory":"Household Appliances",
            "type":"Retail Goods"
        }
    ],
    "sg:phone":"+1 804 901 9273",
    "sg:postcode":"23234",
    "sg:province":"VA",
    "sg:tags":[
        "machine",
        "sewing"
    ],
    "wof:name":"A 1 Johnnys Sew & Vac",
    "wof:placetype":"venue"
},
  "geometry": {"coordinates":[-77.472697,37.441763],"type":"Point"}
}