{
  "type": "Feature",
  "properties": {
    "iso:country":"US",
    "sg:address":"1816 Todds Ln",
    "sg:city":"Hampton",
    "sg:classifiers":[
        {
            "category":"Wholesale",
            "subcategory":"Machinery & Supplies",
            "type":"Manufacturing & Wholesale Goods"
        }
    ],
    "sg:phone":"+1 757 825 0212",
    "sg:postcode":"23666",
    "sg:province":"VA",
    "sg:tags":[
        "equipment",
        "salon",
        "establishment",
        "beauty"
    ],
    "wof:name":"J's Beauty Outlet",
    "wof:placetype":"venue"
},
  "geometry": {"coordinates":[-76.404938,37.041083],"type":"Point"}
}