{
  "type": "Feature",
  "properties": {
    "iso:country":"US",
    "sg:address":"223 W Shirley Ave",
    "sg:city":"Warrenton",
    "sg:classifiers":[
        {
            "category":"Government",
            "subcategory":"Office",
            "type":"Public Place"
        }
    ],
    "sg:phone":"+1 540 347 6125",
    "sg:postcode":"20186",
    "sg:province":"VA",
    "sg:website":"www.fauquiercounty.gov",
    "wof:name":"Support Services Dept",
    "wof:placetype":"venue"
},
  "geometry": {"coordinates":[-77.80636699999999,38.713452],"type":"Point"}
}