{
  "type": "Feature",
  "properties": {
    "addr:full":"5308 Jefferson Davis Hwy Fredericksburg VA 22408",
    "addr:housenumber":"5308",
    "addr:postcode":"22408",
    "addr:street":"Jefferson Davis Hwy",
    "iso:country":"US",
    "sg:address":"5308 Jefferson Davis Hwy",
    "sg:city":"Fredericksburg",
    "sg:phone":"+1 540 898 1000",
    "sg:postcode":"22408",
    "sg:province":"VA",
    "wof:name":"Motel 6",
    "wof:placetype":"venue"
},
  "geometry": {"coordinates":[-77.49897,38.247849],"type":"Point"}
}