{
  "type": "Feature",
  "properties": {
    "iso:country":"US",
    "sg:address":"7100 George Washington Memorial Hwy",
    "sg:city":"Yorktown",
    "sg:classifiers":[
        {
            "category":"Real Estate",
            "subcategory":"Real Estate Agent",
            "type":"Services"
        }
    ],
    "sg:phone":"+1 757 890 4555",
    "sg:postcode":"23692",
    "sg:province":"VA",
    "wof:name":"Tony Urban Remax Capital",
    "wof:placetype":"venue"
},
  "geometry": {"coordinates":[-76.479253,37.17826],"type":"Point"}
}