{
  "type": "Feature",
  "properties": {
    "iso:country":"US",
    "sg:address":"314 Colony Trl",
    "sg:city":"Lanexa",
    "sg:classifiers":[
        {
            "category":"Professional",
            "subcategory":"Engineering",
            "type":"Services"
        }
    ],
    "sg:phone":"+1 804 966 7262",
    "sg:postcode":"23089",
    "sg:province":"VA",
    "wof:name":"P Stowell Engineering LTD",
    "wof:placetype":"venue"
},
  "geometry": {"coordinates":[-76.909341,37.387377],"type":"Point"}
}