{
  "type": "Feature",
  "properties": {
    "addr:full":"4412 Hamilton Dr Woodbridge VA 22193",
    "addr:housenumber":"4412",
    "addr:postcode":"22193",
    "addr:street":"Hamilton Dr",
    "iso:country":"US",
    "sg:address":"4412 Hamilton Dr",
    "sg:city":"Woodbridge",
    "sg:classifiers":[
        {
            "category":"Shopping",
            "subcategory":"Catalog Store",
            "type":"Retail Goods"
        }
    ],
    "sg:phone":"+1 703 680 7865",
    "sg:postcode":"22193",
    "sg:province":"VA",
    "sg:tags":[
        "house",
        "mail"
    ],
    "wof:name":"American Mailing Systems",
    "wof:placetype":"venue"
},
  "geometry": {"coordinates":[-77.342277,38.665485],"type":"Point"}
}