{
  "type": "Feature",
  "properties": {
    "addr:full":"4238 Wilson Blvd Arlington VA 22203",
    "addr:housenumber":"4238",
    "addr:postcode":"22203",
    "addr:street":"Wilson Blvd",
    "iso:country":"US",
    "sg:address":"4238 Wilson Blvd",
    "sg:city":"Arlington",
    "sg:classifiers":[
        {
            "category":"Banks & Credit Unions",
            "subcategory":"Investment Brokerage",
            "type":"Services"
        },
        {
            "category":"Shopping",
            "subcategory":"Music",
            "type":"Retail Goods"
        }
    ],
    "sg:phone":"+1 703 528 6940",
    "sg:postcode":"22203",
    "sg:province":"VA",
    "sg:tags":[
        "used",
        "tapes",
        "vintage",
        "sale",
        "dvds-rental",
        "records",
        "video",
        "cd's",
        "tape",
        "store"
    ],
    "sg:website":"http://www.fye.com/",
    "wof:name":"f.y.e",
    "wof:placetype":"venue"
},
  "geometry": {"coordinates":[-77.111557,38.880051],"type":"Point"}
}