{
  "type": "Feature",
  "properties": {
    "addr:full":"5407 Port Royal Rd Springfield VA 22151",
    "addr:housenumber":"5407",
    "addr:postcode":"22151",
    "addr:street":"Port Royal Rd",
    "iso:country":"US",
    "sg:address":"5407 Port Royal Rd",
    "sg:city":"Springfield",
    "sg:classifiers":[
        {
            "category":"Manufacturing",
            "subcategory":"Signs",
            "type":"Manufacturing & Wholesale Goods"
        }
    ],
    "sg:phone":"+1 571 321 0228",
    "sg:postcode":"22151",
    "sg:province":"VA",
    "sg:tags":[
        "advertising",
        "specialty"
    ],
    "wof:name":"Fastsigns",
    "wof:placetype":"venue"
},
  "geometry": {"coordinates":[-77.21463,38.804183],"type":"Point"}
}