{
  "type": "Feature",
  "properties": {
    "addr:full":"4214 Takach Rd Prince George VA 23875",
    "addr:housenumber":"4214",
    "addr:postcode":"23875",
    "addr:street":"Takach Rd",
    "iso:country":"US",
    "sg:address":"4214 Takach Rd",
    "sg:city":"Prince George",
    "sg:classifiers":[
        {
            "category":"Freight",
            "type":"Transportation"
        }
    ],
    "sg:phone":"+1 804 458 2399",
    "sg:postcode":"23875",
    "sg:province":"VA",
    "sg:tags":[
        "operator",
        "local",
        "trucking"
    ],
    "wof:name":"Bell Trucking Inc",
    "wof:placetype":"venue"
},
  "geometry": {"coordinates":[-77.29503099999999,37.255207],"type":"Point"}
}