{
  "type": "Feature",
  "properties": {
    "addr:full":"2001 Crystal Spring Ave SW Roanoke VA 24014",
    "addr:housenumber":"2001",
    "addr:postcode":"24014",
    "addr:street":"Crystal Spring Ave Sw",
    "iso:country":"US",
    "sg:address":"2001 Crystal Spring Ave SW",
    "sg:city":"Roanoke",
    "sg:classifiers":[
        {
            "category":"Health Services",
            "subcategory":"Medical Lab",
            "type":"Services"
        }
    ],
    "sg:phone":"+1 540 981 7600",
    "sg:postcode":"24014",
    "sg:province":"VA",
    "sg:tags":[
        "laboratory"
    ],
    "wof:name":"Carilion Imaging",
    "wof:placetype":"venue"
},
  "geometry": {"coordinates":[-79.94566399999999,37.249798],"type":"Point"}
}