{
  "type": "Feature",
  "properties": {
    "addr:full":"6993 Hearthside Dr Prince George VA 23875",
    "addr:housenumber":"6993",
    "addr:postcode":"23875",
    "addr:street":"Hearthside Dr",
    "iso:country":"US",
    "sg:address":"6993 Hearthside Dr",
    "sg:city":"Prince George",
    "sg:classifiers":[
        {
            "category":"Banks & Credit Unions",
            "subcategory":"Bank",
            "type":"Services"
        }
    ],
    "sg:phone":"+1 804 452 7252",
    "sg:postcode":"23875",
    "sg:province":"VA",
    "sg:tags":[
        "loan",
        "real estate"
    ],
    "wof:name":"Barksdale Loan Consultants",
    "wof:placetype":"venue"
},
  "geometry": {"coordinates":[-77.281306,37.245146],"type":"Point"}
}