{
  "type": "Feature",
  "properties": {
    "iso:country":"US",
    "sg:address":"6570 Forsythia St",
    "sg:city":"Springfield",
    "sg:classifiers":[
        {
            "category":"Health Services",
            "subcategory":"Doctor",
            "type":"Services"
        }
    ],
    "sg:phone":"+1 703 719 0628",
    "sg:postcode":"22150",
    "sg:province":"VA",
    "sg:tags":[
        "medical"
    ],
    "wof:name":"Colon Stomach & Liver Center",
    "wof:placetype":"venue"
},
  "geometry": {"coordinates":[-77.16695199999999,38.777598],"type":"Point"}
}