{
  "type": "Feature",
  "properties": {
    "addr:full":"23 Smith St Warrenton VA 20186",
    "addr:housenumber":"23",
    "addr:postcode":"20186",
    "addr:street":"Smith St",
    "iso:country":"US",
    "sg:address":"23 Smith St",
    "sg:city":"Warrenton",
    "sg:classifiers":[
        {
            "category":"Building & Trades",
            "subcategory":"Construction",
            "type":"Services"
        }
    ],
    "sg:phone":"+1 540 428 1889",
    "sg:postcode":"20186",
    "sg:province":"VA",
    "sg:tags":[
        "handyman"
    ],
    "wof:name":"Alls & Co",
    "wof:placetype":"venue"
},
  "geometry": {"coordinates":[-77.79695100000001,38.714961],"type":"Point"}
}