{
  "type": "Feature",
  "properties": {
    "iso:country":"US",
    "sg:address":"13100 Warwick Blvd",
    "sg:city":"Newport News",
    "sg:classifiers":[
        {
            "category":"Organizations",
            "subcategory":"Religious Organization",
            "type":"Services"
        }
    ],
    "sg:phone":"+1 757 249 0374",
    "sg:postcode":"23602",
    "sg:province":"VA",
    "sg:tags":[
        "church"
    ],
    "sg:website":"www.reformationlc.org",
    "wof:name":"Reformation Lutheran Church",
    "wof:placetype":"venue"
},
  "geometry": {"coordinates":[-76.516762,37.1107],"type":"Point"}
}