{
  "type": "Feature",
  "properties": {
    "iso:country":"US",
    "sg:address":"405 Fairmont Ave",
    "sg:city":"Winchester",
    "sg:classifiers":[
        {
            "category":"Professional",
            "type":"Services"
        }
    ],
    "sg:phone":"+1 540 665 8033",
    "sg:postcode":"22601",
    "sg:province":"VA",
    "wof:name":"Lucky Dog Inc",
    "wof:placetype":"venue"
},
  "geometry": {"coordinates":[-78.16730200000001,39.190705],"type":"Point"}
}