{
  "type": "Feature",
  "properties": {
    "addr:full":"708 Crowe Hollow Rd Atkins VA 24311",
    "addr:housenumber":"708",
    "addr:postcode":"24311",
    "addr:street":"Crowe Hollow Rd",
    "iso:country":"US",
    "sg:address":"708 Crowe Hollow Rd",
    "sg:city":"Atkins",
    "sg:classifiers":[
        {
            "category":"Retail",
            "subcategory":"Repair Shop",
            "type":"Services"
        }
    ],
    "sg:phone":"+1 276 783 3508",
    "sg:postcode":"24311",
    "sg:province":"VA",
    "sg:tags":[
        "appliance"
    ],
    "wof:name":"DMAC Appliance & Furnace",
    "wof:placetype":"venue"
},
  "geometry": {"coordinates":[-81.39583,36.887902],"type":"Point"}
}