{
  "type": "Feature",
  "properties": {
    "iso:country":"US",
    "sg:address":"1454 CROSSWAYS BLVD",
    "sg:city":"CHESAPEAKE",
    "sg:classifiers":[
        {
            "category":"Travel",
            "subcategory":"Hotels & Motels",
            "type":"Entertainment"
        },
        {
            "category":"Travel",
            "subcategory":"Resort",
            "type":"Entertainment"
        },
        {
            "category":"Sports & Exercise",
            "subcategory":"Ski Resort",
            "type":"Entertainment"
        }
    ],
    "sg:phone":"+1 757 410 9562",
    "sg:postcode":"23320",
    "sg:province":"VA",
    "sg:tags":[
        "corporate",
        "lodging"
    ],
    "sg:website":"http://clk.atdmt.com/NYC/go/156347018/direct/01/",
    "wof:name":"aloft Chesapeake",
    "wof:placetype":"venue"
},
  "geometry": {"coordinates":[-76.245638,36.776317],"type":"Point"}
}