{
  "type": "Feature",
  "properties": {
    "addr:full":"9338 Gerljean Dr Mechanicsville VA 23116",
    "addr:housenumber":"9338",
    "addr:postcode":"23116",
    "addr:street":"Gerljean Dr",
    "iso:country":"US",
    "sg:address":"9338 Gerljean Dr",
    "sg:city":"Mechanicsville",
    "sg:classifiers":[
        {
            "category":"Place Of Worship",
            "subcategory":"Church",
            "type":"Public Place"
        },
        {
            "category":"Place Of Worship",
            "type":"Public Place"
        }
    ],
    "sg:phone":"+1 804 569 0567",
    "sg:postcode":"23116",
    "sg:province":"VA",
    "sg:tags":[
        "testament",
        "christ-new",
        "churches-church",
        "christ"
    ],
    "wof:name":"New Found Church Of Christ",
    "wof:placetype":"venue"
},
  "geometry": {"coordinates":[-77.42732599999999,37.675711],"type":"Point"}
}