{
  "type": "Feature",
  "properties": {
    "addr:full":"1038 N Garfield St Arlington VA 22201",
    "addr:housenumber":"1038",
    "addr:postcode":"22201",
    "addr:street":"N Garfield St",
    "iso:country":"US",
    "sg:address":"1038 N Garfield St",
    "sg:city":"Arlington",
    "sg:classifiers":[
        {
            "category":"Building & Trades",
            "subcategory":"Locksmith",
            "type":"Services"
        }
    ],
    "sg:phone":"+1 703 258 0280",
    "sg:postcode":"22201",
    "sg:province":"VA",
    "sg:tags":[
        "key"
    ],
    "wof:name":"Jhon Lock and Key",
    "wof:placetype":"venue"
},
  "geometry": {"coordinates":[-77.093987,38.885557],"type":"Point"}
}