{
  "type": "Feature",
  "properties": {
    "addr:full":"703 Wenonah Ave Pearisburg VA 24134",
    "addr:housenumber":"703",
    "addr:postcode":"24134",
    "addr:street":"Wenonah Ave",
    "iso:country":"US",
    "sg:address":"703 Wenonah Ave",
    "sg:city":"Pearisburg",
    "sg:classifiers":[
        {
            "category":"Real Estate",
            "subcategory":"Surveying",
            "type":"Services"
        }
    ],
    "sg:phone":"+1 540 921 3988",
    "sg:postcode":"24134",
    "sg:province":"VA",
    "wof:name":"Efi Inc",
    "wof:placetype":"venue"
},
  "geometry": {"coordinates":[-80.73244699999999,37.327338],"type":"Point"}
}