{
  "type": "Feature",
  "properties": {
    "iso:country":"US",
    "sg:address":"386 Maple Ave E",
    "sg:city":"Vienna",
    "sg:classifiers":[
        {
            "category":"Banks & Credit Unions",
            "subcategory":"Investment Brokerage",
            "type":"Services"
        }
    ],
    "sg:phone":"+1 703 865 8060",
    "sg:postcode":"22180",
    "sg:province":"VA",
    "sg:tags":[
        "investing"
    ],
    "wof:name":"Shinsegae USA Inc",
    "wof:placetype":"venue"
},
  "geometry": {"coordinates":[-77.258765,38.906908],"type":"Point"}
}