{
  "type": "Feature",
  "properties": {
    "addr:full":"719 Ferry Rd Colonial Beach VA 22473",
    "addr:housenumber":"719",
    "addr:postcode":"22473",
    "addr:street":"Ferry Rd",
    "iso:country":"US",
    "sg:address":"719 Ferry Rd",
    "sg:city":"Colonial Beach",
    "sg:classifiers":[
        {
            "category":"Organizations",
            "subcategory":"Community Association",
            "type":"Services"
        }
    ],
    "sg:phone":"+1 804 224 0364",
    "sg:postcode":"22473",
    "sg:province":"VA",
    "sg:tags":[
        "membership",
        "fraternal",
        "civic"
    ],
    "wof:name":"Elks Lodge 2666",
    "wof:placetype":"venue"
},
  "geometry": {"coordinates":[-76.27791999999999,37.901579],"type":"Point"}
}