{
  "type": "Feature",
  "properties": {
    "iso:country":"US",
    "sg:address":"133 Tilden Ave",
    "sg:city":"Chesapeake",
    "sg:classifiers":[
        {
            "category":"Building & Trades",
            "subcategory":"Pest Control",
            "type":"Services"
        }
    ],
    "sg:phone":"+1 757 312 8081",
    "sg:postcode":"23320",
    "sg:province":"VA",
    "wof:name":"Tidewater Termite & Repair Inc",
    "wof:placetype":"venue"
},
  "geometry": {"coordinates":[-76.243949,36.725409],"type":"Point"}
}