{
  "type": "Feature",
  "properties": {
    "addr:full":"20998 Ashburn Village Blvd Ashburn VA 20147",
    "addr:housenumber":"20998",
    "addr:postcode":"20147",
    "addr:street":"Ashburn Village Blvd",
    "iso:country":"US",
    "sg:address":"20998 Ashburn Village Blvd",
    "sg:city":"Ashburn",
    "sg:classifiers":[
        {
            "category":"Coffee & Tea",
            "type":"Food & Drink"
        }
    ],
    "sg:menulink":"http://www.allmenus.com/va/broad-run/111947-starbucks-coffee/menu/",
    "sg:phone":"+1 703 723 2910",
    "sg:postcode":"20147",
    "sg:province":"VA",
    "sg:tags":[
        "american"
    ],
    "wof:name":"Starbucks Coffee",
    "wof:placetype":"venue"
},
  "geometry": {"coordinates":[-77.476468,39.03467],"type":"Point"}
}