{
  "type": "Feature",
  "properties": {
    "addr:full":"110 Washington St Madison VA 22727",
    "addr:housenumber":"110",
    "addr:postcode":"22727",
    "addr:street":"Washington St",
    "iso:country":"US",
    "sg:address":"110 Washington St",
    "sg:city":"Madison",
    "sg:classifiers":[
        {
            "category":"Manufacturing",
            "subcategory":"Apparel",
            "type":"Manufacturing & Wholesale Goods"
        }
    ],
    "sg:phone":"+1 540 948 3800",
    "sg:postcode":"22727",
    "sg:province":"VA",
    "sg:tags":[
        "dress",
        "mfg"
    ],
    "wof:name":"Every Girls Dream",
    "wof:placetype":"venue"
},
  "geometry": {"coordinates":[-78.255858,38.381903],"type":"Point"}
}