{
  "type": "Feature",
  "properties": {
    "addr:full":"300 Valley St NE Abingdon VA 24210",
    "addr:housenumber":"300",
    "addr:postcode":"24210",
    "addr:street":"Valley St Ne",
    "iso:country":"US",
    "sg:address":"300 Valley St NE",
    "sg:city":"Abingdon",
    "sg:classifiers":[
        {
            "category":"Health Services",
            "subcategory":"Doctor",
            "type":"Services"
        }
    ],
    "sg:phone":"+1 276 628 7600",
    "sg:postcode":"24210",
    "sg:province":"VA",
    "sg:tags":[
        "physician",
        "pediatrics-orthopedic",
        "surgeons",
        "orthopedics",
        "surgeon",
        "surgery"
    ],
    "wof:name":"McGarry Timothy G MD",
    "wof:placetype":"venue"
},
  "geometry": {"coordinates":[-81.96766700000001,36.714249],"type":"Point"}
}