{
  "type": "Feature",
  "properties": {
    "addr:full":"9534 Arlington Blvd Fairfax VA 22031",
    "addr:housenumber":"9534",
    "addr:postcode":"22031",
    "addr:street":"Arlington Blvd",
    "iso:country":"US",
    "sg:address":"9534 Arlington Blvd",
    "sg:city":"Fairfax",
    "sg:classifiers":[
        {
            "category":"Restaurant",
            "type":"Food & Drink"
        }
    ],
    "sg:phone":"+1 703 359 5865",
    "sg:postcode":"22031",
    "sg:province":"VA",
    "wof:name":"Casa Grande Cafe",
    "wof:placetype":"venue"
},
  "geometry": {"coordinates":[-77.272111,38.864983],"type":"Point"}
}