{
  "type": "Feature",
  "properties": {
    "iso:country":"US",
    "sg:address":"707 Gittings St",
    "sg:city":"Suffolk",
    "sg:classifiers":[
        {
            "category":"Health Services",
            "subcategory":"Doctor",
            "type":"Services"
        }
    ],
    "sg:phone":"+1 757 934 2061",
    "sg:postcode":"23434",
    "sg:province":"VA",
    "sg:tags":[
        "medical"
    ],
    "wof:name":"Joseph W Musgrave MD",
    "wof:placetype":"venue"
},
  "geometry": {"coordinates":[-76.596007,36.729455],"type":"Point"}
}