{
  "type": "Feature",
  "properties": {
    "addr:full":"2133 S Loudoun St Winchester VA 22601",
    "addr:housenumber":"2133",
    "addr:postcode":"22601",
    "addr:street":"S Loudoun St",
    "iso:country":"US",
    "sg:address":"2133 S Loudoun St",
    "sg:city":"Winchester",
    "sg:classifiers":[
        {
            "category":"Shopping",
            "subcategory":"Musical Instruments",
            "type":"Retail Goods"
        }
    ],
    "sg:phone":"+1 540 665 2781",
    "sg:postcode":"22601",
    "sg:province":"VA",
    "wof:name":"Shenandoah Music Inc",
    "wof:placetype":"venue"
},
  "geometry": {"coordinates":[-78.17498500000001,39.161808],"type":"Point"}
}