{
  "type": "Feature",
  "properties": {
    "addr:full":"5345 Hickory Hill Dr Lynchburg VA 24503",
    "addr:housenumber":"5345",
    "addr:postcode":"24503",
    "addr:street":"Hickory Hill Dr",
    "iso:country":"US",
    "sg:address":"5345 Hickory Hill Dr",
    "sg:city":"Lynchburg",
    "sg:classifiers":[
        {
            "category":"Shopping",
            "subcategory":"Used Merchandise",
            "type":"Retail Goods"
        }
    ],
    "sg:phone":"+1 434 384 1743",
    "sg:postcode":"24503",
    "sg:province":"VA",
    "wof:name":"Looking Back Antiques",
    "wof:placetype":"venue"
},
  "geometry": {"coordinates":[-79.22035,37.439726],"type":"Point"}
}