{
  "type": "Feature",
  "properties": {
    "iso:country":"US",
    "sg:address":"454 Sugar Run Rd",
    "sg:city":"Pearisburg",
    "sg:classifiers":[
        {
            "category":"Insurance",
            "subcategory":"Insurance Agent",
            "type":"Services"
        }
    ],
    "sg:phone":"+1 540 921 4139",
    "sg:postcode":"24134",
    "sg:province":"VA",
    "wof:name":"Prudential Insurance Co",
    "wof:placetype":"venue"
},
  "geometry": {"coordinates":[-80.728094,37.267204],"type":"Point"}
}