{
  "type": "Feature",
  "properties": {
    "iso:country":"US",
    "sg:address":"20 Confederacy Dr",
    "sg:city":"Penn Laird",
    "sg:classifiers":[
        {
            "category":"Retail",
            "subcategory":"Laundry & Dry Cleaning",
            "type":"Services"
        }
    ],
    "sg:phone":"+1 540 801 8778",
    "sg:postcode":"22846",
    "sg:province":"VA",
    "sg:tags":[
        "drycleaning",
        "plant"
    ],
    "wof:name":"Cleaners R Us Inc",
    "wof:placetype":"venue"
},
  "geometry": {"coordinates":[-78.824156,38.400392],"type":"Point"}
}