{
  "type": "Feature",
  "properties": {
    "addr:full":"15495 October Way Haymarket VA 20169",
    "addr:housenumber":"15495",
    "addr:postcode":"20169",
    "addr:street":"October Way",
    "iso:country":"US",
    "sg:address":"15495 October Way",
    "sg:city":"Haymarket",
    "sg:classifiers":[
        {
            "category":"Building & Trades",
            "subcategory":"Construction",
            "type":"Services"
        }
    ],
    "sg:phone":"+1 703 754 8723",
    "sg:postcode":"20169",
    "sg:province":"VA",
    "sg:tags":[
        "house"
    ],
    "wof:name":"Jes Homes LLC",
    "wof:placetype":"venue"
},
  "geometry": {"coordinates":[-77.651432,38.919478],"type":"Point"}
}