{
  "type": "Feature",
  "properties": {
    "addr:full":"184 Shawnee Dr Shawsville VA 24162",
    "addr:housenumber":"184",
    "addr:postcode":"24162",
    "addr:street":"Shawnee Dr",
    "iso:country":"US",
    "sg:address":"184 Shawnee Dr",
    "sg:city":"Shawsville",
    "sg:classifiers":[
        {
            "category":"Autos & Motor Vehicles",
            "subcategory":"Automobile Sales",
            "type":"Retail Goods"
        }
    ],
    "sg:phone":"+1 540 268 2410",
    "sg:postcode":"24162",
    "sg:province":"VA",
    "sg:tags":[
        "used"
    ],
    "wof:name":"Old Town Auto Inc",
    "wof:placetype":"venue"
},
  "geometry": {"coordinates":[-80.244699,37.173606],"type":"Point"}
}