{
  "type": "Feature",
  "properties": {
    "addr:full":"9011 Centerville Rd Bridgewater VA 22812",
    "addr:postcode":"9011;22812",
    "addr:street":"Centerville Rd",
    "iso:country":"US",
    "sg:address":"9011 Centerville Rd",
    "sg:city":"Bridgewater",
    "sg:classifiers":[
        {
            "category":"Professional",
            "subcategory":"Management & Consulting",
            "type":"Services"
        }
    ],
    "sg:phone":"+1 540 828 6040",
    "sg:postcode":"22812",
    "sg:province":"VA",
    "wof:name":"Simmons Consulting Service",
    "wof:placetype":"venue"
},
  "geometry": {"coordinates":[-78.988843,38.362962],"type":"Point"}
}