{
  "type": "Feature",
  "properties": {
    "addr:full":"107 Juliad Ct Fredericksburg VA 22406",
    "addr:housenumber":"107",
    "addr:postcode":"22406",
    "addr:street":"Juliad Ct",
    "iso:country":"US",
    "sg:address":"107 Juliad Ct",
    "sg:city":"Fredericksburg",
    "sg:classifiers":[
        {
            "category":"Wholesale",
            "subcategory":"Hardware",
            "type":"Manufacturing & Wholesale Goods"
        }
    ],
    "sg:phone":"+1 540 286 3104",
    "sg:postcode":"22406",
    "sg:province":"VA",
    "sg:tags":[
        "plumbing",
        "fixture",
        "supply"
    ],
    "wof:name":"Ferguson Enterprises Inc",
    "wof:placetype":"venue"
},
  "geometry": {"coordinates":[-77.512607,38.360055],"type":"Point"}
}