{
  "type": "Feature",
  "properties": {
    "addr:full":"10621 Canterberry Rd Fairfax Station VA 22039",
    "addr:housenumber":"10621",
    "addr:postcode":"22039",
    "addr:street":"Canterberry Rd",
    "iso:country":"US",
    "sg:address":"10621 Canterberry Rd",
    "sg:city":"Fairfax Station",
    "sg:classifiers":[
        {
            "category":"Professional",
            "subcategory":"Business Services",
            "type":"Services"
        }
    ],
    "sg:phone":"+1 703 425 0552",
    "sg:postcode":"22039",
    "sg:province":"VA",
    "wof:name":"Manassas Madows Assoc Ltd Part",
    "wof:placetype":"venue"
},
  "geometry": {"coordinates":[-77.312961,38.761132],"type":"Point"}
}