{
  "type": "Feature",
  "properties": {
    "iso:country":"US",
    "sg:address":"4929 Trade Center Dr",
    "sg:city":"Fredericksburg",
    "sg:classifiers":[
        {
            "category":"Building & Trades",
            "subcategory":"Plumbing",
            "type":"Services"
        }
    ],
    "sg:phone":"+1 540 898 8247",
    "sg:postcode":"22408",
    "sg:province":"VA",
    "sg:tags":[
        "industry",
        "mfg",
        "m",
        "mach"
    ],
    "wof:name":"Affordable Water Treatment",
    "wof:placetype":"venue"
},
  "geometry": {"coordinates":[-77.504319,38.257787],"type":"Point"}
}