{
  "type": "Feature",
  "properties": {
    "addr:full":"7317 Bell Creek Rd Mechanicsville VA 23111",
    "addr:housenumber":"7317",
    "addr:postcode":"23111",
    "addr:street":"Bell Creek Rd",
    "iso:country":"US",
    "sg:address":"7317 Bell Creek Rd",
    "sg:city":"Mechanicsville",
    "sg:classifiers":[
        {
            "category":"Sports & Exercise",
            "subcategory":"Bowling",
            "type":"Entertainment"
        }
    ],
    "sg:phone":"+1 804 559 2600",
    "sg:postcode":"23111",
    "sg:province":"VA",
    "sg:tags":[
        "center"
    ],
    "wof:name":"AMF Hanover Lanes",
    "wof:placetype":"venue"
},
  "geometry": {"coordinates":[-77.353437,37.602856],"type":"Point"}
}