{
  "type": "Feature",
  "properties": {
    "iso:country":"US",
    "sg:address":"8427 Dorsey Cir",
    "sg:city":"Manassas",
    "sg:classifiers":[
        {
            "category":"Organizations",
            "subcategory":"Non-profit Organization",
            "type":"Services"
        }
    ],
    "sg:phone":"+1 703 330 7517",
    "sg:postcode":"20110",
    "sg:province":"VA",
    "sg:tags":[
        "info",
        "addiction",
        "abuse",
        "treatment",
        "drug"
    ],
    "wof:name":"Cardinal Group",
    "wof:placetype":"venue"
},
  "geometry": {"coordinates":[-77.486401,38.769526],"type":"Point"}
}