{
  "type": "Feature",
  "properties": {
    "addr:full":"11015 Warwick Blvd Newport News VA 23601",
    "addr:housenumber":"11015",
    "addr:postcode":"23601",
    "addr:street":"Warwick Blvd",
    "iso:country":"US",
    "sg:address":"11015 Warwick Blvd",
    "sg:city":"Newport News",
    "sg:classifiers":[
        {
            "category":"Sports & Exercise",
            "subcategory":"Gym",
            "type":"Entertainment"
        }
    ],
    "sg:phone":"+1 757 344 9844",
    "sg:postcode":"23601",
    "sg:province":"VA",
    "sg:tags":[
        "fitness",
        "physical",
        "facility"
    ],
    "wof:name":"Fit Bodies Unlimited",
    "wof:placetype":"venue"
},
  "geometry": {"coordinates":[-76.473752,37.045344],"type":"Point"}
}