{
  "type": "Feature",
  "properties": {
    "addr:full":"1204 Olive Rd Virginia Beach VA 23464",
    "addr:housenumber":"1204",
    "addr:postcode":"23464",
    "addr:street":"Olive Rd",
    "iso:country":"US",
    "sg:address":"1204 Olive Rd",
    "sg:city":"Virginia Beach",
    "sg:classifiers":[
        {
            "category":"Building & Trades",
            "subcategory":"Construction",
            "type":"Services"
        }
    ],
    "sg:phone":"+1 757 237 9663",
    "sg:postcode":"23464",
    "sg:province":"VA",
    "sg:tags":[
        "resurfacing",
        "laying",
        "refinishing",
        "floor"
    ],
    "wof:name":"Ozark Flooring",
    "wof:placetype":"venue"
},
  "geometry": {"coordinates":[-76.169577,36.800374],"type":"Point"}
}