{
  "type": "Feature",
  "properties": {
    "iso:country":"US",
    "sg:address":"5801 Duke St Ste D108",
    "sg:city":"Alexandria",
    "sg:classifiers":[
        {
            "category":"Real Estate",
            "subcategory":"Real Estate Services",
            "type":"Services"
        },
        {
            "category":"Shopping Center",
            "type":"Public Place"
        }
    ],
    "sg:phone":"+1 703 333 2856",
    "sg:postcode":"22304",
    "sg:province":"VA",
    "sg:tags":[
        "mall",
        "management"
    ],
    "wof:name":"Landmark Mall",
    "wof:placetype":"venue"
},
  "geometry": {"coordinates":[-77.13364199999999,38.81432],"type":"Point"}
}