{
  "type": "Feature",
  "properties": {
    "addr:full":"4103 Chain Bridge Rd Fairfax VA 22030",
    "addr:housenumber":"4103",
    "addr:postcode":"22030",
    "addr:street":"Chain Bridge Rd",
    "iso:country":"US",
    "sg:address":"4103 Chain Bridge Rd",
    "sg:city":"Fairfax",
    "sg:classifiers":[
        {
            "category":"Professional",
            "subcategory":"Management & Consulting",
            "type":"Services"
        },
        {
            "category":"Professional",
            "subcategory":"Computer Services",
            "type":"Services"
        }
    ],
    "sg:phone":"+1 703 359 2680",
    "sg:postcode":"22030",
    "sg:province":"VA",
    "sg:tags":[
        "information",
        "business",
        "consultant",
        "system",
        "technology",
        "engineer"
    ],
    "sg:website":"www.cetech-inc.com",
    "wof:name":"Cetech Inc",
    "wof:placetype":"venue"
},
  "geometry": {"coordinates":[-77.307633,38.844285],"type":"Point"}
}