{
  "type": "Feature",
  "properties": {
    "addr:full":"307 Rosewood Ln Yorktown VA 23692",
    "addr:housenumber":"307",
    "addr:postcode":"23692",
    "addr:street":"Rosewood Ln",
    "iso:country":"US",
    "sg:address":"307 Rosewood Ln",
    "sg:city":"Yorktown",
    "sg:classifiers":[
        {
            "category":"Real Estate",
            "subcategory":"Architect",
            "type":"Services"
        }
    ],
    "sg:phone":"+1 757 890 0061",
    "sg:postcode":"23692",
    "sg:province":"VA",
    "sg:tags":[
        "home",
        "planning",
        "design"
    ],
    "wof:name":"Renaissance Design Group LTD",
    "wof:placetype":"venue"
},
  "geometry": {"coordinates":[-76.46631499999999,37.17806],"type":"Point"}
}