{
  "type": "Feature",
  "properties": {
    "addr:full":"90 River Birch Dr Great Falls VA 22066",
    "addr:housenumber":"90",
    "addr:postcode":"22066",
    "addr:street":"River Birch Dr",
    "iso:country":"US",
    "sg:address":"90 River Birch Dr",
    "sg:city":"Great Falls",
    "sg:classifiers":[
        {
            "category":"Professional",
            "subcategory":"Management & Consulting",
            "type":"Services"
        }
    ],
    "sg:phone":"+1 703 757 1362",
    "sg:postcode":"22066",
    "sg:province":"VA",
    "wof:name":"Dziak Group Inc",
    "wof:placetype":"venue"
},
  "geometry": {"coordinates":[-77.258607,39.024306],"type":"Point"}
}