{
  "type": "Feature",
  "properties": {
    "addr:full":"3008 Cardinal Dr Quinton VA 23141",
    "addr:housenumber":"3008",
    "addr:postcode":"23141",
    "addr:street":"Cardinal Dr",
    "iso:country":"US",
    "sg:address":"3008 Cardinal Dr",
    "sg:city":"Quinton",
    "sg:classifiers":[
        {
            "category":"Shopping",
            "subcategory":"Pharmacy",
            "type":"Retail Goods"
        }
    ],
    "sg:phone":"+1 804 932 4243",
    "sg:postcode":"23141",
    "sg:province":"VA",
    "sg:tags":[
        "store",
        "variety"
    ],
    "wof:name":"Varina Cardinal Pharmacy",
    "wof:placetype":"venue"
},
  "geometry": {"coordinates":[-77.17536,37.507708],"type":"Point"}
}