{
  "type": "Feature",
  "properties": {
    "addr:full":"11009 Nokesville Rd Manassas VA 20110",
    "addr:housenumber":"11009",
    "addr:postcode":"20110",
    "addr:street":"Nokesville Rd",
    "iso:country":"US",
    "sg:address":"11009 Nokesville Rd",
    "sg:city":"Manassas",
    "sg:classifiers":[
        {
            "category":"Home & Garden",
            "subcategory":"Building Materials",
            "type":"Retail Goods"
        }
    ],
    "sg:phone":"+1 703 365 8800",
    "sg:postcode":"20110",
    "sg:province":"VA",
    "sg:tags":[
        "paint"
    ],
    "wof:name":"Mc Cormick Paints",
    "wof:placetype":"venue"
},
  "geometry": {"coordinates":[-77.528538,38.738724],"type":"Point"}
}