{
  "type": "Feature",
  "properties": {
    "iso:country":"US",
    "sg:address":"805 Redbud Rd",
    "sg:city":"Blacksburg",
    "sg:classifiers":[
        {
            "category":"Building & Trades",
            "subcategory":"Construction",
            "type":"Services"
        }
    ],
    "sg:phone":"+1 540 951 9624",
    "sg:postcode":"24060",
    "sg:province":"VA",
    "sg:tags":[
        "home"
    ],
    "wof:name":"Goforth Construction Services",
    "wof:placetype":"venue"
},
  "geometry": {"coordinates":[-80.434005,37.24903],"type":"Point"}
}