{
  "type": "Feature",
  "properties": {
    "addr:full":"450 Wassona Dr Marion VA 24354",
    "addr:housenumber":"450",
    "addr:postcode":"24354",
    "addr:street":"Wassona Dr",
    "iso:country":"US",
    "sg:address":"450 Wassona Dr",
    "sg:city":"Marion",
    "sg:classifiers":[
        {
            "category":"Wholesale",
            "subcategory":"Non-durable Goods",
            "type":"Manufacturing & Wholesale Goods"
        }
    ],
    "sg:phone":"+1 276 783 2334",
    "sg:postcode":"24354",
    "sg:province":"VA",
    "wof:name":"T&S Distributors Inc",
    "wof:placetype":"venue"
},
  "geometry": {"coordinates":[-81.49848,36.849884],"type":"Point"}
}