{
  "type": "Feature",
  "properties": {
    "addr:full":"6837 Hollow Glen Ct Gainesville VA 20155",
    "addr:housenumber":"6837",
    "addr:postcode":"20155",
    "addr:street":"Hollow Glen Ct",
    "iso:country":"US",
    "sg:address":"6837 Hollow Glen Ct",
    "sg:city":"Gainesville",
    "sg:classifiers":[
        {
            "category":"Organizations",
            "subcategory":"Professional Association",
            "type":"Services"
        }
    ],
    "sg:phone":"+1 703 754 4426",
    "sg:postcode":"20155",
    "sg:province":"VA",
    "sg:tags":[
        "business"
    ],
    "wof:name":"Robert Glass",
    "wof:placetype":"venue"
},
  "geometry": {"coordinates":[-77.615471,38.80957],"type":"Point"}
}