{
  "type": "Feature",
  "properties": {
    "iso:country":"US",
    "sg:address":"14300 Midlothian Tpke B",
    "sg:city":"Midlothian",
    "sg:classifiers":[
        {
            "category":"Personal",
            "type":"Services"
        },
        {
            "category":"Autos & Motor Vehicles",
            "subcategory":"Auto Supplies",
            "type":"Retail Goods"
        },
        {
            "category":"Professional",
            "subcategory":"Detective & Security Services",
            "type":"Services"
        },
        {
            "category":"Building & Trades",
            "subcategory":"Electrical",
            "type":"Services"
        },
        {
            "category":"Retail",
            "subcategory":"Auto Repair",
            "type":"Services"
        }
    ],
    "sg:phone":"+1 804 755 1161",
    "sg:postcode":"23113",
    "sg:province":"VA",
    "sg:tags":[
        "control",
        "stereo",
        "monitoring",
        "electric",
        "automobile",
        "medical",
        "system",
        "accessory",
        "radio",
        "electrician",
        "alarm"
    ],
    "wof:name":"Automotive Accessories Unlimited Inc",
    "wof:placetype":"venue"
},
  "geometry": {"coordinates":[-77.66929500000001,37.50628],"type":"Point"}
}