{
  "type": "Feature",
  "properties": {
    "addr:full":"75 Nursery Ln NE Christiansburg VA 24073",
    "addr:housenumber":"75",
    "addr:postcode":"24073",
    "addr:street":"Nursery Ln Ne",
    "iso:country":"US",
    "sg:address":"75 Nursery Ln NE",
    "sg:city":"Christiansburg",
    "sg:classifiers":[
        {
            "category":"Building & Trades",
            "subcategory":"Landscaping Services",
            "type":"Services"
        }
    ],
    "sg:phone":"+1 540 382 3600",
    "sg:postcode":"24073",
    "sg:province":"VA",
    "sg:tags":[
        "florist",
        "supp",
        "landscape"
    ],
    "wof:name":"Accent Landscaping Nursery",
    "wof:placetype":"venue"
},
  "geometry": {"coordinates":[-80.340062,37.140127],"type":"Point"}
}