{
  "type": "Feature",
  "properties": {
    "iso:country":"US",
    "sg:address":"2001 Carroll Ave NW",
    "sg:city":"Roanoke",
    "sg:classifiers":[
        {
            "category":"Organizations",
            "subcategory":"Religious Organization",
            "type":"Services"
        }
    ],
    "sg:phone":"+1 540 344 8196",
    "sg:postcode":"24017",
    "sg:province":"VA",
    "sg:tags":[
        "church"
    ],
    "wof:name":"First Church of Brethren",
    "wof:placetype":"venue"
},
  "geometry": {"coordinates":[-79.96952899999999,37.289949],"type":"Point"}
}