{
  "type": "Feature",
  "properties": {
    "iso:country":"US",
    "sg:address":"14112 Bermuda Point Ct",
    "sg:city":"Chester",
    "sg:classifiers":[
        {
            "category":"Organizations",
            "subcategory":"Religious Organization",
            "type":"Services"
        }
    ],
    "sg:phone":"+1 804 530 1594",
    "sg:postcode":"23836",
    "sg:province":"VA",
    "wof:name":"Unlimited Faith Inc",
    "wof:placetype":"venue"
},
  "geometry": {"coordinates":[-77.33528,37.329188],"type":"Point"}
}