{
  "type": "Feature",
  "properties": {
    "addr:full":"711 Church St Ridgeway VA 24148",
    "addr:housenumber":"711",
    "addr:postcode":"24148",
    "addr:street":"Church St",
    "iso:country":"US",
    "sg:address":"711 Church St",
    "sg:city":"Ridgeway",
    "sg:classifiers":[
        {
            "category":"Shopping",
            "type":"Retail Goods"
        }
    ],
    "sg:phone":"+1 276 956 2601",
    "sg:postcode":"24148",
    "sg:province":"VA",
    "sg:tags":[
        "monument"
    ],
    "wof:name":"Mountain View Cemetery & Sales",
    "wof:placetype":"venue"
},
  "geometry": {"coordinates":[-79.871506,36.571593],"type":"Point"}
}