{
  "type": "Feature",
  "properties": {
    "addr:full":"424 Wittington Rd Chesapeake VA 23322",
    "addr:housenumber":"424",
    "addr:postcode":"23322",
    "addr:street":"Wittington Rd",
    "iso:country":"US",
    "sg:address":"424 Wittington Rd",
    "sg:city":"Chesapeake",
    "sg:classifiers":[
        {
            "category":"Professional",
            "subcategory":"Employment Agencies",
            "type":"Services"
        }
    ],
    "sg:phone":"+1 757 436 9738",
    "sg:postcode":"23322",
    "sg:province":"VA",
    "wof:name":"Dtrikes",
    "wof:placetype":"venue"
},
  "geometry": {"coordinates":[-76.27201700000001,36.705551],"type":"Point"}
}