{
  "type": "Feature",
  "properties": {
    "addr:full":"11110 Sandy Fields Rd Charles City VA 23030",
    "addr:housenumber":"11110",
    "addr:postcode":"23030",
    "addr:street":"Sandy Fields Rd",
    "iso:country":"US",
    "sg:address":"11110 Sandy Fields Rd",
    "sg:city":"Charles City",
    "sg:classifiers":[
        {
            "category":"Farming",
            "subcategory":"Nursery",
            "type":"Manufacturing & Wholesale Goods"
        }
    ],
    "sg:phone":"+1 804 829 6201",
    "sg:postcode":"23030",
    "sg:province":"VA",
    "sg:tags":[
        "grower"
    ],
    "wof:name":"Weyanoke Nursery",
    "wof:placetype":"venue"
},
  "geometry": {"coordinates":[-77.076342,37.293423],"type":"Point"}
}