{
  "type": "Feature",
  "properties": {
    "iso:country":"US",
    "sg:address":"5505 Jeffersonton Rd",
    "sg:city":"Jeffersonton",
    "sg:classifiers":[
        {
            "category":"Professional",
            "subcategory":"Business Services",
            "type":"Services"
        }
    ],
    "sg:phone":"+1 540 937 6148",
    "sg:postcode":"22724",
    "sg:province":"VA",
    "wof:name":"Free & Accepted Masons In",
    "wof:placetype":"venue"
},
  "geometry": {"coordinates":[-77.90719,38.623802],"type":"Point"}
}