{
  "type": "Feature",
  "properties": {
    "addr:full":"3130 Peters Creek Rd NW Roanoke VA 24019",
    "addr:housenumber":"3130",
    "addr:postcode":"24019",
    "addr:street":"Peters Creek Rd Nw",
    "iso:country":"US",
    "sg:address":"3130 Peters Creek Rd NW",
    "sg:city":"Roanoke",
    "sg:classifiers":[
        {
            "category":"Banks & Credit Unions",
            "subcategory":"Bank",
            "type":"Services"
        }
    ],
    "sg:phone":"+1 540 777 2010",
    "sg:postcode":"24019",
    "sg:province":"VA",
    "wof:name":"Bank Of Botetourt",
    "wof:placetype":"venue"
},
  "geometry": {"coordinates":[-79.999185,37.320458],"type":"Point"}
}