{
  "type": "Feature",
  "properties": {
    "addr:full":"6333 Myers Mill Rd Jeffersonton VA 22724",
    "addr:housenumber":"6333",
    "addr:postcode":"22724",
    "addr:street":"Myers Mill Rd",
    "iso:country":"US",
    "sg:address":"6333 Myers Mill Rd",
    "sg:city":"Jeffersonton",
    "sg:classifiers":[
        {
            "category":"Building & Trades",
            "subcategory":"Equipment Rental",
            "type":"Services"
        }
    ],
    "sg:phone":"+1 540 937 7117",
    "sg:postcode":"22724",
    "sg:province":"VA",
    "sg:tags":[
        "heavy",
        "construction"
    ],
    "wof:name":"Dunrite Leasing Co",
    "wof:placetype":"venue"
},
  "geometry": {"coordinates":[-77.896744,38.618729],"type":"Point"}
}