{
  "type": "Feature",
  "properties": {
    "addr:full":"167 E Davis St Culpeper VA 22701",
    "addr:housenumber":"167",
    "addr:postcode":"22701",
    "addr:street":"E Davis St",
    "iso:country":"US",
    "sg:address":"167 E Davis St",
    "sg:city":"Culpeper",
    "sg:classifiers":[
        {
            "category":"Retail",
            "subcategory":"Portrait Studio",
            "type":"Services"
        },
        {
            "category":"Professional",
            "subcategory":"Art Services",
            "type":"Services"
        }
    ],
    "sg:phone":"+1 540 825 1880",
    "sg:postcode":"22701",
    "sg:province":"VA",
    "sg:tags":[
        "photographer",
        "photography",
        "camera",
        "framing",
        "custom"
    ],
    "wof:name":"Alan's Photography Studio",
    "wof:placetype":"venue"
},
  "geometry": {"coordinates":[-77.99532499999999,38.473003],"type":"Point"}
}