{
  "type": "Feature",
  "properties": {
    "iso:country":"US",
    "sg:address":"2337 Chestnut Hill Ave",
    "sg:city":"Falls Church",
    "sg:classifiers":[
        {
            "category":"Retail",
            "subcategory":"Laundry & Dry Cleaning",
            "type":"Services"
        }
    ],
    "sg:phone":"+1 703 585 5900",
    "sg:postcode":"22043",
    "sg:province":"VA",
    "wof:name":"Thoro Clean Carpet Service",
    "wof:placetype":"venue"
},
  "geometry": {"coordinates":[-77.209869,38.895727],"type":"Point"}
}