{
  "type": "Feature",
  "properties": {
    "addr:full":"4829 Hampshire Ave Norfolk VA 23513",
    "addr:housenumber":"4829",
    "addr:postcode":"23513",
    "addr:street":"Hampshire Ave",
    "iso:country":"US",
    "sg:address":"4829 Hampshire Ave",
    "sg:city":"Norfolk",
    "sg:classifiers":[
        {
            "category":"Personal",
            "subcategory":"Beauty Salon",
            "type":"Services"
        }
    ],
    "sg:phone":"+1 757 857 5585",
    "sg:postcode":"23513",
    "sg:province":"VA",
    "sg:tags":[
        "shop"
    ],
    "wof:name":"Helens Beauty Secrets",
    "wof:placetype":"venue"
},
  "geometry": {"coordinates":[-76.236436,36.888357],"type":"Point"}
}