{
  "type": "Feature",
  "properties": {
    "iso:country":"US",
    "sg:address":"5245 Cobblers Stone Ct",
    "sg:city":"Glen Allen",
    "sg:classifiers":[
        {
            "category":"Professional",
            "type":"Services"
        }
    ],
    "sg:phone":"+1 804 364 8193",
    "sg:postcode":"23059",
    "sg:province":"VA",
    "wof:name":"Consumernet LLC",
    "wof:placetype":"venue"
},
  "geometry": {"coordinates":[-77.605509,37.661184],"type":"Point"}
}