{
  "type": "Feature",
  "properties": {
    "addr:full":"17 Lewis Dr Newport News VA 23606",
    "addr:housenumber":"17",
    "addr:postcode":"23606",
    "addr:street":"Lewis Dr",
    "iso:country":"US",
    "sg:address":"17 Lewis Dr",
    "sg:city":"Newport News",
    "sg:classifiers":[
        {
            "category":"Retail",
            "subcategory":"Repair Shop",
            "type":"Services"
        }
    ],
    "sg:phone":"+1 757 879 2745",
    "sg:postcode":"23606",
    "sg:province":"VA",
    "sg:tags":[
        "refrigeration"
    ],
    "wof:name":"Johnny Bruce Miller",
    "wof:placetype":"venue"
},
  "geometry": {"coordinates":[-76.49566299999999,37.097013],"type":"Point"}
}