{
  "type": "Feature",
  "properties": {
    "addr:full":"340 Old Franklin Tpke Rocky Mount VA 24151",
    "addr:housenumber":"340",
    "addr:postcode":"24151",
    "addr:street":"Old Franklin Tpke",
    "iso:country":"US",
    "sg:address":"340 Old Franklin Tpke",
    "sg:city":"Rocky Mount",
    "sg:classifiers":[
        {
            "category":"Professional",
            "subcategory":"Business Services",
            "type":"Services"
        }
    ],
    "sg:phone":"+1 540 489 4399",
    "sg:postcode":"24151",
    "sg:province":"VA",
    "sg:tags":[
        "interior",
        "consultant",
        "design",
        "decorator"
    ],
    "wof:name":"PAC Interiors & Floor",
    "wof:placetype":"venue"
},
  "geometry": {"coordinates":[-79.872243,37.009852],"type":"Point"}
}