{
  "type": "Feature",
  "properties": {
    "addr:full":"8419 Belle Haven Rd Roanoke VA 24019",
    "addr:housenumber":"8419",
    "addr:postcode":"24019",
    "addr:street":"Belle Haven Rd",
    "iso:country":"US",
    "sg:address":"8419 Belle Haven Rd",
    "sg:city":"Roanoke",
    "sg:classifiers":[
        {
            "category":"Building & Trades",
            "subcategory":"Construction",
            "type":"Services"
        }
    ],
    "sg:phone":"+1 540 563 0678",
    "sg:postcode":"24019",
    "sg:province":"VA",
    "sg:tags":[
        "house"
    ],
    "wof:name":"J&S Carpetry & Home Maint",
    "wof:placetype":"venue"
},
  "geometry": {"coordinates":[-79.978951,37.351989],"type":"Point"}
}