{
  "type": "Feature",
  "properties": {
    "iso:country":"US",
    "sg:address":"3331 Carlyn Ct",
    "sg:city":"Falls Church",
    "sg:classifiers":[
        {
            "category":"Professional",
            "subcategory":"Business Services",
            "type":"Services"
        }
    ],
    "sg:phone":"+1 703 379 4467",
    "sg:postcode":"22041",
    "sg:province":"VA",
    "wof:name":"Sev Advanced Writing Solutions",
    "wof:placetype":"venue"
},
  "geometry": {"coordinates":[-77.13727799999999,38.853904],"type":"Point"}
}