{
  "type": "Feature",
  "properties": {
    "addr:full":"12062 Center St Remington VA 22734",
    "addr:housenumber":"12062",
    "addr:postcode":"22734",
    "addr:street":"Center St",
    "iso:country":"US",
    "sg:address":"12062 Center St",
    "sg:city":"Remington",
    "sg:classifiers":[
        {
            "category":"Building & Trades",
            "subcategory":"Plumbing",
            "type":"Services"
        }
    ],
    "sg:phone":"+1 540 439 1764",
    "sg:postcode":"22734",
    "sg:province":"VA",
    "sg:tags":[
        "sheet",
        "work",
        "metal",
        "contractor"
    ],
    "wof:name":"Wayne Martin Sheet Metal",
    "wof:placetype":"venue"
},
  "geometry": {"coordinates":[-77.808735,38.53908],"type":"Point"}
}