{
  "type": "Feature",
  "properties": {
    "addr:full":"119 E Main St Salem VA 24153",
    "addr:housenumber":"119",
    "addr:postcode":"24153",
    "addr:street":"E Main St",
    "iso:country":"US",
    "sg:address":"119 E Main St",
    "sg:city":"Salem",
    "sg:classifiers":[
        {
            "category":"Shopping",
            "subcategory":"Used Merchandise",
            "type":"Retail Goods"
        }
    ],
    "sg:phone":"+1 540 444 0333",
    "sg:postcode":"24153",
    "sg:province":"VA",
    "sg:tags":[
        "antique"
    ],
    "wof:name":"Past Thymes",
    "wof:placetype":"venue"
},
  "geometry": {"coordinates":[-80.056095,37.293187],"type":"Point"}
}