{
  "type": "Feature",
  "properties": {
    "addr:full":"DESIGN IS IN THE DETAILS.\u00ae Arlington VA 22207",
    "addr:postcode":"22207",
    "addr:street":"R",
    "iso:country":"US",
    "sg:address":"DESIGN IS IN THE DETAILS.\u00ae",
    "sg:city":"Arlington",
    "sg:classifiers":[
        {
            "category":"Professional",
            "subcategory":"Management & Consulting",
            "type":"Services"
        },
        {
            "category":"Professional",
            "subcategory":"Advertising",
            "type":"Services"
        },
        {
            "category":"Professional",
            "subcategory":"Art Services",
            "type":"Services"
        },
        {
            "category":"Professional",
            "subcategory":"Computer Services",
            "type":"Services"
        }
    ],
    "sg:phone":"+1 888 377 4935",
    "sg:postcode":"22207",
    "sg:province":"VA",
    "sg:tags":[
        "web",
        "graphic",
        "government",
        "consultant",
        "marketing",
        "site",
        "designer",
        "design",
        "internet"
    ],
    "sg:website":"http://www.pixelgood.com",
    "wof:name":"PixelGood.?",
    "wof:placetype":"venue"
},
  "geometry": {"coordinates":[-77.121559,38.925941],"type":"Point"}
}