{
  "type": "Feature",
  "properties": {
    "iso:country":"US",
    "sg:address":"14301 S Crater Rd",
    "sg:city":"Petersburg",
    "sg:classifiers":[
        {
            "category":"Manufacturing",
            "subcategory":"Building Materials",
            "type":"Manufacturing & Wholesale Goods"
        },
        {
            "category":"Building & Trades",
            "subcategory":"Construction",
            "type":"Services"
        }
    ],
    "sg:phone":"+1 804 861 3171",
    "sg:postcode":"23805",
    "sg:province":"VA",
    "sg:tags":[
        "cabinet",
        "wood",
        "maker",
        "kitchen",
        "mfg"
    ],
    "wof:name":"Tri-City Industries Inc",
    "wof:placetype":"venue"
},
  "geometry": {"coordinates":[-77.349276,37.114872],"type":"Point"}
}