{
  "type": "Feature",
  "properties": {
    "iso:country":"US",
    "sg:address":"2604 Whispering Oaks Ct",
    "sg:city":"Midlothian",
    "sg:classifiers":[
        {
            "category":"Professional",
            "subcategory":"Business Services",
            "type":"Services"
        }
    ],
    "sg:phone":"+1 804 744 4885",
    "sg:postcode":"23112",
    "sg:province":"VA",
    "wof:name":"Jane Staley Interiors",
    "wof:placetype":"venue"
},
  "geometry": {"coordinates":[-77.66628900000001,37.452958],"type":"Point"}
}