{
  "type": "Feature",
  "properties": {
    "iso:country":"US",
    "sg:address":"1005 N Daniel St",
    "sg:city":"Arlington",
    "sg:classifiers":[
        {
            "category":"Professional",
            "subcategory":"Lawyer & Legal Services",
            "type":"Services"
        }
    ],
    "sg:phone":"+1 703 294 6183",
    "sg:postcode":"22201",
    "sg:province":"VA",
    "wof:name":"David W Elbaor",
    "wof:placetype":"venue"
},
  "geometry": {"coordinates":[-77.090564,38.884661],"type":"Point"}
}