{
  "type": "Feature",
  "properties": {
    "addr:full":"5411 Franconia Rd Alexandria VA 22310",
    "addr:housenumber":"5411",
    "addr:postcode":"22310",
    "addr:street":"Franconia Rd",
    "iso:country":"US",
    "sg:address":"5411 Franconia Rd",
    "sg:city":"Alexandria",
    "sg:classifiers":[
        {
            "category":"Education",
            "subcategory":"School",
            "type":"Public Place"
        }
    ],
    "sg:phone":"+1 703 971 0558",
    "sg:postcode":"22310",
    "sg:province":"VA",
    "sg:website":"www.ccmfamily.org",
    "wof:name":"Christian Center School",
    "wof:placetype":"venue"
},
  "geometry": {"coordinates":[-77.128798,38.784007],"type":"Point"}
}