{
  "type": "Feature",
  "properties": {
    "addr:full":"4011 Lee Jackson Memorial Hwy Fairfax VA 22033",
    "addr:housenumber":"4011",
    "addr:postcode":"22033",
    "addr:street":"Lee Jackson Memorial Hwy",
    "iso:country":"US",
    "sg:address":"4011 Lee Jackson Memorial Hwy",
    "sg:city":"Fairfax",
    "sg:classifiers":[
        {
            "category":"Insurance",
            "subcategory":"Hazard Insurance",
            "type":"Services"
        },
        {
            "category":"Insurance",
            "subcategory":"Health Insurance",
            "type":"Services"
        }
    ],
    "sg:phone":"+1 703 383 5400",
    "sg:postcode":"22033",
    "sg:province":"VA",
    "sg:tags":[
        "maintenance"
    ],
    "wof:name":"Kaiser Foundation Health Plan",
    "wof:placetype":"venue"
},
  "geometry": {"coordinates":[-77.346554,38.862915],"type":"Point"}
}