{
  "type": "Feature",
  "properties": {
    "addr:full":"115 2nd St SE Charlottesville VA 22902",
    "addr:housenumber":"115",
    "addr:postcode":"22902",
    "addr:street":"2Nd St Se",
    "iso:country":"US",
    "sg:address":"115 2nd St SE",
    "sg:city":"Charlottesville",
    "sg:classifiers":[
        {
            "category":"Museum",
            "type":"Entertainment"
        },
        {
            "category":"Organizations",
            "subcategory":"Non-profit Organization",
            "type":"Services"
        }
    ],
    "sg:phone":"+1 434 977 7284",
    "sg:postcode":"22902",
    "sg:province":"VA",
    "sg:tags":[
        "art",
        "gallery",
        "merchandise"
    ],
    "sg:website":"www.secondstreetgallery.com",
    "wof:name":"Second Street Gallery",
    "wof:placetype":"venue"
},
  "geometry": {"coordinates":[-78.48088799999999,38.030398],"type":"Point"}
}