{
  "type": "Feature",
  "properties": {
    "addr:full":"505 Jamestown Ave Portsmouth VA 23704",
    "addr:housenumber":"505",
    "addr:postcode":"23704",
    "addr:street":"Jamestown Ave",
    "iso:country":"US",
    "sg:address":"505 Jamestown Ave",
    "sg:city":"Portsmouth",
    "sg:classifiers":[
        {
            "category":"Social Services",
            "type":"Services"
        }
    ],
    "sg:phone":"+1 757 393 8926",
    "sg:postcode":"23704",
    "sg:province":"VA",
    "wof:name":"Community Services Board",
    "wof:placetype":"venue"
},
  "geometry": {"coordinates":[-76.323927,36.834022],"type":"Point"}
}