{
  "type": "Feature",
  "properties": {
    "addr:full":"4954 Sunset Ln Annandale VA 22003",
    "addr:housenumber":"4954",
    "addr:postcode":"22003",
    "addr:street":"Sunset Ln",
    "iso:country":"US",
    "sg:address":"4954 Sunset Ln",
    "sg:city":"Annandale",
    "sg:classifiers":[
        {
            "category":"Personal",
            "type":"Services"
        }
    ],
    "sg:phone":"+1 703 333 5355",
    "sg:postcode":"22003",
    "sg:province":"VA",
    "wof:name":"A W Handyman Services",
    "wof:placetype":"venue"
},
  "geometry": {"coordinates":[-77.18681599999999,38.815793],"type":"Point"}
}