{
  "type": "Feature",
  "properties": {
    "addr:full":"565 Radio Hill Rd Marion VA 24354",
    "addr:housenumber":"565",
    "addr:postcode":"24354",
    "addr:street":"Radio Hill Rd",
    "iso:country":"US",
    "sg:address":"565 Radio Hill Rd",
    "sg:city":"Marion",
    "sg:classifiers":[
        {
            "category":"Health Services",
            "subcategory":"Hospital",
            "type":"Services"
        }
    ],
    "sg:phone":"+1 276 782 1116",
    "sg:postcode":"24354",
    "sg:province":"VA",
    "sg:website":"www.scchosp.org",
    "wof:name":"Smyth County Comm Hospital",
    "wof:placetype":"venue"
},
  "geometry": {"coordinates":[-81.508702,36.85082],"type":"Point"}
}