{
  "type": "Feature",
  "properties": {
    "iso:country":"US",
    "sg:address":"263 W Main St",
    "sg:city":"Covington",
    "sg:classifiers":[
        {
            "category":"Professional",
            "subcategory":"Accounting & Tax Preparation",
            "type":"Services"
        }
    ],
    "sg:phone":"+1 540 965 0241",
    "sg:postcode":"24426",
    "sg:province":"VA",
    "sg:tags":[
        "accountant"
    ],
    "wof:name":"Harry Newman Inc",
    "wof:placetype":"venue"
},
  "geometry": {"coordinates":[-79.99515599999999,37.792597],"type":"Point"}
}