{
  "type": "Feature",
  "properties": {
    "addr:full":"3000 E River Rd Petersburg VA 23803",
    "addr:housenumber":"3000",
    "addr:postcode":"23803",
    "addr:street":"E River Rd",
    "iso:country":"US",
    "sg:address":"3000 E River Rd",
    "sg:city":"Petersburg",
    "sg:classifiers":[
        {
            "category":"Food & Beverages",
            "subcategory":"Groceries & Convenience Stores",
            "type":"Retail Goods"
        }
    ],
    "sg:phone":"+1 804 526 8116",
    "sg:postcode":"23803",
    "sg:province":"VA",
    "wof:name":"Ettrick Chevron",
    "wof:placetype":"venue"
},
  "geometry": {"coordinates":[-77.417239,37.243631],"type":"Point"}
}