{
  "type": "Feature",
  "properties": {
    "addr:full":"338 E Market St Leesburg VA 20176",
    "addr:housenumber":"338",
    "addr:postcode":"20176",
    "addr:street":"E Market St",
    "iso:country":"US",
    "sg:address":"338 E Market St",
    "sg:city":"Leesburg",
    "sg:classifiers":[
        {
            "category":"Food & Beverages",
            "subcategory":"Specialty",
            "type":"Retail Goods"
        }
    ],
    "sg:phone":"+1 703 777 6580",
    "sg:postcode":"20176",
    "sg:province":"VA",
    "sg:tags":[
        "product"
    ],
    "wof:name":"Lodestone Wellness",
    "wof:placetype":"venue"
},
  "geometry": {"coordinates":[-77.557653,39.111718],"type":"Point"}
}