{
  "type": "Feature",
  "properties": {
    "addr:full":"106 S Locust St Floyd VA 24091",
    "addr:housenumber":"106",
    "addr:postcode":"24091",
    "addr:street":"S Locust St",
    "iso:country":"US",
    "sg:address":"106 S Locust St",
    "sg:city":"Floyd",
    "sg:classifiers":[
        {
            "category":"Professional",
            "subcategory":"Lawyer & Legal Services",
            "type":"Services"
        }
    ],
    "sg:phone":"+1 540 745 3930",
    "sg:postcode":"24091",
    "sg:province":"VA",
    "sg:tags":[
        "attorney"
    ],
    "wof:name":"Stephanie Shortt PC Attorney",
    "wof:placetype":"venue"
},
  "geometry": {"coordinates":[-80.32028699999999,36.911149],"type":"Point"}
}