{
  "type": "Feature",
  "properties": {
    "iso:country":"US",
    "sg:address":"150 W Brambleton Ave",
    "sg:city":"Norfolk",
    "sg:classifiers":[
        {
            "category":"Social Services",
            "subcategory":"Adult Care",
            "type":"Services"
        }
    ],
    "sg:phone":"+1 757 446 2074",
    "sg:postcode":"23510",
    "sg:province":"VA",
    "sg:tags":[
        "organization",
        "senior",
        "citizen"
    ],
    "wof:name":"Seniority",
    "wof:placetype":"venue"
},
  "geometry": {"coordinates":[-76.290604,36.854281],"type":"Point"}
}