{
  "type": "Feature",
  "properties": {
    "addr:full":"690 S Main St Harrisonburg VA 22801",
    "addr:housenumber":"690",
    "addr:postcode":"22801",
    "addr:street":"S Main St",
    "iso:country":"US",
    "sg:address":"690 S Main St",
    "sg:city":"Harrisonburg",
    "sg:classifiers":[
        {
            "category":"Retail",
            "subcategory":"Auto Repair",
            "type":"Services"
        }
    ],
    "sg:phone":"+1 540 434 5500",
    "sg:postcode":"22801",
    "sg:province":"VA",
    "sg:tags":[
        "wrecker"
    ],
    "wof:name":"R & J Towing",
    "wof:placetype":"venue"
},
  "geometry": {"coordinates":[-78.87283600000001,38.442498],"type":"Point"}
}