{
  "type": "Feature",
  "properties": {
    "addr:full":"1155 International Pkwy Fredericksburg VA 22406",
    "addr:housenumber":"1155",
    "addr:postcode":"22406",
    "addr:street":"International Pkwy",
    "iso:country":"US",
    "sg:address":"1155 International Pkwy",
    "sg:city":"Fredericksburg",
    "sg:classifiers":[
        {
            "category":"Wholesale",
            "subcategory":"Vending Machines",
            "type":"Manufacturing & Wholesale Goods"
        }
    ],
    "sg:phone":"+1 540 752 5757",
    "sg:postcode":"22406",
    "sg:province":"VA",
    "wof:name":"Golden Coin Amusements Inc",
    "wof:placetype":"venue"
},
  "geometry": {"coordinates":[-77.513458,38.363263],"type":"Point"}
}