{
  "type": "Feature",
  "properties": {
    "addr:full":"9139 Hyde Ln Warrenton VA 20186",
    "addr:housenumber":"9139",
    "addr:postcode":"20186",
    "addr:street":"Hyde Ln",
    "iso:country":"US",
    "sg:address":"9139 Hyde Ln",
    "sg:city":"Warrenton",
    "sg:classifiers":[
        {
            "category":"Food & Beverages",
            "subcategory":"Specialty",
            "type":"Retail Goods"
        }
    ],
    "sg:phone":"+1 540 347 9678",
    "sg:postcode":"20186",
    "sg:province":"VA",
    "sg:tags":[
        "herb"
    ],
    "wof:name":"Family Thyme Herbs",
    "wof:placetype":"venue"
},
  "geometry": {"coordinates":[-77.884373,38.706769],"type":"Point"}
}