{
  "type": "Feature",
  "properties": {
    "addr:full":"4126 Winter Harbor Ct Chantilly VA 20151",
    "addr:housenumber":"4126",
    "addr:postcode":"20151",
    "addr:street":"Winter Harbor Ct",
    "iso:country":"US",
    "sg:address":"4126 Winter Harbor Ct",
    "sg:city":"Chantilly",
    "sg:classifiers":[
        {
            "category":"Wholesale",
            "subcategory":"Plants",
            "type":"Manufacturing & Wholesale Goods"
        }
    ],
    "sg:phone":"+1 703 378 2327",
    "sg:postcode":"20151",
    "sg:province":"VA",
    "sg:tags":[
        "supply"
    ],
    "wof:name":"Mac-Plants Enterprise",
    "wof:placetype":"venue"
},
  "geometry": {"coordinates":[-77.426136,38.888352],"type":"Point"}
}