{
  "type": "Feature",
  "properties": {
    "addr:full":"8210 Sinclair Mill Rd Manassas VA 20112",
    "addr:housenumber":"8210",
    "addr:postcode":"20112",
    "addr:street":"Sinclair Mill Rd",
    "iso:country":"US",
    "sg:address":"8210 Sinclair Mill Rd",
    "sg:city":"Manassas",
    "sg:classifiers":[
        {
            "category":"Retail",
            "subcategory":"Repair Shop",
            "type":"Services"
        }
    ],
    "sg:phone":"+1 703 791 5892",
    "sg:postcode":"20112",
    "sg:province":"VA",
    "wof:name":"Muffetts Cleaning S",
    "wof:placetype":"venue"
},
  "geometry": {"coordinates":[-77.451048,38.685139],"type":"Point"}
}