{
  "type": "Feature",
  "properties": {
    "iso:country":"US",
    "sg:address":"1508 Carroll Rd",
    "sg:city":"Goodview",
    "sg:classifiers":[
        {
            "category":"Building & Trades",
            "subcategory":"Construction",
            "type":"Services"
        }
    ],
    "sg:phone":"+1 540 890 3961",
    "sg:postcode":"24095",
    "sg:province":"VA",
    "sg:tags":[
        "house"
    ],
    "wof:name":"Light Brothers Construction",
    "wof:placetype":"venue"
},
  "geometry": {"coordinates":[-79.73207499999999,37.209603],"type":"Point"}
}