{
  "type": "Feature",
  "properties": {
    "iso:country":"US",
    "sg:address":"112 Mathews Grant",
    "sg:city":"Williamsburg",
    "sg:classifiers":[
        {
            "category":"Professional",
            "type":"Services"
        }
    ],
    "sg:phone":"+1 757 817 4632",
    "sg:postcode":"23185",
    "sg:province":"VA",
    "sg:tags":[
        "processing",
        "data"
    ],
    "wof:name":"Uibs",
    "wof:placetype":"venue"
},
  "geometry": {"coordinates":[-76.686809,37.236104],"type":"Point"}
}