{
  "type": "Feature",
  "properties": {
    "iso:country":"US",
    "sg:address":"1899 Churchville Rd",
    "sg:city":"West Point",
    "sg:classifiers":[
        {
            "category":"Organizations",
            "subcategory":"Religious Organization",
            "type":"Services"
        }
    ],
    "sg:phone":"+1 804 843 4794",
    "sg:postcode":"23181",
    "sg:province":"VA",
    "sg:tags":[
        "church"
    ],
    "wof:name":"Bethany Baptist Church",
    "wof:placetype":"venue"
},
  "geometry": {"coordinates":[-76.927869,37.603315],"type":"Point"}
}