{
  "type": "Feature",
  "properties": {
    "iso:country":"US",
    "sg:address":"6020 N Wilson Blvd",
    "sg:city":"Arlington",
    "sg:classifiers":[
        {
            "category":"Professional",
            "type":"Services"
        }
    ],
    "sg:phone":"+1 703 533 2057",
    "sg:postcode":"22205",
    "sg:province":"VA",
    "wof:name":"Arlington County Govt",
    "wof:placetype":"venue"
},
  "geometry": {"coordinates":[-77.140238,38.87356],"type":"Point"}
}