{
  "type": "Feature",
  "properties": {
    "iso:country":"US",
    "sg:address":"127 W Clay St",
    "sg:city":"Richmond",
    "sg:classifiers":[
        {
            "category":"Manufacturing",
            "subcategory":"Printing",
            "type":"Manufacturing & Wholesale Goods"
        }
    ],
    "sg:phone":"+1 804 344 8500",
    "sg:postcode":"23220",
    "sg:province":"VA",
    "sg:tags":[
        "commercial",
        "design",
        "publishing"
    ],
    "wof:name":"Cambell Marilyn",
    "wof:placetype":"venue"
},
  "geometry": {"coordinates":[-77.44203400000001,37.54827],"type":"Point"}
}