{
  "type": "Feature",
  "properties": {
    "addr:full":"5318 Hull Street Rd Richmond VA 23224",
    "addr:housenumber":"5318",
    "addr:postcode":"23224",
    "addr:street":"Hull Street Rd",
    "iso:country":"US",
    "sg:address":"5318 Hull Street Rd",
    "sg:city":"Richmond",
    "sg:classifiers":[
        {
            "category":"Real Estate",
            "subcategory":"Real Estate Operator",
            "type":"Services"
        }
    ],
    "sg:phone":"+1 804 232 2870",
    "sg:postcode":"23224",
    "sg:province":"VA",
    "sg:tags":[
        "apartment"
    ],
    "wof:name":"Pinebrook Apartments",
    "wof:placetype":"venue"
},
  "geometry": {"coordinates":[-77.488814,37.492367],"type":"Point"}
}