{
  "type": "Feature",
  "properties": {
    "iso:country":"US",
    "sg:address":"704 Yateley Ct",
    "sg:city":"Chesapeake",
    "sg:classifiers":[
        {
            "category":"Professional",
            "type":"Services"
        }
    ],
    "sg:phone":"+1 757 482 5475",
    "sg:postcode":"23322",
    "sg:province":"VA",
    "sg:tags":[
        "establishment"
    ],
    "wof:name":"Kraft & Kraft",
    "wof:placetype":"venue"
},
  "geometry": {"coordinates":[-76.202382,36.686832],"type":"Point"}
}