{
  "type": "Feature",
  "properties": {
    "iso:country":"US",
    "sg:address":"3892 Riner Rd",
    "sg:city":"Riner",
    "sg:classifiers":[
        {
            "category":"Freight",
            "type":"Transportation"
        }
    ],
    "sg:phone":"+1 540 382 9679",
    "sg:postcode":"24149",
    "sg:province":"VA",
    "sg:tags":[
        "distance",
        "long",
        "trucking"
    ],
    "wof:name":"L G S Inc",
    "wof:placetype":"venue"
},
  "geometry": {"coordinates":[-80.442042,37.069014],"type":"Point"}
}