{
  "type": "Feature",
  "properties": {
    "addr:full":"201 E Jackson St Front Royal VA 22630",
    "addr:housenumber":"201",
    "addr:postcode":"22630",
    "addr:street":"E Jackson St",
    "iso:country":"US",
    "sg:address":"201 E Jackson St",
    "sg:city":"Front Royal",
    "sg:classifiers":[
        {
            "category":"Retail",
            "subcategory":"Laundry & Dry Cleaning",
            "type":"Services"
        },
        {
            "category":"Shopping",
            "subcategory":"Clothing, Apparel, & Fashions",
            "type":"Retail Goods"
        }
    ],
    "sg:phone":"+1 540 636 8045",
    "sg:postcode":"22630",
    "sg:province":"VA",
    "sg:tags":[
        "alteration"
    ],
    "wof:name":"Sue's Sewing & Embroidery",
    "wof:placetype":"venue"
},
  "geometry": {"coordinates":[-78.19182499999999,38.916787],"type":"Point"}
}