{
  "type": "Feature",
  "properties": {
    "addr:full":"2209 N Pershing Dr Arlington VA 22201",
    "addr:housenumber":"2209",
    "addr:postcode":"22201",
    "addr:street":"N Pershing Dr",
    "iso:country":"US",
    "sg:address":"2209 N Pershing Dr",
    "sg:city":"Arlington",
    "sg:classifiers":[
        {
            "category":"Personal",
            "subcategory":"Shoe Repair & Shine",
            "type":"Services"
        }
    ],
    "sg:phone":"+1 703 527 6894",
    "sg:postcode":"22201",
    "sg:province":"VA",
    "wof:name":"Modern Shoe Repair",
    "wof:placetype":"venue"
},
  "geometry": {"coordinates":[-77.08569300000001,38.880699],"type":"Point"}
}