{
  "type": "Feature",
  "properties": {
    "iso:country":"US",
    "sg:address":"18476 Canteberry Ln",
    "sg:city":"Smithfield",
    "sg:classifiers":[
        {
            "category":"Banks & Credit Unions",
            "subcategory":"Bank",
            "type":"Services"
        }
    ],
    "sg:phone":"+1 757 357 2777",
    "sg:postcode":"23430",
    "sg:province":"VA",
    "wof:name":"Whitehead Insurance Agency Inc",
    "wof:placetype":"venue"
},
  "geometry": {"coordinates":[-76.601097,36.9571],"type":"Point"}
}