{
  "type": "Feature",
  "properties": {
    "iso:country":"US",
    "sg:address":"9738 Nazarene Church Rd",
    "sg:city":"Bridgewater",
    "sg:classifiers":[
        {
            "category":"Building & Trades",
            "subcategory":"Construction",
            "type":"Services"
        }
    ],
    "sg:phone":"+1 540 828 3684",
    "sg:postcode":"22812",
    "sg:province":"VA",
    "sg:tags":[
        "masonry",
        "contractor"
    ],
    "wof:name":"A & C Masonry",
    "wof:placetype":"venue"
},
  "geometry": {"coordinates":[-79.078028,38.418226],"type":"Point"}
}