{
  "type": "Feature",
  "properties": {
    "addr:full":"2910 Meadow Ln Falls Church VA 22042",
    "addr:housenumber":"2910",
    "addr:postcode":"22042",
    "addr:street":"Meadow Ln",
    "iso:country":"US",
    "sg:address":"2910 Meadow Ln",
    "sg:city":"Falls Church",
    "sg:classifiers":[
        {
            "category":"Professional",
            "subcategory":"Management & Consulting",
            "type":"Services"
        }
    ],
    "sg:phone":"+1 703 532 8289",
    "sg:postcode":"22042",
    "sg:province":"VA",
    "sg:tags":[
        "business"
    ],
    "wof:name":"Creek Walker Consulting Inc",
    "wof:placetype":"venue"
},
  "geometry": {"coordinates":[-77.167663,38.874041],"type":"Point"}
}