{
  "type": "Feature",
  "properties": {
    "addr:full":"1919 Westover Ave SW Roanoke VA 24015",
    "addr:housenumber":"1919",
    "addr:postcode":"24015",
    "addr:street":"Westover Ave Sw",
    "iso:country":"US",
    "sg:address":"1919 Westover Ave SW",
    "sg:city":"Roanoke",
    "sg:classifiers":[
        {
            "category":"Restaurant",
            "type":"Food & Drink"
        }
    ],
    "sg:phone":"+1 540 981 1078",
    "sg:postcode":"24015",
    "sg:province":"VA",
    "sg:tags":[
        "caterer"
    ],
    "wof:name":"Murphy's Of Course",
    "wof:placetype":"venue"
},
  "geometry": {"coordinates":[-79.977073,37.264612],"type":"Point"}
}