{
  "type": "Feature",
  "properties": {
    "iso:country":"US",
    "sg:address":"5256 Crooked Creek Ln",
    "sg:city":"King George",
    "sg:classifiers":[
        {
            "category":"Building & Trades",
            "subcategory":"Plumbing",
            "type":"Services"
        }
    ],
    "sg:phone":"+1 540 644 8188",
    "sg:postcode":"22485",
    "sg:province":"VA",
    "sg:tags":[
        "contractor"
    ],
    "wof:name":"B&B Enterprises",
    "wof:placetype":"venue"
},
  "geometry": {"coordinates":[-77.098405,38.342963],"type":"Point"}
}