{
  "type": "Feature",
  "properties": {
    "addr:full":"2325 N Franklin St Christiansburg VA 24073",
    "addr:housenumber":"2325",
    "addr:postcode":"24073",
    "addr:street":"N Franklin St",
    "iso:country":"US",
    "sg:address":"2325 N Franklin St",
    "sg:city":"Christiansburg",
    "sg:classifiers":[
        {
            "category":"Banks & Credit Unions",
            "subcategory":"Bank",
            "type":"Services"
        }
    ],
    "sg:phone":"+1 540 381 6236",
    "sg:postcode":"24073",
    "sg:province":"VA",
    "sg:tags":[
        "mortgage"
    ],
    "wof:name":"Wachodia Mortgage Corporation",
    "wof:placetype":"venue"
},
  "geometry": {"coordinates":[-80.42238,37.161407],"type":"Point"}
}