{
  "type": "Feature",
  "properties": {
    "iso:country":"US",
    "sg:address":"122 Dogwood Tree Dr",
    "sg:city":"Front Royal",
    "sg:classifiers":[
        {
            "category":"Professional",
            "subcategory":"Computer Services",
            "type":"Services"
        }
    ],
    "sg:phone":"+1 540 635 3357",
    "sg:postcode":"22630",
    "sg:province":"VA",
    "wof:name":"Warren Electronics",
    "wof:placetype":"venue"
},
  "geometry": {"coordinates":[-78.155368,38.86809],"type":"Point"}
}