{
  "type": "Feature",
  "properties": {
    "addr:full":"30363 Hicks Rd Spotsylvania VA 22508",
    "addr:housenumber":"30363",
    "addr:postcode":"22508",
    "addr:street":"Hicks Rd",
    "iso:country":"US",
    "sg:address":"30363 Hicks Rd",
    "sg:city":"Spotsylvania",
    "sg:classifiers":[
        {
            "category":"Professional",
            "subcategory":"Management & Consulting",
            "type":"Services"
        }
    ],
    "sg:phone":"+1 540 854 8630",
    "sg:postcode":"22508",
    "sg:province":"VA",
    "sg:tags":[
        "consultant",
        "safety"
    ],
    "sg:website":"www.system-safety.org",
    "wof:name":"System Safety Society",
    "wof:placetype":"venue"
},
  "geometry": {"coordinates":[-77.85249899999999,38.228204],"type":"Point"}
}