{
  "type": "Feature",
  "properties": {
    "addr:full":"112 S Patrick St Alexandria VA 22314",
    "addr:housenumber":"112",
    "addr:postcode":"22314",
    "addr:street":"S Patrick St",
    "iso:country":"US",
    "sg:address":"112 S Patrick St",
    "sg:city":"Alexandria",
    "sg:classifiers":[
        {
            "category":"Professional",
            "subcategory":"Management & Consulting",
            "type":"Services"
        }
    ],
    "sg:phone":"+1 703 683 2800",
    "sg:postcode":"22314",
    "sg:province":"VA",
    "sg:tags":[
        "consultant",
        "r",
        "commercial",
        "business",
        "nonphysical"
    ],
    "wof:name":"Capitol Representation Inc",
    "wof:placetype":"venue"
},
  "geometry": {"coordinates":[-77.05028799999999,38.805482],"type":"Point"}
}