{
  "type": "Feature",
  "properties": {
    "addr:full":"4413 1st St S Arlington VA 22204",
    "addr:housenumber":"4413",
    "addr:postcode":"22204",
    "addr:street":"1St St S",
    "iso:country":"US",
    "sg:address":"4413 1st St S",
    "sg:city":"Arlington",
    "sg:classifiers":[
        {
            "category":"Professional",
            "subcategory":"Computer Services",
            "type":"Services"
        }
    ],
    "sg:phone":"+1 703 930 5383",
    "sg:postcode":"22204",
    "sg:province":"VA",
    "sg:tags":[
        "development",
        "consulting",
        "software"
    ],
    "wof:name":"Metalake LLC",
    "wof:placetype":"venue"
},
  "geometry": {"coordinates":[-77.11045,38.866769],"type":"Point"}
}