{
  "type": "Feature",
  "properties": {
    "iso:country":"US",
    "sg:address":"8071 Mechanicsville Tpke",
    "sg:city":"Mechanicsville",
    "sg:classifiers":[
        {
            "category":"Banks & Credit Unions",
            "subcategory":"Bank",
            "type":"Services"
        }
    ],
    "sg:phone":"+1 804 559 9000",
    "sg:postcode":"23111",
    "sg:province":"VA",
    "sg:website":"www.hanoverbank.net",
    "wof:name":"Hanover Bank",
    "wof:placetype":"venue"
},
  "geometry": {"coordinates":[-77.37566200000001,37.601148],"type":"Point"}
}