{
  "type": "Feature",
  "properties": {
    "addr:full":"15402 Nelson Hill Rd Milford VA 22514",
    "addr:housenumber":"15402",
    "addr:postcode":"22514",
    "addr:street":"Nelson Hill Rd",
    "iso:country":"US",
    "sg:address":"15402 Nelson Hill Rd",
    "sg:city":"Milford",
    "sg:classifiers":[
        {
            "category":"Retail",
            "subcategory":"Auto Repair",
            "type":"Services"
        }
    ],
    "sg:phone":"+1 804 633 1571",
    "sg:postcode":"22514",
    "sg:province":"VA",
    "sg:tags":[
        "truck"
    ],
    "wof:name":"Hanover Truck Repair",
    "wof:placetype":"venue"
},
  "geometry": {"coordinates":[-77.37699600000001,38.019147],"type":"Point"}
}