{
  "type": "Feature",
  "properties": {
    "addr:full":"9253 Marlow Ave Norfolk VA 23503",
    "addr:housenumber":"9253",
    "addr:postcode":"23503",
    "addr:street":"Marlow Ave",
    "iso:country":"US",
    "sg:address":"9253 Marlow Ave",
    "sg:city":"Norfolk",
    "sg:classifiers":[
        {
            "category":"Insurance",
            "subcategory":"Title Insurance",
            "type":"Services"
        }
    ],
    "sg:phone":"+1 757 587 1228",
    "sg:postcode":"23503",
    "sg:province":"VA",
    "sg:tags":[
        "carrier"
    ],
    "wof:name":"Security American Exports",
    "wof:placetype":"venue"
},
  "geometry": {"coordinates":[-76.26561599999999,36.946129],"type":"Point"}
}