{
  "type": "Feature",
  "properties": {
    "addr:full":"15651 Bleak Hill Rd Culpeper VA 22701",
    "addr:postcode":"15651;22701",
    "addr:street":"Bleak Hill Rd",
    "iso:country":"US",
    "sg:address":"15651 Bleak Hill Rd",
    "sg:city":"Culpeper",
    "sg:classifiers":[
        {
            "category":"Professional",
            "type":"Services"
        }
    ],
    "sg:phone":"+1 540 829 0809",
    "sg:postcode":"22701",
    "sg:province":"VA",
    "wof:name":"Aqua-Tek",
    "wof:placetype":"venue"
},
  "geometry": {"coordinates":[-77.957685,38.540784],"type":"Point"}
}