{
  "type": "Feature",
  "properties": {
    "addr:full":"2229 Yorktown Ave Lynchburg VA 24501",
    "addr:housenumber":"2229",
    "addr:postcode":"24501",
    "addr:street":"Yorktown Ave",
    "iso:country":"US",
    "sg:address":"2229 Yorktown Ave",
    "sg:city":"Lynchburg",
    "sg:classifiers":[
        {
            "category":"Social Services",
            "subcategory":"Adult Care",
            "type":"Services"
        }
    ],
    "sg:phone":"+1 434 528 5225",
    "sg:postcode":"24501",
    "sg:province":"VA",
    "sg:tags":[
        "residential"
    ],
    "wof:name":"Alfreda Payne",
    "wof:placetype":"venue"
},
  "geometry": {"coordinates":[-79.176602,37.411493],"type":"Point"}
}