{
  "type": "Feature",
  "properties": {
    "iso:country":"US",
    "sg:address":"11447 Walters Rd",
    "sg:city":"Orange",
    "sg:classifiers":[
        {
            "category":"Building & Trades",
            "subcategory":"Construction",
            "type":"Services"
        }
    ],
    "sg:phone":"+1 540 672 3877",
    "sg:postcode":"22960",
    "sg:province":"VA",
    "sg:tags":[
        "contractor"
    ],
    "wof:name":"Orange Masonry Inc",
    "wof:placetype":"venue"
},
  "geometry": {"coordinates":[-78.075669,38.241855],"type":"Point"}
}