{
  "type": "Feature",
  "properties": {
    "addr:full":"111 Carpenter Dr Sterling VA 20164",
    "addr:housenumber":"111",
    "addr:postcode":"20164",
    "addr:street":"Carpenter Dr",
    "iso:country":"US",
    "sg:address":"111 Carpenter Dr",
    "sg:city":"Sterling",
    "sg:classifiers":[
        {
            "category":"Utilities",
            "subcategory":"Telephone",
            "type":"Services"
        }
    ],
    "sg:phone":"+1 703 481 4500",
    "sg:postcode":"20164",
    "sg:province":"VA",
    "sg:tags":[
        "company"
    ],
    "wof:name":"Wireless Systems Engineering",
    "wof:placetype":"venue"
},
  "geometry": {"coordinates":[-77.419487,38.991278],"type":"Point"}
}