{
  "type": "Feature",
  "properties": {
    "addr:full":"28524 Phillips Dr Melfa VA 23410",
    "addr:housenumber":"28524",
    "addr:postcode":"melfa;23410",
    "addr:street":"Phillips Dr",
    "iso:country":"US",
    "sg:address":"28524 Phillips Dr",
    "sg:city":"Melfa",
    "sg:classifiers":[
        {
            "category":"Farming",
            "subcategory":"Farm",
            "type":"Manufacturing & Wholesale Goods"
        }
    ],
    "sg:phone":"+1 757 787 1823",
    "sg:postcode":"23410",
    "sg:province":"VA",
    "sg:tags":[
        "crop",
        "general"
    ],
    "wof:name":"Donny & Donald",
    "wof:placetype":"venue"
},
  "geometry": {"coordinates":[-75.727996,37.650843],"type":"Point"}
}