{
  "type": "Feature",
  "properties": {
    "iso:country":"US",
    "sg:address":"736 Merrimac Trl",
    "sg:city":"Williamsburg",
    "sg:phone":"+1 757 229 1924",
    "sg:postcode":"23185",
    "sg:province":"VA",
    "sg:website":"http://www.ljsilvers.com",
    "wof:name":"Long John Silver's",
    "wof:placetype":"venue"
},
  "geometry": {"coordinates":[-76.67657,37.267852],"type":"Point"}
}