{
  "type": "Feature",
  "properties": {
    "iso:country":"US",
    "sg:address":"4605 New Kent Ave",
    "sg:city":"Richmond",
    "sg:classifiers":[
        {
            "category":"Professional",
            "subcategory":"Management & Consulting",
            "type":"Services"
        }
    ],
    "sg:phone":"+1 804 231 2081",
    "sg:postcode":"23225",
    "sg:province":"VA",
    "sg:tags":[
        "public",
        "relations"
    ],
    "wof:name":"Mary R Martin Inc",
    "wof:placetype":"venue"
},
  "geometry": {"coordinates":[-77.481967,37.52341],"type":"Point"}
}