{
  "type": "Feature",
  "properties": {
    "addr:full":"215 Fort Evans Rd NE Leesburg VA 20176",
    "addr:housenumber":"215",
    "addr:postcode":"20176",
    "addr:street":"Fort Evans Rd Ne",
    "iso:country":"US",
    "sg:address":"215 Fort Evans Rd NE",
    "sg:city":"Leesburg",
    "sg:classifiers":[
        {
            "category":"Fast Food",
            "type":"Food & Drink"
        },
        {
            "category":"Coffee & Tea",
            "type":"Food & Drink"
        },
        {
            "category":"Restaurant",
            "type":"Food & Drink"
        },
        {
            "category":"Bakery",
            "type":"Food & Drink"
        },
        {
            "category":"Food & Beverages",
            "subcategory":"Groceries & Convenience Stores",
            "type":"Retail Goods"
        }
    ],
    "sg:phone":"+1 703 669 0411",
    "sg:postcode":"20176",
    "sg:province":"VA",
    "sg:tags":[
        "shop",
        "sandwich",
        "espresso",
        "take"
    ],
    "sg:website":"http://www.panerabread.com",
    "wof:name":"Panera Bread",
    "wof:placetype":"venue"
},
  "geometry": {"coordinates":[-77.536676,39.109822],"type":"Point"}
}