{
  "type": "Feature",
  "properties": {
    "iso:country":"US",
    "sg:address":"9992 Main St",
    "sg:city":"Fairfax",
    "sg:classifiers":[
        {
            "category":"Retail",
            "subcategory":"Repair Shop",
            "type":"Services"
        }
    ],
    "sg:phone":"+1 703 359 1444",
    "sg:postcode":"22031",
    "sg:province":"VA",
    "sg:tags":[
        "lock",
        "locksmith"
    ],
    "wof:name":"A 1 Emergency Locksmith Inc",
    "wof:placetype":"venue"
},
  "geometry": {"coordinates":[-77.290768,38.843669],"type":"Point"}
}