{
  "type": "Feature",
  "properties": {
    "addr:full":"1369 S Military Hwy Chesapeake VA 23320",
    "addr:housenumber":"1369",
    "addr:postcode":"23320",
    "addr:street":"S Military Hwy",
    "iso:country":"US",
    "sg:address":"1369 S Military Hwy",
    "sg:city":"Chesapeake",
    "sg:classifiers":[
        {
            "category":"Personal",
            "subcategory":"Barber",
            "type":"Services"
        }
    ],
    "sg:phone":"+1 757 420 6406",
    "sg:postcode":"23320",
    "sg:province":"VA",
    "sg:tags":[
        "shop",
        "beauty"
    ],
    "wof:name":"Charlies Unisex Barbra Shop",
    "wof:placetype":"venue"
},
  "geometry": {"coordinates":[-76.22912700000001,36.801923],"type":"Point"}
}