{
  "type": "Feature",
  "properties": {
    "addr:full":"12290 Cedar Keep Ln Ashland VA 23005",
    "addr:housenumber":"12290",
    "addr:postcode":"23005",
    "addr:street":"Cedar Keep Ln",
    "iso:country":"US",
    "sg:address":"12290 Cedar Keep Ln",
    "sg:city":"Ashland",
    "sg:classifiers":[
        {
            "category":"Professional",
            "subcategory":"Business Services",
            "type":"Services"
        }
    ],
    "sg:phone":"+1 804 752 7492",
    "sg:postcode":"23005",
    "sg:province":"VA",
    "wof:name":"Glave Enterprises Inc",
    "wof:placetype":"venue"
},
  "geometry": {"coordinates":[-77.439374,37.742413],"type":"Point"}
}