{
  "type": "Feature",
  "properties": {
    "iso:country":"US",
    "sg:address":"802 Ridge Rd",
    "sg:city":"Chester",
    "sg:classifiers":[
        {
            "category":"Professional",
            "type":"Services"
        }
    ],
    "sg:phone":"+1 804 530 1270",
    "sg:postcode":"23824",
    "sg:province":"VA",
    "sg:tags":[
        "personal"
    ],
    "wof:name":"Joyce P Jones",
    "wof:placetype":"venue"
},
  "geometry": {"coordinates":[-77.99376100000001,37.056245],"type":"Point"}
}