{
  "type": "Feature",
  "properties": {
    "addr:full":"620 Jamestown Rd Williamsburg VA 23185",
    "addr:housenumber":"620",
    "addr:postcode":"23185",
    "addr:street":"Jamestown Rd",
    "iso:country":"US",
    "sg:address":"620 Jamestown Rd",
    "sg:city":"Williamsburg",
    "sg:classifiers":[
        {
            "category":"Organizations",
            "subcategory":"Religious Organization",
            "type":"Services"
        }
    ],
    "sg:phone":"+1 757 229 3820",
    "sg:postcode":"23185",
    "sg:province":"VA",
    "wof:name":"Christian Science",
    "wof:placetype":"venue"
},
  "geometry": {"coordinates":[-76.715568,37.266835],"type":"Point"}
}