{
  "type": "Feature",
  "properties": {
    "addr:full":"136 Peyton Rd Williamsburg VA 23185",
    "addr:housenumber":"136",
    "addr:postcode":"23185",
    "addr:street":"Peyton Rd",
    "iso:country":"US",
    "sg:address":"136 Peyton Rd",
    "sg:city":"Williamsburg",
    "sg:classifiers":[
        {
            "category":"Professional",
            "type":"Services"
        }
    ],
    "sg:phone":"+1 757 564 8542",
    "sg:postcode":"23185",
    "sg:province":"VA",
    "wof:name":"Parishes Online LLC",
    "wof:placetype":"venue"
},
  "geometry": {"coordinates":[-76.676648,37.245142],"type":"Point"}
}