{
  "type": "Feature",
  "properties": {
    "addr:full":"1995 Jefferson Davis Hwy Stafford VA 22554",
    "addr:housenumber":"1995",
    "addr:postcode":"22554",
    "addr:street":"Jefferson Davis Hwy",
    "iso:country":"US",
    "sg:address":"1995 Jefferson Davis Hwy",
    "sg:city":"Stafford",
    "sg:classifiers":[
        {
            "category":"Health Services",
            "subcategory":"Doctor",
            "type":"Services"
        }
    ],
    "sg:phone":"+1 540 899 7791",
    "sg:postcode":"22554",
    "sg:province":"VA",
    "sg:tags":[
        "dentist"
    ],
    "wof:name":"Cathie H Butterworth DDS",
    "wof:placetype":"venue"
},
  "geometry": {"coordinates":[-77.41029,38.414411],"type":"Point"}
}