{
  "type": "Feature",
  "properties": {
    "addr:full":"224 Main St Port Royal VA 22535",
    "addr:housenumber":"224",
    "addr:postcode":"22535",
    "addr:street":"Main St",
    "iso:country":"US",
    "sg:address":"224 Main St",
    "sg:city":"Port Royal",
    "sg:classifiers":[
        {
            "category":"Professional",
            "subcategory":"Testing Lab",
            "type":"Services"
        }
    ],
    "sg:phone":"+1 804 742 5577",
    "sg:postcode":"22535",
    "sg:province":"VA",
    "sg:tags":[
        "environmental",
        "laboratory"
    ],
    "wof:name":"Mid Atlantic Laboratories Inc",
    "wof:placetype":"venue"
},
  "geometry": {"coordinates":[-77.191131,38.171733],"type":"Point"}
}