{
  "type": "Feature",
  "properties": {
    "iso:country":"US",
    "sg:address":"1601 Littlepage St",
    "sg:city":"Richmond",
    "sg:classifiers":[
        {
            "category":"Place Of Worship",
            "subcategory":"Church",
            "type":"Public Place"
        },
        {
            "category":"Place Of Worship",
            "type":"Public Place"
        }
    ],
    "sg:phone":"+1 804 644 8898",
    "sg:postcode":"23223",
    "sg:province":"VA",
    "sg:tags":[
        "churches-presbyterian-arp",
        "churches-presbyterian"
    ],
    "wof:name":"Eastminster Presbyterian Church",
    "wof:placetype":"venue"
},
  "geometry": {"coordinates":[-77.41806,37.544689],"type":"Point"}
}