{
  "type": "Feature",
  "properties": {
    "addr:full":"350 Sinegar Pl Great Falls VA 22066",
    "addr:housenumber":"350",
    "addr:postcode":"22066",
    "addr:street":"Sinegar Pl",
    "iso:country":"US",
    "sg:address":"350 Sinegar Pl",
    "sg:city":"Great Falls",
    "sg:classifiers":[
        {
            "category":"Professional",
            "type":"Services"
        }
    ],
    "sg:phone":"+1 703 433 0579",
    "sg:postcode":"22066",
    "sg:province":"VA",
    "sg:tags":[
        "establishment"
    ],
    "wof:name":"South 49 Solutions",
    "wof:placetype":"venue"
},
  "geometry": {"coordinates":[-77.34016,39.042025],"type":"Point"}
}