{
  "type": "Feature",
  "properties": {
    "iso:country":"US",
    "sg:address":"5122 Upland Game Rd",
    "sg:city":"Roanoke",
    "sg:classifiers":[
        {
            "category":"Health Services",
            "subcategory":"Doctor",
            "type":"Services"
        }
    ],
    "sg:phone":"+1 540 345 0907",
    "sg:postcode":"24018",
    "sg:province":"VA",
    "sg:tags":[
        "physician",
        "surgeon"
    ],
    "wof:name":"Crailion Internal Medicine",
    "wof:placetype":"venue"
},
  "geometry": {"coordinates":[-79.96914099999999,37.208007],"type":"Point"}
}