{
  "type": "Feature",
  "properties": {
    "addr:full":"3533 Devon Dr Falls Church VA 22042",
    "addr:housenumber":"3533",
    "addr:postcode":"22042",
    "addr:street":"Devon Dr",
    "iso:country":"US",
    "sg:address":"3533 Devon Dr",
    "sg:city":"Falls Church",
    "sg:classifiers":[
        {
            "category":"Professional",
            "subcategory":"Computer Services",
            "type":"Services"
        }
    ],
    "sg:phone":"+1 703 237 4516",
    "sg:postcode":"22042",
    "sg:province":"VA",
    "sg:tags":[
        "datum"
    ],
    "wof:name":"Joyce Turk",
    "wof:placetype":"venue"
},
  "geometry": {"coordinates":[-77.177065,38.848043],"type":"Point"}
}