{
  "type": "Feature",
  "properties": {
    "addr:full":"2010 S Loudoun St Winchester VA 22601",
    "addr:housenumber":"2010",
    "addr:postcode":"22601",
    "addr:street":"S Loudoun St",
    "iso:country":"US",
    "sg:address":"2010 S Loudoun St",
    "sg:city":"Winchester",
    "sg:classifiers":[
        {
            "category":"Home & Garden",
            "subcategory":"Household Appliances",
            "type":"Retail Goods"
        }
    ],
    "sg:phone":"+1 540 722 6271",
    "sg:postcode":"22601",
    "sg:province":"VA",
    "sg:tags":[
        "repair",
        "electrical"
    ],
    "wof:name":"Discount Vac Shack",
    "wof:placetype":"venue"
},
  "geometry": {"coordinates":[-78.171828,39.165012],"type":"Point"}
}