{
  "type": "Feature",
  "properties": {
    "addr:full":"12533 Dillingham Sq Woodbridge VA 22192",
    "addr:housenumber":"12533",
    "addr:postcode":"22192",
    "addr:street":"Dillingham Sq",
    "iso:country":"US",
    "sg:address":"12533 Dillingham Sq",
    "sg:city":"Woodbridge",
    "sg:classifiers":[
        {
            "category":"Education",
            "subcategory":"Dance Studio",
            "type":"Public Place"
        }
    ],
    "sg:phone":"+1 703 590 2739",
    "sg:postcode":"22192",
    "sg:province":"VA",
    "wof:name":"Lindas Ballet Workshop Inc",
    "wof:placetype":"venue"
},
  "geometry": {"coordinates":[-77.319684,38.682609],"type":"Point"}
}