{
  "type": "Feature",
  "properties": {
    "addr:full":"17488 Kings Hwy Montross VA 22520",
    "addr:housenumber":"17488",
    "addr:postcode":"22520",
    "addr:street":"Kings Hwy",
    "iso:country":"US",
    "sg:address":"17488 Kings Hwy",
    "sg:city":"Montross",
    "sg:classifiers":[
        {
            "category":"Personal",
            "subcategory":"Beauty Salon",
            "type":"Services"
        },
        {
            "category":"Personal",
            "subcategory":"Tanning Parlor",
            "type":"Services"
        }
    ],
    "sg:phone":"+1 804 493 7773",
    "sg:postcode":"22520",
    "sg:province":"VA",
    "wof:name":"Simply Angela S Hair And Tanning Salon",
    "wof:placetype":"venue"
},
  "geometry": {"coordinates":[-76.797844,38.092101],"type":"Point"}
}