{
  "type": "Feature",
  "properties": {
    "addr:full":"8910 Quioccasin Rd Richmond VA 23229",
    "addr:housenumber":"8910",
    "addr:postcode":"23229",
    "addr:street":"Quioccasin Rd",
    "iso:country":"US",
    "sg:address":"8910 Quioccasin Rd",
    "sg:city":"Richmond",
    "sg:classifiers":[
        {
            "category":"Food & Beverages",
            "subcategory":"Groceries & Convenience Stores",
            "type":"Retail Goods"
        }
    ],
    "sg:phone":"+1 804 741 0600",
    "sg:postcode":"23229",
    "sg:province":"VA",
    "sg:tags":[
        "grocer"
    ],
    "sg:website":"www.foodlion.com",
    "wof:name":"Food Lion",
    "wof:placetype":"venue"
},
  "geometry": {"coordinates":[-77.57063100000001,37.605184],"type":"Point"}
}