{
  "type": "Feature",
  "properties": {
    "iso:country":"US",
    "sg:address":"Falls Church/McLean area",
    "sg:city":"Falls Church",
    "sg:classifiers":[
        {
            "category":"Education",
            "subcategory":"Special Training",
            "type":"Public Place"
        }
    ],
    "sg:phone":"+1 703 899 6803",
    "sg:postcode":"22043",
    "sg:province":"VA",
    "sg:tags":[
        "tutor",
        "private"
    ],
    "sg:website":"www.dougsmathtutoring.com",
    "wof:name":"Doug's Math Tutoring Services",
    "wof:placetype":"venue"
},
  "geometry": {"coordinates":[-77.200275,38.898947],"type":"Point"}
}