{
  "type": "Feature",
  "properties": {
    "addr:full":"6851 Courthouse Rd Chesterfield VA 23832",
    "addr:housenumber":"6851",
    "addr:postcode":"23832",
    "addr:street":"Courthouse Rd",
    "iso:country":"US",
    "sg:address":"6851 Courthouse Rd",
    "sg:city":"Chesterfield",
    "sg:classifiers":[
        {
            "category":"Education",
            "subcategory":"School",
            "type":"Public Place"
        }
    ],
    "sg:phone":"+1 804 271 1891",
    "sg:postcode":"23832",
    "sg:province":"VA",
    "sg:tags":[
        "association"
    ],
    "sg:website":"www.gcakids.com",
    "wof:name":"Guardian Christian Academy",
    "wof:placetype":"venue"
},
  "geometry": {"coordinates":[-77.563514,37.405304],"type":"Point"}
}