{
  "type": "Feature",
  "properties": {
    "addr:full":"6845 Blantyre Rd Warrenton VA 20187",
    "addr:postcode":"6845;20187",
    "addr:street":"Blantyre Rd",
    "iso:country":"US",
    "sg:address":"6845 Blantyre Rd",
    "sg:city":"Warrenton",
    "sg:classifiers":[
        {
            "category":"Retail",
            "subcategory":"Animal Services",
            "type":"Services"
        }
    ],
    "sg:phone":"+1 540 349 1339",
    "sg:postcode":"20187",
    "sg:province":"VA",
    "sg:tags":[
        "farm",
        "general"
    ],
    "sg:website":"www.marefield.com",
    "wof:name":"Marefield Meadows Inc",
    "wof:placetype":"venue"
},
  "geometry": {"coordinates":[-77.805847,38.771495],"type":"Point"}
}