{
  "type": "Feature",
  "properties": {
    "iso:country":"US",
    "sg:address":"1600 Duke St",
    "sg:city":"Alexandria",
    "sg:classifiers":[
        {
            "category":"Organizations",
            "subcategory":"Non-profit Organization",
            "type":"Services"
        }
    ],
    "sg:phone":"+1 703 684 3600",
    "sg:postcode":"22314",
    "sg:province":"VA",
    "sg:website":"www.nacsonline.com",
    "wof:name":"National Association",
    "wof:placetype":"venue"
},
  "geometry": {"coordinates":[-77.05951,38.80432],"type":"Point"}
}