{
  "type": "Feature",
  "properties": {
    "addr:full":"352 W College St Rocky Mount VA 24151",
    "addr:housenumber":"352",
    "addr:postcode":"24151",
    "addr:street":"W College St",
    "iso:country":"US",
    "sg:address":"352 W College St",
    "sg:city":"Rocky Mount",
    "sg:classifiers":[
        {
            "category":"Professional",
            "type":"Services"
        }
    ],
    "sg:phone":"+1 540 489 7484",
    "sg:postcode":"24151",
    "sg:province":"VA",
    "sg:tags":[
        "establishment"
    ],
    "wof:name":"Step Inc",
    "wof:placetype":"venue"
},
  "geometry": {"coordinates":[-79.89796699999999,36.995191],"type":"Point"}
}