{
  "type": "Feature",
  "properties": {
    "iso:country":"US",
    "sg:address":"377 Campostella Rd",
    "sg:city":"Norfolk",
    "sg:classifiers":[
        {
            "category":"Restaurant",
            "type":"Food & Drink"
        }
    ],
    "sg:menulink":"http://www.allmenus.com/va/norfolk/155117-hardees/menu/",
    "sg:phone":"+1 757 543 9189",
    "sg:postcode":"23523",
    "sg:province":"VA",
    "sg:tags":[
        "burger",
        "american"
    ],
    "wof:name":"Hardee's",
    "wof:placetype":"venue"
},
  "geometry": {"coordinates":[-76.26399600000001,36.837096],"type":"Point"}
}