{
  "type": "Feature",
  "properties": {
    "iso:country":"US",
    "sg:address":"3853 Robin Hood Rd",
    "sg:city":"Norfolk",
    "sg:classifiers":[
        {
            "category":"Building & Trades",
            "subcategory":"Construction",
            "type":"Services"
        }
    ],
    "sg:phone":"+1 757 855 7504",
    "sg:postcode":"23513",
    "sg:province":"VA",
    "sg:tags":[
        "contractor"
    ],
    "wof:name":"Spectrum Masonry Services",
    "wof:placetype":"venue"
},
  "geometry": {"coordinates":[-76.241219,36.875848],"type":"Point"}
}