{
  "type": "Feature",
  "properties": {
    "addr:full":"142 Deer Run Rd Danville VA 24540",
    "addr:housenumber":"142",
    "addr:postcode":"24540",
    "addr:street":"Deer Run Rd",
    "iso:country":"US",
    "sg:address":"142 Deer Run Rd",
    "sg:city":"Danville",
    "sg:classifiers":[
        {
            "category":"Real Estate",
            "subcategory":"Real Estate Agent",
            "type":"Services"
        }
    ],
    "sg:phone":"+1 434 792 6390",
    "sg:postcode":"24540",
    "sg:province":"VA",
    "wof:name":"John L Foster Agency Inc",
    "wof:placetype":"venue"
},
  "geometry": {"coordinates":[-79.410371,36.613523],"type":"Point"}
}