{
  "type": "Feature",
  "properties": {
    "addr:full":"9698 Hayters Gap Rd Abingdon VA 24210",
    "addr:housenumber":"9698",
    "addr:postcode":"24210",
    "addr:street":"Hayters Gap Rd",
    "iso:country":"US",
    "sg:address":"9698 Hayters Gap Rd",
    "sg:city":"Abingdon",
    "sg:classifiers":[
        {
            "category":"Building & Trades",
            "subcategory":"Construction",
            "type":"Services"
        }
    ],
    "sg:phone":"+1 276 944 4648",
    "sg:postcode":"24210",
    "sg:province":"VA",
    "sg:tags":[
        "house",
        "general",
        "contractor"
    ],
    "wof:name":"Russell Construction Co",
    "wof:placetype":"venue"
},
  "geometry": {"coordinates":[-81.908406,36.810235],"type":"Point"}
}