{
  "type": "Feature",
  "properties": {
    "addr:full":"6607 White Oak Ct Sandston VA 23150",
    "addr:housenumber":"6607",
    "addr:postcode":"23150",
    "addr:street":"White Oak Ct",
    "iso:country":"US",
    "sg:address":"6607 White Oak Ct",
    "sg:city":"Sandston",
    "sg:classifiers":[
        {
            "category":"Building & Trades",
            "subcategory":"Landscaping Services",
            "type":"Services"
        }
    ],
    "sg:phone":"+1 804 328 4378",
    "sg:postcode":"23150",
    "sg:province":"VA",
    "sg:tags":[
        "landscape"
    ],
    "wof:name":"Signature Landscapes",
    "wof:placetype":"venue"
},
  "geometry": {"coordinates":[-77.20557100000001,37.482615],"type":"Point"}
}