{
  "type": "Feature",
  "properties": {
    "addr:full":"9402 Braken Ct Fredericksburg VA 22408",
    "addr:postcode":"9402;22408",
    "addr:street":"Braken Ct",
    "iso:country":"US",
    "sg:address":"9402 Braken Ct",
    "sg:city":"Fredericksburg",
    "sg:classifiers":[
        {
            "category":"Professional",
            "subcategory":"Computer Services",
            "type":"Services"
        }
    ],
    "sg:phone":"+1 804 852 0451",
    "sg:postcode":"22408",
    "sg:province":"VA",
    "sg:tags":[
        "consulting",
        "it"
    ],
    "wof:name":"MGM Global Technologies",
    "wof:placetype":"venue"
},
  "geometry": {"coordinates":[-77.468126,38.217153],"type":"Point"}
}