{
  "type": "Feature",
  "properties": {
    "iso:country":"US",
    "sg:address":"6022 Grinton Rd",
    "sg:city":"Richmond",
    "sg:classifiers":[
        {
            "category":"Building & Trades",
            "subcategory":"Construction",
            "type":"Services"
        }
    ],
    "sg:phone":"+1 804 275 8568",
    "sg:postcode":"23234",
    "sg:province":"VA",
    "sg:tags":[
        "house"
    ],
    "wof:name":"Humphries Contracting",
    "wof:placetype":"venue"
},
  "geometry": {"coordinates":[-77.445932,37.441162],"type":"Point"}
}