{
  "type": "Feature",
  "properties": {
    "iso:country":"US",
    "sg:address":"3805 Claremont Ln",
    "sg:city":"Woodbridge",
    "sg:classifiers":[
        {
            "category":"Building & Trades",
            "subcategory":"Landscaping Services",
            "type":"Services"
        }
    ],
    "sg:phone":"+1 703 670 3737",
    "sg:postcode":"22193",
    "sg:province":"VA",
    "sg:tags":[
        "landscape",
        "contractor"
    ],
    "wof:name":"K Y Landscaping Svc Inc",
    "wof:placetype":"venue"
},
  "geometry": {"coordinates":[-77.32725600000001,38.623866],"type":"Point"}
}