{
  "type": "Feature",
  "properties": {
    "addr:full":"8421 New Ashcake Rd Mechanicsville VA 23116",
    "addr:housenumber":"8421",
    "addr:postcode":"23116",
    "addr:street":"New Ashcake Rd",
    "iso:country":"US",
    "sg:address":"8421 New Ashcake Rd",
    "sg:city":"Mechanicsville",
    "sg:classifiers":[
        {
            "category":"Wholesale",
            "subcategory":"Construction Materials",
            "type":"Manufacturing & Wholesale Goods"
        },
        {
            "category":"Building & Trades",
            "subcategory":"Construction",
            "type":"Services"
        }
    ],
    "sg:phone":"+1 804 730 7166",
    "sg:postcode":"23116",
    "sg:province":"VA",
    "sg:tags":[
        "house",
        "fence",
        "contractor"
    ],
    "sg:website":"www.fencingunlimitedinc.com",
    "wof:name":"Fencing Unlimited Inc",
    "wof:placetype":"venue"
},
  "geometry": {"coordinates":[-77.396861,37.680974],"type":"Point"}
}