{
  "type": "Feature",
  "properties": {
    "addr:full":"11130 State Rte 92 Chase City VA 23924",
    "addr:housenumber":"11130",
    "addr:postcode":"23924",
    "addr:street":"State Rte 92",
    "iso:country":"US",
    "sg:address":"11130 State Rte 92",
    "sg:city":"Chase City",
    "sg:classifiers":[
        {
            "category":"Wholesale",
            "subcategory":"Farm Supplies",
            "type":"Manufacturing & Wholesale Goods"
        }
    ],
    "sg:phone":"+1 434 372 3107",
    "sg:postcode":"23924",
    "sg:province":"VA",
    "sg:tags":[
        "hardware"
    ],
    "wof:name":"Mecklenburg Supply Inc",
    "wof:placetype":"venue"
},
  "geometry": {"coordinates":[-78.476039,36.796551],"type":"Point"}
}