{
  "type": "Feature",
  "properties": {
    "iso:country":"US",
    "sg:address":"3525 Prosperity Ave",
    "sg:city":"Fairfax",
    "sg:classifiers":[
        {
            "category":"Restaurant",
            "type":"Food & Drink"
        }
    ],
    "sg:phone":"+1 703 641 1560",
    "sg:postcode":"22031",
    "sg:province":"VA",
    "sg:tags":[
        "eating"
    ],
    "wof:name":"All Seasons Catering Inc",
    "wof:placetype":"venue"
},
  "geometry": {"coordinates":[-77.247111,38.850317],"type":"Point"}
}