{
  "type": "Feature",
  "properties": {
    "iso:country":"US",
    "sg:address":"1029 Main St",
    "sg:city":"Altavista",
    "sg:classifiers":[
        {
            "category":"Insurance",
            "subcategory":"Insurance Agent",
            "type":"Services"
        }
    ],
    "sg:phone":"+1 434 369 5611",
    "sg:postcode":"24517",
    "sg:province":"VA",
    "wof:name":"Kinlaw Insurance",
    "wof:placetype":"venue"
},
  "geometry": {"coordinates":[-79.281942,37.114377],"type":"Point"}
}