{
  "type": "Feature",
  "properties": {
    "addr:full":"6000 Claypoint Rd Chesterfield VA 23832",
    "addr:housenumber":"6000",
    "addr:postcode":"23832",
    "addr:street":"Claypoint Rd",
    "iso:country":"US",
    "sg:address":"6000 Claypoint Rd",
    "sg:city":"Chesterfield",
    "sg:classifiers":[
        {
            "category":"Building & Trades",
            "subcategory":"Landscaping Services",
            "type":"Services"
        }
    ],
    "sg:phone":"+1 804 744 6316",
    "sg:postcode":"23832",
    "sg:province":"VA",
    "wof:name":"Dale Hanen Tree Serv",
    "wof:placetype":"venue"
},
  "geometry": {"coordinates":[-77.60145199999999,37.407709],"type":"Point"}
}