{
  "type": "Feature",
  "properties": {
    "addr:full":"1193 N Main St Marion VA 24354",
    "addr:housenumber":"1193",
    "addr:postcode":"24354",
    "addr:street":"N Main St",
    "iso:country":"US",
    "sg:address":"1193 N Main St",
    "sg:city":"Marion",
    "sg:classifiers":[
        {
            "category":"Shopping",
            "subcategory":"Department Store",
            "type":"Retail Goods"
        }
    ],
    "sg:phone":"+1 276 783 4244",
    "sg:postcode":"24354",
    "sg:province":"VA",
    "sg:tags":[
        "discount"
    ],
    "sg:website":"www.walmart.com",
    "wof:name":"Wal-Mart",
    "wof:placetype":"venue"
},
  "geometry": {"coordinates":[-81.49994,36.844794],"type":"Point"}
}