{
  "type": "Feature",
  "properties": {
    "iso:country":"US",
    "sg:address":"13241 Gateway Center Dr",
    "sg:city":"Gainesville",
    "sg:classifiers":[
        {
            "category":"Retail",
            "subcategory":"Veterinary Services",
            "type":"Services"
        }
    ],
    "sg:phone":"+1 571 261 4080",
    "sg:postcode":"20155",
    "sg:province":"VA",
    "sg:tags":[
        "clinic",
        "hospital",
        "veterinarian",
        "specialty"
    ],
    "sg:website":"www.banfield.net",
    "wof:name":"Banfield the Pet Hospital",
    "wof:placetype":"venue"
},
  "geometry": {"coordinates":[-77.606347,38.79622],"type":"Point"}
}