{
  "type": "Feature",
  "properties": {
    "iso:country":"US",
    "sg:address":"1320 Traway Dr",
    "sg:city":"Richmond",
    "sg:classifiers":[
        {
            "category":"Wholesale",
            "subcategory":"Non-durable Goods",
            "type":"Manufacturing & Wholesale Goods"
        }
    ],
    "sg:phone":"+1 804 276 0271",
    "sg:postcode":"23235",
    "sg:province":"VA",
    "sg:tags":[
        "dry",
        "goods-wholesale"
    ],
    "wof:name":"Msc Supply Co",
    "wof:placetype":"venue"
},
  "geometry": {"coordinates":[-77.543812,37.479418],"type":"Point"}
}