{
  "type": "Feature",
  "properties": {
    "iso:country":"US",
    "sg:address":"608 S King St",
    "sg:city":"Leesburg",
    "sg:classifiers":[
        {
            "category":"Professional",
            "subcategory":"Management & Consulting",
            "type":"Services"
        }
    ],
    "sg:phone":"+1 703 669 1413",
    "sg:postcode":"20175",
    "sg:province":"VA",
    "wof:name":"Kenneth A Maiden MAI",
    "wof:placetype":"venue"
},
  "geometry": {"coordinates":[-77.56891,39.106023],"type":"Point"}
}