{
  "type": "Feature",
  "properties": {
    "iso:country":"US",
    "sg:address":"4706 Peacock Ave",
    "sg:city":"Alexandria",
    "sg:classifiers":[
        {
            "category":"Professional",
            "type":"Services"
        }
    ],
    "sg:phone":"+1 703 370 2186",
    "sg:postcode":"22304",
    "sg:province":"VA",
    "wof:name":"Lee and Lau Inc",
    "wof:placetype":"venue"
},
  "geometry": {"coordinates":[-77.11278299999999,38.820913],"type":"Point"}
}