{
  "type": "Feature",
  "properties": {
    "iso:country":"US",
    "sg:address":"13892 Metrotech Dr",
    "sg:city":"Chantilly",
    "sg:phone":"+1 703 803 3103",
    "sg:postcode":"20151",
    "sg:province":"VA",
    "wof:name":"Chantilly Piper Hobby",
    "wof:placetype":"venue"
},
  "geometry": {"coordinates":[-77.424522,38.89417],"type":"Point"}
}