{
  "type": "Feature",
  "properties": {
    "addr:full":"4912 Heversham Ct Fairfax VA 22032",
    "addr:housenumber":"4912",
    "addr:postcode":"22032",
    "addr:street":"Heversham Ct",
    "iso:country":"US",
    "sg:address":"4912 Heversham Ct",
    "sg:city":"Fairfax",
    "sg:classifiers":[
        {
            "category":"Professional",
            "subcategory":"Detective & Security Services",
            "type":"Services"
        }
    ],
    "sg:phone":"+1 703 425 9625",
    "sg:postcode":"22032",
    "sg:province":"VA",
    "sg:tags":[
        "investigation",
        "private"
    ],
    "wof:name":"Ralph E Lawrence",
    "wof:placetype":"venue"
},
  "geometry": {"coordinates":[-77.294332,38.820176],"type":"Point"}
}