{
  "type": "Feature",
  "properties": {
    "iso:country":"US",
    "sg:address":"1314 Vincent Pl",
    "sg:city":"Mc Lean",
    "sg:classifiers":[
        {
            "category":"Health Services",
            "subcategory":"Doctor",
            "type":"Services"
        }
    ],
    "sg:phone":"+1 703 821 1018",
    "sg:postcode":"22101",
    "sg:province":"VA",
    "sg:tags":[
        "medical"
    ],
    "wof:name":"John D Payne MD Ltd",
    "wof:placetype":"venue"
},
  "geometry": {"coordinates":[-77.180809,38.936742],"type":"Point"}
}