{
  "type": "Feature",
  "properties": {
    "addr:full":"5927 Westchester St Alexandria VA 22310",
    "addr:housenumber":"5927",
    "addr:postcode":"22310",
    "addr:street":"Westchester St",
    "iso:country":"US",
    "sg:address":"5927 Westchester St",
    "sg:city":"Alexandria",
    "sg:classifiers":[
        {
            "category":"Education",
            "subcategory":"School",
            "type":"Public Place"
        }
    ],
    "sg:phone":"+1 703 924 5600",
    "sg:postcode":"22310",
    "sg:province":"VA",
    "wof:name":"Bush Hill Elementary School",
    "wof:placetype":"venue"
},
  "geometry": {"coordinates":[-77.12554900000001,38.790159],"type":"Point"}
}