{
  "type": "Feature",
  "properties": {
    "iso:country":"US",
    "sg:address":"555 Southlake Blvd",
    "sg:city":"Richmond",
    "sg:classifiers":[
        {
            "category":"Professional",
            "subcategory":"Management & Consulting",
            "type":"Services"
        }
    ],
    "sg:phone":"+1 804 379 1442",
    "sg:postcode":"23236",
    "sg:province":"VA",
    "sg:tags":[
        "training",
        "sales"
    ],
    "sg:website":"www.bobvieno.com",
    "wof:name":"Bob Vieno & Assoc Inc",
    "wof:placetype":"venue"
},
  "geometry": {"coordinates":[-77.600521,37.499358],"type":"Point"}
}