{
  "type": "Feature",
  "properties": {
    "addr:full":"210 S College Ave Salem VA 24153",
    "addr:housenumber":"210",
    "addr:postcode":"24153",
    "addr:street":"S College Ave",
    "iso:country":"US",
    "sg:address":"210 S College Ave",
    "sg:city":"Salem",
    "sg:classifiers":[
        {
            "category":"Organizations",
            "subcategory":"Religious Organization",
            "type":"Services"
        }
    ],
    "sg:phone":"+1 540 389 4963",
    "sg:postcode":"24153",
    "sg:province":"VA",
    "sg:website":"www.collegelutheran.org",
    "wof:name":"College Lutheran Church",
    "wof:placetype":"venue"
},
  "geometry": {"coordinates":[-80.053999,37.291383],"type":"Point"}
}