{
  "type": "Feature",
  "properties": {
    "iso:country":"US",
    "sg:address":"200 Yoakum Pkwy",
    "sg:city":"Alexandria",
    "sg:classifiers":[
        {
            "category":"Professional",
            "subcategory":"Computer Services",
            "type":"Services"
        }
    ],
    "sg:phone":"+1 703 461 7179",
    "sg:postcode":"22304",
    "sg:province":"VA",
    "sg:tags":[
        "hardware",
        "consulting",
        "design",
        "software"
    ],
    "wof:name":"Innovative Technical Solutions",
    "wof:placetype":"venue"
},
  "geometry": {"coordinates":[-77.13980599999999,38.812481],"type":"Point"}
}