{
  "type": "Feature",
  "properties": {
    "addr:full":"9324 Troy Dr Nokesville VA 20181",
    "addr:housenumber":"9324",
    "addr:postcode":"20181",
    "addr:street":"Troy Dr",
    "iso:country":"US",
    "sg:address":"9324 Troy Dr",
    "sg:city":"Nokesville",
    "sg:classifiers":[
        {
            "category":"Building & Trades",
            "subcategory":"Construction",
            "type":"Services"
        }
    ],
    "sg:phone":"+1 703 791 4747",
    "sg:postcode":"20181",
    "sg:province":"VA",
    "sg:tags":[
        "concrete",
        "contractor"
    ],
    "wof:name":"S & S Concrete Cutting Co",
    "wof:placetype":"venue"
},
  "geometry": {"coordinates":[-77.478865,38.670835],"type":"Point"}
}