{
  "type": "Feature",
  "properties": {
    "addr:full":"7390 Bell Creek Rd Mechanicsville VA 23111",
    "addr:housenumber":"7390",
    "addr:postcode":"23111",
    "addr:street":"Bell Creek Rd",
    "iso:country":"US",
    "sg:address":"7390 Bell Creek Rd",
    "sg:city":"Mechanicsville",
    "sg:classifiers":[
        {
            "category":"Shopping",
            "subcategory":"Discount & Variety Stores",
            "type":"Retail Goods"
        },
        {
            "category":"Shopping",
            "subcategory":"Department Store",
            "type":"Retail Goods"
        }
    ],
    "sg:phone":"+1 804 746 3535",
    "sg:postcode":"23111",
    "sg:province":"VA",
    "sg:tags":[
        "shop"
    ],
    "sg:website":"www.dollartree.com",
    "wof:name":"Dollar Tree",
    "wof:placetype":"venue"
},
  "geometry": {"coordinates":[-77.353123,37.602905],"type":"Point"}
}