{
  "type": "Feature",
  "properties": {
    "addr:full":"107 1st St S Charlottesville VA 22902",
    "addr:housenumber":"107",
    "addr:postcode":"22902",
    "addr:street":"1St St",
    "iso:country":"US",
    "sg:address":"107 1st St S",
    "sg:city":"Charlottesville",
    "sg:classifiers":[
        {
            "category":"Professional",
            "subcategory":"Management & Consulting",
            "type":"Services"
        }
    ],
    "sg:phone":"+1 434 244 3400",
    "sg:postcode":"22902",
    "sg:province":"VA",
    "sg:tags":[
        "business"
    ],
    "wof:name":"Generation Power Products",
    "wof:placetype":"venue"
},
  "geometry": {"coordinates":[-78.481914,38.030113],"type":"Point"}
}