{
  "type": "Feature",
  "properties": {
    "iso:country":"US",
    "sg:address":"7722 Fisher Dr",
    "sg:city":"Falls Church",
    "sg:classifiers":[
        {
            "category":"Retail",
            "subcategory":"Repair Shop",
            "type":"Services"
        }
    ],
    "sg:phone":"+1 703 893 5993",
    "sg:postcode":"22043",
    "sg:province":"VA",
    "sg:tags":[
        "equipment",
        "conditioning",
        "air"
    ],
    "wof:name":"TNP Refrigeration Co",
    "wof:placetype":"venue"
},
  "geometry": {"coordinates":[-77.213944,38.911447],"type":"Point"}
}