{
  "type": "Feature",
  "properties": {
    "iso:country":"US",
    "sg:address":"3007 Delaplane Grade Rd",
    "sg:city":"Delaplane",
    "sg:classifiers":[
        {
            "category":"Professional",
            "subcategory":"Art Services",
            "type":"Services"
        }
    ],
    "sg:phone":"+1 540 364 4588",
    "sg:postcode":"20144",
    "sg:province":"VA",
    "sg:tags":[
        "photographer"
    ],
    "wof:name":"Image Of Virginia",
    "wof:placetype":"venue"
},
  "geometry": {"coordinates":[-77.919169,38.916803],"type":"Point"}
}