{
  "type": "Feature",
  "properties": {
    "addr:full":"19614 Turkey Egg Rd Dinwiddie VA 23841",
    "addr:housenumber":"19614",
    "addr:postcode":"23841",
    "addr:street":"Turkey Egg Rd",
    "iso:country":"US",
    "sg:address":"19614 Turkey Egg Rd",
    "sg:city":"Dinwiddie",
    "sg:classifiers":[
        {
            "category":"Recreation",
            "type":"Entertainment"
        }
    ],
    "sg:phone":"+1 804 469 3075",
    "sg:postcode":"23841",
    "sg:province":"VA",
    "wof:name":"Tri City Aikikai",
    "wof:placetype":"venue"
},
  "geometry": {"coordinates":[-77.58393100000001,37.10618],"type":"Point"}
}