{
  "type": "Feature",
  "properties": {
    "addr:full":"1765 Nelsons Bridge Rd Hanover VA 23069",
    "addr:housenumber":"1765",
    "addr:postcode":"23069",
    "addr:street":"Nelsons Bridge Rd",
    "iso:country":"US",
    "sg:address":"1765 Nelsons Bridge Rd",
    "sg:city":"Hanover",
    "sg:phone":"+1 804 994 2791",
    "sg:postcode":"23069",
    "sg:province":"VA",
    "sg:tags":[
        "farm"
    ],
    "wof:name":"L W Rudolph Farms",
    "wof:placetype":"venue"
},
  "geometry": {"coordinates":[-77.25966200000001,37.791001],"type":"Point"}
}