{
  "type": "Feature",
  "properties": {
    "iso:country":"US",
    "sg:address":"1718 N King St",
    "sg:city":"Hampton",
    "sg:classifiers":[
        {
            "category":"Organizations",
            "subcategory":"Religious Organization",
            "type":"Services"
        }
    ],
    "sg:phone":"+1 757 728 0386",
    "sg:postcode":"23669",
    "sg:province":"VA",
    "wof:name":"Lift Jesus Higher Ministries",
    "wof:placetype":"venue"
},
  "geometry": {"coordinates":[-76.348383,37.065909],"type":"Point"}
}