{
  "type": "Feature",
  "properties": {
    "iso:country":"US",
    "sg:address":"521 Wilson St",
    "sg:city":"Danville",
    "sg:classifiers":[
        {
            "category":"Autos & Motor Vehicles",
            "subcategory":"Automobile Sales",
            "type":"Retail Goods"
        }
    ],
    "sg:phone":"+1 434 792 0688",
    "sg:postcode":"24541",
    "sg:province":"VA",
    "sg:tags":[
        "car",
        "dealer"
    ],
    "wof:name":"R L Hall Motors",
    "wof:placetype":"venue"
},
  "geometry": {"coordinates":[-79.391419,36.583777],"type":"Point"}
}