{
  "type": "Feature",
  "properties": {
    "addr:full":"6822 Wilson Ln Bethesda MD 20817",
    "addr:housenumber":"6822",
    "addr:postcode":"20817",
    "addr:street":"Wilson Ln",
    "iso:country":"US",
    "sg:address":"6822 Wilson Ln",
    "sg:city":"Bethesda",
    "sg:classifiers":[
        {
            "category":"Professional",
            "type":"Services"
        }
    ],
    "sg:phone":"+1 301 229 2098",
    "sg:postcode":"20817",
    "sg:province":"MD",
    "wof:name":"Dr Jeffrey Walder",
    "wof:placetype":"venue"
},
  "geometry": {"coordinates":[-77.140455,38.981459],"type":"Point"}
}