{
  "type": "Feature",
  "properties": {
    "iso:country":"US",
    "sg:address":"10225 Nokesville Rd",
    "sg:city":"Manassas",
    "sg:classifiers":[
        {
            "category":"Shopping",
            "subcategory":"Gifts & Souvenirs",
            "type":"Retail Goods"
        }
    ],
    "sg:phone":"+1 703 368 6019",
    "sg:postcode":"20110",
    "sg:province":"VA",
    "sg:tags":[
        "baseball",
        "memorabilia"
    ],
    "wof:name":"Harris Baseball",
    "wof:placetype":"venue"
},
  "geometry": {"coordinates":[-77.50330700000001,38.747436],"type":"Point"}
}