{
  "type": "Feature",
  "properties": {
    "addr:full":"12 Oak Grove Ln Hanover VA 23069",
    "addr:housenumber":"12",
    "addr:postcode":"23069",
    "addr:street":"Oak Grove Ln",
    "iso:country":"US",
    "sg:address":"12 Oak Grove Ln",
    "sg:city":"Hanover",
    "sg:classifiers":[
        {
            "category":"Farming",
            "subcategory":"Livestock Farm",
            "type":"Manufacturing & Wholesale Goods"
        }
    ],
    "sg:phone":"+1 804 994 5228",
    "sg:postcode":"23069",
    "sg:province":"VA",
    "sg:tags":[
        "hog",
        "or",
        "feedlot"
    ],
    "wof:name":"James Connor",
    "wof:placetype":"venue"
},
  "geometry": {"coordinates":[-77.272516,37.751556],"type":"Point"}
}