{
  "type": "Feature",
  "properties": {
    "iso:country":"US",
    "sg:address":"3930 Castle Rock Rd",
    "sg:city":"Midlothian",
    "sg:classifiers":[
        {
            "category":"Home & Garden",
            "subcategory":"Building Materials",
            "type":"Retail Goods"
        },
        {
            "category":"Wholesale",
            "subcategory":"Auto Parts",
            "type":"Manufacturing & Wholesale Goods"
        }
    ],
    "sg:phone":"+1 804 763 0600",
    "sg:postcode":"23112",
    "sg:province":"VA",
    "sg:tags":[
        "plate",
        "window",
        "glass",
        "replacement"
    ],
    "wof:name":"Diamond Auto Glass",
    "wof:placetype":"venue"
},
  "geometry": {"coordinates":[-77.612397,37.430902],"type":"Point"}
}