{
  "type": "Feature",
  "properties": {
    "addr:full":"199 Spotnap Rd Ste 4 Charlottesville VA 22911",
    "addr:housenumber":"199",
    "addr:postcode":"22911",
    "addr:street":"Spotnap Rd Ste 4",
    "iso:country":"US",
    "sg:address":"199 Spotnap Rd Ste 4",
    "sg:city":"Charlottesville",
    "sg:classifiers":[
        {
            "category":"Health Services",
            "subcategory":"Doctor",
            "type":"Services"
        }
    ],
    "sg:phone":"+1 434 220 4555",
    "sg:postcode":"22911",
    "sg:province":"VA",
    "sg:tags":[
        "medicine",
        "internal"
    ],
    "wof:name":"Devincentis Christina MD Plc",
    "wof:placetype":"venue"
},
  "geometry": {"coordinates":[-78.45292600000001,38.031699],"type":"Point"}
}