{
  "type": "Feature",
  "properties": {
    "addr:full":"310 1st St SW Roanoke VA 24011",
    "addr:housenumber":"310",
    "addr:postcode":"24011",
    "addr:street":"1St St Sw",
    "iso:country":"US",
    "sg:address":"310 1st St SW",
    "sg:city":"Roanoke",
    "sg:classifiers":[
        {
            "category":"Government",
            "subcategory":"Office",
            "type":"Public Place"
        }
    ],
    "sg:phone":"+1 540 985 0103",
    "sg:postcode":"24011",
    "sg:province":"VA",
    "wof:name":"Charles S Robb",
    "wof:placetype":"venue"
},
  "geometry": {"coordinates":[-79.94234899999999,37.270612],"type":"Point"}
}