{
  "type": "Feature",
  "properties": {
    "iso:country":"US",
    "sg:address":"294 Sunset Park Dr",
    "sg:city":"Herndon",
    "sg:classifiers":[
        {
            "category":"Food & Beverages",
            "subcategory":"Bakery",
            "type":"Retail Goods"
        }
    ],
    "sg:phone":"+1 703 481 1570",
    "sg:postcode":"20170",
    "sg:province":"VA",
    "sg:tags":[
        "baker"
    ],
    "wof:name":"Amphor Bakery",
    "wof:placetype":"venue"
},
  "geometry": {"coordinates":[-77.37419,38.956883],"type":"Point"}
}