{
  "type": "Feature",
  "properties": {
    "addr:full":"286 Sugar Tree Hollow Rd Eagle Rock VA 24085",
    "addr:housenumber":"286",
    "addr:postcode":"24085",
    "addr:street":"Sugar Tree Hollow Rd",
    "iso:country":"US",
    "sg:address":"286 Sugar Tree Hollow Rd",
    "sg:city":"Eagle Rock",
    "sg:classifiers":[
        {
            "category":"Professional",
            "type":"Services"
        }
    ],
    "sg:phone":"+1 540 884 3487",
    "sg:postcode":"24085",
    "sg:province":"VA",
    "wof:name":"Gregory L Austin",
    "wof:placetype":"venue"
},
  "geometry": {"coordinates":[-79.846959,37.618109],"type":"Point"}
}