{
  "type": "Feature",
  "properties": {
    "addr:full":"719 Garrisonville Rd Stafford VA 22554",
    "addr:housenumber":"719",
    "addr:postcode":"22554",
    "addr:street":"Garrisonville Rd",
    "iso:country":"US",
    "sg:address":"719 Garrisonville Rd",
    "sg:city":"Stafford",
    "sg:classifiers":[
        {
            "category":"Shopping",
            "subcategory":"Bicycles & Sporting Goods",
            "type":"Retail Goods"
        }
    ],
    "sg:phone":"+1 703 490 3190",
    "sg:postcode":"22554",
    "sg:province":"VA",
    "sg:tags":[
        "tent"
    ],
    "sg:website":"www.totalrentalva.com",
    "wof:name":"Parton's Tents",
    "wof:placetype":"venue"
},
  "geometry": {"coordinates":[-77.448162,38.472716],"type":"Point"}
}