{
  "type": "Feature",
  "properties": {
    "addr:full":"150 Pinetree Ln Bedford VA 24523",
    "addr:housenumber":"150",
    "addr:postcode":"24523",
    "addr:street":"Pinetree Ln",
    "iso:country":"US",
    "sg:address":"150 Pinetree Ln",
    "sg:city":"Bedford",
    "sg:classifiers":[
        {
            "category":"Building & Trades",
            "subcategory":"Plumbing",
            "type":"Services"
        }
    ],
    "sg:phone":"+1 540 586 6966",
    "sg:postcode":"24523",
    "sg:province":"VA",
    "sg:tags":[
        "conditioning",
        "air",
        "system",
        "contractor"
    ],
    "wof:name":"Bedford Heating & Cooling",
    "wof:placetype":"venue"
},
  "geometry": {"coordinates":[-79.600475,37.288123],"type":"Point"}
}