{
  "type": "Feature",
  "properties": {
    "addr:full":"7007 George Washington Memorial Hwy Gloucester VA 23061",
    "addr:housenumber":"7007",
    "addr:postcode":"23061",
    "addr:street":"George Washington Memorial Hwy",
    "iso:country":"US",
    "sg:address":"7007 George Washington Memorial Hwy",
    "sg:city":"Gloucester",
    "sg:classifiers":[
        {
            "category":"Restaurant",
            "type":"Food & Drink"
        }
    ],
    "sg:menulink":"http://www.allmenus.com/va/abingdon/155079-hardees/menu/",
    "sg:phone":"+1 804 693 0363",
    "sg:postcode":"23061",
    "sg:province":"VA",
    "sg:tags":[
        "burger",
        "american"
    ],
    "wof:name":"Hardee's",
    "wof:placetype":"venue"
},
  "geometry": {"coordinates":[-76.528868,37.392833],"type":"Point"}
}