{
  "type": "Feature",
  "properties": {
    "iso:country":"US",
    "sg:address":"6022 Florence Ln",
    "sg:city":"Alexandria",
    "sg:classifiers":[
        {
            "category":"Professional",
            "subcategory":"Computer Services",
            "type":"Services"
        }
    ],
    "sg:phone":"+1 703 960 2278",
    "sg:postcode":"22310",
    "sg:province":"VA",
    "sg:tags":[
        "design",
        "system"
    ],
    "wof:name":"DK Web Designs Inc",
    "wof:placetype":"venue"
},
  "geometry": {"coordinates":[-77.08760100000001,38.786631],"type":"Point"}
}