{
  "type": "Feature",
  "properties": {
    "iso:country":"US",
    "sg:address":"216 Aspen St",
    "sg:city":"Alexandria",
    "sg:classifiers":[
        {
            "category":"Professional",
            "subcategory":"Art Services",
            "type":"Services"
        }
    ],
    "sg:phone":"+1 703 518 8999",
    "sg:postcode":"22305",
    "sg:province":"VA",
    "sg:tags":[
        "commercial",
        "design"
    ],
    "wof:name":"Reunion Graphics",
    "wof:placetype":"venue"
},
  "geometry": {"coordinates":[-77.064009,38.834725],"type":"Point"}
}