{
  "type": "Feature",
  "properties": {
    "iso:country":"US",
    "sg:address":"107 Royal St SW",
    "sg:city":"Leesburg",
    "sg:classifiers":[
        {
            "category":"Professional",
            "type":"Services"
        }
    ],
    "sg:phone":"+1 703 669 4411",
    "sg:postcode":"20175",
    "sg:province":"VA",
    "sg:tags":[
        "establishment"
    ],
    "wof:name":"New World Apps",
    "wof:placetype":"venue"
},
  "geometry": {"coordinates":[-77.567764,39.114137],"type":"Point"}
}