{
  "type": "Feature",
  "properties": {
    "addr:full":"5509 Wellington Rd Gainesville VA 20155",
    "addr:housenumber":"5509",
    "addr:postcode":"20155",
    "addr:street":"Wellington Rd",
    "iso:country":"US",
    "sg:address":"5509 Wellington Rd",
    "sg:city":"Gainesville",
    "sg:classifiers":[
        {
            "category":"Autos & Motor Vehicles",
            "subcategory":"Automobile Sales",
            "type":"Retail Goods"
        }
    ],
    "sg:phone":"+1 703 753 7002",
    "sg:postcode":"20155",
    "sg:province":"VA",
    "wof:name":"American Truck & Bus  Inc",
    "wof:placetype":"venue"
},
  "geometry": {"coordinates":[-77.59547600000001,38.793874],"type":"Point"}
}