{
  "type": "Feature",
  "properties": {
    "addr:full":"145 Nina Dr Virginia Beach VA 23462",
    "addr:housenumber":"145",
    "addr:postcode":"23462",
    "addr:street":"Nina Dr",
    "iso:country":"US",
    "sg:address":"145 Nina Dr",
    "sg:city":"Virginia Beach",
    "sg:classifiers":[
        {
            "category":"Professional",
            "subcategory":"Accounting & Tax Preparation",
            "type":"Services"
        }
    ],
    "sg:phone":"+1 757 497 6627",
    "sg:postcode":"23462",
    "sg:province":"VA",
    "sg:tags":[
        "bookkeeping",
        "general"
    ],
    "wof:name":"Keeping Up With The Books",
    "wof:placetype":"venue"
},
  "geometry": {"coordinates":[-76.133426,36.839151],"type":"Point"}
}