{
  "type": "Feature",
  "properties": {
    "iso:country":"US",
    "sg:address":"128 Carter Ct SW",
    "sg:city":"Vienna",
    "sg:classifiers":[
        {
            "category":"Professional",
            "type":"Services"
        }
    ],
    "sg:phone":"+1 703 255 0410",
    "sg:postcode":"22180",
    "sg:province":"VA",
    "sg:tags":[
        "establishment"
    ],
    "wof:name":"Referential System",
    "wof:placetype":"venue"
},
  "geometry": {"coordinates":[-77.273566,38.893239],"type":"Point"}
}