{
  "type": "Feature",
  "properties": {
    "addr:full":"8022 Langbrook Rd Springfield VA 22152",
    "addr:housenumber":"8022",
    "addr:postcode":"22152",
    "addr:street":"Langbrook Rd",
    "iso:country":"US",
    "sg:address":"8022 Langbrook Rd",
    "sg:city":"Springfield",
    "sg:classifiers":[
        {
            "category":"Professional",
            "subcategory":"Management & Consulting",
            "type":"Services"
        }
    ],
    "sg:phone":"+1 703 451 2175",
    "sg:postcode":"22152",
    "sg:province":"VA",
    "wof:name":"Mancomp Systems Inc",
    "wof:placetype":"venue"
},
  "geometry": {"coordinates":[-77.22346899999999,38.787526],"type":"Point"}
}