{
  "type": "Feature",
  "properties": {
    "iso:country":"US",
    "sg:address":"3301 Jefferson Davis Hwy",
    "sg:city":"Alexandria",
    "sg:classifiers":[
        {
            "category":"Professional",
            "subcategory":"Printing & Photocopies",
            "type":"Services"
        }
    ],
    "sg:phone":"+1 703 713 0275",
    "sg:postcode":"22305",
    "sg:province":"VA",
    "wof:name":"Staples the Office Superstore",
    "wof:placetype":"venue"
},
  "geometry": {"coordinates":[-77.051598,38.834801],"type":"Point"}
}