{
  "type": "Feature",
  "properties": {
    "iso:country":"US",
    "sg:address":"7504 Venice Ct",
    "sg:city":"Falls Church",
    "sg:classifiers":[
        {
            "category":"Professional",
            "subcategory":"Management & Consulting",
            "type":"Services"
        }
    ],
    "sg:phone":"+1 703 207 0444",
    "sg:postcode":"22043",
    "sg:province":"VA",
    "wof:name":"Leadership Consultation Svcs",
    "wof:placetype":"venue"
},
  "geometry": {"coordinates":[-77.204852,38.89128],"type":"Point"}
}