{
  "type": "Feature",
  "properties": {
    "addr:full":"560 Virginia Ave Bluefield VA 24605",
    "addr:housenumber":"560",
    "addr:postcode":"24605",
    "addr:street":"Virginia Ave",
    "iso:country":"US",
    "sg:address":"560 Virginia Ave",
    "sg:city":"Bluefield",
    "sg:classifiers":[
        {
            "category":"Manufacturing",
            "subcategory":"Printing",
            "type":"Manufacturing & Wholesale Goods"
        }
    ],
    "sg:phone":"+1 276 326 1323",
    "sg:postcode":"24605",
    "sg:province":"VA",
    "sg:tags":[
        "commercial"
    ],
    "wof:name":"Ben Franklin Press",
    "wof:placetype":"venue"
},
  "geometry": {"coordinates":[-81.27036,37.25285],"type":"Point"}
}