{
  "type": "Feature",
  "properties": {
    "addr:full":"8212 Rocky Branch Ln Richmond VA 23228",
    "addr:housenumber":"8212",
    "addr:postcode":"23228",
    "addr:street":"Rocky Branch Ln",
    "iso:country":"US",
    "sg:address":"8212 Rocky Branch Ln",
    "sg:city":"Richmond",
    "sg:classifiers":[
        {
            "category":"Retail",
            "subcategory":"Portrait Studio",
            "type":"Services"
        }
    ],
    "sg:phone":"+1 804 262 8850",
    "sg:postcode":"23228",
    "sg:province":"VA",
    "sg:tags":[
        "photo",
        "photography",
        "commercial"
    ],
    "wof:name":"Lewis & Clark Photographers",
    "wof:placetype":"venue"
},
  "geometry": {"coordinates":[-77.481234,37.629234],"type":"Point"}
}