{
  "type": "Feature",
  "properties": {
    "iso:country":"US",
    "sg:address":"164 N Madison Rd",
    "sg:city":"Orange",
    "sg:classifiers":[
        {
            "category":"Insurance",
            "subcategory":"Insurance Agent",
            "type":"Services"
        }
    ],
    "sg:phone":"+1 540 672 4644",
    "sg:postcode":"22960",
    "sg:province":"VA",
    "wof:name":"Mason Insurance Inc",
    "wof:placetype":"venue"
},
  "geometry": {"coordinates":[-78.11212999999999,38.247451],"type":"Point"}
}