{
  "type": "Feature",
  "properties": {
    "addr:full":"3644 Virginia Beach Blvd Virginia Beach VA 23452",
    "addr:housenumber":"3644",
    "addr:postcode":"23452",
    "addr:street":"Virginia Beach Blvd",
    "iso:country":"US",
    "sg:address":"3644 Virginia Beach Blvd",
    "sg:city":"Virginia Beach",
    "sg:classifiers":[
        {
            "category":"Personal",
            "type":"Services"
        }
    ],
    "sg:phone":"+1 757 498 1116",
    "sg:postcode":"23452",
    "sg:province":"VA",
    "sg:tags":[
        "pet",
        "exercising"
    ],
    "wof:name":"Centre City Grill",
    "wof:placetype":"venue"
},
  "geometry": {"coordinates":[-76.097235,36.840712],"type":"Point"}
}