{
  "type": "Feature",
  "properties": {
    "addr:full":"720 N Amelia St Sterling VA 20164",
    "addr:housenumber":"720",
    "addr:postcode":"20164",
    "addr:street":"N Amelia St",
    "iso:country":"US",
    "sg:address":"720 N Amelia St",
    "sg:city":"Sterling",
    "sg:classifiers":[
        {
            "category":"Manufacturing",
            "subcategory":"Buildings",
            "type":"Manufacturing & Wholesale Goods"
        },
        {
            "category":"Structure",
            "subcategory":"Warehouse",
            "type":"Public Place"
        },
        {
            "category":"Building & Trades",
            "subcategory":"Construction",
            "type":"Services"
        }
    ],
    "sg:phone":"+1 703 421 3126",
    "sg:postcode":"20164",
    "sg:province":"VA",
    "sg:tags":[
        "warehouses-merchandise",
        "warehouses-public-commercial",
        "builder",
        "contractor",
        "home",
        "estimate"
    ],
    "wof:name":"Construction Of Cavalier",
    "wof:placetype":"venue"
},
  "geometry": {"coordinates":[-77.39751699999999,39.009123],"type":"Point"}
}