{
  "type": "Feature",
  "properties": {
    "iso:country":"US",
    "sg:address":"10669 Spotsylvania Ave",
    "sg:city":"Fredericksburg",
    "sg:classifiers":[
        {
            "category":"Personal",
            "type":"Services"
        }
    ],
    "sg:phone":"+1 540 898 0700",
    "sg:postcode":"22408",
    "sg:province":"VA",
    "wof:name":"Family Tae Kwon Do Academy",
    "wof:placetype":"venue"
},
  "geometry": {"coordinates":[-77.494968,38.247682],"type":"Point"}
}