{
  "type": "Feature",
  "properties": {
    "addr:full":"9109 Berry Patch Dr Chesterfield VA 23832",
    "addr:housenumber":"9109",
    "addr:postcode":"23832",
    "addr:street":"Berry Patch Dr",
    "iso:country":"US",
    "sg:address":"9109 Berry Patch Dr",
    "sg:city":"Chesterfield",
    "sg:classifiers":[
        {
            "category":"Building & Trades",
            "subcategory":"Construction",
            "type":"Services"
        }
    ],
    "sg:phone":"+1 804 276 6653",
    "sg:postcode":"23832",
    "sg:province":"VA",
    "sg:tags":[
        "house"
    ],
    "wof:name":"King Builders",
    "wof:placetype":"venue"
},
  "geometry": {"coordinates":[-77.55641,37.430037],"type":"Point"}
}