{
  "type": "Feature",
  "properties": {
    "iso:country":"US",
    "sg:address":"649 30th St",
    "sg:city":"Newport News",
    "sg:classifiers":[
        {
            "category":"Organizations",
            "subcategory":"Religious Organization",
            "type":"Services"
        }
    ],
    "sg:phone":"+1 757 380 5327",
    "sg:postcode":"23607",
    "sg:province":"VA",
    "sg:tags":[
        "church"
    ],
    "wof:name":"First Baptist Church-East End",
    "wof:placetype":"venue"
},
  "geometry": {"coordinates":[-76.42144999999999,36.985253],"type":"Point"}
}