{
  "type": "Feature",
  "properties": {
    "addr:full":"24 Dashiell Dr Smithfield VA 23430",
    "addr:housenumber":"24",
    "addr:postcode":"23430",
    "addr:street":"Dashiell Dr",
    "iso:country":"US",
    "sg:address":"24 Dashiell Dr",
    "sg:city":"Smithfield",
    "sg:classifiers":[
        {
            "category":"Real Estate",
            "subcategory":"Architect",
            "type":"Services"
        }
    ],
    "sg:phone":"+1 757 356 9970",
    "sg:postcode":"23430",
    "sg:province":"VA",
    "wof:name":"Parrish Design",
    "wof:placetype":"venue"
},
  "geometry": {"coordinates":[-76.602279,36.987626],"type":"Point"}
}