{
  "type": "Feature",
  "properties": {
    "iso:country":"US",
    "sg:address":"4396 Poplar Tree Ct",
    "sg:city":"Chantilly",
    "sg:classifiers":[
        {
            "category":"Professional",
            "type":"Services"
        }
    ],
    "sg:phone":"+1 703 631 7087",
    "sg:postcode":"20151",
    "sg:province":"VA",
    "wof:name":"Ampa Inc",
    "wof:placetype":"venue"
},
  "geometry": {"coordinates":[-77.416184,38.87524],"type":"Point"}
}