{
  "type": "Feature",
  "properties": {
    "iso:country":"US",
    "sg:address":"7176 Salisbury Rd",
    "sg:city":"Spring Grove",
    "sg:classifiers":[
        {
            "category":"Organizations",
            "subcategory":"Religious Organization",
            "type":"Services"
        }
    ],
    "sg:phone":"+1 804 834 3493",
    "sg:postcode":"23881",
    "sg:province":"VA",
    "wof:name":"Church All Nations-Apostolic",
    "wof:placetype":"venue"
},
  "geometry": {"coordinates":[-77.023544,37.158112],"type":"Point"}
}