{
  "type": "Feature",
  "properties": {
    "iso:country":"US",
    "sg:address":"9440 Mathy Dr",
    "sg:city":"Fairfax",
    "sg:classifiers":[
        {
            "category":"Education",
            "subcategory":"Dance Studio",
            "type":"Public Place"
        }
    ],
    "sg:phone":"+1 703 323 8304",
    "sg:postcode":"22031",
    "sg:province":"VA",
    "wof:name":"In Step School Of Dance",
    "wof:placetype":"venue"
},
  "geometry": {"coordinates":[-77.271315,38.844589],"type":"Point"}
}