{
  "type": "Feature",
  "properties": {
    "addr:full":"905 Dorchester Pl Charlottesville VA 22911",
    "addr:housenumber":"905",
    "addr:postcode":"22911",
    "addr:street":"Dorchester Pl",
    "iso:country":"US",
    "sg:address":"905 Dorchester Pl",
    "sg:city":"Charlottesville",
    "sg:classifiers":[
        {
            "category":"Shopping",
            "subcategory":"Discount & Variety Stores",
            "type":"Retail Goods"
        }
    ],
    "sg:phone":"+1 434 293 4428",
    "sg:postcode":"22911",
    "sg:province":"VA",
    "sg:tags":[
        "post",
        "trading"
    ],
    "wof:name":"Smile International Trading",
    "wof:placetype":"venue"
},
  "geometry": {"coordinates":[-78.449682,38.030676],"type":"Point"}
}