{
  "type": "Feature",
  "properties": {
    "addr:full":"9644 S Congress St New Market VA 22844",
    "addr:housenumber":"9644",
    "addr:postcode":"22844",
    "addr:street":"S Congress St",
    "iso:country":"US",
    "sg:address":"9644 S Congress St",
    "sg:city":"New Market",
    "sg:classifiers":[
        {
            "category":"Building & Trades",
            "subcategory":"Construction",
            "type":"Services"
        }
    ],
    "sg:phone":"+1 540 740 2696",
    "sg:postcode":"22844",
    "sg:province":"VA",
    "sg:tags":[
        "fire",
        "restoration",
        "damage"
    ],
    "wof:name":"Paul Davis Restoration-Nw Va",
    "wof:placetype":"venue"
},
  "geometry": {"coordinates":[-78.675594,38.642054],"type":"Point"}
}