{
  "type": "Feature",
  "properties": {
    "addr:full":"8425 Overbrook Rd Fairfax VA 22031",
    "addr:housenumber":"8425",
    "addr:postcode":"22031",
    "addr:street":"Overbrook Rd",
    "iso:country":"US",
    "sg:address":"8425 Overbrook Rd",
    "sg:city":"Fairfax",
    "sg:classifiers":[
        {
            "category":"Building & Trades",
            "subcategory":"Construction",
            "type":"Services"
        }
    ],
    "sg:phone":"+1 703 209 7307",
    "sg:postcode":"22031",
    "sg:province":"VA",
    "sg:tags":[
        "house"
    ],
    "wof:name":"J T Carpentry",
    "wof:placetype":"venue"
},
  "geometry": {"coordinates":[-77.24128,38.862865],"type":"Point"}
}