{
  "type": "Feature",
  "properties": {
    "addr:full":"4350 Fairfax Dr Arlington VA 22203",
    "addr:housenumber":"4350",
    "addr:postcode":"22203",
    "addr:street":"Fairfax Dr",
    "iso:country":"US",
    "sg:address":"4350 Fairfax Dr",
    "sg:city":"Arlington",
    "sg:classifiers":[
        {
            "category":"Banks & Credit Unions",
            "subcategory":"Investment Brokerage",
            "type":"Services"
        }
    ],
    "sg:phone":"+1 703 528 5785",
    "sg:postcode":"22203",
    "sg:province":"VA",
    "sg:tags":[
        "advisory",
        "consulting",
        "management",
        "financial"
    ],
    "wof:name":"Government Finance Group Inc",
    "wof:placetype":"venue"
},
  "geometry": {"coordinates":[-77.113287,38.882068],"type":"Point"}
}