{
  "type": "Feature",
  "properties": {
    "iso:country":"US",
    "sg:address":"3319 Lee Hwy",
    "sg:city":"Arlington",
    "sg:classifiers":[
        {
            "category":"Animal Shelter",
            "type":"Public Place"
        }
    ],
    "sg:phone":"+1 703 351 4998",
    "sg:postcode":"22207",
    "sg:province":"VA",
    "wof:name":"Shreves Schudel Devol Saunders Jacksson",
    "wof:placetype":"venue"
},
  "geometry": {"coordinates":[-77.10192499999999,38.896438],"type":"Point"}
}