{
  "type": "Feature",
  "properties": {
    "addr:full":"2705 S Oakland St Arlington VA 22206",
    "addr:housenumber":"2705",
    "addr:postcode":"22206",
    "addr:street":"S Oakland St",
    "iso:country":"US",
    "sg:address":"2705 S Oakland St",
    "sg:city":"Arlington",
    "sg:classifiers":[
        {
            "category":"Retail",
            "subcategory":"Auto Repair",
            "type":"Services"
        }
    ],
    "sg:phone":"+1 703 379 1624",
    "sg:postcode":"22206",
    "sg:province":"VA",
    "sg:tags":[
        "body",
        "shop"
    ],
    "wof:name":"Jose Auto Body",
    "wof:placetype":"venue"
},
  "geometry": {"coordinates":[-77.0896,38.845001],"type":"Point"}
}