{
  "type": "Feature",
  "properties": {
    "addr:full":"25441 Morse Dr Chantilly VA 20152",
    "addr:housenumber":"25441",
    "addr:postcode":"20152",
    "addr:street":"Morse Dr",
    "iso:country":"US",
    "sg:address":"25441 Morse Dr",
    "sg:city":"Chantilly",
    "sg:classifiers":[
        {
            "category":"Arena",
            "subcategory":"Sports Club",
            "type":"Entertainment"
        }
    ],
    "sg:phone":"+1 703 542 6014",
    "sg:postcode":"20152",
    "sg:province":"VA",
    "sg:tags":[
        "production",
        "event"
    ],
    "wof:name":"Ocb Productions LLC",
    "wof:placetype":"venue"
},
  "geometry": {"coordinates":[-77.50933999999999,38.91314],"type":"Point"}
}