{
  "type": "Feature",
  "properties": {
    "addr:full":"1422 Main St SW Roanoke VA 24015",
    "addr:housenumber":"1422",
    "addr:postcode":"24015",
    "addr:street":"Main St Sw",
    "iso:country":"US",
    "sg:address":"1422 Main St SW",
    "sg:city":"Roanoke",
    "sg:classifiers":[
        {
            "category":"Arts & Performance",
            "subcategory":"Theater",
            "type":"Entertainment"
        }
    ],
    "sg:phone":"+1 540 342 5808",
    "sg:postcode":"24015",
    "sg:province":"VA",
    "sg:tags":[
        "live",
        "music"
    ],
    "sg:website":"www.djsonny.com",
    "wof:name":"Sonny Widener DJ Svc",
    "wof:placetype":"venue"
},
  "geometry": {"coordinates":[-79.961299,37.261312],"type":"Point"}
}