{
  "type": "Feature",
  "properties": {
    "iso:country":"US",
    "sg:address":"3401 Fairfax Dr",
    "sg:city":"Arlington",
    "sg:classifiers":[
        {
            "category":"Education",
            "subcategory":"College",
            "type":"Public Place"
        }
    ],
    "sg:phone":"+1 703 993 8199",
    "sg:postcode":"22201",
    "sg:province":"VA",
    "sg:tags":[
        "academic",
        "school"
    ],
    "wof:name":"Va Commonwealth University",
    "wof:placetype":"venue"
},
  "geometry": {"coordinates":[-77.10158699999999,38.884105],"type":"Point"}
}