{
  "type": "Feature",
  "properties": {
    "iso:country":"US",
    "sg:address":"1305 Shallow Ford Rd",
    "sg:city":"Herndon",
    "sg:classifiers":[
        {
            "category":"Building & Trades",
            "subcategory":"Plumbing",
            "type":"Services"
        }
    ],
    "sg:phone":"+1 703 430 8138",
    "sg:postcode":"20170",
    "sg:province":"VA",
    "sg:tags":[
        "plumbing",
        "contractor"
    ],
    "wof:name":"Drain Masters",
    "wof:placetype":"venue"
},
  "geometry": {"coordinates":[-77.374396,39.001431],"type":"Point"}
}