{
  "type": "Feature",
  "properties": {
    "addr:full":"712 Main St Altavista VA 24517",
    "addr:housenumber":"712",
    "addr:postcode":"24517",
    "addr:street":"Main St",
    "iso:country":"US",
    "sg:address":"712 Main St",
    "sg:city":"Altavista",
    "sg:classifiers":[
        {
            "category":"Professional",
            "subcategory":"Lawyer & Legal Services",
            "type":"Services"
        }
    ],
    "sg:phone":"+1 434 369 5661",
    "sg:postcode":"24517",
    "sg:province":"VA",
    "sg:tags":[
        "attorney"
    ],
    "wof:name":"J Johnson Eller Jr",
    "wof:placetype":"venue"
},
  "geometry": {"coordinates":[-79.28700000000001,37.110732],"type":"Point"}
}