{
  "type": "Feature",
  "properties": {
    "addr:full":"60 3rd St NW Pulaski VA 24301",
    "addr:housenumber":"60",
    "addr:postcode":"24301",
    "addr:street":"3Rd St Nw",
    "iso:country":"US",
    "sg:address":"60 3rd St NW",
    "sg:city":"Pulaski",
    "sg:classifiers":[
        {
            "category":"Education",
            "subcategory":"Library",
            "type":"Public Place"
        }
    ],
    "sg:phone":"+1 540 980 7770",
    "sg:postcode":"24301",
    "sg:province":"VA",
    "sg:tags":[
        "executive"
    ],
    "wof:name":"Pulaski County Public Library",
    "wof:placetype":"venue"
},
  "geometry": {"coordinates":[-80.78223300000001,37.049028],"type":"Point"}
}