{
  "type": "Feature",
  "properties": {
    "iso:country":"US",
    "sg:address":"2928 W Cary St",
    "sg:city":"Richmond",
    "sg:classifiers":[
        {
            "category":"Restaurant",
            "type":"Food & Drink"
        }
    ],
    "sg:phone":"+1 804 355 2040",
    "sg:postcode":"23221",
    "sg:province":"VA",
    "sg:tags":[
        "dessert"
    ],
    "wof:name":"Coffee and Co.",
    "wof:placetype":"venue"
},
  "geometry": {"coordinates":[-77.477946,37.552194],"type":"Point"}
}