{
  "type": "Feature",
  "properties": {
    "addr:full":"1522 Park Rd Waynesboro VA 22980",
    "addr:housenumber":"1522",
    "addr:postcode":"22980",
    "addr:street":"Park Rd",
    "iso:country":"US",
    "sg:address":"1522 Park Rd",
    "sg:city":"Waynesboro",
    "sg:classifiers":[
        {
            "category":"Professional",
            "type":"Services"
        }
    ],
    "sg:phone":"+1 540 943 3176",
    "sg:postcode":"22980",
    "sg:province":"VA",
    "sg:tags":[
        "establishment"
    ],
    "wof:name":"RAHE Inc",
    "wof:placetype":"venue"
},
  "geometry": {"coordinates":[-78.90217199999999,38.073925],"type":"Point"}
}