{
  "type": "Feature",
  "properties": {
    "iso:country":"US",
    "sg:address":"8809 Telegraph Rd",
    "sg:city":"Lorton",
    "sg:classifiers":[
        {
            "category":"Building & Trades",
            "subcategory":"Plumbing",
            "type":"Services"
        }
    ],
    "sg:phone":"+1 703 550 2566",
    "sg:postcode":"22079",
    "sg:province":"VA",
    "sg:tags":[
        "contractor"
    ],
    "wof:name":"American Plumbing",
    "wof:placetype":"venue"
},
  "geometry": {"coordinates":[-77.192622,38.718095],"type":"Point"}
}