{
  "type": "Feature",
  "properties": {
    "addr:full":"1710 16th St N Arlington VA 22209",
    "addr:housenumber":"1710",
    "addr:postcode":"22209",
    "addr:street":"16Th St N",
    "iso:country":"US",
    "sg:address":"1710 16th St N",
    "sg:city":"Arlington",
    "sg:classifiers":[
        {
            "category":"Communications",
            "subcategory":"Radio Station",
            "type":"Services"
        }
    ],
    "sg:phone":"+1 703 522 4186",
    "sg:postcode":"22209",
    "sg:province":"VA",
    "sg:tags":[
        "instructor",
        "language",
        "foreign"
    ],
    "wof:name":"Hailu Wondwossen",
    "wof:placetype":"venue"
},
  "geometry": {"coordinates":[-77.077834,38.89191],"type":"Point"}
}