{
  "type": "Feature",
  "properties": {
    "addr:full":"606 Park Ave NE Norton VA 24273",
    "addr:housenumber":"606",
    "addr:postcode":"24273",
    "addr:street":"Park Ave Ne",
    "iso:country":"US",
    "sg:address":"606 Park Ave NE",
    "sg:city":"Norton",
    "sg:classifiers":[
        {
            "category":"Manufacturing",
            "subcategory":"Printing",
            "type":"Manufacturing & Wholesale Goods"
        }
    ],
    "sg:phone":"+1 276 679 2523",
    "sg:postcode":"24273",
    "sg:province":"VA",
    "sg:tags":[
        "newspaper"
    ],
    "wof:name":"Kingsport Times News",
    "wof:placetype":"venue"
},
  "geometry": {"coordinates":[-82.617846,36.945936],"type":"Point"}
}