{
  "type": "Feature",
  "properties": {
    "iso:country":"US",
    "sg:address":"851 Green St",
    "sg:city":"Stephens City",
    "sg:classifiers":[
        {
            "category":"Shopping",
            "type":"Retail Goods"
        }
    ],
    "sg:phone":"+1 540 869 8588",
    "sg:postcode":"22655",
    "sg:province":"VA",
    "sg:tags":[
        "merchandise"
    ],
    "wof:name":"Herbs Warehouse Sales",
    "wof:placetype":"venue"
},
  "geometry": {"coordinates":[-78.21910099999999,39.081858],"type":"Point"}
}