{
  "type": "Feature",
  "properties": {
    "iso:country":"US",
    "sg:address":"35496 General Mahone Blvd",
    "sg:city":"Ivor",
    "sg:classifiers":[
        {
            "category":"Autos & Motor Vehicles",
            "subcategory":"Automobile Sales",
            "type":"Retail Goods"
        }
    ],
    "sg:phone":"+1 757 859 6982",
    "sg:postcode":"23866",
    "sg:province":"VA",
    "sg:tags":[
        "used"
    ],
    "wof:name":"Just Used Auto Sales",
    "wof:placetype":"venue"
},
  "geometry": {"coordinates":[-76.895954,36.908301],"type":"Point"}
}