{
  "type": "Feature",
  "properties": {
    "addr:full":"3608 S Plaza Trl Virginia Beach VA 23452",
    "addr:housenumber":"3608",
    "addr:postcode":"23452",
    "addr:street":"S Plaza Trl",
    "iso:country":"US",
    "sg:address":"3608 S Plaza Trl",
    "sg:city":"Virginia Beach",
    "sg:classifiers":[
        {
            "category":"Government",
            "subcategory":"Fire Station",
            "type":"Public Place"
        }
    ],
    "sg:phone":"+1 757 431 3728",
    "sg:postcode":"23452",
    "sg:province":"VA",
    "sg:tags":[
        "protection"
    ],
    "wof:name":"Fire Dept-Station 16",
    "wof:placetype":"venue"
},
  "geometry": {"coordinates":[-76.09589699999999,36.830001],"type":"Point"}
}