{
  "type": "Feature",
  "properties": {
    "iso:country":"US",
    "sg:address":"3834 Virginia Beach Blvd",
    "sg:city":"Virginia Beach",
    "sg:classifiers":[
        {
            "category":"Retail",
            "subcategory":"Portrait Studio",
            "type":"Services"
        }
    ],
    "sg:phone":"+1 757 431 1121",
    "sg:postcode":"23452",
    "sg:province":"VA",
    "sg:tags":[
        "photography"
    ],
    "wof:name":"Lifetime Memories",
    "wof:placetype":"venue"
},
  "geometry": {"coordinates":[-76.108318,36.840177],"type":"Point"}
}