{
  "type": "Feature",
  "properties": {
    "iso:country":"US",
    "sg:address":"210 E Southwerk St",
    "sg:city":"Winchester",
    "sg:classifiers":[
        {
            "category":"Manufacturing",
            "subcategory":"Signs",
            "type":"Manufacturing & Wholesale Goods"
        }
    ],
    "sg:phone":"+1 540 662 1089",
    "sg:postcode":"22601",
    "sg:province":"VA",
    "sg:tags":[
        "specialty",
        "mfg"
    ],
    "wof:name":"A Sign For You LLC",
    "wof:placetype":"venue"
},
  "geometry": {"coordinates":[-78.164942,39.172779],"type":"Point"}
}