{
  "type": "Feature",
  "properties": {
    "iso:country":"US",
    "sg:address":"6349 Maddox Blvd",
    "sg:city":"Chincoteague",
    "sg:classifiers":[
        {
            "category":"Personal",
            "subcategory":"Beauty Salon",
            "type":"Services"
        }
    ],
    "sg:phone":"+1 757 336 6300",
    "sg:postcode":"23336",
    "sg:province":"VA",
    "sg:tags":[
        "manicuring"
    ],
    "wof:name":"Glamour Nails",
    "wof:placetype":"venue"
},
  "geometry": {"coordinates":[-75.36493400000001,37.933602],"type":"Point"}
}