{
  "type": "Feature",
  "properties": {
    "iso:country":"US",
    "sg:address":"7375 Sudley Rd",
    "sg:city":"Manassas",
    "sg:classifiers":[
        {
            "category":"Autos & Motor Vehicles",
            "subcategory":"Auto Supplies",
            "type":"Retail Goods"
        }
    ],
    "sg:phone":"+1 703 367 7390",
    "sg:postcode":"20109",
    "sg:province":"VA",
    "sg:tags":[
        "automobile",
        "stereo",
        "radio"
    ],
    "sg:website":"www.tweeter.com",
    "wof:name":"Tweeter",
    "wof:placetype":"venue"
},
  "geometry": {"coordinates":[-77.517071,38.795713],"type":"Point"}
}