{
  "type": "Feature",
  "properties": {
    "iso:country":"US",
    "sg:address":"3605 Hopkins Rd",
    "sg:city":"Richmond",
    "sg:classifiers":[
        {
            "category":"Freight",
            "type":"Transportation"
        }
    ],
    "sg:phone":"+1 804 233 3191",
    "sg:postcode":"23234",
    "sg:province":"VA",
    "sg:tags":[
        "trucking"
    ],
    "sg:website":"www.centraltransportint.com",
    "wof:name":"Central Transport Inc",
    "wof:placetype":"venue"
},
  "geometry": {"coordinates":[-77.46863999999999,37.473265],"type":"Point"}
}