{
  "type": "Feature",
  "properties": {
    "addr:full":"1717 Driftwood Ln SW Roanoke VA 24018",
    "addr:housenumber":"1717",
    "addr:postcode":"24018",
    "addr:street":"Driftwood Ln Sw",
    "iso:country":"US",
    "sg:address":"1717 Driftwood Ln SW",
    "sg:city":"Roanoke",
    "sg:classifiers":[
        {
            "category":"Insurance",
            "subcategory":"Life Insurance",
            "type":"Services"
        }
    ],
    "sg:phone":"+1 540 774 1748",
    "sg:postcode":"24018",
    "sg:province":"VA",
    "sg:tags":[
        "carrier"
    ],
    "wof:name":"John A Morra Agency",
    "wof:placetype":"venue"
},
  "geometry": {"coordinates":[-80.029641,37.252012],"type":"Point"}
}