{
  "type": "Feature",
  "properties": {
    "iso:country":"US",
    "sg:address":"406 13th St NE",
    "sg:city":"Charlottesville",
    "sg:classifiers":[
        {
            "category":"Wholesale",
            "subcategory":"Apparel",
            "type":"Manufacturing & Wholesale Goods"
        }
    ],
    "sg:phone":"+1 434 977 5013",
    "sg:postcode":"22902",
    "sg:province":"VA",
    "sg:tags":[
        "clothing"
    ],
    "wof:name":"Memees Closet",
    "wof:placetype":"venue"
},
  "geometry": {"coordinates":[-78.46616899999999,38.029971],"type":"Point"}
}