{
  "type": "Feature",
  "properties": {
    "iso:country":"US",
    "sg:address":"1823 Pimmit Dr",
    "sg:city":"Falls Church",
    "sg:classifiers":[
        {
            "category":"Building & Trades",
            "subcategory":"Construction",
            "type":"Services"
        }
    ],
    "sg:phone":"+1 703 734 9650",
    "sg:postcode":"22043",
    "sg:province":"VA",
    "sg:tags":[
        "home",
        "improvement"
    ],
    "wof:name":"Complete Home Solutions Inc",
    "wof:placetype":"venue"
},
  "geometry": {"coordinates":[-77.196467,38.919191],"type":"Point"}
}