{
  "type": "Feature",
  "properties": {
    "addr:full":"3492 Gamage Dr Norfolk VA 23518",
    "addr:housenumber":"3492",
    "addr:postcode":"23518",
    "addr:street":"Gamage Dr",
    "iso:country":"US",
    "sg:address":"3492 Gamage Dr",
    "sg:city":"Norfolk",
    "sg:classifiers":[
        {
            "category":"Airline",
            "type":"Transportation"
        }
    ],
    "sg:phone":"+1 757 615 3734",
    "sg:postcode":"23518",
    "sg:province":"VA",
    "sg:tags":[
        "cargo",
        "air"
    ],
    "wof:name":"Full Sail Inc",
    "wof:placetype":"venue"
},
  "geometry": {"coordinates":[-76.214927,36.892643],"type":"Point"}
}