{
  "type": "Feature",
  "properties": {
    "iso:country":"US",
    "sg:address":"6198 Old Franconia Rd",
    "sg:city":"Alexandria",
    "sg:classifiers":[
        {
            "category":"Professional",
            "type":"Services"
        }
    ],
    "sg:phone":"+1 703 719 5578",
    "sg:postcode":"22310",
    "sg:province":"VA",
    "wof:name":"Ginko Therapy",
    "wof:placetype":"venue"
},
  "geometry": {"coordinates":[-77.152315,38.780629],"type":"Point"}
}