{
  "type": "Feature",
  "properties": {
    "iso:country":"US",
    "sg:address":"3149 Pittsville Rd",
    "sg:city":"Gretna",
    "sg:classifiers":[
        {
            "category":"Building & Trades",
            "subcategory":"Electrical",
            "type":"Services"
        }
    ],
    "sg:phone":"+1 434 656 8113",
    "sg:postcode":"24557",
    "sg:province":"VA",
    "sg:tags":[
        "electrical",
        "contractor"
    ],
    "sg:website":"www.ross-electric.com",
    "wof:name":"Ross Electric Inc",
    "wof:placetype":"venue"
},
  "geometry": {"coordinates":[-79.430294,36.98442],"type":"Point"}
}