{
  "type": "Feature",
  "properties": {
    "addr:full":"2576 Free Union Rd Charlottesville VA 22901",
    "addr:housenumber":"2576",
    "addr:postcode":"22901",
    "addr:street":"Free Union Rd",
    "iso:country":"US",
    "sg:address":"2576 Free Union Rd",
    "sg:city":"Charlottesville",
    "sg:classifiers":[
        {
            "category":"Real Estate",
            "subcategory":"Real Estate Agent",
            "type":"Services"
        }
    ],
    "sg:phone":"+1 434 971 7587",
    "sg:postcode":"22901",
    "sg:province":"VA",
    "wof:name":"Johnson Village Inc",
    "wof:placetype":"venue"
},
  "geometry": {"coordinates":[-78.552176,38.106091],"type":"Point"}
}