{
  "type": "Feature",
  "properties": {
    "iso:country":"US",
    "sg:address":"4300 Thomas Ln",
    "sg:city":"Chesapeake",
    "sg:classifiers":[
        {
            "category":"Professional",
            "type":"Services"
        }
    ],
    "sg:phone":"+1 757 483 5921",
    "sg:postcode":"23321",
    "sg:province":"VA",
    "wof:name":"B & S Services",
    "wof:placetype":"venue"
},
  "geometry": {"coordinates":[-76.410055,36.848592],"type":"Point"}
}