{
  "type": "Feature",
  "properties": {
    "iso:country":"US",
    "sg:address":"7902 Freehollow Dr",
    "sg:city":"Falls Church",
    "sg:classifiers":[
        {
            "category":"Professional",
            "subcategory":"Lawyer & Legal Services",
            "type":"Services"
        }
    ],
    "sg:phone":"+1 703 208 1024",
    "sg:postcode":"22042",
    "sg:province":"VA",
    "wof:name":"Charles K Morrison",
    "wof:placetype":"venue"
},
  "geometry": {"coordinates":[-77.217786,38.85568],"type":"Point"}
}