{
  "type": "Feature",
  "properties": {
    "iso:country":"US",
    "sg:address":"1800 Diagonal Rd",
    "sg:city":"Alexandria",
    "sg:classifiers":[
        {
            "category":"Banks & Credit Unions",
            "subcategory":"Investment Brokerage",
            "type":"Services"
        }
    ],
    "sg:phone":"+1 571 366 1700",
    "sg:postcode":"22314",
    "sg:province":"VA",
    "sg:tags":[
        "advisory"
    ],
    "wof:name":"Tortoise Capital Advisors",
    "wof:placetype":"venue"
},
  "geometry": {"coordinates":[-77.05986799999999,38.806122],"type":"Point"}
}