{
  "type": "Feature",
  "properties": {
    "iso:country":"US",
    "sg:address":"3402 Plantation Rd NE",
    "sg:city":"Roanoke",
    "sg:classifiers":[
        {
            "category":"Professional",
            "subcategory":"Employment Agencies",
            "type":"Services"
        }
    ],
    "sg:phone":"+1 540 283 9886",
    "sg:postcode":"24012",
    "sg:province":"VA",
    "sg:tags":[
        "temporary",
        "help"
    ],
    "sg:website":"http://roanoke.citysearch.com/profile/external/10635737/roanoke_va/manpower.html?publisher=yellowpages&reference_id=1&placement=ypwebsitemip",
    "wof:name":"Manpower",
    "wof:placetype":"venue"
},
  "geometry": {"coordinates":[-79.931753,37.30614],"type":"Point"}
}