{
  "type": "Feature",
  "properties": {
    "addr:full":"7808 Cinderbed Rd Lorton VA 22079",
    "addr:housenumber":"7808",
    "addr:postcode":"22079",
    "addr:street":"Cinderbed Rd",
    "iso:country":"US",
    "sg:address":"7808 Cinderbed Rd",
    "sg:city":"Lorton",
    "sg:classifiers":[
        {
            "category":"Building & Trades",
            "subcategory":"Construction",
            "type":"Services"
        }
    ],
    "sg:phone":"+1 703 541 9283",
    "sg:postcode":"22079",
    "sg:province":"VA",
    "sg:tags":[
        "builder",
        "operative",
        "nonresidential"
    ],
    "wof:name":"Neco Construction & Management",
    "wof:placetype":"venue"
},
  "geometry": {"coordinates":[-77.17991600000001,38.7455],"type":"Point"}
}