{
  "type": "Feature",
  "properties": {
    "iso:country":"US",
    "sg:address":"1108 Jefferson St",
    "sg:city":"Alexandria",
    "sg:classifiers":[
        {
            "category":"Government",
            "subcategory":"Office",
            "type":"Public Place"
        }
    ],
    "sg:phone":"+1 703 838 4999",
    "sg:postcode":"22314",
    "sg:province":"VA",
    "sg:tags":[
        "village"
    ],
    "wof:name":"Alexandria City Arborist",
    "wof:placetype":"venue"
},
  "geometry": {"coordinates":[-77.05369899999999,38.797549],"type":"Point"}
}