{
  "type": "Feature",
  "properties": {
    "addr:full":"3200 Washington Blvd Arlington VA 22201",
    "addr:housenumber":"3200",
    "addr:postcode":"22201",
    "addr:street":"Washington Blvd",
    "iso:country":"US",
    "sg:address":"3200 Washington Blvd",
    "sg:city":"Arlington",
    "sg:phone":"+1 703 276 7387",
    "sg:postcode":"22201",
    "sg:province":"VA",
    "sg:website":"http://www.petco.com",
    "wof:name":"PETCO",
    "wof:placetype":"venue"
},
  "geometry": {"coordinates":[-77.097511,38.886028],"type":"Point"}
}