{
  "type": "Feature",
  "properties": {
    "iso:country":"US",
    "sg:address":"105 N Union St Ste 224",
    "sg:city":"Alexandria",
    "sg:classifiers":[
        {
            "category":"Wholesale",
            "subcategory":"Painting Supplies",
            "type":"Manufacturing & Wholesale Goods"
        },
        {
            "category":"Arts & Performance",
            "subcategory":"Art Gallery",
            "type":"Entertainment"
        },
        {
            "category":"Shopping",
            "subcategory":"Crafts & Fabrics",
            "type":"Retail Goods"
        }
    ],
    "sg:phone":"+1 703 549 1434",
    "sg:postcode":"22314",
    "sg:province":"VA",
    "sg:tags":[
        "consultant",
        "goods-wholesale",
        "galleries",
        "manufacturer"
    ],
    "sg:website":"http://www.rosemaryfeitcovey.com",
    "wof:name":"Covey, Rosemary",
    "wof:placetype":"venue"
},
  "geometry": {"coordinates":[-77.04025900000001,38.804276],"type":"Point"}
}