{
  "type": "Feature",
  "properties": {
    "addr:full":"6563 Loisdale Rd Springfield VA 22150",
    "addr:postcode":"6563;22150",
    "addr:street":"Loisdale Rd",
    "iso:country":"US",
    "sg:address":"6563 Loisdale Rd",
    "sg:city":"Springfield",
    "sg:classifiers":[
        {
            "category":"Personal",
            "type":"Services"
        }
    ],
    "sg:phone":"+1 703 924 9100",
    "sg:postcode":"22150",
    "sg:province":"VA",
    "sg:tags":[
        "wear",
        "formal"
    ],
    "wof:name":"Blue Gene's",
    "wof:placetype":"venue"
},
  "geometry": {"coordinates":[-77.176035,38.777946],"type":"Point"}
}