{
  "type": "Feature",
  "properties": {
    "addr:full":"7502 Diplomat Dr Manassas VA 20109",
    "addr:housenumber":"7502",
    "addr:postcode":"20109",
    "addr:street":"Diplomat Dr",
    "iso:country":"US",
    "sg:address":"7502 Diplomat Dr",
    "sg:city":"Manassas",
    "sg:classifiers":[
        {
            "category":"Building & Trades",
            "subcategory":"Equipment Rental",
            "type":"Services"
        }
    ],
    "sg:phone":"+1 703 361 1191",
    "sg:postcode":"20109",
    "sg:province":"VA",
    "sg:tags":[
        "aircraft",
        "leasing",
        "charter"
    ],
    "sg:website":"www.mercymedical.org",
    "wof:name":"Mercy Medical Airlift",
    "wof:placetype":"venue"
},
  "geometry": {"coordinates":[-77.51804799999999,38.793904],"type":"Point"}
}