{
  "type": "Feature",
  "properties": {
    "iso:country":"US",
    "sg:address":"2100 Clover Hill Rd",
    "sg:city":"Dayton",
    "sg:classifiers":[
        {
            "category":"Government",
            "subcategory":"Fire Station",
            "type":"Public Place"
        }
    ],
    "sg:phone":"+1 540 879 9930",
    "sg:postcode":"22821",
    "sg:province":"VA",
    "sg:tags":[
        "department",
        "protection"
    ],
    "wof:name":"Clover Hill Fire Department",
    "wof:placetype":"venue"
},
  "geometry": {"coordinates":[-79.025015,38.458456],"type":"Point"}
}