{
  "type": "Feature",
  "properties": {
    "addr:full":"501 Washington Ave Colonial Beach VA 22443",
    "addr:housenumber":"501",
    "addr:postcode":"beach;22443",
    "addr:street":"Washington Ave",
    "iso:country":"US",
    "sg:address":"501 Washington Ave",
    "sg:city":"Colonial Beach",
    "sg:classifiers":[
        {
            "category":"Real Estate",
            "subcategory":"Real Estate Agent",
            "type":"Services"
        }
    ],
    "sg:phone":"+1 804 224 0001",
    "sg:postcode":"22443",
    "sg:province":"VA",
    "wof:name":"Colonial Beach Real Estate",
    "wof:placetype":"venue"
},
  "geometry": {"coordinates":[-76.963571,38.255255],"type":"Point"}
}