{
  "type": "Feature",
  "properties": {
    "iso:country":"US",
    "sg:address":"2021 Haviland Dr",
    "sg:city":"Virginia Beach",
    "sg:classifiers":[
        {
            "category":"Professional",
            "subcategory":"Research",
            "type":"Services"
        }
    ],
    "sg:phone":"+1 757 301 9527",
    "sg:postcode":"23454",
    "sg:province":"VA",
    "sg:tags":[
        "environmental",
        "ecological"
    ],
    "wof:name":"Air Link Environmental",
    "wof:placetype":"venue"
},
  "geometry": {"coordinates":[-75.98766999999999,36.770368],"type":"Point"}
}