{
  "type": "Feature",
  "properties": {
    "addr:full":"6635 Greensboro Rd Ridgeway VA 24148",
    "addr:housenumber":"6635",
    "addr:postcode":"24148",
    "addr:street":"Greensboro Rd",
    "iso:country":"US",
    "sg:address":"6635 Greensboro Rd",
    "sg:city":"Ridgeway",
    "sg:classifiers":[
        {
            "category":"Home & Garden",
            "subcategory":"Carpets & Floor Coverings",
            "type":"Retail Goods"
        }
    ],
    "sg:phone":"+1 276 956 2559",
    "sg:postcode":"24148",
    "sg:province":"VA",
    "sg:tags":[
        "material"
    ],
    "wof:name":"Custom Floor Covering",
    "wof:placetype":"venue"
},
  "geometry": {"coordinates":[-79.86173599999999,36.60172],"type":"Point"}
}