{
  "type": "Feature",
  "properties": {
    "addr:full":"231 Shady Ln Hillsville VA 24343",
    "addr:housenumber":"231",
    "addr:postcode":"24343",
    "addr:street":"Shady Ln",
    "iso:country":"US",
    "sg:address":"231 Shady Ln",
    "sg:city":"Hillsville",
    "sg:classifiers":[
        {
            "category":"Building & Trades",
            "subcategory":"Construction",
            "type":"Services"
        }
    ],
    "sg:phone":"+1 276 728 7563",
    "sg:postcode":"24343",
    "sg:province":"VA",
    "sg:tags":[
        "contractor"
    ],
    "wof:name":"Edwards Drywall Co",
    "wof:placetype":"venue"
},
  "geometry": {"coordinates":[-80.753326,36.779732],"type":"Point"}
}