{
  "type": "Feature",
  "properties": {
    "iso:country":"US",
    "sg:address":"5220 Rolling Rd",
    "sg:city":"Burke",
    "sg:classifiers":[
        {
            "category":"Retail",
            "subcategory":"Laundry & Dry Cleaning",
            "type":"Services"
        }
    ],
    "sg:phone":"+1 703 425 7900",
    "sg:postcode":"22015",
    "sg:province":"VA",
    "sg:tags":[
        "cleaners"
    ],
    "wof:name":"Ki Hyeon Pak",
    "wof:placetype":"venue"
},
  "geometry": {"coordinates":[-77.25503,38.808023],"type":"Point"}
}