{
  "type": "Feature",
  "properties": {
    "addr:full":"24 E Loudoun St Leesburg VA 20141",
    "addr:housenumber":"24",
    "addr:postcode":"20141",
    "addr:street":"E Loudoun St",
    "iso:country":"US",
    "sg:address":"24 E Loudoun St",
    "sg:city":"Leesburg",
    "sg:classifiers":[
        {
            "category":"Retail",
            "subcategory":"Auto Repair",
            "type":"Services"
        }
    ],
    "sg:phone":"+1 540 338 3116",
    "sg:postcode":"20141",
    "sg:province":"VA",
    "sg:tags":[
        "repairing",
        "automobile"
    ],
    "wof:name":"Clark's Cycle Auto Repairs",
    "wof:placetype":"venue"
},
  "geometry": {"coordinates":[-77.76792500000001,39.132871],"type":"Point"}
}