{
  "type": "Feature",
  "properties": {
    "addr:full":"10 Weems Ln Winchester VA 22601",
    "addr:housenumber":"10",
    "addr:postcode":"22601",
    "addr:street":"Weems Ln",
    "iso:country":"US",
    "sg:address":"10 Weems Ln",
    "sg:city":"Winchester",
    "sg:classifiers":[
        {
            "category":"Shopping",
            "subcategory":"Discount & Variety Stores",
            "type":"Retail Goods"
        }
    ],
    "sg:phone":"+1 540 722 9722",
    "sg:postcode":"22601",
    "sg:province":"VA",
    "wof:name":"Dollar N More",
    "wof:placetype":"venue"
},
  "geometry": {"coordinates":[-78.17684300000001,39.161463],"type":"Point"}
}