{
  "type": "Feature",
  "properties": {
    "addr:full":"8397 Terminal Rd Lorton VA 22079",
    "addr:housenumber":"8397",
    "addr:postcode":"22079",
    "addr:street":"Terminal Rd",
    "iso:country":"US",
    "sg:address":"8397 Terminal Rd",
    "sg:city":"Lorton",
    "sg:classifiers":[
        {
            "category":"Retail",
            "subcategory":"Repair Shop",
            "type":"Services"
        }
    ],
    "sg:phone":"+1 703 842 5130",
    "sg:postcode":"22079",
    "sg:province":"VA",
    "sg:tags":[
        "lock",
        "locksmith"
    ],
    "wof:name":"1 All Day Emergency",
    "wof:placetype":"venue"
},
  "geometry": {"coordinates":[-77.190308,38.734272],"type":"Point"}
}