{
  "type": "Feature",
  "properties": {
    "iso:country":"US",
    "sg:address":"1548 Lawyers Rd",
    "sg:city":"Lynchburg",
    "sg:classifiers":[
        {
            "category":"Building & Trades",
            "subcategory":"Construction",
            "type":"Services"
        }
    ],
    "sg:phone":"+1 434 239 9119",
    "sg:postcode":"24501",
    "sg:province":"VA",
    "sg:tags":[
        "paving",
        "contractor"
    ],
    "sg:website":"www.mvt-sons.com",
    "wof:name":"Marvin V Templeton & Sons Inc",
    "wof:placetype":"venue"
},
  "geometry": {"coordinates":[-79.205585,37.301059],"type":"Point"}
}