{
  "type": "Feature",
  "properties": {
    "iso:country":"US",
    "sg:address":"3976 Butler Dr",
    "sg:city":"Suffolk",
    "sg:classifiers":[
        {
            "category":"Real Estate",
            "subcategory":"Real Estate Operator",
            "type":"Services"
        }
    ],
    "sg:phone":"+1 757 986 4736",
    "sg:postcode":"23437",
    "sg:province":"VA",
    "sg:tags":[
        "property",
        "lessor"
    ],
    "wof:name":"Samuel Barnes",
    "wof:placetype":"venue"
},
  "geometry": {"coordinates":[-76.77364900000001,36.597289],"type":"Point"}
}