{
  "type": "Feature",
  "properties": {
    "iso:country":"US",
    "sg:address":"2707 Mosby St",
    "sg:city":"Alexandria",
    "sg:classifiers":[
        {
            "category":"Professional",
            "subcategory":"Research",
            "type":"Services"
        }
    ],
    "sg:phone":"+1 703 548 1327",
    "sg:postcode":"22305",
    "sg:province":"VA",
    "sg:tags":[
        "nonphysical",
        "commercial"
    ],
    "wof:name":"Arnolds Research Corp",
    "wof:placetype":"venue"
},
  "geometry": {"coordinates":[-77.064431,38.833119],"type":"Point"}
}