{
  "type": "Feature",
  "properties": {
    "addr:full":"5827 Columbia Pike Falls Church VA 22041",
    "addr:housenumber":"5827",
    "addr:postcode":"22041",
    "addr:street":"Columbia Pike",
    "iso:country":"US",
    "sg:address":"5827 Columbia Pike",
    "sg:city":"Falls Church",
    "sg:classifiers":[
        {
            "category":"Health Services",
            "subcategory":"Doctor",
            "type":"Services"
        }
    ],
    "sg:phone":"+1 703 820 7170",
    "sg:postcode":"22041",
    "sg:province":"VA",
    "sg:tags":[
        "dentist"
    ],
    "wof:name":"Northern Virginia Dental",
    "wof:placetype":"venue"
},
  "geometry": {"coordinates":[-77.131896,38.849343],"type":"Point"}
}