{
  "type": "Feature",
  "properties": {
    "addr:full":"5214 W Grace St Richmond VA 23226",
    "addr:housenumber":"5214",
    "addr:postcode":"23226",
    "addr:street":"W Grace St",
    "iso:country":"US",
    "sg:address":"5214 W Grace St",
    "sg:city":"Richmond",
    "sg:classifiers":[
        {
            "category":"Health Services",
            "subcategory":"Clinic",
            "type":"Services"
        }
    ],
    "sg:phone":"+1 804 288 1521",
    "sg:postcode":"23226",
    "sg:province":"VA",
    "wof:name":"Rainbow Recipe",
    "wof:placetype":"venue"
},
  "geometry": {"coordinates":[-77.50351499999999,37.581143],"type":"Point"}
}