{
  "type": "Feature",
  "properties": {
    "addr:full":"615 Bland Blvd Newport News VA 23602",
    "addr:housenumber":"615",
    "addr:postcode":"23602",
    "addr:street":"Bland Blvd",
    "iso:country":"US",
    "sg:address":"615 Bland Blvd",
    "sg:city":"Newport News",
    "sg:classifiers":[
        {
            "category":"Restaurant",
            "type":"Food & Drink"
        }
    ],
    "sg:phone":"+1 757 874 5256",
    "sg:postcode":"23602",
    "sg:province":"VA",
    "sg:tags":[
        "machine",
        "operator",
        "vending",
        "contract"
    ],
    "wof:name":"Centerplate",
    "wof:placetype":"venue"
},
  "geometry": {"coordinates":[-76.518176,37.12475],"type":"Point"}
}