{
  "type": "Feature",
  "properties": {
    "addr:full":"2499 E Washington Ave Vinton VA 24179",
    "addr:housenumber":"2499",
    "addr:postcode":"24179",
    "addr:street":"E Washington Ave",
    "iso:country":"US",
    "sg:address":"2499 E Washington Ave",
    "sg:city":"Vinton",
    "sg:classifiers":[
        {
            "category":"Food & Beverages",
            "subcategory":"Groceries & Convenience Stores",
            "type":"Retail Goods"
        }
    ],
    "sg:phone":"+1 540 890 8399",
    "sg:postcode":"24179",
    "sg:province":"VA",
    "wof:name":"Sky Mart",
    "wof:placetype":"venue"
},
  "geometry": {"coordinates":[-79.863179,37.28004],"type":"Point"}
}