{
  "type": "Feature",
  "properties": {
    "iso:country":"US",
    "sg:address":"12330 James Madison Hwy",
    "sg:city":"Palmyra",
    "sg:classifiers":[
        {
            "category":"Travel",
            "subcategory":"Hotels & Motels",
            "type":"Entertainment"
        }
    ],
    "sg:phone":"+1 434 589 1977",
    "sg:postcode":"22963",
    "sg:province":"VA",
    "sg:tags":[
        "breakfast",
        "accommodation",
        "bed"
    ],
    "wof:name":"Old Courthouse Inn",
    "wof:placetype":"venue"
},
  "geometry": {"coordinates":[-78.27188099999999,37.847025],"type":"Point"}
}