{
  "type": "Feature",
  "properties": {
    "addr:full":"1125 Gaskins Rd Richmond VA 23238",
    "addr:housenumber":"1125",
    "addr:postcode":"23238",
    "addr:street":"Gaskins Rd",
    "iso:country":"US",
    "sg:address":"1125 Gaskins Rd",
    "sg:city":"Richmond",
    "sg:classifiers":[
        {
            "category":"Wholesale",
            "subcategory":"Stationery",
            "type":"Manufacturing & Wholesale Goods"
        }
    ],
    "sg:phone":"+1 804 741 6855",
    "sg:postcode":"23238",
    "sg:province":"VA",
    "sg:tags":[
        "paper",
        "representative",
        "plastic"
    ],
    "wof:name":"TP & P",
    "wof:placetype":"venue"
},
  "geometry": {"coordinates":[-77.594112,37.596941],"type":"Point"}
}