{
  "type": "Feature",
  "properties": {
    "iso:country":"US",
    "sg:address":"1453 Clearbrook Ln",
    "sg:city":"Charlottesville",
    "sg:classifiers":[
        {
            "category":"Retail",
            "subcategory":"Repair Shop",
            "type":"Services"
        }
    ],
    "sg:phone":"+1 434 978 4911",
    "sg:postcode":"22911",
    "sg:province":"VA",
    "sg:tags":[
        "electrical"
    ],
    "wof:name":"Interlaken Inc",
    "wof:placetype":"venue"
},
  "geometry": {"coordinates":[-78.417106,38.074739],"type":"Point"}
}