{
  "type": "Feature",
  "properties": {
    "addr:full":"415 Mason St Dayton VA 22821",
    "addr:housenumber":"415",
    "addr:postcode":"22821",
    "addr:street":"Mason St",
    "iso:country":"US",
    "sg:address":"415 Mason St",
    "sg:city":"Dayton",
    "sg:classifiers":[
        {
            "category":"Manufacturing",
            "subcategory":"Glass & Minerals",
            "type":"Manufacturing & Wholesale Goods"
        }
    ],
    "sg:phone":"+1 540 879 2110",
    "sg:postcode":"22821",
    "sg:province":"VA",
    "sg:tags":[
        "plate",
        "window",
        "replacement",
        "repair"
    ],
    "sg:website":"http://www.braithwaitestudios.com",
    "wof:name":"Braithwaite Studios",
    "wof:placetype":"venue"
},
  "geometry": {"coordinates":[-78.944107,38.412776],"type":"Point"}
}