{
  "type": "Feature",
  "properties": {
    "addr:full":"2483 Northumberland Hwy Lottsburg VA 22511",
    "addr:housenumber":"2483",
    "addr:postcode":"22511",
    "addr:street":"Northumberland Hwy",
    "iso:country":"US",
    "sg:address":"2483 Northumberland Hwy",
    "sg:city":"Lottsburg",
    "sg:classifiers":[
        {
            "category":"Building & Trades",
            "subcategory":"Construction",
            "type":"Services"
        }
    ],
    "sg:phone":"+1 804 529 6118",
    "sg:postcode":"22511",
    "sg:province":"VA",
    "sg:tags":[
        "contractor"
    ],
    "wof:name":"Manning Builders",
    "wof:placetype":"venue"
},
  "geometry": {"coordinates":[-76.52354099999999,37.96723],"type":"Point"}
}