{
  "type": "Feature",
  "properties": {
    "addr:full":"459 Locust Ave Charlottesville VA 22902",
    "addr:housenumber":"459",
    "addr:postcode":"22902",
    "addr:street":"Locust Ave",
    "iso:country":"US",
    "sg:address":"459 Locust Ave",
    "sg:city":"Charlottesville",
    "sg:classifiers":[
        {
            "category":"Professional",
            "subcategory":"Management & Consulting",
            "type":"Services"
        }
    ],
    "sg:phone":"+1 434 982 7000",
    "sg:postcode":"22902",
    "sg:province":"VA",
    "sg:tags":[
        "hospital"
    ],
    "wof:name":"Martha Jefferson Wns Hlth Ctr",
    "wof:placetype":"venue"
},
  "geometry": {"coordinates":[-78.471261,38.031953],"type":"Point"}
}