{
  "type": "Feature",
  "properties": {
    "addr:full":"13875 Napa Dr Manassas VA 20112",
    "addr:housenumber":"13875",
    "addr:postcode":"20112",
    "addr:street":"Napa Dr",
    "iso:country":"US",
    "sg:address":"13875 Napa Dr",
    "sg:city":"Manassas",
    "sg:classifiers":[
        {
            "category":"Building & Trades",
            "subcategory":"Cleaning & Sanitation",
            "type":"Services"
        },
        {
            "category":"Retail",
            "subcategory":"Repair Shop",
            "type":"Services"
        }
    ],
    "sg:phone":"+1 703 791 3977",
    "sg:postcode":"20112",
    "sg:province":"VA",
    "sg:tags":[
        "janitor",
        "maintenance"
    ],
    "wof:name":"Bedknobs & Broomsticks Clg",
    "wof:placetype":"venue"
},
  "geometry": {"coordinates":[-77.422374,38.655237],"type":"Point"}
}