{
  "type": "Feature",
  "properties": {
    "addr:full":"8100 Wolftrap Rd Vienna VA 22182",
    "addr:housenumber":"8100",
    "addr:postcode":"22182",
    "addr:street":"Wolftrap Rd",
    "iso:country":"US",
    "sg:address":"8100 Wolftrap Rd",
    "sg:city":"Vienna",
    "sg:classifiers":[
        {
            "category":"Education",
            "subcategory":"School",
            "type":"Public Place"
        }
    ],
    "sg:phone":"+1 703 846 8800",
    "sg:postcode":"22182",
    "sg:province":"VA",
    "sg:tags":[
        "high",
        "middle",
        "elementary"
    ],
    "wof:name":"Fairfax County School District",
    "wof:placetype":"venue"
},
  "geometry": {"coordinates":[-77.223939,38.902346],"type":"Point"}
}