{
  "type": "Feature",
  "properties": {
    "addr:full":"1523 Rodman Ave Portsmouth VA 23707",
    "addr:housenumber":"1523",
    "addr:postcode":"23707",
    "addr:street":"Rodman Ave",
    "iso:country":"US",
    "sg:address":"1523 Rodman Ave",
    "sg:city":"Portsmouth",
    "sg:classifiers":[
        {
            "category":"Professional",
            "subcategory":"Accounting & Tax Preparation",
            "type":"Services"
        }
    ],
    "sg:phone":"+1 757 399 6881",
    "sg:postcode":"23707",
    "sg:province":"VA",
    "sg:tags":[
        "bookkeeping",
        "return",
        "filing"
    ],
    "wof:name":"Earlies Bookkeeping & Tax Svcs",
    "wof:placetype":"venue"
},
  "geometry": {"coordinates":[-76.34720900000001,36.82613],"type":"Point"}
}