{
  "type": "Feature",
  "properties": {
    "addr:full":"2722 Colley Ave Norfolk VA 23517",
    "addr:housenumber":"2722",
    "addr:postcode":"23517",
    "addr:street":"Colley Ave",
    "iso:country":"US",
    "sg:address":"2722 Colley Ave",
    "sg:city":"Norfolk",
    "sg:classifiers":[
        {
            "category":"Home & Garden",
            "subcategory":"Carpets & Floor Coverings",
            "type":"Retail Goods"
        }
    ],
    "sg:phone":"+1 757 627 0238",
    "sg:postcode":"23517",
    "sg:province":"VA",
    "sg:tags":[
        "installs",
        "refinishes",
        "ma",
        "flooring",
        "wooden"
    ],
    "wof:name":"Jayen Company",
    "wof:placetype":"venue"
},
  "geometry": {"coordinates":[-76.295058,36.875771],"type":"Point"}
}