{
  "type": "Feature",
  "properties": {
    "iso:country":"US",
    "sg:address":"3801 Fairfax Dr",
    "sg:city":"Arlington",
    "sg:classifiers":[
        {
            "category":"Health Services",
            "subcategory":"Doctor",
            "type":"Services"
        }
    ],
    "sg:phone":"+1 703 351 9700",
    "sg:postcode":"22203",
    "sg:province":"VA",
    "wof:name":"Filipescu Nicolae Dr",
    "wof:placetype":"venue"
},
  "geometry": {"coordinates":[-77.105008,38.882937],"type":"Point"}
}