{
  "type": "Feature",
  "properties": {
    "iso:country":"US",
    "sg:address":"9205 Happy Hollow Ln",
    "sg:city":"Spotsylvania",
    "sg:classifiers":[
        {
            "category":"Shopping",
            "type":"Retail Goods"
        }
    ],
    "sg:phone":"+1 540 972 7874",
    "sg:postcode":"22553",
    "sg:province":"VA",
    "sg:tags":[
        "installation"
    ],
    "wof:name":"Tim Redman",
    "wof:placetype":"venue"
},
  "geometry": {"coordinates":[-77.65089399999999,38.238739],"type":"Point"}
}