{
  "type": "Feature",
  "properties": {
    "addr:full":"1941 Rosser Ave Waynesboro VA 22980",
    "addr:housenumber":"1941",
    "addr:postcode":"22980",
    "addr:street":"Rosser Ave",
    "iso:country":"US",
    "sg:address":"1941 Rosser Ave",
    "sg:city":"Waynesboro",
    "sg:classifiers":[
        {
            "category":"Restaurant",
            "type":"Food & Drink"
        }
    ],
    "sg:menulink":"http://www.allmenus.com/va/waynesboro/104061-ruby-tuesdays/menu/",
    "sg:phone":"+1 540 943 1610",
    "sg:postcode":"22980",
    "sg:province":"VA",
    "sg:tags":[
        "burger",
        "american"
    ],
    "wof:name":"Ruby Tuesdays",
    "wof:placetype":"venue"
},
  "geometry": {"coordinates":[-78.933273,38.06504],"type":"Point"}
}