{
  "type": "Feature",
  "properties": {
    "addr:full":"25 Tillerson Dr Newport News VA 23602",
    "addr:housenumber":"25",
    "addr:postcode":"23602",
    "addr:street":"Tillerson Dr",
    "iso:country":"US",
    "sg:address":"25 Tillerson Dr",
    "sg:city":"Newport News",
    "sg:classifiers":[
        {
            "category":"Building & Trades",
            "subcategory":"Construction",
            "type":"Services"
        }
    ],
    "sg:phone":"+1 757 872 0770",
    "sg:postcode":"23602",
    "sg:province":"VA",
    "sg:tags":[
        "hanging",
        "contractor"
    ],
    "wof:name":"North American Painting",
    "wof:placetype":"venue"
},
  "geometry": {"coordinates":[-76.525069,37.128119],"type":"Point"}
}