{
  "type": "Feature",
  "properties": {
    "iso:country":"US",
    "sg:address":"101 E Davis St",
    "sg:city":"Culpeper",
    "sg:classifiers":[
        {
            "category":"Restaurant",
            "type":"Food & Drink"
        }
    ],
    "sg:phone":"+1 540 829 0344",
    "sg:postcode":"22701",
    "sg:province":"VA",
    "wof:name":"Frost Cafe",
    "wof:placetype":"venue"
},
  "geometry": {"coordinates":[-77.996127,38.473327],"type":"Point"}
}