{
  "type": "Feature",
  "properties": {
    "iso:country":"US",
    "sg:address":"4238 Wilson Blvd",
    "sg:city":"Arlington",
    "sg:classifiers":[
        {
            "category":"Manufacturing",
            "subcategory":"Toys & Sporting Goods",
            "type":"Manufacturing & Wholesale Goods"
        },
        {
            "category":"Shopping",
            "subcategory":"Hobbies, Toys, & Games",
            "type":"Retail Goods"
        }
    ],
    "sg:phone":"+1 703 875 8999",
    "sg:postcode":"22203",
    "sg:province":"VA",
    "sg:tags":[
        "toys-wholesale",
        "manufacturer",
        "store",
        "supply"
    ],
    "wof:name":"Curious Kids",
    "wof:placetype":"venue"
},
  "geometry": {"coordinates":[-77.111524,38.87986],"type":"Point"}
}