{
  "type": "Feature",
  "properties": {
    "addr:full":"218 Franklin St Petersburg VA 23803",
    "addr:housenumber":"218",
    "addr:postcode":"23803",
    "addr:street":"Franklin",
    "iso:country":"US",
    "sg:address":"218 Franklin St",
    "sg:city":"Petersburg",
    "sg:classifiers":[
        {
            "category":"Health Services",
            "subcategory":"Nursing And Care Facility",
            "type":"Services"
        },
        {
            "category":"Social Services",
            "subcategory":"Adult Care",
            "type":"Services"
        }
    ],
    "sg:phone":"+1 804 861 1287",
    "sg:postcode":"23803",
    "sg:province":"VA",
    "sg:tags":[
        "home",
        "living",
        "assisted",
        "rest",
        "elder"
    ],
    "wof:name":"Stanback Home For Adults Inc",
    "wof:placetype":"venue"
},
  "geometry": {"coordinates":[-77.399727,37.22916],"type":"Point"}
}