{
  "type": "Feature",
  "properties": {
    "addr:full":"7404 Gallerher Rd Gainesville VA 20155",
    "addr:housenumber":"7404",
    "addr:postcode":"20155",
    "addr:street":"Gallerher Rd",
    "iso:country":"US",
    "sg:address":"7404 Gallerher Rd",
    "sg:city":"Gainesville",
    "sg:classifiers":[
        {
            "category":"Health Services",
            "subcategory":"Clinic",
            "type":"Services"
        }
    ],
    "sg:phone":"+1 703 909 8963",
    "sg:postcode":"20155",
    "sg:province":"VA",
    "sg:tags":[
        "counseling",
        "mental"
    ],
    "sg:website":"www.phoenixfamilycounseling.com",
    "wof:name":"Phoenix Family Counseling & Play Therapy Center, PLLC",
    "wof:placetype":"venue"
},
  "geometry": {"coordinates":[-77.613507,38.797108],"type":"Point"}
}