{
  "type": "Feature",
  "properties": {
    "addr:full":"2028 E Lee Hwy Wytheville VA 24382",
    "addr:housenumber":"2028",
    "addr:postcode":"24382",
    "addr:street":"E Lee Hwy",
    "iso:country":"US",
    "sg:address":"2028 E Lee Hwy",
    "sg:city":"Wytheville",
    "sg:classifiers":[
        {
            "category":"Shopping",
            "subcategory":"Bicycles & Sporting Goods",
            "type":"Retail Goods"
        },
        {
            "category":"Shopping",
            "subcategory":"Clothing, Apparel, & Fashions",
            "type":"Retail Goods"
        }
    ],
    "sg:phone":"+1 276 223 1118",
    "sg:postcode":"24382",
    "sg:province":"VA",
    "sg:tags":[
        "tack",
        "western"
    ],
    "wof:name":"Old Fort Western Store",
    "wof:placetype":"venue"
},
  "geometry": {"coordinates":[-80.971092,36.942283],"type":"Point"}
}