{
  "type": "Feature",
  "properties": {
    "addr:full":"2348 Eastover Dr South Boston VA 24592",
    "addr:housenumber":"2348",
    "addr:postcode":"24592",
    "addr:street":"Eastover Dr",
    "iso:country":"US",
    "sg:address":"2348 Eastover Dr",
    "sg:city":"South Boston",
    "sg:classifiers":[
        {
            "category":"Manufacturing",
            "subcategory":"Tools & Machinery",
            "type":"Manufacturing & Wholesale Goods"
        }
    ],
    "sg:phone":"+1 434 575 7200",
    "sg:postcode":"24592",
    "sg:province":"VA",
    "sg:tags":[
        "equipment",
        "fertilizing"
    ],
    "wof:name":"Arctech Inc",
    "wof:placetype":"venue"
},
  "geometry": {"coordinates":[-78.875602,36.703297],"type":"Point"}
}