{
  "type": "Feature",
  "properties": {
    "iso:country":"US",
    "sg:address":"3390 Harborwood Rd",
    "sg:city":"Salem",
    "sg:classifiers":[
        {
            "category":"Insurance",
            "subcategory":"Insurance Agent",
            "type":"Services"
        }
    ],
    "sg:phone":"+1 540 389 9055",
    "sg:postcode":"24153",
    "sg:province":"VA",
    "wof:name":"RSW & Assoc",
    "wof:placetype":"venue"
},
  "geometry": {"coordinates":[-80.105762,37.253504],"type":"Point"}
}