{
  "type": "Feature",
  "properties": {
    "addr:full":"258 Nor Dan Dr Danville VA 24540",
    "addr:housenumber":"258",
    "addr:postcode":"24540",
    "addr:street":"Dan Dr",
    "iso:country":"US",
    "sg:address":"258 Nor Dan Dr",
    "sg:city":"Danville",
    "sg:classifiers":[
        {
            "category":"Restaurant",
            "type":"Food & Drink"
        }
    ],
    "sg:menulink":"http://www.allmenus.com/va/danville/80450-dominos-pizza/menu/",
    "sg:phone":"+1 434 836 9503",
    "sg:postcode":"24540",
    "sg:province":"VA",
    "sg:tags":[
        "american",
        "wing",
        "pizza"
    ],
    "wof:name":"Domino's Pizza",
    "wof:placetype":"venue"
},
  "geometry": {"coordinates":[-79.398081,36.627703],"type":"Point"}
}