{
  "type": "Feature",
  "properties": {
    "addr:full":"509 Hunt Way Ln Herndon VA 20170",
    "addr:housenumber":"509",
    "addr:postcode":"20170",
    "addr:street":"Hunt Way Ln",
    "iso:country":"US",
    "sg:address":"509 Hunt Way Ln",
    "sg:city":"Herndon",
    "sg:classifiers":[
        {
            "category":"Professional",
            "subcategory":"Engineering",
            "type":"Services"
        }
    ],
    "sg:phone":"+1 703 481 1700",
    "sg:postcode":"20170",
    "sg:province":"VA",
    "sg:tags":[
        "engineer"
    ],
    "wof:name":"Gac Corp",
    "wof:placetype":"venue"
},
  "geometry": {"coordinates":[-77.385288,38.957208],"type":"Point"}
}