{
  "type": "Feature",
  "properties": {
    "addr:full":"305 Campbell Ave SW Roanoke VA 24016",
    "addr:housenumber":"305",
    "addr:postcode":"24016",
    "addr:street":"Campbell Ave Sw",
    "iso:country":"US",
    "sg:address":"305 Campbell Ave SW",
    "sg:city":"Roanoke",
    "sg:classifiers":[
        {
            "category":"Professional",
            "type":"Services"
        },
        {
            "category":"Professional",
            "subcategory":"Management & Consulting",
            "type":"Services"
        }
    ],
    "sg:phone":"+1 540 342 0616",
    "sg:postcode":"24016",
    "sg:province":"VA",
    "sg:tags":[
        "establishment",
        "business"
    ],
    "wof:name":"Eastern Assignment Corporation",
    "wof:placetype":"venue"
},
  "geometry": {"coordinates":[-79.948504,37.271449],"type":"Point"}
}