{
  "type": "Feature",
  "properties": {
    "addr:full":"500 Piney Rd Danville VA 24531",
    "addr:housenumber":"500",
    "addr:postcode":"24531",
    "addr:street":"Piney Rd",
    "iso:country":"US",
    "sg:address":"500 Piney Rd",
    "sg:city":"Danville",
    "sg:classifiers":[
        {
            "category":"Health Services",
            "subcategory":"Doctor",
            "type":"Services"
        }
    ],
    "sg:phone":"+1 434 799 3466",
    "sg:postcode":"24531",
    "sg:province":"VA",
    "sg:tags":[
        "medical"
    ],
    "wof:name":"Piedmont Pain Medicine PC",
    "wof:placetype":"venue"
},
  "geometry": {"coordinates":[-79.45304899999999,36.916309],"type":"Point"}
}