{
  "type": "Feature",
  "properties": {
    "addr:full":"4141 Valley Pike Winchester VA 22602",
    "addr:housenumber":"4141",
    "addr:postcode":"22602",
    "addr:street":"Valley Pike",
    "iso:country":"US",
    "sg:address":"4141 Valley Pike",
    "sg:city":"Winchester",
    "sg:classifiers":[
        {
            "category":"Retail",
            "subcategory":"Auto Repair",
            "type":"Services"
        }
    ],
    "sg:phone":"+1 540 869 3622",
    "sg:postcode":"22602",
    "sg:province":"VA",
    "sg:tags":[
        "repairing",
        "automobile"
    ],
    "wof:name":"Snappy Lube Plus",
    "wof:placetype":"venue"
},
  "geometry": {"coordinates":[-78.201914,39.113059],"type":"Point"}
}