{
  "type": "Feature",
  "properties": {
    "addr:full":"134 Evergreen Dr Lancaster VA 22503",
    "addr:housenumber":"134",
    "addr:postcode":"22503",
    "addr:street":"Evergreen Dr",
    "iso:country":"US",
    "sg:address":"134 Evergreen Dr",
    "sg:city":"Lancaster",
    "sg:classifiers":[
        {
            "category":"Professional",
            "subcategory":"Accounting & Tax Preparation",
            "type":"Services"
        }
    ],
    "sg:phone":"+1 804 462 5752",
    "sg:postcode":"22503",
    "sg:province":"VA",
    "sg:tags":[
        "return",
        "filing"
    ],
    "wof:name":"Chris Naumann Accounting-Taxes",
    "wof:placetype":"venue"
},
  "geometry": {"coordinates":[-76.52355799999999,37.738443],"type":"Point"}
}