{
  "type": "Feature",
  "properties": {
    "iso:country":"US",
    "sg:address":"10113 Tate Ct",
    "sg:city":"Oakton",
    "sg:classifiers":[
        {
            "category":"Professional",
            "subcategory":"Computer Services",
            "type":"Services"
        }
    ],
    "sg:phone":"+1 703 938 5025",
    "sg:postcode":"22124",
    "sg:province":"VA",
    "sg:tags":[
        "development",
        "software"
    ],
    "wof:name":"Systems Architects Inc",
    "wof:placetype":"venue"
},
  "geometry": {"coordinates":[-77.293722,38.878507],"type":"Point"}
}