{
  "type": "Feature",
  "properties": {
    "iso:country":"US",
    "sg:address":"13502 Stoney Creek Ct",
    "sg:city":"Chester",
    "sg:classifiers":[
        {
            "category":"Building & Trades",
            "subcategory":"Plumbing",
            "type":"Services"
        }
    ],
    "sg:phone":"+1 804 748 3676",
    "sg:postcode":"23831",
    "sg:province":"VA",
    "sg:tags":[
        "air",
        "heating",
        "conditioning",
        "contractor"
    ],
    "wof:name":"Covington Mechanical Service",
    "wof:placetype":"venue"
},
  "geometry": {"coordinates":[-77.442475,37.328722],"type":"Point"}
}