{
  "type": "Feature",
  "properties": {
    "iso:country":"US",
    "sg:address":"6249 Jefferson Davis Hwy",
    "sg:city":"Richmond",
    "sg:classifiers":[
        {
            "category":"Food & Beverages",
            "subcategory":"Groceries & Convenience Stores",
            "type":"Retail Goods"
        }
    ],
    "sg:phone":"+1 804 275 8247",
    "sg:postcode":"23234",
    "sg:province":"VA",
    "wof:name":"Fast & Friendly",
    "wof:placetype":"venue"
},
  "geometry": {"coordinates":[-77.4393,37.439028],"type":"Point"}
}