{
  "type": "Feature",
  "properties": {
    "addr:full":"1503 King St Alexandria VA 22314",
    "addr:housenumber":"1503",
    "addr:postcode":"22314",
    "addr:street":"King St",
    "iso:country":"US",
    "sg:address":"1503 King St",
    "sg:city":"Alexandria",
    "sg:classifiers":[
        {
            "category":"Building & Trades",
            "subcategory":"Construction",
            "type":"Services"
        }
    ],
    "sg:phone":"+1 703 549 1545",
    "sg:postcode":"22314",
    "sg:province":"VA",
    "sg:tags":[
        "general",
        "dwelling",
        "contractor"
    ],
    "wof:name":"Pollard Construction Company",
    "wof:placetype":"venue"
},
  "geometry": {"coordinates":[-77.057261,38.806454],"type":"Point"}
}