{
  "type": "Feature",
  "properties": {
    "iso:country":"US",
    "sg:address":"837 Old Airport Rd",
    "sg:city":"Chilhowie",
    "sg:classifiers":[
        {
            "category":"Autos & Motor Vehicles",
            "subcategory":"Automobile Sales",
            "type":"Retail Goods"
        }
    ],
    "sg:phone":"+1 276 646 2654",
    "sg:postcode":"24319",
    "sg:province":"VA",
    "sg:tags":[
        "car",
        "dealer"
    ],
    "wof:name":"St Clair Motors",
    "wof:placetype":"venue"
},
  "geometry": {"coordinates":[-81.64725199999999,36.757291],"type":"Point"}
}