{
  "type": "Feature",
  "properties": {
    "addr:full":"4019 Cool Brooke Way Alexandria VA 22306",
    "addr:housenumber":"4019",
    "addr:postcode":"22306",
    "addr:street":"Cool Brooke Way",
    "iso:country":"US",
    "sg:address":"4019 Cool Brooke Way",
    "sg:city":"Alexandria",
    "sg:classifiers":[
        {
            "category":"Social Services",
            "subcategory":"Child Care",
            "type":"Services"
        }
    ],
    "sg:phone":"+1 703 768 1949",
    "sg:postcode":"22306",
    "sg:province":"VA",
    "sg:tags":[
        "day"
    ],
    "wof:name":"Sheree H Watt",
    "wof:placetype":"venue"
},
  "geometry": {"coordinates":[-77.102418,38.766079],"type":"Point"}
}