{
  "type": "Feature",
  "properties": {
    "addr:full":"9315 Briarwood Pl Fairfax VA 22032",
    "addr:housenumber":"9315",
    "addr:postcode":"22032",
    "addr:street":"Briarwood Pl",
    "iso:country":"US",
    "sg:address":"9315 Briarwood Pl",
    "sg:city":"Fairfax",
    "sg:classifiers":[
        {
            "category":"Government",
            "subcategory":"Police Station",
            "type":"Public Place"
        }
    ],
    "sg:phone":"+1 703 978 1691",
    "sg:postcode":"22032",
    "sg:province":"VA",
    "sg:tags":[
        "investigation"
    ],
    "wof:name":"FBI",
    "wof:placetype":"venue"
},
  "geometry": {"coordinates":[-77.26698399999999,38.821582],"type":"Point"}
}