{
  "type": "Feature",
  "properties": {
    "addr:full":"2004 Dock Landing Rd Chesapeake VA 23321",
    "addr:housenumber":"2004",
    "addr:postcode":"23321",
    "addr:street":"Dock Landing Rd",
    "iso:country":"US",
    "sg:address":"2004 Dock Landing Rd",
    "sg:city":"Chesapeake",
    "sg:classifiers":[
        {
            "category":"Social Services",
            "subcategory":"Child Care",
            "type":"Services"
        }
    ],
    "sg:phone":"+1 757 465 2662",
    "sg:postcode":"23321",
    "sg:province":"VA",
    "wof:name":"After School Care",
    "wof:placetype":"venue"
},
  "geometry": {"coordinates":[-76.408135,36.813852],"type":"Point"}
}