{
  "type": "Feature",
  "properties": {
    "addr:full":"4415 Carrollton Pike Woodlawn VA 24381",
    "addr:housenumber":"4415",
    "addr:postcode":"24381",
    "addr:street":"Carrollton Pike",
    "iso:country":"US",
    "sg:address":"4415 Carrollton Pike",
    "sg:city":"Woodlawn",
    "sg:classifiers":[
        {
            "category":"Home & Garden",
            "subcategory":"Carpets & Floor Coverings",
            "type":"Retail Goods"
        }
    ],
    "sg:phone":"+1 276 236 5981",
    "sg:postcode":"24381",
    "sg:province":"VA",
    "sg:tags":[
        "material",
        "rug"
    ],
    "wof:name":"Hawks Carpet Outlet",
    "wof:placetype":"venue"
},
  "geometry": {"coordinates":[-80.813287,36.725751],"type":"Point"}
}