{
  "type": "Feature",
  "properties": {
    "addr:full":"612 Longfellow Dr NE Leesburg VA 20176",
    "addr:housenumber":"612",
    "addr:postcode":"20176",
    "addr:street":"Longfellow Dr Ne",
    "iso:country":"US",
    "sg:address":"612 Longfellow Dr NE",
    "sg:city":"Leesburg",
    "sg:classifiers":[
        {
            "category":"Retail",
            "subcategory":"Auto Rental",
            "type":"Services"
        }
    ],
    "sg:phone":"+1 703 669 4074",
    "sg:postcode":"20176",
    "sg:province":"VA",
    "sg:tags":[
        "renting",
        "automobile"
    ],
    "wof:name":"Avis America",
    "wof:placetype":"venue"
},
  "geometry": {"coordinates":[-77.549941,39.128109],"type":"Point"}
}