{
  "type": "Feature",
  "properties": {
    "iso:country":"US",
    "sg:address":"3500 Pemberton Rd",
    "sg:city":"Richmond",
    "sg:classifiers":[
        {
            "category":"Social Services",
            "subcategory":"Child Care",
            "type":"Services"
        }
    ],
    "sg:phone":"+1 804 290 0000",
    "sg:postcode":"23233",
    "sg:province":"VA",
    "sg:tags":[
        "repair",
        "day"
    ],
    "wof:name":"Day & Night Locksmith",
    "wof:placetype":"venue"
},
  "geometry": {"coordinates":[-77.560689,37.640667],"type":"Point"}
}