{
  "type": "Feature",
  "properties": {
    "addr:full":"6844 General Lafayette Way Gainesville VA 20155",
    "addr:housenumber":"6844",
    "addr:postcode":"20155",
    "addr:street":"General Lafayette Way",
    "iso:country":"US",
    "sg:address":"6844 General Lafayette Way",
    "sg:city":"Gainesville",
    "sg:classifiers":[
        {
            "category":"Professional",
            "subcategory":"Management & Consulting",
            "type":"Services"
        }
    ],
    "sg:phone":"+1 703 753 4100",
    "sg:postcode":"20155",
    "sg:province":"VA",
    "sg:tags":[
        "consultant",
        "solution"
    ],
    "wof:name":"Highviz Consulting Group",
    "wof:placetype":"venue"
},
  "geometry": {"coordinates":[-77.61342,38.809114],"type":"Point"}
}