{
  "type": "Feature",
  "properties": {
    "addr:full":"1215 Volvo Pkwy Chesapeake VA 23320",
    "addr:housenumber":"1215",
    "addr:postcode":"23320",
    "addr:street":"Volvo Pkwy",
    "iso:country":"US",
    "sg:address":"1215 Volvo Pkwy",
    "sg:city":"Chesapeake",
    "sg:classifiers":[
        {
            "category":"Banks & Credit Unions",
            "subcategory":"Investment Brokerage",
            "type":"Services"
        }
    ],
    "sg:phone":"+1 757 382 4160",
    "sg:postcode":"23320",
    "sg:province":"VA",
    "sg:tags":[
        "security"
    ],
    "wof:name":"Merrill Lynch",
    "wof:placetype":"venue"
},
  "geometry": {"coordinates":[-76.218473,36.768676],"type":"Point"}
}