{
  "type": "Feature",
  "properties": {
    "iso:country":"US",
    "sg:address":"1267 Pryor Ridge Trl",
    "sg:city":"Lynchburg",
    "sg:classifiers":[
        {
            "category":"Professional",
            "subcategory":"Business Services",
            "type":"Services"
        }
    ],
    "sg:phone":"+1 434 384 3847",
    "sg:postcode":"24503",
    "sg:province":"VA",
    "wof:name":"Mary Booth",
    "wof:placetype":"venue"
},
  "geometry": {"coordinates":[-79.276123,37.467648],"type":"Point"}
}