{
  "type": "Feature",
  "properties": {
    "addr:full":"11117 Stainsby Ct Bristow VA 20136",
    "addr:postcode":"11117;20136",
    "addr:street":"Stainsby Ct",
    "iso:country":"US",
    "sg:address":"11117 Stainsby Ct",
    "sg:city":"Bristow",
    "sg:classifiers":[
        {
            "category":"Professional",
            "subcategory":"Management & Consulting",
            "type":"Services"
        }
    ],
    "sg:phone":"+1 703 392 4614",
    "sg:postcode":"20136",
    "sg:province":"VA",
    "sg:tags":[
        "accounting",
        "finance"
    ],
    "wof:name":"Liberty Tax Service",
    "wof:placetype":"venue"
},
  "geometry": {"coordinates":[-77.528688,38.707512],"type":"Point"}
}