{
  "type": "Feature",
  "properties": {
    "iso:country":"US",
    "sg:address":"22 Von Steuben Dr",
    "sg:city":"Newport News",
    "sg:classifiers":[
        {
            "category":"Building & Trades",
            "subcategory":"Construction",
            "type":"Services"
        }
    ],
    "sg:phone":"+1 757 887 5664",
    "sg:postcode":"23603",
    "sg:province":"VA",
    "sg:tags":[
        "maintenance",
        "contractor"
    ],
    "sg:website":"www.kira.com",
    "wof:name":"Kira Inc",
    "wof:placetype":"venue"
},
  "geometry": {"coordinates":[-76.57155,37.215551],"type":"Point"}
}