{
  "type": "Feature",
  "properties": {
    "iso:country":"US",
    "sg:address":"106 W South St",
    "sg:city":"Charlottesville",
    "sg:classifiers":[
        {
            "category":"Banks & Credit Unions",
            "subcategory":"Financial Services",
            "type":"Services"
        }
    ],
    "sg:phone":"+1 434 817 8688",
    "sg:postcode":"22902",
    "sg:province":"VA",
    "sg:tags":[
        "broker",
        "mortgage"
    ],
    "wof:name":"1st Nations Mortgage Corp",
    "wof:placetype":"venue"
},
  "geometry": {"coordinates":[-78.482268,38.029223],"type":"Point"}
}