{
  "type": "Feature",
  "properties": {
    "addr:full":"13016 Bristersburg Rd Midland VA 22728",
    "addr:housenumber":"13016",
    "addr:postcode":"22728",
    "addr:street":"Bristersburg Rd",
    "iso:country":"US",
    "sg:address":"13016 Bristersburg Rd",
    "sg:city":"Midland",
    "sg:classifiers":[
        {
            "category":"Professional",
            "type":"Services"
        }
    ],
    "sg:phone":"+1 540 752 1600",
    "sg:postcode":"22728",
    "sg:province":"VA",
    "wof:name":"V Sealock Inc",
    "wof:placetype":"venue"
},
  "geometry": {"coordinates":[-77.60199799999999,38.497594],"type":"Point"}
}