{
  "type": "Feature",
  "properties": {
    "addr:full":"782 Shopping Center Rd Strasburg VA 22657",
    "addr:postcode":"22657",
    "addr:street":"Shopping Center Rd",
    "iso:country":"US",
    "sg:address":"782 Shopping Center Rd",
    "sg:city":"Strasburg",
    "sg:classifiers":[
        {
            "category":"Restaurant",
            "type":"Food & Drink"
        }
    ],
    "sg:phone":"+1 540 465 8336",
    "sg:postcode":"22657",
    "sg:province":"VA",
    "sg:tags":[
        "eating"
    ],
    "wof:name":"Great Wall Restaurant",
    "wof:placetype":"venue"
},
  "geometry": {"coordinates":[-78.349915,38.997703],"type":"Point"}
}