{
  "type": "Feature",
  "properties": {
    "addr:full":"773 Swift Run Rd Ruckersville VA 22968",
    "addr:housenumber":"773",
    "addr:postcode":"22968",
    "addr:street":"Swift Run Rd",
    "iso:country":"US",
    "sg:address":"773 Swift Run Rd",
    "sg:city":"Ruckersville",
    "sg:classifiers":[
        {
            "category":"Building & Trades",
            "subcategory":"Equipment Rental",
            "type":"Services"
        }
    ],
    "sg:phone":"+1 434 985 2929",
    "sg:postcode":"22968",
    "sg:province":"VA",
    "wof:name":"Make Co",
    "wof:placetype":"venue"
},
  "geometry": {"coordinates":[-78.440837,38.261768],"type":"Point"}
}