{
  "type": "Feature",
  "properties": {
    "iso:country":"US",
    "sg:address":"4345 High Ridge Rd",
    "sg:city":"Haymarket",
    "sg:classifiers":[
        {
            "category":"Professional",
            "subcategory":"Computer Services",
            "type":"Services"
        }
    ],
    "sg:phone":"+1 703 754 0115",
    "sg:postcode":"20169",
    "sg:province":"VA",
    "sg:tags":[
        "consulting",
        "management"
    ],
    "wof:name":"Dressage Expressions",
    "wof:placetype":"venue"
},
  "geometry": {"coordinates":[-77.624988,38.864517],"type":"Point"}
}