{
  "type": "Feature",
  "properties": {
    "addr:full":"2225 Rose Hall Dr Virginia Beach VA 23454",
    "addr:housenumber":"2225",
    "addr:postcode":"23454",
    "addr:street":"Rose Hall Dr",
    "iso:country":"US",
    "sg:address":"2225 Rose Hall Dr",
    "sg:city":"Virginia Beach",
    "sg:classifiers":[
        {
            "category":"Social Services",
            "subcategory":"Child Care",
            "type":"Services"
        }
    ],
    "sg:phone":"+1 757 481 9217",
    "sg:postcode":"23454",
    "sg:province":"VA",
    "sg:tags":[
        "kindergarten",
        "academic",
        "school",
        "day"
    ],
    "wof:name":"Great Neck Pre-School",
    "wof:placetype":"venue"
},
  "geometry": {"coordinates":[-76.04468900000001,36.866302],"type":"Point"}
}