{
  "type": "Feature",
  "properties": {
    "addr:full":"41970 Saddlebrook Pl Leesburg VA 20176",
    "addr:housenumber":"41970",
    "addr:postcode":"20176",
    "addr:street":"Saddlebrook Pl",
    "iso:country":"US",
    "sg:address":"41970 Saddlebrook Pl",
    "sg:city":"Leesburg",
    "sg:classifiers":[
        {
            "category":"Real Estate",
            "subcategory":"Real Estate Operator",
            "type":"Services"
        }
    ],
    "sg:phone":"+1 703 777 7536",
    "sg:postcode":"20176",
    "sg:province":"VA",
    "sg:tags":[
        "building",
        "nonresidential"
    ],
    "wof:name":"Pamaro Properties LLC",
    "wof:placetype":"venue"
},
  "geometry": {"coordinates":[-77.548136,39.148106],"type":"Point"}
}