{
  "type": "Feature",
  "properties": {
    "addr:full":"1221 Mottrom Dr Mc Lean VA 22101",
    "addr:housenumber":"1221",
    "addr:postcode":"22101",
    "addr:street":"Mottrom Dr",
    "iso:country":"US",
    "sg:address":"1221 Mottrom Dr",
    "sg:city":"Mc Lean",
    "sg:classifiers":[
        {
            "category":"Organizations",
            "subcategory":"Non-profit Organization",
            "type":"Services"
        },
        {
            "category":"Cinema",
            "subcategory":"Movie Theater",
            "type":"Entertainment"
        }
    ],
    "sg:phone":"+1 703 848 2632",
    "sg:postcode":"22101",
    "sg:province":"VA",
    "sg:tags":[
        "motion",
        "theatrical",
        "picture"
    ],
    "sg:website":"www.interacttheatre.com",
    "wof:name":"Interact Theater Co",
    "wof:placetype":"venue"
},
  "geometry": {"coordinates":[-77.198494,38.941162],"type":"Point"}
}