{
  "type": "Feature",
  "properties": {
    "iso:country":"US",
    "sg:address":"917 W Grace St",
    "sg:city":"Richmond",
    "sg:classifiers":[
        {
            "category":"Restaurant",
            "type":"Food & Drink"
        }
    ],
    "sg:phone":"+1 804 355 7364",
    "sg:postcode":"23220",
    "sg:province":"VA",
    "sg:website":"www.tbrinsurance.com",
    "wof:name":"Tabb Brockenbaugh & Ragland",
    "wof:placetype":"venue"
},
  "geometry": {"coordinates":[-77.452943,37.550761],"type":"Point"}
}