{
  "type": "Feature",
  "properties": {
    "addr:full":"4211 Mechanicsville Tpke Mechanicsville VA 23111",
    "addr:housenumber":"4211",
    "addr:postcode":"23111",
    "addr:street":"Mechanicsville Tpke",
    "iso:country":"US",
    "sg:address":"4211 Mechanicsville Tpke",
    "sg:city":"Mechanicsville",
    "sg:classifiers":[
        {
            "category":"Retail",
            "subcategory":"Animal Services",
            "type":"Services"
        }
    ],
    "sg:phone":"+1 804 779 2903",
    "sg:postcode":"23111",
    "sg:province":"VA",
    "wof:name":"Critter Care Boarding Kennel",
    "wof:placetype":"venue"
},
  "geometry": {"coordinates":[-77.24594999999999,37.646594],"type":"Point"}
}