{
  "type": "Feature",
  "properties": {
    "addr:full":"9606 Treemont Ln Spotsylvania VA 22553",
    "addr:housenumber":"9606",
    "addr:postcode":"22553",
    "addr:street":"Treemont Ln",
    "iso:country":"US",
    "sg:address":"9606 Treemont Ln",
    "sg:city":"Spotsylvania",
    "sg:classifiers":[
        {
            "category":"Professional",
            "subcategory":"Business Services",
            "type":"Services"
        }
    ],
    "sg:phone":"+1 540 582 2623",
    "sg:postcode":"22553",
    "sg:province":"VA",
    "wof:name":"Cimorelli Enterprises",
    "wof:placetype":"venue"
},
  "geometry": {"coordinates":[-77.57461000000001,38.218906],"type":"Point"}
}