{
  "type": "Feature",
  "properties": {
    "iso:country":"US",
    "sg:address":"220 E Nelson Ave",
    "sg:city":"Alexandria",
    "sg:classifiers":[
        {
            "category":"Building & Trades",
            "subcategory":"Construction",
            "type":"Services"
        }
    ],
    "sg:phone":"+1 703 283 8412",
    "sg:postcode":"22301",
    "sg:province":"VA",
    "sg:tags":[
        "house"
    ],
    "wof:name":"G I Kubela",
    "wof:placetype":"venue"
},
  "geometry": {"coordinates":[-77.057682,38.81967],"type":"Point"}
}