{
  "type": "Feature",
  "properties": {
    "addr:full":"3209 Blossom Dr Mt Crawford VA 22841",
    "addr:housenumber":"3209",
    "addr:postcode":"22841",
    "addr:street":"Blossom Dr Mt",
    "iso:country":"US",
    "sg:address":"3209 Blossom Dr",
    "sg:city":"Mt Crawford",
    "sg:classifiers":[
        {
            "category":"Retail",
            "subcategory":"Auto Repair",
            "type":"Services"
        }
    ],
    "sg:phone":"+1 540 438 8005",
    "sg:postcode":"22841",
    "sg:province":"VA",
    "sg:tags":[
        "truck",
        "general"
    ],
    "wof:name":"Service On Wheels",
    "wof:placetype":"venue"
},
  "geometry": {"coordinates":[-78.863264,38.374466],"type":"Point"}
}