{
  "type": "Feature",
  "properties": {
    "addr:full":"2116 Banister Rd Petersburg VA 23805",
    "addr:housenumber":"2116",
    "addr:postcode":"23805",
    "addr:street":"Banister Rd",
    "iso:country":"US",
    "sg:address":"2116 Banister Rd",
    "sg:city":"Petersburg",
    "sg:classifiers":[
        {
            "category":"Professional",
            "subcategory":"Business Services",
            "type":"Services"
        }
    ],
    "sg:phone":"+1 804 733 8600",
    "sg:postcode":"23805",
    "sg:province":"VA",
    "sg:tags":[
        "roofing",
        "painting",
        "flooring",
        "carpeting"
    ],
    "wof:name":"Petersburgs Homes Improvement",
    "wof:placetype":"venue"
},
  "geometry": {"coordinates":[-77.411784,37.194038],"type":"Point"}
}