{
  "type": "Feature",
  "properties": {
    "addr:full":"1125 Commerce Rd Richmond VA 23224",
    "addr:housenumber":"1125",
    "addr:postcode":"23224",
    "addr:street":"Commerce Rd",
    "iso:country":"US",
    "sg:address":"1125 Commerce Rd",
    "sg:city":"Richmond",
    "sg:classifiers":[
        {
            "category":"Manufacturing",
            "subcategory":"Retail Goods",
            "type":"Manufacturing & Wholesale Goods"
        }
    ],
    "sg:phone":"+1 804 231 7727",
    "sg:postcode":"23224",
    "sg:province":"VA",
    "sg:tags":[
        "product",
        "mfg"
    ],
    "sg:website":"www.hawkeyespas.com",
    "wof:name":"Hawkeye Manufacturing Inc",
    "wof:placetype":"venue"
},
  "geometry": {"coordinates":[-77.432486,37.51286],"type":"Point"}
}