{
  "type": "Feature",
  "properties": {
    "addr:full":"3142 Brambleton Ave Roanoke VA 24018",
    "addr:housenumber":"3142",
    "addr:postcode":"24018",
    "addr:street":"Brambleton Ave",
    "iso:country":"US",
    "sg:address":"3142 Brambleton Ave",
    "sg:city":"Roanoke",
    "sg:classifiers":[
        {
            "category":"Personal",
            "subcategory":"Beauty Salon",
            "type":"Services"
        }
    ],
    "sg:phone":"+1 540 776 8255",
    "sg:postcode":"24018",
    "sg:province":"VA",
    "sg:tags":[
        "shop"
    ],
    "wof:name":"Classic Image",
    "wof:placetype":"venue"
},
  "geometry": {"coordinates":[-79.99527,37.240462],"type":"Point"}
}