{
  "type": "Feature",
  "properties": {
    "iso:country":"US",
    "sg:address":"4423 S Ox Rd",
    "sg:city":"Edinburg",
    "sg:classifiers":[
        {
            "category":"Farming",
            "subcategory":"Livestock Farm",
            "type":"Manufacturing & Wholesale Goods"
        }
    ],
    "sg:phone":"+1 540 459 3456",
    "sg:postcode":"22824",
    "sg:province":"VA",
    "sg:tags":[
        "beef",
        "feedlot",
        "cattle"
    ],
    "wof:name":"Frenchfield Farms",
    "wof:placetype":"venue"
},
  "geometry": {"coordinates":[-78.555571,38.847094],"type":"Point"}
}