{
  "type": "Feature",
  "properties": {
    "addr:full":"11179 Hopson Rd Ashland VA 23005",
    "addr:housenumber":"11179",
    "addr:postcode":"23005",
    "addr:street":"Hopson Rd",
    "iso:country":"US",
    "sg:address":"11179 Hopson Rd",
    "sg:city":"Ashland",
    "sg:classifiers":[
        {
            "category":"Wholesale",
            "subcategory":"Office Equipment",
            "type":"Manufacturing & Wholesale Goods"
        }
    ],
    "sg:phone":"+1 804 752 6154",
    "sg:postcode":"23005",
    "sg:province":"VA",
    "sg:tags":[
        "machine",
        "duplicating",
        "supply"
    ],
    "wof:name":"Southern Copiers Sales & Svc",
    "wof:placetype":"venue"
},
  "geometry": {"coordinates":[-77.441309,37.710361],"type":"Point"}
}