{
  "type": "Feature",
  "properties": {
    "addr:full":"815 Park Ave NE Norton VA 24273",
    "addr:housenumber":"815",
    "addr:postcode":"24273",
    "addr:street":"Park Ave Ne",
    "iso:country":"US",
    "sg:address":"815 Park Ave NE",
    "sg:city":"Norton",
    "sg:classifiers":[
        {
            "category":"Local Transit",
            "type":"Transportation"
        }
    ],
    "sg:phone":"+1 276 679 7410",
    "sg:postcode":"24273",
    "sg:province":"VA",
    "sg:tags":[
        "ambulance"
    ],
    "wof:name":"First Choice Ambulance Svc",
    "wof:placetype":"venue"
},
  "geometry": {"coordinates":[-82.61642399999999,36.948771],"type":"Point"}
}