{
  "type": "Feature",
  "properties": {
    "addr:full":"106 South St E Charlottesville VA 22902",
    "addr:housenumber":"106",
    "addr:postcode":"22902",
    "addr:street":"South St E",
    "iso:country":"US",
    "sg:address":"106 South St E",
    "sg:city":"Charlottesville",
    "sg:classifiers":[
        {
            "category":"Professional",
            "type":"Services"
        }
    ],
    "sg:phone":"+1 434 972 9881",
    "sg:postcode":"22902",
    "sg:province":"VA",
    "sg:tags":[
        "establishment"
    ],
    "wof:name":"Harry Frazier Fleishman Hillrd",
    "wof:placetype":"venue"
},
  "geometry": {"coordinates":[-78.481482,38.029067],"type":"Point"}
}