{
  "type": "Feature",
  "properties": {
    "addr:full":"7627 Quail Run Ln Manassas VA 20109",
    "addr:housenumber":"7627",
    "addr:postcode":"20109",
    "addr:street":"Quail Run Ln",
    "iso:country":"US",
    "sg:address":"7627 Quail Run Ln",
    "sg:city":"Manassas",
    "sg:classifiers":[
        {
            "category":"Manufacturing",
            "subcategory":"Printing",
            "type":"Manufacturing & Wholesale Goods"
        }
    ],
    "sg:phone":"+1 703 361 4474",
    "sg:postcode":"20109",
    "sg:province":"VA",
    "sg:tags":[
        "lithographic",
        "commercial"
    ],
    "wof:name":"Inkspot Printing",
    "wof:placetype":"venue"
},
  "geometry": {"coordinates":[-77.504397,38.790267],"type":"Point"}
}