{
  "type": "Feature",
  "properties": {
    "addr:full":"267 Ellis Dr Luray VA 22835",
    "addr:housenumber":"267",
    "addr:postcode":"22835",
    "addr:street":"Ellis Dr",
    "iso:country":"US",
    "sg:address":"267 Ellis Dr",
    "sg:city":"Luray",
    "sg:classifiers":[
        {
            "category":"Organizations",
            "subcategory":"Labor Organization",
            "type":"Services"
        }
    ],
    "sg:phone":"+1 540 743 7571",
    "sg:postcode":"22835",
    "sg:province":"VA",
    "wof:name":"Wrights Plumbing Lc",
    "wof:placetype":"venue"
},
  "geometry": {"coordinates":[-78.43232500000001,38.648264],"type":"Point"}
}