{
  "type": "Feature",
  "properties": {
    "iso:country":"US",
    "sg:address":"11648 Plaza America Dr",
    "sg:city":"Reston",
    "sg:classifiers":[
        {
            "category":"Restaurant",
            "type":"Food & Drink"
        }
    ],
    "sg:menulink":"http://www.allmenus.com/va/hunter-mill/24670-rotisserie/menu/",
    "sg:phone":"+1 703 834 1100",
    "sg:postcode":"20190",
    "sg:province":"VA",
    "sg:tags":[
        "american"
    ],
    "wof:name":"Rotisserie",
    "wof:placetype":"venue"
},
  "geometry": {"coordinates":[-77.348642,38.951476],"type":"Point"}
}