{
  "type": "Feature",
  "properties": {
    "addr:full":"10111 Landrum Rd Spotsylvania VA 22553",
    "addr:housenumber":"10111",
    "addr:postcode":"22553",
    "addr:street":"Landrum Rd",
    "iso:country":"US",
    "sg:address":"10111 Landrum Rd",
    "sg:city":"Spotsylvania",
    "sg:classifiers":[
        {
            "category":"Banks & Credit Unions",
            "subcategory":"Investment Brokerage",
            "type":"Services"
        }
    ],
    "sg:phone":"+1 540 785 8113",
    "sg:postcode":"22553",
    "sg:province":"VA",
    "sg:tags":[
        "security"
    ],
    "wof:name":"Mizelle Liquidators",
    "wof:placetype":"venue"
},
  "geometry": {"coordinates":[-77.594538,38.234854],"type":"Point"}
}