{
  "type": "Feature",
  "properties": {
    "iso:country":"US",
    "sg:address":"601 S Atlantic Ave",
    "sg:city":"Virginia Beach",
    "sg:classifiers":[
        {
            "category":"Building & Trades",
            "subcategory":"Construction",
            "type":"Services"
        }
    ],
    "sg:phone":"+1 757 436 0000",
    "sg:postcode":"23451",
    "sg:province":"VA",
    "sg:tags":[
        "plate",
        "contractor",
        "work",
        "fabricated",
        "mfg"
    ],
    "wof:name":"Steca Inc",
    "wof:placetype":"venue"
},
  "geometry": {"coordinates":[-75.968891,36.82318],"type":"Point"}
}