{
  "type": "Feature",
  "properties": {
    "addr:full":"25006 Raccoon Ford Rd Culpeper VA 22701",
    "addr:postcode":"25006;22701",
    "addr:street":"Raccoon Ford Rd",
    "iso:country":"US",
    "sg:address":"25006 Raccoon Ford Rd",
    "sg:city":"Culpeper",
    "sg:classifiers":[
        {
            "category":"Building & Trades",
            "subcategory":"Construction",
            "type":"Services"
        }
    ],
    "sg:phone":"+1 540 399 1501",
    "sg:postcode":"22701",
    "sg:province":"VA",
    "sg:tags":[
        "concrete",
        "contractor"
    ],
    "wof:name":"G S D Interstate Concrete",
    "wof:placetype":"venue"
},
  "geometry": {"coordinates":[-77.93650700000001,38.36226],"type":"Point"}
}