{
  "type": "Feature",
  "properties": {
    "addr:full":"3418 Country Hill Dr Fairfax VA 22030",
    "addr:housenumber":"3418",
    "addr:postcode":"22030",
    "addr:street":"Country Hill Dr",
    "iso:country":"US",
    "sg:address":"3418 Country Hill Dr",
    "sg:city":"Fairfax",
    "sg:classifiers":[
        {
            "category":"Building & Trades",
            "subcategory":"Construction",
            "type":"Services"
        }
    ],
    "sg:phone":"+1 703 869 6678",
    "sg:postcode":"22030",
    "sg:province":"VA",
    "sg:tags":[
        "residential"
    ],
    "wof:name":"Contractors Inc",
    "wof:placetype":"venue"
},
  "geometry": {"coordinates":[-77.287401,38.857589],"type":"Point"}
}