{
  "type": "Feature",
  "properties": {
    "addr:full":"3269 Londonderry Ln Roanoke VA 24018",
    "addr:housenumber":"3269",
    "addr:postcode":"24018",
    "addr:street":"Londonderry Ln",
    "iso:country":"US",
    "sg:address":"3269 Londonderry Ln",
    "sg:city":"Roanoke",
    "sg:classifiers":[
        {
            "category":"Freight",
            "type":"Transportation"
        }
    ],
    "sg:phone":"+1 540 774 8795",
    "sg:postcode":"24018",
    "sg:province":"VA",
    "sg:tags":[
        "trucking"
    ],
    "wof:name":"Direct Express Inc",
    "wof:placetype":"venue"
},
  "geometry": {"coordinates":[-79.99205000000001,37.221061],"type":"Point"}
}