{
  "type": "Feature",
  "properties": {
    "addr:full":"3525 Carrsville Hwy Franklin VA 23851",
    "addr:housenumber":"3525",
    "addr:postcode":"23851",
    "addr:street":"Carrsville Hwy",
    "iso:country":"US",
    "sg:address":"3525 Carrsville Hwy",
    "sg:city":"Franklin",
    "sg:phone":"+1 757 562 5519",
    "sg:postcode":"23851",
    "sg:province":"VA",
    "sg:tags":[
        "farm",
        "field",
        "crop",
        "cotton"
    ],
    "wof:name":"Michael Long",
    "wof:placetype":"venue"
},
  "geometry": {"coordinates":[-76.86896299999999,36.702435],"type":"Point"}
}