{
  "type": "Feature",
  "properties": {
    "addr:full":"8913 Arley Dr Springfield VA 22153",
    "addr:housenumber":"8913",
    "addr:postcode":"22153",
    "addr:street":"Arley Dr",
    "iso:country":"US",
    "sg:address":"8913 Arley Dr",
    "sg:city":"Springfield",
    "sg:classifiers":[
        {
            "category":"Wholesale",
            "subcategory":"Office Equipment",
            "type":"Manufacturing & Wholesale Goods"
        }
    ],
    "sg:phone":"+1 703 509 1591",
    "sg:postcode":"22153",
    "sg:province":"VA",
    "wof:name":"American Business Specialist",
    "wof:placetype":"venue"
},
  "geometry": {"coordinates":[-77.254009,38.758682],"type":"Point"}
}