{
  "type": "Feature",
  "properties": {
    "addr:full":"5801 Duke St Ste E248 Alexandria VA 22304",
    "addr:housenumber":"5801",
    "addr:postcode":"22304",
    "addr:street":"Duke St Ste E248",
    "iso:country":"US",
    "sg:address":"5801 Duke St Ste E248",
    "sg:city":"Alexandria",
    "sg:classifiers":[
        {
            "category":"Shopping",
            "subcategory":"Shoes",
            "type":"Retail Goods"
        }
    ],
    "sg:phone":"+1 703 658 1391",
    "sg:postcode":"22304",
    "sg:province":"VA",
    "sg:tags":[
        "store"
    ],
    "sg:website":"www.footlocker.com",
    "wof:name":"Foot Locker",
    "wof:placetype":"venue"
},
  "geometry": {"coordinates":[-77.130957,38.815673],"type":"Point"}
}