{
  "type": "Feature",
  "properties": {
    "addr:full":"5068 George Washington Memorial Hwy Hayes VA 23072",
    "addr:housenumber":"5068",
    "addr:postcode":"23072",
    "addr:street":"George Washington Memorial Hwy",
    "iso:country":"US",
    "sg:address":"5068 George Washington Memorial Hwy",
    "sg:city":"Hayes",
    "sg:classifiers":[
        {
            "category":"Retail",
            "subcategory":"Auto Repair",
            "type":"Services"
        }
    ],
    "sg:phone":"+1 804 693 9380",
    "sg:postcode":"23072",
    "sg:province":"VA",
    "sg:tags":[
        "muffler",
        "exhaust",
        "system"
    ],
    "wof:name":"Affordable Mufflers & Auto",
    "wof:placetype":"venue"
},
  "geometry": {"coordinates":[-76.52054,37.341947],"type":"Point"}
}