{
  "type": "Feature",
  "properties": {
    "iso:country":"US",
    "sg:address":"4551 Strutfield Ln",
    "sg:city":"Alexandria",
    "sg:classifiers":[
        {
            "category":"Professional",
            "subcategory":"Business Services",
            "type":"Services"
        },
        {
            "category":"Professional",
            "subcategory":"Art Services",
            "type":"Services"
        }
    ],
    "sg:phone":"+1 703 933 2266",
    "sg:postcode":"22311",
    "sg:province":"VA",
    "sg:tags":[
        "graphic",
        "designer"
    ],
    "wof:name":"C77 Design",
    "wof:placetype":"venue"
},
  "geometry": {"coordinates":[-77.105996,38.835799],"type":"Point"}
}