{
  "type": "Feature",
  "properties": {
    "iso:country":"US",
    "sg:address":"1073 Spring Hill Rd",
    "sg:city":"McLean",
    "sg:classifiers":[
        {
            "category":"Professional",
            "subcategory":"Lawyer & Legal Services",
            "type":"Services"
        }
    ],
    "sg:phone":"+1 703 448 7446",
    "sg:postcode":"22102",
    "sg:province":"VA",
    "wof:name":"Jensen Robert N Atty",
    "wof:placetype":"venue"
},
  "geometry": {"coordinates":[-77.225926,38.951051],"type":"Point"}
}