{
  "type": "Feature",
  "properties": {
    "addr:full":"167 N Loudoun St Winchester VA 22601",
    "addr:housenumber":"167",
    "addr:postcode":"22601",
    "addr:street":"N Loudoun St",
    "iso:country":"US",
    "sg:address":"167 N Loudoun St",
    "sg:city":"Winchester",
    "sg:classifiers":[
        {
            "category":"Manufacturing",
            "subcategory":"Food",
            "type":"Manufacturing & Wholesale Goods"
        }
    ],
    "sg:phone":"+1 540 723 9719",
    "sg:postcode":"22601",
    "sg:province":"VA",
    "sg:tags":[
        "drink",
        "soft",
        "mfg"
    ],
    "wof:name":"Murphy Beverage Co",
    "wof:placetype":"venue"
},
  "geometry": {"coordinates":[-78.165657,39.184086],"type":"Point"}
}