{
  "type": "Feature",
  "properties": {
    "addr:full":"2000 14th St N Arlington VA 22201",
    "addr:housenumber":"2000",
    "addr:postcode":"22201",
    "addr:street":"14Th St N",
    "iso:country":"US",
    "sg:address":"2000 14th St N",
    "sg:city":"Arlington",
    "sg:classifiers":[
        {
            "category":"Government",
            "subcategory":"Office",
            "type":"Public Place"
        }
    ],
    "sg:phone":"+1 703 243 7404",
    "sg:postcode":"22201",
    "sg:province":"VA",
    "sg:tags":[
        "federal",
        "affairs"
    ],
    "wof:name":"Jordan Tourism Board",
    "wof:placetype":"venue"
},
  "geometry": {"coordinates":[-77.082786,38.889665],"type":"Point"}
}