{
  "type": "Feature",
  "properties": {
    "addr:full":"4120 Maplehurst Rd Virginia Beach VA 23462",
    "addr:housenumber":"4120",
    "addr:postcode":"23462",
    "addr:street":"Maplehurst Rd",
    "iso:country":"US",
    "sg:address":"4120 Maplehurst Rd",
    "sg:city":"Virginia Beach",
    "sg:classifiers":[
        {
            "category":"Professional",
            "type":"Services"
        }
    ],
    "sg:phone":"+1 757 962 9890",
    "sg:postcode":"23462",
    "sg:province":"VA",
    "wof:name":"Nine Sixteen Exec Suites LLC",
    "wof:placetype":"venue"
},
  "geometry": {"coordinates":[-76.118635,36.808947],"type":"Point"}
}