{
  "type": "Feature",
  "properties": {
    "iso:country":"US",
    "sg:address":"139 W Davis St",
    "sg:city":"Culpeper",
    "sg:classifiers":[
        {
            "category":"Building & Trades",
            "subcategory":"Construction",
            "type":"Services"
        }
    ],
    "sg:phone":"+1 540 825 8823",
    "sg:postcode":"22701",
    "sg:province":"VA",
    "sg:tags":[
        "excavating",
        "contractor"
    ],
    "wof:name":"James Samuel Construction Inc",
    "wof:placetype":"venue"
},
  "geometry": {"coordinates":[-77.99721599999999,38.473479],"type":"Point"}
}