{
  "type": "Feature",
  "properties": {
    "addr:full":"3510 Arlington Rd Cape Charles VA 23310",
    "addr:housenumber":"3510",
    "addr:postcode":"23310",
    "addr:street":"Arlington Rd",
    "iso:country":"US",
    "sg:address":"3510 Arlington Rd",
    "sg:city":"Cape Charles",
    "sg:classifiers":[
        {
            "category":"Farming",
            "subcategory":"Farm & Veterinary Services",
            "type":"Manufacturing & Wholesale Goods"
        }
    ],
    "sg:phone":"+1 757 331 3034",
    "sg:postcode":"23310",
    "sg:province":"VA",
    "sg:tags":[
        "crop"
    ],
    "wof:name":"Windys Flying Svc",
    "wof:placetype":"venue"
},
  "geometry": {"coordinates":[-75.976101,37.218835],"type":"Point"}
}