{
  "type": "Feature",
  "properties": {
    "addr:full":"1403 Archangle Ct Richmond VA 23236",
    "addr:housenumber":"1403",
    "addr:postcode":"23236",
    "addr:street":"Archangle Ct",
    "iso:country":"US",
    "sg:address":"1403 Archangle Ct",
    "sg:city":"Richmond",
    "sg:classifiers":[
        {
            "category":"Building & Trades",
            "subcategory":"Construction",
            "type":"Services"
        }
    ],
    "sg:phone":"+1 804 276 1688",
    "sg:postcode":"23236",
    "sg:province":"VA",
    "sg:tags":[
        "house"
    ],
    "wof:name":"Da Williams Construction Co",
    "wof:placetype":"venue"
},
  "geometry": {"coordinates":[-77.56416299999999,37.480467],"type":"Point"}
}