{
  "type": "Feature",
  "properties": {
    "addr:full":"5701 Charles City Cir Richmond VA 23231",
    "addr:housenumber":"5701",
    "addr:postcode":"23231",
    "addr:street":"Charles City Cir",
    "iso:country":"US",
    "sg:address":"5701 Charles City Cir",
    "sg:city":"Richmond",
    "sg:classifiers":[
        {
            "category":"Building & Trades",
            "subcategory":"Pest Control",
            "type":"Services"
        }
    ],
    "sg:phone":"+1 804 652 0888",
    "sg:postcode":"23231",
    "sg:province":"VA",
    "wof:name":"D & N Exterminating LLC",
    "wof:placetype":"venue"
},
  "geometry": {"coordinates":[-77.344903,37.502442],"type":"Point"}
}