{
  "type": "Feature",
  "properties": {
    "addr:full":"7605 Forest Ave Richmond VA 23229",
    "addr:housenumber":"7605",
    "addr:postcode":"23229",
    "addr:street":"Forest Ave",
    "iso:country":"US",
    "sg:address":"7605 Forest Ave",
    "sg:city":"Richmond",
    "sg:classifiers":[
        {
            "category":"Health Services",
            "subcategory":"Doctor",
            "type":"Services"
        }
    ],
    "sg:phone":"+1 804 288 8313",
    "sg:postcode":"23229",
    "sg:province":"VA",
    "sg:tags":[
        "physician",
        "surgeon"
    ],
    "wof:name":"Milan P Krickovic LTD",
    "wof:placetype":"venue"
},
  "geometry": {"coordinates":[-77.544349,37.603515],"type":"Point"}
}