{
  "type": "Feature",
  "properties": {
    "addr:full":"5616 Sheldon Dr Alexandria VA 22312",
    "addr:housenumber":"5616",
    "addr:postcode":"22312",
    "addr:street":"Sheldon Dr",
    "iso:country":"US",
    "sg:address":"5616 Sheldon Dr",
    "sg:city":"Alexandria",
    "sg:classifiers":[
        {
            "category":"Building & Trades",
            "subcategory":"Cleaning & Sanitation",
            "type":"Services"
        }
    ],
    "sg:phone":"+1 703 941 0305",
    "sg:postcode":"22312",
    "sg:province":"VA",
    "sg:tags":[
        "janitor"
    ],
    "wof:name":"Pro Cleaning Janitorial",
    "wof:placetype":"venue"
},
  "geometry": {"coordinates":[-77.157144,38.799859],"type":"Point"}
}