{
  "type": "Feature",
  "properties": {
    "addr:full":"4612 Sutton Oaks Dr Chantilly VA 20151",
    "addr:housenumber":"4612",
    "addr:postcode":"20151",
    "addr:street":"Sutton Oaks Dr",
    "iso:country":"US",
    "sg:address":"4612 Sutton Oaks Dr",
    "sg:city":"Chantilly",
    "sg:classifiers":[
        {
            "category":"Professional",
            "subcategory":"Business Services",
            "type":"Services"
        }
    ],
    "sg:phone":"+1 703 968 9363",
    "sg:postcode":"20151",
    "sg:province":"VA",
    "sg:tags":[
        "marketing",
        "financial"
    ],
    "wof:name":"Dorado Servicing Corp",
    "wof:placetype":"venue"
},
  "geometry": {"coordinates":[-77.42029599999999,38.868771],"type":"Point"}
}