{
  "type": "Feature",
  "properties": {
    "addr:full":"1310 N Courthouse Rd Arlington VA 22201",
    "addr:housenumber":"1310",
    "addr:postcode":"22201",
    "addr:street":"N Courthouse Rd",
    "iso:country":"US",
    "sg:address":"1310 N Courthouse Rd",
    "sg:city":"Arlington",
    "sg:classifiers":[
        {
            "category":"Shopping",
            "subcategory":"Musical Instruments",
            "type":"Retail Goods"
        }
    ],
    "sg:phone":"+1 703 247 2748",
    "sg:postcode":"22201",
    "sg:province":"VA",
    "sg:tags":[
        "guitar",
        "amplifier"
    ],
    "wof:name":"Ba Pit Team 062401",
    "wof:placetype":"venue"
},
  "geometry": {"coordinates":[-77.08350799999999,38.888351],"type":"Point"}
}