{
  "type": "Feature",
  "properties": {
    "addr:full":"10 Catoctin Cir SE Leesburg VA 20175",
    "addr:housenumber":"10",
    "addr:postcode":"20175",
    "addr:street":"Catoctin Cir Se",
    "iso:country":"US",
    "sg:address":"10 Catoctin Cir SE",
    "sg:city":"Leesburg",
    "sg:classifiers":[
        {
            "category":"Health Services",
            "subcategory":"Podiatrist",
            "type":"Services"
        }
    ],
    "sg:phone":"+1 703 777 8655",
    "sg:postcode":"20175",
    "sg:province":"VA",
    "wof:name":"Cardinal Podiatry Ctr",
    "wof:placetype":"venue"
},
  "geometry": {"coordinates":[-77.567303,39.10754],"type":"Point"}
}