{
  "type": "Feature",
  "properties": {
    "addr:full":"9922 Fairfax Sq Fairfax VA 22031",
    "addr:housenumber":"9922",
    "addr:postcode":"22031",
    "addr:street":"Fairfax Sq",
    "iso:country":"US",
    "sg:address":"9922 Fairfax Sq",
    "sg:city":"Fairfax",
    "sg:classifiers":[
        {
            "category":"Organizations",
            "subcategory":"Religious Organization",
            "type":"Services"
        }
    ],
    "sg:phone":"+1 703 591 0216",
    "sg:postcode":"22031",
    "sg:province":"VA",
    "wof:name":"Charles N Pickell Rev",
    "wof:placetype":"venue"
},
  "geometry": {"coordinates":[-77.289855,38.843523],"type":"Point"}
}