{
  "type": "Feature",
  "properties": {
    "iso:country":"US",
    "sg:address":"3131 S Crater Rd",
    "sg:city":"Petersburg",
    "sg:classifiers":[
        {
            "category":"Government",
            "subcategory":"Post Office",
            "type":"Public Place"
        }
    ],
    "sg:phone":"+1 804 733 8012",
    "sg:postcode":"23805",
    "sg:province":"VA",
    "wof:name":"Walnut Hill Classified Sta",
    "wof:placetype":"venue"
},
  "geometry": {"coordinates":[-77.370457,37.188758],"type":"Point"}
}