{
  "type": "Feature",
  "properties": {
    "addr:full":"1425 S Eads St Arlington VA 22202",
    "addr:housenumber":"1425",
    "addr:postcode":"22202",
    "addr:street":"S Eads St",
    "iso:country":"US",
    "sg:address":"1425 S Eads St",
    "sg:city":"Arlington",
    "sg:classifiers":[
        {
            "category":"Professional",
            "subcategory":"Management & Consulting",
            "type":"Services"
        }
    ],
    "sg:phone":"+1 703 486 1711",
    "sg:postcode":"22202",
    "sg:province":"VA",
    "sg:tags":[
        "consultant"
    ],
    "wof:name":"MSJ Consulting",
    "wof:placetype":"venue"
},
  "geometry": {"coordinates":[-77.054001,38.862251],"type":"Point"}
}