{
  "type": "Feature",
  "properties": {
    "iso:country":"US",
    "sg:address":"516 S Van Dorn St",
    "sg:city":"Alexandria",
    "sg:classifiers":[
        {
            "category":"Shopping",
            "subcategory":"Used Merchandise",
            "type":"Retail Goods"
        }
    ],
    "sg:phone":"+1 703 823 3800",
    "sg:postcode":"22304",
    "sg:province":"VA",
    "sg:tags":[
        "pawnbroker",
        "pawnshop"
    ],
    "wof:name":"First Cash Pawn 78",
    "wof:placetype":"venue"
},
  "geometry": {"coordinates":[-77.13331599999999,38.80691],"type":"Point"}
}