{
  "type": "Feature",
  "properties": {
    "iso:country":"US",
    "sg:address":"208 Holston Dr",
    "sg:city":"Weber City",
    "sg:classifiers":[
        {
            "category":"Government",
            "subcategory":"Office",
            "type":"Public Place"
        }
    ],
    "sg:phone":"+1 276 386 3705",
    "sg:postcode":"24290",
    "sg:province":"VA",
    "sg:tags":[
        "program",
        "administrative"
    ],
    "wof:name":"Transplant Recipients Int",
    "wof:placetype":"venue"
},
  "geometry": {"coordinates":[-82.578205,36.612007],"type":"Point"}
}