{
  "type": "Feature",
  "properties": {
    "addr:full":"459 S Lynnhaven Rd Virginia Beach VA 23452",
    "addr:housenumber":"459",
    "addr:postcode":"23452",
    "addr:street":"S Lynnhaven Rd",
    "iso:country":"US",
    "sg:address":"459 S Lynnhaven Rd",
    "sg:city":"Virginia Beach",
    "sg:classifiers":[
        {
            "category":"Retail",
            "subcategory":"Repair Shop",
            "type":"Services"
        }
    ],
    "sg:phone":"+1 757 340 0850",
    "sg:postcode":"23452",
    "sg:province":"VA",
    "sg:tags":[
        "tv",
        "television",
        "radio"
    ],
    "wof:name":"Joe Searles TV Repair Inc",
    "wof:placetype":"venue"
},
  "geometry": {"coordinates":[-76.078411,36.823554],"type":"Point"}
}