{
  "type": "Feature",
  "properties": {
    "iso:country":"US",
    "sg:address":"2916 Bus Center Dr",
    "sg:city":"Alexandria",
    "sg:classifiers":[
        {
            "category":"Wholesale",
            "subcategory":"Machinery & Supplies",
            "type":"Manufacturing & Wholesale Goods"
        }
    ],
    "sg:phone":"+1 703 461 3400",
    "sg:postcode":"22314",
    "sg:province":"VA",
    "sg:tags":[
        "equipment",
        "industrial"
    ],
    "wof:name":"Otis Elevator Company",
    "wof:placetype":"venue"
},
  "geometry": {"coordinates":[-77.081171,38.80543],"type":"Point"}
}