{
  "type": "Feature",
  "properties": {
    "iso:country":"US",
    "sg:address":"5903 Reservoir Heights Ave",
    "sg:city":"Alexandria",
    "sg:classifiers":[
        {
            "category":"Shopping",
            "type":"Retail Goods"
        }
    ],
    "sg:phone":"+1 703 820 8414",
    "sg:postcode":"22311",
    "sg:province":"VA",
    "sg:tags":[
        "chemical"
    ],
    "wof:name":"Chemical Abstracts Svc",
    "wof:placetype":"venue"
},
  "geometry": {"coordinates":[-77.134911,38.839408],"type":"Point"}
}