{
  "type": "Feature",
  "properties": {
    "addr:full":"421 Church St NE Vienna VA 22180",
    "addr:housenumber":"421",
    "addr:postcode":"22180",
    "addr:street":"Church St Ne",
    "iso:country":"US",
    "sg:address":"421 Church St NE",
    "sg:city":"Vienna",
    "sg:classifiers":[
        {
            "category":"Professional",
            "subcategory":"Management & Consulting",
            "type":"Services"
        }
    ],
    "sg:phone":"+1 703 938 0300",
    "sg:postcode":"22180",
    "sg:province":"VA",
    "sg:tags":[
        "marketing",
        "program"
    ],
    "sg:website":"www.talismanlimited.com",
    "wof:name":"Talisman Limited",
    "wof:placetype":"venue"
},
  "geometry": {"coordinates":[-77.258774,38.90873],"type":"Point"}
}