{
  "type": "Feature",
  "properties": {
    "addr:full":"1920 Dry Bread Rd Emporia VA 23847",
    "addr:housenumber":"1920",
    "addr:postcode":"23847",
    "addr:street":"Dry Bread Rd",
    "iso:country":"US",
    "sg:address":"1920 Dry Bread Rd",
    "sg:city":"Emporia",
    "sg:classifiers":[
        {
            "category":"Organizations",
            "subcategory":"Religious Organization",
            "type":"Services"
        }
    ],
    "sg:phone":"+1 434 634 3451",
    "sg:postcode":"23847",
    "sg:province":"VA",
    "wof:name":"Rising Star Baptist Church",
    "wof:placetype":"venue"
},
  "geometry": {"coordinates":[-77.581237,36.6888],"type":"Point"}
}