{
  "type": "Feature",
  "properties": {
    "addr:full":"8027 Orkney Grade Mount Jackson VA 22842",
    "addr:housenumber":"8027",
    "addr:postcode":"22842",
    "addr:street":"Orkney Grade",
    "iso:country":"US",
    "sg:address":"8027 Orkney Grade",
    "sg:city":"Mount Jackson",
    "sg:classifiers":[
        {
            "category":"Professional",
            "type":"Services"
        }
    ],
    "sg:phone":"+1 540 477 2316",
    "sg:postcode":"22842",
    "sg:province":"VA",
    "wof:name":"Claude & Pat Rush",
    "wof:placetype":"venue"
},
  "geometry": {"coordinates":[-78.71903500000001,38.764447],"type":"Point"}
}