{
  "type": "Feature",
  "properties": {
    "iso:country":"US",
    "sg:address":"400 Shop Rd",
    "sg:city":"Fort Lee",
    "sg:classifiers":[
        {
            "category":"Food & Beverages",
            "subcategory":"Groceries & Convenience Stores",
            "type":"Retail Goods"
        }
    ],
    "sg:phone":"+1 804 765 1036",
    "sg:postcode":"23801",
    "sg:province":"VA",
    "wof:name":"Fort Lee Commissary",
    "wof:placetype":"venue"
},
  "geometry": {"coordinates":[-77.32907899999999,37.251591],"type":"Point"}
}