{
  "type": "Feature",
  "properties": {
    "addr:full":"421 State Rte 400 Alexandria VA 22314",
    "addr:housenumber":"421",
    "addr:postcode":"22314",
    "addr:street":"State Rte 400",
    "iso:country":"US",
    "sg:address":"421 State Rte 400",
    "sg:city":"Alexandria",
    "sg:classifiers":[
        {
            "category":"Organizations",
            "subcategory":"Non-profit Organization",
            "type":"Services"
        }
    ],
    "sg:phone":"+1 703 838 4911",
    "sg:postcode":"22314",
    "sg:province":"VA",
    "sg:tags":[
        "social"
    ],
    "wof:name":"Office On Woman",
    "wof:placetype":"venue"
},
  "geometry": {"coordinates":[-77.045962,38.809368],"type":"Point"}
}