{
  "type": "Feature",
  "properties": {
    "addr:full":"7100 Heritage Village Plz Ste 101 Gainesville VA 20155",
    "addr:housenumber":"7100",
    "addr:postcode":"20155",
    "addr:street":"Heritage Village Plz Ste 101",
    "iso:country":"US",
    "sg:address":"7100 Heritage Village Plz Ste 101",
    "sg:city":"Gainesville",
    "sg:classifiers":[
        {
            "category":"Health Services",
            "subcategory":"Dentist",
            "type":"Services"
        }
    ],
    "sg:phone":"+1 703 754 5800",
    "sg:postcode":"20155",
    "sg:province":"VA",
    "sg:website":"www.heritagehuntdental.com",
    "wof:name":"Houser Chris DMD PC Dr",
    "wof:placetype":"venue"
},
  "geometry": {"coordinates":[-77.602436,38.80308],"type":"Point"}
}