{
  "type": "Feature",
  "properties": {
    "addr:full":"8081 Alban Rd Springfield VA 22150",
    "addr:housenumber":"8081",
    "addr:postcode":"22150",
    "addr:street":"Alban Rd",
    "iso:country":"US",
    "sg:address":"8081 Alban Rd",
    "sg:city":"Springfield",
    "sg:classifiers":[
        {
            "category":"Retail",
            "subcategory":"Laundry & Dry Cleaning",
            "type":"Services"
        }
    ],
    "sg:phone":"+1 703 440 9277",
    "sg:postcode":"22150",
    "sg:province":"VA",
    "sg:tags":[
        "drycleaning",
        "plant"
    ],
    "wof:name":"Superior Cleaners",
    "wof:placetype":"venue"
},
  "geometry": {"coordinates":[-77.193236,38.738957],"type":"Point"}
}