{
  "type": "Feature",
  "properties": {
    "addr:full":"1700 N Moore St Ste 1010 Arlington VA 22209",
    "addr:housenumber":"1700",
    "addr:postcode":"22209",
    "addr:street":"N Moore St Ste 1010",
    "iso:country":"US",
    "sg:address":"1700 N Moore St Ste 1010",
    "sg:city":"Arlington",
    "sg:classifiers":[
        {
            "category":"Professional",
            "subcategory":"Lawyer & Legal Services",
            "type":"Services"
        }
    ],
    "sg:phone":"+1 703 243 3500",
    "sg:postcode":"22209",
    "sg:province":"VA",
    "sg:tags":[
        "personal",
        "injury"
    ],
    "wof:name":"Michel Dominique D",
    "wof:placetype":"venue"
},
  "geometry": {"coordinates":[-77.071297,38.895],"type":"Point"}
}