{
  "type": "Feature",
  "properties": {
    "iso:country":"US",
    "sg:address":"5368 Providence Rd",
    "sg:city":"Virginia Beach",
    "sg:classifiers":[
        {
            "category":"Real Estate",
            "subcategory":"Real Estate Agent",
            "type":"Services"
        }
    ],
    "sg:phone":"+1 757 424 5102",
    "sg:postcode":"23464",
    "sg:province":"VA",
    "wof:name":"Competition Realty",
    "wof:placetype":"venue"
},
  "geometry": {"coordinates":[-76.175062,36.815349],"type":"Point"}
}