{
  "type": "Feature",
  "properties": {
    "addr:full":"8300 Epinard Ct Annandale VA 22003",
    "addr:postcode":"8300;22003",
    "addr:street":"Epinard Ct",
    "iso:country":"US",
    "sg:address":"8300 Epinard Ct",
    "sg:city":"Annandale",
    "sg:classifiers":[
        {
            "category":"Professional",
            "subcategory":"Management & Consulting",
            "type":"Services"
        }
    ],
    "sg:phone":"+1 703 731 7005",
    "sg:postcode":"22003",
    "sg:province":"VA",
    "sg:tags":[
        "it"
    ],
    "wof:name":"Integrasys Inc",
    "wof:placetype":"venue"
},
  "geometry": {"coordinates":[-77.235023,38.821425],"type":"Point"}
}