{
  "type": "Feature",
  "properties": {
    "addr:full":"200 George Washington Hwy N Chesapeake VA 23323",
    "addr:housenumber":"200",
    "addr:postcode":"23323",
    "addr:street":"George Washington Hwy N",
    "iso:country":"US",
    "sg:address":"200 George Washington Hwy N",
    "sg:city":"Chesapeake",
    "sg:classifiers":[
        {
            "category":"Autos & Motor Vehicles",
            "subcategory":"Fuel & Gas Station",
            "type":"Retail Goods"
        }
    ],
    "sg:phone":"+1 757 487 2988",
    "sg:postcode":"23323",
    "sg:province":"VA",
    "sg:tags":[
        "oil"
    ],
    "wof:name":"Deep Creek Amoco",
    "wof:placetype":"venue"
},
  "geometry": {"coordinates":[-76.345985,36.745295],"type":"Point"}
}