{
  "type": "Feature",
  "properties": {
    "addr:full":"12113 Sandy Ct Herndon VA 20170",
    "addr:housenumber":"12113",
    "addr:postcode":"20170",
    "addr:street":"Sandy Ct",
    "iso:country":"US",
    "sg:address":"12113 Sandy Ct",
    "sg:city":"Herndon",
    "sg:classifiers":[
        {
            "category":"Professional",
            "subcategory":"Computer Services",
            "type":"Services"
        }
    ],
    "sg:phone":"+1 703 404 1950",
    "sg:postcode":"20170",
    "sg:province":"VA",
    "sg:tags":[
        "software"
    ],
    "wof:name":"Indrasoft Inc",
    "wof:placetype":"venue"
},
  "geometry": {"coordinates":[-77.367131,38.99587],"type":"Point"}
}