{
  "type": "Feature",
  "properties": {
    "iso:country":"US",
    "sg:address":"520 Georgetown Rd",
    "sg:city":"Charlottesville",
    "sg:classifiers":[
        {
            "category":"Building & Trades",
            "subcategory":"Construction",
            "type":"Services"
        }
    ],
    "sg:phone":"+1 434 295 0213",
    "sg:postcode":"22901",
    "sg:province":"VA",
    "sg:tags":[
        "house"
    ],
    "wof:name":"G T Weeks Contracting Inc",
    "wof:placetype":"venue"
},
  "geometry": {"coordinates":[-78.500601,38.069631],"type":"Point"}
}