{
  "type": "Feature",
  "properties": {
    "addr:full":"8422 Electric Ave Vienna VA 22182",
    "addr:housenumber":"8422",
    "addr:postcode":"22182",
    "addr:street":"Electric Ave",
    "iso:country":"US",
    "sg:address":"8422 Electric Ave",
    "sg:city":"Vienna",
    "sg:classifiers":[
        {
            "category":"Government",
            "subcategory":"Office",
            "type":"Public Place"
        }
    ],
    "sg:phone":"+1 703 849 1312",
    "sg:postcode":"22182",
    "sg:province":"VA",
    "wof:name":"Fairfax County Alcohol & Drug",
    "wof:placetype":"venue"
},
  "geometry": {"coordinates":[-77.236158,38.901338],"type":"Point"}
}