{
  "type": "Feature",
  "properties": {
    "addr:full":"4115 Mount Vernon Ave Alexandria VA 22305",
    "addr:housenumber":"4115",
    "addr:postcode":"22305",
    "addr:street":"Mount Vernon Ave",
    "iso:country":"US",
    "sg:address":"4115 Mount Vernon Ave",
    "sg:city":"Alexandria",
    "sg:classifiers":[
        {
            "category":"Restaurant",
            "type":"Food & Drink"
        }
    ],
    "sg:menulink":"http://www.allmenus.com/va/alexandria/71888-pizza-hut/menu/",
    "sg:phone":"+1 703 519 7722",
    "sg:postcode":"22305",
    "sg:province":"VA",
    "sg:tags":[
        "american",
        "pizza"
    ],
    "wof:name":"Pizza Hut",
    "wof:placetype":"venue"
},
  "geometry": {"coordinates":[-77.064013,38.843057],"type":"Point"}
}