{
  "type": "Feature",
  "properties": {
    "addr:full":"316 Clover St Galax VA 24333",
    "addr:housenumber":"316",
    "addr:postcode":"24333",
    "addr:street":"Clover St",
    "iso:country":"US",
    "sg:address":"316 Clover St",
    "sg:city":"Galax",
    "sg:classifiers":[
        {
            "category":"Professional",
            "type":"Services"
        }
    ],
    "sg:phone":"+1 276 236 8344",
    "sg:postcode":"24333",
    "sg:province":"VA",
    "wof:name":"Ellen Moretz",
    "wof:placetype":"venue"
},
  "geometry": {"coordinates":[-80.926811,36.676006],"type":"Point"}
}