{
  "type": "Feature",
  "properties": {
    "iso:country":"US",
    "sg:address":"214 Court St",
    "sg:city":"Lawrenceville",
    "sg:classifiers":[
        {
            "category":"Insurance",
            "subcategory":"Insurance Agent",
            "type":"Services"
        }
    ],
    "sg:phone":"+1 434 848 3542",
    "sg:postcode":"23868",
    "sg:province":"VA",
    "wof:name":"Brunswick County Farm Bureau",
    "wof:placetype":"venue"
},
  "geometry": {"coordinates":[-77.846554,36.759443],"type":"Point"}
}