{
  "type": "Feature",
  "properties": {
    "addr:full":"44285 Lord Fairfax Pl Ashburn VA 20147",
    "addr:housenumber":"44285",
    "addr:postcode":"20147",
    "addr:street":"Lord Fairfax Pl",
    "iso:country":"US",
    "sg:address":"44285 Lord Fairfax Pl",
    "sg:city":"Ashburn",
    "sg:classifiers":[
        {
            "category":"Wholesale",
            "subcategory":"Computers",
            "type":"Manufacturing & Wholesale Goods"
        }
    ],
    "sg:phone":"+1 703 858 5457",
    "sg:postcode":"20147",
    "sg:province":"VA",
    "sg:tags":[
        "computer-wholesale",
        "manufacturer"
    ],
    "sg:website":"http://www.brma.com",
    "wof:name":"Hewlett-Packard Company",
    "wof:placetype":"venue"
},
  "geometry": {"coordinates":[-77.468648,39.024475],"type":"Point"}
}