{
  "type": "Feature",
  "properties": {
    "addr:full":"3328 Peters Creek Rd NW Roanoke VA 24019",
    "addr:housenumber":"3328",
    "addr:postcode":"24019",
    "addr:street":"Peters Creek Rd Nw",
    "iso:country":"US",
    "sg:address":"3328 Peters Creek Rd NW",
    "sg:city":"Roanoke",
    "sg:classifiers":[
        {
            "category":"Retail",
            "subcategory":"Auto Repair",
            "type":"Services"
        }
    ],
    "sg:phone":"+1 540 563 1133",
    "sg:postcode":"24019",
    "sg:province":"VA",
    "sg:tags":[
        "general"
    ],
    "wof:name":"Sportscar Clinic",
    "wof:placetype":"venue"
},
  "geometry": {"coordinates":[-79.998023,37.321186],"type":"Point"}
}