{
  "type": "Feature",
  "properties": {
    "iso:country":"US",
    "sg:address":"7973 Stonewall Shoppes Sq",
    "sg:city":"Gainesville",
    "sg:classifiers":[
        {
            "category":"Shopping",
            "subcategory":"Stationery & Office Supplies",
            "type":"Retail Goods"
        }
    ],
    "sg:phone":"+1 571 261 2174",
    "sg:postcode":"20155",
    "sg:province":"VA",
    "sg:tags":[
        "equipment"
    ],
    "sg:website":"www.staples.com/",
    "wof:name":"Staples",
    "wof:placetype":"venue"
},
  "geometry": {"coordinates":[-77.650144,38.785887],"type":"Point"}
}