{
  "type": "Feature",
  "properties": {
    "iso:country":"US",
    "sg:address":"1630 S Loudoun St",
    "sg:city":"Winchester",
    "sg:classifiers":[
        {
            "category":"Food & Beverages",
            "subcategory":"Groceries & Convenience Stores",
            "type":"Retail Goods"
        }
    ],
    "sg:phone":"+1 540 722 3246",
    "sg:postcode":"22601",
    "sg:province":"VA",
    "wof:name":"Jiffy Mart",
    "wof:placetype":"venue"
},
  "geometry": {"coordinates":[-78.171344,39.168727],"type":"Point"}
}