{
  "type": "Feature",
  "properties": {
    "addr:full":"8661 Leesburg Pike Vienna VA 22182",
    "addr:housenumber":"8661",
    "addr:postcode":"22182",
    "addr:street":"Leesburg Pike",
    "iso:country":"US",
    "sg:address":"8661 Leesburg Pike",
    "sg:city":"Vienna",
    "sg:classifiers":[
        {
            "category":"Professional",
            "type":"Services"
        }
    ],
    "sg:phone":"+1 703 883 1123",
    "sg:postcode":"22182",
    "sg:province":"VA",
    "wof:name":"Wynette Exposition Service",
    "wof:placetype":"venue"
},
  "geometry": {"coordinates":[-77.243877,38.931063],"type":"Point"}
}