{
  "type": "Feature",
  "properties": {
    "iso:country":"US",
    "sg:address":"2900 S Quincy St Ste 800",
    "sg:city":"Arlington",
    "sg:classifiers":[
        {
            "category":"Professional",
            "subcategory":"Research",
            "type":"Services"
        },
        {
            "category":"Professional",
            "subcategory":"Advertising",
            "type":"Services"
        },
        {
            "category":"Science Facility",
            "type":"Public Place"
        }
    ],
    "sg:phone":"+1 703 416 2000",
    "sg:postcode":"22206",
    "sg:province":"VA",
    "sg:tags":[
        "development",
        "advertising-telephone",
        "fax",
        "laboratories-research",
        "telemarketing"
    ],
    "wof:name":"Anser",
    "wof:placetype":"venue"
},
  "geometry": {"coordinates":[-77.086766,38.84042],"type":"Point"}
}