{
  "type": "Feature",
  "properties": {
    "addr:full":"3301 Mount Vernon Ave Alexandria VA 22305",
    "addr:housenumber":"3301",
    "addr:postcode":"22305",
    "addr:street":"Mount Vernon Ave",
    "iso:country":"US",
    "sg:address":"3301 Mount Vernon Ave",
    "sg:city":"Alexandria",
    "sg:classifiers":[
        {
            "category":"Insurance",
            "subcategory":"Insurance Agent",
            "type":"Services"
        }
    ],
    "sg:phone":"+1 703 684 0224",
    "sg:postcode":"22305",
    "sg:province":"VA",
    "wof:name":"Nationwide Insurance",
    "wof:placetype":"venue"
},
  "geometry": {"coordinates":[-77.060239,38.835075],"type":"Point"}
}