{
  "type": "Feature",
  "properties": {
    "addr:full":"208 Richmond Heights Rd Bristol VA 37620",
    "addr:housenumber":"208",
    "addr:postcode":"37620",
    "addr:street":"Richmond Heights Rd",
    "iso:country":"US",
    "sg:address":"208 Richmond Heights Rd",
    "sg:city":"Bristol",
    "sg:classifiers":[
        {
            "category":"Professional",
            "subcategory":"Business Services",
            "type":"Services"
        }
    ],
    "sg:phone":"+1 423 764 1105",
    "sg:postcode":"37620",
    "sg:province":"VA",
    "wof:name":"Cdr Pro Home Inspections",
    "wof:placetype":"venue"
},
  "geometry": {"coordinates":[-82.23947800000001,36.539608],"type":"Point"}
}