{
  "type": "Feature",
  "properties": {
    "addr:full":"913 S Hill Ave South Hill VA 23970",
    "addr:housenumber":"913",
    "addr:postcode":"23970",
    "addr:street":"S Hill Ave",
    "iso:country":"US",
    "sg:address":"913 S Hill Ave",
    "sg:city":"South Hill",
    "sg:classifiers":[
        {
            "category":"Shopping",
            "subcategory":"Used Merchandise",
            "type":"Retail Goods"
        }
    ],
    "sg:phone":"+1 434 447 2825",
    "sg:postcode":"23970",
    "sg:province":"VA",
    "wof:name":"Pawn Shop",
    "wof:placetype":"venue"
},
  "geometry": {"coordinates":[-78.13324299999999,36.718086],"type":"Point"}
}