{
  "type": "Feature",
  "properties": {
    "addr:full":"5105 Plaza Dr Hopewell VA 23860",
    "addr:housenumber":"5105",
    "addr:postcode":"23860",
    "addr:street":"Plaza Dr",
    "iso:country":"US",
    "sg:address":"5105 Plaza Dr",
    "sg:city":"Hopewell",
    "sg:classifiers":[
        {
            "category":"Restaurant",
            "type":"Food & Drink"
        }
    ],
    "sg:menulink":"http://www.allmenus.com/va/hopewell/111465-waffle-house/menu/",
    "sg:phone":"+1 804 452 0386",
    "sg:postcode":"23860",
    "sg:province":"VA",
    "sg:tags":[
        "american"
    ],
    "wof:name":"Waffle House",
    "wof:placetype":"venue"
},
  "geometry": {"coordinates":[-77.324772,37.262776],"type":"Point"}
}