{
  "type": "Feature",
  "properties": {
    "iso:country":"US",
    "sg:address":"2289 S Military Hwy",
    "sg:city":"Chesapeake",
    "sg:classifiers":[
        {
            "category":"Building & Trades",
            "subcategory":"Plumbing",
            "type":"Services"
        }
    ],
    "sg:phone":"+1 757 545 5000",
    "sg:postcode":"23320",
    "sg:province":"VA",
    "sg:tags":[
        "air",
        "heating",
        "conditioning",
        "contractor"
    ],
    "wof:name":"Controlled Conditions Corp",
    "wof:placetype":"venue"
},
  "geometry": {"coordinates":[-76.274225,36.77502],"type":"Point"}
}