{
  "type": "Feature",
  "properties": {
    "addr:full":"5619 Oakland Blvd Roanoke VA 24019",
    "addr:housenumber":"5619",
    "addr:postcode":"24019",
    "addr:street":"Oakland Blvd",
    "iso:country":"US",
    "sg:address":"5619 Oakland Blvd",
    "sg:city":"Roanoke",
    "sg:classifiers":[
        {
            "category":"Social Services",
            "subcategory":"Child Care",
            "type":"Services"
        }
    ],
    "sg:phone":"+1 540 563 2928",
    "sg:postcode":"24019",
    "sg:province":"VA",
    "wof:name":"Kid Zone",
    "wof:placetype":"venue"
},
  "geometry": {"coordinates":[-79.945667,37.332498],"type":"Point"}
}