{
  "type": "Feature",
  "properties": {
    "iso:country":"US",
    "sg:address":"7100 Forest Hill Ave",
    "sg:city":"Richmond",
    "sg:classifiers":[
        {
            "category":"Manufacturing",
            "subcategory":"Glass & Minerals",
            "type":"Manufacturing & Wholesale Goods"
        },
        {
            "category":"Shopping",
            "subcategory":"Computers & Home Electronics",
            "type":"Retail Goods"
        }
    ],
    "sg:phone":"+1 804 767 1051",
    "sg:postcode":"23225",
    "sg:province":"VA",
    "sg:tags":[
        "etc-manufacturers",
        "plate",
        "glass-auto",
        "window",
        "glass-automobile"
    ],
    "sg:website":"http://www.smileysglass.com",
    "wof:name":"Smiley's Mobile Glass Shop",
    "wof:placetype":"venue"
},
  "geometry": {"coordinates":[-77.525986,37.537745],"type":"Point"}
}