{
  "type": "Feature",
  "properties": {
    "addr:full":"1961 Chain Bridge Road Mclean VA 22107",
    "addr:housenumber":"1961",
    "addr:postcode":"22107",
    "addr:street":"Chain Bridge Road",
    "iso:country":"US",
    "sg:address":"1961 Chain Bridge Road",
    "sg:city":"Mclean",
    "sg:classifiers":[
        {
            "category":"Shopping",
            "subcategory":"Clothing, Apparel, & Fashions",
            "type":"Retail Goods"
        }
    ],
    "sg:phone":"+1 703 893 4377",
    "sg:postcode":"22107",
    "sg:province":"VA",
    "sg:website":"www.mexx.com",
    "wof:name":"Mexx",
    "wof:placetype":"venue"
},
  "geometry": {"coordinates":[-77.225899,38.919601],"type":"Point"}
}