{
  "type": "Feature",
  "properties": {
    "addr:full":"317 Potomac Ave Quantico VA 22134",
    "addr:housenumber":"317",
    "addr:postcode":"22134",
    "addr:street":"Potomac Ave",
    "iso:country":"US",
    "sg:address":"317 Potomac Ave",
    "sg:city":"Quantico",
    "sg:classifiers":[
        {
            "category":"Building & Trades",
            "subcategory":"Construction",
            "type":"Services"
        }
    ],
    "sg:phone":"+1 703 640 6421",
    "sg:postcode":"22134",
    "sg:province":"VA",
    "sg:tags":[
        "concrete",
        "contractor"
    ],
    "wof:name":"Mr Concrete Of Virginia",
    "wof:placetype":"venue"
},
  "geometry": {"coordinates":[-77.29222799999999,38.522328],"type":"Point"}
}