{
  "type": "Feature",
  "properties": {
    "addr:full":"6532 Richmond Rd Williamsburg VA 23188",
    "addr:housenumber":"6532",
    "addr:postcode":"23188",
    "addr:street":"Richmond Rd",
    "iso:country":"US",
    "sg:address":"6532 Richmond Rd",
    "sg:city":"Williamsburg",
    "sg:classifiers":[
        {
            "category":"Retail",
            "subcategory":"Auto Rental",
            "type":"Services"
        }
    ],
    "sg:phone":"+1 757 258 9199",
    "sg:postcode":"23188",
    "sg:province":"VA",
    "sg:tags":[
        "passenger",
        "car"
    ],
    "wof:name":"Enterprise Rent-A-Car",
    "wof:placetype":"venue"
},
  "geometry": {"coordinates":[-76.75566000000001,37.341992],"type":"Point"}
}