{
  "type": "Feature",
  "properties": {
    "addr:full":"619 E Riverside Dr North Tazewell VA 24630",
    "addr:housenumber":"619",
    "addr:postcode":"24630",
    "addr:street":"E Riverside Dr North",
    "iso:country":"US",
    "sg:address":"619 E Riverside Dr",
    "sg:city":"North Tazewell",
    "sg:classifiers":[
        {
            "category":"Restaurant",
            "type":"Food & Drink"
        }
    ],
    "sg:menulink":"http://www.allmenus.com/va/southern/147764-subway/menu/",
    "sg:phone":"+1 276 988 2499",
    "sg:postcode":"24630",
    "sg:province":"VA",
    "sg:tags":[
        "american",
        "sandwich"
    ],
    "wof:name":"Subway",
    "wof:placetype":"venue"
},
  "geometry": {"coordinates":[-81.49834300000001,37.133322],"type":"Point"}
}