{
  "type": "Feature",
  "properties": {
    "iso:country":"US",
    "sg:address":"8 Coe Pl",
    "sg:city":"Lexington",
    "sg:classifiers":[
        {
            "category":"Organizations",
            "subcategory":"Membership Organization",
            "type":"Services"
        }
    ],
    "sg:phone":"+1 540 463 9198",
    "sg:postcode":"24450",
    "sg:province":"VA",
    "wof:name":"National Scty Colonial Dans 17",
    "wof:placetype":"venue"
},
  "geometry": {"coordinates":[-79.46230199999999,37.765802],"type":"Point"}
}