{
  "type": "Feature",
  "properties": {
    "addr:full":"29156 Old Valley Pike Strasburg VA 22657",
    "addr:housenumber":"29156",
    "addr:postcode":"22657",
    "addr:street":"Old Valley Pike",
    "iso:country":"US",
    "sg:address":"29156 Old Valley Pike",
    "sg:city":"Strasburg",
    "sg:classifiers":[
        {
            "category":"Travel",
            "subcategory":"Hotels & Motels",
            "type":"Entertainment"
        }
    ],
    "sg:phone":"+1 540 465 8510",
    "sg:postcode":"22657",
    "sg:province":"VA",
    "sg:tags":[
        "operation"
    ],
    "wof:name":"Valley View Motel",
    "wof:placetype":"venue"
},
  "geometry": {"coordinates":[-78.401786,38.973213],"type":"Point"}
}