{
  "type": "Feature",
  "properties": {
    "addr:full":"5802 Rivers Landing Dr White Stone VA 22578",
    "addr:housenumber":"5802",
    "addr:postcode":"22578",
    "addr:street":"Rivers Landing Dr White Stone",
    "iso:country":"US",
    "sg:address":"5802 Rivers Landing Dr",
    "sg:city":"White Stone",
    "sg:classifiers":[
        {
            "category":"Professional",
            "subcategory":"Management & Consulting",
            "type":"Services"
        }
    ],
    "sg:phone":"+1 804 435 9119",
    "sg:postcode":"22578",
    "sg:province":"VA",
    "sg:tags":[
        "business"
    ],
    "wof:name":"River Group",
    "wof:placetype":"venue"
},
  "geometry": {"coordinates":[-76.407746,37.63918],"type":"Point"}
}