{
  "type": "Feature",
  "properties": {
    "addr:full":"4419 Lafayette Blvd Fredericksburg VA 22408",
    "addr:housenumber":"4419",
    "addr:postcode":"22408",
    "addr:street":"Lafayette Blvd",
    "iso:country":"US",
    "sg:address":"4419 Lafayette Blvd",
    "sg:city":"Fredericksburg",
    "sg:classifiers":[
        {
            "category":"Manufacturing",
            "subcategory":"Signs",
            "type":"Manufacturing & Wholesale Goods"
        }
    ],
    "sg:phone":"+1 540 710 6177",
    "sg:postcode":"22408",
    "sg:province":"VA",
    "sg:tags":[
        "specialty",
        "mfg"
    ],
    "wof:name":"Signs By Shelley",
    "wof:placetype":"venue"
},
  "geometry": {"coordinates":[-77.49365299999999,38.258236],"type":"Point"}
}