{
  "type": "Feature",
  "properties": {
    "iso:country":"US",
    "sg:address":"6023 Dunnbrook Ter",
    "sg:city":"Haymarket",
    "sg:classifiers":[
        {
            "category":"Professional",
            "subcategory":"Engineering",
            "type":"Services"
        }
    ],
    "sg:phone":"+1 703 754 3849",
    "sg:postcode":"20169",
    "sg:province":"VA",
    "wof:name":"Integrity Aviation Services",
    "wof:placetype":"venue"
},
  "geometry": {"coordinates":[-77.61994,38.825971],"type":"Point"}
}