{
  "type": "Feature",
  "properties": {
    "iso:country":"US",
    "sg:address":"360 E Virginia Ave",
    "sg:city":"Vinton",
    "sg:classifiers":[
        {
            "category":"Shopping",
            "subcategory":"Discount & Variety Stores",
            "type":"Retail Goods"
        }
    ],
    "sg:phone":"+1 540 857 9889",
    "sg:postcode":"24179",
    "sg:province":"VA",
    "sg:tags":[
        "merchandise",
        "general"
    ],
    "wof:name":"Country Cousins",
    "wof:placetype":"venue"
},
  "geometry": {"coordinates":[-79.89663400000001,37.275306],"type":"Point"}
}