{
  "type": "Feature",
  "properties": {
    "addr:full":"460 Hall Farmer Rd Blairs VA 24527",
    "addr:housenumber":"460",
    "addr:postcode":"24527",
    "addr:street":"Hall Farmer Rd",
    "iso:country":"US",
    "sg:address":"460 Hall Farmer Rd",
    "sg:city":"Blairs",
    "sg:classifiers":[
        {
            "category":"Retail",
            "subcategory":"Laundry & Dry Cleaning",
            "type":"Services"
        }
    ],
    "sg:phone":"+1 434 797 1275",
    "sg:postcode":"24527",
    "sg:province":"VA",
    "wof:name":"Complete Carpet Upholstery Clg",
    "wof:placetype":"venue"
},
  "geometry": {"coordinates":[-79.341071,36.682241],"type":"Point"}
}