{
  "type": "Feature",
  "properties": {
    "addr:full":"2138 Barracks Rd Charlottesville VA 22903",
    "addr:housenumber":"2138",
    "addr:postcode":"22903",
    "addr:street":"Barracks Rd",
    "iso:country":"US",
    "sg:address":"2138 Barracks Rd",
    "sg:city":"Charlottesville",
    "sg:classifiers":[
        {
            "category":"Home & Garden",
            "subcategory":"Furniture",
            "type":"Retail Goods"
        }
    ],
    "sg:phone":"+1 434 296 7018",
    "sg:postcode":"22903",
    "sg:province":"VA",
    "sg:tags":[
        "store"
    ],
    "wof:name":"Creme De La Creme",
    "wof:placetype":"venue"
},
  "geometry": {"coordinates":[-78.50039700000001,38.054298],"type":"Point"}
}