{
  "type": "Feature",
  "properties": {
    "iso:country":"US",
    "sg:address":"230 Battlefield Blvd N",
    "sg:city":"Chesapeake",
    "sg:classifiers":[
        {
            "category":"Shopping",
            "subcategory":"Clothing, Apparel, & Fashions",
            "type":"Retail Goods"
        }
    ],
    "sg:phone":"+1 757 547 0200",
    "sg:postcode":"23320",
    "sg:province":"VA",
    "sg:tags":[
        "baby",
        "furniture",
        "wear",
        "accessory"
    ],
    "wof:name":"Bye Bye Baby",
    "wof:placetype":"venue"
},
  "geometry": {"coordinates":[-76.241359,36.725864],"type":"Point"}
}