{
  "type": "Feature",
  "properties": {
    "addr:full":"1585 Dorset Rd Powhatan VA 23139",
    "addr:housenumber":"1585",
    "addr:postcode":"23139",
    "addr:street":"Dorset Rd",
    "iso:country":"US",
    "sg:address":"1585 Dorset Rd",
    "sg:city":"Powhatan",
    "sg:classifiers":[
        {
            "category":"Insurance",
            "subcategory":"Insurance Agent",
            "type":"Services"
        }
    ],
    "sg:phone":"+1 804 598 6001",
    "sg:postcode":"23139",
    "sg:province":"VA",
    "sg:tags":[
        "life",
        "pension"
    ],
    "wof:name":"Bob Hodges and Company",
    "wof:placetype":"venue"
},
  "geometry": {"coordinates":[-77.818654,37.501196],"type":"Point"}
}