{
  "type": "Feature",
  "properties": {
    "iso:country":"US",
    "sg:address":"513 Carnation Ave",
    "sg:city":"Virginia Beach",
    "sg:classifiers":[
        {
            "category":"Social Services",
            "subcategory":"Child Care",
            "type":"Services"
        }
    ],
    "sg:phone":"+1 757 456 2025",
    "sg:postcode":"23462",
    "sg:province":"VA",
    "wof:name":"Tidewater Sitting Svc LLC",
    "wof:placetype":"venue"
},
  "geometry": {"coordinates":[-76.146401,36.851406],"type":"Point"}
}