{
  "type": "Feature",
  "properties": {
    "addr:full":"1537 Cow Rd Buffalo Junction VA 24529",
    "addr:housenumber":"1537",
    "addr:postcode":"24529",
    "addr:street":"Cow Rd",
    "iso:country":"US",
    "sg:address":"1537 Cow Rd",
    "sg:city":"Buffalo Junction",
    "sg:classifiers":[
        {
            "category":"Freight",
            "type":"Transportation"
        }
    ],
    "sg:phone":"+1 434 374 2692",
    "sg:postcode":"24529",
    "sg:province":"VA",
    "sg:tags":[
        "trucking"
    ],
    "wof:name":"Nelson & Co Inc",
    "wof:placetype":"venue"
},
  "geometry": {"coordinates":[-78.61209100000001,36.633862],"type":"Point"}
}