{
  "type": "Feature",
  "properties": {
    "addr:full":"4101 Washington Ave Newport News VA 23607",
    "addr:housenumber":"4101",
    "addr:postcode":"23607",
    "addr:street":"Washington Ave",
    "iso:country":"US",
    "sg:address":"4101 Washington Ave",
    "sg:city":"Newport News",
    "sg:classifiers":[
        {
            "category":"Building & Trades",
            "subcategory":"Plumbing",
            "type":"Services"
        }
    ],
    "sg:phone":"+1 757 244 3133",
    "sg:postcode":"23607",
    "sg:province":"VA",
    "sg:tags":[
        "plumbing",
        "contractor"
    ],
    "wof:name":"Warwick Plumbing & Htg Corp",
    "wof:placetype":"venue"
},
  "geometry": {"coordinates":[-76.437004,36.988647],"type":"Point"}
}