{
  "type": "Feature",
  "properties": {
    "iso:country":"US",
    "sg:address":"986 Bellmore Ave",
    "sg:city":"Norfolk",
    "sg:classifiers":[
        {
            "category":"Real Estate",
            "subcategory":"Architect",
            "type":"Services"
        }
    ],
    "sg:phone":"+1 757 627 5751",
    "sg:postcode":"23504",
    "sg:province":"VA",
    "wof:name":"Lemole Pointon Architects",
    "wof:placetype":"venue"
},
  "geometry": {"coordinates":[-76.249781,36.852176],"type":"Point"}
}