{
  "type": "Feature",
  "properties": {
    "addr:full":"8400 Salem Ave Marshall VA 20115",
    "addr:housenumber":"8400",
    "addr:postcode":"20115",
    "addr:street":"Salem Ave",
    "iso:country":"US",
    "sg:address":"8400 Salem Ave",
    "sg:city":"Marshall",
    "sg:classifiers":[
        {
            "category":"Real Estate",
            "subcategory":"Real Estate Operator",
            "type":"Services"
        }
    ],
    "sg:phone":"+1 540 364 9586",
    "sg:postcode":"20115",
    "sg:province":"VA",
    "sg:tags":[
        "building",
        "nonresidential"
    ],
    "wof:name":"Marshall Ruritan Club Inc",
    "wof:placetype":"venue"
},
  "geometry": {"coordinates":[-77.859925,38.86513],"type":"Point"}
}