{
  "type": "Feature",
  "properties": {
    "addr:full":"3401 Beechtree Ln Falls Church VA 22042",
    "addr:housenumber":"3401",
    "addr:postcode":"22042",
    "addr:street":"Beechtree Ln",
    "iso:country":"US",
    "sg:address":"3401 Beechtree Ln",
    "sg:city":"Falls Church",
    "sg:classifiers":[
        {
            "category":"Education",
            "subcategory":"School",
            "type":"Public Place"
        }
    ],
    "sg:phone":"+1 703 531 2600",
    "sg:postcode":"22042",
    "sg:province":"VA",
    "sg:tags":[
        "elementary"
    ],
    "wof:name":"Beech Tree Elementary School",
    "wof:placetype":"venue"
},
  "geometry": {"coordinates":[-77.181513,38.853274],"type":"Point"}
}