{
  "type": "Feature",
  "properties": {
    "addr:full":"5209 Catawba Valley Dr Catawba VA 24070",
    "addr:housenumber":"5209",
    "addr:postcode":"catawba;24070",
    "addr:street":"Catawba Valley Dr",
    "iso:country":"US",
    "sg:address":"5209 Catawba Valley Dr",
    "sg:city":"Catawba",
    "sg:classifiers":[
        {
            "category":"Travel",
            "subcategory":"Hotels & Motels",
            "type":"Entertainment"
        }
    ],
    "sg:phone":"+1 540 384 6865",
    "sg:postcode":"24070",
    "sg:province":"VA",
    "sg:tags":[
        "breakfast",
        "accommodation",
        "bed"
    ],
    "wof:name":"Down Home Bed & Breakfast",
    "wof:placetype":"venue"
},
  "geometry": {"coordinates":[-80.12127099999999,37.3808],"type":"Point"}
}