{
  "type": "Feature",
  "properties": {
    "addr:full":"12401 Redwater Creek Rd Chester VA 23831",
    "addr:housenumber":"12401",
    "addr:postcode":"23831",
    "addr:street":"Redwater Creek Rd",
    "iso:country":"US",
    "sg:address":"12401 Redwater Creek Rd",
    "sg:city":"Chester",
    "sg:classifiers":[
        {
            "category":"Bars & Pubs",
            "type":"Food & Drink"
        }
    ],
    "sg:menulink":"http://www.allmenus.com/va/bermuda/35313-cracker-barrel-old-country-store/menu/",
    "sg:phone":"+1 804 748 4032",
    "sg:postcode":"23831",
    "sg:province":"VA",
    "sg:tags":[
        "american",
        "southern"
    ],
    "wof:name":"Cracker Barrel Old Country Store",
    "wof:placetype":"venue"
},
  "geometry": {"coordinates":[-77.407816,37.355559],"type":"Point"}
}