{
  "type": "Feature",
  "properties": {
    "iso:country":"US",
    "sg:address":"708 N Jackson St",
    "sg:city":"Arlington",
    "sg:classifiers":[
        {
            "category":"Professional",
            "subcategory":"Management & Consulting",
            "type":"Services"
        }
    ],
    "sg:phone":"+1 703 528 8760",
    "sg:postcode":"22201",
    "sg:province":"VA",
    "sg:tags":[
        "business"
    ],
    "wof:name":"Gourekos Consulting",
    "wof:placetype":"venue"
},
  "geometry": {"coordinates":[-77.098553,38.879844],"type":"Point"}
}