{
  "type": "Feature",
  "properties": {
    "addr:full":"9000 Pams Ave Richmond VA 23237",
    "addr:postcode":"9000;23237",
    "addr:street":"Pams Ave",
    "iso:country":"US",
    "sg:address":"9000 Pams Ave",
    "sg:city":"Richmond",
    "sg:classifiers":[
        {
            "category":"Building & Trades",
            "subcategory":"Construction",
            "type":"Services"
        }
    ],
    "sg:phone":"+1 804 275 9373",
    "sg:postcode":"23237",
    "sg:province":"VA",
    "sg:tags":[
        "roofing",
        "contractor"
    ],
    "wof:name":"Cross Timbers",
    "wof:placetype":"venue"
},
  "geometry": {"coordinates":[-77.428156,37.402058],"type":"Point"}
}