{
  "type": "Feature",
  "properties": {
    "addr:full":"7012 Sea Cliff Rd Mc Lean VA 22101",
    "addr:housenumber":"7012",
    "addr:postcode":"22101",
    "addr:street":"Sea Cliff Rd",
    "iso:country":"US",
    "sg:address":"7012 Sea Cliff Rd",
    "sg:city":"Mc Lean",
    "sg:classifiers":[
        {
            "category":"Professional",
            "subcategory":"Business Services",
            "type":"Services"
        }
    ],
    "sg:phone":"+1 703 827 0319",
    "sg:postcode":"22101",
    "sg:province":"VA",
    "sg:tags":[
        "interpreter",
        "court"
    ],
    "wof:name":"Mariano E Gowland",
    "wof:placetype":"venue"
},
  "geometry": {"coordinates":[-77.186702,38.923156],"type":"Point"}
}