{
  "type": "Feature",
  "properties": {
    "addr:full":"925 Dorchester Pl Charlottesville VA 22911",
    "addr:housenumber":"925",
    "addr:postcode":"22911",
    "addr:street":"Dorchester Pl",
    "iso:country":"US",
    "sg:address":"925 Dorchester Pl",
    "sg:city":"Charlottesville",
    "sg:classifiers":[
        {
            "category":"Real Estate",
            "subcategory":"Real Estate Operator",
            "type":"Services"
        }
    ],
    "sg:phone":"+1 434 293 6912",
    "sg:postcode":"22911",
    "sg:province":"VA",
    "sg:tags":[
        "apartment"
    ],
    "wof:name":"Carriage Hills Apt",
    "wof:placetype":"venue"
},
  "geometry": {"coordinates":[-78.450073,38.030357],"type":"Point"}
}