{
  "type": "Feature",
  "properties": {
    "iso:country":"US",
    "sg:address":"4401 1st St S",
    "sg:city":"Arlington",
    "sg:classifiers":[
        {
            "category":"Professional",
            "subcategory":"Business Services",
            "type":"Services"
        }
    ],
    "sg:phone":"+1 703 892 6892",
    "sg:postcode":"22204",
    "sg:province":"VA",
    "wof:name":"Organization Unlimited Co",
    "wof:placetype":"venue"
},
  "geometry": {"coordinates":[-77.11068400000001,38.866685],"type":"Point"}
}