{
  "type": "Feature",
  "properties": {
    "iso:country":"US",
    "sg:address":"5884 Poplar Hall Dr",
    "sg:city":"Norfolk",
    "sg:classifiers":[
        {
            "category":"Autos & Motor Vehicles",
            "subcategory":"Auto Supplies",
            "type":"Retail Goods"
        }
    ],
    "sg:phone":"+1 757 455 8802",
    "sg:postcode":"23502",
    "sg:province":"VA",
    "sg:tags":[
        "automobile",
        "stereo",
        "radio",
        "transportation"
    ],
    "wof:name":"Car Stereo Intl & Tint Co",
    "wof:placetype":"venue"
},
  "geometry": {"coordinates":[-76.20272199999999,36.849536],"type":"Point"}
}