{
  "type": "Feature",
  "properties": {
    "iso:country":"US",
    "sg:address":"15075 Litton Rd",
    "sg:city":"Abingdon",
    "sg:classifiers":[
        {
            "category":"Building & Trades",
            "subcategory":"Construction",
            "type":"Services"
        }
    ],
    "sg:phone":"+1 276 676 0259",
    "sg:postcode":"24210",
    "sg:province":"VA",
    "sg:tags":[
        "general",
        "contractor"
    ],
    "wof:name":"Stone Mountain Construction",
    "wof:placetype":"venue"
},
  "geometry": {"coordinates":[-82.022947,36.731725],"type":"Point"}
}