{
  "type": "Feature",
  "properties": {
    "addr:full":"4362 Electric Rd Roanoke VA 24018",
    "addr:housenumber":"4362",
    "addr:postcode":"24018",
    "addr:street":"Electric Rd",
    "iso:country":"US",
    "sg:address":"4362 Electric Rd",
    "sg:city":"Roanoke",
    "sg:classifiers":[
        {
            "category":"Shopping",
            "subcategory":"Bicycles & Sporting Goods",
            "type":"Retail Goods"
        }
    ],
    "sg:phone":"+1 540 774 4311",
    "sg:postcode":"24018",
    "sg:province":"VA",
    "wof:name":"Blueridge Outdoors",
    "wof:placetype":"venue"
},
  "geometry": {"coordinates":[-79.978122,37.228131],"type":"Point"}
}