{
  "type": "Feature",
  "properties": {
    "iso:country":"US",
    "sg:address":"5981 Cloverdale Rd",
    "sg:city":"Roanoke",
    "sg:classifiers":[
        {
            "category":"Food & Beverages",
            "subcategory":"Groceries & Convenience Stores",
            "type":"Retail Goods"
        }
    ],
    "sg:phone":"+1 540 977 5806",
    "sg:postcode":"24019",
    "sg:province":"VA",
    "wof:name":"604 Minute Market",
    "wof:placetype":"venue"
},
  "geometry": {"coordinates":[-79.878626,37.342587],"type":"Point"}
}