{
  "type": "Feature",
  "properties": {
    "addr:full":"9805 Kohoutek Ct Vienna VA 22182",
    "addr:housenumber":"9805",
    "addr:postcode":"22182",
    "addr:street":"Kohoutek Ct",
    "iso:country":"US",
    "sg:address":"9805 Kohoutek Ct",
    "sg:city":"Vienna",
    "sg:classifiers":[
        {
            "category":"Organizations",
            "subcategory":"Non-profit Organization",
            "type":"Services"
        }
    ],
    "sg:phone":"+1 703 242 0365",
    "sg:postcode":"22182",
    "sg:province":"VA",
    "sg:tags":[
        "social"
    ],
    "wof:name":"Center For Sceince of Min",
    "wof:placetype":"venue"
},
  "geometry": {"coordinates":[-77.285781,38.923127],"type":"Point"}
}