{
  "type": "Feature",
  "properties": {
    "iso:country":"US",
    "sg:address":"3754 Troutdale Hwy",
    "sg:city":"Mouth Of Wilson",
    "sg:classifiers":[
        {
            "category":"Personal",
            "subcategory":"Barber",
            "type":"Services"
        }
    ],
    "sg:phone":"+1 276 579 2005",
    "sg:postcode":"24363",
    "sg:province":"VA",
    "wof:name":"Halsey's Barbershop",
    "wof:placetype":"venue"
},
  "geometry": {"coordinates":[-81.366345,36.611359],"type":"Point"}
}