{
  "type": "Feature",
  "properties": {
    "addr:full":"2802 Greensboro Rd Martinsville VA 24112",
    "addr:housenumber":"2802",
    "addr:postcode":"24112",
    "addr:street":"Greensboro Rd",
    "iso:country":"US",
    "sg:address":"2802 Greensboro Rd",
    "sg:city":"Martinsville",
    "sg:classifiers":[
        {
            "category":"Shopping",
            "subcategory":"Clothing, Apparel, & Fashions",
            "type":"Retail Goods"
        }
    ],
    "sg:phone":"+1 276 632 4157",
    "sg:postcode":"24112",
    "sg:province":"VA",
    "wof:name":"It's Fashion",
    "wof:placetype":"venue"
},
  "geometry": {"coordinates":[-79.874048,36.652899],"type":"Point"}
}