{
  "type": "Feature",
  "properties": {
    "addr:full":"30 Marshall Rd Ruckersville VA 22968",
    "addr:housenumber":"30",
    "addr:postcode":"22968",
    "addr:street":"Marshall Rd",
    "iso:country":"US",
    "sg:address":"30 Marshall Rd",
    "sg:city":"Ruckersville",
    "sg:classifiers":[
        {
            "category":"Professional",
            "subcategory":"Business Services",
            "type":"Services"
        }
    ],
    "sg:phone":"+1 434 985 4309",
    "sg:postcode":"22968",
    "sg:province":"VA",
    "wof:name":"Southeast Horse Sales",
    "wof:placetype":"venue"
},
  "geometry": {"coordinates":[-78.410742,38.228617],"type":"Point"}
}