{
  "type": "Feature",
  "properties": {
    "iso:country":"US",
    "sg:address":"1600 South Hayes St.",
    "sg:city":"Arlington",
    "sg:classifiers":[
        {
            "category":"Park",
            "type":"Public Place"
        }
    ],
    "sg:postcode":"22202",
    "sg:province":"VA",
    "sg:website":"www.arlingtonva.us/departments/p...",
    "wof:name":"Virginia Highlands Park",
    "wof:placetype":"venue"
},
  "geometry": {"coordinates":[-77.059887,38.858508],"type":"Point"}
}