{
  "type": "Feature",
  "properties": {
    "iso:country":"US",
    "sg:address":"5411 Williamson Rd NE",
    "sg:city":"Roanoke",
    "sg:classifiers":[
        {
            "category":"Shopping",
            "subcategory":"Gifts & Souvenirs",
            "type":"Retail Goods"
        }
    ],
    "sg:phone":"+1 540 366 0757",
    "sg:postcode":"24012",
    "sg:province":"VA",
    "sg:tags":[
        "collectible"
    ],
    "wof:name":"Star City Collectibles",
    "wof:placetype":"venue"
},
  "geometry": {"coordinates":[-79.95367,37.323557],"type":"Point"}
}