{
  "type": "Feature",
  "properties": {
    "iso:country":"US",
    "sg:address":"6834 Elm St",
    "sg:city":"Mc Lean",
    "sg:classifiers":[
        {
            "category":"Personal",
            "subcategory":"Massage",
            "type":"Services"
        }
    ],
    "sg:phone":"+1 703 883 0255",
    "sg:postcode":"22101",
    "sg:province":"VA",
    "wof:name":"Mark Halbeisen",
    "wof:placetype":"venue"
},
  "geometry": {"coordinates":[-77.18029900000001,38.936319],"type":"Point"}
}