{
  "type": "Feature",
  "properties": {
    "addr:full":"930 Rife's Ford Rd Verona VA 24401",
    "addr:housenumber":"930",
    "addr:postcode":"24401",
    "addr:street":"Rife'S Ford Rd",
    "iso:country":"US",
    "sg:address":"930 Rife's Ford Rd",
    "sg:city":"Verona",
    "sg:classifiers":[
        {
            "category":"Manufacturing",
            "subcategory":"Textiles",
            "type":"Manufacturing & Wholesale Goods"
        }
    ],
    "sg:phone":"+1 540 363 0802",
    "sg:postcode":"24401",
    "sg:province":"VA",
    "sg:tags":[
        "mill",
        "fabric",
        "cotton"
    ],
    "wof:name":"Folk Art Basketry",
    "wof:placetype":"venue"
},
  "geometry": {"coordinates":[-78.971253,38.208656],"type":"Point"}
}