{
  "type": "Feature",
  "properties": {
    "addr:full":"316 Pintail Rd Virginia Beach VA 23456",
    "addr:housenumber":"316",
    "addr:postcode":"23456",
    "addr:street":"Pintail Rd",
    "iso:country":"US",
    "sg:address":"316 Pintail Rd",
    "sg:city":"Virginia Beach",
    "sg:classifiers":[
        {
            "category":"Wholesale",
            "subcategory":"Machinery & Supplies",
            "type":"Manufacturing & Wholesale Goods"
        }
    ],
    "sg:phone":"+1 757 426 9070",
    "sg:postcode":"23456",
    "sg:province":"VA",
    "sg:tags":[
        "abrasive"
    ],
    "wof:name":"Abrasive Specialists",
    "wof:placetype":"venue"
},
  "geometry": {"coordinates":[-75.943038,36.730786],"type":"Point"}
}