{
  "type": "Feature",
  "properties": {
    "iso:country":"US",
    "sg:address":"2278 Compass Point Ln",
    "sg:city":"Reston",
    "sg:classifiers":[
        {
            "category":"Manufacturing",
            "subcategory":"Printing",
            "type":"Manufacturing & Wholesale Goods"
        }
    ],
    "sg:phone":"+1 703 476 5982",
    "sg:postcode":"20191",
    "sg:province":"VA",
    "sg:tags":[
        "publishing"
    ],
    "wof:name":"South Lakes Publishing",
    "wof:placetype":"venue"
},
  "geometry": {"coordinates":[-77.33404899999999,38.926956],"type":"Point"}
}