{
  "type": "Feature",
  "properties": {
    "iso:country":"US",
    "sg:address":"11710 Jefferson Ave",
    "sg:city":"Newport News",
    "sg:classifiers":[
        {
            "category":"Health Services",
            "subcategory":"Chiropractor",
            "type":"Services"
        }
    ],
    "sg:phone":"+1 757 873 7786",
    "sg:postcode":"23606",
    "sg:province":"VA",
    "sg:tags":[
        "clinic"
    ],
    "wof:name":"Back In Action",
    "wof:placetype":"venue"
},
  "geometry": {"coordinates":[-76.47844600000001,37.080007],"type":"Point"}
}