{
  "type": "Feature",
  "properties": {
    "addr:full":"1455 Old Bridge Rd Woodbridge VA 22192",
    "addr:housenumber":"1455",
    "addr:postcode":"22192",
    "addr:street":"Old Bridge Rd",
    "iso:country":"US",
    "sg:address":"1455 Old Bridge Rd",
    "sg:city":"Woodbridge",
    "sg:classifiers":[
        {
            "category":"Professional",
            "type":"Services"
        }
    ],
    "sg:phone":"+1 703 494 4196",
    "sg:postcode":"22192",
    "sg:province":"VA",
    "sg:tags":[
        "establishment"
    ],
    "wof:name":"Sportslife Enterprises",
    "wof:placetype":"venue"
},
  "geometry": {"coordinates":[-77.25864300000001,38.67306],"type":"Point"}
}