{
  "type": "Feature",
  "properties": {
    "iso:country":"US",
    "sg:address":"1097 Independence Blvd",
    "sg:city":"Virginia Beach",
    "sg:classifiers":[
        {
            "category":"Restaurant",
            "type":"Food & Drink"
        }
    ],
    "sg:menulink":"http://www.allmenus.com/va/virginia-beach/179497-chick-fil-a/menu/",
    "sg:phone":"+1 757 318 7641",
    "sg:postcode":"23455",
    "sg:province":"VA",
    "sg:tags":[
        "wrap",
        "soup",
        "american",
        "sandwich",
        "salad"
    ],
    "wof:name":"Chick-fil-A",
    "wof:placetype":"venue"
},
  "geometry": {"coordinates":[-76.134664,36.874824],"type":"Point"}
}