{
  "type": "Feature",
  "properties": {
    "iso:country":"US",
    "sg:address":"2711 Dorr Ave",
    "sg:city":"Fairfax",
    "sg:classifiers":[
        {
            "category":"Building & Trades",
            "subcategory":"Construction",
            "type":"Services"
        }
    ],
    "sg:phone":"+1 703 560 0993",
    "sg:postcode":"22031",
    "sg:province":"VA",
    "sg:tags":[
        "installation",
        "elevator",
        "maintenance"
    ],
    "wof:name":"Apex Elevator Company",
    "wof:placetype":"venue"
},
  "geometry": {"coordinates":[-77.233529,38.878377],"type":"Point"}
}