{
  "type": "Feature",
  "properties": {
    "iso:country":"US",
    "sg:address":"1900 Kraft Dr",
    "sg:city":"Blacksburg",
    "sg:classifiers":[
        {
            "category":"Professional",
            "subcategory":"Computer Services",
            "type":"Services"
        }
    ],
    "sg:phone":"+1 540 552 0888",
    "sg:postcode":"24060",
    "sg:province":"VA",
    "sg:tags":[
        "internet"
    ],
    "wof:name":"X Systems Inc",
    "wof:placetype":"venue"
},
  "geometry": {"coordinates":[-80.410061,37.202431],"type":"Point"}
}