{
  "type": "Feature",
  "properties": {
    "addr:full":"3522 Laurel Leaf Ln Fairfax VA 22031",
    "addr:housenumber":"3522",
    "addr:postcode":"22031",
    "addr:street":"Laurel Leaf Ln",
    "iso:country":"US",
    "sg:address":"3522 Laurel Leaf Ln",
    "sg:city":"Fairfax",
    "sg:classifiers":[
        {
            "category":"Building & Trades",
            "subcategory":"Construction",
            "type":"Services"
        }
    ],
    "sg:phone":"+1 703 280 8171",
    "sg:postcode":"22031",
    "sg:province":"VA",
    "sg:tags":[
        "industrial"
    ],
    "wof:name":"Keith W Reiss Dr",
    "wof:placetype":"venue"
},
  "geometry": {"coordinates":[-77.251903,38.849811],"type":"Point"}
}