{
  "type": "Feature",
  "properties": {
    "iso:country":"US",
    "sg:address":"2405 Bennett Cir",
    "sg:city":"Keeling",
    "sg:classifiers":[
        {
            "category":"Autos & Motor Vehicles",
            "subcategory":"Automobile Sales",
            "type":"Retail Goods"
        }
    ],
    "sg:phone":"+1 434 799 3340",
    "sg:postcode":"24566",
    "sg:province":"VA",
    "sg:tags":[
        "body",
        "car",
        "used",
        "dealer"
    ],
    "wof:name":"Rick's Auto & Body Shop",
    "wof:placetype":"venue"
},
  "geometry": {"coordinates":[-79.289551,36.686777],"type":"Point"}
}