{
  "type": "Feature",
  "properties": {
    "addr:full":"10525 Battleview Pkwy Manassas VA 20109",
    "addr:housenumber":"10525",
    "addr:postcode":"20109",
    "addr:street":"Battleview Pkwy",
    "iso:country":"US",
    "sg:address":"10525 Battleview Pkwy",
    "sg:city":"Manassas",
    "sg:classifiers":[
        {
            "category":"Professional",
            "subcategory":"Engineering",
            "type":"Services"
        }
    ],
    "sg:phone":"+1 703 369 0906",
    "sg:postcode":"20109",
    "sg:province":"VA",
    "sg:tags":[
        "surveying"
    ],
    "sg:website":"www.dewberry.com",
    "wof:name":"Dewberry & Davis",
    "wof:placetype":"venue"
},
  "geometry": {"coordinates":[-77.51779999999999,38.805774],"type":"Point"}
}