{
  "type": "Feature",
  "properties": {
    "iso:country":"US",
    "sg:address":"459 Merrimac Trl",
    "sg:city":"Williamsburg",
    "sg:classifiers":[
        {
            "category":"Retail",
            "subcategory":"Laundry & Dry Cleaning",
            "type":"Services"
        }
    ],
    "sg:phone":"+1 757 229 4990",
    "sg:postcode":"23185",
    "sg:province":"VA",
    "sg:tags":[
        "cleaners"
    ],
    "wof:name":"Town & Country Cleaners",
    "wof:placetype":"venue"
},
  "geometry": {"coordinates":[-76.67976400000001,37.273713],"type":"Point"}
}