{
  "type": "Feature",
  "properties": {
    "addr:full":"328 Adwolfe Rd Marion VA 24354",
    "addr:housenumber":"328",
    "addr:postcode":"24354",
    "addr:street":"Adwolfe Rd",
    "iso:country":"US",
    "sg:address":"328 Adwolfe Rd",
    "sg:city":"Marion",
    "sg:classifiers":[
        {
            "category":"Autos & Motor Vehicles",
            "subcategory":"Automobile Sales",
            "type":"Retail Goods"
        }
    ],
    "sg:phone":"+1 276 783 2959",
    "sg:postcode":"24354",
    "sg:province":"VA",
    "sg:tags":[
        "used"
    ],
    "wof:name":"R & M Used Cars",
    "wof:placetype":"venue"
},
  "geometry": {"coordinates":[-81.57776699999999,36.804145],"type":"Point"}
}