{
  "type": "Feature",
  "properties": {
    "iso:country":"US",
    "sg:address":"1915 N Hamilton St",
    "sg:city":"Richmond",
    "sg:classifiers":[
        {
            "category":"Autos & Motor Vehicles",
            "subcategory":"Motorcycle Sales",
            "type":"Retail Goods"
        }
    ],
    "sg:phone":"+1 804 355 0550",
    "sg:postcode":"23230",
    "sg:province":"VA",
    "sg:tags":[
        "scooter"
    ],
    "sg:website":"www.motoeuropa.com",
    "wof:name":"Ducati Moto Europa",
    "wof:placetype":"venue"
},
  "geometry": {"coordinates":[-77.476365,37.572862],"type":"Point"}
}