{
  "type": "Feature",
  "properties": {
    "iso:country":"US",
    "sg:address":"1768 Prodan Ln",
    "sg:city":"Virginia Beach",
    "sg:classifiers":[
        {
            "category":"Retail",
            "subcategory":"Laundry & Dry Cleaning",
            "type":"Services"
        }
    ],
    "sg:phone":"+1 757 754 3874",
    "sg:postcode":"23453",
    "sg:province":"VA",
    "wof:name":"Larry Edward De Guzman",
    "wof:placetype":"venue"
},
  "geometry": {"coordinates":[-76.05320500000001,36.762479],"type":"Point"}
}