{
  "type": "Feature",
  "properties": {
    "addr:full":"20789 Eskridge Ct Sterling VA 20165",
    "addr:postcode":"20789;20165",
    "addr:street":"Eskridge Ct",
    "iso:country":"US",
    "sg:address":"20789 Eskridge Ct",
    "sg:city":"Sterling",
    "sg:classifiers":[
        {
            "category":"Building & Trades",
            "subcategory":"Construction",
            "type":"Services"
        }
    ],
    "sg:phone":"+1 703 932 1506",
    "sg:postcode":"20165",
    "sg:province":"VA",
    "sg:tags":[
        "general",
        "contractor"
    ],
    "wof:name":"Wolf Steel Inc",
    "wof:placetype":"venue"
},
  "geometry": {"coordinates":[-77.393764,39.040874],"type":"Point"}
}