{
  "type": "Feature",
  "properties": {
    "addr:full":"7049 Snow Creek Rd Penhook VA 24137",
    "addr:housenumber":"7049",
    "addr:postcode":"24137",
    "addr:street":"Snow Creek Rd",
    "iso:country":"US",
    "sg:address":"7049 Snow Creek Rd",
    "sg:city":"Penhook",
    "sg:classifiers":[
        {
            "category":"Professional",
            "type":"Services"
        }
    ],
    "sg:phone":"+1 540 576 3666",
    "sg:postcode":"24137",
    "sg:province":"VA",
    "sg:tags":[
        "establishment"
    ],
    "wof:name":"Snow Creek Rescue Squad",
    "wof:placetype":"venue"
},
  "geometry": {"coordinates":[-79.73855,36.836677],"type":"Point"}
}