{
  "type": "Feature",
  "properties": {
    "iso:country":"US",
    "sg:address":"1816 Wigglesworth Way",
    "sg:city":"Woodbridge",
    "sg:classifiers":[
        {
            "category":"Professional",
            "subcategory":"Computer Services",
            "type":"Services"
        }
    ],
    "sg:phone":"+1 703 490 3685",
    "sg:postcode":"22191",
    "sg:province":"VA",
    "sg:tags":[
        "planning",
        "network"
    ],
    "wof:name":"Cldugan Associates Inc",
    "wof:placetype":"venue"
},
  "geometry": {"coordinates":[-77.26473,38.647513],"type":"Point"}
}