{
  "type": "Feature",
  "properties": {
    "addr:full":"154 S Main St Broadway VA 22815",
    "addr:housenumber":"154",
    "addr:postcode":"22815",
    "addr:street":"S Main St",
    "iso:country":"US",
    "sg:address":"154 S Main St",
    "sg:city":"Broadway",
    "sg:classifiers":[
        {
            "category":"Utilities",
            "subcategory":"Refuse",
            "type":"Services"
        }
    ],
    "sg:phone":"+1 540 896 4554",
    "sg:postcode":"22815",
    "sg:province":"VA",
    "sg:tags":[
        "disposal",
        "waste"
    ],
    "wof:name":"Medical Removal Svc",
    "wof:placetype":"venue"
},
  "geometry": {"coordinates":[-78.799294,38.612924],"type":"Point"}
}