{
  "type": "Feature",
  "properties": {
    "iso:country":"US",
    "sg:address":"10857 Gambril Dr",
    "sg:city":"Manassas",
    "sg:classifiers":[
        {
            "category":"Professional",
            "type":"Services"
        }
    ],
    "sg:phone":"+1 703 367 0085",
    "sg:postcode":"20109",
    "sg:province":"VA",
    "wof:name":"Fix A Crack LLC",
    "wof:placetype":"venue"
},
  "geometry": {"coordinates":[-77.521081,38.77946],"type":"Point"}
}