{
  "type": "Feature",
  "properties": {
    "iso:country":"US",
    "sg:address":"118 Bosley Ave",
    "sg:city":"Suffolk",
    "sg:classifiers":[
        {
            "category":"Education",
            "subcategory":"Library",
            "type":"Public Place"
        }
    ],
    "sg:phone":"+1 757 539 3175",
    "sg:postcode":"23434",
    "sg:province":"VA",
    "wof:name":"Morgan Memorial Library",
    "wof:placetype":"venue"
},
  "geometry": {"coordinates":[-76.59474,36.729518],"type":"Point"}
}