{
  "type": "Feature",
  "properties": {
    "addr:full":"9120 Burkwood Club Dr Mechanicsville VA 23116",
    "addr:postcode":"9120;23116",
    "addr:street":"Club Dr",
    "iso:country":"US",
    "sg:address":"9120 Burkwood Club Dr",
    "sg:city":"Mechanicsville",
    "sg:classifiers":[
        {
            "category":"Organizations",
            "subcategory":"Community Association",
            "type":"Services"
        }
    ],
    "sg:phone":"+1 804 730 2472",
    "sg:postcode":"23116",
    "sg:province":"VA",
    "sg:tags":[
        "club"
    ],
    "wof:name":"Burkwood Recreation Assn",
    "wof:placetype":"venue"
},
  "geometry": {"coordinates":[-77.374233,37.650464],"type":"Point"}
}