{
  "type": "Feature",
  "properties": {
    "iso:country":"US",
    "sg:address":"12825 Noltland Castle Dr",
    "sg:city":"Bristow",
    "sg:classifiers":[
        {
            "category":"Professional",
            "subcategory":"Accounting & Tax Preparation",
            "type":"Services"
        }
    ],
    "sg:phone":"+1 703 335 2017",
    "sg:postcode":"20136",
    "sg:province":"VA",
    "wof:name":"Fast Lane Cycles",
    "wof:placetype":"venue"
},
  "geometry": {"coordinates":[-77.57215600000001,38.741617],"type":"Point"}
}