{
  "type": "Feature",
  "properties": {
    "addr:full":"710 Brumfield Rd Blacksburg VA 24060",
    "addr:housenumber":"710",
    "addr:postcode":"24060",
    "addr:street":"Brumfield Rd",
    "iso:country":"US",
    "sg:address":"710 Brumfield Rd",
    "sg:city":"Blacksburg",
    "sg:classifiers":[
        {
            "category":"Organizations",
            "subcategory":"Religious Organization",
            "type":"Services"
        }
    ],
    "sg:phone":"+1 540 382 8519",
    "sg:postcode":"24060",
    "sg:province":"VA",
    "wof:name":"Cedar Run Faith Tabernacl",
    "wof:placetype":"venue"
},
  "geometry": {"coordinates":[-80.387719,37.186924],"type":"Point"}
}