{
  "type": "Feature",
  "properties": {
    "iso:country":"US",
    "sg:address":"128 S Cameron St",
    "sg:city":"Winchester",
    "sg:classifiers":[
        {
            "category":"Insurance",
            "subcategory":"Insurance Agent",
            "type":"Services"
        }
    ],
    "sg:phone":"+1 540 667 9335",
    "sg:postcode":"22601",
    "sg:province":"VA",
    "wof:name":"Allstate Insurance",
    "wof:placetype":"venue"
},
  "geometry": {"coordinates":[-78.16458799999999,39.182423],"type":"Point"}
}