{
  "type": "Feature",
  "properties": {
    "addr:full":"1014 Vernon St Alexandria VA 22314",
    "addr:housenumber":"1014",
    "addr:postcode":"22314",
    "addr:street":"Vernon St",
    "iso:country":"US",
    "sg:address":"1014 Vernon St",
    "sg:city":"Alexandria",
    "sg:classifiers":[
        {
            "category":"Professional",
            "type":"Services"
        }
    ],
    "sg:phone":"+1 703 739 6773",
    "sg:postcode":"22314",
    "sg:province":"VA",
    "wof:name":"Adrienne Rodas",
    "wof:placetype":"venue"
},
  "geometry": {"coordinates":[-77.048524,38.816164],"type":"Point"}
}