{
  "type": "Feature",
  "properties": {
    "addr:full":"1100 Dandy Loop Rd Yorktown VA 23692",
    "addr:housenumber":"1100",
    "addr:postcode":"23692",
    "addr:street":"Dandy Loop Rd",
    "iso:country":"US",
    "sg:address":"1100 Dandy Loop Rd",
    "sg:city":"Yorktown",
    "sg:classifiers":[
        {
            "category":"Building & Trades",
            "subcategory":"Construction",
            "type":"Services"
        }
    ],
    "sg:phone":"+1 757 591 9523",
    "sg:postcode":"23692",
    "sg:province":"VA",
    "sg:tags":[
        "painter"
    ],
    "wof:name":"Bill Jones Painting Contractor",
    "wof:placetype":"venue"
},
  "geometry": {"coordinates":[-76.421729,37.216536],"type":"Point"}
}