{
  "type": "Feature",
  "properties": {
    "addr:full":"1329 Fishpaw Rd Berryville VA 22611",
    "addr:housenumber":"1329",
    "addr:postcode":"22611",
    "addr:street":"Fishpaw Rd",
    "iso:country":"US",
    "sg:address":"1329 Fishpaw Rd",
    "sg:city":"Berryville",
    "sg:classifiers":[
        {
            "category":"Retail",
            "subcategory":"Auto Repair",
            "type":"Services"
        }
    ],
    "sg:phone":"+1 540 955 3363",
    "sg:postcode":"22611",
    "sg:province":"VA",
    "sg:tags":[
        "re",
        "mach",
        "electrical",
        "general"
    ],
    "wof:name":"Braggs Truck Repair",
    "wof:placetype":"venue"
},
  "geometry": {"coordinates":[-78.039008,39.206334],"type":"Point"}
}