{
  "type": "Feature",
  "properties": {
    "iso:country":"US",
    "sg:address":"1128 Riva Ridge Dr",
    "sg:city":"Great Falls",
    "sg:classifiers":[
        {
            "category":"Professional",
            "subcategory":"Management & Consulting",
            "type":"Services"
        }
    ],
    "sg:phone":"+1 703 759 4484",
    "sg:postcode":"22066",
    "sg:province":"VA",
    "sg:tags":[
        "business"
    ],
    "wof:name":"Atr Consultants",
    "wof:placetype":"venue"
},
  "geometry": {"coordinates":[-77.317824,38.984376],"type":"Point"}
}