{
  "type": "Feature",
  "properties": {
    "iso:country":"US",
    "sg:address":"2400 Falkirk Dr",
    "sg:city":"Richmond",
    "sg:classifiers":[
        {
            "category":"Professional",
            "type":"Services"
        }
    ],
    "sg:phone":"+1 804 745 4623",
    "sg:postcode":"23236",
    "sg:province":"VA",
    "sg:tags":[
        "processing",
        "data"
    ],
    "wof:name":"Acs Data Services Inc",
    "wof:placetype":"venue"
},
  "geometry": {"coordinates":[-77.57195299999999,37.45734],"type":"Point"}
}