{
  "type": "Feature",
  "properties": {
    "addr:full":"4537 Evansdale Rd Woodbridge VA 22193",
    "addr:housenumber":"4537",
    "addr:postcode":"22193",
    "addr:street":"Evansdale Rd",
    "iso:country":"US",
    "sg:address":"4537 Evansdale Rd",
    "sg:city":"Woodbridge",
    "sg:classifiers":[
        {
            "category":"Professional",
            "type":"Services"
        }
    ],
    "sg:phone":"+1 703 730 5497",
    "sg:postcode":"22193",
    "sg:province":"VA",
    "wof:name":"Home Installation Services LLC",
    "wof:placetype":"venue"
},
  "geometry": {"coordinates":[-77.343915,38.631316],"type":"Point"}
}