{
  "type": "Feature",
  "properties": {
    "iso:country":"US",
    "sg:address":"345 Circuit Ln",
    "sg:city":"Newport News",
    "sg:classifiers":[
        {
            "category":"Health Services",
            "subcategory":"Health Practitioner",
            "type":"Services"
        }
    ],
    "sg:phone":"+1 757 872 7017",
    "sg:postcode":"23608",
    "sg:province":"VA",
    "sg:tags":[
        "assistant",
        "medical"
    ],
    "wof:name":"Joan Thompson",
    "wof:placetype":"venue"
},
  "geometry": {"coordinates":[-76.53271599999999,37.14144],"type":"Point"}
}