{
  "type": "Feature",
  "properties": {
    "addr:full":"14845 Forest Rd Forest VA 24551",
    "addr:housenumber":"14845",
    "addr:postcode":"24551",
    "addr:street":"Forest Rd",
    "iso:country":"US",
    "sg:address":"14845 Forest Rd",
    "sg:city":"Forest",
    "sg:classifiers":[
        {
            "category":"Insurance",
            "subcategory":"Insurance Agent",
            "type":"Services"
        }
    ],
    "sg:phone":"+1 434 525 9300",
    "sg:postcode":"24551",
    "sg:province":"VA",
    "sg:tags":[
        "consultant"
    ],
    "wof:name":"Bill Brown Agency LLC",
    "wof:placetype":"venue"
},
  "geometry": {"coordinates":[-79.295536,37.366252],"type":"Point"}
}