{
  "type": "Feature",
  "properties": {
    "iso:country":"US",
    "sg:address":"10234 Brittenford Dr",
    "sg:city":"Vienna",
    "sg:classifiers":[
        {
            "category":"Restaurant",
            "type":"Food & Drink"
        }
    ],
    "sg:phone":"+1 703 716 8596",
    "sg:postcode":"22182",
    "sg:province":"VA",
    "sg:tags":[
        "eating"
    ],
    "wof:name":"Que H Pham",
    "wof:placetype":"venue"
},
  "geometry": {"coordinates":[-77.300366,38.946092],"type":"Point"}
}