{
  "type": "Feature",
  "properties": {
    "iso:country":"US",
    "sg:address":"521 Butler Farm Rd",
    "sg:city":"Hampton",
    "sg:classifiers":[
        {
            "category":"Building & Trades",
            "subcategory":"Cleaning & Sanitation",
            "type":"Services"
        }
    ],
    "sg:phone":"+1 757 766 7223",
    "sg:postcode":"23666",
    "sg:province":"VA",
    "sg:tags":[
        "janitorial"
    ],
    "wof:name":"Rock Solid Janitorial Inc",
    "wof:placetype":"venue"
},
  "geometry": {"coordinates":[-76.410838,37.061517],"type":"Point"}
}