{
  "type": "Feature",
  "properties": {
    "addr:full":"417 New Britain Dr Lynchburg VA 24503",
    "addr:housenumber":"417",
    "addr:postcode":"24503",
    "addr:street":"New Britain Dr",
    "iso:country":"US",
    "sg:address":"417 New Britain Dr",
    "sg:city":"Lynchburg",
    "sg:classifiers":[
        {
            "category":"Professional",
            "subcategory":"Computer Services",
            "type":"Services"
        }
    ],
    "sg:phone":"+1 434 384 5199",
    "sg:postcode":"24503",
    "sg:province":"VA",
    "sg:tags":[
        "programing",
        "custom"
    ],
    "wof:name":"Palmway Productions Inc",
    "wof:placetype":"venue"
},
  "geometry": {"coordinates":[-79.2242,37.432758],"type":"Point"}
}