{
  "type": "Feature",
  "properties": {
    "iso:country":"US",
    "sg:address":"10404 Central Park Dr",
    "sg:city":"Manassas",
    "sg:classifiers":[
        {
            "category":"Retail",
            "subcategory":"Auto Repair",
            "type":"Services"
        }
    ],
    "sg:phone":"+1 703 361 3374",
    "sg:postcode":"20110",
    "sg:province":"VA",
    "sg:tags":[
        "automobile",
        "restoration",
        "classic"
    ],
    "wof:name":"V W Restorations & Customs",
    "wof:placetype":"venue"
},
  "geometry": {"coordinates":[-77.50075699999999,38.740993],"type":"Point"}
}