{
  "type": "Feature",
  "properties": {
    "addr:full":"5705 Portsmouth Blvd Portsmouth VA 23701",
    "addr:housenumber":"5705",
    "addr:postcode":"23701",
    "addr:street":"Portsmouth Blvd",
    "iso:country":"US",
    "sg:address":"5705 Portsmouth Blvd",
    "sg:city":"Portsmouth",
    "sg:classifiers":[
        {
            "category":"Restaurant",
            "type":"Food & Drink"
        }
    ],
    "sg:menulink":"http://www.allmenus.com/va/portsmouth/155130-hardees/menu/",
    "sg:phone":"+1 757 488 0548",
    "sg:postcode":"23701",
    "sg:province":"VA",
    "sg:tags":[
        "burger",
        "american"
    ],
    "wof:name":"Hardee's",
    "wof:placetype":"venue"
},
  "geometry": {"coordinates":[-76.380668,36.819659],"type":"Point"}
}