{
  "type": "Feature",
  "properties": {
    "iso:country":"US",
    "sg:address":"3964 Wyckoff Dr",
    "sg:city":"Virginia Beach",
    "sg:classifiers":[
        {
            "category":"Manufacturing",
            "subcategory":"Watercraft",
            "type":"Manufacturing & Wholesale Goods"
        }
    ],
    "sg:phone":"+1 757 615 1530",
    "sg:postcode":"23452",
    "sg:province":"VA",
    "wof:name":"K & K Boatworks",
    "wof:placetype":"venue"
},
  "geometry": {"coordinates":[-76.11534399999999,36.845109],"type":"Point"}
}