{
  "type": "Feature",
  "properties": {
    "iso:country":"US",
    "sg:address":"4205 Annandale Center Dr",
    "sg:city":"Annandale",
    "sg:classifiers":[
        {
            "category":"Restaurant",
            "type":"Food & Drink"
        }
    ],
    "sg:phone":"+1 703 941 2663",
    "sg:postcode":"22003",
    "sg:province":"VA",
    "sg:tags":[
        "eating"
    ],
    "wof:name":"New China Carry Out",
    "wof:placetype":"venue"
},
  "geometry": {"coordinates":[-77.192133,38.83198],"type":"Point"}
}