{
  "type": "Feature",
  "properties": {
    "iso:country":"US",
    "sg:address":"130 Addie Dr",
    "sg:city":"Madison Heights",
    "sg:classifiers":[
        {
            "category":"Personal",
            "subcategory":"Beauty Salon",
            "type":"Services"
        }
    ],
    "sg:phone":"+1 434 384 2247",
    "sg:postcode":"24572",
    "sg:province":"VA",
    "sg:tags":[
        "shop"
    ],
    "wof:name":"Beauty Central",
    "wof:placetype":"venue"
},
  "geometry": {"coordinates":[-79.191368,37.511279],"type":"Point"}
}