{
  "type": "Feature",
  "properties": {
    "iso:country":"US",
    "sg:address":"154 Evening Star Ln",
    "sg:city":"Shipman",
    "sg:classifiers":[
        {
            "category":"Professional",
            "type":"Services"
        }
    ],
    "sg:phone":"+1 434 263 5706",
    "sg:postcode":"22971",
    "sg:province":"VA",
    "wof:name":"Inyo Studio",
    "wof:placetype":"venue"
},
  "geometry": {"coordinates":[-78.828478,37.720513],"type":"Point"}
}