{
  "type": "Feature",
  "properties": {
    "addr:full":"20 Garfield Dr Newport News VA 23608",
    "addr:housenumber":"20",
    "addr:postcode":"23608",
    "addr:street":"Garfield Dr",
    "iso:country":"US",
    "sg:address":"20 Garfield Dr",
    "sg:city":"Newport News",
    "sg:classifiers":[
        {
            "category":"Organizations",
            "subcategory":"Religious Organization",
            "type":"Services"
        }
    ],
    "sg:phone":"+1 757 877 8245",
    "sg:postcode":"23608",
    "sg:province":"VA",
    "wof:name":"Gates of Praise",
    "wof:placetype":"venue"
},
  "geometry": {"coordinates":[-76.55600200000001,37.143553],"type":"Point"}
}