{
  "type": "Feature",
  "properties": {
    "addr:full":"16600 Danville Pike Laurel Fork VA 24352",
    "addr:housenumber":"16600",
    "addr:postcode":"24352",
    "addr:street":"Danville Pike",
    "iso:country":"US",
    "sg:address":"16600 Danville Pike",
    "sg:city":"Laurel Fork",
    "sg:classifiers":[
        {
            "category":"Health Services",
            "subcategory":"Nursing And Care Facility",
            "type":"Services"
        }
    ],
    "sg:phone":"+1 276 398 2117",
    "sg:postcode":"24352",
    "sg:province":"VA",
    "sg:tags":[
        "home",
        "convalescent"
    ],
    "wof:name":"Heritage Hall-Laurel Meadows",
    "wof:placetype":"venue"
},
  "geometry": {"coordinates":[-80.47463999999999,36.721862],"type":"Point"}
}