{
  "type": "Feature",
  "properties": {
    "addr:full":"8578 Cold Harbor Loop Manassas VA 20111",
    "addr:housenumber":"8578",
    "addr:postcode":"20111",
    "addr:street":"Cold Harbor Loop",
    "iso:country":"US",
    "sg:address":"8578 Cold Harbor Loop",
    "sg:city":"Manassas",
    "sg:classifiers":[
        {
            "category":"Local Transit",
            "type":"Transportation"
        }
    ],
    "sg:phone":"+1 703 330 8206",
    "sg:postcode":"20111",
    "sg:province":"VA",
    "sg:tags":[
        "limousine"
    ],
    "wof:name":"Pak Sedan Svc Inc",
    "wof:placetype":"venue"
},
  "geometry": {"coordinates":[-77.456441,38.777254],"type":"Point"}
}