{
  "type": "Feature",
  "properties": {
    "addr:full":"417 New Hampshire Ave Norfolk VA 23508",
    "addr:housenumber":"417",
    "addr:postcode":"23508",
    "addr:street":"New Hampshire Ave",
    "iso:country":"US",
    "sg:address":"417 New Hampshire Ave",
    "sg:city":"Norfolk",
    "sg:classifiers":[
        {
            "category":"Professional",
            "subcategory":"Business Services",
            "type":"Services"
        }
    ],
    "sg:phone":"+1 757 652 8234",
    "sg:postcode":"23508",
    "sg:province":"VA",
    "sg:tags":[
        "interior",
        "designer"
    ],
    "wof:name":"Ben Teague Original Art Design",
    "wof:placetype":"venue"
},
  "geometry": {"coordinates":[-76.282995,36.887871],"type":"Point"}
}