{
  "type": "Feature",
  "properties": {
    "iso:country":"US",
    "sg:address":"901 N Washington St",
    "sg:city":"Alexandria",
    "sg:classifiers":[
        {
            "category":"Personal",
            "subcategory":"Tanning Parlor",
            "type":"Services"
        },
        {
            "category":"Personal",
            "type":"Services"
        }
    ],
    "sg:phone":"+1 703 836 8185",
    "sg:postcode":"22314",
    "sg:province":"VA",
    "sg:tags":[
        "salon"
    ],
    "wof:name":"Solar Planet",
    "wof:placetype":"venue"
},
  "geometry": {"coordinates":[-77.044766,38.815273],"type":"Point"}
}