{
  "type": "Feature",
  "properties": {
    "iso:country":"US",
    "sg:address":"19292 Clearview Ln",
    "sg:city":"Culpeper",
    "sg:classifiers":[
        {
            "category":"Building & Trades",
            "subcategory":"Landscaping Services",
            "type":"Services"
        }
    ],
    "sg:phone":"+1 540 399 1374",
    "sg:postcode":"22701",
    "sg:province":"VA",
    "sg:tags":[
        "control",
        "mowing",
        "landscape",
        "weed"
    ],
    "wof:name":"Kildee Farms Ldscp & Lawn Svc",
    "wof:placetype":"venue"
},
  "geometry": {"coordinates":[-77.898443,38.439154],"type":"Point"}
}