{
  "type": "Feature",
  "properties": {
    "addr:full":"146 Gene Ave Suffolk VA 23434",
    "addr:housenumber":"146",
    "addr:postcode":"23434",
    "addr:street":"Gene Ave",
    "iso:country":"US",
    "sg:address":"146 Gene Ave",
    "sg:city":"Suffolk",
    "sg:classifiers":[
        {
            "category":"Professional",
            "type":"Services"
        }
    ],
    "sg:phone":"+1 757 925 4642",
    "sg:postcode":"23434",
    "sg:province":"VA",
    "wof:name":"Clyde Edmond",
    "wof:placetype":"venue"
},
  "geometry": {"coordinates":[-76.65848,36.711752],"type":"Point"}
}