{
  "type": "Feature",
  "properties": {
    "addr:full":"3003 Jeb Stuart Hwy Meadows Of Dan VA 24120",
    "addr:housenumber":"3003",
    "addr:postcode":"dan;24120",
    "addr:street":"Jeb Stuart Hwy Meadows",
    "iso:country":"US",
    "sg:address":"3003 Jeb Stuart Hwy",
    "sg:city":"Meadows Of Dan",
    "sg:classifiers":[
        {
            "category":"Education",
            "subcategory":"School",
            "type":"Public Place"
        }
    ],
    "sg:phone":"+1 276 952 2424",
    "sg:postcode":"24120",
    "sg:province":"VA",
    "wof:name":"Meadows Of Dan Elem School",
    "wof:placetype":"venue"
},
  "geometry": {"coordinates":[-80.404053,36.735814],"type":"Point"}
}