{
  "type": "Feature",
  "properties": {
    "addr:full":"2965 Hopkins Rd Rocky Mount VA 24151",
    "addr:housenumber":"2965",
    "addr:postcode":"24151",
    "addr:street":"Hopkins Rd",
    "iso:country":"US",
    "sg:address":"2965 Hopkins Rd",
    "sg:city":"Rocky Mount",
    "sg:classifiers":[
        {
            "category":"Professional",
            "type":"Services"
        }
    ],
    "sg:phone":"+1 540 489 5218",
    "sg:postcode":"24151",
    "sg:province":"VA",
    "wof:name":"St George Deliverance Inc",
    "wof:placetype":"venue"
},
  "geometry": {"coordinates":[-79.93942199999999,37.014471],"type":"Point"}
}