{
  "type": "Feature",
  "properties": {
    "addr:full":"19 Tall Tree Ln Fredericksburg VA 22406",
    "addr:housenumber":"19",
    "addr:postcode":"22406",
    "addr:street":"Tall Tree Ln",
    "iso:country":"US",
    "sg:address":"19 Tall Tree Ln",
    "sg:city":"Fredericksburg",
    "sg:classifiers":[
        {
            "category":"Building & Trades",
            "subcategory":"Construction",
            "type":"Services"
        }
    ],
    "sg:phone":"+1 540 752 5143",
    "sg:postcode":"22406",
    "sg:province":"VA",
    "sg:tags":[
        "siding",
        "contractor"
    ],
    "wof:name":"Benny Thacker Siding Co Inc",
    "wof:placetype":"venue"
},
  "geometry": {"coordinates":[-77.578507,38.398763],"type":"Point"}
}