{
  "type": "Feature",
  "properties": {
    "addr:full":"45901 Nokes Blvd Sterling VA 20166",
    "addr:housenumber":"45901",
    "addr:postcode":"20166",
    "addr:street":"Nokes Blvd",
    "iso:country":"US",
    "sg:address":"45901 Nokes Blvd",
    "sg:city":"Sterling",
    "sg:classifiers":[
        {
            "category":"Real Estate",
            "subcategory":"Real Estate Agent",
            "type":"Services"
        }
    ],
    "sg:phone":"+1 571 323 0018",
    "sg:postcode":"20166",
    "sg:province":"VA",
    "wof:name":"Real Media",
    "wof:placetype":"venue"
},
  "geometry": {"coordinates":[-77.412111,39.023594],"type":"Point"}
}