{
  "type": "Feature",
  "properties": {
    "iso:country":"US",
    "sg:address":"4262 Sunrise Drive Cir",
    "sg:city":"Chincoteague",
    "sg:classifiers":[
        {
            "category":"Building & Trades",
            "subcategory":"Electrical",
            "type":"Services"
        }
    ],
    "sg:phone":"+1 757 336 6776",
    "sg:postcode":"23336",
    "sg:province":"VA",
    "sg:tags":[
        "electrical",
        "electric",
        "contractor"
    ],
    "wof:name":"Harper Electric Inc",
    "wof:placetype":"venue"
},
  "geometry": {"coordinates":[-75.373946,37.919317],"type":"Point"}
}