{
  "type": "Feature",
  "properties": {
    "iso:country":"US",
    "sg:address":"11528 Vale Rd",
    "sg:city":"Oakton",
    "sg:classifiers":[
        {
            "category":"Organizations",
            "subcategory":"Religious Organization",
            "type":"Services"
        }
    ],
    "sg:phone":"+1 703 620 2594",
    "sg:postcode":"22124",
    "sg:province":"VA",
    "wof:name":"Vale United Methdst Preschool",
    "wof:placetype":"venue"
},
  "geometry": {"coordinates":[-77.34579600000001,38.892327],"type":"Point"}
}