{
  "type": "Feature",
  "properties": {
    "addr:full":"6441 McCoy Rd Centreville VA 20121",
    "addr:housenumber":"6441",
    "addr:postcode":"20121",
    "addr:street":"Mccoy Rd",
    "iso:country":"US",
    "sg:address":"6441 McCoy Rd",
    "sg:city":"Centreville",
    "sg:classifiers":[
        {
            "category":"Building & Trades",
            "subcategory":"Cleaning & Sanitation",
            "type":"Services"
        }
    ],
    "sg:phone":"+1 703 862 9401",
    "sg:postcode":"20121",
    "sg:province":"VA",
    "sg:tags":[
        "maintenance"
    ],
    "wof:name":"Regency Cleaning Service",
    "wof:placetype":"venue"
},
  "geometry": {"coordinates":[-77.458043,38.833104],"type":"Point"}
}