{
  "type": "Feature",
  "properties": {
    "iso:country":"US",
    "sg:address":"6922 University Dr",
    "sg:city":"Alexandria",
    "sg:classifiers":[
        {
            "category":"Building & Trades",
            "subcategory":"Construction",
            "type":"Services"
        }
    ],
    "sg:phone":"+1 703 217 1996",
    "sg:postcode":"22307",
    "sg:province":"VA",
    "sg:tags":[
        "house"
    ],
    "wof:name":"Clarks Home Improvement",
    "wof:placetype":"venue"
},
  "geometry": {"coordinates":[-77.075155,38.766519],"type":"Point"}
}