{
  "type": "Feature",
  "properties": {
    "iso:country":"US",
    "sg:address":"2246 N Beauregard St Apt 3",
    "sg:city":"Alexandria",
    "sg:classifiers":[
        {
            "category":"Real Estate",
            "subcategory":"Real Estate Operator",
            "type":"Services"
        }
    ],
    "sg:phone":"+1 703 379 9094",
    "sg:postcode":"22311",
    "sg:province":"VA",
    "sg:tags":[
        "apartment"
    ],
    "wof:name":"Hermitage Hill Apartments",
    "wof:placetype":"venue"
},
  "geometry": {"coordinates":[-77.115196,38.835201],"type":"Point"}
}