{
  "type": "Feature",
  "properties": {
    "addr:full":"3445 Seminole Trl Charlottesville VA 22911",
    "addr:housenumber":"3445",
    "addr:postcode":"22911",
    "addr:street":"Seminole Trl",
    "iso:country":"US",
    "sg:address":"3445 Seminole Trl",
    "sg:city":"Charlottesville",
    "sg:classifiers":[
        {
            "category":"Communications",
            "subcategory":"Film & Video Production",
            "type":"Services"
        }
    ],
    "sg:phone":"+1 434 990 6521",
    "sg:postcode":"22911",
    "sg:province":"VA",
    "sg:tags":[
        "taping"
    ],
    "wof:name":"Paladin Pictures",
    "wof:placetype":"venue"
},
  "geometry": {"coordinates":[-78.435287,38.132123],"type":"Point"}
}