{
  "type": "Feature",
  "properties": {
    "addr:full":"312 S Back River Rd Hampton VA 23669",
    "addr:housenumber":"312",
    "addr:postcode":"23669",
    "addr:street":"S Back River Rd",
    "iso:country":"US",
    "sg:address":"312 S Back River Rd",
    "sg:city":"Hampton",
    "sg:classifiers":[
        {
            "category":"Organizations",
            "subcategory":"Religious Organization",
            "type":"Services"
        }
    ],
    "sg:phone":"+1 757 726 2244",
    "sg:postcode":"23669",
    "sg:province":"VA",
    "sg:tags":[
        "church"
    ],
    "wof:name":"Living Tabernacle Church",
    "wof:placetype":"venue"
},
  "geometry": {"coordinates":[-76.356543,37.022484],"type":"Point"}
}