{
  "type": "Feature",
  "properties": {
    "iso:country":"US",
    "sg:address":"4727 Rippling Pond Dr",
    "sg:city":"Fairfax",
    "sg:classifiers":[
        {
            "category":"Professional",
            "subcategory":"Computer Services",
            "type":"Services"
        }
    ],
    "sg:phone":"+1 703 863 7215",
    "sg:postcode":"22033",
    "sg:province":"VA",
    "sg:tags":[
        "technical",
        "information"
    ],
    "wof:name":"Leena Technologies",
    "wof:placetype":"venue"
},
  "geometry": {"coordinates":[-77.40282500000001,38.861943],"type":"Point"}
}