{
  "type": "Feature",
  "properties": {
    "addr:full":"5637 Flagler Dr Centreville VA 20120",
    "addr:housenumber":"5637",
    "addr:postcode":"20120",
    "addr:street":"Flagler Dr",
    "iso:country":"US",
    "sg:address":"5637 Flagler Dr",
    "sg:city":"Centreville",
    "sg:classifiers":[
        {
            "category":"Organizations",
            "subcategory":"Religious Organization",
            "type":"Services"
        }
    ],
    "sg:phone":"+1 703 802 6444",
    "sg:postcode":"20120",
    "sg:province":"VA",
    "wof:name":"Pt Ministry Resources Inc",
    "wof:placetype":"venue"
},
  "geometry": {"coordinates":[-77.458614,38.854322],"type":"Point"}
}