{
  "type": "Feature",
  "properties": {
    "addr:full":"11921 Freedom Drive Two Fountain Square Suite 588 Reston VA 20190",
    "addr:housenumber":"11921;suite 588",
    "addr:postcode":"20190",
    "addr:street":"Freedom Drive Two",
    "iso:country":"US",
    "sg:address":"11921 Freedom Drive Two Fountain Square Suite 588",
    "sg:city":"Reston",
    "sg:classifiers":[
        {
            "category":"Professional",
            "subcategory":"Computer Services",
            "type":"Services"
        }
    ],
    "sg:phone":"+1 877 826 6427",
    "sg:postcode":"20190",
    "sg:province":"VA",
    "sg:tags":[
        "remote-support",
        "remote-control",
        "remote-access",
        "helpdesk",
        "remote-desktop-control",
        "service-desk"
    ],
    "sg:website":"http://www.bomgar.com/",
    "wof:name":"Bomgar",
    "wof:placetype":"venue"
},
  "geometry": {"coordinates":[-77.357596,38.959337],"type":"Point"}
}