{
  "type": "Feature",
  "properties": {
    "addr:full":"1320 N Veitch St Arlington VA 22201",
    "addr:housenumber":"1320",
    "addr:postcode":"22201",
    "addr:street":"N Veitch St",
    "iso:country":"US",
    "sg:address":"1320 N Veitch St",
    "sg:city":"Arlington",
    "sg:classifiers":[
        {
            "category":"Professional",
            "subcategory":"Business Services",
            "type":"Services"
        }
    ],
    "sg:phone":"+1 703 812 9081",
    "sg:postcode":"22201",
    "sg:province":"VA",
    "sg:tags":[
        "not",
        "classified",
        "elsewhere"
    ],
    "wof:name":"Bah-Sanchez Rougiata",
    "wof:placetype":"venue"
},
  "geometry": {"coordinates":[-77.08531600000001,38.889239],"type":"Point"}
}