{
  "type": "Feature",
  "properties": {
    "addr:full":"1412 Audmar Dr Mc Lean VA 22101",
    "addr:housenumber":"1412",
    "addr:postcode":"22101",
    "addr:street":"Audmar Dr",
    "iso:country":"US",
    "sg:address":"1412 Audmar Dr",
    "sg:city":"Mc Lean",
    "sg:classifiers":[
        {
            "category":"Building & Trades",
            "subcategory":"Equipment Rental",
            "type":"Services"
        }
    ],
    "sg:phone":"+1 703 862 6230",
    "sg:postcode":"22101",
    "sg:province":"VA",
    "wof:name":"Global Railroad Leasing LLC",
    "wof:placetype":"venue"
},
  "geometry": {"coordinates":[-77.18945100000001,38.932924],"type":"Point"}
}