{
  "type": "Feature",
  "properties": {
    "addr:full":"106 Westminster Dr Front Royal VA 22630",
    "addr:housenumber":"106",
    "addr:postcode":"22630",
    "addr:street":"Westminster Dr",
    "iso:country":"US",
    "sg:address":"106 Westminster Dr",
    "sg:city":"Front Royal",
    "sg:classifiers":[
        {
            "category":"Health Services",
            "subcategory":"Nursing And Care Facility",
            "type":"Services"
        }
    ],
    "sg:phone":"+1 540 631 0505",
    "sg:postcode":"22630",
    "sg:province":"VA",
    "wof:name":"Amerisist",
    "wof:placetype":"venue"
},
  "geometry": {"coordinates":[-78.16582099999999,38.914597],"type":"Point"}
}