{
  "type": "Feature",
  "properties": {
    "addr:full":"6070 Indian River Rd Virginia Beach VA 23464",
    "addr:housenumber":"6070",
    "addr:postcode":"23464",
    "addr:street":"Indian River Rd",
    "iso:country":"US",
    "sg:address":"6070 Indian River Rd",
    "sg:city":"Virginia Beach",
    "sg:classifiers":[
        {
            "category":"Retail",
            "subcategory":"Animal Services",
            "type":"Services"
        }
    ],
    "sg:phone":"+1 757 420 5009",
    "sg:postcode":"23464",
    "sg:province":"VA",
    "wof:name":"Grooming World",
    "wof:placetype":"venue"
},
  "geometry": {"coordinates":[-76.203709,36.811653],"type":"Point"}
}