{
  "type": "Feature",
  "properties": {
    "addr:full":"618 W 11th St Waynesboro VA 22980",
    "addr:housenumber":"618",
    "addr:postcode":"22980",
    "addr:street":"W 11Th St",
    "iso:country":"US",
    "sg:address":"618 W 11th St",
    "sg:city":"Waynesboro",
    "sg:classifiers":[
        {
            "category":"Health Services",
            "subcategory":"Chiropractor",
            "type":"Services"
        }
    ],
    "sg:phone":"+1 540 943 6036",
    "sg:postcode":"22980",
    "sg:province":"VA",
    "wof:name":"Dicicco Dr Jay",
    "wof:placetype":"venue"
},
  "geometry": {"coordinates":[-78.89197,38.066799],"type":"Point"}
}