{
  "type": "Feature",
  "properties": {
    "addr:full":"15469 Cagney Ct Woodbridge VA 22193",
    "addr:postcode":"15469;22193",
    "addr:street":"Cagney Ct",
    "iso:country":"US",
    "sg:address":"15469 Cagney Ct",
    "sg:city":"Woodbridge",
    "sg:classifiers":[
        {
            "category":"Professional",
            "type":"Services"
        }
    ],
    "sg:phone":"+1 703 897 6844",
    "sg:postcode":"22193",
    "sg:province":"VA",
    "wof:name":"Rm McGuire Designs",
    "wof:placetype":"venue"
},
  "geometry": {"coordinates":[-77.32314599999999,38.616925],"type":"Point"}
}