{
  "type": "Feature",
  "properties": {
    "addr:full":"700 Caramel St Virginia Beach VA 23457",
    "addr:housenumber":"700",
    "addr:postcode":"beach;23457",
    "addr:street":"Caramel St",
    "iso:country":"US",
    "sg:address":"700 Caramel St",
    "sg:city":"Virginia Beach",
    "sg:classifiers":[
        {
            "category":"Manufacturing",
            "subcategory":"Furniture",
            "type":"Manufacturing & Wholesale Goods"
        }
    ],
    "sg:phone":"+1 757 426 9522",
    "sg:postcode":"23457",
    "sg:province":"VA",
    "sg:tags":[
        "household",
        "mfg"
    ],
    "wof:name":"Thirteen Clnies Cbin Mkers LLC",
    "wof:placetype":"venue"
},
  "geometry": {"coordinates":[-76.04315,36.619172],"type":"Point"}
}