{
  "type": "Feature",
  "properties": {
    "iso:country":"US",
    "sg:address":"7800 Hayfield Rd",
    "sg:city":"Alexandria",
    "sg:classifiers":[
        {
            "category":"Professional",
            "subcategory":"Management & Consulting",
            "type":"Services"
        }
    ],
    "sg:phone":"+1 703 924 9737",
    "sg:postcode":"22315",
    "sg:province":"VA",
    "sg:tags":[
        "engineering",
        "computer"
    ],
    "wof:name":"Augmented Systems Inc",
    "wof:placetype":"venue"
},
  "geometry": {"coordinates":[-77.132604,38.745091],"type":"Point"}
}