{
  "type": "Feature",
  "properties": {
    "addr:full":"716 Dicks Hollow Rd Winchester VA 22603",
    "addr:housenumber":"716",
    "addr:postcode":"22603",
    "addr:street":"Dicks Hollow Rd",
    "iso:country":"US",
    "sg:address":"716 Dicks Hollow Rd",
    "sg:city":"Winchester",
    "sg:classifiers":[
        {
            "category":"Manufacturing",
            "subcategory":"Printing",
            "type":"Manufacturing & Wholesale Goods"
        }
    ],
    "sg:phone":"+1 540 877 1477",
    "sg:postcode":"22603",
    "sg:province":"VA",
    "sg:tags":[
        "publisher"
    ],
    "wof:name":"Technical Books-The Lay Person",
    "wof:placetype":"venue"
},
  "geometry": {"coordinates":[-78.241703,39.213608],"type":"Point"}
}