{
  "type": "Feature",
  "properties": {
    "iso:country":"US",
    "sg:address":"3706 Cook Blvd",
    "sg:city":"Chesapeake",
    "sg:classifiers":[
        {
            "category":"Manufacturing",
            "subcategory":"Wood Products",
            "type":"Manufacturing & Wholesale Goods"
        }
    ],
    "sg:phone":"+1 757 485 1123",
    "sg:postcode":"23323",
    "sg:province":"VA",
    "sg:tags":[
        "picture",
        "frame"
    ],
    "wof:name":"Frame & Art Wholesale Supply",
    "wof:placetype":"venue"
},
  "geometry": {"coordinates":[-76.384039,36.783191],"type":"Point"}
}