{
  "type": "Feature",
  "properties": {
    "iso:country":"US",
    "sg:address":"3557 Forestdale Ave",
    "sg:city":"Woodbridge",
    "sg:classifiers":[
        {
            "category":"Building & Trades",
            "subcategory":"Construction",
            "type":"Services"
        }
    ],
    "sg:phone":"+1 703 580 6869",
    "sg:postcode":"22193",
    "sg:province":"VA",
    "sg:tags":[
        "house"
    ],
    "wof:name":"Homecraft Inc",
    "wof:placetype":"venue"
},
  "geometry": {"coordinates":[-77.31809699999999,38.646552],"type":"Point"}
}