{
  "type": "Feature",
  "properties": {
    "addr:full":"7075 Balmoral Forest Rd Clifton VA 20124",
    "addr:housenumber":"7075",
    "addr:postcode":"20124",
    "addr:street":"Balmoral Forest Rd",
    "iso:country":"US",
    "sg:address":"7075 Balmoral Forest Rd",
    "sg:city":"Clifton",
    "sg:classifiers":[
        {
            "category":"Professional",
            "subcategory":"Business Services",
            "type":"Services"
        }
    ],
    "sg:phone":"+1 703 815 1650",
    "sg:postcode":"20124",
    "sg:province":"VA",
    "wof:name":"Bolzie Interiors",
    "wof:placetype":"venue"
},
  "geometry": {"coordinates":[-77.40747399999999,38.784276],"type":"Point"}
}