{
  "type": "Feature",
  "properties": {
    "iso:country":"US",
    "sg:address":"20336 River Ridge Ter",
    "sg:city":"Ashburn",
    "sg:classifiers":[
        {
            "category":"Professional",
            "subcategory":"Computer Services",
            "type":"Services"
        }
    ],
    "sg:phone":"+1 703 729 1941",
    "sg:postcode":"20147",
    "sg:province":"VA",
    "sg:tags":[
        "programing",
        "custom"
    ],
    "wof:name":"Harrington Software Assoc",
    "wof:placetype":"venue"
},
  "geometry": {"coordinates":[-77.436634,39.052263],"type":"Point"}
}