{
  "type": "Feature",
  "properties": {
    "iso:country":"US",
    "sg:address":"11073 Summer Breeze Dr",
    "sg:city":"Glen Allen",
    "sg:classifiers":[
        {
            "category":"Building & Trades",
            "subcategory":"Construction",
            "type":"Services"
        }
    ],
    "sg:phone":"+1 804 798 5103",
    "sg:postcode":"23059",
    "sg:province":"VA",
    "sg:tags":[
        "concrete",
        "contractor"
    ],
    "wof:name":"Ace Concrete Co",
    "wof:placetype":"venue"
},
  "geometry": {"coordinates":[-77.526083,37.704696],"type":"Point"}
}