{
  "type": "Feature",
  "properties": {
    "addr:full":"10501 Vermeer Pl Ashland VA 23005",
    "addr:housenumber":"10501",
    "addr:postcode":"23005",
    "addr:street":"Vermeer Pl",
    "iso:country":"US",
    "sg:address":"10501 Vermeer Pl",
    "sg:city":"Ashland",
    "sg:classifiers":[
        {
            "category":"Wholesale",
            "subcategory":"Machinery & Supplies",
            "type":"Manufacturing & Wholesale Goods"
        }
    ],
    "sg:phone":"+1 804 798 0321",
    "sg:postcode":"23005",
    "sg:province":"VA",
    "sg:tags":[
        "equipment",
        "excavating"
    ],
    "wof:name":"Vermeer Sales & Svc",
    "wof:placetype":"venue"
},
  "geometry": {"coordinates":[-77.470466,37.716153],"type":"Point"}
}