{
  "type": "Feature",
  "properties": {
    "addr:full":"944 S Wakefield St Arlington VA 22204",
    "addr:housenumber":"944",
    "addr:postcode":"22204",
    "addr:street":"S Wakefield St",
    "iso:country":"US",
    "sg:address":"944 S Wakefield St",
    "sg:city":"Arlington",
    "sg:classifiers":[
        {
            "category":"Autos & Motor Vehicles",
            "subcategory":"Automobile Sales",
            "type":"Retail Goods"
        }
    ],
    "sg:phone":"+1 703 271 0177",
    "sg:postcode":"22204",
    "sg:province":"VA",
    "sg:tags":[
        "limo"
    ],
    "wof:name":"Satellite Connection Inc",
    "wof:placetype":"venue"
},
  "geometry": {"coordinates":[-77.09699999999999,38.860001],"type":"Point"}
}