{
  "type": "Feature",
  "properties": {
    "addr:full":"10 Cheval Ct Sterling VA 20164",
    "addr:housenumber":"10",
    "addr:postcode":"20164",
    "addr:street":"Cheval Ct",
    "iso:country":"US",
    "sg:address":"10 Cheval Ct",
    "sg:city":"Sterling",
    "sg:classifiers":[
        {
            "category":"Building & Trades",
            "subcategory":"Construction",
            "type":"Services"
        }
    ],
    "sg:phone":"+1 703 444 2272",
    "sg:postcode":"20164",
    "sg:province":"VA",
    "sg:tags":[
        "remodeling",
        "contractor"
    ],
    "wof:name":"Casa Construction Inc",
    "wof:placetype":"venue"
},
  "geometry": {"coordinates":[-77.36613800000001,39.033919],"type":"Point"}
}