{
  "type": "Feature",
  "properties": {
    "iso:country":"US",
    "sg:address":"6110 Greenlawn Ct",
    "sg:city":"Springfield",
    "sg:classifiers":[
        {
            "category":"Government",
            "subcategory":"Office",
            "type":"Public Place"
        }
    ],
    "sg:phone":"+1 703 644 6221",
    "sg:postcode":"22152",
    "sg:province":"VA",
    "sg:tags":[
        "consultant",
        "national",
        "on",
        "security",
        "matter"
    ],
    "wof:name":"John A Shaud",
    "wof:placetype":"venue"
},
  "geometry": {"coordinates":[-77.216568,38.786065],"type":"Point"}
}