{
  "type": "Feature",
  "properties": {
    "iso:country":"US",
    "sg:address":"PO Box 271",
    "sg:city":"Alexandria",
    "sg:classifiers":[
        {
            "category":"Professional",
            "subcategory":"Computer Services",
            "type":"Services"
        }
    ],
    "sg:phone":"+1 202 657 5040",
    "sg:postcode":"22313 ",
    "sg:province":"VA",
    "sg:tags":[
        "online-registration",
        "e-ticketing",
        "event-planning",
        "events",
        "ticketing",
        "alexandria",
        "virginia"
    ],
    "sg:website":"http://www.SimpleTick.com",
    "wof:name":"SimpleTick",
    "wof:placetype":"venue"
},
  "geometry": {"coordinates":[-77.09005000000001,38.815762],"type":"Point"}
}