{
  "type": "Feature",
  "properties": {
    "addr:full":"12606 Saylers Creek Ln Herndon VA 20170",
    "addr:housenumber":"12606",
    "addr:postcode":"20170",
    "addr:street":"Saylers Creek Ln",
    "iso:country":"US",
    "sg:address":"12606 Saylers Creek Ln",
    "sg:city":"Herndon",
    "sg:classifiers":[
        {
            "category":"Professional",
            "subcategory":"Management & Consulting",
            "type":"Services"
        }
    ],
    "sg:phone":"+1 919 876 7594",
    "sg:postcode":"20170",
    "sg:province":"VA",
    "wof:name":"Eastern Electronics",
    "wof:placetype":"venue"
},
  "geometry": {"coordinates":[-77.385217,38.989467],"type":"Point"}
}