{
  "type": "Feature",
  "properties": {
    "addr:full":"40 Franklin Rd Newport News VA 23601",
    "addr:housenumber":"40",
    "addr:postcode":"23601",
    "addr:street":"Franklin Rd",
    "iso:country":"US",
    "sg:address":"40 Franklin Rd",
    "sg:city":"Newport News",
    "sg:classifiers":[
        {
            "category":"Building & Trades",
            "subcategory":"Cleaning & Sanitation",
            "type":"Services"
        }
    ],
    "sg:phone":"+1 757 595 9400",
    "sg:postcode":"23601",
    "sg:province":"VA",
    "sg:tags":[
        "house",
        "help",
        "maintenance",
        "supply"
    ],
    "wof:name":"Blue Chip Cleaning Service",
    "wof:placetype":"venue"
},
  "geometry": {"coordinates":[-76.455214,37.025416],"type":"Point"}
}