{
  "type": "Feature",
  "properties": {
    "addr:full":"401 Southlake Blvd Richmond VA 23236",
    "addr:housenumber":"401",
    "addr:postcode":"23236",
    "addr:street":"Southlake Blvd",
    "iso:country":"US",
    "sg:address":"401 Southlake Blvd",
    "sg:city":"Richmond",
    "sg:classifiers":[
        {
            "category":"Professional",
            "subcategory":"Computer Services",
            "type":"Services"
        }
    ],
    "sg:phone":"+1 804 897 0200",
    "sg:postcode":"23236",
    "sg:province":"VA",
    "sg:tags":[
        "both",
        "leasing",
        "purchase",
        "engaged",
        "sale",
        "new",
        "rental"
    ],
    "sg:website":"www.tlc96.com",
    "wof:name":"Technology Leasing Concepts",
    "wof:placetype":"venue"
},
  "geometry": {"coordinates":[-77.606537,37.49966],"type":"Point"}
}