{
  "type": "Feature",
  "properties": {
    "iso:country":"US",
    "sg:address":"4718 Carr Dr",
    "sg:city":"Fredericksburg",
    "sg:classifiers":[
        {
            "category":"Health Services",
            "subcategory":"Doctor",
            "type":"Services"
        }
    ],
    "sg:phone":"+1 540 891 8935",
    "sg:postcode":"22408",
    "sg:province":"VA",
    "sg:tags":[
        "physician",
        "surgeon"
    ],
    "wof:name":"Medical Collection Svc",
    "wof:placetype":"venue"
},
  "geometry": {"coordinates":[-77.49482,38.252926],"type":"Point"}
}