{
  "type": "Feature",
  "properties": {
    "addr:full":"6206 Belmont Rd Chesterfield VA 23832",
    "addr:housenumber":"6206",
    "addr:postcode":"23832",
    "addr:street":"Belmont Rd",
    "iso:country":"US",
    "sg:address":"6206 Belmont Rd",
    "sg:city":"Chesterfield",
    "sg:classifiers":[
        {
            "category":"Manufacturing",
            "subcategory":"Glass & Minerals",
            "type":"Manufacturing & Wholesale Goods"
        }
    ],
    "sg:phone":"+1 804 328 4896",
    "sg:postcode":"23832",
    "sg:province":"VA",
    "sg:tags":[
        "concrete",
        "mfg",
        "contractor"
    ],
    "wof:name":"Chimney Chap LLC",
    "wof:placetype":"venue"
},
  "geometry": {"coordinates":[-77.513017,37.453785],"type":"Point"}
}