{
  "type": "Feature",
  "properties": {
    "iso:country":"US",
    "sg:address":"2509 Winfred Rd",
    "sg:city":"Hayes",
    "sg:classifiers":[
        {
            "category":"Freight",
            "type":"Transportation"
        }
    ],
    "sg:phone":"+1 804 642 7513",
    "sg:postcode":"23072",
    "sg:province":"VA",
    "sg:tags":[
        "operator",
        "local",
        "trucking"
    ],
    "wof:name":"Jenkins Hauling",
    "wof:placetype":"venue"
},
  "geometry": {"coordinates":[-76.50808499999999,37.28173],"type":"Point"}
}