{
  "type": "Feature",
  "properties": {
    "addr:full":"4826 Ledura Rd Virginia Beach VA 23462",
    "addr:housenumber":"4826",
    "addr:postcode":"23462",
    "addr:street":"Ledura Rd",
    "iso:country":"US",
    "sg:address":"4826 Ledura Rd",
    "sg:city":"Virginia Beach",
    "sg:classifiers":[
        {
            "category":"Professional",
            "subcategory":"Detective & Security Services",
            "type":"Services"
        }
    ],
    "sg:phone":"+1 757 639 6111",
    "sg:postcode":"23462",
    "sg:province":"VA",
    "sg:tags":[
        "car"
    ],
    "wof:name":"Ellison Security Service",
    "wof:placetype":"venue"
},
  "geometry": {"coordinates":[-76.152905,36.829287],"type":"Point"}
}