{
  "type": "Feature",
  "properties": {
    "addr:full":"6421 Lignum St Springfield VA 22150",
    "addr:postcode":"6421;22150",
    "addr:street":"Lignum St",
    "iso:country":"US",
    "sg:address":"6421 Lignum St",
    "sg:city":"Springfield",
    "sg:classifiers":[
        {
            "category":"Building & Trades",
            "subcategory":"Cleaning & Sanitation",
            "type":"Services"
        }
    ],
    "sg:phone":"+1 703 924 4033",
    "sg:postcode":"22150",
    "sg:province":"VA",
    "sg:tags":[
        "maintenance"
    ],
    "wof:name":"Marlenys Cleaning & Maint",
    "wof:placetype":"venue"
},
  "geometry": {"coordinates":[-77.165772,38.770879],"type":"Point"}
}