{
  "type": "Feature",
  "properties": {
    "addr:full":"1035 Highlands Dr Charlottesville VA 22901",
    "addr:housenumber":"1035",
    "addr:postcode":"22901",
    "addr:street":"Highlands Dr",
    "iso:country":"US",
    "sg:address":"1035 Highlands Dr",
    "sg:city":"Charlottesville",
    "sg:classifiers":[
        {
            "category":"Professional",
            "subcategory":"Management & Consulting",
            "type":"Services"
        }
    ],
    "sg:phone":"+1 434 823 4454",
    "sg:postcode":"22901",
    "sg:province":"VA",
    "sg:tags":[
        "planner",
        "meeting"
    ],
    "wof:name":"Krista Weih",
    "wof:placetype":"venue"
},
  "geometry": {"coordinates":[-78.666096,38.065111],"type":"Point"}
}