{
  "type": "Feature",
  "properties": {
    "iso:country":"US",
    "sg:address":"1547 Laskin Rd",
    "sg:city":"Virginia Beach",
    "sg:classifiers":[
        {
            "category":"Shopping",
            "subcategory":"Optical Goods",
            "type":"Retail Goods"
        }
    ],
    "sg:phone":"+1 757 425 2293",
    "sg:postcode":"23451",
    "sg:province":"VA",
    "wof:name":"Gilbert Optical Eye Exam Dept",
    "wof:placetype":"venue"
},
  "geometry": {"coordinates":[-76.014849,36.851057],"type":"Point"}
}