{
  "type": "Feature",
  "properties": {
    "addr:full":"4821 1st St N Arlington VA 22203",
    "addr:housenumber":"4821",
    "addr:postcode":"22203",
    "addr:street":"1St St N",
    "iso:country":"US",
    "sg:address":"4821 1st St N",
    "sg:city":"Arlington",
    "sg:classifiers":[
        {
            "category":"Building & Trades",
            "subcategory":"Locksmith",
            "type":"Services"
        }
    ],
    "sg:phone":"+1 703 652 9082",
    "sg:postcode":"22203",
    "sg:province":"VA",
    "sg:tags":[
        "key"
    ],
    "wof:name":"Lock and Locksmith Twenty Four",
    "wof:placetype":"venue"
},
  "geometry": {"coordinates":[-77.116831,38.867533],"type":"Point"}
}