{
  "type": "Feature",
  "properties": {
    "addr:full":"4016 Plank Rd Fredericksburg VA 22407",
    "addr:housenumber":"4016",
    "addr:postcode":"22407",
    "addr:street":"Plank Rd",
    "iso:country":"US",
    "sg:address":"4016 Plank Rd",
    "sg:city":"Fredericksburg",
    "sg:classifiers":[
        {
            "category":"Insurance",
            "subcategory":"Insurance Agent",
            "type":"Services"
        }
    ],
    "sg:phone":"+1 540 898 2183",
    "sg:postcode":"22407",
    "sg:province":"VA",
    "sg:website":"www.vafb.com",
    "wof:name":"Farm Bureau Insurance",
    "wof:placetype":"venue"
},
  "geometry": {"coordinates":[-77.529307,38.289951],"type":"Point"}
}