{
  "type": "Feature",
  "properties": {
    "iso:country":"US",
    "sg:address":"813 Forrest Dr",
    "sg:city":"Newport News",
    "sg:classifiers":[
        {
            "category":"Organizations",
            "subcategory":"Professional Association",
            "type":"Services"
        }
    ],
    "sg:phone":"+1 757 595 9802",
    "sg:postcode":"23606",
    "sg:province":"VA",
    "sg:tags":[
        "business"
    ],
    "wof:name":"Girl Scouts Clnl Coast Council",
    "wof:placetype":"venue"
},
  "geometry": {"coordinates":[-76.46990099999999,37.076853],"type":"Point"}
}