{
  "type": "Feature",
  "properties": {
    "iso:country":"US",
    "sg:address":"844 J Clyde Morris Blvd",
    "sg:city":"Newport News",
    "sg:classifiers":[
        {
            "category":"Shopping",
            "subcategory":"Computers & Home Electronics",
            "type":"Retail Goods"
        }
    ],
    "sg:phone":"+1 757 595 5151",
    "sg:postcode":"23601",
    "sg:province":"VA",
    "sg:tags":[
        "equipment",
        "electronic",
        "supply"
    ],
    "wof:name":"Radio Shack",
    "wof:placetype":"venue"
},
  "geometry": {"coordinates":[-76.45887399999999,37.086036],"type":"Point"}
}