{
  "type": "Feature",
  "properties": {
    "addr:full":"11000 Hull Street Rd Midlothian VA 23112",
    "addr:housenumber":"11000",
    "addr:postcode":"23112",
    "addr:street":"Hull Street Rd",
    "iso:country":"US",
    "sg:address":"11000 Hull Street Rd",
    "sg:city":"Midlothian",
    "sg:classifiers":[
        {
            "category":"Organizations",
            "subcategory":"Religious Organization",
            "type":"Services"
        }
    ],
    "sg:phone":"+1 804 674 0222",
    "sg:postcode":"23112",
    "sg:province":"VA",
    "sg:tags":[
        "church"
    ],
    "wof:name":"First Commonwealth Church",
    "wof:placetype":"venue"
},
  "geometry": {"coordinates":[-77.597345,37.438631],"type":"Point"}
}