{
  "type": "Feature",
  "properties": {
    "iso:country":"US",
    "sg:address":"7556 Gardner Park Dr",
    "sg:city":"Gainesville",
    "sg:classifiers":[
        {
            "category":"Shopping",
            "subcategory":"Hobbies, Toys, & Games",
            "type":"Retail Goods"
        },
        {
            "category":"Shopping",
            "subcategory":"Books",
            "type":"Retail Goods"
        }
    ],
    "sg:phone":"+1 571 248 6722",
    "sg:postcode":"20155",
    "sg:province":"VA",
    "sg:tags":[
        "shop",
        "mags",
        "books",
        "video",
        "hobby",
        "music"
    ],
    "sg:website":"www.comics-gaming.com",
    "wof:name":"Comics and Gaming",
    "wof:placetype":"venue"
},
  "geometry": {"coordinates":[-77.62111,38.794483],"type":"Point"}
}