{
  "type": "Feature",
  "properties": {
    "iso:country":"US",
    "sg:address":"908 E Little Creek Rd",
    "sg:city":"Norfolk",
    "sg:classifiers":[
        {
            "category":"Retail",
            "subcategory":"Car Wash",
            "type":"Services"
        }
    ],
    "sg:phone":"+1 757 587 5892",
    "sg:postcode":"23518",
    "sg:province":"VA",
    "sg:tags":[
        "carwash"
    ],
    "wof:name":"SSS Car Wash",
    "wof:placetype":"venue"
},
  "geometry": {"coordinates":[-76.245395,36.914992],"type":"Point"}
}