{
  "type": "Feature",
  "properties": {
    "iso:country":"US",
    "sg:address":"6902 Leeds Manor Rd",
    "sg:city":"Orlean",
    "sg:classifiers":[
        {
            "category":"Home & Garden",
            "subcategory":"Garden Supply",
            "type":"Retail Goods"
        }
    ],
    "sg:phone":"+1 540 364 7664",
    "sg:postcode":"20115",
    "sg:province":"VA",
    "sg:tags":[
        "center"
    ],
    "wof:name":"Village Green",
    "wof:placetype":"venue"
},
  "geometry": {"coordinates":[-77.962808,38.750671],"type":"Point"}
}