{
  "type": "Feature",
  "properties": {
    "iso:country":"US",
    "sg:address":"1916 Valley Wood Rd",
    "sg:city":"Mc Lean",
    "sg:classifiers":[
        {
            "category":"Professional",
            "subcategory":"Management & Consulting",
            "type":"Services"
        }
    ],
    "sg:phone":"+1 703 237 1128",
    "sg:postcode":"22101",
    "sg:province":"VA",
    "sg:tags":[
        "business"
    ],
    "wof:name":"Seale & Associates LLC",
    "wof:placetype":"venue"
},
  "geometry": {"coordinates":[-77.14975200000001,38.913868],"type":"Point"}
}