{
  "type": "Feature",
  "properties": {
    "addr:full":"2888 Colonial Trl E Surry VA 23883",
    "addr:housenumber":"2888",
    "addr:postcode":"23883",
    "addr:street":"Colonial Trl E Surry",
    "iso:country":"US",
    "sg:address":"2888 Colonial Trl E",
    "sg:city":"Surry",
    "sg:classifiers":[
        {
            "category":"Organizations",
            "subcategory":"Religious Organization",
            "type":"Services"
        },
        {
            "category":"Social Services",
            "type":"Services"
        }
    ],
    "sg:phone":"+1 757 294 3213",
    "sg:postcode":"23883",
    "sg:province":"VA",
    "sg:tags":[
        "church"
    ],
    "wof:name":"Watson Work Life & Family Life",
    "wof:placetype":"venue"
},
  "geometry": {"coordinates":[-76.79254400000001,37.117779],"type":"Point"}
}