{
  "type": "Feature",
  "properties": {
    "iso:country":"US",
    "sg:address":"11313 Winston Pl",
    "sg:city":"Newport News",
    "sg:classifiers":[
        {
            "category":"Professional",
            "subcategory":"Accounting & Tax Preparation",
            "type":"Services"
        }
    ],
    "sg:phone":"+1 757 240 4025",
    "sg:postcode":"23601",
    "sg:province":"VA",
    "sg:tags":[
        "civil",
        "engineering",
        "datum",
        "statistical",
        "analysis"
    ],
    "wof:name":"Research Avenues",
    "wof:placetype":"venue"
},
  "geometry": {"coordinates":[-76.47093,37.067177],"type":"Point"}
}