{
  "type": "Feature",
  "properties": {
    "addr:full":"381 Fairfax Pike Stephens City VA 22655",
    "addr:housenumber":"381",
    "addr:postcode":"22655",
    "addr:street":"Fairfax Pike",
    "iso:country":"US",
    "sg:address":"381 Fairfax Pike",
    "sg:city":"Stephens City",
    "sg:classifiers":[
        {
            "category":"Food & Beverages",
            "subcategory":"Groceries & Convenience Stores",
            "type":"Retail Goods"
        },
        {
            "category":"Restaurant",
            "type":"Food & Drink"
        }
    ],
    "sg:phone":"+1 540 869 2414",
    "sg:postcode":"22655",
    "sg:province":"VA",
    "sg:tags":[
        "out"
    ],
    "wof:name":"C B's Corner Store & Deli",
    "wof:placetype":"venue"
},
  "geometry": {"coordinates":[-78.204016,39.080871],"type":"Point"}
}