{
  "type": "Feature",
  "properties": {
    "iso:country":"US",
    "sg:address":"409 S Main St",
    "sg:city":"Emporia",
    "sg:classifiers":[
        {
            "category":"Shopping",
            "type":"Retail Goods"
        }
    ],
    "sg:phone":"+1 434 634 5850",
    "sg:postcode":"23847",
    "sg:province":"VA",
    "sg:tags":[
        "cosmetic",
        "perfume"
    ],
    "wof:name":"G & A Salon Svc",
    "wof:placetype":"venue"
},
  "geometry": {"coordinates":[-77.542829,36.68575],"type":"Point"}
}