{
  "type": "Feature",
  "properties": {
    "iso:country":"US",
    "sg:address":"256 W Morgan Ave",
    "sg:city":"Pennington Gap",
    "sg:classifiers":[
        {
            "category":"Shopping",
            "subcategory":"Computers & Home Electronics",
            "type":"Retail Goods"
        }
    ],
    "sg:phone":"+1 276 546 4020",
    "sg:postcode":"24277",
    "sg:province":"VA",
    "sg:tags":[
        "related"
    ],
    "wof:name":"G BS Computer Sales & Service",
    "wof:placetype":"venue"
},
  "geometry": {"coordinates":[-83.029658,36.757231],"type":"Point"}
}