{
  "type": "Feature",
  "properties": {
    "addr:full":"1115 Indiana St Salem VA 24153",
    "addr:housenumber":"1115",
    "addr:postcode":"24153",
    "addr:street":"Indiana St",
    "iso:country":"US",
    "sg:address":"1115 Indiana St",
    "sg:city":"Salem",
    "sg:classifiers":[
        {
            "category":"Freight",
            "type":"Transportation"
        }
    ],
    "sg:phone":"+1 540 375 8831",
    "sg:postcode":"24153",
    "sg:province":"VA",
    "wof:name":"D & L Transportation",
    "wof:placetype":"venue"
},
  "geometry": {"coordinates":[-80.045875,37.280622],"type":"Point"}
}