{
  "type": "Feature",
  "properties": {
    "iso:country":"US",
    "sg:address":"2601 Columbia Pike",
    "sg:city":"Arlington",
    "sg:classifiers":[
        {
            "category":"Shopping",
            "subcategory":"Pharmacy",
            "type":"Retail Goods"
        }
    ],
    "sg:phone":"+1 703 271 7910",
    "sg:postcode":"22204",
    "sg:province":"VA",
    "sg:tags":[
        "drugstore"
    ],
    "sg:website":"www.cvs.com",
    "wof:name":"Cvs Pharmacy",
    "wof:placetype":"venue"
},
  "geometry": {"coordinates":[-77.08519699999999,38.8629],"type":"Point"}
}