{
  "type": "Feature",
  "properties": {
    "addr:full":"6966 Wellington Rd Manassas VA 20109",
    "addr:housenumber":"6966",
    "addr:postcode":"20109",
    "addr:street":"Wellington Rd",
    "iso:country":"US",
    "sg:address":"6966 Wellington Rd",
    "sg:city":"Manassas",
    "sg:classifiers":[
        {
            "category":"Wholesale",
            "subcategory":"Construction Materials",
            "type":"Manufacturing & Wholesale Goods"
        }
    ],
    "sg:phone":"+1 703 335 5700",
    "sg:postcode":"20109",
    "sg:province":"VA",
    "sg:tags":[
        "hardware",
        "lumber"
    ],
    "wof:name":"American Bldrs & Contrs Sup Co",
    "wof:placetype":"venue"
},
  "geometry": {"coordinates":[-77.560149,38.781764],"type":"Point"}
}