{
  "type": "Feature",
  "properties": {
    "iso:country":"US",
    "sg:address":"8990 Fern Park Dr",
    "sg:city":"Burke",
    "sg:classifiers":[
        {
            "category":"Professional",
            "subcategory":"Management & Consulting",
            "type":"Services"
        }
    ],
    "sg:phone":"+1 703 890 0465",
    "sg:postcode":"22015",
    "sg:province":"VA",
    "sg:tags":[
        "marketing",
        "program"
    ],
    "wof:name":"JBJ Enterprises",
    "wof:placetype":"venue"
},
  "geometry": {"coordinates":[-77.256485,38.809617],"type":"Point"}
}