{
  "type": "Feature",
  "properties": {
    "addr:full":"3100 Main St Exmore VA 23350",
    "addr:housenumber":"3100",
    "addr:postcode":"23350",
    "addr:street":"Main St",
    "iso:country":"US",
    "sg:address":"3100 Main St",
    "sg:city":"Exmore",
    "sg:classifiers":[
        {
            "category":"Social Services",
            "type":"Services"
        }
    ],
    "sg:phone":"+1 757 414 0310",
    "sg:postcode":"23350",
    "sg:province":"VA",
    "wof:name":"Center For Life Changes Inc",
    "wof:placetype":"venue"
},
  "geometry": {"coordinates":[-75.82365299999999,37.536393],"type":"Point"}
}