{
  "type": "Feature",
  "properties": {
    "addr:full":"300 Dupont St West Point VA 23181",
    "addr:housenumber":"300",
    "addr:postcode":"23181",
    "addr:street":"Dupont St",
    "iso:country":"US",
    "sg:address":"300 Dupont St",
    "sg:city":"West Point",
    "sg:classifiers":[
        {
            "category":"Manufacturing",
            "subcategory":"Chemicals & Compounds",
            "type":"Manufacturing & Wholesale Goods"
        }
    ],
    "sg:phone":"+1 804 843 4873",
    "sg:postcode":"23181",
    "sg:province":"VA",
    "sg:tags":[
        "gas"
    ],
    "wof:name":"M G Industries",
    "wof:placetype":"venue"
},
  "geometry": {"coordinates":[-76.80645800000001,37.545665],"type":"Point"}
}