{
  "type": "Feature",
  "properties": {
    "iso:country":"US",
    "sg:address":"11260 Roger Bacon Dr",
    "sg:city":"Reston",
    "sg:classifiers":[
        {
            "category":"Professional",
            "subcategory":"Computer Services",
            "type":"Services"
        }
    ],
    "sg:phone":"+1 703 709 9210",
    "sg:postcode":"20190",
    "sg:province":"VA",
    "sg:tags":[
        "consultant",
        "designer"
    ],
    "sg:website":"www.extent.com",
    "wof:name":"Emergent Technologies",
    "wof:placetype":"venue"
},
  "geometry": {"coordinates":[-77.334698,38.951497],"type":"Point"}
}