{
  "type": "Feature",
  "properties": {
    "addr:full":"9001 Graves Rd Petersburg VA 23803",
    "addr:housenumber":"9001",
    "addr:postcode":"23803",
    "addr:street":"Graves Rd",
    "iso:country":"US",
    "sg:address":"9001 Graves Rd",
    "sg:city":"Petersburg",
    "sg:classifiers":[
        {
            "category":"Shopping",
            "subcategory":"Hobbies, Toys, & Games",
            "type":"Retail Goods"
        }
    ],
    "sg:phone":"+1 804 590 9123",
    "sg:postcode":"23803",
    "sg:province":"VA",
    "wof:name":"Creekwood Baskets & Gifts",
    "wof:placetype":"venue"
},
  "geometry": {"coordinates":[-77.533744,37.261807],"type":"Point"}
}