{
  "type": "Feature",
  "properties": {
    "iso:country":"US",
    "sg:address":"812 Moorefield Park Dr",
    "sg:city":"Richmond",
    "sg:classifiers":[
        {
            "category":"Professional",
            "subcategory":"Lawyer & Legal Services",
            "type":"Services"
        }
    ],
    "sg:phone":"+1 804 330 7755",
    "sg:postcode":"23236",
    "sg:province":"VA",
    "sg:tags":[
        "attorney"
    ],
    "wof:name":"William R Deeley II",
    "wof:placetype":"venue"
},
  "geometry": {"coordinates":[-77.579798,37.499431],"type":"Point"}
}