{
  "type": "Feature",
  "properties": {
    "addr:full":"206 Berkshire Rd Richmond VA 23221",
    "addr:housenumber":"206",
    "addr:postcode":"23221",
    "addr:street":"Berkshire Rd",
    "iso:country":"US",
    "sg:address":"206 Berkshire Rd",
    "sg:city":"Richmond",
    "sg:classifiers":[
        {
            "category":"Professional",
            "subcategory":"Management & Consulting",
            "type":"Services"
        }
    ],
    "sg:phone":"+1 804 355 0405",
    "sg:postcode":"23221",
    "sg:province":"VA",
    "wof:name":"Consolidated Amalgamated LLC",
    "wof:placetype":"venue"
},
  "geometry": {"coordinates":[-77.50414499999999,37.555801],"type":"Point"}
}