{
  "type": "Feature",
  "properties": {
    "addr:full":"28082 Raccoon Ford Rd Culpeper VA 22701",
    "addr:postcode":"28082;22701",
    "addr:street":"Raccoon Ford Rd",
    "iso:country":"US",
    "sg:address":"28082 Raccoon Ford Rd",
    "sg:city":"Culpeper",
    "sg:classifiers":[
        {
            "category":"Organizations",
            "subcategory":"Religious Organization",
            "type":"Services"
        }
    ],
    "sg:phone":"+1 540 854 7346",
    "sg:postcode":"22701",
    "sg:province":"VA",
    "sg:tags":[
        "church"
    ],
    "wof:name":"Mount Pisgah Baptist Church",
    "wof:placetype":"venue"
},
  "geometry": {"coordinates":[-77.88715999999999,38.348337],"type":"Point"}
}