{
  "type": "Feature",
  "properties": {
    "iso:country":"US",
    "sg:address":"14379 Saguaro Pl",
    "sg:city":"Centreville",
    "sg:classifiers":[
        {
            "category":"Building & Trades",
            "subcategory":"Construction",
            "type":"Services"
        }
    ],
    "sg:phone":"+1 703 266 5901",
    "sg:postcode":"20121",
    "sg:province":"VA",
    "sg:tags":[
        "contractor"
    ],
    "wof:name":"Deavers Tile Co",
    "wof:placetype":"venue"
},
  "geometry": {"coordinates":[-77.44332199999999,38.836653],"type":"Point"}
}