{
  "type": "Feature",
  "properties": {
    "iso:country":"US",
    "sg:address":"1230 Forbes St",
    "sg:city":"Fredericksburg",
    "sg:classifiers":[
        {
            "category":"Education",
            "subcategory":"Vocational School",
            "type":"Public Place"
        }
    ],
    "sg:phone":"+1 540 373 5303",
    "sg:postcode":"22405",
    "sg:province":"VA",
    "sg:tags":[
        "processing",
        "datum"
    ],
    "wof:name":"Rkb Enterprises",
    "wof:placetype":"venue"
},
  "geometry": {"coordinates":[-77.45406699999999,38.342251],"type":"Point"}
}