{
  "type": "Feature",
  "properties": {
    "addr:full":"5765 Burke Centre Pkwy Burke VA 22015",
    "addr:housenumber":"5765",
    "addr:postcode":"22015",
    "addr:street":"Burke Centre Pkwy",
    "iso:country":"US",
    "sg:address":"5765 Burke Centre Pkwy",
    "sg:city":"Burke",
    "sg:classifiers":[
        {
            "category":"Professional",
            "subcategory":"Business Services",
            "type":"Services"
        },
        {
            "category":"Professional",
            "subcategory":"Advertising",
            "type":"Services"
        }
    ],
    "sg:phone":"+1 703 425 0500",
    "sg:postcode":"22015",
    "sg:province":"VA",
    "sg:tags":[
        "mailing",
        "shipping"
    ],
    "wof:name":"UPS Stores",
    "wof:placetype":"venue"
},
  "geometry": {"coordinates":[-77.31965,38.798548],"type":"Point"}
}