{
  "type": "Feature",
  "properties": {
    "addr:full":"500 Woodlake Dr Chesapeake VA 23320",
    "addr:housenumber":"500",
    "addr:postcode":"23320",
    "addr:street":"Woodlake Dr",
    "iso:country":"US",
    "sg:address":"500 Woodlake Dr",
    "sg:city":"Chesapeake",
    "sg:classifiers":[
        {
            "category":"Professional",
            "subcategory":"Computer Services",
            "type":"Services"
        }
    ],
    "sg:phone":"+1 757 523 7200",
    "sg:postcode":"23320",
    "sg:province":"VA",
    "sg:tags":[
        "prepackaged",
        "design",
        "system",
        "software"
    ],
    "wof:name":"VSE Corporation",
    "wof:placetype":"venue"
},
  "geometry": {"coordinates":[-76.247328,36.783696],"type":"Point"}
}