{
  "type": "Feature",
  "properties": {
    "addr:full":"4265 Americana Dr Annandale VA 22003",
    "addr:housenumber":"4265",
    "addr:postcode":"22003",
    "addr:street":"Americana Dr",
    "iso:country":"US",
    "sg:address":"4265 Americana Dr",
    "sg:city":"Annandale",
    "sg:classifiers":[
        {
            "category":"Building & Trades",
            "subcategory":"Construction",
            "type":"Services"
        }
    ],
    "sg:phone":"+1 703 750 5443",
    "sg:postcode":"22003",
    "sg:province":"VA",
    "sg:tags":[
        "hanging",
        "painter",
        "contractor"
    ],
    "wof:name":"Christo Painting",
    "wof:placetype":"venue"
},
  "geometry": {"coordinates":[-77.21714900000001,38.832073],"type":"Point"}
}