{
  "type": "Feature",
  "properties": {
    "addr:full":"1001 Tazewell Ave North Tazewell VA 24630",
    "addr:housenumber":"1001",
    "addr:postcode":"24630",
    "addr:street":"Tazewell Ave North",
    "iso:country":"US",
    "sg:address":"1001 Tazewell Ave",
    "sg:city":"North Tazewell",
    "sg:classifiers":[
        {
            "category":"Shopping",
            "subcategory":"Books",
            "type":"Retail Goods"
        }
    ],
    "sg:phone":"+1 276 979 0660",
    "sg:postcode":"24630",
    "sg:province":"VA",
    "wof:name":"Promise Land Bookstore",
    "wof:placetype":"venue"
},
  "geometry": {"coordinates":[-81.526687,37.132059],"type":"Point"}
}