{
  "type": "Feature",
  "properties": {
    "iso:country":"US",
    "sg:address":"6303 Little River Tpke",
    "sg:city":"Alexandria",
    "sg:classifiers":[
        {
            "category":"Retail",
            "subcategory":"Auto Rental",
            "type":"Services"
        }
    ],
    "sg:phone":"+1 703 256 4600",
    "sg:postcode":"22312",
    "sg:province":"VA",
    "sg:tags":[
        "car",
        "leasing"
    ],
    "sg:website":"www.enterprise.com",
    "wof:name":"Enterprise Rent-A-Car",
    "wof:placetype":"venue"
},
  "geometry": {"coordinates":[-77.144335,38.81863],"type":"Point"}
}