{
  "type": "Feature",
  "properties": {
    "addr:full":"1231 Alverser Dr Midlothian VA 23113",
    "addr:housenumber":"1231",
    "addr:postcode":"23113",
    "addr:street":"Alverser Dr",
    "iso:country":"US",
    "sg:address":"1231 Alverser Dr",
    "sg:city":"Midlothian",
    "sg:classifiers":[
        {
            "category":"Health Services",
            "subcategory":"Doctor",
            "type":"Services"
        }
    ],
    "sg:phone":"+1 804 794 2299",
    "sg:postcode":"23113",
    "sg:province":"VA",
    "sg:tags":[
        "medical"
    ],
    "wof:name":"Cullen Elizabeth M Dr",
    "wof:placetype":"venue"
},
  "geometry": {"coordinates":[-77.616789,37.508129],"type":"Point"}
}