{
  "type": "Feature",
  "properties": {
    "iso:country":"US",
    "sg:address":"212 Lambert Dr",
    "sg:city":"Manassas",
    "sg:classifiers":[
        {
            "category":"Building & Trades",
            "subcategory":"Construction",
            "type":"Services"
        }
    ],
    "sg:phone":"+1 703 499 6251",
    "sg:postcode":"20111",
    "sg:province":"VA",
    "sg:tags":[
        "contractor"
    ],
    "wof:name":"Riverbend Contracting",
    "wof:placetype":"venue"
},
  "geometry": {"coordinates":[-77.469987,38.787009],"type":"Point"}
}