{
  "type": "Feature",
  "properties": {
    "iso:country":"US",
    "sg:address":"1089 Pensive Ln",
    "sg:city":"Great Falls",
    "sg:classifiers":[
        {
            "category":"Professional",
            "subcategory":"Management & Consulting",
            "type":"Services"
        }
    ],
    "sg:phone":"+1 703 759 5120",
    "sg:postcode":"22066",
    "sg:province":"VA",
    "sg:tags":[
        "counselor",
        "public",
        "relations"
    ],
    "wof:name":"Barksdale Ballard & Co",
    "wof:placetype":"venue"
},
  "geometry": {"coordinates":[-77.30197,38.985239],"type":"Point"}
}