{
  "type": "Feature",
  "properties": {
    "addr:full":"9504 Yardarm Ln Burke VA 22015",
    "addr:housenumber":"9504",
    "addr:postcode":"22015",
    "addr:street":"Yardarm Ln",
    "iso:country":"US",
    "sg:address":"9504 Yardarm Ln",
    "sg:city":"Burke",
    "sg:classifiers":[
        {
            "category":"Professional",
            "subcategory":"Business Services",
            "type":"Services"
        }
    ],
    "sg:phone":"+1 703 451 3036",
    "sg:postcode":"22015",
    "sg:province":"VA",
    "wof:name":"D & A Associates LLC",
    "wof:placetype":"venue"
},
  "geometry": {"coordinates":[-77.275133,38.754999],"type":"Point"}
}