{
  "type": "Feature",
  "properties": {
    "addr:full":"92 Bull Pine Rd Afton VA 22920",
    "addr:housenumber":"92",
    "addr:postcode":"22920",
    "addr:street":"Bull Pine Rd",
    "iso:country":"US",
    "sg:address":"92 Bull Pine Rd",
    "sg:city":"Afton",
    "sg:classifiers":[
        {
            "category":"Wholesale",
            "subcategory":"Plants",
            "type":"Manufacturing & Wholesale Goods"
        }
    ],
    "sg:phone":"+1 540 456 6554",
    "sg:postcode":"22920",
    "sg:province":"VA",
    "sg:tags":[
        "nursery"
    ],
    "wof:name":"Speak To Cheryl",
    "wof:placetype":"venue"
},
  "geometry": {"coordinates":[-78.84641999999999,37.992213],"type":"Point"}
}