{
  "type": "Feature",
  "properties": {
    "iso:country":"US",
    "sg:address":"601 Merrimac Rd",
    "sg:city":"Blacksburg",
    "sg:classifiers":[
        {
            "category":"Manufacturing",
            "subcategory":"Textiles",
            "type":"Manufacturing & Wholesale Goods"
        }
    ],
    "sg:phone":"+1 540 961 1731",
    "sg:postcode":"24060",
    "sg:province":"VA",
    "sg:tags":[
        "sewing",
        "contractor"
    ],
    "wof:name":"Nannys Sewing & Alteration",
    "wof:placetype":"venue"
},
  "geometry": {"coordinates":[-80.42396100000001,37.186479],"type":"Point"}
}