{
  "type": "Feature",
  "properties": {
    "addr:full":"5819 High Bluff Ct Burke VA 22015",
    "addr:housenumber":"5819",
    "addr:postcode":"22015",
    "addr:street":"High Bluff Ct",
    "iso:country":"US",
    "sg:address":"5819 High Bluff Ct",
    "sg:city":"Burke",
    "sg:classifiers":[
        {
            "category":"Professional",
            "subcategory":"Management & Consulting",
            "type":"Services"
        }
    ],
    "sg:phone":"+1 703 250 0506",
    "sg:postcode":"22015",
    "sg:province":"VA",
    "sg:tags":[
        "consultant",
        "develops",
        "computer",
        "system",
        "software"
    ],
    "wof:name":"Groupware Technologies Inc",
    "wof:placetype":"venue"
},
  "geometry": {"coordinates":[-77.283345,38.793692],"type":"Point"}
}