{
  "type": "Feature",
  "properties": {
    "iso:country":"US",
    "sg:address":"2336 N Wolfsnare Dr",
    "sg:city":"Virginia Beach",
    "sg:classifiers":[
        {
            "category":"Professional",
            "type":"Services"
        }
    ],
    "sg:phone":"+1 757 481 6492",
    "sg:postcode":"23454",
    "sg:province":"VA",
    "wof:name":"Norman & Kathryn Blinn",
    "wof:placetype":"venue"
},
  "geometry": {"coordinates":[-76.050952,36.859677],"type":"Point"}
}