{
  "type": "Feature",
  "properties": {
    "iso:country":"US",
    "sg:address":"101 S Whiting St # 402",
    "sg:city":"Alexandria",
    "sg:classifiers":[
        {
            "category":"Retail",
            "subcategory":"Auto Rental",
            "type":"Services"
        }
    ],
    "sg:phone":"+1 571 238 0261",
    "sg:postcode":"22304",
    "sg:province":"VA",
    "sg:tags":[
        "limousine"
    ],
    "wof:name":"Covenant Limo Svc",
    "wof:placetype":"venue"
},
  "geometry": {"coordinates":[-77.137191,38.813171],"type":"Point"}
}