{
  "type": "Feature",
  "properties": {
    "addr:full":"10565 Moncure Dr Ruther Glen VA 22546",
    "addr:housenumber":"10565",
    "addr:postcode":"22546",
    "addr:street":"Moncure Dr",
    "iso:country":"US",
    "sg:address":"10565 Moncure Dr",
    "sg:city":"Ruther Glen",
    "sg:classifiers":[
        {
            "category":"Retail",
            "subcategory":"Repair Shop",
            "type":"Services"
        }
    ],
    "sg:phone":"+1 804 448 2114",
    "sg:postcode":"22546",
    "sg:province":"VA",
    "sg:tags":[
        "building",
        "maintenance"
    ],
    "wof:name":"Wsw Services",
    "wof:placetype":"venue"
},
  "geometry": {"coordinates":[-77.458513,37.957627],"type":"Point"}
}