{
  "type": "Feature",
  "properties": {
    "addr:full":"2314 Franklin Ave Colonial Heights VA 23834",
    "addr:housenumber":"2314",
    "addr:postcode":"23834",
    "addr:street":"Franklin Ave",
    "iso:country":"US",
    "sg:address":"2314 Franklin Ave",
    "sg:city":"Colonial Heights",
    "sg:classifiers":[
        {
            "category":"Wholesale",
            "subcategory":"Machinery & Supplies",
            "type":"Manufacturing & Wholesale Goods"
        }
    ],
    "sg:phone":"+1 804 520 9173",
    "sg:postcode":"23834",
    "sg:province":"VA",
    "sg:tags":[
        "gage"
    ],
    "wof:name":"Old Dominion Industrial Inc",
    "wof:placetype":"venue"
},
  "geometry": {"coordinates":[-77.41298399999999,37.26163],"type":"Point"}
}