{
  "type": "Feature",
  "properties": {
    "iso:country":"US",
    "sg:address":"1245 Cedar Rd",
    "sg:city":"Chesapeake",
    "sg:classifiers":[
        {
            "category":"Professional",
            "type":"Services"
        }
    ],
    "sg:phone":"+1 757 548 7100",
    "sg:postcode":"23322",
    "sg:province":"VA",
    "sg:tags":[
        "establishment"
    ],
    "wof:name":"Kaboom Kollectibles",
    "wof:placetype":"venue"
},
  "geometry": {"coordinates":[-76.284161,36.716799],"type":"Point"}
}