{
  "type": "Feature",
  "properties": {
    "iso:country":"US",
    "sg:address":"3929 Old Lee Hwy",
    "sg:city":"Fairfax",
    "sg:classifiers":[
        {
            "category":"Organizations",
            "subcategory":"Professional Association",
            "type":"Services"
        }
    ],
    "sg:phone":"+1 703 691 3357",
    "sg:postcode":"22030",
    "sg:province":"VA",
    "sg:website":"www.simhq.org",
    "wof:name":"Society For Ind Microbiology",
    "wof:placetype":"venue"
},
  "geometry": {"coordinates":[-77.302024,38.847548],"type":"Point"}
}