{
  "type": "Feature",
  "properties": {
    "addr:full":"901 N Stuart St Ste 210 Arlington VA 22203",
    "addr:housenumber":"901",
    "addr:postcode":"22203",
    "addr:street":"N Stuart St Ste 210",
    "iso:country":"US",
    "sg:address":"901 N Stuart St Ste 210",
    "sg:city":"Arlington",
    "sg:classifiers":[
        {
            "category":"Health Services",
            "subcategory":"Optometrist",
            "type":"Services"
        }
    ],
    "sg:phone":"+1 703 525 7477",
    "sg:postcode":"22203",
    "sg:province":"VA",
    "wof:name":"Fredirick Siegal, Md",
    "wof:placetype":"venue"
},
  "geometry": {"coordinates":[-77.111649,38.88105],"type":"Point"}
}