{
  "type": "Feature",
  "properties": {
    "iso:country":"US",
    "sg:address":"614 Kenmore Ave",
    "sg:city":"Fredericksburg",
    "sg:classifiers":[
        {
            "category":"Wholesale",
            "subcategory":"Machinery & Supplies",
            "type":"Manufacturing & Wholesale Goods"
        }
    ],
    "sg:phone":"+1 540 371 6500",
    "sg:postcode":"22401",
    "sg:province":"VA",
    "sg:tags":[
        "equipment",
        "ride",
        "park",
        "amusement"
    ],
    "wof:name":"Mid-Atlantic Vending",
    "wof:placetype":"venue"
},
  "geometry": {"coordinates":[-77.462374,38.298337],"type":"Point"}
}