{
  "type": "Feature",
  "properties": {
    "addr:full":"6899 Virginia Ave Pembroke VA 24136",
    "addr:housenumber":"6899",
    "addr:postcode":"24136",
    "addr:street":"Virginia Ave",
    "iso:country":"US",
    "sg:address":"6899 Virginia Ave",
    "sg:city":"Pembroke",
    "sg:classifiers":[
        {
            "category":"Education",
            "subcategory":"School",
            "type":"Public Place"
        }
    ],
    "sg:phone":"+1 540 626 7281",
    "sg:postcode":"24136",
    "sg:province":"VA",
    "wof:name":"Eastern Elementary School",
    "wof:placetype":"venue"
},
  "geometry": {"coordinates":[-80.581677,37.312304],"type":"Point"}
}