{
  "type": "Feature",
  "properties": {
    "addr:full":"12411 Reed Grass Ln Midlothian VA 23114",
    "addr:housenumber":"12411",
    "addr:postcode":"23114",
    "addr:street":"Reed Grass Ln",
    "iso:country":"US",
    "sg:address":"12411 Reed Grass Ln",
    "sg:city":"Midlothian",
    "sg:classifiers":[
        {
            "category":"Professional",
            "subcategory":"Advertising",
            "type":"Services"
        }
    ],
    "sg:phone":"+1 804 794 5019",
    "sg:postcode":"23114",
    "sg:province":"VA",
    "sg:tags":[
        "agency"
    ],
    "wof:name":"McGraw Lauren Creative Svcs",
    "wof:placetype":"venue"
},
  "geometry": {"coordinates":[-77.631597,37.469942],"type":"Point"}
}