{
  "type": "Feature",
  "properties": {
    "addr:full":"289 US Hwy 360 Danville VA 24540",
    "addr:housenumber":"289",
    "addr:postcode":"24540",
    "addr:street":"Us Hwy 360",
    "iso:country":"US",
    "sg:address":"289 US Hwy 360",
    "sg:city":"Danville",
    "sg:classifiers":[
        {
            "category":"Wholesale",
            "subcategory":"Machinery & Supplies",
            "type":"Manufacturing & Wholesale Goods"
        }
    ],
    "sg:phone":"+1 434 793 4851",
    "sg:postcode":"24540",
    "sg:province":"VA",
    "sg:tags":[
        "industrial",
        "mfg"
    ],
    "wof:name":"Ace Machine Inc",
    "wof:placetype":"venue"
},
  "geometry": {"coordinates":[-79.382732,36.588927],"type":"Point"}
}