{
  "type": "Feature",
  "properties": {
    "iso:country":"US",
    "sg:address":"200 Snead Fairway",
    "sg:city":"Portsmouth",
    "sg:classifiers":[
        {
            "category":"Professional",
            "subcategory":"Lawyer & Legal Services",
            "type":"Services"
        }
    ],
    "sg:phone":"+1 757 393 0087",
    "sg:postcode":"23701",
    "sg:province":"VA",
    "sg:tags":[
        "attorney"
    ],
    "wof:name":"Richard D Mattox",
    "wof:placetype":"venue"
},
  "geometry": {"coordinates":[-76.39166299999999,36.812579],"type":"Point"}
}