{
  "type": "Feature",
  "properties": {
    "addr:full":"1805 S Oakland St Arlington VA 22204",
    "addr:housenumber":"1805",
    "addr:postcode":"22204",
    "addr:street":"S Oakland St",
    "iso:country":"US",
    "sg:address":"1805 S Oakland St",
    "sg:city":"Arlington",
    "sg:classifiers":[
        {
            "category":"Professional",
            "type":"Services"
        }
    ],
    "sg:phone":"+1 703 892 0551",
    "sg:postcode":"22204",
    "sg:province":"VA",
    "sg:tags":[
        "establishment"
    ],
    "wof:name":"Rogers & Rogers",
    "wof:placetype":"venue"
},
  "geometry": {"coordinates":[-77.092675,38.851919],"type":"Point"}
}