{
  "type": "Feature",
  "properties": {
    "addr:full":"4483 James Madison Pkwy King George VA 22485",
    "addr:housenumber":"4483",
    "addr:postcode":"22485",
    "addr:street":"James Madison Pkwy",
    "iso:country":"US",
    "sg:address":"4483 James Madison Pkwy",
    "sg:city":"King George",
    "sg:classifiers":[
        {
            "category":"Health Services",
            "subcategory":"Chiropractor",
            "type":"Services"
        }
    ],
    "sg:phone":"+1 540 644 1119",
    "sg:postcode":"22485",
    "sg:province":"VA",
    "wof:name":"Dahlgren Chiropractic Clinic",
    "wof:placetype":"venue"
},
  "geometry": {"coordinates":[-77.05041199999999,38.351526],"type":"Point"}
}