{
  "type": "Feature",
  "properties": {
    "addr:full":"722 Grant St Ste A Herndon VA 20170",
    "addr:housenumber":"722",
    "addr:postcode":"20170",
    "addr:street":"Grant St Ste A",
    "iso:country":"US",
    "sg:address":"722 Grant St Ste A",
    "sg:city":"Herndon",
    "sg:classifiers":[
        {
            "category":"Health Services",
            "subcategory":"Doctor",
            "type":"Services"
        }
    ],
    "sg:phone":"+1 703 573 7200",
    "sg:postcode":"20170",
    "sg:province":"VA",
    "sg:tags":[
        "medicine",
        "physician",
        "practice",
        "surgeons",
        "family"
    ],
    "wof:name":"My Family Doctor",
    "wof:placetype":"venue"
},
  "geometry": {"coordinates":[-77.37928100000001,38.9691],"type":"Point"}
}