{
  "type": "Feature",
  "properties": {
    "addr:full":"15813 Donald Curtis Dr Woodbridge VA 22191",
    "addr:housenumber":"15813",
    "addr:postcode":"22191",
    "addr:street":"Donald Curtis Dr",
    "iso:country":"US",
    "sg:address":"15813 Donald Curtis Dr",
    "sg:city":"Woodbridge",
    "sg:classifiers":[
        {
            "category":"Banks & Credit Unions",
            "subcategory":"Investment Brokerage",
            "type":"Services"
        }
    ],
    "sg:phone":"+1 703 730 6070",
    "sg:postcode":"22191",
    "sg:province":"VA",
    "sg:tags":[
        "advisory",
        "financial"
    ],
    "wof:name":"CEI & Commodities Svc",
    "wof:placetype":"venue"
},
  "geometry": {"coordinates":[-77.30026700000001,38.607424],"type":"Point"}
}