{
  "type": "Feature",
  "properties": {
    "addr:full":"94 Campbell Ave SW Bassett VA 24016",
    "addr:housenumber":"94",
    "addr:postcode":"24016",
    "addr:street":"Campbell Ave Sw",
    "iso:country":"US",
    "sg:address":"94 Campbell Ave SW",
    "sg:city":"Bassett",
    "sg:classifiers":[
        {
            "category":"Freight",
            "type":"Transportation"
        }
    ],
    "sg:phone":"+1 276 629 3236",
    "sg:postcode":"24016",
    "sg:province":"VA",
    "sg:tags":[
        "operator",
        "trucking"
    ],
    "wof:name":"Adams Bus Service",
    "wof:placetype":"venue"
},
  "geometry": {"coordinates":[-79.940963,37.271752],"type":"Point"}
}