{
  "type": "Feature",
  "properties": {
    "addr:full":"7950 Jones Branch Dr McLean VA 22107",
    "addr:housenumber":"7950",
    "addr:postcode":"22107",
    "addr:street":"Jones Branch Dr",
    "iso:country":"US",
    "sg:address":"7950 Jones Branch Dr",
    "sg:city":"McLean",
    "sg:classifiers":[
        {
            "category":"Communications",
            "subcategory":"Newspaper",
            "type":"Services"
        }
    ],
    "sg:phone":"+1 800 872 0001",
    "sg:postcode":"22107",
    "sg:province":"VA",
    "sg:tags":[
        "print",
        "medium"
    ],
    "sg:website":"www.usatoday.com",
    "wof:name":"USA Today",
    "wof:placetype":"venue"
},
  "geometry": {"coordinates":[-77.21658499999999,38.929289],"type":"Point"}
}