{
  "type": "Feature",
  "properties": {
    "addr:full":"501 Blount Point Rd Newport News VA 23606",
    "addr:housenumber":"501",
    "addr:postcode":"23606",
    "addr:street":"Blount Point Rd",
    "iso:country":"US",
    "sg:address":"501 Blount Point Rd",
    "sg:city":"Newport News",
    "sg:classifiers":[
        {
            "category":"Education",
            "subcategory":"School",
            "type":"Public Place"
        }
    ],
    "sg:phone":"+1 757 591 4766",
    "sg:postcode":"23606",
    "sg:province":"VA",
    "sg:tags":[
        "executive"
    ],
    "sg:website":"www.nn.k12.va.us",
    "wof:name":"Hidenwood Elementary School",
    "wof:placetype":"venue"
},
  "geometry": {"coordinates":[-76.51320200000001,37.064054],"type":"Point"}
}