{
  "type": "Feature",
  "properties": {
    "addr:full":"1259 E Main St Salem VA 24153",
    "addr:housenumber":"1259",
    "addr:postcode":"24153",
    "addr:street":"E Main St",
    "iso:country":"US",
    "sg:address":"1259 E Main St",
    "sg:city":"Salem",
    "sg:classifiers":[
        {
            "category":"Autos & Motor Vehicles",
            "subcategory":"Automobile Sales",
            "type":"Retail Goods"
        }
    ],
    "sg:phone":"+1 540 387 0202",
    "sg:postcode":"24153",
    "sg:province":"VA",
    "sg:tags":[
        "new",
        "car"
    ],
    "sg:website":"http://www.dodge.com/hostc/fad/findDealers.do",
    "wof:name":"Dominion Car Company",
    "wof:placetype":"venue"
},
  "geometry": {"coordinates":[-80.036411,37.297073],"type":"Point"}
}