{
  "type": "Feature",
  "properties": {
    "addr:full":"1047 Clement Town Rd Powhatan VA 23139",
    "addr:housenumber":"1047",
    "addr:postcode":"23139",
    "addr:street":"Clement Town Rd",
    "iso:country":"US",
    "sg:address":"1047 Clement Town Rd",
    "sg:city":"Powhatan",
    "sg:classifiers":[
        {
            "category":"Building & Trades",
            "subcategory":"Construction",
            "type":"Services"
        }
    ],
    "sg:phone":"+1 804 492 3114",
    "sg:postcode":"23139",
    "sg:province":"VA",
    "sg:tags":[
        "contractor"
    ],
    "wof:name":"Powhatan Gutter Co",
    "wof:placetype":"venue"
},
  "geometry": {"coordinates":[-78.09568400000001,37.47407],"type":"Point"}
}