{
  "type": "Feature",
  "properties": {
    "addr:full":"2020 14th St N Arlington VA 22201",
    "addr:housenumber":"2020",
    "addr:postcode":"22201",
    "addr:street":"14Th St N",
    "iso:country":"US",
    "sg:address":"2020 14th St N",
    "sg:city":"Arlington",
    "sg:classifiers":[
        {
            "category":"Professional",
            "subcategory":"Engineering",
            "type":"Services"
        },
        {
            "category":"Professional",
            "subcategory":"Computer Services",
            "type":"Services"
        }
    ],
    "sg:phone":"+1 614 558 5287",
    "sg:postcode":"22201",
    "sg:province":"VA",
    "sg:tags":[
        "engineer",
        "consultant",
        "designer",
        "system",
        "integration"
    ],
    "wof:name":"Data Current",
    "wof:placetype":"venue"
},
  "geometry": {"coordinates":[-77.08289600000001,38.889667],"type":"Point"}
}