{
  "type": "Feature",
  "properties": {
    "addr:full":"118 S West St Culpeper VA 22701",
    "addr:housenumber":"118",
    "addr:postcode":"west;22701",
    "addr:street":"S;St",
    "iso:country":"US",
    "sg:address":"118 S West St",
    "sg:city":"Culpeper",
    "sg:classifiers":[
        {
            "category":"Professional",
            "subcategory":"Accounting & Tax Preparation",
            "type":"Services"
        }
    ],
    "sg:phone":"+1 540 825 2771",
    "sg:postcode":"22701",
    "sg:province":"VA",
    "wof:name":"Dan G Hazel CPA",
    "wof:placetype":"venue"
},
  "geometry": {"coordinates":[-77.99776300000001,38.473599],"type":"Point"}
}