{
  "type": "Feature",
  "properties": {
    "addr:full":"2214 Wilson Blvd Winchester VA 22601",
    "addr:housenumber":"2214",
    "addr:postcode":"22601",
    "addr:street":"Wilson Blvd",
    "iso:country":"US",
    "sg:address":"2214 Wilson Blvd",
    "sg:city":"Winchester",
    "sg:classifiers":[
        {
            "category":"Sports & Exercise",
            "subcategory":"Gym",
            "type":"Entertainment"
        }
    ],
    "sg:phone":"+1 540 678 5500",
    "sg:postcode":"22601",
    "sg:province":"VA",
    "sg:tags":[
        "center",
        "fitness"
    ],
    "wof:name":"Curves For Women",
    "wof:placetype":"venue"
},
  "geometry": {"coordinates":[-78.178641,39.161021],"type":"Point"}
}