{
  "type": "Feature",
  "properties": {
    "addr:full":"466 Wind Mill Point Rd Hampton VA 23664",
    "addr:housenumber":"466",
    "addr:postcode":"23664",
    "addr:street":"Wind Mill Point Rd",
    "iso:country":"US",
    "sg:address":"466 Wind Mill Point Rd",
    "sg:city":"Hampton",
    "sg:classifiers":[
        {
            "category":"Professional",
            "subcategory":"Business Services",
            "type":"Services"
        }
    ],
    "sg:phone":"+1 757 851 0414",
    "sg:postcode":"23664",
    "sg:province":"VA",
    "sg:tags":[
        "broker"
    ],
    "wof:name":"Dominion Brokerage LLC",
    "wof:placetype":"venue"
},
  "geometry": {"coordinates":[-76.306104,37.092877],"type":"Point"}
}