{
  "type": "Feature",
  "properties": {
    "iso:country":"US",
    "sg:address":"12600 Jefferson Ave",
    "sg:city":"Newport News",
    "sg:classifiers":[
        {
            "category":"Freight",
            "type":"Transportation"
        }
    ],
    "sg:phone":"+1 757 874 2929",
    "sg:postcode":"23602",
    "sg:province":"VA",
    "sg:tags":[
        "commercial",
        "storage"
    ],
    "wof:name":"Public Storage",
    "wof:placetype":"venue"
},
  "geometry": {"coordinates":[-76.51470399999999,37.131875],"type":"Point"}
}