{
  "type": "Feature",
  "properties": {
    "addr:full":"1112 Memorial Blvd S Martinsville VA 24112",
    "addr:housenumber":"1112",
    "addr:postcode":"24112",
    "addr:street":"Memorial Blvd S Martinsville",
    "iso:country":"US",
    "sg:address":"1112 Memorial Blvd S",
    "sg:city":"Martinsville",
    "sg:classifiers":[
        {
            "category":"Retail",
            "subcategory":"Repair Shop",
            "type":"Services"
        }
    ],
    "sg:phone":"+1 276 638 4011",
    "sg:postcode":"24112",
    "sg:province":"VA",
    "sg:tags":[
        "upholsterer"
    ],
    "wof:name":"Roger's Quality Upholstery",
    "wof:placetype":"venue"
},
  "geometry": {"coordinates":[-79.876242,36.675627],"type":"Point"}
}