{
  "type": "Feature",
  "properties": {
    "addr:full":"19860 Main St Buchanan VA 24066",
    "addr:housenumber":"19860",
    "addr:postcode":"24066",
    "addr:street":"Main St",
    "iso:country":"US",
    "sg:address":"19860 Main St",
    "sg:city":"Buchanan",
    "sg:classifiers":[
        {
            "category":"Personal",
            "subcategory":"Barber",
            "type":"Services"
        }
    ],
    "sg:phone":"+1 540 254 2878",
    "sg:postcode":"24066",
    "sg:province":"VA",
    "sg:tags":[
        "shop"
    ],
    "wof:name":"J Jordan's Barber Shop",
    "wof:placetype":"venue"
},
  "geometry": {"coordinates":[-79.679569,37.527884],"type":"Point"}
}