{
  "type": "Feature",
  "properties": {
    "addr:full":"4957 Warwick Ct Prince George VA 23875",
    "addr:housenumber":"4957",
    "addr:postcode":"23875",
    "addr:street":"Warwick Ct",
    "iso:country":"US",
    "sg:address":"4957 Warwick Ct",
    "sg:city":"Prince George",
    "sg:classifiers":[
        {
            "category":"Building & Trades",
            "subcategory":"Plumbing",
            "type":"Services"
        }
    ],
    "sg:phone":"+1 804 458 6711",
    "sg:postcode":"23875",
    "sg:province":"VA",
    "sg:tags":[
        "contractor"
    ],
    "wof:name":"JC Plumbing Sewer Servic",
    "wof:placetype":"venue"
},
  "geometry": {"coordinates":[-77.28796199999999,37.247562],"type":"Point"}
}