{
  "type": "Feature",
  "properties": {
    "iso:country":"US",
    "sg:address":"142 N Wayne Ave",
    "sg:city":"Waynesboro",
    "sg:classifiers":[
        {
            "category":"Personal",
            "subcategory":"Beauty Salon",
            "type":"Services"
        }
    ],
    "sg:phone":"+1 540 941 3505",
    "sg:postcode":"22980",
    "sg:province":"VA",
    "wof:name":"Green's Beauty & Barber Supls",
    "wof:placetype":"venue"
},
  "geometry": {"coordinates":[-78.889318,38.069218],"type":"Point"}
}