{
  "type": "Feature",
  "properties": {
    "iso:country":"US",
    "sg:address":"107 Hailsham Pl",
    "sg:city":"Yorktown",
    "sg:classifiers":[
        {
            "category":"Building & Trades",
            "subcategory":"Construction",
            "type":"Services"
        }
    ],
    "sg:phone":"+1 757 898 1147",
    "sg:postcode":"23692",
    "sg:province":"VA",
    "sg:tags":[
        "heavy"
    ],
    "wof:name":"Guinsler Enterprises",
    "wof:placetype":"venue"
},
  "geometry": {"coordinates":[-76.44394,37.165356],"type":"Point"}
}