{
  "type": "Feature",
  "properties": {
    "iso:country":"US",
    "sg:address":"1008 White Pl SW",
    "sg:city":"Leesburg",
    "sg:classifiers":[
        {
            "category":"Professional",
            "type":"Services"
        }
    ],
    "sg:phone":"+1 703 779 0219",
    "sg:postcode":"20175",
    "sg:province":"VA",
    "wof:name":"Word For Word",
    "wof:placetype":"venue"
},
  "geometry": {"coordinates":[-77.580674,39.098405],"type":"Point"}
}