{
  "type": "Feature",
  "properties": {
    "addr:full":"8402 Tidewater Dr Norfolk VA 23518",
    "addr:housenumber":"8402",
    "addr:postcode":"23518",
    "addr:street":"Tidewater Dr",
    "iso:country":"US",
    "sg:address":"8402 Tidewater Dr",
    "sg:city":"Norfolk",
    "sg:classifiers":[
        {
            "category":"Restaurant",
            "type":"Food & Drink"
        }
    ],
    "sg:phone":"+1 757 588 5675",
    "sg:postcode":"23518",
    "sg:province":"VA",
    "wof:name":"Mc Donald's",
    "wof:placetype":"venue"
},
  "geometry": {"coordinates":[-76.25248499999999,36.92598],"type":"Point"}
}