{
  "type": "Feature",
  "properties": {
    "addr:full":"4870 Sadler Rd Glen Allen VA 23060",
    "addr:housenumber":"4870",
    "addr:postcode":"23060",
    "addr:street":"Sadler Rd",
    "iso:country":"US",
    "sg:address":"4870 Sadler Rd",
    "sg:city":"Glen Allen",
    "sg:classifiers":[
        {
            "category":"Real Estate",
            "subcategory":"Real Estate Operator",
            "type":"Services"
        }
    ],
    "sg:phone":"+1 804 935 6004",
    "sg:postcode":"23060",
    "sg:province":"VA",
    "sg:tags":[
        "building",
        "nonresidential"
    ],
    "wof:name":"Overlook 1 Office Park",
    "wof:placetype":"venue"
},
  "geometry": {"coordinates":[-77.578638,37.666101],"type":"Point"}
}