{
  "type": "Feature",
  "properties": {
    "addr:full":"129 Harvest Cir Williamsburg VA 23185",
    "addr:housenumber":"129",
    "addr:postcode":"23185",
    "addr:street":"Harvest Cir",
    "iso:country":"US",
    "sg:address":"129 Harvest Cir",
    "sg:city":"Williamsburg",
    "sg:classifiers":[
        {
            "category":"Professional",
            "type":"Services"
        }
    ],
    "sg:phone":"+1 757 253 0733",
    "sg:postcode":"23185",
    "sg:province":"VA",
    "wof:name":"L J Rae Inc",
    "wof:placetype":"venue"
},
  "geometry": {"coordinates":[-76.75487099999999,37.2418],"type":"Point"}
}