{
  "type": "Feature",
  "properties": {
    "addr:full":"2022 Opitz Blvd Woodbridge VA 22191",
    "addr:postcode":"2022;22191",
    "addr:street":"Opitz Blvd",
    "iso:country":"US",
    "sg:address":"2022 Opitz Blvd",
    "sg:city":"Woodbridge",
    "sg:classifiers":[
        {
            "category":"Professional",
            "subcategory":"Employment Agencies",
            "type":"Services"
        }
    ],
    "sg:phone":"+1 703 490 4622",
    "sg:postcode":"22191",
    "sg:province":"VA",
    "sg:tags":[
        "help",
        "supply"
    ],
    "wof:name":"Enployment Enterprises",
    "wof:placetype":"venue"
},
  "geometry": {"coordinates":[-77.275429,38.6341],"type":"Point"}
}