{
  "type": "Feature",
  "properties": {
    "addr:full":"535 Westfield Rd Ste 100 Charlottesville VA 22901",
    "addr:housenumber":"535",
    "addr:postcode":"22901",
    "addr:street":"Westfield Rd Ste 100",
    "iso:country":"US",
    "sg:address":"535 Westfield Rd Ste 100",
    "sg:city":"Charlottesville",
    "sg:classifiers":[
        {
            "category":"Health Services",
            "subcategory":"Doctor",
            "type":"Services"
        }
    ],
    "sg:phone":"+1 434 973 4040",
    "sg:postcode":"22901",
    "sg:province":"VA",
    "sg:tags":[
        "practice",
        "family"
    ],
    "wof:name":"Brown David W MD",
    "wof:placetype":"venue"
},
  "geometry": {"coordinates":[-78.482399,38.070801],"type":"Point"}
}