{
  "type": "Feature",
  "properties": {
    "addr:full":"308 N Magnolia Ave Waynesboro VA 22980",
    "addr:housenumber":"308",
    "addr:postcode":"22980",
    "addr:street":"N Magnolia Ave",
    "iso:country":"US",
    "sg:address":"308 N Magnolia Ave",
    "sg:city":"Waynesboro",
    "sg:classifiers":[
        {
            "category":"Shopping",
            "subcategory":"Bicycles & Sporting Goods",
            "type":"Retail Goods"
        }
    ],
    "sg:phone":"+1 540 256 1594",
    "sg:postcode":"22980",
    "sg:province":"VA",
    "sg:tags":[
        "gun",
        "gunsmith"
    ],
    "wof:name":"Outback Gun & Machine Works",
    "wof:placetype":"venue"
},
  "geometry": {"coordinates":[-78.898309,38.074897],"type":"Point"}
}