{
  "type": "Feature",
  "properties": {
    "addr:full":"742 15th St S Arlington VA 22202",
    "addr:housenumber":"742",
    "addr:postcode":"22202",
    "addr:street":"15Th St S",
    "iso:country":"US",
    "sg:address":"742 15th St S",
    "sg:city":"Arlington",
    "sg:classifiers":[
        {
            "category":"Shopping",
            "subcategory":"Gifts & Souvenirs",
            "type":"Retail Goods"
        }
    ],
    "sg:phone":"+1 703 271 0921",
    "sg:postcode":"22202",
    "sg:province":"VA",
    "wof:name":"European Curio Corp",
    "wof:placetype":"venue"
},
  "geometry": {"coordinates":[-77.057233,38.859675],"type":"Point"}
}