{
  "type": "Feature",
  "properties": {
    "iso:country":"US",
    "sg:address":"2350 Starfish Rd",
    "sg:city":"Virginia Beach",
    "sg:classifiers":[
        {
            "category":"Recreation",
            "type":"Entertainment"
        }
    ],
    "sg:phone":"+1 757 481 7071",
    "sg:postcode":"23451",
    "sg:province":"VA",
    "sg:tags":[
        "pier",
        "fishing"
    ],
    "wof:name":"Lynnhaven Inlet Fishing Pier",
    "wof:placetype":"venue"
},
  "geometry": {"coordinates":[-76.077567,36.910444],"type":"Point"}
}