{
  "type": "Feature",
  "properties": {
    "addr:full":"7076 Lee Hwy Fairlawn VA 24141",
    "addr:housenumber":"7076",
    "addr:postcode":"24141",
    "addr:street":"Lee Hwy",
    "iso:country":"US",
    "sg:address":"7076 Lee Hwy",
    "sg:city":"Fairlawn",
    "sg:classifiers":[
        {
            "category":"Personal",
            "subcategory":"Beauty Salon",
            "type":"Services"
        }
    ],
    "sg:phone":"+1 540 639 0432",
    "sg:postcode":"24141",
    "sg:province":"VA",
    "sg:tags":[
        "shop",
        "health"
    ],
    "wof:name":"Intouch Salon & Body Clinic",
    "wof:placetype":"venue"
},
  "geometry": {"coordinates":[-80.60360799999999,37.142677],"type":"Point"}
}