{
  "type": "Feature",
  "properties": {
    "addr:full":"595 N 8th St Wytheville VA 24382",
    "addr:housenumber":"595",
    "addr:postcode":"24382",
    "addr:street":"N 8Th St",
    "iso:country":"US",
    "sg:address":"595 N 8th St",
    "sg:city":"Wytheville",
    "sg:classifiers":[
        {
            "category":"Building & Trades",
            "subcategory":"Construction",
            "type":"Services"
        }
    ],
    "sg:phone":"+1 276 620 5950",
    "sg:postcode":"24382",
    "sg:province":"VA",
    "sg:tags":[
        "roofing",
        "contractor"
    ],
    "wof:name":"A-1 Quality Construction",
    "wof:placetype":"venue"
},
  "geometry": {"coordinates":[-81.09130999999999,36.95035],"type":"Point"}
}