{
  "type": "Feature",
  "properties": {
    "addr:full":"3800 Ivanhoe Ln Alexandria VA 22310",
    "addr:housenumber":"3800",
    "addr:postcode":"22310",
    "addr:street":"Ivanhoe Ln",
    "iso:country":"US",
    "sg:address":"3800 Ivanhoe Ln",
    "sg:city":"Alexandria",
    "sg:classifiers":[
        {
            "category":"Communications",
            "subcategory":"Film & Video Production",
            "type":"Services"
        }
    ],
    "sg:phone":"+1 703 960 0039",
    "sg:postcode":"22310",
    "sg:province":"VA",
    "sg:tags":[
        "motion"
    ],
    "wof:name":"Lynn Kessler Productions",
    "wof:placetype":"venue"
},
  "geometry": {"coordinates":[-77.097019,38.788171],"type":"Point"}
}