{
  "type": "Feature",
  "properties": {
    "iso:country":"US",
    "sg:address":"4905 Ridgewood Rd",
    "sg:city":"Alexandria",
    "sg:classifiers":[
        {
            "category":"Shopping",
            "subcategory":"Bicycles & Sporting Goods",
            "type":"Retail Goods"
        }
    ],
    "sg:phone":"+1 703 642 8557",
    "sg:postcode":"22312",
    "sg:province":"VA",
    "wof:name":"Virginia Archery & Rifle",
    "wof:placetype":"venue"
},
  "geometry": {"coordinates":[-77.167142,38.814528],"type":"Point"}
}