{
  "type": "Feature",
  "properties": {
    "addr:full":"413 Moorland Dr Virginia Beach VA 23452",
    "addr:housenumber":"413",
    "addr:postcode":"23452",
    "addr:street":"Moorland Dr",
    "iso:country":"US",
    "sg:address":"413 Moorland Dr",
    "sg:city":"Virginia Beach",
    "sg:classifiers":[
        {
            "category":"Building & Trades",
            "subcategory":"Construction",
            "type":"Services"
        }
    ],
    "sg:phone":"+1 757 431 4445",
    "sg:postcode":"23452",
    "sg:province":"VA",
    "sg:tags":[
        "trim",
        "installation",
        "work",
        "window",
        "contractor",
        "siding",
        "vinyl",
        "door"
    ],
    "wof:name":"Discount Window & Siding Sales",
    "wof:placetype":"venue"
},
  "geometry": {"coordinates":[-76.101814,36.843998],"type":"Point"}
}