{
  "type": "Feature",
  "properties": {
    "addr:full":"3774 Sherwood Pl Newport News VA 23602",
    "addr:housenumber":"3774",
    "addr:postcode":"23602",
    "addr:street":"Sherwood Pl",
    "iso:country":"US",
    "sg:address":"3774 Sherwood Pl",
    "sg:city":"Newport News",
    "sg:classifiers":[
        {
            "category":"Communications",
            "subcategory":"Film & Video Production",
            "type":"Services"
        }
    ],
    "sg:phone":"+1 757 833 6927",
    "sg:postcode":"23602",
    "sg:province":"VA",
    "sg:tags":[
        "motion"
    ],
    "wof:name":"Get Loose Crew Production",
    "wof:placetype":"venue"
},
  "geometry": {"coordinates":[-76.52914,37.123132],"type":"Point"}
}