{
  "type": "Feature",
  "properties": {
    "addr:full":"1263 Lake Taylor Dr Norfolk VA 23502",
    "addr:housenumber":"1263",
    "addr:postcode":"23502",
    "addr:street":"Lake Taylor Dr",
    "iso:country":"US",
    "sg:address":"1263 Lake Taylor Dr",
    "sg:city":"Norfolk",
    "sg:classifiers":[
        {
            "category":"Building & Trades",
            "subcategory":"Construction",
            "type":"Services"
        }
    ],
    "sg:phone":"+1 757 461 6147",
    "sg:postcode":"23502",
    "sg:province":"VA",
    "sg:tags":[
        "hanging",
        "contractor"
    ],
    "wof:name":"Schlatres Painting",
    "wof:placetype":"venue"
},
  "geometry": {"coordinates":[-76.194373,36.863483],"type":"Point"}
}