{
  "type": "Feature",
  "properties": {
    "addr:full":"1702 Monticello Ave Chesapeake VA 23324",
    "addr:housenumber":"1702",
    "addr:postcode":"23324",
    "addr:street":"Monticello Ave",
    "iso:country":"US",
    "sg:address":"1702 Monticello Ave",
    "sg:city":"Chesapeake",
    "sg:classifiers":[
        {
            "category":"Building & Trades",
            "subcategory":"Construction",
            "type":"Services"
        }
    ],
    "sg:phone":"+1 757 545 8540",
    "sg:postcode":"23324",
    "sg:province":"VA",
    "sg:tags":[
        "paving",
        "contractor"
    ],
    "wof:name":"Collins Asphalt Paving",
    "wof:placetype":"venue"
},
  "geometry": {"coordinates":[-76.278109,36.80767],"type":"Point"}
}