{
  "type": "Feature",
  "properties": {
    "iso:country":"US",
    "sg:address":"13205 Pressmont Ln",
    "sg:city":"Fairfax",
    "sg:classifiers":[
        {
            "category":"Restaurant",
            "type":"Food & Drink"
        }
    ],
    "sg:phone":"+1 703 378 6928",
    "sg:postcode":"22033",
    "sg:province":"VA",
    "wof:name":"Saigon Crepes",
    "wof:placetype":"venue"
},
  "geometry": {"coordinates":[-77.40004999999999,38.875531],"type":"Point"}
}