{
  "type": "Feature",
  "properties": {
    "addr:full":"3904 Deep Run Rd Chesapeake VA 23321",
    "addr:housenumber":"3904",
    "addr:postcode":"23321",
    "addr:street":"Deep Run Rd",
    "iso:country":"US",
    "sg:address":"3904 Deep Run Rd",
    "sg:city":"Chesapeake",
    "sg:classifiers":[
        {
            "category":"Shopping",
            "subcategory":"Jewelry",
            "type":"Retail Goods"
        }
    ],
    "sg:phone":"+1 757 488 5696",
    "sg:postcode":"23321",
    "sg:province":"VA",
    "sg:tags":[
        "repair"
    ],
    "wof:name":"Russells Jewelers",
    "wof:placetype":"venue"
},
  "geometry": {"coordinates":[-76.410246,36.792835],"type":"Point"}
}