{
  "type": "Feature",
  "properties": {
    "iso:country":"US",
    "sg:address":"7902 Westpark Dr",
    "sg:city":"Mc Lean",
    "sg:classifiers":[
        {
            "category":"Building & Trades",
            "subcategory":"Construction",
            "type":"Services"
        }
    ],
    "sg:phone":"+1 703 273 7500",
    "sg:postcode":"22102",
    "sg:province":"VA",
    "sg:tags":[
        "development",
        "living",
        "assisted",
        "home",
        "consul",
        "developer"
    ],
    "wof:name":"Sunrise Development Inc",
    "wof:placetype":"venue"
},
  "geometry": {"coordinates":[-77.21854999999999,38.924951],"type":"Point"}
}