{
  "type": "Feature",
  "properties": {
    "addr:full":"14635 Corky's Farm Ln Waterford VA 20197",
    "addr:housenumber":"14635",
    "addr:postcode":"20197",
    "addr:street":"Corky'S Farm Ln",
    "iso:country":"US",
    "sg:address":"14635 Corky's Farm Ln",
    "sg:city":"Waterford",
    "sg:classifiers":[
        {
            "category":"Farming",
            "subcategory":"Vineyard",
            "type":"Manufacturing & Wholesale Goods"
        }
    ],
    "sg:phone":"+1 540 882 9672",
    "sg:postcode":"20197",
    "sg:province":"VA",
    "sg:tags":[
        "grape"
    ],
    "wof:name":"Waterford Vineyards LLC",
    "wof:placetype":"venue"
},
  "geometry": {"coordinates":[-77.654929,39.212871],"type":"Point"}
}