{
  "type": "Feature",
  "properties": {
    "addr:full":"240 Pleasant View Rd Staunton VA 24401",
    "addr:housenumber":"240",
    "addr:postcode":"24401",
    "addr:street":"Pleasant View Rd",
    "iso:country":"US",
    "sg:address":"240 Pleasant View Rd",
    "sg:city":"Staunton",
    "sg:classifiers":[
        {
            "category":"Building & Trades",
            "subcategory":"Construction",
            "type":"Services"
        }
    ],
    "sg:phone":"+1 540 248 0631",
    "sg:postcode":"24401",
    "sg:province":"VA",
    "sg:tags":[
        "contractor"
    ],
    "wof:name":"Paul H Morrison Welding",
    "wof:placetype":"venue"
},
  "geometry": {"coordinates":[-79.08240499999999,38.203182],"type":"Point"}
}