{
  "type": "Feature",
  "properties": {
    "addr:full":"5300 George Washington Memorial Hwy Yorktown VA 23692",
    "addr:housenumber":"5300",
    "addr:postcode":"23692",
    "addr:street":"George Washington Memorial Hwy",
    "iso:country":"US",
    "sg:address":"5300 George Washington Memorial Hwy",
    "sg:city":"Yorktown",
    "sg:classifiers":[
        {
            "category":"Cinema",
            "subcategory":"Movie Rental",
            "type":"Entertainment"
        }
    ],
    "sg:phone":"+1 757 890 0057",
    "sg:postcode":"23692",
    "sg:province":"VA",
    "sg:tags":[
        "video",
        "tape"
    ],
    "wof:name":"Video Update",
    "wof:placetype":"venue"
},
  "geometry": {"coordinates":[-76.463184,37.159535],"type":"Point"}
}