{
  "type": "Feature",
  "properties": {
    "addr:full":"5 Walnut St Middleburg VA 20117",
    "addr:housenumber":"5",
    "addr:postcode":"20117",
    "addr:street":"Walnut St",
    "iso:country":"US",
    "sg:address":"5 Walnut St",
    "sg:city":"Middleburg",
    "sg:classifiers":[
        {
            "category":"Building & Trades",
            "subcategory":"Construction",
            "type":"Services"
        }
    ],
    "sg:phone":"+1 540 687 3834",
    "sg:postcode":"20117",
    "sg:province":"VA",
    "sg:tags":[
        "general",
        "contractor"
    ],
    "wof:name":"Built By Bruce",
    "wof:placetype":"venue"
},
  "geometry": {"coordinates":[-77.74177,38.968105],"type":"Point"}
}