{
  "type": "Feature",
  "properties": {
    "addr:full":"116 Wesley St Cedar Bluff VA 24605",
    "addr:housenumber":"116",
    "addr:postcode":"24605",
    "addr:street":"Wesley St",
    "iso:country":"US",
    "sg:address":"116 Wesley St",
    "sg:city":"Cedar Bluff",
    "sg:classifiers":[
        {
            "category":"Building & Trades",
            "subcategory":"Construction",
            "type":"Services"
        },
        {
            "category":"Home & Garden",
            "subcategory":"Furniture",
            "type":"Retail Goods"
        }
    ],
    "sg:phone":"+1 276 964 5524",
    "sg:postcode":"24605",
    "sg:province":"VA",
    "sg:tags":[
        "cabinet",
        "carpentry",
        "contractor"
    ],
    "wof:name":"Barb's Cabinet Magic Shoppe",
    "wof:placetype":"venue"
},
  "geometry": {"coordinates":[-81.29896599999999,37.248445],"type":"Point"}
}