{
  "type": "Feature",
  "properties": {
    "addr:full":"14148 Yankeetown Rd Ashland VA 23005",
    "addr:housenumber":"14148",
    "addr:postcode":"23005",
    "addr:street":"Yankeetown Rd",
    "iso:country":"US",
    "sg:address":"14148 Yankeetown Rd",
    "sg:city":"Ashland",
    "sg:classifiers":[
        {
            "category":"Social Services",
            "subcategory":"Child Care",
            "type":"Services"
        }
    ],
    "sg:phone":"+1 804 798 7397",
    "sg:postcode":"23005",
    "sg:province":"VA",
    "wof:name":"Hawk Haven Child Care Ctr Inc",
    "wof:placetype":"venue"
},
  "geometry": {"coordinates":[-77.524326,37.78874],"type":"Point"}
}