{
  "type": "Feature",
  "properties": {
    "iso:country":"US",
    "sg:address":"1500 Forest Ave",
    "sg:city":"Richmond",
    "sg:classifiers":[
        {
            "category":"Wholesale",
            "subcategory":"Computers",
            "type":"Manufacturing & Wholesale Goods"
        }
    ],
    "sg:phone":"+1 804 288 3003",
    "sg:postcode":"23229",
    "sg:province":"VA",
    "sg:tags":[
        "international",
        "banking",
        "software"
    ],
    "wof:name":"Micro Banking Automation",
    "wof:placetype":"venue"
},
  "geometry": {"coordinates":[-77.544563,37.601106],"type":"Point"}
}