{
  "type": "Feature",
  "properties": {
    "iso:country":"US",
    "sg:address":"402 Idaho St",
    "sg:city":"Salem",
    "sg:classifiers":[
        {
            "category":"Organizations",
            "subcategory":"Membership Organization",
            "type":"Services"
        }
    ],
    "sg:phone":"+1 540 389 7373",
    "sg:postcode":"24153",
    "sg:province":"VA",
    "sg:tags":[
        "athletic"
    ],
    "sg:website":"www.odaconline.com",
    "wof:name":"Old Dominion Athletic Cnfrnce",
    "wof:placetype":"venue"
},
  "geometry": {"coordinates":[-80.04475100000001,37.289995],"type":"Point"}
}