{
  "type": "Feature",
  "properties": {
    "iso:country":"US",
    "sg:address":"708 Appalachian Dr",
    "sg:city":"Blacksburg",
    "sg:classifiers":[
        {
            "category":"Professional",
            "type":"Services"
        }
    ],
    "sg:phone":"+1 540 951 3085",
    "sg:postcode":"24060",
    "sg:province":"VA",
    "wof:name":"Meadows Leslie",
    "wof:placetype":"venue"
},
  "geometry": {"coordinates":[-80.430014,37.241297],"type":"Point"}
}