{
  "type": "Feature",
  "properties": {
    "iso:country":"US",
    "sg:address":"801 21st St S",
    "sg:city":"Arlington",
    "sg:classifiers":[
        {
            "category":"Professional",
            "subcategory":"Business Services",
            "type":"Services"
        }
    ],
    "sg:phone":"+1 703 979 7979",
    "sg:postcode":"22202",
    "sg:province":"VA",
    "sg:tags":[
        "plant",
        "design",
        "maintenance"
    ],
    "wof:name":"Natural Interiors Inc",
    "wof:placetype":"venue"
},
  "geometry": {"coordinates":[-77.061409,38.8548],"type":"Point"}
}