{
  "type": "Feature",
  "properties": {
    "addr:full":"17387 General Puller Hwy Deltaville VA 23043",
    "addr:housenumber":"17387",
    "addr:postcode":"23043",
    "addr:street":"General Puller Hwy",
    "iso:country":"US",
    "sg:address":"17387 General Puller Hwy",
    "sg:city":"Deltaville",
    "sg:classifiers":[
        {
            "category":"Personal",
            "subcategory":"Tanning Parlor",
            "type":"Services"
        }
    ],
    "sg:phone":"+1 804 776 8826",
    "sg:postcode":"23043",
    "sg:province":"VA",
    "sg:tags":[
        "salon"
    ],
    "wof:name":"Endless Summer LLC",
    "wof:placetype":"venue"
},
  "geometry": {"coordinates":[-76.335342,37.555068],"type":"Point"}
}