{
  "type": "Feature",
  "properties": {
    "addr:full":"27889 Walters Hwy Carrsville VA 23315",
    "addr:housenumber":"27889",
    "addr:postcode":"23315",
    "addr:street":"Walters Hwy",
    "iso:country":"US",
    "sg:address":"27889 Walters Hwy",
    "sg:city":"Carrsville",
    "sg:classifiers":[
        {
            "category":"Food & Beverages",
            "subcategory":"Groceries & Convenience Stores",
            "type":"Retail Goods"
        }
    ],
    "sg:phone":"+1 757 569 0668",
    "sg:postcode":"23315",
    "sg:province":"VA",
    "wof:name":"Walters Market",
    "wof:placetype":"venue"
},
  "geometry": {"coordinates":[-76.85425499999999,36.768855],"type":"Point"}
}