{
  "type": "Feature",
  "properties": {
    "iso:country":"US",
    "sg:address":"221 Biltmore Dr",
    "sg:city":"Colonial Heights",
    "sg:classifiers":[
        {
            "category":"Building & Trades",
            "subcategory":"Plumbing",
            "type":"Services"
        }
    ],
    "sg:phone":"+1 804 520 7930",
    "sg:postcode":"23834",
    "sg:province":"VA",
    "sg:tags":[
        "contractor"
    ],
    "wof:name":"Tri City Plumbing & Heating Co",
    "wof:placetype":"venue"
},
  "geometry": {"coordinates":[-77.42454600000001,37.276772],"type":"Point"}
}