{
  "type": "Feature",
  "properties": {
    "addr:full":"13572 Waterford Pl Midlothian VA 23112",
    "addr:housenumber":"13572",
    "addr:postcode":"23112",
    "addr:street":"Waterford Pl",
    "iso:country":"US",
    "sg:address":"13572 Waterford Pl",
    "sg:city":"Midlothian",
    "sg:classifiers":[
        {
            "category":"Health Services",
            "subcategory":"Doctor",
            "type":"Services"
        }
    ],
    "sg:phone":"+1 804 560 8782",
    "sg:postcode":"23112",
    "sg:province":"VA",
    "sg:tags":[
        "physician",
        "surgeon"
    ],
    "wof:name":"Mark E Johns Md Facc",
    "wof:placetype":"venue"
},
  "geometry": {"coordinates":[-77.64660499999999,37.450581],"type":"Point"}
}