{
  "type": "Feature",
  "properties": {
    "addr:full":"30 Prospect Pkwy Portsmouth VA 23702",
    "addr:housenumber":"30",
    "addr:postcode":"23702",
    "addr:street":"Prospect Pkwy",
    "iso:country":"US",
    "sg:address":"30 Prospect Pkwy",
    "sg:city":"Portsmouth",
    "sg:classifiers":[
        {
            "category":"Government",
            "subcategory":"Post Office",
            "type":"Public Place"
        }
    ],
    "sg:phone":"+1 757 393 6771",
    "sg:postcode":"23702",
    "sg:province":"VA",
    "wof:name":"US Post Office",
    "wof:placetype":"venue"
},
  "geometry": {"coordinates":[-76.31717399999999,36.802353],"type":"Point"}
}