{
  "type": "Feature",
  "properties": {
    "addr:full":"5459 Mary Ball Rd Lancaster VA 22503",
    "addr:housenumber":"5459",
    "addr:postcode":"22503",
    "addr:street":"Mary Ball Rd",
    "iso:country":"US",
    "sg:address":"5459 Mary Ball Rd",
    "sg:city":"Lancaster",
    "sg:classifiers":[
        {
            "category":"Manufacturing",
            "subcategory":"Printing",
            "type":"Manufacturing & Wholesale Goods"
        }
    ],
    "sg:phone":"+1 804 462 0123",
    "sg:postcode":"22503",
    "sg:province":"VA",
    "sg:tags":[
        "imprinting"
    ],
    "sg:website":"www.fairwayproducts.com",
    "wof:name":"Fairway Products Inc",
    "wof:placetype":"venue"
},
  "geometry": {"coordinates":[-76.513604,37.777745],"type":"Point"}
}