{
  "type": "Feature",
  "properties": {
    "iso:country":"US",
    "sg:address":"12511 Bermuda Triangle Rd",
    "sg:city":"Chester",
    "sg:classifiers":[
        {
            "category":"Freight",
            "type":"Transportation"
        }
    ],
    "sg:phone":"+1 804 748 6385",
    "sg:postcode":"23836",
    "sg:province":"VA",
    "sg:tags":[
        "warehouse",
        "self",
        "storage"
    ],
    "wof:name":"Bermuda Distribution Inc",
    "wof:placetype":"venue"
},
  "geometry": {"coordinates":[-77.391248,37.355819],"type":"Point"}
}