{
  "type": "Feature",
  "properties": {
    "addr:full":"1141 Turtle Rock Trce Chesapeake VA 23320",
    "addr:housenumber":"1141",
    "addr:postcode":"23320",
    "addr:street":"Turtle Rock Trce",
    "iso:country":"US",
    "sg:address":"1141 Turtle Rock Trce",
    "sg:city":"Chesapeake",
    "sg:classifiers":[
        {
            "category":"Professional",
            "subcategory":"Business Services",
            "type":"Services"
        }
    ],
    "sg:phone":"+1 757 617 4300",
    "sg:postcode":"23320",
    "sg:province":"VA",
    "sg:tags":[
        "printing",
        "document"
    ],
    "wof:name":"G&S Document Solutions",
    "wof:placetype":"venue"
},
  "geometry": {"coordinates":[-76.22395,36.771792],"type":"Point"}
}