{
  "type": "Feature",
  "properties": {
    "iso:country":"US",
    "sg:address":"930 Pecan Point Rd",
    "sg:city":"Norfolk",
    "sg:classifiers":[
        {
            "category":"Organizations",
            "subcategory":"Religious Organization",
            "type":"Services"
        }
    ],
    "sg:phone":"+1 757 461 2480",
    "sg:postcode":"23502",
    "sg:province":"VA",
    "sg:tags":[
        "church"
    ],
    "wof:name":"Fountain Of Life",
    "wof:placetype":"venue"
},
  "geometry": {"coordinates":[-76.221333,36.85454],"type":"Point"}
}