{
  "type": "Feature",
  "properties": {
    "addr:full":"103 Withers Cir Danville VA 24541",
    "addr:housenumber":"103",
    "addr:postcode":"24541",
    "addr:street":"Withers Cir",
    "iso:country":"US",
    "sg:address":"103 Withers Cir",
    "sg:city":"Danville",
    "sg:classifiers":[
        {
            "category":"Organizations",
            "subcategory":"Religious Organization",
            "type":"Services"
        }
    ],
    "sg:phone":"+1 434 793 6022",
    "sg:postcode":"24541",
    "sg:province":"VA",
    "sg:tags":[
        "clergy"
    ],
    "wof:name":"Kenneth D Hall Rev",
    "wof:placetype":"venue"
},
  "geometry": {"coordinates":[-79.465698,36.553142],"type":"Point"}
}