{
  "type": "Feature",
  "properties": {
    "addr:full":"7152 Middle Rd Middletown VA 22645",
    "addr:housenumber":"7152",
    "addr:postcode":"22645",
    "addr:street":"Middle Rd",
    "iso:country":"US",
    "sg:address":"7152 Middle Rd",
    "sg:city":"Middletown",
    "sg:classifiers":[
        {
            "category":"Organizations",
            "subcategory":"Religious Organization",
            "type":"Services"
        }
    ],
    "sg:phone":"+1 540 869 2456",
    "sg:postcode":"22645",
    "sg:province":"VA",
    "sg:tags":[
        "church"
    ],
    "wof:name":"Presbyterian Parish of Valleys",
    "wof:placetype":"venue"
},
  "geometry": {"coordinates":[-78.320982,39.081988],"type":"Point"}
}