{
  "type": "Feature",
  "properties": {
    "addr:full":"7091 Indian Trl Suffolk VA 23437",
    "addr:housenumber":"7091",
    "addr:postcode":"23437",
    "addr:street":"Indian Trl",
    "iso:country":"US",
    "sg:address":"7091 Indian Trl",
    "sg:city":"Suffolk",
    "sg:phone":"+1 757 657 6759",
    "sg:postcode":"23437",
    "sg:province":"VA",
    "sg:tags":[
        "farm",
        "field",
        "crop",
        "cotton"
    ],
    "wof:name":"Martha Rountree",
    "wof:placetype":"venue"
},
  "geometry": {"coordinates":[-76.78894699999999,36.707626],"type":"Point"}
}