{
  "type": "Feature",
  "properties": {
    "addr:full":"1959 E Pembroke Ave Hampton VA 23663",
    "addr:housenumber":"1959",
    "addr:postcode":"23663",
    "addr:street":"E Pembroke Ave",
    "iso:country":"US",
    "sg:address":"1959 E Pembroke Ave",
    "sg:city":"Hampton",
    "sg:classifiers":[
        {
            "category":"Health Services",
            "subcategory":"Doctor",
            "type":"Services"
        }
    ],
    "sg:phone":"+1 757 723 6565",
    "sg:postcode":"23663",
    "sg:province":"VA",
    "sg:tags":[
        "dentist"
    ],
    "wof:name":"William Pearlman Assoc",
    "wof:placetype":"venue"
},
  "geometry": {"coordinates":[-76.305153,37.040154],"type":"Point"}
}