{
  "type": "Feature",
  "properties": {
    "iso:country":"US",
    "sg:address":"800 W Constance Rd",
    "sg:city":"Suffolk",
    "sg:classifiers":[
        {
            "category":"Personal",
            "subcategory":"Barber",
            "type":"Services"
        }
    ],
    "sg:phone":"+1 757 539 9509",
    "sg:postcode":"23434",
    "sg:province":"VA",
    "wof:name":"Harris' US Male Hair Styling",
    "wof:placetype":"venue"
},
  "geometry": {"coordinates":[-76.59728699999999,36.733149],"type":"Point"}
}