{
  "type": "Feature",
  "properties": {
    "addr:full":"1438 Lake Geneve Dr Virginia Beach VA 23464",
    "addr:housenumber":"1438",
    "addr:postcode":"23464",
    "addr:street":"Lake Geneve Dr",
    "iso:country":"US",
    "sg:address":"1438 Lake Geneve Dr",
    "sg:city":"Virginia Beach",
    "sg:classifiers":[
        {
            "category":"Banks & Credit Unions",
            "subcategory":"Financial Services",
            "type":"Services"
        }
    ],
    "sg:phone":"+1 757 495 8558",
    "sg:postcode":"23464",
    "sg:province":"VA",
    "sg:tags":[
        "investor"
    ],
    "wof:name":"Ehub Investments",
    "wof:placetype":"venue"
},
  "geometry": {"coordinates":[-76.160804,36.794624],"type":"Point"}
}