{
  "type": "Feature",
  "properties": {
    "addr:full":"12 Cattlemans Ln Berryville VA 22611",
    "addr:housenumber":"12",
    "addr:postcode":"22611",
    "addr:street":"Cattlemans Ln",
    "iso:country":"US",
    "sg:address":"12 Cattlemans Ln",
    "sg:city":"Berryville",
    "sg:classifiers":[
        {
            "category":"Home & Garden",
            "subcategory":"Building Materials",
            "type":"Retail Goods"
        },
        {
            "category":"Building & Trades",
            "subcategory":"Construction",
            "type":"Services"
        },
        {
            "category":"Home & Garden",
            "subcategory":"Carpets & Floor Coverings",
            "type":"Retail Goods"
        }
    ],
    "sg:phone":"+1 540 955 3021",
    "sg:postcode":"22611",
    "sg:province":"VA",
    "sg:tags":[
        "hardwood",
        "specialty"
    ],
    "sg:website":"http://www.kortekinc.com",
    "wof:name":"Kor-Tek Inc",
    "wof:placetype":"venue"
},
  "geometry": {"coordinates":[-77.97417900000001,39.14782],"type":"Point"}
}