{
  "type": "Feature",
  "properties": {
    "iso:country":"US",
    "sg:address":"2210 Dominion Dr",
    "sg:city":"Charlottesville",
    "sg:classifiers":[
        {
            "category":"Social Services",
            "type":"Services"
        }
    ],
    "sg:phone":"+1 434 295 4652",
    "sg:postcode":"22901",
    "sg:province":"VA",
    "wof:name":"Castlewood Adult Home",
    "wof:placetype":"venue"
},
  "geometry": {"coordinates":[-78.48204800000001,38.08037],"type":"Point"}
}