{
  "type": "Feature",
  "properties": {
    "iso:country":"US",
    "sg:address":"409 Front St E",
    "sg:city":"Coeburn",
    "sg:classifiers":[
        {
            "category":"Shopping",
            "type":"Retail Goods"
        }
    ],
    "sg:phone":"+1 276 395 5160",
    "sg:postcode":"24230",
    "sg:province":"VA",
    "sg:tags":[
        "craft",
        "gallery",
        "dealer"
    ],
    "wof:name":"Purely Appalachian Crafts",
    "wof:placetype":"venue"
},
  "geometry": {"coordinates":[-82.46535900000001,36.943662],"type":"Point"}
}