{
  "type": "Feature",
  "properties": {
    "iso:country":"US",
    "sg:address":"2733 E Princess Anne Rd",
    "sg:city":"Norfolk",
    "sg:classifiers":[
        {
            "category":"Personal",
            "subcategory":"Beauty Salon",
            "type":"Services"
        }
    ],
    "sg:phone":"+1 757 625 4684",
    "sg:postcode":"23504",
    "sg:province":"VA",
    "wof:name":"Rance's World Of Beauty",
    "wof:placetype":"venue"
},
  "geometry": {"coordinates":[-76.25551400000001,36.856144],"type":"Point"}
}