{
  "type": "Feature",
  "properties": {
    "iso:country":"US",
    "sg:address":"1506 Belle View Blvd",
    "sg:city":"Alexandria",
    "sg:classifiers":[
        {
            "category":"Restaurant",
            "type":"Food & Drink"
        }
    ],
    "sg:phone":"+1 703 768 9393",
    "sg:postcode":"22307",
    "sg:province":"VA",
    "sg:tags":[
        "house",
        "steak"
    ],
    "wof:name":"Rustler Steak House",
    "wof:placetype":"venue"
},
  "geometry": {"coordinates":[-77.05845600000001,38.775131],"type":"Point"}
}