{
  "type": "Feature",
  "properties": {
    "addr:full":"3321 Nottoway Ln Amelia Court House VA 23002",
    "addr:housenumber":"3321",
    "addr:postcode":"23002",
    "addr:street":"Nottoway Ln",
    "iso:country":"US",
    "sg:address":"3321 Nottoway Ln",
    "sg:city":"Amelia Court House",
    "sg:classifiers":[
        {
            "category":"Home & Garden",
            "subcategory":"Furniture",
            "type":"Retail Goods"
        }
    ],
    "sg:phone":"+1 804 561 5457",
    "sg:postcode":"23002",
    "sg:province":"VA",
    "wof:name":"Wh Hux Furniture",
    "wof:placetype":"venue"
},
  "geometry": {"coordinates":[-78.015563,37.246969],"type":"Point"}
}