{
  "type": "Feature",
  "properties": {
    "iso:country":"US",
    "sg:address":"6126 Mountain Springs Ln",
    "sg:city":"Clifton",
    "sg:classifiers":[
        {
            "category":"Communications",
            "subcategory":"Film & Video Production",
            "type":"Services"
        }
    ],
    "sg:phone":"+1 703 359 8290",
    "sg:postcode":"20124",
    "sg:province":"VA",
    "sg:tags":[
        "motion"
    ],
    "wof:name":"Silver Ridge Productions Inc",
    "wof:placetype":"venue"
},
  "geometry": {"coordinates":[-77.41879,38.823301],"type":"Point"}
}