{
  "type": "Feature",
  "properties": {
    "addr:full":"106 Free Ct Sterling VA 20164",
    "addr:housenumber":"106",
    "addr:postcode":"20164",
    "addr:street":"Free Ct",
    "iso:country":"US",
    "sg:address":"106 Free Ct",
    "sg:city":"Sterling",
    "sg:classifiers":[
        {
            "category":"Social Services",
            "subcategory":"Child Care",
            "type":"Services"
        }
    ],
    "sg:phone":"+1 703 430 7373",
    "sg:postcode":"20164",
    "sg:province":"VA",
    "wof:name":"Children's World Learning Ctr",
    "wof:placetype":"venue"
},
  "geometry": {"coordinates":[-77.405124,39.000106],"type":"Point"}
}