{
  "type": "Feature",
  "properties": {
    "addr:full":"2859 Duke St Alexandria VA 22314",
    "addr:housenumber":"2859",
    "addr:postcode":"22314",
    "addr:street":"Duke St",
    "iso:country":"US",
    "sg:address":"2859 Duke St",
    "sg:city":"Alexandria",
    "sg:classifiers":[
        {
            "category":"Health Services",
            "subcategory":"Doctor",
            "type":"Services"
        }
    ],
    "sg:phone":"+1 703 535 1778",
    "sg:postcode":"22314",
    "sg:province":"VA",
    "sg:tags":[
        "medicine",
        "physician",
        "surgeon",
        "internal",
        "surgeons"
    ],
    "wof:name":"Capital Pulmonary Internist Pc",
    "wof:placetype":"venue"
},
  "geometry": {"coordinates":[-77.078603,38.807203],"type":"Point"}
}