{
  "type": "Feature",
  "properties": {
    "iso:country":"US",
    "sg:address":"1213 W Main St",
    "sg:city":"Richmond",
    "sg:classifiers":[
        {
            "category":"Personal",
            "subcategory":"Beauty Salon",
            "type":"Services"
        }
    ],
    "sg:phone":"+1 804 353 2911",
    "sg:postcode":"23220",
    "sg:province":"VA",
    "sg:tags":[
        "shop"
    ],
    "wof:name":"Beltons of Richmond",
    "wof:placetype":"venue"
},
  "geometry": {"coordinates":[-77.457188,37.546029],"type":"Point"}
}