{
  "type": "Feature",
  "properties": {
    "addr:full":"514 Bedford Ave Bedford VA 24523",
    "addr:housenumber":"514",
    "addr:postcode":"24523",
    "addr:street":"Bedford Ave",
    "iso:country":"US",
    "sg:address":"514 Bedford Ave",
    "sg:city":"Bedford",
    "sg:classifiers":[
        {
            "category":"Sports & Exercise",
            "subcategory":"Gym",
            "type":"Entertainment"
        }
    ],
    "sg:phone":"+1 540 587 7540",
    "sg:postcode":"24523",
    "sg:province":"VA",
    "sg:tags":[
        "organization",
        "health"
    ],
    "wof:name":"Curves For Women",
    "wof:placetype":"venue"
},
  "geometry": {"coordinates":[-79.52757800000001,37.337758],"type":"Point"}
}