{
  "type": "Feature",
  "properties": {
    "iso:country":"US",
    "sg:address":"8301 Winterslow Ter",
    "sg:city":"Richmond",
    "sg:classifiers":[
        {
            "category":"Restaurant",
            "type":"Food & Drink"
        }
    ],
    "sg:phone":"+1 804 828 2782",
    "sg:postcode":"23235",
    "sg:province":"VA",
    "sg:tags":[
        "eating"
    ],
    "wof:name":"Subway",
    "wof:placetype":"venue"
},
  "geometry": {"coordinates":[-77.55200499999999,37.501749],"type":"Point"}
}