{
  "type": "Feature",
  "properties": {
    "iso:country":"US",
    "sg:address":"1406 Todds Ln",
    "sg:city":"Hampton",
    "sg:classifiers":[
        {
            "category":"Recreation",
            "type":"Entertainment"
        }
    ],
    "sg:phone":"+1 757 838 2970",
    "sg:postcode":"23666",
    "sg:province":"VA",
    "sg:tags":[
        "club",
        "membership"
    ],
    "wof:name":"Northampton Little League Inc",
    "wof:placetype":"venue"
},
  "geometry": {"coordinates":[-76.42553700000001,37.042094],"type":"Point"}
}