{
  "type": "Feature",
  "properties": {
    "iso:country":"US",
    "sg:address":"4605 Alabama Ave",
    "sg:city":"Lynchburg",
    "sg:classifiers":[
        {
            "category":"Restaurant",
            "type":"Food & Drink"
        }
    ],
    "sg:phone":"+1 434 237 1345",
    "sg:postcode":"24502",
    "sg:province":"VA",
    "sg:tags":[
        "eating"
    ],
    "wof:name":"Phillip Wayne Whitt",
    "wof:placetype":"venue"
},
  "geometry": {"coordinates":[-79.190855,37.386347],"type":"Point"}
}