{
  "type": "Feature",
  "properties": {
    "addr:full":"1011 Sydnor Jennings Rd Nathalie VA 24577",
    "addr:housenumber":"1011",
    "addr:postcode":"24577",
    "addr:street":"Sydnor Jennings Rd",
    "iso:country":"US",
    "sg:address":"1011 Sydnor Jennings Rd",
    "sg:city":"Nathalie",
    "sg:classifiers":[
        {
            "category":"Education",
            "subcategory":"School",
            "type":"Public Place"
        }
    ],
    "sg:phone":"+1 434 349 1013",
    "sg:postcode":"24577",
    "sg:province":"VA",
    "wof:name":"Sydnor Jennings Elem School",
    "wof:placetype":"venue"
},
  "geometry": {"coordinates":[-79.013856,36.924523],"type":"Point"}
}