{
  "type": "Feature",
  "properties": {
    "addr:full":"9492 Chamberlayne Rd Mechanicsville VA 23116",
    "addr:postcode":"9492;23116",
    "addr:street":"Chamberlayne Rd",
    "iso:country":"US",
    "sg:address":"9492 Chamberlayne Rd",
    "sg:city":"Mechanicsville",
    "sg:classifiers":[
        {
            "category":"Food & Beverages",
            "subcategory":"Groceries & Convenience Stores",
            "type":"Retail Goods"
        }
    ],
    "sg:phone":"+1 804 730 4899",
    "sg:postcode":"23116",
    "sg:province":"VA",
    "wof:name":"Fas Mart",
    "wof:placetype":"venue"
},
  "geometry": {"coordinates":[-77.38500500000001,37.660148],"type":"Point"}
}