{
  "type": "Feature",
  "properties": {
    "addr:full":"7482 Lee Hwy Falls Church VA 22042",
    "addr:housenumber":"7482",
    "addr:postcode":"22042",
    "addr:street":"Lee Hwy",
    "iso:country":"US",
    "sg:address":"7482 Lee Hwy",
    "sg:city":"Falls Church",
    "sg:classifiers":[
        {
            "category":"Real Estate",
            "subcategory":"Developer",
            "type":"Services"
        }
    ],
    "sg:phone":"+1 703 560 0019",
    "sg:postcode":"22042",
    "sg:province":"VA",
    "sg:tags":[
        "cemetery"
    ],
    "wof:name":"Islamic National Mem Cmtry",
    "wof:placetype":"venue"
},
  "geometry": {"coordinates":[-77.19999199999999,38.875893],"type":"Point"}
}