{
  "type": "Feature",
  "properties": {
    "iso:country":"US",
    "sg:address":"271 Laymantown Rd",
    "sg:city":"Troutville",
    "sg:classifiers":[
        {
            "category":"Professional",
            "subcategory":"Engineering",
            "type":"Services"
        }
    ],
    "sg:phone":"+1 540 977 3702",
    "sg:postcode":"24175",
    "sg:province":"VA",
    "wof:name":"PCA Mechanical Engineering",
    "wof:placetype":"venue"
},
  "geometry": {"coordinates":[-79.84658399999999,37.349005],"type":"Point"}
}