{
  "type": "Feature",
  "properties": {
    "addr:full":"106 Jonadab Rd Yorktown VA 23692",
    "addr:housenumber":"106",
    "addr:postcode":"23692",
    "addr:street":"Jonadab Rd",
    "iso:country":"US",
    "sg:address":"106 Jonadab Rd",
    "sg:city":"Yorktown",
    "sg:classifiers":[
        {
            "category":"Utilities",
            "subcategory":"Mobile Phone",
            "type":"Services"
        }
    ],
    "sg:phone":"+1 757 833 6099",
    "sg:postcode":"23692",
    "sg:province":"VA",
    "sg:tags":[
        "communication",
        "radiotelephone",
        "merchandise"
    ],
    "wof:name":"T & M General Services Inc",
    "wof:placetype":"venue"
},
  "geometry": {"coordinates":[-76.43804299999999,37.140401],"type":"Point"}
}