{
  "type": "Feature",
  "properties": {
    "addr:full":"235 First Colonial Rd Virginia Beach VA 23454",
    "addr:housenumber":"235",
    "addr:postcode":"23454",
    "addr:street":"First Colonial Rd",
    "iso:country":"US",
    "sg:address":"235 First Colonial Rd",
    "sg:city":"Virginia Beach",
    "sg:classifiers":[
        {
            "category":"Shopping",
            "subcategory":"Used Merchandise",
            "type":"Retail Goods"
        }
    ],
    "sg:phone":"+1 757 428 2332",
    "sg:postcode":"23454",
    "sg:province":"VA",
    "sg:tags":[
        "woman",
        "clothing"
    ],
    "sg:website":"www.echoes-of-time.com",
    "wof:name":"Echoes Of Time",
    "wof:placetype":"venue"
},
  "geometry": {"coordinates":[-76.021051,36.846344],"type":"Point"}
}