{
  "type": "Feature",
  "properties": {
    "iso:country":"US",
    "sg:address":"457 S Main St",
    "sg:city":"Rocky Mount",
    "sg:classifiers":[
        {
            "category":"Home & Garden",
            "subcategory":"Garden Supply",
            "type":"Retail Goods"
        }
    ],
    "sg:phone":"+1 540 483 5920",
    "sg:postcode":"24151",
    "sg:province":"VA",
    "sg:tags":[
        "lawn",
        "mower"
    ],
    "wof:name":"Coast To Coast Small Engines",
    "wof:placetype":"venue"
},
  "geometry": {"coordinates":[-79.889752,36.992072],"type":"Point"}
}