{
  "type": "Feature",
  "properties": {
    "iso:country":"US",
    "sg:address":"3869 Lawrenceville Plank Rd",
    "sg:city":"Lawrenceville",
    "sg:classifiers":[
        {
            "category":"Food & Beverages",
            "subcategory":"Groceries & Convenience Stores",
            "type":"Retail Goods"
        }
    ],
    "sg:phone":"+1 434 848 4666",
    "sg:postcode":"23868",
    "sg:province":"VA",
    "sg:tags":[
        "grocer"
    ],
    "wof:name":"Eastwood Food Mart",
    "wof:placetype":"venue"
},
  "geometry": {"coordinates":[-77.81420799999999,36.771663],"type":"Point"}
}