{
  "type": "Feature",
  "properties": {
    "addr:full":"7101 Brook Rd Richmond VA 23227",
    "addr:housenumber":"7101",
    "addr:postcode":"23227",
    "addr:street":"Brook Rd",
    "iso:country":"US",
    "sg:address":"7101 Brook Rd",
    "sg:city":"Richmond",
    "sg:classifiers":[
        {
            "category":"Food & Beverages",
            "subcategory":"Groceries & Convenience Stores",
            "type":"Retail Goods"
        }
    ],
    "sg:phone":"+1 804 264 6986",
    "sg:postcode":"23227",
    "sg:province":"VA",
    "wof:name":"Q-Markets Inc",
    "wof:placetype":"venue"
},
  "geometry": {"coordinates":[-77.45699500000001,37.618032],"type":"Point"}
}