{
  "type": "Feature",
  "properties": {
    "iso:country":"US",
    "sg:address":"825 Fairfax Ave",
    "sg:city":"Norfolk",
    "sg:classifiers":[
        {
            "category":"Health Services",
            "subcategory":"Doctor",
            "type":"Services"
        }
    ],
    "sg:phone":"+1 757 624 2240",
    "sg:postcode":"23507",
    "sg:province":"VA",
    "sg:tags":[
        "medical"
    ],
    "wof:name":"Paul P Koonings",
    "wof:placetype":"venue"
},
  "geometry": {"coordinates":[-76.30319,36.860614],"type":"Point"}
}