{
  "type": "Feature",
  "properties": {
    "iso:country":"US",
    "sg:address":"276 W Main St",
    "sg:city":"Abingdon",
    "sg:classifiers":[
        {
            "category":"Shopping",
            "subcategory":"Optical Goods",
            "type":"Retail Goods"
        },
        {
            "category":"Health Services",
            "subcategory":"Optometrist",
            "type":"Services"
        }
    ],
    "sg:phone":"+1 276 628 7311",
    "sg:postcode":"24210",
    "sg:province":"VA",
    "wof:name":"Abingdon Eyeglass Co",
    "wof:placetype":"venue"
},
  "geometry": {"coordinates":[-81.979223,36.709039],"type":"Point"}
}