{
  "type": "Feature",
  "properties": {
    "iso:country":"US",
    "sg:address":"13055 Worldgate Dr",
    "sg:city":"Herndon",
    "sg:classifiers":[
        {
            "category":"Restaurant",
            "type":"Food & Drink"
        }
    ],
    "sg:menulink":"http://www.allmenus.com/va/dranesville/24759-supper-club-of-india/menu/",
    "sg:phone":"+1 703 736 0466",
    "sg:postcode":"20170",
    "sg:province":"VA",
    "sg:tags":[
        "indian",
        "asian"
    ],
    "wof:name":"Supper Club Of India",
    "wof:placetype":"venue"
},
  "geometry": {"coordinates":[-77.391836,38.954996],"type":"Point"}
}