{
  "type": "Feature",
  "properties": {
    "iso:country":"US",
    "sg:address":"13800 Coppermine Rd",
    "sg:city":"Herndon",
    "sg:classifiers":[
        {
            "category":"Professional",
            "type":"Services"
        }
    ],
    "sg:phone":"+1 703 234 7906",
    "sg:postcode":"20171",
    "sg:province":"VA",
    "sg:tags":[
        "establishment"
    ],
    "wof:name":"People Ventures",
    "wof:placetype":"venue"
},
  "geometry": {"coordinates":[-77.419062,38.950357],"type":"Point"}
}