{
  "type": "Feature",
  "properties": {
    "addr:full":"2314 E Parham Rd Richmond VA 23228",
    "addr:housenumber":"2314",
    "addr:postcode":"23228",
    "addr:street":"E Parham Rd",
    "iso:country":"US",
    "sg:address":"2314 E Parham Rd",
    "sg:city":"Richmond",
    "sg:classifiers":[
        {
            "category":"Health Services",
            "subcategory":"Doctor",
            "type":"Services"
        }
    ],
    "sg:phone":"+1 804 262 1060",
    "sg:postcode":"23228",
    "sg:province":"VA",
    "wof:name":"III Smith",
    "wof:placetype":"venue"
},
  "geometry": {"coordinates":[-77.493893,37.638282],"type":"Point"}
}