{
  "type": "Feature",
  "properties": {
    "addr:full":"10638 Crest Hill Rd Marshall VA 20115",
    "addr:housenumber":"10638",
    "addr:postcode":"20115",
    "addr:street":"Crest Hill Rd",
    "iso:country":"US",
    "sg:address":"10638 Crest Hill Rd",
    "sg:city":"Marshall",
    "sg:classifiers":[
        {
            "category":"Farming",
            "subcategory":"Farm",
            "type":"Manufacturing & Wholesale Goods"
        }
    ],
    "sg:phone":"+1 540 364 2470",
    "sg:postcode":"20115",
    "sg:province":"VA",
    "sg:tags":[
        "crop",
        "general"
    ],
    "wof:name":"Millway Farm",
    "wof:placetype":"venue"
},
  "geometry": {"coordinates":[-77.94504999999999,38.809928],"type":"Point"}
}