{
  "type": "Feature",
  "properties": {
    "iso:country":"US",
    "sg:address":"2523 Trophy Ln",
    "sg:city":"Reston",
    "sg:classifiers":[
        {
            "category":"Professional",
            "subcategory":"Management & Consulting",
            "type":"Services"
        }
    ],
    "sg:phone":"+1 703 476 6683",
    "sg:postcode":"20191",
    "sg:province":"VA",
    "sg:tags":[
        "business"
    ],
    "wof:name":"Milton Bearden",
    "wof:placetype":"venue"
},
  "geometry": {"coordinates":[-77.36497900000001,38.924682],"type":"Point"}
}