{
  "type": "Feature",
  "properties": {
    "iso:country":"US",
    "sg:address":"301 W Main St",
    "sg:city":"Christiansburg",
    "sg:classifiers":[
        {
            "category":"Freight",
            "type":"Transportation"
        }
    ],
    "sg:phone":"+1 540 382 1791",
    "sg:postcode":"24073",
    "sg:province":"VA",
    "sg:tags":[
        "general"
    ],
    "wof:name":"Brockenbrough Wayne",
    "wof:placetype":"venue"
},
  "geometry": {"coordinates":[-80.412003,37.127125],"type":"Point"}
}