{
  "type": "Feature",
  "properties": {
    "addr:full":"4405 33rd Rd N Arlington VA 22207",
    "addr:housenumber":"4405",
    "addr:postcode":"22207",
    "addr:street":"33Rd Rd N",
    "iso:country":"US",
    "sg:address":"4405 33rd Rd N",
    "sg:city":"Arlington",
    "sg:classifiers":[
        {
            "category":"Health Services",
            "subcategory":"Doctor",
            "type":"Services"
        },
        {
            "category":"Health Services",
            "subcategory":"Clinic",
            "type":"Services"
        }
    ],
    "sg:phone":"+1 703 534 4407",
    "sg:postcode":"22207",
    "sg:province":"VA",
    "sg:tags":[
        "counseling",
        "mental"
    ],
    "wof:name":"Crowe Patricia B PHD",
    "wof:placetype":"venue"
},
  "geometry": {"coordinates":[-77.123901,38.914299],"type":"Point"}
}