{
  "type": "Feature",
  "properties": {
    "addr:full":"5808 Midlothian Tpke Richmond VA 23225",
    "addr:housenumber":"5808",
    "addr:postcode":"23225",
    "addr:street":"Midlothian Tpke",
    "iso:country":"US",
    "sg:address":"5808 Midlothian Tpke",
    "sg:city":"Richmond",
    "sg:classifiers":[
        {
            "category":"Wholesale",
            "subcategory":"Machinery & Supplies",
            "type":"Manufacturing & Wholesale Goods"
        }
    ],
    "sg:phone":"+1 804 232 7816",
    "sg:postcode":"23225",
    "sg:province":"VA",
    "sg:tags":[
        "equipment",
        "material",
        "handling"
    ],
    "wof:name":"Vbs Inc Material Handling Eqpt",
    "wof:placetype":"venue"
},
  "geometry": {"coordinates":[-77.50354799999999,37.505493],"type":"Point"}
}