{
  "type": "Feature",
  "properties": {
    "addr:full":"4760 Euclid Rd Virginia Beach VA 23462",
    "addr:housenumber":"4760",
    "addr:postcode":"23462",
    "addr:street":"Euclid Rd",
    "iso:country":"US",
    "sg:address":"4760 Euclid Rd",
    "sg:city":"Virginia Beach",
    "sg:classifiers":[
        {
            "category":"Travel",
            "subcategory":"Hotels & Motels",
            "type":"Entertainment"
        }
    ],
    "sg:phone":"+1 757 499 1935",
    "sg:postcode":"23462",
    "sg:province":"VA",
    "sg:tags":[
        "operation"
    ],
    "wof:name":"Fairfield Inn",
    "wof:placetype":"venue"
},
  "geometry": {"coordinates":[-76.13924299999999,36.836636],"type":"Point"}
}