{
  "type": "Feature",
  "properties": {
    "addr:full":"320 Lordley Ln Richmond VA 23224",
    "addr:housenumber":"320",
    "addr:postcode":"23224",
    "addr:street":"Lordley Ln",
    "iso:country":"US",
    "sg:address":"320 Lordley Ln",
    "sg:city":"Richmond",
    "sg:classifiers":[
        {
            "category":"Building & Trades",
            "subcategory":"Plumbing",
            "type":"Services"
        }
    ],
    "sg:phone":"+1 804 231 5053",
    "sg:postcode":"23224",
    "sg:province":"VA",
    "sg:tags":[
        "mechanical",
        "contractor"
    ],
    "wof:name":"Baker & Hazlewood Mechanical",
    "wof:placetype":"venue"
},
  "geometry": {"coordinates":[-77.479068,37.504287],"type":"Point"}
}