{
  "type": "Feature",
  "properties": {
    "iso:country":"US",
    "sg:address":"6355 Walker Ln",
    "sg:city":"Alexandria",
    "sg:classifiers":[
        {
            "category":"Health Services",
            "subcategory":"Doctor",
            "type":"Services"
        }
    ],
    "sg:phone":"+1 703 719 5901",
    "sg:postcode":"22310",
    "sg:province":"VA",
    "sg:tags":[
        "gynecologist"
    ],
    "wof:name":"Ob Gyn Associates",
    "wof:placetype":"venue"
},
  "geometry": {"coordinates":[-77.155936,38.768214],"type":"Point"}
}