{
  "type": "Feature",
  "properties": {
    "addr:full":"8648 Richmond Hwy Alexandria VA 22309",
    "addr:housenumber":"8648",
    "addr:postcode":"22309",
    "addr:street":"Richmond Hwy",
    "iso:country":"US",
    "sg:address":"8648 Richmond Hwy",
    "sg:city":"Alexandria",
    "sg:classifiers":[
        {
            "category":"Home & Garden",
            "subcategory":"Home Furnishings",
            "type":"Retail Goods"
        }
    ],
    "sg:phone":"+1 703 619 1800",
    "sg:postcode":"22309",
    "sg:province":"VA",
    "sg:tags":[
        "fireplace"
    ],
    "wof:name":"Suburban Hearth & Patio",
    "wof:placetype":"venue"
},
  "geometry": {"coordinates":[-77.12099000000001,38.7228],"type":"Point"}
}