{
  "type": "Feature",
  "properties": {
    "iso:country":"US",
    "sg:address":"103 Barrington Ct",
    "sg:city":"Hardy",
    "sg:classifiers":[
        {
            "category":"Organizations",
            "subcategory":"Religious Organization",
            "type":"Services"
        }
    ],
    "sg:phone":"+1 540 890 9254",
    "sg:postcode":"24101",
    "sg:province":"VA",
    "wof:name":"R C Wagner Rev",
    "wof:placetype":"venue"
},
  "geometry": {"coordinates":[-79.826632,37.234719],"type":"Point"}
}