{
  "type": "Feature",
  "properties": {
    "addr:full":"103 Rose Hill Cir Staunton VA 24401",
    "addr:housenumber":"103",
    "addr:postcode":"24401",
    "addr:street":"Rose Hill Cir",
    "iso:country":"US",
    "sg:address":"103 Rose Hill Cir",
    "sg:city":"Staunton",
    "sg:classifiers":[
        {
            "category":"Shopping",
            "subcategory":"Gifts & Souvenirs",
            "type":"Retail Goods"
        }
    ],
    "sg:phone":"+1 540 887 7528",
    "sg:postcode":"24401",
    "sg:province":"VA",
    "sg:tags":[
        "basket",
        "parcel"
    ],
    "wof:name":"Lavender Lane Gardens",
    "wof:placetype":"venue"
},
  "geometry": {"coordinates":[-79.04815600000001,38.17285],"type":"Point"}
}