{
  "type": "Feature",
  "properties": {
    "addr:full":"1425 Sampson Ln Virginia Beach VA 23462",
    "addr:housenumber":"1425",
    "addr:postcode":"23462",
    "addr:street":"Sampson Ln",
    "iso:country":"US",
    "sg:address":"1425 Sampson Ln",
    "sg:city":"Virginia Beach",
    "sg:classifiers":[
        {
            "category":"Professional",
            "subcategory":"Computer Services",
            "type":"Services"
        }
    ],
    "sg:phone":"+1 757 963 8588",
    "sg:postcode":"23462",
    "sg:province":"VA",
    "sg:tags":[
        "related"
    ],
    "wof:name":"Abecca Investmentscom",
    "wof:placetype":"venue"
},
  "geometry": {"coordinates":[-76.125721,36.817092],"type":"Point"}
}