{
  "type": "Feature",
  "properties": {
    "iso:country":"US",
    "sg:address":"106 Kapok Cir",
    "sg:city":"Winchester",
    "sg:classifiers":[
        {
            "category":"Social Services",
            "subcategory":"Job Training",
            "type":"Services"
        }
    ],
    "sg:phone":"+1 540 667 4907",
    "sg:postcode":"22602",
    "sg:province":"VA",
    "wof:name":"Howland International Training",
    "wof:placetype":"venue"
},
  "geometry": {"coordinates":[-78.09792,39.165169],"type":"Point"}
}