{
  "type": "Feature",
  "properties": {
    "iso:country":"US",
    "sg:address":"2717 Sonic Dr",
    "sg:city":"Virginia Beach",
    "sg:classifiers":[
        {
            "category":"Professional",
            "type":"Services"
        }
    ],
    "sg:phone":"+1 757 368 2385",
    "sg:postcode":"23453",
    "sg:province":"VA",
    "sg:tags":[
        "establishment"
    ],
    "sg:website":"www.cheerunlimited.com",
    "wof:name":"Cheer Unlimited",
    "wof:placetype":"venue"
},
  "geometry": {"coordinates":[-76.064789,36.799668],"type":"Point"}
}