{
  "type": "Feature",
  "properties": {
    "iso:country":"US",
    "sg:address":"328 Granny's Bar Rd",
    "sg:city":"Hague",
    "sg:classifiers":[
        {
            "category":"Retail",
            "subcategory":"Repair Shop",
            "type":"Services"
        }
    ],
    "sg:phone":"+1 804 472 2698",
    "sg:postcode":"22469",
    "sg:province":"VA",
    "wof:name":"Harding Brothers Marine",
    "wof:placetype":"venue"
},
  "geometry": {"coordinates":[-76.635127,38.135505],"type":"Point"}
}