{
  "type": "Feature",
  "properties": {
    "addr:full":"659 Zachary Taylor Hwy Flint Hill VA 22627",
    "addr:housenumber":"659",
    "addr:postcode":"22627",
    "addr:street":"Zachary Taylor Hwy Flint Hill",
    "iso:country":"US",
    "sg:address":"659 Zachary Taylor Hwy",
    "sg:city":"Flint Hill",
    "sg:classifiers":[
        {
            "category":"Restaurant",
            "type":"Food & Drink"
        }
    ],
    "sg:phone":"+1 540 675 3227",
    "sg:postcode":"22627",
    "sg:province":"VA",
    "sg:website":"www.griffintavern.com",
    "wof:name":"Griffin Tavern",
    "wof:placetype":"venue"
},
  "geometry": {"coordinates":[-78.100273,38.763785],"type":"Point"}
}