{
  "type": "Feature",
  "properties": {
    "addr:full":"11280 James Swart Cir Fairfax VA 22030",
    "addr:housenumber":"11280",
    "addr:postcode":"22030",
    "addr:street":"James Swart Cir",
    "iso:country":"US",
    "sg:address":"11280 James Swart Cir",
    "sg:city":"Fairfax",
    "sg:classifiers":[
        {
            "category":"Restaurant",
            "type":"Food & Drink"
        }
    ],
    "sg:phone":"+1 703 352 6247",
    "sg:postcode":"22030",
    "sg:province":"VA",
    "sg:tags":[
        "eating"
    ],
    "wof:name":"Persian Grill Inc",
    "wof:placetype":"venue"
},
  "geometry": {"coordinates":[-77.333414,38.855057],"type":"Point"}
}