{
  "type": "Feature",
  "properties": {
    "iso:country":"US",
    "sg:address":"9207 Enterprise Ct",
    "sg:city":"Manassas Park",
    "sg:classifiers":[
        {
            "category":"Building & Trades",
            "subcategory":"Construction",
            "type":"Services"
        }
    ],
    "sg:phone":"+1 703 393 1146",
    "sg:postcode":"20111",
    "sg:province":"VA",
    "sg:tags":[
        "house",
        "contractor"
    ],
    "wof:name":"Bradley Turner Builders Inc",
    "wof:placetype":"venue"
},
  "geometry": {"coordinates":[-77.43668,38.775047],"type":"Point"}
}