{
  "type": "Feature",
  "properties": {
    "iso:country":"US",
    "sg:address":"6109 Amherst Ave",
    "sg:city":"Springfield",
    "sg:classifiers":[
        {
            "category":"Retail",
            "subcategory":"Auto Repair",
            "type":"Services"
        }
    ],
    "sg:phone":"+1 703 591 1676",
    "sg:postcode":"22150",
    "sg:province":"VA",
    "sg:tags":[
        "automotive"
    ],
    "wof:name":"T M S",
    "wof:placetype":"venue"
},
  "geometry": {"coordinates":[-77.18685499999999,38.78383],"type":"Point"}
}