{
  "type": "Feature",
  "properties": {
    "addr:full":"3700 Columbia Pike Arlington VA 22204",
    "addr:housenumber":"3700",
    "addr:postcode":"22204",
    "addr:street":"Columbia Pike",
    "iso:country":"US",
    "sg:address":"3700 Columbia Pike",
    "sg:city":"Arlington",
    "sg:classifiers":[
        {
            "category":"Autos & Motor Vehicles",
            "subcategory":"Automobile Sales",
            "type":"Retail Goods"
        }
    ],
    "sg:phone":"+1 703 920 7100",
    "sg:postcode":"22204",
    "sg:province":"VA",
    "sg:tags":[
        "dealers-used",
        "car",
        "used",
        "cars-wholesale",
        "new"
    ],
    "wof:name":"Autos by Good Guys",
    "wof:placetype":"venue"
},
  "geometry": {"coordinates":[-77.09520000000001,38.8606],"type":"Point"}
}