{
  "type": "Feature",
  "properties": {
    "addr:full":"45 Broad Street Rd Manakin Sabot VA 23103",
    "addr:housenumber":"45",
    "addr:postcode":"sabot;23103",
    "addr:street":"Broad Street Rd",
    "iso:country":"US",
    "sg:address":"45 Broad Street Rd",
    "sg:city":"Manakin Sabot",
    "sg:classifiers":[
        {
            "category":"Food & Beverages",
            "subcategory":"Groceries & Convenience Stores",
            "type":"Retail Goods"
        }
    ],
    "sg:phone":"+1 804 784 1263",
    "sg:postcode":"23103",
    "sg:province":"VA",
    "sg:tags":[
        "station",
        "gasoline"
    ],
    "wof:name":"Country Store The",
    "wof:placetype":"venue"
},
  "geometry": {"coordinates":[-77.68218299999999,37.669831],"type":"Point"}
}