{
  "type": "Feature",
  "properties": {
    "iso:country":"US",
    "sg:address":"1365 Stephens Rd",
    "sg:city":"Virginia Beach",
    "sg:classifiers":[
        {
            "category":"Professional",
            "type":"Services"
        }
    ],
    "sg:phone":"+1 757 481 6827",
    "sg:postcode":"23454",
    "sg:province":"VA",
    "wof:name":"Mli Inc",
    "wof:placetype":"venue"
},
  "geometry": {"coordinates":[-76.030738,36.879651],"type":"Point"}
}