{
  "type": "Feature",
  "properties": {
    "iso:country":"US",
    "sg:address":"3005 Valley Stream Dr",
    "sg:city":"Roanoke",
    "sg:classifiers":[
        {
            "category":"Retail",
            "subcategory":"Auto Repair",
            "type":"Services"
        }
    ],
    "sg:phone":"+1 540 427 4887",
    "sg:postcode":"24014",
    "sg:province":"VA",
    "sg:tags":[
        "repairing",
        "automobile"
    ],
    "wof:name":"Monro Muffler Brake & Svc",
    "wof:placetype":"venue"
},
  "geometry": {"coordinates":[-79.910426,37.237275],"type":"Point"}
}