{
  "type": "Feature",
  "properties": {
    "addr:full":"11321 Nuckols Rd Glen Allen VA 23059",
    "addr:housenumber":"11321",
    "addr:postcode":"23059",
    "addr:street":"Nuckols Rd",
    "iso:country":"US",
    "sg:address":"11321 Nuckols Rd",
    "sg:city":"Glen Allen",
    "sg:classifiers":[
        {
            "category":"Restaurant",
            "type":"Food & Drink"
        }
    ],
    "sg:menulink":"http://www.allmenus.com/va/three-chopt/236494-tropical-smoothie/menu/",
    "sg:phone":"+1 804 346 5101",
    "sg:postcode":"23059",
    "sg:province":"VA",
    "sg:tags":[
        "smoothy",
        "juice",
        "american"
    ],
    "wof:name":"Tropical Smoothie",
    "wof:placetype":"venue"
},
  "geometry": {"coordinates":[-77.58654,37.68456],"type":"Point"}
}