{
  "type": "Feature",
  "properties": {
    "addr:full":"4404 36th St N Arlington VA 22207",
    "addr:housenumber":"4404",
    "addr:postcode":"22207",
    "addr:street":"36Th St N",
    "iso:country":"US",
    "sg:address":"4404 36th St N",
    "sg:city":"Arlington",
    "sg:classifiers":[
        {
            "category":"Banks & Credit Unions",
            "subcategory":"Bank",
            "type":"Services"
        }
    ],
    "sg:phone":"+1 703 536 4770",
    "sg:postcode":"22207",
    "sg:province":"VA",
    "sg:tags":[
        "mortgage"
    ],
    "wof:name":"John A Dreswick C D R",
    "wof:placetype":"venue"
},
  "geometry": {"coordinates":[-77.12670300000001,38.916762],"type":"Point"}
}