{
  "type": "Feature",
  "properties": {
    "iso:country":"US",
    "sg:address":"3520 Courthouse Rd",
    "sg:city":"Richmond",
    "sg:classifiers":[
        {
            "category":"Real Estate",
            "subcategory":"Surveying",
            "type":"Services"
        }
    ],
    "sg:phone":"+1 804 745 2876",
    "sg:postcode":"23236",
    "sg:province":"VA",
    "sg:tags":[
        "civil",
        "surveyor",
        "engineering",
        "land",
        "planning"
    ],
    "sg:website":"www.pottsminter.com",
    "wof:name":"Potts Minter & Assoc PC",
    "wof:placetype":"venue"
},
  "geometry": {"coordinates":[-77.58207,37.444246],"type":"Point"}
}