{
  "type": "Feature",
  "properties": {
    "iso:country":"US",
    "sg:address":"1120 Chatmoss Dr",
    "sg:city":"Virginia Beach",
    "sg:classifiers":[
        {
            "category":"Wholesale",
            "subcategory":"Hardware",
            "type":"Manufacturing & Wholesale Goods"
        }
    ],
    "sg:phone":"+1 757 495 3255",
    "sg:postcode":"23464",
    "sg:province":"VA",
    "sg:tags":[
        "air",
        "parts",
        "conditioning",
        "supply"
    ],
    "wof:name":"G B Vaughan Co Inc",
    "wof:placetype":"venue"
},
  "geometry": {"coordinates":[-76.17262100000001,36.804143],"type":"Point"}
}