{
  "type": "Feature",
  "properties": {
    "addr:full":"9606 Mercedes Dr Manassas VA 20110",
    "addr:housenumber":"9606",
    "addr:postcode":"20110",
    "addr:street":"Mercedes Dr",
    "iso:country":"US",
    "sg:address":"9606 Mercedes Dr",
    "sg:city":"Manassas",
    "sg:classifiers":[
        {
            "category":"Professional",
            "subcategory":"Employment Agencies",
            "type":"Services"
        }
    ],
    "sg:phone":"+1 703 369 7229",
    "sg:postcode":"20110",
    "sg:province":"VA",
    "wof:name":"Infinite Resources Inc",
    "wof:placetype":"venue"
},
  "geometry": {"coordinates":[-77.45549800000001,38.745108],"type":"Point"}
}