{
  "type": "Feature",
  "properties": {
    "iso:country":"US",
    "sg:address":"5004 Monument Ave",
    "sg:city":"Richmond",
    "sg:classifiers":[
        {
            "category":"Banks & Credit Unions",
            "subcategory":"Investment Brokerage",
            "type":"Services"
        }
    ],
    "sg:phone":"+1 804 353 5651",
    "sg:postcode":"23230",
    "sg:province":"VA",
    "sg:tags":[
        "advisory",
        "financial"
    ],
    "wof:name":"Timber Resource Mgmt",
    "wof:placetype":"venue"
},
  "geometry": {"coordinates":[-77.499066,37.577308],"type":"Point"}
}