{
  "type": "Feature",
  "properties": {
    "addr:full":"4256 Allison Cir Fairfax VA 22030",
    "addr:housenumber":"4256",
    "addr:postcode":"22030",
    "addr:street":"Allison Cir",
    "iso:country":"US",
    "sg:address":"4256 Allison Cir",
    "sg:city":"Fairfax",
    "sg:classifiers":[
        {
            "category":"Food & Beverages",
            "subcategory":"Bakery",
            "type":"Retail Goods"
        }
    ],
    "sg:phone":"+1 703 591 6998",
    "sg:postcode":"22030",
    "sg:province":"VA",
    "wof:name":"Punjabi Roti & Pratha Inc",
    "wof:placetype":"venue"
},
  "geometry": {"coordinates":[-77.318079,38.842701],"type":"Point"}
}