{
  "type": "Feature",
  "properties": {
    "addr:full":"10313 Brickerton Dr Mechanicsville VA 23116",
    "addr:housenumber":"10313",
    "addr:postcode":"23116",
    "addr:street":"Brickerton Dr",
    "iso:country":"US",
    "sg:address":"10313 Brickerton Dr",
    "sg:city":"Mechanicsville",
    "sg:classifiers":[
        {
            "category":"Professional",
            "type":"Services"
        }
    ],
    "sg:phone":"+1 804 550 7260",
    "sg:postcode":"23116",
    "sg:province":"VA",
    "wof:name":"Joseph V Cantafio",
    "wof:placetype":"venue"
},
  "geometry": {"coordinates":[-77.414452,37.688765],"type":"Point"}
}