{
  "type": "Feature",
  "properties": {
    "iso:country":"US",
    "sg:address":"10706 Oldfield Dr",
    "sg:city":"Reston",
    "sg:classifiers":[
        {
            "category":"Professional",
            "subcategory":"Computer Services",
            "type":"Services"
        }
    ],
    "sg:phone":"+1 703 391 0489",
    "sg:postcode":"20191",
    "sg:province":"VA",
    "wof:name":"Cr8ive Inc",
    "wof:placetype":"venue"
},
  "geometry": {"coordinates":[-77.317015,38.940991],"type":"Point"}
}