{
  "type": "Feature",
  "properties": {
    "addr:full":"101 Church St Rich Creek VA 24147",
    "addr:housenumber":"101",
    "addr:postcode":"24147",
    "addr:street":"Church St",
    "iso:country":"US",
    "sg:address":"101 Church St",
    "sg:city":"Rich Creek",
    "sg:classifiers":[
        {
            "category":"Restaurant",
            "type":"Food & Drink"
        }
    ],
    "sg:phone":"+1 540 726 3660",
    "sg:postcode":"24147",
    "sg:province":"VA",
    "wof:name":"New Central Restaurant",
    "wof:placetype":"venue"
},
  "geometry": {"coordinates":[-80.822372,37.383672],"type":"Point"}
}