{
  "type": "Feature",
  "properties": {
    "iso:country":"US",
    "sg:address":"3773 Karlin Ave",
    "sg:city":"Norfolk",
    "sg:classifiers":[
        {
            "category":"Freight",
            "type":"Transportation"
        }
    ],
    "sg:phone":"+1 757 461 0107",
    "sg:postcode":"23502",
    "sg:province":"VA",
    "sg:tags":[
        "operator",
        "local",
        "trucking"
    ],
    "wof:name":"Banks Trucking Co",
    "wof:placetype":"venue"
},
  "geometry": {"coordinates":[-76.23344299999999,36.849234],"type":"Point"}
}