{
  "type": "Feature",
  "properties": {
    "addr:full":"1600 Wildwood Dr Virginia Beach VA 23454",
    "addr:housenumber":"1600",
    "addr:postcode":"23454",
    "addr:street":"Wildwood Dr",
    "iso:country":"US",
    "sg:address":"1600 Wildwood Dr",
    "sg:city":"Virginia Beach",
    "sg:classifiers":[
        {
            "category":"Banks & Credit Unions",
            "subcategory":"Investment Brokerage",
            "type":"Services"
        }
    ],
    "sg:phone":"+1 757 481 2742",
    "sg:postcode":"23454",
    "sg:province":"VA",
    "sg:tags":[
        "advisory",
        "financial"
    ],
    "wof:name":"Weisert Investment Services",
    "wof:placetype":"venue"
},
  "geometry": {"coordinates":[-76.01793000000001,36.863355],"type":"Point"}
}