{
  "type": "Feature",
  "properties": {
    "iso:country":"US",
    "sg:address":"1569 Mill Dam Rd",
    "sg:city":"Virginia Beach",
    "sg:classifiers":[
        {
            "category":"Social Services",
            "subcategory":"Child Care",
            "type":"Services"
        }
    ],
    "sg:phone":"+1 757 481 6078",
    "sg:postcode":"23454",
    "sg:province":"VA",
    "sg:tags":[
        "day"
    ],
    "wof:name":"La Petite Academy 987",
    "wof:placetype":"venue"
},
  "geometry": {"coordinates":[-76.041021,36.878872],"type":"Point"}
}