{
  "type": "Feature",
  "properties": {
    "iso:country":"US",
    "sg:address":"1592 Penniman Rd",
    "sg:city":"Williamsburg",
    "sg:classifiers":[
        {
            "category":"Food & Beverages",
            "subcategory":"Specialty",
            "type":"Retail Goods"
        }
    ],
    "sg:phone":"+1 757 565 1400",
    "sg:postcode":"23185",
    "sg:province":"VA",
    "sg:tags":[
        "tea",
        "coffee"
    ],
    "sg:website":"www.wcoffee.com",
    "wof:name":"Williamsburg Coffee & Tea Co",
    "wof:placetype":"venue"
},
  "geometry": {"coordinates":[-76.64525399999999,37.262817],"type":"Point"}
}