{
  "type": "Feature",
  "properties": {
    "addr:full":"23489 Owen Farm Rd Carrollton VA 23314",
    "addr:housenumber":"23489",
    "addr:postcode":"23314",
    "addr:street":"Owen Farm Rd",
    "iso:country":"US",
    "sg:address":"23489 Owen Farm Rd",
    "sg:city":"Carrollton",
    "sg:classifiers":[
        {
            "category":"Professional",
            "subcategory":"Secretarial Services",
            "type":"Services"
        }
    ],
    "sg:phone":"+1 757 238 9669",
    "sg:postcode":"23314",
    "sg:province":"VA",
    "sg:tags":[
        "reporting"
    ],
    "wof:name":"James Med Transcript",
    "wof:placetype":"venue"
},
  "geometry": {"coordinates":[-76.51822799999999,36.913933],"type":"Point"}
}