{
  "type": "Feature",
  "properties": {
    "iso:country":"US",
    "sg:address":"10700 Midlothian Tpke",
    "sg:city":"Richmond",
    "sg:classifiers":[
        {
            "category":"Education",
            "subcategory":"Special Training",
            "type":"Public Place"
        }
    ],
    "sg:phone":"+1 804 378 8180",
    "sg:postcode":"23235",
    "sg:province":"VA",
    "sg:tags":[
        "school",
        "language"
    ],
    "wof:name":"Spanish Academy & Cultural",
    "wof:placetype":"venue"
},
  "geometry": {"coordinates":[-77.59499099999999,37.50698],"type":"Point"}
}