{
  "type": "Feature",
  "properties": {
    "iso:country":"US",
    "sg:address":"4513 Bainbridge Blvd",
    "sg:city":"Chesapeake",
    "sg:classifiers":[
        {
            "category":"Wholesale",
            "subcategory":"Auto Parts",
            "type":"Manufacturing & Wholesale Goods"
        }
    ],
    "sg:phone":"+1 757 545 8370",
    "sg:postcode":"23320",
    "sg:province":"VA",
    "sg:tags":[
        "used",
        "automobile",
        "equipment",
        "truck",
        "accessories-wholesale",
        "rebuilt",
        "manufacturer"
    ],
    "wof:name":"Johnson's Mustang & TRUCK Parts",
    "wof:placetype":"venue"
},
  "geometry": {"coordinates":[-76.28821600000001,36.770083],"type":"Point"}
}