{
  "type": "Feature",
  "properties": {
    "addr:full":"12797 Tumbling Brook Ln Woodbridge VA 22192",
    "addr:housenumber":"12797",
    "addr:postcode":"22192",
    "addr:street":"Tumbling Brook Ln",
    "iso:country":"US",
    "sg:address":"12797 Tumbling Brook Ln",
    "sg:city":"Woodbridge",
    "sg:classifiers":[
        {
            "category":"Building & Trades",
            "subcategory":"Construction",
            "type":"Services"
        }
    ],
    "sg:phone":"+1 703 909 0802",
    "sg:postcode":"22192",
    "sg:province":"VA",
    "sg:tags":[
        "planning",
        "remodeling",
        "kitchen"
    ],
    "wof:name":"Elwell Kitchens",
    "wof:placetype":"venue"
},
  "geometry": {"coordinates":[-77.271365,38.674369],"type":"Point"}
}