{
  "type": "Feature",
  "properties": {
    "addr:full":"1271 Traway Dr Richmond VA 23235",
    "addr:housenumber":"1271",
    "addr:postcode":"23235",
    "addr:street":"Traway Dr",
    "iso:country":"US",
    "sg:address":"1271 Traway Dr",
    "sg:city":"Richmond",
    "sg:classifiers":[
        {
            "category":"Professional",
            "subcategory":"Computer Services",
            "type":"Services"
        }
    ],
    "sg:phone":"+1 804 745 3270",
    "sg:postcode":"23235",
    "sg:province":"VA",
    "wof:name":"D&J Services Inc",
    "wof:placetype":"venue"
},
  "geometry": {"coordinates":[-77.542911,37.482627],"type":"Point"}
}