{
  "type": "Feature",
  "properties": {
    "iso:country":"US",
    "sg:address":"621 John Marshall Dr NE",
    "sg:city":"Vienna",
    "sg:classifiers":[
        {
            "category":"Professional",
            "subcategory":"Computer Services",
            "type":"Services"
        }
    ],
    "sg:phone":"+1 703 281 3768",
    "sg:postcode":"22180",
    "sg:province":"VA",
    "sg:tags":[
        "related"
    ],
    "wof:name":"B Tech",
    "wof:placetype":"venue"
},
  "geometry": {"coordinates":[-77.263935,38.916838],"type":"Point"}
}