{
  "type": "Feature",
  "properties": {
    "addr:full":"223 Loudoun St SE Leesburg VA 20175",
    "addr:housenumber":"223",
    "addr:postcode":"20175",
    "addr:street":"Loudoun St Se",
    "iso:country":"US",
    "sg:address":"223 Loudoun St SE",
    "sg:city":"Leesburg",
    "sg:classifiers":[
        {
            "category":"Personal",
            "subcategory":"Beauty Salon",
            "type":"Services"
        }
    ],
    "sg:phone":"+1 703 777 7045",
    "sg:postcode":"20175",
    "sg:province":"VA",
    "wof:name":"Trendz Hair Design Ltd",
    "wof:placetype":"venue"
},
  "geometry": {"coordinates":[-77.560355,39.112727],"type":"Point"}
}