{
  "type": "Feature",
  "properties": {
    "addr:full":"5810 Frament Ave Norfolk VA 23502",
    "addr:housenumber":"5810",
    "addr:postcode":"23502",
    "addr:street":"Frament Ave",
    "iso:country":"US",
    "sg:address":"5810 Frament Ave",
    "sg:city":"Norfolk",
    "sg:classifiers":[
        {
            "category":"Real Estate",
            "subcategory":"Real Estate Operator",
            "type":"Services"
        }
    ],
    "sg:phone":"+1 757 461 0523",
    "sg:postcode":"23502",
    "sg:province":"VA",
    "sg:tags":[
        "building",
        "apartment"
    ],
    "wof:name":"Lexington Park Associates",
    "wof:placetype":"venue"
},
  "geometry": {"coordinates":[-76.204972,36.862942],"type":"Point"}
}