{
  "type": "Feature",
  "properties": {
    "addr:full":"4256 Collins Dr Coeburn VA 24230",
    "addr:housenumber":"4256",
    "addr:postcode":"24230",
    "addr:street":"Collins Dr",
    "iso:country":"US",
    "sg:address":"4256 Collins Dr",
    "sg:city":"Coeburn",
    "sg:classifiers":[
        {
            "category":"Retail",
            "subcategory":"Auto Repair",
            "type":"Services"
        }
    ],
    "sg:phone":"+1 276 395 7559",
    "sg:postcode":"24230",
    "sg:province":"VA",
    "sg:tags":[
        "wrecker"
    ],
    "wof:name":"Liberty Towing Svc",
    "wof:placetype":"venue"
},
  "geometry": {"coordinates":[-82.52691900000001,36.930705],"type":"Point"}
}