{
  "type": "Feature",
  "properties": {
    "addr:full":"10172 W Broad St Glen Allen VA 23060",
    "addr:housenumber":"10172",
    "addr:postcode":"23060",
    "addr:street":"W Broad St",
    "iso:country":"US",
    "sg:address":"10172 W Broad St",
    "sg:city":"Glen Allen",
    "sg:classifiers":[
        {
            "category":"Shopping",
            "type":"Retail Goods"
        }
    ],
    "sg:phone":"+1 804 762 8600",
    "sg:postcode":"23060",
    "sg:province":"VA",
    "sg:tags":[
        "merchandise"
    ],
    "wof:name":"A B C Phones",
    "wof:placetype":"venue"
},
  "geometry": {"coordinates":[-77.57523999999999,37.645908],"type":"Point"}
}