{
  "type": "Feature",
  "properties": {
    "addr:full":"7666 Fullerton Rd Springfield VA 22153",
    "addr:housenumber":"7666",
    "addr:postcode":"22153",
    "addr:street":"Fullerton Rd",
    "iso:country":"US",
    "sg:address":"7666 Fullerton Rd",
    "sg:city":"Springfield",
    "sg:classifiers":[
        {
            "category":"Wholesale",
            "subcategory":"Metals & Minerals",
            "type":"Manufacturing & Wholesale Goods"
        }
    ],
    "sg:phone":"+1 703 644 5434",
    "sg:postcode":"22153",
    "sg:province":"VA",
    "sg:tags":[
        "building",
        "product",
        "aluminum"
    ],
    "wof:name":"Norandex",
    "wof:placetype":"venue"
},
  "geometry": {"coordinates":[-77.211217,38.742283],"type":"Point"}
}