{
  "type": "Feature",
  "properties": {
    "iso:country":"US",
    "sg:address":"716 Kentland Dr",
    "sg:city":"Great Falls",
    "sg:classifiers":[
        {
            "category":"Banks & Credit Unions",
            "subcategory":"Financial Services",
            "type":"Services"
        }
    ],
    "sg:phone":"+1 703 430 4270",
    "sg:postcode":"22066",
    "sg:province":"VA",
    "sg:tags":[
        "investor"
    ],
    "wof:name":"Capital Structures",
    "wof:placetype":"venue"
},
  "geometry": {"coordinates":[-77.351311,39.022846],"type":"Point"}
}