{
  "type": "Feature",
  "properties": {
    "iso:country":"US",
    "sg:address":"22082 Haynes Ln",
    "sg:city":"Carrollton",
    "sg:classifiers":[
        {
            "category":"Building & Trades",
            "subcategory":"Construction",
            "type":"Services"
        }
    ],
    "sg:phone":"+1 757 357 3930",
    "sg:postcode":"23314",
    "sg:province":"VA",
    "sg:tags":[
        "concrete",
        "placing",
        "reinforcement"
    ],
    "wof:name":"Pka Construction Co LLC",
    "wof:placetype":"venue"
},
  "geometry": {"coordinates":[-76.54656,36.962444],"type":"Point"}
}