{
  "type": "Feature",
  "properties": {
    "iso:country":"US",
    "sg:address":"5231 Orchard Hill Dr",
    "sg:city":"Roanoke",
    "sg:classifiers":[
        {
            "category":"Professional",
            "subcategory":"Management & Consulting",
            "type":"Services"
        }
    ],
    "sg:phone":"+1 540 977 5352",
    "sg:postcode":"24019",
    "sg:province":"VA",
    "wof:name":"Capitol Management Consulting",
    "wof:placetype":"venue"
},
  "geometry": {"coordinates":[-79.875817,37.324871],"type":"Point"}
}