{
  "type": "Feature",
  "properties": {
    "addr:full":"2628 Barrett St Virginia Beach VA 23452",
    "addr:housenumber":"2628",
    "addr:postcode":"23452",
    "addr:street":"Barrett St",
    "iso:country":"US",
    "sg:address":"2628 Barrett St",
    "sg:city":"Virginia Beach",
    "sg:classifiers":[
        {
            "category":"Professional",
            "subcategory":"Employment Agencies",
            "type":"Services"
        }
    ],
    "sg:phone":"+1 757 463 5766",
    "sg:postcode":"23452",
    "sg:province":"VA",
    "sg:tags":[
        "opportunity"
    ],
    "sg:website":"www.creditcardrecruiters.com",
    "wof:name":"National Banking Network",
    "wof:placetype":"venue"
},
  "geometry": {"coordinates":[-76.062343,36.836635],"type":"Point"}
}