{
  "type": "Feature",
  "properties": {
    "addr:full":"8615 Hilltop Rd Vienna VA 22180",
    "addr:housenumber":"8615",
    "addr:postcode":"22180",
    "addr:street":"Hilltop Rd",
    "iso:country":"US",
    "sg:address":"8615 Hilltop Rd",
    "sg:city":"Vienna",
    "sg:classifiers":[
        {
            "category":"Social Services",
            "subcategory":"Child Care",
            "type":"Services"
        }
    ],
    "sg:phone":"+1 703 698 0934",
    "sg:postcode":"22180",
    "sg:province":"VA",
    "sg:tags":[
        "day"
    ],
    "wof:name":"Wonder Kids Child Care Inc",
    "wof:placetype":"venue"
},
  "geometry": {"coordinates":[-77.24297300000001,38.877347],"type":"Point"}
}