{
  "type": "Feature",
  "properties": {
    "iso:country":"US",
    "sg:address":"3 S Stafford Ave",
    "sg:city":"Richmond",
    "sg:classifiers":[
        {
            "category":"Restaurant",
            "type":"Food & Drink"
        }
    ],
    "sg:phone":"+1 804 714 3466",
    "sg:postcode":"23220",
    "sg:province":"VA",
    "sg:tags":[
        "caterer"
    ],
    "wof:name":"Catering Offered By Ralfe Finn",
    "wof:placetype":"venue"
},
  "geometry": {"coordinates":[-77.47132999999999,37.549849],"type":"Point"}
}