{
  "type": "Feature",
  "properties": {
    "addr:full":"10120 Fire Tower Rd Toano VA 23168",
    "addr:housenumber":"10120",
    "addr:postcode":"23168",
    "addr:street":"Fire Tower Rd",
    "iso:country":"US",
    "sg:address":"10120 Fire Tower Rd",
    "sg:city":"Toano",
    "sg:classifiers":[
        {
            "category":"Personal",
            "type":"Services"
        }
    ],
    "sg:phone":"+1 757 566 1775",
    "sg:postcode":"23168",
    "sg:province":"VA",
    "sg:tags":[
        "therapist",
        "massage"
    ],
    "wof:name":"Dreamcatchers Therapuetic Rdng",
    "wof:placetype":"venue"
},
  "geometry": {"coordinates":[-76.82274,37.447027],"type":"Point"}
}