{
  "type": "Feature",
  "properties": {
    "addr:full":"8417 Idylwood Rd Vienna VA 22182",
    "addr:housenumber":"8417",
    "addr:postcode":"22182",
    "addr:street":"Idylwood Rd",
    "iso:country":"US",
    "sg:address":"8417 Idylwood Rd",
    "sg:city":"Vienna",
    "sg:classifiers":[
        {
            "category":"Shopping",
            "subcategory":"Computers & Home Electronics",
            "type":"Retail Goods"
        }
    ],
    "sg:phone":"+1 703 849 9601",
    "sg:postcode":"22182",
    "sg:province":"VA",
    "sg:tags":[
        "software"
    ],
    "wof:name":"Tros",
    "wof:placetype":"venue"
},
  "geometry": {"coordinates":[-77.237008,38.899266],"type":"Point"}
}