{
  "type": "Feature",
  "properties": {
    "addr:full":"1305 S Walter Reed Dr Arlington VA 22204",
    "addr:housenumber":"1305",
    "addr:postcode":"22204",
    "addr:street":"S Walter Reed Dr",
    "iso:country":"US",
    "sg:address":"1305 S Walter Reed Dr",
    "sg:city":"Arlington",
    "sg:classifiers":[
        {
            "category":"Building & Trades",
            "subcategory":"Construction",
            "type":"Services"
        }
    ],
    "sg:phone":"+1 703 553 9708",
    "sg:postcode":"22204",
    "sg:province":"VA",
    "sg:tags":[
        "designer",
        "dealer",
        "pool",
        "swimming"
    ],
    "wof:name":"Commons Of Arlington Pool",
    "wof:placetype":"venue"
},
  "geometry": {"coordinates":[-77.087369,38.85946],"type":"Point"}
}