{
  "type": "Feature",
  "properties": {
    "iso:country":"US",
    "sg:address":"8904 S Quay Rd",
    "sg:city":"Suffolk",
    "sg:classifiers":[
        {
            "category":"Organizations",
            "subcategory":"Religious Organization",
            "type":"Services"
        }
    ],
    "sg:phone":"+1 757 657 6188",
    "sg:postcode":"23437",
    "sg:province":"VA",
    "wof:name":"Bethel Assembly of God Church",
    "wof:placetype":"venue"
},
  "geometry": {"coordinates":[-76.84598,36.651009],"type":"Point"}
}