{
  "type": "Feature",
  "properties": {
    "iso:country":"US",
    "sg:address":"700 Nelms Cir",
    "sg:city":"Fredericksburg",
    "sg:classifiers":[
        {
            "category":"Manufacturing",
            "subcategory":"Building Materials",
            "type":"Manufacturing & Wholesale Goods"
        }
    ],
    "sg:phone":"+1 540 373 2553",
    "sg:postcode":"22406",
    "sg:province":"VA",
    "wof:name":"Mastercraft Inc",
    "wof:placetype":"venue"
},
  "geometry": {"coordinates":[-77.497558,38.351204],"type":"Point"}
}