{
  "type": "Feature",
  "properties": {
    "iso:country":"US",
    "sg:address":"3078 Stony Point Rd",
    "sg:city":"Richmond",
    "sg:classifiers":[
        {
            "category":"Restaurant",
            "type":"Food & Drink"
        }
    ],
    "sg:phone":"+1 804 320 7299",
    "sg:postcode":"23235",
    "sg:province":"VA",
    "wof:name":"Subway Sandwiches & Salads",
    "wof:placetype":"venue"
},
  "geometry": {"coordinates":[-77.56596399999999,37.541389],"type":"Point"}
}