{
  "type": "Feature",
  "properties": {
    "iso:country":"US",
    "sg:address":"116 S Sycamore St",
    "sg:city":"Petersburg",
    "sg:classifiers":[
        {
            "category":"Retail",
            "subcategory":"Funeral Services",
            "type":"Services"
        }
    ],
    "sg:phone":"+1 804 861 4880",
    "sg:postcode":"23803",
    "sg:province":"VA",
    "sg:tags":[
        "director"
    ],
    "wof:name":"Kelly Funeral Home LLC",
    "wof:placetype":"venue"
},
  "geometry": {"coordinates":[-77.40280199999999,37.226301],"type":"Point"}
}