{
  "type": "Feature",
  "properties": {
    "iso:country":"US",
    "sg:address":"1791 Cambridge Dr",
    "sg:city":"Richmond",
    "sg:classifiers":[
        {
            "category":"Banks & Credit Unions",
            "subcategory":"Bank",
            "type":"Services"
        }
    ],
    "sg:phone":"+1 804 741 4440",
    "sg:postcode":"23238",
    "sg:province":"VA",
    "sg:tags":[
        "broker",
        "mortgage"
    ],
    "wof:name":"Bridge Capital Corp",
    "wof:placetype":"venue"
},
  "geometry": {"coordinates":[-77.63473399999999,37.615259],"type":"Point"}
}