{
  "type": "Feature",
  "properties": {
    "addr:full":"7426 Sudley Rd Manassas VA 20109",
    "addr:housenumber":"7426",
    "addr:postcode":"20109",
    "addr:street":"Sudley Rd",
    "iso:country":"US",
    "sg:address":"7426 Sudley Rd",
    "sg:city":"Manassas",
    "sg:classifiers":[
        {
            "category":"Retail",
            "subcategory":"Portrait Studio",
            "type":"Services"
        },
        {
            "category":"Banks & Credit Unions",
            "subcategory":"Bank",
            "type":"Services"
        }
    ],
    "sg:phone":"+1 703 551 2318",
    "sg:postcode":"20109",
    "sg:province":"VA",
    "sg:tags":[
        "cashing",
        "photographer",
        "check",
        "passport"
    ],
    "wof:name":"Eagle Check Cashing Co",
    "wof:placetype":"venue"
},
  "geometry": {"coordinates":[-77.515912,38.79175],"type":"Point"}
}