{
  "type": "Feature",
  "properties": {
    "addr:full":"556 Newtown Rd Virginia Beach VA 23462",
    "addr:housenumber":"556",
    "addr:postcode":"23462",
    "addr:street":"Newtown Rd",
    "iso:country":"US",
    "sg:address":"556 Newtown Rd",
    "sg:city":"Virginia Beach",
    "sg:classifiers":[
        {
            "category":"Restaurant",
            "type":"Food & Drink"
        }
    ],
    "sg:phone":"+1 757 490 9727",
    "sg:postcode":"23462",
    "sg:province":"VA",
    "sg:tags":[
        "fast"
    ],
    "wof:name":"KFC",
    "wof:placetype":"venue"
},
  "geometry": {"coordinates":[-76.176292,36.857834],"type":"Point"}
}