{
  "type": "Feature",
  "properties": {
    "addr:full":"8318 Peaks Rd Hanover VA 23069",
    "addr:housenumber":"8318",
    "addr:postcode":"23069",
    "addr:street":"Peaks Rd",
    "iso:country":"US",
    "sg:address":"8318 Peaks Rd",
    "sg:city":"Hanover",
    "sg:classifiers":[
        {
            "category":"Building & Trades",
            "subcategory":"Plumbing",
            "type":"Services"
        }
    ],
    "sg:phone":"+1 804 746 5030",
    "sg:postcode":"23069",
    "sg:province":"VA",
    "sg:tags":[
        "plumbing",
        "air",
        "heating",
        "conditioning",
        "contractor"
    ],
    "wof:name":"Paul Brown Plumbing & Heating",
    "wof:placetype":"venue"
},
  "geometry": {"coordinates":[-77.390916,37.722952],"type":"Point"}
}