{
  "type": "Feature",
  "properties": {
    "addr:full":"11504 Allecingie Pkwy Richmond VA 23235",
    "addr:housenumber":"11504",
    "addr:postcode":"23235",
    "addr:street":"Allecingie Pkwy",
    "iso:country":"US",
    "sg:address":"11504 Allecingie Pkwy",
    "sg:city":"Richmond",
    "sg:classifiers":[
        {
            "category":"Professional",
            "subcategory":"Lawyer & Legal Services",
            "type":"Services"
        }
    ],
    "sg:phone":"+1 804 794 3415",
    "sg:postcode":"23235",
    "sg:province":"VA",
    "wof:name":"Solodar & Solodar",
    "wof:placetype":"venue"
},
  "geometry": {"coordinates":[-77.615759,37.519678],"type":"Point"}
}