{
  "type": "Feature",
  "properties": {
    "addr:full":"3381 Mount View Rd Blairs VA 24540",
    "addr:housenumber":"3381",
    "addr:postcode":"24540",
    "addr:street":"Mount View Rd",
    "iso:country":"US",
    "sg:address":"3381 Mount View Rd",
    "sg:city":"Blairs",
    "sg:classifiers":[
        {
            "category":"Wholesale",
            "subcategory":"Petroleum",
            "type":"Manufacturing & Wholesale Goods"
        }
    ],
    "sg:phone":"+1 434 836 4716",
    "sg:postcode":"24540",
    "sg:province":"VA",
    "sg:tags":[
        "refined",
        "pipeline"
    ],
    "wof:name":"Colonial Pipeline Company",
    "wof:placetype":"venue"
},
  "geometry": {"coordinates":[-79.397637,36.675763],"type":"Point"}
}