{
  "type": "Feature",
  "properties": {
    "iso:country":"US",
    "sg:address":"110 S West St",
    "sg:city":"Alexandria",
    "sg:classifiers":[
        {
            "category":"Shopping",
            "subcategory":"Used Merchandise",
            "type":"Retail Goods"
        }
    ],
    "sg:phone":"+1 703 842 7541",
    "sg:postcode":"22314",
    "sg:province":"VA",
    "sg:tags":[
        "shop",
        "consignment"
    ],
    "wof:name":"EZ Auctioning",
    "wof:placetype":"venue"
},
  "geometry": {"coordinates":[-77.05477,38.805011],"type":"Point"}
}