{
  "type": "Feature",
  "properties": {
    "iso:country":"US",
    "sg:address":"11934 Cherry Rd",
    "sg:city":"Fredericksburg",
    "sg:classifiers":[
        {
            "category":"Shopping",
            "subcategory":"Crafts & Fabrics",
            "type":"Retail Goods"
        }
    ],
    "sg:phone":"+1 540 786 5957",
    "sg:postcode":"22407",
    "sg:province":"VA",
    "sg:tags":[
        "shop",
        "sewing"
    ],
    "wof:name":"Fabrics Unlimited Inc",
    "wof:placetype":"venue"
},
  "geometry": {"coordinates":[-77.552755,38.287111],"type":"Point"}
}