{
  "type": "Feature",
  "properties": {
    "addr:full":"11624 Cedar Ln Ashland VA 23005",
    "addr:housenumber":"11624",
    "addr:postcode":"23005",
    "addr:street":"Cedar Ln",
    "iso:country":"US",
    "sg:address":"11624 Cedar Ln",
    "sg:city":"Ashland",
    "sg:classifiers":[
        {
            "category":"Organizations",
            "subcategory":"Religious Organization",
            "type":"Services"
        }
    ],
    "sg:phone":"+1 804 798 6473",
    "sg:postcode":"23005",
    "sg:province":"VA",
    "sg:tags":[
        "church"
    ],
    "wof:name":"First Baptist Church Of Elmont",
    "wof:placetype":"venue"
},
  "geometry": {"coordinates":[-77.507768,37.713374],"type":"Point"}
}