{
  "type": "Feature",
  "properties": {
    "iso:country":"US",
    "sg:address":"8422 Richmond Hwy Apt 80",
    "sg:city":"Alexandria",
    "sg:classifiers":[
        {
            "category":"Building & Trades",
            "subcategory":"Construction",
            "type":"Services"
        }
    ],
    "sg:phone":"+1 703 780 8464",
    "sg:postcode":"22309",
    "sg:province":"VA",
    "sg:tags":[
        "mason",
        "masonry",
        "industrial",
        "contractors-commercial",
        "contractor"
    ],
    "wof:name":"Rg Masonry",
    "wof:placetype":"venue"
},
  "geometry": {"coordinates":[-77.10817,38.729179],"type":"Point"}
}