{
  "type": "Feature",
  "properties": {
    "addr:full":"18 Auburn Ct Alexandria VA 22305",
    "addr:housenumber":"18",
    "addr:postcode":"22305",
    "addr:street":"Auburn Ct",
    "iso:country":"US",
    "sg:address":"18 Auburn Ct",
    "sg:city":"Alexandria",
    "sg:classifiers":[
        {
            "category":"Personal",
            "type":"Services"
        }
    ],
    "sg:phone":"+1 703 684 5366",
    "sg:postcode":"22305",
    "sg:province":"VA",
    "wof:name":"David Logan Cmt",
    "wof:placetype":"venue"
},
  "geometry": {"coordinates":[-77.057455,38.833815],"type":"Point"}
}