{
  "type": "Feature",
  "properties": {
    "addr:full":"11600 Long Meadow Dr Glen Allen VA 23059",
    "addr:housenumber":"11600",
    "addr:postcode":"23059",
    "addr:street":"Long Meadow Dr",
    "iso:country":"US",
    "sg:address":"11600 Long Meadow Dr",
    "sg:city":"Glen Allen",
    "sg:classifiers":[
        {
            "category":"Real Estate",
            "subcategory":"Real Estate Operator",
            "type":"Services"
        }
    ],
    "sg:phone":"+1 804 553 4546",
    "sg:postcode":"23059",
    "sg:province":"VA",
    "sg:tags":[
        "building",
        "nonresidential"
    ],
    "wof:name":"Donald R Cone",
    "wof:placetype":"venue"
},
  "geometry": {"coordinates":[-77.52961999999999,37.690561],"type":"Point"}
}