{
  "type": "Feature",
  "properties": {
    "iso:country":"US",
    "sg:address":"3925 S Main St",
    "sg:city":"Christiansburg",
    "sg:classifiers":[
        {
            "category":"Retail",
            "subcategory":"Auto Repair",
            "type":"Services"
        }
    ],
    "sg:phone":"+1 540 552 6731",
    "sg:postcode":"24073",
    "sg:province":"VA",
    "sg:tags":[
        "general"
    ],
    "wof:name":"Gabor Import Car Service Inc",
    "wof:placetype":"venue"
},
  "geometry": {"coordinates":[-80.407039,37.187317],"type":"Point"}
}