{
  "type": "Feature",
  "properties": {
    "addr:full":"147 E Main St Martinsville VA 24112",
    "addr:housenumber":"147",
    "addr:postcode":"24112",
    "addr:street":"E Main St",
    "iso:country":"US",
    "sg:address":"147 E Main St",
    "sg:city":"Martinsville",
    "sg:classifiers":[
        {
            "category":"Restaurant",
            "type":"Food & Drink"
        }
    ],
    "sg:phone":"+1 276 638 8930",
    "sg:postcode":"24112",
    "sg:province":"VA",
    "wof:name":"Hometown USA",
    "wof:placetype":"venue"
},
  "geometry": {"coordinates":[-79.87042599999999,36.691049],"type":"Point"}
}