{
  "type": "Feature",
  "properties": {
    "iso:country":"US",
    "sg:address":"377 Mt Jackson Rd",
    "sg:city":"Mt Jackson",
    "sg:classifiers":[
        {
            "category":"Freight",
            "type":"Transportation"
        }
    ],
    "sg:phone":"+1 540 477 3000",
    "sg:postcode":"22842",
    "sg:province":"VA",
    "sg:tags":[
        "warehouse",
        "public"
    ],
    "wof:name":"Mt Jackson Press Inc",
    "wof:placetype":"venue"
},
  "geometry": {"coordinates":[-78.64939699999999,38.76476],"type":"Point"}
}