{
  "type": "Feature",
  "properties": {
    "iso:country":"US",
    "sg:address":"40 Appalachian Ridge Rd",
    "sg:city":"Front Royal",
    "sg:classifiers":[
        {
            "category":"Professional",
            "subcategory":"Management & Consulting",
            "type":"Services"
        }
    ],
    "sg:phone":"+1 540 636 4899",
    "sg:postcode":"22630",
    "sg:province":"VA",
    "wof:name":"Nutrition Zone",
    "wof:placetype":"venue"
},
  "geometry": {"coordinates":[-78.12701800000001,38.875451],"type":"Point"}
}