{
  "type": "Feature",
  "properties": {
    "addr:full":"322 Pierce's Mill Rd Amherst VA 24521",
    "addr:housenumber":"322",
    "addr:postcode":"24521",
    "addr:street":"Pierce'S Mill Rd",
    "iso:country":"US",
    "sg:address":"322 Pierce's Mill Rd",
    "sg:city":"Amherst",
    "sg:classifiers":[
        {
            "category":"Retail",
            "subcategory":"Repair Shop",
            "type":"Services"
        }
    ],
    "sg:phone":"+1 434 946 2583",
    "sg:postcode":"24521",
    "sg:province":"VA",
    "sg:tags":[
        "taxidermist"
    ],
    "wof:name":"Woods & Water Alive Taxidermy",
    "wof:placetype":"venue"
},
  "geometry": {"coordinates":[-78.994163,37.56549],"type":"Point"}
}