{
  "type": "Feature",
  "properties": {
    "addr:full":"10 E Washington St Middleburg VA 20117",
    "addr:housenumber":"10",
    "addr:postcode":"20117",
    "addr:street":"E Washington St",
    "iso:country":"US",
    "sg:address":"10 E Washington St",
    "sg:city":"Middleburg",
    "sg:classifiers":[
        {
            "category":"Utilities",
            "subcategory":"Refuse",
            "type":"Services"
        }
    ],
    "sg:phone":"+1 540 687 6336",
    "sg:postcode":"20117",
    "sg:province":"VA",
    "sg:tags":[
        "garbage",
        "system",
        "collection"
    ],
    "wof:name":"Robinson's Refuse",
    "wof:placetype":"venue"
},
  "geometry": {"coordinates":[-77.73427599999999,38.969384],"type":"Point"}
}