{
  "type": "Feature",
  "properties": {
    "addr:full":"6508 Beverly Ave Mc Lean VA 22101",
    "addr:housenumber":"6508",
    "addr:postcode":"22101",
    "addr:street":"Beverly Ave Mc Lean",
    "iso:country":"US",
    "sg:address":"6508 Beverly Ave",
    "sg:city":"Mc Lean",
    "sg:classifiers":[
        {
            "category":"Professional",
            "subcategory":"Business Services",
            "type":"Services"
        }
    ],
    "sg:phone":"+1 703 734 7900",
    "sg:postcode":"22101",
    "sg:province":"VA",
    "wof:name":"Interiors By Decorating Den",
    "wof:placetype":"venue"
},
  "geometry": {"coordinates":[-77.165823,38.917881],"type":"Point"}
}