{
  "type": "Feature",
  "properties": {
    "iso:country":"US",
    "sg:address":"1244 Baker Rd",
    "sg:city":"Virginia Beach",
    "sg:classifiers":[
        {
            "category":"Retail",
            "subcategory":"Auto Repair",
            "type":"Services"
        }
    ],
    "sg:phone":"+1 757 460 9700",
    "sg:postcode":"23455",
    "sg:province":"VA",
    "sg:tags":[
        "wrecker"
    ],
    "wof:name":"Century Towing Svc",
    "wof:placetype":"venue"
},
  "geometry": {"coordinates":[-76.18369300000001,36.887283],"type":"Point"}
}