{
  "type": "Feature",
  "properties": {
    "iso:country":"US",
    "sg:address":"3103 Scottsville Rd",
    "sg:city":"Charlottesville",
    "sg:classifiers":[
        {
            "category":"Food & Beverages",
            "subcategory":"Groceries & Convenience Stores",
            "type":"Retail Goods"
        }
    ],
    "sg:phone":"+1 434 979 4924",
    "sg:postcode":"22902",
    "sg:province":"VA",
    "wof:name":"Ys Enterprise Llc",
    "wof:placetype":"venue"
},
  "geometry": {"coordinates":[-78.534342,37.948501],"type":"Point"}
}