{
  "type": "Feature",
  "properties": {
    "addr:full":"2800 E Broad St Richmond VA 23223",
    "addr:housenumber":"2800",
    "addr:postcode":"23223",
    "addr:street":"E Broad St",
    "iso:country":"US",
    "sg:address":"2800 E Broad St",
    "sg:city":"Richmond",
    "sg:classifiers":[
        {
            "category":"Restaurant",
            "type":"Food & Drink"
        }
    ],
    "sg:phone":"+1 804 648 0360",
    "sg:postcode":"23223",
    "sg:province":"VA",
    "wof:name":"Hill Cafe",
    "wof:placetype":"venue"
},
  "geometry": {"coordinates":[-77.415188,37.52943],"type":"Point"}
}