{
  "type": "Feature",
  "properties": {
    "iso:country":"US",
    "sg:address":"330 Hickory Ln",
    "sg:city":"Emporia",
    "sg:classifiers":[
        {
            "category":"Building & Trades",
            "subcategory":"Construction",
            "type":"Services"
        }
    ],
    "sg:phone":"+1 434 634 4429",
    "sg:postcode":"23847",
    "sg:province":"VA",
    "sg:tags":[
        "house"
    ],
    "wof:name":"Rhoads Gene Builders",
    "wof:placetype":"venue"
},
  "geometry": {"coordinates":[-77.653873,36.642253],"type":"Point"}
}