{
  "type": "Feature",
  "properties": {
    "addr:full":"325 Florence Ave Waynesboro VA 22980",
    "addr:housenumber":"325",
    "addr:postcode":"22980",
    "addr:street":"Florence Ave",
    "iso:country":"US",
    "sg:address":"325 Florence Ave",
    "sg:city":"Waynesboro",
    "sg:classifiers":[
        {
            "category":"Organizations",
            "subcategory":"Religious Organization",
            "type":"Services"
        }
    ],
    "sg:phone":"+1 540 943 1541",
    "sg:postcode":"22980",
    "sg:province":"VA",
    "sg:tags":[
        "clergy"
    ],
    "wof:name":"Jerry H Cline",
    "wof:placetype":"venue"
},
  "geometry": {"coordinates":[-78.888051,38.074858],"type":"Point"}
}