{
  "type": "Feature",
  "properties": {
    "addr:full":"407 Spring Valley Rd Lexington VA 24450",
    "addr:housenumber":"407",
    "addr:postcode":"24450",
    "addr:street":"Spring Valley Rd",
    "iso:country":"US",
    "sg:address":"407 Spring Valley Rd",
    "sg:city":"Lexington",
    "sg:classifiers":[
        {
            "category":"Professional",
            "subcategory":"Business Services",
            "type":"Services"
        }
    ],
    "sg:phone":"+1 540 464 1195",
    "sg:postcode":"24450",
    "sg:province":"VA",
    "sg:tags":[
        "group"
    ],
    "wof:name":"Schola Antiqua",
    "wof:placetype":"venue"
},
  "geometry": {"coordinates":[-79.503163,37.78974],"type":"Point"}
}