{
  "type": "Feature",
  "properties": {
    "addr:full":"112 Country Club Dr SE Blacksburg VA 24060",
    "addr:housenumber":"112",
    "addr:postcode":"24060",
    "addr:street":"Country Club Dr Se",
    "iso:country":"US",
    "sg:address":"112 Country Club Dr SE",
    "sg:city":"Blacksburg",
    "sg:classifiers":[
        {
            "category":"Shopping",
            "subcategory":"Musical Instruments",
            "type":"Retail Goods"
        }
    ],
    "sg:phone":"+1 540 951 1801",
    "sg:postcode":"24060",
    "sg:province":"VA",
    "wof:name":"Music Shop Inc",
    "wof:placetype":"venue"
},
  "geometry": {"coordinates":[-80.401681,37.217928],"type":"Point"}
}