{
  "type": "Feature",
  "properties": {
    "iso:country":"US",
    "sg:address":"1105 Roanoke St",
    "sg:city":"Christiansburg",
    "sg:classifiers":[
        {
            "category":"Retail",
            "subcategory":"Car Wash",
            "type":"Services"
        }
    ],
    "sg:phone":"+1 540 381 5593",
    "sg:postcode":"24073",
    "sg:province":"VA",
    "sg:tags":[
        "automobile",
        "detail",
        "clean"
    ],
    "wof:name":"Davis Car Care",
    "wof:placetype":"venue"
},
  "geometry": {"coordinates":[-80.38845000000001,37.134188],"type":"Point"}
}