{
  "type": "Feature",
  "properties": {
    "addr:full":"1312 S Main St Blacksburg VA 24060",
    "addr:housenumber":"1312",
    "addr:postcode":"24060",
    "addr:street":"S Main St",
    "iso:country":"US",
    "sg:address":"1312 S Main St",
    "sg:city":"Blacksburg",
    "sg:classifiers":[
        {
            "category":"Professional",
            "subcategory":"Business Services",
            "type":"Services"
        }
    ],
    "sg:phone":"+1 540 951 9347",
    "sg:postcode":"24060",
    "sg:province":"VA",
    "sg:tags":[
        "interior",
        "consultant",
        "design",
        "decorator"
    ],
    "wof:name":"Design Interiors Inc",
    "wof:placetype":"venue"
},
  "geometry": {"coordinates":[-80.401775,37.217625],"type":"Point"}
}