{
  "type": "Feature",
  "properties": {
    "addr:full":"1500 Tyler Ave Radford VA 24141",
    "addr:housenumber":"1500",
    "addr:postcode":"24141",
    "addr:street":"Tyler Ave",
    "iso:country":"US",
    "sg:address":"1500 Tyler Ave",
    "sg:city":"Radford",
    "sg:classifiers":[
        {
            "category":"Retail",
            "subcategory":"Auto Rental",
            "type":"Services"
        }
    ],
    "sg:phone":"+1 540 731 1159",
    "sg:postcode":"24141",
    "sg:province":"VA",
    "sg:tags":[
        "renting",
        "automobile"
    ],
    "wof:name":"Enterprise Rent-A-Car",
    "wof:placetype":"venue"
},
  "geometry": {"coordinates":[-80.541826,37.128122],"type":"Point"}
}