{
  "type": "Feature",
  "properties": {
    "addr:full":"5800 Iron Willow Ct Alexandria VA 22310",
    "addr:housenumber":"5800",
    "addr:postcode":"22310",
    "addr:street":"Iron Willow Ct",
    "iso:country":"US",
    "sg:address":"5800 Iron Willow Ct",
    "sg:city":"Alexandria",
    "sg:classifiers":[
        {
            "category":"Professional",
            "subcategory":"Business Services",
            "type":"Services"
        }
    ],
    "sg:phone":"+1 703 922 8333",
    "sg:postcode":"22310",
    "sg:province":"VA",
    "sg:tags":[
        "real estate"
    ],
    "sg:website":"www.realestatebuddy.com",
    "wof:name":"Chuck & Buddy Enterprises",
    "wof:placetype":"venue"
},
  "geometry": {"coordinates":[-77.134141,38.78965],"type":"Point"}
}