{
  "type": "Feature",
  "properties": {
    "addr:full":"4701 Fries Rd Galax VA 24333",
    "addr:postcode":"4701;24333",
    "addr:street":"Fries Rd",
    "iso:country":"US",
    "sg:address":"4701 Fries Rd",
    "sg:city":"Galax",
    "sg:classifiers":[
        {
            "category":"Real Estate",
            "subcategory":"Real Estate Operator",
            "type":"Services"
        }
    ],
    "sg:phone":"+1 276 744 7837",
    "sg:postcode":"24333",
    "sg:province":"VA",
    "sg:tags":[
        "building",
        "nonresidential"
    ],
    "wof:name":"New River Properties Inc",
    "wof:placetype":"venue"
},
  "geometry": {"coordinates":[-80.95100600000001,36.705394],"type":"Point"}
}