{
  "type": "Feature",
  "properties": {
    "iso:country":"US",
    "sg:address":"2646 Roadside Ln",
    "sg:city":"Chesapeake",
    "sg:classifiers":[
        {
            "category":"Organizations",
            "subcategory":"Religious Organization",
            "type":"Services"
        }
    ],
    "sg:phone":"+1 757 461 4848",
    "sg:postcode":"23325",
    "sg:province":"VA",
    "wof:name":"Hezekiah Family Worship Center",
    "wof:placetype":"venue"
},
  "geometry": {"coordinates":[-76.254829,36.803743],"type":"Point"}
}