{
  "type": "Feature",
  "properties": {
    "iso:country":"US",
    "sg:address":"21595 Smith Switch Rd",
    "sg:city":"Ashburn",
    "sg:classifiers":[
        {
            "category":"Restaurant",
            "type":"Food & Drink"
        }
    ],
    "sg:phone":"+1 703 726 6377",
    "sg:postcode":"20147",
    "sg:province":"VA",
    "wof:name":"Pomodoro Ice House",
    "wof:placetype":"venue"
},
  "geometry": {"coordinates":[-77.466973,39.019367],"type":"Point"}
}