{
  "type": "Feature",
  "properties": {
    "addr:full":"101 US Hwy 23 Gate City VA 24251",
    "addr:housenumber":"101",
    "addr:postcode":"24251",
    "addr:street":"Us Hwy 23 Gate",
    "iso:country":"US",
    "sg:address":"101 US Hwy 23",
    "sg:city":"Gate City",
    "sg:classifiers":[
        {
            "category":"Autos & Motor Vehicles",
            "subcategory":"Auto Supplies",
            "type":"Retail Goods"
        }
    ],
    "sg:phone":"+1 276 386 6263",
    "sg:postcode":"24251",
    "sg:province":"VA",
    "sg:tags":[
        "automobile",
        "parts"
    ],
    "wof:name":"Advance Auto Parts Inc",
    "wof:placetype":"venue"
},
  "geometry": {"coordinates":[-82.568568,36.609997],"type":"Point"}
}