{
  "type": "Feature",
  "properties": {
    "addr:full":"135 Knollwood Dr Rocky Mount VA 24151",
    "addr:housenumber":"135",
    "addr:postcode":"24151",
    "addr:street":"Knollwood Dr",
    "iso:country":"US",
    "sg:address":"135 Knollwood Dr",
    "sg:city":"Rocky Mount",
    "sg:classifiers":[
        {
            "category":"Shopping",
            "subcategory":"Computers & Home Electronics",
            "type":"Retail Goods"
        }
    ],
    "sg:phone":"+1 540 982 3038",
    "sg:postcode":"24151",
    "sg:province":"VA",
    "wof:name":"Computer Simplicity Inc",
    "wof:placetype":"venue"
},
  "geometry": {"coordinates":[-79.893642,36.984986],"type":"Point"}
}