{
  "type": "Feature",
  "properties": {
    "addr:full":"1228 Bradfield Dr SW Leesburg VA 20175",
    "addr:housenumber":"1228",
    "addr:postcode":"20175",
    "addr:street":"Bradfield Dr Sw",
    "iso:country":"US",
    "sg:address":"1228 Bradfield Dr SW",
    "sg:city":"Leesburg",
    "sg:classifiers":[
        {
            "category":"Professional",
            "subcategory":"Management & Consulting",
            "type":"Services"
        }
    ],
    "sg:phone":"+1 703 779 8682",
    "sg:postcode":"20175",
    "sg:province":"VA",
    "wof:name":"Zozer Inc",
    "wof:placetype":"venue"
},
  "geometry": {"coordinates":[-77.588342,39.09775],"type":"Point"}
}