{
  "type": "Feature",
  "properties": {
    "addr:full":"10011 Chesney Dr Spotsylvania VA 22553",
    "addr:housenumber":"10011",
    "addr:postcode":"22553",
    "addr:street":"Chesney Dr",
    "iso:country":"US",
    "sg:address":"10011 Chesney Dr",
    "sg:city":"Spotsylvania",
    "sg:classifiers":[
        {
            "category":"Building & Trades",
            "subcategory":"Construction",
            "type":"Services"
        }
    ],
    "sg:phone":"+1 540 710 0797",
    "sg:postcode":"22553",
    "sg:province":"VA",
    "sg:tags":[
        "home",
        "builder"
    ],
    "wof:name":"Hamlet Homes JV",
    "wof:placetype":"venue"
},
  "geometry": {"coordinates":[-77.54010100000001,38.234728],"type":"Point"}
}