{
  "type": "Feature",
  "properties": {
    "addr:full":"1226 Sam Lions Trl Martinsville VA 24112",
    "addr:housenumber":"1226",
    "addr:postcode":"24112",
    "addr:street":"Sam Lions Trl",
    "iso:country":"US",
    "sg:address":"1226 Sam Lions Trl",
    "sg:city":"Martinsville",
    "sg:classifiers":[
        {
            "category":"Professional",
            "subcategory":"Management & Consulting",
            "type":"Services"
        }
    ],
    "sg:phone":"+1 276 666 4112",
    "sg:postcode":"24112",
    "sg:province":"VA",
    "sg:tags":[
        "consultant",
        "general"
    ],
    "wof:name":"Campbell Advisers PC",
    "wof:placetype":"venue"
},
  "geometry": {"coordinates":[-79.848619,36.666571],"type":"Point"}
}