{
  "type": "Feature",
  "properties": {
    "addr:full":"6808 Ridgeway Dr Springfield VA 22150",
    "addr:housenumber":"6808",
    "addr:postcode":"22150",
    "addr:street":"Ridgeway Dr",
    "iso:country":"US",
    "sg:address":"6808 Ridgeway Dr",
    "sg:city":"Springfield",
    "sg:classifiers":[
        {
            "category":"Professional",
            "type":"Services"
        }
    ],
    "sg:phone":"+1 703 451 3296",
    "sg:postcode":"22150",
    "sg:province":"VA",
    "sg:tags":[
        "establishment"
    ],
    "wof:name":"Harry Zimmerman Assoc Inc",
    "wof:placetype":"venue"
},
  "geometry": {"coordinates":[-77.19406600000001,38.768281],"type":"Point"}
}