{
  "type": "Feature",
  "properties": {
    "iso:country":"US",
    "sg:address":"5412 Louisa Rd",
    "sg:city":"Keswick",
    "sg:classifiers":[
        {
            "category":"Shopping",
            "subcategory":"Department Store",
            "type":"Retail Goods"
        }
    ],
    "sg:phone":"+1 434 295 1866",
    "sg:postcode":"22947",
    "sg:province":"VA",
    "wof:name":"Cismont General Store",
    "wof:placetype":"venue"
},
  "geometry": {"coordinates":[-78.318085,38.05434],"type":"Point"}
}