{
  "type": "Feature",
  "properties": {
    "iso:country":"US",
    "sg:address":"7713 Erie St",
    "sg:city":"Annandale",
    "sg:classifiers":[
        {
            "category":"Insurance",
            "subcategory":"Insurance Agent",
            "type":"Services"
        }
    ],
    "sg:phone":"+1 703 750 3522",
    "sg:postcode":"22003",
    "sg:province":"VA",
    "wof:name":"Vazzana Dooley Inc",
    "wof:placetype":"venue"
},
  "geometry": {"coordinates":[-77.212137,38.821771],"type":"Point"}
}