{
  "type": "Feature",
  "properties": {
    "addr:full":"116 Elmwood Rd Winchester VA 22602",
    "addr:housenumber":"116",
    "addr:postcode":"22602",
    "addr:street":"Elmwood Rd",
    "iso:country":"US",
    "sg:address":"116 Elmwood Rd",
    "sg:city":"Winchester",
    "sg:classifiers":[
        {
            "category":"Retail",
            "subcategory":"Auto Repair",
            "type":"Services"
        }
    ],
    "sg:phone":"+1 540 327 9588",
    "sg:postcode":"22602",
    "sg:province":"VA",
    "sg:tags":[
        "automotive"
    ],
    "wof:name":"Metal Works LLC",
    "wof:placetype":"venue"
},
  "geometry": {"coordinates":[-78.156108,39.138517],"type":"Point"}
}