{
  "type": "Feature",
  "properties": {
    "addr:full":"544 Battlefield Blvd S Chesapeake VA 23322",
    "addr:housenumber":"544",
    "addr:postcode":"23322",
    "addr:street":"Battlefield Blvd",
    "iso:country":"US",
    "sg:address":"544 Battlefield Blvd S",
    "sg:city":"Chesapeake",
    "sg:classifiers":[
        {
            "category":"Banks & Credit Unions",
            "subcategory":"Bank",
            "type":"Services"
        }
    ],
    "sg:phone":"+1 757 482 4421",
    "sg:postcode":"23322",
    "sg:province":"VA",
    "wof:name":"Chesapeake Public School CU",
    "wof:placetype":"venue"
},
  "geometry": {"coordinates":[-76.235733,36.704864],"type":"Point"}
}