{
  "type": "Feature",
  "properties": {
    "iso:country":"US",
    "sg:address":"505 W Queen St",
    "sg:city":"Hampton",
    "sg:classifiers":[
        {
            "category":"Organizations",
            "subcategory":"Religious Organization",
            "type":"Services"
        }
    ],
    "sg:phone":"+1 757 723 9300",
    "sg:postcode":"23669",
    "sg:province":"VA",
    "wof:name":"New Mission AME Zion Church",
    "wof:placetype":"venue"
},
  "geometry": {"coordinates":[-76.35788100000001,37.025959],"type":"Point"}
}