{
  "type": "Feature",
  "properties": {
    "addr:full":"1331 Wenonah Ave Pearisburg VA 24134",
    "addr:housenumber":"1331",
    "addr:postcode":"24134",
    "addr:street":"Wenonah Ave",
    "iso:country":"US",
    "sg:address":"1331 Wenonah Ave",
    "sg:city":"Pearisburg",
    "sg:classifiers":[
        {
            "category":"Food & Beverages",
            "subcategory":"Groceries & Convenience Stores",
            "type":"Retail Goods"
        }
    ],
    "sg:phone":"+1 540 921 2354",
    "sg:postcode":"24134",
    "sg:province":"VA",
    "sg:tags":[
        "grocer"
    ],
    "wof:name":"7 Day Market Inc",
    "wof:placetype":"venue"
},
  "geometry": {"coordinates":[-80.723236,37.327001],"type":"Point"}
}