{
  "type": "Feature",
  "properties": {
    "iso:country":"US",
    "sg:address":"8092 Tysons Corner Ctr",
    "sg:city":"Mclean",
    "sg:classifiers":[
        {
            "category":"Restaurant",
            "type":"Food & Drink"
        }
    ],
    "sg:phone":"+1 703 288 3890",
    "sg:postcode":"22102",
    "sg:province":"VA",
    "sg:tags":[
        "mexican"
    ],
    "sg:website":"www.chipotle.com",
    "wof:name":"Chipotle Mexican Grill",
    "wof:placetype":"venue"
},
  "geometry": {"coordinates":[-77.21970399999999,38.9188],"type":"Point"}
}