{
  "type": "Feature",
  "properties": {
    "iso:country":"US",
    "sg:address":"16 Chester St",
    "sg:city":"Front Royal",
    "sg:classifiers":[
        {
            "category":"Health Services",
            "subcategory":"Doctor",
            "type":"Services"
        }
    ],
    "sg:phone":"+1 540 636 4370",
    "sg:postcode":"22630",
    "sg:province":"VA",
    "sg:tags":[
        "medical"
    ],
    "wof:name":"Timothy S Harlin MD",
    "wof:placetype":"venue"
},
  "geometry": {"coordinates":[-78.190415,38.917823],"type":"Point"}
}