{
  "type": "Feature",
  "properties": {
    "iso:country":"US",
    "sg:address":"12 Hazelwood Dr",
    "sg:city":"Urbanna",
    "sg:classifiers":[
        {
            "category":"Manufacturing",
            "subcategory":"Rubber & Plastics",
            "type":"Manufacturing & Wholesale Goods"
        }
    ],
    "sg:phone":"+1 804 758 0776",
    "sg:postcode":"23175",
    "sg:province":"VA",
    "sg:tags":[
        "manufacture",
        "a",
        "made",
        "from",
        "dice",
        "novelty",
        "retail"
    ],
    "wof:name":"King of Dice",
    "wof:placetype":"venue"
},
  "geometry": {"coordinates":[-76.580386,37.658721],"type":"Point"}
}