{
  "type": "Feature",
  "properties": {
    "iso:country":"US",
    "sg:address":"510 Eastpark Ct",
    "sg:city":"Sandston",
    "sg:classifiers":[
        {
            "category":"Wholesale",
            "subcategory":"Computers",
            "type":"Manufacturing & Wholesale Goods"
        }
    ],
    "sg:phone":"+1 585 272 9769",
    "sg:postcode":"23150",
    "sg:province":"VA",
    "sg:tags":[
        "peripheral",
        "supply"
    ],
    "wof:name":"Meridian Technology Group",
    "wof:placetype":"venue"
},
  "geometry": {"coordinates":[-77.334132,37.531847],"type":"Point"}
}