{
  "type": "Feature",
  "properties": {
    "addr:full":"14659 James Monroe Hwy Leesburg VA 20176",
    "addr:housenumber":"14659",
    "addr:postcode":"20176",
    "addr:street":"James Monroe Hwy",
    "iso:country":"US",
    "sg:address":"14659 James Monroe Hwy",
    "sg:city":"Leesburg",
    "sg:classifiers":[
        {
            "category":"Building & Trades",
            "subcategory":"Construction",
            "type":"Services"
        }
    ],
    "sg:phone":"+1 703 737 6538",
    "sg:postcode":"20176",
    "sg:province":"VA",
    "sg:tags":[
        "dry wall",
        "contractor"
    ],
    "wof:name":"Atlantic Dry Wall",
    "wof:placetype":"venue"
},
  "geometry": {"coordinates":[-77.53607599999999,39.209997],"type":"Point"}
}