{
  "type": "Feature",
  "properties": {
    "iso:country":"US",
    "sg:address":"4436 Park Rd",
    "sg:city":"Alexandria",
    "sg:classifiers":[
        {
            "category":"Professional",
            "subcategory":"Business Services",
            "type":"Services"
        }
    ],
    "sg:phone":"+1 703 750 3835",
    "sg:postcode":"22312",
    "sg:province":"VA",
    "wof:name":"Clarion Hlthcare MGT Group LLC",
    "wof:placetype":"venue"
},
  "geometry": {"coordinates":[-77.153053,38.827674],"type":"Point"}
}