{
  "type": "Feature",
  "properties": {
    "iso:country":"US",
    "sg:address":"201 Picker Cir",
    "sg:city":"Hurt",
    "sg:classifiers":[
        {
            "category":"Building & Trades",
            "subcategory":"Construction",
            "type":"Services"
        }
    ],
    "sg:phone":"+1 434 324 7377",
    "sg:postcode":"24563",
    "sg:province":"VA",
    "sg:tags":[
        "residential",
        "commercial",
        "light"
    ],
    "wof:name":"Scotts Construction & Imprv",
    "wof:placetype":"venue"
},
  "geometry": {"coordinates":[-79.26539,37.082347],"type":"Point"}
}