{
  "type": "Feature",
  "properties": {
    "addr:full":"1011 Amelia St Petersburg VA 23803",
    "addr:housenumber":"1011",
    "addr:postcode":"23803",
    "addr:street":"Amelia St",
    "iso:country":"US",
    "sg:address":"1011 Amelia St",
    "sg:city":"Petersburg",
    "sg:classifiers":[
        {
            "category":"Real Estate",
            "subcategory":"Real Estate Agent",
            "type":"Services"
        }
    ],
    "sg:phone":"+1 804 861 0808",
    "sg:postcode":"23803",
    "sg:province":"VA",
    "sg:tags":[
        "building",
        "operator",
        "apartment"
    ],
    "wof:name":"H L Henshaw Realty Inc",
    "wof:placetype":"venue"
},
  "geometry": {"coordinates":[-77.38537599999999,37.234166],"type":"Point"}
}