{
  "type": "Feature",
  "properties": {
    "iso:country":"US",
    "sg:address":"9797 Braddock Rd",
    "sg:city":"Fairfax",
    "sg:classifiers":[
        {
            "category":"Government",
            "subcategory":"Office",
            "type":"Public Place"
        }
    ],
    "sg:phone":"+1 703 764 4640",
    "sg:postcode":"22032",
    "sg:province":"VA",
    "sg:tags":[
        "state",
        "program",
        "health"
    ],
    "wof:name":"Medical Examiner",
    "wof:placetype":"venue"
},
  "geometry": {"coordinates":[-77.281074,38.823132],"type":"Point"}
}