{
  "type": "Feature",
  "properties": {
    "addr:full":"486 Cambridge St Fredericksburg VA 22405",
    "addr:housenumber":"486",
    "addr:postcode":"22405",
    "addr:street":"Cambridge St",
    "iso:country":"US",
    "sg:address":"486 Cambridge St",
    "sg:city":"Fredericksburg",
    "sg:classifiers":[
        {
            "category":"Autos & Motor Vehicles",
            "subcategory":"Boat Sales",
            "type":"Retail Goods"
        }
    ],
    "sg:phone":"+1 540 288 1684",
    "sg:postcode":"22405",
    "sg:province":"VA",
    "sg:tags":[
        "dealer",
        "sales"
    ],
    "wof:name":"Family Boating Ctr",
    "wof:placetype":"venue"
},
  "geometry": {"coordinates":[-77.458399,38.345797],"type":"Point"}
}