{
  "type": "Feature",
  "properties": {
    "iso:country":"US",
    "sg:address":"2410 Willow Point Arch",
    "sg:city":"Chesapeake",
    "sg:classifiers":[
        {
            "category":"Retail",
            "subcategory":"Laundry & Dry Cleaning",
            "type":"Services"
        }
    ],
    "sg:phone":"+1 757 548 2376",
    "sg:postcode":"23320",
    "sg:province":"VA",
    "wof:name":"Complete Carpet Care",
    "wof:placetype":"venue"
},
  "geometry": {"coordinates":[-76.259322,36.743994],"type":"Point"}
}