{
  "type": "Feature",
  "properties": {
    "addr:full":"19681 Chilesburg Rd Beaverdam VA 23015",
    "addr:housenumber":"19681",
    "addr:postcode":"23015",
    "addr:street":"Chilesburg Rd",
    "iso:country":"US",
    "sg:address":"19681 Chilesburg Rd",
    "sg:city":"Beaverdam",
    "sg:phone":"+1 804 448 2977",
    "sg:postcode":"23015",
    "sg:province":"VA",
    "sg:tags":[
        "farm",
        "field",
        "crop"
    ],
    "wof:name":"Bellemount Farms Inc",
    "wof:placetype":"venue"
},
  "geometry": {"coordinates":[-77.61668400000001,37.998356],"type":"Point"}
}