{
  "type": "Feature",
  "properties": {
    "addr:full":"201 W Holly Ave Sterling VA 20164",
    "addr:housenumber":"201",
    "addr:postcode":"20164",
    "addr:street":"W Holly Ave",
    "iso:country":"US",
    "sg:address":"201 W Holly Ave",
    "sg:city":"Sterling",
    "sg:classifiers":[
        {
            "category":"Education",
            "subcategory":"School",
            "type":"Public Place"
        }
    ],
    "sg:phone":"+1 703 444 7490",
    "sg:postcode":"20164",
    "sg:province":"VA",
    "sg:tags":[
        "middle"
    ],
    "wof:name":"Sterling Middle School",
    "wof:placetype":"venue"
},
  "geometry": {"coordinates":[-77.404251,39.002449],"type":"Point"}
}