{
  "type": "Feature",
  "properties": {
    "addr:full":"18234 Mountain Rd Montpelier VA 23192",
    "addr:housenumber":"18234",
    "addr:postcode":"23192",
    "addr:street":"Mountain Rd",
    "iso:country":"US",
    "sg:address":"18234 Mountain Rd",
    "sg:city":"Montpelier",
    "sg:classifiers":[
        {
            "category":"Wholesale",
            "subcategory":"Sporting Goods",
            "type":"Manufacturing & Wholesale Goods"
        }
    ],
    "sg:phone":"+1 804 883 6552",
    "sg:postcode":"23192",
    "sg:province":"VA",
    "wof:name":"K & L Sports",
    "wof:placetype":"venue"
},
  "geometry": {"coordinates":[-77.729585,37.836359],"type":"Point"}
}