{
  "type": "Feature",
  "properties": {
    "addr:full":"1800 Keswick Dr Norfolk VA 23518",
    "addr:housenumber":"1800",
    "addr:postcode":"23518",
    "addr:street":"Keswick Dr",
    "iso:country":"US",
    "sg:address":"1800 Keswick Dr",
    "sg:city":"Norfolk",
    "sg:classifiers":[
        {
            "category":"Health Services",
            "subcategory":"Doctor",
            "type":"Services"
        }
    ],
    "sg:phone":"+1 757 855 3643",
    "sg:postcode":"23518",
    "sg:province":"VA",
    "sg:tags":[
        "dentist"
    ],
    "wof:name":"Calvin L Belkov DDS",
    "wof:placetype":"venue"
},
  "geometry": {"coordinates":[-76.223024,36.904872],"type":"Point"}
}