{
  "type": "Feature",
  "properties": {
    "addr:full":"13609 Twin Team Ln Midlothian VA 23113",
    "addr:housenumber":"13609",
    "addr:postcode":"23113",
    "addr:street":"Twin Team Ln",
    "iso:country":"US",
    "sg:address":"13609 Twin Team Ln",
    "sg:city":"Midlothian",
    "sg:classifiers":[
        {
            "category":"Wholesale",
            "subcategory":"Non-durable Goods",
            "type":"Manufacturing & Wholesale Goods"
        }
    ],
    "sg:phone":"+1 804 794 1009",
    "sg:postcode":"23113",
    "sg:province":"VA",
    "sg:tags":[
        "party",
        "advertising",
        "specialty"
    ],
    "wof:name":"Smith and Associates",
    "wof:placetype":"venue"
},
  "geometry": {"coordinates":[-77.65190200000001,37.541849],"type":"Point"}
}