{
  "type": "Feature",
  "properties": {
    "addr:full":"1076 Shain Ct Great Falls VA 22066",
    "addr:housenumber":"1076",
    "addr:postcode":"22066",
    "addr:street":"Shain Ct",
    "iso:country":"US",
    "sg:address":"1076 Shain Ct",
    "sg:city":"Great Falls",
    "sg:classifiers":[
        {
            "category":"Professional",
            "subcategory":"Business Services",
            "type":"Services"
        }
    ],
    "sg:phone":"+1 703 447 7584",
    "sg:postcode":"22066",
    "sg:province":"VA",
    "wof:name":"Nicsa Group Inc",
    "wof:placetype":"venue"
},
  "geometry": {"coordinates":[-77.33949200000001,38.997407],"type":"Point"}
}