{
  "type": "Feature",
  "properties": {
    "iso:country":"US",
    "sg:address":"830 White Oak Dr",
    "sg:city":"Covington",
    "sg:classifiers":[
        {
            "category":"Education",
            "subcategory":"Special Training",
            "type":"Public Place"
        }
    ],
    "sg:phone":"+1 540 962 9491",
    "sg:postcode":"24426",
    "sg:province":"VA",
    "wof:name":"Divine Mercy Academy",
    "wof:placetype":"venue"
},
  "geometry": {"coordinates":[-80.004851,37.797714],"type":"Point"}
}