{
  "type": "Feature",
  "properties": {
    "iso:country":"US",
    "sg:address":"524 Holston Ave",
    "sg:city":"Bristol",
    "sg:classifiers":[
        {
            "category":"Professional",
            "subcategory":"Lawyer & Legal Services",
            "type":"Services"
        }
    ],
    "sg:phone":"+1 423 764 7700",
    "sg:postcode":"37620",
    "sg:province":"VA",
    "sg:tags":[
        "attorney"
    ],
    "wof:name":"William R Mc Call",
    "wof:placetype":"venue"
},
  "geometry": {"coordinates":[-82.18709800000001,36.588957],"type":"Point"}
}