{
  "type": "Feature",
  "properties": {
    "iso:country":"US",
    "sg:address":"603 King St",
    "sg:city":"Alexandria",
    "sg:classifiers":[
        {
            "category":"Real Estate",
            "subcategory":"Architect",
            "type":"Services"
        }
    ],
    "sg:phone":"+1 703 837 0080",
    "sg:postcode":"22314",
    "sg:province":"VA",
    "sg:tags":[
        "architectural"
    ],
    "wof:name":"Moore Architects PC",
    "wof:placetype":"venue"
},
  "geometry": {"coordinates":[-77.04639,38.805059],"type":"Point"}
}