{
  "type": "Feature",
  "properties": {
    "addr:full":"12463 Iona Sound Dr Bristow VA 20136",
    "addr:housenumber":"12463",
    "addr:postcode":"20136",
    "addr:street":"Iona Sound Dr",
    "iso:country":"US",
    "sg:address":"12463 Iona Sound Dr",
    "sg:city":"Bristow",
    "sg:classifiers":[
        {
            "category":"Professional",
            "subcategory":"Business Services",
            "type":"Services"
        }
    ],
    "sg:phone":"+1 703 393 0915",
    "sg:postcode":"20136",
    "sg:province":"VA",
    "wof:name":"Rehearsal- One",
    "wof:placetype":"venue"
},
  "geometry": {"coordinates":[-77.568462,38.737281],"type":"Point"}
}