{
  "type": "Feature",
  "properties": {
    "addr:full":"105 Lorraine Ave Fredericksburg VA 22408",
    "addr:housenumber":"105",
    "addr:postcode":"22408",
    "addr:street":"Lorraine Ave",
    "iso:country":"US",
    "sg:address":"105 Lorraine Ave",
    "sg:city":"Fredericksburg",
    "sg:classifiers":[
        {
            "category":"Utilities",
            "subcategory":"Cable",
            "type":"Services"
        }
    ],
    "sg:phone":"+1 540 891 7833",
    "sg:postcode":"22408",
    "sg:province":"VA",
    "sg:tags":[
        "television"
    ],
    "wof:name":"TNT Satelite Systems",
    "wof:placetype":"venue"
},
  "geometry": {"coordinates":[-77.49218999999999,38.258901],"type":"Point"}
}