{
  "type": "Feature",
  "properties": {
    "addr:full":"9217 Terrapin Ct Richmond VA 23228",
    "addr:housenumber":"9217",
    "addr:postcode":"23228",
    "addr:street":"Terrapin Ct",
    "iso:country":"US",
    "sg:address":"9217 Terrapin Ct",
    "sg:city":"Richmond",
    "sg:classifiers":[
        {
            "category":"Building & Trades",
            "subcategory":"Construction",
            "type":"Services"
        }
    ],
    "sg:phone":"+1 804 672 6213",
    "sg:postcode":"23228",
    "sg:province":"VA",
    "sg:tags":[
        "steam",
        "cleaning"
    ],
    "wof:name":"E C Mitchell Power Cleaning",
    "wof:placetype":"venue"
},
  "geometry": {"coordinates":[-77.518818,37.641262],"type":"Point"}
}