{
  "type": "Feature",
  "properties": {
    "addr:full":"150 Walker St Lexington VA 24450",
    "addr:housenumber":"150",
    "addr:postcode":"24450",
    "addr:street":"Walker St",
    "iso:country":"US",
    "sg:address":"150 Walker St",
    "sg:city":"Lexington",
    "sg:classifiers":[
        {
            "category":"Food & Beverages",
            "subcategory":"Specialty",
            "type":"Retail Goods"
        }
    ],
    "sg:phone":"+1 540 462 2509",
    "sg:postcode":"24450",
    "sg:province":"VA",
    "wof:name":"Designs For Health",
    "wof:placetype":"venue"
},
  "geometry": {"coordinates":[-79.43643,37.778036],"type":"Point"}
}