{
  "type": "Feature",
  "properties": {
    "iso:country":"US",
    "sg:address":"8003 Trevor Pl",
    "sg:city":"Vienna",
    "sg:classifiers":[
        {
            "category":"Freight",
            "type":"Transportation"
        }
    ],
    "sg:phone":"+1 703 442 4999",
    "sg:postcode":"22182",
    "sg:province":"VA",
    "sg:tags":[
        "moving"
    ],
    "wof:name":"Hometown Movers LLC",
    "wof:placetype":"venue"
},
  "geometry": {"coordinates":[-77.221278,38.903995],"type":"Point"}
}