{
  "type": "Feature",
  "properties": {
    "addr:full":"201 Church St Blackstone VA 23824",
    "addr:housenumber":"201",
    "addr:postcode":"23824",
    "addr:street":"Church St",
    "iso:country":"US",
    "sg:address":"201 Church St",
    "sg:city":"Blackstone",
    "sg:classifiers":[
        {
            "category":"Shopping",
            "subcategory":"Computers & Home Electronics",
            "type":"Retail Goods"
        }
    ],
    "sg:phone":"+1 434 292 6525",
    "sg:postcode":"23824",
    "sg:province":"VA",
    "wof:name":"Computer Factory",
    "wof:placetype":"venue"
},
  "geometry": {"coordinates":[-78.001842,37.076406],"type":"Point"}
}