{
  "type": "Feature",
  "properties": {
    "addr:full":"1075 American Legion Rd Stuart VA 24171",
    "addr:housenumber":"1075",
    "addr:postcode":"24171",
    "addr:street":"American Legion Rd",
    "iso:country":"US",
    "sg:address":"1075 American Legion Rd",
    "sg:city":"Stuart",
    "sg:phone":"+1 276 694 3203",
    "sg:postcode":"24171",
    "sg:province":"VA",
    "sg:tags":[
        "farm"
    ],
    "wof:name":"Levi West",
    "wof:placetype":"venue"
},
  "geometry": {"coordinates":[-80.218497,36.625936],"type":"Point"}
}