{
  "type": "Feature",
  "properties": {
    "addr:full":"6001 Miller Store Rd Norfolk VA 23502",
    "addr:housenumber":"6001",
    "addr:postcode":"23502",
    "addr:street":"Miller Store Rd",
    "iso:country":"US",
    "sg:address":"6001 Miller Store Rd",
    "sg:city":"Norfolk",
    "sg:classifiers":[
        {
            "category":"Building & Trades",
            "subcategory":"Construction",
            "type":"Services"
        }
    ],
    "sg:phone":"+1 757 853 6026",
    "sg:postcode":"23502",
    "sg:province":"VA",
    "sg:tags":[
        "house"
    ],
    "wof:name":"Top Side Designs",
    "wof:placetype":"venue"
},
  "geometry": {"coordinates":[-76.205004,36.882298],"type":"Point"}
}