{
  "type": "Feature",
  "properties": {
    "iso:country":"US",
    "sg:address":"7119 Bradford Cottage Ct",
    "sg:city":"Mechanicsville",
    "sg:classifiers":[
        {
            "category":"Professional",
            "type":"Services"
        }
    ],
    "sg:phone":"+1 804 569 8162",
    "sg:postcode":"23111",
    "sg:province":"VA",
    "wof:name":"Mary Puckett",
    "wof:placetype":"venue"
},
  "geometry": {"coordinates":[-77.347354,37.624534],"type":"Point"}
}