{
  "type": "Feature",
  "properties": {
    "iso:country":"US",
    "sg:address":"7718 Silo Mill Ct",
    "sg:city":"Manassas",
    "sg:classifiers":[
        {
            "category":"Shopping",
            "subcategory":"Stationery & Office Supplies",
            "type":"Retail Goods"
        },
        {
            "category":"Professional",
            "subcategory":"Printing & Photocopies",
            "type":"Services"
        }
    ],
    "sg:phone":"+1 703 794 8311",
    "sg:postcode":"20112",
    "sg:province":"VA",
    "sg:tags":[
        "announcement",
        "services-commercial",
        "invitation"
    ],
    "wof:name":"Babies N Bells 28",
    "wof:placetype":"venue"
},
  "geometry": {"coordinates":[-77.435716,38.687311],"type":"Point"}
}