{
  "type": "Feature",
  "properties": {
    "addr:full":"127 US Hwy 23 Bus Gate City VA 24251",
    "addr:housenumber":"127",
    "addr:postcode":"24251",
    "addr:street":"Us Hwy 23 Bus Gate",
    "iso:country":"US",
    "sg:address":"127 US Hwy 23 Bus",
    "sg:city":"Gate City",
    "sg:classifiers":[
        {
            "category":"Autos & Motor Vehicles",
            "subcategory":"Automobile Sales",
            "type":"Retail Goods"
        }
    ],
    "sg:phone":"+1 276 386 2235",
    "sg:postcode":"24251",
    "sg:province":"VA",
    "sg:tags":[
        "car",
        "dealer"
    ],
    "wof:name":"Wade's Motors",
    "wof:placetype":"venue"
},
  "geometry": {"coordinates":[-82.58213499999999,36.636704],"type":"Point"}
}