{
  "type": "Feature",
  "properties": {
    "iso:country":"US",
    "sg:address":"1904 Byrd Ave",
    "sg:city":"Richmond",
    "sg:classifiers":[
        {
            "category":"Personal",
            "type":"Services"
        }
    ],
    "sg:phone":"+1 804 285 2005",
    "sg:postcode":"23230",
    "sg:province":"VA",
    "wof:name":"Rubies & Pearls",
    "wof:placetype":"venue"
},
  "geometry": {"coordinates":[-77.500497,37.584854],"type":"Point"}
}