{
  "type": "Feature",
  "properties": {
    "addr:full":"47123 Southampton Ct Sterling VA 20165",
    "addr:postcode":"47123;20165",
    "addr:street":"Southampton Ct",
    "iso:country":"US",
    "sg:address":"47123 Southampton Ct",
    "sg:city":"Sterling",
    "sg:classifiers":[
        {
            "category":"Shopping",
            "type":"Retail Goods"
        }
    ],
    "sg:phone":"+1 703 450 5788",
    "sg:postcode":"20165",
    "sg:province":"VA",
    "sg:tags":[
        "merchandise"
    ],
    "wof:name":"Sterling Botanicals",
    "wof:placetype":"venue"
},
  "geometry": {"coordinates":[-77.369618,39.051731],"type":"Point"}
}