{
  "type": "Feature",
  "properties": {
    "iso:country":"US",
    "sg:address":"9623 Ridge View Dr",
    "sg:city":"Marshall",
    "sg:classifiers":[
        {
            "category":"Real Estate",
            "subcategory":"Real Estate Agent",
            "type":"Services"
        }
    ],
    "sg:phone":"+1 540 428 2265",
    "sg:postcode":"20115",
    "sg:province":"VA",
    "wof:name":"Sandy Burke Realty Inc",
    "wof:placetype":"venue"
},
  "geometry": {"coordinates":[-77.898802,38.729835],"type":"Point"}
}