{
  "type": "Feature",
  "properties": {
    "iso:country":"US",
    "sg:address":"536 Granite Ave",
    "sg:city":"Richmond",
    "sg:classifiers":[
        {
            "category":"Personal",
            "subcategory":"Beauty Salon",
            "type":"Services"
        }
    ],
    "sg:phone":"+1 804 673 2581",
    "sg:postcode":"23226",
    "sg:province":"VA",
    "sg:tags":[
        "shop"
    ],
    "wof:name":"K Hair Waves",
    "wof:placetype":"venue"
},
  "geometry": {"coordinates":[-77.51382599999999,37.577721],"type":"Point"}
}