{
  "type": "Feature",
  "properties": {
    "iso:country":"US",
    "sg:address":"4605 Haygood Rd",
    "sg:city":"Virginia Beach",
    "sg:classifiers":[
        {
            "category":"Health Services",
            "subcategory":"Doctor",
            "type":"Services"
        }
    ],
    "sg:phone":"+1 757 464 6228",
    "sg:postcode":"23455",
    "sg:province":"VA",
    "sg:tags":[
        "dentist"
    ],
    "wof:name":"Christopher King DDS",
    "wof:placetype":"venue"
},
  "geometry": {"coordinates":[-76.13459400000001,36.875378],"type":"Point"}
}