{
  "type": "Feature",
  "properties": {
    "addr:full":"723 Smith St Martinsville VA 24112",
    "addr:housenumber":"723",
    "addr:postcode":"24112",
    "addr:street":"Smith St",
    "iso:country":"US",
    "sg:address":"723 Smith St",
    "sg:city":"Martinsville",
    "sg:classifiers":[
        {
            "category":"Wholesale",
            "subcategory":"Construction Materials",
            "type":"Manufacturing & Wholesale Goods"
        }
    ],
    "sg:phone":"+1 276 632 6172",
    "sg:postcode":"24112",
    "sg:province":"VA",
    "wof:name":"Ed Holland Cement Contrac",
    "wof:placetype":"venue"
},
  "geometry": {"coordinates":[-79.88749900000001,36.691921],"type":"Point"}
}