{
  "type": "Feature",
  "properties": {
    "addr:full":"2750 Clifton St NW Roanoke VA 24017",
    "addr:housenumber":"2750",
    "addr:postcode":"24017",
    "addr:street":"Clifton St Nw",
    "iso:country":"US",
    "sg:address":"2750 Clifton St NW",
    "sg:city":"Roanoke",
    "sg:classifiers":[
        {
            "category":"Recreation",
            "type":"Entertainment"
        }
    ],
    "sg:phone":"+1 540 853 2570",
    "sg:postcode":"24017",
    "sg:province":"VA",
    "sg:tags":[
        "club",
        "membership",
        "center"
    ],
    "wof:name":"Villa Heights Recreation Ctr",
    "wof:placetype":"venue"
},
  "geometry": {"coordinates":[-79.978578,37.293513],"type":"Point"}
}