{
  "type": "Feature",
  "properties": {
    "addr:full":"8201 Osborne Tpke Richmond VA 23231",
    "addr:housenumber":"8201",
    "addr:postcode":"23231",
    "addr:street":"Osborne Tpke",
    "iso:country":"US",
    "sg:address":"8201 Osborne Tpke",
    "sg:city":"Richmond",
    "sg:classifiers":[
        {
            "category":"Building & Trades",
            "subcategory":"Construction",
            "type":"Services"
        }
    ],
    "sg:phone":"+1 804 795 2433",
    "sg:postcode":"23231",
    "sg:province":"VA",
    "sg:tags":[
        "home",
        "family"
    ],
    "wof:name":"Country Construction Inc",
    "wof:placetype":"venue"
},
  "geometry": {"coordinates":[-77.39387600000001,37.441972],"type":"Point"}
}