{
  "type": "Feature",
  "properties": {
    "addr:full":"10424 Balls Ford Rd Manassas VA 20109",
    "addr:housenumber":"10424",
    "addr:postcode":"20109",
    "addr:street":"Balls Ford Rd",
    "iso:country":"US",
    "sg:address":"10424 Balls Ford Rd",
    "sg:city":"Manassas",
    "sg:classifiers":[
        {
            "category":"Travel",
            "subcategory":"Hotels & Motels",
            "type":"Entertainment"
        },
        {
            "category":"Retail",
            "subcategory":"Event Space",
            "type":"Services"
        },
        {
            "category":"Travel",
            "subcategory":"Resort",
            "type":"Entertainment"
        }
    ],
    "sg:phone":"+1 571 292 5400",
    "sg:postcode":"20109",
    "sg:province":"VA",
    "sg:tags":[
        "facility",
        "venue",
        "hall",
        "reception",
        "lodging",
        "banquet"
    ],
    "sg:website":"www.holidayinn.com",
    "wof:name":"Holiday Inn Hotel Manassas - Battlefield",
    "wof:placetype":"venue"
},
  "geometry": {"coordinates":[-77.509062,38.800995],"type":"Point"}
}