{
  "type": "Feature",
  "properties": {
    "addr:full":"25467 Sparta Rd Milford VA 22514",
    "addr:housenumber":"25467",
    "addr:postcode":"22514",
    "addr:street":"Sparta Rd",
    "iso:country":"US",
    "sg:address":"25467 Sparta Rd",
    "sg:city":"Milford",
    "sg:classifiers":[
        {
            "category":"Building & Trades",
            "subcategory":"Construction",
            "type":"Services"
        }
    ],
    "sg:phone":"+1 804 633 4461",
    "sg:postcode":"22514",
    "sg:province":"VA",
    "sg:tags":[
        "excavation",
        "contractor"
    ],
    "wof:name":"Caroline Excavators",
    "wof:placetype":"venue"
},
  "geometry": {"coordinates":[-77.202709,37.989395],"type":"Point"}
}