{
  "type": "Feature",
  "properties": {
    "addr:full":"2701 Park Center Dr Alexandria VA 22302",
    "addr:housenumber":"2701",
    "addr:postcode":"22302",
    "addr:street":"Park Center Dr",
    "iso:country":"US",
    "sg:address":"2701 Park Center Dr",
    "sg:city":"Alexandria",
    "sg:classifiers":[
        {
            "category":"Insurance",
            "subcategory":"Insurance Agent",
            "type":"Services"
        },
        {
            "category":"Insurance",
            "subcategory":"Hazard Insurance",
            "type":"Services"
        }
    ],
    "sg:phone":"+1 703 845 0440",
    "sg:postcode":"22302",
    "sg:province":"VA",
    "sg:tags":[
        "adjuster"
    ],
    "wof:name":"Farmers Insurance Group",
    "wof:placetype":"venue"
},
  "geometry": {"coordinates":[-77.104202,38.83342],"type":"Point"}
}