{
  "type": "Feature",
  "properties": {
    "addr:full":"305 E Main St Salem VA 24153",
    "addr:housenumber":"305",
    "addr:postcode":"24153",
    "addr:street":"E Main St",
    "iso:country":"US",
    "sg:address":"305 E Main St",
    "sg:city":"Salem",
    "sg:classifiers":[
        {
            "category":"Government",
            "subcategory":"Court House",
            "type":"Public Place"
        }
    ],
    "sg:phone":"+1 540 387 6205",
    "sg:postcode":"24153",
    "sg:province":"VA",
    "sg:tags":[
        "county"
    ],
    "wof:name":"Roanoke County Circuit Court",
    "wof:placetype":"venue"
},
  "geometry": {"coordinates":[-80.054219,37.293537],"type":"Point"}
}