{
  "type": "Feature",
  "properties": {
    "addr:full":"11719 Fair Oaks Mall Fairfax VA 22033",
    "addr:housenumber":"11719",
    "addr:postcode":"22033",
    "addr:street":"Fair Oaks Mall",
    "iso:country":"US",
    "sg:address":"11719 Fair Oaks Mall",
    "sg:city":"Fairfax",
    "sg:classifiers":[
        {
            "category":"Restaurant",
            "type":"Food & Drink"
        }
    ],
    "sg:phone":"+1 703 352 0587",
    "sg:postcode":"22033",
    "sg:province":"VA",
    "sg:tags":[
        "eating"
    ],
    "wof:name":"Frank & Stein Restaurant",
    "wof:placetype":"venue"
},
  "geometry": {"coordinates":[-77.356928,38.861031],"type":"Point"}
}