{
  "type": "Feature",
  "properties": {
    "addr:full":"849 Old George Washington Hwy N Chesapeake VA 23323",
    "addr:housenumber":"849",
    "addr:postcode":"23323",
    "addr:street":"Old George Washington Hwy N",
    "iso:country":"US",
    "sg:address":"849 Old George Washington Hwy N",
    "sg:city":"Chesapeake",
    "sg:classifiers":[
        {
            "category":"Wholesale",
            "subcategory":"Sporting Goods",
            "type":"Manufacturing & Wholesale Goods"
        }
    ],
    "sg:phone":"+1 757 485 5403",
    "sg:postcode":"23323",
    "sg:province":"VA",
    "wof:name":"Deep Creek Pool & Spa Center",
    "wof:placetype":"venue"
},
  "geometry": {"coordinates":[-76.344189,36.769075],"type":"Point"}
}