{
  "type": "Feature",
  "properties": {
    "iso:country":"US",
    "sg:address":"10726 Jefferson Ave",
    "sg:city":"Newport News",
    "sg:classifiers":[
        {
            "category":"Wholesale",
            "subcategory":"Durable Goods & Equipment",
            "type":"Manufacturing & Wholesale Goods"
        }
    ],
    "sg:phone":"+1 757 599 3377",
    "sg:postcode":"23601",
    "sg:province":"VA",
    "sg:tags":[
        "importer"
    ],
    "wof:name":"Karna International LC",
    "wof:placetype":"venue"
},
  "geometry": {"coordinates":[-76.46031000000001,37.050166],"type":"Point"}
}