{
  "type": "Feature",
  "properties": {
    "iso:country":"US",
    "sg:address":"113 Brook Rd",
    "sg:city":"Yorktown",
    "sg:classifiers":[
        {
            "category":"Building & Trades",
            "subcategory":"Landscaping Services",
            "type":"Services"
        }
    ],
    "sg:phone":"+1 757 898 5025",
    "sg:postcode":"23692",
    "sg:province":"VA",
    "sg:tags":[
        "lawn",
        "maintenance",
        "grounds"
    ],
    "wof:name":"Tye's Lawn Svc",
    "wof:placetype":"venue"
},
  "geometry": {"coordinates":[-76.49897199999999,37.192868],"type":"Point"}
}