{
  "type": "Feature",
  "properties": {
    "iso:country":"US",
    "sg:address":"238 E Beverley St",
    "sg:city":"Staunton",
    "sg:classifiers":[
        {
            "category":"Travel",
            "subcategory":"Hotels & Motels",
            "type":"Entertainment"
        }
    ],
    "sg:phone":"+1 540 886 8200",
    "sg:postcode":"24401",
    "sg:province":"VA",
    "sg:tags":[
        "operation"
    ],
    "sg:website":"www.stauntonva.com",
    "wof:name":"Sampson Eagon Inn",
    "wof:placetype":"venue"
},
  "geometry": {"coordinates":[-79.068872,38.149718],"type":"Point"}
}