{
  "type": "Feature",
  "properties": {
    "iso:country":"US",
    "sg:address":"210 Franklin Rd SW",
    "sg:city":"Roanoke",
    "sg:classifiers":[
        {
            "category":"Government",
            "subcategory":"Police Station",
            "type":"Public Place"
        }
    ],
    "sg:phone":"+1 540 857 2300",
    "sg:postcode":"24011",
    "sg:province":"VA",
    "sg:tags":[
        "federal"
    ],
    "wof:name":"US Alcohol Tobacco & Firearms",
    "wof:placetype":"venue"
},
  "geometry": {"coordinates":[-79.944739,37.268692],"type":"Point"}
}