{
  "type": "Feature",
  "properties": {
    "addr:full":"6648 Hazel Ln Mc Lean VA 22101",
    "addr:housenumber":"6648",
    "addr:postcode":"22101",
    "addr:street":"Hazel Ln Mc Lean",
    "iso:country":"US",
    "sg:address":"6648 Hazel Ln",
    "sg:city":"Mc Lean",
    "sg:classifiers":[
        {
            "category":"Professional",
            "subcategory":"Management & Consulting",
            "type":"Services"
        }
    ],
    "sg:phone":"+1 703 827 2006",
    "sg:postcode":"22101",
    "sg:province":"VA",
    "sg:tags":[
        "business"
    ],
    "wof:name":"A & C Consulting Services LLC",
    "wof:placetype":"venue"
},
  "geometry": {"coordinates":[-77.173243,38.923475],"type":"Point"}
}