{
  "type": "Feature",
  "properties": {
    "iso:country":"US",
    "sg:address":"415 Rotary St",
    "sg:city":"Hampton",
    "sg:classifiers":[
        {
            "category":"Freight",
            "type":"Transportation"
        }
    ],
    "sg:phone":"+1 757 826 5348",
    "sg:postcode":"23661",
    "sg:province":"VA",
    "sg:tags":[
        "mover"
    ],
    "wof:name":"Guardian Storage & Van Corp",
    "wof:placetype":"venue"
},
  "geometry": {"coordinates":[-76.40034799999999,37.008193],"type":"Point"}
}