{
  "type": "Feature",
  "properties": {
    "addr:full":"5 Myra Dr Hampton VA 23661",
    "addr:housenumber":"5",
    "addr:postcode":"23661",
    "addr:street":"Myra Dr",
    "iso:country":"US",
    "sg:address":"5 Myra Dr",
    "sg:city":"Hampton",
    "sg:classifiers":[
        {
            "category":"Building & Trades",
            "subcategory":"Construction",
            "type":"Services"
        }
    ],
    "sg:phone":"+1 757 594 0298",
    "sg:postcode":"23661",
    "sg:province":"VA",
    "sg:tags":[
        "house"
    ],
    "wof:name":"Bcmg Restoration Property Svcs",
    "wof:placetype":"venue"
},
  "geometry": {"coordinates":[-76.413346,37.013261],"type":"Point"}
}