{
  "type": "Feature",
  "properties": {
    "iso:country":"US",
    "sg:address":"4032 Floyd Hwy S",
    "sg:city":"Floyd",
    "sg:classifiers":[
        {
            "category":"Manufacturing",
            "subcategory":"Signs",
            "type":"Manufacturing & Wholesale Goods"
        }
    ],
    "sg:phone":"+1 540 789 4200",
    "sg:postcode":"24091",
    "sg:province":"VA",
    "sg:tags":[
        "specialty",
        "mfg"
    ],
    "wof:name":"Sign Studio",
    "wof:placetype":"venue"
},
  "geometry": {"coordinates":[-80.434015,36.869625],"type":"Point"}
}