{
  "type": "Feature",
  "properties": {
    "addr:full":"315 Caroline St Orange VA 22960",
    "addr:housenumber":"315",
    "addr:postcode":"22960",
    "addr:street":"Caroline St",
    "iso:country":"US",
    "sg:address":"315 Caroline St",
    "sg:city":"Orange",
    "sg:classifiers":[
        {
            "category":"Building & Trades",
            "subcategory":"Construction",
            "type":"Services"
        }
    ],
    "sg:phone":"+1 540 672 9460",
    "sg:postcode":"22960",
    "sg:province":"VA",
    "sg:tags":[
        "cabinet",
        "carpentry",
        "maker",
        "contractor"
    ],
    "wof:name":"Corner Cabinet Shop",
    "wof:placetype":"venue"
},
  "geometry": {"coordinates":[-78.11129699999999,38.236149],"type":"Point"}
}