{
  "type": "Feature",
  "properties": {
    "addr:full":"7717 Sudley Rd Manassas VA 20109",
    "addr:housenumber":"7717",
    "addr:postcode":"20109",
    "addr:street":"Sudley Rd",
    "iso:country":"US",
    "sg:address":"7717 Sudley Rd",
    "sg:city":"Manassas",
    "sg:classifiers":[
        {
            "category":"Retail",
            "subcategory":"Laundry & Dry Cleaning",
            "type":"Services"
        }
    ],
    "sg:phone":"+1 703 392 6618",
    "sg:postcode":"20109",
    "sg:province":"VA",
    "sg:tags":[
        "cleaner"
    ],
    "wof:name":"Green Cleaners",
    "wof:placetype":"venue"
},
  "geometry": {"coordinates":[-77.51419799999999,38.789001],"type":"Point"}
}