{
  "type": "Feature",
  "properties": {
    "addr:full":"5001 Althea Dr Annandale VA 22003",
    "addr:housenumber":"5001",
    "addr:postcode":"22003",
    "addr:street":"Althea Dr",
    "iso:country":"US",
    "sg:address":"5001 Althea Dr",
    "sg:city":"Annandale",
    "sg:classifiers":[
        {
            "category":"Wholesale",
            "subcategory":"Non-durable Goods",
            "type":"Manufacturing & Wholesale Goods"
        }
    ],
    "sg:phone":"+1 703 425 6691",
    "sg:postcode":"22003",
    "sg:province":"VA",
    "wof:name":"Peacock Hill Trading Co",
    "wof:placetype":"venue"
},
  "geometry": {"coordinates":[-77.245819,38.814947],"type":"Point"}
}