{
  "type": "Feature",
  "properties": {
    "addr:full":"1310 Elmart Ln Richmond VA 23235",
    "addr:housenumber":"1310",
    "addr:postcode":"23235",
    "addr:street":"Elmart Ln",
    "iso:country":"US",
    "sg:address":"1310 Elmart Ln",
    "sg:city":"Richmond",
    "sg:classifiers":[
        {
            "category":"Building & Trades",
            "subcategory":"Construction",
            "type":"Services"
        }
    ],
    "sg:phone":"+1 804 675 7707",
    "sg:postcode":"23235",
    "sg:province":"VA",
    "sg:tags":[
        "hanging",
        "contractor"
    ],
    "wof:name":"Hughes Painting",
    "wof:placetype":"venue"
},
  "geometry": {"coordinates":[-77.54528500000001,37.479849],"type":"Point"}
}