{
  "type": "Feature",
  "properties": {
    "addr:full":"200 E Nine Mile Rd Highland Springs VA 23075",
    "addr:housenumber":"200",
    "addr:postcode":"23075",
    "addr:street":"E Nine Mile Rd",
    "iso:country":"US",
    "sg:address":"200 E Nine Mile Rd",
    "sg:city":"Highland Springs",
    "sg:classifiers":[
        {
            "category":"Insurance",
            "subcategory":"Insurance Agent",
            "type":"Services"
        }
    ],
    "sg:phone":"+1 804 737 2900",
    "sg:postcode":"23075",
    "sg:province":"VA",
    "wof:name":"Virginia's Preferred Insurance",
    "wof:placetype":"venue"
},
  "geometry": {"coordinates":[-77.32588199999999,37.544238],"type":"Point"}
}