{
  "type": "Feature",
  "properties": {
    "addr:full":"474 Painter St Apt B Norfolk VA 23505",
    "addr:housenumber":"474",
    "addr:postcode":"23505",
    "addr:street":"Painter St Apt B",
    "iso:country":"US",
    "sg:address":"474 Painter St Apt B",
    "sg:city":"Norfolk",
    "sg:classifiers":[
        {
            "category":"Manufacturing",
            "subcategory":"Electronics",
            "type":"Manufacturing & Wholesale Goods"
        },
        {
            "category":"Shopping",
            "subcategory":"Computers & Home Electronics",
            "type":"Retail Goods"
        }
    ],
    "sg:phone":"+1 757 679 5927",
    "sg:postcode":"23505",
    "sg:province":"VA",
    "sg:tags":[
        "audio-visual",
        "stereo",
        "equipment-wholesale",
        "video",
        "equipment-dealers",
        "audio",
        "manufacturer"
    ],
    "wof:name":"Avpi Security",
    "wof:placetype":"venue"
},
  "geometry": {"coordinates":[-76.28536699999999,36.900565],"type":"Point"}
}