{
  "type": "Feature",
  "properties": {
    "iso:country":"US",
    "sg:address":"400 Courthouse Sq",
    "sg:city":"Alexandria",
    "sg:classifiers":[
        {
            "category":"Travel",
            "subcategory":"Hotels & Motels",
            "type":"Entertainment"
        },
        {
            "category":"Travel",
            "subcategory":"Resort",
            "type":"Entertainment"
        },
        {
            "category":"Sports & Exercise",
            "subcategory":"Ski Resort",
            "type":"Entertainment"
        }
    ],
    "sg:phone":"+1 703 253 8600",
    "sg:postcode":"22314",
    "sg:province":"VA",
    "sg:tags":[
        "corporate",
        "lodging"
    ],
    "sg:website":"http://clk.atdmt.com/NYC/go/156347064/direct/01/",
    "wof:name":"The Westin Alexandria",
    "wof:placetype":"venue"
},
  "geometry": {"coordinates":[-77.066063,38.803009],"type":"Point"}
}