{
  "type": "Feature",
  "properties": {
    "iso:country":"US",
    "sg:address":"16 Pine St",
    "sg:city":"Onancock",
    "sg:classifiers":[
        {
            "category":"Shopping",
            "subcategory":"Used Merchandise",
            "type":"Retail Goods"
        }
    ],
    "sg:phone":"+1 757 789 5225",
    "sg:postcode":"23417",
    "sg:province":"VA",
    "wof:name":"Barrel House Gallery",
    "wof:placetype":"venue"
},
  "geometry": {"coordinates":[-75.736445,37.710159],"type":"Point"}
}