{
  "type": "Feature",
  "properties": {
    "addr:full":"10235 Van Thompson Rd Fairfax Station VA 22039",
    "addr:housenumber":"10235",
    "addr:postcode":"22039",
    "addr:street":"Van Thompson Rd",
    "iso:country":"US",
    "sg:address":"10235 Van Thompson Rd",
    "sg:city":"Fairfax Station",
    "sg:classifiers":[
        {
            "category":"Real Estate",
            "subcategory":"Real Estate Agent",
            "type":"Services"
        }
    ],
    "sg:phone":"+1 703 690 8800",
    "sg:postcode":"22039",
    "sg:province":"VA",
    "wof:name":"Advantage Properties Inc",
    "wof:placetype":"venue"
},
  "geometry": {"coordinates":[-77.301743,38.710344],"type":"Point"}
}