{
  "type": "Feature",
  "properties": {
    "addr:full":"12716 Lee Hwy Fairfax VA 22030",
    "addr:housenumber":"12716",
    "addr:postcode":"22030",
    "addr:street":"Lee Hwy",
    "iso:country":"US",
    "sg:address":"12716 Lee Hwy",
    "sg:city":"Fairfax",
    "sg:classifiers":[
        {
            "category":"Building & Trades",
            "subcategory":"Equipment Rental",
            "type":"Services"
        }
    ],
    "sg:phone":"+1 703 803 1304",
    "sg:postcode":"22030",
    "sg:province":"VA",
    "sg:tags":[
        "heavy",
        "construction",
        "yard"
    ],
    "sg:website":"www.capitalrentals.com",
    "wof:name":"Capital Rentals Inc",
    "wof:placetype":"venue"
},
  "geometry": {"coordinates":[-77.38831500000001,38.842425],"type":"Point"}
}