{
  "type": "Feature",
  "properties": {
    "addr:full":"1835 Nigel Ct Vienna VA 22182",
    "addr:housenumber":"1835",
    "addr:postcode":"22182",
    "addr:street":"Nigel Ct",
    "iso:country":"US",
    "sg:address":"1835 Nigel Ct",
    "sg:city":"Vienna",
    "sg:classifiers":[
        {
            "category":"Social Services",
            "subcategory":"Child Care",
            "type":"Services"
        }
    ],
    "sg:phone":"+1 703 938 7412",
    "sg:postcode":"22182",
    "sg:province":"VA",
    "sg:tags":[
        "day"
    ],
    "wof:name":"Learning Tree Presc of Vienna",
    "wof:placetype":"venue"
},
  "geometry": {"coordinates":[-77.26516700000001,38.919494],"type":"Point"}
}