{
  "type": "Feature",
  "properties": {
    "addr:full":"6902 Essex Ave Springfield VA 22150",
    "addr:housenumber":"6902",
    "addr:postcode":"22150",
    "addr:street":"Essex Ave",
    "iso:country":"US",
    "sg:address":"6902 Essex Ave",
    "sg:city":"Springfield",
    "sg:classifiers":[
        {
            "category":"Professional",
            "subcategory":"Management & Consulting",
            "type":"Services"
        }
    ],
    "sg:phone":"+1 703 451 8309",
    "sg:postcode":"22150",
    "sg:province":"VA",
    "wof:name":"Morgan Management Ltd",
    "wof:placetype":"venue"
},
  "geometry": {"coordinates":[-77.182401,38.790103],"type":"Point"}
}