{
  "type": "Feature",
  "properties": {
    "iso:country":"US",
    "sg:address":"1934 Old Gallows Rd",
    "sg:city":"Vienna",
    "sg:classifiers":[
        {
            "category":"Banks & Credit Unions",
            "subcategory":"Investment Brokerage",
            "type":"Services"
        },
        {
            "category":"Professional",
            "subcategory":"Management & Consulting",
            "type":"Services"
        }
    ],
    "sg:phone":"+1 703 356 4360",
    "sg:postcode":"22182",
    "sg:province":"VA",
    "sg:tags":[
        "consultant",
        "planning",
        "financial"
    ],
    "wof:name":"Financial Network Investment",
    "wof:placetype":"venue"
},
  "geometry": {"coordinates":[-77.222618,38.910857],"type":"Point"}
}