{
  "type": "Feature",
  "properties": {
    "addr:full":"4528 Massaponax Church Rd Fredericksburg VA 22408",
    "addr:housenumber":"4528",
    "addr:postcode":"22408",
    "addr:street":"Massaponax Church Rd",
    "iso:country":"US",
    "sg:address":"4528 Massaponax Church Rd",
    "sg:city":"Fredericksburg",
    "sg:classifiers":[
        {
            "category":"Building & Trades",
            "subcategory":"Construction",
            "type":"Services"
        }
    ],
    "sg:phone":"+1 540 898 6448",
    "sg:postcode":"22408",
    "sg:province":"VA",
    "sg:tags":[
        "house",
        "c",
        "hanging",
        "contractor"
    ],
    "wof:name":"C & K Painting Services",
    "wof:placetype":"venue"
},
  "geometry": {"coordinates":[-77.488219,38.191672],"type":"Point"}
}