{
  "type": "Feature",
  "properties": {
    "iso:country":"US",
    "sg:address":"1009 Duke St",
    "sg:city":"Alexandria",
    "sg:classifiers":[
        {
            "category":"Professional",
            "subcategory":"Business Services",
            "type":"Services"
        }
    ],
    "sg:phone":"+1 703 739 0400",
    "sg:postcode":"22314",
    "sg:province":"VA",
    "sg:tags":[
        "litigation",
        "support"
    ],
    "wof:name":"Litcom",
    "wof:placetype":"venue"
},
  "geometry": {"coordinates":[-77.051771,38.803399],"type":"Point"}
}