{
  "type": "Feature",
  "properties": {
    "iso:country":"US",
    "sg:address":"700 Independence Cir",
    "sg:city":"Virginia Beach",
    "sg:classifiers":[
        {
            "category":"Health Services",
            "subcategory":"Doctor",
            "type":"Services"
        }
    ],
    "sg:phone":"+1 757 499 8855",
    "sg:postcode":"23455",
    "sg:province":"VA",
    "sg:tags":[
        "physician",
        "surgeon"
    ],
    "wof:name":"Abraham Mahini MD",
    "wof:placetype":"venue"
},
  "geometry": {"coordinates":[-76.13174600000001,36.861033],"type":"Point"}
}