{
  "type": "Feature",
  "properties": {
    "iso:country":"US",
    "sg:address":"21749 Tottenham Hale Ct",
    "sg:city":"Sterling",
    "sg:classifiers":[
        {
            "category":"Professional",
            "subcategory":"Business Services",
            "type":"Services"
        }
    ],
    "sg:phone":"+1 571 434 0658",
    "sg:postcode":"20166",
    "sg:province":"VA",
    "wof:name":"Magna It Solutions Inc",
    "wof:placetype":"venue"
},
  "geometry": {"coordinates":[-77.42182099999999,39.014026],"type":"Point"}
}