{
  "type": "Feature",
  "properties": {
    "addr:full":"842 Cumberland St Bristol VA 24201",
    "addr:housenumber":"842",
    "addr:postcode":"24201",
    "addr:street":"Cumberland St",
    "iso:country":"US",
    "sg:address":"842 Cumberland St",
    "sg:city":"Bristol",
    "sg:classifiers":[
        {
            "category":"Building & Trades",
            "subcategory":"Construction",
            "type":"Services"
        }
    ],
    "sg:phone":"+1 276 466 4134",
    "sg:postcode":"24201",
    "sg:province":"VA",
    "sg:tags":[
        "demolition",
        "contractor"
    ],
    "wof:name":"Taff & Frye Demolition",
    "wof:placetype":"venue"
},
  "geometry": {"coordinates":[-82.186611,36.597891],"type":"Point"}
}