{
  "type": "Feature",
  "properties": {
    "iso:country":"US",
    "sg:address":"224 E Broad St",
    "sg:city":"Richmond",
    "sg:classifiers":[
        {
            "category":"Organizations",
            "subcategory":"Membership Organization",
            "type":"Services"
        }
    ],
    "sg:phone":"+1 804 225 7909",
    "sg:postcode":"23219",
    "sg:province":"VA",
    "wof:name":"Homeward",
    "wof:placetype":"venue"
},
  "geometry": {"coordinates":[-77.43946200000001,37.544161],"type":"Point"}
}