{
  "type": "Feature",
  "properties": {
    "addr:full":"5599 Sugar Grove Hwy Sugar Grove VA 24375",
    "addr:housenumber":"5599",
    "addr:postcode":"24375",
    "addr:street":"Sugar Grove Hwy",
    "iso:country":"US",
    "sg:address":"5599 Sugar Grove Hwy",
    "sg:city":"Sugar Grove",
    "sg:classifiers":[
        {
            "category":"Building & Trades",
            "subcategory":"Construction",
            "type":"Services"
        }
    ],
    "sg:phone":"+1 276 677 3299",
    "sg:postcode":"24375",
    "sg:province":"VA",
    "sg:tags":[
        "excavation",
        "contractor"
    ],
    "wof:name":"P&D Back Hoe Service",
    "wof:placetype":"venue"
},
  "geometry": {"coordinates":[-81.41594000000001,36.770258],"type":"Point"}
}