{
  "type": "Feature",
  "properties": {
    "iso:country":"US",
    "sg:address":"2129 Crystal Plz",
    "sg:city":"Alexandria",
    "sg:classifiers":[
        {
            "category":"Food & Beverages",
            "subcategory":"Groceries & Convenience Stores",
            "type":"Retail Goods"
        }
    ],
    "sg:phone":"+1 703 415 0422",
    "sg:postcode":"22301",
    "sg:province":"VA",
    "sg:website":"www.safeway.com",
    "wof:name":"Safeway Food & Drug",
    "wof:placetype":"venue"
},
  "geometry": {"coordinates":[-77.04942699999999,38.854587],"type":"Point"}
}