{
  "type": "Feature",
  "properties": {
    "iso:country":"US",
    "sg:address":"1000 Wilson Blvd",
    "sg:city":"Arlington",
    "sg:classifiers":[
        {
            "category":"Building & Trades",
            "subcategory":"Locksmith",
            "type":"Services"
        }
    ],
    "sg:phone":"+1 703 258 0260",
    "sg:postcode":"22209",
    "sg:province":"VA",
    "sg:tags":[
        "key"
    ],
    "wof:name":"Locksout Locksmith",
    "wof:placetype":"venue"
},
  "geometry": {"coordinates":[-77.068575,38.893863],"type":"Point"}
}