{
  "type": "Feature",
  "properties": {
    "iso:country":"US",
    "sg:address":"153 E Morgan Ave",
    "sg:city":"Pennington Gap",
    "sg:classifiers":[
        {
            "category":"Health Services",
            "subcategory":"Doctor",
            "type":"Services"
        }
    ],
    "sg:phone":"+1 276 546 2042",
    "sg:postcode":"24277",
    "sg:province":"VA",
    "sg:tags":[
        "dentist"
    ],
    "wof:name":"Roy S Shelburne DDS",
    "wof:placetype":"venue"
},
  "geometry": {"coordinates":[-83.025825,36.759167],"type":"Point"}
}