{
  "type": "Feature",
  "properties": {
    "iso:country":"US",
    "sg:address":"3547 Byrn Brae Dr",
    "sg:city":"Virginia Beach",
    "sg:classifiers":[
        {
            "category":"Wholesale",
            "subcategory":"Electrical",
            "type":"Manufacturing & Wholesale Goods"
        }
    ],
    "sg:phone":"+1 757 523 6323",
    "sg:postcode":"23464",
    "sg:province":"VA",
    "sg:tags":[
        "equipment",
        "electric",
        "supply"
    ],
    "wof:name":"Todd Marine Electrical Supply",
    "wof:placetype":"venue"
},
  "geometry": {"coordinates":[-76.22233300000001,36.832018],"type":"Point"}
}