{
  "type": "Feature",
  "properties": {
    "iso:country":"US",
    "sg:address":"736 Florida Ave",
    "sg:city":"Portsmouth",
    "sg:classifiers":[
        {
            "category":"Autos & Motor Vehicles",
            "subcategory":"Auto Supplies",
            "type":"Retail Goods"
        }
    ],
    "sg:phone":"+1 757 397 2739",
    "sg:postcode":"23707",
    "sg:province":"VA",
    "sg:tags":[
        "engine",
        "used",
        "diesel",
        "parts"
    ],
    "wof:name":"Robert P Kellam Enterprises",
    "wof:placetype":"venue"
},
  "geometry": {"coordinates":[-76.33749,36.841791],"type":"Point"}
}