{
  "type": "Feature",
  "properties": {
    "iso:country":"US",
    "sg:address":"14230 Boondock Ln",
    "sg:city":"Montpelier",
    "sg:classifiers":[
        {
            "category":"Building & Trades",
            "subcategory":"Construction",
            "type":"Services"
        }
    ],
    "sg:phone":"+1 804 883 5704",
    "sg:postcode":"23192",
    "sg:province":"VA",
    "sg:tags":[
        "concrete",
        "contractor"
    ],
    "wof:name":"S & B Concrete Inc",
    "wof:placetype":"venue"
},
  "geometry": {"coordinates":[-77.766223,37.796753],"type":"Point"}
}