{
  "type": "Feature",
  "properties": {
    "addr:full":"211 Buxton Rd Falls Church VA 22046",
    "addr:housenumber":"211",
    "addr:postcode":"22046",
    "addr:street":"Buxton Rd",
    "iso:country":"US",
    "sg:address":"211 Buxton Rd",
    "sg:city":"Falls Church",
    "sg:classifiers":[
        {
            "category":"Food & Beverages",
            "subcategory":"Dairy",
            "type":"Retail Goods"
        }
    ],
    "sg:phone":"+1 703 533 0477",
    "sg:postcode":"22046",
    "sg:province":"VA",
    "sg:tags":[
        "product"
    ],
    "wof:name":"Bowers Dairy",
    "wof:placetype":"venue"
},
  "geometry": {"coordinates":[-77.16120600000001,38.879533],"type":"Point"}
}