{
  "type": "Feature",
  "properties": {
    "addr:full":"10316 Ridgeway Dr King George VA 22485",
    "addr:housenumber":"10316",
    "addr:postcode":"22485",
    "addr:street":"Ridgeway Dr",
    "iso:country":"US",
    "sg:address":"10316 Ridgeway Dr",
    "sg:city":"King George",
    "sg:classifiers":[
        {
            "category":"Shopping",
            "subcategory":"Gifts & Souvenirs",
            "type":"Retail Goods"
        }
    ],
    "sg:phone":"+1 540 775 7573",
    "sg:postcode":"22485",
    "sg:province":"VA",
    "sg:tags":[
        "shop"
    ],
    "wof:name":"Pirates Chest Of Fresco",
    "wof:placetype":"venue"
},
  "geometry": {"coordinates":[-77.228533,38.269411],"type":"Point"}
}