{
  "type": "Feature",
  "properties": {
    "iso:country":"US",
    "sg:address":"100 Rappahannock Rd",
    "sg:city":"Irvington",
    "sg:classifiers":[
        {
            "category":"Organizations",
            "subcategory":"Community Association",
            "type":"Services"
        }
    ],
    "sg:phone":"+1 804 438 6650",
    "sg:postcode":"22480",
    "sg:province":"VA",
    "sg:tags":[
        "club"
    ],
    "wof:name":"Rappahannock River Yacht Club",
    "wof:placetype":"venue"
},
  "geometry": {"coordinates":[-76.43347799999999,37.657022],"type":"Point"}
}