{
  "type": "Feature",
  "properties": {
    "addr:full":"9070 W Broad St Richmond VA 23294",
    "addr:housenumber":"9070",
    "addr:postcode":"23294",
    "addr:street":"W Broad St",
    "iso:country":"US",
    "sg:address":"9070 W Broad St",
    "sg:city":"Richmond",
    "sg:classifiers":[
        {
            "category":"Banks & Credit Unions",
            "subcategory":"Bank",
            "type":"Services"
        }
    ],
    "sg:phone":"+1 804 217 8990",
    "sg:postcode":"23294",
    "sg:province":"VA",
    "sg:tags":[
        "personal",
        "institution"
    ],
    "wof:name":"Advance America",
    "wof:placetype":"venue"
},
  "geometry": {"coordinates":[-77.54758200000001,37.635665],"type":"Point"}
}