{
  "type": "Feature",
  "properties": {
    "iso:country":"US",
    "sg:address":"1218 Raleigh Ave",
    "sg:city":"Norfolk",
    "sg:classifiers":[
        {
            "category":"Building & Trades",
            "subcategory":"Construction",
            "type":"Services"
        }
    ],
    "sg:phone":"+1 757 622 9752",
    "sg:postcode":"23507",
    "sg:province":"VA",
    "sg:tags":[
        "house"
    ],
    "wof:name":"Ghent Construction Inc",
    "wof:placetype":"venue"
},
  "geometry": {"coordinates":[-76.308548,36.866228],"type":"Point"}
}