{
  "type": "Feature",
  "properties": {
    "iso:country":"US",
    "sg:address":"2242 Ives Ln",
    "sg:city":"Richmond",
    "sg:classifiers":[
        {
            "category":"Professional",
            "subcategory":"Computer Services",
            "type":"Services"
        }
    ],
    "sg:phone":"+1 804 786 0838",
    "sg:postcode":"23235",
    "sg:province":"VA",
    "sg:tags":[
        "datum"
    ],
    "wof:name":"Together & Apart",
    "wof:placetype":"venue"
},
  "geometry": {"coordinates":[-77.53196800000001,37.47247],"type":"Point"}
}