{
  "type": "Feature",
  "properties": {
    "addr:full":"913 Main St West Point VA 23181",
    "addr:housenumber":"913",
    "addr:postcode":"23181",
    "addr:street":"Main St",
    "iso:country":"US",
    "sg:address":"913 Main St",
    "sg:city":"West Point",
    "sg:classifiers":[
        {
            "category":"Banks & Credit Unions",
            "subcategory":"Investment Brokerage",
            "type":"Services"
        }
    ],
    "sg:phone":"+1 804 843 6100",
    "sg:postcode":"23181",
    "sg:province":"VA",
    "sg:tags":[
        "security"
    ],
    "wof:name":"Edward Jones Co",
    "wof:placetype":"venue"
},
  "geometry": {"coordinates":[-76.79773900000001,37.53388],"type":"Point"}
}