{
  "type": "Feature",
  "properties": {
    "iso:country":"US",
    "sg:address":"4744 Price Cir",
    "sg:city":"Virginia Beach",
    "sg:classifiers":[
        {
            "category":"Professional",
            "subcategory":"Business Services",
            "type":"Services"
        }
    ],
    "sg:phone":"+1 757 460 9182",
    "sg:postcode":"23455",
    "sg:province":"VA",
    "wof:name":"Atlantic Decorating",
    "wof:placetype":"venue"
},
  "geometry": {"coordinates":[-76.134395,36.902721],"type":"Point"}
}