{
  "type": "Feature",
  "properties": {
    "iso:country":"US",
    "sg:address":"813 Courthouse Rd",
    "sg:city":"Stafford",
    "sg:classifiers":[
        {
            "category":"Manufacturing",
            "subcategory":"Signs",
            "type":"Manufacturing & Wholesale Goods"
        }
    ],
    "sg:phone":"+1 540 720 0402",
    "sg:postcode":"22554",
    "sg:province":"VA",
    "sg:tags":[
        "advertising",
        "specialty"
    ],
    "wof:name":"Triple Signs",
    "wof:placetype":"venue"
},
  "geometry": {"coordinates":[-77.437133,38.427643],"type":"Point"}
}