{
  "type": "Feature",
  "properties": {
    "addr:full":"6680 Indian River Rd Virginia Beach VA 23464",
    "addr:housenumber":"6680",
    "addr:postcode":"23464",
    "addr:street":"Indian River Rd",
    "iso:country":"US",
    "sg:address":"6680 Indian River Rd",
    "sg:city":"Virginia Beach",
    "sg:classifiers":[
        {
            "category":"Restaurant",
            "type":"Food & Drink"
        }
    ],
    "sg:phone":"+1 757 420 6804",
    "sg:postcode":"23464",
    "sg:province":"VA",
    "sg:website":"www.mcdonalds.com",
    "wof:name":"Mc Donald's",
    "wof:placetype":"venue"
},
  "geometry": {"coordinates":[-76.222193,36.819589],"type":"Point"}
}