{
  "type": "Feature",
  "properties": {
    "addr:full":"6080 Spotswood Trl Penn Laird VA 22846",
    "addr:housenumber":"6080",
    "addr:postcode":"22846",
    "addr:street":"Spotswood Trl",
    "iso:country":"US",
    "sg:address":"6080 Spotswood Trl",
    "sg:city":"Penn Laird",
    "sg:classifiers":[
        {
            "category":"Food & Beverages",
            "subcategory":"Groceries & Convenience Stores",
            "type":"Retail Goods"
        }
    ],
    "sg:phone":"+1 540 289 7617",
    "sg:postcode":"22846",
    "sg:province":"VA",
    "wof:name":"Valley's Convenience Store",
    "wof:placetype":"venue"
},
  "geometry": {"coordinates":[-78.79680399999999,38.378115],"type":"Point"}
}