{
  "type": "Feature",
  "properties": {
    "addr:full":"6947 Jones Hollow Rd Norton VA 24273",
    "addr:housenumber":"6947",
    "addr:postcode":"24273",
    "addr:street":"Jones Hollow Rd",
    "iso:country":"US",
    "sg:address":"6947 Jones Hollow Rd",
    "sg:city":"Norton",
    "sg:classifiers":[
        {
            "category":"Mining & Drilling",
            "type":"Manufacturing & Wholesale Goods"
        }
    ],
    "sg:phone":"+1 276 679 5031",
    "sg:postcode":"24273",
    "sg:province":"VA",
    "sg:tags":[
        "coal",
        "bituminous"
    ],
    "wof:name":"Roberts Coal Haul",
    "wof:placetype":"venue"
},
  "geometry": {"coordinates":[-82.649897,36.994917],"type":"Point"}
}