{
  "type": "Feature",
  "properties": {
    "addr:full":"540 Maple Ave W Vienna VA 22180",
    "addr:housenumber":"540",
    "addr:postcode":"22180",
    "addr:street":"Maple Ave W",
    "iso:country":"US",
    "sg:address":"540 Maple Ave W",
    "sg:city":"Vienna",
    "sg:classifiers":[
        {
            "category":"Retail",
            "subcategory":"Car Wash",
            "type":"Services"
        }
    ],
    "sg:phone":"+1 703 242 0540",
    "sg:postcode":"22180",
    "sg:province":"VA",
    "sg:tags":[
        "polishing",
        "washing"
    ],
    "sg:website":"www.mrwash.com",
    "wof:name":"Mr Wash",
    "wof:placetype":"venue"
},
  "geometry": {"coordinates":[-77.27420499999999,38.894461],"type":"Point"}
}