{
  "type": "Feature",
  "properties": {
    "addr:full":"20747 Ruffs Dale Ct Ashburn VA 20147",
    "addr:postcode":"20747;20147",
    "addr:street":"Ruffs Dale Ct",
    "iso:country":"US",
    "sg:address":"20747 Ruffs Dale Ct",
    "sg:city":"Ashburn",
    "sg:classifiers":[
        {
            "category":"Freight",
            "type":"Transportation"
        }
    ],
    "sg:phone":"+1 703 729 0561",
    "sg:postcode":"20147",
    "sg:province":"VA",
    "sg:tags":[
        "operator",
        "local",
        "trucking"
    ],
    "wof:name":"Pth Trucking LLC",
    "wof:placetype":"venue"
},
  "geometry": {"coordinates":[-77.47029000000001,39.042154],"type":"Point"}
}