{
  "type": "Feature",
  "properties": {
    "iso:country":"US",
    "sg:address":"21488 Colonial Village Way",
    "sg:city":"Ashburn",
    "sg:classifiers":[
        {
            "category":"Professional",
            "subcategory":"Computer Services",
            "type":"Services"
        }
    ],
    "sg:phone":"+1 703 858 9700",
    "sg:postcode":"20147",
    "sg:province":"VA",
    "sg:tags":[
        "website",
        "design"
    ],
    "wof:name":"Virid Inc",
    "wof:placetype":"venue"
},
  "geometry": {"coordinates":[-77.46785300000001,39.021382],"type":"Point"}
}