{
  "type": "Feature",
  "properties": {
    "iso:country":"US",
    "sg:address":"226 Maple Ave W",
    "sg:city":"Vienna",
    "sg:classifiers":[
        {
            "category":"Personal",
            "type":"Services"
        }
    ],
    "sg:phone":"+1 703 319 0437",
    "sg:postcode":"22180",
    "sg:province":"VA",
    "sg:tags":[
        "therapist",
        "massage"
    ],
    "wof:name":"A Touch Of Health",
    "wof:placetype":"venue"
},
  "geometry": {"coordinates":[-77.268916,38.898606],"type":"Point"}
}