{
  "type": "Feature",
  "properties": {
    "addr:full":"14015 Noblewood Plz Woodbridge VA 22193",
    "addr:housenumber":"14015",
    "addr:postcode":"22193",
    "addr:street":"Noblewood Plz",
    "iso:country":"US",
    "sg:address":"14015 Noblewood Plz",
    "sg:city":"Woodbridge",
    "sg:classifiers":[
        {
            "category":"Personal",
            "subcategory":"Beauty Salon",
            "type":"Services"
        }
    ],
    "sg:phone":"+1 703 670 4376",
    "sg:postcode":"22193",
    "sg:province":"VA",
    "sg:tags":[
        "manicuring"
    ],
    "wof:name":"Kim's Corner Nail",
    "wof:placetype":"venue"
},
  "geometry": {"coordinates":[-77.31482200000001,38.65053],"type":"Point"}
}