{
  "type": "Feature",
  "properties": {
    "addr:full":"26 Walnut Ln Petersburg VA 23803",
    "addr:housenumber":"26",
    "addr:postcode":"23803",
    "addr:street":"Walnut Ln",
    "iso:country":"US",
    "sg:address":"26 Walnut Ln",
    "sg:city":"Petersburg",
    "sg:classifiers":[
        {
            "category":"Restaurant",
            "type":"Food & Drink"
        }
    ],
    "sg:phone":"+1 434 223 7938",
    "sg:postcode":"23803",
    "sg:province":"VA",
    "sg:tags":[
        "caterer"
    ],
    "wof:name":"Ross Catering & Rental Svc",
    "wof:placetype":"venue"
},
  "geometry": {"coordinates":[-77.401591,37.218977],"type":"Point"}
}