{
  "type": "Feature",
  "properties": {
    "addr:full":"6451 Statute St Chesterfield VA 23832",
    "addr:housenumber":"6451",
    "addr:postcode":"23832",
    "addr:street":"Statute St",
    "iso:country":"US",
    "sg:address":"6451 Statute St",
    "sg:city":"Chesterfield",
    "sg:classifiers":[
        {
            "category":"Manufacturing",
            "subcategory":"Petroleum Products",
            "type":"Manufacturing & Wholesale Goods"
        }
    ],
    "sg:phone":"+1 804 243 0859",
    "sg:postcode":"23832",
    "sg:province":"VA",
    "sg:tags":[
        "candles-wholesale",
        "manufacturer"
    ],
    "wof:name":"Soy Candle Lovers",
    "wof:placetype":"venue"
},
  "geometry": {"coordinates":[-77.499106,37.378568],"type":"Point"}
}