{
  "type": "Feature",
  "properties": {
    "addr:full":"212 Hickory Rd E Chesapeake VA 23322",
    "addr:housenumber":"212",
    "addr:postcode":"23322",
    "addr:street":"Hickory Rd E",
    "iso:country":"US",
    "sg:address":"212 Hickory Rd E",
    "sg:city":"Chesapeake",
    "sg:classifiers":[
        {
            "category":"Farming",
            "subcategory":"Farm",
            "type":"Manufacturing & Wholesale Goods"
        }
    ],
    "sg:phone":"+1 757 421 4340",
    "sg:postcode":"23322",
    "sg:province":"VA",
    "sg:tags":[
        "equine",
        "crop",
        "general"
    ],
    "wof:name":"Pam Herman Farms",
    "wof:placetype":"venue"
},
  "geometry": {"coordinates":[-76.209464,36.642622],"type":"Point"}
}