{
  "type": "Feature",
  "properties": {
    "addr:full":"20324 Bradford Rd Melfa VA 23410",
    "addr:housenumber":"20324",
    "addr:postcode":"23410",
    "addr:street":"Bradford Rd",
    "iso:country":"US",
    "sg:address":"20324 Bradford Rd",
    "sg:city":"Melfa",
    "sg:classifiers":[
        {
            "category":"Shopping",
            "subcategory":"Computers & Home Electronics",
            "type":"Retail Goods"
        }
    ],
    "sg:phone":"+1 757 787 2219",
    "sg:postcode":"23410",
    "sg:province":"VA",
    "wof:name":"Collins Electronics Sls & Svc",
    "wof:placetype":"venue"
},
  "geometry": {"coordinates":[-75.72774699999999,37.617779],"type":"Point"}
}