{
  "type": "Feature",
  "properties": {
    "addr:full":"6301 Hull Street Rd Richmond VA 23224",
    "addr:housenumber":"6301",
    "addr:postcode":"23224",
    "addr:street":"Hull Street Rd",
    "iso:country":"US",
    "sg:address":"6301 Hull Street Rd",
    "sg:city":"Richmond",
    "sg:classifiers":[
        {
            "category":"Personal",
            "type":"Services"
        }
    ],
    "sg:phone":"+1 804 745 5577",
    "sg:postcode":"23224",
    "sg:province":"VA",
    "wof:name":"Creative Designs Tattoo Studio",
    "wof:placetype":"venue"
},
  "geometry": {"coordinates":[-77.507104,37.481049],"type":"Point"}
}