{
  "type": "Feature",
  "properties": {
    "addr:full":"7900 Fort Hunt Rd Alexandria VA 22308",
    "addr:housenumber":"7900",
    "addr:postcode":"22308",
    "addr:street":"Fort Hunt Rd",
    "iso:country":"US",
    "sg:address":"7900 Fort Hunt Rd",
    "sg:city":"Alexandria",
    "sg:classifiers":[
        {
            "category":"Food & Beverages",
            "subcategory":"Groceries & Convenience Stores",
            "type":"Retail Goods"
        }
    ],
    "sg:phone":"+1 703 765 0924",
    "sg:postcode":"22308",
    "sg:province":"VA",
    "wof:name":"Safeway",
    "wof:placetype":"venue"
},
  "geometry": {"coordinates":[-77.056905,38.743541],"type":"Point"}
}