{
  "type": "Feature",
  "properties": {
    "iso:country":"US",
    "sg:address":"215 Morning Dove Ln",
    "sg:city":"Vinton",
    "sg:classifiers":[
        {
            "category":"Building & Trades",
            "subcategory":"Plumbing",
            "type":"Services"
        }
    ],
    "sg:phone":"+1 540 890 1661",
    "sg:postcode":"24179",
    "sg:province":"VA",
    "sg:tags":[
        "contractor"
    ],
    "wof:name":"Control Maintenance Inc",
    "wof:placetype":"venue"
},
  "geometry": {"coordinates":[-79.827251,37.262588],"type":"Point"}
}