{
  "type": "Feature",
  "properties": {
    "addr:full":"11711U Fair Oaks Mall Fairfax VA 22033",
    "addr:postcode":"22033",
    "addr:street":"Fair Oaks Mall",
    "iso:country":"US",
    "sg:address":"11711U Fair Oaks Mall",
    "sg:city":"Fairfax",
    "sg:classifiers":[
        {
            "category":"Shopping",
            "subcategory":"Clothing, Apparel, & Fashions",
            "type":"Retail Goods"
        },
        {
            "category":"Shopping",
            "subcategory":"Shoes",
            "type":"Retail Goods"
        }
    ],
    "sg:phone":"+1 703 359 2591",
    "sg:postcode":"22033",
    "sg:province":"VA",
    "sg:tags":[
        "sportswear",
        "store"
    ],
    "sg:website":"http://www.champssports.com",
    "wof:name":"Champs Sports",
    "wof:placetype":"venue"
},
  "geometry": {"coordinates":[-77.354873,38.861467],"type":"Point"}
}