{
  "type": "Feature",
  "properties": {
    "addr:full":"210 N Madison St Richmond VA 23220",
    "addr:housenumber":"210",
    "addr:postcode":"23220",
    "addr:street":"N Madison St",
    "iso:country":"US",
    "sg:address":"210 N Madison St",
    "sg:city":"Richmond",
    "sg:classifiers":[
        {
            "category":"Social Services",
            "type":"Services"
        }
    ],
    "sg:phone":"+1 804 644 2095",
    "sg:postcode":"23220",
    "sg:province":"VA",
    "wof:name":"Alcoholics Anonymous",
    "wof:placetype":"venue"
},
  "geometry": {"coordinates":[-77.444744,37.547134],"type":"Point"}
}