{
  "type": "Feature",
  "properties": {
    "iso:country":"US",
    "sg:address":"6981 Hechinger Dr",
    "sg:city":"Springfield",
    "sg:classifiers":[
        {
            "category":"Restaurant",
            "type":"Food & Drink"
        }
    ],
    "sg:phone":"+1 703 916 7661",
    "sg:postcode":"22151",
    "sg:province":"VA",
    "sg:tags":[
        "korean",
        "asian",
        "pan"
    ],
    "wof:name":"Options Korean Restaurant",
    "wof:placetype":"venue"
},
  "geometry": {"coordinates":[-77.183115,38.795575],"type":"Point"}
}