{
  "type": "Feature",
  "properties": {
    "addr:full":"2512 Sisco Ave Richmond VA 23234",
    "addr:housenumber":"2512",
    "addr:postcode":"23234",
    "addr:street":"Sisco Ave",
    "iso:country":"US",
    "sg:address":"2512 Sisco Ave",
    "sg:city":"Richmond",
    "sg:classifiers":[
        {
            "category":"Manufacturing",
            "subcategory":"Metals",
            "type":"Manufacturing & Wholesale Goods"
        }
    ],
    "sg:phone":"+1 804 271 8355",
    "sg:postcode":"23234",
    "sg:province":"VA",
    "sg:tags":[
        "fabricator",
        "sheet"
    ],
    "wof:name":"American Metal Fabrication Inc",
    "wof:placetype":"venue"
},
  "geometry": {"coordinates":[-77.442977,37.468894],"type":"Point"}
}