{
  "type": "Feature",
  "properties": {
    "addr:full":"400 Preston Ave Charlottesville VA 22903",
    "addr:housenumber":"400",
    "addr:postcode":"22903",
    "addr:street":"Preston Ave",
    "iso:country":"US",
    "sg:address":"400 Preston Ave",
    "sg:city":"Charlottesville",
    "sg:classifiers":[
        {
            "category":"Social Services",
            "subcategory":"Job Training",
            "type":"Services"
        }
    ],
    "sg:phone":"+1 434 984 7630",
    "sg:postcode":"22903",
    "sg:province":"VA",
    "sg:tags":[
        "rehab",
        "government"
    ],
    "wof:name":"Job Service",
    "wof:placetype":"venue"
},
  "geometry": {"coordinates":[-78.48504,38.034428],"type":"Point"}
}