{
  "type": "Feature",
  "properties": {
    "addr:full":"816 Federal St Rich Creek VA 24147",
    "addr:housenumber":"816",
    "addr:postcode":"24147",
    "addr:street":"Federal St",
    "iso:country":"US",
    "sg:address":"816 Federal St",
    "sg:city":"Rich Creek",
    "sg:classifiers":[
        {
            "category":"Home & Garden",
            "subcategory":"Furniture",
            "type":"Retail Goods"
        }
    ],
    "sg:phone":"+1 540 726 2785",
    "sg:postcode":"24147",
    "sg:province":"VA",
    "wof:name":"Mutt's Trading Post",
    "wof:placetype":"venue"
},
  "geometry": {"coordinates":[-80.805544,37.393282],"type":"Point"}
}