{
  "type": "Feature",
  "properties": {
    "iso:country":"US",
    "sg:address":"20789 Great Falls Plz",
    "sg:city":"Sterling",
    "sg:classifiers":[
        {
            "category":"Personal",
            "type":"Services"
        },
        {
            "category":"Retail",
            "subcategory":"Animal Services",
            "type":"Services"
        }
    ],
    "sg:phone":"+1 703 433 1300",
    "sg:postcode":"20165",
    "sg:province":"VA",
    "sg:tags":[
        "pet",
        "boarding",
        "sitting"
    ],
    "sg:website":"www.theanimalshouse.com",
    "wof:name":"Animals House",
    "wof:placetype":"venue"
},
  "geometry": {"coordinates":[-77.357916,39.040244],"type":"Point"}
}