{
  "type": "Feature",
  "properties": {
    "addr:full":"11802 Fair Oaks Mall Fairfax VA 22033",
    "addr:housenumber":"11802",
    "addr:postcode":"22033",
    "addr:street":"Fair Oaks Mall",
    "iso:country":"US",
    "sg:address":"11802 Fair Oaks Mall",
    "sg:city":"Fairfax",
    "sg:classifiers":[
        {
            "category":"Shopping",
            "subcategory":"Florist",
            "type":"Retail Goods"
        }
    ],
    "sg:phone":"+1 703 691 0303",
    "sg:postcode":"22033",
    "sg:province":"VA",
    "sg:tags":[
        "potted",
        "full",
        "plant",
        "accessory"
    ],
    "wof:name":"Greensleeves",
    "wof:placetype":"venue"
},
  "geometry": {"coordinates":[-77.35802,38.864746],"type":"Point"}
}