{
  "type": "Feature",
  "properties": {
    "addr:full":"4502 Medford Dr Annandale VA 22003",
    "addr:housenumber":"4502",
    "addr:postcode":"22003",
    "addr:street":"Medford Dr",
    "iso:country":"US",
    "sg:address":"4502 Medford Dr",
    "sg:city":"Annandale",
    "sg:classifiers":[
        {
            "category":"Wholesale",
            "subcategory":"Vending Machines",
            "type":"Manufacturing & Wholesale Goods"
        }
    ],
    "sg:phone":"+1 703 642 8017",
    "sg:postcode":"22003",
    "sg:province":"VA",
    "sg:tags":[
        "operator"
    ],
    "wof:name":"Keung Vending",
    "wof:placetype":"venue"
},
  "geometry": {"coordinates":[-77.205474,38.825001],"type":"Point"}
}