{
  "type": "Feature",
  "properties": {
    "addr:full":"3208 Utah Pl Richmond VA 23222",
    "addr:housenumber":"3208",
    "addr:postcode":"23222",
    "addr:street":"Utah Pl",
    "iso:country":"US",
    "sg:address":"3208 Utah Pl",
    "sg:city":"Richmond",
    "sg:classifiers":[
        {
            "category":"Professional",
            "type":"Services"
        }
    ],
    "sg:phone":"+1 804 329 3961",
    "sg:postcode":"23222",
    "sg:province":"VA",
    "wof:name":"Jimmie L Anderson",
    "wof:placetype":"venue"
},
  "geometry": {"coordinates":[-77.413265,37.572557],"type":"Point"}
}