{
  "type": "Feature",
  "properties": {
    "addr:full":"3416 Martinsburg Pike Clear Brook VA 22624",
    "addr:housenumber":"3416",
    "addr:postcode":"22624",
    "addr:street":"Martinsburg Pike",
    "iso:country":"US",
    "sg:address":"3416 Martinsburg Pike",
    "sg:city":"Clear Brook",
    "sg:classifiers":[
        {
            "category":"Wholesale",
            "subcategory":"Home Furnishings",
            "type":"Manufacturing & Wholesale Goods"
        }
    ],
    "sg:phone":"+1 540 662 3442",
    "sg:postcode":"22624",
    "sg:province":"VA",
    "sg:tags":[
        "blanket"
    ],
    "wof:name":"Clearbrook Woolen Shop",
    "wof:placetype":"venue"
},
  "geometry": {"coordinates":[-78.09660599999999,39.255082],"type":"Point"}
}