{
  "type": "Feature",
  "properties": {
    "iso:country":"US",
    "sg:address":"700 E Main St",
    "sg:city":"Richmond",
    "sg:classifiers":[
        {
            "category":"Mining & Drilling",
            "type":"Manufacturing & Wholesale Goods"
        }
    ],
    "sg:phone":"+1 804 377 0114",
    "sg:postcode":"23219",
    "sg:province":"VA",
    "sg:tags":[
        "stone"
    ],
    "wof:name":"Stone Assignments",
    "wof:placetype":"venue"
},
  "geometry": {"coordinates":[-77.437201,37.53875],"type":"Point"}
}