{
  "type": "Feature",
  "properties": {
    "addr:full":"715 W Main St Salem VA 24153",
    "addr:housenumber":"715",
    "addr:postcode":"24153",
    "addr:street":"W Main St",
    "iso:country":"US",
    "sg:address":"715 W Main St",
    "sg:city":"Salem",
    "sg:classifiers":[
        {
            "category":"Professional",
            "type":"Services"
        }
    ],
    "sg:phone":"+1 540 389 2615",
    "sg:postcode":"24153",
    "sg:province":"VA",
    "sg:tags":[
        "establishment"
    ],
    "wof:name":"Cook & Cook",
    "wof:placetype":"venue"
},
  "geometry": {"coordinates":[-80.069562,37.290919],"type":"Point"}
}