{
  "type": "Feature",
  "properties": {
    "addr:full":"3022 22nd St S Arlington VA 22204",
    "addr:housenumber":"3022",
    "addr:postcode":"22204",
    "addr:street":"22Nd St S",
    "iso:country":"US",
    "sg:address":"3022 22nd St S",
    "sg:city":"Arlington",
    "sg:classifiers":[
        {
            "category":"Autos & Motor Vehicles",
            "subcategory":"Automobile Sales",
            "type":"Retail Goods"
        },
        {
            "category":"Airline",
            "type":"Transportation"
        }
    ],
    "sg:phone":"+1 703 892 2540",
    "sg:postcode":"22204",
    "sg:province":"VA",
    "sg:tags":[
        "shuttle",
        "airport",
        "limo"
    ],
    "sg:website":"friendlylimo.net/",
    "wof:name":"Friendly Sudan & Limosine Service",
    "wof:placetype":"venue"
},
  "geometry": {"coordinates":[-77.084396,38.850201],"type":"Point"}
}