{
  "type": "Feature",
  "properties": {
    "iso:country":"US",
    "sg:address":"1524 Johnstons Rd",
    "sg:city":"Norfolk",
    "sg:classifiers":[
        {
            "category":"Restaurant",
            "type":"Food & Drink"
        }
    ],
    "sg:phone":"+1 757 853 5341",
    "sg:postcode":"23518",
    "sg:province":"VA",
    "sg:tags":[
        "eating"
    ],
    "wof:name":"Michael Bobs",
    "wof:placetype":"venue"
},
  "geometry": {"coordinates":[-76.232415,36.909832],"type":"Point"}
}