{
  "type": "Feature",
  "properties": {
    "addr:full":"13655 Lee Jackson Memorial Hwy Chantilly VA 20151",
    "addr:housenumber":"13655",
    "addr:postcode":"20151",
    "addr:street":"Lee Jackson Memorial Hwy",
    "iso:country":"US",
    "sg:address":"13655 Lee Jackson Memorial Hwy",
    "sg:city":"Chantilly",
    "sg:classifiers":[
        {
            "category":"Health Services",
            "subcategory":"Doctor",
            "type":"Services"
        }
    ],
    "sg:phone":"+1 703 263 7222",
    "sg:postcode":"20151",
    "sg:province":"VA",
    "sg:tags":[
        "dentist"
    ],
    "wof:name":"Chantilly Dental Arts Ctr",
    "wof:placetype":"venue"
},
  "geometry": {"coordinates":[-77.42105599999999,38.890098],"type":"Point"}
}