{
  "type": "Feature",
  "properties": {
    "addr:full":"9701 Rich Patch Rd Covington VA 24474",
    "addr:housenumber":"9701",
    "addr:postcode":"24474",
    "addr:street":"Rich Patch Rd",
    "iso:country":"US",
    "sg:address":"9701 Rich Patch Rd",
    "sg:city":"Covington",
    "sg:classifiers":[
        {
            "category":"Personal",
            "subcategory":"Beauty Salon",
            "type":"Services"
        }
    ],
    "sg:phone":"+1 540 862 5555",
    "sg:postcode":"24474",
    "sg:province":"VA",
    "sg:tags":[
        "shop"
    ],
    "wof:name":"Hair Crafters",
    "wof:placetype":"venue"
},
  "geometry": {"coordinates":[-79.885013,37.784689],"type":"Point"}
}