{
  "type": "Feature",
  "properties": {
    "addr:full":"1423 Johnston Willis Dr Richmond VA 23235",
    "addr:housenumber":"1423",
    "addr:postcode":"23235",
    "addr:street":"Johnston Willis Dr",
    "iso:country":"US",
    "sg:address":"1423 Johnston Willis Dr",
    "sg:city":"Richmond",
    "sg:classifiers":[
        {
            "category":"Health Services",
            "subcategory":"Health Practitioner",
            "type":"Services"
        }
    ],
    "sg:phone":"+1 804 323 5040",
    "sg:postcode":"23235",
    "sg:province":"VA",
    "sg:tags":[
        "medical"
    ],
    "wof:name":"Randal J West MD",
    "wof:placetype":"venue"
},
  "geometry": {"coordinates":[-77.59756400000001,37.51122],"type":"Point"}
}