{
  "type": "Feature",
  "properties": {
    "iso:country":"US",
    "sg:address":"738 Main St",
    "sg:city":"Monterey",
    "sg:classifiers":[
        {
            "category":"Professional",
            "subcategory":"Management & Consulting",
            "type":"Services"
        }
    ],
    "sg:phone":"+1 540 468 2023",
    "sg:postcode":"24422",
    "sg:province":"VA",
    "sg:tags":[
        "marketing",
        "program"
    ],
    "sg:website":"www.immigrationcontrol.com",
    "wof:name":"Americans For Immigrations",
    "wof:placetype":"venue"
},
  "geometry": {"coordinates":[-79.822148,37.815747],"type":"Point"}
}