{
  "type": "Feature",
  "properties": {
    "iso:country":"US",
    "sg:address":"2003 Mount Vernon Ave",
    "sg:city":"Alexandria",
    "sg:classifiers":[
        {
            "category":"Social Services",
            "subcategory":"Child Care",
            "type":"Services"
        }
    ],
    "sg:phone":"+1 703 548 1263",
    "sg:postcode":"22301",
    "sg:province":"VA",
    "sg:tags":[
        "day"
    ],
    "wof:name":"Creative Play School",
    "wof:placetype":"venue"
},
  "geometry": {"coordinates":[-77.058306,38.824648],"type":"Point"}
}