{
  "type": "Feature",
  "properties": {
    "addr:full":"4580 Virginia Beach Blvd Virginia Beach VA 23462",
    "addr:housenumber":"4580",
    "addr:postcode":"23462",
    "addr:street":"Virginia Beach Blvd",
    "iso:country":"US",
    "sg:address":"4580 Virginia Beach Blvd",
    "sg:city":"Virginia Beach",
    "sg:classifiers":[
        {
            "category":"Manufacturing",
            "subcategory":"Food",
            "type":"Manufacturing & Wholesale Goods"
        }
    ],
    "sg:phone":"+1 757 490 4556",
    "sg:postcode":"23462",
    "sg:province":"VA",
    "sg:tags":[
        "pretzel"
    ],
    "wof:name":"Pretzels Plus",
    "wof:placetype":"venue"
},
  "geometry": {"coordinates":[-76.136526,36.843746],"type":"Point"}
}