{
  "type": "Feature",
  "properties": {
    "addr:full":"13009 Lupine Turn Woodbridge VA 22192",
    "addr:housenumber":"13009",
    "addr:postcode":"22192",
    "addr:street":"Lupine Turn",
    "iso:country":"US",
    "sg:address":"13009 Lupine Turn",
    "sg:city":"Woodbridge",
    "sg:classifiers":[
        {
            "category":"Professional",
            "subcategory":"Management & Consulting",
            "type":"Services"
        }
    ],
    "sg:phone":"+1 703 600 3330",
    "sg:postcode":"22192",
    "sg:province":"VA",
    "sg:tags":[
        "information",
        "technology"
    ],
    "wof:name":"Ent Cnsciousness For Bus Ntwks",
    "wof:placetype":"venue"
},
  "geometry": {"coordinates":[-77.272723,38.670187],"type":"Point"}
}