{
  "type": "Feature",
  "properties": {
    "addr:full":"2906 Sycamore St Alexandria VA 22305",
    "addr:housenumber":"2906",
    "addr:postcode":"22305",
    "addr:street":"Sycamore St",
    "iso:country":"US",
    "sg:address":"2906 Sycamore St",
    "sg:city":"Alexandria",
    "sg:classifiers":[
        {
            "category":"Retail",
            "subcategory":"Animal Services",
            "type":"Services"
        }
    ],
    "sg:phone":"+1 703 548 8304",
    "sg:postcode":"22305",
    "sg:province":"VA",
    "wof:name":"Westie Rescue of Mid Atlantic",
    "wof:placetype":"venue"
},
  "geometry": {"coordinates":[-77.062894,38.832928],"type":"Point"}
}