{
  "type": "Feature",
  "properties": {
    "iso:country":"US",
    "sg:address":"6525 Centralia Rd",
    "sg:city":"Chesterfield",
    "sg:classifiers":[
        {
            "category":"Personal",
            "subcategory":"Tanning Parlor",
            "type":"Services"
        }
    ],
    "sg:phone":"+1 804 748 3922",
    "sg:postcode":"23832",
    "sg:province":"VA",
    "sg:tags":[
        "salon"
    ],
    "wof:name":"Capri Tan",
    "wof:placetype":"venue"
},
  "geometry": {"coordinates":[-77.500123,37.373675],"type":"Point"}
}