{
  "type": "Feature",
  "properties": {
    "addr:full":"225 A & W Dr Danville VA 24540",
    "addr:housenumber":"225 a",
    "addr:postcode":"24540",
    "addr:street":"& W Dr",
    "iso:country":"US",
    "sg:address":"225 A & W Dr",
    "sg:city":"Danville",
    "sg:classifiers":[
        {
            "category":"Food & Beverages",
            "subcategory":"Groceries & Convenience Stores",
            "type":"Retail Goods"
        }
    ],
    "sg:phone":"+1 434 822 5015",
    "sg:postcode":"24540",
    "sg:province":"VA",
    "sg:tags":[
        "grocer"
    ],
    "wof:name":"Allen's Grocery & Tackle",
    "wof:placetype":"venue"
},
  "geometry": {"coordinates":[-79.46625400000001,36.633201],"type":"Point"}
}