{
  "type": "Feature",
  "properties": {
    "addr:full":"9000 Three Chopt Rd Richmond VA 23229",
    "addr:housenumber":"9000",
    "addr:postcode":"23229",
    "addr:street":"Three Chopt Rd",
    "iso:country":"US",
    "sg:address":"9000 Three Chopt Rd",
    "sg:city":"Richmond",
    "sg:classifiers":[
        {
            "category":"Education",
            "subcategory":"School",
            "type":"Public Place"
        }
    ],
    "sg:phone":"+1 804 673 3720",
    "sg:postcode":"23229",
    "sg:province":"VA",
    "sg:website":"www.henrico.k12.va.us/ms/tuckahoems",
    "wof:name":"Tuckahoe Middle School",
    "wof:placetype":"venue"
},
  "geometry": {"coordinates":[-77.56238399999999,37.609985],"type":"Point"}
}