{
  "type": "Feature",
  "properties": {
    "iso:country":"US",
    "sg:address":"6060 Jefferson Ave",
    "sg:city":"Newport News",
    "sg:classifiers":[
        {
            "category":"Real Estate",
            "subcategory":"Architect",
            "type":"Services"
        }
    ],
    "sg:phone":"+1 757 245 0195",
    "sg:postcode":"23605",
    "sg:province":"VA",
    "sg:tags":[
        "marine",
        "naval",
        "engineer"
    ],
    "wof:name":"CDI Marine",
    "wof:placetype":"venue"
},
  "geometry": {"coordinates":[-76.444546,37.019543],"type":"Point"}
}