{
  "type": "Feature",
  "properties": {
    "iso:country":"US",
    "sg:address":"7020 Seminole Trl",
    "sg:city":"Ruckersville",
    "sg:classifiers":[
        {
            "category":"Food & Beverages",
            "subcategory":"Groceries & Convenience Stores",
            "type":"Retail Goods"
        }
    ],
    "sg:phone":"+1 434 985 4007",
    "sg:postcode":"22968",
    "sg:province":"VA",
    "sg:tags":[
        "filling",
        "station",
        "gasoline"
    ],
    "wof:name":"Sheetz Convenience Store",
    "wof:placetype":"venue"
},
  "geometry": {"coordinates":[-78.385794,38.207832],"type":"Point"}
}