{
  "type": "Feature",
  "properties": {
    "addr:full":"272 Jefferson Dr W Palmyra VA 22963",
    "addr:housenumber":"272",
    "addr:postcode":"22963",
    "addr:street":"Jefferson Dr W",
    "iso:country":"US",
    "sg:address":"272 Jefferson Dr W",
    "sg:city":"Palmyra",
    "sg:classifiers":[
        {
            "category":"Professional",
            "type":"Services"
        }
    ],
    "sg:phone":"+1 434 923 3515",
    "sg:postcode":"22963",
    "sg:province":"VA",
    "sg:tags":[
        "establishment"
    ],
    "wof:name":"BPO Intl",
    "wof:placetype":"venue"
},
  "geometry": {"coordinates":[-78.327507,37.91108],"type":"Point"}
}