{
  "type": "Feature",
  "properties": {
    "addr:full":"102 Jolly Roger Cove Stafford VA 22554",
    "addr:housenumber":"102",
    "addr:postcode":"22554",
    "addr:street":"Jolly Roger Cove",
    "iso:country":"US",
    "sg:address":"102 Jolly Roger Cove",
    "sg:city":"Stafford",
    "sg:classifiers":[
        {
            "category":"Professional",
            "type":"Services"
        }
    ],
    "sg:phone":"+1 540 659 0081",
    "sg:postcode":"22554",
    "sg:province":"VA",
    "wof:name":"Hpenterprises Ltd",
    "wof:placetype":"venue"
},
  "geometry": {"coordinates":[-77.386955,38.456718],"type":"Point"}
}