{
  "type": "Feature",
  "properties": {
    "iso:country":"US",
    "sg:address":"933 Aberdeen Rd",
    "sg:city":"Hampton",
    "sg:classifiers":[
        {
            "category":"Food & Beverages",
            "subcategory":"Groceries & Convenience Stores",
            "type":"Retail Goods"
        }
    ],
    "sg:phone":"+1 757 838 0661",
    "sg:postcode":"23666",
    "sg:province":"VA",
    "wof:name":"Miller Mart 24",
    "wof:placetype":"venue"
},
  "geometry": {"coordinates":[-76.40421499999999,37.021204],"type":"Point"}
}