{
  "type": "Feature",
  "properties": {
    "addr:full":"5415 Quarles Ct Woodbridge VA 22193",
    "addr:housenumber":"5415",
    "addr:postcode":"22193",
    "addr:street":"Quarles Ct",
    "iso:country":"US",
    "sg:address":"5415 Quarles Ct",
    "sg:city":"Woodbridge",
    "sg:classifiers":[
        {
            "category":"Restaurant",
            "type":"Food & Drink"
        }
    ],
    "sg:phone":"+1 703 680 9247",
    "sg:postcode":"22193",
    "sg:province":"VA",
    "sg:tags":[
        "eating"
    ],
    "wof:name":"David Samuelson",
    "wof:placetype":"venue"
},
  "geometry": {"coordinates":[-77.368295,38.66379],"type":"Point"}
}