{
  "type": "Feature",
  "properties": {
    "iso:country":"US",
    "sg:address":"1917 Arctic Ave",
    "sg:city":"Virginia Beach",
    "sg:classifiers":[
        {
            "category":"Parking",
            "type":"Transportation"
        }
    ],
    "sg:phone":"+1 757 437 1157",
    "sg:postcode":"23451",
    "sg:province":"VA",
    "sg:tags":[
        "garage"
    ],
    "wof:name":"Central Parking System",
    "wof:placetype":"venue"
},
  "geometry": {"coordinates":[-75.97807299999999,36.847586],"type":"Point"}
}