{
  "type": "Feature",
  "properties": {
    "addr:full":"1817 Roundfield Ln Manakin Sabot VA 23103",
    "addr:housenumber":"1817",
    "addr:postcode":"23103",
    "addr:street":"Roundfield Ln",
    "iso:country":"US",
    "sg:address":"1817 Roundfield Ln",
    "sg:city":"Manakin Sabot",
    "sg:classifiers":[
        {
            "category":"Insurance",
            "subcategory":"Insurance Agent",
            "type":"Services"
        }
    ],
    "sg:phone":"+1 804 784 0036",
    "sg:postcode":"23103",
    "sg:province":"VA",
    "wof:name":"Crawford Financial Group",
    "wof:placetype":"venue"
},
  "geometry": {"coordinates":[-77.712621,37.677437],"type":"Point"}
}