{
  "type": "Feature",
  "properties": {
    "iso:country":"US",
    "sg:address":"3008 Marisa Ct",
    "sg:city":"Woodbridge",
    "sg:classifiers":[
        {
            "category":"Professional",
            "subcategory":"Computer Services",
            "type":"Services"
        }
    ],
    "sg:phone":"+1 703 338 8486",
    "sg:postcode":"22192",
    "sg:province":"VA",
    "sg:tags":[
        "web",
        "consulting"
    ],
    "wof:name":"L F Designs",
    "wof:placetype":"venue"
},
  "geometry": {"coordinates":[-77.303135,38.659157],"type":"Point"}
}