{
  "type": "Feature",
  "properties": {
    "addr:full":"4030 Plank Rd Fredericksburg VA 22407",
    "addr:housenumber":"4030",
    "addr:postcode":"22407",
    "addr:street":"Plank Rd",
    "iso:country":"US",
    "sg:address":"4030 Plank Rd",
    "sg:city":"Fredericksburg",
    "sg:classifiers":[
        {
            "category":"Professional",
            "subcategory":"Lawyer & Legal Services",
            "type":"Services"
        }
    ],
    "sg:phone":"+1 540 786 4772",
    "sg:postcode":"22407",
    "sg:province":"VA",
    "sg:tags":[
        "attorney"
    ],
    "wof:name":"John A Mell Law Office",
    "wof:placetype":"venue"
},
  "geometry": {"coordinates":[-77.529673,38.289844],"type":"Point"}
}