{
  "type": "Feature",
  "properties": {
    "addr:full":"4200 Portsmouth Blvd Chesapeake VA 23321",
    "addr:housenumber":"4200",
    "addr:postcode":"23321",
    "addr:street":"Portsmouth Blvd",
    "iso:country":"US",
    "sg:address":"4200 Portsmouth Blvd",
    "sg:city":"Chesapeake",
    "sg:classifiers":[
        {
            "category":"Shopping",
            "subcategory":"Clothing, Apparel, & Fashions",
            "type":"Retail Goods"
        }
    ],
    "sg:phone":"+1 757 405 0054",
    "sg:postcode":"23321",
    "sg:province":"VA",
    "sg:tags":[
        "leather"
    ],
    "wof:name":"Wilsons Leather",
    "wof:placetype":"venue"
},
  "geometry": {"coordinates":[-76.417018,36.822703],"type":"Point"}
}