{
  "type": "Feature",
  "properties": {
    "addr:full":"873 Gough Rd Rustburg VA 24588",
    "addr:housenumber":"873",
    "addr:postcode":"24588",
    "addr:street":"Gough Rd",
    "iso:country":"US",
    "sg:address":"873 Gough Rd",
    "sg:city":"Rustburg",
    "sg:classifiers":[
        {
            "category":"Manufacturing",
            "subcategory":"Signs",
            "type":"Manufacturing & Wholesale Goods"
        }
    ],
    "sg:phone":"+1 434 821 1190",
    "sg:postcode":"24588",
    "sg:province":"VA",
    "sg:tags":[
        "advertising",
        "specialty"
    ],
    "wof:name":"Raleigh Signs",
    "wof:placetype":"venue"
},
  "geometry": {"coordinates":[-79.169679,37.246571],"type":"Point"}
}