{
  "type": "Feature",
  "properties": {
    "addr:full":"6601 Springfield Mall Springfield VA 22150",
    "addr:housenumber":"6601",
    "addr:postcode":"22150",
    "addr:street":"Springfield Mall",
    "iso:country":"US",
    "sg:address":"6601 Springfield Mall",
    "sg:city":"Springfield",
    "sg:classifiers":[
        {
            "category":"Utilities",
            "subcategory":"Telephone",
            "type":"Services"
        }
    ],
    "sg:phone":"+1 703 971 4208",
    "sg:postcode":"22150",
    "sg:province":"VA",
    "sg:tags":[
        "equipment",
        "system"
    ],
    "sg:website":"http://www.att.com",
    "wof:name":"AT&T",
    "wof:placetype":"venue"
},
  "geometry": {"coordinates":[-77.175532,38.771994],"type":"Point"}
}