{
  "type": "Feature",
  "properties": {
    "addr:full":"55 Parkwood Ct Collinsville VA 24078",
    "addr:housenumber":"55",
    "addr:postcode":"24078",
    "addr:street":"Parkwood Ct",
    "iso:country":"US",
    "sg:address":"55 Parkwood Ct",
    "sg:city":"Collinsville",
    "sg:classifiers":[
        {
            "category":"Professional",
            "type":"Services"
        }
    ],
    "sg:phone":"+1 276 647 1028",
    "sg:postcode":"24078",
    "sg:province":"VA",
    "wof:name":"Muzik Box & Co LLC",
    "wof:placetype":"venue"
},
  "geometry": {"coordinates":[-79.905851,36.739114],"type":"Point"}
}