{
  "type": "Feature",
  "properties": {
    "addr:full":"4854 Longhill Rd Williamsburg VA 23188",
    "addr:housenumber":"4854",
    "addr:postcode":"23188",
    "addr:street":"Longhill Rd",
    "iso:country":"US",
    "sg:address":"4854 Longhill Rd",
    "sg:city":"Williamsburg",
    "sg:classifiers":[
        {
            "category":"Food & Beverages",
            "subcategory":"Groceries & Convenience Stores",
            "type":"Retail Goods"
        }
    ],
    "sg:phone":"+1 757 253 8761",
    "sg:postcode":"23188",
    "sg:province":"VA",
    "wof:name":"Ameristop Food Mart",
    "wof:placetype":"venue"
},
  "geometry": {"coordinates":[-76.75122399999999,37.305285],"type":"Point"}
}