{
  "type": "Feature",
  "properties": {
    "iso:country":"US",
    "sg:address":"9229 Forest Haven Dr",
    "sg:city":"Alexandria",
    "sg:classifiers":[
        {
            "category":"Organizations",
            "subcategory":"Non-profit Organization",
            "type":"Services"
        }
    ],
    "sg:phone":"+1 703 360 9417",
    "sg:postcode":"22309",
    "sg:province":"VA",
    "sg:tags":[
        "association",
        "social"
    ],
    "wof:name":"78th Troop Carrier Squadrent",
    "wof:placetype":"venue"
},
  "geometry": {"coordinates":[-77.111375,38.705461],"type":"Point"}
}