{
  "type": "Feature",
  "properties": {
    "iso:country":"US",
    "sg:address":"1489 Shadow Oaks Pl",
    "sg:city":"Charlottesville",
    "sg:classifiers":[
        {
            "category":"Health Services",
            "subcategory":"Health Practitioner",
            "type":"Services"
        }
    ],
    "sg:phone":"+1 434 973 7218",
    "sg:postcode":"22901",
    "sg:province":"VA",
    "wof:name":"Aquatic Wellness Center Inc",
    "wof:placetype":"venue"
},
  "geometry": {"coordinates":[-78.465761,38.078082],"type":"Point"}
}