{
  "type": "Feature",
  "properties": {
    "iso:country":"US",
    "sg:address":"2632 Battlefield Blvd S",
    "sg:city":"Chesapeake",
    "sg:classifiers":[
        {
            "category":"Food & Beverages",
            "subcategory":"Groceries & Convenience Stores",
            "type":"Retail Goods"
        }
    ],
    "sg:phone":"+1 571 330 0303",
    "sg:postcode":"23322",
    "sg:province":"VA",
    "sg:tags":[
        "grocer"
    ],
    "wof:name":"Little Earl's",
    "wof:placetype":"venue"
},
  "geometry": {"coordinates":[-76.208139,36.632051],"type":"Point"}
}