{
  "type": "Feature",
  "properties": {
    "iso:country":"US",
    "sg:address":"4656 Briarwood Dr",
    "sg:city":"Charlottesville",
    "sg:classifiers":[
        {
            "category":"Personal",
            "subcategory":"Beauty Salon",
            "type":"Services"
        }
    ],
    "sg:phone":"+1 434 964 1114",
    "sg:postcode":"22911",
    "sg:province":"VA",
    "sg:tags":[
        "shop"
    ],
    "wof:name":"Renovations",
    "wof:placetype":"venue"
},
  "geometry": {"coordinates":[-78.418936,38.164429],"type":"Point"}
}