{
  "type": "Feature",
  "properties": {
    "iso:country":"US",
    "sg:address":"2222 Monument Ave",
    "sg:city":"Richmond",
    "sg:classifiers":[
        {
            "category":"Professional",
            "subcategory":"Lawyer & Legal Services",
            "type":"Services"
        }
    ],
    "sg:phone":"+1 804 358 5533",
    "sg:postcode":"23220",
    "sg:province":"VA",
    "sg:tags":[
        "attorney"
    ],
    "wof:name":"Sanford B Norman",
    "wof:placetype":"venue"
},
  "geometry": {"coordinates":[-77.46520200000001,37.557104],"type":"Point"}
}