{
  "type": "Feature",
  "properties": {
    "iso:country":"US",
    "sg:address":"1400 Ingram Ave",
    "sg:city":"Richmond",
    "sg:classifiers":[
        {
            "category":"Wholesale",
            "subcategory":"Tobacco Products",
            "type":"Manufacturing & Wholesale Goods"
        }
    ],
    "sg:phone":"+1 804 232 7027",
    "sg:postcode":"23224",
    "sg:province":"VA",
    "wof:name":"Lucky Strike Storages",
    "wof:placetype":"venue"
},
  "geometry": {"coordinates":[-77.43701900000001,37.509385],"type":"Point"}
}