{
  "type": "Feature",
  "properties": {
    "addr:full":"730 Grove Rd Midlothian VA 23114",
    "addr:housenumber":"730",
    "addr:postcode":"23114",
    "addr:street":"Grove Rd",
    "iso:country":"US",
    "sg:address":"730 Grove Rd",
    "sg:city":"Midlothian",
    "sg:classifiers":[
        {
            "category":"Wholesale",
            "subcategory":"Machinery & Supplies",
            "type":"Manufacturing & Wholesale Goods"
        }
    ],
    "sg:phone":"+1 804 379 7795",
    "sg:postcode":"23114",
    "sg:province":"VA",
    "sg:tags":[
        "industrial"
    ],
    "wof:name":"R J S Sales Company",
    "wof:placetype":"venue"
},
  "geometry": {"coordinates":[-77.61471,37.499527],"type":"Point"}
}