{
  "type": "Feature",
  "properties": {
    "addr:full":"30 E 8th St Front Royal VA 22630",
    "addr:housenumber":"30",
    "addr:postcode":"22630",
    "addr:street":"E 8Th St",
    "iso:country":"US",
    "sg:address":"30 E 8th St",
    "sg:city":"Front Royal",
    "sg:classifiers":[
        {
            "category":"Home & Garden",
            "subcategory":"Building Materials",
            "type":"Retail Goods"
        }
    ],
    "sg:phone":"+1 540 631 3467",
    "sg:postcode":"22630",
    "sg:province":"VA",
    "wof:name":"Zenglass Studio",
    "wof:placetype":"venue"
},
  "geometry": {"coordinates":[-78.193665,38.928875],"type":"Point"}
}