{
  "type": "Feature",
  "properties": {
    "iso:country":"US",
    "sg:address":"119 S Fairfax St Ste 1",
    "sg:city":"Alexandria",
    "sg:classifiers":[
        {
            "category":"Social Services",
            "subcategory":"Job Training",
            "type":"Services"
        },
        {
            "category":"Education",
            "subcategory":"Vocational School",
            "type":"Public Place"
        }
    ],
    "sg:phone":"+1 703 684 8807",
    "sg:postcode":"22314",
    "sg:province":"VA",
    "sg:tags":[
        "consultant",
        "business"
    ],
    "sg:website":"http://www.penncentral088088.com",
    "wof:name":"Alan L Freed Associates Inc",
    "wof:placetype":"venue"
},
  "geometry": {"coordinates":[-77.04266699999999,38.803904],"type":"Point"}
}