{
  "type": "Feature",
  "properties": {
    "addr:full":"501 Southlake Blvd Richmond VA 23236",
    "addr:housenumber":"501",
    "addr:postcode":"23236",
    "addr:street":"Southlake Blvd",
    "iso:country":"US",
    "sg:address":"501 Southlake Blvd",
    "sg:city":"Richmond",
    "sg:classifiers":[
        {
            "category":"Manufacturing",
            "subcategory":"Tools & Machinery",
            "type":"Manufacturing & Wholesale Goods"
        }
    ],
    "sg:phone":"+1 804 794 9777",
    "sg:postcode":"23236",
    "sg:province":"VA",
    "sg:tags":[
        "packaging"
    ],
    "sg:website":"www.gdpackagemachinery.com",
    "wof:name":"G D Package Machinery Inc",
    "wof:placetype":"venue"
},
  "geometry": {"coordinates":[-77.59822699999999,37.498982],"type":"Point"}
}