{
  "type": "Feature",
  "properties": {
    "addr:full":"285 Poor Creek Ln Greenville VA 24440",
    "addr:housenumber":"285",
    "addr:postcode":"24440",
    "addr:street":"Poor Creek Ln",
    "iso:country":"US",
    "sg:address":"285 Poor Creek Ln",
    "sg:city":"Greenville",
    "sg:classifiers":[
        {
            "category":"Retail",
            "subcategory":"Auto Repair",
            "type":"Services"
        }
    ],
    "sg:phone":"+1 540 377 2369",
    "sg:postcode":"24440",
    "sg:province":"VA",
    "sg:tags":[
        "transmission"
    ],
    "wof:name":"Sweet's Transmission Svc",
    "wof:placetype":"venue"
},
  "geometry": {"coordinates":[-79.15448600000001,37.975918],"type":"Point"}
}