{
  "type": "Feature",
  "properties": {
    "addr:full":"9824 Sudley Manor Dr Manassas VA 20109",
    "addr:housenumber":"9824",
    "addr:postcode":"20109",
    "addr:street":"Sudley Manor Dr",
    "iso:country":"US",
    "sg:address":"9824 Sudley Manor Dr",
    "sg:city":"Manassas",
    "sg:classifiers":[
        {
            "category":"Building & Trades",
            "subcategory":"Cleaning & Sanitation",
            "type":"Services"
        }
    ],
    "sg:phone":"+1 703 335 6580",
    "sg:postcode":"20109",
    "sg:province":"VA",
    "sg:tags":[
        "carpet"
    ],
    "wof:name":"Bmc Carpet Services",
    "wof:placetype":"venue"
},
  "geometry": {"coordinates":[-77.494471,38.790669],"type":"Point"}
}