{
  "type": "Feature",
  "properties": {
    "iso:country":"US",
    "sg:address":"146 James River Rd",
    "sg:city":"Scottsville",
    "sg:classifiers":[
        {
            "category":"Banks & Credit Unions",
            "subcategory":"Bank",
            "type":"Services"
        }
    ],
    "sg:phone":"+1 434 286 3851",
    "sg:postcode":"24590",
    "sg:province":"VA",
    "sg:tags":[
        "national",
        "commercial"
    ],
    "wof:name":"One Valley Bank",
    "wof:placetype":"venue"
},
  "geometry": {"coordinates":[-78.501197,37.809544],"type":"Point"}
}