{
  "type": "Feature",
  "properties": {
    "addr:full":"200 N Glebe Rd Arlington VA 22203",
    "addr:housenumber":"200",
    "addr:postcode":"22203",
    "addr:street":"N Glebe Rd",
    "iso:country":"US",
    "sg:address":"200 N Glebe Rd",
    "sg:city":"Arlington",
    "sg:classifiers":[
        {
            "category":"Real Estate",
            "subcategory":"Real Estate Operator",
            "type":"Services"
        }
    ],
    "sg:phone":"+1 703 527 1050",
    "sg:postcode":"22203",
    "sg:province":"VA",
    "sg:tags":[
        "building",
        "commercial",
        "parks"
    ],
    "wof:name":"200 North Glebe Road Inc",
    "wof:placetype":"venue"
},
  "geometry": {"coordinates":[-77.103555,38.872704],"type":"Point"}
}