{
  "type": "Feature",
  "properties": {
    "iso:country":"US",
    "sg:address":"6135 Rockfish Gap Tpke",
    "sg:city":"Crozet",
    "sg:classifiers":[
        {
            "category":"Organizations",
            "subcategory":"Community Association",
            "type":"Services"
        }
    ],
    "sg:phone":"+1 434 823 2316",
    "sg:postcode":"22932",
    "sg:province":"VA",
    "sg:tags":[
        "fraternal"
    ],
    "wof:name":"Crozet Moose Lodge",
    "wof:placetype":"venue"
},
  "geometry": {"coordinates":[-78.713691,38.049259],"type":"Point"}
}