{
  "type": "Feature",
  "properties": {
    "iso:country":"US",
    "sg:address":"2007 15th St N",
    "sg:city":"Arlington",
    "sg:classifiers":[
        {
            "category":"Professional",
            "subcategory":"Lawyer & Legal Services",
            "type":"Services"
        }
    ],
    "sg:phone":"+1 703 243 0097",
    "sg:postcode":"22201",
    "sg:province":"VA",
    "wof:name":"McKenzie & Kim Plc",
    "wof:placetype":"venue"
},
  "geometry": {"coordinates":[-77.08228800000001,38.891062],"type":"Point"}
}