{
  "type": "Feature",
  "properties": {
    "iso:country":"US",
    "sg:address":"10504 Lawyers Rd",
    "sg:city":"Vienna",
    "sg:classifiers":[
        {
            "category":"Professional",
            "subcategory":"Computer Services",
            "type":"Services"
        }
    ],
    "sg:phone":"+1 703 242 7734",
    "sg:postcode":"22181",
    "sg:province":"VA",
    "sg:tags":[
        "consulting",
        "management",
        "related"
    ],
    "wof:name":"Critical Path Consulting Corp",
    "wof:placetype":"venue"
},
  "geometry": {"coordinates":[-77.30604700000001,38.920558],"type":"Point"}
}