{
  "type": "Feature",
  "properties": {
    "iso:country":"US",
    "sg:address":"3313 Douglas Rd",
    "sg:city":"Chesapeake",
    "sg:classifiers":[
        {
            "category":"Shopping",
            "subcategory":"Clothing, Apparel, & Fashions",
            "type":"Retail Goods"
        }
    ],
    "sg:phone":"+1 757 421 0211",
    "sg:postcode":"23322",
    "sg:province":"VA",
    "wof:name":"Adam & Eve Christian Wear",
    "wof:placetype":"venue"
},
  "geometry": {"coordinates":[-76.33963199999999,36.629031],"type":"Point"}
}