{
  "type": "Feature",
  "properties": {
    "addr:full":"11160 Hull Street Rd Midlothian VA 23112",
    "addr:housenumber":"11160",
    "addr:postcode":"23112",
    "addr:street":"Hull Street Rd",
    "iso:country":"US",
    "sg:address":"11160 Hull Street Rd",
    "sg:city":"Midlothian",
    "sg:classifiers":[
        {
            "category":"Utilities",
            "subcategory":"Mobile Phone",
            "type":"Services"
        },
        {
            "category":"Shopping",
            "type":"Retail Goods"
        }
    ],
    "sg:phone":"+1 804 639 6400",
    "sg:postcode":"23112",
    "sg:province":"VA",
    "sg:tags":[
        "communication",
        "system",
        "equipment",
        "paging",
        "radiotelephone",
        "merchandise",
        "signaling"
    ],
    "wof:name":"Cellular City Inc",
    "wof:placetype":"venue"
},
  "geometry": {"coordinates":[-77.600543,37.437328],"type":"Point"}
}