{
  "type": "Feature",
  "properties": {
    "addr:full":"5319 Jefferson Davis Hwy Fredericksburg VA 22408",
    "addr:housenumber":"5319",
    "addr:postcode":"22408",
    "addr:street":"Jefferson Davis Hwy",
    "iso:country":"US",
    "sg:address":"5319 Jefferson Davis Hwy",
    "sg:city":"Fredericksburg",
    "sg:classifiers":[
        {
            "category":"Travel",
            "subcategory":"Hotels & Motels",
            "type":"Entertainment"
        }
    ],
    "sg:phone":"+1 540 898 7100",
    "sg:postcode":"22408",
    "sg:province":"VA",
    "wof:name":"Super 8 Motel",
    "wof:placetype":"venue"
},
  "geometry": {"coordinates":[-77.499039,38.24509],"type":"Point"}
}