{
  "type": "Feature",
  "properties": {
    "addr:full":"6279 Spring Hill Rd Waverly VA 23890",
    "addr:housenumber":"6279",
    "addr:postcode":"23890",
    "addr:street":"Spring Hill Rd",
    "iso:country":"US",
    "sg:address":"6279 Spring Hill Rd",
    "sg:city":"Waverly",
    "sg:classifiers":[
        {
            "category":"Professional",
            "type":"Services"
        }
    ],
    "sg:phone":"+1 804 834 3075",
    "sg:postcode":"23890",
    "sg:province":"VA",
    "wof:name":"Wendell H Goss",
    "wof:placetype":"venue"
},
  "geometry": {"coordinates":[-76.99740799999999,37.032113],"type":"Point"}
}