{
  "type": "Feature",
  "properties": {
    "addr:full":"129 Pell Ave Rocky Mount VA 24151",
    "addr:housenumber":"129",
    "addr:postcode":"24151",
    "addr:street":"Pell Ave",
    "iso:country":"US",
    "sg:address":"129 Pell Ave",
    "sg:city":"Rocky Mount",
    "sg:classifiers":[
        {
            "category":"Freight",
            "type":"Transportation"
        }
    ],
    "sg:phone":"+1 540 483 0340",
    "sg:postcode":"24151",
    "sg:province":"VA",
    "sg:tags":[
        "marina",
        "operation",
        "special"
    ],
    "wof:name":"Rocky Mount Indoor Commercial",
    "wof:placetype":"venue"
},
  "geometry": {"coordinates":[-79.884897,37.00393],"type":"Point"}
}