{
  "type": "Feature",
  "properties": {
    "addr:full":"5158 Nine Mile Rd Richmond VA 23223",
    "addr:housenumber":"5158",
    "addr:postcode":"23223",
    "addr:street":"Nine Mile Rd",
    "iso:country":"US",
    "sg:address":"5158 Nine Mile Rd",
    "sg:city":"Richmond",
    "sg:classifiers":[
        {
            "category":"Shopping",
            "subcategory":"Used Merchandise",
            "type":"Retail Goods"
        }
    ],
    "sg:phone":"+1 804 737 9494",
    "sg:postcode":"23223",
    "sg:province":"VA",
    "sg:tags":[
        "shop",
        "thrift"
    ],
    "wof:name":"Love-Jesus Thrift Store East",
    "wof:placetype":"venue"
},
  "geometry": {"coordinates":[-77.360302,37.547755],"type":"Point"}
}