{
  "type": "Feature",
  "properties": {
    "iso:country":"US",
    "sg:address":"12650 Jefferson Davis Hwy",
    "sg:city":"Chester",
    "sg:classifiers":[
        {
            "category":"Shopping",
            "subcategory":"Computers & Home Electronics",
            "type":"Retail Goods"
        }
    ],
    "sg:phone":"+1 804 768 9571",
    "sg:postcode":"23831",
    "sg:province":"VA",
    "sg:tags":[
        "equipment",
        "dealer"
    ],
    "sg:website":"www.tdsol.com",
    "wof:name":"Tailored Data Solutions",
    "wof:placetype":"venue"
},
  "geometry": {"coordinates":[-77.41272600000001,37.353401],"type":"Point"}
}