{
  "type": "Feature",
  "properties": {
    "addr:full":"9210 Jefferson Davis Hwy Richmond VA 23237",
    "addr:housenumber":"9210",
    "addr:postcode":"23237",
    "addr:street":"Jefferson Davis Hwy",
    "iso:country":"US",
    "sg:address":"9210 Jefferson Davis Hwy",
    "sg:city":"Richmond",
    "sg:classifiers":[
        {
            "category":"Autos & Motor Vehicles",
            "subcategory":"Fuel & Gas Station",
            "type":"Retail Goods"
        }
    ],
    "sg:phone":"+1 804 271 8882",
    "sg:postcode":"23237",
    "sg:province":"VA",
    "sg:tags":[
        "grocery",
        "station",
        "gasoline"
    ],
    "wof:name":"Crown Central",
    "wof:placetype":"venue"
},
  "geometry": {"coordinates":[-77.43147,37.39873],"type":"Point"}
}