{
  "type": "Feature",
  "properties": {
    "addr:full":"541 Mc Farland Rd Norfolk VA 23505",
    "addr:housenumber":"541",
    "addr:postcode":"23505",
    "addr:street":"Mc Farland Rd",
    "iso:country":"US",
    "sg:address":"541 Mc Farland Rd",
    "sg:city":"Norfolk",
    "sg:classifiers":[
        {
            "category":"Building & Trades",
            "subcategory":"Construction",
            "type":"Services"
        }
    ],
    "sg:phone":"+1 757 480 6196",
    "sg:postcode":"23505",
    "sg:province":"VA",
    "sg:tags":[
        "general",
        "contractor"
    ],
    "wof:name":"Chiefs Construction Company",
    "wof:placetype":"venue"
},
  "geometry": {"coordinates":[-76.256107,36.919409],"type":"Point"}
}