{
  "type": "Feature",
  "properties": {
    "addr:full":"4300 Eubank Rd Richmond VA 23231",
    "addr:housenumber":"4300",
    "addr:postcode":"23231",
    "addr:street":"Eubank Rd",
    "iso:country":"US",
    "sg:address":"4300 Eubank Rd",
    "sg:city":"Richmond",
    "sg:classifiers":[
        {
            "category":"Wholesale",
            "subcategory":"Farm Supplies",
            "type":"Manufacturing & Wholesale Goods"
        }
    ],
    "sg:phone":"+1 804 222 2848",
    "sg:postcode":"23231",
    "sg:province":"VA",
    "sg:tags":[
        "chemical",
        "lawn"
    ],
    "wof:name":"Simplot Partners",
    "wof:placetype":"venue"
},
  "geometry": {"coordinates":[-77.358644,37.514406],"type":"Point"}
}