{
  "type": "Feature",
  "properties": {
    "iso:country":"US",
    "sg:address":"421 King St",
    "sg:city":"Alexandria",
    "sg:classifiers":[
        {
            "category":"Government",
            "subcategory":"Office",
            "type":"Public Place"
        }
    ],
    "sg:phone":"+1 703 838 5030",
    "sg:postcode":"22314",
    "sg:province":"VA",
    "sg:tags":[
        "village"
    ],
    "wof:name":"Alexandria Office For Women",
    "wof:placetype":"venue"
},
  "geometry": {"coordinates":[-77.04455900000001,38.804818],"type":"Point"}
}