{
  "type": "Feature",
  "properties": {
    "addr:full":"10626 Beechnut Ct Fairfax Station VA 22039",
    "addr:housenumber":"10626",
    "addr:postcode":"22039",
    "addr:street":"Beechnut Ct",
    "iso:country":"US",
    "sg:address":"10626 Beechnut Ct",
    "sg:city":"Fairfax Station",
    "sg:classifiers":[
        {
            "category":"Professional",
            "subcategory":"Research",
            "type":"Services"
        }
    ],
    "sg:phone":"+1 703 250 3442",
    "sg:postcode":"22039",
    "sg:province":"VA",
    "sg:tags":[
        "environmental",
        "ecological"
    ],
    "wof:name":"Biogenesis Enterprises Inc",
    "wof:placetype":"venue"
},
  "geometry": {"coordinates":[-77.316458,38.759189],"type":"Point"}
}