{
  "type": "Feature",
  "properties": {
    "iso:country":"US",
    "sg:address":"101 Malibu Dr",
    "sg:city":"Virginia Beach",
    "sg:classifiers":[
        {
            "category":"Professional",
            "subcategory":"Management & Consulting",
            "type":"Services"
        },
        {
            "category":"Wholesale",
            "subcategory":"Electrical",
            "type":"Manufacturing & Wholesale Goods"
        },
        {
            "category":"Manufacturing",
            "subcategory":"Electronics",
            "type":"Manufacturing & Wholesale Goods"
        }
    ],
    "sg:phone":"+1 757 463 3553",
    "sg:postcode":"23452",
    "sg:province":"VA",
    "sg:tags":[
        "satellite",
        "installation",
        "telecommunication",
        "mfg",
        "consultant",
        "sales",
        "equipment",
        "communication",
        "earth"
    ],
    "sg:website":"www.satsyscorp.com",
    "wof:name":"Satellite Systems Corporation",
    "wof:placetype":"venue"
},
  "geometry": {"coordinates":[-76.095209,36.8407],"type":"Point"}
}