{
  "type": "Feature",
  "properties": {
    "addr:full":"1738 Edgemont Ave Bristol VA 37620",
    "addr:housenumber":"1738",
    "addr:postcode":"37620",
    "addr:street":"Edgemont Ave",
    "iso:country":"US",
    "sg:address":"1738 Edgemont Ave",
    "sg:city":"Bristol",
    "sg:classifiers":[
        {
            "category":"Travel",
            "subcategory":"Travel Agent",
            "type":"Entertainment"
        }
    ],
    "sg:phone":"+1 423 989 4880",
    "sg:postcode":"37620",
    "sg:province":"VA",
    "sg:tags":[
        "agency",
        "bureau"
    ],
    "wof:name":"Travel Authority",
    "wof:placetype":"venue"
},
  "geometry": {"coordinates":[-82.185799,36.57504],"type":"Point"}
}