{
  "type": "Feature",
  "properties": {
    "addr:full":"5508 Gara Rd Virginia Beach VA 23464",
    "addr:housenumber":"5508",
    "addr:postcode":"23464",
    "addr:street":"Gara Rd",
    "iso:country":"US",
    "sg:address":"5508 Gara Rd",
    "sg:city":"Virginia Beach",
    "sg:classifiers":[
        {
            "category":"Building & Trades",
            "subcategory":"Plumbing",
            "type":"Services"
        }
    ],
    "sg:phone":"+1 757 424 3100",
    "sg:postcode":"23464",
    "sg:province":"VA",
    "sg:tags":[
        "conditioning",
        "air",
        "system",
        "contractor"
    ],
    "wof:name":"Metro Mechanical Corp",
    "wof:placetype":"venue"
},
  "geometry": {"coordinates":[-76.184904,36.821002],"type":"Point"}
}