{
  "type": "Feature",
  "properties": {
    "addr:full":"7172 Botetourt Ave Gloucester VA 23061",
    "addr:housenumber":"7172",
    "addr:postcode":"23061",
    "addr:street":"Botetourt Ave",
    "iso:country":"US",
    "sg:address":"7172 Botetourt Ave",
    "sg:city":"Gloucester",
    "sg:classifiers":[
        {
            "category":"Building & Trades",
            "subcategory":"Construction",
            "type":"Services"
        }
    ],
    "sg:phone":"+1 804 695 9370",
    "sg:postcode":"23061",
    "sg:province":"VA",
    "sg:tags":[
        "tile",
        "dealer",
        "contractor"
    ],
    "wof:name":"Robert Ronquest",
    "wof:placetype":"venue"
},
  "geometry": {"coordinates":[-76.527235,37.409829],"type":"Point"}
}