{
  "type": "Feature",
  "properties": {
    "addr:full":"900 Abingdon Ct Newport News VA 23608",
    "addr:housenumber":"900",
    "addr:postcode":"23608",
    "addr:street":"Abingdon Ct",
    "iso:country":"US",
    "sg:address":"900 Abingdon Ct",
    "sg:city":"Newport News",
    "sg:classifiers":[
        {
            "category":"Communications",
            "subcategory":"Film & Video Production",
            "type":"Services"
        }
    ],
    "sg:phone":"+1 757 872 0562",
    "sg:postcode":"23608",
    "sg:province":"VA",
    "sg:tags":[
        "motion",
        "editing",
        "tape"
    ],
    "wof:name":"TSC Video Productions Inc",
    "wof:placetype":"venue"
},
  "geometry": {"coordinates":[-76.513102,37.161028],"type":"Point"}
}