{
  "type": "Feature",
  "properties": {
    "addr:full":"9300 Allwood Ct Alexandria VA 22309",
    "addr:housenumber":"9300",
    "addr:postcode":"22309",
    "addr:street":"Allwood Ct",
    "iso:country":"US",
    "sg:address":"9300 Allwood Ct",
    "sg:city":"Alexandria",
    "sg:classifiers":[
        {
            "category":"Professional",
            "type":"Services"
        }
    ],
    "sg:phone":"+1 703 360 7331",
    "sg:postcode":"22309",
    "sg:province":"VA",
    "wof:name":"T Rutledge",
    "wof:placetype":"venue"
},
  "geometry": {"coordinates":[-77.108656,38.706131],"type":"Point"}
}