{
  "type": "Feature",
  "properties": {
    "addr:full":"105 50th St Virginia Beach VA 23451",
    "addr:housenumber":"105",
    "addr:postcode":"23451",
    "addr:street":"50Th St",
    "iso:country":"US",
    "sg:address":"105 50th St",
    "sg:city":"Virginia Beach",
    "sg:classifiers":[
        {
            "category":"Professional",
            "subcategory":"Management & Consulting",
            "type":"Services"
        }
    ],
    "sg:phone":"+1 757 622 0719",
    "sg:postcode":"23451",
    "sg:province":"VA",
    "wof:name":"Gottlieb & Gottlieb Intl",
    "wof:placetype":"venue"
},
  "geometry": {"coordinates":[-75.984458,36.877632],"type":"Point"}
}