{
  "type": "Feature",
  "properties": {
    "addr:full":"9606 4th View St Norfolk VA 23503",
    "addr:housenumber":"9606",
    "addr:postcode":"23503",
    "addr:street":"4Th View St",
    "iso:country":"US",
    "sg:address":"9606 4th View St",
    "sg:city":"Norfolk",
    "sg:classifiers":[
        {
            "category":"Professional",
            "subcategory":"Business Services",
            "type":"Services"
        }
    ],
    "sg:phone":"+1 757 480 0708",
    "sg:postcode":"23503",
    "sg:province":"VA",
    "wof:name":"Subsurface Technologies Inc",
    "wof:placetype":"venue"
},
  "geometry": {"coordinates":[-76.26104599999999,36.959667],"type":"Point"}
}