{
  "type": "Feature",
  "properties": {
    "addr:full":"3328 Melrose Ave NW Roanoke VA 24017",
    "addr:housenumber":"3328",
    "addr:postcode":"24017",
    "addr:street":"Melrose Ave Nw",
    "iso:country":"US",
    "sg:address":"3328 Melrose Ave NW",
    "sg:city":"Roanoke",
    "sg:classifiers":[
        {
            "category":"Wholesale",
            "subcategory":"Machinery & Supplies",
            "type":"Manufacturing & Wholesale Goods"
        }
    ],
    "sg:phone":"+1 540 344 7276",
    "sg:postcode":"24017",
    "sg:province":"VA",
    "sg:tags":[
        "dry",
        "repair",
        "laundry",
        "commercial",
        "equipment",
        "cleaning"
    ],
    "wof:name":"Cardinal Laundry Equipment Co",
    "wof:placetype":"venue"
},
  "geometry": {"coordinates":[-79.99008000000001,37.29106],"type":"Point"}
}