{
  "type": "Feature",
  "properties": {
    "addr:full":"116 Clover Dr Chesapeake VA 23322",
    "addr:housenumber":"116",
    "addr:postcode":"23322",
    "addr:street":"Clover Dr",
    "iso:country":"US",
    "sg:address":"116 Clover Dr",
    "sg:city":"Chesapeake",
    "sg:classifiers":[
        {
            "category":"Professional",
            "type":"Services"
        }
    ],
    "sg:phone":"+1 757 410 8734",
    "sg:postcode":"23322",
    "sg:province":"VA",
    "sg:tags":[
        "establishment"
    ],
    "wof:name":"Arison & Arison",
    "wof:placetype":"venue"
},
  "geometry": {"coordinates":[-76.234543,36.697923],"type":"Point"}
}