{
  "type": "Feature",
  "properties": {
    "iso:country":"US",
    "sg:address":"1575 Kenwood Ave",
    "sg:city":"Alexandria",
    "sg:classifiers":[
        {
            "category":"Autos & Motor Vehicles",
            "subcategory":"Automobile Sales",
            "type":"Retail Goods"
        }
    ],
    "sg:phone":"+1 703 931 3018",
    "sg:postcode":"22302",
    "sg:province":"VA",
    "sg:tags":[
        "car",
        "dealer"
    ],
    "wof:name":"Lindsay Chevrolet LLC",
    "wof:placetype":"venue"
},
  "geometry": {"coordinates":[-77.08296199999999,38.831009],"type":"Point"}
}