{
  "type": "Feature",
  "properties": {
    "addr:full":"7115 Leesburg Pike Falls Church VA 22043",
    "addr:housenumber":"7115",
    "addr:postcode":"22043",
    "addr:street":"Leesburg Pike",
    "iso:country":"US",
    "sg:address":"7115 Leesburg Pike",
    "sg:city":"Falls Church",
    "sg:classifiers":[
        {
            "category":"Building & Trades",
            "subcategory":"Cleaning & Sanitation",
            "type":"Services"
        }
    ],
    "sg:phone":"+1 703 237 9799",
    "sg:postcode":"22043",
    "sg:province":"VA",
    "sg:tags":[
        "janitor"
    ],
    "wof:name":"X Pert Cleaning Svc",
    "wof:placetype":"venue"
},
  "geometry": {"coordinates":[-77.19087399999999,38.894832],"type":"Point"}
}