{
  "type": "Feature",
  "properties": {
    "addr:full":"7201 Lockport Pl Lorton VA 22079",
    "addr:housenumber":"7201",
    "addr:postcode":"22079",
    "addr:street":"Lockport Pl",
    "iso:country":"US",
    "sg:address":"7201 Lockport Pl",
    "sg:city":"Lorton",
    "sg:classifiers":[
        {
            "category":"Professional",
            "subcategory":"Advertising",
            "type":"Services"
        }
    ],
    "sg:phone":"+1 703 339 7423",
    "sg:postcode":"22079",
    "sg:province":"VA",
    "sg:tags":[
        "mailing",
        "list"
    ],
    "wof:name":"Mailing List Systems LTD",
    "wof:placetype":"venue"
},
  "geometry": {"coordinates":[-77.194025,38.715029],"type":"Point"}
}