{
  "type": "Feature",
  "properties": {
    "iso:country":"US",
    "sg:address":"8306 Leland Rd",
    "sg:city":"Manassas",
    "sg:classifiers":[
        {
            "category":"Building & Trades",
            "subcategory":"Landscaping Services",
            "type":"Services"
        }
    ],
    "sg:phone":"+1 703 367 0022",
    "sg:postcode":"20111",
    "sg:province":"VA",
    "wof:name":"Steve Franks Yard Service",
    "wof:placetype":"venue"
},
  "geometry": {"coordinates":[-77.45164699999999,38.78714],"type":"Point"}
}