{
  "type": "Feature",
  "properties": {
    "addr:full":"1201 S Scott St Arlington VA 22204",
    "addr:housenumber":"1201",
    "addr:postcode":"22204",
    "addr:street":"S Scott St",
    "iso:country":"US",
    "sg:address":"1201 S Scott St",
    "sg:city":"Arlington",
    "sg:classifiers":[
        {
            "category":"Professional",
            "subcategory":"Management & Consulting",
            "type":"Services"
        }
    ],
    "sg:phone":"+1 703 402 6536",
    "sg:postcode":"22204",
    "sg:province":"VA",
    "wof:name":"Miyashiro Associates",
    "wof:placetype":"venue"
},
  "geometry": {"coordinates":[-77.077223,38.86278],"type":"Point"}
}