{
  "type": "Feature",
  "properties": {
    "iso:country":"US",
    "sg:address":"1761 Bus Center Dr",
    "sg:city":"Reston",
    "sg:classifiers":[
        {
            "category":"Utilities",
            "subcategory":"Cable",
            "type":"Services"
        }
    ],
    "sg:phone":"+1 703 438 8000",
    "sg:postcode":"20190",
    "sg:province":"VA",
    "sg:tags":[
        "satellite",
        "carrier"
    ],
    "sg:website":"www.aes.itt.com",
    "wof:name":"Comscore",
    "wof:placetype":"venue"
},
  "geometry": {"coordinates":[-77.325937,38.94938],"type":"Point"}
}