{
  "type": "Feature",
  "properties": {
    "addr:full":"8115 Mims St Lorton VA 22079",
    "addr:housenumber":"8115",
    "addr:postcode":"22079",
    "addr:street":"Mims St",
    "iso:country":"US",
    "sg:address":"8115 Mims St",
    "sg:city":"Lorton",
    "sg:classifiers":[
        {
            "category":"Manufacturing",
            "subcategory":"Glass & Minerals",
            "type":"Manufacturing & Wholesale Goods"
        }
    ],
    "sg:phone":"+1 703 550 7650",
    "sg:postcode":"22079",
    "sg:province":"VA",
    "sg:tags":[
        "ready"
    ],
    "wof:name":"Cardinal Concrete Co",
    "wof:placetype":"venue"
},
  "geometry": {"coordinates":[-77.22167399999999,38.69029],"type":"Point"}
}