{
  "type": "Feature",
  "properties": {
    "addr:full":"9452 Main St Fairfax VA 22031",
    "addr:housenumber":"9452",
    "addr:postcode":"22031",
    "addr:street":"Main St",
    "iso:country":"US",
    "sg:address":"9452 Main St",
    "sg:city":"Fairfax",
    "sg:classifiers":[
        {
            "category":"Health Services",
            "subcategory":"Hospital",
            "type":"Services"
        },
        {
            "category":"Health Services",
            "subcategory":"Doctor",
            "type":"Services"
        }
    ],
    "sg:phone":"+1 703 503 1112",
    "sg:postcode":"22031",
    "sg:province":"VA",
    "sg:tags":[
        "clinic",
        "general"
    ],
    "wof:name":"Med First Urgent Care",
    "wof:placetype":"venue"
},
  "geometry": {"coordinates":[-77.27128999999999,38.84116],"type":"Point"}
}