{
  "type": "Feature",
  "properties": {
    "iso:country":"US",
    "sg:address":"11294 Washington Hwy",
    "sg:city":"Ashland",
    "sg:classifiers":[
        {
            "category":"Building & Trades",
            "subcategory":"Construction",
            "type":"Services"
        }
    ],
    "sg:phone":"+1 804 798 8140",
    "sg:postcode":"23005",
    "sg:province":"VA",
    "sg:tags":[
        "contractor"
    ],
    "wof:name":"Piedmont Coverall Inc",
    "wof:placetype":"venue"
},
  "geometry": {"coordinates":[-77.4679,37.715628],"type":"Point"}
}