{
  "type": "Feature",
  "properties": {
    "addr:full":"242 Mustang Trl Virginia Beach VA 23452",
    "addr:housenumber":"242",
    "addr:postcode":"23452",
    "addr:street":"Mustang Trl",
    "iso:country":"US",
    "sg:address":"242 Mustang Trl",
    "sg:city":"Virginia Beach",
    "sg:classifiers":[
        {
            "category":"Health Services",
            "subcategory":"Health Practitioner",
            "type":"Services"
        }
    ],
    "sg:phone":"+1 757 481 6981",
    "sg:postcode":"23452",
    "sg:province":"VA",
    "sg:tags":[
        "therapist",
        "physical"
    ],
    "wof:name":"Therapy Network",
    "wof:placetype":"venue"
},
  "geometry": {"coordinates":[-76.067273,36.840003],"type":"Point"}
}