{
  "type": "Feature",
  "properties": {
    "iso:country":"US",
    "sg:address":"1015 King St",
    "sg:city":"Alexandria",
    "sg:classifiers":[
        {
            "category":"Shopping",
            "subcategory":"Used Merchandise",
            "type":"Retail Goods"
        }
    ],
    "sg:phone":"+1 703 549 0883",
    "sg:postcode":"22314",
    "sg:province":"VA",
    "sg:tags":[
        "antique"
    ],
    "wof:name":"King Street Antiques",
    "wof:placetype":"venue"
},
  "geometry": {"coordinates":[-77.051236,38.805679],"type":"Point"}
}