{
  "type": "Feature",
  "properties": {
    "iso:country":"US",
    "sg:address":"179 Merrimac Trl",
    "sg:city":"Williamsburg",
    "sg:classifiers":[
        {
            "category":"Personal",
            "subcategory":"Beauty Salon",
            "type":"Services"
        }
    ],
    "sg:phone":"+1 757 565 7470",
    "sg:postcode":"23185",
    "sg:province":"VA",
    "sg:tags":[
        "shop"
    ],
    "wof:name":"Darlenes Hair Studio Inc",
    "wof:placetype":"venue"
},
  "geometry": {"coordinates":[-76.684764,37.284116],"type":"Point"}
}