{
  "type": "Feature",
  "properties": {
    "iso:country":"US",
    "sg:address":"824 Greenbrier Pkwy",
    "sg:city":"Chesapeake",
    "sg:classifiers":[
        {
            "category":"Professional",
            "subcategory":"Advertising",
            "type":"Services"
        }
    ],
    "sg:phone":"+1 757 547 5400",
    "sg:postcode":"23320",
    "sg:province":"VA",
    "sg:tags":[
        "medium",
        "management",
        "buying"
    ],
    "sg:website":"www.newtonmedia.com",
    "wof:name":"Newton Media Associates Inc",
    "wof:placetype":"venue"
},
  "geometry": {"coordinates":[-76.22327900000001,36.747544],"type":"Point"}
}