{
  "type": "Feature",
  "properties": {
    "iso:country":"US",
    "sg:address":"2200 Old Williamsburg Rd",
    "sg:city":"Yorktown",
    "sg:classifiers":[
        {
            "category":"Restaurant",
            "type":"Food & Drink"
        }
    ],
    "sg:phone":"+1 757 888 9980",
    "sg:postcode":"23690",
    "sg:province":"VA",
    "wof:name":"Community Deli",
    "wof:placetype":"venue"
},
  "geometry": {"coordinates":[-76.54714800000001,37.23242],"type":"Point"}
}