{
  "type": "Feature",
  "properties": {
    "addr:full":"6308 John Charles Lndg Centreville VA 20121",
    "addr:housenumber":"6308",
    "addr:postcode":"20121",
    "addr:street":"John Charles Lndg",
    "iso:country":"US",
    "sg:address":"6308 John Charles Lndg",
    "sg:city":"Centreville",
    "sg:classifiers":[
        {
            "category":"Personal",
            "subcategory":"Hair Removal",
            "type":"Services"
        }
    ],
    "sg:phone":"+1 703 988 0054",
    "sg:postcode":"20121",
    "sg:province":"VA",
    "wof:name":"Capital Colors LLC",
    "wof:placetype":"venue"
},
  "geometry": {"coordinates":[-77.44354199999999,38.822949],"type":"Point"}
}