{
  "type": "Feature",
  "properties": {
    "iso:country":"US",
    "sg:address":"900 E Broad St",
    "sg:city":"Richmond",
    "sg:classifiers":[
        {
            "category":"Recreation",
            "type":"Entertainment"
        }
    ],
    "sg:phone":"+1 804 780 5733",
    "sg:postcode":"23219",
    "sg:province":"VA",
    "sg:tags":[
        "parks"
    ],
    "wof:name":"Richmond Recreation & Parks",
    "wof:placetype":"venue"
},
  "geometry": {"coordinates":[-77.43301599999999,37.540203],"type":"Point"}
}