{
  "type": "Feature",
  "properties": {
    "addr:full":"6844 Pallister Rd Norfolk VA 23518",
    "addr:postcode":"6844;23518",
    "addr:street":"Pallister Rd",
    "iso:country":"US",
    "sg:address":"6844 Pallister Rd",
    "sg:city":"Norfolk",
    "sg:classifiers":[
        {
            "category":"Professional",
            "type":"Services"
        }
    ],
    "sg:phone":"+1 757 853 1516",
    "sg:postcode":"23518",
    "sg:province":"VA",
    "wof:name":"Baylor Heirs LLC",
    "wof:placetype":"venue"
},
  "geometry": {"coordinates":[-76.22692600000001,36.903835],"type":"Point"}
}