{
  "type": "Feature",
  "properties": {
    "addr:full":"6022 Lincolnia Rd Alexandria VA 22312",
    "addr:postcode":"6022;22312",
    "addr:street":"Lincolnia Rd",
    "iso:country":"US",
    "sg:address":"6022 Lincolnia Rd",
    "sg:city":"Alexandria",
    "sg:classifiers":[
        {
            "category":"Professional",
            "subcategory":"Management & Consulting",
            "type":"Services"
        }
    ],
    "sg:phone":"+1 703 642 3191",
    "sg:postcode":"22312",
    "sg:province":"VA",
    "wof:name":"Adiversified Consulting Svcs",
    "wof:placetype":"venue"
},
  "geometry": {"coordinates":[-77.135486,38.818327],"type":"Point"}
}