{
  "type": "Feature",
  "properties": {
    "addr:full":"5310 Markel Rd Richmond VA 23230",
    "addr:postcode":"5310;23230",
    "addr:street":"Markel Rd",
    "iso:country":"US",
    "sg:address":"5310 Markel Rd",
    "sg:city":"Richmond",
    "sg:classifiers":[
        {
            "category":"Professional",
            "type":"Services"
        }
    ],
    "sg:phone":"+1 804 285 7640",
    "sg:postcode":"23230",
    "sg:province":"VA",
    "sg:tags":[
        "establishment"
    ],
    "wof:name":"Hresource One",
    "wof:placetype":"venue"
},
  "geometry": {"coordinates":[-77.500187,37.584859],"type":"Point"}
}