{
  "type": "Feature",
  "properties": {
    "addr:full":"200 W Grace St Richmond VA 23220",
    "addr:housenumber":"200",
    "addr:postcode":"23220",
    "addr:street":"W Grace St",
    "iso:country":"US",
    "sg:address":"200 W Grace St",
    "sg:city":"Richmond",
    "sg:classifiers":[
        {
            "category":"Professional",
            "type":"Services"
        }
    ],
    "sg:phone":"+1 804 740 8060",
    "sg:postcode":"23220",
    "sg:province":"VA",
    "wof:name":"Winthrop Southeast Ltd Partn",
    "wof:placetype":"venue"
},
  "geometry": {"coordinates":[-77.445386,37.54635],"type":"Point"}
}