{
  "type": "Feature",
  "properties": {
    "addr:full":"1341 N Amherst Hwy Amherst VA 24521",
    "addr:housenumber":"1341",
    "addr:postcode":"24521",
    "addr:street":"N Amherst Hwy",
    "iso:country":"US",
    "sg:address":"1341 N Amherst Hwy",
    "sg:city":"Amherst",
    "sg:classifiers":[
        {
            "category":"Building & Trades",
            "subcategory":"Construction",
            "type":"Services"
        }
    ],
    "sg:phone":"+1 434 946 2695",
    "sg:postcode":"24521",
    "sg:province":"VA",
    "sg:tags":[
        "paving",
        "contractor"
    ],
    "wof:name":"Brockman Asphalt Paving Inc",
    "wof:placetype":"venue"
},
  "geometry": {"coordinates":[-79.015539,37.617598],"type":"Point"}
}