{
  "type": "Feature",
  "properties": {
    "addr:full":"3108 Dashiell Rd Falls Church VA 22042",
    "addr:housenumber":"3108",
    "addr:postcode":"22042",
    "addr:street":"Dashiell Rd",
    "iso:country":"US",
    "sg:address":"3108 Dashiell Rd",
    "sg:city":"Falls Church",
    "sg:classifiers":[
        {
            "category":"Organizations",
            "subcategory":"Membership Organization",
            "type":"Services"
        }
    ],
    "sg:phone":"+1 703 533 3668",
    "sg:postcode":"22042",
    "sg:province":"VA",
    "wof:name":"Puns Corps",
    "wof:placetype":"venue"
},
  "geometry": {"coordinates":[-77.17421,38.864759],"type":"Point"}
}