{
  "type": "Feature",
  "properties": {
    "addr:full":"4660 Kenmore Ave Ste 1100 Alexandria VA 22304",
    "addr:housenumber":"4660",
    "addr:postcode":"22304",
    "addr:street":"Kenmore Ave Ste 1100",
    "iso:country":"US",
    "sg:address":"4660 Kenmore Ave Ste 1100",
    "sg:city":"Alexandria",
    "sg:classifiers":[
        {
            "category":"Health Services",
            "subcategory":"Doctor",
            "type":"Services"
        }
    ],
    "sg:phone":"+1 703 370 0400",
    "sg:postcode":"22304",
    "sg:province":"VA",
    "wof:name":"Rothman Grapin & McKnight PC",
    "wof:placetype":"venue"
},
  "geometry": {"coordinates":[-77.110298,38.829601],"type":"Point"}
}