{
  "type": "Feature",
  "properties": {
    "iso:country":"US",
    "sg:address":"8387 Leesburg Pike",
    "sg:city":"Vienna",
    "sg:classifiers":[
        {
            "category":"Home & Garden",
            "subcategory":"Home Furnishings",
            "type":"Retail Goods"
        },
        {
            "category":"Home & Garden",
            "subcategory":"Carpets & Floor Coverings",
            "type":"Retail Goods"
        }
    ],
    "sg:phone":"+1 703 288 3699",
    "sg:postcode":"22182",
    "sg:province":"VA",
    "sg:tags":[
        "set",
        "bedroom",
        "bed",
        "mattress"
    ],
    "wof:name":"Rockaway Bedding",
    "wof:placetype":"venue"
},
  "geometry": {"coordinates":[-77.23541299999999,38.922199],"type":"Point"}
}