{
  "type": "Feature",
  "properties": {
    "iso:country":"US",
    "sg:address":"48 W Queens Way",
    "sg:city":"Hampton",
    "sg:classifiers":[
        {
            "category":"Professional",
            "subcategory":"Detective & Security Services",
            "type":"Services"
        }
    ],
    "sg:phone":"+1 757 722 7411",
    "sg:postcode":"23669",
    "sg:province":"VA",
    "wof:name":"New Technology Management",
    "wof:placetype":"venue"
},
  "geometry": {"coordinates":[-76.346114,37.025686],"type":"Point"}
}