{
  "type": "Feature",
  "properties": {
    "addr:full":"10094 Nightingale Ln Midland VA 22728",
    "addr:housenumber":"10094",
    "addr:postcode":"22728",
    "addr:street":"Nightingale Ln",
    "iso:country":"US",
    "sg:address":"10094 Nightingale Ln",
    "sg:city":"Midland",
    "sg:classifiers":[
        {
            "category":"Building & Trades",
            "subcategory":"Construction",
            "type":"Services"
        }
    ],
    "sg:phone":"+1 540 439 0736",
    "sg:postcode":"22728",
    "sg:province":"VA",
    "sg:tags":[
        "excavation",
        "work"
    ],
    "wof:name":"Deal Excavating",
    "wof:placetype":"venue"
},
  "geometry": {"coordinates":[-77.777799,38.619012],"type":"Point"}
}