{
  "type": "Feature",
  "properties": {
    "addr:full":"1800 Town Center Pkwy Reston VA 20190",
    "addr:housenumber":"1800",
    "addr:postcode":"20190",
    "addr:street":"Town Center Pkwy",
    "iso:country":"US",
    "sg:address":"1800 Town Center Pkwy",
    "sg:city":"Reston",
    "sg:classifiers":[
        {
            "category":"Shopping",
            "type":"Retail Goods"
        }
    ],
    "sg:phone":"+1 703 478 9898",
    "sg:postcode":"20190",
    "sg:province":"VA",
    "sg:tags":[
        "merchandise"
    ],
    "wof:name":"Professional Hearing Aid Svc",
    "wof:placetype":"venue"
},
  "geometry": {"coordinates":[-77.36109399999999,38.963881],"type":"Point"}
}