{
  "type": "Feature",
  "properties": {
    "addr:full":"7923 Poor Mountain Rd Bent Mountain VA 24059",
    "addr:housenumber":"7923",
    "addr:postcode":"24059",
    "addr:street":"Poor Mountain Rd;Mountain",
    "iso:country":"US",
    "sg:address":"7923 Poor Mountain Rd",
    "sg:city":"Bent Mountain",
    "sg:classifiers":[
        {
            "category":"Professional",
            "subcategory":"Engineering",
            "type":"Services"
        }
    ],
    "sg:phone":"+1 540 330 7249",
    "sg:postcode":"24059",
    "sg:province":"VA",
    "sg:tags":[
        "civil",
        "consulting"
    ],
    "wof:name":"Wallace Group Inc",
    "wof:placetype":"venue"
},
  "geometry": {"coordinates":[-80.13873599999999,37.187253],"type":"Point"}
}