{
  "type": "Feature",
  "properties": {
    "iso:country":"US",
    "sg:address":"1244 Executive Blvd",
    "sg:city":"Chesapeake",
    "sg:classifiers":[
        {
            "category":"Utilities",
            "subcategory":"Mobile Phone",
            "type":"Services"
        }
    ],
    "sg:phone":"+1 757 312 9000",
    "sg:postcode":"23320",
    "sg:province":"VA",
    "sg:tags":[
        "communications",
        "radiotelephone"
    ],
    "wof:name":"Atlantic Wireless Inc",
    "wof:placetype":"venue"
},
  "geometry": {"coordinates":[-76.23415,36.765019],"type":"Point"}
}