{
  "type": "Feature",
  "properties": {
    "addr:full":"14600 Stage Rd Lanexa VA 23089",
    "addr:housenumber":"14600",
    "addr:postcode":"23089",
    "addr:street":"Stage Rd",
    "iso:country":"US",
    "sg:address":"14600 Stage Rd",
    "sg:city":"Lanexa",
    "sg:classifiers":[
        {
            "category":"Professional",
            "subcategory":"Business Services",
            "type":"Services"
        },
        {
            "category":"Building & Trades",
            "subcategory":"Construction",
            "type":"Services"
        }
    ],
    "sg:phone":"+1 804 966 2829",
    "sg:postcode":"23089",
    "sg:province":"VA",
    "sg:tags":[
        "general",
        "contractor"
    ],
    "wof:name":"Charles E Moss Co Inc",
    "wof:placetype":"venue"
},
  "geometry": {"coordinates":[-76.91131300000001,37.485861],"type":"Point"}
}