{
  "type": "Feature",
  "properties": {
    "iso:country":"US",
    "sg:address":"7391 John Marshall Hwy",
    "sg:city":"Marshall",
    "sg:classifiers":[
        {
            "category":"Shopping",
            "subcategory":"Used Merchandise",
            "type":"Retail Goods"
        }
    ],
    "sg:phone":"+1 540 364 0084",
    "sg:postcode":"20115",
    "sg:province":"VA",
    "wof:name":"Euro Trading Post Inc",
    "wof:placetype":"venue"
},
  "geometry": {"coordinates":[-77.81851899999999,38.866551],"type":"Point"}
}