{
  "type": "Feature",
  "properties": {
    "addr:full":"3607 Deerberry Ct Fairfax VA 22033",
    "addr:housenumber":"3607",
    "addr:postcode":"22033",
    "addr:street":"Deerberry Ct",
    "iso:country":"US",
    "sg:address":"3607 Deerberry Ct",
    "sg:city":"Fairfax",
    "sg:classifiers":[
        {
            "category":"Travel",
            "subcategory":"Travel Agent",
            "type":"Entertainment"
        }
    ],
    "sg:phone":"+1 703 263 1998",
    "sg:postcode":"22033",
    "sg:province":"VA",
    "sg:tags":[
        "agency",
        "services-commercial"
    ],
    "wof:name":"Connor, Mary",
    "wof:placetype":"venue"
},
  "geometry": {"coordinates":[-77.410937,38.900565],"type":"Point"}
}