{
  "type": "Feature",
  "properties": {
    "addr:full":"3532 Jefferson Landing Rd Powhatan VA 23139",
    "addr:housenumber":"3532",
    "addr:postcode":"23139",
    "addr:street":"Jefferson Landing Rd",
    "iso:country":"US",
    "sg:address":"3532 Jefferson Landing Rd",
    "sg:city":"Powhatan",
    "sg:classifiers":[
        {
            "category":"Personal",
            "type":"Services"
        }
    ],
    "sg:phone":"+1 804 598 6639",
    "sg:postcode":"23139",
    "sg:province":"VA",
    "sg:tags":[
        "group"
    ],
    "wof:name":"Uncle Curt & Hugs",
    "wof:placetype":"venue"
},
  "geometry": {"coordinates":[-77.91547799999999,37.617316],"type":"Point"}
}