{
  "type": "Feature",
  "properties": {
    "iso:country":"US",
    "sg:address":"201 12th St S",
    "sg:city":"Arlington",
    "sg:classifiers":[
        {
            "category":"Government",
            "subcategory":"Office",
            "type":"Public Place"
        }
    ],
    "sg:phone":"+1 703 602 3301",
    "sg:postcode":"22202",
    "sg:province":"VA",
    "sg:tags":[
        "general"
    ],
    "wof:name":"Ccdr Project Office Osd P",
    "wof:placetype":"venue"
},
  "geometry": {"coordinates":[-77.048734,38.862331],"type":"Point"}
}