{
  "type": "Feature",
  "properties": {
    "iso:country":"US",
    "sg:address":"6969 Hechinger Dr",
    "sg:city":"Springfield",
    "sg:classifiers":[
        {
            "category":"Coffee & Tea",
            "type":"Food & Drink"
        },
        {
            "category":"Restaurant",
            "type":"Food & Drink"
        },
        {
            "category":"Bakery",
            "type":"Food & Drink"
        }
    ],
    "sg:phone":"+1 703 914 1109",
    "sg:postcode":"22151",
    "sg:province":"VA",
    "sg:tags":[
        "shop",
        "espresso"
    ],
    "wof:name":"New Ben Tre Bakery And Deli Inc",
    "wof:placetype":"venue"
},
  "geometry": {"coordinates":[-77.18295999999999,38.795514],"type":"Point"}
}