{
  "type": "Feature",
  "properties": {
    "addr:full":"2986 Kings Hwy Colonial Beach VA 22443",
    "addr:housenumber":"2986",
    "addr:postcode":"beach;22443",
    "addr:street":"Kings Hwy Colonial",
    "iso:country":"US",
    "sg:address":"2986 Kings Hwy",
    "sg:city":"Colonial Beach",
    "sg:classifiers":[
        {
            "category":"Retail",
            "subcategory":"Laundry & Dry Cleaning",
            "type":"Services"
        }
    ],
    "sg:phone":"+1 804 224 0691",
    "sg:postcode":"22443",
    "sg:province":"VA",
    "sg:tags":[
        "drycleaning",
        "plant",
        "cleaners"
    ],
    "wof:name":"Hilltop Cleaners",
    "wof:placetype":"venue"
},
  "geometry": {"coordinates":[-76.996331,38.181309],"type":"Point"}
}