{
  "type": "Feature",
  "properties": {
    "addr:full":"9001 Mulvaney Ct Springfield VA 22152",
    "addr:housenumber":"9001",
    "addr:postcode":"22152",
    "addr:street":"Mulvaney Ct",
    "iso:country":"US",
    "sg:address":"9001 Mulvaney Ct",
    "sg:city":"Springfield",
    "sg:classifiers":[
        {
            "category":"Professional",
            "subcategory":"Business Services",
            "type":"Services"
        }
    ],
    "sg:phone":"+1 703 644 1647",
    "sg:postcode":"22152",
    "sg:province":"VA",
    "sg:tags":[
        "labeling"
    ],
    "wof:name":"Euro Pack Movers",
    "wof:placetype":"venue"
},
  "geometry": {"coordinates":[-77.255371,38.779751],"type":"Point"}
}