{
  "type": "Feature",
  "properties": {
    "addr:full":"1036 Volvo Pkwy Chesapeake VA 23320",
    "addr:housenumber":"1036",
    "addr:postcode":"23320",
    "addr:street":"Volvo Pkwy",
    "iso:country":"US",
    "sg:address":"1036 Volvo Pkwy",
    "sg:city":"Chesapeake",
    "sg:classifiers":[
        {
            "category":"Personal",
            "subcategory":"Beauty Salon",
            "type":"Services"
        }
    ],
    "sg:phone":"+1 757 436 6463",
    "sg:postcode":"23320",
    "sg:province":"VA",
    "sg:tags":[
        "shop"
    ],
    "sg:website":"www.mylesphillipdayspa.com",
    "wof:name":"Myles Phillip Group",
    "wof:placetype":"venue"
},
  "geometry": {"coordinates":[-76.22606500000001,36.769418],"type":"Point"}
}