{
  "type": "Feature",
  "properties": {
    "iso:country":"US",
    "sg:address":"3571 Kidder Ln",
    "sg:city":"Salem",
    "sg:classifiers":[
        {
            "category":"Shopping",
            "type":"Retail Goods"
        }
    ],
    "sg:phone":"+1 540 384 6454",
    "sg:postcode":"24153",
    "sg:province":"VA",
    "sg:tags":[
        "merchandise"
    ],
    "wof:name":"Silver Buckle Detection",
    "wof:placetype":"venue"
},
  "geometry": {"coordinates":[-80.06373499999999,37.367015],"type":"Point"}
}