{
  "type": "Feature",
  "properties": {
    "iso:country":"US",
    "sg:address":"8104 Kenova Ln",
    "sg:city":"Springfield",
    "sg:classifiers":[
        {
            "category":"Professional",
            "subcategory":"Engineering",
            "type":"Services"
        }
    ],
    "sg:phone":"+1 703 912 9284",
    "sg:postcode":"22153",
    "sg:province":"VA",
    "sg:tags":[
        "engineer"
    ],
    "wof:name":"Getting It Straight",
    "wof:placetype":"venue"
},
  "geometry": {"coordinates":[-77.217206,38.738766],"type":"Point"}
}