{
  "type": "Feature",
  "properties": {
    "addr:full":"140 Leonard Ct Harrisonburg VA 22801",
    "addr:housenumber":"140",
    "addr:postcode":"22801",
    "addr:street":"Leonard Ct",
    "iso:country":"US",
    "sg:address":"140 Leonard Ct",
    "sg:city":"Harrisonburg",
    "sg:classifiers":[
        {
            "category":"Building & Trades",
            "subcategory":"Construction",
            "type":"Services"
        }
    ],
    "sg:phone":"+1 540 433 7682",
    "sg:postcode":"22801",
    "sg:province":"VA",
    "sg:tags":[
        "house"
    ],
    "wof:name":"Jpo Construction Inc",
    "wof:placetype":"venue"
},
  "geometry": {"coordinates":[-78.902868,38.453994],"type":"Point"}
}