{
  "type": "Feature",
  "properties": {
    "addr:full":"302 Cedar Pt Galax VA 24333",
    "addr:housenumber":"302",
    "addr:postcode":"24333",
    "addr:street":"Cedar Pt",
    "iso:country":"US",
    "sg:address":"302 Cedar Pt",
    "sg:city":"Galax",
    "sg:classifiers":[
        {
            "category":"Building & Trades",
            "subcategory":"Construction",
            "type":"Services"
        }
    ],
    "sg:phone":"+1 276 238 4682",
    "sg:postcode":"24333",
    "sg:province":"VA",
    "sg:tags":[
        "steel",
        "erection",
        "structural"
    ],
    "wof:name":"Eastern Steel Inc",
    "wof:placetype":"venue"
},
  "geometry": {"coordinates":[-80.865405,36.681006],"type":"Point"}
}