{
  "type": "Feature",
  "properties": {
    "iso:country":"US",
    "sg:address":"1430 Spring Hill Rd Ste 401",
    "sg:city":"Mc Lean",
    "sg:classifiers":[
        {
            "category":"Education",
            "subcategory":"University",
            "type":"Public Place"
        }
    ],
    "sg:phone":"+1 703 556 4411",
    "sg:postcode":"22102",
    "sg:province":"VA",
    "sg:tags":[
        "college"
    ],
    "wof:name":"Rockwell University",
    "wof:placetype":"venue"
},
  "geometry": {"coordinates":[-77.234466,38.932357],"type":"Point"}
}