{
  "type": "Feature",
  "properties": {
    "addr:full":"545 2nd St Christiansburg VA 24073",
    "addr:housenumber":"545",
    "addr:postcode":"24073",
    "addr:street":"2Nd St",
    "iso:country":"US",
    "sg:address":"545 2nd St",
    "sg:city":"Christiansburg",
    "sg:classifiers":[
        {
            "category":"Real Estate",
            "subcategory":"Real Estate Operator",
            "type":"Services"
        }
    ],
    "sg:phone":"+1 540 382 3172",
    "sg:postcode":"24073",
    "sg:province":"VA",
    "sg:tags":[
        "property",
        "lessor"
    ],
    "wof:name":"Highway Contractors Inc",
    "wof:placetype":"venue"
},
  "geometry": {"coordinates":[-80.412218,37.123368],"type":"Point"}
}