{
  "type": "Feature",
  "properties": {
    "addr:full":"4323 Gingham Ct Alexandria VA 22310",
    "addr:housenumber":"4323",
    "addr:postcode":"22310",
    "addr:street":"Gingham Ct",
    "iso:country":"US",
    "sg:address":"4323 Gingham Ct",
    "sg:city":"Alexandria",
    "sg:classifiers":[
        {
            "category":"Professional",
            "subcategory":"Engineering",
            "type":"Services"
        }
    ],
    "sg:phone":"+1 703 567 2322",
    "sg:postcode":"22310",
    "sg:province":"VA",
    "sg:tags":[
        "building",
        "consulting",
        "tool",
        "statistical",
        "measurement"
    ],
    "wof:name":"Tarl Kudrick PHD",
    "wof:placetype":"venue"
},
  "geometry": {"coordinates":[-77.10625400000001,38.791932],"type":"Point"}
}