{
  "type": "Feature",
  "properties": {
    "addr:full":"2810 Ackley Ave Richmond VA 23228",
    "addr:housenumber":"2810",
    "addr:postcode":"23228",
    "addr:street":"Ackley Ave",
    "iso:country":"US",
    "sg:address":"2810 Ackley Ave",
    "sg:city":"Richmond",
    "sg:classifiers":[
        {
            "category":"Wholesale",
            "subcategory":"Machinery & Supplies",
            "type":"Manufacturing & Wholesale Goods"
        }
    ],
    "sg:phone":"+1 804 266 7980",
    "sg:postcode":"23228",
    "sg:province":"VA",
    "sg:tags":[
        "equipment",
        "laundry"
    ],
    "wof:name":"Laundry & Dry Cleaning Eqp Co",
    "wof:placetype":"venue"
},
  "geometry": {"coordinates":[-77.499578,37.637401],"type":"Point"}
}