{
  "type": "Feature",
  "properties": {
    "addr:full":"3020 Lincoln Ave Henrico VA 23228",
    "addr:housenumber":"3020",
    "addr:postcode":"23228",
    "addr:street":"Lincoln Ave",
    "iso:country":"US",
    "sg:address":"3020 Lincoln Ave",
    "sg:city":"Henrico",
    "sg:classifiers":[
        {
            "category":"Autos & Motor Vehicles",
            "subcategory":"Recreational Vehicle Sales",
            "type":"Retail Goods"
        }
    ],
    "sg:phone":"+1 804 264 5992",
    "sg:postcode":"23228",
    "sg:province":"VA",
    "sg:tags":[
        "repairing",
        "automobile",
        "facilities-renting"
    ],
    "wof:name":"Pbm",
    "wof:placetype":"venue"
},
  "geometry": {"coordinates":[-77.492876,37.614494],"type":"Point"}
}