{
  "type": "Feature",
  "properties": {
    "addr:full":"13235 Occoquan Rd Woodbridge VA 22191",
    "addr:housenumber":"13235",
    "addr:postcode":"22191",
    "addr:street":"Occoquan Rd",
    "iso:country":"US",
    "sg:address":"13235 Occoquan Rd",
    "sg:city":"Woodbridge",
    "sg:classifiers":[
        {
            "category":"Personal",
            "subcategory":"Barber",
            "type":"Services"
        }
    ],
    "sg:phone":"+1 703 497 5658",
    "sg:postcode":"22191",
    "sg:province":"VA",
    "sg:tags":[
        "shop"
    ],
    "wof:name":"Clippers Barber Shop",
    "wof:placetype":"venue"
},
  "geometry": {"coordinates":[-77.255062,38.665088],"type":"Point"}
}