{
  "type": "Feature",
  "properties": {
    "iso:country":"US",
    "sg:address":"111 Franklin St",
    "sg:city":"Alexandria",
    "sg:classifiers":[
        {
            "category":"Wholesale",
            "subcategory":"Machinery & Supplies",
            "type":"Manufacturing & Wholesale Goods"
        }
    ],
    "sg:phone":"+1 703 838 7677",
    "sg:postcode":"22314",
    "sg:province":"VA",
    "sg:tags":[
        "equipment",
        "industrial"
    ],
    "wof:name":"Secucontrol Inc",
    "wof:placetype":"venue"
},
  "geometry": {"coordinates":[-77.04292,38.797564],"type":"Point"}
}