{
  "type": "Feature",
  "properties": {
    "addr:full":"13022 Windsor Blvd Windsor VA 23487",
    "addr:housenumber":"13022",
    "addr:postcode":"23487",
    "addr:street":"Windsor Blvd",
    "iso:country":"US",
    "sg:address":"13022 Windsor Blvd",
    "sg:city":"Windsor",
    "sg:classifiers":[
        {
            "category":"Shopping",
            "subcategory":"Gifts & Souvenirs",
            "type":"Retail Goods"
        }
    ],
    "sg:phone":"+1 757 242 0327",
    "sg:postcode":"23487",
    "sg:province":"VA",
    "wof:name":"Cabintowne Cntry Str & Gift Sp",
    "wof:placetype":"venue"
},
  "geometry": {"coordinates":[-76.70522099999999,36.799321],"type":"Point"}
}