{
  "type": "Feature",
  "properties": {
    "addr:full":"4421 Virginia Beach Blvd Virginia Beach VA 23462",
    "addr:housenumber":"4421",
    "addr:postcode":"23462",
    "addr:street":"Virginia Beach Blvd",
    "iso:country":"US",
    "sg:address":"4421 Virginia Beach Blvd",
    "sg:city":"Virginia Beach",
    "sg:classifiers":[
        {
            "category":"Shopping",
            "type":"Retail Goods"
        }
    ],
    "sg:phone":"+1 757 497 1279",
    "sg:postcode":"23462",
    "sg:province":"VA",
    "sg:tags":[
        "pet",
        "shop"
    ],
    "wof:name":"Petsmart",
    "wof:placetype":"venue"
},
  "geometry": {"coordinates":[-76.12748999999999,36.843249],"type":"Point"}
}