{
  "type": "Feature",
  "properties": {
    "iso:country":"US",
    "sg:address":"1415 N Van Dorn St",
    "sg:city":"Alexandria",
    "sg:classifiers":[
        {
            "category":"Professional",
            "subcategory":"Detective & Security Services",
            "type":"Services"
        }
    ],
    "sg:phone":"+1 703 855 8454",
    "sg:postcode":"22304",
    "sg:province":"VA",
    "sg:tags":[
        "car",
        "armored"
    ],
    "wof:name":"US Fugitive Retrieval Agency",
    "wof:placetype":"venue"
},
  "geometry": {"coordinates":[-77.118657,38.826681],"type":"Point"}
}