{
  "type": "Feature",
  "properties": {
    "addr:full":"106 Leftwich Hollow Rd Cana VA 24317",
    "addr:housenumber":"106",
    "addr:postcode":"24317",
    "addr:street":"Leftwich Hollow Rd",
    "iso:country":"US",
    "sg:address":"106 Leftwich Hollow Rd",
    "sg:city":"Cana",
    "sg:classifiers":[
        {
            "category":"Professional",
            "type":"Services"
        }
    ],
    "sg:phone":"+1 276 755 2541",
    "sg:postcode":"24317",
    "sg:province":"VA",
    "wof:name":"Life of Victory Word Fell",
    "wof:placetype":"venue"
},
  "geometry": {"coordinates":[-80.698036,36.61069],"type":"Point"}
}