{
  "type": "Feature",
  "properties": {
    "iso:country":"US",
    "sg:address":"112 N 5th St",
    "sg:city":"Richmond",
    "sg:classifiers":[
        {
            "category":"Organizations",
            "subcategory":"Community Association",
            "type":"Services"
        }
    ],
    "sg:phone":"+1 804 644 3999",
    "sg:postcode":"23219",
    "sg:province":"VA",
    "sg:tags":[
        "club"
    ],
    "wof:name":"Cotton Club",
    "wof:placetype":"venue"
},
  "geometry": {"coordinates":[-77.43841,37.54202],"type":"Point"}
}