{
  "type": "Feature",
  "properties": {
    "iso:country":"US",
    "sg:address":"1820 Dealton Ave",
    "sg:city":"Harrisonburg",
    "sg:classifiers":[
        {
            "category":"Freight",
            "type":"Transportation"
        }
    ],
    "sg:phone":"+1 540 434 6765",
    "sg:postcode":"22801",
    "sg:province":"VA",
    "sg:tags":[
        "yard",
        "stock"
    ],
    "wof:name":"Rockingham Livestock Sales Inc",
    "wof:placetype":"venue"
},
  "geometry": {"coordinates":[-78.88683899999999,38.425507],"type":"Point"}
}