{
  "type": "Feature",
  "properties": {
    "iso:country":"US",
    "sg:address":"1448 Duke St",
    "sg:city":"Alexandria",
    "sg:classifiers":[
        {
            "category":"Recreation",
            "subcategory":"Picnic Area",
            "type":"Entertainment"
        }
    ],
    "sg:phone":"+1 703 836 4800",
    "sg:postcode":"22314",
    "sg:province":"VA",
    "sg:tags":[
        "place",
        "arcade",
        "amusement"
    ],
    "sg:website":"http://www.iaapa.org",
    "wof:name":"International Association Of Amusement Parks & Attractions Inc",
    "wof:placetype":"venue"
},
  "geometry": {"coordinates":[-77.057243,38.80402],"type":"Point"}
}