{
  "type": "Feature",
  "properties": {
    "iso:country":"US",
    "sg:address":"545 E Stuart Dr",
    "sg:city":"Galax",
    "sg:classifiers":[
        {
            "category":"Sports & Exercise",
            "subcategory":"Bowling",
            "type":"Entertainment"
        }
    ],
    "sg:phone":"+1 276 236 2695",
    "sg:postcode":"24333",
    "sg:province":"VA",
    "sg:tags":[
        "center"
    ],
    "wof:name":"Blue Ridge Lanes",
    "wof:placetype":"venue"
},
  "geometry": {"coordinates":[-80.913286,36.672635],"type":"Point"}
}