{
  "type": "Feature",
  "properties": {
    "iso:country":"US",
    "sg:address":"8221 Old Courthouse Rd Ste 101",
    "sg:city":"Vienna",
    "sg:classifiers":[
        {
            "category":"Professional",
            "subcategory":"Lawyer & Legal Services",
            "type":"Services"
        }
    ],
    "sg:phone":"+1 703 883 8035",
    "sg:postcode":"22182",
    "sg:province":"VA",
    "sg:tags":[
        "divorce",
        "attorney",
        "law",
        "family"
    ],
    "wof:name":"Latusek , Elizabeth A. - Maddox, Cole &",
    "wof:placetype":"venue"
},
  "geometry": {"coordinates":[-77.229218,38.912689],"type":"Point"}
}