{
  "type": "Feature",
  "properties": {
    "addr:full":"12616 Kahns Rd Manassas VA 20112",
    "addr:housenumber":"12616",
    "addr:postcode":"20112",
    "addr:street":"Kahns Rd",
    "iso:country":"US",
    "sg:address":"12616 Kahns Rd",
    "sg:city":"Manassas",
    "sg:classifiers":[
        {
            "category":"Manufacturing",
            "subcategory":"Printing",
            "type":"Manufacturing & Wholesale Goods"
        }
    ],
    "sg:phone":"+1 703 791 5039",
    "sg:postcode":"20112",
    "sg:province":"VA",
    "sg:tags":[
        "miscellaneous",
        "publishing"
    ],
    "wof:name":"Smith Publications",
    "wof:placetype":"venue"
},
  "geometry": {"coordinates":[-77.420731,38.686215],"type":"Point"}
}