{
  "type": "Feature",
  "properties": {
    "iso:country":"US",
    "sg:address":"318 Mantua Rd",
    "sg:city":"Heathsville",
    "sg:classifiers":[
        {
            "category":"Retail",
            "subcategory":"Animal Services",
            "type":"Services"
        }
    ],
    "sg:phone":"+1 804 580 5227",
    "sg:postcode":"22473",
    "sg:province":"VA",
    "wof:name":"Lorien Kennels",
    "wof:placetype":"venue"
},
  "geometry": {"coordinates":[-76.463995,37.954015],"type":"Point"}
}