{
  "type": "Feature",
  "properties": {
    "iso:country":"US",
    "sg:address":"11 Acacia Ln",
    "sg:city":"Sterling",
    "sg:classifiers":[
        {
            "category":"Manufacturing",
            "subcategory":"Chemicals & Compounds",
            "type":"Manufacturing & Wholesale Goods"
        }
    ],
    "sg:phone":"+1 703 654 0385",
    "sg:postcode":"20166",
    "sg:province":"VA",
    "sg:tags":[
        "electronic",
        "deodorizers",
        "mfg"
    ],
    "wof:name":"Rainbowair Activators",
    "wof:placetype":"venue"
},
  "geometry": {"coordinates":[-77.446815,38.995554],"type":"Point"}
}