{
  "type": "Feature",
  "properties": {
    "iso:country":"US",
    "sg:address":"2008 Dove View Dr",
    "sg:city":"Virginia Beach",
    "sg:classifiers":[
        {
            "category":"Manufacturing",
            "subcategory":"Tools & Machinery",
            "type":"Manufacturing & Wholesale Goods"
        }
    ],
    "sg:phone":"+1 757 474 2451",
    "sg:postcode":"23464",
    "sg:province":"VA",
    "sg:tags":[
        "industry",
        "mfg"
    ],
    "wof:name":"Pure Living Enterprises",
    "wof:placetype":"venue"
},
  "geometry": {"coordinates":[-76.144642,36.777961],"type":"Point"}
}