{
  "type": "Feature",
  "properties": {
    "iso:country":"US",
    "sg:address":"107 N Kent St",
    "sg:city":"Winchester",
    "sg:classifiers":[
        {
            "category":"Organizations",
            "subcategory":"Community Association",
            "type":"Services"
        }
    ],
    "sg:phone":"+1 540 722 3480",
    "sg:postcode":"22601",
    "sg:province":"VA",
    "sg:tags":[
        "executive"
    ],
    "wof:name":"Fredrick Wnchester Envmtl Hlth",
    "wof:placetype":"venue"
},
  "geometry": {"coordinates":[-78.16225799999999,39.184734],"type":"Point"}
}