{
  "type": "Feature",
  "properties": {
    "addr:full":"810 Catoctin Cir NE Leesburg VA 20176",
    "addr:housenumber":"810",
    "addr:postcode":"20176",
    "addr:street":"Catoctin Cir Ne",
    "iso:country":"US",
    "sg:address":"810 Catoctin Cir NE",
    "sg:city":"Leesburg",
    "sg:classifiers":[
        {
            "category":"Banks & Credit Unions",
            "subcategory":"Investment Brokerage",
            "type":"Services"
        }
    ],
    "sg:phone":"+1 703 727 2147",
    "sg:postcode":"20176",
    "sg:province":"VA",
    "sg:tags":[
        "stock",
        "bond"
    ],
    "wof:name":"Raymond James Financial Svc",
    "wof:placetype":"venue"
},
  "geometry": {"coordinates":[-77.547208,39.129445],"type":"Point"}
}