{
  "type": "Feature",
  "properties": {
    "addr:full":"110 E Main St Salem VA 24153",
    "addr:housenumber":"110",
    "addr:postcode":"24153",
    "addr:street":"E Main St",
    "iso:country":"US",
    "sg:address":"110 E Main St",
    "sg:city":"Salem",
    "sg:classifiers":[
        {
            "category":"Banks & Credit Unions",
            "subcategory":"Bank",
            "type":"Services"
        }
    ],
    "sg:phone":"+1 540 378 1500",
    "sg:postcode":"24153",
    "sg:province":"VA",
    "sg:tags":[
        "national",
        "commercial"
    ],
    "wof:name":"Salem Bank & Trust N A",
    "wof:placetype":"venue"
},
  "geometry": {"coordinates":[-80.05599599999999,37.293055],"type":"Point"}
}