{
  "type": "Feature",
  "properties": {
    "addr:full":"293 Corporate Blvd Norfolk VA 23502",
    "addr:housenumber":"293",
    "addr:postcode":"23502",
    "addr:street":"Corporate Blvd",
    "iso:country":"US",
    "sg:address":"293 Corporate Blvd",
    "sg:city":"Norfolk",
    "sg:classifiers":[
        {
            "category":"Real Estate",
            "subcategory":"Real Estate Operator",
            "type":"Services"
        }
    ],
    "sg:phone":"+1 757 461 4080",
    "sg:postcode":"23502",
    "sg:province":"VA",
    "sg:tags":[
        "apartment"
    ],
    "wof:name":"Shorewood Cove Apartments",
    "wof:placetype":"venue"
},
  "geometry": {"coordinates":[-76.21298400000001,36.837112],"type":"Point"}
}