{
  "type": "Feature",
  "properties": {
    "addr:full":"13337 Worth Ave Woodbridge VA 22192",
    "addr:housenumber":"13337",
    "addr:postcode":"22192",
    "addr:street":"Worth Ave",
    "iso:country":"US",
    "sg:address":"13337 Worth Ave",
    "sg:city":"Woodbridge",
    "sg:classifiers":[
        {
            "category":"Retail",
            "subcategory":"Veterinary Services",
            "type":"Services"
        }
    ],
    "sg:phone":"+1 703 490 6451",
    "sg:postcode":"22192",
    "sg:province":"VA",
    "sg:tags":[
        "veterinarian"
    ],
    "wof:name":"Vetsmart Wellness Center",
    "wof:placetype":"venue"
},
  "geometry": {"coordinates":[-77.294954,38.648938],"type":"Point"}
}