{
  "type": "Feature",
  "properties": {
    "addr:full":"43039 Lake Ridge Pl Leesburg VA 20176",
    "addr:housenumber":"43039",
    "addr:postcode":"20176",
    "addr:street":"Lake Ridge Pl",
    "iso:country":"US",
    "sg:address":"43039 Lake Ridge Pl",
    "sg:city":"Leesburg",
    "sg:classifiers":[
        {
            "category":"Professional",
            "type":"Services"
        }
    ],
    "sg:phone":"+1 703 669 5211",
    "sg:postcode":"20176",
    "sg:province":"VA",
    "sg:tags":[
        "establishment"
    ],
    "wof:name":"Noble",
    "wof:placetype":"venue"
},
  "geometry": {"coordinates":[-77.51156400000001,39.111864],"type":"Point"}
}