{
  "type": "Feature",
  "properties": {
    "addr:full":"800 Park Ave NE Norton VA 24273",
    "addr:housenumber":"800",
    "addr:postcode":"24273",
    "addr:street":"Park Ave Ne",
    "iso:country":"US",
    "sg:address":"800 Park Ave NE",
    "sg:city":"Norton",
    "sg:classifiers":[
        {
            "category":"Food & Beverages",
            "subcategory":"Groceries & Convenience Stores",
            "type":"Retail Goods"
        }
    ],
    "sg:phone":"+1 276 679 2237",
    "sg:postcode":"24273",
    "sg:province":"VA",
    "wof:name":"Double KWIK Markets",
    "wof:placetype":"venue"
},
  "geometry": {"coordinates":[-82.61584499999999,36.94941],"type":"Point"}
}