{
  "type": "Feature",
  "properties": {
    "iso:country":"US",
    "sg:address":"1101 Caroline St",
    "sg:city":"Fredericksburg",
    "sg:classifiers":[
        {
            "category":"Health Services",
            "subcategory":"Health Practitioner",
            "type":"Services"
        }
    ],
    "sg:phone":"+1 540 373 7011",
    "sg:postcode":"22401",
    "sg:province":"VA",
    "wof:name":"Mark Torgeson Ms T",
    "wof:placetype":"venue"
},
  "geometry": {"coordinates":[-77.460871,38.305686],"type":"Point"}
}