{
  "type": "Feature",
  "properties": {
    "iso:country":"US",
    "sg:address":"418 E Washington St",
    "sg:city":"Suffolk",
    "sg:classifiers":[
        {
            "category":"Manufacturing",
            "subcategory":"Metals",
            "type":"Manufacturing & Wholesale Goods"
        }
    ],
    "sg:phone":"+1 757 539 2353",
    "sg:postcode":"23434",
    "sg:province":"VA",
    "sg:tags":[
        "steel"
    ],
    "wof:name":"Suffolk Iron Works Inc",
    "wof:placetype":"venue"
},
  "geometry": {"coordinates":[-76.576626,36.726252],"type":"Point"}
}