{
  "type": "Feature",
  "properties": {
    "addr:full":"2505 N Key Blvd Arlington VA 22201",
    "addr:housenumber":"2505",
    "addr:postcode":"22201",
    "addr:street":"N Key Blvd",
    "iso:country":"US",
    "sg:address":"2505 N Key Blvd",
    "sg:city":"Arlington",
    "sg:classifiers":[
        {
            "category":"Social Services",
            "type":"Services"
        }
    ],
    "sg:phone":"+1 703 525 1515",
    "sg:postcode":"22201",
    "sg:province":"VA",
    "wof:name":"Key Concepts",
    "wof:placetype":"venue"
},
  "geometry": {"coordinates":[-77.089742,38.892689],"type":"Point"}
}