{
  "type": "Feature",
  "properties": {
    "addr:full":"43330 Junction Plz Ashburn VA 20147",
    "addr:housenumber":"43330",
    "addr:postcode":"20147",
    "addr:street":"Junction Plz",
    "iso:country":"US",
    "sg:address":"43330 Junction Plz",
    "sg:city":"Ashburn",
    "sg:classifiers":[
        {
            "category":"Professional",
            "subcategory":"Advertising",
            "type":"Services"
        }
    ],
    "sg:phone":"+1 703 724 3910",
    "sg:postcode":"20147",
    "sg:province":"VA",
    "sg:tags":[
        "mailing",
        "shipping"
    ],
    "wof:name":"Easy Ship Inc",
    "wof:placetype":"venue"
},
  "geometry": {"coordinates":[-77.502594,39.036511],"type":"Point"}
}