{
  "type": "Feature",
  "properties": {
    "iso:country":"US",
    "sg:address":"24 Baltimore Ave",
    "sg:city":"Danville",
    "sg:classifiers":[
        {
            "category":"Organizations",
            "subcategory":"Religious Organization",
            "type":"Services"
        }
    ],
    "sg:phone":"+1 434 797 2313",
    "sg:postcode":"24541",
    "sg:province":"VA",
    "wof:name":"New Vision",
    "wof:placetype":"venue"
},
  "geometry": {"coordinates":[-79.423518,36.5631],"type":"Point"}
}