{
  "type": "Feature",
  "properties": {
    "iso:country":"US",
    "sg:address":"4209 Meadowland Ct",
    "sg:city":"Chantilly",
    "sg:classifiers":[
        {
            "category":"Professional",
            "type":"Services"
        }
    ],
    "sg:phone":"+1 703 263 1206",
    "sg:postcode":"20151",
    "sg:province":"VA",
    "wof:name":"Ruch Inc",
    "wof:placetype":"venue"
},
  "geometry": {"coordinates":[-77.425383,38.890941],"type":"Point"}
}