{
  "type": "Feature",
  "properties": {
    "iso:country":"US",
    "sg:address":"7451 Boston Blvd",
    "sg:city":"Springfield",
    "sg:classifiers":[
        {
            "category":"Manufacturing",
            "subcategory":"Tools & Machinery",
            "type":"Manufacturing & Wholesale Goods"
        },
        {
            "category":"Home & Garden",
            "subcategory":"Household Appliances",
            "type":"Retail Goods"
        },
        {
            "category":"Wholesale",
            "subcategory":"Electrical",
            "type":"Manufacturing & Wholesale Goods"
        }
    ],
    "sg:phone":"+1 703 569 8800",
    "sg:postcode":"22153",
    "sg:province":"VA",
    "sg:tags":[
        "major",
        "electric",
        "supply",
        "appliances-small",
        "equipment",
        "supplies-wholesale",
        "manufacturer"
    ],
    "wof:name":"Ge Co Other Operations Ge Aerospace Syste",
    "wof:placetype":"venue"
},
  "geometry": {"coordinates":[-77.202952,38.738693],"type":"Point"}
}