{
  "type": "Feature",
  "properties": {
    "addr:full":"925 Park Ave SW Norton VA 24273",
    "addr:housenumber":"925",
    "addr:postcode":"24273",
    "addr:street":"Park Ave Sw",
    "iso:country":"US",
    "sg:address":"925 Park Ave SW",
    "sg:city":"Norton",
    "sg:classifiers":[
        {
            "category":"Shopping",
            "subcategory":"Discount & Variety Stores",
            "type":"Retail Goods"
        }
    ],
    "sg:phone":"+1 276 679 5607",
    "sg:postcode":"24273",
    "sg:province":"VA",
    "sg:website":"www.biglots.com",
    "wof:name":"Big Lots",
    "wof:placetype":"venue"
},
  "geometry": {"coordinates":[-82.631919,36.932782],"type":"Point"}
}