{
  "type": "Feature",
  "properties": {
    "addr:full":"102 Holt Cir Seaford VA 23696",
    "addr:housenumber":"102",
    "addr:postcode":"23696",
    "addr:street":"Holt Cir",
    "iso:country":"US",
    "sg:address":"102 Holt Cir",
    "sg:city":"Seaford",
    "sg:classifiers":[
        {
            "category":"Professional",
            "subcategory":"Management & Consulting",
            "type":"Services"
        }
    ],
    "sg:phone":"+1 757 877 2220",
    "sg:postcode":"23696",
    "sg:province":"VA",
    "sg:tags":[
        "consultant",
        "educational"
    ],
    "wof:name":"Pat Youn Experiential Learning",
    "wof:placetype":"venue"
},
  "geometry": {"coordinates":[-76.440055,37.18183],"type":"Point"}
}