{
  "type": "Feature",
  "properties": {
    "addr:full":"1712 Firewood Ct Herndon VA 20170",
    "addr:postcode":"1712;20170",
    "addr:street":"Firewood Ct",
    "iso:country":"US",
    "sg:address":"1712 Firewood Ct",
    "sg:city":"Herndon",
    "sg:classifiers":[
        {
            "category":"Professional",
            "subcategory":"Management & Consulting",
            "type":"Services"
        }
    ],
    "sg:phone":"+1 703 709 6455",
    "sg:postcode":"20170",
    "sg:province":"VA",
    "wof:name":"Sandler Sales Institute VA",
    "wof:placetype":"venue"
},
  "geometry": {"coordinates":[-77.398923,38.984738],"type":"Point"}
}