{
  "type": "Feature",
  "properties": {
    "addr:full":"1199 N Fairfax St Ste 410 Alexandria VA 22314",
    "addr:housenumber":"1199",
    "addr:postcode":"22314",
    "addr:street":"N Fairfax St Ste 410",
    "iso:country":"US",
    "sg:address":"1199 N Fairfax St Ste 410",
    "sg:city":"Alexandria",
    "sg:classifiers":[
        {
            "category":"Professional",
            "subcategory":"Computer Services",
            "type":"Services"
        }
    ],
    "sg:phone":"+1 703 548 4800",
    "sg:postcode":"22314",
    "sg:province":"VA",
    "sg:tags":[
        "repair"
    ],
    "wof:name":"Pillar Systems Corporation",
    "wof:placetype":"venue"
},
  "geometry": {"coordinates":[-77.039694,38.81696],"type":"Point"}
}