{
  "type": "Feature",
  "properties": {
    "addr:full":"243 Ridge McIntire Rd Charlottesville VA 22903",
    "addr:housenumber":"243",
    "addr:postcode":"22903",
    "addr:street":"Ridge Mcintire Rd",
    "iso:country":"US",
    "sg:address":"243 Ridge McIntire Rd",
    "sg:city":"Charlottesville",
    "sg:classifiers":[
        {
            "category":"Shopping",
            "subcategory":"Stationery & Office Supplies",
            "type":"Retail Goods"
        }
    ],
    "sg:phone":"+1 434 977 5506",
    "sg:postcode":"22903",
    "sg:province":"VA",
    "sg:tags":[
        "equipment"
    ],
    "sg:website":"www.staples.com",
    "wof:name":"Staples",
    "wof:placetype":"venue"
},
  "geometry": {"coordinates":[-78.48487799999999,38.032738],"type":"Point"}
}