{
  "type": "Feature",
  "properties": {
    "addr:full":"801 Main St Lynchburg VA 24504",
    "addr:housenumber":"801",
    "addr:postcode":"24504",
    "addr:street":"Main St",
    "iso:country":"US",
    "sg:address":"801 Main St",
    "sg:city":"Lynchburg",
    "sg:classifiers":[
        {
            "category":"Professional",
            "subcategory":"Lawyer & Legal Services",
            "type":"Services"
        }
    ],
    "sg:phone":"+1 434 846 5771",
    "sg:postcode":"24504",
    "sg:province":"VA",
    "sg:tags":[
        "attorney"
    ],
    "wof:name":"Peter O Ward Jr",
    "wof:placetype":"venue"
},
  "geometry": {"coordinates":[-79.14229899999999,37.414849],"type":"Point"}
}