{
  "type": "Feature",
  "properties": {
    "addr:full":"6983 Cornfield Ln Mechanicsville VA 23111",
    "addr:housenumber":"6983",
    "addr:postcode":"23111",
    "addr:street":"Cornfield Ln",
    "iso:country":"US",
    "sg:address":"6983 Cornfield Ln",
    "sg:city":"Mechanicsville",
    "sg:classifiers":[
        {
            "category":"Building & Trades",
            "subcategory":"Plumbing",
            "type":"Services"
        }
    ],
    "sg:phone":"+1 804 559 4875",
    "sg:postcode":"23111",
    "sg:province":"VA",
    "sg:tags":[
        "conditioning",
        "air",
        "system",
        "contractor"
    ],
    "wof:name":"R L Gibson HEATING & AC Inc",
    "wof:placetype":"venue"
},
  "geometry": {"coordinates":[-77.33417900000001,37.60263],"type":"Point"}
}