{
  "type": "Feature",
  "properties": {
    "addr:full":"3205 W Moore St Richmond VA 23230",
    "addr:housenumber":"3205",
    "addr:postcode":"23230",
    "addr:street":"W Moore St",
    "iso:country":"US",
    "sg:address":"3205 W Moore St",
    "sg:city":"Richmond",
    "sg:classifiers":[
        {
            "category":"Building & Trades",
            "subcategory":"Plumbing",
            "type":"Services"
        }
    ],
    "sg:phone":"+1 804 355 7573",
    "sg:postcode":"23230",
    "sg:province":"VA",
    "sg:tags":[
        "air",
        "heating",
        "warm",
        "conditioning",
        "contractor"
    ],
    "wof:name":"Star Service Corp",
    "wof:placetype":"venue"
},
  "geometry": {"coordinates":[-77.47205599999999,37.569522],"type":"Point"}
}