{
  "type": "Feature",
  "properties": {
    "iso:country":"US",
    "sg:address":"1001 Hollins Rd NE",
    "sg:city":"Roanoke",
    "sg:classifiers":[
        {
            "category":"Retail",
            "subcategory":"Auto Repair",
            "type":"Services"
        }
    ],
    "sg:phone":"+1 540 343 9588",
    "sg:postcode":"24012",
    "sg:province":"VA",
    "sg:tags":[
        "automotive"
    ],
    "wof:name":"Roanoke Radiator Service",
    "wof:placetype":"venue"
},
  "geometry": {"coordinates":[-79.92428,37.281931],"type":"Point"}
}