{
  "type": "Feature",
  "properties": {
    "addr:full":"200 Ambriar Plz Amherst VA 24521",
    "addr:housenumber":"200",
    "addr:postcode":"24521",
    "addr:street":"Ambriar Plz",
    "iso:country":"US",
    "sg:address":"200 Ambriar Plz",
    "sg:city":"Amherst",
    "sg:classifiers":[
        {
            "category":"Insurance",
            "subcategory":"Hazard Insurance",
            "type":"Services"
        }
    ],
    "sg:phone":"+1 434 946 5550",
    "sg:postcode":"24521",
    "sg:province":"VA",
    "wof:name":"Allstate Insurance Company - Randall Campbell",
    "wof:placetype":"venue"
},
  "geometry": {"coordinates":[-79.063957,37.564571],"type":"Point"}
}