{
  "type": "Feature",
  "properties": {
    "addr:full":"5631 Sara Kay Dr Richmond VA 23237",
    "addr:housenumber":"5631",
    "addr:postcode":"23237",
    "addr:street":"Sara Kay Dr",
    "iso:country":"US",
    "sg:address":"5631 Sara Kay Dr",
    "sg:city":"Richmond",
    "sg:classifiers":[
        {
            "category":"Building & Trades",
            "subcategory":"Electrical",
            "type":"Services"
        }
    ],
    "sg:phone":"+1 804 363 0521",
    "sg:postcode":"23237",
    "sg:province":"VA",
    "sg:tags":[
        "electric",
        "contractor"
    ],
    "wof:name":"Certified Electric Inc",
    "wof:placetype":"venue"
},
  "geometry": {"coordinates":[-77.483548,37.388556],"type":"Point"}
}