{
  "type": "Feature",
  "properties": {
    "addr:full":"4915 Ox Rd Fairfax VA 22030",
    "addr:housenumber":"4915",
    "addr:postcode":"22030",
    "addr:street":"Ox Rd",
    "iso:country":"US",
    "sg:address":"4915 Ox Rd",
    "sg:city":"Fairfax",
    "sg:classifiers":[
        {
            "category":"Education",
            "subcategory":"School",
            "type":"Public Place"
        }
    ],
    "sg:phone":"+1 703 385 8702",
    "sg:postcode":"22030",
    "sg:province":"VA",
    "wof:name":"University View Child Care Ctr",
    "wof:placetype":"venue"
},
  "geometry": {"coordinates":[-77.31644300000001,38.827301],"type":"Point"}
}