{
  "type": "Feature",
  "properties": {
    "iso:country":"US",
    "sg:address":"3132 Shenandoah Ave NW",
    "sg:city":"Roanoke",
    "sg:classifiers":[
        {
            "category":"Restaurant",
            "type":"Food & Drink"
        },
        {
            "category":"Bars & Pubs",
            "subcategory":"Nightclub",
            "type":"Food & Drink"
        }
    ],
    "sg:phone":"+1 540 344 4404",
    "sg:postcode":"24017",
    "sg:province":"VA",
    "sg:tags":[
        "club",
        "style",
        "family",
        "night"
    ],
    "wof:name":"Hilltop Restaurant",
    "wof:placetype":"venue"
},
  "geometry": {"coordinates":[-79.987145,37.28235],"type":"Point"}
}