{
  "type": "Feature",
  "properties": {
    "addr:full":"6371 Buffie Ct Burke VA 22015",
    "addr:postcode":"6371;22015",
    "addr:street":"Buffie Ct",
    "iso:country":"US",
    "sg:address":"6371 Buffie Ct",
    "sg:city":"Burke",
    "sg:classifiers":[
        {
            "category":"Professional",
            "subcategory":"Business Services",
            "type":"Services"
        }
    ],
    "sg:phone":"+1 703 455 1941",
    "sg:postcode":"22015",
    "sg:province":"VA",
    "wof:name":"C & K Window Design",
    "wof:placetype":"venue"
},
  "geometry": {"coordinates":[-77.271694,38.780379],"type":"Point"}
}