{
  "type": "Feature",
  "properties": {
    "iso:country":"US",
    "sg:address":"1525 N Kentucky St",
    "sg:city":"Arlington",
    "sg:classifiers":[
        {
            "category":"Professional",
            "subcategory":"Management & Consulting",
            "type":"Services"
        }
    ],
    "sg:phone":"+1 703 532 8360",
    "sg:postcode":"22205",
    "sg:province":"VA",
    "wof:name":"Rob Cahill and Associates",
    "wof:placetype":"venue"
},
  "geometry": {"coordinates":[-77.13624900000001,38.885105],"type":"Point"}
}