{
  "type": "Feature",
  "properties": {
    "iso:country":"US",
    "sg:address":"35 Beechdale Rd",
    "sg:city":"Portsmouth",
    "sg:classifiers":[
        {
            "category":"Retail",
            "subcategory":"Auto Repair",
            "type":"Services"
        }
    ],
    "sg:phone":"+1 757 487 7777",
    "sg:postcode":"23702",
    "sg:province":"VA",
    "sg:tags":[
        "truck"
    ],
    "wof:name":"Finks Truck Frame & Alignment",
    "wof:placetype":"venue"
},
  "geometry": {"coordinates":[-76.343603,36.793821],"type":"Point"}
}