{
  "type": "Feature",
  "properties": {
    "iso:country":"US",
    "sg:address":"3341 Weaver Pike",
    "sg:city":"Bristol",
    "sg:classifiers":[
        {
            "category":"Education",
            "subcategory":"School",
            "type":"Public Place"
        }
    ],
    "sg:phone":"+1 423 878 1953",
    "sg:postcode":"37620",
    "sg:province":"VA",
    "wof:name":"Weavers Elementary School",
    "wof:placetype":"venue"
},
  "geometry": {"coordinates":[-82.185762,36.526501],"type":"Point"}
}