{
  "type": "Feature",
  "properties": {
    "addr:full":"9502 Chamberlayne Rd Mechanicsville VA 23116",
    "addr:housenumber":"9502",
    "addr:postcode":"23116",
    "addr:street":"Chamberlayne Rd",
    "iso:country":"US",
    "sg:address":"9502 Chamberlayne Rd",
    "sg:city":"Mechanicsville",
    "sg:classifiers":[
        {
            "category":"Shopping",
            "subcategory":"Florist",
            "type":"Retail Goods"
        }
    ],
    "sg:phone":"+1 804 569 1303",
    "sg:postcode":"23116",
    "sg:province":"VA",
    "wof:name":"Enchanted Florist LLC",
    "wof:placetype":"venue"
},
  "geometry": {"coordinates":[-77.38526299999999,37.659592],"type":"Point"}
}