{
  "type": "Feature",
  "properties": {
    "iso:country":"US",
    "sg:address":"3458 Orange Ave NE",
    "sg:city":"Roanoke",
    "sg:classifiers":[
        {
            "category":"Banks & Credit Unions",
            "subcategory":"Bank",
            "type":"Services"
        }
    ],
    "sg:phone":"+1 540 561 8796",
    "sg:postcode":"24012",
    "sg:province":"VA",
    "sg:tags":[
        "state"
    ],
    "wof:name":"First Virginia Bank-Southwest",
    "wof:placetype":"venue"
},
  "geometry": {"coordinates":[-79.892788,37.302744],"type":"Point"}
}