{
  "type": "Feature",
  "properties": {
    "iso:country":"US",
    "sg:address":"8321 Old Courthouse Rd",
    "sg:city":"Vienna",
    "sg:classifiers":[
        {
            "category":"Education",
            "subcategory":"Preschool",
            "type":"Public Place"
        }
    ],
    "sg:phone":"+1 703 761 7700",
    "sg:postcode":"22182",
    "sg:province":"VA",
    "sg:tags":[
        "kindergarten"
    ],
    "wof:name":"Dolley Madison Associates Limited Partne",
    "wof:placetype":"venue"
},
  "geometry": {"coordinates":[-77.23226200000001,38.91415],"type":"Point"}
}