{
  "type": "Feature",
  "properties": {
    "addr:full":"1824 Laskin Rd Virginia Beach VA 23454",
    "addr:housenumber":"1824",
    "addr:postcode":"23454",
    "addr:street":"Laskin Rd",
    "iso:country":"US",
    "sg:address":"1824 Laskin Rd",
    "sg:city":"Virginia Beach",
    "sg:classifiers":[
        {
            "category":"Restaurant",
            "type":"Food & Drink"
        }
    ],
    "sg:phone":"+1 757 422 5999",
    "sg:postcode":"23454",
    "sg:province":"VA",
    "sg:tags":[
        "eating"
    ],
    "wof:name":"Asia Garden Buffet & Sushi Bar",
    "wof:placetype":"venue"
},
  "geometry": {"coordinates":[-76.030402,36.849229],"type":"Point"}
}