{
  "type": "Feature",
  "properties": {
    "iso:country":"US",
    "sg:address":"12531 Jefferson Ave",
    "sg:city":"Newport News",
    "sg:classifiers":[
        {
            "category":"Coffee & Tea",
            "type":"Food & Drink"
        }
    ],
    "sg:menulink":"http://www.allmenus.com/va/newport-news/112052-starbucks-coffee/menu/",
    "sg:phone":"+1 757 874 3592",
    "sg:postcode":"23602",
    "sg:province":"VA",
    "sg:tags":[
        "american"
    ],
    "wof:name":"Starbucks Coffee",
    "wof:placetype":"venue"
},
  "geometry": {"coordinates":[-76.511048,37.126999],"type":"Point"}
}