{
  "type": "Feature",
  "properties": {
    "addr:full":"4022 Guinea Rd Fairfax VA 22032",
    "addr:housenumber":"4022",
    "addr:postcode":"22032",
    "addr:street":"Guinea Rd",
    "iso:country":"US",
    "sg:address":"4022 Guinea Rd",
    "sg:city":"Fairfax",
    "sg:classifiers":[
        {
            "category":"Home & Garden",
            "subcategory":"Home Furnishings",
            "type":"Retail Goods"
        }
    ],
    "sg:phone":"+1 703 218 2881",
    "sg:postcode":"22032",
    "sg:province":"VA",
    "wof:name":"Susanna Ciao Inc",
    "wof:placetype":"venue"
},
  "geometry": {"coordinates":[-77.252494,38.836286],"type":"Point"}
}