{
  "type": "Feature",
  "properties": {
    "addr:full":"12976 Clifton Creek Dr Clifton VA 20124",
    "addr:housenumber":"12976",
    "addr:postcode":"20124",
    "addr:street":"Clifton Creek Dr",
    "iso:country":"US",
    "sg:address":"12976 Clifton Creek Dr",
    "sg:city":"Clifton",
    "sg:classifiers":[
        {
            "category":"Social Services",
            "subcategory":"Child Care",
            "type":"Services"
        }
    ],
    "sg:phone":"+1 703 803 0781",
    "sg:postcode":"20124",
    "sg:province":"VA",
    "sg:tags":[
        "day"
    ],
    "wof:name":"Elizabeth Esmay Day Care",
    "wof:placetype":"venue"
},
  "geometry": {"coordinates":[-77.39627900000001,38.783761],"type":"Point"}
}