{
  "type": "Feature",
  "properties": {
    "addr:full":"5459 Cove Rd NW Roanoke VA 24019",
    "addr:housenumber":"5459",
    "addr:postcode":"24019",
    "addr:street":"Cove Rd Nw",
    "iso:country":"US",
    "sg:address":"5459 Cove Rd NW",
    "sg:city":"Roanoke",
    "sg:classifiers":[
        {
            "category":"Food & Beverages",
            "subcategory":"Specialty",
            "type":"Retail Goods"
        }
    ],
    "sg:phone":"+1 540 353 4404",
    "sg:postcode":"24019",
    "sg:province":"VA",
    "sg:tags":[
        "health",
        "diet"
    ],
    "wof:name":"Healthworks",
    "wof:placetype":"venue"
},
  "geometry": {"coordinates":[-80.014867,37.315839],"type":"Point"}
}