{
  "type": "Feature",
  "properties": {
    "iso:country":"US",
    "sg:address":"218 Mill Rd",
    "sg:city":"Woodstock",
    "sg:classifiers":[
        {
            "category":"Social Services",
            "subcategory":"Adult Care",
            "type":"Services"
        }
    ],
    "sg:phone":"+1 540 459 4480",
    "sg:postcode":"22664",
    "sg:province":"VA",
    "sg:tags":[
        "residential"
    ],
    "wof:name":"Pine Meadow",
    "wof:placetype":"venue"
},
  "geometry": {"coordinates":[-78.497456,38.88727],"type":"Point"}
}