{
  "type": "Feature",
  "properties": {
    "iso:country":"US",
    "sg:address":"8308 E Boulevard Dr",
    "sg:city":"Alexandria",
    "sg:classifiers":[
        {
            "category":"Professional",
            "subcategory":"Management & Consulting",
            "type":"Services"
        }
    ],
    "sg:phone":"+1 703 768 2396",
    "sg:postcode":"22308",
    "sg:province":"VA",
    "sg:tags":[
        "business"
    ],
    "wof:name":"Northern VA Power Squadron",
    "wof:placetype":"venue"
},
  "geometry": {"coordinates":[-77.047082,38.732375],"type":"Point"}
}