{
  "type": "Feature",
  "properties": {
    "iso:country":"US",
    "sg:address":"3388 Britton Rd",
    "sg:city":"Richmond",
    "sg:classifiers":[
        {
            "category":"Building & Trades",
            "subcategory":"Construction",
            "type":"Services"
        }
    ],
    "sg:phone":"+1 804 795 9477",
    "sg:postcode":"23231",
    "sg:province":"VA",
    "sg:tags":[
        "excavating",
        "contractor"
    ],
    "wof:name":"White Oak Excavating",
    "wof:placetype":"venue"
},
  "geometry": {"coordinates":[-77.326307,37.470904],"type":"Point"}
}