{
  "type": "Feature",
  "properties": {
    "addr:full":"102 Prosperity Ave SE Leesburg VA 20175",
    "addr:housenumber":"102",
    "addr:postcode":"20175",
    "addr:street":"Prosperity Ave Se",
    "iso:country":"US",
    "sg:address":"102 Prosperity Ave SE",
    "sg:city":"Leesburg",
    "sg:classifiers":[
        {
            "category":"Food & Beverages",
            "subcategory":"Bakery",
            "type":"Retail Goods"
        }
    ],
    "sg:phone":"+1 703 318 2923",
    "sg:postcode":"20175",
    "sg:province":"VA",
    "wof:name":"Rondas Creative Cakes",
    "wof:placetype":"venue"
},
  "geometry": {"coordinates":[-77.547825,39.106345],"type":"Point"}
}