{
  "type": "Feature",
  "properties": {
    "addr:full":"8653 Sudley Rd Manassas VA 20110",
    "addr:housenumber":"8653",
    "addr:postcode":"20110",
    "addr:street":"Sudley Rd",
    "iso:country":"US",
    "sg:address":"8653 Sudley Rd",
    "sg:city":"Manassas",
    "sg:classifiers":[
        {
            "category":"Social Services",
            "subcategory":"Child Care",
            "type":"Services"
        }
    ],
    "sg:phone":"+1 703 368 3871",
    "sg:postcode":"20110",
    "sg:province":"VA",
    "sg:tags":[
        "center"
    ],
    "wof:name":"Seven Oaks Academy",
    "wof:placetype":"venue"
},
  "geometry": {"coordinates":[-77.48622899999999,38.768538],"type":"Point"}
}