{
  "type": "Feature",
  "properties": {
    "iso:country":"US",
    "sg:address":"11601 Robious Rd",
    "sg:city":"Midlothian",
    "sg:classifiers":[
        {
            "category":"Health Services",
            "subcategory":"Doctor",
            "type":"Services"
        }
    ],
    "sg:phone":"+1 804 379 9494",
    "sg:postcode":"23113",
    "sg:province":"VA",
    "sg:tags":[
        "physician",
        "surgeon",
        "medical"
    ],
    "wof:name":"Capitol Pediatrics PC",
    "wof:placetype":"venue"
},
  "geometry": {"coordinates":[-77.615771,37.523472],"type":"Point"}
}