{
  "type": "Feature",
  "properties": {
    "addr:full":"443 Clayton Ln Alexandria VA 22304",
    "addr:housenumber":"443",
    "addr:postcode":"22304",
    "addr:street":"Clayton Ln",
    "iso:country":"US",
    "sg:address":"443 Clayton Ln",
    "sg:city":"Alexandria",
    "sg:classifiers":[
        {
            "category":"Banks & Credit Unions",
            "subcategory":"Bank",
            "type":"Services"
        }
    ],
    "sg:phone":"+1 202 623 8651",
    "sg:postcode":"22304",
    "sg:province":"VA",
    "sg:tags":[
        "foreign"
    ],
    "wof:name":"International Monetary Fund",
    "wof:placetype":"venue"
},
  "geometry": {"coordinates":[-77.13646199999999,38.808622],"type":"Point"}
}