{
  "type": "Feature",
  "properties": {
    "iso:country":"US",
    "sg:address":"837 W 44th St",
    "sg:city":"Norfolk",
    "sg:classifiers":[
        {
            "category":"Retail",
            "subcategory":"Auto Repair",
            "type":"Services"
        }
    ],
    "sg:phone":"+1 757 440 1053",
    "sg:postcode":"23508",
    "sg:province":"VA",
    "sg:tags":[
        "automotive",
        "general"
    ],
    "wof:name":"Lees Auto Service",
    "wof:placetype":"venue"
},
  "geometry": {"coordinates":[-76.29714199999999,36.884208],"type":"Point"}
}