{
  "type": "Feature",
  "properties": {
    "iso:country":"US",
    "sg:address":"10651 Balls Ford Rd",
    "sg:city":"Manassas",
    "sg:classifiers":[
        {
            "category":"Restaurant",
            "type":"Food & Drink"
        }
    ],
    "sg:phone":"+1 703 369 5800",
    "sg:postcode":"20109",
    "sg:province":"VA",
    "sg:tags":[
        "eating"
    ],
    "wof:name":"Pargos Restaurant 7701",
    "wof:placetype":"venue"
},
  "geometry": {"coordinates":[-77.51811499999999,38.797962],"type":"Point"}
}