{
  "type": "Feature",
  "properties": {
    "iso:country":"US",
    "sg:address":"3953 Aeries Way",
    "sg:city":"Virginia Beach",
    "sg:classifiers":[
        {
            "category":"Professional",
            "subcategory":"Computer Services",
            "type":"Services"
        }
    ],
    "sg:phone":"+1 757 685 4547",
    "sg:postcode":"23455",
    "sg:province":"VA",
    "sg:tags":[
        "technical",
        "staffing"
    ],
    "wof:name":"Webster Data Communication",
    "wof:placetype":"venue"
},
  "geometry": {"coordinates":[-76.113792,36.911202],"type":"Point"}
}