{
  "type": "Feature",
  "properties": {
    "addr:full":"10749 Midlothian Tpke Richmond VA 23235",
    "addr:housenumber":"10749",
    "addr:postcode":"23235",
    "addr:street":"Midlothian Tpke",
    "iso:country":"US",
    "sg:address":"10749 Midlothian Tpke",
    "sg:city":"Richmond",
    "sg:classifiers":[
        {
            "category":"Home & Garden",
            "subcategory":"Home Furnishings",
            "type":"Retail Goods"
        }
    ],
    "sg:phone":"+1 804 794 7618",
    "sg:postcode":"23235",
    "sg:province":"VA",
    "sg:website":"www.hearthandpatioshoppe.com",
    "wof:name":"Hearth & Patio Shoppe",
    "wof:placetype":"venue"
},
  "geometry": {"coordinates":[-77.595181,37.507032],"type":"Point"}
}