{
  "type": "Feature",
  "properties": {
    "addr:full":"9311 Walhala Pt Richmond VA 23236",
    "addr:postcode":"9311;23236",
    "addr:street":"Walhala Pt",
    "iso:country":"US",
    "sg:address":"9311 Walhala Pt",
    "sg:city":"Richmond",
    "sg:classifiers":[
        {
            "category":"Professional",
            "subcategory":"Lawyer & Legal Services",
            "type":"Services"
        }
    ],
    "sg:phone":"+1 804 745 0032",
    "sg:postcode":"23236",
    "sg:province":"VA",
    "wof:name":"William J Irvin Atty",
    "wof:placetype":"venue"
},
  "geometry": {"coordinates":[-77.56544,37.45624],"type":"Point"}
}