{
  "type": "Feature",
  "properties": {
    "addr:full":"8311 Mary Ball Rd Lancaster VA 22503",
    "addr:housenumber":"8311",
    "addr:postcode":"22503",
    "addr:street":"Mary Ball Rd",
    "iso:country":"US",
    "sg:address":"8311 Mary Ball Rd",
    "sg:city":"Lancaster",
    "sg:classifiers":[
        {
            "category":"Government",
            "subcategory":"Office",
            "type":"Public Place"
        }
    ],
    "sg:phone":"+1 804 462 5611",
    "sg:postcode":"22503",
    "sg:province":"VA",
    "wof:name":"Lancaster Cnty Circuit Ct Clrk",
    "wof:placetype":"venue"
},
  "geometry": {"coordinates":[-76.455519,37.767988],"type":"Point"}
}