{
  "type": "Feature",
  "properties": {
    "addr:full":"511 Euclid Ave Colonial Beach VA 22443",
    "addr:housenumber":"511",
    "addr:postcode":"beach;22443",
    "addr:street":"Euclid Ave",
    "iso:country":"US",
    "sg:address":"511 Euclid Ave",
    "sg:city":"Colonial Beach",
    "sg:classifiers":[
        {
            "category":"Food & Beverages",
            "subcategory":"Groceries & Convenience Stores",
            "type":"Retail Goods"
        }
    ],
    "sg:phone":"+1 804 214 9771",
    "sg:postcode":"22443",
    "sg:province":"VA",
    "sg:tags":[
        "eating"
    ],
    "wof:name":"LA Mexicana",
    "wof:placetype":"venue"
},
  "geometry": {"coordinates":[-76.97197,38.255324],"type":"Point"}
}