{
  "type": "Feature",
  "properties": {
    "iso:country":"US",
    "sg:address":"511 Euclid Ave",
    "sg:city":"Colonial Beach",
    "sg:classifiers":[
        {
            "category":"Food & Beverages",
            "subcategory":"Groceries & Convenience Stores",
            "type":"Retail Goods"
        }
    ],
    "sg:phone":"+1 804 214 9771",
    "sg:postcode":"22443",
    "sg:province":"VA",
    "sg:tags":[
        "eating"
    ],
    "wof:name":"LA Mexicana",
    "wof:placetype":"venue"
},
  "geometry": {"coordinates":[-76.97197,38.255324],"type":"Point"}
}