{
  "type": "Feature",
  "properties": {
    "addr:full":"6409 Rigsby Rd Richmond VA 23226",
    "addr:housenumber":"6409",
    "addr:postcode":"23226",
    "addr:street":"Rigsby Rd",
    "iso:country":"US",
    "sg:address":"6409 Rigsby Rd",
    "sg:city":"Richmond",
    "sg:classifiers":[
        {
            "category":"Food & Beverages",
            "subcategory":"Groceries & Convenience Stores",
            "type":"Retail Goods"
        }
    ],
    "sg:phone":"+1 804 282 2629",
    "sg:postcode":"23226",
    "sg:province":"VA",
    "wof:name":"Mexico Mini Market Inc",
    "wof:placetype":"venue"
},
  "geometry": {"coordinates":[-77.51538499999999,37.595951],"type":"Point"}
}