{
  "type": "Feature",
  "properties": {
    "addr:full":"1071 Cedrus Ln Mc Lean VA 22102",
    "addr:housenumber":"1071",
    "addr:postcode":"22102",
    "addr:street":"Cedrus Ln Mc Lean",
    "iso:country":"US",
    "sg:address":"1071 Cedrus Ln",
    "sg:city":"Mc Lean",
    "sg:classifiers":[
        {
            "category":"Health Services",
            "subcategory":"Doctor",
            "type":"Services"
        }
    ],
    "sg:phone":"+1 703 757 5404",
    "sg:postcode":"22102",
    "sg:province":"VA",
    "wof:name":"Bioniche Inc",
    "wof:placetype":"venue"
},
  "geometry": {"coordinates":[-77.25340300000001,38.9645],"type":"Point"}
}