{
  "type": "Feature",
  "properties": {
    "addr:full":"3301 George Washington Hwy Portsmouth VA 23704",
    "addr:housenumber":"3301",
    "addr:postcode":"23704",
    "addr:street":"George Washington Hwy",
    "iso:country":"US",
    "sg:address":"3301 George Washington Hwy",
    "sg:city":"Portsmouth",
    "sg:classifiers":[
        {
            "category":"Retail",
            "subcategory":"Repair Shop",
            "type":"Services"
        }
    ],
    "sg:phone":"+1 757 399 6908",
    "sg:postcode":"23704",
    "sg:province":"VA",
    "sg:tags":[
        "antique",
        "restoring"
    ],
    "wof:name":"Wooden Things",
    "wof:placetype":"venue"
},
  "geometry": {"coordinates":[-76.31444399999999,36.812539],"type":"Point"}
}