{
  "type": "Feature",
  "properties": {
    "iso:country":"US",
    "sg:address":"14809 Spotswood Trl",
    "sg:city":"Elkton",
    "sg:classifiers":[
        {
            "category":"Restaurant",
            "type":"Food & Drink"
        }
    ],
    "sg:menulink":"http://www.allmenus.com/va/stonewall/80369-dominos-pizza/menu/",
    "sg:phone":"+1 540 298 2220",
    "sg:postcode":"22827",
    "sg:province":"VA",
    "sg:tags":[
        "american",
        "wing",
        "pizza"
    ],
    "wof:name":"Domino's Pizza",
    "wof:placetype":"venue"
},
  "geometry": {"coordinates":[-78.65258900000001,38.406852],"type":"Point"}
}