{
  "type": "Feature",
  "properties": {
    "iso:country":"US",
    "sg:address":"12701 Fair Lakes Cir",
    "sg:city":"Fairfax",
    "sg:classifiers":[
        {
            "category":"Autos & Motor Vehicles",
            "subcategory":"Automobile Sales",
            "type":"Retail Goods"
        }
    ],
    "sg:phone":"+1 703 802 3480",
    "sg:postcode":"22033",
    "sg:province":"VA",
    "sg:tags":[
        "car",
        "dealer"
    ],
    "wof:name":"Sheehy Auto Stores",
    "wof:placetype":"venue"
},
  "geometry": {"coordinates":[-77.38163,38.858138],"type":"Point"}
}