{
  "type": "Feature",
  "properties": {
    "iso:country":"US",
    "sg:address":"6621 Indian River Rd",
    "sg:city":"Virginia Beach",
    "sg:classifiers":[
        {
            "category":"Utilities",
            "subcategory":"Natural Gas",
            "type":"Services"
        }
    ],
    "sg:phone":"+1 757 420 5441",
    "sg:postcode":"23464",
    "sg:province":"VA",
    "sg:tags":[
        "company"
    ],
    "wof:name":"Sunoco",
    "wof:placetype":"venue"
},
  "geometry": {"coordinates":[-76.21936599999999,36.81864],"type":"Point"}
}