{
  "type": "Feature",
  "properties": {
    "iso:country":"US",
    "sg:address":"5647 Locust Dr",
    "sg:city":"Dublin",
    "sg:classifiers":[
        {
            "category":"Professional",
            "subcategory":"Computer Services",
            "type":"Services"
        }
    ],
    "sg:phone":"+1 540 674 4084",
    "sg:postcode":"24084",
    "sg:province":"VA",
    "sg:tags":[
        "website",
        "design"
    ],
    "wof:name":"Scents The Beginning",
    "wof:placetype":"venue"
},
  "geometry": {"coordinates":[-80.67247399999999,37.109418],"type":"Point"}
}