{
  "type": "Feature",
  "properties": {
    "iso:country":"US",
    "sg:address":"1524 N Augusta St",
    "sg:city":"Staunton",
    "sg:classifiers":[
        {
            "category":"Health Services",
            "subcategory":"Doctor",
            "type":"Services"
        }
    ],
    "sg:phone":"+1 540 885 8163",
    "sg:postcode":"24401",
    "sg:province":"VA",
    "sg:tags":[
        "surgeon",
        "orthopedic"
    ],
    "wof:name":"Harrison Carrington III PC",
    "wof:placetype":"venue"
},
  "geometry": {"coordinates":[-79.065254,38.164833],"type":"Point"}
}