{
  "type": "Feature",
  "properties": {
    "iso:country":"US",
    "sg:address":"7029 Clifton Knoll Ct",
    "sg:city":"Alexandria",
    "sg:classifiers":[
        {
            "category":"Wholesale",
            "subcategory":"Durable Goods & Equipment",
            "type":"Manufacturing & Wholesale Goods"
        }
    ],
    "sg:phone":"+1 703 971 9418",
    "sg:postcode":"22315",
    "sg:province":"VA",
    "sg:tags":[
        "exporter"
    ],
    "wof:name":"Grand Vet Intl LLC",
    "wof:placetype":"venue"
},
  "geometry": {"coordinates":[-77.129453,38.765836],"type":"Point"}
}