{
  "type": "Feature",
  "properties": {
    "addr:full":"2148 Proffitt Rd Manakin Sabot VA 23103",
    "addr:housenumber":"2148",
    "addr:postcode":"sabot;23103",
    "addr:street":"Proffitt Rd",
    "iso:country":"US",
    "sg:address":"2148 Proffitt Rd",
    "sg:city":"Manakin Sabot",
    "sg:classifiers":[
        {
            "category":"Building & Trades",
            "subcategory":"Construction",
            "type":"Services"
        }
    ],
    "sg:phone":"+1 804 749 8939",
    "sg:postcode":"23103",
    "sg:province":"VA",
    "sg:tags":[
        "house",
        "commercial"
    ],
    "wof:name":"Sabot Construction",
    "wof:placetype":"venue"
},
  "geometry": {"coordinates":[-77.705624,37.68057],"type":"Point"}
}