{
  "type": "Feature",
  "properties": {
    "addr:full":"5300 Sunbeam Rd Richmond VA 23234",
    "addr:postcode":"5300;23234",
    "addr:street":"Sunbeam Rd",
    "iso:country":"US",
    "sg:address":"5300 Sunbeam Rd",
    "sg:city":"Richmond",
    "sg:classifiers":[
        {
            "category":"Shopping",
            "subcategory":"Gifts & Souvenirs",
            "type":"Retail Goods"
        }
    ],
    "sg:phone":"+1 804 275 1264",
    "sg:postcode":"23234",
    "sg:province":"VA",
    "sg:tags":[
        "shop"
    ],
    "wof:name":"Tasteful Treasures By Lynda",
    "wof:placetype":"venue"
},
  "geometry": {"coordinates":[-77.474709,37.449558],"type":"Point"}
}