{
  "type": "Feature",
  "properties": {
    "iso:country":"US",
    "sg:address":"325 N Augusta St",
    "sg:city":"Staunton",
    "sg:classifiers":[
        {
            "category":"Organizations",
            "subcategory":"Religious Organization",
            "type":"Services"
        }
    ],
    "sg:phone":"+1 540 886 7283",
    "sg:postcode":"24401",
    "sg:province":"VA",
    "wof:name":"Augusta St Untd Methdst Church",
    "wof:placetype":"venue"
},
  "geometry": {"coordinates":[-79.07307299999999,38.153253],"type":"Point"}
}