{
  "type": "Feature",
  "properties": {
    "iso:country":"US",
    "sg:address":"6723 Whittier Ave Ste 303C",
    "sg:city":"Mc Lean",
    "sg:classifiers":[
        {
            "category":"Building & Trades",
            "subcategory":"Construction",
            "type":"Services"
        }
    ],
    "sg:phone":"+1 703 288 8576",
    "sg:postcode":"22101",
    "sg:province":"VA",
    "sg:tags":[
        "interior",
        "design"
    ],
    "wof:name":"J S Designs For Interiors",
    "wof:placetype":"venue"
},
  "geometry": {"coordinates":[-77.176102,38.931499],"type":"Point"}
}