{
  "type": "Feature",
  "properties": {
    "iso:country":"US",
    "sg:address":"805 N Emerson St",
    "sg:city":"Arlington",
    "sg:classifiers":[
        {
            "category":"Shopping",
            "subcategory":"Used Merchandise",
            "type":"Retail Goods"
        }
    ],
    "sg:phone":"+1 703 527 7797",
    "sg:postcode":"22205",
    "sg:province":"VA",
    "sg:tags":[
        "book",
        "rare",
        "dealer"
    ],
    "sg:website":"www.bookhouse.com",
    "wof:name":"Bookhouse",
    "wof:placetype":"venue"
},
  "geometry": {"coordinates":[-77.123096,38.877685],"type":"Point"}
}