{
  "type": "Feature",
  "properties": {
    "addr:full":"3532 Richards Run Powhatan VA 23139",
    "addr:housenumber":"3532",
    "addr:postcode":"23139",
    "addr:street":"Richards Run",
    "iso:country":"US",
    "sg:address":"3532 Richards Run",
    "sg:city":"Powhatan",
    "sg:classifiers":[
        {
            "category":"Professional",
            "type":"Services"
        }
    ],
    "sg:phone":"+1 804 598 2737",
    "sg:postcode":"23139",
    "sg:province":"VA",
    "wof:name":"Je Hosley & Assoc",
    "wof:placetype":"venue"
},
  "geometry": {"coordinates":[-77.902779,37.548296],"type":"Point"}
}