{
  "type": "Feature",
  "properties": {
    "iso:country":"US",
    "sg:address":"13822 Riviera Ct",
    "sg:city":"Woodbridge",
    "sg:classifiers":[
        {
            "category":"Professional",
            "type":"Services"
        }
    ],
    "sg:phone":"+1 703 670 3660",
    "sg:postcode":"22193",
    "sg:province":"VA",
    "wof:name":"Michele Taylor",
    "wof:placetype":"venue"
},
  "geometry": {"coordinates":[-77.37966400000001,38.654358],"type":"Point"}
}