{
  "type": "Feature",
  "properties": {
    "addr:full":"189 Merrimac Trl Williamsburg VA 23185",
    "addr:housenumber":"189",
    "addr:postcode":"23185",
    "addr:street":"Merrimac Trl",
    "iso:country":"US",
    "sg:address":"189 Merrimac Trl",
    "sg:city":"Williamsburg",
    "sg:classifiers":[
        {
            "category":"Professional",
            "type":"Services"
        }
    ],
    "sg:phone":"+1 757 258 0070",
    "sg:postcode":"23185",
    "sg:province":"VA",
    "wof:name":"Squire Williamsburg",
    "wof:placetype":"venue"
},
  "geometry": {"coordinates":[-76.684605,37.283909],"type":"Point"}
}