{
  "type": "Feature",
  "properties": {
    "addr:full":"13617 Ellendale Dr Chantilly VA 20151",
    "addr:housenumber":"13617",
    "addr:postcode":"20151",
    "addr:street":"Ellendale Dr",
    "iso:country":"US",
    "sg:address":"13617 Ellendale Dr",
    "sg:city":"Chantilly",
    "sg:classifiers":[
        {
            "category":"Building & Trades",
            "subcategory":"Construction",
            "type":"Services"
        }
    ],
    "sg:phone":"+1 703 378 7341",
    "sg:postcode":"20151",
    "sg:province":"VA",
    "sg:tags":[
        "carpentry",
        "contractor"
    ],
    "wof:name":"Complete Drywall Service",
    "wof:placetype":"venue"
},
  "geometry": {"coordinates":[-77.417952,38.880395],"type":"Point"}
}