{
  "type": "Feature",
  "properties": {
    "iso:country":"US",
    "sg:address":"1300 E Little Creek Rd",
    "sg:city":"Norfolk",
    "sg:classifiers":[
        {
            "category":"Home & Garden",
            "subcategory":"Furniture",
            "type":"Retail Goods"
        }
    ],
    "sg:phone":"+1 757 480 9600",
    "sg:postcode":"23518",
    "sg:province":"VA",
    "sg:tags":[
        "bedding",
        "supply"
    ],
    "wof:name":"Mattress Discounters",
    "wof:placetype":"venue"
},
  "geometry": {"coordinates":[-76.236874,36.915666],"type":"Point"}
}