{
  "type": "Feature",
  "properties": {
    "addr:full":"10065 Indiantown Rd King George VA 22485",
    "addr:housenumber":"10065",
    "addr:postcode":"22485",
    "addr:street":"Indiantown Rd",
    "iso:country":"US",
    "sg:address":"10065 Indiantown Rd",
    "sg:city":"King George",
    "sg:classifiers":[
        {
            "category":"Building & Trades",
            "subcategory":"Plumbing",
            "type":"Services"
        }
    ],
    "sg:phone":"+1 540 775 3794",
    "sg:postcode":"22485",
    "sg:province":"VA",
    "sg:tags":[
        "plumbing",
        "ventilation",
        "heating",
        "contractor"
    ],
    "wof:name":"Commonwealth Plumbing Inc",
    "wof:placetype":"venue"
},
  "geometry": {"coordinates":[-77.181096,38.275955],"type":"Point"}
}