{
  "type": "Feature",
  "properties": {
    "addr:full":"117 Stone Ct NE Leesburg VA 20176",
    "addr:housenumber":"117",
    "addr:postcode":"20176",
    "addr:street":"Stone Ct Ne",
    "iso:country":"US",
    "sg:address":"117 Stone Ct NE",
    "sg:city":"Leesburg",
    "sg:classifiers":[
        {
            "category":"Professional",
            "subcategory":"Management & Consulting",
            "type":"Services"
        }
    ],
    "sg:phone":"+1 703 777 5936",
    "sg:postcode":"20176",
    "sg:province":"VA",
    "wof:name":"Corle Group Inc",
    "wof:placetype":"venue"
},
  "geometry": {"coordinates":[-77.540497,39.129192],"type":"Point"}
}