{
  "type": "Feature",
  "properties": {
    "addr:full":"1420 E Parham Rd Richmond VA 23228",
    "addr:housenumber":"1420",
    "addr:postcode":"23228",
    "addr:street":"E Parham Rd",
    "iso:country":"US",
    "sg:address":"1420 E Parham Rd",
    "sg:city":"Richmond",
    "sg:classifiers":[
        {
            "category":"Shopping",
            "type":"Retail Goods"
        }
    ],
    "sg:phone":"+1 804 741 3123",
    "sg:postcode":"23228",
    "sg:province":"VA",
    "sg:tags":[
        "outdoor",
        "lighting",
        "specialty"
    ],
    "wof:name":"Christmas Store",
    "wof:placetype":"venue"
},
  "geometry": {"coordinates":[-77.469139,37.638948],"type":"Point"}
}