{
  "type": "Feature",
  "properties": {
    "addr:full":"800 Shoppers World Ct Charlottesville VA 22901",
    "addr:housenumber":"800",
    "addr:postcode":"22901",
    "addr:street":"World Ct",
    "iso:country":"US",
    "sg:address":"800 Shoppers World Ct",
    "sg:city":"Charlottesville",
    "sg:classifiers":[
        {
            "category":"Shopping",
            "subcategory":"Bicycles & Sporting Goods",
            "type":"Retail Goods"
        }
    ],
    "sg:phone":"+1 434 975 4653",
    "sg:postcode":"22901",
    "sg:province":"VA",
    "wof:name":"Charlottesville Golf Center",
    "wof:placetype":"venue"
},
  "geometry": {"coordinates":[-78.4785,38.077702],"type":"Point"}
}