{
  "type": "Feature",
  "properties": {
    "iso:country":"US",
    "sg:address":"1233 Whaley Ave",
    "sg:city":"Norfolk",
    "sg:classifiers":[
        {
            "category":"Shopping",
            "subcategory":"Florist",
            "type":"Retail Goods"
        }
    ],
    "sg:phone":"+1 757 466 7849",
    "sg:postcode":"23502",
    "sg:province":"VA",
    "wof:name":"Master's Touch Floral Designs",
    "wof:placetype":"venue"
},
  "geometry": {"coordinates":[-76.193659,36.861455],"type":"Point"}
}