{
  "type": "Feature",
  "properties": {
    "addr:full":"325 Pine Dr Amissville VA 20106",
    "addr:housenumber":"325",
    "addr:postcode":"20106",
    "addr:street":"Pine Dr",
    "iso:country":"US",
    "sg:address":"325 Pine Dr",
    "sg:city":"Amissville",
    "sg:classifiers":[
        {
            "category":"Building & Trades",
            "subcategory":"Construction",
            "type":"Services"
        }
    ],
    "sg:phone":"+1 540 937 5994",
    "sg:postcode":"20106",
    "sg:province":"VA",
    "sg:tags":[
        "water",
        "well",
        "drilling"
    ],
    "wof:name":"Aquaman Water Service Inc",
    "wof:placetype":"venue"
},
  "geometry": {"coordinates":[-78.007238,38.7162],"type":"Point"}
}