{
  "type": "Feature",
  "properties": {
    "addr:full":"2221 Willow Oak Cir Virginia Beach VA 23451",
    "addr:housenumber":"2221",
    "addr:postcode":"23451",
    "addr:street":"Willow Oak Cir",
    "iso:country":"US",
    "sg:address":"2221 Willow Oak Cir",
    "sg:city":"Virginia Beach",
    "sg:classifiers":[
        {
            "category":"Professional",
            "subcategory":"Secretarial Services",
            "type":"Services"
        }
    ],
    "sg:phone":"+1 757 581 9361",
    "sg:postcode":"23451",
    "sg:province":"VA",
    "sg:tags":[
        "reporting"
    ],
    "wof:name":"Wilson Danette Court Reporter",
    "wof:placetype":"venue"
},
  "geometry": {"coordinates":[-76.066064,36.909019],"type":"Point"}
}