{
  "type": "Feature",
  "properties": {
    "addr:full":"6450 Commonwealth Dr Roanoke VA 24018",
    "addr:housenumber":"6450",
    "addr:postcode":"24018",
    "addr:street":"Commonwealth Dr",
    "iso:country":"US",
    "sg:address":"6450 Commonwealth Dr",
    "sg:city":"Roanoke",
    "sg:classifiers":[
        {
            "category":"Building & Trades",
            "subcategory":"Construction",
            "type":"Services"
        }
    ],
    "sg:phone":"+1 540 774 4176",
    "sg:postcode":"24018",
    "sg:province":"VA",
    "sg:tags":[
        "masonry",
        "contractor"
    ],
    "wof:name":"Century Stone Inc",
    "wof:placetype":"venue"
},
  "geometry": {"coordinates":[-79.999135,37.20163],"type":"Point"}
}