{
  "type": "Feature",
  "properties": {
    "addr:full":"4536 Lee Hwy Arlington VA 22207",
    "addr:housenumber":"4536",
    "addr:postcode":"22207",
    "addr:street":"Lee Hwy",
    "iso:country":"US",
    "sg:address":"4536 Lee Hwy",
    "sg:city":"Arlington",
    "sg:classifiers":[
        {
            "category":"Coffee & Tea",
            "type":"Food & Drink"
        },
        {
            "category":"Restaurant",
            "type":"Food & Drink"
        },
        {
            "category":"Museum",
            "type":"Entertainment"
        }
    ],
    "sg:menulink":"http://www.allmenus.com/va/arlington/260217-cassatts/menu/",
    "sg:phone":"+1 703 527 3330",
    "sg:postcode":"22207",
    "sg:province":"VA",
    "sg:tags":[
        "tea",
        "coffee",
        "american"
    ],
    "wof:name":"Cassatt's",
    "wof:placetype":"venue"
},
  "geometry": {"coordinates":[-77.11917800000001,38.898423],"type":"Point"}
}