{
  "type": "Feature",
  "properties": {
    "iso:country":"US",
    "sg:address":"3601 Fairfax Dr",
    "sg:city":"Arlington",
    "sg:classifiers":[
        {
            "category":"Professional",
            "subcategory":"Accounting & Tax Preparation",
            "type":"Services"
        }
    ],
    "sg:phone":"+1 703 312 8648",
    "sg:postcode":"22201",
    "sg:province":"VA",
    "sg:tags":[
        "accountant"
    ],
    "wof:name":"Hanson Frank E CPA",
    "wof:placetype":"venue"
},
  "geometry": {"coordinates":[-77.10340100000001,38.8834],"type":"Point"}
}