{
  "type": "Feature",
  "properties": {
    "iso:country":"US",
    "sg:address":"18 Sarasota Dr",
    "sg:city":"Stafford",
    "sg:classifiers":[
        {
            "category":"Professional",
            "subcategory":"Computer Services",
            "type":"Services"
        }
    ],
    "sg:phone":"+1 540 720 8681",
    "sg:postcode":"22554",
    "sg:province":"VA",
    "sg:tags":[
        "network"
    ],
    "wof:name":"Watech Group Inc",
    "wof:placetype":"venue"
},
  "geometry": {"coordinates":[-77.43995099999999,38.462129],"type":"Point"}
}