{
  "type": "Feature",
  "properties": {
    "addr:full":"101 Beechwood Hills Dr Newport News VA 23608",
    "addr:housenumber":"101",
    "addr:postcode":"23608",
    "addr:street":"Beechwood Hills Dr",
    "iso:country":"US",
    "sg:address":"101 Beechwood Hills Dr",
    "sg:city":"Newport News",
    "sg:classifiers":[
        {
            "category":"Professional",
            "subcategory":"Business Services",
            "type":"Services"
        }
    ],
    "sg:phone":"+1 757 872 6693",
    "sg:postcode":"23608",
    "sg:province":"VA",
    "wof:name":"Johnise Custom Interiors",
    "wof:placetype":"venue"
},
  "geometry": {"coordinates":[-76.569619,37.136877],"type":"Point"}
}