{
  "type": "Feature",
  "properties": {
    "addr:full":"1000 Diamond St Petersburg VA 23803",
    "addr:housenumber":"1000",
    "addr:postcode":"23803",
    "addr:street":"Diamond St",
    "iso:country":"US",
    "sg:address":"1000 Diamond St",
    "sg:city":"Petersburg",
    "sg:classifiers":[
        {
            "category":"Organizations",
            "subcategory":"Community Association",
            "type":"Services"
        }
    ],
    "sg:phone":"+1 804 861 0046",
    "sg:postcode":"23803",
    "sg:province":"VA",
    "wof:name":"Virginia Cngress Prnts Tachers",
    "wof:placetype":"venue"
},
  "geometry": {"coordinates":[-77.40228399999999,37.213153],"type":"Point"}
}