{
  "type": "Feature",
  "properties": {
    "addr:full":"11517 Catalpa Ct Reston VA 20191",
    "addr:housenumber":"11517",
    "addr:postcode":"20191",
    "addr:street":"Catalpa Ct",
    "iso:country":"US",
    "sg:address":"11517 Catalpa Ct",
    "sg:city":"Reston",
    "sg:classifiers":[
        {
            "category":"Professional",
            "subcategory":"Computer Services",
            "type":"Services"
        }
    ],
    "sg:phone":"+1 703 620 4488",
    "sg:postcode":"20191",
    "sg:province":"VA",
    "sg:tags":[
        "prepackaged",
        "software"
    ],
    "wof:name":"Computer Presentation Systems",
    "wof:placetype":"venue"
},
  "geometry": {"coordinates":[-77.345254,38.923561],"type":"Point"}
}