{
  "type": "Feature",
  "properties": {
    "iso:country":"US",
    "sg:address":"5134 Leesburg Pike",
    "sg:city":"Alexandria",
    "sg:classifiers":[
        {
            "category":"Shopping",
            "subcategory":"Computers & Home Electronics",
            "type":"Retail Goods"
        }
    ],
    "sg:phone":"+1 703 820 9400",
    "sg:postcode":"22302",
    "sg:province":"VA",
    "sg:tags":[
        "publisher",
        "developer",
        "software"
    ],
    "wof:name":"Advanced Logistics Technology",
    "wof:placetype":"venue"
},
  "geometry": {"coordinates":[-77.11626,38.845505],"type":"Point"}
}