{
  "type": "Feature",
  "properties": {
    "addr:full":"2097 New Market Rd Richmond VA 23231",
    "addr:housenumber":"2097",
    "addr:postcode":"23231",
    "addr:street":"New Market Rd",
    "iso:country":"US",
    "sg:address":"2097 New Market Rd",
    "sg:city":"Richmond",
    "sg:classifiers":[
        {
            "category":"Restaurant",
            "type":"Food & Drink"
        }
    ],
    "sg:phone":"+1 804 795 4114",
    "sg:postcode":"23231",
    "sg:province":"VA",
    "sg:tags":[
        "eating"
    ],
    "wof:name":"Chillin & Grillin",
    "wof:placetype":"venue"
},
  "geometry": {"coordinates":[-77.37267199999999,37.455098],"type":"Point"}
}