{
  "type": "Feature",
  "properties": {
    "addr:full":"1444 Ballard Dr Crozet VA 22932",
    "addr:housenumber":"1444",
    "addr:postcode":"22932",
    "addr:street":"Ballard Dr",
    "iso:country":"US",
    "sg:address":"1444 Ballard Dr",
    "sg:city":"Crozet",
    "sg:classifiers":[
        {
            "category":"Organizations",
            "subcategory":"Religious Organization",
            "type":"Services"
        }
    ],
    "sg:phone":"+1 434 823 4135",
    "sg:postcode":"22932",
    "sg:province":"VA",
    "sg:tags":[
        "clergy"
    ],
    "wof:name":"Thomas D Maddrey",
    "wof:placetype":"venue"
},
  "geometry": {"coordinates":[-78.70134,38.077861],"type":"Point"}
}