{
  "type": "Feature",
  "properties": {
    "iso:country":"US",
    "sg:address":"5624 Chamberlayne Ave",
    "sg:city":"Richmond",
    "sg:classifiers":[
        {
            "category":"Building & Trades",
            "subcategory":"Cleaning & Sanitation",
            "type":"Services"
        }
    ],
    "sg:phone":"+1 804 553 4482",
    "sg:postcode":"23227",
    "sg:province":"VA",
    "sg:tags":[
        "maintenance"
    ],
    "wof:name":"Sparkling House Cleaning",
    "wof:placetype":"venue"
},
  "geometry": {"coordinates":[-77.455129,37.621446],"type":"Point"}
}