{
  "type": "Feature",
  "properties": {
    "addr:full":"3660 Colonial Ave Roanoke VA 24018",
    "addr:housenumber":"3660",
    "addr:postcode":"24018",
    "addr:street":"Colonial Ave",
    "iso:country":"US",
    "sg:address":"3660 Colonial Ave",
    "sg:city":"Roanoke",
    "sg:classifiers":[
        {
            "category":"Autos & Motor Vehicles",
            "subcategory":"Fuel & Gas Station",
            "type":"Retail Goods"
        }
    ],
    "sg:phone":"+1 540 774 1664",
    "sg:postcode":"24018",
    "sg:province":"VA",
    "sg:tags":[
        "station",
        "gasoline"
    ],
    "wof:name":"Super Mart",
    "wof:placetype":"venue"
},
  "geometry": {"coordinates":[-79.994737,37.230447],"type":"Point"}
}