{
  "type": "Feature",
  "properties": {
    "addr:full":"7203 Three Chopt Rd Richmond VA 23226",
    "addr:housenumber":"7203",
    "addr:postcode":"23226",
    "addr:street":"Three Chopt Rd",
    "iso:country":"US",
    "sg:address":"7203 Three Chopt Rd",
    "sg:city":"Richmond",
    "sg:classifiers":[
        {
            "category":"Real Estate",
            "subcategory":"Real Estate Agent",
            "type":"Services"
        }
    ],
    "sg:phone":"+1 804 285 4157",
    "sg:postcode":"23226",
    "sg:province":"VA",
    "wof:name":"First Washington Realty",
    "wof:placetype":"venue"
},
  "geometry": {"coordinates":[-77.53188400000001,37.593938],"type":"Point"}
}