{
  "type": "Feature",
  "properties": {
    "iso:country":"US",
    "sg:address":"6000 W Run Rd",
    "sg:city":"Charles City",
    "sg:classifiers":[
        {
            "category":"Organizations",
            "subcategory":"Community Association",
            "type":"Services"
        }
    ],
    "sg:phone":"+1 804 829 5440",
    "sg:postcode":"23030",
    "sg:province":"VA",
    "sg:tags":[
        "club"
    ],
    "wof:name":"Buck Hill Hunt Club",
    "wof:placetype":"venue"
},
  "geometry": {"coordinates":[-77.159111,37.357441],"type":"Point"}
}