{
  "type": "Feature",
  "properties": {
    "addr:full":"2800 S Fort Scott Dr Arlington VA 22202",
    "addr:housenumber":"2800",
    "addr:postcode":"22202",
    "addr:street":"S Fort Scott Dr",
    "iso:country":"US",
    "sg:address":"2800 S Fort Scott Dr",
    "sg:city":"Arlington",
    "sg:classifiers":[
        {
            "category":"Park",
            "type":"Public Place"
        }
    ],
    "sg:postcode":"22202",
    "sg:province":"VA",
    "sg:website":"www.co.arlington.va.us/Departmen...",
    "wof:name":"Fort Scott Park",
    "wof:placetype":"venue"
},
  "geometry": {"coordinates":[-77.058606,38.84737],"type":"Point"}
}