{
  "type": "Feature",
  "properties": {
    "addr:full":"3534 Carlin Springs Rd Ste 1 Falls Church VA 22041",
    "addr:housenumber":"3534",
    "addr:postcode":"22041",
    "addr:street":"Carlin Springs Rd Ste 1",
    "iso:country":"US",
    "sg:address":"3534 Carlin Springs Rd Ste 1",
    "sg:city":"Falls Church",
    "sg:classifiers":[
        {
            "category":"Shopping",
            "subcategory":"Books",
            "type":"Retail Goods"
        }
    ],
    "sg:phone":"+1 703 671 2980",
    "sg:postcode":"22041",
    "sg:province":"VA",
    "sg:tags":[
        "bookstore"
    ],
    "sg:website":"www.rinconcristiano.com",
    "wof:name":"Rincon Cristiano Christian Book Store",
    "wof:placetype":"venue"
},
  "geometry": {"coordinates":[-77.1241,38.8493],"type":"Point"}
}