{
  "type": "Feature",
  "properties": {
    "addr:full":"910 Aberdeen Rd Hampton VA 23666",
    "addr:housenumber":"910",
    "addr:postcode":"23666",
    "addr:street":"Aberdeen Rd",
    "iso:country":"US",
    "sg:address":"910 Aberdeen Rd",
    "sg:city":"Hampton",
    "sg:classifiers":[
        {
            "category":"Shopping",
            "subcategory":"Discount & Variety Stores",
            "type":"Retail Goods"
        }
    ],
    "sg:phone":"+1 757 262 0396",
    "sg:postcode":"23666",
    "sg:province":"VA",
    "wof:name":"Family Dollar Stores",
    "wof:placetype":"venue"
},
  "geometry": {"coordinates":[-76.404048,37.020547],"type":"Point"}
}