{
  "type": "Feature",
  "properties": {
    "addr:full":"2605 Torquay Loop Richmond VA 23236",
    "addr:housenumber":"2605",
    "addr:postcode":"23236",
    "addr:street":"Torquay Loop",
    "iso:country":"US",
    "sg:address":"2605 Torquay Loop",
    "sg:city":"Richmond",
    "sg:classifiers":[
        {
            "category":"Insurance",
            "subcategory":"Insurance Agent",
            "type":"Services"
        }
    ],
    "sg:phone":"+1 804 745 6606",
    "sg:postcode":"23236",
    "sg:province":"VA",
    "wof:name":"Insurance Intelligence Inc",
    "wof:placetype":"venue"
},
  "geometry": {"coordinates":[-77.557118,37.458603],"type":"Point"}
}