{
  "type": "Feature",
  "properties": {
    "iso:country":"US",
    "sg:address":"42 Carrollton Rd",
    "sg:city":"Sterling",
    "sg:classifiers":[
        {
            "category":"Real Estate",
            "subcategory":"Real Estate Agent",
            "type":"Services"
        }
    ],
    "sg:phone":"+1 703 450 7440",
    "sg:postcode":"20165",
    "sg:province":"VA",
    "sg:tags":[
        "management"
    ],
    "wof:name":"Real Estate Network",
    "wof:placetype":"venue"
},
  "geometry": {"coordinates":[-77.407381,39.049568],"type":"Point"}
}