{
  "type": "Feature",
  "properties": {
    "iso:country":"US",
    "sg:address":"2313 Homeview Dr",
    "sg:city":"Richmond",
    "sg:classifiers":[
        {
            "category":"Building & Trades",
            "subcategory":"Construction",
            "type":"Services"
        }
    ],
    "sg:phone":"+1 804 346 0255",
    "sg:postcode":"23294",
    "sg:province":"VA",
    "sg:tags":[
        "house"
    ],
    "wof:name":"Taylor Made Homes Inc",
    "wof:placetype":"venue"
},
  "geometry": {"coordinates":[-77.54484100000001,37.631053],"type":"Point"}
}