{
  "type": "Feature",
  "properties": {
    "addr:full":"2906 Putney Rd Richmond VA 23228",
    "addr:housenumber":"2906",
    "addr:postcode":"23228",
    "addr:street":"Putney Rd",
    "iso:country":"US",
    "sg:address":"2906 Putney Rd",
    "sg:city":"Richmond",
    "sg:classifiers":[
        {
            "category":"Building & Trades",
            "subcategory":"Cleaning & Sanitation",
            "type":"Services"
        }
    ],
    "sg:phone":"+1 804 304 9452",
    "sg:postcode":"23228",
    "sg:province":"VA",
    "sg:tags":[
        "commercial"
    ],
    "wof:name":"Presto Janitorial Service",
    "wof:placetype":"venue"
},
  "geometry": {"coordinates":[-77.48960599999999,37.612323],"type":"Point"}
}