{
  "type": "Feature",
  "properties": {
    "addr:full":"1930 Isaac Newton Sq W Reston VA 20190",
    "addr:housenumber":"1930",
    "addr:postcode":"20190",
    "addr:street":"Isaac Newton Sq W",
    "iso:country":"US",
    "sg:address":"1930 Isaac Newton Sq W",
    "sg:city":"Reston",
    "sg:classifiers":[
        {
            "category":"Professional",
            "subcategory":"Management & Consulting",
            "type":"Services"
        }
    ],
    "sg:phone":"+1 703 773 1290",
    "sg:postcode":"20190",
    "sg:province":"VA",
    "sg:tags":[
        "business"
    ],
    "wof:name":"Lanpherwilson Corp",
    "wof:placetype":"venue"
},
  "geometry": {"coordinates":[-77.338989,38.953186],"type":"Point"}
}