{
  "type": "Feature",
  "properties": {
    "addr:full":"1607 E Main St Salem VA 24153",
    "addr:housenumber":"1607",
    "addr:postcode":"24153",
    "addr:street":"E Main St",
    "iso:country":"US",
    "sg:address":"1607 E Main St",
    "sg:city":"Salem",
    "sg:classifiers":[
        {
            "category":"Food & Beverages",
            "subcategory":"Groceries & Convenience Stores",
            "type":"Retail Goods"
        }
    ],
    "sg:phone":"+1 540 986 3077",
    "sg:postcode":"24153",
    "sg:province":"VA",
    "wof:name":"Sparkys",
    "wof:placetype":"venue"
},
  "geometry": {"coordinates":[-80.027074,37.298409],"type":"Point"}
}