{
  "type": "Feature",
  "properties": {
    "iso:country":"US",
    "sg:address":"118 Auburn St",
    "sg:city":"Bristol",
    "sg:classifiers":[
        {
            "category":"Retail",
            "subcategory":"Repair Shop",
            "type":"Services"
        },
        {
            "category":"Wholesale",
            "subcategory":"Electrical",
            "type":"Manufacturing & Wholesale Goods"
        }
    ],
    "sg:phone":"+1 423 878 6100",
    "sg:postcode":"37620",
    "sg:province":"VA",
    "sg:tags":[
        "appliance"
    ],
    "wof:name":"Quality Appliance Svc & Repair",
    "wof:placetype":"venue"
},
  "geometry": {"coordinates":[-82.180764,36.579875],"type":"Point"}
}