{
  "type": "Feature",
  "properties": {
    "addr:full":"4476 Hickory Fork Rd Gloucester VA 23061",
    "addr:housenumber":"4476",
    "addr:postcode":"23061",
    "addr:street":"Hickory Fork Rd",
    "iso:country":"US",
    "sg:address":"4476 Hickory Fork Rd",
    "sg:city":"Gloucester",
    "sg:classifiers":[
        {
            "category":"Building & Trades",
            "subcategory":"Construction",
            "type":"Services"
        }
    ],
    "sg:phone":"+1 804 693 7141",
    "sg:postcode":"23061",
    "sg:province":"VA",
    "sg:tags":[
        "contractor"
    ],
    "wof:name":"Hawk Tile",
    "wof:placetype":"venue"
},
  "geometry": {"coordinates":[-76.59475999999999,37.391587],"type":"Point"}
}