{
  "type": "Feature",
  "properties": {
    "addr:full":"431 Messick Rd Poquoson VA 23662",
    "addr:housenumber":"431",
    "addr:postcode":"23662",
    "addr:street":"Messick Rd",
    "iso:country":"US",
    "sg:address":"431 Messick Rd",
    "sg:city":"Poquoson",
    "sg:classifiers":[
        {
            "category":"Manufacturing",
            "subcategory":"Food",
            "type":"Manufacturing & Wholesale Goods"
        },
        {
            "category":"Wholesale",
            "subcategory":"Seafood",
            "type":"Manufacturing & Wholesale Goods"
        }
    ],
    "sg:phone":"+1 757 868 6748",
    "sg:postcode":"23662",
    "sg:province":"VA",
    "sg:tags":[
        "product",
        "mfg",
        "fish",
        "prepared"
    ],
    "wof:name":"W Haywood Forrest Seafood Co",
    "wof:placetype":"venue"
},
  "geometry": {"coordinates":[-76.32228499999999,37.110774],"type":"Point"}
}