{
  "type": "Feature",
  "properties": {
    "iso:country":"US",
    "sg:address":"502 Winona Dr N",
    "sg:city":"Hampton",
    "sg:classifiers":[
        {
            "category":"Professional",
            "type":"Services"
        }
    ],
    "sg:phone":"+1 757 723 5945",
    "sg:postcode":"23661",
    "sg:province":"VA",
    "wof:name":"Jesse L Alston",
    "wof:placetype":"venue"
},
  "geometry": {"coordinates":[-76.379453,37.008963],"type":"Point"}
}