{
  "type": "Feature",
  "properties": {
    "iso:country":"US",
    "sg:address":"2156 Shipyard Rd",
    "sg:city":"Chesapeake",
    "sg:classifiers":[
        {
            "category":"Real Estate",
            "subcategory":"Real Estate Operator",
            "type":"Services"
        }
    ],
    "sg:phone":"+1 757 487 7283",
    "sg:postcode":"23323",
    "sg:province":"VA",
    "sg:tags":[
        "building",
        "nonresidential"
    ],
    "wof:name":"Ames Property Development",
    "wof:placetype":"venue"
},
  "geometry": {"coordinates":[-76.322954,36.744242],"type":"Point"}
}