{
  "type": "Feature",
  "properties": {
    "addr:full":"325 E Church St Martinsville VA 24112",
    "addr:housenumber":"325",
    "addr:postcode":"24112",
    "addr:street":"E Church St",
    "iso:country":"US",
    "sg:address":"325 E Church St",
    "sg:city":"Martinsville",
    "sg:classifiers":[
        {
            "category":"Health Services",
            "subcategory":"Hospital",
            "type":"Services"
        },
        {
            "category":"Health Services",
            "subcategory":"Clinic",
            "type":"Services"
        }
    ],
    "sg:phone":"+1 276 666 2605",
    "sg:postcode":"24112",
    "sg:province":"VA",
    "sg:tags":[
        "mental"
    ],
    "wof:name":"Blue Ridge Wellness Center",
    "wof:placetype":"venue"
},
  "geometry": {"coordinates":[-79.865854,36.688992],"type":"Point"}
}