{
  "type": "Feature",
  "properties": {
    "iso:country":"US",
    "sg:address":"2600 Roswell Ct",
    "sg:city":"Falls Church",
    "sg:classifiers":[
        {
            "category":"Travel",
            "subcategory":"Hotels & Motels",
            "type":"Entertainment"
        }
    ],
    "sg:phone":"+1 703 560 1812",
    "sg:postcode":"22043",
    "sg:province":"VA",
    "wof:name":"Regal Hotels Intl",
    "wof:placetype":"venue"
},
  "geometry": {"coordinates":[-77.216638,38.884982],"type":"Point"}
}