{
  "type": "Feature",
  "properties": {
    "iso:country":"US",
    "sg:address":"221 N Main St",
    "sg:city":"Bowling Green",
    "sg:classifiers":[
        {
            "category":"Real Estate",
            "subcategory":"Real Estate Agent",
            "type":"Services"
        }
    ],
    "sg:phone":"+1 804 633 0432",
    "sg:postcode":"22427",
    "sg:province":"VA",
    "sg:tags":[
        "appraiser"
    ],
    "wof:name":"Ellis Appraisals LLC",
    "wof:placetype":"venue"
},
  "geometry": {"coordinates":[-77.348328,38.053104],"type":"Point"}
}