{
  "type": "Feature",
  "properties": {
    "iso:country":"US",
    "sg:address":"4804 Mallard Cres",
    "sg:city":"Portsmouth",
    "sg:classifiers":[
        {
            "category":"Social Services",
            "subcategory":"Job Training",
            "type":"Services"
        }
    ],
    "sg:phone":"+1 757 484 2056",
    "sg:postcode":"23703",
    "sg:province":"VA",
    "wof:name":"Wood Carving Unlimited",
    "wof:placetype":"venue"
},
  "geometry": {"coordinates":[-76.366118,36.863828],"type":"Point"}
}