{
  "type": "Feature",
  "properties": {
    "iso:country":"US",
    "sg:address":"34 Charlene Loop",
    "sg:city":"Hampton",
    "sg:classifiers":[
        {
            "category":"Real Estate",
            "subcategory":"Developer",
            "type":"Services"
        }
    ],
    "sg:phone":"+1 757 827 7700",
    "sg:postcode":"23666",
    "sg:province":"VA",
    "wof:name":"Nds Development Company LLC",
    "wof:placetype":"venue"
},
  "geometry": {"coordinates":[-76.414187,37.052439],"type":"Point"}
}