{
  "type": "Feature",
  "properties": {
    "iso:country":"US",
    "sg:address":"27 Autumn E",
    "sg:city":"Williamsburg",
    "sg:classifiers":[
        {
            "category":"Wholesale",
            "subcategory":"Apparel",
            "type":"Manufacturing & Wholesale Goods"
        }
    ],
    "sg:phone":"+1 757 345 2425",
    "sg:postcode":"23188",
    "sg:province":"VA",
    "sg:tags":[
        "baby",
        "product"
    ],
    "sg:website":"www.buybabybanz.com",
    "wof:name":"BUYBABYBANZ.COM",
    "wof:placetype":"venue"
},
  "geometry": {"coordinates":[-76.761366,37.317769],"type":"Point"}
}