{
  "type": "Feature",
  "properties": {
    "addr:full":"4915 Caskie St Richmond VA 23230",
    "addr:housenumber":"4915",
    "addr:postcode":"23230",
    "addr:street":"Caskie St",
    "iso:country":"US",
    "sg:address":"4915 Caskie St",
    "sg:city":"Richmond",
    "sg:classifiers":[
        {
            "category":"Personal",
            "subcategory":"Beauty Salon",
            "type":"Services"
        }
    ],
    "sg:phone":"+1 804 355 6363",
    "sg:postcode":"23230",
    "sg:province":"VA",
    "sg:tags":[
        "shop"
    ],
    "wof:name":"Pamper Me Salon",
    "wof:placetype":"venue"
},
  "geometry": {"coordinates":[-77.495265,37.581754],"type":"Point"}
}