{
  "type": "Feature",
  "properties": {
    "iso:country":"US",
    "sg:address":"17767 Dull Hunt Rd",
    "sg:city":"Fulks Run",
    "sg:classifiers":[
        {
            "category":"Farming",
            "subcategory":"Farm",
            "type":"Manufacturing & Wholesale Goods"
        }
    ],
    "sg:phone":"+1 540 896 2056",
    "sg:postcode":"22830",
    "sg:province":"VA",
    "sg:tags":[
        "excavation",
        "general",
        "crop",
        "contractor"
    ],
    "wof:name":"John Henry Ritchie",
    "wof:placetype":"venue"
},
  "geometry": {"coordinates":[-78.99484699999999,38.652177],"type":"Point"}
}