{
  "type": "Feature",
  "properties": {
    "addr:full":"1601 Willow Lawn Dr Richmond VA 23230",
    "addr:housenumber":"1601",
    "addr:postcode":"23230",
    "addr:street":"Willow Lawn Dr",
    "iso:country":"US",
    "sg:address":"1601 Willow Lawn Dr",
    "sg:city":"Richmond",
    "sg:classifiers":[
        {
            "category":"Utilities",
            "subcategory":"Mobile Phone",
            "type":"Services"
        }
    ],
    "sg:phone":"+1 804 673 8847",
    "sg:postcode":"23230",
    "sg:province":"VA",
    "sg:tags":[
        "communication",
        "radiotelephone"
    ],
    "wof:name":"Verizon",
    "wof:placetype":"venue"
},
  "geometry": {"coordinates":[-77.498177,37.583144],"type":"Point"}
}