{
  "type": "Feature",
  "properties": {
    "iso:country":"US",
    "sg:address":"404 N Main St",
    "sg:city":"Chase City",
    "sg:classifiers":[
        {
            "category":"Professional",
            "subcategory":"Employment Agencies",
            "type":"Services"
        }
    ],
    "sg:phone":"+1 434 372 5760",
    "sg:postcode":"23924",
    "sg:province":"VA",
    "sg:tags":[
        "equipment",
        "help",
        "supply"
    ],
    "wof:name":"Atlantic Medical Inc",
    "wof:placetype":"venue"
},
  "geometry": {"coordinates":[-78.459569,36.801141],"type":"Point"}
}