{
  "type": "Feature",
  "properties": {
    "iso:country":"US",
    "sg:address":"8952 Richmond Rd",
    "sg:city":"Williamsburg",
    "sg:classifiers":[
        {
            "category":"Retail",
            "subcategory":"Auto Repair",
            "type":"Services"
        }
    ],
    "sg:phone":"+1 757 249 0000",
    "sg:postcode":"23168",
    "sg:province":"VA",
    "sg:tags":[
        "repairing",
        "automobile"
    ],
    "wof:name":"Jeep Newport News",
    "wof:placetype":"venue"
},
  "geometry": {"coordinates":[-76.84661699999999,37.404872],"type":"Point"}
}