{
  "type": "Feature",
  "properties": {
    "iso:country":"US",
    "sg:address":"480 Kelley St",
    "sg:city":"Harrisonburg",
    "sg:classifiers":[
        {
            "category":"Freight",
            "type":"Transportation"
        }
    ],
    "sg:phone":"+1 540 574 3348",
    "sg:postcode":"22802",
    "sg:province":"VA",
    "sg:tags":[
        "operator",
        "local",
        "trucking"
    ],
    "wof:name":"Radolfo Valdez Trucking",
    "wof:placetype":"venue"
},
  "geometry": {"coordinates":[-78.853464,38.452915],"type":"Point"}
}