{
  "type": "Feature",
  "properties": {
    "addr:full":"104 Vermont Ave Lynchburg VA 24502",
    "addr:housenumber":"104",
    "addr:postcode":"24502",
    "addr:street":"Vermont Ave",
    "iso:country":"US",
    "sg:address":"104 Vermont Ave",
    "sg:city":"Lynchburg",
    "sg:classifiers":[
        {
            "category":"Professional",
            "subcategory":"Business Services",
            "type":"Services"
        }
    ],
    "sg:phone":"+1 434 528 9676",
    "sg:postcode":"24502",
    "sg:province":"VA",
    "wof:name":"Bga Enterprises Inc",
    "wof:placetype":"venue"
},
  "geometry": {"coordinates":[-79.173693,37.389847],"type":"Point"}
}