{
  "type": "Feature",
  "properties": {
    "iso:country":"US",
    "sg:address":"239 Mill St NE",
    "sg:city":"Vienna",
    "sg:classifiers":[
        {
            "category":"Professional",
            "subcategory":"Computer Services",
            "type":"Services"
        }
    ],
    "sg:phone":"+1 703 281 6780",
    "sg:postcode":"22180",
    "sg:province":"VA",
    "sg:tags":[
        "added",
        "compute",
        "integrator",
        "system",
        "value",
        "custom"
    ],
    "wof:name":"Friendly Computer Services",
    "wof:placetype":"venue"
},
  "geometry": {"coordinates":[-77.265911,38.904571],"type":"Point"}
}