{
  "type": "Feature",
  "properties": {
    "iso:country":"US",
    "sg:address":"925 Canal Dr",
    "sg:city":"Chesapeake",
    "sg:classifiers":[
        {
            "category":"Professional",
            "subcategory":"Management & Consulting",
            "type":"Services"
        }
    ],
    "sg:phone":"+1 757 485 9950",
    "sg:postcode":"23323",
    "sg:province":"VA",
    "sg:tags":[
        "consultant",
        "training"
    ],
    "wof:name":"Philadelphia Church-Christ",
    "wof:placetype":"venue"
},
  "geometry": {"coordinates":[-76.32543800000001,36.776253],"type":"Point"}
}