{
  "type": "Feature",
  "properties": {
    "addr:full":"1008 Churchville Ave Staunton VA 24401",
    "addr:housenumber":"1008",
    "addr:postcode":"24401",
    "addr:street":"Churchville Ave",
    "iso:country":"US",
    "sg:address":"1008 Churchville Ave",
    "sg:city":"Staunton",
    "sg:classifiers":[
        {
            "category":"Restaurant",
            "type":"Food & Drink"
        }
    ],
    "sg:phone":"+1 540 886 8626",
    "sg:postcode":"24401",
    "sg:province":"VA",
    "sg:tags":[
        "parlor",
        "eating",
        "ice",
        "cream"
    ],
    "wof:name":"Tastee-Freez",
    "wof:placetype":"venue"
},
  "geometry": {"coordinates":[-79.08736399999999,38.165174],"type":"Point"}
}