{
  "type": "Feature",
  "properties": {
    "addr:full":"2680 Greenway Rd Suffolk VA 23438",
    "addr:housenumber":"2680",
    "addr:postcode":"23438",
    "addr:street":"Greenway Rd",
    "iso:country":"US",
    "sg:address":"2680 Greenway Rd",
    "sg:city":"Suffolk",
    "sg:classifiers":[
        {
            "category":"Real Estate",
            "subcategory":"Real Estate Operator",
            "type":"Services"
        }
    ],
    "sg:phone":"+1 757 986 4960",
    "sg:postcode":"23438",
    "sg:province":"VA",
    "sg:tags":[
        "property",
        "lessor"
    ],
    "wof:name":"David Baines",
    "wof:placetype":"venue"
},
  "geometry": {"coordinates":[-76.63169499999999,36.569897],"type":"Point"}
}