{
  "type": "Feature",
  "properties": {
    "addr:full":"14633 Jefferson Davis Hwy Woodbridge VA 22191",
    "addr:housenumber":"14633",
    "addr:postcode":"22191",
    "addr:street":"Jefferson Davis Hwy",
    "iso:country":"US",
    "sg:address":"14633 Jefferson Davis Hwy",
    "sg:city":"Woodbridge",
    "sg:classifiers":[
        {
            "category":"Restaurant",
            "type":"Food & Drink"
        }
    ],
    "sg:phone":"+1 703 494 4800",
    "sg:postcode":"22191",
    "sg:province":"VA",
    "wof:name":"Kilroy's Restaurant",
    "wof:placetype":"venue"
},
  "geometry": {"coordinates":[-77.27127900000001,38.634146],"type":"Point"}
}