{
  "type": "Feature",
  "properties": {
    "addr:full":"813 Windom Pl Virginia Beach VA 23454",
    "addr:housenumber":"813",
    "addr:postcode":"23454",
    "addr:street":"Windom Pl",
    "iso:country":"US",
    "sg:address":"813 Windom Pl",
    "sg:city":"Virginia Beach",
    "sg:classifiers":[
        {
            "category":"Sports & Exercise",
            "subcategory":"Gym",
            "type":"Entertainment"
        }
    ],
    "sg:phone":"+1 757 340 7339",
    "sg:postcode":"23454",
    "sg:province":"VA",
    "sg:tags":[
        "fitness",
        "physical",
        "facility"
    ],
    "wof:name":"Tops Club Inc",
    "wof:placetype":"venue"
},
  "geometry": {"coordinates":[-76.04447500000001,36.852987],"type":"Point"}
}