{
  "type": "Feature",
  "properties": {
    "addr:full":"2374 Plank Rd Fredericksburg VA 22401",
    "addr:housenumber":"2374",
    "addr:postcode":"22401",
    "addr:street":"Plank Rd",
    "iso:country":"US",
    "sg:address":"2374 Plank Rd",
    "sg:city":"Fredericksburg",
    "sg:classifiers":[
        {
            "category":"Manufacturing",
            "subcategory":"Signs",
            "type":"Manufacturing & Wholesale Goods"
        }
    ],
    "sg:phone":"+1 540 370 1705",
    "sg:postcode":"22401",
    "sg:province":"VA",
    "sg:tags":[
        "specialty",
        "mfg"
    ],
    "wof:name":"Sign Graphx Printing & Spc",
    "wof:placetype":"venue"
},
  "geometry": {"coordinates":[-77.499576,38.296221],"type":"Point"}
}