{
  "type": "Feature",
  "properties": {
    "addr:full":"3136 Carolina Rd Suffolk VA 23434",
    "addr:housenumber":"3136",
    "addr:postcode":"23434",
    "addr:street":"Carolina Rd",
    "iso:country":"US",
    "sg:address":"3136 Carolina Rd",
    "sg:city":"Suffolk",
    "sg:classifiers":[
        {
            "category":"Bus Charters",
            "type":"Transportation"
        }
    ],
    "sg:phone":"+1 757 539 4398",
    "sg:postcode":"23434",
    "sg:province":"VA",
    "wof:name":"Taylor Bus Service Inc",
    "wof:placetype":"venue"
},
  "geometry": {"coordinates":[-76.607561,36.632214],"type":"Point"}
}