{
  "type": "Feature",
  "properties": {
    "addr:full":"109 Covey Rd Sandston VA 23150",
    "addr:housenumber":"109",
    "addr:postcode":"23150",
    "addr:street":"Covey Rd",
    "iso:country":"US",
    "sg:address":"109 Covey Rd",
    "sg:city":"Sandston",
    "sg:classifiers":[
        {
            "category":"Retail",
            "subcategory":"Repair Shop",
            "type":"Services"
        }
    ],
    "sg:phone":"+1 804 328 0851",
    "sg:postcode":"23150",
    "sg:province":"VA",
    "sg:tags":[
        "sporting"
    ],
    "wof:name":"Waynes Gun Shop",
    "wof:placetype":"venue"
},
  "geometry": {"coordinates":[-77.230909,37.50723],"type":"Point"}
}