{
  "type": "Feature",
  "properties": {
    "iso:country":"US",
    "sg:address":"409 E Main St",
    "sg:city":"Radford",
    "sg:classifiers":[
        {
            "category":"Professional",
            "subcategory":"Engineering",
            "type":"Services"
        }
    ],
    "sg:phone":"+1 540 731 8360",
    "sg:postcode":"24141",
    "sg:province":"VA",
    "sg:tags":[
        "consulting"
    ],
    "wof:name":"Ground Vibration Consultants",
    "wof:placetype":"venue"
},
  "geometry": {"coordinates":[-80.54243099999999,37.135889],"type":"Point"}
}