{
  "type": "Feature",
  "properties": {
    "iso:country":"US",
    "sg:address":"11650 W Broad St",
    "sg:city":"Richmond",
    "sg:classifiers":[
        {
            "category":"Cinema",
            "subcategory":"Movie Theater",
            "type":"Entertainment"
        }
    ],
    "sg:phone":"+1 804 360 0947",
    "sg:postcode":"23233",
    "sg:province":"VA",
    "sg:tags":[
        "motion",
        "picture"
    ],
    "wof:name":"Regal Cinemas Inc",
    "wof:placetype":"venue"
},
  "geometry": {"coordinates":[-77.61694300000001,37.65225],"type":"Point"}
}