{
  "type": "Feature",
  "properties": {
    "addr:full":"6401 Courthouse Rd Prince George VA 23875",
    "addr:housenumber":"6401",
    "addr:postcode":"23875",
    "addr:street":"Courthouse Rd",
    "iso:country":"US",
    "sg:address":"6401 Courthouse Rd",
    "sg:city":"Prince George",
    "sg:classifiers":[
        {
            "category":"Banks & Credit Unions",
            "subcategory":"Bank",
            "type":"Services"
        }
    ],
    "sg:phone":"+1 804 732 2706",
    "sg:postcode":"23875",
    "sg:province":"VA",
    "wof:name":"Bank Of Southside Virginia",
    "wof:placetype":"venue"
},
  "geometry": {"coordinates":[-77.290083,37.221007],"type":"Point"}
}