{
  "type": "Feature",
  "properties": {
    "iso:country":"US",
    "sg:address":"8117 Leesburg Pike",
    "sg:city":"Vienna",
    "sg:classifiers":[
        {
            "category":"Retail",
            "subcategory":"Repair Shop",
            "type":"Services"
        }
    ],
    "sg:phone":"+1 703 842 5736",
    "sg:postcode":"22182",
    "sg:province":"VA",
    "sg:tags":[
        "lock",
        "locksmith"
    ],
    "wof:name":"1 All Day Emergency",
    "wof:placetype":"venue"
},
  "geometry": {"coordinates":[-77.225745,38.91474],"type":"Point"}
}