{
  "type": "Feature",
  "properties": {
    "addr:full":"6905 Custis Pkwy Falls Church VA 22042",
    "addr:housenumber":"6905",
    "addr:postcode":"22042",
    "addr:street":"Custis Pkwy",
    "iso:country":"US",
    "sg:address":"6905 Custis Pkwy",
    "sg:city":"Falls Church",
    "sg:classifiers":[
        {
            "category":"Professional",
            "type":"Services"
        }
    ],
    "sg:phone":"+1 703 536 0332",
    "sg:postcode":"22042",
    "sg:province":"VA",
    "wof:name":"Sally Kerner",
    "wof:placetype":"venue"
},
  "geometry": {"coordinates":[-77.182541,38.87402],"type":"Point"}
}