{
  "type": "Feature",
  "properties": {
    "addr:full":"1694 Old Buckroe Rd Hampton VA 23664",
    "addr:housenumber":"1694",
    "addr:postcode":"23664",
    "addr:street":"Old Buckroe Rd",
    "iso:country":"US",
    "sg:address":"1694 Old Buckroe Rd",
    "sg:city":"Hampton",
    "sg:classifiers":[
        {
            "category":"Building & Trades",
            "subcategory":"Construction",
            "type":"Services"
        }
    ],
    "sg:phone":"+1 757 851 2544",
    "sg:postcode":"23664",
    "sg:province":"VA",
    "sg:tags":[
        "concrete",
        "contractor"
    ],
    "wof:name":"Wesley A Ashe",
    "wof:placetype":"venue"
},
  "geometry": {"coordinates":[-76.299632,37.048485],"type":"Point"}
}