{
  "type": "Feature",
  "properties": {
    "iso:country":"US",
    "sg:address":"15819 Thomas Nelson Hwy",
    "sg:city":"Lovingston",
    "sg:classifiers":[
        {
            "category":"Shopping",
            "subcategory":"Used Merchandise",
            "type":"Retail Goods"
        }
    ],
    "sg:phone":"+1 434 263 6604",
    "sg:postcode":"22949",
    "sg:province":"VA",
    "wof:name":"J & M Collectibles",
    "wof:placetype":"venue"
},
  "geometry": {"coordinates":[-78.824432,37.843787],"type":"Point"}
}