{
  "type": "Feature",
  "properties": {
    "addr:full":"11084 Sweetbrier Ln Remington VA 22734",
    "addr:housenumber":"11084",
    "addr:postcode":"22734",
    "addr:street":"Sweetbrier Ln",
    "iso:country":"US",
    "sg:address":"11084 Sweetbrier Ln",
    "sg:city":"Remington",
    "sg:classifiers":[
        {
            "category":"Farming",
            "subcategory":"Dairy Farm",
            "type":"Manufacturing & Wholesale Goods"
        }
    ],
    "sg:phone":"+1 540 439 2309",
    "sg:postcode":"22734",
    "sg:province":"VA",
    "wof:name":"Chester Beahm",
    "wof:placetype":"venue"
},
  "geometry": {"coordinates":[-77.85609599999999,38.573735],"type":"Point"}
}