{
  "type": "Feature",
  "properties": {
    "iso:country":"US",
    "sg:address":"5285 Providence Rd",
    "sg:city":"Virginia Beach",
    "sg:classifiers":[
        {
            "category":"Autos & Motor Vehicles",
            "subcategory":"Fuel & Gas Station",
            "type":"Retail Goods"
        }
    ],
    "sg:phone":"+1 757 495 0978",
    "sg:postcode":"23464",
    "sg:province":"VA",
    "sg:tags":[
        "oil"
    ],
    "wof:name":"Fairfield Amoco",
    "wof:placetype":"venue"
},
  "geometry": {"coordinates":[-76.170231,36.814112],"type":"Point"}
}