{
  "type": "Feature",
  "properties": {
    "iso:country":"US",
    "sg:address":"504 Mountain Stone Way",
    "sg:city":"Chesapeake",
    "sg:classifiers":[
        {
            "category":"Professional",
            "subcategory":"Management & Consulting",
            "type":"Services"
        }
    ],
    "sg:phone":"+1 757 548 8225",
    "sg:postcode":"23320",
    "sg:province":"VA",
    "sg:tags":[
        "business"
    ],
    "wof:name":"Educational Trainers Plus",
    "wof:placetype":"venue"
},
  "geometry": {"coordinates":[-76.23002,36.740763],"type":"Point"}
}