{
  "type": "Feature",
  "properties": {
    "iso:country":"US",
    "sg:address":"2629 Valley Ave",
    "sg:city":"Winchester",
    "sg:classifiers":[
        {
            "category":"Retail",
            "subcategory":"Auto Repair",
            "type":"Services"
        }
    ],
    "sg:phone":"+1 540 662 7244",
    "sg:postcode":"22601",
    "sg:province":"VA",
    "sg:tags":[
        "transmission"
    ],
    "wof:name":"Cottman Transmission Ctr",
    "wof:placetype":"venue"
},
  "geometry": {"coordinates":[-78.18662999999999,39.156069],"type":"Point"}
}