{
  "type": "Feature",
  "properties": {
    "addr:full":"11725 Bristow Rd Bristow VA 20136",
    "addr:housenumber":"11725",
    "addr:postcode":"20136",
    "addr:street":"Bristow Rd",
    "iso:country":"US",
    "sg:address":"11725 Bristow Rd",
    "sg:city":"Bristow",
    "sg:classifiers":[
        {
            "category":"Building & Trades",
            "subcategory":"Landscaping Services",
            "type":"Services"
        }
    ],
    "sg:phone":"+1 703 551 2202",
    "sg:postcode":"20136",
    "sg:province":"VA",
    "sg:tags":[
        "landscape",
        "contractor"
    ],
    "sg:website":"www.commercialscapes.com",
    "wof:name":"Commercial Scapes Inc",
    "wof:placetype":"venue"
},
  "geometry": {"coordinates":[-77.52146399999999,38.711441],"type":"Point"}
}