{
  "type": "Feature",
  "properties": {
    "iso:country":"US",
    "sg:address":"1228 Rives Rd",
    "sg:city":"Martinsville",
    "sg:classifiers":[
        {
            "category":"Retail",
            "subcategory":"Car Wash",
            "type":"Services"
        }
    ],
    "sg:phone":"+1 276 632 8004",
    "sg:postcode":"24112",
    "sg:province":"VA",
    "sg:tags":[
        "carwash"
    ],
    "wof:name":"A1 Car Wash",
    "wof:placetype":"venue"
},
  "geometry": {"coordinates":[-79.86618799999999,36.663563],"type":"Point"}
}