{
  "type": "Feature",
  "properties": {
    "addr:full":"3511 Broad Rock Blvd Richmond VA 23234",
    "addr:housenumber":"3511",
    "addr:postcode":"23234",
    "addr:street":"Broad Rock Blvd",
    "iso:country":"US",
    "sg:address":"3511 Broad Rock Blvd",
    "sg:city":"Richmond",
    "sg:classifiers":[
        {
            "category":"Health Services",
            "subcategory":"Hospital",
            "type":"Services"
        },
        {
            "category":"Community Center",
            "type":"Public Place"
        }
    ],
    "sg:phone":"+1 804 271 9170",
    "sg:postcode":"23234",
    "sg:province":"VA",
    "sg:tags":[
        "medical"
    ],
    "wof:name":"Nancy Giliam Memorial Medical",
    "wof:placetype":"venue"
},
  "geometry": {"coordinates":[-77.48603300000001,37.46818],"type":"Point"}
}