{
  "type": "Feature",
  "properties": {
    "addr:full":"5605 Pignut Mountain Dr Warrenton VA 20187",
    "addr:housenumber":"5605",
    "addr:postcode":"20187",
    "addr:street":"Pignut Mountain Dr",
    "iso:country":"US",
    "sg:address":"5605 Pignut Mountain Dr",
    "sg:city":"Warrenton",
    "sg:classifiers":[
        {
            "category":"Shopping",
            "type":"Retail Goods"
        }
    ],
    "sg:phone":"+1 540 349 8252",
    "sg:postcode":"20187",
    "sg:province":"VA",
    "sg:tags":[
        "merchandise"
    ],
    "wof:name":"Warrenton Pet Shop",
    "wof:placetype":"venue"
},
  "geometry": {"coordinates":[-77.795756,38.800571],"type":"Point"}
}