{
  "type": "Feature",
  "properties": {
    "addr:full":"1031 Blackburn Bluff Charlottesville VA 22901",
    "addr:housenumber":"1031",
    "addr:postcode":"22901",
    "addr:street":"Blackburn Bluff",
    "iso:country":"US",
    "sg:address":"1031 Blackburn Bluff",
    "sg:city":"Charlottesville",
    "sg:classifiers":[
        {
            "category":"Shopping",
            "subcategory":"Computers & Home Electronics",
            "type":"Retail Goods"
        }
    ],
    "sg:phone":"+1 434 973 1499",
    "sg:postcode":"22901",
    "sg:province":"VA",
    "sg:tags":[
        "software"
    ],
    "wof:name":"Tax Resources",
    "wof:placetype":"venue"
},
  "geometry": {"coordinates":[-78.457292,38.066203],"type":"Point"}
}