{
  "type": "Feature",
  "properties": {
    "iso:country":"US",
    "sg:address":"4009 Old Virginia Rd",
    "sg:city":"Chesapeake",
    "sg:classifiers":[
        {
            "category":"Professional",
            "subcategory":"Management & Consulting",
            "type":"Services"
        }
    ],
    "sg:phone":"+1 757 673 2822",
    "sg:postcode":"23323",
    "sg:province":"VA",
    "sg:tags":[
        "business"
    ],
    "wof:name":"3d Communications & Consulting",
    "wof:placetype":"venue"
},
  "geometry": {"coordinates":[-76.379435,36.785916],"type":"Point"}
}