{
  "type": "Feature",
  "properties": {
    "addr:full":"8228 Gunston Corner Ln Lorton VA 22079",
    "addr:housenumber":"8228",
    "addr:postcode":"22079",
    "addr:street":"Gunston Corner Ln",
    "iso:country":"US",
    "sg:address":"8228 Gunston Corner Ln",
    "sg:city":"Lorton",
    "sg:classifiers":[
        {
            "category":"Food & Beverages",
            "subcategory":"Groceries & Convenience Stores",
            "type":"Retail Goods"
        }
    ],
    "sg:phone":"+1 703 690 2463",
    "sg:postcode":"22079",
    "sg:province":"VA",
    "wof:name":"Gunston Food Mart & Deli",
    "wof:placetype":"venue"
},
  "geometry": {"coordinates":[-77.228683,38.70496],"type":"Point"}
}