{
  "type": "Feature",
  "properties": {
    "iso:country":"US",
    "sg:address":"220 Southgate Ave",
    "sg:city":"Virginia Beach",
    "sg:classifiers":[
        {
            "category":"Shopping",
            "subcategory":"Computers & Home Electronics",
            "type":"Retail Goods"
        }
    ],
    "sg:phone":"+1 757 301 3575",
    "sg:postcode":"23462",
    "sg:province":"VA",
    "sg:tags":[
        "audio"
    ],
    "wof:name":"Anvil Integration",
    "wof:placetype":"venue"
},
  "geometry": {"coordinates":[-76.15402,36.843402],"type":"Point"}
}