{
  "type": "Feature",
  "properties": {
    "iso:country":"US",
    "sg:address":"970 Hilton Heights Rd",
    "sg:city":"Charlottesville",
    "sg:classifiers":[
        {
            "category":"Banks & Credit Unions",
            "subcategory":"Bank",
            "type":"Services"
        }
    ],
    "sg:phone":"+1 434 978 7463",
    "sg:postcode":"22901",
    "sg:province":"VA",
    "wof:name":"Carollton Bank",
    "wof:placetype":"venue"
},
  "geometry": {"coordinates":[-78.465569,38.097953],"type":"Point"}
}