{
  "type": "Feature",
  "properties": {
    "addr:full":"900 Covington Ct Waverly VA 23890",
    "addr:housenumber":"900",
    "addr:postcode":"23890",
    "addr:street":"Covington Ct",
    "iso:country":"US",
    "sg:address":"900 Covington Ct",
    "sg:city":"Waverly",
    "sg:classifiers":[
        {
            "category":"Real Estate",
            "subcategory":"Real Estate Agent",
            "type":"Services"
        }
    ],
    "sg:phone":"+1 804 834 2762",
    "sg:postcode":"23890",
    "sg:province":"VA",
    "wof:name":"Waverly Elderly Apartments",
    "wof:placetype":"venue"
},
  "geometry": {"coordinates":[-77.082003,37.040907],"type":"Point"}
}