{
  "type": "Feature",
  "properties": {
    "iso:country":"US",
    "sg:address":"5114 Inglewood Rd",
    "sg:city":"Lynchburg",
    "sg:classifiers":[
        {
            "category":"Farming",
            "subcategory":"Livestock Farm",
            "type":"Manufacturing & Wholesale Goods"
        }
    ],
    "sg:phone":"+1 434 384 3271",
    "sg:postcode":"24503",
    "sg:province":"VA",
    "sg:tags":[
        "animal",
        "general"
    ],
    "wof:name":"Meadow Ridge Ranch",
    "wof:placetype":"venue"
},
  "geometry": {"coordinates":[-79.21672599999999,37.449927],"type":"Point"}
}