{
  "type": "Feature",
  "properties": {
    "addr:full":"1543 Beech Grove Rd Roseland VA 22967",
    "addr:housenumber":"1543",
    "addr:postcode":"22967",
    "addr:street":"Beech Grove Rd",
    "iso:country":"US",
    "sg:address":"1543 Beech Grove Rd",
    "sg:city":"Roseland",
    "sg:classifiers":[
        {
            "category":"Health Services",
            "subcategory":"Health Practitioner",
            "type":"Services"
        }
    ],
    "sg:phone":"+1 434 361 0445",
    "sg:postcode":"22967",
    "sg:province":"VA",
    "sg:tags":[
        "therapist",
        "physical"
    ],
    "wof:name":"Nelson Physical Therapy LLC",
    "wof:placetype":"venue"
},
  "geometry": {"coordinates":[-78.94110999999999,37.875983],"type":"Point"}
}