{
  "type": "Feature",
  "properties": {
    "addr:full":"1001 Roanoke Blvd Salem VA 24153",
    "addr:housenumber":"1001",
    "addr:postcode":"24153",
    "addr:street":"Roanoke Blvd",
    "iso:country":"US",
    "sg:address":"1001 Roanoke Blvd",
    "sg:city":"Salem",
    "sg:classifiers":[
        {
            "category":"Government",
            "subcategory":"Office",
            "type":"Public Place"
        }
    ],
    "sg:phone":"+1 540 375 4013",
    "sg:postcode":"24153",
    "sg:province":"VA",
    "sg:tags":[
        "village"
    ],
    "wof:name":"Salem Fair",
    "wof:placetype":"venue"
},
  "geometry": {"coordinates":[-80.04304399999999,37.28555],"type":"Point"}
}