{
  "type": "Feature",
  "properties": {
    "iso:country":"US",
    "sg:address":"2852 Jefferson Davis Hwy",
    "sg:city":"Stafford",
    "sg:classifiers":[
        {
            "category":"Utilities",
            "subcategory":"Mobile Phone",
            "type":"Services"
        }
    ],
    "sg:phone":"+1 540 288 8825",
    "sg:postcode":"22554",
    "sg:province":"VA",
    "sg:tags":[
        "telephone",
        "cellular"
    ],
    "wof:name":"Cellular Solutions",
    "wof:placetype":"venue"
},
  "geometry": {"coordinates":[-77.405541,38.463488],"type":"Point"}
}