{
  "type": "Feature",
  "properties": {
    "addr:full":"5675 Stone Rd Centreville VA 20120",
    "addr:housenumber":"5675",
    "addr:postcode":"20120",
    "addr:street":"Stone Rd",
    "iso:country":"US",
    "sg:address":"5675 Stone Rd",
    "sg:city":"Centreville",
    "sg:classifiers":[
        {
            "category":"Social Services",
            "type":"Services"
        }
    ],
    "sg:phone":"+1 703 830 9720",
    "sg:postcode":"20120",
    "sg:province":"VA",
    "wof:name":"Mary Lee",
    "wof:placetype":"venue"
},
  "geometry": {"coordinates":[-77.45117399999999,38.853353],"type":"Point"}
}