{
  "type": "Feature",
  "properties": {
    "addr:full":"4990 Old Buckingham Rd Powhatan VA 23139",
    "addr:housenumber":"4990",
    "addr:postcode":"23139",
    "addr:street":"Old Buckingham Rd",
    "iso:country":"US",
    "sg:address":"4990 Old Buckingham Rd",
    "sg:city":"Powhatan",
    "sg:classifiers":[
        {
            "category":"Professional",
            "type":"Services"
        }
    ],
    "sg:phone":"+1 804 598 2664",
    "sg:postcode":"23139",
    "sg:province":"VA",
    "wof:name":"Frank Baldwin",
    "wof:placetype":"venue"
},
  "geometry": {"coordinates":[-77.99989100000001,37.522703],"type":"Point"}
}