{
  "type": "Feature",
  "properties": {
    "iso:country":"US",
    "sg:address":"1705 Atlantic Ave",
    "sg:city":"Virginia Beach",
    "sg:classifiers":[
        {
            "category":"Travel",
            "subcategory":"Hotels & Motels",
            "type":"Entertainment"
        }
    ],
    "sg:phone":"+1 757 491 1420",
    "sg:postcode":"23451",
    "sg:province":"VA",
    "sg:website":"www.dolphinhotel.com",
    "wof:name":"Dolphin Inn",
    "wof:placetype":"venue"
},
  "geometry": {"coordinates":[-75.974311,36.845804],"type":"Point"}
}