{
  "type": "Feature",
  "properties": {
    "iso:country":"US",
    "sg:address":"415 E Main St",
    "sg:city":"Berryville",
    "sg:classifiers":[
        {
            "category":"Retail",
            "subcategory":"Car Wash",
            "type":"Services"
        }
    ],
    "sg:phone":"+1 540 955 0626",
    "sg:postcode":"22611",
    "sg:province":"VA",
    "sg:tags":[
        "automobile",
        "detail",
        "clean"
    ],
    "wof:name":"Big Daddy Detail",
    "wof:placetype":"venue"
},
  "geometry": {"coordinates":[-77.97544000000001,39.147795],"type":"Point"}
}