{
  "type": "Feature",
  "properties": {
    "addr:full":"9854 Lori Rd Chesterfield VA 23832",
    "addr:housenumber":"9854",
    "addr:postcode":"23832",
    "addr:street":"Lori Rd",
    "iso:country":"US",
    "sg:address":"9854 Lori Rd",
    "sg:city":"Chesterfield",
    "sg:classifiers":[
        {
            "category":"Shopping",
            "subcategory":"Computers & Home Electronics",
            "type":"Retail Goods"
        }
    ],
    "sg:phone":"+1 804 796 6939",
    "sg:postcode":"23832",
    "sg:province":"VA",
    "sg:tags":[
        "software"
    ],
    "sg:website":"www.haldengroup.com",
    "wof:name":"Halden Group",
    "wof:placetype":"venue"
},
  "geometry": {"coordinates":[-77.50991500000001,37.37885],"type":"Point"}
}