{
  "type": "Feature",
  "properties": {
    "addr:full":"451 Pleasant Valley Rd Harrisonburg VA 22801",
    "addr:housenumber":"451",
    "addr:postcode":"22801",
    "addr:street":"Pleasant Valley Rd",
    "iso:country":"US",
    "sg:address":"451 Pleasant Valley Rd",
    "sg:city":"Harrisonburg",
    "sg:classifiers":[
        {
            "category":"Professional",
            "subcategory":"Advertising",
            "type":"Services"
        }
    ],
    "sg:phone":"+1 540 432 0082",
    "sg:postcode":"22801",
    "sg:province":"VA",
    "sg:tags":[
        "mailing",
        "shipping"
    ],
    "wof:name":"First Class Svc",
    "wof:placetype":"venue"
},
  "geometry": {"coordinates":[-78.89953199999999,38.401895],"type":"Point"}
}