{
  "type": "Feature",
  "properties": {
    "addr:full":"6008 Waterman Dr Fredericksburg VA 22407",
    "addr:housenumber":"6008",
    "addr:postcode":"22407",
    "addr:street":"Waterman Dr",
    "iso:country":"US",
    "sg:address":"6008 Waterman Dr",
    "sg:city":"Fredericksburg",
    "sg:classifiers":[
        {
            "category":"Professional",
            "subcategory":"Engineering",
            "type":"Services"
        }
    ],
    "sg:phone":"+1 540 834 0718",
    "sg:postcode":"22407",
    "sg:province":"VA",
    "sg:tags":[
        "consulting",
        "engineer"
    ],
    "sg:website":"http://www.navarro-inc.com",
    "wof:name":"Navarro Research And Engineering, Inc.",
    "wof:placetype":"venue"
},
  "geometry": {"coordinates":[-77.538709,38.224505],"type":"Point"}
}