{
  "type": "Feature",
  "properties": {
    "addr:full":"16110 Lankford Hwy Bloxom VA 23308",
    "addr:housenumber":"16110",
    "addr:postcode":"23308",
    "addr:street":"Lankford Hwy Bloxom",
    "iso:country":"US",
    "sg:address":"16110 Lankford Hwy",
    "sg:city":"Bloxom",
    "sg:classifiers":[
        {
            "category":"Autos & Motor Vehicles",
            "subcategory":"Automobile Sales",
            "type":"Retail Goods"
        }
    ],
    "sg:phone":"+1 757 665 4500",
    "sg:postcode":"23308",
    "sg:province":"VA",
    "sg:tags":[
        "used"
    ],
    "wof:name":"Cash Auto Sales",
    "wof:placetype":"venue"
},
  "geometry": {"coordinates":[-75.587689,37.819612],"type":"Point"}
}