{
  "type": "Feature",
  "properties": {
    "iso:country":"US",
    "sg:address":"171 S Main St",
    "sg:city":"Halifax",
    "sg:classifiers":[
        {
            "category":"Government",
            "subcategory":"Office",
            "type":"Public Place"
        }
    ],
    "sg:phone":"+1 434 476 7923",
    "sg:postcode":"24558",
    "sg:province":"VA",
    "wof:name":"Halifax Soil & Water Cnsrtn",
    "wof:placetype":"venue"
},
  "geometry": {"coordinates":[-78.92845199999999,36.76372],"type":"Point"}
}