{
  "type": "Feature",
  "properties": {
    "iso:country":"US",
    "sg:address":"1919 Westchester Ave SW",
    "sg:city":"Roanoke",
    "sg:classifiers":[
        {
            "category":"Building & Trades",
            "subcategory":"Landscaping Services",
            "type":"Services"
        }
    ],
    "sg:phone":"+1 540 774 1328",
    "sg:postcode":"24018",
    "sg:province":"VA",
    "wof:name":"Gomez Lawn Service",
    "wof:placetype":"venue"
},
  "geometry": {"coordinates":[-80.016299,37.250475],"type":"Point"}
}