{
  "type": "Feature",
  "properties": {
    "addr:full":"2134 Lakeside Dr Lynchburg VA 24501",
    "addr:housenumber":"2134",
    "addr:postcode":"24501",
    "addr:street":"Lakeside Dr",
    "iso:country":"US",
    "sg:address":"2134 Lakeside Dr",
    "sg:city":"Lynchburg",
    "sg:classifiers":[
        {
            "category":"Real Estate",
            "subcategory":"Real Estate Operator",
            "type":"Services"
        }
    ],
    "sg:phone":"+1 434 385 5332",
    "sg:postcode":"24501",
    "sg:province":"VA",
    "sg:tags":[
        "mobile",
        "home",
        "site",
        "community"
    ],
    "wof:name":"Forest Road Trailer Park",
    "wof:placetype":"venue"
},
  "geometry": {"coordinates":[-79.20654999999999,37.399501],"type":"Point"}
}