{
  "type": "Feature",
  "properties": {
    "iso:country":"US",
    "sg:address":"2424 Drum Creek Rd",
    "sg:city":"Chesapeake",
    "sg:classifiers":[
        {
            "category":"Building & Trades",
            "subcategory":"Construction",
            "type":"Services"
        }
    ],
    "sg:phone":"+1 757 488 5328",
    "sg:postcode":"23321",
    "sg:province":"VA",
    "sg:tags":[
        "house",
        "nonresidential"
    ],
    "wof:name":"R T Construction Co",
    "wof:placetype":"venue"
},
  "geometry": {"coordinates":[-76.420855,36.835243],"type":"Point"}
}