{
  "type": "Feature",
  "properties": {
    "iso:country":"US",
    "sg:address":"1800 Roseneath Rd",
    "sg:city":"Richmond",
    "sg:classifiers":[
        {
            "category":"Building & Trades",
            "subcategory":"Construction",
            "type":"Services"
        }
    ],
    "sg:phone":"+1 804 213 0400",
    "sg:postcode":"23230",
    "sg:province":"VA",
    "sg:tags":[
        "general",
        "contractor"
    ],
    "sg:website":"www.danielco.net",
    "wof:name":"Daniel & Co Inc",
    "wof:placetype":"venue"
},
  "geometry": {"coordinates":[-77.470636,37.572305],"type":"Point"}
}