{
  "type": "Feature",
  "properties": {
    "iso:country":"US",
    "sg:address":"124 Ridgeview Dr",
    "sg:city":"Stuarts Draft",
    "sg:classifiers":[
        {
            "category":"Organizations",
            "subcategory":"Religious Organization",
            "type":"Services"
        }
    ],
    "sg:phone":"+1 540 337 1025",
    "sg:postcode":"24477",
    "sg:province":"VA",
    "sg:tags":[
        "church"
    ],
    "wof:name":"Ridgeview Baptist Church",
    "wof:placetype":"venue"
},
  "geometry": {"coordinates":[-79.034284,38.012357],"type":"Point"}
}