{
  "type": "Feature",
  "properties": {
    "iso:country":"US",
    "sg:address":"209 Tintern Ct",
    "sg:city":"Chesapeake",
    "sg:classifiers":[
        {
            "category":"Building & Trades",
            "subcategory":"Construction",
            "type":"Services"
        }
    ],
    "sg:phone":"+1 757 410 7235",
    "sg:postcode":"23320",
    "sg:province":"VA",
    "sg:tags":[
        "commercial",
        "contractor"
    ],
    "wof:name":"McKinley Chugach Inc",
    "wof:placetype":"venue"
},
  "geometry": {"coordinates":[-76.25764599999999,36.768082],"type":"Point"}
}