{
  "type": "Feature",
  "properties": {
    "addr:full":"16545 Moneta Rd Moneta VA 24121",
    "addr:housenumber":"16545",
    "addr:postcode":"24121",
    "addr:street":"Moneta Rd",
    "iso:country":"US",
    "sg:address":"16545 Moneta Rd",
    "sg:city":"Moneta",
    "sg:classifiers":[
        {
            "category":"Shopping",
            "subcategory":"Gifts & Souvenirs",
            "type":"Retail Goods"
        }
    ],
    "sg:phone":"+1 540 297 2255",
    "sg:postcode":"24121",
    "sg:province":"VA",
    "wof:name":"Gazebo",
    "wof:placetype":"venue"
},
  "geometry": {"coordinates":[-79.66143599999999,37.151411],"type":"Point"}
}