{
  "type": "Feature",
  "properties": {
    "iso:country":"US",
    "sg:address":"2240 Gallows Rd",
    "sg:city":"Vienna",
    "sg:classifiers":[
        {
            "category":"Professional",
            "subcategory":"Credit Reporting & Collection",
            "type":"Services"
        }
    ],
    "sg:phone":"+1 703 573 9704",
    "sg:postcode":"22182",
    "sg:province":"VA",
    "wof:name":"Transportation Revenue MGT",
    "wof:placetype":"venue"
},
  "geometry": {"coordinates":[-77.224391,38.898773],"type":"Point"}
}