{
  "type": "Feature",
  "properties": {
    "iso:country":"US",
    "sg:address":"10428 Bus Center Ct",
    "sg:city":"Manassas",
    "sg:classifiers":[
        {
            "category":"Professional",
            "subcategory":"Engineering",
            "type":"Services"
        }
    ],
    "sg:phone":"+1 703 361 9898",
    "sg:postcode":"20110",
    "sg:province":"VA",
    "sg:tags":[
        "engineer"
    ],
    "wof:name":"Engineering & Materials Tech",
    "wof:placetype":"venue"
},
  "geometry": {"coordinates":[-77.506648,38.741872],"type":"Point"}
}