{
  "type": "Feature",
  "properties": {
    "iso:country":"US",
    "sg:address":"10169 Piper Ln",
    "sg:city":"Bristow",
    "sg:classifiers":[
        {
            "category":"Bus Charters",
            "type":"Transportation"
        }
    ],
    "sg:phone":"+1 703 393 1441",
    "sg:postcode":"20136",
    "sg:province":"VA",
    "sg:tags":[
        "rental"
    ],
    "sg:website":"www.scenic-usa.com",
    "wof:name":"Scenic America Inc",
    "wof:placetype":"venue"
},
  "geometry": {"coordinates":[-77.532369,38.735995],"type":"Point"}
}