{
  "type": "Feature",
  "properties": {
    "addr:full":"6721 Jefferson Davis Hwy Spotsylvania VA 22551",
    "addr:housenumber":"6721",
    "addr:postcode":"22551",
    "addr:street":"Jefferson Davis Hwy",
    "iso:country":"US",
    "sg:address":"6721 Jefferson Davis Hwy",
    "sg:city":"Spotsylvania",
    "sg:classifiers":[
        {
            "category":"Autos & Motor Vehicles",
            "subcategory":"Auto Supplies",
            "type":"Retail Goods"
        },
        {
            "category":"Retail",
            "subcategory":"Auto Repair",
            "type":"Services"
        }
    ],
    "sg:phone":"+1 540 582 6966",
    "sg:postcode":"22551",
    "sg:province":"VA",
    "sg:tags":[
        "body",
        "transmission",
        "automobile",
        "part",
        "brake",
        "painting",
        "repairing"
    ],
    "wof:name":"Jacobs Auto",
    "wof:placetype":"venue"
},
  "geometry": {"coordinates":[-77.52346,38.143395],"type":"Point"}
}