{
  "type": "Feature",
  "properties": {
    "addr:full":"5050 Valley View Blvd NW Roanoke VA 24012",
    "addr:housenumber":"5050",
    "addr:postcode":"24012",
    "addr:street":"Valley View Blvd Nw",
    "iso:country":"US",
    "sg:address":"5050 Valley View Blvd NW",
    "sg:city":"Roanoke",
    "sg:classifiers":[
        {
            "category":"Travel",
            "subcategory":"Hotels & Motels",
            "type":"Entertainment"
        }
    ],
    "sg:phone":"+1 877 574 2464",
    "sg:postcode":"24012",
    "sg:province":"VA",
    "sg:website":"http://book.bestwestern.com/bestwestern/priceAvail.do?propertyCode=47094&cm_mmc=IYP-_-YP-_-property-_-47094",
    "wof:name":"Best Western Inn At Valley View",
    "wof:placetype":"venue"
},
  "geometry": {"coordinates":[-79.969337,37.308811],"type":"Point"}
}