{
  "type": "Feature",
  "properties": {
    "iso:country":"US",
    "sg:address":"7606 Broadway Dr",
    "sg:city":"Falls Church",
    "sg:classifiers":[
        {
            "category":"Real Estate",
            "subcategory":"Real Estate Operator",
            "type":"Services"
        }
    ],
    "sg:phone":"+1 703 573 1493",
    "sg:postcode":"22043",
    "sg:province":"VA",
    "sg:tags":[
        "building",
        "apartment"
    ],
    "wof:name":"Hollywood Manor",
    "wof:placetype":"venue"
},
  "geometry": {"coordinates":[-77.206592,38.879367],"type":"Point"}
}