{
  "type": "Feature",
  "properties": {
    "iso:country":"US",
    "sg:address":"2937 Ridgefield Dr",
    "sg:city":"Norfolk",
    "sg:classifiers":[
        {
            "category":"Banks & Credit Unions",
            "subcategory":"Investment Brokerage",
            "type":"Services"
        }
    ],
    "sg:phone":"+1 757 583 4800",
    "sg:postcode":"23518",
    "sg:province":"VA",
    "sg:tags":[
        "commodity",
        "broker",
        "contract"
    ],
    "wof:name":"Futures Workshop",
    "wof:placetype":"venue"
},
  "geometry": {"coordinates":[-76.20481100000001,36.921648],"type":"Point"}
}