{
  "type": "Feature",
  "properties": {
    "addr:full":"1810 Michael Faraday Ct Reston VA 20190",
    "addr:housenumber":"1810",
    "addr:postcode":"20190",
    "addr:street":"Michael Faraday Ct",
    "iso:country":"US",
    "sg:address":"1810 Michael Faraday Ct",
    "sg:city":"Reston",
    "sg:classifiers":[
        {
            "category":"Health Services",
            "subcategory":"Doctor",
            "type":"Services"
        }
    ],
    "sg:phone":"+1 703 471 0508",
    "sg:postcode":"20190",
    "sg:province":"VA",
    "sg:tags":[
        "physician",
        "surgeon"
    ],
    "wof:name":"Doris Snow MD",
    "wof:placetype":"venue"
},
  "geometry": {"coordinates":[-77.332385,38.950016],"type":"Point"}
}