{
  "type": "Feature",
  "properties": {
    "addr:full":"80 Ellsworth Ct Ridgeway VA 24148",
    "addr:housenumber":"80",
    "addr:postcode":"24148",
    "addr:street":"Ellsworth Ct",
    "iso:country":"US",
    "sg:address":"80 Ellsworth Ct",
    "sg:city":"Ridgeway",
    "sg:classifiers":[
        {
            "category":"Building & Trades",
            "subcategory":"Construction",
            "type":"Services"
        }
    ],
    "sg:phone":"+1 276 956 3294",
    "sg:postcode":"24148",
    "sg:province":"VA",
    "sg:tags":[
        "house"
    ],
    "wof:name":"Eggleston Builders",
    "wof:placetype":"venue"
},
  "geometry": {"coordinates":[-79.86305,36.571201],"type":"Point"}
}