{
  "type": "Feature",
  "properties": {
    "addr:full":"5215 S Laburnum Ave Richmond VA 23231",
    "addr:housenumber":"5215",
    "addr:postcode":"23231",
    "addr:street":"S Laburnum Ave",
    "iso:country":"US",
    "sg:address":"5215 S Laburnum Ave",
    "sg:city":"Richmond",
    "sg:classifiers":[
        {
            "category":"Shopping",
            "subcategory":"Clothing, Apparel, & Fashions",
            "type":"Retail Goods"
        }
    ],
    "sg:phone":"+1 804 226 1366",
    "sg:postcode":"23231",
    "sg:province":"VA",
    "sg:tags":[
        "work",
        "shoes",
        "clothes"
    ],
    "sg:website":"www.work-duds.com",
    "wof:name":"Work Duds",
    "wof:placetype":"venue"
},
  "geometry": {"coordinates":[-77.349932,37.517212],"type":"Point"}
}