{
  "type": "Feature",
  "properties": {
    "addr:full":"2920 N Armistead Ave Hampton VA 23666",
    "addr:housenumber":"2920",
    "addr:postcode":"23666",
    "addr:street":"N Armistead Ave",
    "iso:country":"US",
    "sg:address":"2920 N Armistead Ave",
    "sg:city":"Hampton",
    "sg:classifiers":[
        {
            "category":"Real Estate",
            "subcategory":"Real Estate Operator",
            "type":"Services"
        }
    ],
    "sg:phone":"+1 757 766 1093",
    "sg:postcode":"23666",
    "sg:province":"VA",
    "sg:tags":[
        "mobile",
        "home",
        "site",
        "community"
    ],
    "wof:name":"Gardners Trailer Court Inc",
    "wof:placetype":"venue"
},
  "geometry": {"coordinates":[-76.382178,37.072575],"type":"Point"}
}