{
  "type": "Feature",
  "properties": {
    "addr:full":"1107 Queensgate Ct Midlothian VA 23114",
    "addr:housenumber":"1107",
    "addr:postcode":"23114",
    "addr:street":"Queensgate Ct",
    "iso:country":"US",
    "sg:address":"1107 Queensgate Ct",
    "sg:city":"Midlothian",
    "sg:classifiers":[
        {
            "category":"Real Estate",
            "subcategory":"Real Estate Agent",
            "type":"Services"
        }
    ],
    "sg:phone":"+1 804 378 6209",
    "sg:postcode":"23114",
    "sg:province":"VA",
    "wof:name":"C21 All American",
    "wof:placetype":"venue"
},
  "geometry": {"coordinates":[-77.652253,37.478989],"type":"Point"}
}