{
  "type": "Feature",
  "properties": {
    "addr:full":"14309 Belleville Ave Woodbridge VA 22193",
    "addr:housenumber":"14309",
    "addr:postcode":"22193",
    "addr:street":"Belleville Ave",
    "iso:country":"US",
    "sg:address":"14309 Belleville Ave",
    "sg:city":"Woodbridge",
    "sg:classifiers":[
        {
            "category":"Professional",
            "type":"Services"
        }
    ],
    "sg:phone":"+1 703 730 9212",
    "sg:postcode":"22193",
    "sg:province":"VA",
    "wof:name":"Eyler Santos",
    "wof:placetype":"venue"
},
  "geometry": {"coordinates":[-77.306147,38.639168],"type":"Point"}
}