{
  "type": "Feature",
  "properties": {
    "iso:country":"US",
    "sg:address":"5217 Overland Ct",
    "sg:city":"Virginia Beach",
    "sg:classifiers":[
        {
            "category":"Building & Trades",
            "subcategory":"Landscaping Services",
            "type":"Services"
        }
    ],
    "sg:phone":"+1 757 227 5211",
    "sg:postcode":"23462",
    "sg:province":"VA",
    "wof:name":"Grey Lawns of Tidewater",
    "wof:placetype":"venue"
},
  "geometry": {"coordinates":[-76.16373400000001,36.83242],"type":"Point"}
}