{
  "type": "Feature",
  "properties": {
    "iso:country":"US",
    "sg:address":"147 Fenton Mill Rd",
    "sg:city":"Williamsburg",
    "sg:classifiers":[
        {
            "category":"Manufacturing",
            "subcategory":"Lumber",
            "type":"Manufacturing & Wholesale Goods"
        }
    ],
    "sg:phone":"+1 757 253 4695",
    "sg:postcode":"23188",
    "sg:province":"VA",
    "sg:tags":[
        "government"
    ],
    "wof:name":"Forestry Dept",
    "wof:placetype":"venue"
},
  "geometry": {"coordinates":[-76.715396,37.338897],"type":"Point"}
}