{
  "type": "Feature",
  "properties": {
    "addr:full":"2101 Harper's Mill Williamsburg VA 23185",
    "addr:housenumber":"2101",
    "addr:postcode":"23185",
    "addr:street":"Harper'S Mill",
    "iso:country":"US",
    "sg:address":"2101 Harper's Mill",
    "sg:city":"Williamsburg",
    "sg:classifiers":[
        {
            "category":"Professional",
            "subcategory":"Management & Consulting",
            "type":"Services"
        }
    ],
    "sg:phone":"+1 757 565 5421",
    "sg:postcode":"23185",
    "sg:province":"VA",
    "sg:tags":[
        "marketing",
        "consultant"
    ],
    "sg:website":"www.deciphermarketing.com",
    "wof:name":"Decipher Marketing Inc",
    "wof:placetype":"venue"
},
  "geometry": {"coordinates":[-76.846158,37.252752],"type":"Point"}
}