{
  "type": "Feature",
  "properties": {
    "addr:full":"1925 E Market St Ste 312 Harrisonburg VA 22801",
    "addr:housenumber":"1925",
    "addr:postcode":"22801",
    "addr:street":"E Market St Ste 312",
    "iso:country":"US",
    "sg:address":"1925 E Market St Ste 312",
    "sg:city":"Harrisonburg",
    "sg:classifiers":[
        {
            "category":"Shopping",
            "subcategory":"Clothing, Apparel, & Fashions",
            "type":"Retail Goods"
        }
    ],
    "sg:phone":"+1 540 442 8388",
    "sg:postcode":"22801",
    "sg:province":"VA",
    "sg:tags":[
        "apparel",
        "women's"
    ],
    "sg:website":"http://www.christopherandbanks.com",
    "wof:name":"Christopher & Banks",
    "wof:placetype":"venue"
},
  "geometry": {"coordinates":[-78.841976,38.429602],"type":"Point"}
}