{
  "type": "Feature",
  "properties": {
    "addr:full":"15142 Brandy Rd Culpeper VA 22701",
    "addr:housenumber":"15142",
    "addr:postcode":"22701",
    "addr:street":"Brandy Rd",
    "iso:country":"US",
    "sg:address":"15142 Brandy Rd",
    "sg:city":"Culpeper",
    "sg:classifiers":[
        {
            "category":"Social Services",
            "type":"Services"
        }
    ],
    "sg:phone":"+1 540 825 6725",
    "sg:postcode":"22701",
    "sg:province":"VA",
    "sg:tags":[
        "counseling"
    ],
    "wof:name":"Counseling Interventions",
    "wof:placetype":"venue"
},
  "geometry": {"coordinates":[-77.972722,38.48317],"type":"Point"}
}