{
  "type": "Feature",
  "properties": {
    "addr:full":"743 Grim Rd Stephens City VA 22655",
    "addr:housenumber":"743",
    "addr:postcode":"22655",
    "addr:street":"Grim Rd",
    "iso:country":"US",
    "sg:address":"743 Grim Rd",
    "sg:city":"Stephens City",
    "sg:classifiers":[
        {
            "category":"Professional",
            "subcategory":"Business Services",
            "type":"Services"
        }
    ],
    "sg:phone":"+1 540 869 1187",
    "sg:postcode":"22655",
    "sg:province":"VA",
    "sg:tags":[
        "auctioneer"
    ],
    "wof:name":"Leon W Strosnider Auctioneer",
    "wof:placetype":"venue"
},
  "geometry": {"coordinates":[-78.203817,39.049565],"type":"Point"}
}