{
  "type": "Feature",
  "properties": {
    "addr:full":"10984 Richardson Rd Ashland VA 23005",
    "addr:housenumber":"10984",
    "addr:postcode":"23005",
    "addr:street":"Richardson Rd",
    "iso:country":"US",
    "sg:address":"10984 Richardson Rd",
    "sg:city":"Ashland",
    "sg:classifiers":[
        {
            "category":"Manufacturing",
            "subcategory":"Tools & Machinery",
            "type":"Manufacturing & Wholesale Goods"
        }
    ],
    "sg:phone":"+1 804 798 9029",
    "sg:postcode":"23005",
    "sg:province":"VA",
    "sg:tags":[
        "sensor",
        "temperature",
        "mfg"
    ],
    "wof:name":"Refrigeration Solutions Inc",
    "wof:placetype":"venue"
},
  "geometry": {"coordinates":[-77.440721,37.697516],"type":"Point"}
}