{
  "type": "Feature",
  "properties": {
    "addr:full":"1704 Cabriole Mews Virginia Beach VA 23455",
    "addr:housenumber":"1704",
    "addr:postcode":"23455",
    "addr:street":"Cabriole Mews",
    "iso:country":"US",
    "sg:address":"1704 Cabriole Mews",
    "sg:city":"Virginia Beach",
    "sg:classifiers":[
        {
            "category":"Professional",
            "subcategory":"Computer Services",
            "type":"Services"
        }
    ],
    "sg:phone":"+1 757 363 9894",
    "sg:postcode":"23455",
    "sg:province":"VA",
    "sg:tags":[
        "prepackaged",
        "software"
    ],
    "wof:name":"Check Point Software Tech",
    "wof:placetype":"venue"
},
  "geometry": {"coordinates":[-76.13466699999999,36.897365],"type":"Point"}
}