{
  "type": "Feature",
  "properties": {
    "iso:country":"US",
    "sg:address":"1142 W Broad St",
    "sg:city":"Falls Church",
    "sg:classifiers":[
        {
            "category":"Restaurant",
            "type":"Food & Drink"
        }
    ],
    "sg:menulink":"http://www.allmenus.com/va/falls-church/147631-subway/menu/",
    "sg:phone":"+1 703 536 7870",
    "sg:postcode":"22046",
    "sg:province":"VA",
    "sg:tags":[
        "american",
        "sandwich"
    ],
    "wof:name":"Subway",
    "wof:placetype":"venue"
},
  "geometry": {"coordinates":[-77.18735100000001,38.892763],"type":"Point"}
}