{
  "type": "Feature",
  "properties": {
    "iso:country":"US",
    "sg:address":"13130 Frog Hollow Ct",
    "sg:city":"Herndon",
    "sg:classifiers":[
        {
            "category":"Professional",
            "type":"Services"
        }
    ],
    "sg:phone":"+1 703 318 0014",
    "sg:postcode":"20171",
    "sg:province":"VA",
    "wof:name":"Vollmerhausen",
    "wof:placetype":"venue"
},
  "geometry": {"coordinates":[-77.40407399999999,38.927082],"type":"Point"}
}