{
  "type": "Feature",
  "properties": {
    "addr:full":"384 Jolly Pond Rd Williamsburg VA 23188",
    "addr:housenumber":"384",
    "addr:postcode":"23188",
    "addr:street":"Jolly Pond Rd",
    "iso:country":"US",
    "sg:address":"384 Jolly Pond Rd",
    "sg:city":"Williamsburg",
    "sg:classifiers":[
        {
            "category":"Building & Trades",
            "subcategory":"Construction",
            "type":"Services"
        }
    ],
    "sg:phone":"+1 757 564 9776",
    "sg:postcode":"23188",
    "sg:province":"VA",
    "sg:tags":[
        "house"
    ],
    "wof:name":"K M Kraus Builder Inc",
    "wof:placetype":"venue"
},
  "geometry": {"coordinates":[-76.797088,37.3377],"type":"Point"}
}