{
  "type": "Feature",
  "properties": {
    "addr:full":"201 Indian Springs Rd Williamsburg VA 23185",
    "addr:housenumber":"201",
    "addr:postcode":"23185",
    "addr:street":"Indian Springs Rd",
    "iso:country":"US",
    "sg:address":"201 Indian Springs Rd",
    "sg:city":"Williamsburg",
    "sg:classifiers":[
        {
            "category":"Professional",
            "subcategory":"Management & Consulting",
            "type":"Services"
        }
    ],
    "sg:phone":"+1 757 258 1073",
    "sg:postcode":"23185",
    "sg:province":"VA",
    "sg:tags":[
        "business"
    ],
    "wof:name":"Robert L Hicks",
    "wof:placetype":"venue"
},
  "geometry": {"coordinates":[-76.712889,37.265831],"type":"Point"}
}