{
  "type": "Feature",
  "properties": {
    "addr:full":"344 Canterwood Ln Great Falls VA 22066",
    "addr:housenumber":"344",
    "addr:postcode":"22066",
    "addr:street":"Canterwood Ln",
    "iso:country":"US",
    "sg:address":"344 Canterwood Ln",
    "sg:city":"Great Falls",
    "sg:classifiers":[
        {
            "category":"Professional",
            "subcategory":"Business Services",
            "type":"Services"
        }
    ],
    "sg:phone":"+1 703 450 7813",
    "sg:postcode":"22066",
    "sg:province":"VA",
    "wof:name":"Sabre Systems Ltd",
    "wof:placetype":"venue"
},
  "geometry": {"coordinates":[-77.34155699999999,39.040231],"type":"Point"}
}