{
  "type": "Feature",
  "properties": {
    "addr:full":"13179 Opal Ln Woodbridge VA 22193",
    "addr:housenumber":"13179",
    "addr:postcode":"22193",
    "addr:street":"Opal Ln",
    "iso:country":"US",
    "sg:address":"13179 Opal Ln",
    "sg:city":"Woodbridge",
    "sg:classifiers":[
        {
            "category":"Building & Trades",
            "subcategory":"Construction",
            "type":"Services"
        }
    ],
    "sg:phone":"+1 703 590 3500",
    "sg:postcode":"22193",
    "sg:province":"VA",
    "sg:tags":[
        "house"
    ],
    "wof:name":"Hylton Enterprises (virginia)",
    "wof:placetype":"venue"
},
  "geometry": {"coordinates":[-77.40031,38.669206],"type":"Point"}
}