{
  "type": "Feature",
  "properties": {
    "iso:country":"US",
    "sg:address":"2 Northampton Blvd",
    "sg:city":"Stafford",
    "sg:classifiers":[
        {
            "category":"Recreation",
            "type":"Entertainment"
        }
    ],
    "sg:phone":"+1 540 658 4241",
    "sg:postcode":"22554",
    "sg:province":"VA",
    "sg:tags":[
        "pool",
        "swimming"
    ],
    "sg:website":"www.staffordparks.com",
    "wof:name":"Woodlands Pool",
    "wof:placetype":"venue"
},
  "geometry": {"coordinates":[-77.43333699999999,38.462728],"type":"Point"}
}