{
  "type": "Feature",
  "properties": {
    "addr:full":"5671 Floyd Hwy S Willis VA 24380",
    "addr:housenumber":"5671",
    "addr:postcode":"24380",
    "addr:street":"Floyd Hwy S",
    "iso:country":"US",
    "sg:address":"5671 Floyd Hwy S",
    "sg:city":"Willis",
    "sg:classifiers":[
        {
            "category":"Organizations",
            "subcategory":"Religious Organization",
            "type":"Services"
        }
    ],
    "sg:phone":"+1 540 789 7941",
    "sg:postcode":"24380",
    "sg:province":"VA",
    "sg:tags":[
        "church"
    ],
    "wof:name":"Floyd United Methodist Circuit",
    "wof:placetype":"venue"
},
  "geometry": {"coordinates":[-80.483723,36.856978],"type":"Point"}
}