{
  "type": "Feature",
  "properties": {
    "iso:country":"US",
    "sg:address":"12109 Wilfong Ct",
    "sg:city":"Midlothian",
    "sg:classifiers":[
        {
            "category":"Manufacturing",
            "subcategory":"Motor Vehicles & Parts",
            "type":"Manufacturing & Wholesale Goods"
        },
        {
            "category":"Wholesale",
            "subcategory":"Auto Parts",
            "type":"Manufacturing & Wholesale Goods"
        },
        {
            "category":"Retail",
            "subcategory":"Auto Repair",
            "type":"Services"
        }
    ],
    "sg:phone":"+1 804 739 2362",
    "sg:postcode":"23112",
    "sg:province":"VA",
    "sg:tags":[
        "body",
        "shop",
        "supply",
        "automobile",
        "supply-wholesale",
        "equipment",
        "service-equipment",
        "repairing",
        "manufacturer"
    ],
    "wof:name":"Crashmax Equipment",
    "wof:placetype":"venue"
},
  "geometry": {"coordinates":[-77.62404600000001,37.460548],"type":"Point"}
}