{
  "type": "Feature",
  "properties": {
    "iso:country":"US",
    "sg:address":"131 Sesco Dr",
    "sg:city":"Hampton",
    "sg:classifiers":[
        {
            "category":"Professional",
            "subcategory":"Art Services",
            "type":"Services"
        }
    ],
    "sg:phone":"+1 757 851 6407",
    "sg:postcode":"23664",
    "sg:province":"VA",
    "sg:tags":[
        "commercial",
        "design"
    ],
    "wof:name":"Genesis One Creations",
    "wof:placetype":"venue"
},
  "geometry": {"coordinates":[-76.302693,37.054803],"type":"Point"}
}