{
  "type": "Feature",
  "properties": {
    "addr:full":"1057 E Lee Hwy Chilhowie VA 24319",
    "addr:housenumber":"1057",
    "addr:postcode":"24319",
    "addr:street":"E Lee Hwy",
    "iso:country":"US",
    "sg:address":"1057 E Lee Hwy",
    "sg:city":"Chilhowie",
    "sg:classifiers":[
        {
            "category":"Retail",
            "subcategory":"Auto Repair",
            "type":"Services"
        }
    ],
    "sg:phone":"+1 276 646 8111",
    "sg:postcode":"24319",
    "sg:province":"VA",
    "sg:tags":[
        "automobile",
        "top",
        "upholstery"
    ],
    "wof:name":"H & H Auto Trim",
    "wof:placetype":"venue"
},
  "geometry": {"coordinates":[-81.675225,36.803682],"type":"Point"}
}