{
  "type": "Feature",
  "properties": {
    "iso:country":"US",
    "sg:address":"4520 Black Cove Rd",
    "sg:city":"Virginia Beach",
    "sg:classifiers":[
        {
            "category":"Building & Trades",
            "subcategory":"Construction",
            "type":"Services"
        }
    ],
    "sg:phone":"+1 757 460 6110",
    "sg:postcode":"23455",
    "sg:province":"VA",
    "sg:tags":[
        "house",
        "nonresidential"
    ],
    "wof:name":"Francavilla Building Co",
    "wof:placetype":"venue"
},
  "geometry": {"coordinates":[-76.128725,36.908313],"type":"Point"}
}