{
  "type": "Feature",
  "properties": {
    "iso:country":"US",
    "sg:address":"13410 Torrington Dr",
    "sg:city":"Midlothian",
    "sg:classifiers":[
        {
            "category":"Professional",
            "type":"Services"
        }
    ],
    "sg:phone":"+1 804 379 1552",
    "sg:postcode":"23113",
    "sg:province":"VA",
    "wof:name":"Frederick and Gail Woods",
    "wof:placetype":"venue"
},
  "geometry": {"coordinates":[-77.648026,37.521651],"type":"Point"}
}