{
  "type": "Feature",
  "properties": {
    "addr:full":"4818 Lexington Tpke Amherst VA 24521",
    "addr:housenumber":"4818",
    "addr:postcode":"24521",
    "addr:street":"Lexington Tpke",
    "iso:country":"US",
    "sg:address":"4818 Lexington Tpke",
    "sg:city":"Amherst",
    "sg:classifiers":[
        {
            "category":"Restaurant",
            "type":"Food & Drink"
        }
    ],
    "sg:phone":"+1 434 922 4660",
    "sg:postcode":"24521",
    "sg:province":"VA",
    "sg:tags":[
        "delicatessen"
    ],
    "wof:name":"May's Market",
    "wof:placetype":"venue"
},
  "geometry": {"coordinates":[-79.21538099999999,37.670741],"type":"Point"}
}