{
  "type": "Feature",
  "properties": {
    "addr:full":"6425 Lakeview Dr Falls Church VA 22041",
    "addr:housenumber":"6425",
    "addr:postcode":"22041",
    "addr:street":"Lakeview Dr",
    "iso:country":"US",
    "sg:address":"6425 Lakeview Dr",
    "sg:city":"Falls Church",
    "sg:classifiers":[
        {
            "category":"Communications",
            "subcategory":"Film & Video Production",
            "type":"Services"
        }
    ],
    "sg:phone":"+1 703 941 4400",
    "sg:postcode":"22041",
    "sg:province":"VA",
    "sg:tags":[
        "motion"
    ],
    "wof:name":"Lawson Media",
    "wof:placetype":"venue"
},
  "geometry": {"coordinates":[-77.15804,38.844171],"type":"Point"}
}