{
  "type": "Feature",
  "properties": {
    "addr:full":"102 Jenkins Ct Manassas Park VA 20111",
    "addr:housenumber":"102",
    "addr:postcode":"20111",
    "addr:street":"Jenkins Ct;Park",
    "iso:country":"US",
    "sg:address":"102 Jenkins Ct",
    "sg:city":"Manassas Park",
    "sg:classifiers":[
        {
            "category":"Retail",
            "subcategory":"Repair Shop",
            "type":"Services"
        }
    ],
    "sg:phone":"+1 703 361 8075",
    "sg:postcode":"20111",
    "sg:province":"VA",
    "sg:tags":[
        "related"
    ],
    "wof:name":"Cowboy Brick Washing Inc",
    "wof:placetype":"venue"
},
  "geometry": {"coordinates":[-77.475866,38.784307],"type":"Point"}
}