{
  "type": "Feature",
  "properties": {
    "iso:country":"US",
    "sg:address":"4623 5th St S",
    "sg:city":"Arlington",
    "sg:classifiers":[
        {
            "category":"Professional",
            "subcategory":"Business Services",
            "type":"Services"
        }
    ],
    "sg:phone":"+1 703 271 4658",
    "sg:postcode":"22204",
    "sg:province":"VA",
    "sg:tags":[
        "interior",
        "architecture"
    ],
    "wof:name":"Fifth Street Designs Pllc",
    "wof:placetype":"venue"
},
  "geometry": {"coordinates":[-77.11357599999999,38.863562],"type":"Point"}
}