{
  "type": "Feature",
  "properties": {
    "iso:country":"US",
    "sg:address":"5836 Woodstock Pt",
    "sg:city":"Virginia Beach",
    "sg:classifiers":[
        {
            "category":"Wholesale",
            "subcategory":"Construction Materials",
            "type":"Manufacturing & Wholesale Goods"
        }
    ],
    "sg:phone":"+1 757 413 2020",
    "sg:postcode":"23464",
    "sg:province":"VA",
    "sg:tags":[
        "abrasive",
        "grit"
    ],
    "wof:name":"Virginia Materials",
    "wof:placetype":"venue"
},
  "geometry": {"coordinates":[-76.19857,36.826086],"type":"Point"}
}