{
  "type": "Feature",
  "properties": {
    "iso:country":"US",
    "sg:address":"1833 W Grace St",
    "sg:city":"Richmond",
    "sg:classifiers":[
        {
            "category":"Shopping",
            "subcategory":"Used Merchandise",
            "type":"Retail Goods"
        }
    ],
    "sg:phone":"+1 804 353 7955",
    "sg:postcode":"23220",
    "sg:province":"VA",
    "sg:tags":[
        "shop",
        "thrift"
    ],
    "wof:name":"Pleiades",
    "wof:placetype":"venue"
},
  "geometry": {"coordinates":[-77.460807,37.555551],"type":"Point"}
}