{
  "type": "Feature",
  "properties": {
    "addr:full":"708 Manor Dr Virginia Beach VA 23464",
    "addr:housenumber":"708",
    "addr:postcode":"23464",
    "addr:street":"Manor Dr",
    "iso:country":"US",
    "sg:address":"708 Manor Dr",
    "sg:city":"Virginia Beach",
    "sg:classifiers":[
        {
            "category":"Home & Garden",
            "subcategory":"Home Furnishings",
            "type":"Retail Goods"
        }
    ],
    "sg:phone":"+1 757 467 0898",
    "sg:postcode":"23464",
    "sg:province":"VA",
    "sg:tags":[
        "blind",
        "installation",
        "venetian",
        "other",
        "w",
        "curtain",
        "drapery"
    ],
    "wof:name":"Professional Sales Estab",
    "wof:placetype":"venue"
},
  "geometry": {"coordinates":[-76.15761999999999,36.816007],"type":"Point"}
}