{
  "type": "Feature",
  "properties": {
    "addr:full":"13459 Spruce Dr King George VA 22485",
    "addr:housenumber":"13459",
    "addr:postcode":"22485",
    "addr:street":"Spruce Dr",
    "iso:country":"US",
    "sg:address":"13459 Spruce Dr",
    "sg:city":"King George",
    "sg:classifiers":[
        {
            "category":"Building & Trades",
            "subcategory":"Construction",
            "type":"Services"
        }
    ],
    "sg:phone":"+1 540 775 4031",
    "sg:postcode":"22485",
    "sg:province":"VA",
    "sg:tags":[
        "excavating",
        "contractor"
    ],
    "wof:name":"Aliff Construction",
    "wof:placetype":"venue"
},
  "geometry": {"coordinates":[-77.10981,38.297813],"type":"Point"}
}