{
  "type": "Feature",
  "properties": {
    "iso:country":"US",
    "sg:address":"1009 Lynnhaven Pkwy",
    "sg:city":"Virginia Beach",
    "sg:classifiers":[
        {
            "category":"Restaurant",
            "type":"Food & Drink"
        }
    ],
    "sg:menulink":"http://www.allmenus.com/va/virginia-beach/32634-ruby-tuesdays/menu/",
    "sg:phone":"+1 757 340 8857",
    "sg:postcode":"23452",
    "sg:province":"VA",
    "sg:tags":[
        "burger",
        "american"
    ],
    "wof:name":"Ruby Tuesdays",
    "wof:placetype":"venue"
},
  "geometry": {"coordinates":[-76.077826,36.807045],"type":"Point"}
}