{
  "type": "Feature",
  "properties": {
    "iso:country":"US",
    "sg:address":"6406 Alexander St",
    "sg:city":"Norfolk",
    "sg:classifiers":[
        {
            "category":"Organizations",
            "subcategory":"Religious Organization",
            "type":"Services"
        }
    ],
    "sg:phone":"+1 757 855 3557",
    "sg:postcode":"23513",
    "sg:province":"VA",
    "sg:tags":[
        "church"
    ],
    "wof:name":"Tabernacle Voice Deliverance",
    "wof:placetype":"venue"
},
  "geometry": {"coordinates":[-76.237498,36.896423],"type":"Point"}
}