{
  "type": "Feature",
  "properties": {
    "iso:country":"US",
    "sg:address":"214 E 13th St",
    "sg:city":"Richmond",
    "sg:classifiers":[
        {
            "category":"Social Services",
            "type":"Services"
        }
    ],
    "sg:phone":"+1 804 788 0232",
    "sg:postcode":"23224",
    "sg:province":"VA",
    "sg:tags":[
        "community"
    ],
    "wof:name":"Richmond Community Action",
    "wof:placetype":"venue"
},
  "geometry": {"coordinates":[-77.442381,37.518071],"type":"Point"}
}