{
  "type": "Feature",
  "properties": {
    "iso:country":"US",
    "sg:address":"509 Georgetowne Ct",
    "sg:city":"Stephens City",
    "sg:classifiers":[
        {
            "category":"Shopping",
            "subcategory":"Clothing, Apparel, & Fashions",
            "type":"Retail Goods"
        }
    ],
    "sg:phone":"+1 540 869 7784",
    "sg:postcode":"22655",
    "sg:province":"VA",
    "sg:tags":[
        "family"
    ],
    "wof:name":"Flashback",
    "wof:placetype":"venue"
},
  "geometry": {"coordinates":[-78.198007,39.083039],"type":"Point"}
}