{
  "type": "Feature",
  "properties": {
    "addr:full":"100 Martha Lee Dr Hampton VA 23666",
    "addr:housenumber":"100",
    "addr:postcode":"23666",
    "addr:street":"Martha Lee Dr",
    "iso:country":"US",
    "sg:address":"100 Martha Lee Dr",
    "sg:city":"Hampton",
    "sg:classifiers":[
        {
            "category":"Real Estate",
            "subcategory":"Real Estate Operator",
            "type":"Services"
        }
    ],
    "sg:phone":"+1 757 826 8925",
    "sg:postcode":"23666",
    "sg:province":"VA",
    "sg:tags":[
        "building",
        "apartment"
    ],
    "wof:name":"Paula Maria Village",
    "wof:placetype":"venue"
},
  "geometry": {"coordinates":[-76.422404,37.022622],"type":"Point"}
}