{
  "type": "Feature",
  "properties": {
    "iso:country":"US",
    "sg:address":"1732 Kelly Rd",
    "sg:city":"Richmond",
    "sg:classifiers":[
        {
            "category":"Wholesale",
            "subcategory":"Electrical",
            "type":"Manufacturing & Wholesale Goods"
        }
    ],
    "sg:phone":"+1 804 353 2511",
    "sg:postcode":"23230",
    "sg:province":"VA",
    "sg:tags":[
        "equipment",
        "electric",
        "supply"
    ],
    "sg:website":"www.richmondelectric.net",
    "wof:name":"Richmond Electric Supply Co",
    "wof:placetype":"venue"
},
  "geometry": {"coordinates":[-77.46528499999999,37.576641],"type":"Point"}
}