{
  "type": "Feature",
  "properties": {
    "iso:country":"US",
    "sg:address":"901 N. Pitt Street, Suite 325",
    "sg:city":"Alexandria",
    "sg:classifiers":[
        {
            "category":"Professional",
            "subcategory":"Computer Services",
            "type":"Services"
        }
    ],
    "sg:postcode":"22314",
    "sg:province":"VA",
    "sg:tags":[
        "imaging",
        "image-processing",
        "photo-processing",
        "image-upload",
        "image-transfer",
        "file-transfer",
        "web-2-0",
        "photo-business",
        "content-delivery"
    ],
    "sg:website":"http://www.aurigma.com",
    "wof:name":"Aurigma",
    "wof:placetype":"venue"
},
  "geometry": {"coordinates":[-77.04255999999999,38.815008],"type":"Point"}
}