{
  "type": "Feature",
  "properties": {
    "addr:full":"4960 Cedar Point Rd Gloucester VA 23061",
    "addr:housenumber":"4960",
    "addr:postcode":"23061",
    "addr:street":"Cedar Point Rd",
    "iso:country":"US",
    "sg:address":"4960 Cedar Point Rd",
    "sg:city":"Gloucester",
    "sg:classifiers":[
        {
            "category":"Freight",
            "type":"Transportation"
        }
    ],
    "sg:phone":"+1 804 693 6973",
    "sg:postcode":"23061",
    "sg:province":"VA",
    "sg:tags":[
        "operator",
        "local",
        "trucking"
    ],
    "wof:name":"Hardwoods Hauling Inc",
    "wof:placetype":"venue"
},
  "geometry": {"coordinates":[-76.591117,37.345937],"type":"Point"}
}