{
  "type": "Feature",
  "properties": {
    "iso:country":"US",
    "sg:address":"134 Tunstall Rd",
    "sg:city":"Danville",
    "sg:classifiers":[
        {
            "category":"Organizations",
            "subcategory":"Community Association",
            "type":"Services"
        }
    ],
    "sg:phone":"+1 434 793 9805",
    "sg:postcode":"24541",
    "sg:province":"VA",
    "sg:tags":[
        "sorority",
        "fraternity"
    ],
    "wof:name":"Scottish Rite Masons",
    "wof:placetype":"venue"
},
  "geometry": {"coordinates":[-79.420834,36.571633],"type":"Point"}
}