{
  "type": "Feature",
  "properties": {
    "addr:full":"1311 Barterbrook Rd Staunton VA 24401",
    "addr:housenumber":"1311",
    "addr:postcode":"24401",
    "addr:street":"Barterbrook Rd",
    "iso:country":"US",
    "sg:address":"1311 Barterbrook Rd",
    "sg:city":"Staunton",
    "sg:classifiers":[
        {
            "category":"Recreation",
            "type":"Entertainment"
        }
    ],
    "sg:phone":"+1 540 885 3798",
    "sg:postcode":"24401",
    "sg:province":"VA",
    "sg:tags":[
        "skating",
        "rink"
    ],
    "wof:name":"Skatetown Headquarters",
    "wof:placetype":"venue"
},
  "geometry": {"coordinates":[-79.062483,38.129084],"type":"Point"}
}