{
  "type": "Feature",
  "properties": {
    "addr:full":"1733 Summit Ave Richmond VA 23230",
    "addr:housenumber":"1733",
    "addr:postcode":"23230",
    "addr:street":"Summit Ave",
    "iso:country":"US",
    "sg:address":"1733 Summit Ave",
    "sg:city":"Richmond",
    "sg:classifiers":[
        {
            "category":"Professional",
            "type":"Services"
        }
    ],
    "sg:phone":"+1 804 775 1048",
    "sg:postcode":"23230",
    "sg:province":"VA",
    "wof:name":"Cellar Selections Inc",
    "wof:placetype":"venue"
},
  "geometry": {"coordinates":[-77.468521,37.569084],"type":"Point"}
}