{
  "type": "Feature",
  "properties": {
    "addr:full":"291 Sunset Park Dr Herndon VA 20170",
    "addr:housenumber":"291",
    "addr:postcode":"20170",
    "addr:street":"Sunset Park Dr",
    "iso:country":"US",
    "sg:address":"291 Sunset Park Dr",
    "sg:city":"Herndon",
    "sg:classifiers":[
        {
            "category":"Restaurant",
            "type":"Food & Drink"
        },
        {
            "category":"Food & Beverages",
            "subcategory":"Groceries & Convenience Stores",
            "type":"Retail Goods"
        }
    ],
    "sg:phone":"+1 703 471 9194",
    "sg:postcode":"20170",
    "sg:province":"VA",
    "sg:tags":[
        "grocer",
        "eating"
    ],
    "wof:name":"Apsara Gourmet Oriental Food",
    "wof:placetype":"venue"
},
  "geometry": {"coordinates":[-77.37413100000001,38.956946],"type":"Point"}
}