{
  "type": "Feature",
  "properties": {
    "iso:country":"US",
    "sg:address":"6616 Scandia Lakes Pl",
    "sg:city":"Sandston",
    "sg:classifiers":[
        {
            "category":"Professional",
            "subcategory":"Business Services",
            "type":"Services"
        }
    ],
    "sg:phone":"+1 804 737 9508",
    "sg:postcode":"23150",
    "sg:province":"VA",
    "wof:name":"Maplehill Associates LLC",
    "wof:placetype":"venue"
},
  "geometry": {"coordinates":[-77.19269,37.481658],"type":"Point"}
}