{
  "type": "Feature",
  "properties": {
    "iso:country":"US",
    "sg:address":"2009 Hanover Ave",
    "sg:city":"Richmond",
    "sg:classifiers":[
        {
            "category":"Professional",
            "subcategory":"Management & Consulting",
            "type":"Services"
        }
    ],
    "sg:phone":"+1 804 358 8020",
    "sg:postcode":"23220",
    "sg:province":"VA",
    "sg:tags":[
        "consultant",
        "business"
    ],
    "wof:name":"Gartner Inc",
    "wof:placetype":"venue"
},
  "geometry": {"coordinates":[-77.46517299999999,37.552902],"type":"Point"}
}