{
  "type": "Feature",
  "properties": {
    "addr:full":"221 Camp Ln Star Tannery VA 22654",
    "addr:housenumber":"221",
    "addr:postcode":"22654",
    "addr:street":"Camp Ln",
    "iso:country":"US",
    "sg:address":"221 Camp Ln",
    "sg:city":"Star Tannery",
    "sg:classifiers":[
        {
            "category":"Travel",
            "subcategory":"Campground",
            "type":"Entertainment"
        }
    ],
    "sg:phone":"+1 540 436 3665",
    "sg:postcode":"22654",
    "sg:province":"VA",
    "sg:tags":[
        "camp"
    ],
    "wof:name":"Camp Paddy Run Of Shenandoah",
    "wof:placetype":"venue"
},
  "geometry": {"coordinates":[-78.46784100000001,39.040973],"type":"Point"}
}