{
  "type": "Feature",
  "properties": {
    "iso:country":"US",
    "sg:address":"1405 E Market St",
    "sg:city":"Charlottesville",
    "sg:classifiers":[
        {
            "category":"Social Services",
            "subcategory":"Child Care",
            "type":"Services"
        },
        {
            "category":"Education",
            "subcategory":"Preschool",
            "type":"Public Place"
        },
        {
            "category":"Education",
            "subcategory":"School",
            "type":"Public Place"
        }
    ],
    "sg:phone":"+1 434 979 9867",
    "sg:postcode":"22902",
    "sg:province":"VA",
    "sg:tags":[
        "elementary",
        "day"
    ],
    "wof:name":"Living Stones Montessori Christian Preschool",
    "wof:placetype":"venue"
},
  "geometry": {"coordinates":[-78.463097,38.0247],"type":"Point"}
}