{
  "type": "Feature",
  "properties": {
    "addr:full":"14334 Compton Village Dr Centreville VA 20121",
    "addr:housenumber":"14334",
    "addr:postcode":"20121",
    "addr:street":"Compton Village Dr",
    "iso:country":"US",
    "sg:address":"14334 Compton Village Dr",
    "sg:city":"Centreville",
    "sg:classifiers":[
        {
            "category":"Retail",
            "subcategory":"Repair Shop",
            "type":"Services"
        }
    ],
    "sg:phone":"+1 703 335 2085",
    "sg:postcode":"20121",
    "sg:province":"VA",
    "wof:name":"A Quality Finish",
    "wof:placetype":"venue"
},
  "geometry": {"coordinates":[-77.44036,38.817802],"type":"Point"}
}