{
  "type": "Feature",
  "properties": {
    "iso:country":"US",
    "sg:address":"4160 Pleasant Valley Rd",
    "sg:city":"Chantilly",
    "sg:classifiers":[
        {
            "category":"Banks & Credit Unions",
            "subcategory":"Bank",
            "type":"Services"
        }
    ],
    "sg:phone":"+1 703 378 5200",
    "sg:postcode":"20151",
    "sg:province":"VA",
    "wof:name":"First Financial Bank",
    "wof:placetype":"venue"
},
  "geometry": {"coordinates":[-77.473067,38.907569],"type":"Point"}
}