{
  "type": "Feature",
  "properties": {
    "addr:full":"929 Upper Hastings Way Virginia Beach VA 23452",
    "addr:housenumber":"929",
    "addr:postcode":"23452",
    "addr:street":"Upper Hastings Way",
    "iso:country":"US",
    "sg:address":"929 Upper Hastings Way",
    "sg:city":"Virginia Beach",
    "sg:classifiers":[
        {
            "category":"Real Estate",
            "subcategory":"Real Estate Operator",
            "type":"Services"
        }
    ],
    "sg:phone":"+1 757 340 7035",
    "sg:postcode":"23452",
    "sg:province":"VA",
    "sg:tags":[
        "building",
        "nonresidential"
    ],
    "wof:name":"Island Wharf Company Inc",
    "wof:placetype":"venue"
},
  "geometry": {"coordinates":[-76.083046,36.873782],"type":"Point"}
}