{
  "type": "Feature",
  "properties": {
    "addr:full":"17521 Mahogany Dr Abingdon VA 24210",
    "addr:housenumber":"17521",
    "addr:postcode":"24210",
    "addr:street":"Mahogany Dr",
    "iso:country":"US",
    "sg:address":"17521 Mahogany Dr",
    "sg:city":"Abingdon",
    "sg:classifiers":[
        {
            "category":"Shopping",
            "subcategory":"Gifts & Souvenirs",
            "type":"Retail Goods"
        }
    ],
    "sg:phone":"+1 276 628 4692",
    "sg:postcode":"24210",
    "sg:province":"VA",
    "wof:name":"Sprys Quality Gifts",
    "wof:placetype":"venue"
},
  "geometry": {"coordinates":[-82.058071,36.678717],"type":"Point"}
}