{
  "type": "Feature",
  "properties": {
    "addr:full":"11535 Nuckols Rd Glen Allen VA 23059",
    "addr:housenumber":"11535",
    "addr:postcode":"23059",
    "addr:street":"Nuckols Rd",
    "iso:country":"US",
    "sg:address":"11535 Nuckols Rd",
    "sg:city":"Glen Allen",
    "sg:classifiers":[
        {
            "category":"Professional",
            "subcategory":"Accounting & Tax Preparation",
            "type":"Services"
        }
    ],
    "sg:phone":"+1 804 290 0896",
    "sg:postcode":"23059",
    "sg:province":"VA",
    "sg:tags":[
        "accountant"
    ],
    "wof:name":"S R Accounting Svc",
    "wof:placetype":"venue"
},
  "geometry": {"coordinates":[-77.59314500000001,37.688086],"type":"Point"}
}