{
  "type": "Feature",
  "properties": {
    "iso:country":"US",
    "sg:address":"404 Elden St",
    "sg:city":"Herndon",
    "sg:phone":"+1 703 574 3746",
    "sg:postcode":"20170",
    "sg:province":"VA",
    "sg:website":"http://www.kitchentablesandchairs.com",
    "wof:name":"Dinettes & Stools",
    "wof:placetype":"venue"
},
  "geometry": {"coordinates":[-77.375214,38.967775],"type":"Point"}
}