{
  "type": "Feature",
  "properties": {
    "addr:full":"12814 Mill Rd Fredericksburg VA 22407",
    "addr:housenumber":"12814",
    "addr:postcode":"22407",
    "addr:street":"Mill Rd",
    "iso:country":"US",
    "sg:address":"12814 Mill Rd",
    "sg:city":"Fredericksburg",
    "sg:classifiers":[
        {
            "category":"Professional",
            "subcategory":"Accounting & Tax Preparation",
            "type":"Services"
        }
    ],
    "sg:phone":"+1 540 786 4090",
    "sg:postcode":"22407",
    "sg:province":"VA",
    "wof:name":"T C Steiniger",
    "wof:placetype":"venue"
},
  "geometry": {"coordinates":[-77.576983,38.304519],"type":"Point"}
}