{
  "type": "Feature",
  "properties": {
    "addr:full":"541 Tazewell Ave Cape Charles VA 23310",
    "addr:housenumber":"541",
    "addr:postcode":"charles;23310",
    "addr:street":"Tazewell Ave",
    "iso:country":"US",
    "sg:address":"541 Tazewell Ave",
    "sg:city":"Cape Charles",
    "sg:classifiers":[
        {
            "category":"Professional",
            "subcategory":"Management & Consulting",
            "type":"Services"
        }
    ],
    "sg:phone":"+1 757 331 4088",
    "sg:postcode":"23310",
    "sg:province":"VA",
    "sg:tags":[
        "construction"
    ],
    "wof:name":"Hoffman Co Constr Management",
    "wof:placetype":"venue"
},
  "geometry": {"coordinates":[-76.01372000000001,37.269173],"type":"Point"}
}