{
  "type": "Feature",
  "properties": {
    "iso:country":"US",
    "sg:address":"31 Winchester St",
    "sg:city":"Warrenton",
    "sg:classifiers":[
        {
            "category":"Professional",
            "subcategory":"Lawyer & Legal Services",
            "type":"Services"
        }
    ],
    "sg:phone":"+1 540 347 9223",
    "sg:postcode":"20186",
    "sg:province":"VA",
    "wof:name":"Robinson Whitson W Attorney",
    "wof:placetype":"venue"
},
  "geometry": {"coordinates":[-77.79589799999999,38.714699],"type":"Point"}
}