{
  "type": "Feature",
  "properties": {
    "addr:full":"202 S Randolph St Lexington VA 24450",
    "addr:housenumber":"202",
    "addr:postcode":"24450",
    "addr:street":"S Randolph St",
    "iso:country":"US",
    "sg:address":"202 S Randolph St",
    "sg:city":"Lexington",
    "sg:classifiers":[
        {
            "category":"Professional",
            "subcategory":"Lawyer & Legal Services",
            "type":"Services"
        }
    ],
    "sg:phone":"+1 540 463 6016",
    "sg:postcode":"24450",
    "sg:province":"VA",
    "wof:name":"Thomas Tomy",
    "wof:placetype":"venue"
},
  "geometry": {"coordinates":[-79.444124,37.781821],"type":"Point"}
}