{
  "type": "Feature",
  "properties": {
    "addr:full":"1715 N George Mason Dr Arlington VA 22205",
    "addr:housenumber":"1715",
    "addr:postcode":"22205",
    "addr:street":"N George Mason Dr",
    "iso:country":"US",
    "sg:address":"1715 N George Mason Dr",
    "sg:city":"Arlington",
    "sg:classifiers":[
        {
            "category":"Health Services",
            "subcategory":"Doctor",
            "type":"Services"
        }
    ],
    "sg:phone":"+1 703 525 0844",
    "sg:postcode":"22205",
    "sg:province":"VA",
    "wof:name":"Foxhall Surgical Associates",
    "wof:placetype":"venue"
},
  "geometry": {"coordinates":[-77.12869999999999,38.889099],"type":"Point"}
}