{
  "type": "Feature",
  "properties": {
    "iso:country":"US",
    "sg:address":"377 Maple Ave W",
    "sg:city":"Vienna",
    "sg:classifiers":[
        {
            "category":"Restaurant",
            "type":"Food & Drink"
        }
    ],
    "sg:menulink":"http://www.allmenus.com/va/hunter-mill/280574-amphora-restaurant/menu/",
    "sg:phone":"+1 703 938 7877",
    "sg:postcode":"22180",
    "sg:province":"VA",
    "sg:tags":[
        "new",
        "american"
    ],
    "wof:name":"Amphora Restaurant",
    "wof:placetype":"venue"
},
  "geometry": {"coordinates":[-77.27228100000001,38.896556],"type":"Point"}
}