{
  "type": "Feature",
  "properties": {
    "addr:full":"736 Leigh Mill Rd Great Falls VA 22066",
    "addr:housenumber":"736",
    "addr:postcode":"22066",
    "addr:street":"Leigh Mill Rd",
    "iso:country":"US",
    "sg:address":"736 Leigh Mill Rd",
    "sg:city":"Great Falls",
    "sg:classifiers":[
        {
            "category":"Retail",
            "subcategory":"Animal Services",
            "type":"Services"
        }
    ],
    "sg:phone":"+1 703 759 9009",
    "sg:postcode":"22066",
    "sg:province":"VA",
    "sg:tags":[
        "boarding",
        "horse"
    ],
    "wof:name":"Rokeby Farm Stables",
    "wof:placetype":"venue"
},
  "geometry": {"coordinates":[-77.27441899999999,38.9898],"type":"Point"}
}