{
  "type": "Feature",
  "properties": {
    "iso:country":"US",
    "sg:address":"1400 Melbourne Rd",
    "sg:city":"Charlottesville",
    "sg:classifiers":[
        {
            "category":"Education",
            "subcategory":"School",
            "type":"Public Place"
        }
    ],
    "sg:phone":"+1 434 296 5131",
    "sg:postcode":"22901",
    "sg:province":"VA",
    "wof:name":"Charlottesville High School",
    "wof:placetype":"venue"
},
  "geometry": {"coordinates":[-78.472976,38.053385],"type":"Point"}
}