{
  "type": "Feature",
  "properties": {
    "addr:full":"2200 Wilson Blvd Arlington VA 22201",
    "addr:housenumber":"2200",
    "addr:postcode":"22201",
    "addr:street":"Wilson Blvd",
    "iso:country":"US",
    "sg:address":"2200 Wilson Blvd",
    "sg:city":"Arlington",
    "sg:classifiers":[
        {
            "category":"Shopping",
            "subcategory":"Clothing, Apparel, & Fashions",
            "type":"Retail Goods"
        },
        {
            "category":"Personal",
            "type":"Services"
        }
    ],
    "sg:phone":"+1 703 525 3377",
    "sg:postcode":"22201",
    "sg:province":"VA",
    "sg:tags":[
        "tailoring",
        "tailor",
        "alteration",
        "wedding"
    ],
    "wof:name":"Young's Tailors",
    "wof:placetype":"venue"
},
  "geometry": {"coordinates":[-77.085808,38.89122],"type":"Point"}
}