{
  "type": "Feature",
  "properties": {
    "iso:country":"US",
    "sg:address":"11610 Plaza America Dr",
    "sg:city":"Reston",
    "sg:classifiers":[
        {
            "category":"Coffee & Tea",
            "type":"Food & Drink"
        }
    ],
    "sg:menulink":"http://www.allmenus.com/va/hunter-mill/112069-starbucks-coffee/menu/",
    "sg:phone":"+1 703 481 3485",
    "sg:postcode":"20190",
    "sg:province":"VA",
    "sg:tags":[
        "american"
    ],
    "wof:name":"Starbucks Coffee",
    "wof:placetype":"venue"
},
  "geometry": {"coordinates":[-77.349667,38.953682],"type":"Point"}
}