{
  "type": "Feature",
  "properties": {
    "addr:full":"3041 N Frederick Pike Winchester VA 22603",
    "addr:housenumber":"3041",
    "addr:postcode":"22603",
    "addr:street":"N Frederick Pike",
    "iso:country":"US",
    "sg:address":"3041 N Frederick Pike",
    "sg:city":"Winchester",
    "sg:classifiers":[
        {
            "category":"Professional",
            "subcategory":"Computer Services",
            "type":"Services"
        }
    ],
    "sg:phone":"+1 540 545 8006",
    "sg:postcode":"22603",
    "sg:province":"VA",
    "sg:tags":[
        "programing",
        "custom"
    ],
    "wof:name":"Visual Control Systems Inc",
    "wof:placetype":"venue"
},
  "geometry": {"coordinates":[-78.202378,39.24467],"type":"Point"}
}