{
  "type": "Feature",
  "properties": {
    "addr:full":"2774 Burrough Hill Ln Woodbridge VA 22191",
    "addr:housenumber":"2774",
    "addr:postcode":"22191",
    "addr:street":"Burrough Hill Ln",
    "iso:country":"US",
    "sg:address":"2774 Burrough Hill Ln",
    "sg:city":"Woodbridge",
    "sg:classifiers":[
        {
            "category":"Organizations",
            "subcategory":"Religious Organization",
            "type":"Services"
        }
    ],
    "sg:phone":"+1 703 221 7541",
    "sg:postcode":"22191",
    "sg:province":"VA",
    "wof:name":"Word Alive Ministry",
    "wof:placetype":"venue"
},
  "geometry": {"coordinates":[-77.299588,38.580205],"type":"Point"}
}