{
  "type": "Feature",
  "properties": {
    "addr:full":"517 Kempsville Rd Chesapeake VA 23320",
    "addr:housenumber":"517",
    "addr:postcode":"23320",
    "addr:street":"Kempsville Rd",
    "iso:country":"US",
    "sg:address":"517 Kempsville Rd",
    "sg:city":"Chesapeake",
    "sg:classifiers":[
        {
            "category":"Education",
            "subcategory":"Dance Studio",
            "type":"Public Place"
        }
    ],
    "sg:phone":"+1 757 361 9400",
    "sg:postcode":"23320",
    "sg:province":"VA",
    "sg:tags":[
        "instruction",
        "dancing"
    ],
    "wof:name":"Chesapeake Dance Center",
    "wof:placetype":"venue"
},
  "geometry": {"coordinates":[-76.221912,36.744052],"type":"Point"}
}