{
  "type": "Feature",
  "properties": {
    "iso:country":"US",
    "sg:address":"1303 Vincent Pl",
    "sg:city":"Mc Lean",
    "sg:classifiers":[
        {
            "category":"Insurance",
            "subcategory":"Insurance Agent",
            "type":"Services"
        }
    ],
    "sg:phone":"+1 703 790 8690",
    "sg:postcode":"22101",
    "sg:province":"VA",
    "sg:tags":[
        "broker"
    ],
    "wof:name":"Kelso Risk Management Inc",
    "wof:placetype":"venue"
},
  "geometry": {"coordinates":[-77.18073,38.936599],"type":"Point"}
}