{
  "type": "Feature",
  "properties": {
    "addr:full":"6910 Spelman Dr Springfield VA 22153",
    "addr:housenumber":"6910",
    "addr:postcode":"22153",
    "addr:street":"Spelman Dr",
    "iso:country":"US",
    "sg:address":"6910 Spelman Dr",
    "sg:city":"Springfield",
    "sg:classifiers":[
        {
            "category":"Freight",
            "type":"Transportation"
        }
    ],
    "sg:phone":"+1 703 912 3619",
    "sg:postcode":"22153",
    "sg:province":"VA",
    "sg:tags":[
        "operator",
        "trucking"
    ],
    "wof:name":"Mj Express",
    "wof:placetype":"venue"
},
  "geometry": {"coordinates":[-77.25314299999999,38.763244],"type":"Point"}
}