{
  "type": "Feature",
  "properties": {
    "addr:full":"15610 Cosby Rd Chesterfield VA 23832",
    "addr:housenumber":"15610",
    "addr:postcode":"23832",
    "addr:street":"Cosby Rd",
    "iso:country":"US",
    "sg:address":"15610 Cosby Rd",
    "sg:city":"Chesterfield",
    "sg:classifiers":[
        {
            "category":"Building & Trades",
            "subcategory":"Construction",
            "type":"Services"
        }
    ],
    "sg:phone":"+1 804 639 1007",
    "sg:postcode":"23832",
    "sg:province":"VA",
    "sg:tags":[
        "house"
    ],
    "wof:name":"English Construction Co",
    "wof:placetype":"venue"
},
  "geometry": {"coordinates":[-77.702572,37.402278],"type":"Point"}
}