{
  "type": "Feature",
  "properties": {
    "iso:country":"US",
    "sg:address":"3104 Duke St",
    "sg:city":"Alexandria",
    "sg:classifiers":[
        {
            "category":"Shopping",
            "subcategory":"Crafts & Fabrics",
            "type":"Retail Goods"
        }
    ],
    "sg:phone":"+1 703 751 9193",
    "sg:postcode":"22314",
    "sg:province":"VA",
    "sg:tags":[
        "shop",
        "art",
        "supply"
    ],
    "wof:name":"De Varis Needlepoint Finishing",
    "wof:placetype":"venue"
},
  "geometry": {"coordinates":[-77.083826,38.807762],"type":"Point"}
}