{
  "type": "Feature",
  "properties": {
    "iso:country":"US",
    "sg:address":"823 College Ave",
    "sg:city":"Fredericksburg",
    "sg:classifiers":[
        {
            "category":"Professional",
            "type":"Services"
        }
    ],
    "sg:phone":"+1 540 654 5329",
    "sg:postcode":"22401",
    "sg:province":"VA",
    "wof:name":"Colonial Colors Inc",
    "wof:placetype":"venue"
},
  "geometry": {"coordinates":[-77.472649,38.296978],"type":"Point"}
}