{
  "type": "Feature",
  "properties": {
    "iso:country":"US",
    "sg:address":"6060 Wilson Blvd",
    "sg:city":"Arlington",
    "sg:classifiers":[
        {
            "category":"Park",
            "type":"Public Place"
        },
        {
            "category":"Landmark",
            "subcategory":"Tourist Information",
            "type":"Public Place"
        }
    ],
    "sg:phone":"+1 703 237 4953",
    "sg:postcode":"22205",
    "sg:province":"VA",
    "sg:tags":[
        "attraction"
    ],
    "wof:name":"Upton Hill Regional Park",
    "wof:placetype":"venue"
},
  "geometry": {"coordinates":[-77.142585,38.873162],"type":"Point"}
}