{
  "type": "Feature",
  "properties": {
    "addr:full":"116 Embrey Mill Rd Stafford VA 22554",
    "addr:housenumber":"116",
    "addr:postcode":"22554",
    "addr:street":"Embrey Mill Rd",
    "iso:country":"US",
    "sg:address":"116 Embrey Mill Rd",
    "sg:city":"Stafford",
    "sg:classifiers":[
        {
            "category":"Building & Trades",
            "subcategory":"Construction",
            "type":"Services"
        }
    ],
    "sg:phone":"+1 540 659 1064",
    "sg:postcode":"22554",
    "sg:province":"VA",
    "sg:tags":[
        "contractor"
    ],
    "wof:name":"Authentic Construction & Remodeling",
    "wof:placetype":"venue"
},
  "geometry": {"coordinates":[-77.445296,38.447548],"type":"Point"}
}