{
  "type": "Feature",
  "properties": {
    "addr:full":"13800 Westfield Rd Midlothian VA 23113",
    "addr:housenumber":"13800",
    "addr:postcode":"23113",
    "addr:street":"Westfield Rd",
    "iso:country":"US",
    "sg:address":"13800 Westfield Rd",
    "sg:city":"Midlothian",
    "sg:classifiers":[
        {
            "category":"Organizations",
            "subcategory":"Religious Organization",
            "type":"Services"
        }
    ],
    "sg:phone":"+1 804 794 5583",
    "sg:postcode":"23113",
    "sg:province":"VA",
    "sg:tags":[
        "church"
    ],
    "wof:name":"First Bapt Church-Midlothian",
    "wof:placetype":"venue"
},
  "geometry": {"coordinates":[-77.655433,37.507807],"type":"Point"}
}