{
  "type": "Feature",
  "properties": {
    "addr:full":"607 E Jubal Early Dr Winchester VA 22601",
    "addr:housenumber":"607",
    "addr:postcode":"22601",
    "addr:street":"E;Early Dr",
    "iso:country":"US",
    "sg:address":"607 E Jubal Early Dr",
    "sg:city":"Winchester",
    "sg:classifiers":[
        {
            "category":"Health Services",
            "subcategory":"Hospital",
            "type":"Services"
        }
    ],
    "sg:phone":"+1 540 536 2232",
    "sg:postcode":"22601",
    "sg:province":"VA",
    "wof:name":"Urgent Care Ctr",
    "wof:placetype":"venue"
},
  "geometry": {"coordinates":[-78.16483100000001,39.16543],"type":"Point"}
}