{
  "type": "Feature",
  "properties": {
    "addr:full":"4603 May Hunt Ct Alexandria VA 22312",
    "addr:housenumber":"4603",
    "addr:postcode":"22312",
    "addr:street":"May Hunt Ct",
    "iso:country":"US",
    "sg:address":"4603 May Hunt Ct",
    "sg:city":"Alexandria",
    "sg:classifiers":[
        {
            "category":"Professional",
            "subcategory":"Research",
            "type":"Services"
        }
    ],
    "sg:phone":"+1 703 256 3778",
    "sg:postcode":"22312",
    "sg:province":"VA",
    "sg:tags":[
        "market"
    ],
    "wof:name":"Stea Research",
    "wof:placetype":"venue"
},
  "geometry": {"coordinates":[-77.168261,38.822544],"type":"Point"}
}