{
  "type": "Feature",
  "properties": {
    "iso:country":"US",
    "sg:address":"13284 Warwick Blvd",
    "sg:city":"Newport News",
    "sg:classifiers":[
        {
            "category":"Shopping",
            "subcategory":"Clothing, Apparel, & Fashions",
            "type":"Retail Goods"
        }
    ],
    "sg:phone":"+1 757 877 1148",
    "sg:postcode":"23602",
    "sg:province":"VA",
    "wof:name":"Fashion Max",
    "wof:placetype":"venue"
},
  "geometry": {"coordinates":[-76.51796899999999,37.112435],"type":"Point"}
}