{
  "type": "Feature",
  "properties": {
    "addr:full":"412 W Washington St Suffolk VA 23434",
    "addr:housenumber":"412",
    "addr:postcode":"23434",
    "addr:street":"W Washington St",
    "iso:country":"US",
    "sg:address":"412 W Washington St",
    "sg:city":"Suffolk",
    "sg:classifiers":[
        {
            "category":"Autos & Motor Vehicles",
            "subcategory":"Auto Supplies",
            "type":"Retail Goods"
        },
        {
            "category":"Shopping",
            "subcategory":"Computers & Home Electronics",
            "type":"Retail Goods"
        }
    ],
    "sg:phone":"+1 757 539 6142",
    "sg:postcode":"23434",
    "sg:province":"VA",
    "sg:tags":[
        "automobile",
        "stereo",
        "radio"
    ],
    "wof:name":"Underground Sound",
    "wof:placetype":"venue"
},
  "geometry": {"coordinates":[-76.58778100000001,36.729531],"type":"Point"}
}