{
  "type": "Feature",
  "properties": {
    "iso:country":"US",
    "sg:address":"3405 Candlers Mountain Rd",
    "sg:city":"Lynchburg",
    "sg:classifiers":[
        {
            "category":"Shopping",
            "subcategory":"Jewelry",
            "type":"Retail Goods"
        }
    ],
    "sg:phone":"+1 434 239 8673",
    "sg:postcode":"24502",
    "sg:province":"VA",
    "sg:tags":[
        "jeweler"
    ],
    "wof:name":"Friedman's",
    "wof:placetype":"venue"
},
  "geometry": {"coordinates":[-79.17427000000001,37.366787],"type":"Point"}
}