{
  "type": "Feature",
  "properties": {
    "iso:country":"US",
    "sg:address":"4312 Sandy Bay Dr",
    "sg:city":"Virginia Beach",
    "sg:classifiers":[
        {
            "category":"Building & Trades",
            "subcategory":"Construction",
            "type":"Services"
        }
    ],
    "sg:phone":"+1 757 460 6110",
    "sg:postcode":"23455",
    "sg:province":"VA",
    "sg:tags":[
        "general",
        "contractor"
    ],
    "wof:name":"Francavilla Building Co",
    "wof:placetype":"venue"
},
  "geometry": {"coordinates":[-76.120051,36.914913],"type":"Point"}
}