{
  "type": "Feature",
  "properties": {
    "addr:full":"7145 Staples Mill Rd Richmond VA 23228",
    "addr:housenumber":"7145",
    "addr:postcode":"23228",
    "addr:street":"Staples Mill Rd",
    "iso:country":"US",
    "sg:address":"7145 Staples Mill Rd",
    "sg:city":"Richmond",
    "sg:classifiers":[
        {
            "category":"Personal",
            "subcategory":"Shoe Repair & Shine",
            "type":"Services"
        }
    ],
    "sg:phone":"+1 804 261 5927",
    "sg:postcode":"23228",
    "sg:province":"VA",
    "sg:tags":[
        "repairing",
        "parlor",
        "boot"
    ],
    "wof:name":"Dumbarton Shoe Repair & Altrtn",
    "wof:placetype":"venue"
},
  "geometry": {"coordinates":[-77.497736,37.615794],"type":"Point"}
}