{
  "type": "Feature",
  "properties": {
    "iso:country":"US",
    "sg:address":"2201 W Broad St Ste 108",
    "sg:city":"Richmond",
    "sg:classifiers":[
        {
            "category":"Professional",
            "subcategory":"Art Services",
            "type":"Services"
        },
        {
            "category":"Professional",
            "subcategory":"Business Services",
            "type":"Services"
        }
    ],
    "sg:phone":"+1 804 354 5335",
    "sg:postcode":"23220",
    "sg:province":"VA",
    "sg:tags":[
        "development",
        "product",
        "graphic",
        "designers-industrial",
        "marketing",
        "commercial",
        "designer",
        "design"
    ],
    "sg:website":"http://www.meganck.com",
    "wof:name":"Communication Design Inc",
    "wof:placetype":"venue"
},
  "geometry": {"coordinates":[-77.46241000000001,37.557861],"type":"Point"}
}