{
  "type": "Feature",
  "properties": {
    "addr:full":"10710 Courthouse Rd Charles City VA 23030",
    "addr:housenumber":"10710",
    "addr:postcode":"23030",
    "addr:street":"Courthouse Rd",
    "iso:country":"US",
    "sg:address":"10710 Courthouse Rd",
    "sg:city":"Charles City",
    "sg:classifiers":[
        {
            "category":"Government",
            "subcategory":"Court House",
            "type":"Public Place"
        }
    ],
    "sg:phone":"+1 804 829 9215",
    "sg:postcode":"23030",
    "sg:province":"VA",
    "sg:tags":[
        "county",
        "counsel"
    ],
    "wof:name":"Charles City County Attorney",
    "wof:placetype":"venue"
},
  "geometry": {"coordinates":[-77.071853,37.342686],"type":"Point"}
}