{
  "type": "Feature",
  "properties": {
    "addr:full":"3538 Echo Valley Rd Barboursville VA 22923",
    "addr:housenumber":"3538",
    "addr:postcode":"22923",
    "addr:street":"Echo Valley Rd",
    "iso:country":"US",
    "sg:address":"3538 Echo Valley Rd",
    "sg:city":"Barboursville",
    "sg:classifiers":[
        {
            "category":"Home & Garden",
            "subcategory":"Furniture",
            "type":"Retail Goods"
        }
    ],
    "sg:phone":"+1 540 832 3935",
    "sg:postcode":"22923",
    "sg:province":"VA",
    "sg:tags":[
        "cabinet"
    ],
    "wof:name":"Blue Run Cabinet Shop",
    "wof:placetype":"venue"
},
  "geometry": {"coordinates":[-78.300219,38.133953],"type":"Point"}
}