{
  "type": "Feature",
  "properties": {
    "addr:full":"45367 Gable Sq Sterling VA 20164",
    "addr:housenumber":"45367",
    "addr:postcode":"20164",
    "addr:street":"Gable Sq",
    "iso:country":"US",
    "sg:address":"45367 Gable Sq",
    "sg:city":"Sterling",
    "sg:classifiers":[
        {
            "category":"Organizations",
            "subcategory":"Religious Organization",
            "type":"Services"
        }
    ],
    "sg:phone":"+1 703 444 1529",
    "sg:postcode":"20164",
    "sg:province":"VA",
    "wof:name":"Faith Comini",
    "wof:placetype":"venue"
},
  "geometry": {"coordinates":[-77.428594,39.001758],"type":"Point"}
}