{
  "type": "Feature",
  "properties": {
    "addr:full":"2546 S Crater Rd Petersburg VA 23805",
    "addr:housenumber":"2546",
    "addr:postcode":"23805",
    "addr:street":"S Crater Rd",
    "iso:country":"US",
    "sg:address":"2546 S Crater Rd",
    "sg:city":"Petersburg",
    "sg:classifiers":[
        {
            "category":"Banks & Credit Unions",
            "subcategory":"Bank",
            "type":"Services"
        }
    ],
    "sg:phone":"+1 804 862 1229",
    "sg:postcode":"23805",
    "sg:province":"VA",
    "sg:tags":[
        "depository",
        "banking"
    ],
    "wof:name":"E Z Check Cashing",
    "wof:placetype":"venue"
},
  "geometry": {"coordinates":[-77.376606,37.196839],"type":"Point"}
}