{
  "type": "Feature",
  "properties": {
    "addr:full":"10210 Marsh Rd Bealeton VA 22712",
    "addr:housenumber":"10210",
    "addr:postcode":"22712",
    "addr:street":"Marsh Rd",
    "iso:country":"US",
    "sg:address":"10210 Marsh Rd",
    "sg:city":"Bealeton",
    "sg:classifiers":[
        {
            "category":"Personal",
            "type":"Services"
        }
    ],
    "sg:phone":"+1 540 439 6007",
    "sg:postcode":"22712",
    "sg:province":"VA",
    "sg:tags":[
        "mover"
    ],
    "wof:name":"Adam's Moving and Storage Inc",
    "wof:placetype":"venue"
},
  "geometry": {"coordinates":[-77.79540299999999,38.615898],"type":"Point"}
}