{
  "type": "Feature",
  "properties": {
    "addr:full":"104 Selma Dr Winchester VA 22601",
    "addr:housenumber":"104",
    "addr:postcode":"22601",
    "addr:street":"Selma Dr",
    "iso:country":"US",
    "sg:address":"104 Selma Dr",
    "sg:city":"Winchester",
    "sg:classifiers":[
        {
            "category":"Health Services",
            "subcategory":"Doctor",
            "type":"Services"
        }
    ],
    "sg:phone":"+1 540 678 2800",
    "sg:postcode":"22601",
    "sg:province":"VA",
    "sg:tags":[
        "medical"
    ],
    "wof:name":"Gaither Neal MD",
    "wof:placetype":"venue"
},
  "geometry": {"coordinates":[-78.17312099999999,39.188796],"type":"Point"}
}