{
  "type": "Feature",
  "properties": {
    "addr:full":"13916 Hardy Rd Hardy VA 24101",
    "addr:housenumber":"13916",
    "addr:postcode":"24101",
    "addr:street":"Hardy Rd",
    "iso:country":"US",
    "sg:address":"13916 Hardy Rd",
    "sg:city":"Hardy",
    "sg:classifiers":[
        {
            "category":"Building & Trades",
            "subcategory":"Construction",
            "type":"Services"
        }
    ],
    "sg:phone":"+1 540 890 6881",
    "sg:postcode":"24101",
    "sg:province":"VA",
    "sg:tags":[
        "demolition",
        "contractor"
    ],
    "wof:name":"R & R Contractors LTD",
    "wof:placetype":"venue"
},
  "geometry": {"coordinates":[-79.803264,37.221022],"type":"Point"}
}