{
  "type": "Feature",
  "properties": {
    "iso:country":"US",
    "sg:address":"5201 Leesburg Pike",
    "sg:city":"Falls Church",
    "sg:classifiers":[
        {
            "category":"Health Services",
            "subcategory":"Doctor",
            "type":"Services"
        }
    ],
    "sg:phone":"+1 703 998 8000",
    "sg:postcode":"22041",
    "sg:province":"VA",
    "sg:tags":[
        "medical"
    ],
    "wof:name":"Friedlis Mayo",
    "wof:placetype":"venue"
},
  "geometry": {"coordinates":[-77.11769700000001,38.845717],"type":"Point"}
}