{
  "type": "Feature",
  "properties": {
    "addr:full":"1634 Fairfax Dr Virginia Beach VA 23453",
    "addr:housenumber":"1634",
    "addr:postcode":"23453",
    "addr:street":"Fairfax Dr",
    "iso:country":"US",
    "sg:address":"1634 Fairfax Dr",
    "sg:city":"Virginia Beach",
    "sg:classifiers":[
        {
            "category":"Building & Trades",
            "subcategory":"Construction",
            "type":"Services"
        }
    ],
    "sg:phone":"+1 757 749 9040",
    "sg:postcode":"23453",
    "sg:province":"VA",
    "sg:tags":[
        "house"
    ],
    "wof:name":"Johnsons Home Repair",
    "wof:placetype":"venue"
},
  "geometry": {"coordinates":[-76.108422,36.793394],"type":"Point"}
}