{
  "type": "Feature",
  "properties": {
    "addr:full":"312 Creek Rd Front Royal VA 22630",
    "addr:housenumber":"312",
    "addr:postcode":"22630",
    "addr:street":"Creek Rd",
    "iso:country":"US",
    "sg:address":"312 Creek Rd",
    "sg:city":"Front Royal",
    "sg:classifiers":[
        {
            "category":"Autos & Motor Vehicles",
            "subcategory":"Recreational Vehicle Sales",
            "type":"Retail Goods"
        }
    ],
    "sg:phone":"+1 540 636 2712",
    "sg:postcode":"22630",
    "sg:province":"VA",
    "wof:name":"Pro Kart Motorsport Inc",
    "wof:placetype":"venue"
},
  "geometry": {"coordinates":[-78.146822,38.873131],"type":"Point"}
}