{
  "type": "Feature",
  "properties": {
    "iso:country":"US",
    "sg:address":"372 S Main St",
    "sg:city":"Timberville",
    "sg:classifiers":[
        {
            "category":"Autos & Motor Vehicles",
            "subcategory":"Automobile Sales",
            "type":"Retail Goods"
        }
    ],
    "sg:phone":"+1 540 901 9600",
    "sg:postcode":"22853",
    "sg:province":"VA",
    "sg:tags":[
        "used"
    ],
    "wof:name":"Evans Auto Sales",
    "wof:placetype":"venue"
},
  "geometry": {"coordinates":[-78.777817,38.630204],"type":"Point"}
}