{
  "type": "Feature",
  "properties": {
    "addr:full":"14700 Potomac Mills Rd Woodbridge VA 22192",
    "addr:housenumber":"14700",
    "addr:postcode":"22192",
    "addr:street":"Potomac Mills Rd",
    "iso:country":"US",
    "sg:address":"14700 Potomac Mills Rd",
    "sg:city":"Woodbridge",
    "sg:classifiers":[
        {
            "category":"Local Transit",
            "type":"Transportation"
        }
    ],
    "sg:phone":"+1 703 583 0950",
    "sg:postcode":"22192",
    "sg:province":"VA",
    "wof:name":"Washington Metropolitan Area",
    "wof:placetype":"venue"
},
  "geometry": {"coordinates":[-77.297984,38.634643],"type":"Point"}
}