{
  "type": "Feature",
  "properties": {
    "iso:country":"US",
    "sg:address":"4600 Fairfax Dr",
    "sg:city":"Arlington",
    "sg:classifiers":[
        {
            "category":"Building & Trades",
            "subcategory":"Construction",
            "type":"Services"
        },
        {
            "category":"Real Estate",
            "subcategory":"Architect",
            "type":"Services"
        }
    ],
    "sg:phone":"+1 703 528 1150",
    "sg:postcode":"22203",
    "sg:province":"VA",
    "sg:tags":[
        "interior",
        "design"
    ],
    "wof:name":"Kerns Group Architects",
    "wof:placetype":"venue"
},
  "geometry": {"coordinates":[-77.113297,38.875702],"type":"Point"}
}