{
  "type": "Feature",
  "properties": {
    "addr:full":"10682 Wakemen Ct Manassas VA 20110",
    "addr:housenumber":"10682",
    "addr:postcode":"20110",
    "addr:street":"Wakemen Ct",
    "iso:country":"US",
    "sg:address":"10682 Wakemen Ct",
    "sg:city":"Manassas",
    "sg:classifiers":[
        {
            "category":"Wholesale",
            "subcategory":"Chemicals & Plastics",
            "type":"Manufacturing & Wholesale Goods"
        }
    ],
    "sg:phone":"+1 703 392 0200",
    "sg:postcode":"20110",
    "sg:province":"VA",
    "wof:name":"P C I Co",
    "wof:placetype":"venue"
},
  "geometry": {"coordinates":[-77.519339,38.734563],"type":"Point"}
}