{
  "type": "Feature",
  "properties": {
    "addr:full":"8956 Miles Pl Manassas VA 20110",
    "addr:housenumber":"8956",
    "addr:postcode":"20110",
    "addr:street":"Miles Pl",
    "iso:country":"US",
    "sg:address":"8956 Miles Pl",
    "sg:city":"Manassas",
    "sg:classifiers":[
        {
            "category":"Building & Trades",
            "subcategory":"Construction",
            "type":"Services"
        }
    ],
    "sg:phone":"+1 703 368 7558",
    "sg:postcode":"20110",
    "sg:province":"VA",
    "sg:tags":[
        "repairing",
        "remodeling",
        "contractor"
    ],
    "wof:name":"Eagle Home Improvement",
    "wof:placetype":"venue"
},
  "geometry": {"coordinates":[-77.498711,38.759817],"type":"Point"}
}