{
  "type": "Feature",
  "properties": {
    "addr:full":"14906 Laurel Point Ln Spotsylvania VA 22551",
    "addr:housenumber":"14906",
    "addr:postcode":"22551",
    "addr:street":"Laurel Point Ln",
    "iso:country":"US",
    "sg:address":"14906 Laurel Point Ln",
    "sg:city":"Spotsylvania",
    "sg:classifiers":[
        {
            "category":"Building & Trades",
            "subcategory":"Construction",
            "type":"Services"
        }
    ],
    "sg:phone":"+1 540 854 7575",
    "sg:postcode":"22551",
    "sg:province":"VA",
    "sg:tags":[
        "a",
        "general",
        "class",
        "contractor"
    ],
    "wof:name":"Trexman Corporation",
    "wof:placetype":"venue"
},
  "geometry": {"coordinates":[-77.849287,38.130817],"type":"Point"}
}