{
  "type": "Feature",
  "properties": {
    "addr:full":"1685 Crystal Square Arc Arlington VA 22202",
    "addr:housenumber":"1685",
    "addr:postcode":"22202",
    "addr:street":"Crystal Square Arc",
    "iso:country":"US",
    "sg:address":"1685 Crystal Square Arc",
    "sg:city":"Arlington",
    "sg:classifiers":[
        {
            "category":"Shopping",
            "subcategory":"Jewelry",
            "type":"Retail Goods"
        }
    ],
    "sg:phone":"+1 703 412 6066",
    "sg:postcode":"22202",
    "sg:province":"VA",
    "wof:name":"Richard Carroll",
    "wof:placetype":"venue"
},
  "geometry": {"coordinates":[-77.049896,38.860001],"type":"Point"}
}