{
  "type": "Feature",
  "properties": {
    "addr:full":"12021 Iron Bridge Rd Chester VA 23831",
    "addr:housenumber":"12021",
    "addr:postcode":"23831",
    "addr:street":"Iron Bridge Rd",
    "iso:country":"US",
    "sg:address":"12021 Iron Bridge Rd",
    "sg:city":"Chester",
    "sg:classifiers":[
        {
            "category":"Retail",
            "subcategory":"Veterinary Services",
            "type":"Services"
        }
    ],
    "sg:phone":"+1 804 748 2244",
    "sg:postcode":"23831",
    "sg:province":"VA",
    "sg:tags":[
        "hospital"
    ],
    "wof:name":"Chester Animal Clinic",
    "wof:placetype":"venue"
},
  "geometry": {"coordinates":[-77.481927,37.352977],"type":"Point"}
}