{
  "type": "Feature",
  "properties": {
    "addr:full":"2617 Turner Rd Richmond VA 23225",
    "addr:housenumber":"2617",
    "addr:postcode":"23225",
    "addr:street":"Turner Rd",
    "iso:country":"US",
    "sg:address":"2617 Turner Rd",
    "sg:city":"Richmond",
    "sg:classifiers":[
        {
            "category":"Social Services",
            "subcategory":"Child Care",
            "type":"Services"
        }
    ],
    "sg:phone":"+1 804 745 9333",
    "sg:postcode":"23225",
    "sg:province":"VA",
    "sg:tags":[
        "day"
    ],
    "wof:name":"Sunshine Child Dycare Lrng Ctr",
    "wof:placetype":"venue"
},
  "geometry": {"coordinates":[-77.52507799999999,37.472947],"type":"Point"}
}