{
  "type": "Feature",
  "properties": {
    "iso:country":"US",
    "sg:address":"306 Magnolia Ave",
    "sg:city":"Buena Vista",
    "sg:classifiers":[
        {
            "category":"Building & Trades",
            "subcategory":"Construction",
            "type":"Services"
        }
    ],
    "sg:phone":"+1 540 261 2684",
    "sg:postcode":"24416",
    "sg:province":"VA",
    "sg:tags":[
        "contractor"
    ],
    "wof:name":"Signature Siding",
    "wof:placetype":"venue"
},
  "geometry": {"coordinates":[-79.364869,37.717946],"type":"Point"}
}