{
  "type": "Feature",
  "properties": {
    "addr:full":"325 E Bayview Blvd Norfolk VA 23503",
    "addr:housenumber":"325",
    "addr:postcode":"23503",
    "addr:street":"E Bayview Blvd",
    "iso:country":"US",
    "sg:address":"325 E Bayview Blvd",
    "sg:city":"Norfolk",
    "sg:classifiers":[
        {
            "category":"Manufacturing",
            "subcategory":"Printing",
            "type":"Manufacturing & Wholesale Goods"
        }
    ],
    "sg:phone":"+1 757 961 9887",
    "sg:postcode":"23503",
    "sg:province":"VA",
    "sg:tags":[
        "publisher"
    ],
    "wof:name":"KMS Svc Inc",
    "wof:placetype":"venue"
},
  "geometry": {"coordinates":[-76.256451,36.932793],"type":"Point"}
}