{
  "type": "Feature",
  "properties": {
    "addr:full":"5556 Seminole Trl Charlottesville VA 22923",
    "addr:housenumber":"5556",
    "addr:postcode":"22923",
    "addr:street":"Seminole Trl",
    "iso:country":"US",
    "sg:address":"5556 Seminole Trl",
    "sg:city":"Charlottesville",
    "sg:classifiers":[
        {
            "category":"Shopping",
            "subcategory":"Clothing, Apparel, & Fashions",
            "type":"Retail Goods"
        }
    ],
    "sg:phone":"+1 434 973 4772",
    "sg:postcode":"22923",
    "sg:province":"VA",
    "sg:tags":[
        "alteration"
    ],
    "wof:name":"Accent Tailoring & Alterations",
    "wof:placetype":"venue"
},
  "geometry": {"coordinates":[-78.396484,38.192409],"type":"Point"}
}