{
  "type": "Feature",
  "properties": {
    "addr:full":"323 W Main St Waynesboro VA 22980",
    "addr:housenumber":"323",
    "addr:postcode":"22980",
    "addr:street":"W Main St",
    "iso:country":"US",
    "sg:address":"323 W Main St",
    "sg:city":"Waynesboro",
    "sg:classifiers":[
        {
            "category":"Shopping",
            "subcategory":"Jewelry",
            "type":"Retail Goods"
        }
    ],
    "sg:phone":"+1 540 942 2753",
    "sg:postcode":"22980",
    "sg:province":"VA",
    "sg:tags":[
        "jeweler"
    ],
    "wof:name":"Denton & Co Jewelers",
    "wof:placetype":"venue"
},
  "geometry": {"coordinates":[-78.886146,38.068042],"type":"Point"}
}