{
  "type": "Feature",
  "properties": {
    "addr:full":"5401 Staples Mill Rd Richmond VA 23228",
    "addr:housenumber":"5401",
    "addr:postcode":"23228",
    "addr:street":"Staples Mill Rd",
    "iso:country":"US",
    "sg:address":"5401 Staples Mill Rd",
    "sg:city":"Richmond",
    "sg:classifiers":[
        {
            "category":"Utilities",
            "subcategory":"Telephone",
            "type":"Services"
        }
    ],
    "sg:phone":"+1 804 915 2500",
    "sg:postcode":"23228",
    "sg:province":"VA",
    "sg:tags":[
        "company"
    ],
    "wof:name":"Te",
    "wof:placetype":"venue"
},
  "geometry": {"coordinates":[-77.49172299999999,37.603356],"type":"Point"}
}