{
  "type": "Feature",
  "properties": {
    "addr:full":"845 Foxridge Trl Chesapeake VA 23322",
    "addr:housenumber":"845",
    "addr:postcode":"23322",
    "addr:street":"Foxridge Trl",
    "iso:country":"US",
    "sg:address":"845 Foxridge Trl",
    "sg:city":"Chesapeake",
    "sg:classifiers":[
        {
            "category":"Building & Trades",
            "subcategory":"Construction",
            "type":"Services"
        }
    ],
    "sg:phone":"+1 757 436 3288",
    "sg:postcode":"23322",
    "sg:province":"VA",
    "sg:tags":[
        "house"
    ],
    "wof:name":"Bohn Const Co",
    "wof:placetype":"venue"
},
  "geometry": {"coordinates":[-76.27317499999999,36.717495],"type":"Point"}
}