{
  "type": "Feature",
  "properties": {
    "addr:full":"2733 Campostella Rd Chesapeake VA 23324",
    "addr:housenumber":"2733",
    "addr:postcode":"23324",
    "addr:street":"Campostella Rd",
    "iso:country":"US",
    "sg:address":"2733 Campostella Rd",
    "sg:city":"Chesapeake",
    "sg:classifiers":[
        {
            "category":"Organizations",
            "subcategory":"Religious Organization",
            "type":"Services"
        }
    ],
    "sg:phone":"+1 757 494 7070",
    "sg:postcode":"23324",
    "sg:province":"VA",
    "wof:name":"St Damascus Outreach Ministry",
    "wof:placetype":"venue"
},
  "geometry": {"coordinates":[-76.259413,36.813685],"type":"Point"}
}