{
  "type": "Feature",
  "properties": {
    "iso:country":"US",
    "sg:address":"916 Brookdale St",
    "sg:city":"Martinsville",
    "sg:classifiers":[
        {
            "category":"Professional",
            "subcategory":"Management & Consulting",
            "type":"Services"
        }
    ],
    "sg:phone":"+1 276 666 2358",
    "sg:postcode":"24112",
    "sg:province":"VA",
    "sg:tags":[
        "business"
    ],
    "wof:name":"Sunbelt Business Brokers",
    "wof:placetype":"venue"
},
  "geometry": {"coordinates":[-79.851918,36.686005],"type":"Point"}
}