{
  "type": "Feature",
  "properties": {
    "addr:full":"14831 Ensor Ct Woodbridge VA 22193",
    "addr:housenumber":"14831",
    "addr:postcode":"22193",
    "addr:street":"Ensor Ct",
    "iso:country":"US",
    "sg:address":"14831 Ensor Ct",
    "sg:city":"Woodbridge",
    "sg:classifiers":[
        {
            "category":"Professional",
            "subcategory":"Management & Consulting",
            "type":"Services"
        }
    ],
    "sg:phone":"+1 703 670 3751",
    "sg:postcode":"22193",
    "sg:province":"VA",
    "sg:tags":[
        "retail",
        "miscellaneous"
    ],
    "wof:name":"Home Intr Tlecom Solutions LLC",
    "wof:placetype":"venue"
},
  "geometry": {"coordinates":[-77.340514,38.632048],"type":"Point"}
}