{
  "type": "Feature",
  "properties": {
    "addr:full":"1607 Bridge Rd Suffolk VA 23433",
    "addr:housenumber":"1607",
    "addr:postcode":"23433",
    "addr:street":"Bridge Rd",
    "iso:country":"US",
    "sg:address":"1607 Bridge Rd",
    "sg:city":"Suffolk",
    "sg:classifiers":[
        {
            "category":"Organizations",
            "subcategory":"Religious Organization",
            "type":"Services"
        }
    ],
    "sg:phone":"+1 757 238 8803",
    "sg:postcode":"23433",
    "sg:province":"VA",
    "wof:name":"Malachi Outreach International Church Ofc",
    "wof:placetype":"venue"
},
  "geometry": {"coordinates":[-76.49815,36.906099],"type":"Point"}
}