{
  "type": "Feature",
  "properties": {
    "iso:country":"US",
    "sg:address":"13400 Marie Dr",
    "sg:city":"Manassas",
    "sg:classifiers":[
        {
            "category":"Professional",
            "subcategory":"Computer Services",
            "type":"Services"
        }
    ],
    "sg:phone":"+1 703 791 6109",
    "sg:postcode":"20112",
    "sg:province":"VA",
    "sg:tags":[
        "design",
        "integrated",
        "system"
    ],
    "wof:name":"Ispa Inc",
    "wof:placetype":"venue"
},
  "geometry": {"coordinates":[-77.45625099999999,38.658817],"type":"Point"}
}