{
  "type": "Feature",
  "properties": {
    "iso:country":"US",
    "sg:address":"11615 Braddock Rd",
    "sg:city":"Fairfax",
    "sg:classifiers":[
        {
            "category":"Organizations",
            "subcategory":"Religious Organization",
            "type":"Services"
        }
    ],
    "sg:phone":"+1 703 218 8466",
    "sg:postcode":"22030",
    "sg:province":"VA",
    "wof:name":"Jerusalem Korean Baptist",
    "wof:placetype":"venue"
},
  "geometry": {"coordinates":[-77.348046,38.832783],"type":"Point"}
}