{
  "type": "Feature",
  "properties": {
    "addr:full":"43685 Kenmore Ln Chantilly VA 20152",
    "addr:housenumber":"43685",
    "addr:postcode":"20152",
    "addr:street":"Kenmore Ln",
    "iso:country":"US",
    "sg:address":"43685 Kenmore Ln",
    "sg:city":"Chantilly",
    "sg:classifiers":[
        {
            "category":"Professional",
            "subcategory":"Business Services",
            "type":"Services"
        }
    ],
    "sg:phone":"+1 703 327 7336",
    "sg:postcode":"20152",
    "sg:province":"VA",
    "wof:name":"Defender Tech Group LLC",
    "wof:placetype":"venue"
},
  "geometry": {"coordinates":[-77.490235,38.894704],"type":"Point"}
}