{
  "type": "Feature",
  "properties": {
    "addr:full":"4501 W Hundred Rd Chester VA 23831",
    "addr:housenumber":"4501",
    "addr:postcode":"23831",
    "addr:street":"W Hundred Rd",
    "iso:country":"US",
    "sg:address":"4501 W Hundred Rd",
    "sg:city":"Chester",
    "sg:classifiers":[
        {
            "category":"Restaurant",
            "type":"Food & Drink"
        }
    ],
    "sg:menulink":"http://www.allmenus.com/va/bermuda/71788-pizza-hut/menu/",
    "sg:phone":"+1 804 768 8100",
    "sg:postcode":"23831",
    "sg:province":"VA",
    "sg:tags":[
        "american",
        "pizza"
    ],
    "wof:name":"Pizza Hut",
    "wof:placetype":"venue"
},
  "geometry": {"coordinates":[-77.449271,37.353956],"type":"Point"}
}