{
  "type": "Feature",
  "properties": {
    "iso:country":"US",
    "sg:address":"5908 Woodhaven Ct",
    "sg:city":"Virginia Beach",
    "sg:classifiers":[
        {
            "category":"Building & Trades",
            "subcategory":"Electrical",
            "type":"Services"
        }
    ],
    "sg:phone":"+1 757 413 9090",
    "sg:postcode":"23464",
    "sg:province":"VA",
    "sg:tags":[
        "work",
        "electrical"
    ],
    "wof:name":"Copeland Electric Company Inc",
    "wof:placetype":"venue"
},
  "geometry": {"coordinates":[-76.200638,36.821234],"type":"Point"}
}