{
  "type": "Feature",
  "properties": {
    "iso:country":"US",
    "sg:address":"2505 N Key Blvd",
    "sg:city":"Arlington",
    "sg:classifiers":[
        {
            "category":"Social Services",
            "type":"Services"
        }
    ],
    "sg:phone":"+1 703 525 1555",
    "sg:postcode":"22201",
    "sg:province":"VA",
    "sg:tags":[
        "project",
        "work"
    ],
    "wof:name":"James Balick",
    "wof:placetype":"venue"
},
  "geometry": {"coordinates":[-77.089742,38.892689],"type":"Point"}
}