{
  "type": "Feature",
  "properties": {
    "addr:full":"7110 Rural Point Rd Mechanicsville VA 23116",
    "addr:housenumber":"7110",
    "addr:postcode":"23116",
    "addr:street":"Rural Point Rd",
    "iso:country":"US",
    "sg:address":"7110 Rural Point Rd",
    "sg:city":"Mechanicsville",
    "sg:classifiers":[
        {
            "category":"Building & Trades",
            "subcategory":"Cleaning & Sanitation",
            "type":"Services"
        }
    ],
    "sg:phone":"+1 804 746 0260",
    "sg:postcode":"23116",
    "sg:province":"VA",
    "sg:tags":[
        "maintenance"
    ],
    "wof:name":"Spotless Janitorial",
    "wof:placetype":"venue"
},
  "geometry": {"coordinates":[-77.339851,37.667275],"type":"Point"}
}