{
  "type": "Feature",
  "properties": {
    "iso:country":"US",
    "sg:address":"719 W Main St",
    "sg:city":"Charlottesville",
    "sg:classifiers":[
        {
            "category":"Retail",
            "subcategory":"Auto Repair",
            "type":"Services"
        }
    ],
    "sg:phone":"+1 434 923 0964",
    "sg:postcode":"22903",
    "sg:province":"VA",
    "wof:name":"Land Rover Dealership Alternative",
    "wof:placetype":"venue"
},
  "geometry": {"coordinates":[-78.490402,38.031502],"type":"Point"}
}