{
  "type": "Feature",
  "properties": {
    "addr:full":"2006 Hardwick St Blacksburg VA 24060",
    "addr:housenumber":"2006",
    "addr:postcode":"24060",
    "addr:street":"Hardwick St",
    "iso:country":"US",
    "sg:address":"2006 Hardwick St",
    "sg:city":"Blacksburg",
    "sg:classifiers":[
        {
            "category":"Professional",
            "subcategory":"Computer Services",
            "type":"Services"
        }
    ],
    "sg:phone":"+1 540 953 3360",
    "sg:postcode":"24060",
    "sg:province":"VA",
    "sg:tags":[
        "internet"
    ],
    "wof:name":"Sylvia Scott Horse Training",
    "wof:placetype":"venue"
},
  "geometry": {"coordinates":[-80.410033,37.264441],"type":"Point"}
}