{
  "type": "Feature",
  "properties": {
    "addr:full":"4217 Kings Mill Ln Annandale VA 22003",
    "addr:housenumber":"4217",
    "addr:postcode":"22003",
    "addr:street":"Kings Mill Ln",
    "iso:country":"US",
    "sg:address":"4217 Kings Mill Ln",
    "sg:city":"Annandale",
    "sg:classifiers":[
        {
            "category":"Government",
            "subcategory":"Fire Station",
            "type":"Public Place"
        }
    ],
    "sg:phone":"+1 703 256 2004",
    "sg:postcode":"22003",
    "sg:province":"VA",
    "sg:tags":[
        "protection",
        "engineer"
    ],
    "wof:name":"Harold Nelson",
    "wof:placetype":"venue"
},
  "geometry": {"coordinates":[-77.167929,38.833081],"type":"Point"}
}