{
  "type": "Feature",
  "properties": {
    "addr:full":"8519 Chapin St Norfolk VA 23503",
    "addr:housenumber":"8519",
    "addr:postcode":"23503",
    "addr:street":"Chapin St",
    "iso:country":"US",
    "sg:address":"8519 Chapin St",
    "sg:city":"Norfolk",
    "sg:classifiers":[
        {
            "category":"Communications",
            "subcategory":"Film & Video Production",
            "type":"Services"
        }
    ],
    "sg:phone":"+1 757 480 1056",
    "sg:postcode":"23503",
    "sg:province":"VA",
    "sg:tags":[
        "motion"
    ],
    "wof:name":"Crkd Productions",
    "wof:placetype":"venue"
},
  "geometry": {"coordinates":[-76.250231,36.931191],"type":"Point"}
}