{
  "type": "Feature",
  "properties": {
    "addr:full":"2000 14th St N Arlington VA 22201",
    "addr:housenumber":"2000",
    "addr:postcode":"22201",
    "addr:street":"14Th St N",
    "iso:country":"US",
    "sg:address":"2000 14th St N",
    "sg:city":"Arlington",
    "sg:classifiers":[
        {
            "category":"Professional",
            "subcategory":"Lawyer & Legal Services",
            "type":"Services"
        }
    ],
    "sg:phone":"+1 703 569 6550",
    "sg:postcode":"22201",
    "sg:province":"VA",
    "sg:tags":[
        "attorney",
        "law"
    ],
    "wof:name":"Bean Kinney & Korman PC",
    "wof:placetype":"venue"
},
  "geometry": {"coordinates":[-77.082786,38.889665],"type":"Point"}
}