{
  "type": "Feature",
  "properties": {
    "addr:full":"2401 S Main St Blacksburg VA 24060",
    "addr:housenumber":"2401",
    "addr:postcode":"24060",
    "addr:street":"S Main St",
    "iso:country":"US",
    "sg:address":"2401 S Main St",
    "sg:city":"Blacksburg",
    "sg:classifiers":[
        {
            "category":"Banks & Credit Unions",
            "subcategory":"Bank",
            "type":"Services"
        }
    ],
    "sg:phone":"+1 540 961 3966",
    "sg:postcode":"24060",
    "sg:province":"VA",
    "sg:tags":[
        "mortgage"
    ],
    "wof:name":"Salem Financial L L C",
    "wof:placetype":"venue"
},
  "geometry": {"coordinates":[-80.400285,37.199968],"type":"Point"}
}