{
  "type": "Feature",
  "properties": {
    "addr:full":"6197 Fishermans Way Mechanicsville VA 23116",
    "addr:housenumber":"6197",
    "addr:postcode":"23116",
    "addr:street":"Fishermans Way",
    "iso:country":"US",
    "sg:address":"6197 Fishermans Way",
    "sg:city":"Mechanicsville",
    "sg:classifiers":[
        {
            "category":"Building & Trades",
            "subcategory":"Plumbing",
            "type":"Services"
        }
    ],
    "sg:phone":"+1 804 779 0490",
    "sg:postcode":"23116",
    "sg:province":"VA",
    "sg:tags":[
        "contractor"
    ],
    "wof:name":"Cool 2 Heat Mechanical",
    "wof:placetype":"venue"
},
  "geometry": {"coordinates":[-77.312252,37.641959],"type":"Point"}
}