{
  "type": "Feature",
  "properties": {
    "addr:full":"320 King St Alexandria VA 22314",
    "addr:housenumber":"320",
    "addr:postcode":"22314",
    "addr:street":"King St",
    "iso:country":"US",
    "sg:address":"320 King St",
    "sg:city":"Alexandria",
    "sg:classifiers":[
        {
            "category":"Shopping",
            "subcategory":"Gifts & Souvenirs",
            "type":"Retail Goods"
        }
    ],
    "sg:phone":"+1 703 548 9661",
    "sg:postcode":"22314",
    "sg:province":"VA",
    "sg:tags":[
        "shop"
    ],
    "wof:name":"Strawberries & Cream",
    "wof:placetype":"venue"
},
  "geometry": {"coordinates":[-77.043463,38.804529],"type":"Point"}
}