{
  "type": "Feature",
  "properties": {
    "addr:full":"850 Tower Rd SE Christiansburg VA 24073",
    "addr:housenumber":"850",
    "addr:postcode":"24073",
    "addr:street":"Tower Rd Se",
    "iso:country":"US",
    "sg:address":"850 Tower Rd SE",
    "sg:city":"Christiansburg",
    "sg:classifiers":[
        {
            "category":"Retail",
            "subcategory":"Repair Shop",
            "type":"Services"
        }
    ],
    "sg:phone":"+1 540 382 5568",
    "sg:postcode":"24073",
    "sg:province":"VA",
    "wof:name":"Night Shift Upholstery",
    "wof:placetype":"venue"
},
  "geometry": {"coordinates":[-80.34676899999999,37.131492],"type":"Point"}
}