{
  "type": "Feature",
  "properties": {
    "iso:country":"US",
    "sg:address":"2410 Deep Creek Blvd",
    "sg:city":"Portsmouth",
    "sg:classifiers":[
        {
            "category":"Retail",
            "subcategory":"Auto Repair",
            "type":"Services"
        }
    ],
    "sg:phone":"+1 757 397 3036",
    "sg:postcode":"23704",
    "sg:province":"VA",
    "sg:tags":[
        "repairing",
        "automobile"
    ],
    "wof:name":"B & B Auto Repair",
    "wof:placetype":"venue"
},
  "geometry": {"coordinates":[-76.32271799999999,36.820895],"type":"Point"}
}