{
  "type": "Feature",
  "properties": {
    "iso:country":"US",
    "sg:address":"13973 Hull Street Rd",
    "sg:city":"Midlothian",
    "sg:classifiers":[
        {
            "category":"Retail",
            "subcategory":"Laundry & Dry Cleaning",
            "type":"Services"
        }
    ],
    "sg:phone":"+1 804 739 5013",
    "sg:postcode":"23112",
    "sg:province":"VA",
    "sg:tags":[
        "cleaner",
        "plant",
        "drycleaning"
    ],
    "wof:name":"Nova Cleaners",
    "wof:placetype":"venue"
},
  "geometry": {"coordinates":[-77.663382,37.404475],"type":"Point"}
}