{
  "type": "Feature",
  "properties": {
    "addr:full":"4411 Jordantown Rd Vinton VA 24179",
    "addr:housenumber":"4411",
    "addr:postcode":"24179",
    "addr:street":"Jordantown Rd",
    "iso:country":"US",
    "sg:address":"4411 Jordantown Rd",
    "sg:city":"Vinton",
    "sg:classifiers":[
        {
            "category":"Building & Trades",
            "subcategory":"Landscaping Services",
            "type":"Services"
        }
    ],
    "sg:phone":"+1 540 947 5000",
    "sg:postcode":"24179",
    "sg:province":"VA",
    "sg:tags":[
        "landscape",
        "contractor"
    ],
    "wof:name":"Richardson Lawn Svc",
    "wof:placetype":"venue"
},
  "geometry": {"coordinates":[-79.752078,37.3014],"type":"Point"}
}