{
  "type": "Feature",
  "properties": {
    "iso:country":"US",
    "sg:address":"37553 Chestnut Mountain Rd",
    "sg:city":"Damascus",
    "sg:classifiers":[
        {
            "category":"Food & Beverages",
            "subcategory":"Groceries & Convenience Stores",
            "type":"Retail Goods"
        }
    ],
    "sg:phone":"+1 276 475 5175",
    "sg:postcode":"24236",
    "sg:province":"VA",
    "sg:tags":[
        "station",
        "gasoline"
    ],
    "wof:name":"Wideners Grocery",
    "wof:placetype":"venue"
},
  "geometry": {"coordinates":[-81.70995499999999,36.618347],"type":"Point"}
}