{
  "type": "Feature",
  "properties": {
    "addr:full":"8381 Old Courthouse Rd Ste 320 Vienna VA 22182",
    "addr:housenumber":"8381",
    "addr:postcode":"22182",
    "addr:street":"Old Courthouse Rd Ste 320",
    "iso:country":"US",
    "sg:address":"8381 Old Courthouse Rd Ste 320",
    "sg:city":"Vienna",
    "sg:classifiers":[
        {
            "category":"Professional",
            "subcategory":"Lawyer & Legal Services",
            "type":"Services"
        }
    ],
    "sg:phone":"+1 703 893 1880",
    "sg:postcode":"22182",
    "sg:province":"VA",
    "wof:name":"Hung Yea-Tung Law Offices",
    "wof:placetype":"venue"
},
  "geometry": {"coordinates":[-77.234398,38.915001],"type":"Point"}
}