{
  "type": "Feature",
  "properties": {
    "addr:full":"15377 W River Rd King William VA 23086",
    "addr:housenumber":"15377",
    "addr:postcode":"23086",
    "addr:street":"W River Rd",
    "iso:country":"US",
    "sg:address":"15377 W River Rd",
    "sg:city":"King William",
    "sg:phone":"+1 804 769 0372",
    "sg:postcode":"23086",
    "sg:province":"VA",
    "sg:tags":[
        "farm",
        "grain",
        "cash"
    ],
    "wof:name":"Thomas Fox",
    "wof:placetype":"venue"
},
  "geometry": {"coordinates":[-77.09245799999999,37.758869],"type":"Point"}
}