{
  "type": "Feature",
  "properties": {
    "iso:country":"US",
    "sg:address":"7820 Rebel Dr",
    "sg:city":"Annandale",
    "sg:classifiers":[
        {
            "category":"Professional",
            "subcategory":"Business Services",
            "type":"Services"
        }
    ],
    "sg:phone":"+1 703 698 1331",
    "sg:postcode":"22003",
    "sg:province":"VA",
    "sg:tags":[
        "translator"
    ],
    "wof:name":"Luis A Omana",
    "wof:placetype":"venue"
},
  "geometry": {"coordinates":[-77.216261,38.84824],"type":"Point"}
}