{
  "type": "Feature",
  "properties": {
    "iso:country":"US",
    "sg:address":"4 E Main St",
    "sg:city":"Richmond",
    "sg:classifiers":[
        {
            "category":"Organizations",
            "subcategory":"Membership Organization",
            "type":"Services"
        },
        {
            "category":"Bus Charters",
            "type":"Transportation"
        }
    ],
    "sg:phone":"+1 804 643 7407",
    "sg:postcode":"23219",
    "sg:province":"VA",
    "sg:tags":[
        "society",
        "restoration",
        "rental",
        "historical"
    ],
    "wof:name":"Historic Richmond Foundation",
    "wof:placetype":"venue"
},
  "geometry": {"coordinates":[-77.44346,37.542586],"type":"Point"}
}