{
  "type": "Feature",
  "properties": {
    "addr:full":"11835 Canon Blvd Newport News VA 23606",
    "addr:housenumber":"11835",
    "addr:postcode":"23606",
    "addr:street":"Canon Blvd",
    "iso:country":"US",
    "sg:address":"11835 Canon Blvd",
    "sg:city":"Newport News",
    "sg:classifiers":[
        {
            "category":"Real Estate",
            "subcategory":"Real Estate Services",
            "type":"Services"
        }
    ],
    "sg:phone":"+1 757 873 5707",
    "sg:postcode":"23606",
    "sg:province":"VA",
    "sg:tags":[
        "company",
        "title"
    ],
    "wof:name":"Virginia Home Title & Escrow",
    "wof:placetype":"venue"
},
  "geometry": {"coordinates":[-76.469191,37.085791],"type":"Point"}
}