{
  "type": "Feature",
  "properties": {
    "addr:full":"213 E German School Rd Richmond VA 23224",
    "addr:housenumber":"213",
    "addr:postcode":"23224",
    "addr:street":"E German School Rd",
    "iso:country":"US",
    "sg:address":"213 E German School Rd",
    "sg:city":"Richmond",
    "sg:classifiers":[
        {
            "category":"Utilities",
            "subcategory":"Cable",
            "type":"Services"
        }
    ],
    "sg:phone":"+1 804 230 2540",
    "sg:postcode":"23224",
    "sg:province":"VA",
    "sg:tags":[
        "television"
    ],
    "wof:name":"A 1 Communications",
    "wof:placetype":"venue"
},
  "geometry": {"coordinates":[-77.504114,37.503203],"type":"Point"}
}