{
  "type": "Feature",
  "properties": {
    "addr:full":"11116 Industrial Rd Manassas VA 20109",
    "addr:housenumber":"11116",
    "addr:postcode":"20109",
    "addr:street":"Industrial Rd",
    "iso:country":"US",
    "sg:address":"11116 Industrial Rd",
    "sg:city":"Manassas",
    "sg:classifiers":[
        {
            "category":"Real Estate",
            "subcategory":"Developer",
            "type":"Services"
        }
    ],
    "sg:phone":"+1 703 335 2571",
    "sg:postcode":"20109",
    "sg:province":"VA",
    "sg:tags":[
        "development",
        "land"
    ],
    "wof:name":"Site Works Inc",
    "wof:placetype":"venue"
},
  "geometry": {"coordinates":[-77.539402,38.752871],"type":"Point"}
}