{
  "type": "Feature",
  "properties": {
    "addr:full":"11272 Jefferson Ave Newport News VA 23601",
    "addr:housenumber":"11272",
    "addr:postcode":"23601",
    "addr:street":"Jefferson Ave",
    "iso:country":"US",
    "sg:address":"11272 Jefferson Ave",
    "sg:city":"Newport News",
    "sg:classifiers":[
        {
            "category":"Home & Garden",
            "subcategory":"Mobile Homes",
            "type":"Retail Goods"
        }
    ],
    "sg:phone":"+1 757 595 9231",
    "sg:postcode":"23601",
    "sg:province":"VA",
    "sg:tags":[
        "material"
    ],
    "wof:name":"Clayton Homes Inc",
    "wof:placetype":"venue"
},
  "geometry": {"coordinates":[-76.46850999999999,37.063982],"type":"Point"}
}