{
  "type": "Feature",
  "properties": {
    "addr:full":"8260 Greensboro Dr Mc Lean VA 22102",
    "addr:housenumber":"8260",
    "addr:postcode":"22102",
    "addr:street":"Greensboro Dr",
    "iso:country":"US",
    "sg:address":"8260 Greensboro Dr",
    "sg:city":"Mc Lean",
    "sg:classifiers":[
        {
            "category":"Banks & Credit Unions",
            "subcategory":"Investment Brokerage",
            "type":"Services"
        }
    ],
    "sg:phone":"+1 703 506 5059",
    "sg:postcode":"22102",
    "sg:province":"VA",
    "sg:tags":[
        "security"
    ],
    "wof:name":"AMI Marketing Inc",
    "wof:placetype":"venue"
},
  "geometry": {"coordinates":[-77.230321,38.922758],"type":"Point"}
}