{
  "type": "Feature",
  "properties": {
    "addr:full":"4655 Monticello Ave Williamsburg VA 23188",
    "addr:housenumber":"4655",
    "addr:postcode":"23188",
    "addr:street":"Monticello Ave",
    "iso:country":"US",
    "sg:address":"4655 Monticello Ave",
    "sg:city":"Williamsburg",
    "sg:classifiers":[
        {
            "category":"Personal",
            "subcategory":"Beauty Salon",
            "type":"Services"
        }
    ],
    "sg:phone":"+1 757 565 3020",
    "sg:postcode":"23188",
    "sg:province":"VA",
    "sg:tags":[
        "shop"
    ],
    "wof:name":"K Nails",
    "wof:placetype":"venue"
},
  "geometry": {"coordinates":[-76.755978,37.27068],"type":"Point"}
}