{
  "type": "Feature",
  "properties": {
    "addr:full":"2200 Columbia Pike # 612 Arlington VA 22204",
    "addr:housenumber":"2200",
    "addr:postcode":"22204",
    "addr:street":"Columbia Pike # 612",
    "iso:country":"US",
    "sg:address":"2200 Columbia Pike # 612",
    "sg:city":"Arlington",
    "sg:classifiers":[
        {
            "category":"Communications",
            "subcategory":"Radio Station",
            "type":"Services"
        }
    ],
    "sg:phone":"+1 703 271 0198",
    "sg:postcode":"22204",
    "sg:province":"VA",
    "sg:tags":[
        "broadcast"
    ],
    "wof:name":"David K Cohler",
    "wof:placetype":"venue"
},
  "geometry": {"coordinates":[-77.08123000000001,38.864059],"type":"Point"}
}