{
  "type": "Feature",
  "properties": {
    "addr:full":"2930 Patrick Henry Dr Falls Church VA 22044",
    "addr:housenumber":"2930",
    "addr:postcode":"22044",
    "addr:street":"Patrick Henry Dr",
    "iso:country":"US",
    "sg:address":"2930 Patrick Henry Dr",
    "sg:city":"Falls Church",
    "sg:classifiers":[
        {
            "category":"Education",
            "subcategory":"Vocational School",
            "type":"Public Place"
        }
    ],
    "sg:phone":"+1 703 237 6200",
    "sg:postcode":"22044",
    "sg:province":"VA",
    "wof:name":"Sanz School",
    "wof:placetype":"venue"
},
  "geometry": {"coordinates":[-77.146355,38.870523],"type":"Point"}
}