{
  "type": "Feature",
  "properties": {
    "addr:full":"5819 Northampton Blvd Virginia Beach VA 23455",
    "addr:housenumber":"5819",
    "addr:postcode":"23455",
    "addr:street":"Northampton Blvd",
    "iso:country":"US",
    "sg:address":"5819 Northampton Blvd",
    "sg:city":"Virginia Beach",
    "sg:classifiers":[
        {
            "category":"Travel",
            "subcategory":"Hotels & Motels",
            "type":"Entertainment"
        }
    ],
    "sg:phone":"+1 757 460 1000",
    "sg:postcode":"23455",
    "sg:province":"VA",
    "wof:name":"Econo Lodge",
    "wof:placetype":"venue"
},
  "geometry": {"coordinates":[-76.186024,36.881434],"type":"Point"}
}