{
  "type": "Feature",
  "properties": {
    "addr:full":"601 N Main St Bridgewater VA 22812",
    "addr:housenumber":"601",
    "addr:postcode":"22812",
    "addr:street":"N Main St",
    "iso:country":"US",
    "sg:address":"601 N Main St",
    "sg:city":"Bridgewater",
    "sg:classifiers":[
        {
            "category":"Home & Garden",
            "subcategory":"Hardware",
            "type":"Retail Goods"
        }
    ],
    "sg:phone":"+1 540 828 2561",
    "sg:postcode":"22812",
    "sg:province":"VA",
    "sg:website":"www.rockinghamcoop.com",
    "wof:name":"Rockingham Cooperative",
    "wof:placetype":"venue"
},
  "geometry": {"coordinates":[-78.96629,38.390454],"type":"Point"}
}