{
  "type": "Feature",
  "properties": {
    "iso:country":"US",
    "sg:address":"9520 Lee Hwy",
    "sg:city":"Fairfax",
    "sg:classifiers":[
        {
            "category":"Building & Trades",
            "subcategory":"Plumbing",
            "type":"Services"
        },
        {
            "category":"Health Services",
            "subcategory":"Health Practitioner",
            "type":"Services"
        }
    ],
    "sg:phone":"+1 703 385 0837",
    "sg:postcode":"22031",
    "sg:province":"VA",
    "sg:tags":[
        "acupuncture",
        "contractor"
    ],
    "wof:name":"Immanuel Acupuncture & Hea",
    "wof:placetype":"venue"
},
  "geometry": {"coordinates":[-77.272631,38.867776],"type":"Point"}
}