{
  "type": "Feature",
  "properties": {
    "addr:full":"3936 Holland Blvd Chesapeake VA 23323",
    "addr:housenumber":"3936",
    "addr:postcode":"23323",
    "addr:street":"Holland Blvd",
    "iso:country":"US",
    "sg:address":"3936 Holland Blvd",
    "sg:city":"Chesapeake",
    "sg:classifiers":[
        {
            "category":"Manufacturing",
            "subcategory":"Tools & Machinery",
            "type":"Manufacturing & Wholesale Goods"
        }
    ],
    "sg:phone":"+1 757 625 6878",
    "sg:postcode":"23323",
    "sg:province":"VA",
    "sg:tags":[
        "machine",
        "shop"
    ],
    "wof:name":"Hampton Roads Machine Shop",
    "wof:placetype":"venue"
},
  "geometry": {"coordinates":[-76.377776,36.779572],"type":"Point"}
}