{
  "type": "Feature",
  "properties": {
    "addr:full":"2639 Logmill Rd Haymarket VA 20169",
    "addr:housenumber":"2639",
    "addr:postcode":"20169",
    "addr:street":"Logmill Rd",
    "iso:country":"US",
    "sg:address":"2639 Logmill Rd",
    "sg:city":"Haymarket",
    "sg:classifiers":[
        {
            "category":"Professional",
            "subcategory":"Business Services",
            "type":"Services"
        }
    ],
    "sg:phone":"+1 703 754 5891",
    "sg:postcode":"20169",
    "sg:province":"VA",
    "sg:tags":[
        "interior",
        "consultant",
        "design",
        "decorator"
    ],
    "wof:name":"MMB Enterprises Inc",
    "wof:placetype":"venue"
},
  "geometry": {"coordinates":[-77.616861,38.899228],"type":"Point"}
}