{
  "type": "Feature",
  "properties": {
    "addr:full":"10320 Festival Ln Manassas VA 20109",
    "addr:housenumber":"10320",
    "addr:postcode":"20109",
    "addr:street":"Festival Ln",
    "iso:country":"US",
    "sg:address":"10320 Festival Ln",
    "sg:city":"Manassas",
    "sg:classifiers":[
        {
            "category":"Shopping",
            "subcategory":"Clothing, Apparel, & Fashions",
            "type":"Retail Goods"
        }
    ],
    "sg:phone":"+1 703 369 3335",
    "sg:postcode":"20109",
    "sg:province":"VA",
    "wof:name":"Donita Dress",
    "wof:placetype":"venue"
},
  "geometry": {"coordinates":[-77.50474699999999,38.778748],"type":"Point"}
}