{
  "type": "Feature",
  "properties": {
    "addr:full":"203 W Little Creek Rd Norfolk VA 23505",
    "addr:housenumber":"203",
    "addr:postcode":"23505",
    "addr:street":"W Little Creek Rd",
    "iso:country":"US",
    "sg:address":"203 W Little Creek Rd",
    "sg:city":"Norfolk",
    "sg:classifiers":[
        {
            "category":"Professional",
            "subcategory":"Business Services",
            "type":"Services"
        }
    ],
    "sg:phone":"+1 757 451 8545",
    "sg:postcode":"23505",
    "sg:province":"VA",
    "sg:tags":[
        "diver"
    ],
    "wof:name":"Underwater Ordinance Recovery",
    "wof:placetype":"venue"
},
  "geometry": {"coordinates":[-76.27654699999999,36.915104],"type":"Point"}
}