{
  "type": "Feature",
  "properties": {
    "addr:full":"1257 Duncan Mill Rd Dugspur VA 24325",
    "addr:housenumber":"1257",
    "addr:postcode":"24325",
    "addr:street":"Duncan Mill Rd",
    "iso:country":"US",
    "sg:address":"1257 Duncan Mill Rd",
    "sg:city":"Dugspur",
    "sg:classifiers":[
        {
            "category":"Manufacturing",
            "subcategory":"Lumber",
            "type":"Manufacturing & Wholesale Goods"
        }
    ],
    "sg:phone":"+1 276 728 9847",
    "sg:postcode":"24325",
    "sg:province":"VA",
    "sg:tags":[
        "mill"
    ],
    "wof:name":"R M T Sawmill",
    "wof:placetype":"venue"
},
  "geometry": {"coordinates":[-80.606025,36.8589],"type":"Point"}
}