{
  "type": "Feature",
  "properties": {
    "iso:country":"US",
    "sg:address":"2110 S Monroe St",
    "sg:city":"Arlington",
    "sg:classifiers":[
        {
            "category":"Professional",
            "type":"Services"
        }
    ],
    "sg:phone":"+1 703 892 1199",
    "sg:postcode":"22204",
    "sg:province":"VA",
    "sg:website":"www.digitalprism.net",
    "wof:name":"Digital Prism",
    "wof:placetype":"venue"
},
  "geometry": {"coordinates":[-77.09019600000001,38.851479],"type":"Point"}
}