{
  "type": "Feature",
  "properties": {
    "addr:full":"919 Berry Rd Brodnax VA 23920",
    "addr:housenumber":"919",
    "addr:postcode":"23920",
    "addr:street":"Berry Rd",
    "iso:country":"US",
    "sg:address":"919 Berry Rd",
    "sg:city":"Brodnax",
    "sg:classifiers":[
        {
            "category":"Professional",
            "type":"Services"
        }
    ],
    "sg:phone":"+1 434 676 6067",
    "sg:postcode":"23920",
    "sg:province":"VA",
    "wof:name":"Gary C Pifer",
    "wof:placetype":"venue"
},
  "geometry": {"coordinates":[-78.07310099999999,36.813621],"type":"Point"}
}