{
  "type": "Feature",
  "properties": {
    "addr:full":"771 Green Ln Faber VA 22938",
    "addr:housenumber":"771",
    "addr:postcode":"22938",
    "addr:street":"Green Ln",
    "iso:country":"US",
    "sg:address":"771 Green Ln",
    "sg:city":"Faber",
    "sg:classifiers":[
        {
            "category":"Professional",
            "type":"Services"
        }
    ],
    "sg:phone":"+1 434 263 8525",
    "sg:postcode":"22938",
    "sg:province":"VA",
    "wof:name":"JP Gates Inc",
    "wof:placetype":"venue"
},
  "geometry": {"coordinates":[-78.78401599999999,37.857286],"type":"Point"}
}