{
  "type": "Feature",
  "properties": {
    "iso:country":"US",
    "sg:address":"10029 Crawford Ln",
    "sg:city":"Nokesville",
    "sg:classifiers":[
        {
            "category":"Wholesale",
            "subcategory":"Machinery & Supplies",
            "type":"Manufacturing & Wholesale Goods"
        }
    ],
    "sg:phone":"+1 703 754 0841",
    "sg:postcode":"20181",
    "sg:province":"VA",
    "sg:tags":[
        "equipment",
        "printing"
    ],
    "wof:name":"Julie Mouganis",
    "wof:placetype":"venue"
},
  "geometry": {"coordinates":[-77.62683,38.741124],"type":"Point"}
}