{
  "type": "Feature",
  "properties": {
    "iso:country":"US",
    "sg:address":"2201 Tomlyn St",
    "sg:city":"Richmond",
    "sg:classifiers":[
        {
            "category":"Wholesale",
            "subcategory":"Stationery",
            "type":"Manufacturing & Wholesale Goods"
        }
    ],
    "sg:phone":"+1 804 355 1577",
    "sg:postcode":"23230",
    "sg:province":"VA",
    "sg:tags":[
        "product",
        "retail"
    ],
    "wof:name":"Atlantic Office Supply Inc",
    "wof:placetype":"venue"
},
  "geometry": {"coordinates":[-77.481709,37.583256],"type":"Point"}
}