{
  "type": "Feature",
  "properties": {
    "addr:full":"23035 Douglas Ct Sterling VA 20166",
    "addr:housenumber":"23035",
    "addr:postcode":"20166",
    "addr:street":"Douglas Ct",
    "iso:country":"US",
    "sg:address":"23035 Douglas Ct",
    "sg:city":"Sterling",
    "sg:classifiers":[
        {
            "category":"Wholesale",
            "subcategory":"Computers",
            "type":"Manufacturing & Wholesale Goods"
        }
    ],
    "sg:phone":"+1 703 397 9454",
    "sg:postcode":"20166",
    "sg:province":"VA",
    "sg:tags":[
        "component"
    ],
    "wof:name":"Affinity Computer Technology",
    "wof:placetype":"venue"
},
  "geometry": {"coordinates":[-77.414996,38.977968],"type":"Point"}
}