{
  "type": "Feature",
  "properties": {
    "addr:full":"14835 Whitley St Chester VA 23836",
    "addr:housenumber":"14835",
    "addr:postcode":"23836",
    "addr:street":"Whitley St",
    "iso:country":"US",
    "sg:address":"14835 Whitley St",
    "sg:city":"Chester",
    "sg:classifiers":[
        {
            "category":"Freight",
            "type":"Transportation"
        }
    ],
    "sg:phone":"+1 804 530 7759",
    "sg:postcode":"23836",
    "sg:province":"VA",
    "sg:tags":[
        "operator",
        "local",
        "trucking"
    ],
    "wof:name":"Novia Trucking LLC",
    "wof:placetype":"venue"
},
  "geometry": {"coordinates":[-77.32656900000001,37.322216],"type":"Point"}
}