{
  "type": "Feature",
  "properties": {
    "addr:full":"6325 Antler Rd Richmond VA 23226",
    "addr:housenumber":"6325",
    "addr:postcode":"23226",
    "addr:street":"Antler Rd",
    "iso:country":"US",
    "sg:address":"6325 Antler Rd",
    "sg:city":"Richmond",
    "sg:classifiers":[
        {
            "category":"Building & Trades",
            "subcategory":"Construction",
            "type":"Services"
        }
    ],
    "sg:phone":"+1 804 285 0706",
    "sg:postcode":"23226",
    "sg:province":"VA",
    "sg:tags":[
        "carpentry",
        "contractor"
    ],
    "wof:name":"Nu-Sash of VA",
    "wof:placetype":"venue"
},
  "geometry": {"coordinates":[-77.516791,37.597819],"type":"Point"}
}