{
  "type": "Feature",
  "properties": {
    "addr:full":"12872 Harbor Dr Woodbridge VA 22192",
    "addr:housenumber":"12872",
    "addr:postcode":"22192",
    "addr:street":"Harbor Dr",
    "iso:country":"US",
    "sg:address":"12872 Harbor Dr",
    "sg:city":"Woodbridge",
    "sg:classifiers":[
        {
            "category":"Health Services",
            "subcategory":"Clinic",
            "type":"Services"
        }
    ],
    "sg:phone":"+1 703 497 0901",
    "sg:postcode":"22192",
    "sg:province":"VA",
    "sg:tags":[
        "specialty",
        "outpatient"
    ],
    "wof:name":"A Counseling Place",
    "wof:placetype":"venue"
},
  "geometry": {"coordinates":[-77.280227,38.673741],"type":"Point"}
}