{
  "type": "Feature",
  "properties": {
    "addr:full":"4002 University Dr Fairfax VA 22030",
    "addr:housenumber":"4002",
    "addr:postcode":"22030",
    "addr:street":"University Dr",
    "iso:country":"US",
    "sg:address":"4002 University Dr",
    "sg:city":"Fairfax",
    "sg:classifiers":[
        {
            "category":"Personal",
            "type":"Services"
        },
        {
            "category":"Recreation",
            "type":"Entertainment"
        }
    ],
    "sg:phone":"+1 703 218 2007",
    "sg:postcode":"22030",
    "sg:province":"VA",
    "sg:tags":[
        "therapist",
        "massage"
    ],
    "wof:name":"Young's Therapy",
    "wof:placetype":"venue"
},
  "geometry": {"coordinates":[-77.30561,38.845367],"type":"Point"}
}