{
  "type": "Feature",
  "properties": {
    "addr:full":"641 Lynnhaven Pkwy Virginia Beach VA 23452",
    "addr:housenumber":"641",
    "addr:postcode":"23452",
    "addr:street":"Lynnhaven Pkwy",
    "iso:country":"US",
    "sg:address":"641 Lynnhaven Pkwy",
    "sg:city":"Virginia Beach",
    "sg:classifiers":[
        {
            "category":"Banks & Credit Unions",
            "subcategory":"Bank",
            "type":"Services"
        }
    ],
    "sg:phone":"+1 757 486 9410",
    "sg:postcode":"23452",
    "sg:province":"VA",
    "sg:tags":[
        "state"
    ],
    "sg:website":"www.southtrust.com",
    "wof:name":"South Trust Bank",
    "wof:placetype":"venue"
},
  "geometry": {"coordinates":[-76.06726999999999,36.825322],"type":"Point"}
}