{
  "type": "Feature",
  "properties": {
    "addr:full":"4805 Eisenhower Ave Suite A Alexandria VA 22304",
    "addr:housenumber":"4805",
    "addr:postcode":"22304",
    "addr:street":"Eisenhower Ave Suite A",
    "iso:country":"US",
    "sg:address":"4805 Eisenhower Ave Suite A",
    "sg:city":"Alexandria",
    "sg:classifiers":[
        {
            "category":"Shopping",
            "subcategory":"Stationery & Office Supplies",
            "type":"Retail Goods"
        },
        {
            "category":"Professional",
            "subcategory":"Advertising",
            "type":"Services"
        },
        {
            "category":"Professional",
            "subcategory":"Printing & Photocopies",
            "type":"Services"
        }
    ],
    "sg:phone":"+1 703 823 7444",
    "sg:postcode":"22304",
    "sg:province":"VA",
    "sg:tags":[
        "announcement",
        "product",
        "services-commercial",
        "duplicating",
        "copying",
        "invitation",
        "advertising-promotional"
    ],
    "sg:website":"http://allamericanprintinginc.com",
    "wof:name":"All American Printing Incorporated",
    "wof:placetype":"venue"
},
  "geometry": {"coordinates":[-77.119719,38.803184],"type":"Point"}
}