{
  "type": "Feature",
  "properties": {
    "addr:full":"12175 Lincoln Lake Way Fairfax VA 22030",
    "addr:housenumber":"12175",
    "addr:postcode":"22030",
    "addr:street":"Lincoln Lake Way",
    "iso:country":"US",
    "sg:address":"12175 Lincoln Lake Way",
    "sg:city":"Fairfax",
    "sg:classifiers":[
        {
            "category":"Organizations",
            "subcategory":"Membership Organization",
            "type":"Services"
        }
    ],
    "sg:phone":"+1 703 322 1096",
    "sg:postcode":"22030",
    "sg:province":"VA",
    "wof:name":"Turning Point",
    "wof:placetype":"venue"
},
  "geometry": {"coordinates":[-77.36851,38.857374],"type":"Point"}
}