{
  "type": "Feature",
  "properties": {
    "iso:country":"US",
    "sg:address":"719 N Saint Asaph St",
    "sg:city":"Alexandria",
    "sg:classifiers":[
        {
            "category":"Retail",
            "subcategory":"Laundry & Dry Cleaning",
            "type":"Services"
        }
    ],
    "sg:phone":"+1 703 535 5950",
    "sg:postcode":"22314",
    "sg:province":"VA",
    "sg:tags":[
        "drycleaning",
        "plant"
    ],
    "wof:name":"Michaels 3 Cleaners",
    "wof:placetype":"venue"
},
  "geometry": {"coordinates":[-77.044078,38.812652],"type":"Point"}
}