{
  "type": "Feature",
  "properties": {
    "iso:country":"US",
    "sg:address":"24209 Gaydell Dr",
    "sg:city":"Petersburg",
    "sg:classifiers":[
        {
            "category":"Building & Trades",
            "subcategory":"Landscaping Services",
            "type":"Services"
        }
    ],
    "sg:phone":"+1 804 536 1088",
    "sg:postcode":"23803",
    "sg:province":"VA",
    "wof:name":"Wades Lawn Care",
    "wof:placetype":"venue"
},
  "geometry": {"coordinates":[-77.48405700000001,37.216687],"type":"Point"}
}