{
  "type": "Feature",
  "properties": {
    "addr:full":"3100 S Columbia Pike Arlington VA 22204",
    "addr:housenumber":"3100",
    "addr:postcode":"22204",
    "addr:street":"S Columbia Pike",
    "iso:country":"US",
    "sg:address":"3100 S Columbia Pike",
    "sg:city":"Arlington",
    "sg:classifiers":[
        {
            "category":"Professional",
            "type":"Services"
        }
    ],
    "sg:phone":"+1 703 920 8630",
    "sg:postcode":"22204",
    "sg:province":"VA",
    "sg:tags":[
        "establishment"
    ],
    "wof:name":"E & C Enterprises Inc",
    "wof:placetype":"venue"
},
  "geometry": {"coordinates":[-77.08904099999999,38.862042],"type":"Point"}
}