{
  "type": "Feature",
  "properties": {
    "addr:full":"7939 Yahley Mill Rd Richmond VA 23231",
    "addr:housenumber":"7939",
    "addr:postcode":"23231",
    "addr:street":"Yahley Mill Rd",
    "iso:country":"US",
    "sg:address":"7939 Yahley Mill Rd",
    "sg:city":"Richmond",
    "sg:classifiers":[
        {
            "category":"Wholesale",
            "subcategory":"Construction Materials",
            "type":"Manufacturing & Wholesale Goods"
        }
    ],
    "sg:phone":"+1 804 795 4250",
    "sg:postcode":"23231",
    "sg:province":"VA",
    "sg:tags":[
        "fence"
    ],
    "wof:name":"Richmond Fence LLC",
    "wof:placetype":"venue"
},
  "geometry": {"coordinates":[-77.28919500000001,37.449942],"type":"Point"}
}