{
  "type": "Feature",
  "properties": {
    "addr:full":"205 Church St Wytheville VA 24382",
    "addr:housenumber":"205",
    "addr:postcode":"24382",
    "addr:street":"Church St",
    "iso:country":"US",
    "sg:address":"205 Church St",
    "sg:city":"Wytheville",
    "sg:classifiers":[
        {
            "category":"Organizations",
            "subcategory":"Religious Organization",
            "type":"Services"
        }
    ],
    "sg:phone":"+1 276 228 3712",
    "sg:postcode":"24382",
    "sg:province":"VA",
    "sg:tags":[
        "church"
    ],
    "sg:website":"www.wythevillebaptist.org",
    "wof:name":"Wytheville Baptist Church",
    "wof:placetype":"venue"
},
  "geometry": {"coordinates":[-81.082162,36.948715],"type":"Point"}
}