{
  "type": "Feature",
  "properties": {
    "iso:country":"US",
    "sg:address":"5912 Lewis Rd",
    "sg:city":"Sandston",
    "sg:classifiers":[
        {
            "category":"Building & Trades",
            "subcategory":"Electrical",
            "type":"Services"
        }
    ],
    "sg:phone":"+1 804 222 0584",
    "sg:postcode":"23150",
    "sg:province":"VA",
    "sg:tags":[
        "electrical",
        "contractor"
    ],
    "wof:name":"Crosby Gd Electric Inc",
    "wof:placetype":"venue"
},
  "geometry": {"coordinates":[-77.341832,37.500019],"type":"Point"}
}