{
  "type": "Feature",
  "properties": {
    "addr:full":"1380 Blackberry Ln Harrisonburg VA 22802",
    "addr:housenumber":"1380",
    "addr:postcode":"22802",
    "addr:street":"Blackberry Ln",
    "iso:country":"US",
    "sg:address":"1380 Blackberry Ln",
    "sg:city":"Harrisonburg",
    "sg:classifiers":[
        {
            "category":"Organizations",
            "subcategory":"Religious Organization",
            "type":"Services"
        }
    ],
    "sg:phone":"+1 540 432 6158",
    "sg:postcode":"22802",
    "sg:province":"VA",
    "sg:tags":[
        "church"
    ],
    "wof:name":"Word Of Life",
    "wof:placetype":"venue"
},
  "geometry": {"coordinates":[-78.886623,38.475045],"type":"Point"}
}