{
  "type": "Feature",
  "properties": {
    "addr:full":"369 Springdale Rd Winchester VA 22602",
    "addr:housenumber":"369",
    "addr:postcode":"22602",
    "addr:street":"Springdale Rd",
    "iso:country":"US",
    "sg:address":"369 Springdale Rd",
    "sg:city":"Winchester",
    "sg:classifiers":[
        {
            "category":"Retail",
            "subcategory":"Animal Services",
            "type":"Services"
        }
    ],
    "sg:phone":"+1 540 869 1462",
    "sg:postcode":"22602",
    "sg:province":"VA",
    "sg:tags":[
        "pet",
        "boarding",
        "sitting"
    ],
    "wof:name":"Longacre Kennels",
    "wof:placetype":"venue"
},
  "geometry": {"coordinates":[-78.21223999999999,39.111653],"type":"Point"}
}