{
  "type": "Feature",
  "properties": {
    "iso:country":"US",
    "sg:address":"3615 Barcroft View Ter",
    "sg:city":"Falls Church",
    "sg:classifiers":[
        {
            "category":"Professional",
            "subcategory":"Research",
            "type":"Services"
        }
    ],
    "sg:phone":"+1 202 210 5570",
    "sg:postcode":"22041",
    "sg:province":"VA",
    "sg:tags":[
        "market",
        "analysis"
    ],
    "wof:name":"Documental Solutions LLC",
    "wof:placetype":"venue"
},
  "geometry": {"coordinates":[-77.13739700000001,38.846809],"type":"Point"}
}