{
  "type": "Feature",
  "properties": {
    "addr:full":"4900 Farnham Creek Rd Farnham VA 22460",
    "addr:housenumber":"4900",
    "addr:postcode":"22460",
    "addr:street":"Farnham Creek Rd",
    "iso:country":"US",
    "sg:address":"4900 Farnham Creek Rd",
    "sg:city":"Farnham",
    "sg:classifiers":[
        {
            "category":"Building & Trades",
            "subcategory":"Construction",
            "type":"Services"
        }
    ],
    "sg:phone":"+1 804 394 4343",
    "sg:postcode":"22460",
    "sg:province":"VA",
    "sg:tags":[
        "home",
        "improvement"
    ],
    "wof:name":"B & B Complete",
    "wof:placetype":"venue"
},
  "geometry": {"coordinates":[-76.60694599999999,37.848388],"type":"Point"}
}