{
  "type": "Feature",
  "properties": {
    "addr:full":"8801 Lynnhurst Dr Fairfax VA 22031",
    "addr:housenumber":"8801",
    "addr:postcode":"22031",
    "addr:street":"Lynnhurst Dr",
    "iso:country":"US",
    "sg:address":"8801 Lynnhurst Dr",
    "sg:city":"Fairfax",
    "sg:classifiers":[
        {
            "category":"Professional",
            "subcategory":"Management & Consulting",
            "type":"Services"
        }
    ],
    "sg:phone":"+1 703 280 2697",
    "sg:postcode":"22031",
    "sg:province":"VA",
    "sg:tags":[
        "business"
    ],
    "wof:name":"Cyber Quest Consulting",
    "wof:placetype":"venue"
},
  "geometry": {"coordinates":[-77.250314,38.851603],"type":"Point"}
}