{
  "type": "Feature",
  "properties": {
    "iso:country":"US",
    "sg:address":"15127 Shirley Rd",
    "sg:city":"Unionville",
    "sg:classifiers":[
        {
            "category":"Shopping",
            "subcategory":"Hobbies, Toys, & Games",
            "type":"Retail Goods"
        }
    ],
    "sg:phone":"+1 540 854 6176",
    "sg:postcode":"22567",
    "sg:province":"VA",
    "sg:tags":[
        "product",
        "ceramic"
    ],
    "wof:name":"Countryside Ceramics",
    "wof:placetype":"venue"
},
  "geometry": {"coordinates":[-77.875714,38.192787],"type":"Point"}
}