{
  "type": "Feature",
  "properties": {
    "iso:country":"US",
    "sg:address":"345 S Main St",
    "sg:city":"Harrisonburg",
    "sg:classifiers":[
        {
            "category":"Government",
            "subcategory":"Fire Station",
            "type":"Public Place"
        }
    ],
    "sg:phone":"+1 540 432 7703",
    "sg:postcode":"22801",
    "sg:province":"VA",
    "sg:tags":[
        "protection"
    ],
    "wof:name":"Harrisonbug Fire Department",
    "wof:placetype":"venue"
},
  "geometry": {"coordinates":[-78.869479,38.446188],"type":"Point"}
}