{
  "type": "Feature",
  "properties": {
    "iso:country":"US",
    "sg:address":"13167 Lea Anna Ln",
    "sg:city":"Maidens",
    "sg:classifiers":[
        {
            "category":"Professional",
            "subcategory":"Business Services",
            "type":"Services"
        }
    ],
    "sg:phone":"+1 804 749 4411",
    "sg:postcode":"23102",
    "sg:province":"VA",
    "sg:tags":[
        "group"
    ],
    "wof:name":"Soundset Recordings LLC",
    "wof:placetype":"venue"
},
  "geometry": {"coordinates":[-77.76715299999999,37.763167],"type":"Point"}
}