{
  "type": "Feature",
  "properties": {
    "iso:country":"US",
    "sg:address":"9309 Center St Ste 304",
    "sg:city":"Manassas",
    "sg:classifiers":[
        {
            "category":"Government",
            "subcategory":"Office",
            "type":"Public Place"
        }
    ],
    "sg:phone":"+1 703 335 5550",
    "sg:postcode":"20110",
    "sg:province":"VA",
    "sg:tags":[
        "government-state",
        "government-united",
        "state"
    ],
    "sg:website":"http://www.atlfa.org",
    "wof:name":"Virginia Department Of Rehabilitative Services",
    "wof:placetype":"venue"
},
  "geometry": {"coordinates":[-77.477824,38.75042],"type":"Point"}
}