{
  "type": "Feature",
  "properties": {
    "iso:country":"US",
    "sg:address":"25 Tarleton Way",
    "sg:city":"Stafford",
    "sg:classifiers":[
        {
            "category":"Home & Garden",
            "subcategory":"Hardware",
            "type":"Retail Goods"
        }
    ],
    "sg:phone":"+1 540 720 1268",
    "sg:postcode":"22554",
    "sg:province":"VA",
    "wof:name":"Ricks Tools Inc",
    "wof:placetype":"venue"
},
  "geometry": {"coordinates":[-77.39452900000001,38.44307],"type":"Point"}
}