{
  "type": "Feature",
  "properties": {
    "addr:full":"12586 Lake Coventry Dr Bealeton VA 22712",
    "addr:housenumber":"12586",
    "addr:postcode":"22712",
    "addr:street":"Lake Coventry Dr",
    "iso:country":"US",
    "sg:address":"12586 Lake Coventry Dr",
    "sg:city":"Bealeton",
    "sg:classifiers":[
        {
            "category":"Professional",
            "type":"Services"
        }
    ],
    "sg:phone":"+1 540 439 4748",
    "sg:postcode":"22712",
    "sg:province":"VA",
    "wof:name":"Leann Farrell",
    "wof:placetype":"venue"
},
  "geometry": {"coordinates":[-77.700315,38.512916],"type":"Point"}
}