{
  "type": "Feature",
  "properties": {
    "addr:full":"45945 Center Oak Plz Sterling VA 20166",
    "addr:housenumber":"45945",
    "addr:postcode":"20166",
    "addr:street":"Center Oak Plz",
    "iso:country":"US",
    "sg:address":"45945 Center Oak Plz",
    "sg:city":"Sterling",
    "sg:classifiers":[
        {
            "category":"Health Services",
            "subcategory":"Health Practitioner",
            "type":"Services"
        }
    ],
    "sg:phone":"+1 703 406 0296",
    "sg:postcode":"20166",
    "sg:province":"VA",
    "wof:name":"Physiotherapy Associates Inc",
    "wof:placetype":"venue"
},
  "geometry": {"coordinates":[-77.40955599999999,39.028786],"type":"Point"}
}