{
  "type": "Feature",
  "properties": {
    "iso:country":"US",
    "sg:address":"5681 Rushmere Dr",
    "sg:city":"Virginia Beach",
    "sg:classifiers":[
        {
            "category":"Retail",
            "subcategory":"Laundry & Dry Cleaning",
            "type":"Services"
        }
    ],
    "sg:phone":"+1 757 479 0899",
    "sg:postcode":"23464",
    "sg:province":"VA",
    "sg:tags":[
        "drycleaning",
        "plant"
    ],
    "wof:name":"Kleiners Cleaners",
    "wof:placetype":"venue"
},
  "geometry": {"coordinates":[-76.179648,36.792188],"type":"Point"}
}