{
  "type": "Feature",
  "properties": {
    "iso:country":"US",
    "sg:address":"4026 Plank Rd",
    "sg:city":"Fredericksburg",
    "sg:classifiers":[
        {
            "category":"Building & Trades",
            "subcategory":"Construction",
            "type":"Services"
        }
    ],
    "sg:phone":"+1 540 786 0752",
    "sg:postcode":"22407",
    "sg:province":"VA",
    "sg:tags":[
        "contractor"
    ],
    "wof:name":"Newhouse Builders Inc",
    "wof:placetype":"venue"
},
  "geometry": {"coordinates":[-77.529662,38.289933],"type":"Point"}
}