{
  "type": "Feature",
  "properties": {
    "addr:full":"402 N Jackson St Arlington VA 22201",
    "addr:housenumber":"402",
    "addr:postcode":"22201",
    "addr:street":"N Jackson St",
    "iso:country":"US",
    "sg:address":"402 N Jackson St",
    "sg:city":"Arlington",
    "sg:classifiers":[
        {
            "category":"Professional",
            "subcategory":"Art Services",
            "type":"Services"
        }
    ],
    "sg:phone":"+1 703 544 1596",
    "sg:postcode":"22201",
    "sg:province":"VA",
    "sg:tags":[
        "commercial",
        "design"
    ],
    "wof:name":"Marty Anderson",
    "wof:placetype":"venue"
},
  "geometry": {"coordinates":[-77.09745700000001,38.877295],"type":"Point"}
}