{
  "type": "Feature",
  "properties": {
    "addr:full":"13340 Leland Rd Centreville VA 20120",
    "addr:housenumber":"13340",
    "addr:postcode":"20120",
    "addr:street":"Leland Rd",
    "iso:country":"US",
    "sg:address":"13340 Leland Rd",
    "sg:city":"Centreville",
    "sg:classifiers":[
        {
            "category":"Education",
            "subcategory":"School",
            "type":"Public Place"
        }
    ],
    "sg:phone":"+1 571 522 6000",
    "sg:postcode":"20120",
    "sg:province":"VA",
    "wof:name":"Powell Elementary School",
    "wof:placetype":"venue"
},
  "geometry": {"coordinates":[-77.407674,38.84538],"type":"Point"}
}