{
  "type": "Feature",
  "properties": {
    "addr:full":"10604 Patterson Ave Richmond VA 23238",
    "addr:housenumber":"10604",
    "addr:postcode":"23238",
    "addr:street":"Patterson Ave",
    "iso:country":"US",
    "sg:address":"10604 Patterson Ave",
    "sg:city":"Richmond",
    "sg:classifiers":[
        {
            "category":"Personal",
            "subcategory":"Barber",
            "type":"Services"
        }
    ],
    "sg:phone":"+1 804 741 5400",
    "sg:postcode":"23238",
    "sg:province":"VA",
    "sg:tags":[
        "shop"
    ],
    "wof:name":"Tony's Hair",
    "wof:placetype":"venue"
},
  "geometry": {"coordinates":[-77.60895600000001,37.597128],"type":"Point"}
}