{
  "type": "Feature",
  "properties": {
    "addr:full":"1160 Robindale Dr Great Falls VA 22066",
    "addr:housenumber":"1160",
    "addr:postcode":"22066",
    "addr:street":"Robindale Dr",
    "iso:country":"US",
    "sg:address":"1160 Robindale Dr",
    "sg:city":"Great Falls",
    "sg:classifiers":[
        {
            "category":"Organizations",
            "subcategory":"Political Organization",
            "type":"Services"
        }
    ],
    "sg:phone":"+1 703 757 2216",
    "sg:postcode":"22066",
    "sg:province":"VA",
    "wof:name":"Iranian Amercn Cmnty Nthrn VA",
    "wof:placetype":"venue"
},
  "geometry": {"coordinates":[-77.292191,38.972519],"type":"Point"}
}