{
  "type": "Feature",
  "properties": {
    "addr:full":"3402 Acorn St Ste 103 Williamsburg VA 23188",
    "addr:housenumber":"3402",
    "addr:postcode":"23188",
    "addr:street":"Acorn St Ste 103",
    "iso:country":"US",
    "sg:address":"3402 Acorn St Ste 103",
    "sg:city":"Williamsburg",
    "sg:classifiers":[
        {
            "category":"Professional",
            "subcategory":"Engineering",
            "type":"Services"
        }
    ],
    "sg:phone":"+1 757 645 4895",
    "sg:postcode":"23188",
    "sg:province":"VA",
    "sg:tags":[
        "ecological",
        "engineer"
    ],
    "wof:name":"Colonial Soil & Water Conservation District",
    "wof:placetype":"venue"
},
  "geometry": {"coordinates":[-76.775627,37.370557],"type":"Point"}
}