{
  "type": "Feature",
  "properties": {
    "addr:full":"5023 Richardson St Chincoteague VA 23336",
    "addr:housenumber":"5023",
    "addr:postcode":"23336",
    "addr:street":"Richardson St",
    "iso:country":"US",
    "sg:address":"5023 Richardson St",
    "sg:city":"Chincoteague",
    "sg:classifiers":[
        {
            "category":"Professional",
            "type":"Services"
        }
    ],
    "sg:phone":"+1 757 336 5845",
    "sg:postcode":"23336",
    "sg:province":"VA",
    "wof:name":"Charles W & Bever Gorsuch",
    "wof:placetype":"venue"
},
  "geometry": {"coordinates":[-75.346176,37.953325],"type":"Point"}
}