{
  "type": "Feature",
  "properties": {
    "iso:country":"US",
    "sg:address":"7537 Gary Rd",
    "sg:city":"Manassas",
    "sg:classifiers":[
        {
            "category":"Professional",
            "subcategory":"Printing & Photocopies",
            "type":"Services"
        }
    ],
    "sg:phone":"+1 703 980 8239",
    "sg:postcode":"20109",
    "sg:province":"VA",
    "sg:tags":[
        "lithographer"
    ],
    "wof:name":"Mr. Graphics Print Shop",
    "wof:placetype":"venue"
},
  "geometry": {"coordinates":[-77.50577,38.799855],"type":"Point"}
}