{
  "type": "Feature",
  "properties": {
    "addr:full":"8740 Badger Dr Alexandria VA 22309",
    "addr:housenumber":"8740",
    "addr:postcode":"22309",
    "addr:street":"Badger Dr",
    "iso:country":"US",
    "sg:address":"8740 Badger Dr",
    "sg:city":"Alexandria",
    "sg:classifiers":[
        {
            "category":"Organizations",
            "subcategory":"Labor Organization",
            "type":"Services"
        }
    ],
    "sg:phone":"+1 703 360 5292",
    "sg:postcode":"22309",
    "sg:province":"VA",
    "wof:name":"Lohman & Assoc Lc",
    "wof:placetype":"venue"
},
  "geometry": {"coordinates":[-77.10982300000001,38.719961],"type":"Point"}
}