{
  "type": "Feature",
  "properties": {
    "addr:full":"75 Cool Spring Rd Fredericksburg VA 22405",
    "addr:housenumber":"75",
    "addr:postcode":"22405",
    "addr:street":"Cool Spring Rd",
    "iso:country":"US",
    "sg:address":"75 Cool Spring Rd",
    "sg:city":"Fredericksburg",
    "sg:classifiers":[
        {
            "category":"Building & Trades",
            "subcategory":"Construction",
            "type":"Services"
        }
    ],
    "sg:phone":"+1 540 898 8898",
    "sg:postcode":"22405",
    "sg:province":"VA",
    "sg:tags":[
        "contractor"
    ],
    "wof:name":"Resurrection Builders",
    "wof:placetype":"venue"
},
  "geometry": {"coordinates":[-77.44309,38.304222],"type":"Point"}
}