{
  "type": "Feature",
  "properties": {
    "iso:country":"US",
    "sg:address":"30 Macirvin Dr",
    "sg:city":"Newport News",
    "sg:classifiers":[
        {
            "category":"Retail",
            "subcategory":"Animal Services",
            "type":"Services"
        }
    ],
    "sg:phone":"+1 757 595 5279",
    "sg:postcode":"23606",
    "sg:province":"VA",
    "wof:name":"Canine & Co",
    "wof:placetype":"venue"
},
  "geometry": {"coordinates":[-76.51393,37.067502],"type":"Point"}
}