{
  "type": "Feature",
  "properties": {
    "iso:country":"US",
    "sg:address":"6 Loudoun St SW",
    "sg:city":"Leesburg",
    "sg:classifiers":[
        {
            "category":"Professional",
            "subcategory":"Management & Consulting",
            "type":"Services"
        }
    ],
    "sg:phone":"+1 703 471 7488",
    "sg:postcode":"20175",
    "sg:province":"VA",
    "sg:tags":[
        "town",
        "city",
        "regional",
        "planner"
    ],
    "wof:name":"Horizon Associates Inc",
    "wof:placetype":"venue"
},
  "geometry": {"coordinates":[-77.56655600000001,39.114717],"type":"Point"}
}