{
  "type": "Feature",
  "properties": {
    "iso:country":"US",
    "sg:address":"4139 Valley Pike",
    "sg:city":"Winchester",
    "sg:classifiers":[
        {
            "category":"Insurance",
            "subcategory":"Insurance Agent",
            "type":"Services"
        }
    ],
    "sg:phone":"+1 540 869 0644",
    "sg:postcode":"22602",
    "sg:province":"VA",
    "wof:name":"Grant Rich",
    "wof:placetype":"venue"
},
  "geometry": {"coordinates":[-78.201847,39.113179],"type":"Point"}
}