{
  "type": "Feature",
  "properties": {
    "addr:full":"842 N King St Hampton VA 23669",
    "addr:housenumber":"842",
    "addr:postcode":"23669",
    "addr:street":"N King St",
    "iso:country":"US",
    "sg:address":"842 N King St",
    "sg:city":"Hampton",
    "sg:classifiers":[
        {
            "category":"Shopping",
            "type":"Retail Goods"
        }
    ],
    "sg:phone":"+1 757 723 5008",
    "sg:postcode":"23669",
    "sg:province":"VA",
    "sg:tags":[
        "wedding",
        "supply"
    ],
    "wof:name":"Edwards Video Svc",
    "wof:placetype":"venue"
},
  "geometry": {"coordinates":[-76.347353,37.036765],"type":"Point"}
}