{
  "type": "Feature",
  "properties": {
    "addr:full":"12926 Lyme Bay Dr Herndon VA 20171",
    "addr:housenumber":"12926",
    "addr:postcode":"20171",
    "addr:street":"Lyme Bay Dr",
    "iso:country":"US",
    "sg:address":"12926 Lyme Bay Dr",
    "sg:city":"Herndon",
    "sg:classifiers":[
        {
            "category":"Health Services",
            "subcategory":"Doctor",
            "type":"Services"
        }
    ],
    "sg:phone":"+1 703 742 0379",
    "sg:postcode":"20171",
    "sg:province":"VA",
    "sg:tags":[
        "medical"
    ],
    "wof:name":"Danilo E Perico",
    "wof:placetype":"venue"
},
  "geometry": {"coordinates":[-77.39455700000001,38.931525],"type":"Point"}
}