{
  "type": "Feature",
  "properties": {
    "addr:full":"3416 Teakwood Ct Quinton VA 23141",
    "addr:housenumber":"3416",
    "addr:postcode":"23141",
    "addr:street":"Teakwood Ct",
    "iso:country":"US",
    "sg:address":"3416 Teakwood Ct",
    "sg:city":"Quinton",
    "sg:classifiers":[
        {
            "category":"Organizations",
            "subcategory":"Community Association",
            "type":"Services"
        }
    ],
    "sg:phone":"+1 804 932 9636",
    "sg:postcode":"23141",
    "sg:province":"VA",
    "wof:name":"Interntnal Assn of Lions Clubs",
    "wof:placetype":"venue"
},
  "geometry": {"coordinates":[-77.168347,37.504437],"type":"Point"}
}