{
  "type": "Feature",
  "properties": {
    "addr:full":"1437 W Main St Salem VA 24153",
    "addr:housenumber":"1437",
    "addr:postcode":"24153",
    "addr:street":"W Main St",
    "iso:country":"US",
    "sg:address":"1437 W Main St",
    "sg:city":"Salem",
    "sg:classifiers":[
        {
            "category":"Shopping",
            "subcategory":"Department Store",
            "type":"Retail Goods"
        }
    ],
    "sg:phone":"+1 540 375 6541",
    "sg:postcode":"24153",
    "sg:province":"VA",
    "wof:name":"Goody's Family Clothing",
    "wof:placetype":"venue"
},
  "geometry": {"coordinates":[-80.081363,37.289547],"type":"Point"}
}