{
  "type": "Feature",
  "properties": {
    "addr:full":"2429 Ridge Road Dr Alexandria VA 22302",
    "addr:housenumber":"2429",
    "addr:postcode":"22302",
    "addr:street":"Ridge Road Dr",
    "iso:country":"US",
    "sg:address":"2429 Ridge Road Dr",
    "sg:city":"Alexandria",
    "sg:classifiers":[
        {
            "category":"Professional",
            "subcategory":"Management & Consulting",
            "type":"Services"
        }
    ],
    "sg:phone":"+1 703 549 1718",
    "sg:postcode":"22302",
    "sg:province":"VA",
    "sg:tags":[
        "consultant",
        "business"
    ],
    "wof:name":"Snider Consulting LTD",
    "wof:placetype":"venue"
},
  "geometry": {"coordinates":[-77.07733399999999,38.827085],"type":"Point"}
}