{
  "type": "Feature",
  "properties": {
    "addr:full":"2602 Valley Ave Winchester VA 22601",
    "addr:housenumber":"2602",
    "addr:postcode":"22601",
    "addr:street":"Valley Ave",
    "iso:country":"US",
    "sg:address":"2602 Valley Ave",
    "sg:city":"Winchester",
    "sg:classifiers":[
        {
            "category":"Shopping",
            "subcategory":"Pharmacy",
            "type":"Retail Goods"
        }
    ],
    "sg:phone":"+1 540 723 8876",
    "sg:postcode":"22601",
    "sg:province":"VA",
    "wof:name":"CVS Pharmacy",
    "wof:placetype":"venue"
},
  "geometry": {"coordinates":[-78.18642199999999,39.156295],"type":"Point"}
}