{
  "type": "Feature",
  "properties": {
    "addr:full":"4103 36th St S Arlington VA 22206",
    "addr:housenumber":"4103",
    "addr:postcode":"22206",
    "addr:street":"36Th St S",
    "iso:country":"US",
    "sg:address":"4103 36th St S",
    "sg:city":"Arlington",
    "sg:classifiers":[
        {
            "category":"Building & Trades",
            "subcategory":"Construction",
            "type":"Services"
        }
    ],
    "sg:phone":"+1 703 379 7733",
    "sg:postcode":"22206",
    "sg:province":"VA",
    "sg:tags":[
        "interior",
        "condominium"
    ],
    "wof:name":"Fairlington Maintenance Svc",
    "wof:placetype":"venue"
},
  "geometry": {"coordinates":[-77.087768,38.828324],"type":"Point"}
}