{
  "type": "Feature",
  "properties": {
    "addr:full":"157 E Washington St Strasburg VA 22657",
    "addr:housenumber":"157",
    "addr:postcode":"22657",
    "addr:street":"E Washington St",
    "iso:country":"US",
    "sg:address":"157 E Washington St",
    "sg:city":"Strasburg",
    "sg:classifiers":[
        {
            "category":"Organizations",
            "subcategory":"Community Association",
            "type":"Services"
        }
    ],
    "sg:phone":"+1 540 465 8167",
    "sg:postcode":"22657",
    "sg:province":"VA",
    "sg:tags":[
        "military"
    ],
    "wof:name":"American Legion",
    "wof:placetype":"venue"
},
  "geometry": {"coordinates":[-78.360563,38.990218],"type":"Point"}
}