{
  "type": "Feature",
  "properties": {
    "addr:full":"11648 Leehigh Dr Fairfax VA 22030",
    "addr:housenumber":"11648",
    "addr:postcode":"22030",
    "addr:street":"Leehigh Dr",
    "iso:country":"US",
    "sg:address":"11648 Leehigh Dr",
    "sg:city":"Fairfax",
    "sg:classifiers":[
        {
            "category":"Personal",
            "type":"Services"
        }
    ],
    "sg:phone":"+1 703 591 5477",
    "sg:postcode":"22030",
    "sg:province":"VA",
    "wof:name":"Patricia Goins",
    "wof:placetype":"venue"
},
  "geometry": {"coordinates":[-77.349357,38.845054],"type":"Point"}
}