{
  "type": "Feature",
  "properties": {
    "addr:full":"6620 Indian River Rd Virginia Beach VA 23464",
    "addr:housenumber":"6620",
    "addr:postcode":"23464",
    "addr:street":"Indian River Rd",
    "iso:country":"US",
    "sg:address":"6620 Indian River Rd",
    "sg:city":"Virginia Beach",
    "sg:classifiers":[
        {
            "category":"Education",
            "subcategory":"School",
            "type":"Public Place"
        }
    ],
    "sg:phone":"+1 757 413 7177",
    "sg:postcode":"23464",
    "sg:province":"VA",
    "wof:name":"Christian Daniels Academy",
    "wof:placetype":"venue"
},
  "geometry": {"coordinates":[-76.22016600000001,36.819107],"type":"Point"}
}