{
  "type": "Feature",
  "properties": {
    "iso:country":"US",
    "sg:address":"900 First Colonial Rd",
    "sg:city":"Virginia Beach",
    "sg:classifiers":[
        {
            "category":"Real Estate",
            "subcategory":"Real Estate Operator",
            "type":"Services"
        }
    ],
    "sg:phone":"+1 757 481 0770",
    "sg:postcode":"23454",
    "sg:province":"VA",
    "sg:tags":[
        "building",
        "apartment"
    ],
    "wof:name":"Russell House Inc",
    "wof:placetype":"venue"
},
  "geometry": {"coordinates":[-76.02564599999999,36.857194],"type":"Point"}
}