{
  "type": "Feature",
  "properties": {
    "addr:full":"512 Broadway St Quantico VA 22134",
    "addr:housenumber":"512",
    "addr:postcode":"22134",
    "addr:street":"Broadway St",
    "iso:country":"US",
    "sg:address":"512 Broadway St",
    "sg:city":"Quantico",
    "sg:classifiers":[
        {
            "category":"Retail",
            "subcategory":"Laundry & Dry Cleaning",
            "type":"Services"
        }
    ],
    "sg:phone":"+1 703 640 6400",
    "sg:postcode":"22134",
    "sg:province":"VA",
    "wof:name":"Chois Catalanos Dry Cleaners",
    "wof:placetype":"venue"
},
  "geometry": {"coordinates":[-77.29159300000001,38.521277],"type":"Point"}
}