{
  "type": "Feature",
  "properties": {
    "addr:full":"2700 Stuart Ave Richmond VA 23220",
    "addr:housenumber":"2700",
    "addr:postcode":"23220",
    "addr:street":"Stuart Ave",
    "iso:country":"US",
    "sg:address":"2700 Stuart Ave",
    "sg:city":"Richmond",
    "sg:classifiers":[
        {
            "category":"Education",
            "subcategory":"Library",
            "type":"Public Place"
        }
    ],
    "sg:phone":"+1 804 359 3743",
    "sg:postcode":"23220",
    "sg:province":"VA",
    "wof:name":"Braille Circulating Library Inc",
    "wof:placetype":"venue"
},
  "geometry": {"coordinates":[-77.471992,37.55677],"type":"Point"}
}