{
  "type": "Feature",
  "properties": {
    "addr:full":"208 Pamela Dr Hampton VA 23666",
    "addr:housenumber":"208",
    "addr:postcode":"23666",
    "addr:street":"Pamela Dr",
    "iso:country":"US",
    "sg:address":"208 Pamela Dr",
    "sg:city":"Hampton",
    "sg:classifiers":[
        {
            "category":"Professional",
            "subcategory":"Management & Consulting",
            "type":"Services"
        }
    ],
    "sg:phone":"+1 757 838 6006",
    "sg:postcode":"23666",
    "sg:province":"VA",
    "wof:name":"Barnes Associates LLC",
    "wof:placetype":"venue"
},
  "geometry": {"coordinates":[-76.39798,37.028166],"type":"Point"}
}