{
  "type": "Feature",
  "properties": {
    "iso:country":"US",
    "sg:address":"4905 Radford Ave",
    "sg:city":"Richmond",
    "sg:classifiers":[
        {
            "category":"Banks & Credit Unions",
            "subcategory":"Investment Brokerage",
            "type":"Services"
        },
        {
            "category":"Professional",
            "subcategory":"Management & Consulting",
            "type":"Services"
        }
    ],
    "sg:phone":"+1 804 359 6220",
    "sg:postcode":"23230",
    "sg:province":"VA",
    "sg:tags":[
        "consultant",
        "planning",
        "financial"
    ],
    "wof:name":"Ifg Network Securities",
    "wof:placetype":"venue"
},
  "geometry": {"coordinates":[-77.495898,37.581119],"type":"Point"}
}