{
  "type": "Feature",
  "properties": {
    "iso:country":"US",
    "sg:address":"10717 Warren Rd",
    "sg:city":"Glen Allen",
    "sg:classifiers":[
        {
            "category":"Professional",
            "type":"Services"
        },
        {
            "category":"Manufacturing",
            "subcategory":"Printing",
            "type":"Manufacturing & Wholesale Goods"
        }
    ],
    "sg:phone":"+1 804 672 0201",
    "sg:postcode":"23060",
    "sg:province":"VA",
    "sg:tags":[
        "writer",
        "book"
    ],
    "wof:name":"Walrus Books",
    "wof:placetype":"venue"
},
  "geometry": {"coordinates":[-77.509084,37.669238],"type":"Point"}
}