{
  "type": "Feature",
  "properties": {
    "iso:country":"US",
    "sg:address":"86 Tulip Grove Cir",
    "sg:city":"Bristol",
    "sg:classifiers":[
        {
            "category":"Building & Trades",
            "subcategory":"Electrical",
            "type":"Services"
        }
    ],
    "sg:phone":"+1 423 652 7718",
    "sg:postcode":"37620",
    "sg:province":"VA",
    "sg:tags":[
        "electrical",
        "contractor"
    ],
    "wof:name":"C & L Electric Service",
    "wof:placetype":"venue"
},
  "geometry": {"coordinates":[-82.136785,36.577053],"type":"Point"}
}