{
  "type": "Feature",
  "properties": {
    "iso:country":"US",
    "sg:address":"118 S Royal St",
    "sg:city":"Alexandria",
    "sg:classifiers":[
        {
            "category":"Insurance",
            "subcategory":"Insurance Agent",
            "type":"Services"
        }
    ],
    "sg:phone":"+1 703 549 1501",
    "sg:postcode":"22314",
    "sg:province":"VA",
    "wof:name":"McClellan & Company",
    "wof:placetype":"venue"
},
  "geometry": {"coordinates":[-77.043764,38.803699],"type":"Point"}
}