{
  "type": "Feature",
  "properties": {
    "addr:full":"5135 New Kent Hwy Quinton VA 23141",
    "addr:housenumber":"5135",
    "addr:postcode":"23141",
    "addr:street":"New Kent Hwy",
    "iso:country":"US",
    "sg:address":"5135 New Kent Hwy",
    "sg:city":"Quinton",
    "sg:classifiers":[
        {
            "category":"Education",
            "subcategory":"Special Training",
            "type":"Public Place"
        },
        {
            "category":"Education",
            "subcategory":"Vocational School",
            "type":"Public Place"
        },
        {
            "category":"Professional",
            "subcategory":"Computer Services",
            "type":"Services"
        }
    ],
    "sg:phone":"+1 804 932 4310",
    "sg:postcode":"23141",
    "sg:province":"VA",
    "sg:tags":[
        "consultant",
        "designer",
        "technology",
        "system",
        "business"
    ],
    "wof:name":"Church Computer Workshops",
    "wof:placetype":"venue"
},
  "geometry": {"coordinates":[-77.124701,37.533508],"type":"Point"}
}