{
  "type": "Feature",
  "properties": {
    "addr:full":"5591 Senedo Rd Quicksburg VA 22847",
    "addr:housenumber":"5591",
    "addr:postcode":"22847",
    "addr:street":"Senedo Rd",
    "iso:country":"US",
    "sg:address":"5591 Senedo Rd",
    "sg:city":"Quicksburg",
    "sg:classifiers":[
        {
            "category":"Farming",
            "subcategory":"Orchard",
            "type":"Manufacturing & Wholesale Goods"
        }
    ],
    "sg:phone":"+1 540 740 8028",
    "sg:postcode":"22847",
    "sg:province":"VA",
    "sg:tags":[
        "grove",
        "management",
        "fruit",
        "tree"
    ],
    "wof:name":"Paugh's Orchard",
    "wof:placetype":"venue"
},
  "geometry": {"coordinates":[-78.750517,38.731488],"type":"Point"}
}