{
  "type": "Feature",
  "properties": {
    "iso:country":"US",
    "sg:address":"207 Court House Rd SW",
    "sg:city":"Vienna",
    "sg:classifiers":[
        {
            "category":"Building & Trades",
            "subcategory":"Electrical",
            "type":"Services"
        }
    ],
    "sg:phone":"+1 703 281 4565",
    "sg:postcode":"22180",
    "sg:province":"VA",
    "sg:tags":[
        "electric",
        "contractor"
    ],
    "wof:name":"Bill Buhl Electric Inc",
    "wof:placetype":"venue"
},
  "geometry": {"coordinates":[-77.186774,38.914107],"type":"Point"}
}