{
  "type": "Feature",
  "properties": {
    "addr:full":"644 Park Ave NW Norton VA 24273",
    "addr:housenumber":"644",
    "addr:postcode":"24273",
    "addr:street":"Park Ave Nw",
    "iso:country":"US",
    "sg:address":"644 Park Ave NW",
    "sg:city":"Norton",
    "sg:classifiers":[
        {
            "category":"Government",
            "subcategory":"Office",
            "type":"Public Place"
        }
    ],
    "sg:phone":"+1 276 679 2701",
    "sg:postcode":"24273",
    "sg:province":"VA",
    "sg:tags":[
        "city",
        "resource",
        "human"
    ],
    "wof:name":"Norton Welfare Dept",
    "wof:placetype":"venue"
},
  "geometry": {"coordinates":[-82.627467,36.934505],"type":"Point"}
}