{
  "type": "Feature",
  "properties": {
    "addr:full":"8287 Reunion Dr Mechanicsville VA 23111",
    "addr:housenumber":"8287",
    "addr:postcode":"23111",
    "addr:street":"Reunion Dr",
    "iso:country":"US",
    "sg:address":"8287 Reunion Dr",
    "sg:city":"Mechanicsville",
    "sg:classifiers":[
        {
            "category":"Professional",
            "subcategory":"Management & Consulting",
            "type":"Services"
        }
    ],
    "sg:phone":"+1 804 779 2452",
    "sg:postcode":"23111",
    "sg:province":"VA",
    "wof:name":"Waw Construction Consultants",
    "wof:placetype":"venue"
},
  "geometry": {"coordinates":[-77.30677799999999,37.632391],"type":"Point"}
}