{
  "type": "Feature",
  "properties": {
    "iso:country":"US",
    "sg:address":"36061 Goodwin Dr",
    "sg:city":"Locust Grove",
    "sg:classifiers":[
        {
            "category":"Restaurant",
            "type":"Food & Drink"
        }
    ],
    "sg:phone":"+1 540 972 7477",
    "sg:postcode":"22508",
    "sg:province":"VA",
    "sg:tags":[
        "eating"
    ],
    "wof:name":"Burger King",
    "wof:placetype":"venue"
},
  "geometry": {"coordinates":[-77.74744,38.34749],"type":"Point"}
}