{
  "type": "Feature",
  "properties": {
    "addr:full":"9407 Hull Street Rd Richmond VA 23236",
    "addr:housenumber":"9407",
    "addr:postcode":"23236",
    "addr:street":"Hull Street Rd",
    "iso:country":"US",
    "sg:address":"9407 Hull Street Rd",
    "sg:city":"Richmond",
    "sg:classifiers":[
        {
            "category":"Organizations",
            "subcategory":"Religious Organization",
            "type":"Services"
        }
    ],
    "sg:phone":"+1 804 675 2575",
    "sg:postcode":"23236",
    "sg:province":"VA",
    "wof:name":"Interntonal Christn Ministries",
    "wof:placetype":"venue"
},
  "geometry": {"coordinates":[-77.570245,37.446865],"type":"Point"}
}