{
  "type": "Feature",
  "properties": {
    "addr:full":"1045 Woodrow Rd Christiansburg VA 24073",
    "addr:housenumber":"1045",
    "addr:postcode":"24073",
    "addr:street":"Woodrow Rd",
    "iso:country":"US",
    "sg:address":"1045 Woodrow Rd",
    "sg:city":"Christiansburg",
    "sg:classifiers":[
        {
            "category":"Wholesale",
            "subcategory":"Construction Materials",
            "type":"Manufacturing & Wholesale Goods"
        }
    ],
    "sg:phone":"+1 540 381 7511",
    "sg:postcode":"24073",
    "sg:province":"VA",
    "sg:tags":[
        "fence"
    ],
    "wof:name":"We Care Fencing",
    "wof:placetype":"venue"
},
  "geometry": {"coordinates":[-80.388491,37.147081],"type":"Point"}
}