{
  "type": "Feature",
  "properties": {
    "iso:country":"US",
    "sg:address":"1961 Bloomer Springs Rd",
    "sg:city":"Mc Gaheysville",
    "sg:classifiers":[
        {
            "category":"Building & Trades",
            "subcategory":"Construction",
            "type":"Services"
        }
    ],
    "sg:phone":"+1 540 289 9339",
    "sg:postcode":"22840",
    "sg:province":"VA",
    "sg:tags":[
        "house"
    ],
    "wof:name":"Eli Slabaugh & Sons",
    "wof:placetype":"venue"
},
  "geometry": {"coordinates":[-78.706576,38.399898],"type":"Point"}
}