{
  "type": "Feature",
  "properties": {
    "addr:full":"14351 Sommerville Ct Midlothian VA 23113",
    "addr:housenumber":"14351",
    "addr:postcode":"23113",
    "addr:street":"Sommerville Ct",
    "iso:country":"US",
    "sg:address":"14351 Sommerville Ct",
    "sg:city":"Midlothian",
    "sg:classifiers":[
        {
            "category":"Health Services",
            "subcategory":"Doctor",
            "type":"Services"
        }
    ],
    "sg:phone":"+1 804 378 0584",
    "sg:postcode":"23113",
    "sg:province":"VA",
    "sg:tags":[
        "physician",
        "surgeon"
    ],
    "wof:name":"Virginia Adult & Pediatric",
    "wof:placetype":"venue"
},
  "geometry": {"coordinates":[-77.67391000000001,37.508487],"type":"Point"}
}