{
  "type": "Feature",
  "properties": {
    "addr:full":"Manassas Mall 8300 Sudley Rd Manassas VA 20109",
    "addr:housenumber":"8300",
    "addr:postcode":"20109",
    "addr:street":"Sudley Rd",
    "iso:country":"US",
    "sg:address":"Manassas Mall 8300 Sudley Rd",
    "sg:city":"Manassas",
    "sg:classifiers":[
        {
            "category":"Shopping",
            "subcategory":"Tobacco",
            "type":"Retail Goods"
        }
    ],
    "sg:phone":"+1 703 330 9753",
    "sg:postcode":"20109",
    "sg:province":"VA",
    "sg:tags":[
        "shop"
    ],
    "sg:website":"www.ovtc.com",
    "wof:name":"Old Virginia Tobacco Company",
    "wof:placetype":"venue"
},
  "geometry": {"coordinates":[-77.503185,38.775209],"type":"Point"}
}