{
  "type": "Feature",
  "properties": {
    "iso:country":"US",
    "sg:address":"920 Ivy St",
    "sg:city":"Waynesboro",
    "sg:classifiers":[
        {
            "category":"Retail",
            "subcategory":"Auto Repair",
            "type":"Services"
        }
    ],
    "sg:phone":"+1 540 949 6275",
    "sg:postcode":"22980",
    "sg:province":"VA",
    "sg:tags":[
        "cover",
        "installation",
        "seat"
    ],
    "wof:name":"Seat Cover Center",
    "wof:placetype":"venue"
},
  "geometry": {"coordinates":[-78.893592,38.074853],"type":"Point"}
}