{
  "type": "Feature",
  "properties": {
    "addr:full":"5106 Ballycastle Cir Alexandria VA 22310",
    "addr:postcode":"5106;22310",
    "addr:street":"Ballycastle Cir",
    "iso:country":"US",
    "sg:address":"5106 Ballycastle Cir",
    "sg:city":"Alexandria",
    "sg:classifiers":[
        {
            "category":"Banks & Credit Unions",
            "subcategory":"Investment Brokerage",
            "type":"Services"
        }
    ],
    "sg:phone":"+1 703 719 6870",
    "sg:postcode":"22310",
    "sg:province":"VA",
    "sg:tags":[
        "advisory",
        "financial"
    ],
    "wof:name":"R T Financial Inc",
    "wof:placetype":"venue"
},
  "geometry": {"coordinates":[-77.12640500000001,38.779355],"type":"Point"}
}