{
  "type": "Feature",
  "properties": {
    "iso:country":"US",
    "sg:address":"6908 Compton Valley Ct",
    "sg:city":"Centreville",
    "sg:classifiers":[
        {
            "category":"Freight",
            "type":"Transportation"
        }
    ],
    "sg:phone":"+1 703 631 1780",
    "sg:postcode":"20121",
    "sg:province":"VA",
    "sg:tags":[
        "operator",
        "local",
        "trucking"
    ],
    "wof:name":"America Delivery LLC",
    "wof:placetype":"venue"
},
  "geometry": {"coordinates":[-77.437265,38.807042],"type":"Point"}
}