{
  "type": "Feature",
  "properties": {
    "addr:full":"8405 Richmond Hwy Ste D Alexandria VA 22309",
    "addr:housenumber":"8405",
    "addr:postcode":"22309",
    "addr:street":"Richmond Hwy Ste D",
    "iso:country":"US",
    "sg:address":"8405 Richmond Hwy Ste D",
    "sg:city":"Alexandria",
    "sg:classifiers":[
        {
            "category":"Retail",
            "subcategory":"Repair Shop",
            "type":"Services"
        },
        {
            "category":"Professional",
            "subcategory":"Detective & Security Services",
            "type":"Services"
        }
    ],
    "sg:phone":"+1 703 660 9022",
    "sg:postcode":"22309",
    "sg:province":"VA",
    "sg:tags":[
        "skip",
        "tracing",
        "bail",
        "bond"
    ],
    "wof:name":"Charlies Angels Bail Bonds",
    "wof:placetype":"venue"
},
  "geometry": {"coordinates":[-77.108559,38.728512],"type":"Point"}
}