{
  "type": "Feature",
  "properties": {
    "addr:full":"8408 Spring Meadow Rd Richmond VA 23235",
    "addr:housenumber":"8408",
    "addr:postcode":"23235",
    "addr:street":"Spring Meadow Rd",
    "iso:country":"US",
    "sg:address":"8408 Spring Meadow Rd",
    "sg:city":"Richmond",
    "sg:classifiers":[
        {
            "category":"Professional",
            "subcategory":"Art Services",
            "type":"Services"
        }
    ],
    "sg:phone":"+1 804 320 8600",
    "sg:postcode":"23235",
    "sg:province":"VA",
    "sg:tags":[
        "commercial",
        "design"
    ],
    "wof:name":"Shepherd Visual Communications",
    "wof:placetype":"venue"
},
  "geometry": {"coordinates":[-77.549386,37.516948],"type":"Point"}
}