{
  "type": "Feature",
  "properties": {
    "addr:full":"7646 Brook Rd Richmond VA 23227",
    "addr:housenumber":"7646",
    "addr:postcode":"23227",
    "addr:street":"Brook Rd",
    "iso:country":"US",
    "sg:address":"7646 Brook Rd",
    "sg:city":"Richmond",
    "sg:classifiers":[
        {
            "category":"Professional",
            "type":"Services"
        }
    ],
    "sg:phone":"+1 804 262 5555",
    "sg:postcode":"23227",
    "sg:province":"VA",
    "wof:name":"Josh Wilson",
    "wof:placetype":"venue"
},
  "geometry": {"coordinates":[-77.458585,37.628499],"type":"Point"}
}