{
  "type": "Feature",
  "properties": {
    "iso:country":"US",
    "sg:address":"856 N Main St",
    "sg:city":"Pearisburg",
    "sg:classifiers":[
        {
            "category":"Wholesale",
            "subcategory":"Farm Supplies",
            "type":"Manufacturing & Wholesale Goods"
        }
    ],
    "sg:phone":"+1 540 921 3853",
    "sg:postcode":"24134",
    "sg:province":"VA",
    "sg:tags":[
        "feed"
    ],
    "wof:name":"Giles County Farm Bureau Inc",
    "wof:placetype":"venue"
},
  "geometry": {"coordinates":[-80.75298100000001,37.335398],"type":"Point"}
}