{
  "type": "Feature",
  "properties": {
    "addr:full":"401 N 11th St Richmond VA 23219",
    "addr:housenumber":"401",
    "addr:postcode":"23219",
    "addr:street":"N 11Th St",
    "iso:country":"US",
    "sg:address":"401 N 11th St",
    "sg:city":"Richmond",
    "sg:classifiers":[
        {
            "category":"Health Services",
            "subcategory":"Doctor",
            "type":"Services"
        }
    ],
    "sg:phone":"+1 804 828 3030",
    "sg:postcode":"23219",
    "sg:province":"VA",
    "sg:tags":[
        "physician",
        "surgeon"
    ],
    "wof:name":"Ronald Barton MD",
    "wof:placetype":"venue"
},
  "geometry": {"coordinates":[-77.43046099999999,37.541461],"type":"Point"}
}