{
  "type": "Feature",
  "properties": {
    "addr:full":"16415 Horseshoe Ln Beaverdam VA 23015",
    "addr:housenumber":"16415",
    "addr:postcode":"23015",
    "addr:street":"Horseshoe Ln",
    "iso:country":"US",
    "sg:address":"16415 Horseshoe Ln",
    "sg:city":"Beaverdam",
    "sg:classifiers":[
        {
            "category":"Professional",
            "subcategory":"Computer Services",
            "type":"Services"
        }
    ],
    "sg:phone":"+1 804 449 6890",
    "sg:postcode":"23015",
    "sg:province":"VA",
    "sg:tags":[
        "design",
        "system"
    ],
    "wof:name":"Wolfe Systems",
    "wof:placetype":"venue"
},
  "geometry": {"coordinates":[-77.66963800000001,37.92227],"type":"Point"}
}