{
  "type": "Feature",
  "properties": {
    "addr:full":"6641 Old Dominion Dr Mc Lean VA 22101",
    "addr:housenumber":"6641",
    "addr:postcode":"22101",
    "addr:street":"Old Dominion Dr",
    "iso:country":"US",
    "sg:address":"6641 Old Dominion Dr",
    "sg:city":"Mc Lean",
    "sg:classifiers":[
        {
            "category":"Real Estate",
            "subcategory":"Real Estate Agent",
            "type":"Services"
        }
    ],
    "sg:phone":"+1 703 748 6147",
    "sg:postcode":"22101",
    "sg:province":"VA",
    "sg:website":"www.c21nm.com",
    "wof:name":"Century 21",
    "wof:placetype":"venue"
},
  "geometry": {"coordinates":[-77.17286199999999,38.931056],"type":"Point"}
}