{
  "type": "Feature",
  "properties": {
    "addr:full":"594 Orange Ln Troutville VA 24175",
    "addr:housenumber":"594",
    "addr:postcode":"24175",
    "addr:street":"Orange Ln",
    "iso:country":"US",
    "sg:address":"594 Orange Ln",
    "sg:city":"Troutville",
    "sg:classifiers":[
        {
            "category":"Home & Garden",
            "subcategory":"Building Materials",
            "type":"Retail Goods"
        }
    ],
    "sg:phone":"+1 540 966 1899",
    "sg:postcode":"24175",
    "sg:province":"VA",
    "sg:tags":[
        "lumber"
    ],
    "wof:name":"Premier Hardwood Flooring",
    "wof:placetype":"venue"
},
  "geometry": {"coordinates":[-79.869466,37.378865],"type":"Point"}
}