{
  "type": "Feature",
  "properties": {
    "addr:full":"1515 Deyerle Rd SW Roanoke VA 24018",
    "addr:housenumber":"1515",
    "addr:postcode":"24018",
    "addr:street":"Deyerle Rd Sw",
    "iso:country":"US",
    "sg:address":"1515 Deyerle Rd SW",
    "sg:city":"Roanoke",
    "sg:classifiers":[
        {
            "category":"Health Services",
            "subcategory":"Doctor",
            "type":"Services"
        }
    ],
    "sg:phone":"+1 540 774 7119",
    "sg:postcode":"24018",
    "sg:province":"VA",
    "sg:tags":[
        "physician"
    ],
    "wof:name":"Young S Kang",
    "wof:placetype":"venue"
},
  "geometry": {"coordinates":[-80.01459800000001,37.260412],"type":"Point"}
}