{
  "type": "Feature",
  "properties": {
    "addr:full":"5107 Lakeside Ave Richmond VA 23228",
    "addr:housenumber":"5107",
    "addr:postcode":"23228",
    "addr:street":"Lakeside Ave",
    "iso:country":"US",
    "sg:address":"5107 Lakeside Ave",
    "sg:city":"Richmond",
    "sg:classifiers":[
        {
            "category":"Wholesale",
            "subcategory":"Office Equipment",
            "type":"Manufacturing & Wholesale Goods"
        }
    ],
    "sg:phone":"+1 804 266 2983",
    "sg:postcode":"23228",
    "sg:province":"VA",
    "sg:tags":[
        "machine",
        "duplicating",
        "copying"
    ],
    "wof:name":"Imtek Office Solutions",
    "wof:placetype":"venue"
},
  "geometry": {"coordinates":[-77.46717700000001,37.600635],"type":"Point"}
}