{
  "type": "Feature",
  "properties": {
    "addr:full":"107 Essex Cir Stephens City VA 22655",
    "addr:housenumber":"107",
    "addr:postcode":"22655",
    "addr:street":"Essex Cir",
    "iso:country":"US",
    "sg:address":"107 Essex Cir",
    "sg:city":"Stephens City",
    "sg:classifiers":[
        {
            "category":"Organizations",
            "subcategory":"Community Association",
            "type":"Services"
        }
    ],
    "sg:phone":"+1 540 868 0719",
    "sg:postcode":"22655",
    "sg:province":"VA",
    "wof:name":"Optimist International",
    "wof:placetype":"venue"
},
  "geometry": {"coordinates":[-78.197136,39.08956],"type":"Point"}
}