{
  "type": "Feature",
  "properties": {
    "addr:full":"21401 Sturman Pl Ashburn VA 20148",
    "addr:housenumber":"21401",
    "addr:postcode":"20148",
    "addr:street":"Sturman Pl",
    "iso:country":"US",
    "sg:address":"21401 Sturman Pl",
    "sg:city":"Ashburn",
    "sg:classifiers":[
        {
            "category":"Manufacturing",
            "subcategory":"Electronics",
            "type":"Manufacturing & Wholesale Goods"
        }
    ],
    "sg:phone":"+1 703 726 3004",
    "sg:postcode":"20148",
    "sg:province":"VA",
    "sg:tags":[
        "apparatus",
        "mfg"
    ],
    "wof:name":"Converged Tech Communications",
    "wof:placetype":"venue"
},
  "geometry": {"coordinates":[-77.52727299999999,39.024822],"type":"Point"}
}