{
  "type": "Feature",
  "properties": {
    "iso:country":"US",
    "sg:address":"13135 Lee Jackson Memorial Hwy",
    "sg:city":"Fairfax",
    "sg:classifiers":[
        {
            "category":"Real Estate",
            "subcategory":"Real Estate Agent",
            "type":"Services"
        }
    ],
    "sg:phone":"+1 703 961 8450",
    "sg:postcode":"22033",
    "sg:province":"VA",
    "wof:name":"Tim Walsh",
    "wof:placetype":"venue"
},
  "geometry": {"coordinates":[-77.39773,38.881024],"type":"Point"}
}