{
  "type": "Feature",
  "properties": {
    "iso:country":"US",
    "sg:address":"418 Garrisonville Rd",
    "sg:city":"Stafford",
    "sg:classifiers":[
        {
            "category":"Home & Garden",
            "subcategory":"Carpets & Floor Coverings",
            "type":"Retail Goods"
        }
    ],
    "sg:phone":"+1 540 657 6990",
    "sg:postcode":"22554",
    "sg:province":"VA",
    "wof:name":"Quality Carpet",
    "wof:placetype":"venue"
},
  "geometry": {"coordinates":[-77.42984,38.474585],"type":"Point"}
}