{
  "type": "Feature",
  "properties": {
    "iso:country":"US",
    "sg:address":"4511 Singer Ct",
    "sg:city":"Chantilly",
    "sg:classifiers":[
        {
            "category":"Professional",
            "subcategory":"Business Services",
            "type":"Services"
        }
    ],
    "sg:phone":"+1 703 817 1999",
    "sg:postcode":"20151",
    "sg:province":"VA",
    "sg:tags":[
        "transcription",
        "medical",
        "management",
        "consulting"
    ],
    "wof:name":"Medgarde",
    "wof:placetype":"venue"
},
  "geometry": {"coordinates":[-77.45860999999999,38.889747],"type":"Point"}
}