{
  "type": "Feature",
  "properties": {
    "addr:full":"311 Potomac Ave Quantico VA 22134",
    "addr:housenumber":"311",
    "addr:postcode":"22134",
    "addr:street":"Potomac Ave",
    "iso:country":"US",
    "sg:address":"311 Potomac Ave",
    "sg:city":"Quantico",
    "sg:classifiers":[
        {
            "category":"Banks & Credit Unions",
            "subcategory":"Investment Brokerage",
            "type":"Services"
        },
        {
            "category":"Insurance",
            "subcategory":"Insurance Agent",
            "type":"Services"
        }
    ],
    "sg:phone":"+1 703 630 1754",
    "sg:postcode":"22134",
    "sg:province":"VA",
    "sg:tags":[
        "consultant",
        "planning",
        "financial"
    ],
    "wof:name":"First Command Financial Plan",
    "wof:placetype":"venue"
},
  "geometry": {"coordinates":[-77.292283,38.522351],"type":"Point"}
}