{
  "type": "Feature",
  "properties": {
    "addr:full":"9509 Hull Street Rd Ste A Richmond VA 23236",
    "addr:housenumber":"9509",
    "addr:postcode":"23236",
    "addr:street":"Hull Street Rd Ste A",
    "iso:country":"US",
    "sg:address":"9509 Hull Street Rd Ste A",
    "sg:city":"Richmond",
    "sg:classifiers":[
        {
            "category":"Insurance",
            "subcategory":"Hazard Insurance",
            "type":"Services"
        },
        {
            "category":"Insurance",
            "subcategory":"Insurance Agent",
            "type":"Services"
        },
        {
            "category":"Insurance",
            "subcategory":"Life Insurance",
            "type":"Services"
        },
        {
            "category":"Insurance",
            "subcategory":"Title Insurance",
            "type":"Services"
        }
    ],
    "sg:phone":"+1 804 276 9410",
    "sg:postcode":"23236",
    "sg:province":"VA",
    "sg:tags":[
        "auto",
        "homeowner"
    ],
    "sg:website":"http://www.nationwide.com/agent/Richmond-VIRGINIA-insurance-agent/bill-benton/office.html",
    "wof:name":"William H Benton - Nationwide Insurance",
    "wof:placetype":"venue"
},
  "geometry": {"coordinates":[-77.570554,37.446851],"type":"Point"}
}