{
  "type": "Feature",
  "properties": {
    "iso:country":"US",
    "sg:address":"4485 Danube Dr",
    "sg:city":"King George",
    "sg:classifiers":[
        {
            "category":"Professional",
            "type":"Services"
        }
    ],
    "sg:phone":"+1 540 663 9227",
    "sg:postcode":"22485",
    "sg:province":"VA",
    "wof:name":"Technology Service Corp",
    "wof:placetype":"venue"
},
  "geometry": {"coordinates":[-77.063541,38.346877],"type":"Point"}
}