{
  "type": "Feature",
  "properties": {
    "addr:full":"3301 Lee Hwy Arlington VA 22207",
    "addr:housenumber":"3301",
    "addr:postcode":"22207",
    "addr:street":"Lee Hwy",
    "iso:country":"US",
    "sg:address":"3301 Lee Hwy",
    "sg:city":"Arlington",
    "sg:classifiers":[
        {
            "category":"Shopping",
            "subcategory":"Mobile Phones",
            "type":"Retail Goods"
        }
    ],
    "sg:phone":"+1 703 528 3200",
    "sg:postcode":"22207",
    "sg:province":"VA",
    "wof:name":"Newcom Digital",
    "wof:placetype":"venue"
},
  "geometry": {"coordinates":[-77.101601,38.896301],"type":"Point"}
}