{
  "type": "Feature",
  "properties": {
    "iso:country":"US",
    "sg:address":"15618 N Valley Pike",
    "sg:city":"New Market",
    "sg:classifiers":[
        {
            "category":"Retail",
            "subcategory":"Repair Shop",
            "type":"Services"
        }
    ],
    "sg:phone":"+1 540 740 4324",
    "sg:postcode":"22844",
    "sg:province":"VA",
    "sg:tags":[
        "refinishing",
        "furniture"
    ],
    "wof:name":"Scott's",
    "wof:placetype":"venue"
},
  "geometry": {"coordinates":[-78.694654,38.618144],"type":"Point"}
}