{
  "type": "Feature",
  "properties": {
    "addr:full":"6333 Leesburg Pike Falls Church VA 22044",
    "addr:housenumber":"6333",
    "addr:postcode":"22044",
    "addr:street":"Leesburg Pike",
    "iso:country":"US",
    "sg:address":"6333 Leesburg Pike",
    "sg:city":"Falls Church",
    "sg:classifiers":[
        {
            "category":"Retail",
            "subcategory":"Self-service Laundry",
            "type":"Services"
        }
    ],
    "sg:phone":"+1 703 538 6622",
    "sg:postcode":"22044",
    "sg:province":"VA",
    "sg:tags":[
        "coin"
    ],
    "wof:name":"Seven Corners Laundrymat",
    "wof:placetype":"venue"
},
  "geometry": {"coordinates":[-77.15489700000001,38.870773],"type":"Point"}
}