{
  "type": "Feature",
  "properties": {
    "addr:full":"1002 King St Alexandria VA 22314",
    "addr:housenumber":"1002",
    "addr:postcode":"22314",
    "addr:street":"King St",
    "iso:country":"US",
    "sg:address":"1002 King St",
    "sg:city":"Alexandria",
    "sg:classifiers":[
        {
            "category":"Professional",
            "subcategory":"Management & Consulting",
            "type":"Services"
        }
    ],
    "sg:phone":"+1 703 836 0331",
    "sg:postcode":"22314",
    "sg:province":"VA",
    "sg:tags":[
        "consultant",
        "business"
    ],
    "sg:website":"www.star123.com",
    "wof:name":"Star Care",
    "wof:placetype":"venue"
},
  "geometry": {"coordinates":[-77.05136400000001,38.805548],"type":"Point"}
}