{
  "type": "Feature",
  "properties": {
    "addr:full":"9411 Main St Manassas VA 20110",
    "addr:housenumber":"9411",
    "addr:postcode":"20110",
    "addr:street":"Main St",
    "iso:country":"US",
    "sg:address":"9411 Main St",
    "sg:city":"Manassas",
    "sg:classifiers":[
        {
            "category":"Real Estate",
            "subcategory":"Architect",
            "type":"Services"
        }
    ],
    "sg:phone":"+1 703 368 1600",
    "sg:postcode":"20110",
    "sg:province":"VA",
    "sg:tags":[
        "architectural"
    ],
    "wof:name":"Loveless Rbert B AIA Archtects",
    "wof:placetype":"venue"
},
  "geometry": {"coordinates":[-77.471419,38.750856],"type":"Point"}
}