{
  "type": "Feature",
  "properties": {
    "addr:full":"5111 Westfields Blvd Chantilly VA 20151",
    "addr:housenumber":"5111",
    "addr:postcode":"20151",
    "addr:street":"Westfields Blvd",
    "iso:country":"US",
    "sg:address":"5111 Westfields Blvd",
    "sg:city":"Chantilly",
    "sg:classifiers":[
        {
            "category":"Food & Beverages",
            "subcategory":"Supermarket",
            "type":"Retail Goods"
        },
        {
            "category":"Shopping",
            "subcategory":"Pharmacy",
            "type":"Retail Goods"
        }
    ],
    "sg:phone":"+1 703 631 7472",
    "sg:postcode":"20151",
    "sg:province":"VA",
    "sg:tags":[
        "super",
        "store"
    ],
    "wof:name":"Safeway Food & Drug",
    "wof:placetype":"venue"
},
  "geometry": {"coordinates":[-77.44532,38.873192],"type":"Point"}
}