{
  "type": "Feature",
  "properties": {
    "addr:full":"1248 Locust Ln Bedford VA 24523",
    "addr:housenumber":"1248",
    "addr:postcode":"24523",
    "addr:street":"Locust Ln",
    "iso:country":"US",
    "sg:address":"1248 Locust Ln",
    "sg:city":"Bedford",
    "sg:classifiers":[
        {
            "category":"Farming",
            "subcategory":"Farm",
            "type":"Manufacturing & Wholesale Goods"
        }
    ],
    "sg:phone":"+1 540 587 7611",
    "sg:postcode":"24523",
    "sg:province":"VA",
    "sg:tags":[
        "crop",
        "general"
    ],
    "wof:name":"Lane Locust Fibre Farm",
    "wof:placetype":"venue"
},
  "geometry": {"coordinates":[-79.44333,37.433234],"type":"Point"}
}