{
  "type": "Feature",
  "properties": {
    "iso:country":"US",
    "sg:address":"12914 Old Stage Rd",
    "sg:city":"Chester",
    "sg:classifiers":[
        {
            "category":"Building & Trades",
            "subcategory":"Plumbing",
            "type":"Services"
        }
    ],
    "sg:phone":"+1 804 764 0886",
    "sg:postcode":"23836",
    "sg:province":"VA",
    "sg:tags":[
        "retail",
        "conditioning"
    ],
    "wof:name":"Barlett Mechanical",
    "wof:placetype":"venue"
},
  "geometry": {"coordinates":[-77.396918,37.35127],"type":"Point"}
}