{
  "type": "Feature",
  "properties": {
    "addr:full":"6194 Deer Path Ct Manassas VA 20112",
    "addr:housenumber":"6194",
    "addr:postcode":"20112",
    "addr:street":"Deer Path Ct",
    "iso:country":"US",
    "sg:address":"6194 Deer Path Ct",
    "sg:city":"Manassas",
    "sg:classifiers":[
        {
            "category":"Professional",
            "subcategory":"Computer Services",
            "type":"Services"
        }
    ],
    "sg:phone":"+1 703 335 0848",
    "sg:postcode":"20112",
    "sg:province":"VA",
    "sg:tags":[
        "consultant",
        "designer"
    ],
    "wof:name":"Pbvr",
    "wof:placetype":"venue"
},
  "geometry": {"coordinates":[-77.390038,38.726951],"type":"Point"}
}