{
  "type": "Feature",
  "properties": {
    "addr:full":"5900 E Virginia Beach Blvd Norfolk VA 23502",
    "addr:housenumber":"5900",
    "addr:postcode":"23502",
    "addr:street":"E Virginia Beach Blvd",
    "iso:country":"US",
    "sg:address":"5900 E Virginia Beach Blvd",
    "sg:city":"Norfolk",
    "sg:classifiers":[
        {
            "category":"Shopping",
            "subcategory":"Department Store",
            "type":"Retail Goods"
        }
    ],
    "sg:phone":"+1 757 461 8113",
    "sg:postcode":"23502",
    "sg:province":"VA",
    "sg:tags":[
        "shop"
    ],
    "wof:name":"Dollar Tree",
    "wof:placetype":"venue"
},
  "geometry": {"coordinates":[-76.200554,36.85546],"type":"Point"}
}