{
  "type": "Feature",
  "properties": {
    "iso:country":"US",
    "sg:address":"1340 S Main St",
    "sg:city":"Harrisonburg",
    "sg:classifiers":[
        {
            "category":"Health Services",
            "subcategory":"Chiropractor",
            "type":"Services"
        }
    ],
    "sg:phone":"+1 540 434 8962",
    "sg:postcode":"22801",
    "sg:province":"VA",
    "sg:tags":[
        "medicine",
        "injury",
        "sport",
        "treatment"
    ],
    "sg:website":"http://www.rigglemanchiropracticandacupuncture.com",
    "wof:name":"Riggleman Chiropractic",
    "wof:placetype":"venue"
},
  "geometry": {"coordinates":[-78.880821,38.434952],"type":"Point"}
}