{
  "type": "Feature",
  "properties": {
    "iso:country":"US",
    "sg:address":"11423 Jefferson Ave",
    "sg:city":"Newport News",
    "sg:classifiers":[
        {
            "category":"Retail",
            "subcategory":"Repair Shop",
            "type":"Services"
        }
    ],
    "sg:phone":"+1 757 595 8655",
    "sg:postcode":"23601",
    "sg:province":"VA",
    "wof:name":"IBM Enterprises",
    "wof:placetype":"venue"
},
  "geometry": {"coordinates":[-76.471377,37.068043],"type":"Point"}
}