{
  "type": "Feature",
  "properties": {
    "addr:full":"8223 Hull Street Rd Richmond VA 23235",
    "addr:housenumber":"8223",
    "addr:postcode":"23235",
    "addr:street":"Hull Street Rd",
    "iso:country":"US",
    "sg:address":"8223 Hull Street Rd",
    "sg:city":"Richmond",
    "sg:classifiers":[
        {
            "category":"Restaurant",
            "type":"Food & Drink"
        }
    ],
    "sg:phone":"+1 804 276 0330",
    "sg:postcode":"23235",
    "sg:province":"VA",
    "sg:tags":[
        "eating"
    ],
    "wof:name":"Domino's Pizza",
    "wof:placetype":"venue"
},
  "geometry": {"coordinates":[-77.544251,37.461366],"type":"Point"}
}