{
  "type": "Feature",
  "properties": {
    "addr:full":"11500 Midlothian Tpke Richmond VA 23235",
    "addr:housenumber":"11500",
    "addr:postcode":"23235",
    "addr:street":"Midlothian Tpke",
    "iso:country":"US",
    "sg:address":"11500 Midlothian Tpke",
    "sg:city":"Richmond",
    "sg:classifiers":[
        {
            "category":"Cinema",
            "subcategory":"Movie Theater",
            "type":"Entertainment"
        }
    ],
    "sg:phone":"+1 804 379 7800",
    "sg:postcode":"23235",
    "sg:province":"VA",
    "wof:name":"U A Movies",
    "wof:placetype":"venue"
},
  "geometry": {"coordinates":[-77.60893299999999,37.505533],"type":"Point"}
}