{
  "type": "Feature",
  "properties": {
    "addr:full":"10120 W Broad St Glen Allen VA 23060",
    "addr:housenumber":"10120",
    "addr:postcode":"23060",
    "addr:street":"W Broad St",
    "iso:country":"US",
    "sg:address":"10120 W Broad St",
    "sg:city":"Glen Allen",
    "sg:classifiers":[
        {
            "category":"Banks & Credit Unions",
            "subcategory":"Bank",
            "type":"Services"
        }
    ],
    "sg:phone":"+1 804 346 0100",
    "sg:postcode":"23060",
    "sg:province":"VA",
    "sg:tags":[
        "loan",
        "broker",
        "mortgage"
    ],
    "wof:name":"Resource Mrtg Nnconforming Whl",
    "wof:placetype":"venue"
},
  "geometry": {"coordinates":[-77.570413,37.644833],"type":"Point"}
}