{
  "type": "Feature",
  "properties": {
    "iso:country":"US",
    "sg:address":"189 S Main St",
    "sg:city":"Timberville",
    "sg:classifiers":[
        {
            "category":"Autos & Motor Vehicles",
            "subcategory":"Fuel & Gas Station",
            "type":"Retail Goods"
        }
    ],
    "sg:phone":"+1 540 896 3939",
    "sg:postcode":"22853",
    "sg:province":"VA",
    "sg:tags":[
        "oil"
    ],
    "wof:name":"Texaco",
    "wof:placetype":"venue"
},
  "geometry": {"coordinates":[-78.77399,38.636012],"type":"Point"}
}