{
  "type": "Feature",
  "properties": {
    "addr:full":"1128 Norview Ave Norfolk VA 23513",
    "addr:housenumber":"1128",
    "addr:postcode":"23513",
    "addr:street":"Norview Ave",
    "iso:country":"US",
    "sg:address":"1128 Norview Ave",
    "sg:city":"Norfolk",
    "sg:classifiers":[
        {
            "category":"Insurance",
            "subcategory":"Insurance Agent",
            "type":"Services"
        }
    ],
    "sg:phone":"+1 757 747 2200",
    "sg:postcode":"23513",
    "sg:province":"VA",
    "wof:name":"Nationwide Insurance",
    "wof:placetype":"venue"
},
  "geometry": {"coordinates":[-76.23985999999999,36.889856],"type":"Point"}
}