{
  "type": "Feature",
  "properties": {
    "addr:full":"4532 Cochise Trl Richmond VA 23237",
    "addr:housenumber":"4532",
    "addr:postcode":"23237",
    "addr:street":"Cochise Trl",
    "iso:country":"US",
    "sg:address":"4532 Cochise Trl",
    "sg:city":"Richmond",
    "sg:classifiers":[
        {
            "category":"Building & Trades",
            "subcategory":"Construction",
            "type":"Services"
        }
    ],
    "sg:phone":"+1 804 275 3968",
    "sg:postcode":"23237",
    "sg:province":"VA",
    "sg:tags":[
        "house"
    ],
    "wof:name":"Wolverine Const LLC",
    "wof:placetype":"venue"
},
  "geometry": {"coordinates":[-77.470983,37.410831],"type":"Point"}
}