{
  "type": "Feature",
  "properties": {
    "addr:full":"383 Chantilly Rd Rocky Mount VA 24151",
    "addr:housenumber":"383",
    "addr:postcode":"24151",
    "addr:street":"Chantilly Rd",
    "iso:country":"US",
    "sg:address":"383 Chantilly Rd",
    "sg:city":"Rocky Mount",
    "sg:classifiers":[
        {
            "category":"Retail",
            "subcategory":"Auto Rental",
            "type":"Services"
        }
    ],
    "sg:phone":"+1 540 483 3588",
    "sg:postcode":"24151",
    "sg:province":"VA",
    "sg:tags":[
        "equipment",
        "r",
        "truck",
        "trailer",
        "utility"
    ],
    "wof:name":"U-Haul",
    "wof:placetype":"venue"
},
  "geometry": {"coordinates":[-79.899039,36.882101],"type":"Point"}
}