{
  "type": "Feature",
  "properties": {
    "iso:country":"US",
    "sg:address":"10088 Holly Forks Rd",
    "sg:city":"Toano",
    "sg:classifiers":[
        {
            "category":"Building & Trades",
            "subcategory":"Cleaning & Sanitation",
            "type":"Services"
        }
    ],
    "sg:phone":"+1 757 566 8313",
    "sg:postcode":"23168",
    "sg:province":"VA",
    "wof:name":"Crystal Glass Cleaning",
    "wof:placetype":"venue"
},
  "geometry": {"coordinates":[-76.83587300000001,37.438622],"type":"Point"}
}