{
  "type": "Feature",
  "properties": {
    "addr:full":"1204 Acredale Rd Virginia Beach VA 23464",
    "addr:housenumber":"1204",
    "addr:postcode":"23464",
    "addr:street":"Acredale Rd",
    "iso:country":"US",
    "sg:address":"1204 Acredale Rd",
    "sg:city":"Virginia Beach",
    "sg:classifiers":[
        {
            "category":"Building & Trades",
            "subcategory":"Landscaping Services",
            "type":"Services"
        }
    ],
    "sg:phone":"+1 757 718 2892",
    "sg:postcode":"23464",
    "sg:province":"VA",
    "wof:name":"Quality Lawns L L C",
    "wof:placetype":"venue"
},
  "geometry": {"coordinates":[-76.171457,36.800298],"type":"Point"}
}