{
  "type": "Feature",
  "properties": {
    "addr:full":"2602 Sharmar Rd Roanoke VA 24018",
    "addr:housenumber":"2602",
    "addr:postcode":"24018",
    "addr:street":"Sharmar Rd",
    "iso:country":"US",
    "sg:address":"2602 Sharmar Rd",
    "sg:city":"Roanoke",
    "sg:classifiers":[
        {
            "category":"Manufacturing",
            "subcategory":"Tools & Machinery",
            "type":"Manufacturing & Wholesale Goods"
        }
    ],
    "sg:phone":"+1 540 989 9830",
    "sg:postcode":"24018",
    "sg:province":"VA",
    "sg:tags":[
        "surgical",
        "mfg"
    ],
    "wof:name":"Class Sticks",
    "wof:placetype":"venue"
},
  "geometry": {"coordinates":[-79.99851700000001,37.247143],"type":"Point"}
}