{
  "type": "Feature",
  "properties": {
    "addr:full":"9615 Oakington Dr Fairfax Station VA 22039",
    "addr:housenumber":"9615",
    "addr:postcode":"22039",
    "addr:street":"Oakington Dr",
    "iso:country":"US",
    "sg:address":"9615 Oakington Dr",
    "sg:city":"Fairfax Station",
    "sg:classifiers":[
        {
            "category":"Organizations",
            "subcategory":"Membership Organization",
            "type":"Services"
        }
    ],
    "sg:phone":"+1 703 690 2591",
    "sg:postcode":"22039",
    "sg:province":"VA",
    "sg:tags":[
        "swim",
        "team"
    ],
    "wof:name":"Crosspointe Cruiser Swim Team",
    "wof:placetype":"venue"
},
  "geometry": {"coordinates":[-77.27483599999999,38.736987],"type":"Point"}
}