{
  "type": "Feature",
  "properties": {
    "addr:full":"49 S Main St Kilmarnock VA 22482",
    "addr:housenumber":"49",
    "addr:postcode":"22482",
    "addr:street":"S Main St",
    "iso:country":"US",
    "sg:address":"49 S Main St",
    "sg:city":"Kilmarnock",
    "sg:classifiers":[
        {
            "category":"Shopping",
            "subcategory":"Gifts & Souvenirs",
            "type":"Retail Goods"
        }
    ],
    "sg:phone":"+1 804 435 2761",
    "sg:postcode":"22482",
    "sg:province":"VA",
    "sg:tags":[
        "shop"
    ],
    "wof:name":"Main Street Gift Co",
    "wof:placetype":"venue"
},
  "geometry": {"coordinates":[-76.379814,37.709643],"type":"Point"}
}