{
  "type": "Feature",
  "properties": {
    "iso:country":"US",
    "sg:address":"10204 Attems Way",
    "sg:city":"Glen Allen",
    "sg:classifiers":[
        {
            "category":"Organizations",
            "subcategory":"Membership Organization",
            "type":"Services"
        }
    ],
    "sg:phone":"+1 804 672 8043",
    "sg:postcode":"23060",
    "sg:province":"VA",
    "wof:name":"Christian Enterprises Inc",
    "wof:placetype":"venue"
},
  "geometry": {"coordinates":[-77.514949,37.653072],"type":"Point"}
}