{
  "type": "Feature",
  "properties": {
    "iso:country":"US",
    "sg:address":"2310 S Rolfe St",
    "sg:city":"Arlington",
    "sg:classifiers":[
        {
            "category":"Professional",
            "type":"Services"
        }
    ],
    "sg:phone":"+1 703 521 6264",
    "sg:postcode":"22202",
    "sg:province":"VA",
    "wof:name":"Frank W Erwin",
    "wof:placetype":"venue"
},
  "geometry": {"coordinates":[-77.074028,38.851494],"type":"Point"}
}