{
  "type": "Feature",
  "properties": {
    "addr:full":"4408 W Hundred Rd Chester VA 23831",
    "addr:housenumber":"4408",
    "addr:postcode":"23831",
    "addr:street":"W Hundred Rd",
    "iso:country":"US",
    "sg:address":"4408 W Hundred Rd",
    "sg:city":"Chester",
    "sg:classifiers":[
        {
            "category":"Shopping",
            "subcategory":"Pharmacy",
            "type":"Retail Goods"
        }
    ],
    "sg:phone":"+1 804 748 2284",
    "sg:postcode":"23831",
    "sg:province":"VA",
    "wof:name":"Eckerd Drugs",
    "wof:placetype":"venue"
},
  "geometry": {"coordinates":[-77.44872700000001,37.354855],"type":"Point"}
}