{
  "type": "Feature",
  "properties": {
    "addr:full":"22173 General Thomas Hwy Newsoms VA 23827",
    "addr:housenumber":"22173",
    "addr:postcode":"23827",
    "addr:street":"General Thomas Hwy",
    "iso:country":"US",
    "sg:address":"22173 General Thomas Hwy",
    "sg:city":"Newsoms",
    "sg:classifiers":[
        {
            "category":"Restaurant",
            "type":"Food & Drink"
        }
    ],
    "sg:phone":"+1 757 654 6100",
    "sg:postcode":"23827",
    "sg:province":"VA",
    "wof:name":"Newsom's Cafe",
    "wof:placetype":"venue"
},
  "geometry": {"coordinates":[-77.132403,36.627568],"type":"Point"}
}