{
  "type": "Feature",
  "properties": {
    "addr:full":"919 S High St Harrisonburg VA 22801",
    "addr:housenumber":"919",
    "addr:postcode":"22801",
    "addr:street":"S High St",
    "iso:country":"US",
    "sg:address":"919 S High St",
    "sg:city":"Harrisonburg",
    "sg:classifiers":[
        {
            "category":"Restaurant",
            "type":"Food & Drink"
        }
    ],
    "sg:phone":"+1 540 801 8878",
    "sg:postcode":"22801",
    "sg:province":"VA",
    "sg:tags":[
        "eating"
    ],
    "wof:name":"Taste of Thai",
    "wof:placetype":"venue"
},
  "geometry": {"coordinates":[-78.88479700000001,38.440715],"type":"Point"}
}