{
  "type": "Feature",
  "properties": {
    "addr:full":"5502 S Oaks Ave Fredericksburg VA 22407",
    "addr:housenumber":"5502",
    "addr:postcode":"22407",
    "addr:street":"S Oaks Ave",
    "iso:country":"US",
    "sg:address":"5502 S Oaks Ave",
    "sg:city":"Fredericksburg",
    "sg:classifiers":[
        {
            "category":"Building & Trades",
            "subcategory":"Construction",
            "type":"Services"
        }
    ],
    "sg:phone":"+1 540 424 3087",
    "sg:postcode":"22407",
    "sg:province":"VA",
    "sg:tags":[
        "contractor"
    ],
    "wof:name":"Dannys Siding",
    "wof:placetype":"venue"
},
  "geometry": {"coordinates":[-77.519165,38.201901],"type":"Point"}
}