{
  "type": "Feature",
  "properties": {
    "iso:country":"US",
    "sg:address":"1440 Carl D Silver Pkwy",
    "sg:city":"Fredericksburg",
    "sg:classifiers":[
        {
            "category":"Home & Garden",
            "subcategory":"Building Materials",
            "type":"Retail Goods"
        }
    ],
    "sg:phone":"+1 540 548 4562",
    "sg:postcode":"22401",
    "sg:province":"VA",
    "sg:tags":[
        "paint"
    ],
    "wof:name":"Virginia Paint Co & Design Ctr",
    "wof:placetype":"venue"
},
  "geometry": {"coordinates":[-77.50946999999999,38.305187],"type":"Point"}
}