{
  "type": "Feature",
  "properties": {
    "iso:country":"US",
    "sg:address":"30 Perchwood Dr",
    "sg:city":"Fredericksburg",
    "sg:classifiers":[
        {
            "category":"Building & Trades",
            "subcategory":"Construction",
            "type":"Services"
        }
    ],
    "sg:phone":"+1 540 368 9788",
    "sg:postcode":"22405",
    "sg:province":"VA",
    "sg:tags":[
        "roofing",
        "contractor"
    ],
    "wof:name":"Wilsey Home Improvements",
    "wof:placetype":"venue"
},
  "geometry": {"coordinates":[-77.44089,38.383805],"type":"Point"}
}