{
  "type": "Feature",
  "properties": {
    "iso:country":"US",
    "sg:address":"250 Jefferson Ave N",
    "sg:city":"Pulaski",
    "sg:classifiers":[
        {
            "category":"Shopping",
            "subcategory":"Computers & Home Electronics",
            "type":"Retail Goods"
        }
    ],
    "sg:phone":"+1 540 994 5900",
    "sg:postcode":"24301",
    "sg:province":"VA",
    "sg:tags":[
        "equipment",
        "dealer"
    ],
    "wof:name":"Cats Computing",
    "wof:placetype":"venue"
},
  "geometry": {"coordinates":[-80.782269,37.048375],"type":"Point"}
}