{
  "type": "Feature",
  "properties": {
    "addr:full":"3041 Radford Rd Christiansburg VA 24073",
    "addr:housenumber":"3041",
    "addr:postcode":"24073",
    "addr:street":"Radford Rd",
    "iso:country":"US",
    "sg:address":"3041 Radford Rd",
    "sg:city":"Christiansburg",
    "sg:classifiers":[
        {
            "category":"Retail",
            "subcategory":"Auto Repair",
            "type":"Services"
        }
    ],
    "sg:phone":"+1 540 633 2066",
    "sg:postcode":"24073",
    "sg:province":"VA",
    "sg:tags":[
        "truck"
    ],
    "wof:name":"Dove Truck Svc",
    "wof:placetype":"venue"
},
  "geometry": {"coordinates":[-80.495745,37.129521],"type":"Point"}
}