{
  "type": "Feature",
  "properties": {
    "iso:country":"US",
    "sg:address":"40 Hunt Club Blvd",
    "sg:city":"Hampton",
    "sg:classifiers":[
        {
            "category":"Social Services",
            "type":"Services"
        }
    ],
    "sg:phone":"+1 757 827 0000",
    "sg:postcode":"23666",
    "sg:province":"VA",
    "sg:tags":[
        "residence",
        "adult",
        "care"
    ],
    "wof:name":"Mallory Woods Inc",
    "wof:placetype":"venue"
},
  "geometry": {"coordinates":[-76.410538,37.041374],"type":"Point"}
}