{
  "type": "Feature",
  "properties": {
    "iso:country":"US",
    "sg:address":"7309 Hanover Green Dr Ste 100 - 202",
    "sg:city":"Mechanicsville",
    "sg:classifiers":[
        {
            "category":"Professional",
            "subcategory":"Lawyer & Legal Services",
            "type":"Services"
        }
    ],
    "sg:phone":"+1 804 789 0192",
    "sg:postcode":"23111",
    "sg:province":"VA",
    "sg:tags":[
        "attorney",
        "business",
        "corporation",
        "partnership",
        "planning",
        "real estate",
        "law"
    ],
    "sg:website":"http://www.dulinglaw.com",
    "wof:name":"Duling Law Firm",
    "wof:placetype":"venue"
},
  "geometry": {"coordinates":[-77.376606,37.604827],"type":"Point"}
}