{
  "type": "Feature",
  "properties": {
    "addr:full":"205 Gristmill Dr Forest VA 24551",
    "addr:housenumber":"205",
    "addr:postcode":"24551",
    "addr:street":"Gristmill Dr",
    "iso:country":"US",
    "sg:address":"205 Gristmill Dr",
    "sg:city":"Forest",
    "sg:classifiers":[
        {
            "category":"Restaurant",
            "type":"Food & Drink"
        }
    ],
    "sg:menulink":"http://www.allmenus.com/va/jefferson/57697-china-royal---chinese--japanese-restaurant/menu/",
    "sg:phone":"+1 434 385 0011",
    "sg:postcode":"24551",
    "sg:province":"VA",
    "sg:tags":[
        "asian",
        "chinese"
    ],
    "wof:name":"China Royal - Chinese & Japanese Restaurant",
    "wof:placetype":"venue"
},
  "geometry": {"coordinates":[-79.24759,37.375249],"type":"Point"}
}