{
  "type": "Feature",
  "properties": {
    "addr:full":"507 S Main St Rocky Mount VA 24151",
    "addr:housenumber":"507",
    "addr:postcode":"24151",
    "addr:street":"S Main St",
    "iso:country":"US",
    "sg:address":"507 S Main St",
    "sg:city":"Rocky Mount",
    "sg:classifiers":[
        {
            "category":"Farming",
            "subcategory":"Farm & Veterinary Services",
            "type":"Manufacturing & Wholesale Goods"
        }
    ],
    "sg:phone":"+1 540 483 9326",
    "sg:postcode":"24151",
    "sg:province":"VA",
    "sg:tags":[
        "insemination"
    ],
    "wof:name":"Windswept Genetics",
    "wof:placetype":"venue"
},
  "geometry": {"coordinates":[-79.890027,36.987863],"type":"Point"}
}