{
  "type": "Feature",
  "properties": {
    "addr:full":"1834 Mountainside Ave Suffolk VA 23434",
    "addr:housenumber":"1834",
    "addr:postcode":"23434",
    "addr:street":"Mountainside Ave",
    "iso:country":"US",
    "sg:address":"1834 Mountainside Ave",
    "sg:city":"Suffolk",
    "sg:classifiers":[
        {
            "category":"Freight",
            "type":"Transportation"
        }
    ],
    "sg:phone":"+1 757 934 1780",
    "sg:postcode":"23434",
    "sg:province":"VA",
    "sg:tags":[
        "operator",
        "local",
        "trucking"
    ],
    "wof:name":"Bell Street Trucking Inc",
    "wof:placetype":"venue"
},
  "geometry": {"coordinates":[-76.650013,36.723222],"type":"Point"}
}