{
  "type": "Feature",
  "properties": {
    "addr:full":"641 S Washington St Alexandria VA 22314",
    "addr:housenumber":"641",
    "addr:postcode":"22314",
    "addr:street":"S Washington St",
    "iso:country":"US",
    "sg:address":"641 S Washington St",
    "sg:city":"Alexandria",
    "sg:classifiers":[
        {
            "category":"Health Services",
            "subcategory":"Health Practitioner",
            "type":"Services"
        }
    ],
    "sg:phone":"+1 703 683 1155",
    "sg:postcode":"22314",
    "sg:province":"VA",
    "wof:name":"Eugene C Stammeyer",
    "wof:placetype":"venue"
},
  "geometry": {"coordinates":[-77.048429,38.798684],"type":"Point"}
}