{
  "type": "Feature",
  "properties": {
    "addr:full":"5054 Donovan Dr Alexandria VA 22304",
    "addr:housenumber":"5054",
    "addr:postcode":"22304",
    "addr:street":"Donovan Dr",
    "iso:country":"US",
    "sg:address":"5054 Donovan Dr",
    "sg:city":"Alexandria",
    "sg:classifiers":[
        {
            "category":"Education",
            "subcategory":"Special Training",
            "type":"Public Place"
        }
    ],
    "sg:phone":"+1 703 461 8497",
    "sg:postcode":"22304",
    "sg:province":"VA",
    "sg:tags":[
        "instructor",
        "language"
    ],
    "wof:name":"Bae Yeonmi",
    "wof:placetype":"venue"
},
  "geometry": {"coordinates":[-77.120633,38.808148],"type":"Point"}
}