{
  "type": "Feature",
  "properties": {
    "iso:country":"US",
    "sg:address":"4560 Longhill Rd",
    "sg:city":"Williamsburg",
    "sg:classifiers":[
        {
            "category":"Travel",
            "subcategory":"Hotels & Motels",
            "type":"Entertainment"
        }
    ],
    "sg:phone":"+1 757 565 0248",
    "sg:postcode":"23188",
    "sg:province":"VA",
    "sg:tags":[
        "breakfast",
        "bed"
    ],
    "sg:website":"www.warhillinn.com",
    "wof:name":"War Hill Inn Bed & Breakfast",
    "wof:placetype":"venue"
},
  "geometry": {"coordinates":[-76.76197000000001,37.314367],"type":"Point"}
}