{
  "type": "Feature",
  "properties": {
    "addr:full":"1201 S Eads St Apt 1902 Arlington VA 22202",
    "addr:housenumber":"1201;1902",
    "addr:postcode":"22202",
    "addr:street":"S Eads St Apt",
    "iso:country":"US",
    "sg:address":"1201 S Eads St Apt 1902",
    "sg:city":"Arlington",
    "sg:classifiers":[
        {
            "category":"Government",
            "subcategory":"Office",
            "type":"Public Place"
        }
    ],
    "sg:phone":"+1 208 305 4735",
    "sg:postcode":"22202",
    "sg:province":"VA",
    "sg:tags":[
        "government-state"
    ],
    "wof:name":"Idaho State Society",
    "wof:placetype":"venue"
},
  "geometry": {"coordinates":[-77.054253,38.863022],"type":"Point"}
}