{
  "type": "Feature",
  "properties": {
    "addr:full":"100 N Providence Rd Richmond VA 23235",
    "addr:housenumber":"100",
    "addr:postcode":"23235",
    "addr:street":"N Providence Rd",
    "iso:country":"US",
    "sg:address":"100 N Providence Rd",
    "sg:city":"Richmond",
    "sg:classifiers":[
        {
            "category":"Organizations",
            "subcategory":"Religious Organization",
            "type":"Services"
        }
    ],
    "sg:phone":"+1 804 320 4325",
    "sg:postcode":"23235",
    "sg:province":"VA",
    "sg:tags":[
        "church"
    ],
    "wof:name":"Healing Room",
    "wof:placetype":"venue"
},
  "geometry": {"coordinates":[-77.547374,37.498457],"type":"Point"}
}