{
  "type": "Feature",
  "properties": {
    "addr:full":"6552 Green Hill Rd Linville VA 22834",
    "addr:housenumber":"6552",
    "addr:postcode":"22834",
    "addr:street":"Green Hill Rd",
    "iso:country":"US",
    "sg:address":"6552 Green Hill Rd",
    "sg:city":"Linville",
    "sg:classifiers":[
        {
            "category":"Organizations",
            "subcategory":"Religious Organization",
            "type":"Services"
        }
    ],
    "sg:phone":"+1 540 833 2045",
    "sg:postcode":"22834",
    "sg:province":"VA",
    "wof:name":"Green Hill Church",
    "wof:placetype":"venue"
},
  "geometry": {"coordinates":[-78.900094,38.552554],"type":"Point"}
}