{
  "type": "Feature",
  "properties": {
    "addr:full":"8317 Robert Bruce Dr Richmond VA 23235",
    "addr:housenumber":"8317",
    "addr:postcode":"23235",
    "addr:street":"Robert Bruce Dr",
    "iso:country":"US",
    "sg:address":"8317 Robert Bruce Dr",
    "sg:city":"Richmond",
    "sg:classifiers":[
        {
            "category":"Professional",
            "subcategory":"Research",
            "type":"Services"
        }
    ],
    "sg:phone":"+1 804 320 6236",
    "sg:postcode":"23235",
    "sg:province":"VA",
    "sg:tags":[
        "development"
    ],
    "wof:name":"Himicro Inc",
    "wof:placetype":"venue"
},
  "geometry": {"coordinates":[-77.552346,37.528278],"type":"Point"}
}