{
  "type": "Feature",
  "properties": {
    "iso:country":"US",
    "sg:address":"234 W King St",
    "sg:city":"Strasburg",
    "sg:classifiers":[
        {
            "category":"Health Services",
            "subcategory":"Chiropractor",
            "type":"Services"
        }
    ],
    "sg:phone":"+1 540 465 4858",
    "sg:postcode":"22657",
    "sg:province":"VA",
    "wof:name":"Strasburg Chiropractic/Wllness",
    "wof:placetype":"venue"
},
  "geometry": {"coordinates":[-78.365455,38.990272],"type":"Point"}
}