{
  "type": "Feature",
  "properties": {
    "addr:full":"1996 Richmond Hwy Gladstone VA 24553",
    "addr:housenumber":"1996",
    "addr:postcode":"24553",
    "addr:street":"Richmond Hwy",
    "iso:country":"US",
    "sg:address":"1996 Richmond Hwy",
    "sg:city":"Gladstone",
    "sg:classifiers":[
        {
            "category":"Freight",
            "type":"Transportation"
        }
    ],
    "sg:phone":"+1 434 946 9693",
    "sg:postcode":"24553",
    "sg:province":"VA",
    "sg:tags":[
        "operator",
        "local",
        "trucking"
    ],
    "wof:name":"John W Gunter Jr",
    "wof:placetype":"venue"
},
  "geometry": {"coordinates":[-78.96537499999999,37.56272],"type":"Point"}
}