{
  "type": "Feature",
  "properties": {
    "iso:country":"US",
    "sg:address":"13958 Lee Jackson Memorial Hwy",
    "sg:city":"Chantilly",
    "sg:classifiers":[
        {
            "category":"Restaurant",
            "type":"Food & Drink"
        }
    ],
    "sg:menulink":"http://www.allmenus.com/va/sully/70946-jerrys-subs--pizza/menu/",
    "sg:phone":"+1 703 378 7901",
    "sg:postcode":"20151",
    "sg:province":"VA",
    "sg:tags":[
        "sandwich",
        "salad",
        "cheesesteaks",
        "soup",
        "american",
        "wrap",
        "wing",
        "pizza"
    ],
    "wof:name":"Jerry's Subs & Pizza",
    "wof:placetype":"venue"
},
  "geometry": {"coordinates":[-77.429346,38.893538],"type":"Point"}
}