{
  "type": "Feature",
  "properties": {
    "addr:full":"8023 Tysons Corner Ctr Mc Lean VA 22102",
    "addr:housenumber":"8023",
    "addr:postcode":"22102",
    "addr:street":"Tysons Corner Ctr Mc Lean",
    "iso:country":"US",
    "sg:address":"8023 Tysons Corner Ctr",
    "sg:city":"Mc Lean",
    "sg:classifiers":[
        {
            "category":"Shopping",
            "subcategory":"Clothing, Apparel, & Fashions",
            "type":"Retail Goods"
        }
    ],
    "sg:phone":"+1 703 288 1200",
    "sg:postcode":"22102",
    "sg:province":"VA",
    "sg:tags":[
        "accessory",
        "clothing",
        "women's"
    ],
    "wof:name":"White House Black Market 3141",
    "wof:placetype":"venue"
},
  "geometry": {"coordinates":[-77.22008700000001,38.91607],"type":"Point"}
}