{
  "type": "Feature",
  "properties": {
    "addr:full":"350 N Maple Ave Covington VA 24426",
    "addr:housenumber":"350",
    "addr:postcode":"24426",
    "addr:street":"N Maple Ave",
    "iso:country":"US",
    "sg:address":"350 N Maple Ave",
    "sg:city":"Covington",
    "sg:classifiers":[
        {
            "category":"Retail",
            "subcategory":"Funeral Services",
            "type":"Services"
        }
    ],
    "sg:phone":"+1 540 962 2283",
    "sg:postcode":"24426",
    "sg:province":"VA",
    "sg:tags":[
        "director"
    ],
    "wof:name":"Loving Funeral Home",
    "wof:placetype":"venue"
},
  "geometry": {"coordinates":[-79.997005,37.791387],"type":"Point"}
}