{
  "type": "Feature",
  "properties": {
    "addr:full":"903 Hardy Rd Vinton VA 24179",
    "addr:housenumber":"903",
    "addr:postcode":"24179",
    "addr:street":"Hardy Rd",
    "iso:country":"US",
    "sg:address":"903 Hardy Rd",
    "sg:city":"Vinton",
    "sg:classifiers":[
        {
            "category":"Cinema",
            "subcategory":"Movie Rental",
            "type":"Entertainment"
        }
    ],
    "sg:phone":"+1 540 981 0742",
    "sg:postcode":"24179",
    "sg:province":"VA",
    "sg:tags":[
        "leasing",
        "video",
        "disc",
        "tape"
    ],
    "sg:website":"www.blockbuster.com",
    "wof:name":"Blockbuster Video",
    "wof:placetype":"venue"
},
  "geometry": {"coordinates":[-79.887878,37.273009],"type":"Point"}
}