{
  "type": "Feature",
  "properties": {
    "addr:full":"2268 N Upton St Arlington VA 22207",
    "addr:housenumber":"2268",
    "addr:postcode":"22207",
    "addr:street":"N Upton St",
    "iso:country":"US",
    "sg:address":"2268 N Upton St",
    "sg:city":"Arlington",
    "sg:classifiers":[
        {
            "category":"Building & Trades",
            "subcategory":"Landscaping Services",
            "type":"Services"
        }
    ],
    "sg:phone":"+1 703 525 4540",
    "sg:postcode":"22207",
    "sg:province":"VA",
    "wof:name":"Jeff Minnich Garden Design Inc",
    "wof:placetype":"venue"
},
  "geometry": {"coordinates":[-77.117259,38.901697],"type":"Point"}
}