{
  "type": "Feature",
  "properties": {
    "iso:country":"US",
    "sg:address":"5704 Yewing Way",
    "sg:city":"Gainesville",
    "sg:classifiers":[
        {
            "category":"Freight",
            "type":"Transportation"
        }
    ],
    "sg:phone":"+1 703 754 4522",
    "sg:postcode":"20155",
    "sg:province":"VA",
    "sg:tags":[
        "trucking"
    ],
    "sg:website":"http://www.onthelevel-va.com",
    "wof:name":"On The Level Contracting & Trucking Inc",
    "wof:placetype":"venue"
},
  "geometry": {"coordinates":[-77.60303500000001,38.843965],"type":"Point"}
}