{
  "type": "Feature",
  "properties": {
    "addr:full":"1222 Bentley St Richmond VA 23227",
    "addr:housenumber":"1222",
    "addr:postcode":"23227",
    "addr:street":"Bentley St",
    "iso:country":"US",
    "sg:address":"1222 Bentley St",
    "sg:city":"Richmond",
    "sg:classifiers":[
        {
            "category":"Autos & Motor Vehicles",
            "subcategory":"Auto Supplies",
            "type":"Retail Goods"
        }
    ],
    "sg:phone":"+1 804 266 2487",
    "sg:postcode":"23227",
    "sg:province":"VA",
    "wof:name":"Goodyear",
    "wof:placetype":"venue"
},
  "geometry": {"coordinates":[-77.456543,37.602631],"type":"Point"}
}