{
  "type": "Feature",
  "properties": {
    "iso:country":"US",
    "sg:address":"2109 Silver Oaks Ct",
    "sg:city":"Virginia Beach",
    "sg:classifiers":[
        {
            "category":"Building & Trades",
            "subcategory":"Electrical",
            "type":"Services"
        }
    ],
    "sg:phone":"+1 757 739 0024",
    "sg:postcode":"23456",
    "sg:province":"VA",
    "sg:tags":[
        "electrical",
        "contractor"
    ],
    "wof:name":"Pro Mole",
    "wof:placetype":"venue"
},
  "geometry": {"coordinates":[-76.026242,36.763535],"type":"Point"}
}