{
  "type": "Feature",
  "properties": {
    "addr:full":"8560 Rothbury Dr Bristow VA 20136",
    "addr:housenumber":"8560",
    "addr:postcode":"20136",
    "addr:street":"Rothbury Dr",
    "iso:country":"US",
    "sg:address":"8560 Rothbury Dr",
    "sg:city":"Bristow",
    "sg:phone":"+1 703 335 1158",
    "sg:postcode":"20136",
    "sg:province":"VA",
    "sg:tags":[
        "product",
        "petroleum"
    ],
    "wof:name":"GE",
    "wof:placetype":"venue"
},
  "geometry": {"coordinates":[-77.563301,38.772414],"type":"Point"}
}