{
  "type": "Feature",
  "properties": {
    "iso:country":"US",
    "sg:address":"611 Della St",
    "sg:city":"Tappahannock",
    "sg:classifiers":[
        {
            "category":"Health Services",
            "subcategory":"Optometrist",
            "type":"Services"
        }
    ],
    "sg:phone":"+1 804 443 3901",
    "sg:postcode":"22560",
    "sg:province":"VA",
    "wof:name":"William G Ryan LTD",
    "wof:placetype":"venue"
},
  "geometry": {"coordinates":[-76.857429,37.925639],"type":"Point"}
}