{
  "type": "Feature",
  "properties": {
    "iso:country":"US",
    "sg:address":"1008 Bryce Ln",
    "sg:city":"Virginia Beach",
    "sg:classifiers":[
        {
            "category":"Organizations",
            "subcategory":"Membership Organization",
            "type":"Services"
        }
    ],
    "sg:phone":"+1 757 420 0064",
    "sg:postcode":"23464",
    "sg:province":"VA",
    "wof:name":"Amer Veterans Post 69",
    "wof:placetype":"venue"
},
  "geometry": {"coordinates":[-76.203199,36.808818],"type":"Point"}
}