{
  "type": "Feature",
  "properties": {
    "addr:full":"5231 Peters Creek Rd NW Roanoke VA 24019",
    "addr:housenumber":"5231",
    "addr:postcode":"24019",
    "addr:street":"Peters Creek Rd Nw",
    "iso:country":"US",
    "sg:address":"5231 Peters Creek Rd NW",
    "sg:city":"Roanoke",
    "sg:classifiers":[
        {
            "category":"Wholesale",
            "subcategory":"Hardware",
            "type":"Manufacturing & Wholesale Goods"
        }
    ],
    "sg:phone":"+1 540 265 0751",
    "sg:postcode":"24019",
    "sg:province":"VA",
    "sg:tags":[
        "air",
        "parts",
        "conditioning",
        "supply"
    ],
    "wof:name":"Johnstone Supply",
    "wof:placetype":"venue"
},
  "geometry": {"coordinates":[-79.978323,37.332493],"type":"Point"}
}