{
  "type": "Feature",
  "properties": {
    "iso:country":"US",
    "sg:address":"1055 W Broad St",
    "sg:city":"Falls Church",
    "sg:classifiers":[
        {
            "category":"Wholesale",
            "subcategory":"Machinery & Supplies",
            "type":"Manufacturing & Wholesale Goods"
        }
    ],
    "sg:phone":"+1 703 534 8882",
    "sg:postcode":"22046",
    "sg:province":"VA",
    "sg:tags":[
        "salon",
        "beauty"
    ],
    "wof:name":"Universal Beauty Supply",
    "wof:placetype":"venue"
},
  "geometry": {"coordinates":[-77.185497,38.891354],"type":"Point"}
}