{
  "type": "Feature",
  "properties": {
    "addr:full":"210 Wyrick Springrd Crockett VA 24323",
    "addr:housenumber":"210",
    "addr:postcode":"24323",
    "addr:street":"Wyrick Springrd",
    "iso:country":"US",
    "sg:address":"210 Wyrick Springrd",
    "sg:city":"Crockett",
    "sg:classifiers":[
        {
            "category":"Farming",
            "subcategory":"Livestock Farm",
            "type":"Manufacturing & Wholesale Goods"
        }
    ],
    "sg:phone":"+1 276 686 4301",
    "sg:postcode":"24323",
    "sg:province":"VA",
    "sg:tags":[
        "beef",
        "feedlot",
        "cattle"
    ],
    "wof:name":"Larry Taylor",
    "wof:placetype":"venue"
},
  "geometry": {"coordinates":[-81.192143,36.884532],"type":"Point"}
}