{
  "type": "Feature",
  "properties": {
    "addr:full":"629 N Washington Hwy Ashland VA 23005",
    "addr:housenumber":"629",
    "addr:postcode":"23005",
    "addr:street":"N Washington Hwy",
    "iso:country":"US",
    "sg:address":"629 N Washington Hwy",
    "sg:city":"Ashland",
    "sg:classifiers":[
        {
            "category":"Building & Trades",
            "subcategory":"Construction",
            "type":"Services"
        }
    ],
    "sg:phone":"+1 804 752 7600",
    "sg:postcode":"23005",
    "sg:province":"VA",
    "sg:tags":[
        "general",
        "contractor"
    ],
    "wof:name":"Gulf Seaboard General Contrs",
    "wof:placetype":"venue"
},
  "geometry": {"coordinates":[-77.46766100000001,37.773685],"type":"Point"}
}