{
  "type": "Feature",
  "properties": {
    "addr:full":"313 2nd St SE Charlottesville VA 22902",
    "addr:housenumber":"313",
    "addr:postcode":"22902",
    "addr:street":"2Nd St Se",
    "iso:country":"US",
    "sg:address":"313 2nd St SE",
    "sg:city":"Charlottesville",
    "sg:classifiers":[
        {
            "category":"Professional",
            "type":"Services"
        }
    ],
    "sg:phone":"+1 434 971 8949",
    "sg:postcode":"22902",
    "sg:province":"VA",
    "sg:tags":[
        "establishment"
    ],
    "wof:name":"Independent Inventors Fndtn",
    "wof:placetype":"venue"
},
  "geometry": {"coordinates":[-78.48153499999999,38.029045],"type":"Point"}
}