{
  "type": "Feature",
  "properties": {
    "addr:full":"11261 Genito Rd Amelia Court House VA 23002",
    "addr:housenumber":"11261",
    "addr:postcode":"23002",
    "addr:street":"Genito Rd",
    "iso:country":"US",
    "sg:address":"11261 Genito Rd",
    "sg:city":"Amelia Court House",
    "sg:classifiers":[
        {
            "category":"Manufacturing",
            "subcategory":"Apparel",
            "type":"Manufacturing & Wholesale Goods"
        }
    ],
    "sg:phone":"+1 804 763 6504",
    "sg:postcode":"23002",
    "sg:province":"VA",
    "sg:tags":[
        "mfg"
    ],
    "wof:name":"L & H Apparels",
    "wof:placetype":"venue"
},
  "geometry": {"coordinates":[-77.878283,37.446146],"type":"Point"}
}