{
  "type": "Feature",
  "properties": {
    "addr:full":"5827 Columbia Pike Ste 411 Falls Church VA 22041",
    "addr:housenumber":"5827",
    "addr:postcode":"22041",
    "addr:street":"Columbia Pike Ste 411",
    "iso:country":"US",
    "sg:address":"5827 Columbia Pike Ste 411",
    "sg:city":"Falls Church",
    "sg:classifiers":[
        {
            "category":"Professional",
            "subcategory":"Computer Services",
            "type":"Services"
        }
    ],
    "sg:phone":"+1 571 480 8633",
    "sg:postcode":"22041",
    "sg:province":"VA",
    "sg:tags":[
        "repair"
    ],
    "sg:website":"www.itcrs.net",
    "wof:name":"IT Computer Repair & Systems",
    "wof:placetype":"venue"
},
  "geometry": {"coordinates":[-77.131344,38.848719],"type":"Point"}
}