{
  "type": "Feature",
  "properties": {
    "addr:full":"116 Pintail Trce Williamsburg VA 23188",
    "addr:housenumber":"116",
    "addr:postcode":"23188",
    "addr:street":"Pintail Trce",
    "iso:country":"US",
    "sg:address":"116 Pintail Trce",
    "sg:city":"Williamsburg",
    "sg:classifiers":[
        {
            "category":"Banks & Credit Unions",
            "subcategory":"Investment Brokerage",
            "type":"Services"
        }
    ],
    "sg:phone":"+1 757 229 2007",
    "sg:postcode":"23188",
    "sg:province":"VA",
    "sg:tags":[
        "planning",
        "financial"
    ],
    "wof:name":"Roberts Fowler Company LLC",
    "wof:placetype":"venue"
},
  "geometry": {"coordinates":[-76.755505,37.314844],"type":"Point"}
}