{
  "type": "Feature",
  "properties": {
    "iso:country":"US",
    "sg:address":"456 US Hwy 23",
    "sg:city":"Weber City",
    "sg:classifiers":[
        {
            "category":"Retail",
            "subcategory":"Funeral Services",
            "type":"Services"
        }
    ],
    "sg:phone":"+1 276 386 6151",
    "sg:postcode":"24290",
    "sg:province":"VA",
    "sg:tags":[
        "director"
    ],
    "wof:name":"Colonial Funeral Home",
    "wof:placetype":"venue"
},
  "geometry": {"coordinates":[-82.553206,36.62877],"type":"Point"}
}