{
  "type": "Feature",
  "properties": {
    "addr:full":"5347 Lila Ln Virginia Beach VA 23464",
    "addr:housenumber":"5347",
    "addr:postcode":"23464",
    "addr:street":"Lila Ln",
    "iso:country":"US",
    "sg:address":"5347 Lila Ln",
    "sg:city":"Virginia Beach",
    "sg:classifiers":[
        {
            "category":"Shopping",
            "type":"Retail Goods"
        },
        {
            "category":"Shopping",
            "subcategory":"Books",
            "type":"Retail Goods"
        }
    ],
    "sg:phone":"+1 757 420 4941",
    "sg:postcode":"23464",
    "sg:province":"VA",
    "sg:tags":[
        "religious"
    ],
    "wof:name":"JMJ Catholic Books & Articles",
    "wof:placetype":"venue"
},
  "geometry": {"coordinates":[-76.177363,36.798623],"type":"Point"}
}