{
  "type": "Feature",
  "properties": {
    "addr:full":"4401 Gregory Ave Richmond VA 23234",
    "addr:housenumber":"4401",
    "addr:postcode":"23234",
    "addr:street":"Gregory Ave",
    "iso:country":"US",
    "sg:address":"4401 Gregory Ave",
    "sg:city":"Richmond",
    "sg:classifiers":[
        {
            "category":"Freight",
            "type":"Transportation"
        }
    ],
    "sg:phone":"+1 804 233 0565",
    "sg:postcode":"23234",
    "sg:province":"VA",
    "wof:name":"Gilmo Moving & Storage",
    "wof:placetype":"venue"
},
  "geometry": {"coordinates":[-77.47885599999999,37.471655],"type":"Point"}
}