{
  "type": "Feature",
  "properties": {
    "addr:full":"10080 Midlothian Tpke Richmond VA 23235",
    "addr:housenumber":"10080",
    "addr:postcode":"23235",
    "addr:street":"Midlothian Tpke",
    "iso:country":"US",
    "sg:address":"10080 Midlothian Tpke",
    "sg:city":"Richmond",
    "sg:classifiers":[
        {
            "category":"Shopping",
            "subcategory":"Computers & Home Electronics",
            "type":"Retail Goods"
        }
    ],
    "sg:phone":"+1 804 327 5060",
    "sg:postcode":"23235",
    "sg:province":"VA",
    "sg:tags":[
        "equipment",
        "dealer"
    ],
    "wof:name":"2000 Net Computer Inc",
    "wof:placetype":"venue"
},
  "geometry": {"coordinates":[-77.578682,37.505409],"type":"Point"}
}