{
  "type": "Feature",
  "properties": {
    "iso:country":"US",
    "sg:address":"8037 Tyson Oaks Cir",
    "sg:city":"Vienna",
    "sg:classifiers":[
        {
            "category":"Professional",
            "subcategory":"Computer Services",
            "type":"Services"
        }
    ],
    "sg:phone":"+1 202 607 8318",
    "sg:postcode":"22182",
    "sg:province":"VA",
    "sg:tags":[
        "solution",
        "network",
        "it"
    ],
    "wof:name":"Qubic Solution LLC",
    "wof:placetype":"venue"
},
  "geometry": {"coordinates":[-77.22220799999999,38.905492],"type":"Point"}
}