{
  "type": "Feature",
  "properties": {
    "addr:full":"119 W Main St Berryville VA 22611",
    "addr:housenumber":"119",
    "addr:postcode":"22611",
    "addr:street":"W Main St",
    "iso:country":"US",
    "sg:address":"119 W Main St",
    "sg:city":"Berryville",
    "sg:classifiers":[
        {
            "category":"Personal",
            "type":"Services"
        },
        {
            "category":"Sports & Exercise",
            "subcategory":"Gym",
            "type":"Entertainment"
        }
    ],
    "sg:phone":"+1 540 955 9500",
    "sg:postcode":"22611",
    "sg:province":"VA",
    "sg:tags":[
        "therapist",
        "fitness",
        "physical",
        "massage",
        "facility"
    ],
    "wof:name":"Healthy Beginnings Inc",
    "wof:placetype":"venue"
},
  "geometry": {"coordinates":[-77.98461399999999,39.152759],"type":"Point"}
}