{
  "type": "Feature",
  "properties": {
    "addr:full":"700 S Sycamore St Petersburg VA 23803",
    "addr:housenumber":"700",
    "addr:postcode":"23803",
    "addr:street":"S Sycamore",
    "iso:country":"US",
    "sg:address":"700 S Sycamore St",
    "sg:city":"Petersburg",
    "sg:classifiers":[
        {
            "category":"Health Services",
            "subcategory":"Doctor",
            "type":"Services"
        }
    ],
    "sg:phone":"+1 804 861 8600",
    "sg:postcode":"23803",
    "sg:province":"VA",
    "sg:tags":[
        "medical"
    ],
    "wof:name":"Ernest R Rodriguez Dr",
    "wof:placetype":"venue"
},
  "geometry": {"coordinates":[-77.39905,37.216508],"type":"Point"}
}