{
  "type": "Feature",
  "properties": {
    "addr:full":"3509 Washington Dr Falls Church VA 22041",
    "addr:housenumber":"3509",
    "addr:postcode":"22041",
    "addr:street":"Washington Dr",
    "iso:country":"US",
    "sg:address":"3509 Washington Dr",
    "sg:city":"Falls Church",
    "sg:classifiers":[
        {
            "category":"Building & Trades",
            "subcategory":"Locksmith",
            "type":"Services"
        }
    ],
    "sg:phone":"+1 571 431 1258",
    "sg:postcode":"22041",
    "sg:province":"VA",
    "sg:tags":[
        "key"
    ],
    "wof:name":"Washington Dr 24 Hour Emergency Locksmith",
    "wof:placetype":"venue"
},
  "geometry": {"coordinates":[-77.137269,38.848879],"type":"Point"}
}