{
  "type": "Feature",
  "properties": {
    "addr:full":"6608 Potomac Ave Alexandria VA 22307",
    "addr:housenumber":"6608",
    "addr:postcode":"22307",
    "addr:street":"Potomac Ave",
    "iso:country":"US",
    "sg:address":"6608 Potomac Ave",
    "sg:city":"Alexandria",
    "sg:classifiers":[
        {
            "category":"Professional",
            "type":"Services"
        }
    ],
    "sg:phone":"+1 703 721 0600",
    "sg:postcode":"22307",
    "sg:province":"VA",
    "wof:name":"Herbert Wolfe",
    "wof:placetype":"venue"
},
  "geometry": {"coordinates":[-77.057373,38.773016],"type":"Point"}
}