{
  "type": "Feature",
  "properties": {
    "addr:full":"1625 General Booth Blvd Virginia Beach VA 23454",
    "addr:housenumber":"1625",
    "addr:postcode":"23454",
    "addr:street":"General Booth Blvd",
    "iso:country":"US",
    "sg:address":"1625 General Booth Blvd",
    "sg:city":"Virginia Beach",
    "sg:classifiers":[
        {
            "category":"Banks & Credit Unions",
            "subcategory":"Bank",
            "type":"Services"
        }
    ],
    "sg:phone":"+1 757 721 1031",
    "sg:postcode":"23454",
    "sg:province":"VA",
    "wof:name":"Sun Trust Bank",
    "wof:placetype":"venue"
},
  "geometry": {"coordinates":[-75.99973799999999,36.785601],"type":"Point"}
}