{
  "type": "Feature",
  "properties": {
    "addr:full":"84 Pine Forest Rd Lexington VA 24450",
    "addr:housenumber":"84",
    "addr:postcode":"24450",
    "addr:street":"Pine Forest Rd",
    "iso:country":"US",
    "sg:address":"84 Pine Forest Rd",
    "sg:city":"Lexington",
    "sg:classifiers":[
        {
            "category":"Farming",
            "subcategory":"Livestock Farm",
            "type":"Manufacturing & Wholesale Goods"
        }
    ],
    "sg:phone":"+1 540 464 4882",
    "sg:postcode":"24450",
    "sg:province":"VA",
    "sg:tags":[
        "beef",
        "feedlot",
        "cattle"
    ],
    "wof:name":"J2 Farms",
    "wof:placetype":"venue"
},
  "geometry": {"coordinates":[-79.460261,37.747724],"type":"Point"}
}