{
  "type": "Feature",
  "properties": {
    "addr:full":"295 Canal Dr Tappahannock VA 22560",
    "addr:housenumber":"295",
    "addr:postcode":"22560",
    "addr:street":"Canal Dr",
    "iso:country":"US",
    "sg:address":"295 Canal Dr",
    "sg:city":"Tappahannock",
    "sg:classifiers":[
        {
            "category":"Personal",
            "subcategory":"Beauty Salon",
            "type":"Services"
        }
    ],
    "sg:phone":"+1 804 443 3198",
    "sg:postcode":"22560",
    "sg:province":"VA",
    "wof:name":"Arlene's Hair Magic",
    "wof:placetype":"venue"
},
  "geometry": {"coordinates":[-76.83526000000001,37.913319],"type":"Point"}
}