{
  "type": "Feature",
  "properties": {
    "addr:full":"2300 Charles St Fredericksburg VA 22401",
    "addr:housenumber":"2300",
    "addr:postcode":"22401",
    "addr:street":"Charles St",
    "iso:country":"US",
    "sg:address":"2300 Charles St",
    "sg:city":"Fredericksburg",
    "sg:classifiers":[
        {
            "category":"Health Services",
            "subcategory":"Health Practitioner",
            "type":"Services"
        }
    ],
    "sg:phone":"+1 540 368 1400",
    "sg:postcode":"22401",
    "sg:province":"VA",
    "sg:tags":[
        "therapist",
        "physical"
    ],
    "sg:website":"www.childrenshospital.org",
    "wof:name":"Childrens Hospital Of Richmond",
    "wof:placetype":"venue"
},
  "geometry": {"coordinates":[-77.470567,38.314209],"type":"Point"}
}