{
  "type": "Feature",
  "properties": {
    "iso:country":"US",
    "sg:address":"3500 W Ox Rd",
    "sg:city":"Fairfax",
    "sg:classifiers":[
        {
            "category":"Building & Trades",
            "subcategory":"Construction",
            "type":"Services"
        }
    ],
    "sg:phone":"+1 703 262 0160",
    "sg:postcode":"22033",
    "sg:province":"VA",
    "sg:tags":[
        "house"
    ],
    "wof:name":"Milestone Construction",
    "wof:placetype":"venue"
},
  "geometry": {"coordinates":[-77.377567,38.888852],"type":"Point"}
}