{
  "type": "Feature",
  "properties": {
    "iso:country":"US",
    "sg:address":"111 N Market St",
    "sg:city":"Petersburg",
    "sg:classifiers":[
        {
            "category":"Autos & Motor Vehicles",
            "subcategory":"Automobile Sales",
            "type":"Retail Goods"
        }
    ],
    "sg:phone":"+1 804 861 9106",
    "sg:postcode":"23803",
    "sg:province":"VA",
    "sg:tags":[
        "car",
        "used",
        "dealer"
    ],
    "wof:name":"Darbyshire Motors Ltd",
    "wof:placetype":"venue"
},
  "geometry": {"coordinates":[-77.40713100000001,37.229655],"type":"Point"}
}