{
  "type": "Feature",
  "properties": {
    "iso:country":"US",
    "sg:address":"5613 Mount Burnside Way",
    "sg:city":"Burke",
    "sg:classifiers":[
        {
            "category":"Banks & Credit Unions",
            "subcategory":"Financial Services",
            "type":"Services"
        }
    ],
    "sg:phone":"+1 703 323 6657",
    "sg:postcode":"22015",
    "sg:province":"VA",
    "sg:tags":[
        "investor"
    ],
    "wof:name":"Capital Youth Development LLC",
    "wof:placetype":"venue"
},
  "geometry": {"coordinates":[-77.254943,38.79759],"type":"Point"}
}