{
  "type": "Feature",
  "properties": {
    "iso:country":"US",
    "sg:address":"176 Mac St",
    "sg:city":"Virginia Beach",
    "sg:classifiers":[
        {
            "category":"Freight",
            "type":"Transportation"
        }
    ],
    "sg:phone":"+1 757 497 5901",
    "sg:postcode":"23462",
    "sg:province":"VA",
    "sg:tags":[
        "mover"
    ],
    "sg:website":"www.amagicmover.com",
    "wof:name":"A Magic Mover",
    "wof:placetype":"venue"
},
  "geometry": {"coordinates":[-76.157021,36.83789],"type":"Point"}
}