{
  "type": "Feature",
  "properties": {
    "addr:full":"1830 Town Center Dr Reston VA 20190",
    "addr:housenumber":"1830",
    "addr:postcode":"20190",
    "addr:street":"Town Center Dr",
    "iso:country":"US",
    "sg:address":"1830 Town Center Dr",
    "sg:city":"Reston",
    "sg:classifiers":[
        {
            "category":"Health Services",
            "subcategory":"Doctor",
            "type":"Services"
        }
    ],
    "sg:phone":"+1 703 709 1492",
    "sg:postcode":"20190",
    "sg:province":"VA",
    "sg:tags":[
        "medical"
    ],
    "wof:name":"Sebastian Dermatology PC",
    "wof:placetype":"venue"
},
  "geometry": {"coordinates":[-77.36541,38.962197],"type":"Point"}
}