{
  "type": "Feature",
  "properties": {
    "addr:full":"14883 Fancy Gap Hwy Cana VA 24317",
    "addr:housenumber":"14883",
    "addr:postcode":"24317",
    "addr:street":"Fancy Gap Hwy Cana",
    "iso:country":"US",
    "sg:address":"14883 Fancy Gap Hwy",
    "sg:city":"Cana",
    "sg:classifiers":[
        {
            "category":"Home & Garden",
            "subcategory":"Building Materials",
            "type":"Retail Goods"
        },
        {
            "category":"Building & Trades",
            "subcategory":"Construction",
            "type":"Services"
        }
    ],
    "sg:phone":"+1 276 755 5156",
    "sg:postcode":"24317",
    "sg:province":"VA",
    "wof:name":"Fred's Sheds",
    "wof:placetype":"venue"
},
  "geometry": {"coordinates":[-80.654191,36.574402],"type":"Point"}
}