{
  "type": "Feature",
  "properties": {
    "addr:full":"2214 Rock Hill Rd Herndon VA 20170",
    "addr:housenumber":"2214",
    "addr:postcode":"20170",
    "addr:street":"Rock Hill Rd",
    "iso:country":"US",
    "sg:address":"2214 Rock Hill Rd",
    "sg:city":"Herndon",
    "sg:classifiers":[
        {
            "category":"Professional",
            "type":"Services"
        }
    ],
    "sg:phone":"+1 703 709 6681",
    "sg:postcode":"20170",
    "sg:province":"VA",
    "sg:tags":[
        "establishment"
    ],
    "wof:name":"Innovative Technology Authorty",
    "wof:placetype":"venue"
},
  "geometry": {"coordinates":[-77.420182,38.962973],"type":"Point"}
}