{
  "type": "Feature",
  "properties": {
    "addr:full":"8700 Nanlee Dr Springfield VA 22152",
    "addr:postcode":"8700;22152",
    "addr:street":"Nanlee Dr",
    "iso:country":"US",
    "sg:address":"8700 Nanlee Dr",
    "sg:city":"Springfield",
    "sg:classifiers":[
        {
            "category":"Building & Trades",
            "subcategory":"Plumbing",
            "type":"Services"
        }
    ],
    "sg:phone":"+1 703 866 9060",
    "sg:postcode":"22152",
    "sg:province":"VA",
    "sg:tags":[
        "conditioning",
        "air",
        "system",
        "contractor"
    ],
    "wof:name":"Building Environmental Systems",
    "wof:placetype":"venue"
},
  "geometry": {"coordinates":[-77.246934,38.766763],"type":"Point"}
}