{
  "type": "Feature",
  "properties": {
    "iso:country":"US",
    "sg:address":"6328 Lankford Hwy",
    "sg:city":"Nassawadox",
    "sg:classifiers":[
        {
            "category":"Retail",
            "subcategory":"Funeral Services",
            "type":"Services"
        }
    ],
    "sg:phone":"+1 757 442 6612",
    "sg:postcode":"23415",
    "sg:province":"VA",
    "sg:tags":[
        "director"
    ],
    "wof:name":"John O Morris Funeral Home",
    "wof:placetype":"venue"
},
  "geometry": {"coordinates":[-75.539494,37.947617],"type":"Point"}
}