{
  "type": "Feature",
  "properties": {
    "iso:country":"US",
    "sg:address":"129 Indian Creek Rd",
    "sg:city":"Cedar Bluff",
    "sg:classifiers":[
        {
            "category":"Organizations",
            "subcategory":"Religious Organization",
            "type":"Services"
        }
    ],
    "sg:phone":"+1 276 964 4916",
    "sg:postcode":"24609",
    "sg:province":"VA",
    "sg:tags":[
        "church"
    ],
    "wof:name":"Cedar Bluff Presbyterian Chr",
    "wof:placetype":"venue"
},
  "geometry": {"coordinates":[-81.759551,37.087134],"type":"Point"}
}