{
  "type": "Feature",
  "properties": {
    "iso:country":"US",
    "sg:address":"12355 Sunrise Valley Dr",
    "sg:city":"Reston",
    "sg:classifiers":[
        {
            "category":"Professional",
            "subcategory":"Lawyer & Legal Services",
            "type":"Services"
        }
    ],
    "sg:phone":"+1 703 476 4270",
    "sg:postcode":"20191",
    "sg:province":"VA",
    "sg:tags":[
        "attorney"
    ],
    "wof:name":"Atticus Law",
    "wof:placetype":"venue"
},
  "geometry": {"coordinates":[-77.37209799999999,38.951152],"type":"Point"}
}