{
  "type": "Feature",
  "properties": {
    "addr:full":"6 E Nelson Ave Apt 103 Alexandria VA 22301",
    "addr:housenumber":"6;103",
    "addr:postcode":"22301",
    "addr:street":"E Nelson Ave Apt",
    "iso:country":"US",
    "sg:address":"6 E Nelson Ave Apt 103",
    "sg:city":"Alexandria",
    "sg:classifiers":[
        {
            "category":"Real Estate",
            "subcategory":"Real Estate Operator",
            "type":"Services"
        }
    ],
    "sg:phone":"+1 703 836 8500",
    "sg:postcode":"22301",
    "sg:province":"VA",
    "sg:tags":[
        "apartment"
    ],
    "sg:website":"www.manorhouseapartments.postlet...",
    "wof:name":"Manor House Apartments",
    "wof:placetype":"venue"
},
  "geometry": {"coordinates":[-77.06250199999999,38.81924],"type":"Point"}
}