{
  "type": "Feature",
  "properties": {
    "addr:full":"333 Waterside Dr Norfolk VA 23510",
    "addr:housenumber":"333",
    "addr:postcode":"23510",
    "addr:street":"Waterside Dr",
    "iso:country":"US",
    "sg:address":"333 Waterside Dr",
    "sg:city":"Norfolk",
    "sg:classifiers":[
        {
            "category":"Ice Cream",
            "type":"Food & Drink"
        }
    ],
    "sg:menulink":"http://www.allmenus.com/va/norfolk/217445-ben--jerrys/menu/",
    "sg:postcode":"23510",
    "sg:province":"VA",
    "sg:tags":[
        "american"
    ],
    "wof:name":"Ben & Jerry's",
    "wof:placetype":"venue"
},
  "geometry": {"coordinates":[-76.29204900000001,36.845071],"type":"Point"}
}