{
  "type": "Feature",
  "properties": {
    "iso:country":"US",
    "sg:address":"46030 Manekin Plz",
    "sg:city":"Sterling",
    "sg:classifiers":[
        {
            "category":"Wholesale",
            "subcategory":"Machinery & Supplies",
            "type":"Manufacturing & Wholesale Goods"
        },
        {
            "category":"Shopping",
            "type":"Retail Goods"
        }
    ],
    "sg:phone":"+1 703 433 9361",
    "sg:postcode":"20166",
    "sg:province":"VA",
    "sg:tags":[
        "enforcement",
        "forensic",
        "equipment",
        "investigation",
        "supplier",
        "law"
    ],
    "wof:name":"Foster & Freeman USA Inc",
    "wof:placetype":"venue"
},
  "geometry": {"coordinates":[-77.407076,39.023472],"type":"Point"}
}