{
  "type": "Feature",
  "properties": {
    "addr:full":"8324 Professional Hill Dr Fairfax VA 22031",
    "addr:housenumber":"8324",
    "addr:postcode":"22031",
    "addr:street":"Professional Hill Dr",
    "iso:country":"US",
    "sg:address":"8324 Professional Hill Dr",
    "sg:city":"Fairfax",
    "sg:classifiers":[
        {
            "category":"Health Services",
            "subcategory":"Doctor",
            "type":"Services"
        }
    ],
    "sg:phone":"+1 703 573 5600",
    "sg:postcode":"22031",
    "sg:province":"VA",
    "sg:tags":[
        "physician",
        "surgeon"
    ],
    "wof:name":"Jo Ann Herrman MD",
    "wof:placetype":"venue"
},
  "geometry": {"coordinates":[-77.233442,38.868131],"type":"Point"}
}