{
  "type": "Feature",
  "properties": {
    "addr:full":"5009 Andrea Ave Annandale VA 22003",
    "addr:housenumber":"5009",
    "addr:postcode":"22003",
    "addr:street":"Andrea Ave",
    "iso:country":"US",
    "sg:address":"5009 Andrea Ave",
    "sg:city":"Annandale",
    "sg:classifiers":[
        {
            "category":"Sports & Exercise",
            "subcategory":"Gym",
            "type":"Entertainment"
        }
    ],
    "sg:phone":"+1 703 978 0348",
    "sg:postcode":"22003",
    "sg:province":"VA",
    "sg:tags":[
        "fitness",
        "physical",
        "facility"
    ],
    "wof:name":"Sweatbox",
    "wof:placetype":"venue"
},
  "geometry": {"coordinates":[-77.25414600000001,38.814901],"type":"Point"}
}