{
  "type": "Feature",
  "properties": {
    "iso:country":"US",
    "sg:address":"1200 N Kensington St",
    "sg:city":"Arlington",
    "sg:classifiers":[
        {
            "category":"Real Estate",
            "subcategory":"Real Estate Services",
            "type":"Services"
        },
        {
            "category":"Banks & Credit Unions",
            "subcategory":"Financial Services",
            "type":"Services"
        }
    ],
    "sg:phone":"+1 703 534 8422",
    "sg:postcode":"22205",
    "sg:province":"VA",
    "sg:tags":[
        "loan",
        "processing"
    ],
    "wof:name":"Caribbean Mortgage",
    "wof:placetype":"venue"
},
  "geometry": {"coordinates":[-77.133759,38.882111],"type":"Point"}
}