{
  "type": "Feature",
  "properties": {
    "addr:full":"10389 Dow Gil Rd Ashland VA 23005",
    "addr:housenumber":"10389",
    "addr:postcode":"23005",
    "addr:street":"Dow Gil Rd",
    "iso:country":"US",
    "sg:address":"10389 Dow Gil Rd",
    "sg:city":"Ashland",
    "sg:classifiers":[
        {
            "category":"Retail",
            "subcategory":"Auto Repair",
            "type":"Services"
        }
    ],
    "sg:phone":"+1 804 752 7669",
    "sg:postcode":"23005",
    "sg:province":"VA",
    "sg:tags":[
        "repairing",
        "automotive",
        "general",
        "automobile"
    ],
    "wof:name":"Hanover Honda Sports Inc",
    "wof:placetype":"venue"
},
  "geometry": {"coordinates":[-77.46955800000001,37.741309],"type":"Point"}
}