{
  "type": "Feature",
  "properties": {
    "addr:full":"1000 N Main St Blacksburg VA 24060",
    "addr:housenumber":"1000",
    "addr:postcode":"24060",
    "addr:street":"N Main St",
    "iso:country":"US",
    "sg:address":"1000 N Main St",
    "sg:city":"Blacksburg",
    "sg:classifiers":[
        {
            "category":"Food & Beverages",
            "subcategory":"Groceries & Convenience Stores",
            "type":"Retail Goods"
        }
    ],
    "sg:phone":"+1 540 552 1941",
    "sg:postcode":"24060",
    "sg:province":"VA",
    "wof:name":"Deli Mart 61",
    "wof:placetype":"venue"
},
  "geometry": {"coordinates":[-80.41972199999999,37.239502],"type":"Point"}
}