{
  "type": "Feature",
  "properties": {
    "iso:country":"US",
    "sg:address":"8425 Hunt Valley Dr",
    "sg:city":"Vienna",
    "sg:classifiers":[
        {
            "category":"Professional",
            "subcategory":"Computer Services",
            "type":"Services"
        }
    ],
    "sg:phone":"+1 703 734 8215",
    "sg:postcode":"22182",
    "sg:province":"VA",
    "sg:tags":[
        "related"
    ],
    "wof:name":"Natasha Enterprise",
    "wof:placetype":"venue"
},
  "geometry": {"coordinates":[-77.23601600000001,38.907855],"type":"Point"}
}