{
  "type": "Feature",
  "properties": {
    "addr:full":"22530 Aven Ln Abingdon VA 24211",
    "addr:postcode":"22530;24211",
    "addr:street":"Aven Ln",
    "iso:country":"US",
    "sg:address":"22530 Aven Ln",
    "sg:city":"Abingdon",
    "sg:classifiers":[
        {
            "category":"Manufacturing",
            "subcategory":"Building Materials",
            "type":"Manufacturing & Wholesale Goods"
        },
        {
            "category":"Building & Trades",
            "subcategory":"Construction",
            "type":"Services"
        }
    ],
    "sg:phone":"+1 276 676 3770",
    "sg:postcode":"24211",
    "sg:province":"VA",
    "sg:tags":[
        "mfg",
        "wood",
        "cabinet",
        "kitchen",
        "woodworker"
    ],
    "wof:name":"J & W Creations",
    "wof:placetype":"venue"
},
  "geometry": {"coordinates":[-81.97022699999999,36.628942],"type":"Point"}
}