{
  "type": "Feature",
  "properties": {
    "addr:full":"2028 Coral Ivy Ln Chesapeake VA 23323",
    "addr:housenumber":"2028",
    "addr:postcode":"23323",
    "addr:street":"Coral Ivy Ln",
    "iso:country":"US",
    "sg:address":"2028 Coral Ivy Ln",
    "sg:city":"Chesapeake",
    "sg:classifiers":[
        {
            "category":"Shopping",
            "subcategory":"Catalog Store",
            "type":"Retail Goods"
        }
    ],
    "sg:phone":"+1 757 558 4820",
    "sg:postcode":"23323",
    "sg:province":"VA",
    "sg:tags":[
        "mail",
        "house"
    ],
    "wof:name":"Chad William Toussant",
    "wof:placetype":"venue"
},
  "geometry": {"coordinates":[-76.318521,36.725108],"type":"Point"}
}