{
  "type": "Feature",
  "properties": {
    "addr:full":"7064 Tech Cir Manassas VA 20109",
    "addr:housenumber":"7064",
    "addr:postcode":"20109",
    "addr:street":"Tech Cir",
    "iso:country":"US",
    "sg:address":"7064 Tech Cir",
    "sg:city":"Manassas",
    "sg:classifiers":[
        {
            "category":"Manufacturing",
            "subcategory":"Metals",
            "type":"Manufacturing & Wholesale Goods"
        },
        {
            "category":"Building & Trades",
            "subcategory":"Plumbing",
            "type":"Services"
        }
    ],
    "sg:phone":"+1 703 330 4718",
    "sg:postcode":"20109",
    "sg:province":"VA",
    "sg:tags":[
        "contractor",
        "work",
        "sheet",
        "metalwork",
        "mfg"
    ],
    "wof:name":"A & C Sheeetmetal Fabrication",
    "wof:placetype":"venue"
},
  "geometry": {"coordinates":[-77.49894500000001,38.804306],"type":"Point"}
}