{
  "type": "Feature",
  "properties": {
    "addr:full":"4 Insley Cir Poquoson VA 23662",
    "addr:housenumber":"4",
    "addr:postcode":"23662",
    "addr:street":"Insley Cir",
    "iso:country":"US",
    "sg:address":"4 Insley Cir",
    "sg:city":"Poquoson",
    "sg:classifiers":[
        {
            "category":"Shopping",
            "subcategory":"Stationery & Office Supplies",
            "type":"Retail Goods"
        }
    ],
    "sg:phone":"+1 757 868 3898",
    "sg:postcode":"23662",
    "sg:province":"VA",
    "wof:name":"Bohn School Christina Sup",
    "wof:placetype":"venue"
},
  "geometry": {"coordinates":[-76.401872,37.140652],"type":"Point"}
}