{
  "type": "Feature",
  "properties": {
    "iso:country":"US",
    "sg:address":"693 Pigeon Path",
    "sg:city":"Ebony",
    "sg:classifiers":[
        {
            "category":"Professional",
            "type":"Services"
        }
    ],
    "sg:phone":"+1 434 636 2066",
    "sg:postcode":"23845",
    "sg:province":"VA",
    "wof:name":"Harrell Hay & Angie",
    "wof:placetype":"venue"
},
  "geometry": {"coordinates":[-77.98460300000001,36.545804],"type":"Point"}
}