{
  "type": "Feature",
  "properties": {
    "iso:country":"US",
    "sg:address":"1302 Lafayette Dr",
    "sg:city":"Alexandria",
    "sg:classifiers":[
        {
            "category":"Health Services",
            "subcategory":"Doctor",
            "type":"Services"
        }
    ],
    "sg:phone":"+1 703 765 6400",
    "sg:postcode":"22308",
    "sg:province":"VA",
    "sg:tags":[
        "medical"
    ],
    "wof:name":"John Schehl MD",
    "wof:placetype":"venue"
},
  "geometry": {"coordinates":[-77.05573,38.740397],"type":"Point"}
}