{
  "type": "Feature",
  "properties": {
    "addr:full":"109 Charwood Dr Abingdon VA 24210",
    "addr:housenumber":"109",
    "addr:postcode":"24210",
    "addr:street":"Charwood Dr",
    "iso:country":"US",
    "sg:address":"109 Charwood Dr",
    "sg:city":"Abingdon",
    "sg:classifiers":[
        {
            "category":"Health Services",
            "subcategory":"Health Practitioner",
            "type":"Services"
        }
    ],
    "sg:phone":"+1 276 494 1101",
    "sg:postcode":"24210",
    "sg:province":"VA",
    "sg:tags":[
        "psychologist"
    ],
    "wof:name":"SWVA Pyschological Svc Inc",
    "wof:placetype":"venue"
},
  "geometry": {"coordinates":[-82.005371,36.702367],"type":"Point"}
}