{
  "type": "Feature",
  "properties": {
    "iso:country":"US",
    "sg:address":"236 Phlegar Hill Rd NE",
    "sg:city":"Floyd",
    "sg:classifiers":[
        {
            "category":"Building & Trades",
            "subcategory":"Plumbing",
            "type":"Services"
        }
    ],
    "sg:phone":"+1 540 745 3997",
    "sg:postcode":"24091",
    "sg:province":"VA",
    "sg:tags":[
        "contractor"
    ],
    "wof:name":"Morgan McGraw Inc",
    "wof:placetype":"venue"
},
  "geometry": {"coordinates":[-80.29479600000001,36.929112],"type":"Point"}
}