{
  "type": "Feature",
  "properties": {
    "addr:full":"133 Tilden Ave Chesapeake VA 23320",
    "addr:housenumber":"133",
    "addr:postcode":"23320",
    "addr:street":"Tilden Ave",
    "iso:country":"US",
    "sg:address":"133 Tilden Ave",
    "sg:city":"Chesapeake",
    "sg:classifiers":[
        {
            "category":"Building & Trades",
            "subcategory":"Pest Control",
            "type":"Services"
        }
    ],
    "sg:phone":"+1 757 547 0151",
    "sg:postcode":"23320",
    "sg:province":"VA",
    "wof:name":"Eastern Exterminating Company",
    "wof:placetype":"venue"
},
  "geometry": {"coordinates":[-76.243949,36.725409],"type":"Point"}
}