{
  "type": "Feature",
  "properties": {
    "addr:full":"4445 Brookfield Corporate Dr Chantilly VA 20151",
    "addr:housenumber":"4445",
    "addr:postcode":"20151",
    "addr:street":"Brookfield Corporate Dr",
    "iso:country":"US",
    "sg:address":"4445 Brookfield Corporate Dr",
    "sg:city":"Chantilly",
    "sg:classifiers":[
        {
            "category":"Autos & Motor Vehicles",
            "subcategory":"Auto Supplies",
            "type":"Retail Goods"
        }
    ],
    "sg:phone":"+1 703 222 8400",
    "sg:postcode":"20151",
    "sg:province":"VA",
    "sg:tags":[
        "wholesale",
        "parts"
    ],
    "wof:name":"J K All Pro Auto Parts",
    "wof:placetype":"venue"
},
  "geometry": {"coordinates":[-77.438676,38.886314],"type":"Point"}
}