{
  "type": "Feature",
  "properties": {
    "addr:full":"1163 Spruce St Martinsville VA 24112",
    "addr:housenumber":"1163",
    "addr:postcode":"24112",
    "addr:street":"Spruce St",
    "iso:country":"US",
    "sg:address":"1163 Spruce St",
    "sg:city":"Martinsville",
    "sg:classifiers":[
        {
            "category":"Farming",
            "subcategory":"Nursery",
            "type":"Manufacturing & Wholesale Goods"
        }
    ],
    "sg:phone":"+1 276 666 2242",
    "sg:postcode":"24112",
    "sg:province":"VA",
    "sg:tags":[
        "ornamental"
    ],
    "wof:name":"Field Of Dreams",
    "wof:placetype":"venue"
},
  "geometry": {"coordinates":[-79.85169399999999,36.678792],"type":"Point"}
}