{
  "type": "Feature",
  "properties": {
    "iso:country":"US",
    "sg:address":"168 N Loudoun St",
    "sg:city":"Winchester",
    "sg:classifiers":[
        {
            "category":"Restaurant",
            "type":"Food & Drink"
        }
    ],
    "sg:phone":"+1 540 535 0111",
    "sg:postcode":"22601",
    "sg:province":"VA",
    "sg:tags":[
        "eating"
    ],
    "wof:name":"Brewbakers Restaurant Inc",
    "wof:placetype":"venue"
},
  "geometry": {"coordinates":[-78.165042,39.185298],"type":"Point"}
}