{
  "type": "Feature",
  "properties": {
    "addr:full":"1574 Cameron Crescent Dr. #21 Reston VA 20190",
    "addr:housenumber":"1574",
    "addr:postcode":"20190",
    "addr:street":"Cameron Crescent Dr. # 21",
    "iso:country":"US",
    "sg:address":"1574 Cameron Crescent Dr. #21",
    "sg:city":"Reston",
    "sg:classifiers":[
        {
            "category":"Building & Trades",
            "subcategory":"Landscaping Services",
            "type":"Services"
        },
        {
            "category":"Home & Garden",
            "subcategory":"Garden Supply",
            "type":"Retail Goods"
        }
    ],
    "sg:phone":"+1 301 455 7066",
    "sg:postcode":"20190",
    "sg:province":"VA",
    "sg:tags":[
        "control",
        "lawn",
        "designer",
        "consultant",
        "mulch",
        "weed",
        "maintenance",
        "landscape"
    ],
    "sg:website":"http://www.ludyjuarez.com",
    "wof:name":"Ludy's Landscaping",
    "wof:placetype":"venue"
},
  "geometry": {"coordinates":[-77.339209,38.970506],"type":"Point"}
}