{
  "type": "Feature",
  "properties": {
    "addr:full":"160 Pleasant View Ln Charlottesville VA 22920",
    "addr:housenumber":"160",
    "addr:postcode":"22920",
    "addr:street":"Pleasant View Ln",
    "iso:country":"US",
    "sg:address":"160 Pleasant View Ln",
    "sg:city":"Charlottesville",
    "sg:classifiers":[
        {
            "category":"Banks & Credit Unions",
            "subcategory":"Investment Brokerage",
            "type":"Services"
        }
    ],
    "sg:phone":"+1 434 984 3600",
    "sg:postcode":"22920",
    "sg:province":"VA",
    "sg:tags":[
        "consultant",
        "planning",
        "financial"
    ],
    "wof:name":"First Command Financial Plan",
    "wof:placetype":"venue"
},
  "geometry": {"coordinates":[-78.844123,37.993217],"type":"Point"}
}