{
  "type": "Feature",
  "properties": {
    "iso:country":"US",
    "sg:address":"7200 W Broad St",
    "sg:city":"Richmond",
    "sg:classifiers":[
        {
            "category":"Travel",
            "subcategory":"Hotels & Motels",
            "type":"Entertainment"
        }
    ],
    "sg:phone":"+1 804 672 8128",
    "sg:postcode":"23294",
    "sg:province":"VA",
    "sg:tags":[
        "operation"
    ],
    "wof:name":"Super 8 Motel",
    "wof:placetype":"venue"
},
  "geometry": {"coordinates":[-77.520425,37.612593],"type":"Point"}
}