{
  "type": "Feature",
  "properties": {
    "iso:country":"US",
    "sg:address":"32118 S Main St",
    "sg:city":"Boykins",
    "sg:classifiers":[
        {
            "category":"Shopping",
            "subcategory":"Discount & Variety Stores",
            "type":"Retail Goods"
        }
    ],
    "sg:phone":"+1 757 654 6550",
    "sg:postcode":"23827",
    "sg:province":"VA",
    "wof:name":"Saj Main St Emporium Corp",
    "wof:placetype":"venue"
},
  "geometry": {"coordinates":[-77.200361,36.583842],"type":"Point"}
}