{
  "type": "Feature",
  "properties": {
    "iso:country":"US",
    "sg:address":"1804 Hidden Valley Dr",
    "sg:city":"Virginia Beach",
    "sg:classifiers":[
        {
            "category":"Building & Trades",
            "subcategory":"Construction",
            "type":"Services"
        }
    ],
    "sg:phone":"+1 757 479 2489",
    "sg:postcode":"23464",
    "sg:province":"VA",
    "sg:tags":[
        "contractor"
    ],
    "wof:name":"Mark Boyington",
    "wof:placetype":"venue"
},
  "geometry": {"coordinates":[-76.18810000000001,36.778988],"type":"Point"}
}