{
  "type": "Feature",
  "properties": {
    "iso:country":"US",
    "sg:address":"12585 Hunt Rd",
    "sg:city":"Culpeper",
    "sg:classifiers":[
        {
            "category":"Manufacturing",
            "subcategory":"Printing",
            "type":"Manufacturing & Wholesale Goods"
        }
    ],
    "sg:phone":"+1 540 825 0503",
    "sg:postcode":"22701",
    "sg:province":"VA",
    "sg:tags":[
        "publisher"
    ],
    "wof:name":"Glass Onion Productions",
    "wof:placetype":"venue"
},
  "geometry": {"coordinates":[-78.081699,38.527699],"type":"Point"}
}