{
  "type": "Feature",
  "properties": {
    "addr:full":"5253 Providence Rd Virginia Beach VA 23464",
    "addr:housenumber":"5253",
    "addr:postcode":"23464",
    "addr:street":"Providence Rd",
    "iso:country":"US",
    "sg:address":"5253 Providence Rd",
    "sg:city":"Virginia Beach",
    "sg:classifiers":[
        {
            "category":"Shopping",
            "subcategory":"Shoes",
            "type":"Retail Goods"
        }
    ],
    "sg:phone":"+1 757 474 4220",
    "sg:postcode":"23464",
    "sg:province":"VA",
    "wof:name":"Footworks",
    "wof:placetype":"venue"
},
  "geometry": {"coordinates":[-76.169246,36.813911],"type":"Point"}
}