{
  "type": "Feature",
  "properties": {
    "iso:country":"US",
    "sg:address":"1453 Beulah Rd NE",
    "sg:city":"Vienna",
    "sg:classifiers":[
        {
            "category":"Health Services",
            "subcategory":"Doctor",
            "type":"Services"
        }
    ],
    "sg:phone":"+1 703 759 4518",
    "sg:postcode":"22182",
    "sg:province":"VA",
    "wof:name":"Bsei",
    "wof:placetype":"venue"
},
  "geometry": {"coordinates":[-77.284251,38.949251],"type":"Point"}
}