{
  "type": "Feature",
  "properties": {
    "addr:full":"10811 Bluebell Dr Glen Allen VA 23060",
    "addr:housenumber":"10811",
    "addr:postcode":"23060",
    "addr:street":"Bluebell Dr",
    "iso:country":"US",
    "sg:address":"10811 Bluebell Dr",
    "sg:city":"Glen Allen",
    "sg:classifiers":[
        {
            "category":"Utilities",
            "subcategory":"Telephone",
            "type":"Services"
        }
    ],
    "sg:phone":"+1 804 262 1960",
    "sg:postcode":"23060",
    "sg:province":"VA",
    "sg:tags":[
        "communications",
        "radiotelephone",
        "communication"
    ],
    "wof:name":"Lets Talk Communication",
    "wof:placetype":"venue"
},
  "geometry": {"coordinates":[-77.49284900000001,37.667128],"type":"Point"}
}