{
  "type": "Feature",
  "properties": {
    "addr:full":"8501 Jenner Ct Springfield VA 22153",
    "addr:housenumber":"8501",
    "addr:postcode":"22153",
    "addr:street":"Jenner Ct",
    "iso:country":"US",
    "sg:address":"8501 Jenner Ct",
    "sg:city":"Springfield",
    "sg:classifiers":[
        {
            "category":"Education",
            "subcategory":"Special Training",
            "type":"Public Place"
        }
    ],
    "sg:phone":"+1 703 440 1270",
    "sg:postcode":"22153",
    "sg:province":"VA",
    "sg:tags":[
        "arts"
    ],
    "wof:name":"Jemma Gyulamirian",
    "wof:placetype":"venue"
},
  "geometry": {"coordinates":[-77.213341,38.726212],"type":"Point"}
}