{
  "type": "Feature",
  "properties": {
    "addr:full":"7700 Leesburg Pike Falls Church VA 22043",
    "addr:housenumber":"7700",
    "addr:postcode":"22043",
    "addr:street":"Leesburg Pike",
    "iso:country":"US",
    "sg:address":"7700 Leesburg Pike",
    "sg:city":"Falls Church",
    "sg:classifiers":[
        {
            "category":"Banks & Credit Unions",
            "subcategory":"Bank",
            "type":"Services"
        }
    ],
    "sg:phone":"+1 703 356 4668",
    "sg:postcode":"22043",
    "sg:province":"VA",
    "sg:tags":[
        "loan",
        "real estate"
    ],
    "wof:name":"Central Fidelity Mortgage Co",
    "wof:placetype":"venue"
},
  "geometry": {"coordinates":[-77.211935,38.9077],"type":"Point"}
}