{
  "type": "Feature",
  "properties": {
    "addr:full":"3000 Wards Rd Lynchburg VA 24502",
    "addr:housenumber":"3000",
    "addr:postcode":"24502",
    "addr:street":"Wards Rd",
    "iso:country":"US",
    "sg:address":"3000 Wards Rd",
    "sg:city":"Lynchburg",
    "sg:classifiers":[
        {
            "category":"Autos & Motor Vehicles",
            "subcategory":"Automobile Sales",
            "type":"Retail Goods"
        }
    ],
    "sg:phone":"+1 434 528 3202",
    "sg:postcode":"24502",
    "sg:province":"VA",
    "sg:tags":[
        "car",
        "dealer"
    ],
    "wof:name":"Oak Ridge Toyota Inc",
    "wof:placetype":"venue"
},
  "geometry": {"coordinates":[-79.18071999999999,37.359037],"type":"Point"}
}