{
  "type": "Feature",
  "properties": {
    "addr:full":"11710 Jefferson Ave Newport News VA 23606",
    "addr:housenumber":"11710",
    "addr:postcode":"23606",
    "addr:street":"Jefferson Ave",
    "iso:country":"US",
    "sg:address":"11710 Jefferson Ave",
    "sg:city":"Newport News",
    "sg:classifiers":[
        {
            "category":"Restaurant",
            "type":"Food & Drink"
        }
    ],
    "sg:menulink":"http://www.allmenus.com/va/newport-news/42292-super-china/menu/",
    "sg:phone":"+1 757 591 8111",
    "sg:postcode":"23606",
    "sg:province":"VA",
    "sg:tags":[
        "asian",
        "chinese"
    ],
    "wof:name":"Super China",
    "wof:placetype":"venue"
},
  "geometry": {"coordinates":[-76.47709,37.077822],"type":"Point"}
}