{
  "type": "Feature",
  "properties": {
    "addr:full":"8622 Lee Hwy Falls Church VA 22041",
    "addr:housenumber":"8622",
    "addr:postcode":"22041",
    "addr:street":"Lee Hwy",
    "iso:country":"US",
    "sg:address":"8622 Lee Hwy",
    "sg:city":"Falls Church",
    "sg:classifiers":[
        {
            "category":"Personal",
            "subcategory":"Day Spa",
            "type":"Services"
        }
    ],
    "sg:phone":"+1 703 204 0230",
    "sg:postcode":"22041",
    "sg:province":"VA",
    "wof:name":"Lee Highway Spa",
    "wof:placetype":"venue"
},
  "geometry": {"coordinates":[-77.131699,38.844601],"type":"Point"}
}