{
  "type": "Feature",
  "properties": {
    "iso:country":"US",
    "sg:address":"910 Fleeton Rd",
    "sg:city":"Reedville",
    "sg:classifiers":[
        {
            "category":"Food & Beverages",
            "subcategory":"Groceries & Convenience Stores",
            "type":"Retail Goods"
        }
    ],
    "sg:phone":"+1 804 453 4580",
    "sg:postcode":"22539",
    "sg:province":"VA",
    "sg:tags":[
        "grocer"
    ],
    "wof:name":"S F Barnes",
    "wof:placetype":"venue"
},
  "geometry": {"coordinates":[-76.26298300000001,37.839533],"type":"Point"}
}