{
  "type": "Feature",
  "properties": {
    "addr:full":"16331 Rocketts Mill Rd Doswell VA 23047",
    "addr:housenumber":"16331",
    "addr:postcode":"23047",
    "addr:street":"Rocketts Mill Rd",
    "iso:country":"US",
    "sg:address":"16331 Rocketts Mill Rd",
    "sg:city":"Doswell",
    "sg:classifiers":[
        {
            "category":"Retail",
            "subcategory":"Repair Shop",
            "type":"Services"
        }
    ],
    "sg:phone":"+1 804 227 3818",
    "sg:postcode":"23047",
    "sg:province":"VA",
    "sg:tags":[
        "equipment",
        "cleaning",
        "supply"
    ],
    "wof:name":"Cannon's Services Inc",
    "wof:placetype":"venue"
},
  "geometry": {"coordinates":[-77.53294,37.851003],"type":"Point"}
}