{
  "type": "Feature",
  "properties": {
    "addr:full":"7620 Erie St Annandale VA 22003",
    "addr:housenumber":"7620",
    "addr:postcode":"22003",
    "addr:street":"Erie St",
    "iso:country":"US",
    "sg:address":"7620 Erie St",
    "sg:city":"Annandale",
    "sg:classifiers":[
        {
            "category":"Manufacturing",
            "subcategory":"Printing",
            "type":"Manufacturing & Wholesale Goods"
        }
    ],
    "sg:phone":"+1 703 256 1614",
    "sg:postcode":"22003",
    "sg:province":"VA",
    "sg:tags":[
        "publishing"
    ],
    "wof:name":"Sunday Driver Publishing Co",
    "wof:placetype":"venue"
},
  "geometry": {"coordinates":[-77.20859400000001,38.819754],"type":"Point"}
}