{
  "type": "Feature",
  "properties": {
    "iso:country":"US",
    "sg:address":"1828 S Military Hwy",
    "sg:city":"Chesapeake",
    "sg:classifiers":[
        {
            "category":"Autos & Motor Vehicles",
            "subcategory":"Recreational Vehicle Sales",
            "type":"Retail Goods"
        }
    ],
    "sg:phone":"+1 757 361 6681",
    "sg:postcode":"23320",
    "sg:province":"VA",
    "sg:tags":[
        "camper",
        "pick"
    ],
    "wof:name":"Debbie's RC World Inc",
    "wof:placetype":"venue"
},
  "geometry": {"coordinates":[-76.250835,36.787504],"type":"Point"}
}