{
  "type": "Feature",
  "properties": {
    "iso:country":"US",
    "sg:address":"22900 Shaw Rd",
    "sg:city":"Sterling",
    "sg:classifiers":[
        {
            "category":"Professional",
            "subcategory":"Management & Consulting",
            "type":"Services"
        }
    ],
    "sg:phone":"+1 703 471 0155",
    "sg:postcode":"20166",
    "sg:province":"VA",
    "sg:tags":[
        "consultant",
        "business"
    ],
    "wof:name":"Mantech International Corp",
    "wof:placetype":"venue"
},
  "geometry": {"coordinates":[-77.42393199999999,38.979959],"type":"Point"}
}