{
  "type": "Feature",
  "properties": {
    "iso:country":"US",
    "sg:address":"1229 Neals Corner Rd",
    "sg:city":"Clover",
    "sg:phone":"+1 434 454 7664",
    "sg:postcode":"24534",
    "sg:province":"VA",
    "sg:tags":[
        "farm",
        "corn",
        "tobacco"
    ],
    "wof:name":"James Brown",
    "wof:placetype":"venue"
},
  "geometry": {"coordinates":[-78.789025,36.899046],"type":"Point"}
}