{
  "type": "Feature",
  "properties": {
    "addr:full":"4925 Boonsboro Rd Lynchburg VA 24503",
    "addr:housenumber":"4925",
    "addr:postcode":"24503",
    "addr:street":"Boonsboro Rd",
    "iso:country":"US",
    "sg:address":"4925 Boonsboro Rd",
    "sg:city":"Lynchburg",
    "sg:classifiers":[
        {
            "category":"Shopping",
            "subcategory":"Clothing, Apparel, & Fashions",
            "type":"Retail Goods"
        }
    ],
    "sg:phone":"+1 434 386 9100",
    "sg:postcode":"24503",
    "sg:province":"VA",
    "wof:name":"Chicos Fas Inc",
    "wof:placetype":"venue"
},
  "geometry": {"coordinates":[-79.217207,37.447196],"type":"Point"}
}