{
  "type": "Feature",
  "properties": {
    "addr:full":"228 Preston St SW Abingdon VA 24210",
    "addr:housenumber":"228",
    "addr:postcode":"24210",
    "addr:street":"Preston St Sw",
    "iso:country":"US",
    "sg:address":"228 Preston St SW",
    "sg:city":"Abingdon",
    "sg:classifiers":[
        {
            "category":"Professional",
            "type":"Services"
        }
    ],
    "sg:phone":"+1 276 628 2335",
    "sg:postcode":"24210",
    "sg:province":"VA",
    "sg:tags":[
        "establishment"
    ],
    "wof:name":"Good Tymes Enterprises",
    "wof:placetype":"venue"
},
  "geometry": {"coordinates":[-81.985254,36.705361],"type":"Point"}
}