{
  "type": "Feature",
  "properties": {
    "addr:full":"6906 Vancouver Rd Springfield VA 22152",
    "addr:housenumber":"6906",
    "addr:postcode":"22152",
    "addr:street":"Vancouver Rd",
    "iso:country":"US",
    "sg:address":"6906 Vancouver Rd",
    "sg:city":"Springfield",
    "sg:classifiers":[
        {
            "category":"Building & Trades",
            "subcategory":"Construction",
            "type":"Services"
        }
    ],
    "sg:phone":"+1 703 912 6690",
    "sg:postcode":"22152",
    "sg:province":"VA",
    "sg:tags":[
        "contractor"
    ],
    "wof:name":"Dominion Dev & Cons LLC",
    "wof:placetype":"venue"
},
  "geometry": {"coordinates":[-77.22888399999999,38.765737],"type":"Point"}
}