{
  "type": "Feature",
  "properties": {
    "iso:country":"US",
    "sg:address":"13226 Moss Ranch Ln",
    "sg:city":"Fairfax",
    "sg:classifiers":[
        {
            "category":"Shopping",
            "subcategory":"Books",
            "type":"Retail Goods"
        }
    ],
    "sg:phone":"+1 703 817 1185",
    "sg:postcode":"22033",
    "sg:province":"VA",
    "wof:name":"Usborne Books At Home",
    "wof:placetype":"venue"
},
  "geometry": {"coordinates":[-77.40252,38.86915],"type":"Point"}
}