{
  "type": "Feature",
  "properties": {
    "addr:full":"1200 W Jackson St Covington VA 24426",
    "addr:housenumber":"1200",
    "addr:postcode":"24426",
    "addr:street":"W Jackson St",
    "iso:country":"US",
    "sg:address":"1200 W Jackson St",
    "sg:city":"Covington",
    "sg:classifiers":[
        {
            "category":"Building & Trades",
            "subcategory":"Construction",
            "type":"Services"
        }
    ],
    "sg:phone":"+1 540 962 4116",
    "sg:postcode":"24426",
    "sg:province":"VA",
    "sg:tags":[
        "general",
        "contractor"
    ],
    "wof:name":"Red's Construction Co",
    "wof:placetype":"venue"
},
  "geometry": {"coordinates":[-80.000575,37.763972],"type":"Point"}
}