{
  "type": "Feature",
  "properties": {
    "iso:country":"US",
    "sg:address":"810 Forrest Dr",
    "sg:city":"Newport News",
    "sg:classifiers":[
        {
            "category":"Building & Trades",
            "subcategory":"Pest Control",
            "type":"Services"
        }
    ],
    "sg:phone":"+1 757 599 0889",
    "sg:postcode":"23606",
    "sg:province":"VA",
    "sg:tags":[
        "carpentry",
        "contractor"
    ],
    "sg:website":"www.colonialext.com",
    "wof:name":"Colonial Exterminating Co Inc",
    "wof:placetype":"venue"
},
  "geometry": {"coordinates":[-76.470094,37.076902],"type":"Point"}
}