{
  "type": "Feature",
  "properties": {
    "addr:full":"5005 Grandin Rd Exd Roanoke VA 24018",
    "addr:housenumber":"5005",
    "addr:postcode":"24018",
    "addr:street":"Grandin Rd Exd",
    "iso:country":"US",
    "sg:address":"5005 Grandin Rd Exd",
    "sg:city":"Roanoke",
    "sg:classifiers":[
        {
            "category":"Education",
            "subcategory":"School",
            "type":"Public Place"
        }
    ],
    "sg:phone":"+1 540 772 7580",
    "sg:postcode":"24018",
    "sg:province":"VA",
    "wof:name":"Oak Grove Elementary School",
    "wof:placetype":"venue"
},
  "geometry": {"coordinates":[-80.03248499999999,37.246718],"type":"Point"}
}