{
  "type": "Feature",
  "properties": {
    "iso:country":"US",
    "sg:address":"521 E Little Creek Rd",
    "sg:city":"Norfolk",
    "sg:classifiers":[
        {
            "category":"Food & Beverages",
            "subcategory":"Groceries & Convenience Stores",
            "type":"Retail Goods"
        }
    ],
    "sg:phone":"+1 757 480 5995",
    "sg:postcode":"23505",
    "sg:province":"VA",
    "sg:tags":[
        "market"
    ],
    "wof:name":"Nations Market",
    "wof:placetype":"venue"
},
  "geometry": {"coordinates":[-76.257441,36.917045],"type":"Point"}
}