{
  "type": "Feature",
  "properties": {
    "iso:country":"US",
    "sg:address":"18506 Jefferson Davis Hwy",
    "sg:city":"Triangle",
    "sg:classifiers":[
        {
            "category":"Autos & Motor Vehicles",
            "subcategory":"Automobile Sales",
            "type":"Retail Goods"
        }
    ],
    "sg:phone":"+1 703 221 5800",
    "sg:postcode":"22172",
    "sg:province":"VA",
    "sg:tags":[
        "used"
    ],
    "wof:name":"Auto King",
    "wof:placetype":"venue"
},
  "geometry": {"coordinates":[-77.334474,38.549814],"type":"Point"}
}