{
  "type": "Feature",
  "properties": {
    "iso:country":"US",
    "sg:address":"516 S Washington Hwy",
    "sg:city":"Ashland",
    "sg:classifiers":[
        {
            "category":"Autos & Motor Vehicles",
            "subcategory":"Automobile Sales",
            "type":"Retail Goods"
        },
        {
            "category":"Autos & Motor Vehicles",
            "subcategory":"Auto Supplies",
            "type":"Retail Goods"
        },
        {
            "category":"Retail",
            "subcategory":"Auto Repair",
            "type":"Services"
        }
    ],
    "sg:phone":"+1 804 798 9261",
    "sg:postcode":"23005",
    "sg:province":"VA",
    "sg:tags":[
        "car",
        "part",
        "used",
        "truck",
        "new"
    ],
    "sg:website":"http://www.luckchevrolet.com",
    "wof:name":"Luck Chevrolet",
    "wof:placetype":"venue"
},
  "geometry": {"coordinates":[-77.471329,37.746696],"type":"Point"}
}