{
  "type": "Feature",
  "properties": {
    "addr:full":"42134 John Mosby Hwy Aldie VA 20105",
    "addr:housenumber":"42134",
    "addr:postcode":"20105",
    "addr:street":"John Mosby Hwy",
    "iso:country":"US",
    "sg:address":"42134 John Mosby Hwy",
    "sg:city":"Aldie",
    "sg:classifiers":[
        {
            "category":"Manufacturing",
            "subcategory":"Apparel",
            "type":"Manufacturing & Wholesale Goods"
        }
    ],
    "sg:phone":"+1 703 327 3500",
    "sg:postcode":"20105",
    "sg:province":"VA",
    "sg:tags":[
        "flag",
        "banner"
    ],
    "sg:website":"www.signswestinc.com",
    "wof:name":"Signs West Inc",
    "wof:placetype":"venue"
},
  "geometry": {"coordinates":[-77.570346,38.949504],"type":"Point"}
}