{
  "type": "Feature",
  "properties": {
    "addr:full":"706 Church St Lynchburg VA 24504",
    "addr:housenumber":"706",
    "addr:postcode":"24504",
    "addr:street":"Church St",
    "iso:country":"US",
    "sg:address":"706 Church St",
    "sg:city":"Lynchburg",
    "sg:classifiers":[
        {
            "category":"Recreation",
            "type":"Entertainment"
        }
    ],
    "sg:phone":"+1 434 846 8100",
    "sg:postcode":"24504",
    "sg:province":"VA",
    "sg:tags":[
        "ticket"
    ],
    "wof:name":"Ticketmaster",
    "wof:placetype":"venue"
},
  "geometry": {"coordinates":[-79.14391000000001,37.415281],"type":"Point"}
}