{
  "type": "Feature",
  "properties": {
    "addr:full":"525 Rorer Ave SW Roanoke VA 24016",
    "addr:housenumber":"525",
    "addr:postcode":"24016",
    "addr:street":"Rorer Ave Sw",
    "iso:country":"US",
    "sg:address":"525 Rorer Ave SW",
    "sg:city":"Roanoke",
    "sg:classifiers":[
        {
            "category":"Building & Trades",
            "subcategory":"Construction",
            "type":"Services"
        }
    ],
    "sg:phone":"+1 540 342 6071",
    "sg:postcode":"24016",
    "sg:province":"VA",
    "sg:tags":[
        "house"
    ],
    "wof:name":"Valley Construction Services",
    "wof:placetype":"venue"
},
  "geometry": {"coordinates":[-79.951702,37.272008],"type":"Point"}
}