{
  "type": "Feature",
  "properties": {
    "addr:full":"1953 Gallows Rd Gretna VA 24557",
    "addr:housenumber":"1953",
    "addr:postcode":"24557",
    "addr:street":"Gallows Rd",
    "iso:country":"US",
    "sg:address":"1953 Gallows Rd",
    "sg:city":"Gretna",
    "sg:classifiers":[
        {
            "category":"Building & Trades",
            "subcategory":"Landscaping Services",
            "type":"Services"
        }
    ],
    "sg:phone":"+1 434 324 8243",
    "sg:postcode":"24557",
    "sg:province":"VA",
    "wof:name":"Jacksons Ldscpg & Ldscp Ltg",
    "wof:placetype":"venue"
},
  "geometry": {"coordinates":[-79.3759,37.084057],"type":"Point"}
}