{
  "type": "Feature",
  "properties": {
    "iso:country":"US",
    "sg:address":"3464 Huntington Trl",
    "sg:city":"Cascade",
    "sg:classifiers":[
        {
            "category":"Manufacturing",
            "subcategory":"Building Materials",
            "type":"Manufacturing & Wholesale Goods"
        }
    ],
    "sg:phone":"+1 434 685 4000",
    "sg:postcode":"24069",
    "sg:province":"VA",
    "sg:tags":[
        "bathroom",
        "mfg",
        "vanity"
    ],
    "wof:name":"Cascade Cabinets & Millwork",
    "wof:placetype":"venue"
},
  "geometry": {"coordinates":[-79.67029100000001,36.564141],"type":"Point"}
}