{
  "type": "Feature",
  "properties": {
    "addr:full":"28434 General Thomas Hwy Franklin VA 23851",
    "addr:postcode":"28434;23851",
    "addr:street":"General Thomas Hwy",
    "iso:country":"US",
    "sg:address":"28434 General Thomas Hwy",
    "sg:city":"Franklin",
    "sg:classifiers":[
        {
            "category":"Bus Charters",
            "type":"Transportation"
        }
    ],
    "sg:phone":"+1 757 562 4723",
    "sg:postcode":"23851",
    "sg:province":"VA",
    "sg:tags":[
        "chartered"
    ],
    "wof:name":"Franklin Bus Service Inc",
    "wof:placetype":"venue"
},
  "geometry": {"coordinates":[-77.02076599999999,36.647314],"type":"Point"}
}