{
  "type": "Feature",
  "properties": {
    "addr:full":"202 Clearview Dr Valentines VA 23887",
    "addr:housenumber":"202",
    "addr:postcode":"23887",
    "addr:street":"Clearview Dr Valentines",
    "iso:country":"US",
    "sg:address":"202 Clearview Dr",
    "sg:city":"Valentines",
    "sg:classifiers":[
        {
            "category":"Banks & Credit Unions",
            "subcategory":"Financial Services",
            "type":"Services"
        }
    ],
    "sg:phone":"+1 434 577 2227",
    "sg:postcode":"23887",
    "sg:province":"VA",
    "sg:tags":[
        "trust",
        "investment",
        "real estate"
    ],
    "wof:name":"Innovative Investments Inc",
    "wof:placetype":"venue"
},
  "geometry": {"coordinates":[-77.857378,36.554074],"type":"Point"}
}