{
  "type": "Feature",
  "properties": {
    "addr:full":"4 Family Life Ln Front Royal VA 22630",
    "addr:housenumber":"4",
    "addr:postcode":"22630",
    "addr:street":"Life Ln",
    "iso:country":"US",
    "sg:address":"4 Family Life Ln",
    "sg:city":"Front Royal",
    "sg:classifiers":[
        {
            "category":"Organizations",
            "subcategory":"Membership Organization",
            "type":"Services"
        }
    ],
    "sg:phone":"+1 540 635 7884",
    "sg:postcode":"22630",
    "sg:province":"VA",
    "sg:website":"www.hli.org",
    "wof:name":"Human Life Intl",
    "wof:placetype":"venue"
},
  "geometry": {"coordinates":[-78.15546999999999,38.933716],"type":"Point"}
}