{
  "type": "Feature",
  "properties": {
    "addr:full":"5309 Heatherbrook Ln Glen Allen VA 23059",
    "addr:housenumber":"5309",
    "addr:postcode":"23059",
    "addr:street":"Heatherbrook Ln",
    "iso:country":"US",
    "sg:address":"5309 Heatherbrook Ln",
    "sg:city":"Glen Allen",
    "sg:classifiers":[
        {
            "category":"Professional",
            "type":"Services"
        }
    ],
    "sg:phone":"+1 804 360 9336",
    "sg:postcode":"23059",
    "sg:province":"VA",
    "wof:name":"Corbin Brothers Inc",
    "wof:placetype":"venue"
},
  "geometry": {"coordinates":[-77.611102,37.688101],"type":"Point"}
}