{
  "type": "Feature",
  "properties": {
    "addr:full":"113 Paddington Way NE Leesburg VA 20176",
    "addr:housenumber":"113",
    "addr:postcode":"20176",
    "addr:street":"Paddington Way Ne",
    "iso:country":"US",
    "sg:address":"113 Paddington Way NE",
    "sg:city":"Leesburg",
    "sg:classifiers":[
        {
            "category":"Professional",
            "subcategory":"Management & Consulting",
            "type":"Services"
        }
    ],
    "sg:phone":"+1 571 258 1055",
    "sg:postcode":"20176",
    "sg:province":"VA",
    "sg:tags":[
        "party",
        "planning"
    ],
    "wof:name":"Custom Events",
    "wof:placetype":"venue"
},
  "geometry": {"coordinates":[-77.54103499999999,39.110866],"type":"Point"}
}