{
  "type": "Feature",
  "properties": {
    "addr:full":"29109 N Main St Newsoms VA 23829",
    "addr:housenumber":"29109",
    "addr:postcode":"23829",
    "addr:street":"N Main St",
    "iso:country":"US",
    "sg:address":"29109 N Main St",
    "sg:city":"Newsoms",
    "sg:classifiers":[
        {
            "category":"Shopping",
            "subcategory":"Discount & Variety Stores",
            "type":"Retail Goods"
        }
    ],
    "sg:phone":"+1 757 654 6060",
    "sg:postcode":"23829",
    "sg:province":"VA",
    "sg:tags":[
        "merchandise",
        "general"
    ],
    "wof:name":"Bryan Corvette Sales",
    "wof:placetype":"venue"
},
  "geometry": {"coordinates":[-77.125466,36.625523],"type":"Point"}
}