{
  "type": "Feature",
  "properties": {
    "addr:full":"22 Wine St Hampton VA 23669",
    "addr:housenumber":"22",
    "addr:postcode":"23669",
    "addr:street":"Wine St",
    "iso:country":"US",
    "sg:address":"22 Wine St",
    "sg:city":"Hampton",
    "sg:classifiers":[
        {
            "category":"Food & Beverages",
            "subcategory":"Specialty",
            "type":"Retail Goods"
        }
    ],
    "sg:phone":"+1 757 722 8466",
    "sg:postcode":"23669",
    "sg:province":"VA",
    "sg:tags":[
        "general",
        "alcoholic"
    ],
    "wof:name":"Pottery Wine and Cheese",
    "wof:placetype":"venue"
},
  "geometry": {"coordinates":[-76.343011,37.026361],"type":"Point"}
}