{
  "type": "Feature",
  "properties": {
    "addr:full":"4100 Fairfax Dr Ste 600 Arlington VA 22203",
    "addr:housenumber":"4100",
    "addr:postcode":"22203",
    "addr:street":"Fairfax Dr Ste 600",
    "iso:country":"US",
    "sg:address":"4100 Fairfax Dr Ste 600",
    "sg:city":"Arlington",
    "sg:classifiers":[
        {
            "category":"Banks & Credit Unions",
            "subcategory":"Investment Brokerage",
            "type":"Services"
        },
        {
            "category":"Professional",
            "subcategory":"Business Services",
            "type":"Services"
        }
    ],
    "sg:phone":"+1 703 816 8000",
    "sg:postcode":"22203",
    "sg:province":"VA",
    "sg:tags":[
        "broker",
        "commodity"
    ],
    "wof:name":"A R C",
    "wof:placetype":"venue"
},
  "geometry": {"coordinates":[-77.109421,38.882351],"type":"Point"}
}