{
  "type": "Feature",
  "properties": {
    "iso:country":"US",
    "sg:address":"3833 S Crater Rd",
    "sg:city":"Petersburg",
    "sg:classifiers":[
        {
            "category":"Organizations",
            "subcategory":"Religious Organization",
            "type":"Services"
        }
    ],
    "sg:phone":"+1 804 722 8277",
    "sg:postcode":"23805",
    "sg:province":"VA",
    "sg:tags":[
        "church"
    ],
    "wof:name":"Abundant Life Ministries",
    "wof:placetype":"venue"
},
  "geometry": {"coordinates":[-77.36055899999999,37.174339],"type":"Point"}
}