{
  "type": "Feature",
  "properties": {
    "addr:full":"7425 Adams Park Ct Annandale VA 22003",
    "addr:housenumber":"7425",
    "addr:postcode":"22003",
    "addr:street":"Adams Park Ct",
    "iso:country":"US",
    "sg:address":"7425 Adams Park Ct",
    "sg:city":"Annandale",
    "sg:classifiers":[
        {
            "category":"Professional",
            "subcategory":"Accounting & Tax Preparation",
            "type":"Services"
        }
    ],
    "sg:phone":"+1 703 750 9269",
    "sg:postcode":"22003",
    "sg:province":"VA",
    "wof:name":"Charles R Mc Devitt C P A",
    "wof:placetype":"venue"
},
  "geometry": {"coordinates":[-77.200323,38.828383],"type":"Point"}
}