{
  "type": "Feature",
  "properties": {
    "addr:full":"2814 Halsey St Chesapeake VA 23324",
    "addr:housenumber":"2814",
    "addr:postcode":"23324",
    "addr:street":"Halsey St",
    "iso:country":"US",
    "sg:address":"2814 Halsey St",
    "sg:city":"Chesapeake",
    "sg:classifiers":[
        {
            "category":"Building & Trades",
            "subcategory":"Cleaning & Sanitation",
            "type":"Services"
        }
    ],
    "sg:phone":"+1 757 543 3870",
    "sg:postcode":"23324",
    "sg:province":"VA",
    "sg:tags":[
        "maintenance"
    ],
    "wof:name":"A Ace Services",
    "wof:placetype":"venue"
},
  "geometry": {"coordinates":[-76.254419,36.790062],"type":"Point"}
}