{
  "type": "Feature",
  "properties": {
    "iso:country":"US",
    "sg:address":"8913 McGrath Rd",
    "sg:city":"Manassas",
    "sg:classifiers":[
        {
            "category":"Communications",
            "type":"Services"
        }
    ],
    "sg:phone":"+1 703 754 2195",
    "sg:postcode":"20112",
    "sg:province":"VA",
    "sg:tags":[
        "communication"
    ],
    "wof:name":"Fearson Communications",
    "wof:placetype":"venue"
},
  "geometry": {"coordinates":[-77.467506,38.699426],"type":"Point"}
}