{
  "type": "Feature",
  "properties": {
    "iso:country":"US",
    "sg:address":"6546 Townpoint Rd",
    "sg:city":"Suffolk",
    "sg:classifiers":[
        {
            "category":"Personal",
            "subcategory":"Beauty Salon",
            "type":"Services"
        }
    ],
    "sg:phone":"+1 757 686 8946",
    "sg:postcode":"23435",
    "sg:province":"VA",
    "wof:name":"Best Cuts",
    "wof:placetype":"venue"
},
  "geometry": {"coordinates":[-76.419929,36.876937],"type":"Point"}
}