{
  "type": "Feature",
  "properties": {
    "addr:full":"16706 Mountain Track Rd Orange VA 22960",
    "addr:housenumber":"16706",
    "addr:postcode":"22960",
    "addr:street":"Mountain Track Rd",
    "iso:country":"US",
    "sg:address":"16706 Mountain Track Rd",
    "sg:city":"Orange",
    "sg:classifiers":[
        {
            "category":"Organizations",
            "subcategory":"Membership Organization",
            "type":"Services"
        }
    ],
    "sg:phone":"+1 540 672 2133",
    "sg:postcode":"22960",
    "sg:province":"VA",
    "sg:tags":[
        "fraternal"
    ],
    "sg:website":"http://www.mooseintl.org",
    "wof:name":"Loyal Order of Moose Lodges",
    "wof:placetype":"venue"
},
  "geometry": {"coordinates":[-78.086524,38.175171],"type":"Point"}
}