{
  "type": "Feature",
  "properties": {
    "iso:country":"US",
    "sg:address":"208 High View Dr",
    "sg:city":"Blacksburg",
    "sg:classifiers":[
        {
            "category":"Professional",
            "subcategory":"Computer Services",
            "type":"Services"
        }
    ],
    "sg:phone":"+1 540 951 9773",
    "sg:postcode":"24060",
    "sg:province":"VA",
    "sg:tags":[
        "consulting",
        "management",
        "knowledge"
    ],
    "wof:name":"Coolheads Consulting",
    "wof:placetype":"venue"
},
  "geometry": {"coordinates":[-80.410494,37.246404],"type":"Point"}
}