{
  "type": "Feature",
  "properties": {
    "addr:full":"12998 River Ln Coeburn VA 24230",
    "addr:housenumber":"12998",
    "addr:postcode":"24230",
    "addr:street":"River Ln",
    "iso:country":"US",
    "sg:address":"12998 River Ln",
    "sg:city":"Coeburn",
    "sg:classifiers":[
        {
            "category":"Shopping",
            "subcategory":"Hobbies, Toys, & Games",
            "type":"Retail Goods"
        }
    ],
    "sg:phone":"+1 276 395 6905",
    "sg:postcode":"24230",
    "sg:province":"VA",
    "sg:tags":[
        "model",
        "supply"
    ],
    "wof:name":"B's Hobbies N More",
    "wof:placetype":"venue"
},
  "geometry": {"coordinates":[-82.434433,36.91603],"type":"Point"}
}