{
  "type": "Feature",
  "properties": {
    "addr:full":"5756 Hickory Dr Salem VA 24153",
    "addr:housenumber":"5756",
    "addr:postcode":"24153",
    "addr:street":"Hickory Dr",
    "iso:country":"US",
    "sg:address":"5756 Hickory Dr",
    "sg:city":"Salem",
    "sg:classifiers":[
        {
            "category":"Manufacturing",
            "subcategory":"Tools & Machinery",
            "type":"Manufacturing & Wholesale Goods"
        }
    ],
    "sg:phone":"+1 540 380 2683",
    "sg:postcode":"24153",
    "sg:province":"VA",
    "sg:tags":[
        "industrial",
        "mfg"
    ],
    "wof:name":"Harrell Marvin L & Carol L",
    "wof:placetype":"venue"
},
  "geometry": {"coordinates":[-80.134272,37.243065],"type":"Point"}
}