{
  "type": "Feature",
  "properties": {
    "addr:full":"13101 Old Church Rd New Kent VA 23124",
    "addr:housenumber":"13101",
    "addr:postcode":"23124",
    "addr:street":"Old Church Rd",
    "iso:country":"US",
    "sg:address":"13101 Old Church Rd",
    "sg:city":"New Kent",
    "sg:classifiers":[
        {
            "category":"Professional",
            "type":"Services"
        }
    ],
    "sg:phone":"+1 804 932 9785",
    "sg:postcode":"23124",
    "sg:province":"VA",
    "wof:name":"Randolph Reed",
    "wof:placetype":"venue"
},
  "geometry": {"coordinates":[-77.125249,37.611748],"type":"Point"}
}