{
  "type": "Feature",
  "properties": {
    "addr:full":"2300 24th Rd S Apt 1226 Arlington VA 22206",
    "addr:housenumber":"2300;1226",
    "addr:postcode":"22206",
    "addr:street":"24Th Rd",
    "iso:country":"US",
    "sg:address":"2300 24th Rd S Apt 1226",
    "sg:city":"Arlington",
    "sg:classifiers":[
        {
            "category":"Retail",
            "subcategory":"Auto Rental",
            "type":"Services"
        }
    ],
    "sg:phone":"+1 703 521 1212",
    "sg:postcode":"22206",
    "sg:province":"VA",
    "sg:tags":[
        "limousine"
    ],
    "wof:name":"Sly's Limousine Service Inc",
    "wof:placetype":"venue"
},
  "geometry": {"coordinates":[-77.07804899999999,38.8498],"type":"Point"}
}