{
  "type": "Feature",
  "properties": {
    "iso:country":"US",
    "sg:address":"1100 S Hayes St Ste 1024",
    "sg:city":"Arlington",
    "sg:classifiers":[
        {
            "category":"Shopping",
            "subcategory":"Clothing, Apparel, & Fashions",
            "type":"Retail Goods"
        }
    ],
    "sg:phone":"+1 703 415 3710",
    "sg:postcode":"22202",
    "sg:province":"VA",
    "sg:tags":[
        "accessory",
        "clothing",
        "women's"
    ],
    "sg:website":"www.anntaylor.com",
    "wof:name":"Ann Taylor",
    "wof:placetype":"venue"
},
  "geometry": {"coordinates":[-77.0596,38.863547],"type":"Point"}
}