{
  "type": "Feature",
  "properties": {
    "addr:full":"844 Amherst St Winchester VA 22601",
    "addr:housenumber":"844",
    "addr:postcode":"22601",
    "addr:street":"Amherst St",
    "iso:country":"US",
    "sg:address":"844 Amherst St",
    "sg:city":"Winchester",
    "sg:classifiers":[
        {
            "category":"Organizations",
            "subcategory":"Religious Organization",
            "type":"Services"
        }
    ],
    "sg:phone":"+1 540 667 2323",
    "sg:postcode":"22601",
    "sg:province":"VA",
    "wof:name":"Calvary Baptist Church",
    "wof:placetype":"venue"
},
  "geometry": {"coordinates":[-78.179236,39.18853],"type":"Point"}
}