{
  "type": "Feature",
  "properties": {
    "iso:country":"US",
    "sg:address":"144 Robin Ln",
    "sg:city":"Suffolk",
    "sg:classifiers":[
        {
            "category":"Building & Trades",
            "subcategory":"Construction",
            "type":"Services"
        }
    ],
    "sg:phone":"+1 757 235 0690",
    "sg:postcode":"23434",
    "sg:province":"VA",
    "sg:tags":[
        "house"
    ],
    "wof:name":"Smith Improvements",
    "wof:placetype":"venue"
},
  "geometry": {"coordinates":[-76.65712600000001,36.711056],"type":"Point"}
}