{
  "type": "Feature",
  "properties": {
    "addr:full":"1518 Jefferson Hwy Fishersville VA 22939",
    "addr:housenumber":"1518",
    "addr:postcode":"22939",
    "addr:street":"Jefferson Hwy Fishersville",
    "iso:country":"US",
    "sg:address":"1518 Jefferson Hwy",
    "sg:city":"Fishersville",
    "sg:classifiers":[
        {
            "category":"Organizations",
            "subcategory":"Religious Organization",
            "type":"Services"
        }
    ],
    "sg:phone":"+1 540 942 1058",
    "sg:postcode":"22939",
    "sg:province":"VA",
    "sg:tags":[
        "church"
    ],
    "sg:website":"www.fishersville.org",
    "wof:name":"Fishersville Baptist Church",
    "wof:placetype":"venue"
},
  "geometry": {"coordinates":[-78.97845,38.104283],"type":"Point"}
}