{
  "type": "Feature",
  "properties": {
    "addr:full":"1593 S Main St Harrisonburg VA 22801",
    "addr:housenumber":"1593",
    "addr:postcode":"22801",
    "addr:street":"S Main St",
    "iso:country":"US",
    "sg:address":"1593 S Main St",
    "sg:city":"Harrisonburg",
    "sg:classifiers":[
        {
            "category":"Wholesale",
            "subcategory":"Vending Machines",
            "type":"Manufacturing & Wholesale Goods"
        }
    ],
    "sg:phone":"+1 540 568 6681",
    "sg:postcode":"22801",
    "sg:province":"VA",
    "sg:tags":[
        "operator"
    ],
    "wof:name":"Aramark Services Vending Inc",
    "wof:placetype":"venue"
},
  "geometry": {"coordinates":[-78.884291,38.430514],"type":"Point"}
}