{
  "type": "Feature",
  "properties": {
    "iso:country":"US",
    "sg:address":"215 Main St",
    "sg:city":"Brookneal",
    "sg:classifiers":[
        {
            "category":"Health Services",
            "subcategory":"Doctor",
            "type":"Services"
        }
    ],
    "sg:phone":"+1 434 376 2238",
    "sg:postcode":"24528",
    "sg:province":"VA",
    "sg:tags":[
        "dentist"
    ],
    "wof:name":"Richard L Fisher DDS",
    "wof:placetype":"venue"
},
  "geometry": {"coordinates":[-78.942268,37.047386],"type":"Point"}
}