{
  "type": "Feature",
  "properties": {
    "iso:country":"US",
    "sg:address":"712 W 31st St",
    "sg:city":"Norfolk",
    "sg:classifiers":[
        {
            "category":"Building & Trades",
            "subcategory":"Cleaning & Sanitation",
            "type":"Services"
        }
    ],
    "sg:phone":"+1 757 855 4649",
    "sg:postcode":"23508",
    "sg:province":"VA",
    "sg:tags":[
        "janitorial"
    ],
    "wof:name":"Kdt Janitorial",
    "wof:placetype":"venue"
},
  "geometry": {"coordinates":[-76.29346200000001,36.876549],"type":"Point"}
}