{
  "type": "Feature",
  "properties": {
    "iso:country":"US",
    "sg:address":"15695 Palermo Ter",
    "sg:city":"Woodbridge",
    "sg:classifiers":[
        {
            "category":"Organizations",
            "subcategory":"Membership Organization",
            "type":"Services"
        }
    ],
    "sg:phone":"+1 703 590 4047",
    "sg:postcode":"22191",
    "sg:province":"VA",
    "sg:tags":[
        "fraternal"
    ],
    "wof:name":"The Knights Of Virginia",
    "wof:placetype":"venue"
},
  "geometry": {"coordinates":[-77.301073,38.612155],"type":"Point"}
}