{
  "type": "Feature",
  "properties": {
    "iso:country":"US",
    "sg:address":"748 E Main St",
    "sg:city":"Purcellville",
    "sg:classifiers":[
        {
            "category":"Health Services",
            "subcategory":"Chiropractor",
            "type":"Services"
        }
    ],
    "sg:phone":"+1 540 338 3190",
    "sg:postcode":"20132",
    "sg:province":"VA",
    "sg:tags":[
        "chiropractic"
    ],
    "wof:name":"Blue Ridge Chiropractic",
    "wof:placetype":"venue"
},
  "geometry": {"coordinates":[-77.703998,39.13646],"type":"Point"}
}