{
  "type": "Feature",
  "properties": {
    "addr:full":"1207 Richmond Dr Stafford VA 22554",
    "addr:housenumber":"1207",
    "addr:postcode":"22554",
    "addr:street":"Richmond Dr",
    "iso:country":"US",
    "sg:address":"1207 Richmond Dr",
    "sg:city":"Stafford",
    "sg:classifiers":[
        {
            "category":"Education",
            "subcategory":"Special Training",
            "type":"Public Place"
        }
    ],
    "sg:phone":"+1 540 659 8457",
    "sg:postcode":"22554",
    "sg:province":"VA",
    "sg:tags":[
        "educational"
    ],
    "wof:name":"James Smith",
    "wof:placetype":"venue"
},
  "geometry": {"coordinates":[-77.39176,38.462942],"type":"Point"}
}