{
  "type": "Feature",
  "properties": {
    "iso:country":"US",
    "sg:address":"1 N Dooley Ave",
    "sg:city":"Richmond",
    "sg:classifiers":[
        {
            "category":"Utilities",
            "subcategory":"Telephone",
            "type":"Services"
        },
        {
            "category":"Professional",
            "subcategory":"Computer Services",
            "type":"Services"
        }
    ],
    "sg:phone":"+1 804 353 9066",
    "sg:postcode":"23221",
    "sg:province":"VA",
    "sg:tags":[
        "communications",
        "internet"
    ],
    "wof:name":"Abernathy & Quinn Inc",
    "wof:placetype":"venue"
},
  "geometry": {"coordinates":[-77.482569,37.556509],"type":"Point"}
}