{
  "type": "Feature",
  "properties": {
    "addr:full":"8996 Burke Lake Rd Burke VA 22015",
    "addr:housenumber":"8996",
    "addr:postcode":"22015",
    "addr:street":"Burke Lake Rd",
    "iso:country":"US",
    "sg:address":"8996 Burke Lake Rd",
    "sg:city":"Burke",
    "sg:classifiers":[
        {
            "category":"Professional",
            "subcategory":"Lawyer & Legal Services",
            "type":"Services"
        }
    ],
    "sg:phone":"+1 703 323 7000",
    "sg:postcode":"22015",
    "sg:province":"VA",
    "sg:tags":[
        "attorney"
    ],
    "wof:name":"Turbitt & Oherron",
    "wof:placetype":"venue"
},
  "geometry": {"coordinates":[-77.254993,38.807895],"type":"Point"}
}