{
  "type": "Feature",
  "properties": {
    "iso:country":"US",
    "sg:address":"9 Main St",
    "sg:city":"Wachapreague",
    "sg:classifiers":[
        {
            "category":"Food & Beverages",
            "subcategory":"Groceries & Convenience Stores",
            "type":"Retail Goods"
        }
    ],
    "sg:phone":"+1 757 787 4660",
    "sg:postcode":"23480",
    "sg:province":"VA",
    "sg:tags":[
        "grocer"
    ],
    "wof:name":"Carpenter Grocery",
    "wof:placetype":"venue"
},
  "geometry": {"coordinates":[-75.690091,37.60451],"type":"Point"}
}