{
  "type": "Feature",
  "properties": {
    "addr:full":"14701 Cloverdale Rd Woodbridge VA 22193",
    "addr:housenumber":"14701",
    "addr:postcode":"22193",
    "addr:street":"Cloverdale Rd",
    "iso:country":"US",
    "sg:address":"14701 Cloverdale Rd",
    "sg:city":"Woodbridge",
    "sg:classifiers":[
        {
            "category":"Home & Garden",
            "subcategory":"Household Appliances",
            "type":"Retail Goods"
        },
        {
            "category":"Retail",
            "subcategory":"Repair Shop",
            "type":"Services"
        },
        {
            "category":"Building & Trades",
            "subcategory":"Construction",
            "type":"Services"
        }
    ],
    "sg:phone":"+1 703 590 4500",
    "sg:postcode":"22193",
    "sg:province":"VA",
    "sg:tags":[
        "system",
        "major",
        "refinishing",
        "specialty",
        "heating",
        "air conditioning",
        "contractor",
        "freezers-repair",
        "refrigerator"
    ],
    "sg:website":"http://www.ableappliances.com/",
    "wof:name":"Able Appliance Service",
    "wof:placetype":"venue"
},
  "geometry": {"coordinates":[-77.320759,38.633896],"type":"Point"}
}