{
  "type": "Feature",
  "properties": {
    "addr:full":"1170 Memorial Blvd S Martinsville VA 24112",
    "addr:housenumber":"1170",
    "addr:postcode":"24112",
    "addr:street":"Memorial Blvd S Martinsville",
    "iso:country":"US",
    "sg:address":"1170 Memorial Blvd S",
    "sg:city":"Martinsville",
    "sg:classifiers":[
        {
            "category":"Restaurant",
            "type":"Food & Drink"
        }
    ],
    "sg:phone":"+1 276 632 7599",
    "sg:postcode":"24112",
    "sg:province":"VA",
    "wof:name":"Tokyo Express",
    "wof:placetype":"venue"
},
  "geometry": {"coordinates":[-79.876616,36.675293],"type":"Point"}
}