{
  "type": "Feature",
  "properties": {
    "iso:country":"US",
    "sg:address":"2340 Legge Blvd",
    "sg:city":"Winchester",
    "sg:classifiers":[
        {
            "category":"Shopping",
            "subcategory":"Pharmacy",
            "type":"Retail Goods"
        }
    ],
    "sg:phone":"+1 540 535 0220",
    "sg:postcode":"22601",
    "sg:province":"VA",
    "wof:name":"Target",
    "wof:placetype":"venue"
},
  "geometry": {"coordinates":[-78.171221,39.153732],"type":"Point"}
}