{
  "type": "Feature",
  "properties": {
    "addr:full":"10427 Balls Ford Rd Manassas VA 20109",
    "addr:housenumber":"10427",
    "addr:postcode":"20109",
    "addr:street":"Balls Ford Rd",
    "iso:country":"US",
    "sg:address":"10427 Balls Ford Rd",
    "sg:city":"Manassas",
    "sg:classifiers":[
        {
            "category":"Shopping",
            "subcategory":"Florist",
            "type":"Retail Goods"
        }
    ],
    "sg:phone":"+1 703 361 7151",
    "sg:postcode":"20109",
    "sg:province":"VA",
    "wof:name":"Del Rose Florist",
    "wof:placetype":"venue"
},
  "geometry": {"coordinates":[-77.504913,38.802772],"type":"Point"}
}