{
  "type": "Feature",
  "properties": {
    "addr:full":"2188 Rockfish Valley Hwy Nellysford VA 22958",
    "addr:housenumber":"2188",
    "addr:postcode":"22958",
    "addr:street":"Rockfish Valley Hwy Nellysford",
    "iso:country":"US",
    "sg:address":"2188 Rockfish Valley Hwy",
    "sg:city":"Nellysford",
    "sg:classifiers":[
        {
            "category":"Food & Beverages",
            "subcategory":"Groceries & Convenience Stores",
            "type":"Retail Goods"
        }
    ],
    "sg:phone":"+1 434 361 2077",
    "sg:postcode":"22958",
    "sg:province":"VA",
    "wof:name":"Valleymont Market",
    "wof:placetype":"venue"
},
  "geometry": {"coordinates":[-78.88385,37.886802],"type":"Point"}
}