{
  "type": "Feature",
  "properties": {
    "iso:country":"US",
    "sg:address":"1816 General Puller Hwy",
    "sg:city":"Saluda",
    "sg:classifiers":[
        {
            "category":"Retail",
            "subcategory":"Auto Repair",
            "type":"Services"
        }
    ],
    "sg:phone":"+1 804 758 4074",
    "sg:postcode":"23149",
    "sg:province":"VA",
    "sg:tags":[
        "body",
        "automobile",
        "painting"
    ],
    "wof:name":"Johnsons Body Shop",
    "wof:placetype":"venue"
},
  "geometry": {"coordinates":[-76.58063300000001,37.599097],"type":"Point"}
}