{
  "type": "Feature",
  "properties": {
    "addr:full":"14411 Tracy Schar Ln Centreville VA 20121",
    "addr:housenumber":"14411",
    "addr:postcode":"20121",
    "addr:street":"Tracy Schar Ln",
    "iso:country":"US",
    "sg:address":"14411 Tracy Schar Ln",
    "sg:city":"Centreville",
    "sg:classifiers":[
        {
            "category":"Professional",
            "subcategory":"Management & Consulting",
            "type":"Services"
        }
    ],
    "sg:phone":"+1 703 599 9436",
    "sg:postcode":"20121",
    "sg:province":"VA",
    "wof:name":"Construction & Systems Integr",
    "wof:placetype":"venue"
},
  "geometry": {"coordinates":[-77.446685,38.816704],"type":"Point"}
}