{
  "type": "Feature",
  "properties": {
    "iso:country":"US",
    "sg:address":"6520 Peters Creek Rd",
    "sg:city":"Roanoke",
    "sg:classifiers":[
        {
            "category":"Autos & Motor Vehicles",
            "subcategory":"Automobile Sales",
            "type":"Retail Goods"
        },
        {
            "category":"Autos & Motor Vehicles",
            "subcategory":"Auto Supplies",
            "type":"Retail Goods"
        },
        {
            "category":"Retail",
            "subcategory":"Auto Repair",
            "type":"Services"
        }
    ],
    "sg:phone":"+1 540 362 4800",
    "sg:postcode":"24019",
    "sg:province":"VA",
    "sg:tags":[
        "used",
        "car",
        "part",
        "truck",
        "new"
    ],
    "sg:website":"http://firstteamnissan.com/",
    "wof:name":"First Team Nissan",
    "wof:placetype":"venue"
},
  "geometry": {"coordinates":[-79.96217,37.344708],"type":"Point"}
}