{
  "type": "Feature",
  "properties": {
    "iso:country":"US",
    "sg:address":"204 N Main St",
    "sg:city":"Gordonsville",
    "sg:classifiers":[
        {
            "category":"Health Services",
            "subcategory":"Nursing And Care Facility",
            "type":"Services"
        }
    ],
    "sg:phone":"+1 540 832 2286",
    "sg:postcode":"22942",
    "sg:province":"VA",
    "sg:tags":[
        "home",
        "retirement",
        "community"
    ],
    "wof:name":"Gordon House",
    "wof:placetype":"venue"
},
  "geometry": {"coordinates":[-78.18758200000001,38.137459],"type":"Point"}
}