{
  "type": "Feature",
  "properties": {
    "addr:full":"207 E Cawson St Hopewell VA 23860",
    "addr:housenumber":"207",
    "addr:postcode":"23860",
    "addr:street":"E Cawson St",
    "iso:country":"US",
    "sg:address":"207 E Cawson St",
    "sg:city":"Hopewell",
    "sg:classifiers":[
        {
            "category":"Organizations",
            "subcategory":"Religious Organization",
            "type":"Services"
        }
    ],
    "sg:phone":"+1 804 541 0232",
    "sg:postcode":"23860",
    "sg:province":"VA",
    "sg:tags":[
        "church"
    ],
    "wof:name":"Hooray For Hopewell Festival",
    "wof:placetype":"venue"
},
  "geometry": {"coordinates":[-77.28511,37.305789],"type":"Point"}
}