{
  "type": "Feature",
  "properties": {
    "iso:country":"US",
    "sg:address":"201 Weaver Ave",
    "sg:city":"Emporia",
    "sg:classifiers":[
        {
            "category":"Health Services",
            "subcategory":"Clinic",
            "type":"Services"
        }
    ],
    "sg:phone":"+1 434 348 3882",
    "sg:postcode":"23847",
    "sg:province":"VA",
    "sg:tags":[
        "kidney",
        "dialysis",
        "center"
    ],
    "wof:name":"Meherrin Dialysis Center Inc",
    "wof:placetype":"venue"
},
  "geometry": {"coordinates":[-77.539276,36.699405],"type":"Point"}
}