{
  "type": "Feature",
  "properties": {
    "iso:country":"US",
    "sg:address":"8300 Sudley Rd",
    "sg:city":"Manassas",
    "sg:classifiers":[
        {
            "category":"Shopping",
            "subcategory":"Beauty & Cosmetics",
            "type":"Retail Goods"
        },
        {
            "category":"Personal",
            "subcategory":"Beauty Salon",
            "type":"Services"
        }
    ],
    "sg:phone":"+1 703 257 9745",
    "sg:postcode":"20109",
    "sg:province":"VA",
    "sg:tags":[
        "make",
        "studio",
        "product",
        "care"
    ],
    "wof:name":"Bath & Body Works Inc",
    "wof:placetype":"venue"
},
  "geometry": {"coordinates":[-77.501817,38.774311],"type":"Point"}
}