{
  "type": "Feature",
  "properties": {
    "addr:full":"8634 Oak Chase Cir Fairfax Station VA 22039",
    "addr:housenumber":"8634",
    "addr:postcode":"22039",
    "addr:street":"Oak Chase Cir Fairfax",
    "iso:country":"US",
    "sg:address":"8634 Oak Chase Cir",
    "sg:city":"Fairfax Station",
    "sg:classifiers":[
        {
            "category":"Professional",
            "subcategory":"Management & Consulting",
            "type":"Services"
        }
    ],
    "sg:phone":"+1 703 643 1211",
    "sg:postcode":"22039",
    "sg:province":"VA",
    "sg:tags":[
        "marketing",
        "product",
        "construction"
    ],
    "wof:name":"ADM Concepts",
    "wof:placetype":"venue"
},
  "geometry": {"coordinates":[-77.255303,38.726112],"type":"Point"}
}