{
  "type": "Feature",
  "properties": {
    "iso:country":"US",
    "sg:address":"18605 Jefferson Davis Hwy",
    "sg:city":"Woodbridge",
    "sg:classifiers":[
        {
            "category":"Personal",
            "subcategory":"Beauty Salon",
            "type":"Services"
        }
    ],
    "sg:phone":"+1 703 441 1005",
    "sg:postcode":"22172",
    "sg:province":"VA",
    "wof:name":"Changin Faces Hair Studio",
    "wof:placetype":"venue"
},
  "geometry": {"coordinates":[-77.336062,38.546613],"type":"Point"}
}