{
  "type": "Feature",
  "properties": {
    "addr:full":"7801 Laurel Spring Rd Prince George VA 23875",
    "addr:housenumber":"7801",
    "addr:postcode":"23875",
    "addr:street":"Laurel Spring Rd",
    "iso:country":"US",
    "sg:address":"7801 Laurel Spring Rd",
    "sg:city":"Prince George",
    "sg:classifiers":[
        {
            "category":"Education",
            "subcategory":"School",
            "type":"Public Place"
        }
    ],
    "sg:phone":"+1 804 733 2720",
    "sg:postcode":"23875",
    "sg:province":"VA",
    "sg:tags":[
        "executive"
    ],
    "wof:name":"Prince George High School",
    "wof:placetype":"venue"
},
  "geometry": {"coordinates":[-77.265621,37.207919],"type":"Point"}
}