{
  "type": "Feature",
  "properties": {
    "iso:country":"US",
    "sg:address":"415 Park St",
    "sg:city":"Charlottesville",
    "sg:classifiers":[
        {
            "category":"Professional",
            "subcategory":"Lawyer & Legal Services",
            "type":"Services"
        }
    ],
    "sg:phone":"+1 434 295 9011",
    "sg:postcode":"22902",
    "sg:province":"VA",
    "wof:name":"Anderson William Lee Atty",
    "wof:placetype":"venue"
},
  "geometry": {"coordinates":[-78.47689800000001,38.032398],"type":"Point"}
}