{
  "type": "Feature",
  "properties": {
    "addr:full":"5733 Bayside Rd Virginia Beach VA 23455",
    "addr:housenumber":"5733",
    "addr:postcode":"23455",
    "addr:street":"Bayside Rd",
    "iso:country":"US",
    "sg:address":"5733 Bayside Rd",
    "sg:city":"Virginia Beach",
    "sg:classifiers":[
        {
            "category":"Retail",
            "subcategory":"Auto Rental",
            "type":"Services"
        }
    ],
    "sg:phone":"+1 757 460 5559",
    "sg:postcode":"23455",
    "sg:province":"VA",
    "sg:tags":[
        "truck",
        "leasing"
    ],
    "wof:name":"Ryder",
    "wof:placetype":"venue"
},
  "geometry": {"coordinates":[-76.180685,36.896694],"type":"Point"}
}