{
  "type": "Feature",
  "properties": {
    "iso:country":"US",
    "sg:address":"7800 Winona Ct",
    "sg:city":"Annandale",
    "sg:classifiers":[
        {
            "category":"Building & Trades",
            "subcategory":"Cleaning & Sanitation",
            "type":"Services"
        },
        {
            "category":"Retail",
            "subcategory":"Laundry & Dry Cleaning",
            "type":"Services"
        }
    ],
    "sg:phone":"+1 571 405 8748",
    "sg:postcode":"22003",
    "sg:province":"VA",
    "sg:tags":[
        "terrazzo",
        "house",
        "marble",
        "window",
        "steam",
        "chimney"
    ],
    "wof:name":"Tatys Cleaning Service",
    "wof:placetype":"venue"
},
  "geometry": {"coordinates":[-77.215431,38.82048],"type":"Point"}
}