{
  "type": "Feature",
  "properties": {
    "iso:country":"US",
    "sg:address":"1014 Country Club Dr NE",
    "sg:city":"Vienna",
    "sg:classifiers":[
        {
            "category":"Social Services",
            "subcategory":"Child Care",
            "type":"Services"
        }
    ],
    "sg:phone":"+1 703 938 2391",
    "sg:postcode":"22180",
    "sg:province":"VA",
    "sg:tags":[
        "elementary",
        "school",
        "day"
    ],
    "wof:name":"Epiphany Preschool",
    "wof:placetype":"venue"
},
  "geometry": {"coordinates":[-77.252602,38.9212],"type":"Point"}
}