{
  "type": "Feature",
  "properties": {
    "addr:full":"37251 E Richardson Ln Purcellville VA 20132",
    "addr:housenumber":"37251",
    "addr:postcode":"20132",
    "addr:street":"E Richardson Ln",
    "iso:country":"US",
    "sg:address":"37251 E Richardson Ln",
    "sg:city":"Purcellville",
    "sg:classifiers":[
        {
            "category":"Professional",
            "type":"Services"
        }
    ],
    "sg:phone":"+1 540 751 0300",
    "sg:postcode":"20132",
    "sg:province":"VA",
    "sg:tags":[
        "establishment"
    ],
    "wof:name":"Miromar",
    "wof:placetype":"venue"
},
  "geometry": {"coordinates":[-77.717488,39.145809],"type":"Point"}
}