{
  "type": "Feature",
  "properties": {
    "iso:country":"US",
    "sg:address":"2804 Meeting Gate Ct",
    "sg:city":"Midlothian",
    "sg:classifiers":[
        {
            "category":"Wholesale",
            "subcategory":"Machinery & Supplies",
            "type":"Manufacturing & Wholesale Goods"
        },
        {
            "category":"Building & Trades",
            "subcategory":"Cleaning & Sanitation",
            "type":"Services"
        }
    ],
    "sg:phone":"+1 804 763 0149",
    "sg:postcode":"23112",
    "sg:province":"VA",
    "sg:tags":[
        "equipment",
        "establishment",
        "janitor"
    ],
    "wof:name":"Fresh & Clean Pro Cleaning Svc",
    "wof:placetype":"venue"
},
  "geometry": {"coordinates":[-77.66576000000001,37.448634],"type":"Point"}
}