{
  "type": "Feature",
  "properties": {
    "addr:full":"3520 N Military Hwy Norfolk VA 23518",
    "addr:housenumber":"3520",
    "addr:postcode":"23518",
    "addr:street":"N Military Hwy",
    "iso:country":"US",
    "sg:address":"3520 N Military Hwy",
    "sg:city":"Norfolk",
    "sg:classifiers":[
        {
            "category":"Shopping",
            "subcategory":"Clothing, Apparel, & Fashions",
            "type":"Retail Goods"
        }
    ],
    "sg:phone":"+1 757 852 9200",
    "sg:postcode":"23518",
    "sg:province":"VA",
    "sg:tags":[
        "navy",
        "army"
    ],
    "wof:name":"Little GI Joe's Military",
    "wof:placetype":"venue"
},
  "geometry": {"coordinates":[-76.22069999999999,36.890929],"type":"Point"}
}