{
  "type": "Feature",
  "properties": {
    "addr:full":"608 Sussex St Lynchburg VA 24501",
    "addr:housenumber":"608",
    "addr:postcode":"24501",
    "addr:street":"Sussex St",
    "iso:country":"US",
    "sg:address":"608 Sussex St",
    "sg:city":"Lynchburg",
    "sg:classifiers":[
        {
            "category":"Autos & Motor Vehicles",
            "subcategory":"Auto Supplies",
            "type":"Retail Goods"
        }
    ],
    "sg:phone":"+1 434 847 4863",
    "sg:postcode":"24501",
    "sg:province":"VA",
    "wof:name":"Steve S Glass",
    "wof:placetype":"venue"
},
  "geometry": {"coordinates":[-79.181166,37.391458],"type":"Point"}
}