{
  "type": "Feature",
  "properties": {
    "addr:full":"8103 Centreville Rd Manassas VA 20111",
    "addr:housenumber":"8103",
    "addr:postcode":"20111",
    "addr:street":"Centreville Rd",
    "iso:country":"US",
    "sg:address":"8103 Centreville Rd",
    "sg:city":"Manassas",
    "sg:classifiers":[
        {
            "category":"Personal",
            "type":"Services"
        }
    ],
    "sg:phone":"+1 703 335 6455",
    "sg:postcode":"20111",
    "sg:province":"VA",
    "wof:name":"Good Times Tattoo",
    "wof:placetype":"venue"
},
  "geometry": {"coordinates":[-77.45052699999999,38.779722],"type":"Point"}
}