{
  "type": "Feature",
  "properties": {
    "addr:full":"743 Colonial Rd Blue Ridge VA 24064",
    "addr:housenumber":"743",
    "addr:postcode":"24064",
    "addr:street":"Colonial Rd",
    "iso:country":"US",
    "sg:address":"743 Colonial Rd",
    "sg:city":"Blue Ridge",
    "sg:classifiers":[
        {
            "category":"Building & Trades",
            "subcategory":"Construction",
            "type":"Services"
        }
    ],
    "sg:phone":"+1 540 977 5526",
    "sg:postcode":"24064",
    "sg:province":"VA",
    "sg:tags":[
        "house"
    ],
    "wof:name":"Mountcastle RPS Cnstr & Con",
    "wof:placetype":"venue"
},
  "geometry": {"coordinates":[-79.811606,37.368623],"type":"Point"}
}