{
  "type": "Feature",
  "properties": {
    "addr:full":"250 S Main St Rocky Mount VA 24151",
    "addr:housenumber":"250",
    "addr:postcode":"24151",
    "addr:street":"S Main St",
    "iso:country":"US",
    "sg:address":"250 S Main St",
    "sg:city":"Rocky Mount",
    "sg:classifiers":[
        {
            "category":"Real Estate",
            "subcategory":"Surveying",
            "type":"Services"
        }
    ],
    "sg:phone":"+1 540 489 3590",
    "sg:postcode":"24151",
    "sg:province":"VA",
    "sg:tags":[
        "surveyor"
    ],
    "wof:name":"Cornerstone Land Surveying Inc",
    "wof:placetype":"venue"
},
  "geometry": {"coordinates":[-79.88945,36.994659],"type":"Point"}
}