{
  "type": "Feature",
  "properties": {
    "addr:full":"4110 Hull Street Rd Richmond VA 23224",
    "addr:housenumber":"4110",
    "addr:postcode":"23224",
    "addr:street":"Hull Street Rd",
    "iso:country":"US",
    "sg:address":"4110 Hull Street Rd",
    "sg:city":"Richmond",
    "sg:classifiers":[
        {
            "category":"Restaurant",
            "type":"Food & Drink"
        }
    ],
    "sg:menulink":"http://www.allmenus.com/va/richmond/188046-mcdonalds/menu/",
    "sg:phone":"+1 804 233 8449",
    "sg:postcode":"23224",
    "sg:province":"VA",
    "sg:tags":[
        "burger",
        "american"
    ],
    "wof:name":"McDonald's",
    "wof:placetype":"venue"
},
  "geometry": {"coordinates":[-77.475757,37.500909],"type":"Point"}
}