{
  "type": "Feature",
  "properties": {
    "addr:full":"223 Rosemeade Pl SW Leesburg VA 20175",
    "addr:housenumber":"223",
    "addr:postcode":"20175",
    "addr:street":"Rosemeade Pl Sw",
    "iso:country":"US",
    "sg:address":"223 Rosemeade Pl SW",
    "sg:city":"Leesburg",
    "sg:classifiers":[
        {
            "category":"Professional",
            "subcategory":"Computer Services",
            "type":"Services"
        }
    ],
    "sg:phone":"+1 703 771 7897",
    "sg:postcode":"20175",
    "sg:province":"VA",
    "sg:tags":[
        "datum",
        "related"
    ],
    "wof:name":"K3online Co Inc",
    "wof:placetype":"venue"
},
  "geometry": {"coordinates":[-77.57649600000001,39.113733],"type":"Point"}
}