{
  "type": "Feature",
  "properties": {
    "addr:full":"2250 Clarendon Blvd Arlington VA 22201",
    "addr:housenumber":"2250",
    "addr:postcode":"22201",
    "addr:street":"Clarendon Blvd",
    "iso:country":"US",
    "sg:address":"2250 Clarendon Blvd",
    "sg:city":"Arlington",
    "sg:classifiers":[
        {
            "category":"Professional",
            "subcategory":"Business Services",
            "type":"Services"
        }
    ],
    "sg:phone":"+1 330 607 6254",
    "sg:postcode":"22201",
    "sg:province":"VA",
    "sg:tags":[
        "consultant",
        "coach"
    ],
    "wof:name":"Process Optima",
    "wof:placetype":"venue"
},
  "geometry": {"coordinates":[-77.08674499999999,38.890335],"type":"Point"}
}