{
  "type": "Feature",
  "properties": {
    "addr:full":"6141 Leesburg Pike Falls Church VA 22041",
    "addr:housenumber":"6141",
    "addr:postcode":"22041",
    "addr:street":"Leesburg Pike",
    "iso:country":"US",
    "sg:address":"6141 Leesburg Pike",
    "sg:city":"Falls Church",
    "sg:classifiers":[
        {
            "category":"Local Transit",
            "type":"Transportation"
        }
    ],
    "sg:phone":"+1 703 795 4456",
    "sg:postcode":"22041",
    "sg:province":"VA",
    "sg:tags":[
        "passenger"
    ],
    "wof:name":"Castle Sedan Service",
    "wof:placetype":"venue"
},
  "geometry": {"coordinates":[-77.144216,38.858409],"type":"Point"}
}