{
  "type": "Feature",
  "properties": {
    "addr:full":"9415 Atlee Commerce Blvd Ashland VA 23005",
    "addr:housenumber":"9415",
    "addr:postcode":"23005",
    "addr:street":"Atlee Commerce Blvd",
    "iso:country":"US",
    "sg:address":"9415 Atlee Commerce Blvd",
    "sg:city":"Ashland",
    "sg:classifiers":[
        {
            "category":"Professional",
            "subcategory":"Management & Consulting",
            "type":"Services"
        }
    ],
    "sg:phone":"+1 804 550 2193",
    "sg:postcode":"23005",
    "sg:province":"VA",
    "sg:tags":[
        "retail",
        "direct",
        "sales"
    ],
    "wof:name":"Bleu Water Company",
    "wof:placetype":"venue"
},
  "geometry": {"coordinates":[-77.430396,37.694187],"type":"Point"}
}