{
  "type": "Feature",
  "properties": {
    "addr:full":"2519 Jimmy Winters Rd Richmond VA 23235",
    "addr:housenumber":"2519",
    "addr:postcode":"23235",
    "addr:street":"Jimmy Winters Rd",
    "iso:country":"US",
    "sg:address":"2519 Jimmy Winters Rd",
    "sg:city":"Richmond",
    "sg:classifiers":[
        {
            "category":"Wholesale",
            "subcategory":"Electrical",
            "type":"Manufacturing & Wholesale Goods"
        },
        {
            "category":"Social Services",
            "type":"Services"
        }
    ],
    "sg:phone":"+1 804 267 5673",
    "sg:postcode":"23235",
    "sg:province":"VA",
    "sg:tags":[
        "counseling",
        "equipment"
    ],
    "wof:name":"Lord & Bayer Associates Inc",
    "wof:placetype":"venue"
},
  "geometry": {"coordinates":[-77.567145,37.533227],"type":"Point"}
}