{
  "type": "Feature",
  "properties": {
    "addr:full":"1861 Wiehle Ave Reston VA 20190",
    "addr:housenumber":"1861",
    "addr:postcode":"20190",
    "addr:street":"Wiehle Ave",
    "iso:country":"US",
    "sg:address":"1861 Wiehle Ave",
    "sg:city":"Reston",
    "sg:classifiers":[
        {
            "category":"Government",
            "subcategory":"Office",
            "type":"Public Place"
        }
    ],
    "sg:phone":"+1 202 736 7141",
    "sg:postcode":"20190",
    "sg:province":"VA",
    "sg:tags":[
        "state"
    ],
    "wof:name":"US State Dept",
    "wof:placetype":"venue"
},
  "geometry": {"coordinates":[-77.337023,38.948015],"type":"Point"}
}