{
  "type": "Feature",
  "properties": {
    "iso:country":"US",
    "sg:address":"14595 Avion Pkwy Ste 900",
    "sg:city":"Chantilly",
    "sg:classifiers":[
        {
            "category":"Arena",
            "subcategory":"Sports Club",
            "type":"Entertainment"
        }
    ],
    "sg:phone":"+1 703 817 1708",
    "sg:postcode":"20151",
    "sg:province":"VA",
    "sg:tags":[
        "health"
    ],
    "wof:name":"Avion Health Club Inc",
    "wof:placetype":"venue"
},
  "geometry": {"coordinates":[-77.44925499999999,38.907418],"type":"Point"}
}