{
  "type": "Feature",
  "properties": {
    "addr:full":"9127 Westone Rd Mechanicsville VA 23116",
    "addr:housenumber":"9127",
    "addr:postcode":"23116",
    "addr:street":"Westone Rd",
    "iso:country":"US",
    "sg:address":"9127 Westone Rd",
    "sg:city":"Mechanicsville",
    "sg:classifiers":[
        {
            "category":"Personal",
            "type":"Services"
        }
    ],
    "sg:phone":"+1 804 559 7732",
    "sg:postcode":"23116",
    "sg:province":"VA",
    "sg:tags":[
        "towing"
    ],
    "wof:name":"Tri Cities Towing Inc",
    "wof:placetype":"venue"
},
  "geometry": {"coordinates":[-77.409694,37.648795],"type":"Point"}
}