{
  "type": "Feature",
  "properties": {
    "addr:full":"302 Stage Rd Buchanan VA 24066",
    "addr:housenumber":"302",
    "addr:postcode":"24066",
    "addr:street":"Stage Rd",
    "iso:country":"US",
    "sg:address":"302 Stage Rd",
    "sg:city":"Buchanan",
    "sg:classifiers":[
        {
            "category":"Professional",
            "type":"Services"
        }
    ],
    "sg:phone":"+1 540 473 3998",
    "sg:postcode":"24066",
    "sg:province":"VA",
    "wof:name":"Homespun Legacy",
    "wof:placetype":"venue"
},
  "geometry": {"coordinates":[-79.812592,37.535038],"type":"Point"}
}