{
  "type": "Feature",
  "properties": {
    "iso:country":"US",
    "sg:address":"10800 Midlothian Tpke",
    "sg:city":"Richmond",
    "sg:classifiers":[
        {
            "category":"Shopping",
            "subcategory":"Department Store",
            "type":"Retail Goods"
        }
    ],
    "sg:phone":"+1 703 396 7955",
    "sg:postcode":"23235",
    "sg:province":"VA",
    "wof:name":"Sears Roebuck and Co Inc",
    "wof:placetype":"venue"
},
  "geometry": {"coordinates":[-77.59536900000001,37.507009],"type":"Point"}
}