{
  "type": "Feature",
  "properties": {
    "addr:full":"20921 Davenport Dr Sterling VA 20165",
    "addr:housenumber":"20921",
    "addr:postcode":"20165",
    "addr:street":"Davenport Dr",
    "iso:country":"US",
    "sg:address":"20921 Davenport Dr",
    "sg:city":"Sterling",
    "sg:classifiers":[
        {
            "category":"Personal",
            "subcategory":"Barber",
            "type":"Services"
        }
    ],
    "sg:phone":"+1 703 450 6667",
    "sg:postcode":"20165",
    "sg:province":"VA",
    "sg:tags":[
        "shop"
    ],
    "wof:name":"Parc City Barber",
    "wof:placetype":"venue"
},
  "geometry": {"coordinates":[-77.40930299999999,39.036822],"type":"Point"}
}