{
  "type": "Feature",
  "properties": {
    "iso:country":"US",
    "sg:address":"4003 Westfax Dr",
    "sg:city":"Chantilly",
    "sg:classifiers":[
        {
            "category":"Retail",
            "subcategory":"Car Wash",
            "type":"Services"
        }
    ],
    "sg:phone":"+1 703 817 9400",
    "sg:postcode":"20151",
    "sg:province":"VA",
    "sg:tags":[
        "automobile",
        "detail",
        "clean"
    ],
    "wof:name":"Top Notch Detailing",
    "wof:placetype":"venue"
},
  "geometry": {"coordinates":[-77.455861,38.8999],"type":"Point"}
}