{
  "type": "Feature",
  "properties": {
    "addr:full":"16144 Carrollton Blvd Carrollton VA 23314",
    "addr:housenumber":"16144",
    "addr:postcode":"23314",
    "addr:street":"Carrollton Blvd",
    "iso:country":"US",
    "sg:address":"16144 Carrollton Blvd",
    "sg:city":"Carrollton",
    "sg:classifiers":[
        {
            "category":"Organizations",
            "subcategory":"Religious Organization",
            "type":"Services"
        }
    ],
    "sg:phone":"+1 757 238 8866",
    "sg:postcode":"23314",
    "sg:province":"VA",
    "wof:name":"Carrollton Church Of God",
    "wof:placetype":"venue"
},
  "geometry": {"coordinates":[-76.509488,36.917993],"type":"Point"}
}