{
  "type": "Feature",
  "properties": {
    "addr:full":"222 N Main St Hopewell VA 23860",
    "addr:housenumber":"222",
    "addr:postcode":"23860",
    "addr:street":"N Main St",
    "iso:country":"US",
    "sg:address":"222 N Main St",
    "sg:city":"Hopewell",
    "sg:classifiers":[
        {
            "category":"Professional",
            "subcategory":"Lawyer & Legal Services",
            "type":"Services"
        }
    ],
    "sg:phone":"+1 804 541 8960",
    "sg:postcode":"23860",
    "sg:province":"VA",
    "sg:tags":[
        "attorney"
    ],
    "wof:name":"Stephen L Hewlett",
    "wof:placetype":"venue"
},
  "geometry": {"coordinates":[-77.28732599999999,37.303],"type":"Point"}
}