{
  "type": "Feature",
  "properties": {
    "addr:full":"3511 Baileys Crosrds Alexandria VA 22301",
    "addr:housenumber":"3511",
    "addr:postcode":"22301",
    "addr:street":"Baileys Crosrds",
    "iso:country":"US",
    "sg:address":"3511 Baileys Crosrds",
    "sg:city":"Alexandria",
    "sg:classifiers":[
        {
            "category":"Shopping",
            "subcategory":"Computers & Home Electronics",
            "type":"Retail Goods"
        },
        {
            "category":"Professional",
            "subcategory":"Computer Services",
            "type":"Services"
        }
    ],
    "sg:phone":"+1 703 379 8800",
    "sg:postcode":"22301",
    "sg:province":"VA",
    "sg:tags":[
        "stereo",
        "installation"
    ],
    "wof:name":"Myer-Emco Inc",
    "wof:placetype":"venue"
},
  "geometry": {"coordinates":[-77.088143,38.827569],"type":"Point"}
}