{
  "type": "Feature",
  "properties": {
    "iso:country":"US",
    "sg:address":"2107 N Wilson Blvd",
    "sg:city":"Arlington",
    "sg:classifiers":[
        {
            "category":"Professional",
            "type":"Services"
        },
        {
            "category":"Professional",
            "subcategory":"Management & Consulting",
            "type":"Services"
        }
    ],
    "sg:phone":"+1 703 243 5340",
    "sg:postcode":"22201",
    "sg:province":"VA",
    "sg:tags":[
        "business"
    ],
    "wof:name":"Microrate",
    "wof:placetype":"venue"
},
  "geometry": {"coordinates":[-77.085813,38.89132],"type":"Point"}
}