{
  "type": "Feature",
  "properties": {
    "iso:country":"US",
    "sg:address":"8504 Rivermont Dr",
    "sg:city":"Richmond",
    "sg:classifiers":[
        {
            "category":"Professional",
            "subcategory":"Business Services",
            "type":"Services"
        }
    ],
    "sg:phone":"+1 804 303 3301",
    "sg:postcode":"23229",
    "sg:province":"VA",
    "wof:name":"Gxc Home Inspection Services",
    "wof:placetype":"venue"
},
  "geometry": {"coordinates":[-77.56483799999999,37.589703],"type":"Point"}
}