{
  "type": "Feature",
  "properties": {
    "addr:full":"14391 Chalfont Dr Haymarket VA 20169",
    "addr:housenumber":"14391",
    "addr:postcode":"20169",
    "addr:street":"Chalfont Dr",
    "iso:country":"US",
    "sg:address":"14391 Chalfont Dr",
    "sg:city":"Haymarket",
    "sg:classifiers":[
        {
            "category":"Shopping",
            "subcategory":"Jewelry",
            "type":"Retail Goods"
        }
    ],
    "sg:phone":"+1 703 362 7506",
    "sg:postcode":"20169",
    "sg:province":"VA",
    "sg:tags":[
        "jewelery",
        "fine"
    ],
    "wof:name":"Trigon International",
    "wof:placetype":"venue"
},
  "geometry": {"coordinates":[-77.616578,38.825137],"type":"Point"}
}