{
  "type": "Feature",
  "properties": {
    "addr:full":"217 Tarleton Bivouac St Williamsburg VA 23185",
    "addr:housenumber":"217",
    "addr:postcode":"23185",
    "addr:street":"Tarleton Bivouac St",
    "iso:country":"US",
    "sg:address":"217 Tarleton Bivouac St",
    "sg:city":"Williamsburg",
    "sg:classifiers":[
        {
            "category":"Organizations",
            "subcategory":"Religious Organization",
            "type":"Services"
        }
    ],
    "sg:phone":"+1 757 887 9260",
    "sg:postcode":"23185",
    "sg:province":"VA",
    "sg:tags":[
        "clergy"
    ],
    "wof:name":"Douglas N Johnston",
    "wof:placetype":"venue"
},
  "geometry": {"coordinates":[-76.61324,37.211936],"type":"Point"}
}