{
  "type": "Feature",
  "properties": {
    "iso:country":"US",
    "sg:address":"6121 Beech Tree Dr",
    "sg:city":"Alexandria",
    "sg:classifiers":[
        {
            "category":"Retail",
            "subcategory":"Portrait Studio",
            "type":"Services"
        }
    ],
    "sg:phone":"+1 703 960 9142",
    "sg:postcode":"22310",
    "sg:province":"VA",
    "sg:tags":[
        "photo"
    ],
    "wof:name":"Daniel Elza",
    "wof:placetype":"venue"
},
  "geometry": {"coordinates":[-77.090592,38.782245],"type":"Point"}
}