{
  "type": "Feature",
  "properties": {
    "addr:full":"2442 Centre Ave NW Roanoke VA 24017",
    "addr:housenumber":"2442",
    "addr:postcode":"24017",
    "addr:street":"Centre Ave Nw",
    "iso:country":"US",
    "sg:address":"2442 Centre Ave NW",
    "sg:city":"Roanoke",
    "sg:classifiers":[
        {
            "category":"Building & Trades",
            "subcategory":"Construction",
            "type":"Services"
        }
    ],
    "sg:phone":"+1 540 343 4496",
    "sg:postcode":"24017",
    "sg:province":"VA",
    "sg:tags":[
        "roofing",
        "contractor"
    ],
    "wof:name":"A S Pugh Of Roanoke Inc",
    "wof:placetype":"venue"
},
  "geometry": {"coordinates":[-79.97817000000001,37.283331],"type":"Point"}
}