{
  "type": "Feature",
  "properties": {
    "addr:full":"12301 Second Branch Rd Chesterfield VA 23838",
    "addr:housenumber":"12301",
    "addr:postcode":"23838",
    "addr:street":"Second Branch Rd",
    "iso:country":"US",
    "sg:address":"12301 Second Branch Rd",
    "sg:city":"Chesterfield",
    "sg:classifiers":[
        {
            "category":"Manufacturing",
            "subcategory":"Printing",
            "type":"Manufacturing & Wholesale Goods"
        }
    ],
    "sg:phone":"+1 804 639 7613",
    "sg:postcode":"23838",
    "sg:province":"VA",
    "sg:tags":[
        "publishing"
    ],
    "wof:name":"Virginia Portfolio Inc",
    "wof:placetype":"venue"
},
  "geometry": {"coordinates":[-77.633759,37.335346],"type":"Point"}
}