{
  "type": "Feature",
  "properties": {
    "addr:full":"11940 Cherry Rd Fredericksburg VA 22407",
    "addr:housenumber":"11940",
    "addr:postcode":"22407",
    "addr:street":"Cherry Rd",
    "iso:country":"US",
    "sg:address":"11940 Cherry Rd",
    "sg:city":"Fredericksburg",
    "sg:classifiers":[
        {
            "category":"Utilities",
            "subcategory":"Telephone",
            "type":"Services"
        }
    ],
    "sg:phone":"+1 540 786 8349",
    "sg:postcode":"22407",
    "sg:province":"VA",
    "sg:tags":[
        "communications"
    ],
    "wof:name":"Verizon",
    "wof:placetype":"venue"
},
  "geometry": {"coordinates":[-77.55287800000001,38.286901],"type":"Point"}
}