{
  "type": "Feature",
  "properties": {
    "addr:full":"3327 S Amherst Hwy Monroe VA 24574",
    "addr:housenumber":"3327",
    "addr:postcode":"24574",
    "addr:street":"S Amherst Hwy",
    "iso:country":"US",
    "sg:address":"3327 S Amherst Hwy",
    "sg:city":"Monroe",
    "sg:classifiers":[
        {
            "category":"Retail",
            "subcategory":"Veterinary Services",
            "type":"Services"
        }
    ],
    "sg:phone":"+1 434 929 1010",
    "sg:postcode":"24574",
    "sg:province":"VA",
    "sg:tags":[
        "hospital",
        "animal"
    ],
    "wof:name":"Amherst Veterinary Hospital",
    "wof:placetype":"venue"
},
  "geometry": {"coordinates":[-79.124515,37.492233],"type":"Point"}
}