{
  "type": "Feature",
  "properties": {
    "addr:full":"899 Port Republic Rd Harrisonburg VA 22801",
    "addr:housenumber":"899",
    "addr:postcode":"22801",
    "addr:street":"Port Republic Rd",
    "iso:country":"US",
    "sg:address":"899 Port Republic Rd",
    "sg:city":"Harrisonburg",
    "sg:classifiers":[
        {
            "category":"Real Estate",
            "subcategory":"Real Estate Operator",
            "type":"Services"
        }
    ],
    "sg:phone":"+1 540 434 3173",
    "sg:postcode":"22801",
    "sg:province":"VA",
    "sg:tags":[
        "apartment"
    ],
    "wof:name":"Deer Run Apartments",
    "wof:placetype":"venue"
},
  "geometry": {"coordinates":[-78.871275,38.422132],"type":"Point"}
}