{
  "type": "Feature",
  "properties": {
    "iso:country":"US",
    "sg:address":"301 1st St SW",
    "sg:city":"Roanoke",
    "sg:classifiers":[
        {
            "category":"Real Estate",
            "subcategory":"Real Estate Operator",
            "type":"Services"
        }
    ],
    "sg:phone":"+1 540 345 2769",
    "sg:postcode":"24011",
    "sg:province":"VA",
    "sg:tags":[
        "building",
        "parks"
    ],
    "wof:name":"Shenandoah Building Assoc",
    "wof:placetype":"venue"
},
  "geometry": {"coordinates":[-79.942426,37.270548],"type":"Point"}
}