{
  "type": "Feature",
  "properties": {
    "iso:country":"US",
    "sg:address":"3445 Broad Rock Blvd",
    "sg:city":"Richmond",
    "sg:classifiers":[
        {
            "category":"Retail",
            "subcategory":"Auto Repair",
            "type":"Services"
        }
    ],
    "sg:phone":"+1 804 275 8902",
    "sg:postcode":"23234",
    "sg:province":"VA",
    "sg:tags":[
        "repairing",
        "automobile"
    ],
    "wof:name":"Broad Rock Auto Svc",
    "wof:placetype":"venue"
},
  "geometry": {"coordinates":[-77.484709,37.468903],"type":"Point"}
}