{
  "type": "Feature",
  "properties": {
    "addr:full":"5530 Sagefield Dr Harrisonburg VA 22801",
    "addr:housenumber":"5530",
    "addr:postcode":"22801",
    "addr:street":"Sagefield Dr",
    "iso:country":"US",
    "sg:address":"5530 Sagefield Dr",
    "sg:city":"Harrisonburg",
    "sg:classifiers":[
        {
            "category":"Manufacturing",
            "subcategory":"Pet Food",
            "type":"Manufacturing & Wholesale Goods"
        }
    ],
    "sg:phone":"+1 540 434 4909",
    "sg:postcode":"22801",
    "sg:province":"VA",
    "sg:tags":[
        "feed",
        "mfg",
        "prepared"
    ],
    "wof:name":"Eastern Im-Pruv-All",
    "wof:placetype":"venue"
},
  "geometry": {"coordinates":[-78.936228,38.383413],"type":"Point"}
}