{
  "type": "Feature",
  "properties": {
    "iso:country":"US",
    "sg:address":"8430 W Main St",
    "sg:city":"Marshall",
    "sg:classifiers":[
        {
            "category":"Health Services",
            "subcategory":"Clinic",
            "type":"Services"
        }
    ],
    "sg:phone":"+1 540 364 0153",
    "sg:postcode":"20115",
    "sg:province":"VA",
    "wof:name":"Piedmont Nutrition Associates",
    "wof:placetype":"venue"
},
  "geometry": {"coordinates":[-77.860772,38.863281],"type":"Point"}
}