{
  "type": "Feature",
  "properties": {
    "addr:full":"707 E Market St Leesburg VA 20176",
    "addr:housenumber":"707",
    "addr:postcode":"20176",
    "addr:street":"E Market St",
    "iso:country":"US",
    "sg:address":"707 E Market St",
    "sg:city":"Leesburg",
    "sg:classifiers":[
        {
            "category":"Restaurant",
            "type":"Food & Drink"
        }
    ],
    "sg:phone":"+1 703 777 7707",
    "sg:postcode":"20176",
    "sg:province":"VA",
    "sg:tags":[
        "pizza"
    ],
    "sg:website":"http://www.salsnypizza.com",
    "wof:name":"Sal's Ny Pizza",
    "wof:placetype":"venue"
},
  "geometry": {"coordinates":[-77.548731,39.106922],"type":"Point"}
}