{
  "type": "Feature",
  "properties": {
    "addr:full":"120 Falcon Dr Fredericksburg VA 22408",
    "addr:housenumber":"120",
    "addr:postcode":"22408",
    "addr:street":"Falcon Dr",
    "iso:country":"US",
    "sg:address":"120 Falcon Dr",
    "sg:city":"Fredericksburg",
    "sg:classifiers":[
        {
            "category":"Building & Trades",
            "subcategory":"Construction",
            "type":"Services"
        }
    ],
    "sg:phone":"+1 540 834 4663",
    "sg:postcode":"22408",
    "sg:province":"VA",
    "sg:tags":[
        "home",
        "builder"
    ],
    "wof:name":"Down To Earth Homes",
    "wof:placetype":"venue"
},
  "geometry": {"coordinates":[-77.493105,38.256324],"type":"Point"}
}