{
  "type": "Feature",
  "properties": {
    "iso:country":"US",
    "sg:address":"12001 Riverway Rd",
    "sg:city":"Chesterfield",
    "sg:classifiers":[
        {
            "category":"Professional",
            "subcategory":"Business Services",
            "type":"Services"
        }
    ],
    "sg:phone":"+1 804 739 3538",
    "sg:postcode":"23838",
    "sg:province":"VA",
    "wof:name":"Bill Ratliff Rl Est",
    "wof:placetype":"venue"
},
  "geometry": {"coordinates":[-77.66554499999999,37.339394],"type":"Point"}
}