{
  "type": "Feature",
  "properties": {
    "addr:full":"8613 Quarry Rd Manassas VA 20110",
    "addr:housenumber":"8613",
    "addr:postcode":"20110",
    "addr:street":"Quarry Rd",
    "iso:country":"US",
    "sg:address":"8613 Quarry Rd",
    "sg:city":"Manassas",
    "sg:classifiers":[
        {
            "category":"Retail",
            "subcategory":"Repair Shop",
            "type":"Services"
        }
    ],
    "sg:phone":"+1 703 368 7337",
    "sg:postcode":"20110",
    "sg:province":"VA",
    "wof:name":"PWC Oit Nss Radio Service",
    "wof:placetype":"venue"
},
  "geometry": {"coordinates":[-77.458674,38.754567],"type":"Point"}
}