{
  "type": "Feature",
  "properties": {
    "addr:full":"5291 Wellington Rd Gainesville VA 20155",
    "addr:housenumber":"5291",
    "addr:postcode":"20155",
    "addr:street":"Wellington Rd",
    "iso:country":"US",
    "sg:address":"5291 Wellington Rd",
    "sg:city":"Gainesville",
    "sg:classifiers":[
        {
            "category":"Wholesale",
            "subcategory":"Construction Materials",
            "type":"Manufacturing & Wholesale Goods"
        }
    ],
    "sg:phone":"+1 703 754 9009",
    "sg:postcode":"20155",
    "sg:province":"VA",
    "sg:tags":[
        "concrete",
        "mfg"
    ],
    "wof:name":"Old Castle Apg National Inc",
    "wof:placetype":"venue"
},
  "geometry": {"coordinates":[-77.599164,38.795357],"type":"Point"}
}