{
  "type": "Feature",
  "properties": {
    "addr:full":"13005 Lee Jackson Memorial Hwy Fairfax VA 22033",
    "addr:housenumber":"13005",
    "addr:postcode":"22033",
    "addr:street":"Lee Jackson Memorial Hwy",
    "iso:country":"US",
    "sg:address":"13005 Lee Jackson Memorial Hwy",
    "sg:city":"Fairfax",
    "sg:classifiers":[
        {
            "category":"Sports & Exercise",
            "subcategory":"Gym",
            "type":"Entertainment"
        }
    ],
    "sg:phone":"+1 703 263 9777",
    "sg:postcode":"22033",
    "sg:province":"VA",
    "sg:tags":[
        "club",
        "health",
        "studio",
        "gymnasium"
    ],
    "wof:name":"Lady Of America Fitness Ctr",
    "wof:placetype":"venue"
},
  "geometry": {"coordinates":[-77.39568300000001,38.880186],"type":"Point"}
}