{
  "type": "Feature",
  "properties": {
    "addr:full":"5228 Valleypointe Pkwy Roanoke VA 24019",
    "addr:housenumber":"5228",
    "addr:postcode":"24019",
    "addr:street":"Valleypointe Pkwy",
    "iso:country":"US",
    "sg:address":"5228 Valleypointe Pkwy",
    "sg:city":"Roanoke",
    "sg:classifiers":[
        {
            "category":"Insurance",
            "subcategory":"Insurance Agent",
            "type":"Services"
        }
    ],
    "sg:phone":"+1 540 362 1846",
    "sg:postcode":"24019",
    "sg:province":"VA",
    "sg:website":"www.bankerslife.com",
    "wof:name":"Bankers Life & Casualty Co",
    "wof:placetype":"venue"
},
  "geometry": {"coordinates":[-79.987998,37.332823],"type":"Point"}
}