{
  "type": "Feature",
  "properties": {
    "addr:full":"10803 Erin Green Ct Chester VA 23831",
    "addr:housenumber":"10803",
    "addr:postcode":"23831",
    "addr:street":"Erin Green Ct",
    "iso:country":"US",
    "sg:address":"10803 Erin Green Ct",
    "sg:city":"Chester",
    "sg:classifiers":[
        {
            "category":"Organizations",
            "subcategory":"Religious Organization",
            "type":"Services"
        }
    ],
    "sg:phone":"+1 804 748 3973",
    "sg:postcode":"23831",
    "sg:province":"VA",
    "wof:name":"Immanuel Baptist Church",
    "wof:placetype":"venue"
},
  "geometry": {"coordinates":[-77.44451100000001,37.373357],"type":"Point"}
}