{
  "type": "Feature",
  "properties": {
    "addr:full":"3990 Greensboro Rd Ridgeway VA 24148",
    "addr:housenumber":"3990",
    "addr:postcode":"24148",
    "addr:street":"Greensboro Rd",
    "iso:country":"US",
    "sg:address":"3990 Greensboro Rd",
    "sg:city":"Ridgeway",
    "sg:classifiers":[
        {
            "category":"Personal",
            "subcategory":"Tanning Parlor",
            "type":"Services"
        },
        {
            "category":"Personal",
            "type":"Services"
        }
    ],
    "sg:phone":"+1 276 632 8266",
    "sg:postcode":"24148",
    "sg:province":"VA",
    "sg:tags":[
        "salon"
    ],
    "wof:name":"Four Season's Tanning Salon",
    "wof:placetype":"venue"
},
  "geometry": {"coordinates":[-79.85979500000001,36.638171],"type":"Point"}
}