{
  "type": "Feature",
  "properties": {
    "addr:full":"1102 Monticello Rd Charlottesville VA 22902",
    "addr:housenumber":"1102",
    "addr:postcode":"22902",
    "addr:street":"Monticello Rd",
    "iso:country":"US",
    "sg:address":"1102 Monticello Rd",
    "sg:city":"Charlottesville",
    "sg:classifiers":[
        {
            "category":"Government",
            "subcategory":"Office",
            "type":"Public Place"
        }
    ],
    "sg:phone":"+1 434 295 5168",
    "sg:postcode":"22902",
    "sg:province":"VA",
    "sg:tags":[
        "job",
        "m",
        "mfg"
    ],
    "wof:name":"Virginia Industries For Blind",
    "wof:placetype":"venue"
},
  "geometry": {"coordinates":[-78.47287900000001,38.021325],"type":"Point"}
}