{
  "type": "Feature",
  "properties": {
    "iso:country":"US",
    "sg:address":"8203 Guinevere Dr",
    "sg:city":"Annandale",
    "sg:classifiers":[
        {
            "category":"Professional",
            "subcategory":"Advertising",
            "type":"Services"
        }
    ],
    "sg:phone":"+1 703 573 1736",
    "sg:postcode":"22003",
    "sg:province":"VA",
    "wof:name":"Emprise Marketing",
    "wof:placetype":"venue"
},
  "geometry": {"coordinates":[-77.22807899999999,38.848771],"type":"Point"}
}