{
  "type": "Feature",
  "properties": {
    "addr:full":"505 Washington St Portsmouth VA 23704",
    "addr:housenumber":"505",
    "addr:postcode":"23704",
    "addr:street":"Washington St",
    "iso:country":"US",
    "sg:address":"505 Washington St",
    "sg:city":"Portsmouth",
    "sg:classifiers":[
        {
            "category":"Health Services",
            "subcategory":"Clinic",
            "type":"Services"
        }
    ],
    "sg:phone":"+1 757 393 5357",
    "sg:postcode":"23704",
    "sg:province":"VA",
    "sg:tags":[
        "specialty",
        "outpatient"
    ],
    "wof:name":"Behavioral Healthcare Services",
    "wof:placetype":"venue"
},
  "geometry": {"coordinates":[-76.303758,36.83451],"type":"Point"}
}