{
  "type": "Feature",
  "properties": {
    "addr:full":"2432 Matthew Talbot Rd Forest VA 24551",
    "addr:housenumber":"2432",
    "addr:postcode":"24551",
    "addr:street":"Matthew Talbot Rd",
    "iso:country":"US",
    "sg:address":"2432 Matthew Talbot Rd",
    "sg:city":"Forest",
    "sg:classifiers":[
        {
            "category":"Building & Trades",
            "subcategory":"Electrical",
            "type":"Services"
        }
    ],
    "sg:phone":"+1 434 525 6249",
    "sg:postcode":"24551",
    "sg:province":"VA",
    "sg:tags":[
        "electric",
        "contractor"
    ],
    "sg:website":"www.cristelectric.com",
    "wof:name":"Crist Electrical Contractor",
    "wof:placetype":"venue"
},
  "geometry": {"coordinates":[-79.34251,37.319419],"type":"Point"}
}