{
  "type": "Feature",
  "properties": {
    "addr:full":"2510 S Main St Harrisonburg VA 22801",
    "addr:housenumber":"2510",
    "addr:postcode":"22801",
    "addr:street":"S Main St",
    "iso:country":"US",
    "sg:address":"2510 S Main St",
    "sg:city":"Harrisonburg",
    "sg:classifiers":[
        {
            "category":"Wholesale",
            "subcategory":"Auto Parts",
            "type":"Manufacturing & Wholesale Goods"
        }
    ],
    "sg:phone":"+1 540 433 7788",
    "sg:postcode":"22801",
    "sg:province":"VA",
    "wof:name":"Redline Automotive Paint & Sup",
    "wof:placetype":"venue"
},
  "geometry": {"coordinates":[-78.89535100000001,38.418593],"type":"Point"}
}