{
  "type": "Feature",
  "properties": {
    "iso:country":"US",
    "sg:address":"871 Silver Lake Rd",
    "sg:city":"Christiansburg",
    "sg:classifiers":[
        {
            "category":"Building & Trades",
            "subcategory":"Construction",
            "type":"Services"
        }
    ],
    "sg:phone":"+1 540 382 7309",
    "sg:postcode":"24073",
    "sg:province":"VA",
    "sg:tags":[
        "excavation",
        "contractor"
    ],
    "wof:name":"Blevins Contracting",
    "wof:placetype":"venue"
},
  "geometry": {"coordinates":[-80.44740899999999,37.130885],"type":"Point"}
}