{
  "type": "Feature",
  "properties": {
    "addr:full":"12383 James Madison Hwy Orange VA 22960",
    "addr:housenumber":"12383",
    "addr:postcode":"22960",
    "addr:street":"James Madison Hwy",
    "iso:country":"US",
    "sg:address":"12383 James Madison Hwy",
    "sg:city":"Orange",
    "sg:classifiers":[
        {
            "category":"Retail",
            "subcategory":"Auto Rental",
            "type":"Services"
        }
    ],
    "sg:phone":"+1 540 672 6344",
    "sg:postcode":"22960",
    "sg:province":"VA",
    "sg:tags":[
        "renting",
        "automobile"
    ],
    "wof:name":"Enterprise Rent-A-Car",
    "wof:placetype":"venue"
},
  "geometry": {"coordinates":[-78.114102,38.232033],"type":"Point"}
}