{
  "type": "Feature",
  "properties": {
    "addr:full":"9904 Mistyview Ct Glen Allen VA 23060",
    "addr:housenumber":"9904",
    "addr:postcode":"23060",
    "addr:street":"Mistyview Ct",
    "iso:country":"US",
    "sg:address":"9904 Mistyview Ct",
    "sg:city":"Glen Allen",
    "sg:classifiers":[
        {
            "category":"Real Estate",
            "subcategory":"Real Estate Agent",
            "type":"Services"
        }
    ],
    "sg:phone":"+1 804 672 2277",
    "sg:postcode":"23060",
    "sg:province":"VA",
    "wof:name":"Boswell Realty",
    "wof:placetype":"venue"
},
  "geometry": {"coordinates":[-77.50922199999999,37.653145],"type":"Point"}
}