{
  "type": "Feature",
  "properties": {
    "addr:full":"230 Dinges Ln Luray VA 22835",
    "addr:housenumber":"230",
    "addr:postcode":"22835",
    "addr:street":"Dinges Ln",
    "iso:country":"US",
    "sg:address":"230 Dinges Ln",
    "sg:city":"Luray",
    "sg:classifiers":[
        {
            "category":"Professional",
            "type":"Services"
        }
    ],
    "sg:phone":"+1 540 743 6164",
    "sg:postcode":"22835",
    "sg:province":"VA",
    "wof:name":"Jake Heglar",
    "wof:placetype":"venue"
},
  "geometry": {"coordinates":[-78.425999,38.680573],"type":"Point"}
}