{
  "type": "Feature",
  "properties": {
    "iso:country":"US",
    "sg:address":"6610 Granby St",
    "sg:city":"Norfolk",
    "sg:classifiers":[
        {
            "category":"Arts & Performance",
            "subcategory":"Theater",
            "type":"Entertainment"
        }
    ],
    "sg:phone":"+1 757 451 4517",
    "sg:postcode":"23505",
    "sg:province":"VA",
    "sg:tags":[
        "group"
    ],
    "wof:name":"Stressed Out St Dwellaz LLC",
    "wof:placetype":"venue"
},
  "geometry": {"coordinates":[-76.278113,36.901629],"type":"Point"}
}