{
  "type": "Feature",
  "properties": {
    "addr:full":"2938 Chain Bridge Rd Oakton VA 22124",
    "addr:housenumber":"2938",
    "addr:postcode":"22124",
    "addr:street":"Chain Bridge Rd",
    "iso:country":"US",
    "sg:address":"2938 Chain Bridge Rd",
    "sg:city":"Oakton",
    "sg:classifiers":[
        {
            "category":"Banks & Credit Unions",
            "subcategory":"Bank",
            "type":"Services"
        }
    ],
    "sg:phone":"+1 703 255 6485",
    "sg:postcode":"22124",
    "sg:province":"VA",
    "sg:website":"http://www.chevychasebank.com",
    "wof:name":"Chevy Chase Bank, F.S.B.",
    "wof:placetype":"venue"
},
  "geometry": {"coordinates":[-77.300743,38.881124],"type":"Point"}
}