{
  "type": "Feature",
  "properties": {
    "addr:full":"17326 Sligo Loop Dumfries VA 22026",
    "addr:housenumber":"17326",
    "addr:postcode":"22026",
    "addr:street":"Sligo Loop",
    "iso:country":"US",
    "sg:address":"17326 Sligo Loop",
    "sg:city":"Dumfries",
    "sg:classifiers":[
        {
            "category":"Building & Trades",
            "subcategory":"Cleaning & Sanitation",
            "type":"Services"
        }
    ],
    "sg:phone":"+1 703 445 8125",
    "sg:postcode":"22026",
    "sg:province":"VA",
    "sg:tags":[
        "janitorial"
    ],
    "wof:name":"Mobile Cleaning Professionals",
    "wof:placetype":"venue"
},
  "geometry": {"coordinates":[-77.301766,38.575921],"type":"Point"}
}