{
  "type": "Feature",
  "properties": {
    "addr:full":"407 N Washington St Falls Church VA 22046",
    "addr:housenumber":"407",
    "addr:postcode":"22046",
    "addr:street":"N Washington St",
    "iso:country":"US",
    "sg:address":"407 N Washington St",
    "sg:city":"Falls Church",
    "sg:classifiers":[
        {
            "category":"Professional",
            "subcategory":"Lawyer & Legal Services",
            "type":"Services"
        }
    ],
    "sg:phone":"+1 703 241 1976",
    "sg:postcode":"22046",
    "sg:province":"VA",
    "wof:name":"Law Offices Russell & Russell",
    "wof:placetype":"venue"
},
  "geometry": {"coordinates":[-77.166444,38.885073],"type":"Point"}
}