{
  "type": "Feature",
  "properties": {
    "iso:country":"US",
    "sg:address":"7304 Kenneth Dr",
    "sg:city":"Richmond",
    "sg:classifiers":[
        {
            "category":"Building & Trades",
            "subcategory":"Landscaping Services",
            "type":"Services"
        }
    ],
    "sg:phone":"+1 804 266 3227",
    "sg:postcode":"23228",
    "sg:province":"VA",
    "sg:tags":[
        "landscape"
    ],
    "wof:name":"Green With Envy Landscaping",
    "wof:placetype":"venue"
},
  "geometry": {"coordinates":[-77.48587499999999,37.621955],"type":"Point"}
}