{
  "type": "Feature",
  "properties": {
    "addr:full":"15460 Pungoteague Rd Pungoteague VA 23420",
    "addr:housenumber":"15460",
    "addr:postcode":"23420",
    "addr:street":"Pungoteague Rd",
    "iso:country":"US",
    "sg:address":"15460 Pungoteague Rd",
    "sg:city":"Pungoteague",
    "sg:classifiers":[
        {
            "category":"Building & Trades",
            "subcategory":"Electrical",
            "type":"Services"
        }
    ],
    "sg:phone":"+1 757 442 2811",
    "sg:postcode":"23420",
    "sg:province":"VA",
    "sg:tags":[
        "electric",
        "contractor"
    ],
    "wof:name":"Sterling Electric Inc",
    "wof:placetype":"venue"
},
  "geometry": {"coordinates":[-75.80884399999999,37.624475],"type":"Point"}
}