{
  "type": "Feature",
  "properties": {
    "iso:country":"US",
    "sg:address":"7 E 16th St",
    "sg:city":"Richmond",
    "sg:classifiers":[
        {
            "category":"Shopping",
            "subcategory":"Department Store",
            "type":"Retail Goods"
        }
    ],
    "sg:phone":"+1 804 233 6166",
    "sg:postcode":"23224",
    "sg:province":"VA",
    "sg:tags":[
        "shop"
    ],
    "wof:name":"Family Dollar Store",
    "wof:placetype":"venue"
},
  "geometry": {"coordinates":[-77.44681300000001,37.517895],"type":"Point"}
}