{
  "type": "Feature",
  "properties": {
    "addr:full":"5206 Nine Mile Rd Richmond VA 23223",
    "addr:housenumber":"5206",
    "addr:postcode":"23223",
    "addr:street":"Nine Mile Rd",
    "iso:country":"US",
    "sg:address":"5206 Nine Mile Rd",
    "sg:city":"Richmond",
    "sg:classifiers":[
        {
            "category":"Retail",
            "subcategory":"Self-service Laundry",
            "type":"Services"
        },
        {
            "category":"Retail",
            "subcategory":"Laundry & Dry Cleaning",
            "type":"Services"
        }
    ],
    "sg:phone":"+1 804 328 1398",
    "sg:postcode":"23223",
    "sg:province":"VA",
    "sg:tags":[
        "cleaners",
        "coin"
    ],
    "wof:name":"Happy Cleaners & Coin Laundry",
    "wof:placetype":"venue"
},
  "geometry": {"coordinates":[-77.35805999999999,37.54838],"type":"Point"}
}