{
  "type": "Feature",
  "properties": {
    "addr:full":"26 Georgetown Green Charlottesville VA 22901",
    "addr:housenumber":"26",
    "addr:postcode":"22901",
    "addr:street":"Georgetown Green",
    "iso:country":"US",
    "sg:address":"26 Georgetown Green",
    "sg:city":"Charlottesville",
    "sg:classifiers":[
        {
            "category":"Manufacturing",
            "subcategory":"Printing",
            "type":"Manufacturing & Wholesale Goods"
        }
    ],
    "sg:phone":"+1 434 973 4794",
    "sg:postcode":"22901",
    "sg:province":"VA",
    "sg:tags":[
        "publishing"
    ],
    "wof:name":"Virginia Lab Publishing Inc",
    "wof:placetype":"venue"
},
  "geometry": {"coordinates":[-78.502509,38.072365],"type":"Point"}
}