{
  "type": "Feature",
  "properties": {
    "addr:full":"1032 Peck Rd Richmond VA 23235",
    "addr:housenumber":"1032",
    "addr:postcode":"23235",
    "addr:street":"Peck Rd",
    "iso:country":"US",
    "sg:address":"1032 Peck Rd",
    "sg:city":"Richmond",
    "sg:classifiers":[
        {
            "category":"Real Estate",
            "subcategory":"Architect",
            "type":"Services"
        }
    ],
    "sg:phone":"+1 804 272 1146",
    "sg:postcode":"23235",
    "sg:province":"VA",
    "wof:name":"Carter Design",
    "wof:placetype":"venue"
},
  "geometry": {"coordinates":[-77.548222,37.512042],"type":"Point"}
}