{
  "type": "Feature",
  "properties": {
    "addr:full":"8700 Sudley Rd Manassas VA 20110",
    "addr:housenumber":"8700",
    "addr:postcode":"20110",
    "addr:street":"Sudley Rd",
    "iso:country":"US",
    "sg:address":"8700 Sudley Rd",
    "sg:city":"Manassas",
    "sg:classifiers":[
        {
            "category":"Banks & Credit Unions",
            "subcategory":"Bank",
            "type":"Services"
        }
    ],
    "sg:phone":"+1 703 369 8184",
    "sg:postcode":"20110",
    "sg:province":"VA",
    "wof:name":"PWH Employee Credit Union",
    "wof:placetype":"venue"
},
  "geometry": {"coordinates":[-77.485793,38.768054],"type":"Point"}
}