{
  "type": "Feature",
  "properties": {
    "iso:country":"US",
    "sg:address":"2169 Cunningham Dr",
    "sg:city":"Hampton",
    "sg:classifiers":[
        {
            "category":"Shopping",
            "subcategory":"Gifts & Souvenirs",
            "type":"Retail Goods"
        }
    ],
    "sg:phone":"+1 757 262 0979",
    "sg:postcode":"23666",
    "sg:province":"VA",
    "sg:tags":[
        "shop"
    ],
    "wof:name":"T & M Gift World",
    "wof:placetype":"venue"
},
  "geometry": {"coordinates":[-76.389912,37.046798],"type":"Point"}
}