{
  "type": "Feature",
  "properties": {
    "iso:country":"US",
    "sg:address":"4750 Valley View Blvd NW",
    "sg:city":"Roanoke",
    "sg:classifiers":[
        {
            "category":"Shopping",
            "subcategory":"Clothing, Apparel, & Fashions",
            "type":"Retail Goods"
        }
    ],
    "sg:phone":"+1 540 563 4479",
    "sg:postcode":"24012",
    "sg:province":"VA",
    "wof:name":"S & K Americas Mens Store",
    "wof:placetype":"venue"
},
  "geometry": {"coordinates":[-79.956034,37.300017],"type":"Point"}
}