{
  "type": "Feature",
  "properties": {
    "iso:country":"US",
    "sg:address":"8402 Sudley Rd",
    "sg:city":"Manassas",
    "sg:classifiers":[
        {
            "category":"Banks & Credit Unions",
            "subcategory":"Bank",
            "type":"Services"
        }
    ],
    "sg:phone":"+1 703 530 7045",
    "sg:postcode":"20109",
    "sg:province":"VA",
    "wof:name":"Patriot Bank",
    "wof:placetype":"venue"
},
  "geometry": {"coordinates":[-77.501364,38.773953],"type":"Point"}
}