{
  "type": "Feature",
  "properties": {
    "addr:full":"1310 Jamestown Rd Williamsburg VA 23185",
    "addr:housenumber":"1310",
    "addr:postcode":"23185",
    "addr:street":"Jamestown Rd",
    "iso:country":"US",
    "sg:address":"1310 Jamestown Rd",
    "sg:city":"Williamsburg",
    "sg:classifiers":[
        {
            "category":"Travel",
            "subcategory":"Travel Agent",
            "type":"Entertainment"
        }
    ],
    "sg:phone":"+1 757 253 2094",
    "sg:postcode":"23185",
    "sg:province":"VA",
    "sg:tags":[
        "operator",
        "tour"
    ],
    "wof:name":"Williamsburg Group Tours",
    "wof:placetype":"venue"
},
  "geometry": {"coordinates":[-76.73337600000001,37.252409],"type":"Point"}
}