{
  "type": "Feature",
  "properties": {
    "iso:country":"US",
    "sg:address":"63 Healms Rd",
    "sg:city":"Bassett",
    "sg:classifiers":[
        {
            "category":"Manufacturing",
            "subcategory":"Lumber",
            "type":"Manufacturing & Wholesale Goods"
        }
    ],
    "sg:phone":"+1 276 629 1600",
    "sg:postcode":"24055",
    "sg:province":"VA",
    "sg:tags":[
        "mill"
    ],
    "wof:name":"Lewis Lumber Mill",
    "wof:placetype":"venue"
},
  "geometry": {"coordinates":[-80.07672100000001,36.744685],"type":"Point"}
}