{
  "type": "Feature",
  "properties": {
    "addr:full":"1608 Campostella Rd Chesapeake VA 23324",
    "addr:housenumber":"1608",
    "addr:postcode":"23324",
    "addr:street":"Campostella Rd",
    "iso:country":"US",
    "sg:address":"1608 Campostella Rd",
    "sg:city":"Chesapeake",
    "sg:classifiers":[
        {
            "category":"Wholesale",
            "subcategory":"Auto Parts",
            "type":"Manufacturing & Wholesale Goods"
        }
    ],
    "sg:phone":"+1 757 545 4442",
    "sg:postcode":"23324",
    "sg:province":"VA",
    "sg:tags":[
        "battery"
    ],
    "sg:website":"www.batteryout.com",
    "wof:name":"Battery Outlet Inc",
    "wof:placetype":"venue"
},
  "geometry": {"coordinates":[-76.268643,36.780593],"type":"Point"}
}