{
  "type": "Feature",
  "properties": {
    "addr:full":"5024 Southpoint Pkwy Fredericksburg VA 22407",
    "addr:housenumber":"5024",
    "addr:postcode":"22407",
    "addr:street":"Southpoint Pkwy",
    "iso:country":"US",
    "sg:address":"5024 Southpoint Pkwy",
    "sg:city":"Fredericksburg",
    "sg:classifiers":[
        {
            "category":"Professional",
            "type":"Services"
        }
    ],
    "sg:phone":"+1 540 834 0010",
    "sg:postcode":"22407",
    "sg:province":"VA",
    "wof:name":"Nelnet",
    "wof:placetype":"venue"
},
  "geometry": {"coordinates":[-77.50017200000001,38.23201],"type":"Point"}
}