{
  "type": "Feature",
  "properties": {
    "addr:full":"5145 Locke Ln Virginia Beach VA 23464",
    "addr:housenumber":"5145",
    "addr:postcode":"23464",
    "addr:street":"Locke Ln",
    "iso:country":"US",
    "sg:address":"5145 Locke Ln",
    "sg:city":"Virginia Beach",
    "sg:classifiers":[
        {
            "category":"Organizations",
            "subcategory":"Religious Organization",
            "type":"Services"
        }
    ],
    "sg:phone":"+1 757 495 4095",
    "sg:postcode":"23464",
    "sg:province":"VA",
    "sg:tags":[
        "church"
    ],
    "wof:name":"Bethel Revival Center",
    "wof:placetype":"venue"
},
  "geometry": {"coordinates":[-76.163518,36.816949],"type":"Point"}
}