{
  "type": "Feature",
  "properties": {
    "addr:full":"2801 Turner Rd Richmond VA 23224",
    "addr:housenumber":"2801",
    "addr:postcode":"23224",
    "addr:street":"Turner Rd",
    "iso:country":"US",
    "sg:address":"2801 Turner Rd",
    "sg:city":"Richmond",
    "sg:phone":"+1 804 745 3276",
    "sg:postcode":"23224",
    "sg:province":"VA",
    "wof:name":"Pocoshock Animal Hospital",
    "wof:placetype":"venue"
},
  "geometry": {"coordinates":[-77.52289500000001,37.46831],"type":"Point"}
}