{
  "type": "Feature",
  "properties": {
    "addr:full":"332 London Bridge Rd Virginia Beach VA 23454",
    "addr:housenumber":"332",
    "addr:postcode":"23454",
    "addr:street":"London Bridge Rd",
    "iso:country":"US",
    "sg:address":"332 London Bridge Rd",
    "sg:city":"Virginia Beach",
    "sg:classifiers":[
        {
            "category":"Shopping",
            "subcategory":"Clothing, Apparel, & Fashions",
            "type":"Retail Goods"
        }
    ],
    "sg:phone":"+1 757 431 1818",
    "sg:postcode":"23454",
    "sg:province":"VA",
    "sg:tags":[
        "tailor"
    ],
    "wof:name":"Wongs Tailor",
    "wof:placetype":"venue"
},
  "geometry": {"coordinates":[-76.052351,36.830713],"type":"Point"}
}