{
  "type": "Feature",
  "properties": {
    "addr:full":"200 High St Portsmouth VA 23704",
    "addr:housenumber":"200",
    "addr:postcode":"23704",
    "addr:street":"High St",
    "iso:country":"US",
    "sg:address":"200 High St",
    "sg:city":"Portsmouth",
    "sg:classifiers":[
        {
            "category":"Professional",
            "subcategory":"Management & Consulting",
            "type":"Services"
        }
    ],
    "sg:phone":"+1 757 622 2312",
    "sg:postcode":"23704",
    "sg:province":"VA",
    "sg:tags":[
        "development",
        "economic"
    ],
    "wof:name":"Hampton Roads Chamber of",
    "wof:placetype":"venue"
},
  "geometry": {"coordinates":[-76.29937099999999,36.835344],"type":"Point"}
}