{
  "type": "Feature",
  "properties": {
    "addr:full":"8624 J D Reading Dr Manassas VA 20109",
    "addr:housenumber":"8624",
    "addr:postcode":"20109",
    "addr:street":"J D Reading Dr",
    "iso:country":"US",
    "sg:address":"8624 J D Reading Dr",
    "sg:city":"Manassas",
    "sg:classifiers":[
        {
            "category":"Manufacturing",
            "subcategory":"Metals",
            "type":"Manufacturing & Wholesale Goods"
        }
    ],
    "sg:phone":"+1 703 335 7800",
    "sg:postcode":"20109",
    "sg:province":"VA",
    "sg:tags":[
        "steel",
        "fabricator"
    ],
    "sg:website":"http://www.wmsi.com",
    "wof:name":"Williams Industries Incorporated",
    "wof:placetype":"venue"
},
  "geometry": {"coordinates":[-77.530278,38.768096],"type":"Point"}
}