{
  "type": "Feature",
  "properties": {
    "addr:full":"14263 Penny Ln Bristol VA 24202",
    "addr:housenumber":"14263",
    "addr:postcode":"24202",
    "addr:street":"Penny Ln",
    "iso:country":"US",
    "sg:address":"14263 Penny Ln",
    "sg:city":"Bristol",
    "sg:classifiers":[
        {
            "category":"Professional",
            "subcategory":"Computer Services",
            "type":"Services"
        }
    ],
    "sg:phone":"+1 276 669 0195",
    "sg:postcode":"24202",
    "sg:province":"VA",
    "sg:tags":[
        "related"
    ],
    "wof:name":"CST Computers",
    "wof:placetype":"venue"
},
  "geometry": {"coordinates":[-82.10350800000001,36.614088],"type":"Point"}
}