{
  "type": "Feature",
  "properties": {
    "iso:country":"US",
    "sg:address":"23 Cricket Ln",
    "sg:city":"Fredericksburg",
    "sg:classifiers":[
        {
            "category":"Freight",
            "type":"Transportation"
        }
    ],
    "sg:phone":"+1 540 752 2681",
    "sg:postcode":"22406",
    "sg:province":"VA",
    "sg:tags":[
        "broker",
        "trucking"
    ],
    "wof:name":"S Burton & Co Inc",
    "wof:placetype":"venue"
},
  "geometry": {"coordinates":[-77.557209,38.364801],"type":"Point"}
}