{
  "type": "Feature",
  "properties": {
    "addr:full":"5500 Pony Farm Dr Richmond VA 23227",
    "addr:housenumber":"5500",
    "addr:postcode":"23227",
    "addr:street":"Pony Farm Dr",
    "iso:country":"US",
    "sg:address":"5500 Pony Farm Dr",
    "sg:city":"Richmond",
    "sg:classifiers":[
        {
            "category":"Real Estate",
            "subcategory":"Real Estate Operator",
            "type":"Services"
        }
    ],
    "sg:phone":"+1 804 321 4840",
    "sg:postcode":"23227",
    "sg:province":"VA",
    "sg:tags":[
        "building",
        "apartment"
    ],
    "wof:name":"Apartment People The",
    "wof:placetype":"venue"
},
  "geometry": {"coordinates":[-77.42770299999999,37.606547],"type":"Point"}
}