{
  "type": "Feature",
  "properties": {
    "addr:full":"9801 Lomond Dr Manassas VA 20109",
    "addr:housenumber":"9801",
    "addr:postcode":"20109",
    "addr:street":"Lomond Dr",
    "iso:country":"US",
    "sg:address":"9801 Lomond Dr",
    "sg:city":"Manassas",
    "sg:classifiers":[
        {
            "category":"Local Transit",
            "type":"Transportation"
        }
    ],
    "sg:phone":"+1 703 335 5500",
    "sg:postcode":"20109",
    "sg:province":"VA",
    "sg:tags":[
        "limousine"
    ],
    "wof:name":"Lancaster Limousine Inc",
    "wof:placetype":"venue"
},
  "geometry": {"coordinates":[-77.491742,38.784361],"type":"Point"}
}