{
  "type": "Feature",
  "properties": {
    "addr:full":"2957 Sand Bend Rd Virginia Beach VA 23456",
    "addr:housenumber":"2957",
    "addr:postcode":"23456",
    "addr:street":"Sand Bend Rd",
    "iso:country":"US",
    "sg:address":"2957 Sand Bend Rd",
    "sg:city":"Virginia Beach",
    "sg:classifiers":[
        {
            "category":"Retail",
            "subcategory":"Veterinary Services",
            "type":"Services"
        }
    ],
    "sg:phone":"+1 757 721 5531",
    "sg:postcode":"23456",
    "sg:province":"VA",
    "wof:name":"Laburnum Veterinary Hospital",
    "wof:placetype":"venue"
},
  "geometry": {"coordinates":[-75.939655,36.72518],"type":"Point"}
}