{
  "type": "Feature",
  "properties": {
    "addr:full":"8260 Willow Oaks Corporate Dr Fairfax VA 22031",
    "addr:housenumber":"8260",
    "addr:postcode":"22031",
    "addr:street":"Willow;Corporate Dr",
    "iso:country":"US",
    "sg:address":"8260 Willow Oaks Corporate Dr",
    "sg:city":"Fairfax",
    "sg:classifiers":[
        {
            "category":"Restaurant",
            "type":"Food & Drink"
        }
    ],
    "sg:phone":"+1 703 560 9173",
    "sg:postcode":"22031",
    "sg:province":"VA",
    "sg:tags":[
        "delicatessen",
        "eating"
    ],
    "wof:name":"Willow Oaks Cafe",
    "wof:placetype":"venue"
},
  "geometry": {"coordinates":[-77.228712,38.863334],"type":"Point"}
}