{
  "type": "Feature",
  "properties": {
    "iso:country":"US",
    "sg:address":"1206 Jolly Pond Rd",
    "sg:city":"Williamsburg",
    "sg:classifiers":[
        {
            "category":"Government",
            "subcategory":"Office",
            "type":"Public Place"
        }
    ],
    "sg:phone":"+1 757 565 0370",
    "sg:postcode":"23188",
    "sg:province":"VA",
    "sg:tags":[
        "village"
    ],
    "wof:name":"Williamsburg Animal Control",
    "wof:placetype":"venue"
},
  "geometry": {"coordinates":[-76.808077,37.333773],"type":"Point"}
}