{
  "type": "Feature",
  "properties": {
    "addr:full":"123 N Main St Galax VA 24333",
    "addr:housenumber":"123",
    "addr:postcode":"24333",
    "addr:street":"N Main St",
    "iso:country":"US",
    "sg:address":"123 N Main St",
    "sg:city":"Galax",
    "sg:classifiers":[
        {
            "category":"Government",
            "subcategory":"Office",
            "type":"Public Place"
        }
    ],
    "sg:phone":"+1 276 236 7883",
    "sg:postcode":"24333",
    "sg:province":"VA",
    "sg:tags":[
        "village"
    ],
    "wof:name":"Galax Recycling Ctr",
    "wof:placetype":"venue"
},
  "geometry": {"coordinates":[-80.92498999999999,36.662544],"type":"Point"}
}