{
  "type": "Feature",
  "properties": {
    "iso:country":"US",
    "sg:address":"478 Cambridge St",
    "sg:city":"Fredericksburg",
    "sg:classifiers":[
        {
            "category":"Professional",
            "type":"Services"
        }
    ],
    "sg:phone":"+1 540 899 9927",
    "sg:postcode":"22405",
    "sg:province":"VA",
    "wof:name":"Familiy Boating Centers Inc",
    "wof:placetype":"venue"
},
  "geometry": {"coordinates":[-77.45912,38.343684],"type":"Point"}
}