{
  "type": "Feature",
  "properties": {
    "addr:full":"240 Joe Carter Rd Danville VA 24541",
    "addr:housenumber":"240",
    "addr:postcode":"24541",
    "addr:street":"Joe Carter Rd",
    "iso:country":"US",
    "sg:address":"240 Joe Carter Rd",
    "sg:city":"Danville",
    "sg:classifiers":[
        {
            "category":"Building & Trades",
            "subcategory":"Construction",
            "type":"Services"
        }
    ],
    "sg:phone":"+1 434 685 3464",
    "sg:postcode":"24541",
    "sg:province":"VA",
    "sg:tags":[
        "house"
    ],
    "wof:name":"Kendrick Construction Co",
    "wof:placetype":"venue"
},
  "geometry": {"coordinates":[-79.61047499999999,36.660571],"type":"Point"}
}