{
  "type": "Feature",
  "properties": {
    "iso:country":"US",
    "sg:address":"9001 W Broad St",
    "sg:city":"Richmond",
    "sg:classifiers":[
        {
            "category":"Retail",
            "subcategory":"Auto Repair",
            "type":"Services"
        }
    ],
    "sg:phone":"+1 804 217 6354",
    "sg:postcode":"23294",
    "sg:province":"VA",
    "sg:tags":[
        "body"
    ],
    "wof:name":"West Broad Collision Center",
    "wof:placetype":"venue"
},
  "geometry": {"coordinates":[-77.54993,37.636371],"type":"Point"}
}