{
  "type": "Feature",
  "properties": {
    "addr:full":"301 E Oxford Ave Alexandria VA 22301",
    "addr:housenumber":"301",
    "addr:postcode":"22301",
    "addr:street":"E Oxford Ave",
    "iso:country":"US",
    "sg:address":"301 E Oxford Ave",
    "sg:city":"Alexandria",
    "sg:classifiers":[
        {
            "category":"Professional",
            "subcategory":"Research",
            "type":"Services"
        }
    ],
    "sg:phone":"+1 703 836 5755",
    "sg:postcode":"22301",
    "sg:province":"VA",
    "sg:tags":[
        "nonphysical",
        "commercial"
    ],
    "wof:name":"Qsr Intelligent Products",
    "wof:placetype":"venue"
},
  "geometry": {"coordinates":[-77.055566,38.827143],"type":"Point"}
}