{
  "type": "Feature",
  "properties": {
    "addr:full":"40 Liberty St Petersburg VA 23803",
    "addr:housenumber":"40",
    "addr:postcode":"23803",
    "addr:street":"Liberty St",
    "iso:country":"US",
    "sg:address":"40 Liberty St",
    "sg:city":"Petersburg",
    "sg:classifiers":[
        {
            "category":"Health Services",
            "subcategory":"Clinic",
            "type":"Services"
        }
    ],
    "sg:phone":"+1 804 733 3960",
    "sg:postcode":"23803",
    "sg:province":"VA",
    "wof:name":"Tri City Family Health Care",
    "wof:placetype":"venue"
},
  "geometry": {"coordinates":[-77.40185,37.223046],"type":"Point"}
}