{
  "type": "Feature",
  "properties": {
    "iso:country":"US",
    "sg:address":"6599 Windham Ave",
    "sg:city":"Alexandria",
    "sg:classifiers":[
        {
            "category":"Building & Trades",
            "subcategory":"Construction",
            "type":"Services"
        }
    ],
    "sg:phone":"+1 703 971 5078",
    "sg:postcode":"22315",
    "sg:province":"VA",
    "sg:tags":[
        "carpentry",
        "contractor"
    ],
    "wof:name":"Woodys Workshop",
    "wof:placetype":"venue"
},
  "geometry": {"coordinates":[-77.16130699999999,38.763467],"type":"Point"}
}