{
  "type": "Feature",
  "properties": {
    "addr:full":"2722 Merrilee Dr Fairfax VA 22031",
    "addr:housenumber":"2722",
    "addr:postcode":"22031",
    "addr:street":"Merrilee Dr",
    "iso:country":"US",
    "sg:address":"2722 Merrilee Dr",
    "sg:city":"Fairfax",
    "sg:classifiers":[
        {
            "category":"Professional",
            "subcategory":"Engineering",
            "type":"Services"
        }
    ],
    "sg:phone":"+1 703 876 5920",
    "sg:postcode":"22031",
    "sg:province":"VA",
    "sg:tags":[
        "computer",
        "programming"
    ],
    "wof:name":"Aera",
    "wof:placetype":"venue"
},
  "geometry": {"coordinates":[-77.230993,38.878397],"type":"Point"}
}