{
  "type": "Feature",
  "properties": {
    "addr:full":"118 Redwing Ln Fries VA 24330",
    "addr:housenumber":"118",
    "addr:postcode":"24330",
    "addr:street":"Redwing Ln",
    "iso:country":"US",
    "sg:address":"118 Redwing Ln",
    "sg:city":"Fries",
    "sg:classifiers":[
        {
            "category":"Shopping",
            "subcategory":"Bicycles & Sporting Goods",
            "type":"Retail Goods"
        }
    ],
    "sg:phone":"+1 276 744 7476",
    "sg:postcode":"24330",
    "sg:province":"VA",
    "wof:name":"Cv S Sport Shop",
    "wof:placetype":"venue"
},
  "geometry": {"coordinates":[-81.043311,36.71139],"type":"Point"}
}