{
  "type": "Feature",
  "properties": {
    "addr:full":"6711 Whittier Ave Ste 101 Mc Lean VA 22101",
    "addr:housenumber":"6711",
    "addr:postcode":"22101",
    "addr:street":"Whittier Ave Ste 101 Mc Lean",
    "iso:country":"US",
    "sg:address":"6711 Whittier Ave Ste 101",
    "sg:city":"Mc Lean",
    "sg:classifiers":[
        {
            "category":"Health Services",
            "subcategory":"Doctor",
            "type":"Services"
        }
    ],
    "sg:phone":"+1 703 356 5722",
    "sg:postcode":"22101",
    "sg:province":"VA",
    "wof:name":"Evers Joseph C MD",
    "wof:placetype":"venue"
},
  "geometry": {"coordinates":[-77.175499,38.931801],"type":"Point"}
}