{
  "type": "Feature",
  "properties": {
    "addr:full":"11003 Three Chopt Rd Richmond VA 23233",
    "addr:housenumber":"11003",
    "addr:postcode":"23233",
    "addr:street":"Three Chopt Rd",
    "iso:country":"US",
    "sg:address":"11003 Three Chopt Rd",
    "sg:city":"Richmond",
    "sg:classifiers":[
        {
            "category":"Social Services",
            "subcategory":"Child Care",
            "type":"Services"
        }
    ],
    "sg:phone":"+1 804 747 0100",
    "sg:postcode":"23233",
    "sg:province":"VA",
    "sg:tags":[
        "agency",
        "employment",
        "day"
    ],
    "wof:name":"Rainbow Station Senior Club",
    "wof:placetype":"venue"
},
  "geometry": {"coordinates":[-77.58805599999999,37.639665],"type":"Point"}
}