{
  "type": "Feature",
  "properties": {
    "iso:country":"US",
    "sg:address":"211 Pennsylvania Ave",
    "sg:city":"Lynchburg",
    "sg:classifiers":[
        {
            "category":"Autos & Motor Vehicles",
            "subcategory":"Automobile Sales",
            "type":"Retail Goods"
        }
    ],
    "sg:phone":"+1 434 846 2525",
    "sg:postcode":"24502",
    "sg:province":"VA",
    "sg:tags":[
        "house",
        "c",
        "construction",
        "used"
    ],
    "wof:name":"Hillcrest Motors",
    "wof:placetype":"venue"
},
  "geometry": {"coordinates":[-79.17822700000001,37.389898],"type":"Point"}
}