{
  "type": "Feature",
  "properties": {
    "addr:full":"5813 Queens Gate Ct Alexandria VA 22303",
    "addr:housenumber":"5813",
    "addr:postcode":"22303",
    "addr:street":"Queens Gate Ct",
    "iso:country":"US",
    "sg:address":"5813 Queens Gate Ct",
    "sg:city":"Alexandria",
    "sg:classifiers":[
        {
            "category":"Shopping",
            "subcategory":"Discount & Variety Stores",
            "type":"Retail Goods"
        }
    ],
    "sg:phone":"+1 703 960 5080",
    "sg:postcode":"22303",
    "sg:province":"VA",
    "sg:tags":[
        "merchandise",
        "general"
    ],
    "wof:name":"Griffin Sales",
    "wof:placetype":"venue"
},
  "geometry": {"coordinates":[-77.09233,38.793517],"type":"Point"}
}