{
  "type": "Feature",
  "properties": {
    "addr:full":"333 W Main St Luray VA 22835",
    "addr:housenumber":"333",
    "addr:postcode":"22835",
    "addr:street":"W Main St",
    "iso:country":"US",
    "sg:address":"333 W Main St",
    "sg:city":"Luray",
    "sg:classifiers":[
        {
            "category":"Social Services",
            "type":"Services"
        }
    ],
    "sg:phone":"+1 540 843 0414",
    "sg:postcode":"22835",
    "sg:province":"VA",
    "wof:name":"Equal Access Inc",
    "wof:placetype":"venue"
},
  "geometry": {"coordinates":[-78.465057,38.665508],"type":"Point"}
}