{
  "type": "Feature",
  "properties": {
    "iso:country":"US",
    "sg:address":"3829 N Upland St",
    "sg:city":"Arlington",
    "sg:classifiers":[
        {
            "category":"Professional",
            "subcategory":"Accounting & Tax Preparation",
            "type":"Services"
        }
    ],
    "sg:phone":"+1 703 534 4427",
    "sg:postcode":"22207",
    "sg:province":"VA",
    "sg:tags":[
        "accountant"
    ],
    "wof:name":"General Business Services",
    "wof:placetype":"venue"
},
  "geometry": {"coordinates":[-77.128304,38.919899],"type":"Point"}
}