{
  "type": "Feature",
  "properties": {
    "addr:full":"3808 Washington Woods Dr Alexandria VA 22309",
    "addr:housenumber":"3808",
    "addr:postcode":"22309",
    "addr:street":"Washington Woods Dr",
    "iso:country":"US",
    "sg:address":"3808 Washington Woods Dr",
    "sg:city":"Alexandria",
    "sg:classifiers":[
        {
            "category":"Real Estate",
            "subcategory":"Real Estate Agent",
            "type":"Services"
        }
    ],
    "sg:phone":"+1 703 799 7317",
    "sg:postcode":"22309",
    "sg:province":"VA",
    "sg:tags":[
        "residential",
        "recreational",
        "agency"
    ],
    "wof:name":"Rbc Enterprises Inc",
    "wof:placetype":"venue"
},
  "geometry": {"coordinates":[-77.09803599999999,38.704468],"type":"Point"}
}