{
  "type": "Feature",
  "properties": {
    "iso:country":"US",
    "sg:address":"888 Lusk St",
    "sg:city":"Chesapeake",
    "sg:classifiers":[
        {
            "category":"Retail",
            "subcategory":"Auto Repair",
            "type":"Services"
        }
    ],
    "sg:phone":"+1 757 424 4496",
    "sg:postcode":"23325",
    "sg:province":"VA",
    "sg:tags":[
        "transmission"
    ],
    "wof:name":"Greenbrier Transmissions Inc",
    "wof:placetype":"venue"
},
  "geometry": {"coordinates":[-76.225739,36.826237],"type":"Point"}
}