{
  "type": "Feature",
  "properties": {
    "addr:full":"12812 Tewksbury Dr Herndon VA 20171",
    "addr:housenumber":"12812",
    "addr:postcode":"20171",
    "addr:street":"Tewksbury Dr",
    "iso:country":"US",
    "sg:address":"12812 Tewksbury Dr",
    "sg:city":"Herndon",
    "sg:classifiers":[
        {
            "category":"Manufacturing",
            "subcategory":"Tools & Machinery",
            "type":"Manufacturing & Wholesale Goods"
        }
    ],
    "sg:phone":"+1 703 476 6787",
    "sg:postcode":"20171",
    "sg:province":"VA",
    "sg:tags":[
        "surgical",
        "mfg"
    ],
    "wof:name":"Sweetpeas By Shafer Dobry",
    "wof:placetype":"venue"
},
  "geometry": {"coordinates":[-77.386393,38.922011],"type":"Point"}
}