{
  "type": "Feature",
  "properties": {
    "iso:country":"US",
    "sg:address":"4708 Waterstone Way",
    "sg:city":"Chesapeake",
    "sg:classifiers":[
        {
            "category":"Building & Trades",
            "subcategory":"Construction",
            "type":"Services"
        }
    ],
    "sg:phone":"+1 757 488 0050",
    "sg:postcode":"23321",
    "sg:province":"VA",
    "sg:tags":[
        "restoration",
        "cleaning",
        "patio",
        "deck"
    ],
    "wof:name":"Fleming's Powerwash Svc",
    "wof:placetype":"venue"
},
  "geometry": {"coordinates":[-76.428302,36.817234],"type":"Point"}
}