{
  "type": "Feature",
  "properties": {
    "addr:full":"24 N Buckmarsh St Berryville VA 22611",
    "addr:housenumber":"24",
    "addr:postcode":"22611",
    "addr:street":"N Buckmarsh St",
    "iso:country":"US",
    "sg:address":"24 N Buckmarsh St",
    "sg:city":"Berryville",
    "sg:classifiers":[
        {
            "category":"Real Estate",
            "subcategory":"Architect",
            "type":"Services"
        }
    ],
    "sg:phone":"+1 540 955 1669",
    "sg:postcode":"22611",
    "sg:province":"VA",
    "sg:tags":[
        "architectural"
    ],
    "sg:website":"www.mainstreetarch.com",
    "wof:name":"Main Street Architecture PC",
    "wof:placetype":"venue"
},
  "geometry": {"coordinates":[-77.982041,39.152231],"type":"Point"}
}