{
  "type": "Feature",
  "properties": {
    "iso:country":"US",
    "sg:address":"1908 Great Falls St",
    "sg:city":"Mc Lean",
    "sg:classifiers":[
        {
            "category":"Professional",
            "subcategory":"Secretarial Services",
            "type":"Services"
        }
    ],
    "sg:phone":"+1 703 821 0899",
    "sg:postcode":"22101",
    "sg:province":"VA",
    "sg:tags":[
        "editor"
    ],
    "wof:name":"Claudia M Russell",
    "wof:placetype":"venue"
},
  "geometry": {"coordinates":[-77.185534,38.913701],"type":"Point"}
}