{
  "type": "Feature",
  "properties": {
    "addr:full":"1934 Old Gallows Rd Vienna VA 22182",
    "addr:housenumber":"1934",
    "addr:postcode":"22182",
    "addr:street":"Old Gallows Rd",
    "iso:country":"US",
    "sg:address":"1934 Old Gallows Rd",
    "sg:city":"Vienna",
    "sg:classifiers":[
        {
            "category":"Shopping",
            "subcategory":"Computers & Home Electronics",
            "type":"Retail Goods"
        }
    ],
    "sg:phone":"+1 703 893 9095",
    "sg:postcode":"22182",
    "sg:province":"VA",
    "sg:tags":[
        "software"
    ],
    "wof:name":"Lockheed Martin Corp",
    "wof:placetype":"venue"
},
  "geometry": {"coordinates":[-77.222618,38.910857],"type":"Point"}
}