{
  "type": "Feature",
  "properties": {
    "addr:full":"1225 Reservoir St Harrisonburg VA 22801",
    "addr:housenumber":"1225",
    "addr:postcode":"22801",
    "addr:street":"Reservoir St",
    "iso:country":"US",
    "sg:address":"1225 Reservoir St",
    "sg:city":"Harrisonburg",
    "sg:classifiers":[
        {
            "category":"Health Services",
            "subcategory":"Nursing And Care Facility",
            "type":"Services"
        }
    ],
    "sg:phone":"+1 540 433 2623",
    "sg:postcode":"22801",
    "sg:province":"VA",
    "sg:tags":[
        "home",
        "convalescent"
    ],
    "sg:website":"www.mfa.net",
    "wof:name":"Camelot Health & Rehab Ctr",
    "wof:placetype":"venue"
},
  "geometry": {"coordinates":[-78.855767,38.439133],"type":"Point"}
}