{
  "type": "Feature",
  "properties": {
    "addr:full":"6631 Wakefield Dr E Alexandria VA 22307",
    "addr:housenumber":"6631",
    "addr:postcode":"22307",
    "addr:street":"Wakefield Dr E",
    "iso:country":"US",
    "sg:address":"6631 Wakefield Dr E",
    "sg:city":"Alexandria",
    "sg:classifiers":[
        {
            "category":"Building & Trades",
            "subcategory":"Construction",
            "type":"Services"
        }
    ],
    "sg:phone":"+1 703 856 4856",
    "sg:postcode":"22307",
    "sg:province":"VA",
    "sg:tags":[
        "wallpaper"
    ],
    "wof:name":"James M Tiner Paperhanging",
    "wof:placetype":"venue"
},
  "geometry": {"coordinates":[-77.05562500000001,38.772671],"type":"Point"}
}