{
  "type": "Feature",
  "properties": {
    "addr:full":"25454 Gum Spring Rd Chantilly VA 20152",
    "addr:housenumber":"25454",
    "addr:postcode":"20152",
    "addr:street":"Gum Spring Rd",
    "iso:country":"US",
    "sg:address":"25454 Gum Spring Rd",
    "sg:city":"Chantilly",
    "sg:classifiers":[
        {
            "category":"Organizations",
            "subcategory":"Religious Organization",
            "type":"Services"
        }
    ],
    "sg:phone":"+1 703 327 6779",
    "sg:postcode":"20152",
    "sg:province":"VA",
    "wof:name":"Korean Presbyterian Church",
    "wof:placetype":"venue"
},
  "geometry": {"coordinates":[-77.544341,38.910469],"type":"Point"}
}