{
  "type": "Feature",
  "properties": {
    "addr:full":"201 W 4th Ave Franklin VA 23851",
    "addr:housenumber":"201",
    "addr:postcode":"23851",
    "addr:street":"W 4Th Ave",
    "iso:country":"US",
    "sg:address":"201 W 4th Ave",
    "sg:city":"Franklin",
    "sg:classifiers":[
        {
            "category":"Shopping",
            "type":"Retail Goods"
        }
    ],
    "sg:phone":"+1 757 562 6411",
    "sg:postcode":"23851",
    "sg:province":"VA",
    "sg:tags":[
        "pool",
        "supply"
    ],
    "wof:name":"Olivers Pools and Spas",
    "wof:placetype":"venue"
},
  "geometry": {"coordinates":[-76.92467499999999,36.678404],"type":"Point"}
}