{
  "type": "Feature",
  "properties": {
    "iso:country":"US",
    "sg:address":"18142 S Railroad Ave",
    "sg:city":"Boykins",
    "sg:classifiers":[
        {
            "category":"Retail",
            "subcategory":"Funeral Services",
            "type":"Services"
        }
    ],
    "sg:phone":"+1 757 654 0700",
    "sg:postcode":"23827",
    "sg:province":"VA",
    "wof:name":"Entrusting Hand Funeral",
    "wof:placetype":"venue"
},
  "geometry": {"coordinates":[-77.20204200000001,36.583454],"type":"Point"}
}