{
  "type": "Feature",
  "properties": {
    "iso:country":"US",
    "sg:address":"816 Hardwood Dr",
    "sg:city":"Chesapeake",
    "sg:classifiers":[
        {
            "category":"Building & Trades",
            "subcategory":"Landscaping Services",
            "type":"Services"
        }
    ],
    "sg:phone":"+1 757 436 7271",
    "sg:postcode":"23320",
    "sg:province":"VA",
    "sg:tags":[
        "lawn"
    ],
    "wof:name":"Al Halls Lawn Service",
    "wof:placetype":"venue"
},
  "geometry": {"coordinates":[-76.27142600000001,36.743512],"type":"Point"}
}