{
  "type": "Feature",
  "properties": {
    "iso:country":"US",
    "sg:address":"102 S Whiting St",
    "sg:city":"Alexandria",
    "sg:classifiers":[
        {
            "category":"Restaurant",
            "type":"Food & Drink"
        }
    ],
    "sg:phone":"+1 703 823 0559",
    "sg:postcode":"22304",
    "sg:province":"VA",
    "wof:name":"Donquixote Sports Bar & Rstrnt",
    "wof:placetype":"venue"
},
  "geometry": {"coordinates":[-77.13687299999999,38.811257],"type":"Point"}
}