{
  "type": "Feature",
  "properties": {
    "iso:country":"US",
    "sg:address":"1427 Cellar Creek Way",
    "sg:city":"Herndon",
    "sg:classifiers":[
        {
            "category":"Professional",
            "subcategory":"Business Services",
            "type":"Services"
        }
    ],
    "sg:phone":"+1 703 450 1420",
    "sg:postcode":"20170",
    "sg:province":"VA",
    "wof:name":"Advantage Home Inspection",
    "wof:placetype":"venue"
},
  "geometry": {"coordinates":[-77.38078,38.993878],"type":"Point"}
}