{
  "type": "Feature",
  "properties": {
    "addr:full":"3601 Shore Dr Virginia Beach VA 23455",
    "addr:housenumber":"3601",
    "addr:postcode":"23455",
    "addr:street":"Shore Dr",
    "iso:country":"US",
    "sg:address":"3601 Shore Dr",
    "sg:city":"Virginia Beach",
    "sg:classifiers":[
        {
            "category":"Professional",
            "subcategory":"Lawyer & Legal Services",
            "type":"Services"
        }
    ],
    "sg:phone":"+1 757 425 7580",
    "sg:postcode":"23455",
    "sg:province":"VA",
    "sg:tags":[
        "attorney"
    ],
    "wof:name":"Philip J Geib",
    "wof:placetype":"venue"
},
  "geometry": {"coordinates":[-76.09680899999999,36.907786],"type":"Point"}
}