{
  "type": "Feature",
  "properties": {
    "addr:full":"1042 Penniman Rd Williamsburg VA 23185",
    "addr:housenumber":"1042",
    "addr:postcode":"23185",
    "addr:street":"Penniman Rd",
    "iso:country":"US",
    "sg:address":"1042 Penniman Rd",
    "sg:city":"Williamsburg",
    "sg:classifiers":[
        {
            "category":"Organizations",
            "subcategory":"Religious Organization",
            "type":"Services"
        }
    ],
    "sg:phone":"+1 757 220 2038",
    "sg:postcode":"23185",
    "sg:province":"VA",
    "wof:name":"Heritage Free Will Bptst Chrch",
    "wof:placetype":"venue"
},
  "geometry": {"coordinates":[-76.667419,37.265168],"type":"Point"}
}