{
  "type": "Feature",
  "properties": {
    "addr:full":"5952 Appleton Ct Virginia Beach VA 23464",
    "addr:housenumber":"5952",
    "addr:postcode":"23464",
    "addr:street":"Appleton Ct",
    "iso:country":"US",
    "sg:address":"5952 Appleton Ct",
    "sg:city":"Virginia Beach",
    "sg:classifiers":[
        {
            "category":"Building & Trades",
            "subcategory":"Landscaping Services",
            "type":"Services"
        }
    ],
    "sg:phone":"+1 757 424 2075",
    "sg:postcode":"23464",
    "sg:province":"VA",
    "wof:name":"Tosi",
    "wof:placetype":"venue"
},
  "geometry": {"coordinates":[-76.202848,36.804964],"type":"Point"}
}