{
  "type": "Feature",
  "properties": {
    "addr:full":"10203 Bent Tree Ln Manassas VA 20111",
    "addr:housenumber":"10203",
    "addr:postcode":"20111",
    "addr:street":"Bent Tree Ln",
    "iso:country":"US",
    "sg:address":"10203 Bent Tree Ln",
    "sg:city":"Manassas",
    "sg:classifiers":[
        {
            "category":"Professional",
            "subcategory":"Business Services",
            "type":"Services"
        }
    ],
    "sg:phone":"+1 703 631 6376",
    "sg:postcode":"20111",
    "sg:province":"VA",
    "wof:name":"Sounds Reasonable",
    "wof:placetype":"venue"
},
  "geometry": {"coordinates":[-77.407228,38.73542],"type":"Point"}
}