{
  "type": "Feature",
  "properties": {
    "iso:country":"US",
    "sg:address":"512 Neal Davis Rd",
    "sg:city":"Ringgold",
    "sg:classifiers":[
        {
            "category":"Building & Trades",
            "subcategory":"Electrical",
            "type":"Services"
        }
    ],
    "sg:phone":"+1 434 822 5936",
    "sg:postcode":"24586",
    "sg:province":"VA",
    "sg:tags":[
        "electrical",
        "contractor"
    ],
    "wof:name":"Harold G Dykes Electrical",
    "wof:placetype":"venue"
},
  "geometry": {"coordinates":[-79.24864100000001,36.622976],"type":"Point"}
}