{
  "type": "Feature",
  "properties": {
    "iso:country":"US",
    "sg:address":"10768 Sudley Manor Dr",
    "sg:city":"Manassas",
    "sg:classifiers":[
        {
            "category":"Shopping",
            "subcategory":"Computers & Home Electronics",
            "type":"Retail Goods"
        }
    ],
    "sg:phone":"+1 703 369 1847",
    "sg:postcode":"20109",
    "sg:province":"VA",
    "sg:website":"www.radioshack.com/",
    "wof:name":"RadioShack",
    "wof:placetype":"venue"
},
  "geometry": {"coordinates":[-77.51950100000001,38.783199],"type":"Point"}
}