{
  "type": "Feature",
  "properties": {
    "addr:full":"201 Stadium Dr Chesapeake VA 23322",
    "addr:housenumber":"201",
    "addr:postcode":"23322",
    "addr:street":"Stadium Dr",
    "iso:country":"US",
    "sg:address":"201 Stadium Dr",
    "sg:city":"Chesapeake",
    "sg:classifiers":[
        {
            "category":"Organizations",
            "subcategory":"Religious Organization",
            "type":"Services"
        }
    ],
    "sg:phone":"+1 757 482 1049",
    "sg:postcode":"23322",
    "sg:province":"VA",
    "sg:tags":[
        "member"
    ],
    "wof:name":"Great Brdge Untd Mthdst Church",
    "wof:placetype":"venue"
},
  "geometry": {"coordinates":[-76.23605999999999,36.706131],"type":"Point"}
}