{
  "type": "Feature",
  "properties": {
    "iso:country":"US",
    "sg:address":"986 Merrimac Ave",
    "sg:city":"Norfolk",
    "sg:classifiers":[
        {
            "category":"Food & Beverages",
            "subcategory":"Groceries & Convenience Stores",
            "type":"Retail Goods"
        }
    ],
    "sg:phone":"+1 757 622 9796",
    "sg:postcode":"23504",
    "sg:province":"VA",
    "wof:name":"Merrimac Market",
    "wof:placetype":"venue"
},
  "geometry": {"coordinates":[-76.252781,36.851796],"type":"Point"}
}