{
  "type": "Feature",
  "properties": {
    "addr:full":"8710 Choctaw Rd Richmond VA 23235",
    "addr:housenumber":"8710",
    "addr:postcode":"23235",
    "addr:street":"Choctaw Rd",
    "iso:country":"US",
    "sg:address":"8710 Choctaw Rd",
    "sg:city":"Richmond",
    "sg:classifiers":[
        {
            "category":"Professional",
            "subcategory":"Management & Consulting",
            "type":"Services"
        }
    ],
    "sg:phone":"+1 804 323 0312",
    "sg:postcode":"23235",
    "sg:province":"VA",
    "sg:tags":[
        "business"
    ],
    "wof:name":"Integrating Wellness Inc",
    "wof:placetype":"venue"
},
  "geometry": {"coordinates":[-77.559219,37.533956],"type":"Point"}
}