{
  "type": "Feature",
  "properties": {
    "iso:country":"US",
    "sg:address":"2700 North Ave",
    "sg:city":"Richmond",
    "sg:classifiers":[
        {
            "category":"Retail",
            "subcategory":"Funeral Services",
            "type":"Services"
        }
    ],
    "sg:phone":"+1 804 321 1100",
    "sg:postcode":"23222",
    "sg:province":"VA",
    "sg:tags":[
        "director"
    ],
    "wof:name":"W S Watkins & Son Funeral Home",
    "wof:placetype":"venue"
},
  "geometry": {"coordinates":[-77.433064,37.567136],"type":"Point"}
}