{
  "type": "Feature",
  "properties": {
    "iso:country":"US",
    "sg:address":"1400 N Uhle St",
    "sg:city":"Arlington",
    "sg:classifiers":[
        {
            "category":"Professional",
            "subcategory":"Lawyer & Legal Services",
            "type":"Services"
        }
    ],
    "sg:phone":"+1 703 525 2260",
    "sg:postcode":"22201",
    "sg:province":"VA",
    "wof:name":"Gettings Brian P Lwyr",
    "wof:placetype":"venue"
},
  "geometry": {"coordinates":[-77.084991,38.889751],"type":"Point"}
}