{
  "type": "Feature",
  "properties": {
    "addr:full":"213 Roy Rd Troutville VA 24175",
    "addr:housenumber":"213",
    "addr:postcode":"24175",
    "addr:street":"Roy Rd",
    "iso:country":"US",
    "sg:address":"213 Roy Rd",
    "sg:city":"Troutville",
    "sg:classifiers":[
        {
            "category":"Retail",
            "subcategory":"Auto Repair",
            "type":"Services"
        }
    ],
    "sg:phone":"+1 540 966 6031",
    "sg:postcode":"24175",
    "sg:province":"VA",
    "sg:tags":[
        "repairing",
        "automobile"
    ],
    "wof:name":"Rodney Waldon",
    "wof:placetype":"venue"
},
  "geometry": {"coordinates":[-79.869517,37.438098],"type":"Point"}
}