{
  "type": "Feature",
  "properties": {
    "iso:country":"US",
    "sg:address":"3012 Brookforest Rd",
    "sg:city":"Midlothian",
    "sg:classifiers":[
        {
            "category":"Wholesale",
            "subcategory":"Office Equipment",
            "type":"Manufacturing & Wholesale Goods"
        }
    ],
    "sg:phone":"+1 804 744 8164",
    "sg:postcode":"23112",
    "sg:province":"VA",
    "wof:name":"CDP Services LLC",
    "wof:placetype":"venue"
},
  "geometry": {"coordinates":[-77.616871,37.449602],"type":"Point"}
}