{
  "type": "Feature",
  "properties": {
    "iso:country":"US",
    "sg:address":"1705 Flag Ct NE",
    "sg:city":"Leesburg",
    "sg:classifiers":[
        {
            "category":"Professional",
            "subcategory":"Business Services",
            "type":"Services"
        }
    ],
    "sg:phone":"+1 703 777 6037",
    "sg:postcode":"20176",
    "sg:province":"VA",
    "wof:name":"MI Interiors",
    "wof:placetype":"venue"
},
  "geometry": {"coordinates":[-77.531814,39.122268],"type":"Point"}
}