{
  "type": "Feature",
  "properties": {
    "iso:country":"US",
    "sg:address":"7549 Centreville Rd",
    "sg:city":"Manassas",
    "sg:classifiers":[
        {
            "category":"Retail",
            "subcategory":"Repair Shop",
            "type":"Services"
        }
    ],
    "sg:phone":"+1 703 330 2772",
    "sg:postcode":"20111",
    "sg:province":"VA",
    "wof:name":"Dominion Arms Corp",
    "wof:placetype":"venue"
},
  "geometry": {"coordinates":[-77.448168,38.790236],"type":"Point"}
}