{
  "type": "Feature",
  "properties": {
    "addr:full":"110 Kingsley Ln Norfolk VA 23505",
    "addr:housenumber":"110",
    "addr:postcode":"23505",
    "addr:street":"Kingsley Ln",
    "iso:country":"US",
    "sg:address":"110 Kingsley Ln",
    "sg:city":"Norfolk",
    "sg:classifiers":[
        {
            "category":"Health Services",
            "subcategory":"Doctor",
            "type":"Services"
        }
    ],
    "sg:phone":"+1 757 889 6520",
    "sg:postcode":"23505",
    "sg:province":"VA",
    "sg:tags":[
        "physician",
        "surgeon"
    ],
    "wof:name":"Family Physicians Of Tidewater",
    "wof:placetype":"venue"
},
  "geometry": {"coordinates":[-76.28168599999999,36.898447],"type":"Point"}
}