{
  "type": "Feature",
  "properties": {
    "iso:country":"US",
    "sg:address":"6800 Paragon Pl",
    "sg:city":"Richmond",
    "sg:classifiers":[
        {
            "category":"Social Services",
            "subcategory":"Job Training",
            "type":"Services"
        }
    ],
    "sg:phone":"+1 804 288 4800",
    "sg:postcode":"23230",
    "sg:province":"VA",
    "sg:tags":[
        "career",
        "counseling",
        "vocational"
    ],
    "wof:name":"Benchmark Prof Careers",
    "wof:placetype":"venue"
},
  "geometry": {"coordinates":[-77.51485,37.60861],"type":"Point"}
}