{
  "type": "Feature",
  "properties": {
    "addr:full":"2708 Cornet St Chesapeake VA 23321",
    "addr:housenumber":"2708",
    "addr:postcode":"23321",
    "addr:street":"Cornet St",
    "iso:country":"US",
    "sg:address":"2708 Cornet St",
    "sg:city":"Chesapeake",
    "sg:classifiers":[
        {
            "category":"Professional",
            "subcategory":"Business Services",
            "type":"Services"
        }
    ],
    "sg:phone":"+1 757 488 7300",
    "sg:postcode":"23321",
    "sg:province":"VA",
    "wof:name":"Solution A Sound",
    "wof:placetype":"venue"
},
  "geometry": {"coordinates":[-76.428039,36.83121],"type":"Point"}
}