{
  "type": "Feature",
  "properties": {
    "addr:full":"2400 Valley Ave Winchester VA 22601",
    "addr:housenumber":"2400",
    "addr:postcode":"22601",
    "addr:street":"Valley Ave",
    "iso:country":"US",
    "sg:address":"2400 Valley Ave",
    "sg:city":"Winchester",
    "sg:classifiers":[
        {
            "category":"Professional",
            "subcategory":"Advertising",
            "type":"Services"
        }
    ],
    "sg:phone":"+1 540 667 1133",
    "sg:postcode":"22601",
    "sg:province":"VA",
    "sg:tags":[
        "counselor"
    ],
    "wof:name":"Graphic Service",
    "wof:placetype":"venue"
},
  "geometry": {"coordinates":[-78.18556,39.159266],"type":"Point"}
}