{
  "type": "Feature",
  "properties": {
    "iso:country":"US",
    "sg:address":"1111 Arlington Blvd",
    "sg:city":"Arlington",
    "sg:classifiers":[
        {
            "category":"Professional",
            "subcategory":"Computer Services",
            "type":"Services"
        }
    ],
    "sg:phone":"+1 703 243 1787",
    "sg:postcode":"22209",
    "sg:province":"VA",
    "sg:tags":[
        "related"
    ],
    "wof:name":"Sandil Consulting LLC",
    "wof:placetype":"venue"
},
  "geometry": {"coordinates":[-77.07119400000001,38.892136],"type":"Point"}
}