{
  "type": "Feature",
  "properties": {
    "iso:country":"US",
    "sg:address":"1249 W Broad St",
    "sg:city":"Falls Church",
    "sg:classifiers":[
        {
            "category":"Retail",
            "subcategory":"Veterinary Services",
            "type":"Services"
        }
    ],
    "sg:phone":"+1 703 532 6121",
    "sg:postcode":"22046",
    "sg:province":"VA",
    "sg:tags":[
        "hospital",
        "animal"
    ],
    "wof:name":"Falls Church Animal Hospital",
    "wof:placetype":"venue"
},
  "geometry": {"coordinates":[-77.18924699999999,38.893936],"type":"Point"}
}