{
  "type": "Feature",
  "properties": {
    "addr:full":"8113 Diven St Norfolk VA 23505",
    "addr:housenumber":"8113",
    "addr:postcode":"23505",
    "addr:street":"Diven St",
    "iso:country":"US",
    "sg:address":"8113 Diven St",
    "sg:city":"Norfolk",
    "sg:classifiers":[
        {
            "category":"Education",
            "subcategory":"School",
            "type":"Public Place"
        }
    ],
    "sg:phone":"+1 757 489 5838",
    "sg:postcode":"23505",
    "sg:province":"VA",
    "wof:name":"Blessings",
    "wof:placetype":"venue"
},
  "geometry": {"coordinates":[-76.29462599999999,36.926593],"type":"Point"}
}