{
  "type": "Feature",
  "properties": {
    "iso:country":"US",
    "sg:address":"5393 Wesleyan Dr",
    "sg:city":"Virginia Beach",
    "sg:classifiers":[
        {
            "category":"Personal",
            "subcategory":"Beauty Salon",
            "type":"Services"
        }
    ],
    "sg:phone":"+1 757 456 5333",
    "sg:postcode":"23455",
    "sg:province":"VA",
    "wof:name":"Universal Cuts",
    "wof:placetype":"venue"
},
  "geometry": {"coordinates":[-76.162536,36.869892],"type":"Point"}
}