{
  "type": "Feature",
  "properties": {
    "iso:country":"US",
    "sg:address":"4356 Silverleaf Dr",
    "sg:city":"Virginia Beach",
    "sg:classifiers":[
        {
            "category":"Arts & Performance",
            "subcategory":"Theater",
            "type":"Entertainment"
        }
    ],
    "sg:phone":"+1 757 518 8299",
    "sg:postcode":"23462",
    "sg:province":"VA",
    "sg:tags":[
        "musician"
    ],
    "wof:name":"Valetta J Fellenbaum",
    "wof:placetype":"venue"
},
  "geometry": {"coordinates":[-76.128287,36.821014],"type":"Point"}
}