{
  "type": "Feature",
  "properties": {
    "addr:full":"223 E Virginia Ave Vinton VA 24179",
    "addr:housenumber":"223",
    "addr:postcode":"24179",
    "addr:street":"E Virginia Ave",
    "iso:country":"US",
    "sg:address":"223 E Virginia Ave",
    "sg:city":"Vinton",
    "sg:classifiers":[
        {
            "category":"Professional",
            "subcategory":"Accounting & Tax Preparation",
            "type":"Services"
        }
    ],
    "sg:phone":"+1 540 345 1983",
    "sg:postcode":"24179",
    "sg:province":"VA",
    "sg:tags":[
        "return"
    ],
    "wof:name":"Hampden Hills Tax Service Inc",
    "wof:placetype":"venue"
},
  "geometry": {"coordinates":[-79.89517600000001,37.274514],"type":"Point"}
}