{
  "type": "Feature",
  "properties": {
    "addr:full":"130 Church Ave SW Roanoke VA 24011",
    "addr:housenumber":"130",
    "addr:postcode":"24011",
    "addr:street":"Church Ave Sw",
    "iso:country":"US",
    "sg:address":"130 Church Ave SW",
    "sg:city":"Roanoke",
    "sg:classifiers":[
        {
            "category":"Building & Trades",
            "subcategory":"Construction",
            "type":"Services"
        }
    ],
    "sg:phone":"+1 540 389 6673",
    "sg:postcode":"24011",
    "sg:province":"VA",
    "sg:tags":[
        "commercial"
    ],
    "wof:name":"Pro-Constructors Inc",
    "wof:placetype":"venue"
},
  "geometry": {"coordinates":[-79.943686,37.270497],"type":"Point"}
}