{
  "type": "Feature",
  "properties": {
    "addr:full":"8111 Rose Hill Rd Richmond VA 23229",
    "addr:housenumber":"8111",
    "addr:postcode":"23229",
    "addr:street":"Rose Hill Rd",
    "iso:country":"US",
    "sg:address":"8111 Rose Hill Rd",
    "sg:city":"Richmond",
    "sg:classifiers":[
        {
            "category":"Government",
            "subcategory":"Office",
            "type":"Public Place"
        }
    ],
    "sg:phone":"+1 804 285 4728",
    "sg:postcode":"23229",
    "sg:province":"VA",
    "sg:tags":[
        "general"
    ],
    "wof:name":"Board of Supervisors",
    "wof:placetype":"venue"
},
  "geometry": {"coordinates":[-77.556956,37.572086],"type":"Point"}
}