{
  "type": "Feature",
  "properties": {
    "iso:country":"US",
    "sg:address":"4650 Oakleys Ln",
    "sg:city":"Richmond",
    "sg:classifiers":[
        {
            "category":"Wholesale",
            "subcategory":"Drugs",
            "type":"Manufacturing & Wholesale Goods"
        }
    ],
    "sg:phone":"+1 804 236 0078",
    "sg:postcode":"23231",
    "sg:province":"VA",
    "sg:tags":[
        "establishment"
    ],
    "wof:name":"Wella Sebastian",
    "wof:placetype":"venue"
},
  "geometry": {"coordinates":[-77.343684,37.52751],"type":"Point"}
}