{
  "type": "Feature",
  "properties": {
    "addr:full":"21090 Dulles Town Cir Sterling VA 20166",
    "addr:housenumber":"21090",
    "addr:postcode":"20166",
    "addr:street":"Dulles Town Cir",
    "iso:country":"US",
    "sg:address":"21090 Dulles Town Cir",
    "sg:city":"Sterling",
    "sg:classifiers":[
        {
            "category":"Shopping",
            "subcategory":"Department Store",
            "type":"Retail Goods"
        }
    ],
    "sg:phone":"+1 571 434 4000",
    "sg:postcode":"20166",
    "sg:province":"VA",
    "sg:website":"http://nordstrom.com/",
    "wof:name":"Nordstrom",
    "wof:placetype":"venue"
},
  "geometry": {"coordinates":[-77.419983,39.029709],"type":"Point"}
}