{
  "type": "Feature",
  "properties": {
    "addr:full":"3273 Shore Dr Virginia Beach VA 23451",
    "addr:housenumber":"3273",
    "addr:postcode":"23451",
    "addr:street":"Shore Dr",
    "iso:country":"US",
    "sg:address":"3273 Shore Dr",
    "sg:city":"Virginia Beach",
    "sg:classifiers":[
        {
            "category":"Coffee & Tea",
            "type":"Food & Drink"
        }
    ],
    "sg:menulink":"http://www.allmenus.com/va/virginia-beach/112134-starbucks-coffee/menu/",
    "sg:phone":"+1 757 496 6522",
    "sg:postcode":"23451",
    "sg:province":"VA",
    "sg:tags":[
        "american"
    ],
    "wof:name":"Starbucks Coffee",
    "wof:placetype":"venue"
},
  "geometry": {"coordinates":[-76.086022,36.907335],"type":"Point"}
}