{
  "type": "Feature",
  "properties": {
    "iso:country":"US",
    "sg:address":"7837 Rolling Rd",
    "sg:city":"Springfield",
    "sg:classifiers":[
        {
            "category":"Professional",
            "subcategory":"Management & Consulting",
            "type":"Services"
        }
    ],
    "sg:phone":"+1 703 866 5404",
    "sg:postcode":"22153",
    "sg:province":"VA",
    "sg:tags":[
        "consultant"
    ],
    "wof:name":"Camber Corp",
    "wof:placetype":"venue"
},
  "geometry": {"coordinates":[-77.212255,38.744322],"type":"Point"}
}