{
  "type": "Feature",
  "properties": {
    "addr:full":"805 Lakeview Dr Cross Junction VA 22625",
    "addr:housenumber":"805",
    "addr:postcode":"22625",
    "addr:street":"Lakeview Dr",
    "iso:country":"US",
    "sg:address":"805 Lakeview Dr",
    "sg:city":"Cross Junction",
    "sg:classifiers":[
        {
            "category":"Education",
            "subcategory":"Vocational School",
            "type":"Public Place"
        }
    ],
    "sg:phone":"+1 540 888 8428",
    "sg:postcode":"22625",
    "sg:province":"VA",
    "wof:name":"Blue Rdge Edctl AVI Foundation",
    "wof:placetype":"venue"
},
  "geometry": {"coordinates":[-78.32046,39.31392],"type":"Point"}
}