{
  "type": "Feature",
  "properties": {
    "addr:full":"102 Custer Rd Arlington VA 22211",
    "addr:housenumber":"102",
    "addr:postcode":"22211",
    "addr:street":"Custer Rd",
    "iso:country":"US",
    "sg:address":"102 Custer Rd",
    "sg:city":"Arlington",
    "sg:classifiers":[
        {
            "category":"Government",
            "subcategory":"Office",
            "type":"Public Place"
        }
    ],
    "sg:phone":"+1 703 696 4444",
    "sg:postcode":"22211",
    "sg:province":"VA",
    "sg:tags":[
        "management",
        "financial"
    ],
    "wof:name":"United States Dept of Army",
    "wof:placetype":"venue"
},
  "geometry": {"coordinates":[-77.08076199999999,38.885658],"type":"Point"}
}