{
  "type": "Feature",
  "properties": {
    "addr:full":"30460 Ed St Franklin VA 23851",
    "addr:housenumber":"30460",
    "addr:postcode":"23851",
    "addr:street":"Ed St",
    "iso:country":"US",
    "sg:address":"30460 Ed St",
    "sg:city":"Franklin",
    "sg:classifiers":[
        {
            "category":"Building & Trades",
            "subcategory":"Construction",
            "type":"Services"
        }
    ],
    "sg:phone":"+1 757 562 4493",
    "sg:postcode":"23851",
    "sg:province":"VA",
    "sg:tags":[
        "residential"
    ],
    "wof:name":"Bill & Sharon Doege",
    "wof:placetype":"venue"
},
  "geometry": {"coordinates":[-76.983181,36.705702],"type":"Point"}
}