{
  "type": "Feature",
  "properties": {
    "iso:country":"US",
    "sg:address":"13131 Warwick Blvd",
    "sg:city":"Newport News",
    "sg:classifiers":[
        {
            "category":"Food & Beverages",
            "subcategory":"Groceries & Convenience Stores",
            "type":"Retail Goods"
        }
    ],
    "sg:phone":"+1 757 249 3146",
    "sg:postcode":"23602",
    "sg:province":"VA",
    "wof:name":"7-Eleven",
    "wof:placetype":"venue"
},
  "geometry": {"coordinates":[-76.51593,37.108854],"type":"Point"}
}