{
  "type": "Feature",
  "properties": {
    "addr:full":"12137 Beaver Creek Rd Clifton VA 20124",
    "addr:housenumber":"12137",
    "addr:postcode":"20124",
    "addr:street":"Beaver Creek Rd",
    "iso:country":"US",
    "sg:address":"12137 Beaver Creek Rd",
    "sg:city":"Clifton",
    "sg:classifiers":[
        {
            "category":"Professional",
            "type":"Services"
        }
    ],
    "sg:phone":"+1 703 830 3842",
    "sg:postcode":"20124",
    "sg:province":"VA",
    "wof:name":"Professional Sport Information",
    "wof:placetype":"venue"
},
  "geometry": {"coordinates":[-77.368613,38.761461],"type":"Point"}
}