{
  "type": "Feature",
  "properties": {
    "addr:full":"2447 Sugar Mill Way Herndon VA 20171",
    "addr:housenumber":"2447",
    "addr:postcode":"20171",
    "addr:street":"Sugar Mill Way",
    "iso:country":"US",
    "sg:address":"2447 Sugar Mill Way",
    "sg:city":"Herndon",
    "sg:classifiers":[
        {
            "category":"Professional",
            "subcategory":"Business Services",
            "type":"Services"
        }
    ],
    "sg:phone":"+1 703 793 1852",
    "sg:postcode":"20171",
    "sg:province":"VA",
    "wof:name":"Goldstone Technologies Ltd",
    "wof:placetype":"venue"
},
  "geometry": {"coordinates":[-77.404597,38.946462],"type":"Point"}
}