{
  "type": "Feature",
  "properties": {
    "addr:full":"1888 Stonyman Rd Luray VA 22835",
    "addr:housenumber":"1888",
    "addr:postcode":"22835",
    "addr:street":"Stonyman Rd",
    "iso:country":"US",
    "sg:address":"1888 Stonyman Rd",
    "sg:city":"Luray",
    "sg:classifiers":[
        {
            "category":"Retail",
            "subcategory":"Portrait Studio",
            "type":"Services"
        }
    ],
    "sg:phone":"+1 540 843 4803",
    "sg:postcode":"22835",
    "sg:province":"VA",
    "sg:tags":[
        "photographer",
        "photo"
    ],
    "wof:name":"Torry's Photography Studio",
    "wof:placetype":"venue"
},
  "geometry": {"coordinates":[-78.44339100000001,38.639102],"type":"Point"}
}