{
  "type": "Feature",
  "properties": {
    "addr:full":"120 Edmunds Blvd Halifax VA 24558",
    "addr:housenumber":"120",
    "addr:postcode":"24558",
    "addr:street":"Edmunds Blvd",
    "iso:country":"US",
    "sg:address":"120 Edmunds Blvd",
    "sg:city":"Halifax",
    "sg:classifiers":[
        {
            "category":"Insurance",
            "subcategory":"Insurance Agent",
            "type":"Services"
        }
    ],
    "sg:phone":"+1 434 476 1041",
    "sg:postcode":"24558",
    "sg:province":"VA",
    "wof:name":"Ed Owens Insurance",
    "wof:placetype":"venue"
},
  "geometry": {"coordinates":[-78.92964600000001,36.76594],"type":"Point"}
}