{
  "type": "Feature",
  "properties": {
    "addr:full":"416 Main St Lynchburg VA 24504",
    "addr:housenumber":"416",
    "addr:postcode":"24504",
    "addr:street":"Main St",
    "iso:country":"US",
    "sg:address":"416 Main St",
    "sg:city":"Lynchburg",
    "sg:classifiers":[
        {
            "category":"Education",
            "subcategory":"Dance Studio",
            "type":"Public Place"
        }
    ],
    "sg:phone":"+1 434 845 1598",
    "sg:postcode":"24504",
    "sg:province":"VA",
    "sg:tags":[
        "instruction",
        "dancing"
    ],
    "wof:name":"Assemble",
    "wof:placetype":"venue"
},
  "geometry": {"coordinates":[-79.145335,37.41832],"type":"Point"}
}