{
  "type": "Feature",
  "properties": {
    "iso:country":"US",
    "sg:address":"7507 Colonel Lindsay Dr.",
    "sg:city":"Falls Church",
    "sg:classifiers":[
        {
            "category":"Insurance",
            "subcategory":"Hazard Insurance",
            "type":"Services"
        }
    ],
    "sg:phone":"+1 703 631 2882",
    "sg:postcode":"22043",
    "sg:province":"VA",
    "sg:website":"www.jerrywagnerinsurance.com",
    "wof:name":"Nationwide Insurance Jerry Wagner Agency Falls Church VA",
    "wof:placetype":"venue"
},
  "geometry": {"coordinates":[-77.20528400000001,38.896075],"type":"Point"}
}