{
  "type": "Feature",
  "properties": {
    "iso:country":"US",
    "sg:address":"1611 S Walter Reed Dr",
    "sg:city":"Arlington",
    "sg:classifiers":[
        {
            "category":"Banks & Credit Unions",
            "subcategory":"Investment Brokerage",
            "type":"Services"
        }
    ],
    "sg:phone":"+1 703 920 1960",
    "sg:postcode":"22204",
    "sg:province":"VA",
    "wof:name":"S & K Assets & Investments Inc",
    "wof:placetype":"venue"
},
  "geometry": {"coordinates":[-77.088326,38.856294],"type":"Point"}
}