{
  "type": "Feature",
  "properties": {
    "addr:full":"1121 Arlington Blvd Arlington VA 22209",
    "addr:housenumber":"1121",
    "addr:postcode":"22209",
    "addr:street":"Arlington Blvd",
    "iso:country":"US",
    "sg:address":"1121 Arlington Blvd",
    "sg:city":"Arlington",
    "sg:classifiers":[
        {
            "category":"Building & Trades",
            "subcategory":"Cleaning & Sanitation",
            "type":"Services"
        }
    ],
    "sg:phone":"+1 703 351 9222",
    "sg:postcode":"22209",
    "sg:province":"VA",
    "sg:tags":[
        "butler",
        "maid"
    ],
    "wof:name":"Clean Up Crew",
    "wof:placetype":"venue"
},
  "geometry": {"coordinates":[-77.07108599999999,38.89211],"type":"Point"}
}