{
  "type": "Feature",
  "properties": {
    "iso:country":"US",
    "sg:address":"2421 Lofurno Rd",
    "sg:city":"Chesapeake",
    "sg:classifiers":[
        {
            "category":"Personal",
            "subcategory":"Beauty Salon",
            "type":"Services"
        }
    ],
    "sg:phone":"+1 757 487 7206",
    "sg:postcode":"23323",
    "sg:province":"VA",
    "sg:tags":[
        "shop"
    ],
    "wof:name":"Diane Beauty Salon",
    "wof:placetype":"venue"
},
  "geometry": {"coordinates":[-76.335382,36.774176],"type":"Point"}
}