{
  "type": "Feature",
  "properties": {
    "addr:full":"1125 N Royal St Alexandria VA 22314",
    "addr:housenumber":"1125",
    "addr:postcode":"22314",
    "addr:street":"N Royal St",
    "iso:country":"US",
    "sg:address":"1125 N Royal St",
    "sg:city":"Alexandria",
    "sg:classifiers":[
        {
            "category":"Professional",
            "type":"Services"
        }
    ],
    "sg:phone":"+1 703 519 8833",
    "sg:postcode":"22314",
    "sg:province":"VA",
    "sg:tags":[
        "caterer"
    ],
    "wof:name":"Sue Fischer A Division of Catering by Windows",
    "wof:placetype":"venue"
},
  "geometry": {"coordinates":[-77.04119900000001,38.8167],"type":"Point"}
}