{
  "type": "Feature",
  "properties": {
    "addr:full":"3504 Chamberlayne Ave Richmond VA 23227",
    "addr:housenumber":"3504",
    "addr:postcode":"23227",
    "addr:street":"Chamberlayne Ave",
    "iso:country":"US",
    "sg:address":"3504 Chamberlayne Ave",
    "sg:city":"Richmond",
    "sg:classifiers":[
        {
            "category":"Professional",
            "subcategory":"Business Services",
            "type":"Services"
        }
    ],
    "sg:phone":"+1 804 355 4518",
    "sg:postcode":"23227",
    "sg:province":"VA",
    "wof:name":"American Dream Enterprises",
    "wof:placetype":"venue"
},
  "geometry": {"coordinates":[-77.446777,37.581459],"type":"Point"}
}