{
  "type": "Feature",
  "properties": {
    "addr:full":"7112 Old Keene Mill Rd Springfield VA 22150",
    "addr:housenumber":"7112",
    "addr:postcode":"22150",
    "addr:street":"Old Keene Mill Rd",
    "iso:country":"US",
    "sg:address":"7112 Old Keene Mill Rd",
    "sg:city":"Springfield",
    "sg:classifiers":[
        {
            "category":"Personal",
            "subcategory":"Barber",
            "type":"Services"
        }
    ],
    "sg:phone":"+1 703 451 9544",
    "sg:postcode":"22150",
    "sg:province":"VA",
    "wof:name":"Jerry's Barber Shop",
    "wof:placetype":"venue"
},
  "geometry": {"coordinates":[-77.1913,38.778368],"type":"Point"}
}