{
  "type": "Feature",
  "properties": {
    "iso:country":"US",
    "sg:address":"1594 Penniman Rd",
    "sg:city":"Williamsburg",
    "sg:classifiers":[
        {
            "category":"Wholesale",
            "subcategory":"Machinery & Supplies",
            "type":"Manufacturing & Wholesale Goods"
        }
    ],
    "sg:phone":"+1 757 220 8480",
    "sg:postcode":"23185",
    "sg:province":"VA",
    "sg:tags":[
        "contractor"
    ],
    "wof:name":"Colonial Powerlift Inc",
    "wof:placetype":"venue"
},
  "geometry": {"coordinates":[-76.645312,37.262779],"type":"Point"}
}