{
  "type": "Feature",
  "properties": {
    "iso:country":"US",
    "sg:address":"3132 Finch Dr",
    "sg:city":"Danville",
    "sg:classifiers":[
        {
            "category":"Shopping",
            "type":"Retail Goods"
        },
        {
            "category":"Wholesale",
            "subcategory":"Durable Goods & Equipment",
            "type":"Manufacturing & Wholesale Goods"
        }
    ],
    "sg:phone":"+1 434 836 1509",
    "sg:postcode":"24540",
    "sg:province":"VA",
    "sg:tags":[
        "monument"
    ],
    "wof:name":"Bruno's Monument Supply Co",
    "wof:placetype":"venue"
},
  "geometry": {"coordinates":[-79.382366,36.663153],"type":"Point"}
}