{
  "type": "Feature",
  "properties": {
    "addr:full":"10443 Pollard Creek Rd Mechanicsville VA 23116",
    "addr:housenumber":"10443",
    "addr:postcode":"23116",
    "addr:street":"Pollard Creek Rd",
    "iso:country":"US",
    "sg:address":"10443 Pollard Creek Rd",
    "sg:city":"Mechanicsville",
    "sg:classifiers":[
        {
            "category":"Professional",
            "type":"Services"
        }
    ],
    "sg:phone":"+1 804 746 1465",
    "sg:postcode":"23116",
    "sg:province":"VA",
    "wof:name":"C M Coiner",
    "wof:placetype":"venue"
},
  "geometry": {"coordinates":[-77.328531,37.694783],"type":"Point"}
}