{
  "type": "Feature",
  "properties": {
    "iso:country":"US",
    "sg:address":"1900 Campus Commons Dr",
    "sg:city":"Reston",
    "sg:classifiers":[
        {
            "category":"Real Estate",
            "subcategory":"Real Estate Agent",
            "type":"Services"
        }
    ],
    "sg:phone":"+1 703 716 9085",
    "sg:postcode":"20191",
    "sg:province":"VA",
    "sg:tags":[
        "operates",
        "as",
        "property",
        "rental",
        "an"
    ],
    "wof:name":"USAA Real Estate Company",
    "wof:placetype":"venue"
},
  "geometry": {"coordinates":[-77.336214,38.944555],"type":"Point"}
}