{
  "type": "Feature",
  "properties": {
    "addr:full":"461 W Reservoir Rd Woodstock VA 22664",
    "addr:housenumber":"461",
    "addr:postcode":"22664",
    "addr:street":"W Reservoir Rd",
    "iso:country":"US",
    "sg:address":"461 W Reservoir Rd",
    "sg:city":"Woodstock",
    "sg:classifiers":[
        {
            "category":"Personal",
            "subcategory":"Beauty Salon",
            "type":"Services"
        }
    ],
    "sg:phone":"+1 540 459 2523",
    "sg:postcode":"22664",
    "sg:province":"VA",
    "wof:name":"Smart Style Family Hair Salon",
    "wof:placetype":"venue"
},
  "geometry": {"coordinates":[-78.53325,38.872698],"type":"Point"}
}