{
  "type": "Feature",
  "properties": {
    "iso:country":"US",
    "sg:address":"33241 Lees Mill Rd",
    "sg:city":"Franklin",
    "sg:classifiers":[
        {
            "category":"Retail",
            "subcategory":"Auto Repair",
            "type":"Services"
        }
    ],
    "sg:phone":"+1 757 562 3471",
    "sg:postcode":"23851",
    "sg:province":"VA",
    "sg:tags":[
        "truck"
    ],
    "wof:name":"Franklin Transportation Corp",
    "wof:placetype":"venue"
},
  "geometry": {"coordinates":[-76.902973,36.68684],"type":"Point"}
}