{
  "type": "Feature",
  "properties": {
    "iso:country":"US",
    "sg:address":"7515 Collins Meade Way",
    "sg:city":"Alexandria",
    "sg:classifiers":[
        {
            "category":"Professional",
            "subcategory":"Management & Consulting",
            "type":"Services"
        }
    ],
    "sg:phone":"+1 703 922 6303",
    "sg:postcode":"22315",
    "sg:province":"VA",
    "sg:tags":[
        "business"
    ],
    "wof:name":"Cce Consulting LLC",
    "wof:placetype":"venue"
},
  "geometry": {"coordinates":[-77.15233000000001,38.755844],"type":"Point"}
}