{
  "type": "Feature",
  "properties": {
    "addr:full":"14478 Store House Dr Centreville VA 20121",
    "addr:housenumber":"14478",
    "addr:postcode":"20121",
    "addr:street":"House Dr",
    "iso:country":"US",
    "sg:address":"14478 Store House Dr",
    "sg:city":"Centreville",
    "sg:classifiers":[
        {
            "category":"Home & Garden",
            "subcategory":"Building Materials",
            "type":"Retail Goods"
        }
    ],
    "sg:phone":"+1 703 802 8311",
    "sg:postcode":"20121",
    "sg:province":"VA",
    "wof:name":"Skillman Window Inc",
    "wof:placetype":"venue"
},
  "geometry": {"coordinates":[-77.44826399999999,38.825644],"type":"Point"}
}