{
  "type": "Feature",
  "properties": {
    "addr:full":"9423 James Madison Hwy Rapidan VA 22733",
    "addr:housenumber":"9423",
    "addr:postcode":"22733",
    "addr:street":"James Madison Hwy Rapidan",
    "iso:country":"US",
    "sg:address":"9423 James Madison Hwy",
    "sg:city":"Rapidan",
    "sg:classifiers":[
        {
            "category":"Communications",
            "subcategory":"Radio Station",
            "type":"Services"
        }
    ],
    "sg:phone":"+1 540 825 2817",
    "sg:postcode":"22733",
    "sg:province":"VA",
    "wof:name":"Education Tomorrow Inc",
    "wof:placetype":"venue"
},
  "geometry": {"coordinates":[-78.07358600000001,38.396926],"type":"Point"}
}