{
  "type": "Feature",
  "properties": {
    "iso:country":"US",
    "sg:address":"101 S Main St",
    "sg:city":"Woodstock",
    "sg:classifiers":[
        {
            "category":"Insurance",
            "subcategory":"Insurance Agent",
            "type":"Services"
        }
    ],
    "sg:phone":"+1 540 459 8888",
    "sg:postcode":"22664",
    "sg:province":"VA",
    "wof:name":"American Gen Lf Accident Insur",
    "wof:placetype":"venue"
},
  "geometry": {"coordinates":[-78.50529400000001,38.88187],"type":"Point"}
}