{
  "type": "Feature",
  "properties": {
    "addr:full":"5557 Holmes Run Pkwy Alexandria VA 22304",
    "addr:housenumber":"5557",
    "addr:postcode":"22304",
    "addr:street":"Holmes Run Pkwy",
    "iso:country":"US",
    "sg:address":"5557 Holmes Run Pkwy",
    "sg:city":"Alexandria",
    "sg:classifiers":[
        {
            "category":"Professional",
            "subcategory":"Computer Services",
            "type":"Services"
        }
    ],
    "sg:phone":"+1 703 201 6900",
    "sg:postcode":"22304",
    "sg:province":"VA",
    "sg:tags":[
        "engineering",
        "robotics",
        "programing"
    ],
    "wof:name":"Lired",
    "wof:placetype":"venue"
},
  "geometry": {"coordinates":[-77.127334,38.820754],"type":"Point"}
}