{
  "type": "Feature",
  "properties": {
    "addr:full":"305 Hooffs Run Dr Alexandria VA 22314",
    "addr:housenumber":"305",
    "addr:postcode":"22314",
    "addr:street":"Hooffs Run Dr",
    "iso:country":"US",
    "sg:address":"305 Hooffs Run Dr",
    "sg:city":"Alexandria",
    "sg:classifiers":[
        {
            "category":"Recreation",
            "type":"Entertainment"
        }
    ],
    "sg:phone":"+1 703 346 8828",
    "sg:postcode":"22314",
    "sg:province":"VA",
    "sg:tags":[
        "karate",
        "judo",
        "instr"
    ],
    "wof:name":"Capital Jiu-Jitsu Team/Royce",
    "wof:placetype":"venue"
},
  "geometry": {"coordinates":[-77.063085,38.798309],"type":"Point"}
}