{
  "type": "Feature",
  "properties": {
    "iso:country":"US",
    "sg:address":"7412 Spring Village Dr",
    "sg:city":"Springfield",
    "sg:classifiers":[
        {
            "category":"Government",
            "subcategory":"Office",
            "type":"Public Place"
        }
    ],
    "sg:phone":"+1 703 644 1744",
    "sg:postcode":"22150",
    "sg:province":"VA",
    "sg:tags":[
        "national",
        "security"
    ],
    "wof:name":"George H Wheeler Chaplin",
    "wof:placetype":"venue"
},
  "geometry": {"coordinates":[-77.20396700000001,38.767283],"type":"Point"}
}