{
  "type": "Feature",
  "properties": {
    "iso:country":"US",
    "sg:address":"1495 High Peak Rd",
    "sg:city":"Monroe",
    "sg:classifiers":[
        {
            "category":"Professional",
            "subcategory":"Business Services",
            "type":"Services"
        }
    ],
    "sg:phone":"+1 434 929 6359",
    "sg:postcode":"24574",
    "sg:province":"VA",
    "sg:tags":[
        "commercial",
        "design"
    ],
    "wof:name":"Dana Thayer Design",
    "wof:placetype":"venue"
},
  "geometry": {"coordinates":[-79.161097,37.582098],"type":"Point"}
}