{
  "type": "Feature",
  "properties": {
    "iso:country":"US",
    "sg:address":"3199 Battlefield Rd",
    "sg:city":"Fishers Hill",
    "sg:classifiers":[
        {
            "category":"Health Services",
            "subcategory":"Clinic",
            "type":"Services"
        }
    ],
    "sg:phone":"+1 540 465 8683",
    "sg:postcode":"22657",
    "sg:province":"VA",
    "wof:name":"Virginias Organ Prcrement Agcy",
    "wof:placetype":"venue"
},
  "geometry": {"coordinates":[-78.39595199999999,38.983181],"type":"Point"}
}