{
  "type": "Feature",
  "properties": {
    "addr:full":"10400 Midlothian Tpke Richmond VA 23235",
    "addr:housenumber":"10400",
    "addr:postcode":"23235",
    "addr:street":"Midlothian Tpke",
    "iso:country":"US",
    "sg:address":"10400 Midlothian Tpke",
    "sg:city":"Richmond",
    "sg:classifiers":[
        {
            "category":"Wholesale",
            "subcategory":"Groceries",
            "type":"Manufacturing & Wholesale Goods"
        }
    ],
    "sg:phone":"+1 804 330 4033",
    "sg:postcode":"23235",
    "sg:province":"VA",
    "sg:tags":[
        "general"
    ],
    "wof:name":"Community Pride Food Brkg Co",
    "wof:placetype":"venue"
},
  "geometry": {"coordinates":[-77.58847799999999,37.507027],"type":"Point"}
}