{
  "type": "Feature",
  "properties": {
    "addr:full":"7105 Devonshire Rd Alexandria VA 22307",
    "addr:housenumber":"7105",
    "addr:postcode":"22307",
    "addr:street":"Devonshire Rd",
    "iso:country":"US",
    "sg:address":"7105 Devonshire Rd",
    "sg:city":"Alexandria",
    "sg:classifiers":[
        {
            "category":"Professional",
            "subcategory":"Lawyer & Legal Services",
            "type":"Services"
        }
    ],
    "sg:phone":"+1 703 768 0994",
    "sg:postcode":"22307",
    "sg:province":"VA",
    "sg:tags":[
        "attorney",
        "practice"
    ],
    "wof:name":"Law Office Of Adam J Cermak",
    "wof:placetype":"venue"
},
  "geometry": {"coordinates":[-77.070251,38.763371],"type":"Point"}
}