{
  "type": "Feature",
  "properties": {
    "iso:country":"US",
    "sg:address":"1100 Westchester Dr",
    "sg:city":"Lynchburg",
    "sg:classifiers":[
        {
            "category":"Retail",
            "subcategory":"Repair Shop",
            "type":"Services"
        }
    ],
    "sg:phone":"+1 434 239 3298",
    "sg:postcode":"24502",
    "sg:province":"VA",
    "sg:tags":[
        "welding"
    ],
    "wof:name":"Bayer Inspection & Training",
    "wof:placetype":"venue"
},
  "geometry": {"coordinates":[-79.190789,37.392797],"type":"Point"}
}