{
  "type": "Feature",
  "properties": {
    "addr:full":"12120 Sunset Hills Rd Reston VA 20190",
    "addr:housenumber":"12120",
    "addr:postcode":"20190",
    "addr:street":"Sunset Hills Rd",
    "iso:country":"US",
    "sg:address":"12120 Sunset Hills Rd",
    "sg:city":"Reston",
    "sg:classifiers":[
        {
            "category":"Professional",
            "subcategory":"Research",
            "type":"Services"
        }
    ],
    "sg:phone":"+1 703 464 6300",
    "sg:postcode":"20190",
    "sg:province":"VA",
    "sg:tags":[
        "development",
        "laboratory"
    ],
    "sg:website":"www.praint.com",
    "wof:name":"PRA International",
    "wof:placetype":"venue"
},
  "geometry": {"coordinates":[-77.366991,38.954246],"type":"Point"}
}