{
  "type": "Feature",
  "properties": {
    "addr:full":"8008 W Broad St Henrico VA 23294",
    "addr:housenumber":"8008",
    "addr:postcode":"23294",
    "addr:street":"W Broad St",
    "iso:country":"US",
    "sg:address":"8008 W Broad St",
    "sg:city":"Henrico",
    "sg:classifiers":[
        {
            "category":"Travel",
            "subcategory":"Hotels & Motels",
            "type":"Entertainment"
        }
    ],
    "sg:phone":"+1 804 346 0000",
    "sg:postcode":"23294",
    "sg:province":"VA",
    "sg:tags":[
        "lodging"
    ],
    "sg:website":"http://www.qualityinn.com/hotel-richmond-virginia-VA846",
    "wof:name":"Quality Inn West End Richmond",
    "wof:placetype":"venue"
},
  "geometry": {"coordinates":[-77.52979499999999,37.624894],"type":"Point"}
}