{
  "type": "Feature",
  "properties": {
    "addr:full":"2000 Cave Ridge Rd Mount Jackson VA 22842",
    "addr:housenumber":"2000",
    "addr:postcode":"22842",
    "addr:street":"Cave Ridge Rd",
    "iso:country":"US",
    "sg:address":"2000 Cave Ridge Rd",
    "sg:city":"Mount Jackson",
    "sg:classifiers":[
        {
            "category":"Professional",
            "subcategory":"Business Services",
            "type":"Services"
        }
    ],
    "sg:phone":"+1 540 477 3066",
    "sg:postcode":"22842",
    "sg:province":"VA",
    "wof:name":"Cabin Hill Drafting",
    "wof:placetype":"venue"
},
  "geometry": {"coordinates":[-78.672929,38.827796],"type":"Point"}
}