{
  "type": "Feature",
  "properties": {
    "addr:full":"372 Fairfax Pike Stephens City VA 22655",
    "addr:housenumber":"372",
    "addr:postcode":"22655",
    "addr:street":"Fairfax Pike",
    "iso:country":"US",
    "sg:address":"372 Fairfax Pike",
    "sg:city":"Stephens City",
    "sg:phone":"+1 540 869 5360",
    "sg:postcode":"22655",
    "sg:province":"VA",
    "sg:tags":[
        "gas"
    ],
    "sg:website":"www.amerigas.com",
    "wof:name":"Ameri Gas Inc",
    "wof:placetype":"venue"
},
  "geometry": {"coordinates":[-78.20451199999999,39.080781],"type":"Point"}
}