{
  "type": "Feature",
  "properties": {
    "iso:country":"US",
    "sg:address":"49 Bowling Store Ln",
    "sg:city":"Stuart",
    "sg:classifiers":[
        {
            "category":"Professional",
            "subcategory":"Computer Services",
            "type":"Services"
        }
    ],
    "sg:phone":"+1 276 930 2164",
    "sg:postcode":"24171",
    "sg:province":"VA",
    "sg:tags":[
        "datum"
    ],
    "wof:name":"ICP Computer Services",
    "wof:placetype":"venue"
},
  "geometry": {"coordinates":[-80.296888,36.743356],"type":"Point"}
}