{
  "type": "Feature",
  "properties": {
    "iso:country":"US",
    "sg:address":"1301 Gaskins Rd",
    "sg:city":"Richmond",
    "sg:classifiers":[
        {
            "category":"Organizations",
            "subcategory":"Religious Organization",
            "type":"Services"
        }
    ],
    "sg:phone":"+1 804 750 1300",
    "sg:postcode":"23238",
    "sg:province":"VA",
    "sg:tags":[
        "church"
    ],
    "wof:name":"St Clare's Episcopal Church",
    "wof:placetype":"venue"
},
  "geometry": {"coordinates":[-77.590833,37.605415],"type":"Point"}
}