{
  "type": "Feature",
  "properties": {
    "addr:full":"1757 Laskin Rd Virginia Beach VA 23454",
    "addr:housenumber":"1757",
    "addr:postcode":"23454",
    "addr:street":"Laskin Rd",
    "iso:country":"US",
    "sg:address":"1757 Laskin Rd",
    "sg:city":"Virginia Beach",
    "sg:classifiers":[
        {
            "category":"Restaurant",
            "type":"Food & Drink"
        }
    ],
    "sg:menulink":"http://www.allmenus.com/va/virginia-beach/32691-outback-steakhouse/menu/",
    "sg:phone":"+1 757 422 5796",
    "sg:postcode":"23454",
    "sg:province":"VA",
    "sg:tags":[
        "american",
        "steakhouse"
    ],
    "wof:name":"Outback Steakhouse",
    "wof:placetype":"venue"
},
  "geometry": {"coordinates":[-76.02587,36.849927],"type":"Point"}
}