{
  "type": "Feature",
  "properties": {
    "iso:country":"US",
    "sg:address":"206 Washington St SW",
    "sg:city":"Blacksburg",
    "sg:classifiers":[
        {
            "category":"Building & Trades",
            "subcategory":"Construction",
            "type":"Services"
        }
    ],
    "sg:phone":"+1 540 552 1004",
    "sg:postcode":"24060",
    "sg:province":"VA",
    "sg:tags":[
        "woodworker"
    ],
    "wof:name":"Green Valley Woodworks",
    "wof:placetype":"venue"
},
  "geometry": {"coordinates":[-80.413326,37.227422],"type":"Point"}
}