{
  "type": "Feature",
  "properties": {
    "addr:full":"220 Jefferson Ridge Pkwy Lynchburg VA 24501",
    "addr:housenumber":"220",
    "addr:postcode":"24501",
    "addr:street":"Jefferson Ridge Pkwy",
    "iso:country":"US",
    "sg:address":"220 Jefferson Ridge Pkwy",
    "sg:city":"Lynchburg",
    "sg:classifiers":[
        {
            "category":"Professional",
            "subcategory":"Engineering",
            "type":"Services"
        }
    ],
    "sg:phone":"+1 434 239 1979",
    "sg:postcode":"24501",
    "sg:province":"VA",
    "sg:tags":[
        "consultant"
    ],
    "wof:name":"Novatech",
    "wof:placetype":"venue"
},
  "geometry": {"coordinates":[-79.23137699999999,37.398737],"type":"Point"}
}