{
  "type": "Feature",
  "properties": {
    "iso:country":"US",
    "sg:address":"2701 Pacific Ave",
    "sg:city":"Virginia Beach",
    "sg:classifiers":[
        {
            "category":"Travel",
            "subcategory":"Hotels & Motels",
            "type":"Entertainment"
        }
    ],
    "sg:phone":"+1 757 428 4926",
    "sg:postcode":"23451",
    "sg:province":"VA",
    "sg:tags":[
        "operation"
    ],
    "wof:name":"Sea Mist Motel",
    "wof:placetype":"venue"
},
  "geometry": {"coordinates":[-75.97849600000001,36.856237],"type":"Point"}
}