{
  "type": "Feature",
  "properties": {
    "iso:country":"US",
    "sg:address":"11326 Zirkle Ln",
    "sg:city":"Broadway",
    "sg:classifiers":[
        {
            "category":"Building & Trades",
            "subcategory":"Construction",
            "type":"Services"
        }
    ],
    "sg:phone":"+1 540 896 4216",
    "sg:postcode":"22815",
    "sg:province":"VA",
    "sg:tags":[
        "contractor"
    ],
    "wof:name":"JC Masonry",
    "wof:placetype":"venue"
},
  "geometry": {"coordinates":[-78.75865400000001,38.577057],"type":"Point"}
}