{
  "type": "Feature",
  "properties": {
    "iso:country":"US",
    "sg:address":"8724 Hickory Rd",
    "sg:city":"Petersburg",
    "sg:classifiers":[
        {
            "category":"Food & Beverages",
            "subcategory":"Groceries & Convenience Stores",
            "type":"Retail Goods"
        }
    ],
    "sg:phone":"+1 804 590 1717",
    "sg:postcode":"23803",
    "sg:province":"VA",
    "sg:tags":[
        "grocer"
    ],
    "wof:name":"Archers Grocery",
    "wof:placetype":"venue"
},
  "geometry": {"coordinates":[-77.52764999999999,37.274497],"type":"Point"}
}