{
  "type": "Feature",
  "properties": {
    "addr:full":"24600 James Monroe Hwy Aldie VA 20105",
    "addr:housenumber":"24600",
    "addr:postcode":"20105",
    "addr:street":"James Monroe Hwy",
    "iso:country":"US",
    "sg:address":"24600 James Monroe Hwy",
    "sg:city":"Aldie",
    "sg:classifiers":[
        {
            "category":"Shopping",
            "subcategory":"Used Merchandise",
            "type":"Retail Goods"
        }
    ],
    "sg:phone":"+1 703 327 4113",
    "sg:postcode":"20105",
    "sg:province":"VA",
    "wof:name":"Bull Run Castle Antiques Inc",
    "wof:placetype":"venue"
},
  "geometry": {"coordinates":[-77.623981,38.937532],"type":"Point"}
}