{
  "type": "Feature",
  "properties": {
    "iso:country":"US",
    "sg:address":"218 Crestway Dr",
    "sg:city":"Chester",
    "sg:classifiers":[
        {
            "category":"Building & Trades",
            "subcategory":"Construction",
            "type":"Services"
        }
    ],
    "sg:phone":"+1 804 768 6984",
    "sg:postcode":"23831",
    "sg:province":"VA",
    "sg:tags":[
        "hanging",
        "contractor"
    ],
    "wof:name":"Spanish Painting",
    "wof:placetype":"venue"
},
  "geometry": {"coordinates":[-77.41104,37.362381],"type":"Point"}
}