{
  "type": "Feature",
  "properties": {
    "iso:country":"US",
    "sg:address":"23064 Banks Rd",
    "sg:city":"Cape Charles",
    "sg:classifiers":[
        {
            "category":"Organizations",
            "subcategory":"Religious Organization",
            "type":"Services"
        }
    ],
    "sg:phone":"+1 757 331 1014",
    "sg:postcode":"23310",
    "sg:province":"VA",
    "wof:name":"Dining Room",
    "wof:placetype":"venue"
},
  "geometry": {"coordinates":[-75.966885,37.269169],"type":"Point"}
}