{
  "type": "Feature",
  "properties": {
    "addr:full":"1435 Roanoke Rd Daleville VA 24083",
    "addr:housenumber":"1435",
    "addr:postcode":"24083",
    "addr:street":"Roanoke Rd",
    "iso:country":"US",
    "sg:address":"1435 Roanoke Rd",
    "sg:city":"Daleville",
    "sg:classifiers":[
        {
            "category":"Education",
            "subcategory":"School",
            "type":"Public Place"
        }
    ],
    "sg:phone":"+1 540 992 1261",
    "sg:postcode":"24083",
    "sg:province":"VA",
    "sg:tags":[
        "secondary"
    ],
    "wof:name":"Lord Botetourt High School",
    "wof:placetype":"venue"
},
  "geometry": {"coordinates":[-79.91391400000001,37.405307],"type":"Point"}
}