{
  "type": "Feature",
  "properties": {
    "addr:full":"61 Jefferson Ave Newport News VA 23607",
    "addr:housenumber":"61",
    "addr:postcode":"23607",
    "addr:street":"Jefferson Ave",
    "iso:country":"US",
    "sg:address":"61 Jefferson Ave",
    "sg:city":"Newport News",
    "sg:classifiers":[
        {
            "category":"Education",
            "subcategory":"School",
            "type":"Public Place"
        }
    ],
    "sg:phone":"+1 757 591 4950",
    "sg:postcode":"23607",
    "sg:province":"VA",
    "wof:name":"Carver Elementary School",
    "wof:placetype":"venue"
},
  "geometry": {"coordinates":[-76.41138599999999,36.965199],"type":"Point"}
}