{
  "type": "Feature",
  "properties": {
    "iso:country":"US",
    "sg:address":"805 Broad St",
    "sg:city":"Portsmouth",
    "sg:classifiers":[
        {
            "category":"Wholesale",
            "subcategory":"Hardware",
            "type":"Manufacturing & Wholesale Goods"
        }
    ],
    "sg:phone":"+1 757 397 9771",
    "sg:postcode":"23707",
    "sg:province":"VA",
    "sg:tags":[
        "fastener"
    ],
    "wof:name":"J J Fasteners Inc",
    "wof:placetype":"venue"
},
  "geometry": {"coordinates":[-76.334733,36.840611],"type":"Point"}
}