{
  "type": "Feature",
  "properties": {
    "addr:full":"313 Meadowville Rd Chester VA 23836",
    "addr:housenumber":"313",
    "addr:postcode":"23836",
    "addr:street":"Meadowville Rd",
    "iso:country":"US",
    "sg:address":"313 Meadowville Rd",
    "sg:city":"Chester",
    "sg:classifiers":[
        {
            "category":"Building & Trades",
            "subcategory":"Construction",
            "type":"Services"
        }
    ],
    "sg:phone":"+1 804 530 2509",
    "sg:postcode":"23836",
    "sg:province":"VA",
    "sg:tags":[
        "residential",
        "commercial",
        "contractor"
    ],
    "wof:name":"B F Matthews Inc",
    "wof:placetype":"venue"
},
  "geometry": {"coordinates":[-77.35080600000001,37.353893],"type":"Point"}
}