{
  "type": "Feature",
  "properties": {
    "iso:country":"US",
    "sg:address":"7664 Fullerton Rd",
    "sg:city":"Springfield",
    "sg:classifiers":[
        {
            "category":"Manufacturing",
            "subcategory":"Printing",
            "type":"Manufacturing & Wholesale Goods"
        }
    ],
    "sg:phone":"+1 703 866 7715",
    "sg:postcode":"22153",
    "sg:province":"VA",
    "sg:tags":[
        "brokerage",
        "commercial",
        "offset"
    ],
    "wof:name":"Ambertone Press Inc",
    "wof:placetype":"venue"
},
  "geometry": {"coordinates":[-77.21124500000001,38.742281],"type":"Point"}
}