{
  "type": "Feature",
  "properties": {
    "addr:full":"1009 Indian Trl Martinsville VA 24112",
    "addr:housenumber":"1009",
    "addr:postcode":"24112",
    "addr:street":"Indian Trl",
    "iso:country":"US",
    "sg:address":"1009 Indian Trl",
    "sg:city":"Martinsville",
    "sg:classifiers":[
        {
            "category":"Real Estate",
            "subcategory":"Real Estate Operator",
            "type":"Services"
        }
    ],
    "sg:phone":"+1 276 656 1196",
    "sg:postcode":"24112",
    "sg:province":"VA",
    "sg:tags":[
        "building",
        "apartment"
    ],
    "wof:name":"109 Pine St",
    "wof:placetype":"venue"
},
  "geometry": {"coordinates":[-79.846428,36.666874],"type":"Point"}
}