{
  "type": "Feature",
  "properties": {
    "addr:full":"109 W Bank St Petersburg VA 23803",
    "addr:housenumber":"109",
    "addr:postcode":"23803",
    "addr:street":"W Bank St",
    "iso:country":"US",
    "sg:address":"109 W Bank St",
    "sg:city":"Petersburg",
    "sg:classifiers":[
        {
            "category":"Personal",
            "type":"Services"
        }
    ],
    "sg:phone":"+1 804 733 0773",
    "sg:postcode":"23803",
    "sg:province":"VA",
    "wof:name":"Ricks Place Inc",
    "wof:placetype":"venue"
},
  "geometry": {"coordinates":[-77.405928,37.231802],"type":"Point"}
}