{
  "type": "Feature",
  "properties": {
    "iso:country":"US",
    "sg:address":"5775 Alum Spring Rd",
    "sg:city":"Pulaski",
    "sg:classifiers":[
        {
            "category":"Building & Trades",
            "subcategory":"Landscaping Services",
            "type":"Services"
        }
    ],
    "sg:phone":"+1 540 980 5945",
    "sg:postcode":"24301",
    "sg:province":"VA",
    "sg:tags":[
        "landscape",
        "contractor"
    ],
    "wof:name":"Gregory Seeding & Landscaping",
    "wof:placetype":"venue"
},
  "geometry": {"coordinates":[-80.78170900000001,37.111528],"type":"Point"}
}