{
  "type": "Feature",
  "properties": {
    "addr:full":"9000 Wyndale Dr Mechanicsville VA 23116",
    "addr:housenumber":"9000",
    "addr:postcode":"23116",
    "addr:street":"Wyndale Dr",
    "iso:country":"US",
    "sg:address":"9000 Wyndale Dr",
    "sg:city":"Mechanicsville",
    "sg:classifiers":[
        {
            "category":"Building & Trades",
            "subcategory":"Construction",
            "type":"Services"
        }
    ],
    "sg:phone":"+1 804 746 0379",
    "sg:postcode":"23116",
    "sg:province":"VA",
    "sg:tags":[
        "masonry",
        "contractor"
    ],
    "wof:name":"Breedlove Dean O Masonry Contr",
    "wof:placetype":"venue"
},
  "geometry": {"coordinates":[-77.40417600000001,37.701029],"type":"Point"}
}