{
  "type": "Feature",
  "properties": {
    "addr:full":"3691 Persimmon Cir Fairfax VA 22031",
    "addr:housenumber":"3691",
    "addr:postcode":"22031",
    "addr:street":"Persimmon Cir",
    "iso:country":"US",
    "sg:address":"3691 Persimmon Cir",
    "sg:city":"Fairfax",
    "sg:classifiers":[
        {
            "category":"Professional",
            "subcategory":"Management & Consulting",
            "type":"Services"
        }
    ],
    "sg:phone":"+1 703 425 5665",
    "sg:postcode":"22031",
    "sg:province":"VA",
    "sg:tags":[
        "marketing",
        "consultant"
    ],
    "wof:name":"Mind's Eye",
    "wof:placetype":"venue"
},
  "geometry": {"coordinates":[-77.268294,38.843764],"type":"Point"}
}