{
  "type": "Feature",
  "properties": {
    "addr:full":"2663 Rockfish Valley Hwy Nellysford VA 22958",
    "addr:postcode":"2663;22958",
    "addr:street":"Valley Hwy Nellysford",
    "iso:country":"US",
    "sg:address":"2663 Rockfish Valley Hwy",
    "sg:city":"Nellysford",
    "sg:classifiers":[
        {
            "category":"Government",
            "subcategory":"Post Office",
            "type":"Public Place"
        }
    ],
    "sg:phone":"+1 434 361 2247",
    "sg:postcode":"22958",
    "sg:province":"VA",
    "wof:name":"US Post Office",
    "wof:placetype":"venue"
},
  "geometry": {"coordinates":[-78.877227,37.887881],"type":"Point"}
}