{
  "type": "Feature",
  "properties": {
    "iso:country":"US",
    "sg:address":"12998 Warwick Blvd",
    "sg:city":"Newport News",
    "sg:classifiers":[
        {
            "category":"Autos & Motor Vehicles",
            "subcategory":"Fuel & Gas Station",
            "type":"Retail Goods"
        }
    ],
    "sg:phone":"+1 757 882 8961",
    "sg:postcode":"23602",
    "sg:province":"VA",
    "sg:tags":[
        "oil"
    ],
    "wof:name":"Oyster Point Exxon",
    "wof:placetype":"venue"
},
  "geometry": {"coordinates":[-76.511162,37.102805],"type":"Point"}
}