{
  "type": "Feature",
  "properties": {
    "addr:full":"4408 Angus Rd Richmond VA 23234",
    "addr:housenumber":"4408",
    "addr:postcode":"23234",
    "addr:street":"Angus Rd",
    "iso:country":"US",
    "sg:address":"4408 Angus Rd",
    "sg:city":"Richmond",
    "sg:classifiers":[
        {
            "category":"Building & Trades",
            "subcategory":"Construction",
            "type":"Services"
        }
    ],
    "sg:phone":"+1 804 651 2045",
    "sg:postcode":"23234",
    "sg:province":"VA",
    "sg:tags":[
        "masonry",
        "contractor"
    ],
    "wof:name":"American Way Masonry",
    "wof:placetype":"venue"
},
  "geometry": {"coordinates":[-77.458719,37.467899],"type":"Point"}
}