{
  "type": "Feature",
  "properties": {
    "iso:country":"US",
    "sg:address":"9314 Old Keene Mill Rd",
    "sg:city":"Burke",
    "sg:classifiers":[
        {
            "category":"Professional",
            "subcategory":"Lawyer & Legal Services",
            "type":"Services"
        }
    ],
    "sg:phone":"+1 703 451 4506",
    "sg:postcode":"22015",
    "sg:province":"VA",
    "sg:tags":[
        "attorney"
    ],
    "sg:website":"www.birmiel.com",
    "wof:name":"Springburke Title & Escrow LTD",
    "wof:placetype":"venue"
},
  "geometry": {"coordinates":[-77.26818900000001,38.776147],"type":"Point"}
}