{
  "type": "Feature",
  "properties": {
    "addr:full":"919 Clifton Trl Crozet VA 22932",
    "addr:housenumber":"919",
    "addr:postcode":"22932",
    "addr:street":"Clifton Trl",
    "iso:country":"US",
    "sg:address":"919 Clifton Trl",
    "sg:city":"Crozet",
    "sg:classifiers":[
        {
            "category":"Professional",
            "type":"Services"
        }
    ],
    "sg:phone":"+1 540 456 6787",
    "sg:postcode":"22932",
    "sg:province":"VA",
    "wof:name":"Bradley Rodgers Dr",
    "wof:placetype":"venue"
},
  "geometry": {"coordinates":[-78.760609,38.059945],"type":"Point"}
}