{
  "type": "Feature",
  "properties": {
    "addr:full":"22539 Timberlake Rd Lynchburg VA 24502",
    "addr:housenumber":"22539",
    "addr:postcode":"24502",
    "addr:street":"Timberlake Rd",
    "iso:country":"US",
    "sg:address":"22539 Timberlake Rd",
    "sg:city":"Lynchburg",
    "sg:classifiers":[
        {
            "category":"Autos & Motor Vehicles",
            "subcategory":"Fuel & Gas Station",
            "type":"Retail Goods"
        }
    ],
    "sg:phone":"+1 434 237 8346",
    "sg:postcode":"24502",
    "sg:province":"VA",
    "sg:tags":[
        "station",
        "gasoline"
    ],
    "wof:name":"Hines Incorporated Angus I",
    "wof:placetype":"venue"
},
  "geometry": {"coordinates":[-79.26047699999999,37.31798],"type":"Point"}
}