{
  "type": "Feature",
  "properties": {
    "iso:country":"US",
    "sg:address":"218 N Lee St Ste 206",
    "sg:city":"Alexandria",
    "sg:classifiers":[
        {
            "category":"Shopping",
            "subcategory":"Clothing, Apparel, & Fashions",
            "type":"Retail Goods"
        },
        {
            "category":"Shopping",
            "subcategory":"Adult",
            "type":"Retail Goods"
        }
    ],
    "sg:phone":"+1 703 836 9441",
    "sg:postcode":"22314",
    "sg:province":"VA",
    "sg:tags":[
        "girdle",
        "lingerie",
        "corset",
        "bra"
    ],
    "wof:name":"The Full Cup & Co",
    "wof:placetype":"venue"
},
  "geometry": {"coordinates":[-77.04111899999999,38.806094],"type":"Point"}
}