{
  "type": "Feature",
  "properties": {
    "addr:full":"5612 Mooretown Rd Williamsburg VA 23188",
    "addr:housenumber":"5612",
    "addr:postcode":"23188",
    "addr:street":"Mooretown Rd",
    "iso:country":"US",
    "sg:address":"5612 Mooretown Rd",
    "sg:city":"Williamsburg",
    "sg:classifiers":[
        {
            "category":"Retail",
            "subcategory":"Auto Repair",
            "type":"Services"
        }
    ],
    "sg:phone":"+1 757 220 3959",
    "sg:postcode":"23188",
    "sg:province":"VA",
    "sg:tags":[
        "automotive"
    ],
    "wof:name":"Ray-Rays",
    "wof:placetype":"venue"
},
  "geometry": {"coordinates":[-76.733812,37.318145],"type":"Point"}
}