{
  "type": "Feature",
  "properties": {
    "addr:full":"2506 Commonwealth Ave Alexandria VA 22301",
    "addr:housenumber":"2506",
    "addr:postcode":"22301",
    "addr:street":"Commonwealth Ave",
    "iso:country":"US",
    "sg:address":"2506 Commonwealth Ave",
    "sg:city":"Alexandria",
    "sg:classifiers":[
        {
            "category":"Health Services",
            "subcategory":"Clinic",
            "type":"Services"
        }
    ],
    "sg:phone":"+1 703 535 5424",
    "sg:postcode":"22301",
    "sg:province":"VA",
    "sg:tags":[
        "specialty",
        "outpatient"
    ],
    "wof:name":"Dupont Therapy Counseling Ctr",
    "wof:placetype":"venue"
},
  "geometry": {"coordinates":[-77.060824,38.828294],"type":"Point"}
}