{
  "type": "Feature",
  "properties": {
    "addr:full":"10811 Hull Street Rd Midlothian VA 23112",
    "addr:housenumber":"10811",
    "addr:postcode":"23112",
    "addr:street":"Hull Street Rd",
    "iso:country":"US",
    "sg:address":"10811 Hull Street Rd",
    "sg:city":"Midlothian",
    "sg:classifiers":[
        {
            "category":"Restaurant",
            "type":"Food & Drink"
        }
    ],
    "sg:phone":"+1 804 745 3357",
    "sg:postcode":"23112",
    "sg:province":"VA",
    "sg:tags":[
        "eating"
    ],
    "wof:name":"Wing Station",
    "wof:placetype":"venue"
},
  "geometry": {"coordinates":[-77.59687700000001,37.438376],"type":"Point"}
}