{
  "type": "Feature",
  "properties": {
    "addr:full":"8115 Old Dominion Dr Mc Lean VA 22102",
    "addr:housenumber":"8115",
    "addr:postcode":"22102",
    "addr:street":"Old Dominion Dr",
    "iso:country":"US",
    "sg:address":"8115 Old Dominion Dr",
    "sg:city":"Mc Lean",
    "sg:classifiers":[
        {
            "category":"Insurance",
            "subcategory":"Insurance Agent",
            "type":"Services"
        }
    ],
    "sg:phone":"+1 703 847 6166",
    "sg:postcode":"22102",
    "sg:province":"VA",
    "wof:name":"State Farm Insurance",
    "wof:placetype":"venue"
},
  "geometry": {"coordinates":[-77.223519,38.951011],"type":"Point"}
}