{
  "type": "Feature",
  "properties": {
    "iso:country":"US",
    "sg:address":"2312 Hatton St",
    "sg:city":"Virginia Beach",
    "sg:classifiers":[
        {
            "category":"Professional",
            "subcategory":"Management & Consulting",
            "type":"Services"
        }
    ],
    "sg:phone":"+1 757 496 7905",
    "sg:postcode":"23451",
    "sg:province":"VA",
    "sg:tags":[
        "protective",
        "coating"
    ],
    "wof:name":"Atlantic Coast Coatings",
    "wof:placetype":"venue"
},
  "geometry": {"coordinates":[-76.060883,36.915132],"type":"Point"}
}