{
  "type": "Feature",
  "properties": {
    "iso:country":"US",
    "sg:address":"18 S Thompson St",
    "sg:city":"Richmond",
    "sg:classifiers":[
        {
            "category":"Professional",
            "type":"Services"
        }
    ],
    "sg:phone":"+1 804 285 9930",
    "sg:postcode":"23221",
    "sg:province":"VA",
    "sg:tags":[
        "establishment"
    ],
    "wof:name":"Clarkson Enterprises",
    "wof:placetype":"venue"
},
  "geometry": {"coordinates":[-77.488873,37.556301],"type":"Point"}
}