{
  "type": "Feature",
  "properties": {
    "addr:full":"1405 Grandin Rd SW Roanoke VA 24015",
    "addr:housenumber":"1405",
    "addr:postcode":"24015",
    "addr:street":"Grandin Rd Sw",
    "iso:country":"US",
    "sg:address":"1405 Grandin Rd SW",
    "sg:city":"Roanoke",
    "sg:classifiers":[
        {
            "category":"Real Estate",
            "subcategory":"Real Estate Agent",
            "type":"Services"
        },
        {
            "category":"Professional",
            "subcategory":"Business Services",
            "type":"Services"
        }
    ],
    "sg:phone":"+1 540 342 4837",
    "sg:postcode":"24015",
    "sg:province":"VA",
    "sg:tags":[
        "appraiser"
    ],
    "wof:name":"Tom Scarce Appraisal Service",
    "wof:placetype":"venue"
},
  "geometry": {"coordinates":[-79.97767399999999,37.263673],"type":"Point"}
}