{
  "type": "Feature",
  "properties": {
    "addr:full":"471 Mink Ridge Ln Mouth Of Wilson VA 24363",
    "addr:housenumber":"471",
    "addr:postcode":"24363",
    "addr:street":"Mink Ridge Ln",
    "iso:country":"US",
    "sg:address":"471 Mink Ridge Ln",
    "sg:city":"Mouth Of Wilson",
    "sg:classifiers":[
        {
            "category":"Health Services",
            "subcategory":"Nursing And Care Facility",
            "type":"Services"
        }
    ],
    "sg:phone":"+1 276 579 2314",
    "sg:postcode":"24363",
    "sg:province":"VA",
    "sg:tags":[
        "skilled"
    ],
    "wof:name":"Nursing Private",
    "wof:placetype":"venue"
},
  "geometry": {"coordinates":[-81.40948,36.634294],"type":"Point"}
}