{
  "type": "Feature",
  "properties": {
    "addr:full":"921 Newtown Rd Virginia Beach VA 23462",
    "addr:housenumber":"921",
    "addr:postcode":"23462",
    "addr:street":"Newtown Rd",
    "iso:country":"US",
    "sg:address":"921 Newtown Rd",
    "sg:city":"Virginia Beach",
    "sg:classifiers":[
        {
            "category":"Retail",
            "subcategory":"Laundry & Dry Cleaning",
            "type":"Services"
        }
    ],
    "sg:phone":"+1 757 473 2299",
    "sg:postcode":"23462",
    "sg:province":"VA",
    "wof:name":"Clean N Bright",
    "wof:placetype":"venue"
},
  "geometry": {"coordinates":[-76.16258999999999,36.865443],"type":"Point"}
}