{
  "type": "Feature",
  "properties": {
    "iso:country":"US",
    "sg:address":"1249 Wilroy Rd",
    "sg:city":"Suffolk",
    "sg:classifiers":[
        {
            "category":"Retail",
            "subcategory":"Auto Repair",
            "type":"Services"
        }
    ],
    "sg:phone":"+1 757 539 2819",
    "sg:postcode":"23434",
    "sg:province":"VA",
    "sg:tags":[
        "body"
    ],
    "wof:name":"Gordons Body Shop",
    "wof:placetype":"venue"
},
  "geometry": {"coordinates":[-76.56144,36.753138],"type":"Point"}
}