{
  "type": "Feature",
  "properties": {
    "iso:country":"US",
    "sg:address":"760 Westover Dr",
    "sg:city":"Danville",
    "sg:classifiers":[
        {
            "category":"Shopping",
            "subcategory":"Music",
            "type":"Retail Goods"
        }
    ],
    "sg:phone":"+1 434 793 1728",
    "sg:postcode":"24541",
    "sg:province":"VA",
    "sg:tags":[
        "compact",
        "record",
        "disc",
        "tape"
    ],
    "wof:name":"Waterloo Music Co",
    "wof:placetype":"venue"
},
  "geometry": {"coordinates":[-79.43908999999999,36.585512],"type":"Point"}
}