{
  "type": "Feature",
  "properties": {
    "iso:country":"US",
    "sg:address":"3011 Peters Creek Rd NW",
    "sg:city":"Roanoke",
    "sg:classifiers":[
        {
            "category":"Real Estate",
            "subcategory":"Real Estate Agent",
            "type":"Services"
        }
    ],
    "sg:phone":"+1 540 562 1165",
    "sg:postcode":"24019",
    "sg:province":"VA",
    "wof:name":"Brammer Village Office Park",
    "wof:placetype":"venue"
},
  "geometry": {"coordinates":[-80.001504,37.318741],"type":"Point"}
}