{
  "type": "Feature",
  "properties": {
    "iso:country":"US",
    "sg:address":"400 Old Franklin Tpke",
    "sg:city":"Rocky Mount",
    "sg:classifiers":[
        {
            "category":"Restaurant",
            "type":"Food & Drink"
        }
    ],
    "sg:phone":"+1 540 489 5004",
    "sg:postcode":"24151",
    "sg:province":"VA",
    "wof:name":"Wendy's",
    "wof:placetype":"venue"
},
  "geometry": {"coordinates":[-79.872327,37.009788],"type":"Point"}
}