{
  "type": "Feature",
  "properties": {
    "addr:full":"400 Old Franklin Tpke Rocky Mount VA 24151",
    "addr:housenumber":"400",
    "addr:postcode":"24151",
    "addr:street":"Old Franklin Tpke",
    "iso:country":"US",
    "sg:address":"400 Old Franklin Tpke",
    "sg:city":"Rocky Mount",
    "sg:classifiers":[
        {
            "category":"Restaurant",
            "type":"Food & Drink"
        }
    ],
    "sg:phone":"+1 540 489 5004",
    "sg:postcode":"24151",
    "sg:province":"VA",
    "wof:name":"Wendy's",
    "wof:placetype":"venue"
},
  "geometry": {"coordinates":[-79.872327,37.009788],"type":"Point"}
}