{
  "type": "Feature",
  "properties": {
    "addr:full":"893 Yorktown Rd Poquoson VA 23662",
    "addr:housenumber":"893",
    "addr:postcode":"23662",
    "addr:street":"Yorktown Rd",
    "iso:country":"US",
    "sg:address":"893 Yorktown Rd",
    "sg:city":"Poquoson",
    "sg:classifiers":[
        {
            "category":"Food & Beverages",
            "subcategory":"Groceries & Convenience Stores",
            "type":"Retail Goods"
        }
    ],
    "sg:phone":"+1 757 868 8336",
    "sg:postcode":"23662",
    "sg:province":"VA",
    "wof:name":"KWIK Pik Grocery",
    "wof:placetype":"venue"
},
  "geometry": {"coordinates":[-76.39394799999999,37.138875],"type":"Point"}
}