{
  "type": "Feature",
  "properties": {
    "addr:full":"1235 S Jefferson Davis Hwy Arlington VA 22202",
    "addr:housenumber":"1235",
    "addr:postcode":"22202",
    "addr:street":"S Jefferson Davis Hwy",
    "iso:country":"US",
    "sg:address":"1235 S Jefferson Davis Hwy",
    "sg:city":"Arlington",
    "sg:classifiers":[
        {
            "category":"Professional",
            "subcategory":"Management & Consulting",
            "type":"Services"
        }
    ],
    "sg:phone":"+1 703 931 6998",
    "sg:postcode":"22202",
    "sg:province":"VA",
    "wof:name":"Global Resource Group",
    "wof:placetype":"venue"
},
  "geometry": {"coordinates":[-77.051778,38.861277],"type":"Point"}
}