{
  "type": "Feature",
  "properties": {
    "addr:full":"103 Cambridge St Fredericksburg VA 22405",
    "addr:housenumber":"103",
    "addr:postcode":"22405",
    "addr:street":"Cambridge St",
    "iso:country":"US",
    "sg:address":"103 Cambridge St",
    "sg:city":"Fredericksburg",
    "sg:classifiers":[
        {
            "category":"Restaurant",
            "type":"Food & Drink"
        }
    ],
    "sg:phone":"+1 540 368 9000",
    "sg:postcode":"22405",
    "sg:province":"VA",
    "wof:name":"Village Cafe At Falmouth",
    "wof:placetype":"venue"
},
  "geometry": {"coordinates":[-77.467488,38.325609],"type":"Point"}
}