{
  "type": "Feature",
  "properties": {
    "iso:country":"US",
    "sg:address":"35 N Royal Ave",
    "sg:city":"Front Royal",
    "sg:classifiers":[
        {
            "category":"Professional",
            "type":"Services"
        }
    ],
    "sg:phone":"+1 540 636 9220",
    "sg:postcode":"22630",
    "sg:province":"VA",
    "wof:name":"High Knob Incorporated",
    "wof:placetype":"venue"
},
  "geometry": {"coordinates":[-78.19355299999999,38.918949],"type":"Point"}
}