{
  "type": "Feature",
  "properties": {
    "addr:full":"1438 Anderson Hwy Powhatan VA 23139",
    "addr:housenumber":"1438",
    "addr:postcode":"23139",
    "addr:street":"Anderson Hwy",
    "iso:country":"US",
    "sg:address":"1438 Anderson Hwy",
    "sg:city":"Powhatan",
    "sg:classifiers":[
        {
            "category":"Building & Trades",
            "subcategory":"Construction",
            "type":"Services"
        }
    ],
    "sg:phone":"+1 804 794 4109",
    "sg:postcode":"23139",
    "sg:province":"VA",
    "sg:tags":[
        "home",
        "improvement"
    ],
    "wof:name":"Layman Irrigation & Trenching",
    "wof:placetype":"venue"
},
  "geometry": {"coordinates":[-77.745025,37.507874],"type":"Point"}
}