{
  "type": "Feature",
  "properties": {
    "addr:full":"1151 Saint Clairs Creek Rd Chilhowie VA 24319",
    "addr:housenumber":"1151",
    "addr:postcode":"24319",
    "addr:street":"Saint Clairs Creek Rd",
    "iso:country":"US",
    "sg:address":"1151 Saint Clairs Creek Rd",
    "sg:city":"Chilhowie",
    "sg:classifiers":[
        {
            "category":"Retail",
            "subcategory":"Auto Repair",
            "type":"Services"
        }
    ],
    "sg:phone":"+1 276 646 5411",
    "sg:postcode":"24319",
    "sg:province":"VA",
    "sg:tags":[
        "repairing",
        "automobile"
    ],
    "wof:name":"Randy Cook Body & Frame",
    "wof:placetype":"venue"
},
  "geometry": {"coordinates":[-81.634055,36.731902],"type":"Point"}
}