{
  "type": "Feature",
  "properties": {
    "addr:full":"812 Berryville Ave Winchester VA 22601",
    "addr:housenumber":"812",
    "addr:postcode":"22601",
    "addr:street":"Berryville Ave",
    "iso:country":"US",
    "sg:address":"812 Berryville Ave",
    "sg:city":"Winchester",
    "sg:classifiers":[
        {
            "category":"Retail",
            "subcategory":"Self-service Laundry",
            "type":"Services"
        }
    ],
    "sg:phone":"+1 540 662 5974",
    "sg:postcode":"22601",
    "sg:province":"VA",
    "sg:tags":[
        "operated",
        "washer",
        "dryer",
        "coin",
        "laundromat"
    ],
    "wof:name":"Soap Factory Coinop Ldry Ctr",
    "wof:placetype":"venue"
},
  "geometry": {"coordinates":[-78.146964,39.185999],"type":"Point"}
}