{
  "type": "Feature",
  "properties": {
    "iso:country":"US",
    "sg:address":"4903 Haygood Rd",
    "sg:city":"Virginia Beach",
    "sg:classifiers":[
        {
            "category":"Food & Beverages",
            "subcategory":"Groceries & Convenience Stores",
            "type":"Retail Goods"
        }
    ],
    "sg:phone":"+1 757 499 8251",
    "sg:postcode":"23455",
    "sg:province":"VA",
    "wof:name":"7-Eleven",
    "wof:placetype":"venue"
},
  "geometry": {"coordinates":[-76.14900900000001,36.86943],"type":"Point"}
}