{
  "type": "Feature",
  "properties": {
    "addr:full":"4907 Village Dr Fairfax VA 22030",
    "addr:housenumber":"4907",
    "addr:postcode":"22030",
    "addr:street":"Village Dr",
    "iso:country":"US",
    "sg:address":"4907 Village Dr",
    "sg:city":"Fairfax",
    "sg:classifiers":[
        {
            "category":"Health Services",
            "subcategory":"Clinic",
            "type":"Services"
        }
    ],
    "sg:phone":"+1 703 293 9108",
    "sg:postcode":"22030",
    "sg:province":"VA",
    "wof:name":"Lanier Healthcare",
    "wof:placetype":"venue"
},
  "geometry": {"coordinates":[-77.35667100000001,38.836621],"type":"Point"}
}