{
  "type": "Feature",
  "properties": {
    "iso:country":"US",
    "sg:address":"2111 Smith Ave",
    "sg:city":"Chesapeake",
    "sg:classifiers":[
        {
            "category":"Building & Trades",
            "subcategory":"Construction",
            "type":"Services"
        }
    ],
    "sg:phone":"+1 757 366 9505",
    "sg:postcode":"23320",
    "sg:province":"VA",
    "sg:tags":[
        "utility",
        "contractor"
    ],
    "sg:website":"www.tsupiperehab.com",
    "wof:name":"Tristate Utilities",
    "wof:placetype":"venue"
},
  "geometry": {"coordinates":[-76.22839500000001,36.797352],"type":"Point"}
}