{
  "type": "Feature",
  "properties": {
    "addr:full":"40 Panners Ln Fredericksburg VA 22406",
    "addr:housenumber":"40",
    "addr:postcode":"22406",
    "addr:street":"Panners Ln",
    "iso:country":"US",
    "sg:address":"40 Panners Ln",
    "sg:city":"Fredericksburg",
    "sg:classifiers":[
        {
            "category":"Professional",
            "type":"Services"
        }
    ],
    "sg:phone":"+1 540 379 5492",
    "sg:postcode":"22406",
    "sg:province":"VA",
    "wof:name":"Bears Nativ Amer Str",
    "wof:placetype":"venue"
},
  "geometry": {"coordinates":[-77.610024,38.378124],"type":"Point"}
}