{
  "type": "Feature",
  "properties": {
    "addr:full":"5316 Blue Ridge Ave Richmond VA 23231",
    "addr:housenumber":"5316",
    "addr:postcode":"23231",
    "addr:street":"Blue Ridge Ave",
    "iso:country":"US",
    "sg:address":"5316 Blue Ridge Ave",
    "sg:city":"Richmond",
    "sg:classifiers":[
        {
            "category":"Organizations",
            "subcategory":"Religious Organization",
            "type":"Services"
        }
    ],
    "sg:phone":"+1 804 222 1010",
    "sg:postcode":"23231",
    "sg:province":"VA",
    "sg:tags":[
        "clergy"
    ],
    "wof:name":"Walter Mason",
    "wof:placetype":"venue"
},
  "geometry": {"coordinates":[-77.394328,37.510167],"type":"Point"}
}