{
  "type": "Feature",
  "properties": {
    "addr:full":"107 W Center St Galax VA 24333",
    "addr:housenumber":"107",
    "addr:postcode":"24333",
    "addr:street":"W Center St",
    "iso:country":"US",
    "sg:address":"107 W Center St",
    "sg:city":"Galax",
    "sg:classifiers":[
        {
            "category":"Professional",
            "subcategory":"Lawyer & Legal Services",
            "type":"Services"
        }
    ],
    "sg:phone":"+1 276 238 1923",
    "sg:postcode":"24333",
    "sg:province":"VA",
    "sg:tags":[
        "attorney"
    ],
    "wof:name":"Daniel L Crandall & Assoc",
    "wof:placetype":"venue"
},
  "geometry": {"coordinates":[-80.925134,36.662625],"type":"Point"}
}