{
  "type": "Feature",
  "properties": {
    "addr:full":"3492 Germanna Hwy Locust Grove VA 22508",
    "addr:housenumber":"3492",
    "addr:postcode":"22508",
    "addr:street":"Germanna Hwy",
    "iso:country":"US",
    "sg:address":"3492 Germanna Hwy",
    "sg:city":"Locust Grove",
    "sg:classifiers":[
        {
            "category":"Building & Trades",
            "subcategory":"Construction",
            "type":"Services"
        }
    ],
    "sg:phone":"+1 540 972 0607",
    "sg:postcode":"22508",
    "sg:province":"VA",
    "sg:tags":[
        "contractor"
    ],
    "wof:name":"TWS Builders",
    "wof:placetype":"venue"
},
  "geometry": {"coordinates":[-77.753252,38.35309],"type":"Point"}
}