{
  "type": "Feature",
  "properties": {
    "iso:country":"US",
    "sg:address":"2016 Lakebreeze Way",
    "sg:city":"Reston",
    "sg:classifiers":[
        {
            "category":"Health Services",
            "subcategory":"Doctor",
            "type":"Services"
        }
    ],
    "sg:phone":"+1 703 716 5511",
    "sg:postcode":"20191",
    "sg:province":"VA",
    "sg:tags":[
        "psychologist"
    ],
    "wof:name":"Phillip E Nelson Phd",
    "wof:placetype":"venue"
},
  "geometry": {"coordinates":[-77.335267,38.936728],"type":"Point"}
}