{
  "type": "Feature",
  "properties": {
    "iso:country":"US",
    "sg:address":"1215 E Cary St",
    "sg:city":"Richmond",
    "sg:classifiers":[
        {
            "category":"Shopping",
            "subcategory":"Stationery & Office Supplies",
            "type":"Retail Goods"
        },
        {
            "category":"Shopping",
            "subcategory":"Hobbies, Toys, & Games",
            "type":"Retail Goods"
        },
        {
            "category":"Shopping",
            "subcategory":"Gifts & Souvenirs",
            "type":"Retail Goods"
        },
        {
            "category":"Shopping",
            "subcategory":"Crafts & Fabrics",
            "type":"Retail Goods"
        }
    ],
    "sg:phone":"+1 804 783 1744",
    "sg:postcode":"23219",
    "sg:province":"VA",
    "sg:tags":[
        "shop",
        "toy",
        "art",
        "store"
    ],
    "wof:name":"Toymaker of Williamsburg",
    "wof:placetype":"venue"
},
  "geometry": {"coordinates":[-77.434521,37.53578],"type":"Point"}
}