{
  "type": "Feature",
  "properties": {
    "iso:country":"US",
    "sg:address":"515 S Main St",
    "sg:city":"Rocky Mount",
    "sg:classifiers":[
        {
            "category":"Personal",
            "subcategory":"Beauty Salon",
            "type":"Services"
        }
    ],
    "sg:phone":"+1 540 483 1802",
    "sg:postcode":"24151",
    "sg:province":"VA",
    "sg:tags":[
        "shop"
    ],
    "wof:name":"S & M Styles Salon",
    "wof:placetype":"venue"
},
  "geometry": {"coordinates":[-79.890011,36.987847],"type":"Point"}
}