{
  "type": "Feature",
  "properties": {
    "addr:full":"1002 Oakmont Dr Petersburg VA 23805",
    "addr:housenumber":"1002",
    "addr:postcode":"23805",
    "addr:street":"Oakmont Dr",
    "iso:country":"US",
    "sg:address":"1002 Oakmont Dr",
    "sg:city":"Petersburg",
    "sg:classifiers":[
        {
            "category":"Retail",
            "subcategory":"Portrait Studio",
            "type":"Services"
        }
    ],
    "sg:phone":"+1 804 733 6817",
    "sg:postcode":"23805",
    "sg:province":"VA",
    "sg:tags":[
        "laboratory",
        "photofinishing",
        "photo"
    ],
    "wof:name":"Dickens Candid Photo",
    "wof:placetype":"venue"
},
  "geometry": {"coordinates":[-77.389601,37.190009],"type":"Point"}
}