{
  "type": "Feature",
  "properties": {
    "addr:full":"1155 Herndon Pkwy Herndon VA 20170",
    "addr:housenumber":"1155",
    "addr:postcode":"20170",
    "addr:street":"Herndon Pkwy",
    "iso:country":"US",
    "sg:address":"1155 Herndon Pkwy",
    "sg:city":"Herndon",
    "sg:classifiers":[
        {
            "category":"Real Estate",
            "subcategory":"Real Estate Agent",
            "type":"Services"
        }
    ],
    "sg:phone":"+1 703 834 1900",
    "sg:postcode":"20170",
    "sg:province":"VA",
    "sg:tags":[
        "management"
    ],
    "sg:website":"www.wyatt.org",
    "wof:name":"Lincoln Property Co",
    "wof:placetype":"venue"
},
  "geometry": {"coordinates":[-77.401184,38.964193],"type":"Point"}
}