{
  "type": "Feature",
  "properties": {
    "iso:country":"US",
    "sg:address":"4612 Sand Rock Ln",
    "sg:city":"Chantilly",
    "sg:classifiers":[
        {
            "category":"Professional",
            "subcategory":"Management & Consulting",
            "type":"Services"
        }
    ],
    "sg:phone":"+1 703 263 0193",
    "sg:postcode":"20151",
    "sg:province":"VA",
    "sg:tags":[
        "business"
    ],
    "wof:name":"J C L Services",
    "wof:placetype":"venue"
},
  "geometry": {"coordinates":[-77.408384,38.864312],"type":"Point"}
}