{
  "type": "Feature",
  "properties": {
    "iso:country":"US",
    "sg:address":"4024 Belspring Rd",
    "sg:city":"Chester",
    "sg:classifiers":[
        {
            "category":"Building & Trades",
            "subcategory":"Pest Control",
            "type":"Services"
        }
    ],
    "sg:phone":"+1 804 717 2426",
    "sg:postcode":"23831",
    "sg:province":"VA",
    "wof:name":"Brown Exterminating Company",
    "wof:placetype":"venue"
},
  "geometry": {"coordinates":[-77.436111,37.334253],"type":"Point"}
}