{
  "type": "Feature",
  "properties": {
    "iso:country":"US",
    "sg:address":"1609 Hillcrest Dr",
    "sg:city":"Harrisonburg",
    "sg:classifiers":[
        {
            "category":"Organizations",
            "subcategory":"Religious Organization",
            "type":"Services"
        }
    ],
    "sg:phone":"+1 540 433 2961",
    "sg:postcode":"22802",
    "sg:province":"VA",
    "wof:name":"Thomas L Reynolds Jr",
    "wof:placetype":"venue"
},
  "geometry": {"coordinates":[-78.87774400000001,38.47955],"type":"Point"}
}