{
  "type": "Feature",
  "properties": {
    "addr:full":"740 Boush St Norfolk VA 23510",
    "addr:housenumber":"740",
    "addr:postcode":"23510",
    "addr:street":"Boush St",
    "iso:country":"US",
    "sg:address":"740 Boush St",
    "sg:city":"Norfolk",
    "sg:classifiers":[
        {
            "category":"Insurance",
            "subcategory":"Hazard Insurance",
            "type":"Services"
        }
    ],
    "sg:phone":"+1 757 623 2400",
    "sg:postcode":"23510",
    "sg:province":"VA",
    "sg:tags":[
        "profit",
        "sharing",
        "pension",
        "plan"
    ],
    "wof:name":"Atlantic Permanent Savings",
    "wof:placetype":"venue"
},
  "geometry": {"coordinates":[-76.29056300000001,36.854347],"type":"Point"}
}