{
  "type": "Feature",
  "properties": {
    "addr:full":"11246 Lawyers Rd Prince George VA 23875",
    "addr:housenumber":"11246",
    "addr:postcode":"23875",
    "addr:street":"Lawyers Rd",
    "iso:country":"US",
    "sg:address":"11246 Lawyers Rd",
    "sg:city":"Prince George",
    "sg:classifiers":[
        {
            "category":"Retail",
            "subcategory":"Auto Repair",
            "type":"Services"
        }
    ],
    "sg:phone":"+1 804 586 0553",
    "sg:postcode":"23875",
    "sg:province":"VA",
    "sg:tags":[
        "wrecker"
    ],
    "wof:name":"Prince George Towing",
    "wof:placetype":"venue"
},
  "geometry": {"coordinates":[-77.206031,37.199908],"type":"Point"}
}