{
  "type": "Feature",
  "properties": {
    "addr:full":"9800 S Congress St New Market VA 22844",
    "addr:housenumber":"9800",
    "addr:postcode":"22844",
    "addr:street":"S Congress St",
    "iso:country":"US",
    "sg:address":"9800 S Congress St",
    "sg:city":"New Market",
    "sg:classifiers":[
        {
            "category":"Retail",
            "subcategory":"Repair Shop",
            "type":"Services"
        }
    ],
    "sg:phone":"+1 540 740 3490",
    "sg:postcode":"22844",
    "sg:province":"VA",
    "sg:tags":[
        "repairing",
        "lawn",
        "used",
        "farm",
        "mower",
        "equipment"
    ],
    "wof:name":"Route 11 Equipment Sales LLC",
    "wof:placetype":"venue"
},
  "geometry": {"coordinates":[-78.680295,38.636312],"type":"Point"}
}