{
  "type": "Feature",
  "properties": {
    "iso:country":"US",
    "sg:address":"7803 Red Tulip Ct",
    "sg:city":"Springfield",
    "sg:classifiers":[
        {
            "category":"Freight",
            "type":"Transportation"
        },
        {
            "category":"Professional",
            "subcategory":"Business Services",
            "type":"Services"
        },
        {
            "category":"Government",
            "subcategory":"Post Office",
            "type":"Public Place"
        }
    ],
    "sg:phone":"+1 703 913 1701",
    "sg:postcode":"22153",
    "sg:province":"VA",
    "sg:tags":[
        "courier",
        "shipping",
        "trucking",
        "delivery",
        "mail",
        "local"
    ],
    "wof:name":"Greenlight Enterprises",
    "wof:placetype":"venue"
},
  "geometry": {"coordinates":[-77.24275799999999,38.745217],"type":"Point"}
}