{
  "type": "Feature",
  "properties": {
    "addr:full":"3206 Gunston Rd Alexandria VA 22302",
    "addr:housenumber":"3206",
    "addr:postcode":"22302",
    "addr:street":"Gunston Rd",
    "iso:country":"US",
    "sg:address":"3206 Gunston Rd",
    "sg:city":"Alexandria",
    "sg:classifiers":[
        {
            "category":"Professional",
            "subcategory":"Art Services",
            "type":"Services"
        }
    ],
    "sg:phone":"+1 703 998 2992",
    "sg:postcode":"22302",
    "sg:province":"VA",
    "sg:tags":[
        "arts",
        "graphic",
        "design",
        "related"
    ],
    "wof:name":"William A Rawley Incorporated",
    "wof:placetype":"venue"
},
  "geometry": {"coordinates":[-77.077958,38.835233],"type":"Point"}
}