{
  "type": "Feature",
  "properties": {
    "addr:full":"2929 London Blvd Portsmouth VA 23707",
    "addr:housenumber":"2929",
    "addr:postcode":"23707",
    "addr:street":"London Blvd",
    "iso:country":"US",
    "sg:address":"2929 London Blvd",
    "sg:city":"Portsmouth",
    "sg:classifiers":[
        {
            "category":"Health Services",
            "subcategory":"Doctor",
            "type":"Services"
        }
    ],
    "sg:phone":"+1 757 397 1204",
    "sg:postcode":"23707",
    "sg:province":"VA",
    "wof:name":"David E Lannik",
    "wof:placetype":"venue"
},
  "geometry": {"coordinates":[-76.338189,36.836365],"type":"Point"}
}