{
  "type": "Feature",
  "properties": {
    "addr:full":"1550 Commerce St Winchester VA 22601",
    "addr:housenumber":"1550",
    "addr:postcode":"22601",
    "addr:street":"Commerce St",
    "iso:country":"US",
    "sg:address":"1550 Commerce St",
    "sg:city":"Winchester",
    "sg:classifiers":[
        {
            "category":"Building & Trades",
            "subcategory":"Construction",
            "type":"Services"
        }
    ],
    "sg:phone":"+1 540 667 4028",
    "sg:postcode":"22601",
    "sg:province":"VA",
    "sg:tags":[
        "marking",
        "maintenance",
        "parking"
    ],
    "wof:name":"Valley Sweepers",
    "wof:placetype":"venue"
},
  "geometry": {"coordinates":[-78.168578,39.168067],"type":"Point"}
}