{
  "type": "Feature",
  "properties": {
    "addr:full":"6506 Loisdale Rd Springfield VA 22150",
    "addr:housenumber":"6506",
    "addr:postcode":"22150",
    "addr:street":"Loisdale Rd",
    "iso:country":"US",
    "sg:address":"6506 Loisdale Rd",
    "sg:city":"Springfield",
    "sg:classifiers":[
        {
            "category":"Professional",
            "subcategory":"Employment Agencies",
            "type":"Services"
        }
    ],
    "sg:phone":"+1 703 922 4229",
    "sg:postcode":"22150",
    "sg:province":"VA",
    "sg:tags":[
        "opportunity"
    ],
    "wof:name":"Express Personnel Svc",
    "wof:placetype":"venue"
},
  "geometry": {"coordinates":[-77.17633600000001,38.776504],"type":"Point"}
}