{
  "type": "Feature",
  "properties": {
    "addr:full":"6603 Leeds Manor Rd Marshall VA 20115",
    "addr:housenumber":"6603",
    "addr:postcode":"20115",
    "addr:street":"Leeds Manor Rd",
    "iso:country":"US",
    "sg:address":"6603 Leeds Manor Rd",
    "sg:city":"Marshall",
    "sg:classifiers":[
        {
            "category":"Building & Trades",
            "subcategory":"Construction",
            "type":"Services"
        }
    ],
    "sg:phone":"+1 540 364 4872",
    "sg:postcode":"20115",
    "sg:province":"VA",
    "sg:tags":[
        "excavating",
        "contractor"
    ],
    "wof:name":"Herman Harlow Excavating",
    "wof:placetype":"venue"
},
  "geometry": {"coordinates":[-77.974852,38.763795],"type":"Point"}
}