{
  "type": "Feature",
  "properties": {
    "iso:country":"US",
    "sg:address":"6072 Crown Royal Cir",
    "sg:city":"Alexandria",
    "sg:classifiers":[
        {
            "category":"Professional",
            "subcategory":"Management & Consulting",
            "type":"Services"
        }
    ],
    "sg:phone":"+1 703 568 8238",
    "sg:postcode":"22310",
    "sg:province":"VA",
    "sg:tags":[
        "business"
    ],
    "wof:name":"Orion III Consulting",
    "wof:placetype":"venue"
},
  "geometry": {"coordinates":[-77.137978,38.788052],"type":"Point"}
}