{
  "type": "Feature",
  "properties": {
    "addr:full":"16 Walnut Ave SW Roanoke VA 24016",
    "addr:housenumber":"16",
    "addr:postcode":"24016",
    "addr:street":"Walnut Ave Sw",
    "iso:country":"US",
    "sg:address":"16 Walnut Ave SW",
    "sg:city":"Roanoke",
    "sg:classifiers":[
        {
            "category":"Organizations",
            "subcategory":"Non-profit Organization",
            "type":"Services"
        }
    ],
    "sg:phone":"+1 540 345 6468",
    "sg:postcode":"24016",
    "sg:province":"VA",
    "sg:tags":[
        "information",
        "alcoholism",
        "treatment"
    ],
    "wof:name":"Walnut Avenue Assoc",
    "wof:placetype":"venue"
},
  "geometry": {"coordinates":[-79.942008,37.261082],"type":"Point"}
}