{
  "type": "Feature",
  "properties": {
    "addr:full":"311 Park Rd Alexandria VA 22301",
    "addr:housenumber":"311",
    "addr:postcode":"22301",
    "addr:street":"Park Rd",
    "iso:country":"US",
    "sg:address":"311 Park Rd",
    "sg:city":"Alexandria",
    "sg:classifiers":[
        {
            "category":"Real Estate",
            "subcategory":"Real Estate Services",
            "type":"Services"
        },
        {
            "category":"Real Estate",
            "subcategory":"Surveying",
            "type":"Services"
        }
    ],
    "sg:phone":"+1 703 768 5311",
    "sg:postcode":"22301",
    "sg:province":"VA",
    "sg:tags":[
        "industrial",
        "appraisers-commercial",
        "appraiser"
    ],
    "wof:name":"M Campagna Appraisal Service Inc",
    "wof:placetype":"venue"
},
  "geometry": {"coordinates":[-77.06625699999999,38.809021],"type":"Point"}
}