{
  "type": "Feature",
  "properties": {
    "iso:country":"US",
    "sg:address":"6222 E Virginia Beach Blvd",
    "sg:city":"Norfolk",
    "sg:classifiers":[
        {
            "category":"Autos & Motor Vehicles",
            "subcategory":"Automobile Sales",
            "type":"Retail Goods"
        }
    ],
    "sg:phone":"+1 757 455 4600",
    "sg:postcode":"23502",
    "sg:province":"VA",
    "sg:tags":[
        "new",
        "used",
        "dealer",
        "car"
    ],
    "sg:website":"www.caddiville.com",
    "wof:name":"Colonial Cadillac",
    "wof:placetype":"venue"
},
  "geometry": {"coordinates":[-76.19333,36.855256],"type":"Point"}
}