{
  "type": "Feature",
  "properties": {
    "addr:full":"413 Locust Ave Waynesboro VA 22980",
    "addr:housenumber":"413",
    "addr:postcode":"22980",
    "addr:street":"Locust Ave",
    "iso:country":"US",
    "sg:address":"413 Locust Ave",
    "sg:city":"Waynesboro",
    "sg:classifiers":[
        {
            "category":"Health Services",
            "subcategory":"Doctor",
            "type":"Services"
        }
    ],
    "sg:phone":"+1 540 943 2959",
    "sg:postcode":"22980",
    "sg:province":"VA",
    "sg:tags":[
        "medical"
    ],
    "wof:name":"M Edgar Hollowell Jr",
    "wof:placetype":"venue"
},
  "geometry": {"coordinates":[-78.897199,38.067539],"type":"Point"}
}