{
  "type": "Feature",
  "properties": {
    "iso:country":"US",
    "sg:address":"1110 East Market St",
    "sg:city":"Charlottesville",
    "sg:classifiers":[
        {
            "category":"Shopping",
            "subcategory":"Bicycles & Sporting Goods",
            "type":"Retail Goods"
        },
        {
            "category":"Sports & Exercise",
            "subcategory":"Bicycle Rental",
            "type":"Entertainment"
        }
    ],
    "sg:phone":"+1 434 220 0270",
    "sg:postcode":"22902",
    "sg:province":"VA",
    "sg:tags":[
        "bike"
    ],
    "wof:name":"Syklo Bicycles",
    "wof:placetype":"venue"
},
  "geometry": {"coordinates":[-78.47203399999999,38.028088],"type":"Point"}
}