{
  "type": "Feature",
  "properties": {
    "addr:full":"3022 Tyre Neck Rd Portsmouth VA 23703",
    "addr:housenumber":"3022",
    "addr:postcode":"23703",
    "addr:street":"Tyre Neck Rd",
    "iso:country":"US",
    "sg:address":"3022 Tyre Neck Rd",
    "sg:city":"Portsmouth",
    "sg:classifiers":[
        {
            "category":"Manufacturing",
            "subcategory":"Leather Goods",
            "type":"Manufacturing & Wholesale Goods"
        }
    ],
    "sg:phone":"+1 757 483 4872",
    "sg:postcode":"23703",
    "sg:province":"VA",
    "sg:tags":[
        "mfg"
    ],
    "wof:name":"Backwoods Leather",
    "wof:placetype":"venue"
},
  "geometry": {"coordinates":[-76.39589599999999,36.859094],"type":"Point"}
}