{
  "type": "Feature",
  "properties": {
    "addr:full":"3016 Lincoln Ave Richmond VA 23228",
    "addr:housenumber":"3016",
    "addr:postcode":"23228",
    "addr:street":"Lincoln Ave",
    "iso:country":"US",
    "sg:address":"3016 Lincoln Ave",
    "sg:city":"Richmond",
    "sg:classifiers":[
        {
            "category":"Retail",
            "subcategory":"Repair Shop",
            "type":"Services"
        }
    ],
    "sg:phone":"+1 804 266 1072",
    "sg:postcode":"23228",
    "sg:province":"VA",
    "sg:tags":[
        "furniture"
    ],
    "wof:name":"Harrison Furniture Service",
    "wof:placetype":"venue"
},
  "geometry": {"coordinates":[-77.493892,37.614564],"type":"Point"}
}