{
  "type": "Feature",
  "properties": {
    "addr:full":"6813 Jeremiah Ct Fairfax Station VA 22039",
    "addr:housenumber":"6813",
    "addr:postcode":"22039",
    "addr:street":"Jeremiah Ct",
    "iso:country":"US",
    "sg:address":"6813 Jeremiah Ct",
    "sg:city":"Fairfax Station",
    "sg:classifiers":[
        {
            "category":"Professional",
            "subcategory":"Management & Consulting",
            "type":"Services"
        }
    ],
    "sg:phone":"+1 703 764 2060",
    "sg:postcode":"22039",
    "sg:province":"VA",
    "sg:tags":[
        "consultant",
        "business"
    ],
    "wof:name":"Inter Trans Group",
    "wof:placetype":"venue"
},
  "geometry": {"coordinates":[-77.312928,38.769168],"type":"Point"}
}