{
  "type": "Feature",
  "properties": {
    "addr:full":"6813 19th Rd N Arlington VA 22205",
    "addr:housenumber":"6813",
    "addr:postcode":"22205",
    "addr:street":"19Th Rd N",
    "iso:country":"US",
    "sg:address":"6813 19th Rd N",
    "sg:city":"Arlington",
    "sg:classifiers":[
        {
            "category":"Shopping",
            "subcategory":"Musical Instruments",
            "type":"Retail Goods"
        }
    ],
    "sg:phone":"+1 703 237 8932",
    "sg:postcode":"22205",
    "sg:province":"VA",
    "wof:name":"Guitar Doctor",
    "wof:placetype":"venue"
},
  "geometry": {"coordinates":[-77.161286,38.885488],"type":"Point"}
}