{
  "type": "Feature",
  "properties": {
    "iso:country":"US",
    "sg:address":"2390 Roanoke St",
    "sg:city":"Christiansburg",
    "sg:classifiers":[
        {
            "category":"Food & Beverages",
            "subcategory":"Groceries & Convenience Stores",
            "type":"Retail Goods"
        }
    ],
    "sg:phone":"+1 540 382 4572",
    "sg:postcode":"24073",
    "sg:province":"VA",
    "wof:name":"Exxon Express Stop",
    "wof:placetype":"venue"
},
  "geometry": {"coordinates":[-80.360361,37.136733],"type":"Point"}
}