{
  "type": "Feature",
  "properties": {
    "addr:full":"11520 James Madison St Remington VA 22734",
    "addr:housenumber":"11520",
    "addr:postcode":"22734",
    "addr:street":"James Madison St",
    "iso:country":"US",
    "sg:address":"11520 James Madison St",
    "sg:city":"Remington",
    "sg:classifiers":[
        {
            "category":"Real Estate",
            "subcategory":"Real Estate Agent",
            "type":"Services"
        }
    ],
    "sg:phone":"+1 540 439 3808",
    "sg:postcode":"22734",
    "sg:province":"VA",
    "wof:name":"Helm Real Estate",
    "wof:placetype":"venue"
},
  "geometry": {"coordinates":[-77.801014,38.555378],"type":"Point"}
}