{
  "type": "Feature",
  "properties": {
    "addr:full":"3186 Skyline Hwy Galax VA 24333",
    "addr:housenumber":"3186",
    "addr:postcode":"24333",
    "addr:street":"Skyline Hwy",
    "iso:country":"US",
    "sg:address":"3186 Skyline Hwy",
    "sg:city":"Galax",
    "sg:classifiers":[
        {
            "category":"Shopping",
            "subcategory":"Bicycles & Sporting Goods",
            "type":"Retail Goods"
        }
    ],
    "sg:phone":"+1 276 236 0598",
    "sg:postcode":"24333",
    "sg:province":"VA",
    "wof:name":"J Diamond",
    "wof:placetype":"venue"
},
  "geometry": {"coordinates":[-80.91013700000001,36.580318],"type":"Point"}
}