{
  "type": "Feature",
  "properties": {
    "addr:full":"2519 Quail Oak Dr Ruther Glen VA 22546",
    "addr:housenumber":"2519",
    "addr:postcode":"22546",
    "addr:street":"Quail Oak Dr",
    "iso:country":"US",
    "sg:address":"2519 Quail Oak Dr",
    "sg:city":"Ruther Glen",
    "sg:classifiers":[
        {
            "category":"Social Services",
            "subcategory":"Child Care",
            "type":"Services"
        }
    ],
    "sg:phone":"+1 804 448 1949",
    "sg:postcode":"22546",
    "sg:province":"VA",
    "sg:tags":[
        "day"
    ],
    "wof:name":"Rhodes Day Care",
    "wof:placetype":"venue"
},
  "geometry": {"coordinates":[-77.518756,38.029861],"type":"Point"}
}