{
  "type": "Feature",
  "properties": {
    "addr:full":"13000 Bayou Wood Cir Woodbridge VA 22192",
    "addr:housenumber":"13000",
    "addr:postcode":"22192",
    "addr:street":"Bayou Wood Cir",
    "iso:country":"US",
    "sg:address":"13000 Bayou Wood Cir",
    "sg:city":"Woodbridge",
    "sg:classifiers":[
        {
            "category":"Retail",
            "subcategory":"Repair Shop",
            "type":"Services"
        }
    ],
    "sg:phone":"+1 877 557 2757",
    "sg:postcode":"22192",
    "sg:province":"VA",
    "sg:tags":[
        "small",
        "major",
        "appliance",
        "refinishing"
    ],
    "sg:website":"http://local.ingenio.com/Listings/Details.aspx?NUM=a%3a10330081%3a13%3a4859924%3a14%3a0%3a7",
    "wof:name":"Watkins Appliance Repair",
    "wof:placetype":"venue"
},
  "geometry": {"coordinates":[-77.271278,38.670281],"type":"Point"}
}