{
  "type": "Feature",
  "properties": {
    "addr:full":"39469 John Mosby Hwy Aldie VA 20105",
    "addr:housenumber":"39469",
    "addr:postcode":"20105",
    "addr:street":"John Mosby Hwy",
    "iso:country":"US",
    "sg:address":"39469 John Mosby Hwy",
    "sg:city":"Aldie",
    "sg:classifiers":[
        {
            "category":"Shopping",
            "subcategory":"Used Merchandise",
            "type":"Retail Goods"
        }
    ],
    "sg:phone":"+1 703 327 4547",
    "sg:postcode":"20105",
    "sg:province":"VA",
    "sg:tags":[
        "antique"
    ],
    "wof:name":"Mattingly Antiques",
    "wof:placetype":"venue"
},
  "geometry": {"coordinates":[-77.634306,38.973528],"type":"Point"}
}