{
  "type": "Feature",
  "properties": {
    "addr:full":"11175 Ridgefield Pkwy Richmond VA 23233",
    "addr:housenumber":"11175",
    "addr:postcode":"23233",
    "addr:street":"Ridgefield Pkwy",
    "iso:country":"US",
    "sg:address":"11175 Ridgefield Pkwy",
    "sg:city":"Richmond",
    "sg:classifiers":[
        {
            "category":"Professional",
            "subcategory":"Advertising",
            "type":"Services"
        }
    ],
    "sg:phone":"+1 804 750 2555",
    "sg:postcode":"23233",
    "sg:province":"VA",
    "sg:tags":[
        "counselor"
    ],
    "wof:name":"Parrish Anders & Partners",
    "wof:placetype":"venue"
},
  "geometry": {"coordinates":[-77.638018,37.623929],"type":"Point"}
}