{
  "type": "Feature",
  "properties": {
    "addr:full":"7868 Dogue Indian Cir Lorton VA 22079",
    "addr:housenumber":"7868",
    "addr:postcode":"22079",
    "addr:street":"Dogue Indian Cir",
    "iso:country":"US",
    "sg:address":"7868 Dogue Indian Cir",
    "sg:city":"Lorton",
    "sg:classifiers":[
        {
            "category":"Restaurant",
            "type":"Food & Drink"
        }
    ],
    "sg:phone":"+1 703 339 1959",
    "sg:postcode":"22079",
    "sg:province":"VA",
    "sg:tags":[
        "eating"
    ],
    "wof:name":"Kerolos Food Services Inc",
    "wof:placetype":"venue"
},
  "geometry": {"coordinates":[-77.216206,38.694655],"type":"Point"}
}