{
  "type": "Feature",
  "properties": {
    "iso:country":"US",
    "sg:address":"413 Patrick Ln",
    "sg:city":"Herndon",
    "sg:classifiers":[
        {
            "category":"Freight",
            "type":"Transportation"
        }
    ],
    "sg:phone":"+1 703 471 1582",
    "sg:postcode":"20170",
    "sg:province":"VA",
    "sg:tags":[
        "courier"
    ],
    "wof:name":"Smart Courier Service",
    "wof:placetype":"venue"
},
  "geometry": {"coordinates":[-77.394543,38.963734],"type":"Point"}
}