{
  "type": "Feature",
  "properties": {
    "addr:full":"103 Brunswick Rd Stephens City VA 22655",
    "addr:housenumber":"103",
    "addr:postcode":"22655",
    "addr:street":"Brunswick Rd",
    "iso:country":"US",
    "sg:address":"103 Brunswick Rd",
    "sg:city":"Stephens City",
    "sg:classifiers":[
        {
            "category":"Personal",
            "subcategory":"Beauty Salon",
            "type":"Services"
        }
    ],
    "sg:phone":"+1 540 869 3235",
    "sg:postcode":"22655",
    "sg:province":"VA",
    "sg:tags":[
        "manicuring"
    ],
    "wof:name":"Polished Images",
    "wof:placetype":"venue"
},
  "geometry": {"coordinates":[-78.203683,39.084735],"type":"Point"}
}