{
  "type": "Feature",
  "properties": {
    "iso:country":"US",
    "sg:address":"2031 Salem Industrial Dr",
    "sg:city":"Salem",
    "sg:classifiers":[
        {
            "category":"Freight",
            "type":"Transportation"
        }
    ],
    "sg:phone":"+1 540 389 5421",
    "sg:postcode":"24153",
    "sg:province":"VA",
    "sg:tags":[
        "hauling",
        "trucking"
    ],
    "wof:name":"Bayse Transportation Svc",
    "wof:placetype":"venue"
},
  "geometry": {"coordinates":[-80.09619499999999,37.282486],"type":"Point"}
}