{
  "type": "Feature",
  "properties": {
    "iso:country":"US",
    "sg:address":"4600 Gilling Ct",
    "sg:city":"Virginia Beach",
    "sg:classifiers":[
        {
            "category":"Professional",
            "subcategory":"Business Services",
            "type":"Services"
        }
    ],
    "sg:phone":"+1 757 495 8902",
    "sg:postcode":"23464",
    "sg:province":"VA",
    "wof:name":"Abbate Management Group LLC",
    "wof:placetype":"venue"
},
  "geometry": {"coordinates":[-76.135266,36.802212],"type":"Point"}
}