{
  "type": "Feature",
  "properties": {
    "iso:country":"US",
    "sg:address":"12326 Quail Oak Ct",
    "sg:city":"Ashland",
    "sg:classifiers":[
        {
            "category":"Professional",
            "subcategory":"Computer Services",
            "type":"Services"
        }
    ],
    "sg:phone":"+1 804 986 3430",
    "sg:postcode":"23005",
    "sg:province":"VA",
    "sg:tags":[
        "related"
    ],
    "wof:name":"Compu Wizard LLC",
    "wof:placetype":"venue"
},
  "geometry": {"coordinates":[-77.394825,37.742779],"type":"Point"}
}