{
  "type": "Feature",
  "properties": {
    "iso:country":"US",
    "sg:address":"3957 Mountain Rd",
    "sg:city":"Strasburg",
    "sg:classifiers":[
        {
            "category":"Government",
            "subcategory":"Office",
            "type":"Public Place"
        }
    ],
    "sg:phone":"+1 540 635 5350",
    "sg:postcode":"22630",
    "sg:province":"VA",
    "sg:tags":[
        "state",
        "conservation"
    ],
    "wof:name":"Game Inland Fisheries VA Dept",
    "wof:placetype":"venue"
},
  "geometry": {"coordinates":[-78.292241,38.947062],"type":"Point"}
}