{
  "type": "Feature",
  "properties": {
    "iso:country":"US",
    "sg:address":"9022 Mathis Ave",
    "sg:city":"Manassas",
    "sg:classifiers":[
        {
            "category":"Professional",
            "subcategory":"Computer Services",
            "type":"Services"
        }
    ],
    "sg:phone":"+1 703 331 3812",
    "sg:postcode":"20110",
    "sg:province":"VA",
    "sg:tags":[
        "value",
        "integrator",
        "added",
        "system",
        "reseller"
    ],
    "sg:website":"www.vasi.com",
    "wof:name":"VASI",
    "wof:placetype":"venue"
},
  "geometry": {"coordinates":[-77.464454,38.759495],"type":"Point"}
}