{
  "type": "Feature",
  "properties": {
    "iso:country":"US",
    "sg:address":"7302 Statecrest Dr",
    "sg:city":"Annandale",
    "sg:classifiers":[
        {
            "category":"Social Services",
            "subcategory":"Child Care",
            "type":"Services"
        }
    ],
    "sg:phone":"+1 703 573 7994",
    "sg:postcode":"22003",
    "sg:province":"VA",
    "sg:tags":[
        "day"
    ],
    "wof:name":"Crest Childrens Center",
    "wof:placetype":"venue"
},
  "geometry": {"coordinates":[-77.198713,38.849561],"type":"Point"}
}