{
  "type": "Feature",
  "properties": {
    "addr:full":"2312 Windy Pines Bend Virginia Beach VA 23456",
    "addr:housenumber":"2312",
    "addr:postcode":"23456",
    "addr:street":"Windy Pines Bend",
    "iso:country":"US",
    "sg:address":"2312 Windy Pines Bend",
    "sg:city":"Virginia Beach",
    "sg:classifiers":[
        {
            "category":"Building & Trades",
            "subcategory":"Construction",
            "type":"Services"
        }
    ],
    "sg:phone":"+1 757 563 0125",
    "sg:postcode":"23456",
    "sg:province":"VA",
    "wof:name":"Chesapeake Bay Underground",
    "wof:placetype":"venue"
},
  "geometry": {"coordinates":[-76.02878699999999,36.768951],"type":"Point"}
}