{
  "type": "Feature",
  "properties": {
    "iso:country":"US",
    "sg:address":"8206 Leesburg Pike",
    "sg:city":"Vienna",
    "sg:classifiers":[
        {
            "category":"Health Services",
            "subcategory":"Optometrist",
            "type":"Services"
        }
    ],
    "sg:phone":"+1 202 686 6800",
    "sg:postcode":"22182",
    "sg:province":"VA",
    "sg:tags":[
        "ophthalmologist"
    ],
    "wof:name":"University Ophthalmic Consultants of Washington",
    "wof:placetype":"venue"
},
  "geometry": {"coordinates":[-77.22820299999999,38.917099],"type":"Point"}
}