{
  "type": "Feature",
  "properties": {
    "addr:full":"6808 Park Ave Richmond VA 23226",
    "addr:housenumber":"6808",
    "addr:postcode":"23226",
    "addr:street":"Park Ave",
    "iso:country":"US",
    "sg:address":"6808 Park Ave",
    "sg:city":"Richmond",
    "sg:classifiers":[
        {
            "category":"Education",
            "subcategory":"Special Training",
            "type":"Public Place"
        }
    ],
    "sg:phone":"+1 804 288 4415",
    "sg:postcode":"23226",
    "sg:province":"VA",
    "sg:tags":[
        "school",
        "instruction",
        "art"
    ],
    "wof:name":"Overstreet Kim",
    "wof:placetype":"venue"
},
  "geometry": {"coordinates":[-77.528065,37.59176],"type":"Point"}
}