{
  "type": "Feature",
  "properties": {
    "iso:country":"US",
    "sg:address":"811 S Lynnhaven Rd",
    "sg:city":"Virginia Beach",
    "sg:classifiers":[
        {
            "category":"Social Services",
            "subcategory":"Child Care",
            "type":"Services"
        }
    ],
    "sg:phone":"+1 757 463 5072",
    "sg:postcode":"23452",
    "sg:province":"VA",
    "wof:name":"Sitter",
    "wof:placetype":"venue"
},
  "geometry": {"coordinates":[-76.073897,36.812969],"type":"Point"}
}