{
  "type": "Feature",
  "properties": {
    "iso:country":"US",
    "sg:address":"613 Woodland Rd",
    "sg:city":"Rich Creek",
    "sg:classifiers":[
        {
            "category":"Retail",
            "subcategory":"Repair Shop",
            "type":"Services"
        }
    ],
    "sg:phone":"+1 540 726 8115",
    "sg:postcode":"24147",
    "sg:province":"VA",
    "sg:tags":[
        "related"
    ],
    "wof:name":"New River Repair Center",
    "wof:placetype":"venue"
},
  "geometry": {"coordinates":[-80.81902599999999,37.38359],"type":"Point"}
}