{
  "type": "Feature",
  "properties": {
    "iso:country":"US",
    "sg:address":"3315 Garden City Blvd SE",
    "sg:city":"Roanoke",
    "sg:classifiers":[
        {
            "category":"Building & Trades",
            "subcategory":"Electrical",
            "type":"Services"
        }
    ],
    "sg:phone":"+1 540 427 0140",
    "sg:postcode":"24014",
    "sg:province":"VA",
    "sg:tags":[
        "electric",
        "industrial",
        "contractors-commercial",
        "contractor"
    ],
    "wof:name":"Southern Limited Electrical Co",
    "wof:placetype":"venue"
},
  "geometry": {"coordinates":[-79.928427,37.232677],"type":"Point"}
}