{
  "type": "Feature",
  "properties": {
    "addr:full":"1042 N Lexan Cres Norfolk VA 23508",
    "addr:housenumber":"1042",
    "addr:postcode":"23508",
    "addr:street":"N Lexan Cres",
    "iso:country":"US",
    "sg:address":"1042 N Lexan Cres",
    "sg:city":"Norfolk",
    "sg:classifiers":[
        {
            "category":"Wholesale",
            "subcategory":"Groceries",
            "type":"Manufacturing & Wholesale Goods"
        }
    ],
    "sg:phone":"+1 757 440 7800",
    "sg:postcode":"23508",
    "sg:province":"VA",
    "sg:tags":[
        "general"
    ],
    "wof:name":"Stockmeyer North America Inc",
    "wof:placetype":"venue"
},
  "geometry": {"coordinates":[-76.298844,36.900928],"type":"Point"}
}