{
  "type": "Feature",
  "properties": {
    "iso:country":"US",
    "sg:address":"7123 Neuman St",
    "sg:city":"Springfield",
    "sg:classifiers":[
        {
            "category":"Professional",
            "type":"Services"
        }
    ],
    "sg:phone":"+1 703 569 2417",
    "sg:postcode":"22150",
    "sg:province":"VA",
    "wof:name":"Hoxie Foundation Inc",
    "wof:placetype":"venue"
},
  "geometry": {"coordinates":[-77.199183,38.762391],"type":"Point"}
}