{
  "type": "Feature",
  "properties": {
    "iso:country":"US",
    "sg:address":"405 Cabell St",
    "sg:city":"Lynchburg",
    "sg:classifiers":[
        {
            "category":"Organizations",
            "subcategory":"Membership Organization",
            "type":"Services"
        }
    ],
    "sg:phone":"+1 434 847 1696",
    "sg:postcode":"24504",
    "sg:province":"VA",
    "wof:name":"Crossroads House",
    "wof:placetype":"venue"
},
  "geometry": {"coordinates":[-79.14698199999999,37.423392],"type":"Point"}
}