{
  "type": "Feature",
  "properties": {
    "addr:full":"530 E Main St # 800 Richmond VA 23219",
    "addr:housenumber":"530;800",
    "addr:postcode":"23219",
    "addr:street":"E Main St #",
    "iso:country":"US",
    "sg:address":"530 E Main St # 800",
    "sg:city":"Richmond",
    "sg:classifiers":[
        {
            "category":"Professional",
            "subcategory":"Engineering",
            "type":"Services"
        }
    ],
    "sg:phone":"+1 804 644 1680",
    "sg:postcode":"23219",
    "sg:province":"VA",
    "sg:tags":[
        "consultant",
        "energy",
        "conservation"
    ],
    "sg:website":"http://www.nature.org",
    "wof:name":"Nature Conservancy",
    "wof:placetype":"venue"
},
  "geometry": {"coordinates":[-77.43966500000001,37.540216],"type":"Point"}
}