{
  "type": "Feature",
  "properties": {
    "iso:country":"US",
    "sg:address":"9963 Warwick Blvd",
    "sg:city":"Newport News",
    "sg:classifiers":[
        {
            "category":"Banks & Credit Unions",
            "subcategory":"Bank",
            "type":"Services"
        }
    ],
    "sg:phone":"+1 757 599 5184",
    "sg:postcode":"23601",
    "sg:province":"VA",
    "sg:tags":[
        "depository",
        "banking",
        "loan"
    ],
    "wof:name":"Check First Inc",
    "wof:placetype":"venue"
},
  "geometry": {"coordinates":[-76.457874,37.029593],"type":"Point"}
}