{
  "type": "Feature",
  "properties": {
    "addr:full":"771 Fieldstone Dr Keswick VA 22947",
    "addr:housenumber":"771",
    "addr:postcode":"22947",
    "addr:street":"Fieldstone Dr",
    "iso:country":"US",
    "sg:address":"771 Fieldstone Dr",
    "sg:city":"Keswick",
    "sg:classifiers":[
        {
            "category":"Building & Trades",
            "subcategory":"Cleaning & Sanitation",
            "type":"Services"
        }
    ],
    "sg:phone":"+1 434 295 7440",
    "sg:postcode":"22947",
    "sg:province":"VA",
    "sg:tags":[
        "maintenance"
    ],
    "wof:name":"Helping Hands Home Cleaning",
    "wof:placetype":"venue"
},
  "geometry": {"coordinates":[-78.304391,37.976089],"type":"Point"}
}