{
  "type": "Feature",
  "properties": {
    "iso:country":"US",
    "sg:address":"1804 N Star Ct",
    "sg:city":"Virginia Beach",
    "sg:classifiers":[
        {
            "category":"Professional",
            "subcategory":"Computer Services",
            "type":"Services"
        }
    ],
    "sg:phone":"+1 757 471 3266",
    "sg:postcode":"23456",
    "sg:province":"VA",
    "sg:tags":[
        "datum"
    ],
    "wof:name":"WMS/WMS Micro Solutions",
    "wof:placetype":"venue"
},
  "geometry": {"coordinates":[-76.11846,36.785983],"type":"Point"}
}