{
  "type": "Feature",
  "properties": {
    "addr:full":"220 Brand Ave Salem VA 24153",
    "addr:housenumber":"220",
    "addr:postcode":"24153",
    "addr:street":"Brand Ave",
    "iso:country":"US",
    "sg:address":"220 Brand Ave",
    "sg:city":"Salem",
    "sg:classifiers":[
        {
            "category":"Organizations",
            "subcategory":"Labor Organization",
            "type":"Services"
        }
    ],
    "sg:phone":"+1 540 389 2397",
    "sg:postcode":"24153",
    "sg:province":"VA",
    "wof:name":"IBEW",
    "wof:placetype":"venue"
},
  "geometry": {"coordinates":[-80.04322000000001,37.29934],"type":"Point"}
}