{
  "type": "Feature",
  "properties": {
    "iso:country":"US",
    "sg:address":"1650 Valley Ave",
    "sg:city":"Winchester",
    "sg:classifiers":[
        {
            "category":"Home & Garden",
            "subcategory":"Building Materials",
            "type":"Retail Goods"
        }
    ],
    "sg:phone":"+1 540 665 1949",
    "sg:postcode":"22601",
    "sg:province":"VA",
    "sg:tags":[
        "paint"
    ],
    "wof:name":"Color Co",
    "wof:placetype":"venue"
},
  "geometry": {"coordinates":[-78.17652200000001,39.171342],"type":"Point"}
}