{
  "type": "Feature",
  "properties": {
    "addr:full":"1801 S Church St Smithfield VA 23430",
    "addr:housenumber":"1801",
    "addr:postcode":"23430",
    "addr:street":"S Church St",
    "iso:country":"US",
    "sg:address":"1801 S Church St",
    "sg:city":"Smithfield",
    "sg:classifiers":[
        {
            "category":"Professional",
            "subcategory":"Lawyer & Legal Services",
            "type":"Services"
        }
    ],
    "sg:phone":"+1 757 357 2126",
    "sg:postcode":"23430",
    "sg:province":"VA",
    "wof:name":"Wornom Herbert C III Atty",
    "wof:placetype":"venue"
},
  "geometry": {"coordinates":[-76.606268,36.96485],"type":"Point"}
}