{
  "type": "Feature",
  "properties": {
    "addr:full":"7 Black Oak Ct Poquoson VA 23662",
    "addr:housenumber":"7",
    "addr:postcode":"23662",
    "addr:street":"Black Oak Ct",
    "iso:country":"US",
    "sg:address":"7 Black Oak Ct",
    "sg:city":"Poquoson",
    "sg:classifiers":[
        {
            "category":"Health Services",
            "subcategory":"Doctor",
            "type":"Services"
        }
    ],
    "sg:phone":"+1 757 659 0200",
    "sg:postcode":"23662",
    "sg:province":"VA",
    "sg:tags":[
        "medical"
    ],
    "wof:name":"Richard Nixon MD",
    "wof:placetype":"venue"
},
  "geometry": {"coordinates":[-76.368872,37.125941],"type":"Point"}
}