{
  "type": "Feature",
  "properties": {
    "addr:full":"15236 Boydton Plank Rd Dinwiddie VA 23841",
    "addr:postcode":"15236;23841",
    "addr:street":"Plank Rd",
    "iso:country":"US",
    "sg:address":"15236 Boydton Plank Rd",
    "sg:city":"Dinwiddie",
    "sg:classifiers":[
        {
            "category":"Professional",
            "subcategory":"Business Services",
            "type":"Services"
        }
    ],
    "sg:phone":"+1 804 469 9394",
    "sg:postcode":"23841",
    "sg:province":"VA",
    "sg:tags":[
        "financial"
    ],
    "wof:name":"Primerica",
    "wof:placetype":"venue"
},
  "geometry": {"coordinates":[-77.623037,37.053882],"type":"Point"}
}