{
  "type": "Feature",
  "properties": {
    "addr:full":"2255 Big Island Hwy Bedford VA 24523",
    "addr:housenumber":"2255",
    "addr:postcode":"24523",
    "addr:street":"Big Island Hwy",
    "iso:country":"US",
    "sg:address":"2255 Big Island Hwy",
    "sg:city":"Bedford",
    "sg:classifiers":[
        {
            "category":"Freight",
            "type":"Transportation"
        }
    ],
    "sg:phone":"+1 540 586 2216",
    "sg:postcode":"24523",
    "sg:province":"VA",
    "sg:tags":[
        "operator",
        "local",
        "trucking"
    ],
    "wof:name":"Hopkins Trucking",
    "wof:placetype":"venue"
},
  "geometry": {"coordinates":[-79.49947899999999,37.37404],"type":"Point"}
}