{
  "type": "Feature",
  "properties": {
    "addr:full":"1716 Rivermont Ave Lynchburg VA 24503",
    "addr:housenumber":"1716",
    "addr:postcode":"24503",
    "addr:street":"Rivermont Ave",
    "iso:country":"US",
    "sg:address":"1716 Rivermont Ave",
    "sg:city":"Lynchburg",
    "sg:classifiers":[
        {
            "category":"Building & Trades",
            "subcategory":"Construction",
            "type":"Services"
        }
    ],
    "sg:phone":"+1 434 845 8022",
    "sg:postcode":"24503",
    "sg:province":"VA",
    "sg:tags":[
        "roofing",
        "contractor"
    ],
    "wof:name":"Tip-Top Roofing",
    "wof:placetype":"venue"
},
  "geometry": {"coordinates":[-79.15779000000001,37.433038],"type":"Point"}
}