{
  "type": "Feature",
  "properties": {
    "addr:full":"1006 Church Ln Tappahannock VA 22560",
    "addr:housenumber":"1006",
    "addr:postcode":"22560",
    "addr:street":"Church Ln",
    "iso:country":"US",
    "sg:address":"1006 Church Ln",
    "sg:city":"Tappahannock",
    "sg:classifiers":[
        {
            "category":"Retail",
            "subcategory":"Auto Repair",
            "type":"Services"
        }
    ],
    "sg:phone":"+1 804 443 6649",
    "sg:postcode":"22560",
    "sg:province":"VA",
    "sg:tags":[
        "repairing",
        "automobile"
    ],
    "wof:name":"Trent Carson Auto Svc & Clean",
    "wof:placetype":"venue"
},
  "geometry": {"coordinates":[-76.85928699999999,37.915051],"type":"Point"}
}