{
  "type": "Feature",
  "properties": {
    "addr:full":"4314 Richmond Rd Warsaw VA 22572",
    "addr:housenumber":"4314",
    "addr:postcode":"22572",
    "addr:street":"Richmond Rd",
    "iso:country":"US",
    "sg:address":"4314 Richmond Rd",
    "sg:city":"Warsaw",
    "sg:classifiers":[
        {
            "category":"Food & Beverages",
            "subcategory":"Liquor & Beverages",
            "type":"Retail Goods"
        }
    ],
    "sg:phone":"+1 804 333 3505",
    "sg:postcode":"22572",
    "sg:province":"VA",
    "wof:name":"ABC Liquor Stores",
    "wof:placetype":"venue"
},
  "geometry": {"coordinates":[-76.78331799999999,37.963724],"type":"Point"}
}