{
  "type": "Feature",
  "properties": {
    "addr:full":"3801 Plank Rd Ste B1 Fredericksburg VA 22407",
    "addr:housenumber":"3801",
    "addr:postcode":"22407",
    "addr:street":"Plank Rd Ste B1",
    "iso:country":"US",
    "sg:address":"3801 Plank Rd Ste B1",
    "sg:city":"Fredericksburg",
    "sg:classifiers":[
        {
            "category":"Professional",
            "subcategory":"Accounting & Tax Preparation",
            "type":"Services"
        }
    ],
    "sg:phone":"+1 866 871 1040",
    "sg:postcode":"22407",
    "sg:province":"VA",
    "sg:tags":[
        "return",
        "preparation-business"
    ],
    "sg:website":"http://www.libertytax.com/",
    "wof:name":"Liberty Tax Service",
    "wof:placetype":"venue"
},
  "geometry": {"coordinates":[-77.516621,38.29479],"type":"Point"}
}