{
  "type": "Feature",
  "properties": {
    "iso:country":"US",
    "sg:address":"1548 E Main St Ste B",
    "sg:city":"Richmond",
    "sg:classifiers":[
        {
            "category":"Restaurant",
            "type":"Food & Drink"
        }
    ],
    "sg:phone":"+1 804 644 4411",
    "sg:postcode":"23219",
    "sg:province":"VA",
    "wof:name":"White House Catering",
    "wof:placetype":"venue"
},
  "geometry": {"coordinates":[-77.429565,37.534078],"type":"Point"}
}