{
  "type": "Feature",
  "properties": {
    "addr:full":"4309 Allworthy Ln Chesterfield VA 23832",
    "addr:housenumber":"4309",
    "addr:postcode":"23832",
    "addr:street":"Allworthy Ln",
    "iso:country":"US",
    "sg:address":"4309 Allworthy Ln",
    "sg:city":"Chesterfield",
    "sg:classifiers":[
        {
            "category":"Wholesale",
            "subcategory":"Vending Machines",
            "type":"Manufacturing & Wholesale Goods"
        }
    ],
    "sg:phone":"+1 804 276 9767",
    "sg:postcode":"23832",
    "sg:province":"VA",
    "wof:name":"Jada Vending & Amusement",
    "wof:placetype":"venue"
},
  "geometry": {"coordinates":[-77.536616,37.449649],"type":"Point"}
}