{
  "type": "Feature",
  "properties": {
    "addr:full":"300 Killarney Ct Lynchburg VA 24502",
    "addr:housenumber":"300",
    "addr:postcode":"24502",
    "addr:street":"Killarney Ct",
    "iso:country":"US",
    "sg:address":"300 Killarney Ct",
    "sg:city":"Lynchburg",
    "sg:classifiers":[
        {
            "category":"Retail",
            "subcategory":"Portrait Studio",
            "type":"Services"
        }
    ],
    "sg:phone":"+1 434 239 7131",
    "sg:postcode":"24502",
    "sg:province":"VA",
    "sg:tags":[
        "photo"
    ],
    "wof:name":"Visioneerproductionscom",
    "wof:placetype":"venue"
},
  "geometry": {"coordinates":[-79.21023,37.392962],"type":"Point"}
}