{
  "type": "Feature",
  "properties": {
    "iso:country":"US",
    "sg:address":"3015 Patrick Henry Dr",
    "sg:city":"Falls Church",
    "sg:classifiers":[
        {
            "category":"Autos & Motor Vehicles",
            "subcategory":"Fuel & Gas Station",
            "type":"Retail Goods"
        }
    ],
    "sg:phone":"+1 703 532 8868",
    "sg:postcode":"22044",
    "sg:province":"VA",
    "sg:tags":[
        "station",
        "gasoline"
    ],
    "wof:name":"Seven Corners Chevron Auto Svc",
    "wof:placetype":"venue"
},
  "geometry": {"coordinates":[-77.14702699999999,38.868252],"type":"Point"}
}