{
  "type": "Feature",
  "properties": {
    "addr:full":"1008 First Colonial Rd Virginia Beach VA 23454",
    "addr:housenumber":"1008",
    "addr:postcode":"23454",
    "addr:street":"First Colonial Rd",
    "iso:country":"US",
    "sg:address":"1008 First Colonial Rd",
    "sg:city":"Virginia Beach",
    "sg:classifiers":[
        {
            "category":"Health Services",
            "subcategory":"Doctor",
            "type":"Services"
        }
    ],
    "sg:phone":"+1 757 481 1444",
    "sg:postcode":"23454",
    "sg:province":"VA",
    "sg:tags":[
        "medical"
    ],
    "wof:name":"Neurological Cons VA Bch",
    "wof:placetype":"venue"
},
  "geometry": {"coordinates":[-76.02766699999999,36.862733],"type":"Point"}
}