{
  "type": "Feature",
  "properties": {
    "addr:full":"219 King St Alexandria VA 22314",
    "addr:housenumber":"219",
    "addr:postcode":"22314",
    "addr:street":"King St",
    "iso:country":"US",
    "sg:address":"219 King St",
    "sg:city":"Alexandria",
    "sg:classifiers":[
        {
            "category":"Restaurant",
            "type":"Food & Drink"
        }
    ],
    "sg:phone":"+1 703 549 1141",
    "sg:postcode":"22314",
    "sg:province":"VA",
    "sg:tags":[
        "beverage",
        "serving",
        "alcoholic"
    ],
    "sg:website":"http://www.219restaurant.com",
    "wof:name":"Two Nineteen Restaurant",
    "wof:placetype":"venue"
},
  "geometry": {"coordinates":[-77.041676,38.804395],"type":"Point"}
}