{
  "type": "Feature",
  "properties": {
    "iso:country":"US",
    "sg:address":"10611 Springvale Ct",
    "sg:city":"Great Falls",
    "sg:classifiers":[
        {
            "category":"Organizations",
            "subcategory":"Professional Association",
            "type":"Services"
        }
    ],
    "sg:phone":"+1 703 757 4540",
    "sg:postcode":"22066",
    "sg:province":"VA",
    "sg:tags":[
        "business",
        "trade"
    ],
    "wof:name":"Mbi",
    "wof:placetype":"venue"
},
  "geometry": {"coordinates":[-77.311369,38.978435],"type":"Point"}
}