{
  "type": "Feature",
  "properties": {
    "iso:country":"US",
    "sg:address":"11928 Meadow Ridge Ter",
    "sg:city":"Glen Allen",
    "sg:classifiers":[
        {
            "category":"Building & Trades",
            "subcategory":"Construction",
            "type":"Services"
        }
    ],
    "sg:phone":"+1 804 360 7791",
    "sg:postcode":"23059",
    "sg:province":"VA",
    "sg:tags":[
        "home",
        "general",
        "family",
        "contractor"
    ],
    "wof:name":"Walsh Builders Inc",
    "wof:placetype":"venue"
},
  "geometry": {"coordinates":[-77.595904,37.696145],"type":"Point"}
}