{
  "type": "Feature",
  "properties": {
    "addr:full":"1410 Incarnation Dr Charlottesville VA 22901",
    "addr:housenumber":"1410",
    "addr:postcode":"22901",
    "addr:street":"Incarnation Dr",
    "iso:country":"US",
    "sg:address":"1410 Incarnation Dr",
    "sg:city":"Charlottesville",
    "sg:classifiers":[
        {
            "category":"Education",
            "subcategory":"Kindergarten",
            "type":"Public Place"
        }
    ],
    "sg:phone":"+1 434 978 3680",
    "sg:postcode":"22901",
    "sg:province":"VA",
    "sg:tags":[
        "school",
        "driving"
    ],
    "sg:website":"www.gesteducation.mysite.com",
    "wof:name":"1-A Driver Improvement",
    "wof:placetype":"venue"
},
  "geometry": {"coordinates":[-78.477844,38.073089],"type":"Point"}
}