{
  "type": "Feature",
  "properties": {
    "addr:full":"11413 River Run Dr Glen Allen VA 23059",
    "addr:housenumber":"11413",
    "addr:postcode":"23059",
    "addr:street":"River Run Dr",
    "iso:country":"US",
    "sg:address":"11413 River Run Dr",
    "sg:city":"Glen Allen",
    "sg:classifiers":[
        {
            "category":"Professional",
            "type":"Services"
        }
    ],
    "sg:phone":"+1 804 261 9390",
    "sg:postcode":"23059",
    "sg:province":"VA",
    "wof:name":"Bkv Inc",
    "wof:placetype":"venue"
},
  "geometry": {"coordinates":[-77.52163299999999,37.689405],"type":"Point"}
}