{
  "type": "Feature",
  "properties": {
    "addr:full":"7200 Hickory Rd Petersburg VA 23803",
    "addr:housenumber":"7200",
    "addr:postcode":"23803",
    "addr:street":"Hickory Rd",
    "iso:country":"US",
    "sg:address":"7200 Hickory Rd",
    "sg:city":"Petersburg",
    "sg:classifiers":[
        {
            "category":"Organizations",
            "subcategory":"Religious Organization",
            "type":"Services"
        }
    ],
    "sg:phone":"+1 804 590 9231",
    "sg:postcode":"23803",
    "sg:province":"VA",
    "wof:name":"Woods United Methodist Church",
    "wof:placetype":"venue"
},
  "geometry": {"coordinates":[-77.493554,37.263852],"type":"Point"}
}