{
  "type": "Feature",
  "properties": {
    "addr:full":"4504 Irvington Rd Irvington VA 22480",
    "addr:housenumber":"4504",
    "addr:postcode":"22480",
    "addr:street":"Irvington Rd",
    "iso:country":"US",
    "sg:address":"4504 Irvington Rd",
    "sg:city":"Irvington",
    "sg:classifiers":[
        {
            "category":"Banks & Credit Unions",
            "subcategory":"Bank",
            "type":"Services"
        }
    ],
    "sg:phone":"+1 804 438 5277",
    "sg:postcode":"22480",
    "sg:province":"VA",
    "sg:tags":[
        "escrow"
    ],
    "wof:name":"Watermark Settlement & Escrow",
    "wof:placetype":"venue"
},
  "geometry": {"coordinates":[-76.41897899999999,37.660168],"type":"Point"}
}