{
  "type": "Feature",
  "properties": {
    "addr:full":"4029 Monticello St Richmond VA 23227",
    "addr:housenumber":"4029",
    "addr:postcode":"23227",
    "addr:street":"Monticello St",
    "iso:country":"US",
    "sg:address":"4029 Monticello St",
    "sg:city":"Richmond",
    "sg:classifiers":[
        {
            "category":"Building & Trades",
            "subcategory":"Construction",
            "type":"Services"
        }
    ],
    "sg:phone":"+1 804 553 0361",
    "sg:postcode":"23227",
    "sg:province":"VA",
    "sg:tags":[
        "hanging",
        "contractor"
    ],
    "wof:name":"Richmond Painting Company LLC",
    "wof:placetype":"venue"
},
  "geometry": {"coordinates":[-77.460358,37.589957],"type":"Point"}
}