{
  "type": "Feature",
  "properties": {
    "addr:full":"525 23rd St S Arlington VA 22202",
    "addr:housenumber":"525",
    "addr:postcode":"22202",
    "addr:street":"23Rd St S",
    "iso:country":"US",
    "sg:address":"525 23rd St S",
    "sg:city":"Arlington",
    "sg:classifiers":[
        {
            "category":"Restaurant",
            "type":"Food & Drink"
        }
    ],
    "sg:menulink":"http://www.allmenus.com/va/arlington/147541-subway/menu/",
    "sg:phone":"+1 703 979 7755",
    "sg:postcode":"22202",
    "sg:province":"VA",
    "sg:tags":[
        "american",
        "sandwich"
    ],
    "wof:name":"Subway",
    "wof:placetype":"venue"
},
  "geometry": {"coordinates":[-77.05389599999999,38.853349],"type":"Point"}
}