{
  "type": "Feature",
  "properties": {
    "addr:full":"1100 Front Royal Pike Winchester VA 22602",
    "addr:housenumber":"1100",
    "addr:postcode":"22602",
    "addr:street":"Front Royal Pike",
    "iso:country":"US",
    "sg:address":"1100 Front Royal Pike",
    "sg:city":"Winchester",
    "sg:classifiers":[
        {
            "category":"Local Transit",
            "type":"Transportation"
        }
    ],
    "sg:phone":"+1 540 722 2000",
    "sg:postcode":"22602",
    "sg:province":"VA",
    "sg:tags":[
        "limousine"
    ],
    "sg:website":"www.gemlimousine.com",
    "wof:name":"A Gem Limousine Svc",
    "wof:placetype":"venue"
},
  "geometry": {"coordinates":[-78.159735,39.135031],"type":"Point"}
}