{
  "type": "Feature",
  "properties": {
    "iso:country":"US",
    "sg:address":"709 N Allison St",
    "sg:city":"Richmond",
    "sg:classifiers":[
        {
            "category":"Personal",
            "subcategory":"Beauty Salon",
            "type":"Services"
        }
    ],
    "sg:phone":"+1 804 353 7900",
    "sg:postcode":"23220",
    "sg:province":"VA",
    "sg:tags":[
        "shop"
    ],
    "wof:name":"Art Of Hair",
    "wof:placetype":"venue"
},
  "geometry": {"coordinates":[-77.462453,37.557721],"type":"Point"}
}