{
  "type": "Feature",
  "properties": {
    "addr:full":"3543 W Braddock Rd Alexandria VA 22302",
    "addr:housenumber":"3543",
    "addr:postcode":"22302",
    "addr:street":"W Braddock Rd",
    "iso:country":"US",
    "sg:address":"3543 W Braddock Rd",
    "sg:city":"Alexandria",
    "sg:classifiers":[
        {
            "category":"Professional",
            "subcategory":"Engineering",
            "type":"Services"
        }
    ],
    "sg:phone":"+1 703 379 4500",
    "sg:postcode":"22302",
    "sg:province":"VA",
    "sg:tags":[
        "training",
        "system",
        "architectural",
        "engineer"
    ],
    "sg:website":"www.stattech.com",
    "wof:name":"Stat Tech Inc",
    "wof:placetype":"venue"
},
  "geometry": {"coordinates":[-77.090187,38.827135],"type":"Point"}
}