{
  "type": "Feature",
  "properties": {
    "addr:full":"7204 Sperryville Pike Boston VA 22713",
    "addr:housenumber":"7204",
    "addr:postcode":"22713",
    "addr:street":"Sperryville Pike",
    "iso:country":"US",
    "sg:address":"7204 Sperryville Pike",
    "sg:city":"Boston",
    "sg:classifiers":[
        {
            "category":"Building & Trades",
            "subcategory":"Landscaping Services",
            "type":"Services"
        }
    ],
    "sg:phone":"+1 540 547 3728",
    "sg:postcode":"22713",
    "sg:province":"VA",
    "sg:tags":[
        "personal"
    ],
    "wof:name":"Whited Tree Service & Hm Imprv",
    "wof:placetype":"venue"
},
  "geometry": {"coordinates":[-78.11105499999999,38.523908],"type":"Point"}
}