{
  "type": "Feature",
  "properties": {
    "iso:country":"US",
    "sg:address":"7005 Backlick Ct",
    "sg:city":"Springfield",
    "sg:classifiers":[
        {
            "category":"Organizations",
            "subcategory":"Professional Association",
            "type":"Services"
        }
    ],
    "sg:phone":"+1 703 642 9444",
    "sg:postcode":"22151",
    "sg:province":"VA",
    "wof:name":"Commercial Vehicle Training",
    "wof:placetype":"venue"
},
  "geometry": {"coordinates":[-77.18558299999999,38.801435],"type":"Point"}
}