{
  "type": "Feature",
  "properties": {
    "addr:full":"954 Holbrook Dr Newport News VA 23602",
    "addr:housenumber":"954",
    "addr:postcode":"23602",
    "addr:street":"Holbrook Dr",
    "iso:country":"US",
    "sg:address":"954 Holbrook Dr",
    "sg:city":"Newport News",
    "sg:classifiers":[
        {
            "category":"Professional",
            "subcategory":"Business Services",
            "type":"Services"
        }
    ],
    "sg:phone":"+1 757 876 8533",
    "sg:postcode":"23602",
    "sg:province":"VA",
    "wof:name":"Shirin Enterprises Inc",
    "wof:placetype":"venue"
},
  "geometry": {"coordinates":[-76.493753,37.122735],"type":"Point"}
}