{
  "type": "Feature",
  "properties": {
    "addr:full":"19807 Benhams Rd Bristol VA 24202",
    "addr:postcode":"19807;24202",
    "addr:street":"Benhams Rd",
    "iso:country":"US",
    "sg:address":"19807 Benhams Rd",
    "sg:city":"Bristol",
    "sg:classifiers":[
        {
            "category":"Retail",
            "subcategory":"Auto Repair",
            "type":"Services"
        }
    ],
    "sg:phone":"+1 276 466 4161",
    "sg:postcode":"24202",
    "sg:province":"VA",
    "sg:tags":[
        "body",
        "automobile",
        "painting"
    ],
    "wof:name":"Bobby Blaylock Body Shop",
    "wof:placetype":"venue"
},
  "geometry": {"coordinates":[-82.177981,36.665547],"type":"Point"}
}