{
  "type": "Feature",
  "properties": {
    "addr:full":"7734 Tea Table Dr Lorton VA 22079",
    "addr:housenumber":"7734",
    "addr:postcode":"22079",
    "addr:street":"Tea Table Dr",
    "iso:country":"US",
    "sg:address":"7734 Tea Table Dr",
    "sg:city":"Lorton",
    "sg:classifiers":[
        {
            "category":"Freight",
            "type":"Transportation"
        }
    ],
    "sg:phone":"+1 703 339 9393",
    "sg:postcode":"22079",
    "sg:province":"VA",
    "sg:tags":[
        "arrangement"
    ],
    "wof:name":"U M A C D C Inc",
    "wof:placetype":"venue"
},
  "geometry": {"coordinates":[-77.213033,38.704498],"type":"Point"}
}