{
  "type": "Feature",
  "properties": {
    "addr:full":"9094 Eclipse Dr Suffolk VA 23433",
    "addr:housenumber":"9094",
    "addr:postcode":"23433",
    "addr:street":"Eclipse Dr",
    "iso:country":"US",
    "sg:address":"9094 Eclipse Dr",
    "sg:city":"Suffolk",
    "sg:classifiers":[
        {
            "category":"Wholesale",
            "subcategory":"Non-durable Goods",
            "type":"Manufacturing & Wholesale Goods"
        }
    ],
    "sg:phone":"+1 757 238 8502",
    "sg:postcode":"23433",
    "sg:province":"VA",
    "wof:name":"Blue Ribbon Branch",
    "wof:placetype":"venue"
},
  "geometry": {"coordinates":[-76.48839099999999,36.91396],"type":"Point"}
}