{
  "type": "Feature",
  "properties": {
    "addr:full":"3239 Orange Ave NE Roanoke VA 24012",
    "addr:housenumber":"3239",
    "addr:postcode":"24012",
    "addr:street":"Orange Ave Ne",
    "iso:country":"US",
    "sg:address":"3239 Orange Ave NE",
    "sg:city":"Roanoke",
    "sg:classifiers":[
        {
            "category":"Home & Garden",
            "subcategory":"Household Appliances",
            "type":"Retail Goods"
        }
    ],
    "sg:phone":"+1 540 344 1048",
    "sg:postcode":"24012",
    "sg:province":"VA",
    "wof:name":"460 Appliance Center",
    "wof:placetype":"venue"
},
  "geometry": {"coordinates":[-79.895431,37.299273],"type":"Point"}
}