{
  "type": "Feature",
  "properties": {
    "addr:full":"12517 Hedges Run Dr Woodbridge VA 22192",
    "addr:housenumber":"12517",
    "addr:postcode":"22192",
    "addr:street":"Hedges Run Dr",
    "iso:country":"US",
    "sg:address":"12517 Hedges Run Dr",
    "sg:city":"Woodbridge",
    "sg:classifiers":[
        {
            "category":"Professional",
            "subcategory":"Computer Services",
            "type":"Services"
        }
    ],
    "sg:phone":"+1 703 494 1882",
    "sg:postcode":"22192",
    "sg:province":"VA",
    "sg:tags":[
        "related"
    ],
    "wof:name":"Sia Systems Information A",
    "wof:placetype":"venue"
},
  "geometry": {"coordinates":[-77.311212,38.681509],"type":"Point"}
}