{
  "type": "Feature",
  "properties": {
    "addr:full":"209 Laurel Hill Dr Stephens City VA 22655",
    "addr:housenumber":"209",
    "addr:postcode":"22655",
    "addr:street":"Laurel Hill Dr Stephens",
    "iso:country":"US",
    "sg:address":"209 Laurel Hill Dr",
    "sg:city":"Stephens City",
    "sg:classifiers":[
        {
            "category":"Professional",
            "subcategory":"Management & Consulting",
            "type":"Services"
        }
    ],
    "sg:phone":"+1 540 869 2261",
    "sg:postcode":"22655",
    "sg:province":"VA",
    "sg:tags":[
        "business"
    ],
    "wof:name":"Ruff Textile",
    "wof:placetype":"venue"
},
  "geometry": {"coordinates":[-78.183455,39.098303],"type":"Point"}
}