{
  "type": "Feature",
  "properties": {
    "addr:full":"1904 Byrd Ave Richmond VA 23230",
    "addr:housenumber":"1904",
    "addr:postcode":"23230",
    "addr:street":"Byrd Ave",
    "iso:country":"US",
    "sg:address":"1904 Byrd Ave",
    "sg:city":"Richmond",
    "sg:classifiers":[
        {
            "category":"Banks & Credit Unions",
            "subcategory":"Investment Brokerage",
            "type":"Services"
        }
    ],
    "sg:phone":"+1 804 285 2554",
    "sg:postcode":"23230",
    "sg:province":"VA",
    "sg:tags":[
        "trade",
        "barter",
        "exchange"
    ],
    "sg:website":"www.bancmarc.com",
    "wof:name":"Banc Marc",
    "wof:placetype":"venue"
},
  "geometry": {"coordinates":[-77.500497,37.584854],"type":"Point"}
}