{
  "type": "Feature",
  "properties": {
    "addr:full":"206 E Market St Leesburg VA 20176",
    "addr:housenumber":"206",
    "addr:postcode":"20176",
    "addr:street":"E Market St",
    "iso:country":"US",
    "sg:address":"206 E Market St",
    "sg:city":"Leesburg",
    "sg:classifiers":[
        {
            "category":"Home & Garden",
            "subcategory":"Hardware",
            "type":"Retail Goods"
        },
        {
            "category":"Home & Garden",
            "subcategory":"Furniture",
            "type":"Retail Goods"
        }
    ],
    "sg:phone":"+1 571 258 0880",
    "sg:postcode":"20176",
    "sg:province":"VA",
    "wof:name":"Home Specialty Store The Inc",
    "wof:placetype":"venue"
},
  "geometry": {"coordinates":[-77.561324,39.113938],"type":"Point"}
}