{
  "type": "Feature",
  "properties": {
    "addr:full":"17243 Big Island Hwy Big Island VA 24526",
    "addr:housenumber":"17243",
    "addr:postcode":"24526",
    "addr:street":"Big Island Hwy",
    "iso:country":"US",
    "sg:address":"17243 Big Island Hwy",
    "sg:city":"Big Island",
    "sg:classifiers":[
        {
            "category":"Shopping",
            "subcategory":"Bicycles & Sporting Goods",
            "type":"Retail Goods"
        }
    ],
    "sg:phone":"+1 434 299 5134",
    "sg:postcode":"24526",
    "sg:province":"VA",
    "wof:name":"Moreheads Gun Shop",
    "wof:placetype":"venue"
},
  "geometry": {"coordinates":[-79.37537500000001,37.535861],"type":"Point"}
}