{
  "type": "Feature",
  "properties": {
    "addr:full":"8300 Sudley Rd Manassas VA 20109",
    "addr:housenumber":"8300",
    "addr:postcode":"20109",
    "addr:street":"Sudley Rd",
    "iso:country":"US",
    "sg:address":"8300 Sudley Rd",
    "sg:city":"Manassas",
    "sg:classifiers":[
        {
            "category":"Shopping",
            "subcategory":"Hobbies, Toys, & Games",
            "type":"Retail Goods"
        }
    ],
    "sg:phone":"+1 703 257 7441",
    "sg:postcode":"20109",
    "sg:province":"VA",
    "sg:tags":[
        "toy",
        "store"
    ],
    "wof:name":"Eb Kids",
    "wof:placetype":"venue"
},
  "geometry": {"coordinates":[-77.50299800000001,38.775101],"type":"Point"}
}