{
  "type": "Feature",
  "properties": {
    "addr:full":"405 High Point Ave Virginia Beach VA 23451",
    "addr:housenumber":"405",
    "addr:postcode":"23451",
    "addr:street":"High Point Ave",
    "iso:country":"US",
    "sg:address":"405 High Point Ave",
    "sg:city":"Virginia Beach",
    "sg:classifiers":[
        {
            "category":"Professional",
            "subcategory":"Management & Consulting",
            "type":"Services"
        }
    ],
    "sg:phone":"+1 757 427 8559",
    "sg:postcode":"23451",
    "sg:province":"VA",
    "sg:tags":[
        "business"
    ],
    "wof:name":"Herb Maher",
    "wof:placetype":"venue"
},
  "geometry": {"coordinates":[-75.97631,36.833846],"type":"Point"}
}