{
  "type": "Feature",
  "properties": {
    "addr:full":"6517 Summerton Way Springfield VA 22150",
    "addr:housenumber":"6517",
    "addr:postcode":"22150",
    "addr:street":"Summerton Way",
    "iso:country":"US",
    "sg:address":"6517 Summerton Way",
    "sg:city":"Springfield",
    "sg:classifiers":[
        {
            "category":"Professional",
            "subcategory":"Computer Services",
            "type":"Services"
        }
    ],
    "sg:phone":"+1 703 971 1919",
    "sg:postcode":"22150",
    "sg:province":"VA",
    "sg:tags":[
        "internet"
    ],
    "wof:name":"Commercial Lynks Inc",
    "wof:placetype":"venue"
},
  "geometry": {"coordinates":[-77.166911,38.776967],"type":"Point"}
}