{
  "type": "Feature",
  "properties": {
    "iso:country":"US",
    "sg:address":"455 Merrimac Trl",
    "sg:city":"Williamsburg",
    "sg:classifiers":[
        {
            "category":"Cinema",
            "subcategory":"Movie Rental",
            "type":"Entertainment"
        }
    ],
    "sg:phone":"+1 757 253 2008",
    "sg:postcode":"23185",
    "sg:province":"VA",
    "sg:tags":[
        "leasing",
        "video",
        "disc",
        "tape"
    ],
    "wof:name":"Movie Time Video",
    "wof:placetype":"venue"
},
  "geometry": {"coordinates":[-76.679895,37.27395],"type":"Point"}
}