{
  "type": "Feature",
  "properties": {
    "iso:country":"US",
    "sg:address":"1809 William St",
    "sg:city":"Fredericksburg",
    "sg:classifiers":[
        {
            "category":"Real Estate",
            "subcategory":"Real Estate Agent",
            "type":"Services"
        }
    ],
    "sg:phone":"+1 540 373 2000",
    "sg:postcode":"22401",
    "sg:province":"VA",
    "sg:website":"www.century21team.com",
    "wof:name":"Team Real Estate",
    "wof:placetype":"venue"
},
  "geometry": {"coordinates":[-77.489197,38.296212],"type":"Point"}
}