{
  "type": "Feature",
  "properties": {
    "addr:full":"2432 Valley Ave Winchester VA 22601",
    "addr:housenumber":"2432",
    "addr:postcode":"22601",
    "addr:street":"Valley Ave",
    "iso:country":"US",
    "sg:address":"2432 Valley Ave",
    "sg:city":"Winchester",
    "sg:classifiers":[
        {
            "category":"Shopping",
            "type":"Retail Goods"
        }
    ],
    "sg:phone":"+1 540 667 9990",
    "sg:postcode":"22601",
    "sg:province":"VA",
    "sg:tags":[
        "merchandise"
    ],
    "wof:name":"Wahl Business Solutions Inc",
    "wof:placetype":"venue"
},
  "geometry": {"coordinates":[-78.185715,39.158784],"type":"Point"}
}