{
  "type": "Feature",
  "properties": {
    "addr:full":"43984 John Mosby Hwy Chantilly VA 20152",
    "addr:housenumber":"43984",
    "addr:postcode":"20152",
    "addr:street":"John Mosby Hwy",
    "iso:country":"US",
    "sg:address":"43984 John Mosby Hwy",
    "sg:city":"Chantilly",
    "sg:classifiers":[
        {
            "category":"Freight",
            "type":"Transportation"
        }
    ],
    "sg:phone":"+1 703 327 2550",
    "sg:postcode":"20152",
    "sg:province":"VA",
    "sg:tags":[
        "trucking"
    ],
    "wof:name":"Cedar Creek Haulers",
    "wof:placetype":"venue"
},
  "geometry": {"coordinates":[-77.475731,38.912279],"type":"Point"}
}