{
  "type": "Feature",
  "properties": {
    "addr:full":"1723 Wards Ferry Rd Lynchburg VA 24502",
    "addr:housenumber":"1723",
    "addr:postcode":"24502",
    "addr:street":"Wards Ferry Rd",
    "iso:country":"US",
    "sg:address":"1723 Wards Ferry Rd",
    "sg:city":"Lynchburg",
    "sg:classifiers":[
        {
            "category":"Organizations",
            "subcategory":"Religious Organization",
            "type":"Services"
        }
    ],
    "sg:phone":"+1 434 237 2034",
    "sg:postcode":"24502",
    "sg:province":"VA",
    "sg:tags":[
        "book"
    ],
    "wof:name":"Grace Bookstore",
    "wof:placetype":"venue"
},
  "geometry": {"coordinates":[-79.18991699999999,37.357593],"type":"Point"}
}