{
  "type": "Feature",
  "properties": {
    "addr:full":"1300 Roosevelt Blvd Portsmouth VA 23701",
    "addr:housenumber":"1300",
    "addr:postcode":"23701",
    "addr:street":"Roosevelt Blvd",
    "iso:country":"US",
    "sg:address":"1300 Roosevelt Blvd",
    "sg:city":"Portsmouth",
    "sg:classifiers":[
        {
            "category":"Organizations",
            "subcategory":"Religious Organization",
            "type":"Services"
        }
    ],
    "sg:phone":"+1 757 487 6495",
    "sg:postcode":"23701",
    "sg:province":"VA",
    "sg:tags":[
        "clergy"
    ],
    "wof:name":"Lonnie Mc Clain",
    "wof:placetype":"venue"
},
  "geometry": {"coordinates":[-76.37208099999999,36.792207],"type":"Point"}
}