{
  "type": "Feature",
  "properties": {
    "addr:full":"4100 Innslake Dr Glen Allen VA 23060",
    "addr:housenumber":"4100",
    "addr:postcode":"23060",
    "addr:street":"Innslake Dr",
    "iso:country":"US",
    "sg:address":"4100 Innslake Dr",
    "sg:city":"Glen Allen",
    "sg:classifiers":[
        {
            "category":"Travel",
            "subcategory":"Hotels & Motels",
            "type":"Entertainment"
        }
    ],
    "sg:phone":"+1 804 217 8000",
    "sg:postcode":"23060",
    "sg:province":"VA",
    "wof:name":"Homewood Suites",
    "wof:placetype":"venue"
},
  "geometry": {"coordinates":[-77.578975,37.649124],"type":"Point"}
}