{
  "type": "Feature",
  "properties": {
    "addr:full":"31 Sycolin Rd SE Leesburg VA 20175",
    "addr:housenumber":"31",
    "addr:postcode":"20175",
    "addr:street":"Sycolin Rd Se",
    "iso:country":"US",
    "sg:address":"31 Sycolin Rd SE",
    "sg:city":"Leesburg",
    "sg:classifiers":[
        {
            "category":"Professional",
            "subcategory":"Business Services",
            "type":"Services"
        }
    ],
    "sg:phone":"+1 703 669 5847",
    "sg:postcode":"20175",
    "sg:province":"VA",
    "sg:tags":[
        "inspection"
    ],
    "wof:name":"Construction Inspection Svc",
    "wof:placetype":"venue"
},
  "geometry": {"coordinates":[-77.554284,39.108376],"type":"Point"}
}