{
  "type": "Feature",
  "properties": {
    "addr:full":"4905 Radford Ave Ste 110 Richmond VA 23230",
    "addr:housenumber":"4905",
    "addr:postcode":"23230",
    "addr:street":"Radford Ave Ste 110",
    "iso:country":"US",
    "sg:address":"4905 Radford Ave Ste 110",
    "sg:city":"Richmond",
    "sg:classifiers":[
        {
            "category":"Professional",
            "subcategory":"Engineering",
            "type":"Services"
        },
        {
            "category":"Professional",
            "subcategory":"Management & Consulting",
            "type":"Services"
        },
        {
            "category":"Building & Trades",
            "subcategory":"Construction",
            "type":"Services"
        },
        {
            "category":"Professional",
            "subcategory":"Testing Lab",
            "type":"Services"
        }
    ],
    "sg:phone":"+1 804 358 3357",
    "sg:postcode":"23230",
    "sg:province":"VA",
    "sg:tags":[
        "asbestos",
        "consultant",
        "removal",
        "detection",
        "environmental",
        "ecological",
        "analytical",
        "laboratory",
        "engineer"
    ],
    "wof:name":"Work Environment Associates Inc",
    "wof:placetype":"venue"
},
  "geometry": {"coordinates":[-77.495018,37.58065],"type":"Point"}
}