{
  "type": "Feature",
  "properties": {
    "iso:country":"US",
    "sg:address":"211 N 18th St",
    "sg:city":"Richmond",
    "sg:classifiers":[
        {
            "category":"Real Estate",
            "subcategory":"Architect",
            "type":"Services"
        }
    ],
    "sg:phone":"+1 804 643 1019",
    "sg:postcode":"23223",
    "sg:province":"VA",
    "sg:tags":[
        "construction",
        "management",
        "design",
        "architectural"
    ],
    "wof:name":"Design Consortium Architecture",
    "wof:placetype":"venue"
},
  "geometry": {"coordinates":[-77.425151,37.535372],"type":"Point"}
}