{
  "type": "Feature",
  "properties": {
    "iso:country":"US",
    "sg:address":"6611 Lawndale Dr",
    "sg:city":"Falls Church",
    "sg:classifiers":[
        {
            "category":"Professional",
            "type":"Services"
        }
    ],
    "sg:phone":"+1 703 413 4111",
    "sg:postcode":"22042",
    "sg:province":"VA",
    "wof:name":"Adeena Corp",
    "wof:placetype":"venue"
},
  "geometry": {"coordinates":[-77.17067400000001,38.872254],"type":"Point"}
}