{
  "type": "Feature",
  "properties": {
    "addr:full":"1601 N Kent St Ste 100 Arlington VA 22209",
    "addr:housenumber":"1601",
    "addr:postcode":"22209",
    "addr:street":"N Kent St Ste 100",
    "iso:country":"US",
    "sg:address":"1601 N Kent St Ste 100",
    "sg:city":"Arlington",
    "sg:classifiers":[
        {
            "category":"Autos & Motor Vehicles",
            "subcategory":"Automobile Sales",
            "type":"Retail Goods"
        }
    ],
    "sg:phone":"+1 703 778 9400",
    "sg:postcode":"22209",
    "sg:province":"VA",
    "sg:tags":[
        "new",
        "car"
    ],
    "sg:website":"http://www.kjaergroup.com",
    "wof:name":"Kjaer Group (Us Liaison Office), Inc",
    "wof:placetype":"venue"
},
  "geometry": {"coordinates":[-77.069351,38.89476],"type":"Point"}
}