{
  "type": "Feature",
  "properties": {
    "addr:full":"1101 Sam Perry Blvd Fredericksburg VA 22401",
    "addr:housenumber":"1101",
    "addr:postcode":"22401",
    "addr:street":"Sam Perry Blvd",
    "iso:country":"US",
    "sg:address":"1101 Sam Perry Blvd",
    "sg:city":"Fredericksburg",
    "sg:classifiers":[
        {
            "category":"Health Services",
            "subcategory":"Doctor",
            "type":"Services"
        },
        {
            "category":"Health Services",
            "subcategory":"Medical Lab",
            "type":"Services"
        }
    ],
    "sg:phone":"+1 804 448 0198",
    "sg:postcode":"22401",
    "sg:province":"VA",
    "sg:tags":[
        "laboratory"
    ],
    "wof:name":"Mary Washington Hospital Lab",
    "wof:placetype":"venue"
},
  "geometry": {"coordinates":[-77.481408,38.310704],"type":"Point"}
}