{
  "type": "Feature",
  "properties": {
    "addr:full":"604 Chase Ave Chase City VA 23924",
    "addr:housenumber":"604",
    "addr:postcode":"23924",
    "addr:street":"Chase Ave",
    "iso:country":"US",
    "sg:address":"604 Chase Ave",
    "sg:city":"Chase City",
    "sg:classifiers":[
        {
            "category":"Professional",
            "type":"Services"
        }
    ],
    "sg:phone":"+1 434 372 5005",
    "sg:postcode":"23924",
    "sg:province":"VA",
    "wof:name":"Apple Delight",
    "wof:placetype":"venue"
},
  "geometry": {"coordinates":[-78.44571500000001,36.800798],"type":"Point"}
}