{
  "type": "Feature",
  "properties": {
    "iso:country":"US",
    "sg:address":"1988 Cook Rd",
    "sg:city":"Powhatan",
    "sg:classifiers":[
        {
            "category":"Organizations",
            "subcategory":"Membership Organization",
            "type":"Services"
        }
    ],
    "sg:phone":"+1 757 340 0162",
    "sg:postcode":"23139",
    "sg:province":"VA",
    "wof:name":"Virginia Pigeon & Dove Assn",
    "wof:placetype":"venue"
},
  "geometry": {"coordinates":[-78.05325999999999,37.519263],"type":"Point"}
}