{
  "type": "Feature",
  "properties": {
    "addr:full":"5279 Homegrown Ln Zuni VA 23898",
    "addr:housenumber":"5279",
    "addr:postcode":"23898",
    "addr:street":"Homegrown Ln",
    "iso:country":"US",
    "sg:address":"5279 Homegrown Ln",
    "sg:city":"Zuni",
    "sg:classifiers":[
        {
            "category":"Social Services",
            "type":"Services"
        }
    ],
    "sg:phone":"+1 757 242 4408",
    "sg:postcode":"23898",
    "sg:province":"VA",
    "wof:name":"Southeastern Virginia Areawide",
    "wof:placetype":"venue"
},
  "geometry": {"coordinates":[-76.833782,36.834919],"type":"Point"}
}