{
  "type": "Feature",
  "properties": {
    "iso:country":"US",
    "sg:address":"18447 Forest Rd",
    "sg:city":"Lynchburg",
    "sg:classifiers":[
        {
            "category":"Professional",
            "subcategory":"Computer Services",
            "type":"Services"
        }
    ],
    "sg:phone":"+1 434 385 6020",
    "sg:postcode":"24502",
    "sg:province":"VA",
    "sg:tags":[
        "programming",
        "integration"
    ],
    "sg:website":"www.databasesystems.com",
    "wof:name":"Database Computer Systems",
    "wof:placetype":"venue"
},
  "geometry": {"coordinates":[-79.246072,37.382638],"type":"Point"}
}