{
  "type": "Feature",
  "properties": {
    "iso:country":"US",
    "sg:address":"8517 Rixlew Ln",
    "sg:city":"Manassas",
    "sg:classifiers":[
        {
            "category":"Insurance",
            "subcategory":"Health Insurance",
            "type":"Services"
        }
    ],
    "sg:phone":"+1 703 368 6801",
    "sg:postcode":"20109",
    "sg:province":"VA",
    "sg:tags":[
        "carrier"
    ],
    "wof:name":"R C Spears Jr",
    "wof:placetype":"venue"
},
  "geometry": {"coordinates":[-77.50282,38.771423],"type":"Point"}
}