{
  "type": "Feature",
  "properties": {
    "addr:full":"450 S Church St Fincastle VA 24090",
    "addr:housenumber":"450",
    "addr:postcode":"24090",
    "addr:street":"S Church St",
    "iso:country":"US",
    "sg:address":"450 S Church St",
    "sg:city":"Fincastle",
    "sg:classifiers":[
        {
            "category":"Social Services",
            "type":"Services"
        }
    ],
    "sg:phone":"+1 540 473 2056",
    "sg:postcode":"24090",
    "sg:province":"VA",
    "sg:tags":[
        "probation"
    ],
    "wof:name":"Probation & Parole District 40",
    "wof:placetype":"venue"
},
  "geometry": {"coordinates":[-79.876925,37.492477],"type":"Point"}
}