{
  "type": "Feature",
  "properties": {
    "addr:full":"13100 Ramblewood Dr Chester VA 23836",
    "addr:housenumber":"13100",
    "addr:postcode":"23836",
    "addr:street":"Ramblewood Dr",
    "iso:country":"US",
    "sg:address":"13100 Ramblewood Dr",
    "sg:city":"Chester",
    "sg:classifiers":[
        {
            "category":"Wholesale",
            "subcategory":"Groceries",
            "type":"Manufacturing & Wholesale Goods"
        }
    ],
    "sg:phone":"+1 804 796 6867",
    "sg:postcode":"23836",
    "sg:province":"VA",
    "sg:tags":[
        "general"
    ],
    "wof:name":"Schwans Home Service Inc",
    "wof:placetype":"venue"
},
  "geometry": {"coordinates":[-77.39183199999999,37.347324],"type":"Point"}
}