{
  "type": "Feature",
  "properties": {
    "addr:full":"680 Snider Branch Rd Marion VA 24354",
    "addr:housenumber":"680",
    "addr:postcode":"24354",
    "addr:street":"Snider Branch Rd",
    "iso:country":"US",
    "sg:address":"680 Snider Branch Rd",
    "sg:city":"Marion",
    "sg:classifiers":[
        {
            "category":"Professional",
            "type":"Services"
        }
    ],
    "sg:phone":"+1 276 783 5548",
    "sg:postcode":"24354",
    "sg:province":"VA",
    "wof:name":"Groseclose",
    "wof:placetype":"venue"
},
  "geometry": {"coordinates":[-81.468462,36.875881],"type":"Point"}
}