{
  "type": "Feature",
  "properties": {
    "addr:full":"1207 Richeson Ave Richmond VA 23224",
    "addr:housenumber":"1207",
    "addr:postcode":"23224",
    "addr:street":"Richeson Ave",
    "iso:country":"US",
    "sg:address":"1207 Richeson Ave",
    "sg:city":"Richmond",
    "sg:classifiers":[
        {
            "category":"Professional",
            "type":"Services"
        }
    ],
    "sg:phone":"+1 804 560 0504",
    "sg:postcode":"23224",
    "sg:province":"VA",
    "sg:tags":[
        "establishment"
    ],
    "wof:name":"Home Suite Home",
    "wof:placetype":"venue"
},
  "geometry": {"coordinates":[-77.462737,37.497849],"type":"Point"}
}