{
  "type": "Feature",
  "properties": {
    "addr:full":"2941 Chain Bridge Rd Oakton VA 22124",
    "addr:housenumber":"2941",
    "addr:postcode":"22124",
    "addr:street":"Chain Bridge Rd",
    "iso:country":"US",
    "sg:address":"2941 Chain Bridge Rd",
    "sg:city":"Oakton",
    "sg:classifiers":[
        {
            "category":"Banks & Credit Unions",
            "subcategory":"Bank",
            "type":"Services"
        }
    ],
    "sg:phone":"+1 703 241 3495",
    "sg:postcode":"22124",
    "sg:province":"VA",
    "sg:tags":[
        "state"
    ],
    "wof:name":"First Virginia",
    "wof:placetype":"venue"
},
  "geometry": {"coordinates":[-77.300673,38.88099],"type":"Point"}
}