{
  "type": "Feature",
  "properties": {
    "addr:full":"6621 Debra Lu Way Springfield VA 22150",
    "addr:housenumber":"6621",
    "addr:postcode":"22150",
    "addr:street":"Debra Lu Way",
    "iso:country":"US",
    "sg:address":"6621 Debra Lu Way",
    "sg:city":"Springfield",
    "sg:classifiers":[
        {
            "category":"Building & Trades",
            "subcategory":"Construction",
            "type":"Services"
        }
    ],
    "sg:phone":"+1 703 922 9401",
    "sg:postcode":"22150",
    "sg:province":"VA",
    "sg:tags":[
        "designer",
        "dealer",
        "pool",
        "swimming"
    ],
    "wof:name":"Greenwood Pool",
    "wof:placetype":"venue"
},
  "geometry": {"coordinates":[-77.15883100000001,38.776428],"type":"Point"}
}