{
  "type": "Feature",
  "properties": {
    "iso:country":"US",
    "sg:address":"5010 Eddings Dr",
    "sg:city":"Glen Allen",
    "sg:classifiers":[
        {
            "category":"Real Estate",
            "subcategory":"Surveying",
            "type":"Services"
        }
    ],
    "sg:phone":"+1 804 965 9055",
    "sg:postcode":"23060",
    "sg:province":"VA",
    "sg:tags":[
        "surveyor"
    ],
    "wof:name":"W Allen Brown",
    "wof:placetype":"venue"
},
  "geometry": {"coordinates":[-77.55720700000001,37.659325],"type":"Point"}
}