{
  "type": "Feature",
  "properties": {
    "iso:country":"US",
    "sg:address":"10030 Scenic View Ter",
    "sg:city":"Vienna",
    "sg:classifiers":[
        {
            "category":"Professional",
            "subcategory":"Business Services",
            "type":"Services"
        }
    ],
    "sg:phone":"+1 703 759 5770",
    "sg:postcode":"22182",
    "sg:province":"VA",
    "wof:name":"Kathleen L Ballard",
    "wof:placetype":"venue"
},
  "geometry": {"coordinates":[-77.293139,38.966535],"type":"Point"}
}