{
  "type": "Feature",
  "properties": {
    "addr:full":"7600 Tremayne Pl Mc Lean VA 22102",
    "addr:postcode":"7600;22102",
    "addr:street":"Tremayne Pl Mc Lean",
    "iso:country":"US",
    "sg:address":"7600 Tremayne Pl",
    "sg:city":"Mc Lean",
    "sg:classifiers":[
        {
            "category":"Professional",
            "subcategory":"Accounting & Tax Preparation",
            "type":"Services"
        }
    ],
    "sg:phone":"+1 703 893 5708",
    "sg:postcode":"22102",
    "sg:province":"VA",
    "sg:tags":[
        "return",
        "filing"
    ],
    "wof:name":"Hermanek Stover Assoc",
    "wof:placetype":"venue"
},
  "geometry": {"coordinates":[-77.209103,38.919411],"type":"Point"}
}