{
  "type": "Feature",
  "properties": {
    "addr:full":"110 Landridge Ct Newport News VA 23608",
    "addr:housenumber":"110",
    "addr:postcode":"23608",
    "addr:street":"Landridge Ct",
    "iso:country":"US",
    "sg:address":"110 Landridge Ct",
    "sg:city":"Newport News",
    "sg:classifiers":[
        {
            "category":"Building & Trades",
            "subcategory":"Landscaping Services",
            "type":"Services"
        }
    ],
    "sg:phone":"+1 757 875 4263",
    "sg:postcode":"23608",
    "sg:province":"VA",
    "wof:name":"Frazier Lawn Care",
    "wof:placetype":"venue"
},
  "geometry": {"coordinates":[-76.52278800000001,37.145591],"type":"Point"}
}