{
  "type": "Feature",
  "properties": {
    "addr:full":"3004 Linden Dr Bristol VA 24202",
    "addr:housenumber":"3004",
    "addr:postcode":"24202",
    "addr:street":"Linden Dr",
    "iso:country":"US",
    "sg:address":"3004 Linden Dr",
    "sg:city":"Bristol",
    "sg:classifiers":[
        {
            "category":"Cinema",
            "subcategory":"Movie Theater",
            "type":"Entertainment"
        }
    ],
    "sg:phone":"+1 276 669 0588",
    "sg:postcode":"24202",
    "sg:province":"VA",
    "wof:name":"Tinseltown USA",
    "wof:placetype":"venue"
},
  "geometry": {"coordinates":[-82.130882,36.628498],"type":"Point"}
}