{
  "type": "Feature",
  "properties": {
    "addr:full":"32 Bedford Dr Sterling VA 20165",
    "addr:housenumber":"32",
    "addr:postcode":"20165",
    "addr:street":"Bedford Dr",
    "iso:country":"US",
    "sg:address":"32 Bedford Dr",
    "sg:city":"Sterling",
    "sg:classifiers":[
        {
            "category":"Building & Trades",
            "subcategory":"Construction",
            "type":"Services"
        }
    ],
    "sg:phone":"+1 703 406 7560",
    "sg:postcode":"20165",
    "sg:province":"VA",
    "sg:tags":[
        "home",
        "general",
        "remodeling",
        "family",
        "contractor"
    ],
    "wof:name":"Cali Nova Builders",
    "wof:placetype":"venue"
},
  "geometry": {"coordinates":[-77.411911,39.054232],"type":"Point"}
}