{
  "type": "Feature",
  "properties": {
    "addr:full":"12205 S Crater Rd Petersburg VA 23805",
    "addr:housenumber":"12205",
    "addr:postcode":"23805",
    "addr:street":"S Crater Rd",
    "iso:country":"US",
    "sg:address":"12205 S Crater Rd",
    "sg:city":"Petersburg",
    "sg:classifiers":[
        {
            "category":"Travel",
            "subcategory":"Hotels & Motels",
            "type":"Entertainment"
        }
    ],
    "sg:phone":"+1 804 733 0600",
    "sg:postcode":"23805",
    "sg:province":"VA",
    "sg:tags":[
        "operation",
        "eating",
        "drinking"
    ],
    "wof:name":"Steven Kent Best Western",
    "wof:placetype":"venue"
},
  "geometry": {"coordinates":[-77.35858500000001,37.146456],"type":"Point"}
}