{
  "type": "Feature",
  "properties": {
    "addr:full":"2725 Franklin Tpke Danville VA 24540",
    "addr:housenumber":"2725",
    "addr:postcode":"24540",
    "addr:street":"Franklin Tpke",
    "iso:country":"US",
    "sg:address":"2725 Franklin Tpke",
    "sg:city":"Danville",
    "sg:classifiers":[
        {
            "category":"Sports & Exercise",
            "subcategory":"Gym",
            "type":"Entertainment"
        }
    ],
    "sg:phone":"+1 434 836 1187",
    "sg:postcode":"24540",
    "sg:province":"VA",
    "sg:tags":[
        "club",
        "health",
        "studio",
        "gymnasium"
    ],
    "wof:name":"Curves For Women",
    "wof:placetype":"venue"
},
  "geometry": {"coordinates":[-79.411427,36.658204],"type":"Point"}
}