{
  "type": "Feature",
  "properties": {
    "addr:full":"6808 Loisdale Rd Springfield VA 22150",
    "addr:housenumber":"6808",
    "addr:postcode":"22150",
    "addr:street":"Loisdale Rd",
    "iso:country":"US",
    "sg:address":"6808 Loisdale Rd",
    "sg:city":"Springfield",
    "sg:classifiers":[
        {
            "category":"Government",
            "subcategory":"Office",
            "type":"Public Place"
        }
    ],
    "sg:phone":"+1 703 305 7359",
    "sg:postcode":"22150",
    "sg:province":"VA",
    "sg:tags":[
        "federal"
    ],
    "wof:name":"US General Svc Adm",
    "wof:placetype":"venue"
},
  "geometry": {"coordinates":[-77.182362,38.767752],"type":"Point"}
}