{
  "type": "Feature",
  "properties": {
    "addr:full":"319 Cameron St Fl 2 Alexandria VA 22314",
    "addr:housenumber":"319;2",
    "addr:postcode":"22314",
    "addr:street":"Cameron St",
    "iso:country":"US",
    "sg:address":"319 Cameron St Fl 2",
    "sg:city":"Alexandria",
    "sg:classifiers":[
        {
            "category":"Travel",
            "subcategory":"Travel Agent",
            "type":"Entertainment"
        },
        {
            "category":"Landmark",
            "subcategory":"Tourist Information",
            "type":"Public Place"
        }
    ],
    "sg:phone":"+1 703 683 6040",
    "sg:postcode":"22314",
    "sg:province":"VA",
    "sg:tags":[
        "agency",
        "services-commercial",
        "tours-operators",
        "promoter"
    ],
    "sg:website":"http://www.blueheart.com",
    "wof:name":"Blue Heart Travel",
    "wof:placetype":"venue"
},
  "geometry": {"coordinates":[-77.042496,38.805666],"type":"Point"}
}