{
  "type": "Feature",
  "properties": {
    "addr:full":"3866 Whitetop Rd Chilhowie VA 24319",
    "addr:housenumber":"3866",
    "addr:postcode":"24319",
    "addr:street":"Whitetop Rd",
    "iso:country":"US",
    "sg:address":"3866 Whitetop Rd",
    "sg:city":"Chilhowie",
    "sg:classifiers":[
        {
            "category":"Shopping",
            "subcategory":"Bicycles & Sporting Goods",
            "type":"Retail Goods"
        }
    ],
    "sg:phone":"+1 276 646 8817",
    "sg:postcode":"24319",
    "sg:province":"VA",
    "wof:name":"Hopkins Gun Shop",
    "wof:placetype":"venue"
},
  "geometry": {"coordinates":[-81.63871399999999,36.719209],"type":"Point"}
}