{
  "type": "Feature",
  "properties": {
    "iso:country":"US",
    "sg:address":"1754 S Jefferson Davis Hwy",
    "sg:city":"Arlington",
    "sg:classifiers":[
        {
            "category":"Professional",
            "subcategory":"Management & Consulting",
            "type":"Services"
        }
    ],
    "sg:phone":"+1 703 245 2491",
    "sg:postcode":"22202",
    "sg:province":"VA",
    "wof:name":"Perot Systems Government Svcs",
    "wof:placetype":"venue"
},
  "geometry": {"coordinates":[-77.052057,38.859746],"type":"Point"}
}