{
  "type": "Feature",
  "properties": {
    "iso:country":"US",
    "sg:address":"7205 Wimsatt Rd",
    "sg:city":"Springfield",
    "sg:classifiers":[
        {
            "category":"Manufacturing",
            "subcategory":"Printing",
            "type":"Manufacturing & Wholesale Goods"
        }
    ],
    "sg:phone":"+1 703 813 5900",
    "sg:postcode":"22151",
    "sg:province":"VA",
    "sg:tags":[
        "newspaper"
    ],
    "wof:name":"Greater Washington Publishing",
    "wof:placetype":"venue"
},
  "geometry": {"coordinates":[-77.19036,38.799666],"type":"Point"}
}