{
  "type": "Feature",
  "properties": {
    "addr:full":"10205 Beach Mill Rd Great Falls VA 22066",
    "addr:housenumber":"10205",
    "addr:postcode":"22066",
    "addr:street":"Beach Mill Rd",
    "iso:country":"US",
    "sg:address":"10205 Beach Mill Rd",
    "sg:city":"Great Falls",
    "sg:classifiers":[
        {
            "category":"Banks & Credit Unions",
            "subcategory":"Financial Services",
            "type":"Services"
        }
    ],
    "sg:phone":"+1 703 759 7646",
    "sg:postcode":"22066",
    "sg:province":"VA",
    "sg:tags":[
        "investor"
    ],
    "wof:name":"Et Investments LLC",
    "wof:placetype":"venue"
},
  "geometry": {"coordinates":[-77.29734500000001,39.028912],"type":"Point"}
}