{
  "type": "Feature",
  "properties": {
    "addr:full":"6559 Brookfield Rd Roanoke VA 24019",
    "addr:housenumber":"6559",
    "addr:postcode":"24019",
    "addr:street":"Brookfield Rd",
    "iso:country":"US",
    "sg:address":"6559 Brookfield Rd",
    "sg:city":"Roanoke",
    "sg:classifiers":[
        {
            "category":"Building & Trades",
            "subcategory":"Construction",
            "type":"Services"
        }
    ],
    "sg:phone":"+1 540 362 0495",
    "sg:postcode":"24019",
    "sg:province":"VA",
    "sg:tags":[
        "carpentry",
        "contractor"
    ],
    "wof:name":"Parrish Lewis Wayne Inc",
    "wof:placetype":"venue"
},
  "geometry": {"coordinates":[-79.966041,37.349605],"type":"Point"}
}