{
  "type": "Feature",
  "properties": {
    "addr:full":"1000 Twinridge Ln Richmond VA 23235",
    "addr:housenumber":"1000",
    "addr:postcode":"23235",
    "addr:street":"Twinridge Ln",
    "iso:country":"US",
    "sg:address":"1000 Twinridge Ln",
    "sg:city":"Richmond",
    "sg:classifiers":[
        {
            "category":"Social Services",
            "subcategory":"Job Training",
            "type":"Services"
        },
        {
            "category":"Health Services",
            "subcategory":"Nursing And Care Facility",
            "type":"Services"
        },
        {
            "category":"Social Services",
            "subcategory":"Adult Care",
            "type":"Services"
        },
        {
            "category":"Social Services",
            "subcategory":"Retirement Home",
            "type":"Services"
        }
    ],
    "sg:phone":"+1 804 327 1990",
    "sg:postcode":"23235",
    "sg:province":"VA",
    "sg:tags":[
        "living",
        "homes-skilled",
        "people",
        "personal",
        "assisted",
        "community",
        "alzheimer's",
        "convalescent",
        "centers-adult",
        "rest",
        "homes-elderly",
        "elder",
        "day"
    ],
    "sg:website":"http://www.elmcroftal.com",
    "wof:name":"Elmcroft Of Chesterfield",
    "wof:placetype":"venue"
},
  "geometry": {"coordinates":[-77.549053,37.500247],"type":"Point"}
}