{
  "type": "Feature",
  "properties": {
    "addr:full":"204 W Riverside Dr Timberville VA 22853",
    "addr:housenumber":"204",
    "addr:postcode":"22853",
    "addr:street":"W Riverside Dr",
    "iso:country":"US",
    "sg:address":"204 W Riverside Dr",
    "sg:city":"Timberville",
    "sg:classifiers":[
        {
            "category":"Health Services",
            "subcategory":"Doctor",
            "type":"Services"
        }
    ],
    "sg:phone":"+1 540 896 5351",
    "sg:postcode":"22853",
    "sg:province":"VA",
    "wof:name":"Alan Robbins Dr",
    "wof:placetype":"venue"
},
  "geometry": {"coordinates":[-78.776765,38.635113],"type":"Point"}
}