{
  "type": "Feature",
  "properties": {
    "iso:country":"US",
    "sg:address":"100 5th St SE",
    "sg:city":"Charlottesville",
    "sg:classifiers":[
        {
            "category":"Health Services",
            "subcategory":"Health Practitioner",
            "type":"Services"
        }
    ],
    "sg:phone":"+1 434 971 4080",
    "sg:postcode":"22902",
    "sg:province":"VA",
    "sg:tags":[
        "psychologist"
    ],
    "wof:name":"Jungian Analysts",
    "wof:placetype":"venue"
},
  "geometry": {"coordinates":[-78.478864,38.029081],"type":"Point"}
}