{
  "type": "Feature",
  "properties": {
    "addr:full":"2903 Mount Vernon Ave Alexandria VA 22305",
    "addr:housenumber":"2903",
    "addr:postcode":"22305",
    "addr:street":"Mount Vernon Ave",
    "iso:country":"US",
    "sg:address":"2903 Mount Vernon Ave",
    "sg:city":"Alexandria",
    "sg:classifiers":[
        {
            "category":"Building & Trades",
            "subcategory":"Locksmith",
            "type":"Services"
        }
    ],
    "sg:phone":"+1 703 842 7300",
    "sg:postcode":"22305",
    "sg:province":"VA",
    "sg:tags":[
        "key"
    ],
    "wof:name":"1 24 Hour 7 Day A Emerg Locksmith",
    "wof:placetype":"venue"
},
  "geometry": {"coordinates":[-77.059307,38.830867],"type":"Point"}
}