{
  "type": "Feature",
  "properties": {
    "iso:country":"US",
    "sg:address":"3536 Brambleton Ave",
    "sg:city":"Roanoke",
    "sg:classifiers":[
        {
            "category":"Home & Garden",
            "subcategory":"Furniture",
            "type":"Retail Goods"
        }
    ],
    "sg:phone":"+1 540 774 2017",
    "sg:postcode":"24018",
    "sg:province":"VA",
    "wof:name":"Harbor Group",
    "wof:placetype":"venue"
},
  "geometry": {"coordinates":[-80.000387,37.237557],"type":"Point"}
}