{
  "type": "Feature",
  "properties": {
    "iso:country":"US",
    "sg:address":"8300 Old Courthouse Rd Ste 140",
    "sg:city":"Vienna",
    "sg:classifiers":[
        {
            "category":"Health Services",
            "subcategory":"Doctor",
            "type":"Services"
        }
    ],
    "sg:phone":"+1 703 448 0885",
    "sg:postcode":"22182",
    "sg:province":"VA",
    "sg:tags":[
        "obstetrician",
        "gynecologist"
    ],
    "wof:name":"Parks Annalisa Mulhollen MD",
    "wof:placetype":"venue"
},
  "geometry": {"coordinates":[-77.23110200000001,38.9137],"type":"Point"}
}