{
  "type": "Feature",
  "properties": {
    "addr:full":"1670 Daniels Creek Rd Collinsville VA 24078",
    "addr:housenumber":"1670",
    "addr:postcode":"24078",
    "addr:street":"Daniels Creek Rd",
    "iso:country":"US",
    "sg:address":"1670 Daniels Creek Rd",
    "sg:city":"Collinsville",
    "sg:classifiers":[
        {
            "category":"Organizations",
            "subcategory":"Religious Organization",
            "type":"Services"
        }
    ],
    "sg:phone":"+1 276 647 8802",
    "sg:postcode":"24078",
    "sg:province":"VA",
    "wof:name":"Collinsville Baptist Church",
    "wof:placetype":"venue"
},
  "geometry": {"coordinates":[-79.917728,36.712406],"type":"Point"}
}