{
  "type": "Feature",
  "properties": {
    "addr:full":"4238 Wilson Blvd Arlington VA 22203",
    "addr:housenumber":"4238",
    "addr:postcode":"22203",
    "addr:street":"Wilson Blvd",
    "iso:country":"US",
    "sg:address":"4238 Wilson Blvd",
    "sg:city":"Arlington",
    "sg:classifiers":[
        {
            "category":"Shopping",
            "subcategory":"Department Store",
            "type":"Retail Goods"
        }
    ],
    "sg:phone":"+1 703 525 1720",
    "sg:postcode":"22203",
    "sg:province":"VA",
    "sg:website":"www.macys.com",
    "wof:name":"Macy's",
    "wof:placetype":"venue"
},
  "geometry": {"coordinates":[-77.11089699999999,38.879623],"type":"Point"}
}