{
  "type": "Feature",
  "properties": {
    "addr:full":"1117 19th St N Arlington VA 22209",
    "addr:housenumber":"1117",
    "addr:postcode":"22209",
    "addr:street":"19Th St N",
    "iso:country":"US",
    "sg:address":"1117 19th St N",
    "sg:city":"Arlington",
    "sg:classifiers":[
        {
            "category":"Professional",
            "subcategory":"Management & Consulting",
            "type":"Services"
        }
    ],
    "sg:phone":"+1 703 243 6908",
    "sg:postcode":"22209",
    "sg:province":"VA",
    "sg:tags":[
        "consultant",
        "business"
    ],
    "wof:name":"Webglyphs",
    "wof:placetype":"venue"
},
  "geometry": {"coordinates":[-77.07068099999999,38.897194],"type":"Point"}
}