{
  "type": "Feature",
  "properties": {
    "addr:full":"5121 S Lake Rd Virginia Beach VA 23455",
    "addr:housenumber":"5121",
    "addr:postcode":"23455",
    "addr:street":"S Lake Rd",
    "iso:country":"US",
    "sg:address":"5121 S Lake Rd",
    "sg:city":"Virginia Beach",
    "sg:classifiers":[
        {
            "category":"Building & Trades",
            "subcategory":"Construction",
            "type":"Services"
        }
    ],
    "sg:phone":"+1 757 318 7381",
    "sg:postcode":"23455",
    "sg:province":"VA",
    "sg:tags":[
        "contractor"
    ],
    "wof:name":"Bay Lake Construction",
    "wof:placetype":"venue"
},
  "geometry": {"coordinates":[-76.155232,36.900428],"type":"Point"}
}