{
  "type": "Feature",
  "properties": {
    "addr:full":"100 Laurel Pkwy Colonial Heights VA 23834",
    "addr:housenumber":"100",
    "addr:postcode":"23834",
    "addr:street":"Laurel Pkwy",
    "iso:country":"US",
    "sg:address":"100 Laurel Pkwy",
    "sg:city":"Colonial Heights",
    "sg:classifiers":[
        {
            "category":"Building & Trades",
            "subcategory":"Construction",
            "type":"Services"
        }
    ],
    "sg:phone":"+1 804 526 3115",
    "sg:postcode":"23834",
    "sg:province":"VA",
    "sg:tags":[
        "maker",
        "cabinet"
    ],
    "wof:name":"L M Gravitte & Son Inc",
    "wof:placetype":"venue"
},
  "geometry": {"coordinates":[-77.410096,37.261836],"type":"Point"}
}