{
  "type": "Feature",
  "properties": {
    "iso:country":"US",
    "sg:address":"20381 Evergreen Mills Rd",
    "sg:city":"Leesburg",
    "sg:classifiers":[
        {
            "category":"Professional",
            "type":"Services"
        }
    ],
    "sg:phone":"+1 703 669 1838",
    "sg:postcode":"20175",
    "sg:province":"VA",
    "wof:name":"Dirienzo Limited LLC",
    "wof:placetype":"venue"
},
  "geometry": {"coordinates":[-77.57644000000001,39.056379],"type":"Point"}
}