{
  "type": "Feature",
  "properties": {
    "addr:full":"1582 Mud Pike Christiansburg VA 24073",
    "addr:housenumber":"1582",
    "addr:postcode":"24073",
    "addr:street":"Mud Pike",
    "iso:country":"US",
    "sg:address":"1582 Mud Pike",
    "sg:city":"Christiansburg",
    "sg:classifiers":[
        {
            "category":"Retail",
            "subcategory":"Veterinary Services",
            "type":"Services"
        }
    ],
    "sg:phone":"+1 540 382 1891",
    "sg:postcode":"24073",
    "sg:province":"VA",
    "sg:tags":[
        "clinic",
        "hospital"
    ],
    "wof:name":"Four Paws Veterinary Rehabilitation Service",
    "wof:placetype":"venue"
},
  "geometry": {"coordinates":[-80.428966,37.116859],"type":"Point"}
}