{
  "type": "Feature",
  "properties": {
    "addr:full":"2333 Willis Rd Richmond VA 23237",
    "addr:housenumber":"2333",
    "addr:postcode":"23237",
    "addr:street":"Willis Rd",
    "iso:country":"US",
    "sg:address":"2333 Willis Rd",
    "sg:city":"Richmond",
    "sg:classifiers":[
        {
            "category":"Food & Beverages",
            "subcategory":"Groceries & Convenience Stores",
            "type":"Retail Goods"
        },
        {
            "category":"Autos & Motor Vehicles",
            "subcategory":"Fuel & Gas Station",
            "type":"Retail Goods"
        }
    ],
    "sg:phone":"+1 804 271 4010",
    "sg:postcode":"23237",
    "sg:province":"VA",
    "sg:tags":[
        "oil"
    ],
    "wof:name":"Chevron Food Mart",
    "wof:placetype":"venue"
},
  "geometry": {"coordinates":[-77.425833,37.401121],"type":"Point"}
}