{
  "type": "Feature",
  "properties": {
    "addr:full":"327 W Main St Charlottesville VA 22903",
    "addr:housenumber":"327",
    "addr:postcode":"22903",
    "addr:street":"W Main St",
    "iso:country":"US",
    "sg:address":"327 W Main St",
    "sg:city":"Charlottesville",
    "sg:classifiers":[
        {
            "category":"Organizations",
            "subcategory":"Non-profit Organization",
            "type":"Services"
        }
    ],
    "sg:phone":"+1 434 977 3045",
    "sg:postcode":"22903",
    "sg:province":"VA",
    "sg:tags":[
        "action",
        "agency",
        "community",
        "social"
    ],
    "wof:name":"Quality Community Council Inc",
    "wof:placetype":"venue"
},
  "geometry": {"coordinates":[-78.48628100000001,38.030613],"type":"Point"}
}