{
  "type": "Feature",
  "properties": {
    "iso:country":"US",
    "sg:address":"1700 N Alanton Dr",
    "sg:city":"Virginia Beach",
    "sg:classifiers":[
        {
            "category":"Personal",
            "subcategory":"Barber",
            "type":"Services"
        }
    ],
    "sg:phone":"+1 757 481 1632",
    "sg:postcode":"23454",
    "sg:province":"VA",
    "sg:tags":[
        "shop"
    ],
    "wof:name":"Family Haircare of Pembroke",
    "wof:placetype":"venue"
},
  "geometry": {"coordinates":[-76.02366499999999,36.888192],"type":"Point"}
}