{
  "type": "Feature",
  "properties": {
    "iso:country":"US",
    "sg:address":"3718 Templeton Pl",
    "sg:city":"Alexandria",
    "sg:classifiers":[
        {
            "category":"Professional",
            "type":"Services"
        }
    ],
    "sg:phone":"+1 703 751 4772",
    "sg:postcode":"22304",
    "sg:province":"VA",
    "wof:name":"Joseph Paslawski",
    "wof:placetype":"venue"
},
  "geometry": {"coordinates":[-77.094038,38.817321],"type":"Point"}
}