{
  "type": "Feature",
  "properties": {
    "addr:full":"1135 W Main St Abingdon VA 24210",
    "addr:housenumber":"1135",
    "addr:postcode":"24210",
    "addr:street":"W Main St",
    "iso:country":"US",
    "sg:address":"1135 W Main St",
    "sg:city":"Abingdon",
    "sg:classifiers":[
        {
            "category":"Autos & Motor Vehicles",
            "subcategory":"Automobile Sales",
            "type":"Retail Goods"
        }
    ],
    "sg:phone":"+1 276 628 2101",
    "sg:postcode":"24210",
    "sg:province":"VA",
    "sg:tags":[
        "car",
        "dealer"
    ],
    "wof:name":"Pioneer Chevrolet-Oldsmobile",
    "wof:placetype":"venue"
},
  "geometry": {"coordinates":[-82.009834,36.698803],"type":"Point"}
}