{
  "type": "Feature",
  "properties": {
    "addr:full":"12263 Deerhill Rd Midlothian VA 23112",
    "addr:housenumber":"12263",
    "addr:postcode":"23112",
    "addr:street":"Deerhill Rd",
    "iso:country":"US",
    "sg:address":"12263 Deerhill Rd",
    "sg:city":"Midlothian",
    "sg:classifiers":[
        {
            "category":"Home & Garden",
            "subcategory":"Building Materials",
            "type":"Retail Goods"
        }
    ],
    "sg:phone":"+1 804 608 8400",
    "sg:postcode":"23112",
    "sg:province":"VA",
    "sg:tags":[
        "marble-natural"
    ],
    "sg:website":"http://www.virginiagranite.com",
    "wof:name":"Classic Granite & Marble",
    "wof:placetype":"venue"
},
  "geometry": {"coordinates":[-77.62236300000001,37.440122],"type":"Point"}
}