{
  "type": "Feature",
  "properties": {
    "iso:country":"US",
    "sg:address":"112 Whitewood Rd",
    "sg:city":"Charlottesville",
    "sg:classifiers":[
        {
            "category":"Professional",
            "subcategory":"Lawyer & Legal Services",
            "type":"Services"
        }
    ],
    "sg:phone":"+1 434 978 3888",
    "sg:postcode":"22901",
    "sg:province":"VA",
    "sg:tags":[
        "attorney",
        "bureau"
    ],
    "sg:website":"www.rutherford.org",
    "wof:name":"Rutherford Institute",
    "wof:placetype":"venue"
},
  "geometry": {"coordinates":[-78.49219600000001,38.0743],"type":"Point"}
}