{
  "type": "Feature",
  "properties": {
    "addr:full":"761 Windridge Pkwy Hardy VA 24101",
    "addr:housenumber":"761",
    "addr:postcode":"24101",
    "addr:street":"Windridge Pkwy",
    "iso:country":"US",
    "sg:address":"761 Windridge Pkwy",
    "sg:city":"Hardy",
    "sg:phone":"+1 540 427 5107",
    "sg:postcode":"24101",
    "sg:province":"VA",
    "sg:tags":[
        "shelving"
    ],
    "wof:name":"Lista International",
    "wof:placetype":"venue"
},
  "geometry": {"coordinates":[-79.887137,37.188635],"type":"Point"}
}