{
  "type": "Feature",
  "properties": {
    "addr:full":"3275 New Market Rd Henrico VA 23231",
    "addr:housenumber":"3275",
    "addr:postcode":"23231",
    "addr:street":"New Market Rd",
    "iso:country":"US",
    "sg:address":"3275 New Market Rd",
    "sg:city":"Henrico",
    "sg:classifiers":[
        {
            "category":"Food & Beverages",
            "subcategory":"Groceries & Convenience Stores",
            "type":"Retail Goods"
        }
    ],
    "sg:phone":"+1 804 795 4213",
    "sg:postcode":"23231",
    "sg:province":"VA",
    "wof:name":"The Varina Pit Stop",
    "wof:placetype":"venue"
},
  "geometry": {"coordinates":[-77.329306,37.434274],"type":"Point"}
}