{
  "type": "Feature",
  "properties": {
    "addr:full":"5506 Shelburne Ct Centreville VA 20120",
    "addr:housenumber":"5506",
    "addr:postcode":"20120",
    "addr:street":"Shelburne Ct",
    "iso:country":"US",
    "sg:address":"5506 Shelburne Ct",
    "sg:city":"Centreville",
    "sg:classifiers":[
        {
            "category":"Shopping",
            "subcategory":"Computers & Home Electronics",
            "type":"Retail Goods"
        }
    ],
    "sg:phone":"+1 703 631 8045",
    "sg:postcode":"20120",
    "sg:province":"VA",
    "sg:tags":[
        "software"
    ],
    "sg:website":"www.novasoftinc.com",
    "wof:name":"Nova Soft Inc",
    "wof:placetype":"venue"
},
  "geometry": {"coordinates":[-77.42237,38.845801],"type":"Point"}
}