{
  "type": "Feature",
  "properties": {
    "addr:full":"8140 Edwardsville Rd Hardy VA 24101",
    "addr:housenumber":"8140",
    "addr:postcode":"24101",
    "addr:street":"Edwardsville Rd",
    "iso:country":"US",
    "sg:address":"8140 Edwardsville Rd",
    "sg:city":"Hardy",
    "sg:classifiers":[
        {
            "category":"Building & Trades",
            "subcategory":"Construction",
            "type":"Services"
        }
    ],
    "sg:phone":"+1 540 890 3945",
    "sg:postcode":"24101",
    "sg:province":"VA",
    "sg:tags":[
        "house"
    ],
    "wof:name":"Hughs Const Co",
    "wof:placetype":"venue"
},
  "geometry": {"coordinates":[-79.807401,37.202299],"type":"Point"}
}