{
  "type": "Feature",
  "properties": {
    "iso:country":"US",
    "sg:address":"1261 Cobble Pond Way",
    "sg:city":"Vienna",
    "sg:classifiers":[
        {
            "category":"Professional",
            "subcategory":"Management & Consulting",
            "type":"Services"
        }
    ],
    "sg:phone":"+1 703 757 9777",
    "sg:postcode":"22182",
    "sg:province":"VA",
    "sg:tags":[
        "business"
    ],
    "wof:name":"Ferrell & Assoc Consulting",
    "wof:placetype":"venue"
},
  "geometry": {"coordinates":[-77.311105,38.974481],"type":"Point"}
}