{
  "type": "Feature",
  "properties": {
    "addr:full":"8445 Thomas Nelson Hwy Lovingston VA 22949",
    "addr:housenumber":"8445",
    "addr:postcode":"22949",
    "addr:street":"Thomas Nelson Hwy",
    "iso:country":"US",
    "sg:address":"8445 Thomas Nelson Hwy",
    "sg:city":"Lovingston",
    "sg:classifiers":[
        {
            "category":"Restaurant",
            "type":"Food & Drink"
        }
    ],
    "sg:phone":"+1 434 263 4400",
    "sg:postcode":"22949",
    "sg:province":"VA",
    "sg:tags":[
        "eating"
    ],
    "wof:name":"Invisible Chef",
    "wof:placetype":"venue"
},
  "geometry": {"coordinates":[-78.87702299999999,37.751953],"type":"Point"}
}