{
  "type": "Feature",
  "properties": {
    "addr:full":"1235 Jefferson Davis Hwy Arlington VA 22202",
    "addr:housenumber":"1235",
    "addr:postcode":"22202",
    "addr:street":"Jefferson Davis Hwy",
    "iso:country":"US",
    "sg:address":"1235 Jefferson Davis Hwy",
    "sg:city":"Arlington",
    "sg:classifiers":[
        {
            "category":"Sports & Exercise",
            "subcategory":"Sports Center",
            "type":"Entertainment"
        }
    ],
    "sg:phone":"+1 814 539 6148",
    "sg:postcode":"22202",
    "sg:province":"VA",
    "sg:tags":[
        "manager",
        "promoter"
    ],
    "wof:name":"Spirit Of Soccer Inc",
    "wof:placetype":"venue"
},
  "geometry": {"coordinates":[-77.05291,38.84395],"type":"Point"}
}