{
  "type": "Feature",
  "properties": {
    "addr:full":"10816 Bottom Creek Rd Bent Mountain VA 24059",
    "addr:housenumber":"10816",
    "addr:postcode":"24059",
    "addr:street":"Bottom Creek Rd",
    "iso:country":"US",
    "sg:address":"10816 Bottom Creek Rd",
    "sg:city":"Bent Mountain",
    "sg:classifiers":[
        {
            "category":"Shopping",
            "subcategory":"Catalog Store",
            "type":"Retail Goods"
        }
    ],
    "sg:phone":"+1 540 929 4772",
    "sg:postcode":"24059",
    "sg:province":"VA",
    "sg:tags":[
        "mail",
        "house"
    ],
    "wof:name":"Bae",
    "wof:placetype":"venue"
},
  "geometry": {"coordinates":[-80.144552,37.146993],"type":"Point"}
}