{
  "type": "Feature",
  "properties": {
    "iso:country":"US",
    "sg:address":"10305 James Madison Hwy",
    "sg:city":"Culpeper",
    "sg:classifiers":[
        {
            "category":"Professional",
            "subcategory":"Management & Consulting",
            "type":"Services"
        }
    ],
    "sg:phone":"+1 540 829 1118",
    "sg:postcode":"22701",
    "sg:province":"VA",
    "wof:name":"Health Management Consultants",
    "wof:placetype":"venue"
},
  "geometry": {"coordinates":[-78.05746000000001,38.40997],"type":"Point"}
}