{
  "type": "Feature",
  "properties": {
    "addr:full":"11510 W River Rd Aylett VA 23009",
    "addr:housenumber":"11510",
    "addr:postcode":"23009",
    "addr:street":"W River Rd",
    "iso:country":"US",
    "sg:address":"11510 W River Rd",
    "sg:city":"Aylett",
    "sg:classifiers":[
        {
            "category":"Real Estate",
            "subcategory":"Real Estate Agent",
            "type":"Services"
        }
    ],
    "sg:phone":"+1 804 769 8997",
    "sg:postcode":"23009",
    "sg:province":"VA",
    "sg:tags":[
        "appraiser"
    ],
    "sg:website":"www.bayshoreappraisals.com",
    "wof:name":"Bay Shore Appraisals",
    "wof:placetype":"venue"
},
  "geometry": {"coordinates":[-77.102082,37.781968],"type":"Point"}
}