{
  "type": "Feature",
  "properties": {
    "iso:country":"US",
    "sg:address":"6704 S Quay Rd",
    "sg:city":"Suffolk",
    "sg:classifiers":[
        {
            "category":"Shopping",
            "subcategory":"Bicycles & Sporting Goods",
            "type":"Retail Goods"
        }
    ],
    "sg:phone":"+1 757 657 9800",
    "sg:postcode":"23437",
    "sg:province":"VA",
    "sg:tags":[
        "horse",
        "furnishing"
    ],
    "wof:name":"Dutch Pond Saddle Repair",
    "wof:placetype":"venue"
},
  "geometry": {"coordinates":[-76.78089799999999,36.680663],"type":"Point"}
}