{
  "type": "Feature",
  "properties": {
    "addr:full":"14138 Norsworthy Dr Carrollton VA 23314",
    "addr:postcode":"14138;23314",
    "addr:street":"Norsworthy Dr",
    "iso:country":"US",
    "sg:address":"14138 Norsworthy Dr",
    "sg:city":"Carrollton",
    "sg:classifiers":[
        {
            "category":"Recreation",
            "type":"Entertainment"
        }
    ],
    "sg:phone":"+1 757 238 2648",
    "sg:postcode":"23314",
    "sg:province":"VA",
    "sg:tags":[
        "club",
        "membership"
    ],
    "wof:name":"Carrollton Ruritan Club",
    "wof:placetype":"venue"
},
  "geometry": {"coordinates":[-76.559946,36.94607],"type":"Point"}
}