{
  "type": "Feature",
  "properties": {
    "iso:country":"US",
    "sg:address":"2601 C Ave",
    "sg:city":"Fort Lee",
    "sg:classifiers":[
        {
            "category":"Health Services",
            "subcategory":"Doctor",
            "type":"Services"
        }
    ],
    "sg:phone":"+1 804 717 5637",
    "sg:postcode":"23801",
    "sg:province":"VA",
    "sg:tags":[
        "dentist"
    ],
    "wof:name":"Daniel J Vogt",
    "wof:placetype":"venue"
},
  "geometry": {"coordinates":[-77.344656,37.236126],"type":"Point"}
}