{
  "type": "Feature",
  "properties": {
    "addr:full":"4620 Lee Hwy Ste 213 Arlington VA 22207",
    "addr:housenumber":"4620",
    "addr:postcode":"22207",
    "addr:street":"Lee Hwy Ste 213",
    "iso:country":"US",
    "sg:address":"4620 Lee Hwy Ste 213",
    "sg:city":"Arlington",
    "sg:classifiers":[
        {
            "category":"Professional",
            "subcategory":"Computer Services",
            "type":"Services"
        }
    ],
    "sg:phone":"+1 703 528 8548",
    "sg:postcode":"22207",
    "sg:province":"VA",
    "sg:tags":[
        "repair"
    ],
    "sg:website":"teamlogicit.com/Arlington",
    "wof:name":"Team Logic It",
    "wof:placetype":"venue"
},
  "geometry": {"coordinates":[-77.12056,38.898407],"type":"Point"}
}