{
  "type": "Feature",
  "properties": {
    "addr:full":"317 E Main St Luray VA 22835",
    "addr:housenumber":"317",
    "addr:postcode":"22835",
    "addr:street":"E Main St",
    "iso:country":"US",
    "sg:address":"317 E Main St",
    "sg:city":"Luray",
    "sg:classifiers":[
        {
            "category":"Building & Trades",
            "subcategory":"Cleaning & Sanitation",
            "type":"Services"
        }
    ],
    "sg:phone":"+1 540 743 9500",
    "sg:postcode":"22835",
    "sg:province":"VA",
    "sg:tags":[
        "maintenance"
    ],
    "wof:name":"Wallpaper Ladies",
    "wof:placetype":"venue"
},
  "geometry": {"coordinates":[-78.45343099999999,38.665493],"type":"Point"}
}