{
  "type": "Feature",
  "properties": {
    "addr:full":"2980 Prince William Pkwy Woodbridge VA 22192",
    "addr:housenumber":"2980",
    "addr:postcode":"22192",
    "addr:street":"Prince William Pkwy",
    "iso:country":"US",
    "sg:address":"2980 Prince William Pkwy",
    "sg:city":"Woodbridge",
    "sg:classifiers":[
        {
            "category":"Recreation",
            "subcategory":"Arcade",
            "type":"Entertainment"
        }
    ],
    "sg:phone":"+1 703 670 2417",
    "sg:postcode":"22192",
    "sg:province":"VA",
    "sg:tags":[
        "device",
        "operator",
        "amusement"
    ],
    "wof:name":"Game Crazy",
    "wof:placetype":"venue"
},
  "geometry": {"coordinates":[-77.294543,38.651221],"type":"Point"}
}