{
  "type": "Feature",
  "properties": {
    "iso:country":"US",
    "sg:address":"184 Apache Trl",
    "sg:city":"Martinsville",
    "sg:classifiers":[
        {
            "category":"Building & Trades",
            "subcategory":"Construction",
            "type":"Services"
        }
    ],
    "sg:phone":"+1 276 632 9874",
    "sg:postcode":"24112",
    "sg:province":"VA",
    "sg:tags":[
        "house"
    ],
    "wof:name":"Roys Remodeling",
    "wof:placetype":"venue"
},
  "geometry": {"coordinates":[-79.85286000000001,36.709469],"type":"Point"}
}