{
  "type": "Feature",
  "properties": {
    "addr:full":"3000 Oak Ave Newport News VA 23607",
    "addr:housenumber":"3000",
    "addr:postcode":"23607",
    "addr:street":"Oak Ave",
    "iso:country":"US",
    "sg:address":"3000 Oak Ave",
    "sg:city":"Newport News",
    "sg:classifiers":[
        {
            "category":"Building & Trades",
            "subcategory":"Cleaning & Sanitation",
            "type":"Services"
        }
    ],
    "sg:phone":"+1 757 245 0977",
    "sg:postcode":"23607",
    "sg:province":"VA",
    "sg:tags":[
        "maintenance"
    ],
    "wof:name":"Chapman Cleaning Service",
    "wof:placetype":"venue"
},
  "geometry": {"coordinates":[-76.407082,36.991786],"type":"Point"}
}