{
  "type": "Feature",
  "properties": {
    "addr:full":"880 Rio East Ct Charlottesvle VA 22901",
    "addr:housenumber":"880",
    "addr:postcode":"22901",
    "addr:street":"Rio East Ct",
    "iso:country":"US",
    "sg:address":"880 Rio East Ct",
    "sg:city":"Charlottesvle",
    "sg:classifiers":[
        {
            "category":"Professional",
            "subcategory":"Lawyer & Legal Services",
            "type":"Services"
        }
    ],
    "sg:phone":"+1 434 973 3329",
    "sg:postcode":"22901",
    "sg:province":"VA",
    "wof:name":"Disability Benefits Law Center",
    "wof:placetype":"venue"
},
  "geometry": {"coordinates":[-78.46959699999999,38.077202],"type":"Point"}
}