{
  "type": "Feature",
  "properties": {
    "addr:full":"4095 35th St N Arlington VA 22207",
    "addr:housenumber":"4095",
    "addr:postcode":"22207",
    "addr:street":"35Th St N",
    "iso:country":"US",
    "sg:address":"4095 35th St N",
    "sg:city":"Arlington",
    "sg:classifiers":[
        {
            "category":"Wholesale",
            "subcategory":"Books, Periodicals, & Newspapers",
            "type":"Manufacturing & Wholesale Goods"
        }
    ],
    "sg:phone":"+1 703 528 4047",
    "sg:postcode":"22207",
    "sg:province":"VA",
    "sg:tags":[
        "publisher",
        "book"
    ],
    "wof:name":"I Do Publishing",
    "wof:placetype":"venue"
},
  "geometry": {"coordinates":[-77.12240300000001,38.917582],"type":"Point"}
}