{
  "type": "Feature",
  "properties": {
    "addr:full":"112 S Main St La Crosse VA 23950",
    "addr:housenumber":"112",
    "addr:postcode":"23950",
    "addr:street":"S Main St",
    "iso:country":"US",
    "sg:address":"112 S Main St",
    "sg:city":"La Crosse",
    "sg:classifiers":[
        {
            "category":"Professional",
            "subcategory":"Computer Services",
            "type":"Services"
        }
    ],
    "sg:phone":"+1 434 757 9255",
    "sg:postcode":"23950",
    "sg:province":"VA",
    "wof:name":"Virginia Computer Svc Inc",
    "wof:placetype":"venue"
},
  "geometry": {"coordinates":[-78.09412,36.696863],"type":"Point"}
}