{
  "type": "Feature",
  "properties": {
    "iso:country":"US",
    "sg:address":"2147 Valley Ave",
    "sg:city":"Winchester",
    "sg:classifiers":[
        {
            "category":"Banks & Credit Unions",
            "subcategory":"Bank",
            "type":"Services"
        }
    ],
    "sg:phone":"+1 540 662 6900",
    "sg:postcode":"22601",
    "sg:province":"VA",
    "wof:name":"First Citizens Bank",
    "wof:placetype":"venue"
},
  "geometry": {"coordinates":[-78.18364699999999,39.16315],"type":"Point"}
}