{
  "type": "Feature",
  "properties": {
    "addr:full":"2406 Broadway Ave SW Roanoke VA 24014",
    "addr:housenumber":"2406",
    "addr:postcode":"24014",
    "addr:street":"Broadway Ave Sw",
    "iso:country":"US",
    "sg:address":"2406 Broadway Ave SW",
    "sg:city":"Roanoke",
    "sg:classifiers":[
        {
            "category":"Home & Garden",
            "subcategory":"Building Materials",
            "type":"Retail Goods"
        }
    ],
    "sg:phone":"+1 540 344 1147",
    "sg:postcode":"24014",
    "sg:province":"VA",
    "wof:name":"Five Wnds Stained GL Fine Arts",
    "wof:placetype":"venue"
},
  "geometry": {"coordinates":[-79.954978,37.24936],"type":"Point"}
}