{
  "type": "Feature",
  "properties": {
    "addr:full":"31 N Pointe Dr Fredericksburg VA 22405",
    "addr:housenumber":"31",
    "addr:postcode":"22405",
    "addr:street":"N Pointe Dr",
    "iso:country":"US",
    "sg:address":"31 N Pointe Dr",
    "sg:city":"Fredericksburg",
    "sg:classifiers":[
        {
            "category":"Professional",
            "subcategory":"Business Services",
            "type":"Services"
        }
    ],
    "sg:phone":"+1 540 899 2715",
    "sg:postcode":"22405",
    "sg:province":"VA",
    "wof:name":"Casa Assoc Inc",
    "wof:placetype":"venue"
},
  "geometry": {"coordinates":[-77.44199399999999,38.317236],"type":"Point"}
}