{
  "type": "Feature",
  "properties": {
    "iso:country":"US",
    "sg:address":"4428 N Dittmar Rd",
    "sg:city":"Arlington",
    "sg:classifiers":[
        {
            "category":"Professional",
            "subcategory":"Detective & Security Services",
            "type":"Services"
        }
    ],
    "sg:phone":"+1 703 536 6348",
    "sg:postcode":"22207",
    "sg:province":"VA",
    "sg:tags":[
        "car",
        "armored"
    ],
    "wof:name":"William S Jeanette",
    "wof:placetype":"venue"
},
  "geometry": {"coordinates":[-77.127092,38.917528],"type":"Point"}
}