{
  "type": "Feature",
  "properties": {
    "addr:full":"333 N Fairfax St Alexandria VA 22314",
    "addr:housenumber":"333",
    "addr:postcode":"22314",
    "addr:street":"N Fairfax St",
    "iso:country":"US",
    "sg:address":"333 N Fairfax St",
    "sg:city":"Alexandria",
    "sg:classifiers":[
        {
            "category":"Manufacturing",
            "subcategory":"Printing",
            "type":"Manufacturing & Wholesale Goods"
        }
    ],
    "sg:phone":"+1 703 836 7443",
    "sg:postcode":"22314",
    "sg:province":"VA",
    "sg:tags":[
        "publisher",
        "periodical"
    ],
    "wof:name":"Flight International Magazine",
    "wof:placetype":"venue"
},
  "geometry": {"coordinates":[-77.04191299999999,38.807007],"type":"Point"}
}