{
  "type": "Feature",
  "properties": {
    "addr:full":"11421 Donnington Ct Manassas VA 20111",
    "addr:housenumber":"11421",
    "addr:postcode":"20111",
    "addr:street":"Donnington Ct",
    "iso:country":"US",
    "sg:address":"11421 Donnington Ct",
    "sg:city":"Manassas",
    "sg:classifiers":[
        {
            "category":"Real Estate",
            "subcategory":"Real Estate Agent",
            "type":"Services"
        }
    ],
    "sg:phone":"+1 703 361 3740",
    "sg:postcode":"20111",
    "sg:province":"VA",
    "wof:name":"Eagle Management Solutions",
    "wof:placetype":"venue"
},
  "geometry": {"coordinates":[-77.43738,38.70795],"type":"Point"}
}