{
  "type": "Feature",
  "properties": {
    "iso:country":"US",
    "sg:address":"213 Howards Manor Dr",
    "sg:city":"Rustburg",
    "sg:classifiers":[
        {
            "category":"Professional",
            "type":"Services"
        }
    ],
    "sg:phone":"+1 434 821 4849",
    "sg:postcode":"24588",
    "sg:province":"VA",
    "wof:name":"Shannon B Bell",
    "wof:placetype":"venue"
},
  "geometry": {"coordinates":[-79.172724,37.265888],"type":"Point"}
}