{
  "type": "Feature",
  "properties": {
    "addr:full":"462 Fox Hollow Ln Palmyra VA 22963",
    "addr:housenumber":"462",
    "addr:postcode":"22963",
    "addr:street":"Fox Hollow Ln",
    "iso:country":"US",
    "sg:address":"462 Fox Hollow Ln",
    "sg:city":"Palmyra",
    "sg:classifiers":[
        {
            "category":"Professional",
            "subcategory":"Art Services",
            "type":"Services"
        }
    ],
    "sg:phone":"+1 434 589 4665",
    "sg:postcode":"22963",
    "sg:province":"VA",
    "sg:tags":[
        "graphic",
        "design"
    ],
    "wof:name":"Fernandez Clleen Grphic Design",
    "wof:placetype":"venue"
},
  "geometry": {"coordinates":[-78.339585,37.890857],"type":"Point"}
}