{
  "type": "Feature",
  "properties": {
    "addr:full":"1100 Jefferson Davis Hwy Richmond VA 23224",
    "addr:housenumber":"1100",
    "addr:postcode":"23224",
    "addr:street":"Jefferson Davis Hwy",
    "iso:country":"US",
    "sg:address":"1100 Jefferson Davis Hwy",
    "sg:city":"Richmond",
    "sg:classifiers":[
        {
            "category":"Freight",
            "type":"Transportation"
        }
    ],
    "sg:phone":"+1 804 232 8082",
    "sg:postcode":"23224",
    "sg:province":"VA",
    "sg:tags":[
        "real estate"
    ],
    "wof:name":"Model Tobacco Business Park",
    "wof:placetype":"venue"
},
  "geometry": {"coordinates":[-77.446923,37.504373],"type":"Point"}
}