{
  "type": "Feature",
  "properties": {
    "iso:country":"US",
    "sg:address":"6820 Elm St",
    "sg:city":"Mc Lean",
    "sg:classifiers":[
        {
            "category":"Real Estate",
            "subcategory":"Real Estate Services",
            "type":"Services"
        },
        {
            "category":"Real Estate",
            "subcategory":"Real Estate Operator",
            "type":"Services"
        }
    ],
    "sg:phone":"+1 703 847 0060",
    "sg:postcode":"22101",
    "sg:province":"VA",
    "sg:tags":[
        "apartment",
        "property",
        "management"
    ],
    "wof:name":"Metro Management Services Inc",
    "wof:placetype":"venue"
},
  "geometry": {"coordinates":[-77.178596,38.935101],"type":"Point"}
}