{
  "type": "Feature",
  "properties": {
    "addr:full":"1111 Courtland Rd Emporia VA 23847",
    "addr:housenumber":"1111",
    "addr:postcode":"23847",
    "addr:street":"Courtland Rd",
    "iso:country":"US",
    "sg:address":"1111 Courtland Rd",
    "sg:city":"Emporia",
    "sg:classifiers":[
        {
            "category":"Autos & Motor Vehicles",
            "subcategory":"Automobile Sales",
            "type":"Retail Goods"
        }
    ],
    "sg:phone":"+1 434 348 3127",
    "sg:postcode":"23847",
    "sg:province":"VA",
    "sg:tags":[
        "car",
        "dealer"
    ],
    "wof:name":"Fred's Auto Parts",
    "wof:placetype":"venue"
},
  "geometry": {"coordinates":[-77.492046,36.682251],"type":"Point"}
}