{
  "type": "Feature",
  "properties": {
    "addr:full":"402 Coffee Rd Lynchburg VA 24503",
    "addr:housenumber":"402",
    "addr:postcode":"24503",
    "addr:street":"Coffee Rd",
    "iso:country":"US",
    "sg:address":"402 Coffee Rd",
    "sg:city":"Lynchburg",
    "sg:classifiers":[
        {
            "category":"Real Estate",
            "subcategory":"Real Estate Agent",
            "type":"Services"
        }
    ],
    "sg:phone":"+1 434 384 2088",
    "sg:postcode":"24503",
    "sg:province":"VA",
    "sg:tags":[
        "appraiser"
    ],
    "wof:name":"John Stewart Walker Inc",
    "wof:placetype":"venue"
},
  "geometry": {"coordinates":[-79.266626,37.43889],"type":"Point"}
}