{
  "type": "Feature",
  "properties": {
    "addr:full":"5807 Patterson Ave Richmond VA 23226",
    "addr:housenumber":"5807",
    "addr:postcode":"23226",
    "addr:street":"Patterson Ave",
    "iso:country":"US",
    "sg:address":"5807 Patterson Ave",
    "sg:city":"Richmond",
    "sg:classifiers":[
        {
            "category":"Shopping",
            "subcategory":"Beauty & Cosmetics",
            "type":"Retail Goods"
        }
    ],
    "sg:phone":"+1 804 271 9406",
    "sg:postcode":"23226",
    "sg:province":"VA",
    "sg:tags":[
        "merchandise"
    ],
    "wof:name":"York Supply Co LLC",
    "wof:placetype":"venue"
},
  "geometry": {"coordinates":[-77.516413,37.580618],"type":"Point"}
}