{
  "type": "Feature",
  "properties": {
    "addr:full":"3351 Speeks Dr Midlothian VA 23112",
    "addr:housenumber":"3351",
    "addr:postcode":"23112",
    "addr:street":"Speeks Dr",
    "iso:country":"US",
    "sg:address":"3351 Speeks Dr",
    "sg:city":"Midlothian",
    "sg:classifiers":[
        {
            "category":"Professional",
            "type":"Services"
        }
    ],
    "sg:phone":"+1 804 377 6653",
    "sg:postcode":"23112",
    "sg:province":"VA",
    "wof:name":"Moldx",
    "wof:placetype":"venue"
},
  "geometry": {"coordinates":[-77.594174,37.440334],"type":"Point"}
}