{
  "type": "Feature",
  "properties": {
    "iso:country":"US",
    "sg:address":"3400 Payne St",
    "sg:city":"Falls Church",
    "sg:classifiers":[
        {
            "category":"Health Services",
            "subcategory":"Doctor",
            "type":"Services"
        }
    ],
    "sg:phone":"+1 703 578 3384",
    "sg:postcode":"22041",
    "sg:province":"VA",
    "sg:tags":[
        "surgeon",
        "oral"
    ],
    "wof:name":"Chaudhry Maqsood DDS",
    "wof:placetype":"venue"
},
  "geometry": {"coordinates":[-77.133003,38.852402],"type":"Point"}
}