{
  "type": "Feature",
  "properties": {
    "addr:full":"6791 Wilson Blvd Falls Church VA 22044",
    "addr:housenumber":"6791",
    "addr:postcode":"22044",
    "addr:street":"Wilson Blvd",
    "iso:country":"US",
    "sg:address":"6791 Wilson Blvd",
    "sg:city":"Falls Church",
    "sg:classifiers":[
        {
            "category":"Shopping",
            "subcategory":"Gifts & Souvenirs",
            "type":"Retail Goods"
        }
    ],
    "sg:phone":"+1 703 766 0748",
    "sg:postcode":"22044",
    "sg:province":"VA",
    "wof:name":"Mp Gifts",
    "wof:placetype":"venue"
},
  "geometry": {"coordinates":[-77.153244,38.873062],"type":"Point"}
}