{
  "type": "Feature",
  "properties": {
    "addr:full":"101 Henry Anna Ln Bristol VA 37620",
    "addr:housenumber":"101",
    "addr:postcode":"37620",
    "addr:street":"Henry Anna Ln",
    "iso:country":"US",
    "sg:address":"101 Henry Anna Ln",
    "sg:city":"Bristol",
    "sg:classifiers":[
        {
            "category":"Insurance",
            "subcategory":"Insurance Agent",
            "type":"Services"
        }
    ],
    "sg:phone":"+1 423 652 9052",
    "sg:postcode":"37620",
    "sg:province":"VA",
    "wof:name":"Pearson Insurance LLC",
    "wof:placetype":"venue"
},
  "geometry": {"coordinates":[-82.107249,36.58971],"type":"Point"}
}