{
  "type": "Feature",
  "properties": {
    "iso:country":"US",
    "sg:address":"124 Kingsley Rd SE",
    "sg:city":"Vienna",
    "sg:classifiers":[
        {
            "category":"Retail",
            "subcategory":"Repair Shop",
            "type":"Services"
        }
    ],
    "sg:phone":"+1 703 938 6910",
    "sg:postcode":"22180",
    "sg:province":"VA",
    "sg:tags":[
        "appliance"
    ],
    "wof:name":"Master Appliance Svc",
    "wof:placetype":"venue"
},
  "geometry": {"coordinates":[-77.250653,38.890048],"type":"Point"}
}