{
  "type": "Feature",
  "properties": {
    "addr:full":"516 Baylor Ct Chesapeake VA 23320",
    "addr:housenumber":"516",
    "addr:postcode":"23320",
    "addr:street":"Baylor Ct",
    "iso:country":"US",
    "sg:address":"516 Baylor Ct",
    "sg:city":"Chesapeake",
    "sg:classifiers":[
        {
            "category":"Professional",
            "subcategory":"Accounting & Tax Preparation",
            "type":"Services"
        }
    ],
    "sg:phone":"+1 757 436 6230",
    "sg:postcode":"23320",
    "sg:province":"VA",
    "sg:tags":[
        "auditing",
        "bookkeeping"
    ],
    "wof:name":"Charles W Snader PC",
    "wof:placetype":"venue"
},
  "geometry": {"coordinates":[-76.223964,36.750696],"type":"Point"}
}