{
  "type": "Feature",
  "properties": {
    "iso:country":"US",
    "sg:address":"419 Oakridge Blvd",
    "sg:city":"Lynchburg",
    "sg:classifiers":[
        {
            "category":"Professional",
            "type":"Services"
        }
    ],
    "sg:phone":"+1 434 847 2824",
    "sg:postcode":"24502",
    "sg:province":"VA",
    "sg:tags":[
        "establishment"
    ],
    "wof:name":"Steward & Steward",
    "wof:placetype":"venue"
},
  "geometry": {"coordinates":[-79.178872,37.391219],"type":"Point"}
}