{
  "type": "Feature",
  "properties": {
    "addr:full":"403 E Main St Front Royal VA 22630",
    "addr:housenumber":"403",
    "addr:postcode":"22630",
    "addr:street":"E Main St",
    "iso:country":"US",
    "sg:address":"403 E Main St",
    "sg:city":"Front Royal",
    "sg:classifiers":[
        {
            "category":"Real Estate",
            "subcategory":"Real Estate Agent",
            "type":"Services"
        }
    ],
    "sg:phone":"+1 540 635 4900",
    "sg:postcode":"22630",
    "sg:province":"VA",
    "wof:name":"Remax Choice",
    "wof:placetype":"venue"
},
  "geometry": {"coordinates":[-78.189869,38.917432],"type":"Point"}
}