{
  "type": "Feature",
  "properties": {
    "addr:full":"4958 Coulson Church Rd Hillsville VA 24343",
    "addr:housenumber":"4958",
    "addr:postcode":"24343",
    "addr:street":"Coulson Church Rd",
    "iso:country":"US",
    "sg:address":"4958 Coulson Church Rd",
    "sg:city":"Hillsville",
    "sg:classifiers":[
        {
            "category":"Professional",
            "subcategory":"Testing Lab",
            "type":"Services"
        }
    ],
    "sg:phone":"+1 276 728 9221",
    "sg:postcode":"24343",
    "sg:province":"VA",
    "sg:tags":[
        "soil"
    ],
    "wof:name":"Southwest Soils Inc",
    "wof:placetype":"venue"
},
  "geometry": {"coordinates":[-80.83071700000001,36.783108],"type":"Point"}
}