{
  "type": "Feature",
  "properties": {
    "addr:full":"1217 E Main St Bedford VA 24523",
    "addr:housenumber":"1217",
    "addr:postcode":"24523",
    "addr:street":"E Main St",
    "iso:country":"US",
    "sg:address":"1217 E Main St",
    "sg:city":"Bedford",
    "sg:classifiers":[
        {
            "category":"Shopping",
            "subcategory":"Pharmacy",
            "type":"Retail Goods"
        }
    ],
    "sg:phone":"+1 540 586 6025",
    "sg:postcode":"24523",
    "sg:province":"VA",
    "sg:website":"www.cvs.com",
    "wof:name":"CVS Pharmacy",
    "wof:placetype":"venue"
},
  "geometry": {"coordinates":[-79.50445999999999,37.326669],"type":"Point"}
}