{
  "type": "Feature",
  "properties": {
    "addr:full":"18 W Market St Leesburg VA 20176",
    "addr:housenumber":"18",
    "addr:postcode":"20176",
    "addr:street":"W Market St",
    "iso:country":"US",
    "sg:address":"18 W Market St",
    "sg:city":"Leesburg",
    "sg:classifiers":[
        {
            "category":"Insurance",
            "subcategory":"Hazard Insurance",
            "type":"Services"
        }
    ],
    "sg:phone":"+1 703 779 7410",
    "sg:postcode":"20176",
    "sg:province":"VA",
    "sg:tags":[
        "profit",
        "sharing",
        "pension",
        "plan"
    ],
    "wof:name":"Buxton Davidson Assoc",
    "wof:placetype":"venue"
},
  "geometry": {"coordinates":[-77.565862,39.115864],"type":"Point"}
}