{
  "type": "Feature",
  "properties": {
    "iso:country":"US",
    "sg:address":"11668 Gilman Ln",
    "sg:city":"Herndon",
    "sg:classifiers":[
        {
            "category":"Professional",
            "subcategory":"Computer Services",
            "type":"Services"
        }
    ],
    "sg:phone":"+1 703 404 4216",
    "sg:postcode":"20170",
    "sg:province":"VA",
    "sg:tags":[
        "related"
    ],
    "wof:name":"Ole Consulting Inc",
    "wof:placetype":"venue"
},
  "geometry": {"coordinates":[-77.34914499999999,38.991838],"type":"Point"}
}