{
  "type": "Feature",
  "properties": {
    "addr:full":"2921 2nd Rd N Arlington VA 22201",
    "addr:housenumber":"2921",
    "addr:postcode":"22201",
    "addr:street":"2Nd Rd N",
    "iso:country":"US",
    "sg:address":"2921 2nd Rd N",
    "sg:city":"Arlington",
    "sg:classifiers":[
        {
            "category":"Sports & Exercise",
            "subcategory":"Bowling",
            "type":"Entertainment"
        }
    ],
    "sg:phone":"+1 703 527 3911",
    "sg:postcode":"22201",
    "sg:province":"VA",
    "sg:tags":[
        "center"
    ],
    "wof:name":"Bowl America Shirley Inc",
    "wof:placetype":"venue"
},
  "geometry": {"coordinates":[-77.092288,38.877058],"type":"Point"}
}