{
  "type": "Feature",
  "properties": {
    "addr:full":"6104 Gardner Ln Bridgewater VA 22812",
    "addr:housenumber":"6104",
    "addr:postcode":"22812",
    "addr:street":"Gardner Ln",
    "iso:country":"US",
    "sg:address":"6104 Gardner Ln",
    "sg:city":"Bridgewater",
    "sg:classifiers":[
        {
            "category":"Real Estate",
            "subcategory":"Real Estate Operator",
            "type":"Services"
        }
    ],
    "sg:phone":"+1 540 828 3050",
    "sg:postcode":"22812",
    "sg:province":"VA",
    "sg:tags":[
        "property",
        "lessor"
    ],
    "wof:name":"Stanley Cline",
    "wof:placetype":"venue"
},
  "geometry": {"coordinates":[-78.99807800000001,38.381584],"type":"Point"}
}