{
  "type": "Feature",
  "properties": {
    "addr:full":"222 Main St Dayton VA 22821",
    "addr:housenumber":"222",
    "addr:postcode":"22821",
    "addr:street":"Main St",
    "iso:country":"US",
    "sg:address":"222 Main St",
    "sg:city":"Dayton",
    "sg:classifiers":[
        {
            "category":"Restaurant",
            "type":"Food & Drink"
        }
    ],
    "sg:phone":"+1 540 879 2181",
    "sg:postcode":"22821",
    "sg:province":"VA",
    "wof:name":"Thomas House Restaurant",
    "wof:placetype":"venue"
},
  "geometry": {"coordinates":[-78.939127,38.414217],"type":"Point"}
}