{
  "type": "Feature",
  "properties": {
    "iso:country":"US",
    "sg:address":"103 9th Ave",
    "sg:city":"Radford",
    "sg:classifiers":[
        {
            "category":"Building & Trades",
            "subcategory":"Construction",
            "type":"Services"
        }
    ],
    "sg:phone":"+1 540 639 2026",
    "sg:postcode":"24141",
    "sg:province":"VA",
    "sg:tags":[
        "residential",
        "contractor"
    ],
    "wof:name":"B & C Unlimited",
    "wof:placetype":"venue"
},
  "geometry": {"coordinates":[-80.564024,37.137802],"type":"Point"}
}