{
  "type": "Feature",
  "properties": {
    "addr:full":"9000 Fern Park Dr Burke VA 22015",
    "addr:housenumber":"9000",
    "addr:postcode":"22015",
    "addr:street":"Fern Park Dr",
    "iso:country":"US",
    "sg:address":"9000 Fern Park Dr",
    "sg:city":"Burke",
    "sg:classifiers":[
        {
            "category":"Health Services",
            "subcategory":"Doctor",
            "type":"Services"
        }
    ],
    "sg:phone":"+1 703 764 1112",
    "sg:postcode":"22015",
    "sg:province":"VA",
    "sg:tags":[
        "dentist"
    ],
    "wof:name":"Burke Family & Csmtc Dentistry",
    "wof:placetype":"venue"
},
  "geometry": {"coordinates":[-77.256506,38.80851],"type":"Point"}
}