{
  "type": "Feature",
  "properties": {
    "addr:full":"3115 Valley Ave Winchester VA 22601",
    "addr:housenumber":"3115",
    "addr:postcode":"22601",
    "addr:street":"Valley Ave",
    "iso:country":"US",
    "sg:address":"3115 Valley Ave",
    "sg:city":"Winchester",
    "sg:classifiers":[
        {
            "category":"Shopping",
            "subcategory":"Clothing, Apparel, & Fashions",
            "type":"Retail Goods"
        }
    ],
    "sg:phone":"+1 540 535 0519",
    "sg:postcode":"22601",
    "sg:province":"VA",
    "wof:name":"Ann Taylor",
    "wof:placetype":"venue"
},
  "geometry": {"coordinates":[-78.19004099999999,39.142711],"type":"Point"}
}