{
  "type": "Feature",
  "properties": {
    "addr:full":"2915 Columbia Pike Arlington VA 22204",
    "addr:housenumber":"2915",
    "addr:postcode":"22204",
    "addr:street":"Columbia Pike",
    "iso:country":"US",
    "sg:address":"2915 Columbia Pike",
    "sg:city":"Arlington",
    "sg:classifiers":[
        {
            "category":"Building & Trades",
            "subcategory":"Locksmith",
            "type":"Services"
        }
    ],
    "sg:phone":"+1 571 431 1668",
    "sg:postcode":"22204",
    "sg:province":"VA",
    "sg:tags":[
        "key"
    ],
    "wof:name":"Available Columbia Pike Locksmith",
    "wof:placetype":"venue"
},
  "geometry": {"coordinates":[-77.087205,38.862643],"type":"Point"}
}