{
  "type": "Feature",
  "properties": {
    "iso:country":"US",
    "sg:address":"616 S Pickett St",
    "sg:city":"Alexandria",
    "sg:classifiers":[
        {
            "category":"Retail",
            "subcategory":"Repair Shop",
            "type":"Services"
        }
    ],
    "sg:phone":"+1 703 842 4919",
    "sg:postcode":"22304",
    "sg:province":"VA",
    "sg:tags":[
        "lock",
        "locksmith"
    ],
    "wof:name":"7 Day Emergency A 24 Hour",
    "wof:placetype":"venue"
},
  "geometry": {"coordinates":[-77.130539,38.805393],"type":"Point"}
}