{
  "type": "Feature",
  "properties": {
    "addr:full":"43090 Peacock Market Plz #180 Chantilly VA 20152",
    "addr:housenumber":"43090",
    "addr:postcode":"20152",
    "addr:street":"Peacock Market Plz # 180",
    "iso:country":"US",
    "sg:address":"43090 Peacock Market Plz #180",
    "sg:city":"Chantilly",
    "sg:classifiers":[
        {
            "category":"Personal",
            "subcategory":"Nail Salon",
            "type":"Services"
        }
    ],
    "sg:phone":"+1 703 327 7333",
    "sg:postcode":"20152",
    "sg:province":"VA",
    "wof:name":"Hollywood Nails & Salon",
    "wof:placetype":"venue"
},
  "geometry": {"coordinates":[-77.512868,38.915757],"type":"Point"}
}