{
  "type": "Feature",
  "properties": {
    "addr:full":"1329 Coalter St Richmond VA 23223",
    "addr:housenumber":"1329",
    "addr:postcode":"23223",
    "addr:street":"Coalter St",
    "iso:country":"US",
    "sg:address":"1329 Coalter St",
    "sg:city":"Richmond",
    "sg:classifiers":[
        {
            "category":"Real Estate",
            "subcategory":"Real Estate Operator",
            "type":"Services"
        }
    ],
    "sg:phone":"+1 804 643 3959",
    "sg:postcode":"23223",
    "sg:province":"VA",
    "sg:tags":[
        "building",
        "apartment"
    ],
    "wof:name":"Fairhills Apartments",
    "wof:placetype":"venue"
},
  "geometry": {"coordinates":[-77.420444,37.544637],"type":"Point"}
}