{
  "type": "Feature",
  "properties": {
    "addr:full":"1324 Oakmont Pl Norfolk VA 23513",
    "addr:housenumber":"1324",
    "addr:postcode":"23513",
    "addr:street":"Oakmont Pl",
    "iso:country":"US",
    "sg:address":"1324 Oakmont Pl",
    "sg:city":"Norfolk",
    "sg:classifiers":[
        {
            "category":"Social Services",
            "subcategory":"Child Care",
            "type":"Services"
        }
    ],
    "sg:phone":"+1 757 855 0420",
    "sg:postcode":"23513",
    "sg:province":"VA",
    "wof:name":"KEES To My Heart Infant Care",
    "wof:placetype":"venue"
},
  "geometry": {"coordinates":[-76.23808200000001,36.911763],"type":"Point"}
}