{
  "type": "Feature",
  "properties": {
    "addr:full":"147 Wayne Ave Stuarts Draft VA 24477",
    "addr:housenumber":"147",
    "addr:postcode":"24477",
    "addr:street":"Wayne Ave",
    "iso:country":"US",
    "sg:address":"147 Wayne Ave",
    "sg:city":"Stuarts Draft",
    "sg:classifiers":[
        {
            "category":"Retail",
            "subcategory":"Animal Services",
            "type":"Services"
        }
    ],
    "sg:phone":"+1 540 337 4430",
    "sg:postcode":"24477",
    "sg:province":"VA",
    "wof:name":"Sonny Acre Farm",
    "wof:placetype":"venue"
},
  "geometry": {"coordinates":[-79.029094,38.025226],"type":"Point"}
}