{
  "type": "Feature",
  "properties": {
    "iso:country":"US",
    "sg:address":"7004 N Gate Dr",
    "sg:city":"Norfolk",
    "sg:classifiers":[
        {
            "category":"Real Estate",
            "subcategory":"Real Estate Agent",
            "type":"Services"
        }
    ],
    "sg:phone":"+1 757 855 2320",
    "sg:postcode":"23513",
    "sg:province":"VA",
    "wof:name":"Cedarwoods Apartments",
    "wof:placetype":"venue"
},
  "geometry": {"coordinates":[-76.237273,36.907216],"type":"Point"}
}