{
  "type": "Feature",
  "properties": {
    "addr:full":"13299 Worth Ave Woodbridge VA 22192",
    "addr:housenumber":"13299",
    "addr:postcode":"22192",
    "addr:street":"Worth Ave",
    "iso:country":"US",
    "sg:address":"13299 Worth Ave",
    "sg:city":"Woodbridge",
    "sg:classifiers":[
        {
            "category":"Shopping",
            "subcategory":"Clothing, Apparel, & Fashions",
            "type":"Retail Goods"
        }
    ],
    "sg:phone":"+1 703 492 7996",
    "sg:postcode":"22192",
    "sg:province":"VA",
    "wof:name":"Dots Inc",
    "wof:placetype":"venue"
},
  "geometry": {"coordinates":[-77.29498100000001,38.649069],"type":"Point"}
}