{
  "type": "Feature",
  "properties": {
    "addr:full":"3573 Norland Ct Norfolk VA 23513",
    "addr:housenumber":"3573",
    "addr:postcode":"23513",
    "addr:street":"Norland Ct",
    "iso:country":"US",
    "sg:address":"3573 Norland Ct",
    "sg:city":"Norfolk",
    "sg:classifiers":[
        {
            "category":"Retail",
            "subcategory":"Self-service Laundry",
            "type":"Services"
        }
    ],
    "sg:phone":"+1 757 855 2363",
    "sg:postcode":"23513",
    "sg:province":"VA",
    "sg:tags":[
        "coin"
    ],
    "wof:name":"Norview Coin Laundry",
    "wof:placetype":"venue"
},
  "geometry": {"coordinates":[-76.24812900000001,36.883192],"type":"Point"}
}