{
  "type": "Feature",
  "properties": {
    "addr:full":"13663 Lee Hwy Centreville VA 20121",
    "addr:housenumber":"13663",
    "addr:postcode":"20121",
    "addr:street":"Lee Hwy",
    "iso:country":"US",
    "sg:address":"13663 Lee Hwy",
    "sg:city":"Centreville",
    "sg:classifiers":[
        {
            "category":"Retail",
            "subcategory":"Animal Services",
            "type":"Services"
        },
        {
            "category":"Retail",
            "subcategory":"Veterinary Services",
            "type":"Services"
        },
        {
            "category":"Retail",
            "subcategory":"Pet Boarding",
            "type":"Services"
        }
    ],
    "sg:phone":"+1 888 850 8677",
    "sg:postcode":"20121",
    "sg:province":"VA",
    "sg:tags":[
        "hospital",
        "specialty",
        "laboratories-veterinary",
        "clinic",
        "veterinarian",
        "grooming",
        "kennel"
    ],
    "sg:website":"http://local.ingenio.com/Listings/Details.aspx?NUM=a%3a9243176%3a13%3a4859924%3a14%3a0%3a7",
    "wof:name":"Centreville Animal Hospital",
    "wof:placetype":"venue"
},
  "geometry": {"coordinates":[-77.41929399999999,38.838993],"type":"Point"}
}