{
  "type": "Feature",
  "properties": {
    "addr:full":"340 Peppers Ferry Rd Wytheville VA 24382",
    "addr:housenumber":"340",
    "addr:postcode":"24382",
    "addr:street":"Peppers Ferry Rd",
    "iso:country":"US",
    "sg:address":"340 Peppers Ferry Rd",
    "sg:city":"Wytheville",
    "sg:classifiers":[
        {
            "category":"Government",
            "subcategory":"Office",
            "type":"Public Place"
        }
    ],
    "sg:phone":"+1 276 228 3513",
    "sg:postcode":"24382",
    "sg:province":"VA",
    "sg:tags":[
        "federal"
    ],
    "wof:name":"US Consolidated Farm Svc Agcy",
    "wof:placetype":"venue"
},
  "geometry": {"coordinates":[-81.077591,36.956887],"type":"Point"}
}