{
  "type": "Feature",
  "properties": {
    "iso:country":"US",
    "sg:address":"7825 Midlothian Tpke",
    "sg:city":"Richmond",
    "sg:classifiers":[
        {
            "category":"Insurance",
            "subcategory":"Insurance Agent",
            "type":"Services"
        }
    ],
    "sg:phone":"+1 804 272 1595",
    "sg:postcode":"23235",
    "sg:province":"VA",
    "wof:name":"Greene",
    "wof:placetype":"venue"
},
  "geometry": {"coordinates":[-77.54046,37.498713],"type":"Point"}
}