{
  "type": "Feature",
  "properties": {
    "addr:full":"1213 Swallow Dr Virginia Beach VA 23453",
    "addr:housenumber":"1213",
    "addr:postcode":"23453",
    "addr:street":"Swallow Dr",
    "iso:country":"US",
    "sg:address":"1213 Swallow Dr",
    "sg:city":"Virginia Beach",
    "sg:classifiers":[
        {
            "category":"Restaurant",
            "type":"Food & Drink"
        }
    ],
    "sg:phone":"+1 757 721 5245",
    "sg:postcode":"23453",
    "sg:province":"VA",
    "sg:tags":[
        "eating"
    ],
    "wof:name":"Natashas Bistro",
    "wof:placetype":"venue"
},
  "geometry": {"coordinates":[-76.076381,36.8007],"type":"Point"}
}