{
  "type": "Feature",
  "properties": {
    "addr:full":"1146 Walker Rd Great Falls VA 22066",
    "addr:housenumber":"1146",
    "addr:postcode":"22066",
    "addr:street":"Walker Rd",
    "iso:country":"US",
    "sg:address":"1146 Walker Rd",
    "sg:city":"Great Falls",
    "sg:classifiers":[
        {
            "category":"Organizations",
            "subcategory":"Non-profit Organization",
            "type":"Services"
        }
    ],
    "sg:phone":"+1 703 759 3119",
    "sg:postcode":"22066",
    "sg:province":"VA",
    "wof:name":"Neighbors International Fndtn",
    "wof:placetype":"venue"
},
  "geometry": {"coordinates":[-77.295765,38.975103],"type":"Point"}
}