{
  "type": "Feature",
  "properties": {
    "addr:full":"340 Millard Burke Memorial Hwy Goshen VA 24439",
    "addr:housenumber":"340",
    "addr:postcode":"24439",
    "addr:street":"Millard;Memorial Hwy",
    "iso:country":"US",
    "sg:address":"340 Millard Burke Memorial Hwy",
    "sg:city":"Goshen",
    "sg:classifiers":[
        {
            "category":"Travel",
            "subcategory":"Campground",
            "type":"Entertainment"
        }
    ],
    "sg:phone":"+1 540 997 5773",
    "sg:postcode":"24439",
    "sg:province":"VA",
    "sg:tags":[
        "camp"
    ],
    "wof:name":"Boy Scouts of America",
    "wof:placetype":"venue"
},
  "geometry": {"coordinates":[-79.445691,37.989001],"type":"Point"}
}