{
  "type": "Feature",
  "properties": {
    "addr:full":"8000 Holland Rd Alexandria VA 22306",
    "addr:housenumber":"8000",
    "addr:postcode":"22306",
    "addr:street":"Holland Rd",
    "iso:country":"US",
    "sg:address":"8000 Holland Rd",
    "sg:city":"Alexandria",
    "sg:classifiers":[
        {
            "category":"Professional",
            "subcategory":"Management & Consulting",
            "type":"Services"
        }
    ],
    "sg:phone":"+1 703 799 0229",
    "sg:postcode":"22306",
    "sg:province":"VA",
    "sg:tags":[
        "business"
    ],
    "wof:name":"Elegant Products Services",
    "wof:placetype":"venue"
},
  "geometry": {"coordinates":[-77.07809899999999,38.742882],"type":"Point"}
}