{
  "type": "Feature",
  "properties": {
    "iso:country":"US",
    "sg:address":"10 W Cary St",
    "sg:city":"Richmond",
    "sg:classifiers":[
        {
            "category":"Building & Trades",
            "subcategory":"Construction",
            "type":"Services"
        }
    ],
    "sg:phone":"+1 804 775 2200",
    "sg:postcode":"23220",
    "sg:province":"VA",
    "sg:tags":[
        "contracting",
        "commercial"
    ],
    "wof:name":"Walters Construction Co Inc",
    "wof:placetype":"venue"
},
  "geometry": {"coordinates":[-77.445988,37.542741],"type":"Point"}
}