{
  "type": "Feature",
  "properties": {
    "addr:full":"1101 Milroy Ct Winchester VA 22601",
    "addr:housenumber":"1101",
    "addr:postcode":"22601",
    "addr:street":"Milroy Ct",
    "iso:country":"US",
    "sg:address":"1101 Milroy Ct",
    "sg:city":"Winchester",
    "sg:classifiers":[
        {
            "category":"Personal",
            "subcategory":"Beauty Salon",
            "type":"Services"
        }
    ],
    "sg:phone":"+1 540 662 0817",
    "sg:postcode":"22601",
    "sg:province":"VA",
    "sg:tags":[
        "shop"
    ],
    "wof:name":"Westside Beauty Salon",
    "wof:placetype":"venue"
},
  "geometry": {"coordinates":[-78.17819799999999,39.196691],"type":"Point"}
}