{
  "type": "Feature",
  "properties": {
    "addr:full":"11800 W Broad St Ste 1244 Henrico VA 23233",
    "addr:housenumber":"11800",
    "addr:postcode":"23233",
    "addr:street":"W Broad St Ste 1244",
    "iso:country":"US",
    "sg:address":"11800 W Broad St Ste 1244",
    "sg:city":"Henrico",
    "sg:classifiers":[
        {
            "category":"Shopping",
            "subcategory":"Optical Goods",
            "type":"Retail Goods"
        }
    ],
    "sg:phone":"+1 804 592 5424",
    "sg:postcode":"23233",
    "sg:province":"VA",
    "sg:tags":[
        "repair"
    ],
    "sg:website":"http://www.fastfix.com/shortpump/home.htm",
    "wof:name":"Fast Fix Jewelry and Watch Repairs",
    "wof:placetype":"venue"
},
  "geometry": {"coordinates":[-77.623299,37.654301],"type":"Point"}
}