{
  "type": "Feature",
  "properties": {
    "iso:country":"US",
    "sg:address":"5343 Ashleigh Rd",
    "sg:city":"Fairfax",
    "sg:classifiers":[
        {
            "category":"Professional",
            "subcategory":"Management & Consulting",
            "type":"Services"
        }
    ],
    "sg:phone":"+1 703 378 6361",
    "sg:postcode":"22030",
    "sg:province":"VA",
    "sg:tags":[
        "business"
    ],
    "wof:name":"Aries Consulting Inc",
    "wof:placetype":"venue"
},
  "geometry": {"coordinates":[-77.392881,38.836819],"type":"Point"}
}