{
  "type": "Feature",
  "properties": {
    "iso:country":"US",
    "sg:address":"11394 Fox Vale Glen Ct",
    "sg:city":"Oakton",
    "sg:classifiers":[
        {
            "category":"Wholesale",
            "subcategory":"Construction Materials",
            "type":"Manufacturing & Wholesale Goods"
        }
    ],
    "sg:phone":"+1 703 758 9290",
    "sg:postcode":"22124",
    "sg:province":"VA",
    "sg:tags":[
        "building",
        "stone",
        "whole"
    ],
    "wof:name":"Penn Direct",
    "wof:placetype":"venue"
},
  "geometry": {"coordinates":[-77.34018399999999,38.892013],"type":"Point"}
}