{
  "type": "Feature",
  "properties": {
    "addr:full":"8401 Richmond Hwy Alexandria VA 22309",
    "addr:housenumber":"8401",
    "addr:postcode":"22309",
    "addr:street":"Richmond Hwy",
    "iso:country":"US",
    "sg:address":"8401 Richmond Hwy",
    "sg:city":"Alexandria",
    "sg:classifiers":[
        {
            "category":"Personal",
            "subcategory":"Beauty Salon",
            "type":"Services"
        }
    ],
    "sg:phone":"+1 703 360 5664",
    "sg:postcode":"22309",
    "sg:province":"VA",
    "wof:name":"Shades Of Essence",
    "wof:placetype":"venue"
},
  "geometry": {"coordinates":[-77.10813899999999,38.729001],"type":"Point"}
}