{
  "type": "Feature",
  "properties": {
    "addr:full":"498 Gloucester Rd Saluda VA 23149",
    "addr:housenumber":"498",
    "addr:postcode":"23149",
    "addr:street":"Gloucester Rd",
    "iso:country":"US",
    "sg:address":"498 Gloucester Rd",
    "sg:city":"Saluda",
    "sg:classifiers":[
        {
            "category":"Health Services",
            "subcategory":"Chiropractor",
            "type":"Services"
        }
    ],
    "sg:phone":"+1 804 758 1800",
    "sg:postcode":"23149",
    "sg:province":"VA",
    "wof:name":"Family Chiropractic Of Saluda",
    "wof:placetype":"venue"
},
  "geometry": {"coordinates":[-76.5996,37.60079],"type":"Point"}
}