{
  "type": "Feature",
  "properties": {
    "iso:country":"US",
    "sg:address":"653 S Washington St",
    "sg:city":"Alexandria",
    "sg:classifiers":[
        {
            "category":"Communications",
            "subcategory":"Film & Video Production",
            "type":"Services"
        }
    ],
    "sg:phone":"+1 703 683 5944",
    "sg:postcode":"22314",
    "sg:province":"VA",
    "sg:tags":[
        "motion"
    ],
    "wof:name":"Metro Productions",
    "wof:placetype":"venue"
},
  "geometry": {"coordinates":[-77.048405,38.798829],"type":"Point"}
}