{
  "type": "Feature",
  "properties": {
    "iso:country":"US",
    "sg:address":"2336 S Nash St",
    "sg:city":"Arlington",
    "sg:classifiers":[
        {
            "category":"Professional",
            "subcategory":"Management & Consulting",
            "type":"Services"
        }
    ],
    "sg:phone":"+1 703 271 0011",
    "sg:postcode":"22202",
    "sg:province":"VA",
    "sg:tags":[
        "consultant",
        "business"
    ],
    "wof:name":"Focus Marketing Inc",
    "wof:placetype":"venue"
},
  "geometry": {"coordinates":[-77.069574,38.851185],"type":"Point"}
}