{
  "type": "Feature",
  "properties": {
    "iso:country":"US",
    "sg:address":"3138 Western Branch Blvd",
    "sg:city":"Chesapeake",
    "sg:classifiers":[
        {
            "category":"Shopping",
            "subcategory":"Pharmacy",
            "type":"Retail Goods"
        }
    ],
    "sg:phone":"+1 757 686 8981",
    "sg:postcode":"23321",
    "sg:province":"VA",
    "wof:name":"Eckerd Drugs",
    "wof:placetype":"venue"
},
  "geometry": {"coordinates":[-76.403548,36.86308],"type":"Point"}
}