{
  "type": "Feature",
  "properties": {
    "addr:full":"8077 Mechanicsville Tpke Mechanicsville VA 23111",
    "addr:postcode":"8077;23111",
    "addr:street":"Tpke",
    "iso:country":"US",
    "sg:address":"8077 Mechanicsville Tpke",
    "sg:city":"Mechanicsville",
    "sg:classifiers":[
        {
            "category":"Shopping",
            "subcategory":"Pharmacy",
            "type":"Retail Goods"
        }
    ],
    "sg:phone":"+1 804 746 5168",
    "sg:postcode":"23111",
    "sg:province":"VA",
    "wof:name":"Mechanicsville Drug Store",
    "wof:placetype":"venue"
},
  "geometry": {"coordinates":[-77.375426,37.601396],"type":"Point"}
}