{
  "type": "Feature",
  "properties": {
    "addr:full":"19096 Wyatts Way Evington VA 24550",
    "addr:postcode":"19096;24550",
    "addr:street":"Wyatts Way",
    "iso:country":"US",
    "sg:address":"19096 Wyatts Way",
    "sg:city":"Evington",
    "sg:classifiers":[
        {
            "category":"Professional",
            "subcategory":"Business Services",
            "type":"Services"
        }
    ],
    "sg:phone":"+1 434 525 0679",
    "sg:postcode":"24550",
    "sg:province":"VA",
    "sg:tags":[
        "residential",
        "construction"
    ],
    "wof:name":"Koss Construction Inc",
    "wof:placetype":"venue"
},
  "geometry": {"coordinates":[-79.341746,37.248432],"type":"Point"}
}