{
  "type": "Feature",
  "properties": {
    "iso:country":"US",
    "sg:address":"50 Catoctin Cir NE",
    "sg:city":"Leesburg",
    "sg:classifiers":[
        {
            "category":"Building & Trades",
            "subcategory":"Construction",
            "type":"Services"
        }
    ],
    "sg:phone":"+1 703 777 1255",
    "sg:postcode":"20176",
    "sg:province":"VA",
    "sg:tags":[
        "home",
        "contractor"
    ],
    "wof:name":"Burke Homes Corp",
    "wof:placetype":"venue"
},
  "geometry": {"coordinates":[-77.554058,39.112209],"type":"Point"}
}