{
  "type": "Feature",
  "properties": {
    "iso:country":"US",
    "sg:address":"2770 S Arlington Mill Drirve",
    "sg:city":"Arlington",
    "sg:classifiers":[
        {
            "category":"Health Services",
            "subcategory":"Dentist",
            "type":"Services"
        }
    ],
    "sg:phone":"+1 703 931 5333",
    "sg:postcode":"22206",
    "sg:province":"VA",
    "wof:name":"Jeffrey A Sisel, DDS",
    "wof:placetype":"venue"
},
  "geometry": {"coordinates":[-77.088365,38.84186],"type":"Point"}
}