{
  "type": "Feature",
  "properties": {
    "addr:full":"6311 Farmville Rd Farmville VA 23901",
    "addr:housenumber":"6311",
    "addr:postcode":"23901",
    "addr:street":"Farmville Rd",
    "iso:country":"US",
    "sg:address":"6311 Farmville Rd",
    "sg:city":"Farmville",
    "sg:classifiers":[
        {
            "category":"Autos & Motor Vehicles",
            "subcategory":"Fuel & Gas Station",
            "type":"Retail Goods"
        },
        {
            "category":"Food & Beverages",
            "subcategory":"Groceries & Convenience Stores",
            "type":"Retail Goods"
        }
    ],
    "sg:phone":"+1 434 223 4373",
    "sg:postcode":"23901",
    "sg:province":"VA",
    "wof:name":"Worsham Grocery",
    "wof:placetype":"venue"
},
  "geometry": {"coordinates":[-78.44256300000001,37.229283],"type":"Point"}
}