{
  "type": "Feature",
  "properties": {
    "addr:full":"214 E Main St Marion VA 24354",
    "addr:housenumber":"214",
    "addr:postcode":"24354",
    "addr:street":"E Main St",
    "iso:country":"US",
    "sg:address":"214 E Main St",
    "sg:city":"Marion",
    "sg:classifiers":[
        {
            "category":"Social Services",
            "type":"Services"
        }
    ],
    "sg:phone":"+1 276 782 3339",
    "sg:postcode":"24354",
    "sg:province":"VA",
    "sg:tags":[
        "mission"
    ],
    "wof:name":"Project Crossroads",
    "wof:placetype":"venue"
},
  "geometry": {"coordinates":[-81.517099,36.833979],"type":"Point"}
}