{
  "type": "Feature",
  "properties": {
    "addr:full":"30 W Commercial St Winchester VA 22601",
    "addr:housenumber":"30",
    "addr:postcode":"22601",
    "addr:street":"W Commercial St",
    "iso:country":"US",
    "sg:address":"30 W Commercial St",
    "sg:city":"Winchester",
    "sg:classifiers":[
        {
            "category":"Food & Beverages",
            "subcategory":"Groceries & Convenience Stores",
            "type":"Retail Goods"
        }
    ],
    "sg:phone":"+1 540 667 1425",
    "sg:postcode":"22601",
    "sg:province":"VA",
    "wof:name":"Pronto",
    "wof:placetype":"venue"
},
  "geometry": {"coordinates":[-78.164063,39.195635],"type":"Point"}
}