{
  "type": "Feature",
  "properties": {
    "addr:full":"4508 S Laburnum Ave Richmond VA 23231",
    "addr:housenumber":"4508",
    "addr:postcode":"23231",
    "addr:street":"S Laburnum Ave",
    "iso:country":"US",
    "sg:address":"4508 S Laburnum Ave",
    "sg:city":"Richmond",
    "sg:classifiers":[
        {
            "category":"Manufacturing",
            "subcategory":"Tools & Machinery",
            "type":"Manufacturing & Wholesale Goods"
        }
    ],
    "sg:phone":"+1 804 222 1796",
    "sg:postcode":"23231",
    "sg:province":"VA",
    "sg:tags":[
        "measuring",
        "instrument",
        "electrical",
        "mfg"
    ],
    "wof:name":"Tencor KLA",
    "wof:placetype":"venue"
},
  "geometry": {"coordinates":[-77.357747,37.528835],"type":"Point"}
}