{
  "type": "Feature",
  "properties": {
    "iso:country":"US",
    "sg:address":"1635 Prince St",
    "sg:city":"Alexandria",
    "sg:classifiers":[
        {
            "category":"Organizations",
            "subcategory":"Professional Association",
            "type":"Services"
        }
    ],
    "sg:phone":"+1 703 683 4646",
    "sg:postcode":"22314",
    "sg:province":"VA",
    "sg:tags":[
        "aircraft",
        "rotary",
        "for",
        "trade"
    ],
    "wof:name":"HELICOPTER ASSOCIATION INTERNA",
    "wof:placetype":"venue"
},
  "geometry": {"coordinates":[-77.058303,38.805417],"type":"Point"}
}