{
  "type": "Feature",
  "properties": {
    "addr:full":"5247 S Laburnum Ave Richmond VA 23231",
    "addr:housenumber":"5247",
    "addr:postcode":"23231",
    "addr:street":"S Laburnum Ave",
    "iso:country":"US",
    "sg:address":"5247 S Laburnum Ave",
    "sg:city":"Richmond",
    "sg:classifiers":[
        {
            "category":"Health Services",
            "subcategory":"Doctor",
            "type":"Services"
        }
    ],
    "sg:phone":"+1 804 236 5867",
    "sg:postcode":"23231",
    "sg:province":"VA",
    "sg:tags":[
        "dentist",
        "medical"
    ],
    "wof:name":"Pamela F Regimbal DDS",
    "wof:placetype":"venue"
},
  "geometry": {"coordinates":[-77.34944400000001,37.511907],"type":"Point"}
}