{
  "type": "Feature",
  "properties": {
    "iso:country":"US",
    "sg:address":"720 Westwood Ave",
    "sg:city":"Hampton",
    "sg:classifiers":[
        {
            "category":"Personal",
            "type":"Services"
        }
    ],
    "sg:phone":"+1 757 945 0990",
    "sg:postcode":"23661",
    "sg:province":"VA",
    "wof:name":"Abes Handyman",
    "wof:placetype":"venue"
},
  "geometry": {"coordinates":[-76.368909,37.019297],"type":"Point"}
}