{
  "type": "Feature",
  "properties": {
    "addr:full":"1950 Old Gallows Rd Ste 525 Vienna VA 22182",
    "addr:housenumber":"1950",
    "addr:postcode":"22182",
    "addr:street":"Old Gallows Rd Ste 525",
    "iso:country":"US",
    "sg:address":"1950 Old Gallows Rd Ste 525",
    "sg:city":"Vienna",
    "sg:classifiers":[
        {
            "category":"Professional",
            "subcategory":"Lawyer & Legal Services",
            "type":"Services"
        }
    ],
    "sg:phone":"+1 703 288 4777",
    "sg:postcode":"22182",
    "sg:province":"VA",
    "sg:website":"www.ryanandwetmore.com",
    "wof:name":"Ryan & Wetmore PC",
    "wof:placetype":"venue"
},
  "geometry": {"coordinates":[-77.22280499999999,38.910685],"type":"Point"}
}