{
  "type": "Feature",
  "properties": {
    "iso:country":"US",
    "sg:address":"11000 Smoketree Dr",
    "sg:city":"Richmond",
    "sg:classifiers":[
        {
            "category":"Organizations",
            "subcategory":"Religious Organization",
            "type":"Services"
        }
    ],
    "sg:phone":"+1 804 794 0222",
    "sg:postcode":"23236",
    "sg:province":"VA",
    "sg:tags":[
        "church"
    ],
    "sg:website":"www.epiphanychurch.org",
    "wof:name":"Church Of The Epiphany",
    "wof:placetype":"venue"
},
  "geometry": {"coordinates":[-77.60093500000001,37.484304],"type":"Point"}
}