{
  "type": "Feature",
  "properties": {
    "iso:country":"US",
    "sg:address":"326 French Woods Rd",
    "sg:city":"Woodstock",
    "sg:classifiers":[
        {
            "category":"Professional",
            "type":"Services"
        }
    ],
    "sg:phone":"+1 540 459 2964",
    "sg:postcode":"22664",
    "sg:province":"VA",
    "wof:name":"Woodstock/Edinburg Little",
    "wof:placetype":"venue"
},
  "geometry": {"coordinates":[-78.493194,38.873962],"type":"Point"}
}