{
  "type": "Feature",
  "properties": {
    "addr:full":"8624 Phoenix Dr Manassas VA 20110",
    "addr:housenumber":"8624",
    "addr:postcode":"20110",
    "addr:street":"Phoenix Dr",
    "iso:country":"US",
    "sg:address":"8624 Phoenix Dr",
    "sg:city":"Manassas",
    "sg:classifiers":[
        {
            "category":"Organizations",
            "subcategory":"Religious Organization",
            "type":"Services"
        }
    ],
    "sg:phone":"+1 703 361 0890",
    "sg:postcode":"20110",
    "sg:province":"VA",
    "wof:name":"Blest Books",
    "wof:placetype":"venue"
},
  "geometry": {"coordinates":[-77.456384,38.764277],"type":"Point"}
}