{
  "type": "Feature",
  "properties": {
    "addr:full":"5501 Sully Park Dr Centreville VA 20120",
    "addr:postcode":"5501;20120",
    "addr:street":"Sully Park Dr",
    "iso:country":"US",
    "sg:address":"5501 Sully Park Dr",
    "sg:city":"Centreville",
    "sg:classifiers":[
        {
            "category":"Professional",
            "type":"Services"
        }
    ],
    "sg:phone":"+1 703 968 9753",
    "sg:postcode":"20120",
    "sg:province":"VA",
    "sg:tags":[
        "information",
        "bureau"
    ],
    "wof:name":"Sully Station II",
    "wof:placetype":"venue"
},
  "geometry": {"coordinates":[-77.454228,38.855511],"type":"Point"}
}