{
  "type": "Feature",
  "properties": {
    "iso:country":"US",
    "sg:address":"1778 Hamburg Rd",
    "sg:city":"Edinburg",
    "sg:classifiers":[
        {
            "category":"Home & Garden",
            "subcategory":"Building Materials",
            "type":"Retail Goods"
        }
    ],
    "sg:phone":"+1 540 984 9757",
    "sg:postcode":"22824",
    "sg:province":"VA",
    "wof:name":"Central Paint & Decorating",
    "wof:placetype":"venue"
},
  "geometry": {"coordinates":[-78.6233,38.816678],"type":"Point"}
}