{
  "type": "Feature",
  "properties": {
    "iso:country":"US",
    "sg:address":"809 Yearling Ct",
    "sg:city":"Virginia Beach",
    "sg:classifiers":[
        {
            "category":"Building & Trades",
            "subcategory":"Construction",
            "type":"Services"
        }
    ],
    "sg:phone":"+1 757 467 4781",
    "sg:postcode":"23464",
    "sg:province":"VA",
    "sg:tags":[
        "house"
    ],
    "wof:name":"G & S Home Repair",
    "wof:placetype":"venue"
},
  "geometry": {"coordinates":[-76.141773,36.811489],"type":"Point"}
}