{
  "type": "Feature",
  "properties": {
    "addr:full":"3815 S George Mason Dr Falls Church VA 22041",
    "addr:housenumber":"3815",
    "addr:postcode":"22041",
    "addr:street":"S George Mason Dr",
    "iso:country":"US",
    "sg:address":"3815 S George Mason Dr",
    "sg:city":"Falls Church",
    "sg:classifiers":[
        {
            "category":"Manufacturing",
            "subcategory":"Tools & Machinery",
            "type":"Manufacturing & Wholesale Goods"
        }
    ],
    "sg:phone":"+1 703 845 1526",
    "sg:postcode":"22041",
    "sg:province":"VA",
    "sg:tags":[
        "mfg"
    ],
    "wof:name":"Villalva Inc",
    "wof:placetype":"venue"
},
  "geometry": {"coordinates":[-77.11909,38.841797],"type":"Point"}
}