{
  "type": "Feature",
  "properties": {
    "addr:full":"4509 Melrose Ave NW Roanoke VA 24017",
    "addr:housenumber":"4509",
    "addr:postcode":"24017",
    "addr:street":"Melrose Ave Nw",
    "iso:country":"US",
    "sg:address":"4509 Melrose Ave NW",
    "sg:city":"Roanoke",
    "sg:classifiers":[
        {
            "category":"Home & Garden",
            "subcategory":"Mobile Homes",
            "type":"Retail Goods"
        }
    ],
    "sg:phone":"+1 540 986 1027",
    "sg:postcode":"24017",
    "sg:province":"VA",
    "sg:tags":[
        "manufactured"
    ],
    "wof:name":"Fleetwood Homes",
    "wof:placetype":"venue"
},
  "geometry": {"coordinates":[-80.010538,37.297665],"type":"Point"}
}