{
  "type": "Feature",
  "properties": {
    "addr:full":"1605 Lefrak Ct Herndon VA 20170",
    "addr:housenumber":"1605",
    "addr:postcode":"20170",
    "addr:street":"Lefrak Ct",
    "iso:country":"US",
    "sg:address":"1605 Lefrak Ct",
    "sg:city":"Herndon",
    "sg:classifiers":[
        {
            "category":"Communications",
            "subcategory":"Film & Video Production",
            "type":"Services"
        }
    ],
    "sg:phone":"+1 703 437 3051",
    "sg:postcode":"20170",
    "sg:province":"VA",
    "sg:tags":[
        "services-commercial"
    ],
    "wof:name":"Dunbar Productions",
    "wof:placetype":"venue"
},
  "geometry": {"coordinates":[-77.393613,38.989073],"type":"Point"}
}