{
  "type": "Feature",
  "properties": {
    "iso:country":"US",
    "sg:address":"7412 Vernon Square Dr",
    "sg:city":"Alexandria",
    "sg:classifiers":[
        {
            "category":"Social Services",
            "subcategory":"Child Care",
            "type":"Services"
        }
    ],
    "sg:phone":"+1 703 765 3461",
    "sg:postcode":"22306",
    "sg:province":"VA",
    "sg:tags":[
        "day"
    ],
    "wof:name":"Sonia D Hardin",
    "wof:placetype":"venue"
},
  "geometry": {"coordinates":[-77.07867400000001,38.756549],"type":"Point"}
}