{
  "type": "Feature",
  "properties": {
    "iso:country":"US",
    "sg:address":"4115 Melrose Ave NW",
    "sg:city":"Roanoke",
    "sg:classifiers":[
        {
            "category":"Restaurant",
            "type":"Food & Drink"
        }
    ],
    "sg:phone":"+1 540 366 3727",
    "sg:postcode":"24017",
    "sg:province":"VA",
    "sg:tags":[
        "style",
        "chinese",
        "family",
        "asian",
        "pan"
    ],
    "wof:name":"Taipei Restaurant",
    "wof:placetype":"venue"
},
  "geometry": {"coordinates":[-80.00368,37.296159],"type":"Point"}
}