{
  "type": "Feature",
  "properties": {
    "iso:country":"US",
    "sg:address":"6145 Sewells Point Rd",
    "sg:city":"Norfolk",
    "sg:classifiers":[
        {
            "category":"Banks & Credit Unions",
            "subcategory":"Bank",
            "type":"Services"
        }
    ],
    "sg:phone":"+1 757 628 6863",
    "sg:postcode":"23513",
    "sg:province":"VA",
    "sg:tags":[
        "state"
    ],
    "wof:name":"First Vrgnia Bnk - Hmpton Rads",
    "wof:placetype":"venue"
},
  "geometry": {"coordinates":[-76.23862200000001,36.890401],"type":"Point"}
}