{
  "type": "Feature",
  "properties": {
    "addr:full":"1957 Daniel Stuart Sq Woodbridge VA 22191",
    "addr:housenumber":"1957",
    "addr:postcode":"22191",
    "addr:street":"Daniel Stuart Sq",
    "iso:country":"US",
    "sg:address":"1957 Daniel Stuart Sq",
    "sg:city":"Woodbridge",
    "sg:classifiers":[
        {
            "category":"Shopping",
            "subcategory":"Computers & Home Electronics",
            "type":"Retail Goods"
        }
    ],
    "sg:phone":"+1 703 494 7793",
    "sg:postcode":"22191",
    "sg:province":"VA",
    "sg:tags":[
        "equipment",
        "electronic",
        "supply"
    ],
    "wof:name":"Radio Shack",
    "wof:placetype":"venue"
},
  "geometry": {"coordinates":[-77.274894,38.633147],"type":"Point"}
}