{
  "type": "Feature",
  "properties": {
    "addr:full":"8629 Lee Hwy Fairfax VA 22031",
    "addr:housenumber":"8629",
    "addr:postcode":"22031",
    "addr:street":"Lee Hwy",
    "iso:country":"US",
    "sg:address":"8629 Lee Hwy",
    "sg:city":"Fairfax",
    "sg:classifiers":[
        {
            "category":"Personal",
            "subcategory":"Nail Salon",
            "type":"Services"
        }
    ],
    "sg:phone":"+1 703 289 1166",
    "sg:postcode":"22031",
    "sg:province":"VA",
    "wof:name":"U-Neek Nails",
    "wof:placetype":"venue"
},
  "geometry": {"coordinates":[-77.24413300000001,38.873144],"type":"Point"}
}