{
  "type": "Feature",
  "properties": {
    "iso:country":"US",
    "sg:address":"601 Frost Ave",
    "sg:city":"Warrenton",
    "sg:classifiers":[
        {
            "category":"Professional",
            "type":"Services"
        }
    ],
    "sg:phone":"+1 540 347 2955",
    "sg:postcode":"20186",
    "sg:province":"VA",
    "sg:tags":[
        "establishment"
    ],
    "wof:name":"Built By Bruce",
    "wof:placetype":"venue"
},
  "geometry": {"coordinates":[-77.81186,38.716712],"type":"Point"}
}