{
  "type": "Feature",
  "properties": {
    "addr:full":"816 Galway Ln Fredericksburg VA 22407",
    "addr:housenumber":"816",
    "addr:postcode":"22407",
    "addr:street":"Galway Ln",
    "iso:country":"US",
    "sg:address":"816 Galway Ln",
    "sg:city":"Fredericksburg",
    "sg:classifiers":[
        {
            "category":"Building & Trades",
            "subcategory":"Construction",
            "type":"Services"
        }
    ],
    "sg:phone":"+1 540 785 8366",
    "sg:postcode":"22407",
    "sg:province":"VA",
    "sg:tags":[
        "house"
    ],
    "wof:name":"Ed Larkins Construction",
    "wof:placetype":"venue"
},
  "geometry": {"coordinates":[-77.552932,38.284724],"type":"Point"}
}