{
  "type": "Feature",
  "properties": {
    "addr:full":"501 Richmond Rd Williamsburg VA 23185",
    "addr:housenumber":"501",
    "addr:postcode":"23185",
    "addr:street":"Richmond Rd",
    "iso:country":"US",
    "sg:address":"501 Richmond Rd",
    "sg:city":"Williamsburg",
    "sg:classifiers":[
        {
            "category":"Travel",
            "subcategory":"Hotels & Motels",
            "type":"Entertainment"
        }
    ],
    "sg:phone":"+1 757 229 0233",
    "sg:postcode":"23185",
    "sg:province":"VA",
    "sg:tags":[
        "breakfast",
        "accommodation",
        "bed"
    ],
    "sg:website":"www.ccbb.com",
    "wof:name":"Colonial Capital Bed & Brkfst",
    "wof:placetype":"venue"
},
  "geometry": {"coordinates":[-76.71409800000001,37.275064],"type":"Point"}
}