{
  "type": "Feature",
  "properties": {
    "addr:full":"1214 Agnese St Charlottesville VA 22901",
    "addr:housenumber":"1214",
    "addr:postcode":"22901",
    "addr:street":"Agnese St",
    "iso:country":"US",
    "sg:address":"1214 Agnese St",
    "sg:city":"Charlottesville",
    "sg:classifiers":[
        {
            "category":"Organizations",
            "subcategory":"Religious Organization",
            "type":"Services"
        }
    ],
    "sg:phone":"+1 434 979 0617",
    "sg:postcode":"22901",
    "sg:province":"VA",
    "sg:tags":[
        "clergy"
    ],
    "wof:name":"James Johnson",
    "wof:placetype":"venue"
},
  "geometry": {"coordinates":[-78.462137,38.047626],"type":"Point"}
}