{
  "type": "Feature",
  "properties": {
    "iso:country":"US",
    "sg:address":"2100 Memorial Ave",
    "sg:city":"Lynchburg",
    "sg:classifiers":[
        {
            "category":"Wholesale",
            "subcategory":"Electrical",
            "type":"Manufacturing & Wholesale Goods"
        }
    ],
    "sg:phone":"+1 434 845 8833",
    "sg:postcode":"24501",
    "sg:province":"VA",
    "sg:tags":[
        "alarm",
        "burglar",
        "system"
    ],
    "wof:name":"IDS Security",
    "wof:placetype":"venue"
},
  "geometry": {"coordinates":[-79.16431799999999,37.407303],"type":"Point"}
}