{
  "type": "Feature",
  "properties": {
    "iso:country":"US",
    "sg:address":"1950 Old Gallows Rd",
    "sg:city":"Vienna",
    "sg:classifiers":[
        {
            "category":"Professional",
            "subcategory":"Computer Services",
            "type":"Services"
        }
    ],
    "sg:phone":"+1 703 663 1060",
    "sg:postcode":"22182",
    "sg:province":"VA",
    "sg:tags":[
        "pharmaceutical",
        "consulting",
        "agency",
        "employment"
    ],
    "wof:name":"Precept Clinical",
    "wof:placetype":"venue"
},
  "geometry": {"coordinates":[-77.22250200000001,38.911161],"type":"Point"}
}