{
  "type": "Feature",
  "properties": {
    "iso:country":"US",
    "sg:address":"300 Butler Farm Rd",
    "sg:city":"Hampton",
    "sg:classifiers":[
        {
            "category":"Recreation",
            "type":"Entertainment"
        }
    ],
    "sg:phone":"+1 757 766 2391",
    "sg:postcode":"23666",
    "sg:province":"VA",
    "sg:tags":[
        "tennis",
        "instruction"
    ],
    "wof:name":"Matchpoint Inc",
    "wof:placetype":"venue"
},
  "geometry": {"coordinates":[-76.400211,37.063505],"type":"Point"}
}