{
  "type": "Feature",
  "properties": {
    "addr:full":"275 Waqua Creek Rd Warfield VA 23889",
    "addr:housenumber":"275",
    "addr:postcode":"23889",
    "addr:street":"Waqua Creek Rd",
    "iso:country":"US",
    "sg:address":"275 Waqua Creek Rd",
    "sg:city":"Warfield",
    "sg:classifiers":[
        {
            "category":"Organizations",
            "subcategory":"Religious Organization",
            "type":"Services"
        }
    ],
    "sg:phone":"+1 434 949 7720",
    "sg:postcode":"23889",
    "sg:province":"VA",
    "sg:tags":[
        "church"
    ],
    "wof:name":"St James Episcopal Church",
    "wof:placetype":"venue"
},
  "geometry": {"coordinates":[-77.809804,36.901571],"type":"Point"}
}