{
  "type": "Feature",
  "properties": {
    "addr:full":"56 Patch Rd Fort Monroe VA 23651",
    "addr:housenumber":"56",
    "addr:postcode":"23651",
    "addr:street":"Patch Rd",
    "iso:country":"US",
    "sg:address":"56 Patch Rd",
    "sg:city":"Fort Monroe",
    "sg:classifiers":[
        {
            "category":"Government",
            "subcategory":"Office",
            "type":"Public Place"
        }
    ],
    "sg:phone":"+1 757 727 4569",
    "sg:postcode":"23651",
    "sg:province":"VA",
    "sg:tags":[
        "cadet",
        "command",
        "center"
    ],
    "wof:name":"Army Cadet Command",
    "wof:placetype":"venue"
},
  "geometry": {"coordinates":[-76.31151199999999,37.006083],"type":"Point"}
}