{
  "type": "Feature",
  "properties": {
    "addr:full":"10376 Bullock Dr King George VA 22485",
    "addr:housenumber":"10376",
    "addr:postcode":"22485",
    "addr:street":"Bullock Dr",
    "iso:country":"US",
    "sg:address":"10376 Bullock Dr",
    "sg:city":"King George",
    "sg:classifiers":[
        {
            "category":"Utilities",
            "subcategory":"Refuse",
            "type":"Services"
        }
    ],
    "sg:phone":"+1 540 775 3123",
    "sg:postcode":"22485",
    "sg:province":"VA",
    "sg:tags":[
        "landfill",
        "sanitary"
    ],
    "wof:name":"George King Landfill Inc",
    "wof:placetype":"venue"
},
  "geometry": {"coordinates":[-77.306211,38.27389],"type":"Point"}
}