{
  "type": "Feature",
  "properties": {
    "addr:full":"5500 Sully Park Dr Centreville VA 20120",
    "addr:housenumber":"5500",
    "addr:postcode":"20120",
    "addr:street":"Sully Park Dr",
    "iso:country":"US",
    "sg:address":"5500 Sully Park Dr",
    "sg:city":"Centreville",
    "sg:classifiers":[
        {
            "category":"Education",
            "subcategory":"School",
            "type":"Public Place"
        }
    ],
    "sg:phone":"+1 703 631 5500",
    "sg:postcode":"20120",
    "sg:province":"VA",
    "wof:name":"Ormond Stone Middle School",
    "wof:placetype":"venue"
},
  "geometry": {"coordinates":[-77.45416899999999,38.855442],"type":"Point"}
}