{
  "type": "Feature",
  "properties": {
    "iso:country":"US",
    "sg:address":"14207 Junior Ln",
    "sg:city":"Pungoteague",
    "sg:classifiers":[
        {
            "category":"Professional",
            "type":"Services"
        }
    ],
    "sg:phone":"+1 757 442 5136",
    "sg:postcode":"23410",
    "sg:province":"VA",
    "sg:tags":[
        "establishment"
    ],
    "wof:name":"Harborton Post Ofc",
    "wof:placetype":"venue"
},
  "geometry": {"coordinates":[-75.832728,37.661034],"type":"Point"}
}