{
  "type": "Feature",
  "properties": {
    "addr:full":"120 Monitor Rd Portsmouth VA 23707",
    "addr:housenumber":"120",
    "addr:postcode":"23707",
    "addr:street":"Monitor Rd",
    "iso:country":"US",
    "sg:address":"120 Monitor Rd",
    "sg:city":"Portsmouth",
    "sg:classifiers":[
        {
            "category":"Professional",
            "subcategory":"Management & Consulting",
            "type":"Services"
        }
    ],
    "sg:phone":"+1 757 393 9854",
    "sg:postcode":"23707",
    "sg:province":"VA",
    "wof:name":"Northside Management Inc",
    "wof:placetype":"venue"
},
  "geometry": {"coordinates":[-76.344663,36.851891],"type":"Point"}
}