{
  "type": "Feature",
  "properties": {
    "addr:full":"4501 Singer Ct Chantilly VA 20151",
    "addr:housenumber":"4501",
    "addr:postcode":"20151",
    "addr:street":"Singer Ct",
    "iso:country":"US",
    "sg:address":"4501 Singer Ct",
    "sg:city":"Chantilly",
    "sg:classifiers":[
        {
            "category":"Banks & Credit Unions",
            "subcategory":"Bank",
            "type":"Services"
        }
    ],
    "sg:phone":"+1 703 961 7800",
    "sg:postcode":"20151",
    "sg:province":"VA",
    "sg:tags":[
        "lender",
        "residential",
        "mortgage"
    ],
    "wof:name":"Calusa Investments LLC",
    "wof:placetype":"venue"
},
  "geometry": {"coordinates":[-77.458742,38.889801],"type":"Point"}
}