{
  "type": "Feature",
  "properties": {
    "addr:full":"423 Flatridge Rd Cana VA 24317",
    "addr:housenumber":"423",
    "addr:postcode":"24317",
    "addr:street":"Flatridge Rd",
    "iso:country":"US",
    "sg:address":"423 Flatridge Rd",
    "sg:city":"Cana",
    "sg:classifiers":[
        {
            "category":"Building & Trades",
            "subcategory":"Landscaping Services",
            "type":"Services"
        }
    ],
    "sg:phone":"+1 276 755 3893",
    "sg:postcode":"24317",
    "sg:province":"VA",
    "wof:name":"Mondays Lawn Mainten",
    "wof:placetype":"venue"
},
  "geometry": {"coordinates":[-80.623876,36.580937],"type":"Point"}
}