{
  "type": "Feature",
  "properties": {
    "addr:full":"1012 Poplar Dr Falls Church VA 22046",
    "addr:housenumber":"1012",
    "addr:postcode":"22046",
    "addr:street":"Poplar Dr",
    "iso:country":"US",
    "sg:address":"1012 Poplar Dr",
    "sg:city":"Falls Church",
    "sg:classifiers":[
        {
            "category":"Insurance",
            "subcategory":"Hazard Insurance",
            "type":"Services"
        }
    ],
    "sg:phone":"+1 703 241 1788",
    "sg:postcode":"22046",
    "sg:province":"VA",
    "sg:tags":[
        "carrier"
    ],
    "wof:name":"Elite Medical Legal Services",
    "wof:placetype":"venue"
},
  "geometry": {"coordinates":[-77.19344100000001,38.887859],"type":"Point"}
}