{
  "type": "Feature",
  "properties": {
    "addr:full":"407 Harbour Pt Virginia Beach VA 23451",
    "addr:housenumber":"407",
    "addr:postcode":"23451",
    "addr:street":"Harbour Pt",
    "iso:country":"US",
    "sg:address":"407 Harbour Pt",
    "sg:city":"Virginia Beach",
    "sg:classifiers":[
        {
            "category":"Professional",
            "type":"Services"
        }
    ],
    "sg:phone":"+1 757 491 1776",
    "sg:postcode":"23451",
    "sg:province":"VA",
    "sg:tags":[
        "establishment"
    ],
    "wof:name":"Tele Tec",
    "wof:placetype":"venue"
},
  "geometry": {"coordinates":[-75.97433599999999,36.829632],"type":"Point"}
}