{
  "type": "Feature",
  "properties": {
    "iso:country":"US",
    "sg:address":"1333 Ingleside Rd",
    "sg:city":"Norfolk",
    "sg:classifiers":[
        {
            "category":"Building & Trades",
            "subcategory":"Construction",
            "type":"Services"
        }
    ],
    "sg:phone":"+1 757 853 4511",
    "sg:postcode":"23502",
    "sg:province":"VA",
    "sg:tags":[
        "painting",
        "paper",
        "sandblasting",
        "hanging"
    ],
    "wof:name":"E Caligari & Son Inc",
    "wof:placetype":"venue"
},
  "geometry": {"coordinates":[-76.24279300000001,36.859464],"type":"Point"}
}