{
  "type": "Feature",
  "properties": {
    "iso:country":"US",
    "sg:address":"Rock Spring United Church of Christ 5010 Little Falls Rd",
    "sg:city":"Arlington",
    "sg:classifiers":[
        {
            "category":"Arena",
            "subcategory":"Sports Club",
            "type":"Entertainment"
        }
    ],
    "sg:phone":"+1 703 845 0083",
    "sg:postcode":"22216",
    "sg:province":"VA",
    "sg:tags":[
        "martial art"
    ],
    "sg:website":"www.taichischool.org",
    "wof:name":"The School of T'ai Chi Chuan of Metropolitan Washington, Inc.",
    "wof:placetype":"venue"
},
  "geometry": {"coordinates":[-77.138266,38.907569],"type":"Point"}
}