{
  "type": "Feature",
  "properties": {
    "addr:full":"3412 Hull St Richmond VA 23224",
    "addr:housenumber":"3412",
    "addr:postcode":"23224",
    "addr:street":"Hull St",
    "iso:country":"US",
    "sg:address":"3412 Hull St",
    "sg:city":"Richmond",
    "sg:classifiers":[
        {
            "category":"Personal",
            "subcategory":"Beauty Salon",
            "type":"Services"
        }
    ],
    "sg:phone":"+1 804 230 1602",
    "sg:postcode":"23224",
    "sg:province":"VA",
    "wof:name":"P D Charlotte's African Hair",
    "wof:placetype":"venue"
},
  "geometry": {"coordinates":[-77.467647,37.505841],"type":"Point"}
}