{
  "type": "Feature",
  "properties": {
    "addr:full":"2161 Barracks Rd Charlottesville VA 22903",
    "addr:housenumber":"2161",
    "addr:postcode":"22903",
    "addr:street":"Barracks Rd",
    "iso:country":"US",
    "sg:address":"2161 Barracks Rd",
    "sg:city":"Charlottesville",
    "sg:classifiers":[
        {
            "category":"Autos & Motor Vehicles",
            "subcategory":"Fuel & Gas Station",
            "type":"Retail Goods"
        },
        {
            "category":"Autos & Motor Vehicles",
            "subcategory":"Auto Supplies",
            "type":"Retail Goods"
        }
    ],
    "sg:phone":"+1 434 295 0395",
    "sg:postcode":"22903",
    "sg:province":"VA",
    "sg:tags":[
        "tire"
    ],
    "wof:name":"Finley's Barracks Road Service Center Inc",
    "wof:placetype":"venue"
},
  "geometry": {"coordinates":[-78.50099899999999,38.054699],"type":"Point"}
}