{
  "type": "Feature",
  "properties": {
    "addr:full":"1724 Sir William Osler Dr Virginia Beach VA 23454",
    "addr:housenumber":"1724",
    "addr:postcode":"23454",
    "addr:street":"Sir William Osler Dr",
    "iso:country":"US",
    "sg:address":"1724 Sir William Osler Dr",
    "sg:city":"Virginia Beach",
    "sg:classifiers":[
        {
            "category":"Health Services",
            "subcategory":"Doctor",
            "type":"Services"
        }
    ],
    "sg:phone":"+1 757 481 1894",
    "sg:postcode":"23454",
    "sg:province":"VA",
    "sg:tags":[
        "dentist"
    ],
    "wof:name":"James Y Chau DDS PC",
    "wof:placetype":"venue"
},
  "geometry": {"coordinates":[-76.02964299999999,36.864966],"type":"Point"}
}