{
  "type": "Feature",
  "properties": {
    "iso:country":"US",
    "sg:address":"5301 Watercrest Rd",
    "sg:city":"Midlothian",
    "sg:classifiers":[
        {
            "category":"Professional",
            "subcategory":"Business Services",
            "type":"Services"
        }
    ],
    "sg:phone":"+1 804 639 7436",
    "sg:postcode":"23112",
    "sg:province":"VA",
    "wof:name":"Holljes & Assoc Inc",
    "wof:placetype":"venue"
},
  "geometry": {"coordinates":[-77.67044799999999,37.428098],"type":"Point"}
}