{
  "type": "Feature",
  "properties": {
    "addr:full":"11204 James Swart Cir Fairfax VA 22030",
    "addr:housenumber":"11204",
    "addr:postcode":"22030",
    "addr:street":"James Swart Cir",
    "iso:country":"US",
    "sg:address":"11204 James Swart Cir",
    "sg:city":"Fairfax",
    "sg:classifiers":[
        {
            "category":"Restaurant",
            "type":"Food & Drink"
        }
    ],
    "sg:menulink":"http://www.allmenus.com/va/fairfax/104046-ruby-tuesdays/menu/",
    "sg:phone":"+1 703 352 6863",
    "sg:postcode":"22030",
    "sg:province":"VA",
    "sg:tags":[
        "burger",
        "american"
    ],
    "wof:name":"Ruby Tuesdays",
    "wof:placetype":"venue"
},
  "geometry": {"coordinates":[-77.333837,38.85514],"type":"Point"}
}