{
  "type": "Feature",
  "properties": {
    "iso:country":"US",
    "sg:address":"2000 Corporate Ridge",
    "sg:city":"Mc Lean",
    "sg:classifiers":[
        {
            "category":"Professional",
            "subcategory":"Management & Consulting",
            "type":"Services"
        }
    ],
    "sg:phone":"+1 703 506 2929",
    "sg:postcode":"22102",
    "sg:province":"VA",
    "sg:tags":[
        "firm"
    ],
    "wof:name":"MCR Federal",
    "wof:placetype":"venue"
},
  "geometry": {"coordinates":[-77.21711999999999,38.913402],"type":"Point"}
}