{
  "type": "Feature",
  "properties": {
    "iso:country":"US",
    "sg:address":"8221 Midlothian Tpke",
    "sg:city":"Richmond",
    "sg:classifiers":[
        {
            "category":"Shopping",
            "subcategory":"Florist",
            "type":"Retail Goods"
        }
    ],
    "sg:phone":"+1 804 320 0036",
    "sg:postcode":"23235",
    "sg:province":"VA",
    "sg:website":"www.markowflorist.com",
    "wof:name":"Markow Florist",
    "wof:placetype":"venue"
},
  "geometry": {"coordinates":[-77.547792,37.497087],"type":"Point"}
}