{
  "type": "Feature",
  "properties": {
    "iso:country":"US",
    "sg:address":"229 N Courthouse Rd",
    "sg:city":"Richmond",
    "sg:classifiers":[
        {
            "category":"Utilities",
            "subcategory":"Sewage",
            "type":"Services"
        },
        {
            "category":"Building & Trades",
            "subcategory":"Plumbing",
            "type":"Services"
        }
    ],
    "sg:phone":"+1 804 794 7203",
    "sg:postcode":"23236",
    "sg:province":"VA",
    "sg:tags":[
        "disposal",
        "system",
        "contractor"
    ],
    "wof:name":"Gentry Septic Tank Service",
    "wof:placetype":"venue"
},
  "geometry": {"coordinates":[-77.60181900000001,37.493827],"type":"Point"}
}