{
  "type": "Feature",
  "properties": {
    "addr:full":"10017 Rogers Dr Nassawadox VA 23413",
    "addr:housenumber":"10017",
    "addr:postcode":"23413",
    "addr:street":"Rogers Dr",
    "iso:country":"US",
    "sg:address":"10017 Rogers Dr",
    "sg:city":"Nassawadox",
    "sg:classifiers":[
        {
            "category":"Utilities",
            "type":"Services"
        }
    ],
    "sg:phone":"+1 757 442 2981",
    "sg:postcode":"23413",
    "sg:province":"VA",
    "sg:tags":[
        "cleanup",
        "demolition"
    ],
    "wof:name":"Task Force LLC",
    "wof:placetype":"venue"
},
  "geometry": {"coordinates":[-75.86197199999999,37.478911],"type":"Point"}
}