{
  "type": "Feature",
  "properties": {
    "addr:full":"1932 Horseshoe Bend Virginia Beach VA 23455",
    "addr:housenumber":"1932",
    "addr:postcode":"23455",
    "addr:street":"Horseshoe Bend",
    "iso:country":"US",
    "sg:address":"1932 Horseshoe Bend",
    "sg:city":"Virginia Beach",
    "sg:classifiers":[
        {
            "category":"Real Estate",
            "subcategory":"Real Estate Operator",
            "type":"Services"
        }
    ],
    "sg:phone":"+1 757 464 0618",
    "sg:postcode":"23455",
    "sg:province":"VA",
    "sg:tags":[
        "shopping",
        "center",
        "ownership"
    ],
    "wof:name":"Little Creek Investment Corp",
    "wof:placetype":"venue"
},
  "geometry": {"coordinates":[-76.154577,36.903542],"type":"Point"}
}