{
  "type": "Feature",
  "properties": {
    "iso:country":"US",
    "sg:address":"144 Broadview Ave",
    "sg:city":"Warrenton",
    "sg:classifiers":[
        {
            "category":"Arena",
            "subcategory":"Sports Club",
            "type":"Entertainment"
        }
    ],
    "sg:phone":"+1 540 347 4973",
    "sg:postcode":"20186",
    "sg:province":"VA",
    "sg:tags":[
        "martial art"
    ],
    "sg:website":"www.ksatkd.net",
    "wof:name":"Karate Sports Academy",
    "wof:placetype":"venue"
},
  "geometry": {"coordinates":[-77.807098,38.719002],"type":"Point"}
}