{
  "type": "Feature",
  "properties": {
    "addr:full":"6024 1st St N Arlington VA 22203",
    "addr:housenumber":"6024",
    "addr:postcode":"22203",
    "addr:street":"1St St N",
    "iso:country":"US",
    "sg:address":"6024 1st St N",
    "sg:city":"Arlington",
    "sg:classifiers":[
        {
            "category":"Organizations",
            "subcategory":"Membership Organization",
            "type":"Services"
        }
    ],
    "sg:phone":"+1 703 527 3406",
    "sg:postcode":"22203",
    "sg:province":"VA",
    "wof:name":"George Fumich Assoc",
    "wof:placetype":"venue"
},
  "geometry": {"coordinates":[-77.13740199999999,38.868139],"type":"Point"}
}