{
  "type": "Feature",
  "properties": {
    "iso:country":"US",
    "sg:address":"21 N Belmont Ave",
    "sg:city":"Richmond",
    "sg:classifiers":[
        {
            "category":"Shopping",
            "subcategory":"Florist",
            "type":"Retail Goods"
        }
    ],
    "sg:phone":"+1 804 355 1096",
    "sg:postcode":"23221",
    "sg:province":"VA",
    "wof:name":"Floraculture",
    "wof:placetype":"venue"
},
  "geometry": {"coordinates":[-77.47891199999999,37.554928],"type":"Point"}
}