{
  "type": "Feature",
  "properties": {
    "iso:country":"US",
    "sg:address":"15325 Mountain Rd",
    "sg:city":"Montpelier",
    "sg:classifiers":[
        {
            "category":"Recreation",
            "type":"Entertainment"
        }
    ],
    "sg:phone":"+1 804 883 7740",
    "sg:postcode":"23192",
    "sg:province":"VA",
    "sg:tags":[
        "photography",
        "instruction"
    ],
    "wof:name":"Natures Image Photography",
    "wof:placetype":"venue"
},
  "geometry": {"coordinates":[-77.624729,37.772343],"type":"Point"}
}