{
  "type": "Feature",
  "properties": {
    "iso:country":"US",
    "sg:address":"556 Dettor Rd",
    "sg:city":"Charlottesville",
    "sg:classifiers":[
        {
            "category":"Shopping",
            "subcategory":"Computers & Home Electronics",
            "type":"Retail Goods"
        }
    ],
    "sg:phone":"+1 434 977 1971",
    "sg:postcode":"22903",
    "sg:province":"VA",
    "sg:tags":[
        "repair",
        "television",
        "high",
        "stereophonic",
        "radio-service",
        "fidelity"
    ],
    "sg:website":"http://www.tesva.com",
    "wof:name":"Total Entertainment Solutions",
    "wof:placetype":"venue"
},
  "geometry": {"coordinates":[-78.61734199999999,38.058021],"type":"Point"}
}