{
  "type": "Feature",
  "properties": {
    "addr:full":"2725 Market St NE Christiansburg VA 24073",
    "addr:housenumber":"2725",
    "addr:postcode":"24073",
    "addr:street":"Market St Ne",
    "iso:country":"US",
    "sg:address":"2725 Market St NE",
    "sg:city":"Christiansburg",
    "sg:classifiers":[
        {
            "category":"Home & Garden",
            "subcategory":"Furniture",
            "type":"Retail Goods"
        }
    ],
    "sg:phone":"+1 540 381 5837",
    "sg:postcode":"24073",
    "sg:province":"VA",
    "sg:tags":[
        "mattress"
    ],
    "wof:name":"Mattress King 30",
    "wof:placetype":"venue"
},
  "geometry": {"coordinates":[-80.421429,37.166746],"type":"Point"}
}