{
  "type": "Feature",
  "properties": {
    "iso:country":"US",
    "sg:address":"500 Colonial Ave",
    "sg:city":"Colonial Beach",
    "sg:classifiers":[
        {
            "category":"Shopping",
            "subcategory":"Used Merchandise",
            "type":"Retail Goods"
        }
    ],
    "sg:phone":"+1 804 224 4750",
    "sg:postcode":"22443",
    "sg:province":"VA",
    "wof:name":"Wishes & Dreams",
    "wof:placetype":"venue"
},
  "geometry": {"coordinates":[-76.96830799999999,38.254543],"type":"Point"}
}