{
  "type": "Feature",
  "properties": {
    "iso:country":"US",
    "sg:address":"1660 Duke St",
    "sg:city":"Alexandria",
    "sg:classifiers":[
        {
            "category":"Real Estate",
            "subcategory":"Developer",
            "type":"Services"
        }
    ],
    "sg:phone":"+1 703 341 5017",
    "sg:postcode":"22314",
    "sg:province":"VA",
    "sg:tags":[
        "development",
        "housing",
        "low",
        "elderly",
        "income"
    ],
    "wof:name":"Fort Collins Voa Elderly",
    "wof:placetype":"venue"
},
  "geometry": {"coordinates":[-77.058836,38.804132],"type":"Point"}
}