{
  "type": "Feature",
  "properties": {
    "iso:country":"US",
    "sg:address":"6269 Franconia Rd",
    "sg:city":"Alexandria",
    "sg:classifiers":[
        {
            "category":"Professional",
            "subcategory":"Lawyer & Legal Services",
            "type":"Services"
        }
    ],
    "sg:phone":"+1 703 924 0223",
    "sg:postcode":"22310",
    "sg:province":"VA",
    "sg:tags":[
        "practice",
        "law"
    ],
    "sg:website":"www.bbblaw.net",
    "wof:name":"Brown Brown & Brown PC",
    "wof:placetype":"venue"
},
  "geometry": {"coordinates":[-77.153629,38.780452],"type":"Point"}
}