{
  "type": "Feature",
  "properties": {
    "addr:full":"1001 Landfill Ln Scottsburg VA 24589",
    "addr:housenumber":"1001",
    "addr:postcode":"24589",
    "addr:street":"Landfill Ln",
    "iso:country":"US",
    "sg:address":"1001 Landfill Ln",
    "sg:city":"Scottsburg",
    "sg:classifiers":[
        {
            "category":"Banks & Credit Unions",
            "subcategory":"Investment Brokerage",
            "type":"Services"
        }
    ],
    "sg:phone":"+1 434 476 3066",
    "sg:postcode":"24589",
    "sg:province":"VA",
    "sg:tags":[
        "commodity"
    ],
    "wof:name":"Halifax Co Ag Marketing Ctr",
    "wof:placetype":"venue"
},
  "geometry": {"coordinates":[-78.856217,36.789041],"type":"Point"}
}