{
  "type": "Feature",
  "properties": {
    "iso:country":"US",
    "sg:address":"2931 Eskridge Rd",
    "sg:city":"Fairfax",
    "sg:classifiers":[
        {
            "category":"Professional",
            "subcategory":"Engineering",
            "type":"Services"
        }
    ],
    "sg:phone":"+1 703 573 3700",
    "sg:postcode":"22031",
    "sg:province":"VA",
    "sg:tags":[
        "engineer"
    ],
    "wof:name":"Ellis Engineering",
    "wof:placetype":"venue"
},
  "geometry": {"coordinates":[-77.231983,38.872012],"type":"Point"}
}