{
  "type": "Feature",
  "properties": {
    "iso:country":"US",
    "sg:address":"1400 Cavalier Blvd",
    "sg:city":"Chesapeake",
    "sg:classifiers":[
        {
            "category":"Freight",
            "type":"Transportation"
        }
    ],
    "sg:phone":"+1 757 485 1755",
    "sg:postcode":"23323",
    "sg:province":"VA",
    "sg:tags":[
        "trucking"
    ],
    "wof:name":"TNT Logistic North America",
    "wof:placetype":"venue"
},
  "geometry": {"coordinates":[-76.364023,36.786024],"type":"Point"}
}