{
  "type": "Feature",
  "properties": {
    "iso:country":"US",
    "sg:address":"101 Maplewood Ln",
    "sg:city":"Tazewell",
    "sg:classifiers":[
        {
            "category":"Government",
            "subcategory":"Office",
            "type":"Public Place"
        }
    ],
    "sg:phone":"+1 276 988 6515",
    "sg:postcode":"24651",
    "sg:province":"VA",
    "sg:tags":[
        "transportation"
    ],
    "wof:name":"AV Department",
    "wof:placetype":"venue"
},
  "geometry": {"coordinates":[-81.50711699999999,37.124524],"type":"Point"}
}