{
  "type": "Feature",
  "properties": {
    "addr:full":"539 E Duncan Ave Alexandria VA 22301",
    "addr:housenumber":"539",
    "addr:postcode":"22301",
    "addr:street":"E Duncan Ave",
    "iso:country":"US",
    "sg:address":"539 E Duncan Ave",
    "sg:city":"Alexandria",
    "sg:classifiers":[
        {
            "category":"Arts & Performance",
            "subcategory":"Art Gallery",
            "type":"Entertainment"
        },
        {
            "category":"Museum",
            "type":"Entertainment"
        }
    ],
    "sg:phone":"+1 703 655 4327",
    "sg:postcode":"22301",
    "sg:province":"VA",
    "sg:tags":[
        "consultant",
        "galleries"
    ],
    "wof:name":"Jessica Van Opstal",
    "wof:placetype":"venue"
},
  "geometry": {"coordinates":[-77.051579,38.82312],"type":"Point"}
}