{
  "type": "Feature",
  "properties": {
    "iso:country":"US",
    "sg:address":"526 W Main St",
    "sg:city":"Tazewell",
    "sg:classifiers":[
        {
            "category":"Health Services",
            "subcategory":"Hospital",
            "type":"Services"
        }
    ],
    "sg:phone":"+1 276 988 7961",
    "sg:postcode":"24651",
    "sg:province":"VA",
    "sg:tags":[
        "mental"
    ],
    "sg:website":"www.cmcsb.com",
    "wof:name":"Cumberland Mountain Cmmnty Svc",
    "wof:placetype":"venue"
},
  "geometry": {"coordinates":[-81.523939,37.115133],"type":"Point"}
}