{
  "type": "Feature",
  "properties": {
    "addr:full":"22273 Timberlake Rd Lynchburg VA 24502",
    "addr:housenumber":"22273",
    "addr:postcode":"24502",
    "addr:street":"Timberlake Rd",
    "iso:country":"US",
    "sg:address":"22273 Timberlake Rd",
    "sg:city":"Lynchburg",
    "sg:classifiers":[
        {
            "category":"Shopping",
            "subcategory":"Bicycles & Sporting Goods",
            "type":"Retail Goods"
        }
    ],
    "sg:phone":"+1 434 239 3474",
    "sg:postcode":"24502",
    "sg:province":"VA",
    "wof:name":"Timberlake Sporting Goods",
    "wof:placetype":"venue"
},
  "geometry": {"coordinates":[-79.257434,37.321184],"type":"Point"}
}