{
  "type": "Feature",
  "properties": {
    "iso:country":"US",
    "sg:address":"3324 Shore Dr",
    "sg:city":"Virginia Beach",
    "sg:classifiers":[
        {
            "category":"Restaurant",
            "type":"Food & Drink"
        }
    ],
    "sg:phone":"+1 757 481 0201",
    "sg:postcode":"23451",
    "sg:province":"VA",
    "sg:website":"www.duck-in.com",
    "wof:name":"Duck-In & Gazebo",
    "wof:placetype":"venue"
},
  "geometry": {"coordinates":[-76.088323,36.90745],"type":"Point"}
}