{
  "type": "Feature",
  "properties": {
    "iso:country":"US",
    "sg:address":"301 Halifax St",
    "sg:city":"Petersburg",
    "sg:classifiers":[
        {
            "category":"Health Services",
            "subcategory":"Doctor",
            "type":"Services"
        }
    ],
    "sg:phone":"+1 804 863 1652",
    "sg:postcode":"23803",
    "sg:province":"VA",
    "sg:tags":[
        "physician",
        "surgeon"
    ],
    "wof:name":"Va Health Dept-Crater Hlth Dst",
    "wof:placetype":"venue"
},
  "geometry": {"coordinates":[-77.40653399999999,37.221823],"type":"Point"}
}