{
  "type": "Feature",
  "properties": {
    "addr:full":"504 Bridge Wood Dr Yorktown VA 23693",
    "addr:housenumber":"504",
    "addr:postcode":"23693",
    "addr:street":"Bridge Wood Dr",
    "iso:country":"US",
    "sg:address":"504 Bridge Wood Dr",
    "sg:city":"Yorktown",
    "sg:classifiers":[
        {
            "category":"Building & Trades",
            "subcategory":"Construction",
            "type":"Services"
        }
    ],
    "sg:phone":"+1 757 595 6560",
    "sg:postcode":"23693",
    "sg:province":"VA",
    "sg:tags":[
        "contractor"
    ],
    "wof:name":"Lewis Tile",
    "wof:placetype":"venue"
},
  "geometry": {"coordinates":[-76.45377499999999,37.105418],"type":"Point"}
}