{
  "type": "Feature",
  "properties": {
    "addr:full":"7503 Forrester Ln Manassas VA 20109",
    "addr:housenumber":"7503",
    "addr:postcode":"20109",
    "addr:street":"Forrester Ln",
    "iso:country":"US",
    "sg:address":"7503 Forrester Ln",
    "sg:city":"Manassas",
    "sg:classifiers":[
        {
            "category":"Manufacturing",
            "subcategory":"Retail Goods",
            "type":"Manufacturing & Wholesale Goods"
        }
    ],
    "sg:phone":"+1 703 330 5917",
    "sg:postcode":"20109",
    "sg:province":"VA",
    "sg:tags":[
        "lead",
        "mfg"
    ],
    "wof:name":"J Lewis Lettering & Design",
    "wof:placetype":"venue"
},
  "geometry": {"coordinates":[-77.495401,38.794494],"type":"Point"}
}