{
  "type": "Feature",
  "properties": {
    "addr:full":"1027 Huddleston Dr Huddleston VA 24104",
    "addr:housenumber":"1027",
    "addr:postcode":"24104",
    "addr:street":"Huddleston Dr",
    "iso:country":"US",
    "sg:address":"1027 Huddleston Dr",
    "sg:city":"Huddleston",
    "sg:classifiers":[
        {
            "category":"Education",
            "subcategory":"School",
            "type":"Public Place"
        }
    ],
    "sg:phone":"+1 540 297 5144",
    "sg:postcode":"24104",
    "sg:province":"VA",
    "sg:tags":[
        "elementary"
    ],
    "wof:name":"Huddleston Elementary",
    "wof:placetype":"venue"
},
  "geometry": {"coordinates":[-79.472917,37.162934],"type":"Point"}
}