{
  "type": "Feature",
  "properties": {
    "addr:full":"6139 George Washington Memorial Hwy Zanoni VA 23061",
    "addr:housenumber":"6139",
    "addr:postcode":"23061",
    "addr:street":"George Washington Memorial Hwy Zanoni",
    "iso:country":"US",
    "sg:address":"6139 George Washington Memorial Hwy",
    "sg:city":"Zanoni",
    "sg:classifiers":[
        {
            "category":"Recreation",
            "type":"Entertainment"
        }
    ],
    "sg:phone":"+1 804 694 1133",
    "sg:postcode":"23061",
    "sg:province":"VA",
    "sg:tags":[
        "pool",
        "swimming"
    ],
    "wof:name":"Courthouse Aquatics Club",
    "wof:placetype":"venue"
},
  "geometry": {"coordinates":[-76.53190499999999,37.370212],"type":"Point"}
}