{
  "type": "Feature",
  "properties": {
    "iso:country":"US",
    "sg:address":"8941 Miller Ln",
    "sg:city":"Vienna",
    "sg:classifiers":[
        {
            "category":"Recreation",
            "type":"Entertainment"
        }
    ],
    "sg:phone":"+1 703 255 6588",
    "sg:postcode":"22182",
    "sg:province":"VA",
    "wof:name":"Insight Sports Management",
    "wof:placetype":"venue"
},
  "geometry": {"coordinates":[-77.25559699999999,38.921633],"type":"Point"}
}