{
  "type": "Feature",
  "properties": {
    "addr:full":"4747 Valley St Alexandria VA 22312",
    "addr:housenumber":"4747",
    "addr:postcode":"22312",
    "addr:street":"Valley St",
    "iso:country":"US",
    "sg:address":"4747 Valley St",
    "sg:city":"Alexandria",
    "sg:classifiers":[
        {
            "category":"Building & Trades",
            "subcategory":"Plumbing",
            "type":"Services"
        }
    ],
    "sg:phone":"+1 703 354 0600",
    "sg:postcode":"22312",
    "sg:province":"VA",
    "sg:tags":[
        "contractor"
    ],
    "wof:name":"W W Plumbing Co",
    "wof:placetype":"venue"
},
  "geometry": {"coordinates":[-77.15775499999999,38.820337],"type":"Point"}
}