{
  "type": "Feature",
  "properties": {
    "iso:country":"US",
    "sg:address":"2036 Botetourt St",
    "sg:city":"Richmond",
    "sg:classifiers":[
        {
            "category":"Building & Trades",
            "subcategory":"Construction",
            "type":"Services"
        }
    ],
    "sg:phone":"+1 804 358 4238",
    "sg:postcode":"23220",
    "sg:province":"VA",
    "sg:tags":[
        "sewer",
        "contractor"
    ],
    "wof:name":"Mc Lane Construction Co",
    "wof:placetype":"venue"
},
  "geometry": {"coordinates":[-77.456709,37.562551],"type":"Point"}
}