{
  "type": "Feature",
  "properties": {
    "iso:country":"US",
    "sg:address":"124 S Lynnhaven Rd",
    "sg:city":"Virginia Beach",
    "sg:classifiers":[
        {
            "category":"Banks & Credit Unions",
            "subcategory":"Bank",
            "type":"Services"
        }
    ],
    "sg:phone":"+1 757 463 7173",
    "sg:postcode":"23452",
    "sg:province":"VA",
    "sg:tags":[
        "personal",
        "institution"
    ],
    "wof:name":"L M V LLC",
    "wof:placetype":"venue"
},
  "geometry": {"coordinates":[-76.066985,36.838047],"type":"Point"}
}