{
  "type": "Feature",
  "properties": {
    "addr:full":"1169 Devon Ln Harrisonburg VA 22801",
    "addr:housenumber":"1169",
    "addr:postcode":"22801",
    "addr:street":"Devon Ln",
    "iso:country":"US",
    "sg:address":"1169 Devon Ln",
    "sg:city":"Harrisonburg",
    "sg:classifiers":[
        {
            "category":"Building & Trades",
            "subcategory":"Construction",
            "type":"Services"
        }
    ],
    "sg:phone":"+1 540 438 0439",
    "sg:postcode":"22801",
    "sg:province":"VA",
    "sg:tags":[
        "painting"
    ],
    "wof:name":"Big Brush Painters LLC",
    "wof:placetype":"venue"
},
  "geometry": {"coordinates":[-78.868516,38.424677],"type":"Point"}
}