{
  "type": "Feature",
  "properties": {
    "iso:country":"US",
    "sg:address":"3985 Valley Pike",
    "sg:city":"Winchester",
    "sg:classifiers":[
        {
            "category":"Autos & Motor Vehicles",
            "subcategory":"Automobile Sales",
            "type":"Retail Goods"
        }
    ],
    "sg:phone":"+1 540 869 5000",
    "sg:postcode":"22602",
    "sg:province":"VA",
    "sg:tags":[
        "new",
        "used"
    ],
    "wof:name":"Miller Hnd-Vlkswgn-Suzu-suzuki",
    "wof:placetype":"venue"
},
  "geometry": {"coordinates":[-78.199127,39.116818],"type":"Point"}
}