{
  "type": "Feature",
  "properties": {
    "addr:full":"12401 Alder Woods Dr Fairfax VA 22033",
    "addr:housenumber":"12401",
    "addr:postcode":"22033",
    "addr:street":"Alder Woods Dr",
    "iso:country":"US",
    "sg:address":"12401 Alder Woods Dr",
    "sg:city":"Fairfax",
    "sg:classifiers":[
        {
            "category":"Social Services",
            "subcategory":"Child Care",
            "type":"Services"
        }
    ],
    "sg:phone":"+1 703 352 6204",
    "sg:postcode":"22033",
    "sg:province":"VA",
    "sg:tags":[
        "kindergarten",
        "academic",
        "school"
    ],
    "wof:name":"Pender Hill Pre-School & Mothr",
    "wof:placetype":"venue"
},
  "geometry": {"coordinates":[-77.377511,38.874421],"type":"Point"}
}