{
  "type": "Feature",
  "properties": {
    "iso:country":"US",
    "sg:address":"16619 Broad St",
    "sg:city":"St Paul",
    "sg:classifiers":[
        {
            "category":"Real Estate",
            "subcategory":"Real Estate Agent",
            "type":"Services"
        }
    ],
    "sg:phone":"+1 276 762 0125",
    "sg:postcode":"24283",
    "sg:province":"VA",
    "sg:tags":[
        "management"
    ],
    "wof:name":"Phillips & Vicars",
    "wof:placetype":"venue"
},
  "geometry": {"coordinates":[-82.310405,36.905206],"type":"Point"}
}