{
  "type": "Feature",
  "properties": {
    "iso:country":"US",
    "sg:address":"35059 Millville Rd",
    "sg:city":"Middleburg",
    "sg:classifiers":[
        {
            "category":"Building & Trades",
            "subcategory":"Landscaping Services",
            "type":"Services"
        }
    ],
    "sg:phone":"+1 540 687 3771",
    "sg:postcode":"20112",
    "sg:province":"VA",
    "sg:tags":[
        "lawn"
    ],
    "wof:name":"Leroy Leach",
    "wof:placetype":"venue"
},
  "geometry": {"coordinates":[-77.79178899999999,38.995858],"type":"Point"}
}