{
  "type": "Feature",
  "properties": {
    "iso:country":"US",
    "sg:address":"3706 Mount Vernon Ave",
    "sg:city":"Alexandria",
    "sg:classifiers":[
        {
            "category":"Taxi",
            "type":"Transportation"
        },
        {
            "category":"Airline",
            "type":"Transportation"
        }
    ],
    "sg:phone":"+1 703 683 4004",
    "sg:postcode":"22305",
    "sg:province":"VA",
    "sg:tags":[
        "shuttle",
        "airport"
    ],
    "wof:name":"Alexandria Airport Cab Co",
    "wof:placetype":"venue"
},
  "geometry": {"coordinates":[-77.062302,38.838699],"type":"Point"}
}