{
  "type": "Feature",
  "properties": {
    "addr:full":"9418 Victoria St Manassas VA 20110",
    "addr:housenumber":"9418",
    "addr:postcode":"20110",
    "addr:street":"Victoria St",
    "iso:country":"US",
    "sg:address":"9418 Victoria St",
    "sg:city":"Manassas",
    "sg:classifiers":[
        {
            "category":"Restaurant",
            "type":"Food & Drink"
        }
    ],
    "sg:phone":"+1 703 330 8390",
    "sg:postcode":"20110",
    "sg:province":"VA",
    "sg:tags":[
        "eating"
    ],
    "wof:name":"Njw Thai Cusine Corp",
    "wof:placetype":"venue"
},
  "geometry": {"coordinates":[-77.48321799999999,38.775452],"type":"Point"}
}