{
  "type": "Feature",
  "properties": {
    "addr:full":"27918 Carson Rd Carson VA 23830",
    "addr:housenumber":"27918",
    "addr:postcode":"23830",
    "addr:street":"Carson Rd",
    "iso:country":"US",
    "sg:address":"27918 Carson Rd",
    "sg:city":"Carson",
    "sg:classifiers":[
        {
            "category":"Building & Trades",
            "subcategory":"Construction",
            "type":"Services"
        }
    ],
    "sg:phone":"+1 804 732 5763",
    "sg:postcode":"23830",
    "sg:province":"VA",
    "sg:tags":[
        "excavating",
        "contractor"
    ],
    "wof:name":"Hare Excavating & Trucking Inc",
    "wof:placetype":"venue"
},
  "geometry": {"coordinates":[-77.42984,37.049963],"type":"Point"}
}