{
  "type": "Feature",
  "properties": {
    "addr:full":"11839 Fair Oaks Mall Fairfax VA 22033",
    "addr:housenumber":"11839",
    "addr:postcode":"22033",
    "addr:street":"Fair Oaks Mall",
    "iso:country":"US",
    "sg:address":"11839 Fair Oaks Mall",
    "sg:city":"Fairfax",
    "sg:classifiers":[
        {
            "category":"Personal",
            "type":"Services"
        }
    ],
    "sg:phone":"+1 703 352 5995",
    "sg:postcode":"22033",
    "sg:province":"VA",
    "sg:tags":[
        "wear",
        "formal"
    ],
    "wof:name":"After Hours Formalwear",
    "wof:placetype":"venue"
},
  "geometry": {"coordinates":[-77.357752,38.860856],"type":"Point"}
}