{
  "type": "Feature",
  "properties": {
    "iso:country":"US",
    "sg:address":"863 Gilmer Rd",
    "sg:city":"Norfolk",
    "sg:classifiers":[
        {
            "category":"Travel",
            "subcategory":"Travel Agent",
            "type":"Entertainment"
        }
    ],
    "sg:phone":"+1 757 461 3288",
    "sg:postcode":"23502",
    "sg:province":"VA",
    "sg:tags":[
        "agency",
        "services-commercial"
    ],
    "wof:name":"Brooks Travel X-Tras",
    "wof:placetype":"venue"
},
  "geometry": {"coordinates":[-76.233445,36.847667],"type":"Point"}
}