{
  "type": "Feature",
  "properties": {
    "addr:full":"8326 2nd Ave Vienna VA 22182",
    "addr:housenumber":"8326",
    "addr:postcode":"22182",
    "addr:street":"2Nd Ave",
    "iso:country":"US",
    "sg:address":"8326 2nd Ave",
    "sg:city":"Vienna",
    "sg:classifiers":[
        {
            "category":"Professional",
            "subcategory":"Computer Services",
            "type":"Services"
        }
    ],
    "sg:phone":"+1 703 207 7036",
    "sg:postcode":"22182",
    "sg:province":"VA",
    "sg:tags":[
        "related"
    ],
    "wof:name":"Jch Inc",
    "wof:placetype":"venue"
},
  "geometry": {"coordinates":[-77.23326400000001,38.899855],"type":"Point"}
}