{
  "type": "Feature",
  "properties": {
    "addr:full":"4230 Lankford Hwy New Church VA 23415",
    "addr:housenumber":"4230",
    "addr:postcode":"church;23415",
    "addr:street":"Lankford Hwy",
    "iso:country":"US",
    "sg:address":"4230 Lankford Hwy",
    "sg:city":"New Church",
    "sg:classifiers":[
        {
            "category":"Food & Beverages",
            "subcategory":"Groceries & Convenience Stores",
            "type":"Retail Goods"
        }
    ],
    "sg:phone":"+1 757 824 5002",
    "sg:postcode":"23415",
    "sg:province":"VA",
    "sg:tags":[
        "grocer"
    ],
    "wof:name":"Highway Market",
    "wof:placetype":"venue"
},
  "geometry": {"coordinates":[-75.530456,37.979168],"type":"Point"}
}