{
  "type": "Feature",
  "properties": {
    "iso:country":"US",
    "sg:address":"5572 Raby Rd",
    "sg:city":"Norfolk",
    "sg:classifiers":[
        {
            "category":"Retail",
            "subcategory":"Auto Repair",
            "type":"Services"
        }
    ],
    "sg:phone":"+1 757 461 3173",
    "sg:postcode":"23502",
    "sg:province":"VA",
    "sg:tags":[
        "recreational",
        "vehicle"
    ],
    "wof:name":"Johnson's Rv Svc Ctr",
    "wof:placetype":"venue"
},
  "geometry": {"coordinates":[-76.214946,36.859127],"type":"Point"}
}