{
  "type": "Feature",
  "properties": {
    "iso:country":"US",
    "sg:address":"5751 General Washington Dr",
    "sg:city":"Alexandria",
    "sg:classifiers":[
        {
            "category":"Professional",
            "subcategory":"Management & Consulting",
            "type":"Services"
        },
        {
            "category":"Wholesale",
            "subcategory":"Groceries",
            "type":"Manufacturing & Wholesale Goods"
        }
    ],
    "sg:phone":"+1 703 941 1522",
    "sg:postcode":"22312",
    "sg:province":"VA",
    "sg:tags":[
        "break",
        "coffee",
        "supply"
    ],
    "wof:name":"Regency Coffee & Supplies Inc",
    "wof:placetype":"venue"
},
  "geometry": {"coordinates":[-77.16777,38.795583],"type":"Point"}
}