{
  "type": "Feature",
  "properties": {
    "iso:country":"US",
    "sg:address":"20065 Silver Creek Ter # 107",
    "sg:city":"Ashburn",
    "sg:classifiers":[
        {
            "category":"Shopping",
            "type":"Retail Goods"
        }
    ],
    "sg:phone":"+1 703 728 2174",
    "sg:postcode":"20147",
    "sg:province":"VA",
    "sg:tags":[
        "merchandising"
    ],
    "wof:name":"Kdw",
    "wof:placetype":"venue"
},
  "geometry": {"coordinates":[-77.46678900000001,39.060089],"type":"Point"}
}