{
  "type": "Feature",
  "properties": {
    "addr:full":"6252 Banshire Dr Mechanicsville VA 23111",
    "addr:housenumber":"6252",
    "addr:postcode":"23111",
    "addr:street":"Banshire Dr",
    "iso:country":"US",
    "sg:address":"6252 Banshire Dr",
    "sg:city":"Mechanicsville",
    "sg:classifiers":[
        {
            "category":"Manufacturing",
            "subcategory":"Metals",
            "type":"Manufacturing & Wholesale Goods"
        }
    ],
    "sg:phone":"+1 804 559 2929",
    "sg:postcode":"23111",
    "sg:province":"VA",
    "sg:tags":[
        "plate",
        "work",
        "fabricated",
        "mfg"
    ],
    "wof:name":"Comfort Temp Inc",
    "wof:placetype":"venue"
},
  "geometry": {"coordinates":[-77.31913,37.63382],"type":"Point"}
}