{
  "type": "Feature",
  "properties": {
    "addr:full":"1005 N Glebe Rd Arlington VA 22201",
    "addr:housenumber":"1005",
    "addr:postcode":"22201",
    "addr:street":"N Glebe Rd",
    "iso:country":"US",
    "sg:address":"1005 N Glebe Rd",
    "sg:city":"Arlington",
    "sg:classifiers":[
        {
            "category":"Manufacturing",
            "subcategory":"Printing",
            "type":"Manufacturing & Wholesale Goods"
        }
    ],
    "sg:phone":"+1 703 527 5222",
    "sg:postcode":"22201",
    "sg:province":"VA",
    "sg:tags":[
        "commercial"
    ],
    "wof:name":"Infinite Photo & Imaging",
    "wof:placetype":"venue"
},
  "geometry": {"coordinates":[-77.115928,38.882514],"type":"Point"}
}