{
  "type": "Feature",
  "properties": {
    "addr:full":"43761 Parkhurst Plz Ashburn VA 20147",
    "addr:housenumber":"43761",
    "addr:postcode":"20147",
    "addr:street":"Parkhurst Plz",
    "iso:country":"US",
    "sg:address":"43761 Parkhurst Plz",
    "sg:city":"Ashburn",
    "sg:classifiers":[
        {
            "category":"Restaurant",
            "type":"Food & Drink"
        }
    ],
    "sg:phone":"+1 703 726 0972",
    "sg:postcode":"20147",
    "sg:province":"VA",
    "sg:tags":[
        "eating"
    ],
    "wof:name":"Toyama Sushi",
    "wof:placetype":"venue"
},
  "geometry": {"coordinates":[-77.487832,39.029176],"type":"Point"}
}