{
  "type": "Feature",
  "properties": {
    "addr:full":"6192 Old Franconia Rd Alexandria VA 22310",
    "addr:housenumber":"6192",
    "addr:postcode":"22310",
    "addr:street":"Old Franconia Rd",
    "iso:country":"US",
    "sg:address":"6192 Old Franconia Rd",
    "sg:city":"Alexandria",
    "sg:classifiers":[
        {
            "category":"Professional",
            "subcategory":"Management & Consulting",
            "type":"Services"
        }
    ],
    "sg:phone":"+1 703 921 0468",
    "sg:postcode":"22310",
    "sg:province":"VA",
    "sg:tags":[
        "consultant",
        "resource",
        "human"
    ],
    "wof:name":"Blackwell & Assoc LLC",
    "wof:placetype":"venue"
},
  "geometry": {"coordinates":[-77.152308,38.780577],"type":"Point"}
}