{
  "type": "Feature",
  "properties": {
    "addr:full":"4303 Commerce Rd Richmond VA 23234",
    "addr:housenumber":"4303",
    "addr:postcode":"23234",
    "addr:street":"Commerce Rd",
    "iso:country":"US",
    "sg:address":"4303 Commerce Rd",
    "sg:city":"Richmond",
    "sg:classifiers":[
        {
            "category":"Travel",
            "subcategory":"Hotels & Motels",
            "type":"Entertainment"
        },
        {
            "category":"Retail",
            "subcategory":"Event Space",
            "type":"Services"
        },
        {
            "category":"Travel",
            "subcategory":"Resort",
            "type":"Entertainment"
        }
    ],
    "sg:phone":"+1 800 345 8082",
    "sg:postcode":"23234",
    "sg:province":"VA",
    "sg:tags":[
        "hall",
        "lodging",
        "banquet",
        "reception",
        "facility"
    ],
    "sg:website":"http://ad.doubleclick.net/clk;223371278;47096201;d?http://www.holidayinn.com/redirect?path=hd&brandCode=hi&hotelCode=ricbr&_PMID=99601036&cm_mmc=mdpr-_-yellowpages-_-hi-_-ricbr",
    "wof:name":"Holiday Inn Richmond South-Bells Road",
    "wof:placetype":"venue"
},
  "geometry": {"coordinates":[-77.427693,37.462692],"type":"Point"}
}