{
  "type": "Feature",
  "properties": {
    "addr:full":"9110 Sterling Montague Dr Great Falls VA 22066",
    "addr:housenumber":"9110",
    "addr:postcode":"22066",
    "addr:street":"Sterling Montague Dr",
    "iso:country":"US",
    "sg:address":"9110 Sterling Montague Dr",
    "sg:city":"Great Falls",
    "sg:classifiers":[
        {
            "category":"Professional",
            "subcategory":"Management & Consulting",
            "type":"Services"
        }
    ],
    "sg:phone":"+1 703 759 0743",
    "sg:postcode":"22066",
    "sg:province":"VA",
    "sg:tags":[
        "business"
    ],
    "wof:name":"Fiheilbrunn Consulting",
    "wof:placetype":"venue"
},
  "geometry": {"coordinates":[-77.260175,39.010345],"type":"Point"}
}