{
  "type": "Feature",
  "properties": {
    "iso:country":"US",
    "sg:address":"3820 Virginia Beach Blvd",
    "sg:city":"Virginia Beach",
    "sg:classifiers":[
        {
            "category":"Social Services",
            "subcategory":"Child Care",
            "type":"Services"
        }
    ],
    "sg:phone":"+1 757 498 8900",
    "sg:postcode":"23452",
    "sg:province":"VA",
    "sg:tags":[
        "day"
    ],
    "wof:name":"Rainbow II",
    "wof:placetype":"venue"
},
  "geometry": {"coordinates":[-76.108537,36.840196],"type":"Point"}
}