{
  "type": "Feature",
  "properties": {
    "addr:full":"201 N Washington Hwy Ashland VA 23005",
    "addr:housenumber":"201",
    "addr:postcode":"23005",
    "addr:street":"N Washington Hwy",
    "iso:country":"US",
    "sg:address":"201 N Washington Hwy",
    "sg:city":"Ashland",
    "sg:classifiers":[
        {
            "category":"Banks & Credit Unions",
            "subcategory":"Investment Brokerage",
            "type":"Services"
        }
    ],
    "sg:phone":"+1 804 798 5695",
    "sg:postcode":"23005",
    "sg:province":"VA",
    "sg:tags":[
        "security"
    ],
    "wof:name":"Edward Jones Co",
    "wof:placetype":"venue"
},
  "geometry": {"coordinates":[-77.471542,37.760158],"type":"Point"}
}