{
  "type": "Feature",
  "properties": {
    "addr:full":"1801 Lancashire Dr Richmond VA 23235",
    "addr:housenumber":"1801",
    "addr:postcode":"23235",
    "addr:street":"Lancashire Dr",
    "iso:country":"US",
    "sg:address":"1801 Lancashire Dr",
    "sg:city":"Richmond",
    "sg:classifiers":[
        {
            "category":"Building & Trades",
            "subcategory":"Construction",
            "type":"Services"
        }
    ],
    "sg:phone":"+1 804 275 2824",
    "sg:postcode":"23235",
    "sg:province":"VA",
    "sg:tags":[
        "roofing",
        "contractor"
    ],
    "wof:name":"Dominion Roofing Co",
    "wof:placetype":"venue"
},
  "geometry": {"coordinates":[-77.53919999999999,37.476849],"type":"Point"}
}