{
  "type": "Feature",
  "properties": {
    "iso:country":"US",
    "sg:address":"1115 Rock Ridge Rd",
    "sg:city":"Callaway",
    "sg:classifiers":[
        {
            "category":"Professional",
            "subcategory":"Computer Services",
            "type":"Services"
        }
    ],
    "sg:phone":"+1 540 483 8749",
    "sg:postcode":"24067",
    "sg:province":"VA",
    "sg:tags":[
        "related"
    ],
    "wof:name":"Abacus",
    "wof:placetype":"venue"
},
  "geometry": {"coordinates":[-80.091094,36.968904],"type":"Point"}
}