{
  "type": "Feature",
  "properties": {
    "addr:full":"933 Reservoir St Harrisonburg VA 22801",
    "addr:housenumber":"933",
    "addr:postcode":"22801",
    "addr:street":"Reservoir St",
    "iso:country":"US",
    "sg:address":"933 Reservoir St",
    "sg:city":"Harrisonburg",
    "sg:classifiers":[
        {
            "category":"Education",
            "subcategory":"Vocational School",
            "type":"Public Place"
        }
    ],
    "sg:phone":"+1 540 433 6977",
    "sg:postcode":"22801",
    "sg:province":"VA",
    "wof:name":"Dominion Business School",
    "wof:placetype":"venue"
},
  "geometry": {"coordinates":[-78.85784,38.442135],"type":"Point"}
}