{
  "type": "Feature",
  "properties": {
    "iso:country":"US",
    "sg:address":"855 State St",
    "sg:city":"Bristol",
    "sg:classifiers":[
        {
            "category":"Food & Beverages",
            "subcategory":"Groceries & Convenience Stores",
            "type":"Retail Goods"
        }
    ],
    "sg:phone":"+1 276 466 0377",
    "sg:postcode":"24201",
    "sg:province":"VA",
    "wof:name":"Appco Convenience Ctr",
    "wof:placetype":"venue"
},
  "geometry": {"coordinates":[-82.188143,36.595199],"type":"Point"}
}