{
  "type": "Feature",
  "properties": {
    "addr:full":"22225 Campbell Hollow Rd Abingdon VA 24211",
    "addr:housenumber":"22225",
    "addr:postcode":"24211",
    "addr:street":"Campbell Hollow Rd",
    "iso:country":"US",
    "sg:address":"22225 Campbell Hollow Rd",
    "sg:city":"Abingdon",
    "sg:classifiers":[
        {
            "category":"Building & Trades",
            "subcategory":"Electrical",
            "type":"Services"
        }
    ],
    "sg:phone":"+1 276 475 3387",
    "sg:postcode":"24211",
    "sg:province":"VA",
    "sg:tags":[
        "electrical",
        "contractor"
    ],
    "wof:name":"Milhorn Electric",
    "wof:placetype":"venue"
},
  "geometry": {"coordinates":[-81.873231,36.636466],"type":"Point"}
}