{
  "type": "Feature",
  "properties": {
    "iso:country":"US",
    "sg:address":"4112 4th St N",
    "sg:city":"Arlington",
    "sg:classifiers":[
        {
            "category":"Wholesale",
            "subcategory":"Durable Goods & Equipment",
            "type":"Manufacturing & Wholesale Goods"
        }
    ],
    "sg:phone":"+1 703 276 0129",
    "sg:postcode":"22203",
    "sg:province":"VA",
    "sg:tags":[
        "importer"
    ],
    "wof:name":"I S Trading House",
    "wof:placetype":"venue"
},
  "geometry": {"coordinates":[-77.10841499999999,38.874008],"type":"Point"}
}