{
  "type": "Feature",
  "properties": {
    "iso:country":"US",
    "sg:address":"1205 Poindexter St",
    "sg:city":"Chesapeake",
    "sg:classifiers":[
        {
            "category":"Home & Garden",
            "subcategory":"Carpets & Floor Coverings",
            "type":"Retail Goods"
        }
    ],
    "sg:phone":"+1 757 494 7733",
    "sg:postcode":"23324",
    "sg:province":"VA",
    "wof:name":"Pauls Carpet",
    "wof:placetype":"venue"
},
  "geometry": {"coordinates":[-76.27422300000001,36.818136],"type":"Point"}
}