{
  "type": "Feature",
  "properties": {
    "iso:country":"US",
    "sg:address":"5517 Virginia Beach Blvd",
    "sg:city":"Virginia Beach",
    "sg:classifiers":[
        {
            "category":"Shopping",
            "subcategory":"Discount & Variety Stores",
            "type":"Retail Goods"
        }
    ],
    "sg:phone":"+1 757 473 1987",
    "sg:postcode":"23462",
    "sg:province":"VA",
    "sg:tags":[
        "merchandise",
        "general"
    ],
    "wof:name":"Tidewater Thrift Store",
    "wof:placetype":"venue"
},
  "geometry": {"coordinates":[-76.17271,36.85216],"type":"Point"}
}