{
  "type": "Feature",
  "properties": {
    "iso:country":"US",
    "sg:address":"3132 Carolina Rd",
    "sg:city":"Suffolk",
    "sg:classifiers":[
        {
            "category":"Retail",
            "subcategory":"Car Wash",
            "type":"Services"
        }
    ],
    "sg:phone":"+1 757 934 0908",
    "sg:postcode":"23434",
    "sg:province":"VA",
    "sg:tags":[
        "truck",
        "cleaning"
    ],
    "wof:name":"Power Clean",
    "wof:placetype":"venue"
},
  "geometry": {"coordinates":[-76.60812799999999,36.632904],"type":"Point"}
}