{
  "type": "Feature",
  "properties": {
    "addr:full":"10530 Warwick Ave Ste C2 Fairfax VA 22030",
    "addr:housenumber":"10530",
    "addr:postcode":"22030",
    "addr:street":"Warwick Ave Ste C2",
    "iso:country":"US",
    "sg:address":"10530 Warwick Ave Ste C2",
    "sg:city":"Fairfax",
    "sg:classifiers":[
        {
            "category":"Banks & Credit Unions",
            "subcategory":"Investment Brokerage",
            "type":"Services"
        },
        {
            "category":"Banks & Credit Unions",
            "subcategory":"Financial Services",
            "type":"Services"
        }
    ],
    "sg:phone":"+1 571 295 5713",
    "sg:postcode":"22030",
    "sg:province":"VA",
    "sg:tags":[
        "retirement",
        "planner",
        "profit",
        "sharing",
        "planning",
        "plan",
        "pension"
    ],
    "sg:website":"http://www.ameripriseadvisors.com/peter.b.suyama/profile/",
    "wof:name":"Ameriprise Financial - Peter Suyama, CRPC, CRPS, Senior Financial Advisor",
    "wof:placetype":"venue"
},
  "geometry": {"coordinates":[-77.308612,38.856603],"type":"Point"}
}