{
  "type": "Feature",
  "properties": {
    "iso:country":"US",
    "sg:address":"11584 Greenwich Point Rd",
    "sg:city":"Reston",
    "sg:classifiers":[
        {
            "category":"Professional",
            "subcategory":"Advertising",
            "type":"Services"
        }
    ],
    "sg:phone":"+1 703 481 6215",
    "sg:postcode":"20194",
    "sg:province":"VA",
    "sg:tags":[
        "multimedia"
    ],
    "wof:name":"Erickson-Barnett Inc",
    "wof:placetype":"venue"
},
  "geometry": {"coordinates":[-77.344132,38.976701],"type":"Point"}
}