{
  "type": "Feature",
  "properties": {
    "addr:full":"2424 Ocean Shore Cres Virginia Beach VA 23451",
    "addr:housenumber":"2424",
    "addr:postcode":"23451",
    "addr:street":"Ocean Shore Cres",
    "iso:country":"US",
    "sg:address":"2424 Ocean Shore Cres",
    "sg:city":"Virginia Beach",
    "sg:classifiers":[
        {
            "category":"Professional",
            "type":"Services"
        }
    ],
    "sg:phone":"+1 757 481 7986",
    "sg:postcode":"23451",
    "sg:province":"VA",
    "wof:name":"Binford L Snead",
    "wof:placetype":"venue"
},
  "geometry": {"coordinates":[-76.07652899999999,36.912712],"type":"Point"}
}