{
  "type": "Feature",
  "properties": {
    "addr:full":"114 E Midland Trl Lexington VA 24450",
    "addr:housenumber":"114",
    "addr:postcode":"24450",
    "addr:street":"E Midland Trl",
    "iso:country":"US",
    "sg:address":"114 E Midland Trl",
    "sg:city":"Lexington",
    "sg:classifiers":[
        {
            "category":"Restaurant",
            "type":"Food & Drink"
        }
    ],
    "sg:menulink":"http://www.allmenus.com/va/buffalo/262668-papa-johns-pizza/menu/",
    "sg:phone":"+1 540 463 7777",
    "sg:postcode":"24450",
    "sg:province":"VA",
    "sg:tags":[
        "american",
        "pizza"
    ],
    "wof:name":"Papa John's Pizza",
    "wof:placetype":"venue"
},
  "geometry": {"coordinates":[-79.432017,37.773898],"type":"Point"}
}