{
  "type": "Feature",
  "properties": {
    "addr:full":"9803 Nina Ln Midland VA 22728",
    "addr:housenumber":"9803",
    "addr:postcode":"22728",
    "addr:street":"Nina Ln",
    "iso:country":"US",
    "sg:address":"9803 Nina Ln",
    "sg:city":"Midland",
    "sg:classifiers":[
        {
            "category":"Building & Trades",
            "subcategory":"Landscaping Services",
            "type":"Services"
        }
    ],
    "sg:phone":"+1 540 439 9038",
    "sg:postcode":"22728",
    "sg:province":"VA",
    "wof:name":"Four Seasons Landscape & Tree",
    "wof:placetype":"venue"
},
  "geometry": {"coordinates":[-77.741077,38.62322],"type":"Point"}
}