{
  "type": "Feature",
  "properties": {
    "addr:full":"1215 N Fort Myer Dr Arlington VA 22209",
    "addr:housenumber":"1215",
    "addr:postcode":"22209",
    "addr:street":"N Fort Myer Dr",
    "iso:country":"US",
    "sg:address":"1215 N Fort Myer Dr",
    "sg:city":"Arlington",
    "sg:classifiers":[
        {
            "category":"Health Services",
            "subcategory":"Hospital",
            "type":"Services"
        }
    ],
    "sg:phone":"+1 703 696 3706",
    "sg:postcode":"22209",
    "sg:province":"VA",
    "sg:tags":[
        "clinic"
    ],
    "wof:name":"Andrew Rader Health Clinic",
    "wof:placetype":"venue"
},
  "geometry": {"coordinates":[-77.074681,38.890478],"type":"Point"}
}