{
  "type": "Feature",
  "properties": {
    "iso:country":"US",
    "sg:address":"4965 Cleveland St",
    "sg:city":"Virginia Beach",
    "sg:classifiers":[
        {
            "category":"Building & Trades",
            "subcategory":"Construction",
            "type":"Services"
        }
    ],
    "sg:phone":"+1 757 962 1151",
    "sg:postcode":"23462",
    "sg:province":"VA",
    "sg:tags":[
        "utility",
        "contractor"
    ],
    "wof:name":"T T & T",
    "wof:placetype":"venue"
},
  "geometry": {"coordinates":[-76.14976299999999,36.84192],"type":"Point"}
}