{
  "type": "Feature",
  "properties": {
    "addr:full":"106 W Spring St Woodstock VA 22664",
    "addr:housenumber":"106",
    "addr:postcode":"22664",
    "addr:street":"W Spring St",
    "iso:country":"US",
    "sg:address":"106 W Spring St",
    "sg:city":"Woodstock",
    "sg:classifiers":[
        {
            "category":"Real Estate",
            "subcategory":"Real Estate Agent",
            "type":"Services"
        }
    ],
    "sg:phone":"+1 540 459 2937",
    "sg:postcode":"22664",
    "sg:province":"VA",
    "wof:name":"Massanutten Board Of Realtors",
    "wof:placetype":"venue"
},
  "geometry": {"coordinates":[-78.50866499999999,38.880031],"type":"Point"}
}