{
  "type": "Feature",
  "properties": {
    "iso:country":"US",
    "sg:address":"5901 Airport Rd",
    "sg:city":"Wise",
    "sg:classifiers":[
        {
            "category":"Home & Garden",
            "subcategory":"Building Materials",
            "type":"Retail Goods"
        }
    ],
    "sg:phone":"+1 276 328 2224",
    "sg:postcode":"24293",
    "sg:province":"VA",
    "wof:name":"Culby Supply",
    "wof:placetype":"venue"
},
  "geometry": {"coordinates":[-82.52879299999999,36.977152],"type":"Point"}
}