{
  "type": "Feature",
  "properties": {
    "iso:country":"US",
    "sg:address":"55 Executive Cir",
    "sg:city":"Roanoke",
    "sg:classifiers":[
        {
            "category":"Building & Trades",
            "subcategory":"Electrical",
            "type":"Services"
        }
    ],
    "sg:phone":"+1 540 977 4299",
    "sg:postcode":"24012",
    "sg:province":"VA",
    "sg:tags":[
        "electrical",
        "electric",
        "contractor"
    ],
    "wof:name":"Kegley Electric Co Llc",
    "wof:placetype":"venue"
},
  "geometry": {"coordinates":[-79.866202,37.330921],"type":"Point"}
}