{
  "type": "Feature",
  "properties": {
    "addr:full":"1642 Crystal Square Arcade Arlington VA 22209",
    "addr:housenumber":"1642",
    "addr:postcode":"22209",
    "addr:street":"Crystal Square",
    "iso:country":"US",
    "sg:address":"1642 Crystal Square Arcade",
    "sg:city":"Arlington",
    "sg:classifiers":[
        {
            "category":"Deli",
            "type":"Food & Drink"
        }
    ],
    "sg:phone":"+1 703 415 0061",
    "sg:postcode":"22209",
    "sg:province":"VA",
    "wof:name":"Cafe Jenna",
    "wof:placetype":"venue"
},
  "geometry": {"coordinates":[-77.075031,38.890963],"type":"Point"}
}