{
  "type": "Feature",
  "properties": {
    "iso:country":"US",
    "sg:address":"8000 Towers Crescent Dr",
    "sg:city":"Vienna",
    "sg:classifiers":[
        {
            "category":"Wholesale",
            "subcategory":"Photographic Equipment",
            "type":"Manufacturing & Wholesale Goods"
        },
        {
            "category":"Manufacturing",
            "subcategory":"Tools & Machinery",
            "type":"Manufacturing & Wholesale Goods"
        }
    ],
    "sg:phone":"+1 703 821 0007",
    "sg:postcode":"22182",
    "sg:province":"VA",
    "sg:tags":[
        "photo"
    ],
    "wof:name":"Noritsu America Corporation",
    "wof:placetype":"venue"
},
  "geometry": {"coordinates":[-77.21982199999999,38.913664],"type":"Point"}
}