{
  "type": "Feature",
  "properties": {
    "addr:full":"633 Maury St Fredericksburg VA 22401",
    "addr:housenumber":"633",
    "addr:postcode":"22401",
    "addr:street":"Maury St",
    "iso:country":"US",
    "sg:address":"633 Maury St",
    "sg:city":"Fredericksburg",
    "sg:classifiers":[
        {
            "category":"Building & Trades",
            "subcategory":"Electrical",
            "type":"Services"
        }
    ],
    "sg:phone":"+1 540 373 4188",
    "sg:postcode":"22401",
    "sg:province":"VA",
    "sg:tags":[
        "electrical",
        "contractor"
    ],
    "wof:name":"Crowley Electric",
    "wof:placetype":"venue"
},
  "geometry": {"coordinates":[-77.469048,38.308168],"type":"Point"}
}