{
  "type": "Feature",
  "properties": {
    "addr:full":"100 Douglas Ln Pearisburg VA 24134",
    "addr:housenumber":"100",
    "addr:postcode":"24134",
    "addr:street":"Douglas Ln",
    "iso:country":"US",
    "sg:address":"100 Douglas Ln",
    "sg:city":"Pearisburg",
    "sg:classifiers":[
        {
            "category":"Local Transit",
            "type":"Transportation"
        }
    ],
    "sg:phone":"+1 540 626 5050",
    "sg:postcode":"24134",
    "sg:province":"VA",
    "wof:name":"Virginia Dept-Transportation",
    "wof:placetype":"venue"
},
  "geometry": {"coordinates":[-80.734972,37.331071],"type":"Point"}
}