{
  "type": "Feature",
  "properties": {
    "addr:full":"1707 Princess Anne Rd Virginia Beach VA 23456",
    "addr:housenumber":"1707",
    "addr:postcode":"23456",
    "addr:street":"Princess Anne Rd",
    "iso:country":"US",
    "sg:address":"1707 Princess Anne Rd",
    "sg:city":"Virginia Beach",
    "sg:phone":"+1 757 426 7322",
    "sg:postcode":"23456",
    "sg:province":"VA",
    "sg:tags":[
        "wheat",
        "farm",
        "corn",
        "crop",
        "field",
        "soybean"
    ],
    "wof:name":"Flanagan Farms",
    "wof:placetype":"venue"
},
  "geometry": {"coordinates":[-76.02087299999999,36.715917],"type":"Point"}
}