{
  "type": "Feature",
  "properties": {
    "iso:country":"US",
    "sg:address":"115 Seaside Ln",
    "sg:city":"Virginia Beach",
    "sg:classifiers":[
        {
            "category":"Building & Trades",
            "subcategory":"Construction",
            "type":"Services"
        }
    ],
    "sg:phone":"+1 757 235 3850",
    "sg:postcode":"23462",
    "sg:province":"VA",
    "sg:tags":[
        "hanging",
        "contractor"
    ],
    "wof:name":"Kanakaris Painting",
    "wof:placetype":"venue"
},
  "geometry": {"coordinates":[-76.128451,36.838831],"type":"Point"}
}