{
  "type": "Feature",
  "properties": {
    "iso:country":"US",
    "sg:address":"209 Hummel Ross Rd",
    "sg:city":"Hopewell",
    "sg:classifiers":[
        {
            "category":"Building & Trades",
            "subcategory":"Construction",
            "type":"Services"
        }
    ],
    "sg:phone":"+1 804 458 6753",
    "sg:postcode":"23860",
    "sg:province":"VA",
    "sg:tags":[
        "excavating",
        "contractor"
    ],
    "wof:name":"J D Langley Excavating",
    "wof:placetype":"venue"
},
  "geometry": {"coordinates":[-77.26164199999999,37.29457],"type":"Point"}
}