{
  "type": "Feature",
  "properties": {
    "addr:full":"701 N Broad St Suffolk VA 23434",
    "addr:housenumber":"701",
    "addr:postcode":"23434",
    "addr:street":"N Broad St",
    "iso:country":"US",
    "sg:address":"701 N Broad St",
    "sg:city":"Suffolk",
    "sg:classifiers":[
        {
            "category":"Manufacturing",
            "subcategory":"Retail Goods",
            "type":"Manufacturing & Wholesale Goods"
        }
    ],
    "sg:phone":"+1 757 925 1954",
    "sg:postcode":"23434",
    "sg:province":"VA",
    "sg:tags":[
        "product",
        "mfg"
    ],
    "wof:name":"Nancy Dempsey",
    "wof:placetype":"venue"
},
  "geometry": {"coordinates":[-76.590987,36.74212],"type":"Point"}
}