{
  "type": "Feature",
  "properties": {
    "iso:country":"US",
    "sg:address":"540 John Carlyle St",
    "sg:city":"Alexandria",
    "sg:classifiers":[
        {
            "category":"Restaurant",
            "type":"Food & Drink"
        }
    ],
    "sg:menulink":"http://www.allmenus.com/va/alexandria/270136-zikrayet/menu/",
    "sg:phone":"+1 703 838 2008",
    "sg:postcode":"22314",
    "sg:province":"VA",
    "sg:tags":[
        "middle",
        "eastern"
    ],
    "wof:name":"Zikrayet",
    "wof:placetype":"venue"
},
  "geometry": {"coordinates":[-77.061919,38.801712],"type":"Point"}
}