{
  "type": "Feature",
  "properties": {
    "addr:full":"303 Ashcake Rd Ashland VA 23005",
    "addr:housenumber":"303",
    "addr:postcode":"23005",
    "addr:street":"Ashcake Rd",
    "iso:country":"US",
    "sg:address":"303 Ashcake Rd",
    "sg:city":"Ashland",
    "sg:classifiers":[
        {
            "category":"Professional",
            "subcategory":"Accounting & Tax Preparation",
            "type":"Services"
        }
    ],
    "sg:phone":"+1 804 798 3216",
    "sg:postcode":"23005",
    "sg:province":"VA",
    "sg:tags":[
        "accountant"
    ],
    "wof:name":"Bryant & Pleasants CPA",
    "wof:placetype":"venue"
},
  "geometry": {"coordinates":[-77.46999099999999,37.745525],"type":"Point"}
}