{
  "type": "Feature",
  "properties": {
    "addr:full":"501 Courthouse Rd Richmond VA 23236",
    "addr:housenumber":"501",
    "addr:postcode":"23236",
    "addr:street":"Courthouse Rd",
    "iso:country":"US",
    "sg:address":"501 Courthouse Rd",
    "sg:city":"Richmond",
    "sg:classifiers":[
        {
            "category":"Shopping",
            "subcategory":"Florist",
            "type":"Retail Goods"
        }
    ],
    "sg:phone":"+1 804 378 0700",
    "sg:postcode":"23236",
    "sg:province":"VA",
    "wof:name":"Tropical Treehouse Inc",
    "wof:placetype":"venue"
},
  "geometry": {"coordinates":[-77.597737,37.48166],"type":"Point"}
}