{
  "type": "Feature",
  "properties": {
    "iso:country":"US",
    "sg:address":"2634 Martin Luther King Hwy",
    "sg:city":"Waverly",
    "sg:phone":"+1 804 834 3739",
    "sg:postcode":"23890",
    "sg:province":"VA",
    "sg:tags":[
        "farm",
        "corn"
    ],
    "wof:name":"Barry Collier",
    "wof:placetype":"venue"
},
  "geometry": {"coordinates":[-77.039743,37.094817],"type":"Point"}
}