{
  "type": "Feature",
  "properties": {
    "addr:full":"2106 Gallows Rd Vienna VA 22182",
    "addr:housenumber":"2106",
    "addr:postcode":"22182",
    "addr:street":"Gallows Rd",
    "iso:country":"US",
    "sg:address":"2106 Gallows Rd",
    "sg:city":"Vienna",
    "sg:classifiers":[
        {
            "category":"Building & Trades",
            "subcategory":"Construction",
            "type":"Services"
        }
    ],
    "sg:phone":"+1 703 356 3616",
    "sg:postcode":"22182",
    "sg:province":"VA",
    "sg:tags":[
        "general",
        "contractor"
    ],
    "wof:name":"M A Mortenson Co",
    "wof:placetype":"venue"
},
  "geometry": {"coordinates":[-77.222663,38.905108],"type":"Point"}
}