{
  "type": "Feature",
  "properties": {
    "iso:country":"US",
    "sg:address":"518 W Locust St",
    "sg:city":"Covington",
    "sg:classifiers":[
        {
            "category":"Organizations",
            "subcategory":"Religious Organization",
            "type":"Services"
        }
    ],
    "sg:phone":"+1 540 962 0644",
    "sg:postcode":"24426",
    "sg:province":"VA",
    "sg:tags":[
        "church"
    ],
    "wof:name":"Callaghan Church Of God Of",
    "wof:placetype":"venue"
},
  "geometry": {"coordinates":[-79.99810600000001,37.789333],"type":"Point"}
}