{
  "type": "Feature",
  "properties": {
    "addr:full":"106 Sandy Ct Danville VA 24541",
    "addr:housenumber":"106",
    "addr:postcode":"24541",
    "addr:street":"Sandy Ct",
    "iso:country":"US",
    "sg:address":"106 Sandy Ct",
    "sg:city":"Danville",
    "sg:classifiers":[
        {
            "category":"Restaurant",
            "type":"Food & Drink"
        }
    ],
    "sg:menulink":"http://www.allmenus.com/va/danville/153133-bojangles/menu/",
    "sg:phone":"+1 804 797 4071",
    "sg:postcode":"24541",
    "sg:province":"VA",
    "sg:tags":[
        "chicken",
        "sandwich",
        "american"
    ],
    "wof:name":"Bojangle's",
    "wof:placetype":"venue"
},
  "geometry": {"coordinates":[-79.426157,36.589896],"type":"Point"}
}