{
  "type": "Feature",
  "properties": {
    "iso:country":"US",
    "sg:address":"2829 Guardian Ln",
    "sg:city":"Virginia Beach",
    "sg:classifiers":[
        {
            "category":"Professional",
            "subcategory":"Computer Services",
            "type":"Services"
        }
    ],
    "sg:phone":"+1 757 498 7841",
    "sg:postcode":"23452",
    "sg:province":"VA",
    "sg:tags":[
        "other",
        "programming",
        "provides",
        "software"
    ],
    "wof:name":"PCI",
    "wof:placetype":"venue"
},
  "geometry": {"coordinates":[-76.068472,36.825766],"type":"Point"}
}