{
  "type": "Feature",
  "properties": {
    "iso:country":"US",
    "sg:address":"4985 Colony Rd",
    "sg:city":"Fairfax",
    "sg:classifiers":[
        {
            "category":"Building & Trades",
            "subcategory":"Construction",
            "type":"Services"
        }
    ],
    "sg:phone":"+1 703 266 8890",
    "sg:postcode":"22030",
    "sg:province":"VA",
    "sg:tags":[
        "house"
    ],
    "wof:name":"Pulte Homes Heatherbrook",
    "wof:placetype":"venue"
},
  "geometry": {"coordinates":[-77.291809,38.852602],"type":"Point"}
}