{
  "type": "Feature",
  "properties": {
    "addr:full":"8846 Ashgrove House Ln Vienna VA 22182",
    "addr:housenumber":"8846",
    "addr:postcode":"22182",
    "addr:street":"Ashgrove House Ln",
    "iso:country":"US",
    "sg:address":"8846 Ashgrove House Ln",
    "sg:city":"Vienna",
    "sg:classifiers":[
        {
            "category":"Communications",
            "type":"Services"
        }
    ],
    "sg:phone":"+1 703 760 0009",
    "sg:postcode":"22182",
    "sg:province":"VA",
    "sg:tags":[
        "web",
        "design"
    ],
    "wof:name":"Edge Media Inc",
    "wof:placetype":"venue"
},
  "geometry": {"coordinates":[-77.24865,38.931257],"type":"Point"}
}