{
  "type": "Feature",
  "properties": {
    "addr:full":"5113 Leesburg Ct Woodbridge VA 22193",
    "addr:housenumber":"5113",
    "addr:postcode":"22193",
    "addr:street":"Leesburg Ct",
    "iso:country":"US",
    "sg:address":"5113 Leesburg Ct",
    "sg:city":"Woodbridge",
    "sg:classifiers":[
        {
            "category":"Education",
            "subcategory":"Special Training",
            "type":"Public Place"
        }
    ],
    "sg:phone":"+1 703 670 3659",
    "sg:postcode":"22193",
    "sg:province":"VA",
    "wof:name":"SMD Music Inc",
    "wof:placetype":"venue"
},
  "geometry": {"coordinates":[-77.36175900000001,38.653824],"type":"Point"}
}