{
  "type": "Feature",
  "properties": {
    "addr:full":"11813 Judiths Grove Ct Manassas VA 20112",
    "addr:housenumber":"11813",
    "addr:postcode":"20112",
    "addr:street":"Judiths Grove Ct",
    "iso:country":"US",
    "sg:address":"11813 Judiths Grove Ct",
    "sg:city":"Manassas",
    "sg:classifiers":[
        {
            "category":"Social Services",
            "type":"Services"
        },
        {
            "category":"Professional",
            "subcategory":"Employment Agencies",
            "type":"Services"
        }
    ],
    "sg:phone":"+1 703 794 0602",
    "sg:postcode":"20112",
    "sg:province":"VA",
    "sg:tags":[
        "workers'",
        "placement",
        "volunteer"
    ],
    "wof:name":"Iris Memorial Foundation",
    "wof:placetype":"venue"
},
  "geometry": {"coordinates":[-77.41798900000001,38.699191],"type":"Point"}
}