{
  "type": "Feature",
  "properties": {
    "iso:country":"US",
    "sg:address":"3542 Three Notch Rd",
    "sg:city":"Louisa",
    "sg:classifiers":[
        {
            "category":"Food & Beverages",
            "subcategory":"Groceries & Convenience Stores",
            "type":"Retail Goods"
        }
    ],
    "sg:phone":"+1 434 589 3568",
    "sg:postcode":"23093",
    "sg:province":"VA",
    "sg:tags":[
        "grocer"
    ],
    "wof:name":"Ferncliff Market",
    "wof:placetype":"venue"
},
  "geometry": {"coordinates":[-78.10356899999999,37.929498],"type":"Point"}
}