{
  "type": "Feature",
  "properties": {
    "iso:country":"US",
    "sg:address":"38 Rouss Ave",
    "sg:city":"Winchester",
    "sg:classifiers":[
        {
            "category":"Banks & Credit Unions",
            "subcategory":"Financial Services",
            "type":"Services"
        }
    ],
    "sg:phone":"+1 540 665 4204",
    "sg:postcode":"22601",
    "sg:province":"VA",
    "sg:tags":[
        "trust"
    ],
    "wof:name":"B B & T Trust Div",
    "wof:placetype":"venue"
},
  "geometry": {"coordinates":[-78.16496100000001,39.184592],"type":"Point"}
}