{
  "type": "Feature",
  "properties": {
    "addr:full":"2306 Atherholt Rd Lynchburg VA 24501",
    "addr:housenumber":"2306",
    "addr:postcode":"24501",
    "addr:street":"Atherholt Rd",
    "iso:country":"US",
    "sg:address":"2306 Atherholt Rd",
    "sg:city":"Lynchburg",
    "sg:classifiers":[
        {
            "category":"Professional",
            "subcategory":"Lawyer & Legal Services",
            "type":"Services"
        }
    ],
    "sg:phone":"+1 434 846 2731",
    "sg:postcode":"24501",
    "sg:province":"VA",
    "sg:tags":[
        "attorney"
    ],
    "wof:name":"Caskie & Frost",
    "wof:placetype":"venue"
},
  "geometry": {"coordinates":[-79.17300400000001,37.410057],"type":"Point"}
}