{
  "type": "Feature",
  "properties": {
    "iso:country":"US",
    "sg:address":"1561 Alder St",
    "sg:city":"Norfolk",
    "sg:classifiers":[
        {
            "category":"Organizations",
            "subcategory":"Religious Organization",
            "type":"Services"
        }
    ],
    "sg:phone":"+1 757 853 7200",
    "sg:postcode":"23502",
    "sg:province":"VA",
    "wof:name":"Dominion International Church",
    "wof:placetype":"venue"
},
  "geometry": {"coordinates":[-76.23419,36.868052],"type":"Point"}
}