{
  "type": "Feature",
  "properties": {
    "addr:full":"1920 Youngblood St Mc Lean VA 22101",
    "addr:housenumber":"1920",
    "addr:postcode":"22101",
    "addr:street":"Youngblood St Mc Lean",
    "iso:country":"US",
    "sg:address":"1920 Youngblood St",
    "sg:city":"Mc Lean",
    "sg:classifiers":[
        {
            "category":"Wholesale",
            "subcategory":"Durable Goods & Equipment",
            "type":"Manufacturing & Wholesale Goods"
        },
        {
            "category":"Manufacturing",
            "subcategory":"Lumber",
            "type":"Manufacturing & Wholesale Goods"
        }
    ],
    "sg:phone":"+1 703 827 7814",
    "sg:postcode":"22101",
    "sg:province":"VA",
    "sg:tags":[
        "mill",
        "exporter"
    ],
    "wof:name":"Samuels Marketing Company",
    "wof:placetype":"venue"
},
  "geometry": {"coordinates":[-77.17379699999999,38.912697],"type":"Point"}
}