{
  "type": "Feature",
  "properties": {
    "iso:country":"US",
    "sg:address":"1454 Harvest Crossing Dr",
    "sg:city":"Mc Lean",
    "sg:classifiers":[
        {
            "category":"Health Services",
            "subcategory":"Doctor",
            "type":"Services"
        }
    ],
    "sg:phone":"+1 703 848 0075",
    "sg:postcode":"22101",
    "sg:province":"VA",
    "wof:name":"Besner Edward Dr",
    "wof:placetype":"venue"
},
  "geometry": {"coordinates":[-77.191902,38.931801],"type":"Point"}
}