{
  "type": "Feature",
  "properties": {
    "addr:full":"4447 Holly Ave Fairfax VA 22030",
    "addr:housenumber":"4447",
    "addr:postcode":"22030",
    "addr:street":"Holly Ave",
    "iso:country":"US",
    "sg:address":"4447 Holly Ave",
    "sg:city":"Fairfax",
    "sg:classifiers":[
        {
            "category":"Travel",
            "subcategory":"Campground",
            "type":"Entertainment"
        }
    ],
    "sg:phone":"+1 703 222 0072",
    "sg:postcode":"22030",
    "sg:province":"VA",
    "sg:tags":[
        "camp"
    ],
    "wof:name":"Saint Peter Summer Home",
    "wof:placetype":"venue"
},
  "geometry": {"coordinates":[-77.359157,38.850678],"type":"Point"}
}