{
  "type": "Feature",
  "properties": {
    "iso:country":"US",
    "sg:address":"1401 E Broad St",
    "sg:city":"Richmond",
    "sg:classifiers":[
        {
            "category":"Building & Trades",
            "subcategory":"Construction",
            "type":"Services"
        }
    ],
    "sg:phone":"+1 804 786 2700",
    "sg:postcode":"23219",
    "sg:province":"VA",
    "sg:tags":[
        "road",
        "contractor"
    ],
    "sg:website":"www.virginia.dot.org",
    "wof:name":"Tranportation Department",
    "wof:placetype":"venue"
},
  "geometry": {"coordinates":[-77.429547,37.538065],"type":"Point"}
}