{
  "type": "Feature",
  "properties": {
    "addr:full":"14145 Burruss Ln Ruther Glen VA 22546",
    "addr:postcode":"14145;22546",
    "addr:street":"Burruss Ln",
    "iso:country":"US",
    "sg:address":"14145 Burruss Ln",
    "sg:city":"Ruther Glen",
    "sg:classifiers":[
        {
            "category":"Home & Garden",
            "subcategory":"Garden Supply",
            "type":"Retail Goods"
        }
    ],
    "sg:phone":"+1 804 994 2418",
    "sg:postcode":"22546",
    "sg:province":"VA",
    "wof:name":"Perennial Pickle",
    "wof:placetype":"venue"
},
  "geometry": {"coordinates":[-77.404089,37.891569],"type":"Point"}
}