{
  "type": "Feature",
  "properties": {
    "iso:country":"US",
    "sg:address":"4200 Mount Vernon Memorial Hwy",
    "sg:city":"Alexandria",
    "sg:classifiers":[
        {
            "category":"Professional",
            "subcategory":"Management & Consulting",
            "type":"Services"
        }
    ],
    "sg:phone":"+1 703 765 0985",
    "sg:postcode":"22309",
    "sg:province":"VA",
    "sg:tags":[
        "consultant",
        "business"
    ],
    "wof:name":"Karen Hicks Management & Nurse",
    "wof:placetype":"venue"
},
  "geometry": {"coordinates":[-77.10081099999999,38.714089],"type":"Point"}
}