{
  "type": "Feature",
  "properties": {
    "addr:full":"5309 Sylvan Rd Richmond VA 23225",
    "addr:housenumber":"5309",
    "addr:postcode":"23225",
    "addr:street":"Sylvan Rd",
    "iso:country":"US",
    "sg:address":"5309 Sylvan Rd",
    "sg:city":"Richmond",
    "sg:classifiers":[
        {
            "category":"Professional",
            "type":"Services"
        }
    ],
    "sg:phone":"+1 804 225 7828",
    "sg:postcode":"23225",
    "sg:province":"VA",
    "wof:name":"Statproductionscom",
    "wof:placetype":"venue"
},
  "geometry": {"coordinates":[-77.49659,37.528532],"type":"Point"}
}