{
  "type": "Feature",
  "properties": {
    "addr:full":"1008 S Main St Danville VA 24541",
    "addr:housenumber":"1008",
    "addr:postcode":"24541",
    "addr:street":"S Main St",
    "iso:country":"US",
    "sg:address":"1008 S Main St",
    "sg:city":"Danville",
    "sg:classifiers":[
        {
            "category":"Education",
            "subcategory":"College",
            "type":"Public Place"
        }
    ],
    "sg:phone":"+1 434 791 5334",
    "sg:postcode":"24541",
    "sg:province":"VA",
    "sg:tags":[
        "academic",
        "school"
    ],
    "wof:name":"Old Dominion University",
    "wof:placetype":"venue"
},
  "geometry": {"coordinates":[-79.40518299999999,36.566063],"type":"Point"}
}