{
  "type": "Feature",
  "properties": {
    "iso:country":"US",
    "sg:address":"5 Runswick Dr",
    "sg:city":"Richmond",
    "sg:classifiers":[
        {
            "category":"Professional",
            "subcategory":"Detective & Security Services",
            "type":"Services"
        }
    ],
    "sg:phone":"+1 804 740 2278",
    "sg:postcode":"23238",
    "sg:province":"VA",
    "sg:tags":[
        "investigator"
    ],
    "wof:name":"Thomas F Drumm",
    "wof:placetype":"venue"
},
  "geometry": {"coordinates":[-77.611486,37.592734],"type":"Point"}
}