{
  "type": "Feature",
  "properties": {
    "iso:country":"US",
    "sg:address":"701 E Franklin St Ste 110",
    "sg:city":"Richmond",
    "sg:classifiers":[
        {
            "category":"Coffee & Tea",
            "type":"Food & Drink"
        },
        {
            "category":"Restaurant",
            "type":"Food & Drink"
        }
    ],
    "sg:phone":"+1 804 643 6592",
    "sg:postcode":"23219",
    "sg:province":"VA",
    "sg:tags":[
        "cafeteria",
        "espresso"
    ],
    "wof:name":"D J's Fresh Garden Cafe Inc",
    "wof:placetype":"venue"
},
  "geometry": {"coordinates":[-77.437347,37.540138],"type":"Point"}
}