{
  "type": "Feature",
  "properties": {
    "iso:country":"US",
    "sg:address":"2924 Heron Ridge Dr",
    "sg:city":"Virginia Beach",
    "sg:classifiers":[
        {
            "category":"Building & Trades",
            "subcategory":"Plumbing",
            "type":"Services"
        }
    ],
    "sg:phone":"+1 757 422 3123",
    "sg:postcode":"23456",
    "sg:province":"VA",
    "sg:tags":[
        "conditioning",
        "air",
        "system",
        "contractor"
    ],
    "wof:name":"Mechanical Technology Inc",
    "wof:placetype":"venue"
},
  "geometry": {"coordinates":[-76.03397099999999,36.736509],"type":"Point"}
}