{
  "type": "Feature",
  "properties": {
    "iso:country":"US",
    "sg:address":"3620 Mayland Ct",
    "sg:city":"Richmond",
    "sg:classifiers":[
        {
            "category":"Bars & Pubs",
            "type":"Food & Drink"
        }
    ],
    "sg:menulink":"http://www.allmenus.com/va/three-chopt/222980-cracker-barrel-old-country-store/menu/",
    "sg:phone":"+1 804 290 0713",
    "sg:postcode":"23233",
    "sg:province":"VA",
    "sg:tags":[
        "american",
        "southern"
    ],
    "wof:name":"Cracker Barrel Old Country Store",
    "wof:placetype":"venue"
},
  "geometry": {"coordinates":[-77.569402,37.63959],"type":"Point"}
}