{
  "type": "Feature",
  "properties": {
    "addr:full":"3 E 5th St N Big Stone Gap VA 24219",
    "addr:housenumber":"3",
    "addr:postcode":"24219",
    "addr:street":"E 5Th St N",
    "iso:country":"US",
    "sg:address":"3 E 5th St N",
    "sg:city":"Big Stone Gap",
    "sg:classifiers":[
        {
            "category":"Organizations",
            "subcategory":"Professional Association",
            "type":"Services"
        }
    ],
    "sg:phone":"+1 276 523 1932",
    "sg:postcode":"24219",
    "sg:province":"VA",
    "wof:name":"Girl Scouts",
    "wof:placetype":"venue"
},
  "geometry": {"coordinates":[-82.774473,36.867988],"type":"Point"}
}