{
  "type": "Feature",
  "properties": {
    "addr:full":"408 Goodwin Ave Salem VA 24153",
    "addr:housenumber":"408",
    "addr:postcode":"24153",
    "addr:street":"Goodwin Ave",
    "iso:country":"US",
    "sg:address":"408 Goodwin Ave",
    "sg:city":"Salem",
    "sg:classifiers":[
        {
            "category":"Wholesale",
            "subcategory":"Sporting Goods",
            "type":"Manufacturing & Wholesale Goods"
        }
    ],
    "sg:phone":"+1 540 387 1598",
    "sg:postcode":"24153",
    "sg:province":"VA",
    "sg:tags":[
        "equipment",
        "billiard",
        "supply"
    ],
    "wof:name":"Pool Table Svc",
    "wof:placetype":"venue"
},
  "geometry": {"coordinates":[-80.07681100000001,37.295377],"type":"Point"}
}