{
  "type": "Feature",
  "properties": {
    "addr:full":"4324 John Silver Rd Virginia Beach VA 23455",
    "addr:housenumber":"4324",
    "addr:postcode":"23455",
    "addr:street":"John Silver Rd",
    "iso:country":"US",
    "sg:address":"4324 John Silver Rd",
    "sg:city":"Virginia Beach",
    "sg:classifiers":[
        {
            "category":"Autos & Motor Vehicles",
            "subcategory":"Fuel & Gas Station",
            "type":"Retail Goods"
        }
    ],
    "sg:phone":"+1 757 627 9422",
    "sg:postcode":"23455",
    "sg:province":"VA",
    "sg:tags":[
        "station",
        "gasoline"
    ],
    "wof:name":"Davenports Texaco",
    "wof:placetype":"venue"
},
  "geometry": {"coordinates":[-76.122618,36.909819],"type":"Point"}
}