{
  "type": "Feature",
  "properties": {
    "addr:full":"4201 Marble Ln Fairfax VA 22033",
    "addr:housenumber":"4201",
    "addr:postcode":"22033",
    "addr:street":"Marble Ln",
    "iso:country":"US",
    "sg:address":"4201 Marble Ln",
    "sg:city":"Fairfax",
    "sg:classifiers":[
        {
            "category":"Building & Trades",
            "subcategory":"Plumbing",
            "type":"Services"
        }
    ],
    "sg:phone":"+1 703 378 0791",
    "sg:postcode":"22033",
    "sg:province":"VA",
    "sg:tags":[
        "refrigeration",
        "conditioning",
        "air"
    ],
    "wof:name":"Koster & Son Inc David W",
    "wof:placetype":"venue"
},
  "geometry": {"coordinates":[-77.393332,38.87315],"type":"Point"}
}