{
  "type": "Feature",
  "properties": {
    "addr:full":"8103 Tillers Ridge Ct Richmond VA 23235",
    "addr:housenumber":"8103",
    "addr:postcode":"23235",
    "addr:street":"Tillers Ridge Ct",
    "iso:country":"US",
    "sg:address":"8103 Tillers Ridge Ct",
    "sg:city":"Richmond",
    "sg:classifiers":[
        {
            "category":"Building & Trades",
            "subcategory":"Landscaping Services",
            "type":"Services"
        }
    ],
    "sg:phone":"+1 804 745 3956",
    "sg:postcode":"23235",
    "sg:province":"VA",
    "wof:name":"Lawn Care Inc",
    "wof:placetype":"venue"
},
  "geometry": {"coordinates":[-77.545108,37.48423],"type":"Point"}
}