{
  "type": "Feature",
  "properties": {
    "addr:full":"1148 Jensen Dr Virginia Beach VA 23451",
    "addr:housenumber":"1148",
    "addr:postcode":"23451",
    "addr:street":"Jensen Dr",
    "iso:country":"US",
    "sg:address":"1148 Jensen Dr",
    "sg:city":"Virginia Beach",
    "sg:classifiers":[
        {
            "category":"Building & Trades",
            "subcategory":"Construction",
            "type":"Services"
        }
    ],
    "sg:phone":"+1 757 417 0025",
    "sg:postcode":"23451",
    "sg:province":"VA",
    "sg:tags":[
        "specializing",
        "plastering",
        "drywall",
        "contractor"
    ],
    "wof:name":"Tidewater Plst & Drywall Co",
    "wof:placetype":"venue"
},
  "geometry": {"coordinates":[-76.00078000000001,36.835248],"type":"Point"}
}