{
  "type": "Feature",
  "properties": {
    "iso:country":"US",
    "sg:address":"2849 Princess Anne Rd",
    "sg:city":"Virginia Beach",
    "sg:classifiers":[
        {
            "category":"Organizations",
            "subcategory":"Membership Organization",
            "type":"Services"
        }
    ],
    "sg:phone":"+1 757 427 2025",
    "sg:postcode":"23456",
    "sg:province":"VA",
    "wof:name":"Princess Anne Masonic",
    "wof:placetype":"venue"
},
  "geometry": {"coordinates":[-76.074162,36.764584],"type":"Point"}
}