{
  "type": "Feature",
  "properties": {
    "addr:full":"5706 27th St N Arlington VA 22207",
    "addr:housenumber":"5706",
    "addr:postcode":"22207",
    "addr:street":"27Th St N",
    "iso:country":"US",
    "sg:address":"5706 27th St N",
    "sg:city":"Arlington",
    "sg:classifiers":[
        {
            "category":"Professional",
            "type":"Services"
        }
    ],
    "sg:phone":"+1 703 241 2678",
    "sg:postcode":"22207",
    "sg:province":"VA",
    "wof:name":"Lockner Inc",
    "wof:placetype":"venue"
},
  "geometry": {"coordinates":[-77.14479900000001,38.898119],"type":"Point"}
}