{
  "type": "Feature",
  "properties": {
    "addr:full":"208 Stonewall Dr Waynesboro VA 22980",
    "addr:housenumber":"208",
    "addr:postcode":"22980",
    "addr:street":"Stonewall Dr",
    "iso:country":"US",
    "sg:address":"208 Stonewall Dr",
    "sg:city":"Waynesboro",
    "sg:classifiers":[
        {
            "category":"Building & Trades",
            "subcategory":"Construction",
            "type":"Services"
        }
    ],
    "sg:phone":"+1 540 949 8954",
    "sg:postcode":"22980",
    "sg:province":"VA",
    "sg:tags":[
        "painter"
    ],
    "wof:name":"Raymond V Hite & Sons Painting",
    "wof:placetype":"venue"
},
  "geometry": {"coordinates":[-78.92360100000001,38.081899],"type":"Point"}
}