{
  "type": "Feature",
  "properties": {
    "addr:full":"12385 Copenhagen Ct Reston VA 20191",
    "addr:housenumber":"12385",
    "addr:postcode":"20191",
    "addr:street":"Copenhagen Ct",
    "iso:country":"US",
    "sg:address":"12385 Copenhagen Ct",
    "sg:city":"Reston",
    "sg:classifiers":[
        {
            "category":"Personal",
            "type":"Services"
        }
    ],
    "sg:phone":"+1 703 716 7387",
    "sg:postcode":"20191",
    "sg:province":"VA",
    "sg:tags":[
        "pet",
        "sitting"
    ],
    "wof:name":"All Friends Pet Care Corp",
    "wof:placetype":"venue"
},
  "geometry": {"coordinates":[-77.373116,38.930315],"type":"Point"}
}