{
  "type": "Feature",
  "properties": {
    "addr:full":"5638 Bengal Pl Haymarket VA 20169",
    "addr:housenumber":"5638",
    "addr:postcode":"20169",
    "addr:street":"Bengal Pl",
    "iso:country":"US",
    "sg:address":"5638 Bengal Pl",
    "sg:city":"Haymarket",
    "sg:classifiers":[
        {
            "category":"Professional",
            "subcategory":"Business Services",
            "type":"Services"
        }
    ],
    "sg:phone":"+1 703 360 4279",
    "sg:postcode":"20169",
    "sg:province":"VA",
    "wof:name":"Ultimate Solutions LLC",
    "wof:placetype":"venue"
},
  "geometry": {"coordinates":[-77.63081200000001,38.832935],"type":"Point"}
}