{
  "type": "Feature",
  "properties": {
    "addr:full":"455 N Main St Woodstock VA 22664",
    "addr:housenumber":"455",
    "addr:postcode":"22664",
    "addr:street":"N Main St",
    "iso:country":"US",
    "sg:address":"455 N Main St",
    "sg:city":"Woodstock",
    "sg:classifiers":[
        {
            "category":"Professional",
            "type":"Services"
        }
    ],
    "sg:phone":"+1 540 459 2212",
    "sg:postcode":"22664",
    "sg:province":"VA",
    "sg:tags":[
        "establishment"
    ],
    "wof:name":"Walter Enterprises",
    "wof:placetype":"venue"
},
  "geometry": {"coordinates":[-78.500732,38.887555],"type":"Point"}
}