{
  "type": "Feature",
  "properties": {
    "addr:full":"9603 Todds Tavern Dr Spotsylvania VA 22551",
    "addr:housenumber":"9603",
    "addr:postcode":"22551",
    "addr:street":"Todds Tavern Dr",
    "iso:country":"US",
    "sg:address":"9603 Todds Tavern Dr",
    "sg:city":"Spotsylvania",
    "sg:classifiers":[
        {
            "category":"Professional",
            "subcategory":"Computer Services",
            "type":"Services"
        }
    ],
    "sg:phone":"+1 540 972 0804",
    "sg:postcode":"22551",
    "sg:province":"VA",
    "sg:tags":[
        "design",
        "system"
    ],
    "wof:name":"All Lucent Fellows Inc",
    "wof:placetype":"venue"
},
  "geometry": {"coordinates":[-77.664626,38.239017],"type":"Point"}
}