{
  "type": "Feature",
  "properties": {
    "addr:full":"816 Golden Arrow St Great Falls VA 22066",
    "addr:housenumber":"816",
    "addr:postcode":"22066",
    "addr:street":"Golden Arrow St",
    "iso:country":"US",
    "sg:address":"816 Golden Arrow St",
    "sg:city":"Great Falls",
    "sg:classifiers":[
        {
            "category":"Organizations",
            "subcategory":"Membership Organization",
            "type":"Services"
        }
    ],
    "sg:phone":"+1 703 759 3625",
    "sg:postcode":"22066",
    "sg:province":"VA",
    "wof:name":"Tamaroaorg",
    "wof:placetype":"venue"
},
  "geometry": {"coordinates":[-77.29132199999999,38.993802],"type":"Point"}
}