{
  "type": "Feature",
  "properties": {
    "addr:full":"15545 Lee Hwy Bristol VA 24202",
    "addr:housenumber":"15545",
    "addr:postcode":"24202",
    "addr:street":"Lee Hwy",
    "iso:country":"US",
    "sg:address":"15545 Lee Hwy",
    "sg:city":"Bristol",
    "sg:classifiers":[
        {
            "category":"Travel",
            "subcategory":"Hotels & Motels",
            "type":"Entertainment"
        }
    ],
    "sg:phone":"+1 276 669 0166",
    "sg:postcode":"24202",
    "sg:province":"VA",
    "wof:name":"Skyland Inn",
    "wof:placetype":"venue"
},
  "geometry": {"coordinates":[-82.08069500000001,36.655796],"type":"Point"}
}