{
  "type": "Feature",
  "properties": {
    "addr:full":"1401 N Rhodes St Arlington VA 22209",
    "addr:housenumber":"1401",
    "addr:postcode":"22209",
    "addr:street":"N Rhodes St",
    "iso:country":"US",
    "sg:address":"1401 N Rhodes St",
    "sg:city":"Arlington",
    "sg:classifiers":[
        {
            "category":"Professional",
            "subcategory":"Business Services",
            "type":"Services"
        }
    ],
    "sg:phone":"+1 703 294 4015",
    "sg:postcode":"22209",
    "sg:province":"VA",
    "wof:name":"Sandra C Coronado",
    "wof:placetype":"venue"
},
  "geometry": {"coordinates":[-77.079261,38.89186],"type":"Point"}
}