{
  "type": "Feature",
  "properties": {
    "iso:country":"US",
    "sg:address":"9621 Chesapeake Blvd",
    "sg:city":"Norfolk",
    "sg:classifiers":[
        {
            "category":"Building & Trades",
            "subcategory":"Cleaning & Sanitation",
            "type":"Services"
        }
    ],
    "sg:phone":"+1 757 531 8822",
    "sg:postcode":"23503",
    "sg:province":"VA",
    "sg:tags":[
        "janitor"
    ],
    "wof:name":"CID Janitorial Svc",
    "wof:placetype":"venue"
},
  "geometry": {"coordinates":[-76.243476,36.948361],"type":"Point"}
}