{
  "type": "Feature",
  "properties": {
    "addr:full":"975 Hilton Heights Rd Charlottesville VA 22901",
    "addr:housenumber":"975",
    "addr:postcode":"22901",
    "addr:street":"Hilton Heights Rd",
    "iso:country":"US",
    "sg:address":"975 Hilton Heights Rd",
    "sg:city":"Charlottesville",
    "sg:classifiers":[
        {
            "category":"Health Services",
            "subcategory":"Optometrist",
            "type":"Services"
        }
    ],
    "sg:phone":"+1 434 978 3773",
    "sg:postcode":"22901",
    "sg:province":"VA",
    "wof:name":"Wal-Mart Vision Center",
    "wof:placetype":"venue"
},
  "geometry": {"coordinates":[-78.46669799999999,38.0984],"type":"Point"}
}