{
  "type": "Feature",
  "properties": {
    "addr:full":"1505 Roanoke St Christiansburg VA 24073",
    "addr:housenumber":"1505",
    "addr:postcode":"24073",
    "addr:street":"Roanoke St",
    "iso:country":"US",
    "sg:address":"1505 Roanoke St",
    "sg:city":"Christiansburg",
    "sg:classifiers":[
        {
            "category":"Fast Food",
            "type":"Food & Drink"
        },
        {
            "category":"Restaurant",
            "type":"Food & Drink"
        }
    ],
    "sg:phone":"+1 540 382 7901",
    "sg:postcode":"24073",
    "sg:province":"VA",
    "sg:tags":[
        "take"
    ],
    "wof:name":"Dude's Drive Inn",
    "wof:placetype":"venue"
},
  "geometry": {"coordinates":[-80.37979900000001,37.132469],"type":"Point"}
}