{
  "type": "Feature",
  "properties": {
    "addr:full":"107 Tazewell Ave Cape Charles VA 23310",
    "addr:housenumber":"107",
    "addr:postcode":"charles;23310",
    "addr:street":"Tazewell Ave",
    "iso:country":"US",
    "sg:address":"107 Tazewell Ave",
    "sg:city":"Cape Charles",
    "sg:classifiers":[
        {
            "category":"Restaurant",
            "type":"Food & Drink"
        }
    ],
    "sg:phone":"+1 757 640 8000",
    "sg:postcode":"23310",
    "sg:province":"VA",
    "sg:tags":[
        "eating"
    ],
    "wof:name":"Santa Fe Margarita Grill",
    "wof:placetype":"venue"
},
  "geometry": {"coordinates":[-76.019901,37.269074],"type":"Point"}
}