{
  "type": "Feature",
  "properties": {
    "addr:full":"14753 Ealing Ct Centreville VA 20120",
    "addr:postcode":"14753;20120",
    "addr:street":"Ealing Ct",
    "iso:country":"US",
    "sg:address":"14753 Ealing Ct",
    "sg:city":"Centreville",
    "sg:classifiers":[
        {
            "category":"Professional",
            "subcategory":"Advertising",
            "type":"Services"
        }
    ],
    "sg:phone":"+1 703 818 0993",
    "sg:postcode":"20120",
    "sg:province":"VA",
    "sg:tags":[
        "exhibit",
        "display"
    ],
    "wof:name":"Exhibit Express Too",
    "wof:placetype":"venue"
},
  "geometry": {"coordinates":[-77.45784,38.84118],"type":"Point"}
}