{
  "type": "Feature",
  "properties": {
    "iso:country":"US",
    "sg:address":"2516 Volunteer Pkwy",
    "sg:city":"Bristol",
    "sg:classifiers":[
        {
            "category":"Shopping",
            "subcategory":"Hobbies, Toys, & Games",
            "type":"Retail Goods"
        }
    ],
    "sg:phone":"+1 423 764 1720",
    "sg:postcode":"37620",
    "sg:province":"VA",
    "sg:tags":[
        "equipment",
        "video",
        "rental"
    ],
    "wof:name":"Mr Wayne's",
    "wof:placetype":"venue"
},
  "geometry": {"coordinates":[-82.24824099999999,36.530501],"type":"Point"}
}