{
  "type": "Feature",
  "properties": {
    "addr:full":"4166 Longhill Rd Williamsburg VA 23188",
    "addr:housenumber":"4166",
    "addr:postcode":"23188",
    "addr:street":"Longhill Rd",
    "iso:country":"US",
    "sg:address":"4166 Longhill Rd",
    "sg:city":"Williamsburg",
    "sg:classifiers":[
        {
            "category":"Retail",
            "subcategory":"Auto Repair",
            "type":"Services"
        }
    ],
    "sg:phone":"+1 757 253 9433",
    "sg:postcode":"23188",
    "sg:province":"VA",
    "sg:tags":[
        "repairing",
        "automobile"
    ],
    "wof:name":"Auto Clinic Of Long Hill",
    "wof:placetype":"venue"
},
  "geometry": {"coordinates":[-76.774562,37.313033],"type":"Point"}
}