{
  "type": "Feature",
  "properties": {
    "addr:full":"30 S Quaker Ln Alexandria VA 22314",
    "addr:housenumber":"30",
    "addr:postcode":"22314",
    "addr:street":"S Quaker Ln",
    "iso:country":"US",
    "sg:address":"30 S Quaker Ln",
    "sg:city":"Alexandria",
    "sg:classifiers":[
        {
            "category":"Professional",
            "subcategory":"Management & Consulting",
            "type":"Services"
        }
    ],
    "sg:phone":"+1 703 212 8520",
    "sg:postcode":"22314",
    "sg:province":"VA",
    "sg:tags":[
        "consultant",
        "publishing"
    ],
    "sg:website":"www.alexanderstreet.com",
    "wof:name":"Alexander Street Press",
    "wof:placetype":"venue"
},
  "geometry": {"coordinates":[-77.08734200000001,38.807446],"type":"Point"}
}