{
  "type": "Feature",
  "properties": {
    "iso:country":"US",
    "sg:address":"800 Moorefield Park Dr",
    "sg:city":"Richmond",
    "sg:classifiers":[
        {
            "category":"Education",
            "subcategory":"Library",
            "type":"Public Place"
        }
    ],
    "sg:phone":"+1 804 359 3535",
    "sg:postcode":"23236",
    "sg:province":"VA",
    "sg:tags":[
        "special",
        "interest"
    ],
    "wof:name":"Richmond Campus Library",
    "wof:placetype":"venue"
},
  "geometry": {"coordinates":[-77.58020399999999,37.499317],"type":"Point"}
}