{
  "type": "Feature",
  "properties": {
    "iso:country":"US",
    "sg:address":"114 Powhatan Dr",
    "sg:city":"Williamsburg",
    "sg:classifiers":[
        {
            "category":"Retail",
            "subcategory":"Repair Shop",
            "type":"Services"
        }
    ],
    "sg:phone":"+1 757 564 9721",
    "sg:postcode":"23188",
    "sg:province":"VA",
    "wof:name":"R & J Housecleaning Services",
    "wof:placetype":"venue"
},
  "geometry": {"coordinates":[-76.771091,37.366967],"type":"Point"}
}