{
  "type": "Feature",
  "properties": {
    "iso:country":"US",
    "sg:address":"4400 Victoria Blvd",
    "sg:city":"Hampton",
    "sg:classifiers":[
        {
            "category":"Travel",
            "subcategory":"Hotels & Motels",
            "type":"Entertainment"
        }
    ],
    "sg:phone":"+1 757 722 0985",
    "sg:postcode":"23669",
    "sg:province":"VA",
    "sg:tags":[
        "breakfast",
        "accommodation",
        "bed"
    ],
    "wof:name":"Little England Inn",
    "wof:placetype":"venue"
},
  "geometry": {"coordinates":[-76.34820999999999,37.01994],"type":"Point"}
}