{
  "type": "Feature",
  "properties": {
    "addr:full":"4001 9th St N Arlington VA 22203",
    "addr:housenumber":"4001",
    "addr:postcode":"22203",
    "addr:street":"9Th St N",
    "iso:country":"US",
    "sg:address":"4001 9th St N",
    "sg:city":"Arlington",
    "sg:classifiers":[
        {
            "category":"Professional",
            "subcategory":"Computer Services",
            "type":"Services"
        }
    ],
    "sg:phone":"+1 703 528 4544",
    "sg:postcode":"22203",
    "sg:province":"VA",
    "sg:tags":[
        "consulting",
        "tech"
    ],
    "wof:name":"Forrester Tech Consulting Inc",
    "wof:placetype":"venue"
},
  "geometry": {"coordinates":[-77.10921399999999,38.881025],"type":"Point"}
}