{
  "type": "Feature",
  "properties": {
    "addr:full":"8033 Tyson Oaks Cir Vienna VA 22182",
    "addr:housenumber":"8033",
    "addr:postcode":"22182",
    "addr:street":"Tyson Oaks Cir",
    "iso:country":"US",
    "sg:address":"8033 Tyson Oaks Cir",
    "sg:city":"Vienna",
    "sg:classifiers":[
        {
            "category":"Professional",
            "subcategory":"Computer Services",
            "type":"Services"
        }
    ],
    "sg:phone":"+1 703 919 8284",
    "sg:postcode":"22182",
    "sg:province":"VA",
    "sg:tags":[
        "related"
    ],
    "wof:name":"Anet Commerce Consulting Inc",
    "wof:placetype":"venue"
},
  "geometry": {"coordinates":[-77.22214200000001,38.905484],"type":"Point"}
}