{
  "type": "Feature",
  "properties": {
    "addr:full":"906 Hampstead Ave Richmond VA 23226",
    "addr:housenumber":"906",
    "addr:postcode":"23226",
    "addr:street":"Hampstead Ave",
    "iso:country":"US",
    "sg:address":"906 Hampstead Ave",
    "sg:city":"Richmond",
    "sg:classifiers":[
        {
            "category":"Professional",
            "subcategory":"Research",
            "type":"Services"
        }
    ],
    "sg:phone":"+1 804 285 0124",
    "sg:postcode":"23226",
    "sg:province":"VA",
    "sg:tags":[
        "educational"
    ],
    "wof:name":"Proscience Inc",
    "wof:placetype":"venue"
},
  "geometry": {"coordinates":[-77.519859,37.58387],"type":"Point"}
}