{
  "type": "Feature",
  "properties": {
    "iso:country":"US",
    "sg:address":"142 Golf Dr",
    "sg:city":"Bracey",
    "sg:classifiers":[
        {
            "category":"Retail",
            "subcategory":"Auto Repair",
            "type":"Services"
        }
    ],
    "sg:phone":"+1 434 636 2277",
    "sg:postcode":"23919",
    "sg:province":"VA",
    "sg:tags":[
        "repairing",
        "automobile"
    ],
    "wof:name":"Bracey Performance Automotive",
    "wof:placetype":"venue"
},
  "geometry": {"coordinates":[-78.13982900000001,36.593079],"type":"Point"}
}