{
  "type": "Feature",
  "properties": {
    "iso:country":"US",
    "sg:address":"12373 Dillingham Sq",
    "sg:city":"Woodbridge",
    "sg:classifiers":[
        {
            "category":"Shopping",
            "subcategory":"Crafts & Fabrics",
            "type":"Retail Goods"
        }
    ],
    "sg:phone":"+1 703 590 7474",
    "sg:postcode":"22192",
    "sg:province":"VA",
    "sg:tags":[
        "sewing"
    ],
    "wof:name":"Hancock Fabrics Inc",
    "wof:placetype":"venue"
},
  "geometry": {"coordinates":[-77.318084,38.684556],"type":"Point"}
}