{
  "type": "Feature",
  "properties": {
    "iso:country":"US",
    "sg:address":"1029 Huell Matthews Hwy",
    "sg:city":"South Boston",
    "sg:classifiers":[
        {
            "category":"Professional",
            "subcategory":"Accounting & Tax Preparation",
            "type":"Services"
        }
    ],
    "sg:phone":"+1 434 575 8299",
    "sg:postcode":"24592",
    "sg:province":"NC",
    "sg:tags":[
        "return",
        "filing"
    ],
    "wof:name":"Terry's Tax & Bookkeeping Svc",
    "wof:placetype":"venue"
},
  "geometry": {"coordinates":[-78.899957,36.68736],"type":"Point"}
}