{
  "type": "Feature",
  "properties": {
    "addr:full":"3911 Melrose Ave NW Roanoke VA 24017",
    "addr:housenumber":"3911",
    "addr:postcode":"24017",
    "addr:street":"Melrose Ave Nw",
    "iso:country":"US",
    "sg:address":"3911 Melrose Ave NW",
    "sg:city":"Roanoke",
    "sg:classifiers":[
        {
            "category":"Banks & Credit Unions",
            "subcategory":"Bank",
            "type":"Services"
        }
    ],
    "sg:phone":"+1 540 265 8543",
    "sg:postcode":"24017",
    "sg:province":"VA",
    "sg:tags":[
        "machine",
        "teller",
        "automated"
    ],
    "wof:name":"ATM America",
    "wof:placetype":"venue"
},
  "geometry": {"coordinates":[-80.0013,37.295516],"type":"Point"}
}