{
  "type": "Feature",
  "properties": {
    "iso:country":"US",
    "sg:address":"11 E Broad St",
    "sg:city":"Richmond",
    "sg:classifiers":[
        {
            "category":"Building & Trades",
            "subcategory":"Construction",
            "type":"Services"
        }
    ],
    "sg:phone":"+1 804 644 0777",
    "sg:postcode":"23219",
    "sg:province":"VA",
    "sg:tags":[
        "general",
        "painting",
        "maintenance",
        "contractor"
    ],
    "wof:name":"All American Painting Inc",
    "wof:placetype":"venue"
},
  "geometry": {"coordinates":[-77.441092,37.545052],"type":"Point"}
}