{
  "type": "Feature",
  "properties": {
    "iso:country":"US",
    "sg:address":"1591 Dahlia Dr",
    "sg:city":"Virginia Beach",
    "sg:classifiers":[
        {
            "category":"Restaurant",
            "type":"Food & Drink"
        }
    ],
    "sg:phone":"+1 757 368 5995",
    "sg:postcode":"23453",
    "sg:province":"VA",
    "wof:name":"It's All Good",
    "wof:placetype":"venue"
},
  "geometry": {"coordinates":[-76.10664,36.802395],"type":"Point"}
}