{
  "type": "Feature",
  "properties": {
    "iso:country":"US",
    "sg:address":"1201 22nd St",
    "sg:city":"Fort Lee",
    "sg:classifiers":[
        {
            "category":"Education",
            "subcategory":"School",
            "type":"Public Place"
        }
    ],
    "sg:phone":"+1 804 734 3458",
    "sg:postcode":"23801",
    "sg:province":"VA",
    "sg:tags":[
        "military",
        "for",
        "personnel"
    ],
    "wof:name":"US Army Quartermaster Ctr Schl",
    "wof:placetype":"venue"
},
  "geometry": {"coordinates":[-77.344307,37.240323],"type":"Point"}
}