{
  "type": "Feature",
  "properties": {
    "addr:full":"12705 Misty Creek Ln Fairfax VA 22033",
    "addr:housenumber":"12705",
    "addr:postcode":"22033",
    "addr:street":"Misty Creek Ln",
    "iso:country":"US",
    "sg:address":"12705 Misty Creek Ln",
    "sg:city":"Fairfax",
    "sg:classifiers":[
        {
            "category":"Professional",
            "type":"Services"
        }
    ],
    "sg:phone":"+1 703 391 9472",
    "sg:postcode":"22033",
    "sg:province":"VA",
    "sg:tags":[
        "establishment"
    ],
    "wof:name":"Century Oaks",
    "wof:placetype":"venue"
},
  "geometry": {"coordinates":[-77.386481,38.887539],"type":"Point"}
}