{
  "type": "Feature",
  "properties": {
    "iso:country":"US",
    "sg:address":"200 Golden Oak Ct",
    "sg:city":"Virginia Beach",
    "sg:classifiers":[
        {
            "category":"Professional",
            "subcategory":"Management & Consulting",
            "type":"Services"
        }
    ],
    "sg:phone":"+1 757 340 5960",
    "sg:postcode":"23452",
    "sg:province":"VA",
    "sg:tags":[
        "marketing",
        "agency"
    ],
    "wof:name":"Protocol",
    "wof:placetype":"venue"
},
  "geometry": {"coordinates":[-76.07089999999999,36.833052],"type":"Point"}
}