{
  "type": "Feature",
  "properties": {
    "iso:country":"US",
    "sg:address":"10000 Brook Rd",
    "sg:city":"Glen Allen",
    "sg:classifiers":[
        {
            "category":"Professional",
            "type":"Services"
        }
    ],
    "sg:phone":"+1 804 264 0106",
    "sg:postcode":"23059",
    "sg:province":"VA",
    "wof:name":"Perseco",
    "wof:placetype":"venue"
},
  "geometry": {"coordinates":[-77.46096199999999,37.674022],"type":"Point"}
}