{
  "type": "Feature",
  "properties": {
    "addr:full":"119 Sweetgum St Elkton VA 22827",
    "addr:housenumber":"119",
    "addr:postcode":"22827",
    "addr:street":"Sweetgum St",
    "iso:country":"US",
    "sg:address":"119 Sweetgum St",
    "sg:city":"Elkton",
    "sg:classifiers":[
        {
            "category":"Building & Trades",
            "subcategory":"Construction",
            "type":"Services"
        }
    ],
    "sg:phone":"+1 540 298 0525",
    "sg:postcode":"22827",
    "sg:province":"VA",
    "sg:tags":[
        "builder",
        "repairer",
        "chimney",
        "contractor"
    ],
    "wof:name":"Old Dominion Chimney Line",
    "wof:placetype":"venue"
},
  "geometry": {"coordinates":[-78.61664399999999,38.419908],"type":"Point"}
}