{
  "type": "Feature",
  "properties": {
    "iso:country":"US",
    "sg:address":"703 Constitution Ave",
    "sg:city":"Portsmouth",
    "sg:classifiers":[
        {
            "category":"Autos & Motor Vehicles",
            "subcategory":"Auto Supplies",
            "type":"Retail Goods"
        },
        {
            "category":"Retail",
            "subcategory":"Auto Repair",
            "type":"Services"
        }
    ],
    "sg:phone":"+1 757 399 6471",
    "sg:postcode":"23704",
    "sg:province":"VA",
    "sg:tags":[
        "repairing",
        "tire"
    ],
    "wof:name":"Bob Ewell Tire Svc Inc",
    "wof:placetype":"venue"
},
  "geometry": {"coordinates":[-76.32550000000001,36.833215],"type":"Point"}
}