{
  "type": "Feature",
  "properties": {
    "iso:country":"US",
    "sg:address":"45715 Old Ox Rd",
    "sg:city":"Sterling",
    "sg:classifiers":[
        {
            "category":"Retail",
            "subcategory":"Auto Rental",
            "type":"Services"
        }
    ],
    "sg:phone":"+1 703 437 3404",
    "sg:postcode":"20166",
    "sg:province":"VA",
    "sg:tags":[
        "renting",
        "truck",
        "leasing"
    ],
    "wof:name":"U-Haul Co",
    "wof:placetype":"venue"
},
  "geometry": {"coordinates":[-77.42606600000001,38.97887],"type":"Point"}
}