{
  "type": "Feature",
  "properties": {
    "addr:full":"2540 Virginia Beach Blvd Virginia Beach VA 23452",
    "addr:housenumber":"2540",
    "addr:postcode":"23452",
    "addr:street":"Virginia Beach Blvd",
    "iso:country":"US",
    "sg:address":"2540 Virginia Beach Blvd",
    "sg:city":"Virginia Beach",
    "sg:classifiers":[
        {
            "category":"Building & Trades",
            "subcategory":"Construction",
            "type":"Services"
        }
    ],
    "sg:phone":"+1 757 306 9885",
    "sg:postcode":"23452",
    "sg:province":"VA",
    "sg:tags":[
        "house"
    ],
    "wof:name":"Advanced Building & Remodeling",
    "wof:placetype":"venue"
},
  "geometry": {"coordinates":[-76.05831000000001,36.84125],"type":"Point"}
}