{
  "type": "Feature",
  "properties": {
    "iso:country":"US",
    "sg:address":"111 Jackson St",
    "sg:city":"Edinburg",
    "sg:classifiers":[
        {
            "category":"Building & Trades",
            "subcategory":"Cleaning & Sanitation",
            "type":"Services"
        }
    ],
    "sg:phone":"+1 540 984 8471",
    "sg:postcode":"22824",
    "sg:province":"VA",
    "sg:tags":[
        "house",
        "washing"
    ],
    "wof:name":"Day's Pro-Wash",
    "wof:placetype":"venue"
},
  "geometry": {"coordinates":[-78.563919,38.826503],"type":"Point"}
}