{
  "type": "Feature",
  "properties": {
    "addr:full":"208 Pondview St Tappahannock VA 22560",
    "addr:housenumber":"208",
    "addr:postcode":"22560",
    "addr:street":"Pondview St",
    "iso:country":"US",
    "sg:address":"208 Pondview St",
    "sg:city":"Tappahannock",
    "sg:classifiers":[
        {
            "category":"Shopping",
            "subcategory":"Used Merchandise",
            "type":"Retail Goods"
        }
    ],
    "sg:phone":"+1 804 333 0094",
    "sg:postcode":"22560",
    "sg:province":"VA",
    "wof:name":"Corner Bargains",
    "wof:placetype":"venue"
},
  "geometry": {"coordinates":[-76.84526099999999,37.905781],"type":"Point"}
}