{
  "type": "Feature",
  "properties": {
    "iso:country":"US",
    "sg:address":"7207 Lockport Pl",
    "sg:city":"Lorton",
    "sg:classifiers":[
        {
            "category":"Wholesale",
            "subcategory":"Toys & Hobbies",
            "type":"Manufacturing & Wholesale Goods"
        }
    ],
    "sg:phone":"+1 703 339 5800",
    "sg:postcode":"22079",
    "sg:province":"VA",
    "sg:tags":[
        "wholesaler"
    ],
    "wof:name":"Viet-Art",
    "wof:placetype":"venue"
},
  "geometry": {"coordinates":[-77.193837,38.715035],"type":"Point"}
}