{
  "type": "Feature",
  "properties": {
    "iso:country":"US",
    "sg:address":"909 E Main St",
    "sg:city":"Richmond",
    "sg:classifiers":[
        {
            "category":"Professional",
            "subcategory":"Lawyer & Legal Services",
            "type":"Services"
        }
    ],
    "sg:phone":"+1 804 697 4146",
    "sg:postcode":"23219",
    "sg:province":"VA",
    "wof:name":"George H Roberts Jr",
    "wof:placetype":"venue"
},
  "geometry": {"coordinates":[-77.435512,37.537665],"type":"Point"}
}