{
  "type": "Feature",
  "properties": {
    "iso:country":"US",
    "sg:address":"209 Cleveland Ave",
    "sg:city":"Martinsville",
    "sg:classifiers":[
        {
            "category":"Health Services",
            "subcategory":"Doctor",
            "type":"Services"
        }
    ],
    "sg:phone":"+1 276 632 6496",
    "sg:postcode":"24112",
    "sg:province":"VA",
    "sg:tags":[
        "medical"
    ],
    "wof:name":"J Szulecki MD",
    "wof:placetype":"venue"
},
  "geometry": {"coordinates":[-79.867638,36.685913],"type":"Point"}
}