{
  "type": "Feature",
  "properties": {
    "addr:full":"1357 Red Stone Rd Chilhowie VA 24319",
    "addr:housenumber":"1357",
    "addr:postcode":"24319",
    "addr:street":"Red Stone Rd",
    "iso:country":"US",
    "sg:address":"1357 Red Stone Rd",
    "sg:city":"Chilhowie",
    "sg:classifiers":[
        {
            "category":"Freight",
            "type":"Transportation"
        }
    ],
    "sg:phone":"+1 276 646 8903",
    "sg:postcode":"24319",
    "sg:province":"VA",
    "sg:tags":[
        "operator",
        "local",
        "trucking"
    ],
    "wof:name":"D&J Trucking",
    "wof:placetype":"venue"
},
  "geometry": {"coordinates":[-81.59391100000001,36.751085],"type":"Point"}
}