{
  "type": "Feature",
  "properties": {
    "addr:full":"882 N Harrison St Arlington VA 22205",
    "addr:housenumber":"882",
    "addr:postcode":"22205",
    "addr:street":"N Harrison St",
    "iso:country":"US",
    "sg:address":"882 N Harrison St",
    "sg:city":"Arlington",
    "sg:classifiers":[
        {
            "category":"Professional",
            "type":"Services"
        }
    ],
    "sg:phone":"+1 703 358 9720",
    "sg:postcode":"22205",
    "sg:province":"VA",
    "wof:name":"Diver City LLC",
    "wof:placetype":"venue"
},
  "geometry": {"coordinates":[-77.12769900000001,38.878775],"type":"Point"}
}