{
  "type": "Feature",
  "properties": {
    "addr:full":"10 S King St Leesburg VA 20175",
    "addr:housenumber":"10",
    "addr:postcode":"20175",
    "addr:street":"S King St",
    "iso:country":"US",
    "sg:address":"10 S King St",
    "sg:city":"Leesburg",
    "sg:classifiers":[
        {
            "category":"Home & Garden",
            "subcategory":"Furniture",
            "type":"Retail Goods"
        }
    ],
    "sg:phone":"+1 703 669 0140",
    "sg:postcode":"20175",
    "sg:province":"VA",
    "sg:tags":[
        "antique"
    ],
    "wof:name":"Otter Creek Collections",
    "wof:placetype":"venue"
},
  "geometry": {"coordinates":[-77.564502,39.115321],"type":"Point"}
}