{
  "type": "Feature",
  "properties": {
    "addr:full":"9695 Wards Rd Rustburg VA 24588",
    "addr:housenumber":"9695",
    "addr:postcode":"24588",
    "addr:street":"Wards Rd",
    "iso:country":"US",
    "sg:address":"9695 Wards Rd",
    "sg:city":"Rustburg",
    "sg:classifiers":[
        {
            "category":"Personal",
            "type":"Services"
        }
    ],
    "sg:phone":"+1 434 821 2909",
    "sg:postcode":"24588",
    "sg:province":"VA",
    "wof:name":"Gibson Ed Home Improvement",
    "wof:placetype":"venue"
},
  "geometry": {"coordinates":[-79.179929,37.263384],"type":"Point"}
}