{
  "type": "Feature",
  "properties": {
    "addr:full":"121 Broadview Ave Warrenton VA 20186",
    "addr:housenumber":"121",
    "addr:postcode":"20186",
    "addr:street":"Broadview Ave",
    "iso:country":"US",
    "sg:address":"121 Broadview Ave",
    "sg:city":"Warrenton",
    "sg:classifiers":[
        {
            "category":"Autos & Motor Vehicles",
            "subcategory":"Fuel & Gas Station",
            "type":"Retail Goods"
        }
    ],
    "sg:phone":"+1 540 349 1649",
    "sg:postcode":"20186",
    "sg:province":"VA",
    "sg:tags":[
        "oil"
    ],
    "wof:name":"Crown Gas Station",
    "wof:placetype":"venue"
},
  "geometry": {"coordinates":[-77.806076,38.721025],"type":"Point"}
}