{
  "type": "Feature",
  "properties": {
    "iso:country":"US",
    "sg:address":"7484 Lee Hwy",
    "sg:city":"Radford",
    "sg:classifiers":[
        {
            "category":"Restaurant",
            "type":"Food & Drink"
        }
    ],
    "sg:menulink":"http://www.allmenus.com/va/cloyd/188135-mcdonalds/menu/",
    "sg:postcode":"24141",
    "sg:province":"VA",
    "sg:tags":[
        "burger",
        "american"
    ],
    "wof:name":"McDonald's",
    "wof:placetype":"venue"
},
  "geometry": {"coordinates":[-80.578284,37.141713],"type":"Point"}
}