{
  "type": "Feature",
  "properties": {
    "addr:full":"400 Salters Creek Rd Hampton VA 23661",
    "addr:housenumber":"400",
    "addr:postcode":"23661",
    "addr:street":"Salters Creek Rd",
    "iso:country":"US",
    "sg:address":"400 Salters Creek Rd",
    "sg:city":"Hampton",
    "sg:classifiers":[
        {
            "category":"Retail",
            "subcategory":"Auto Repair",
            "type":"Services"
        }
    ],
    "sg:phone":"+1 757 726 0380",
    "sg:postcode":"23661",
    "sg:province":"VA",
    "sg:tags":[
        "repairing",
        "automobile",
        "general"
    ],
    "wof:name":"Barney's Auto Repair",
    "wof:placetype":"venue"
},
  "geometry": {"coordinates":[-76.375759,37.023826],"type":"Point"}
}