{
  "type": "Feature",
  "properties": {
    "addr:full":"1607 Whitlone Dr Richmond VA 23225",
    "addr:housenumber":"1607",
    "addr:postcode":"23225",
    "addr:street":"Whitlone Dr",
    "iso:country":"US",
    "sg:address":"1607 Whitlone Dr",
    "sg:city":"Richmond",
    "sg:classifiers":[
        {
            "category":"Building & Trades",
            "subcategory":"Construction",
            "type":"Services"
        }
    ],
    "sg:phone":"+1 804 233 6970",
    "sg:postcode":"23225",
    "sg:province":"VA",
    "sg:tags":[
        "specializing",
        "general",
        "remodeling",
        "contractor"
    ],
    "wof:name":"Debois Reed H Crafts",
    "wof:placetype":"venue"
},
  "geometry": {"coordinates":[-77.511853,37.52556],"type":"Point"}
}