{
  "type": "Feature",
  "properties": {
    "iso:country":"US",
    "sg:address":"4210 Mozart Brigade Ln",
    "sg:city":"Fairfax",
    "sg:classifiers":[
        {
            "category":"Professional",
            "subcategory":"Detective & Security Services",
            "type":"Services"
        }
    ],
    "sg:phone":"+1 703 379 6676",
    "sg:postcode":"22033",
    "sg:province":"VA",
    "sg:tags":[
        "investigation",
        "background"
    ],
    "wof:name":"Ruben J Munoz",
    "wof:placetype":"venue"
},
  "geometry": {"coordinates":[-77.37170500000001,38.861793],"type":"Point"}
}