{
  "type": "Feature",
  "properties": {
    "addr:full":"402 W Williamsburg Rd Sandston VA 23150",
    "addr:housenumber":"402",
    "addr:postcode":"23150",
    "addr:street":"W Williamsburg Rd",
    "iso:country":"US",
    "sg:address":"402 W Williamsburg Rd",
    "sg:city":"Sandston",
    "sg:classifiers":[
        {
            "category":"Home & Garden",
            "subcategory":"Garden Supply",
            "type":"Retail Goods"
        }
    ],
    "sg:phone":"+1 804 737 2230",
    "sg:postcode":"23150",
    "sg:province":"VA",
    "sg:tags":[
        "lawn",
        "mower"
    ],
    "wof:name":"R & D Sales & Svc",
    "wof:placetype":"venue"
},
  "geometry": {"coordinates":[-77.321798,37.522952],"type":"Point"}
}