{
  "type": "Feature",
  "properties": {
    "iso:country":"US",
    "sg:address":"1051 E Cary St",
    "sg:city":"Richmond",
    "sg:classifiers":[
        {
            "category":"Professional",
            "subcategory":"Computer Services",
            "type":"Services"
        }
    ],
    "sg:phone":"+1 804 225 9222",
    "sg:postcode":"23219",
    "sg:province":"VA",
    "wof:name":"Va Packet Systems",
    "wof:placetype":"venue"
},
  "geometry": {"coordinates":[-77.435338,37.536254],"type":"Point"}
}