{
  "type": "Feature",
  "properties": {
    "addr:full":"15 S Braddock St Winchester VA 22601",
    "addr:housenumber":"15",
    "addr:postcode":"22601",
    "addr:street":"S Braddock St",
    "iso:country":"US",
    "sg:address":"15 S Braddock St",
    "sg:city":"Winchester",
    "sg:classifiers":[
        {
            "category":"Shopping",
            "subcategory":"Jewelry",
            "type":"Retail Goods"
        }
    ],
    "sg:phone":"+1 540 722 1313",
    "sg:postcode":"22601",
    "sg:province":"VA",
    "sg:tags":[
        "jeweler"
    ],
    "wof:name":"Christian Caine Jewlers Inc",
    "wof:placetype":"venue"
},
  "geometry": {"coordinates":[-78.167264,39.184305],"type":"Point"}
}