{
  "type": "Feature",
  "properties": {
    "addr:full":"10842 Stilton Dr Chester VA 23831",
    "addr:housenumber":"10842",
    "addr:postcode":"23831",
    "addr:street":"Stilton Dr",
    "iso:country":"US",
    "sg:address":"10842 Stilton Dr",
    "sg:city":"Chester",
    "sg:classifiers":[
        {
            "category":"Social Services",
            "subcategory":"Child Care",
            "type":"Services"
        }
    ],
    "sg:phone":"+1 804 796 6266",
    "sg:postcode":"23831",
    "sg:province":"VA",
    "sg:tags":[
        "day"
    ],
    "wof:name":"Kat And Kids In Home Child Care",
    "wof:placetype":"venue"
},
  "geometry": {"coordinates":[-77.437279,37.378617],"type":"Point"}
}