{
  "type": "Feature",
  "properties": {
    "iso:country":"US",
    "sg:address":"6627 River Rd",
    "sg:city":"Petersburg",
    "sg:classifiers":[
        {
            "category":"Professional",
            "type":"Services"
        }
    ],
    "sg:phone":"+1 804 590 3100",
    "sg:postcode":"23803",
    "sg:province":"VA",
    "wof:name":"Virginia Congress of Pare",
    "wof:placetype":"venue"
},
  "geometry": {"coordinates":[-77.4836,37.23083],"type":"Point"}
}