{
  "type": "Feature",
  "properties": {
    "iso:country":"US",
    "sg:address":"4114 Legato Rd",
    "sg:city":"Fairfax",
    "sg:classifiers":[
        {
            "category":"Professional",
            "subcategory":"Engineering",
            "type":"Services"
        }
    ],
    "sg:phone":"+1 703 476 1800",
    "sg:postcode":"22033",
    "sg:province":"VA",
    "sg:tags":[
        "datum"
    ],
    "wof:name":"R M Vredenburg and Co",
    "wof:placetype":"venue"
},
  "geometry": {"coordinates":[-77.36308699999999,38.863715],"type":"Point"}
}