{
  "type": "Feature",
  "properties": {
    "addr:full":"609 Lynnhaven Pkwy Virginia Beach VA 23452",
    "addr:housenumber":"609",
    "addr:postcode":"23452",
    "addr:street":"Lynnhaven Pkwy",
    "iso:country":"US",
    "sg:address":"609 Lynnhaven Pkwy",
    "sg:city":"Virginia Beach",
    "sg:classifiers":[
        {
            "category":"Health Services",
            "subcategory":"Doctor",
            "type":"Services"
        }
    ],
    "sg:phone":"+1 757 340 8852",
    "sg:postcode":"23452",
    "sg:province":"VA",
    "sg:tags":[
        "dentist"
    ],
    "sg:website":"www.ffkdental.com",
    "wof:name":"Foster Foster & Kessler",
    "wof:placetype":"venue"
},
  "geometry": {"coordinates":[-76.067233,36.824069],"type":"Point"}
}