{
  "type": "Feature",
  "properties": {
    "iso:country":"US",
    "sg:address":"15241 Wards Rd",
    "sg:city":"Lynchburg",
    "sg:classifiers":[
        {
            "category":"Shopping",
            "subcategory":"Clothing, Apparel, & Fashions",
            "type":"Retail Goods"
        }
    ],
    "sg:phone":"+1 434 239 8989",
    "sg:postcode":"24502",
    "sg:province":"VA",
    "wof:name":"Unity Urban Wear Inc",
    "wof:placetype":"venue"
},
  "geometry": {"coordinates":[-79.191615,37.335425],"type":"Point"}
}