{
  "type": "Feature",
  "properties": {
    "iso:country":"US",
    "sg:address":"5101 Brookshire Ct W",
    "sg:city":"Fredericksburg",
    "sg:classifiers":[
        {
            "category":"Utilities",
            "type":"Services"
        }
    ],
    "sg:phone":"+1 540 891 5296",
    "sg:postcode":"22408",
    "sg:province":"VA",
    "sg:tags":[
        "sanitary"
    ],
    "wof:name":"Steves Snow Removal",
    "wof:placetype":"venue"
},
  "geometry": {"coordinates":[-77.512761,38.270033],"type":"Point"}
}