{
  "type": "Feature",
  "properties": {
    "addr:full":"2101 S Crystal Dr Arlington VA 22202",
    "addr:housenumber":"2101",
    "addr:postcode":"22202",
    "addr:street":"S Crystal Dr",
    "iso:country":"US",
    "sg:address":"2101 S Crystal Dr",
    "sg:city":"Arlington",
    "sg:classifiers":[
        {
            "category":"Food & Beverages",
            "subcategory":"Specialty",
            "type":"Retail Goods"
        }
    ],
    "sg:phone":"+1 703 413 3030",
    "sg:postcode":"22202",
    "sg:province":"VA",
    "wof:name":"Coffee Company The",
    "wof:placetype":"venue"
},
  "geometry": {"coordinates":[-77.04949499999999,38.854238],"type":"Point"}
}