{
  "type": "Feature",
  "properties": {
    "iso:country":"US",
    "sg:address":"249 Wyndover Dr",
    "sg:city":"Danville",
    "sg:classifiers":[
        {
            "category":"Professional",
            "subcategory":"Business Services",
            "type":"Services"
        }
    ],
    "sg:phone":"+1 434 822 1580",
    "sg:postcode":"24541",
    "sg:province":"VA",
    "sg:tags":[
        "appraiser"
    ],
    "wof:name":"H H Brincefield Appraiser",
    "wof:placetype":"venue"
},
  "geometry": {"coordinates":[-79.460959,36.588738],"type":"Point"}
}