{
  "type": "Feature",
  "properties": {
    "addr:full":"1418 Poindexter St Chesapeake VA 23324",
    "addr:housenumber":"1418",
    "addr:postcode":"23324",
    "addr:street":"Poindexter St",
    "iso:country":"US",
    "sg:address":"1418 Poindexter St",
    "sg:city":"Chesapeake",
    "sg:classifiers":[
        {
            "category":"Shopping",
            "subcategory":"Clothing, Apparel, & Fashions",
            "type":"Retail Goods"
        }
    ],
    "sg:phone":"+1 757 543 2949",
    "sg:postcode":"23324",
    "sg:province":"VA",
    "wof:name":"Don Dappa Clothing Co",
    "wof:placetype":"venue"
},
  "geometry": {"coordinates":[-76.271991,36.819704],"type":"Point"}
}