{
  "type": "Feature",
  "properties": {
    "addr:full":"1074 Dobyns Rd Stuart VA 24171",
    "addr:housenumber":"1074",
    "addr:postcode":"24171",
    "addr:street":"Dobyns Rd",
    "iso:country":"US",
    "sg:address":"1074 Dobyns Rd",
    "sg:city":"Stuart",
    "sg:classifiers":[
        {
            "category":"Autos & Motor Vehicles",
            "subcategory":"Automobile Sales",
            "type":"Retail Goods"
        }
    ],
    "sg:phone":"+1 276 694 0244",
    "sg:postcode":"24171",
    "sg:province":"VA",
    "wof:name":"A-J & Son Truckin Inc",
    "wof:placetype":"venue"
},
  "geometry": {"coordinates":[-80.29536400000001,36.641481],"type":"Point"}
}