{
  "type": "Feature",
  "properties": {
    "iso:country":"US",
    "sg:address":"6433 Horton Cir",
    "sg:city":"Norfolk",
    "sg:classifiers":[
        {
            "category":"Professional",
            "type":"Services"
        }
    ],
    "sg:phone":"+1 757 963 5958",
    "sg:postcode":"23513",
    "sg:province":"VA",
    "wof:name":"Solo 5 Reminders",
    "wof:placetype":"venue"
},
  "geometry": {"coordinates":[-76.248,36.896304],"type":"Point"}
}