{
  "type": "Feature",
  "properties": {
    "addr:full":"4660 Monticello Ave Williamsburg VA 23188",
    "addr:housenumber":"4660",
    "addr:postcode":"23188",
    "addr:street":"Monticello Ave",
    "iso:country":"US",
    "sg:address":"4660 Monticello Ave",
    "sg:city":"Williamsburg",
    "sg:classifiers":[
        {
            "category":"Coffee & Tea",
            "type":"Food & Drink"
        }
    ],
    "sg:menulink":"http://www.allmenus.com/va/berkeley/112141-starbucks-coffee/menu/",
    "sg:phone":"+1 757 564 0455",
    "sg:postcode":"23188",
    "sg:province":"VA",
    "sg:tags":[
        "american"
    ],
    "wof:name":"Starbucks Coffee",
    "wof:placetype":"venue"
},
  "geometry": {"coordinates":[-76.759077,37.269981],"type":"Point"}
}