{
  "type": "Feature",
  "properties": {
    "iso:country":"US",
    "sg:address":"4309 Taney Ave",
    "sg:city":"Alexandria",
    "sg:classifiers":[
        {
            "category":"Utilities",
            "subcategory":"Telephone",
            "type":"Services"
        }
    ],
    "sg:phone":"+1 571 216 1286",
    "sg:postcode":"22304",
    "sg:province":"VA",
    "wof:name":"Epns",
    "wof:placetype":"venue"
},
  "geometry": {"coordinates":[-77.106313,38.815229],"type":"Point"}
}