{
  "type": "Feature",
  "properties": {
    "iso:country":"US",
    "sg:address":"1060 Laskin Rd",
    "sg:city":"Virginia Beach",
    "sg:classifiers":[
        {
            "category":"Professional",
            "type":"Services"
        },
        {
            "category":"Professional",
            "subcategory":"Management & Consulting",
            "type":"Services"
        }
    ],
    "sg:phone":"+1 757 425 2494",
    "sg:postcode":"23451",
    "sg:province":"VA",
    "sg:tags":[
        "control",
        "consultant",
        "noise",
        "business"
    ],
    "wof:name":"Citizens Concerned About Jet N",
    "wof:placetype":"venue"
},
  "geometry": {"coordinates":[-75.99739599999999,36.854137],"type":"Point"}
}