{
  "type": "Feature",
  "properties": {
    "iso:country":"US",
    "sg:address":"1642 Pleasure House Rd",
    "sg:city":"Virginia Beach",
    "sg:classifiers":[
        {
            "category":"Shopping",
            "subcategory":"Musical Instruments",
            "type":"Retail Goods"
        }
    ],
    "sg:phone":"+1 757 464 2425",
    "sg:postcode":"23455",
    "sg:province":"VA",
    "sg:tags":[
        "piano",
        "organs"
    ],
    "wof:name":"Church Music Services",
    "wof:placetype":"venue"
},
  "geometry": {"coordinates":[-76.13999800000001,36.895965],"type":"Point"}
}