{
  "type": "Feature",
  "properties": {
    "addr:full":"9030 Craigwood Cir Mechanicsville VA 23116",
    "addr:postcode":"9030;23116",
    "addr:street":"Craigwood Cir",
    "iso:country":"US",
    "sg:address":"9030 Craigwood Cir",
    "sg:city":"Mechanicsville",
    "sg:classifiers":[
        {
            "category":"Travel",
            "subcategory":"Travel Agent",
            "type":"Entertainment"
        }
    ],
    "sg:phone":"+1 804 550 3754",
    "sg:postcode":"23116",
    "sg:province":"VA",
    "sg:tags":[
        "agency",
        "bureau"
    ],
    "wof:name":"Travel Adventures",
    "wof:placetype":"venue"
},
  "geometry": {"coordinates":[-77.405975,37.703682],"type":"Point"}
}