{
  "type": "Feature",
  "properties": {
    "addr:full":"2417 Baum Rd Chesapeake VA 23322",
    "addr:housenumber":"2417",
    "addr:postcode":"23322",
    "addr:street":"Baum Rd",
    "iso:country":"US",
    "sg:address":"2417 Baum Rd",
    "sg:city":"Chesapeake",
    "sg:classifiers":[
        {
            "category":"Building & Trades",
            "subcategory":"Pest Control",
            "type":"Services"
        }
    ],
    "sg:phone":"+1 757 421 3063",
    "sg:postcode":"23322",
    "sg:province":"VA",
    "wof:name":"Allphase Termite & Pest Contro",
    "wof:placetype":"venue"
},
  "geometry": {"coordinates":[-76.122809,36.571683],"type":"Point"}
}