{
  "type": "Feature",
  "properties": {
    "addr:full":"10310 Layton Hall Dr Fairfax VA 22030",
    "addr:postcode":"10310;22030",
    "addr:street":"Hall Dr",
    "iso:country":"US",
    "sg:address":"10310 Layton Hall Dr",
    "sg:city":"Fairfax",
    "sg:classifiers":[
        {
            "category":"Education",
            "subcategory":"School",
            "type":"Public Place"
        }
    ],
    "sg:phone":"+1 703 246 7798",
    "sg:postcode":"22030",
    "sg:province":"VA",
    "sg:tags":[
        "elementary",
        "secondary"
    ],
    "wof:name":"Fairfax County Public Schools",
    "wof:placetype":"venue"
},
  "geometry": {"coordinates":[-77.300161,38.8503],"type":"Point"}
}