{
  "type": "Feature",
  "properties": {
    "addr:full":"8 N Main St Lexington VA 24450",
    "addr:housenumber":"8",
    "addr:postcode":"24450",
    "addr:street":"N Main St",
    "iso:country":"US",
    "sg:address":"8 N Main St",
    "sg:city":"Lexington",
    "sg:classifiers":[
        {
            "category":"Restaurant",
            "type":"Food & Drink"
        }
    ],
    "sg:phone":"+1 540 464 4888",
    "sg:postcode":"24450",
    "sg:province":"VA",
    "sg:tags":[
        "eating"
    ],
    "wof:name":"Bistro On Main",
    "wof:placetype":"venue"
},
  "geometry": {"coordinates":[-79.44180299999999,37.785268],"type":"Point"}
}