{
  "type": "Feature",
  "properties": {
    "addr:full":"6596 Main St Gloucester VA 23061",
    "addr:housenumber":"6596",
    "addr:postcode":"23061",
    "addr:street":"Main St",
    "iso:country":"US",
    "sg:address":"6596 Main St",
    "sg:city":"Gloucester",
    "sg:classifiers":[
        {
            "category":"Professional",
            "subcategory":"Lawyer & Legal Services",
            "type":"Services"
        }
    ],
    "sg:phone":"+1 804 694 3999",
    "sg:postcode":"23061",
    "sg:province":"VA",
    "sg:tags":[
        "grocery"
    ],
    "wof:name":"James Store Experience Inc",
    "wof:placetype":"venue"
},
  "geometry": {"coordinates":[-76.535856,37.416488],"type":"Point"}
}