{
  "type": "Feature",
  "properties": {
    "iso:country":"US",
    "sg:address":"6009 Fox Hill Rd",
    "sg:city":"Williamsburg",
    "sg:classifiers":[
        {
            "category":"Arts & Performance",
            "subcategory":"Theater",
            "type":"Entertainment"
        }
    ],
    "sg:phone":"+1 757 564 3319",
    "sg:postcode":"23188",
    "sg:province":"VA",
    "sg:tags":[
        "musical"
    ],
    "wof:name":"Harmony Entertainments",
    "wof:placetype":"venue"
},
  "geometry": {"coordinates":[-76.785984,37.329803],"type":"Point"}
}