{
  "type": "Feature",
  "properties": {
    "addr:full":"443 Dauphin Ln Virginia Beach VA 23452",
    "addr:housenumber":"443",
    "addr:postcode":"23452",
    "addr:street":"Dauphin Ln",
    "iso:country":"US",
    "sg:address":"443 Dauphin Ln",
    "sg:city":"Virginia Beach",
    "sg:classifiers":[
        {
            "category":"Professional",
            "subcategory":"Business Services",
            "type":"Services"
        }
    ],
    "sg:phone":"+1 757 340 4507",
    "sg:postcode":"23452",
    "sg:province":"VA",
    "sg:tags":[
        "layout",
        "factory"
    ],
    "wof:name":"Freehill Design Svc",
    "wof:placetype":"venue"
},
  "geometry": {"coordinates":[-76.084197,36.821424],"type":"Point"}
}