{
  "type": "Feature",
  "properties": {
    "iso:country":"US",
    "sg:address":"5110 Timbercreek Ct",
    "sg:city":"Richmond",
    "sg:classifiers":[
        {
            "category":"Home & Garden",
            "subcategory":"Building Materials",
            "type":"Retail Goods"
        },
        {
            "category":"Building & Trades",
            "subcategory":"Construction",
            "type":"Services"
        }
    ],
    "sg:phone":"+1 804 714 0019",
    "sg:postcode":"23237",
    "sg:province":"VA",
    "sg:tags":[
        "industrial",
        "contractor",
        "concrete",
        "contractors-commercial",
        "staining",
        "masonry"
    ],
    "sg:website":"http://www.aztekconcrete.com",
    "wof:name":"Aztec Concrete",
    "wof:placetype":"venue"
},
  "geometry": {"coordinates":[-77.475842,37.391546],"type":"Point"}
}