{
  "type": "Feature",
  "properties": {
    "iso:country":"US",
    "sg:address":"13013 Grey Friars Pl",
    "sg:city":"Herndon",
    "sg:classifiers":[
        {
            "category":"Professional",
            "subcategory":"Management & Consulting",
            "type":"Services"
        }
    ],
    "sg:phone":"+1 703 620 5415",
    "sg:postcode":"20171",
    "sg:province":"VA",
    "sg:tags":[
        "business"
    ],
    "wof:name":"Interantional Fincl Svcs Assoc",
    "wof:placetype":"venue"
},
  "geometry": {"coordinates":[-77.39899699999999,38.912999],"type":"Point"}
}