{
  "type": "Feature",
  "properties": {
    "iso:country":"US",
    "sg:address":"5 Main St",
    "sg:city":"Appomattox",
    "sg:classifiers":[
        {
            "category":"Organizations",
            "subcategory":"Professional Association",
            "type":"Services"
        }
    ],
    "sg:phone":"+1 434 352 2621",
    "sg:postcode":"24592",
    "sg:province":"NC",
    "sg:tags":[
        "business"
    ],
    "wof:name":"Appomttox Cnty Chmber Commerce",
    "wof:placetype":"venue"
},
  "geometry": {"coordinates":[-78.90071399999999,36.695065],"type":"Point"}
}