{
  "type": "Feature",
  "properties": {
    "iso:country":"US",
    "sg:address":"7442 Little River Tpke",
    "sg:city":"Annandale",
    "sg:classifiers":[
        {
            "category":"Restaurant",
            "type":"Food & Drink"
        }
    ],
    "sg:menulink":"http://www.allmenus.com/va/mason/282147-pho-hot-restaurant/menu/",
    "sg:phone":"+1 703 333 5955",
    "sg:postcode":"22003",
    "sg:province":"VA",
    "sg:tags":[
        "asian",
        "vietnamese"
    ],
    "wof:name":"Pho Hot Restaurant",
    "wof:placetype":"venue"
},
  "geometry": {"coordinates":[-77.20144000000001,38.831545],"type":"Point"}
}