{
  "type": "Feature",
  "properties": {
    "iso:country":"US",
    "sg:address":"8300 Riverton Ln",
    "sg:city":"Alexandria",
    "sg:classifiers":[
        {
            "category":"Insurance",
            "subcategory":"Insurance Agent",
            "type":"Services"
        }
    ],
    "sg:phone":"+1 703 799 1629",
    "sg:postcode":"22308",
    "sg:province":"VA",
    "wof:name":"Nlc Mutual Insurance Co",
    "wof:placetype":"venue"
},
  "geometry": {"coordinates":[-77.07068700000001,38.730472],"type":"Point"}
}