{
  "type": "Feature",
  "properties": {
    "iso:country":"US",
    "sg:address":"4209 Big Bethel Rd",
    "sg:city":"Yorktown",
    "sg:classifiers":[
        {
            "category":"Organizations",
            "subcategory":"Religious Organization",
            "type":"Services"
        }
    ],
    "sg:phone":"+1 757 867 8530",
    "sg:postcode":"23693",
    "sg:province":"VA",
    "sg:website":"www.peninsulacommunitychapel.com",
    "wof:name":"Peninsula Community Chapel",
    "wof:placetype":"venue"
},
  "geometry": {"coordinates":[-76.43210500000001,37.119633],"type":"Point"}
}