{
  "type": "Feature",
  "properties": {
    "addr:full":"3440 Seminole Trl Charlottesville VA 22911",
    "addr:housenumber":"3440",
    "addr:postcode":"22911",
    "addr:street":"Seminole Trl",
    "iso:country":"US",
    "sg:address":"3440 Seminole Trl",
    "sg:city":"Charlottesville",
    "sg:classifiers":[
        {
            "category":"Personal",
            "subcategory":"Tanning Parlor",
            "type":"Services"
        }
    ],
    "sg:phone":"+1 434 973 0895",
    "sg:postcode":"22911",
    "sg:province":"VA",
    "sg:tags":[
        "salon"
    ],
    "wof:name":"Caribbean Tan Inc",
    "wof:placetype":"venue"
},
  "geometry": {"coordinates":[-78.43737900000001,38.130498],"type":"Point"}
}