{
  "type": "Feature",
  "properties": {
    "addr:full":"8327 Terra Grande Ave Springfield VA 22153",
    "addr:housenumber":"8327",
    "addr:postcode":"22153",
    "addr:street":"Terra Grande Ave",
    "iso:country":"US",
    "sg:address":"8327 Terra Grande Ave",
    "sg:city":"Springfield",
    "sg:classifiers":[
        {
            "category":"Shopping",
            "subcategory":"Discount & Variety Stores",
            "type":"Retail Goods"
        }
    ],
    "sg:phone":"+1 703 440 9089",
    "sg:postcode":"22153",
    "sg:province":"VA",
    "sg:tags":[
        "merchandise",
        "general"
    ],
    "wof:name":"Discount Dollar Plus",
    "wof:placetype":"venue"
},
  "geometry": {"coordinates":[-77.20487300000001,38.729911],"type":"Point"}
}