{
  "type": "Feature",
  "properties": {
    "iso:country":"US",
    "sg:address":"1334 Longwood Ave",
    "sg:city":"Bedford",
    "sg:classifiers":[
        {
            "category":"Health Services",
            "subcategory":"Nursing And Care Facility",
            "type":"Services"
        }
    ],
    "sg:phone":"+1 540 586 5301",
    "sg:postcode":"24523",
    "sg:province":"VA",
    "sg:tags":[
        "skilled"
    ],
    "wof:name":"Campbell Rest Home",
    "wof:placetype":"venue"
},
  "geometry": {"coordinates":[-79.50781000000001,37.345744],"type":"Point"}
}