{
  "type": "Feature",
  "properties": {
    "addr:full":"1655 Fort Myer Dr Ste 700 Arlington VA 22209",
    "addr:housenumber":"1655",
    "addr:postcode":"22209",
    "addr:street":"Fort Myer Dr Ste 700",
    "iso:country":"US",
    "sg:address":"1655 Fort Myer Dr Ste 700",
    "sg:city":"Arlington",
    "sg:classifiers":[
        {
            "category":"Professional",
            "subcategory":"Computer Services",
            "type":"Services"
        },
        {
            "category":"Professional",
            "subcategory":"Business Services",
            "type":"Services"
        },
        {
            "category":"Internet Cafe",
            "subcategory":"None",
            "type":"Food & Drink"
        }
    ],
    "sg:phone":"+1 703 358 9100",
    "sg:postcode":"22209",
    "sg:province":"VA",
    "sg:tags":[
        "consultant",
        "product",
        "coach",
        "software"
    ],
    "sg:website":"http://www.alberscom.com",
    "wof:name":"Albers & Company",
    "wof:placetype":"venue"
},
  "geometry": {"coordinates":[-77.071983,38.893832],"type":"Point"}
}