{
  "type": "Feature",
  "properties": {
    "addr:full":"82 Hayes St Stafford VA 22556",
    "addr:housenumber":"82",
    "addr:postcode":"22556",
    "addr:street":"Hayes St",
    "iso:country":"US",
    "sg:address":"82 Hayes St",
    "sg:city":"Stafford",
    "sg:classifiers":[
        {
            "category":"Animal Shelter",
            "type":"Public Place"
        }
    ],
    "sg:phone":"+1 540 841 3332",
    "sg:postcode":"22556",
    "sg:province":"VA",
    "wof:name":"The Learning Zoo Daycare",
    "wof:placetype":"venue"
},
  "geometry": {"coordinates":[-77.486859,38.484004],"type":"Point"}
}