{
  "type": "Feature",
  "properties": {
    "addr:full":"5765-F Burke Center Pkwy #151 Burke VA 22015 ",
    "addr:housenumber":"5765-f;151",
    "addr:postcode":"22015",
    "addr:street":"Burke Center Pkwy #",
    "iso:country":"US",
    "sg:address":"5765-F Burke Center Pkwy #151",
    "sg:city":"Burke",
    "sg:classifiers":[
        {
            "category":"Professional",
            "subcategory":"Computer Services",
            "type":"Services"
        }
    ],
    "sg:postcode":"22015 ",
    "sg:province":"VA",
    "sg:website":"http://www.digitalgirlmedia.net/",
    "wof:name":"Digital Girl Media",
    "wof:placetype":"venue"
},
  "geometry": {"coordinates":[-77.31965,38.798548],"type":"Point"}
}