{
  "type": "Feature",
  "properties": {
    "addr:full":"128 E Main St Front Royal VA 22630",
    "addr:housenumber":"128",
    "addr:postcode":"22630",
    "addr:street":"E Main St",
    "iso:country":"US",
    "sg:address":"128 E Main St",
    "sg:city":"Front Royal",
    "sg:classifiers":[
        {
            "category":"Organizations",
            "subcategory":"Political Organization",
            "type":"Services"
        }
    ],
    "sg:phone":"+1 540 636 3741",
    "sg:postcode":"22630",
    "sg:province":"VA",
    "wof:name":"Warren County Democratic",
    "wof:placetype":"venue"
},
  "geometry": {"coordinates":[-78.192257,38.917967],"type":"Point"}
}