{
  "type": "Feature",
  "properties": {
    "addr:full":"6290 Old Warwick Rd Richmond VA 23224",
    "addr:housenumber":"6290",
    "addr:postcode":"23224",
    "addr:street":"Old Warwick Rd",
    "iso:country":"US",
    "sg:address":"6290 Old Warwick Rd",
    "sg:city":"Richmond",
    "sg:classifiers":[
        {
            "category":"Utilities",
            "subcategory":"Telephone",
            "type":"Services"
        }
    ],
    "sg:phone":"+1 804 276 2000",
    "sg:postcode":"23224",
    "sg:province":"VA",
    "sg:tags":[
        "telecommunication"
    ],
    "wof:name":"Griffin Telecom",
    "wof:placetype":"venue"
},
  "geometry": {"coordinates":[-77.51367500000001,37.503388],"type":"Point"}
}