{
  "type": "Feature",
  "properties": {
    "addr:full":"6021 Farrington Ave Alexandria VA 22304",
    "addr:housenumber":"6021",
    "addr:postcode":"22304",
    "addr:street":"Farrington Ave",
    "iso:country":"US",
    "sg:address":"6021 Farrington Ave",
    "sg:city":"Alexandria",
    "sg:classifiers":[
        {
            "category":"Freight",
            "type":"Transportation"
        }
    ],
    "sg:phone":"+1 703 461 0723",
    "sg:postcode":"22304",
    "sg:province":"VA",
    "wof:name":"Tobin Transportation",
    "wof:placetype":"venue"
},
  "geometry": {"coordinates":[-77.142268,38.79838],"type":"Point"}
}