{
  "type": "Feature",
  "properties": {
    "addr:full":"311 Banbury Ter Winchester VA 22601",
    "addr:housenumber":"311",
    "addr:postcode":"22601",
    "addr:street":"Banbury Ter",
    "iso:country":"US",
    "sg:address":"311 Banbury Ter",
    "sg:city":"Winchester",
    "sg:classifiers":[
        {
            "category":"Building & Trades",
            "subcategory":"Construction",
            "type":"Services"
        }
    ],
    "sg:phone":"+1 540 664 1482",
    "sg:postcode":"22601",
    "sg:province":"VA",
    "sg:tags":[
        "house"
    ],
    "wof:name":"Schanzenbach Construction",
    "wof:placetype":"venue"
},
  "geometry": {"coordinates":[-78.139414,39.19053],"type":"Point"}
}