{
  "type": "Feature",
  "properties": {
    "addr:full":"1200 Lakeside Dr Lynchburg VA 24501",
    "addr:housenumber":"1200",
    "addr:postcode":"24501",
    "addr:street":"Lakeside Dr",
    "iso:country":"US",
    "sg:address":"1200 Lakeside Dr",
    "sg:city":"Lynchburg",
    "sg:classifiers":[
        {
            "category":"Food & Beverages",
            "subcategory":"Groceries & Convenience Stores",
            "type":"Retail Goods"
        }
    ],
    "sg:phone":"+1 434 845 3102",
    "sg:postcode":"24501",
    "sg:province":"VA",
    "wof:name":"Quik-E Food Stores",
    "wof:placetype":"venue"
},
  "geometry": {"coordinates":[-79.17935199999999,37.402674],"type":"Point"}
}