{
  "type": "Feature",
  "properties": {
    "addr:full":"6041 Indian River Rd Virginia Beach VA 23464",
    "addr:housenumber":"6041",
    "addr:postcode":"23464",
    "addr:street":"Indian River Rd",
    "iso:country":"US",
    "sg:address":"6041 Indian River Rd",
    "sg:city":"Virginia Beach",
    "sg:classifiers":[
        {
            "category":"Shopping",
            "subcategory":"Optical Goods",
            "type":"Retail Goods"
        }
    ],
    "sg:phone":"+1 757 424 2030",
    "sg:postcode":"23464",
    "sg:province":"VA",
    "wof:name":"Lang Optical",
    "wof:placetype":"venue"
},
  "geometry": {"coordinates":[-76.203542,36.811217],"type":"Point"}
}