{
  "type": "Feature",
  "properties": {
    "iso:country":"US",
    "sg:address":"530 Neff Ave",
    "sg:city":"Harrisonburg",
    "sg:classifiers":[
        {
            "category":"Health Services",
            "subcategory":"Doctor",
            "type":"Services"
        }
    ],
    "sg:phone":"+1 540 432 1234",
    "sg:postcode":"22807",
    "sg:province":"VA",
    "sg:tags":[
        "medical"
    ],
    "wof:name":"Valley Medical Group",
    "wof:placetype":"venue"
},
  "geometry": {"coordinates":[-78.856185,38.426007],"type":"Point"}
}