{
  "type": "Feature",
  "properties": {
    "addr:full":"6 S Keswick Dr Troy VA 22974",
    "addr:housenumber":"6",
    "addr:postcode":"22974",
    "addr:street":"S Keswick Dr",
    "iso:country":"US",
    "sg:address":"6 S Keswick Dr",
    "sg:city":"Troy",
    "sg:classifiers":[
        {
            "category":"Farming",
            "subcategory":"Livestock Farm",
            "type":"Manufacturing & Wholesale Goods"
        }
    ],
    "sg:phone":"+1 434 296 7844",
    "sg:postcode":"22974",
    "sg:province":"VA",
    "sg:tags":[
        "beef",
        "feedlot",
        "cattle"
    ],
    "wof:name":"Tony Longenecker",
    "wof:placetype":"venue"
},
  "geometry": {"coordinates":[-78.328638,37.966098],"type":"Point"}
}