{
  "type": "Feature",
  "properties": {
    "addr:full":"38156 Montclair Court Purcellville VA 20132",
    "addr:housenumber":"38156",
    "addr:postcode":"20132",
    "addr:street":"Montclair Court",
    "iso:country":"US",
    "sg:address":"38156 Montclair Court",
    "sg:city":"Purcellville",
    "sg:classifiers":[
        {
            "category":"Real Estate",
            "subcategory":"Real Estate Agent",
            "type":"Services"
        }
    ],
    "sg:phone":"+1 571 233 1111",
    "sg:postcode":"20132",
    "sg:province":"VA",
    "sg:website":"http://profiles.ihouseweb.com/profile/dulleshomesalescom",
    "wof:name":"Burkart & Company LLC",
    "wof:placetype":"venue"
},
  "geometry": {"coordinates":[-77.683132,39.153257],"type":"Point"}
}