{
  "type": "Feature",
  "properties": {
    "addr:full":"1737 Wards Ferry Rd Lynchburg VA 24502",
    "addr:housenumber":"1737",
    "addr:postcode":"24502",
    "addr:street":"Wards Ferry Rd",
    "iso:country":"US",
    "sg:address":"1737 Wards Ferry Rd",
    "sg:city":"Lynchburg",
    "sg:classifiers":[
        {
            "category":"Organizations",
            "subcategory":"Religious Organization",
            "type":"Services"
        }
    ],
    "sg:phone":"+1 434 239 4943",
    "sg:postcode":"24502",
    "sg:province":"VA",
    "sg:website":"www.lynchburgnaz.com",
    "wof:name":"Church Of The Nazarene",
    "wof:placetype":"venue"
},
  "geometry": {"coordinates":[-79.19700400000001,37.360828],"type":"Point"}
}