{
  "type": "Feature",
  "properties": {
    "iso:country":"US",
    "sg:address":"600 E Main St",
    "sg:city":"Richmond",
    "sg:classifiers":[
        {
            "category":"Professional",
            "subcategory":"Computer Services",
            "type":"Services"
        }
    ],
    "sg:phone":"+1 804 786 4050",
    "sg:postcode":"23219",
    "sg:province":"VA",
    "sg:tags":[
        "related"
    ],
    "wof:name":"American Mgt Systems Inc",
    "wof:placetype":"venue"
},
  "geometry": {"coordinates":[-77.438104,37.539289],"type":"Point"}
}