{
  "type": "Feature",
  "properties": {
    "iso:country":"US",
    "sg:address":"8000 Westpark Dr Ste 125",
    "sg:city":"Mc Lean",
    "sg:classifiers":[
        {
            "category":"Education",
            "subcategory":"University",
            "type":"Public Place"
        }
    ],
    "sg:phone":"+1 703 749 3000",
    "sg:postcode":"22102",
    "sg:province":"VA",
    "sg:tags":[
        "college"
    ],
    "wof:name":"National-Louis University",
    "wof:placetype":"venue"
},
  "geometry": {"coordinates":[-77.221901,38.927299],"type":"Point"}
}