{
  "type": "Feature",
  "properties": {
    "iso:country":"US",
    "sg:address":"101 Blue Seal Dr SE",
    "sg:city":"Leesburg",
    "sg:classifiers":[
        {
            "category":"Government",
            "subcategory":"Office",
            "type":"Public Place"
        }
    ],
    "sg:phone":"+1 703 669 6650",
    "sg:postcode":"20175",
    "sg:province":"VA",
    "sg:tags":[
        "educational",
        "program",
        "administrative"
    ],
    "wof:name":"Natef",
    "wof:placetype":"venue"
},
  "geometry": {"coordinates":[-77.555071,39.084889],"type":"Point"}
}