{
  "type": "Feature",
  "properties": {
    "iso:country":"US",
    "sg:address":"1783 Roanoke Rd",
    "sg:city":"Daleville",
    "sg:classifiers":[
        {
            "category":"Restaurant",
            "type":"Food & Drink"
        }
    ],
    "sg:menulink":"http://www.allmenus.com/va/amsterdam/83406-papa-johns-pizza/menu/",
    "sg:phone":"+1 540 966 2555",
    "sg:postcode":"24083",
    "sg:province":"VA",
    "sg:tags":[
        "american",
        "pizza"
    ],
    "wof:name":"Papa John's Pizza",
    "wof:placetype":"venue"
},
  "geometry": {"coordinates":[-79.913083,37.41027],"type":"Point"}
}