{
  "type": "Feature",
  "properties": {
    "iso:country":"US",
    "sg:address":"103 Patrick St SE",
    "sg:city":"Vienna",
    "sg:classifiers":[
        {
            "category":"Food & Beverages",
            "subcategory":"Specialty",
            "type":"Retail Goods"
        }
    ],
    "sg:phone":"+1 703 849 1173",
    "sg:postcode":"22180",
    "sg:province":"VA",
    "sg:tags":[
        "product",
        "health",
        "diet"
    ],
    "wof:name":"Botanical Nutrients",
    "wof:placetype":"venue"
},
  "geometry": {"coordinates":[-77.247203,38.886087],"type":"Point"}
}