{
  "type": "Feature",
  "properties": {
    "iso:country":"US",
    "sg:address":"3352 John Tree Hill Rd",
    "sg:city":"Powhatan",
    "sg:classifiers":[
        {
            "category":"Building & Trades",
            "subcategory":"Construction",
            "type":"Services"
        }
    ],
    "sg:phone":"+1 804 794 1925",
    "sg:postcode":"23139",
    "sg:province":"VA",
    "sg:tags":[
        "residential"
    ],
    "wof:name":"Copliegh Construction Co",
    "wof:placetype":"venue"
},
  "geometry": {"coordinates":[-77.765756,37.607918],"type":"Point"}
}