{
  "type": "Feature",
  "properties": {
    "iso:country":"US",
    "sg:address":"5768 Charles City Cir",
    "sg:city":"Richmond",
    "sg:classifiers":[
        {
            "category":"Freight",
            "type":"Transportation"
        }
    ],
    "sg:phone":"+1 804 222 5880",
    "sg:postcode":"23231",
    "sg:province":"VA",
    "sg:tags":[
        "delivery"
    ],
    "wof:name":"Prestige Delivery System Inc",
    "wof:placetype":"venue"
},
  "geometry": {"coordinates":[-77.34545300000001,37.501865],"type":"Point"}
}