{
  "type": "Feature",
  "properties": {
    "iso:country":"US",
    "sg:address":"319 Shawnee Ave E",
    "sg:city":"Big Stone Gap",
    "sg:classifiers":[
        {
            "category":"Personal",
            "subcategory":"Tanning Parlor",
            "type":"Services"
        },
        {
            "category":"Personal",
            "type":"Services"
        }
    ],
    "sg:phone":"+1 276 523 2000",
    "sg:postcode":"24219",
    "sg:province":"VA",
    "sg:tags":[
        "salon"
    ],
    "wof:name":"Tan World",
    "wof:placetype":"venue"
},
  "geometry": {"coordinates":[-82.775997,36.867673],"type":"Point"}
}