{
  "type": "Feature",
  "properties": {
    "iso:country":"US",
    "sg:address":"1320 Old Chain Bridge Rd Ste 130",
    "sg:city":"Mc Lean",
    "sg:classifiers":[
        {
            "category":"Freight",
            "type":"Transportation"
        }
    ],
    "sg:phone":"+1 703 448 7778",
    "sg:postcode":"22101",
    "sg:province":"VA",
    "sg:tags":[
        "shipping"
    ],
    "sg:website":"www.thepackagingstore.com",
    "wof:name":"The Packaging Store",
    "wof:placetype":"venue"
},
  "geometry": {"coordinates":[-77.176828,38.938138],"type":"Point"}
}