{
  "type": "Feature",
  "properties": {
    "addr:full":"11387 Courthouse Rd Lunenburg VA 23952",
    "addr:housenumber":"11387",
    "addr:postcode":"23952",
    "addr:street":"Courthouse Rd",
    "iso:country":"US",
    "sg:address":"11387 Courthouse Rd",
    "sg:city":"Lunenburg",
    "sg:classifiers":[
        {
            "category":"Social Services",
            "type":"Services"
        }
    ],
    "sg:phone":"+1 434 696 2134",
    "sg:postcode":"23952",
    "sg:province":"VA",
    "wof:name":"Lunenburg Cnty Dept Scial Svcs",
    "wof:placetype":"venue"
},
  "geometry": {"coordinates":[-78.266345,36.961225],"type":"Point"}
}