{
  "type": "Feature",
  "properties": {
    "iso:country":"US",
    "sg:address":"4500 Daly Dr",
    "sg:city":"Chantilly",
    "sg:classifiers":[
        {
            "category":"Professional",
            "type":"Services"
        },
        {
            "category":"Professional",
            "subcategory":"Computer Services",
            "type":"Services"
        }
    ],
    "sg:phone":"+1 703 968 8805",
    "sg:postcode":"20151",
    "sg:province":"VA",
    "sg:tags":[
        "establishment"
    ],
    "wof:name":"Mac Heaven",
    "wof:placetype":"venue"
},
  "geometry": {"coordinates":[-77.44352499999999,38.885251],"type":"Point"}
}