{
  "type": "Feature",
  "properties": {
    "addr:full":"28 Greenwell Dr Hampton VA 23666",
    "addr:housenumber":"28",
    "addr:postcode":"23666",
    "addr:street":"Greenwell Dr",
    "iso:country":"US",
    "sg:address":"28 Greenwell Dr",
    "sg:city":"Hampton",
    "sg:classifiers":[
        {
            "category":"Professional",
            "subcategory":"Management & Consulting",
            "type":"Services"
        }
    ],
    "sg:phone":"+1 757 753 4348",
    "sg:postcode":"23666",
    "sg:province":"VA",
    "sg:tags":[
        "organizational",
        "development"
    ],
    "wof:name":"Grantworks Group",
    "wof:placetype":"venue"
},
  "geometry": {"coordinates":[-76.38338400000001,37.064494],"type":"Point"}
}