{
  "type": "Feature",
  "properties": {
    "iso:country":"US",
    "sg:address":"317 Brook Park Pl",
    "sg:city":"Forest",
    "sg:classifiers":[
        {
            "category":"Social Services",
            "type":"Services"
        }
    ],
    "sg:phone":"+1 434 385 7084",
    "sg:postcode":"24551",
    "sg:province":"VA",
    "wof:name":"Virginia Counselors Assn",
    "wof:placetype":"venue"
},
  "geometry": {"coordinates":[-79.250084,37.368907],"type":"Point"}
}