{
  "type": "Feature",
  "properties": {
    "addr:full":"2011 Chartstone Dr Midlothian VA 23113",
    "addr:housenumber":"2011",
    "addr:postcode":"23113",
    "addr:street":"Chartstone Dr",
    "iso:country":"US",
    "sg:address":"2011 Chartstone Dr",
    "sg:city":"Midlothian",
    "sg:classifiers":[
        {
            "category":"Retail",
            "subcategory":"Portrait Studio",
            "type":"Services"
        }
    ],
    "sg:phone":"+1 804 897 5208",
    "sg:postcode":"23113",
    "sg:province":"VA",
    "sg:tags":[
        "photo"
    ],
    "wof:name":"Photography By Jerrold",
    "wof:placetype":"venue"
},
  "geometry": {"coordinates":[-77.637169,37.520018],"type":"Point"}
}