{
  "type": "Feature",
  "properties": {
    "iso:country":"US",
    "sg:address":"4353 Majestic Ln",
    "sg:city":"Fairfax",
    "sg:classifiers":[
        {
            "category":"Wholesale",
            "subcategory":"Electrical",
            "type":"Manufacturing & Wholesale Goods"
        }
    ],
    "sg:phone":"+1 703 222 5492",
    "sg:postcode":"22033",
    "sg:province":"VA",
    "sg:tags":[
        "control"
    ],
    "wof:name":"Automated Test Labs Inc",
    "wof:placetype":"venue"
},
  "geometry": {"coordinates":[-77.405298,38.869239],"type":"Point"}
}