{
  "type": "Feature",
  "properties": {
    "iso:country":"US",
    "sg:address":"209 Elden St",
    "sg:city":"Herndon",
    "sg:classifiers":[
        {
            "category":"Professional",
            "subcategory":"Research",
            "type":"Services"
        },
        {
            "category":"Shopping",
            "subcategory":"Computers & Home Electronics",
            "type":"Retail Goods"
        }
    ],
    "sg:phone":"+1 703 796 9909",
    "sg:postcode":"20170",
    "sg:province":"VA",
    "sg:tags":[
        "equipment",
        "commercial",
        "dealer",
        "physical"
    ],
    "wof:name":"Prism Pointe Technologies",
    "wof:placetype":"venue"
},
  "geometry": {"coordinates":[-77.370504,38.966594],"type":"Point"}
}