{
  "type": "Feature",
  "properties": {
    "addr:full":"17340 Belsches Rd Bumpass VA 23024",
    "addr:housenumber":"17340",
    "addr:postcode":"23024",
    "addr:street":"Belsches Rd",
    "iso:country":"US",
    "sg:address":"17340 Belsches Rd",
    "sg:city":"Bumpass",
    "sg:classifiers":[
        {
            "category":"Organizations",
            "subcategory":"Religious Organization",
            "type":"Services"
        }
    ],
    "sg:phone":"+1 540 449 6381",
    "sg:postcode":"23024",
    "sg:province":"VA",
    "sg:tags":[
        "church"
    ],
    "wof:name":"Sharon Christian Church",
    "wof:placetype":"venue"
},
  "geometry": {"coordinates":[-77.701668,37.923097],"type":"Point"}
}