{
  "type": "Feature",
  "properties": {
    "iso:country":"US",
    "sg:address":"2138 S Crystal Dr",
    "sg:city":"Arlington",
    "sg:classifiers":[
        {
            "category":"Shopping",
            "subcategory":"Gifts & Souvenirs",
            "type":"Retail Goods"
        }
    ],
    "sg:phone":"+1 703 415 0342",
    "sg:postcode":"22202",
    "sg:province":"VA",
    "wof:name":"Off The Wall",
    "wof:placetype":"venue"
},
  "geometry": {"coordinates":[-77.04932100000001,38.85459],"type":"Point"}
}