{
  "type": "Feature",
  "properties": {
    "iso:country":"US",
    "sg:address":"1727 Rhoadmiller St",
    "sg:city":"Richmond",
    "sg:classifiers":[
        {
            "category":"Home & Garden",
            "subcategory":"Building Materials",
            "type":"Retail Goods"
        }
    ],
    "sg:phone":"+1 804 355 4354",
    "sg:postcode":"23220",
    "sg:province":"VA",
    "wof:name":"Jed Leonard Commercial Hdwr",
    "wof:placetype":"venue"
},
  "geometry": {"coordinates":[-77.46203199999999,37.566646],"type":"Point"}
}