{
  "type": "Feature",
  "properties": {
    "addr:full":"1300 E Main St Richmond VA 23219",
    "addr:housenumber":"1300",
    "addr:postcode":"23219",
    "addr:street":"E Main St",
    "iso:country":"US",
    "sg:address":"1300 E Main St",
    "sg:city":"Richmond",
    "sg:classifiers":[
        {
            "category":"Government",
            "subcategory":"Office",
            "type":"Public Place"
        }
    ],
    "sg:phone":"+1 804 371 9741",
    "sg:postcode":"23219",
    "sg:province":"VA",
    "sg:tags":[
        "executive"
    ],
    "wof:name":"Bureau of Insurance",
    "wof:placetype":"venue"
},
  "geometry": {"coordinates":[-77.432006,37.535595],"type":"Point"}
}