{
  "type": "Feature",
  "properties": {
    "iso:country":"US",
    "sg:address":"4212 Brambleton Ave",
    "sg:city":"Roanoke",
    "sg:classifiers":[
        {
            "category":"Shopping",
            "subcategory":"Musical Instruments",
            "type":"Retail Goods"
        }
    ],
    "sg:phone":"+1 540 989 8777",
    "sg:postcode":"24018",
    "sg:province":"VA",
    "wof:name":"Bandroom The",
    "wof:placetype":"venue"
},
  "geometry": {"coordinates":[-80.009258,37.228499],"type":"Point"}
}