{
  "type": "Feature",
  "properties": {
    "iso:country":"US",
    "sg:address":"2339 W Grace St",
    "sg:city":"Richmond",
    "sg:classifiers":[
        {
            "category":"Banks & Credit Unions",
            "subcategory":"Bank",
            "type":"Services"
        }
    ],
    "sg:phone":"+1 804 301 9371",
    "sg:postcode":"23220",
    "sg:province":"VA",
    "sg:tags":[
        "mortgage"
    ],
    "wof:name":"Toddwater Home Mortgage Group",
    "wof:placetype":"venue"
},
  "geometry": {"coordinates":[-77.466393,37.558836],"type":"Point"}
}