{
  "type": "Feature",
  "properties": {
    "addr:full":"2605 Riverside Dr Danville VA 24540",
    "addr:housenumber":"2605",
    "addr:postcode":"24540",
    "addr:street":"Riverside Dr",
    "iso:country":"US",
    "sg:address":"2605 Riverside Dr",
    "sg:city":"Danville",
    "sg:classifiers":[
        {
            "category":"Autos & Motor Vehicles",
            "subcategory":"Auto Supplies",
            "type":"Retail Goods"
        }
    ],
    "sg:phone":"+1 434 792 3066",
    "sg:postcode":"24540",
    "sg:province":"VA",
    "sg:tags":[
        "tire"
    ],
    "wof:name":"Crane Tire Co & Automotive Ctr",
    "wof:placetype":"venue"
},
  "geometry": {"coordinates":[-79.414131,36.593191],"type":"Point"}
}