{
  "type": "Feature",
  "properties": {
    "addr:full":"1604 Independence Blvd Virginia Beach VA 23455",
    "addr:housenumber":"1604",
    "addr:postcode":"23455",
    "addr:street":"Independence Blvd",
    "iso:country":"US",
    "sg:address":"1604 Independence Blvd",
    "sg:city":"Virginia Beach",
    "sg:classifiers":[
        {
            "category":"Recreation",
            "type":"Entertainment"
        }
    ],
    "sg:phone":"+1 757 460 2178",
    "sg:postcode":"23455",
    "sg:province":"VA",
    "wof:name":"Mrs Sophia Egyptian Reader",
    "wof:placetype":"venue"
},
  "geometry": {"coordinates":[-76.138707,36.891107],"type":"Point"}
}