{
  "type": "Feature",
  "properties": {
    "addr:full":"7140 Mechanicsville Tpke Mechanicsville VA 23111",
    "addr:postcode":"7140;23111",
    "addr:street":"Tpke",
    "iso:country":"US",
    "sg:address":"7140 Mechanicsville Tpke",
    "sg:city":"Mechanicsville",
    "sg:classifiers":[
        {
            "category":"Restaurant",
            "type":"Food & Drink"
        }
    ],
    "sg:phone":"+1 804 569 0411",
    "sg:postcode":"23111",
    "sg:province":"VA",
    "wof:name":"Joe's Out Mechanicsville",
    "wof:placetype":"venue"
},
  "geometry": {"coordinates":[-77.34594199999999,37.61107],"type":"Point"}
}