{
  "type": "Feature",
  "properties": {
    "addr:full":"102 E Main St Marion VA 24354",
    "addr:housenumber":"102",
    "addr:postcode":"24354",
    "addr:street":"E Main St",
    "iso:country":"US",
    "sg:address":"102 E Main St",
    "sg:city":"Marion",
    "sg:classifiers":[
        {
            "category":"Banks & Credit Unions",
            "subcategory":"Bank",
            "type":"Services"
        }
    ],
    "sg:phone":"+1 276 783 7141",
    "sg:postcode":"24354",
    "sg:province":"VA",
    "wof:name":"Wachovia Bank",
    "wof:placetype":"venue"
},
  "geometry": {"coordinates":[-81.51951099999999,36.8329],"type":"Point"}
}