{
  "type": "Feature",
  "properties": {
    "addr:full":"10317 W Broad St Glen Allen VA 23060",
    "addr:housenumber":"10317",
    "addr:postcode":"23060",
    "addr:street":"W Broad St",
    "iso:country":"US",
    "sg:address":"10317 W Broad St",
    "sg:city":"Glen Allen",
    "sg:classifiers":[
        {
            "category":"Professional",
            "subcategory":"Business Services",
            "type":"Services"
        }
    ],
    "sg:phone":"+1 804 527 1800",
    "sg:postcode":"23060",
    "sg:province":"VA",
    "wof:name":"Be Dazzled",
    "wof:placetype":"venue"
},
  "geometry": {"coordinates":[-77.575357,37.645762],"type":"Point"}
}