{
  "type": "Feature",
  "properties": {
    "addr:full":"11301 Edgewood Farm Ct Richmond VA 23233",
    "addr:housenumber":"11301",
    "addr:postcode":"23233",
    "addr:street":"Edgewood Farm Ct",
    "iso:country":"US",
    "sg:address":"11301 Edgewood Farm Ct",
    "sg:city":"Richmond",
    "sg:classifiers":[
        {
            "category":"Insurance",
            "subcategory":"Insurance Agent",
            "type":"Services"
        }
    ],
    "sg:phone":"+1 804 673 9700",
    "sg:postcode":"23233",
    "sg:province":"VA",
    "wof:name":"Jump Start Gis",
    "wof:placetype":"venue"
},
  "geometry": {"coordinates":[-77.597956,37.639226],"type":"Point"}
}