{
  "type": "Feature",
  "properties": {
    "addr:full":"5675 Pageland Ln Gainesville VA 20155",
    "addr:housenumber":"5675",
    "addr:postcode":"20155",
    "addr:street":"Pageland Ln",
    "iso:country":"US",
    "sg:address":"5675 Pageland Ln",
    "sg:city":"Gainesville",
    "sg:classifiers":[
        {
            "category":"Wholesale",
            "subcategory":"Hardware",
            "type":"Manufacturing & Wholesale Goods"
        }
    ],
    "sg:phone":"+1 703 754 8788",
    "sg:postcode":"20155",
    "sg:province":"VA",
    "sg:tags":[
        "fastener"
    ],
    "wof:name":"Dulles Industrial Sales",
    "wof:placetype":"venue"
},
  "geometry": {"coordinates":[-77.570975,38.834176],"type":"Point"}
}