{
  "type": "Feature",
  "properties": {
    "addr:full":"520 Meadowview Dr Danville VA 24541",
    "addr:housenumber":"520",
    "addr:postcode":"24541",
    "addr:street":"Meadowview Dr",
    "iso:country":"US",
    "sg:address":"520 Meadowview Dr",
    "sg:city":"Danville",
    "sg:classifiers":[
        {
            "category":"Retail",
            "subcategory":"Funeral Services",
            "type":"Services"
        }
    ],
    "sg:phone":"+1 434 685 3288",
    "sg:postcode":"24541",
    "sg:province":"VA",
    "wof:name":"Sammy Cox Home Improvemen",
    "wof:placetype":"venue"
},
  "geometry": {"coordinates":[-79.52757699999999,36.604891],"type":"Point"}
}