{
  "type": "Feature",
  "properties": {
    "iso:country":"US",
    "sg:address":"171 Algonquin Rd",
    "sg:city":"Hampton",
    "sg:classifiers":[
        {
            "category":"Professional",
            "subcategory":"Business Services",
            "type":"Services"
        }
    ],
    "sg:phone":"+1 757 825 7282",
    "sg:postcode":"23661",
    "sg:province":"VA",
    "wof:name":"Rotunda Assocs",
    "wof:placetype":"venue"
},
  "geometry": {"coordinates":[-76.364904,37.005535],"type":"Point"}
}