{
  "type": "Feature",
  "properties": {
    "addr:full":"1175 Huntover Ct Mc Lean VA 22102",
    "addr:housenumber":"1175",
    "addr:postcode":"22102",
    "addr:street":"Huntover Ct Mc Lean",
    "iso:country":"US",
    "sg:address":"1175 Huntover Ct",
    "sg:city":"Mc Lean",
    "sg:classifiers":[
        {
            "category":"Professional",
            "type":"Services"
        }
    ],
    "sg:phone":"+1 703 760 4998",
    "sg:postcode":"22102",
    "sg:province":"VA",
    "sg:tags":[
        "journalist"
    ],
    "wof:name":"Frank S Folwell",
    "wof:placetype":"venue"
},
  "geometry": {"coordinates":[-77.211477,38.944185],"type":"Point"}
}