{
  "type": "Feature",
  "properties": {
    "iso:country":"US",
    "sg:address":"425 Woodbridge Dr",
    "sg:city":"Chesapeake",
    "sg:classifiers":[
        {
            "category":"Professional",
            "subcategory":"Computer Services",
            "type":"Services"
        }
    ],
    "sg:phone":"+1 757 547 0492",
    "sg:postcode":"23322",
    "sg:province":"VA",
    "sg:tags":[
        "prepackaged",
        "software"
    ],
    "wof:name":"Computer Software Consultant",
    "wof:placetype":"venue"
},
  "geometry": {"coordinates":[-76.25232099999999,36.703212],"type":"Point"}
}