{
  "type": "Feature",
  "properties": {
    "iso:country":"US",
    "sg:address":"2104 Salem Ave SW",
    "sg:city":"Roanoke",
    "sg:classifiers":[
        {
            "category":"Autos & Motor Vehicles",
            "subcategory":"Automobile Sales",
            "type":"Retail Goods"
        }
    ],
    "sg:phone":"+1 540 344 6051",
    "sg:postcode":"24016",
    "sg:province":"VA",
    "sg:tags":[
        "used"
    ],
    "wof:name":"Bolling Motors LLC",
    "wof:placetype":"venue"
},
  "geometry": {"coordinates":[-79.97506,37.276955],"type":"Point"}
}