{
  "type": "Feature",
  "properties": {
    "addr:full":"219 Nor-Dan Dr Danville VA 24540",
    "addr:housenumber":"219",
    "addr:postcode":"24540",
    "addr:street":"Nor-Dan Dr",
    "iso:country":"US",
    "sg:address":"219 Nor-Dan Dr",
    "sg:city":"Danville",
    "sg:classifiers":[
        {
            "category":"Sports & Exercise",
            "subcategory":"Gym",
            "type":"Entertainment"
        }
    ],
    "sg:phone":"+1 434 836 6155",
    "sg:postcode":"24540",
    "sg:province":"VA",
    "sg:tags":[
        "club",
        "health",
        "studio",
        "gymnasium"
    ],
    "wof:name":"Fitness First",
    "wof:placetype":"venue"
},
  "geometry": {"coordinates":[-79.397397,36.626587],"type":"Point"}
}