{
  "type": "Feature",
  "properties": {
    "addr:full":"206 Sweetbriar Dr Richmond VA 23238",
    "addr:housenumber":"206",
    "addr:postcode":"23238",
    "addr:street":"Sweetbriar Dr",
    "iso:country":"US",
    "sg:address":"206 Sweetbriar Dr",
    "sg:city":"Richmond",
    "sg:classifiers":[
        {
            "category":"Manufacturing",
            "subcategory":"Printing",
            "type":"Manufacturing & Wholesale Goods"
        }
    ],
    "sg:phone":"+1 804 784 3677",
    "sg:postcode":"23238",
    "sg:province":"VA",
    "sg:tags":[
        "engineering",
        "book"
    ],
    "wof:name":"Cpe Corp Inc",
    "wof:placetype":"venue"
},
  "geometry": {"coordinates":[-77.66259100000001,37.576195],"type":"Point"}
}