{
  "type": "Feature",
  "properties": {
    "addr:full":"18029 Brandy Rd Culpeper VA 22701",
    "addr:housenumber":"18029",
    "addr:postcode":"22701",
    "addr:street":"Brandy Rd",
    "iso:country":"US",
    "sg:address":"18029 Brandy Rd",
    "sg:city":"Culpeper",
    "sg:classifiers":[
        {
            "category":"Organizations",
            "subcategory":"Religious Organization",
            "type":"Services"
        }
    ],
    "sg:phone":"+1 540 825 5689",
    "sg:postcode":"22701",
    "sg:province":"VA",
    "wof:name":"Lena B McDonald Rev",
    "wof:placetype":"venue"
},
  "geometry": {"coordinates":[-77.92076900000001,38.493905],"type":"Point"}
}