{
  "type": "Feature",
  "properties": {
    "addr:full":"10710 Midlothian Tpke Ste 101 Richmond VA 23235",
    "addr:housenumber":"10710",
    "addr:postcode":"23235",
    "addr:street":"Midlothian Tpke Ste 101",
    "iso:country":"US",
    "sg:address":"10710 Midlothian Tpke Ste 101",
    "sg:city":"Richmond",
    "sg:classifiers":[
        {
            "category":"Health Services",
            "subcategory":"Clinic",
            "type":"Services"
        },
        {
            "category":"Health Services",
            "subcategory":"Medical Lab",
            "type":"Services"
        }
    ],
    "sg:phone":"+1 866 570 8589",
    "sg:postcode":"23235",
    "sg:province":"VA",
    "sg:tags":[
        "information",
        "aid",
        "welfare"
    ],
    "sg:website":"http://richmond.citysearch.com/profile/external/603490142/richmond_va/std_test_express_richmond.html?publisher=yellowpages&reference_id=1&placement=ypwebsitemip",
    "wof:name":"STD Test Express Richmond",
    "wof:placetype":"venue"
},
  "geometry": {"coordinates":[-77.59419200000001,37.50707],"type":"Point"}
}