{
  "type": "Feature",
  "properties": {
    "addr:full":"5942 Atteentee Rd Springfield VA 22150",
    "addr:housenumber":"5942",
    "addr:postcode":"22150",
    "addr:street":"Atteentee Rd",
    "iso:country":"US",
    "sg:address":"5942 Atteentee Rd",
    "sg:city":"Springfield",
    "sg:classifiers":[
        {
            "category":"Professional",
            "subcategory":"Business Services",
            "type":"Services"
        }
    ],
    "sg:phone":"+1 703 451 4295",
    "sg:postcode":"22150",
    "sg:province":"VA",
    "wof:name":"Stone House Interiors LLC",
    "wof:placetype":"venue"
},
  "geometry": {"coordinates":[-77.203568,38.788584],"type":"Point"}
}