{
  "type": "Feature",
  "properties": {
    "addr:full":"929 Bethel Ln Martinsville VA 24112",
    "addr:housenumber":"929",
    "addr:postcode":"24112",
    "addr:street":"Bethel Ln",
    "iso:country":"US",
    "sg:address":"929 Bethel Ln",
    "sg:city":"Martinsville",
    "sg:classifiers":[
        {
            "category":"Organizations",
            "subcategory":"Religious Organization",
            "type":"Services"
        }
    ],
    "sg:phone":"+1 276 632 6641",
    "sg:postcode":"24112",
    "sg:province":"VA",
    "sg:tags":[
        "church"
    ],
    "wof:name":"New Bethel Holiness Church",
    "wof:placetype":"venue"
},
  "geometry": {"coordinates":[-79.855909,36.698801],"type":"Point"}
}