{
  "type": "Feature",
  "properties": {
    "addr:full":"35 E Main St Salem VA 24153",
    "addr:housenumber":"35",
    "addr:postcode":"24153",
    "addr:street":"E Main St",
    "iso:country":"US",
    "sg:address":"35 E Main St",
    "sg:city":"Salem",
    "sg:classifiers":[
        {
            "category":"Food & Beverages",
            "subcategory":"Specialty",
            "type":"Retail Goods"
        }
    ],
    "sg:phone":"+1 540 389 9583",
    "sg:postcode":"24153",
    "sg:province":"VA",
    "sg:tags":[
        "health",
        "diet"
    ],
    "wof:name":"Nature's Outlet",
    "wof:placetype":"venue"
},
  "geometry": {"coordinates":[-80.056854,37.293055],"type":"Point"}
}