{
  "type": "Feature",
  "properties": {
    "addr:full":"5601 Cavalier Woods Ln Clifton VA 20124",
    "addr:housenumber":"5601",
    "addr:postcode":"20124",
    "addr:street":"Cavalier Woods Ln",
    "iso:country":"US",
    "sg:address":"5601 Cavalier Woods Ln",
    "sg:city":"Clifton",
    "sg:classifiers":[
        {
            "category":"Banks & Credit Unions",
            "subcategory":"Financial Services",
            "type":"Services"
        }
    ],
    "sg:phone":"+1 703 968 7117",
    "sg:postcode":"20124",
    "sg:province":"VA",
    "sg:tags":[
        "trust",
        "investment",
        "real estate"
    ],
    "wof:name":"Wizard Ventures LLC",
    "wof:placetype":"venue"
},
  "geometry": {"coordinates":[-77.410754,38.835381],"type":"Point"}
}