{
  "type": "Feature",
  "properties": {
    "addr:full":"41882 Tutt Ln Leesburg VA 20176",
    "addr:housenumber":"41882",
    "addr:postcode":"20176",
    "addr:street":"Tutt Ln",
    "iso:country":"US",
    "sg:address":"41882 Tutt Ln",
    "sg:city":"Leesburg",
    "sg:classifiers":[
        {
            "category":"Shopping",
            "subcategory":"Computers & Home Electronics",
            "type":"Retail Goods"
        }
    ],
    "sg:phone":"+1 703 777 3211",
    "sg:postcode":"20176",
    "sg:province":"VA",
    "sg:tags":[
        "software"
    ],
    "wof:name":"Knowledge Based Simulations",
    "wof:placetype":"venue"
},
  "geometry": {"coordinates":[-77.553555,39.144791],"type":"Point"}
}