{
  "type": "Feature",
  "properties": {
    "addr:full":"4320 Dulaney St Quantico VA 22134",
    "addr:housenumber":"4320",
    "addr:postcode":"22134",
    "addr:street":"Dulaney St",
    "iso:country":"US",
    "sg:address":"4320 Dulaney St",
    "sg:city":"Quantico",
    "sg:classifiers":[
        {
            "category":"Building & Trades",
            "subcategory":"Construction",
            "type":"Services"
        }
    ],
    "sg:phone":"+1 703 221 0229",
    "sg:postcode":"22134",
    "sg:province":"VA",
    "sg:tags":[
        "contractor"
    ],
    "wof:name":"Biscayne Contractors",
    "wof:placetype":"venue"
},
  "geometry": {"coordinates":[-77.34445100000001,38.527962],"type":"Point"}
}