{
  "type": "Feature",
  "properties": {
    "addr:full":"2324 Woodhurst Ln Chesapeake VA 23322",
    "addr:housenumber":"2324",
    "addr:postcode":"23322",
    "addr:street":"Woodhurst Ln",
    "iso:country":"US",
    "sg:address":"2324 Woodhurst Ln",
    "sg:city":"Chesapeake",
    "sg:classifiers":[
        {
            "category":"Health Services",
            "subcategory":"Optometrist",
            "type":"Services"
        }
    ],
    "sg:phone":"+1 757 421 2374",
    "sg:postcode":"23322",
    "sg:province":"VA",
    "wof:name":"Celeste Lewis",
    "wof:placetype":"venue"
},
  "geometry": {"coordinates":[-76.34537899999999,36.63719],"type":"Point"}
}