{
  "type": "Feature",
  "properties": {
    "addr:full":"25 Herbert St Alexandria VA 22305",
    "addr:housenumber":"25",
    "addr:postcode":"22305",
    "addr:street":"Herbert St",
    "iso:country":"US",
    "sg:address":"25 Herbert St",
    "sg:city":"Alexandria",
    "sg:classifiers":[
        {
            "category":"Communications",
            "subcategory":"Film & Video Production",
            "type":"Services"
        }
    ],
    "sg:phone":"+1 202 321 1069",
    "sg:postcode":"22305",
    "sg:province":"VA",
    "sg:tags":[
        "television"
    ],
    "wof:name":"Laura Foran",
    "wof:placetype":"venue"
},
  "geometry": {"coordinates":[-77.05969,38.834518],"type":"Point"}
}