{
  "type": "Feature",
  "properties": {
    "addr:full":"431 W Main St Covington VA 24426",
    "addr:housenumber":"431",
    "addr:postcode":"24426",
    "addr:street":"W Main St",
    "iso:country":"US",
    "sg:address":"431 W Main St",
    "sg:city":"Covington",
    "sg:classifiers":[
        {
            "category":"Insurance",
            "subcategory":"Life Insurance",
            "type":"Services"
        }
    ],
    "sg:phone":"+1 540 962 2241",
    "sg:postcode":"24426",
    "sg:province":"VA",
    "sg:tags":[
        "carrier"
    ],
    "wof:name":"GE",
    "wof:placetype":"venue"
},
  "geometry": {"coordinates":[-79.997257,37.791051],"type":"Point"}
}