{
  "type": "Feature",
  "properties": {
    "iso:country":"US",
    "sg:address":"11551 Nuckols Rd",
    "sg:city":"Glen Allen",
    "sg:classifiers":[
        {
            "category":"Real Estate",
            "subcategory":"Real Estate Agent",
            "type":"Services"
        }
    ],
    "sg:phone":"+1 804 290 8866",
    "sg:postcode":"23059",
    "sg:province":"VA",
    "sg:website":"www.longandfoster.com",
    "wof:name":"Long & Foster Realtors",
    "wof:placetype":"venue"
},
  "geometry": {"coordinates":[-77.59406199999999,37.68839],"type":"Point"}
}