{
  "type": "Feature",
  "properties": {
    "addr:full":"12219 Henderson Rd Clifton VA 20124",
    "addr:housenumber":"12219",
    "addr:postcode":"20124",
    "addr:street":"Henderson Rd",
    "iso:country":"US",
    "sg:address":"12219 Henderson Rd",
    "sg:city":"Clifton",
    "sg:classifiers":[
        {
            "category":"Professional",
            "subcategory":"Management & Consulting",
            "type":"Services"
        }
    ],
    "sg:phone":"+1 703 222 0307",
    "sg:postcode":"20124",
    "sg:province":"VA",
    "wof:name":"Cybersophic Inc",
    "wof:placetype":"venue"
},
  "geometry": {"coordinates":[-77.368893,38.741886],"type":"Point"}
}