{
  "type": "Feature",
  "properties": {
    "addr:full":"3405 Waterlick Rd Forest VA 24551",
    "addr:housenumber":"3405",
    "addr:postcode":"24551",
    "addr:street":"Waterlick Rd",
    "iso:country":"US",
    "sg:address":"3405 Waterlick Rd",
    "sg:city":"Forest",
    "sg:classifiers":[
        {
            "category":"Shopping",
            "subcategory":"Used Merchandise",
            "type":"Retail Goods"
        }
    ],
    "sg:phone":"+1 434 237 5366",
    "sg:postcode":"24551",
    "sg:province":"VA",
    "wof:name":"Where Kids Things Are Inc",
    "wof:placetype":"venue"
},
  "geometry": {"coordinates":[-79.248893,37.329986],"type":"Point"}
}