{
  "type": "Feature",
  "properties": {
    "iso:country":"US",
    "sg:address":"10844 Warwick Blvd",
    "sg:city":"Newport News",
    "sg:classifiers":[
        {
            "category":"Home & Garden",
            "subcategory":"Carpets & Floor Coverings",
            "type":"Retail Goods"
        }
    ],
    "sg:phone":"+1 757 595 5777",
    "sg:postcode":"23601",
    "sg:province":"VA",
    "sg:tags":[
        "store"
    ],
    "wof:name":"Dominion Floor Covering",
    "wof:placetype":"venue"
},
  "geometry": {"coordinates":[-76.46763199999999,37.038298],"type":"Point"}
}