{
  "type": "Feature",
  "properties": {
    "addr:full":"8600 Leesburg Pike Vienna VA 22182",
    "addr:housenumber":"8600",
    "addr:postcode":"22182",
    "addr:street":"Leesburg Pike",
    "iso:country":"US",
    "sg:address":"8600 Leesburg Pike",
    "sg:city":"Vienna",
    "sg:classifiers":[
        {
            "category":"Personal",
            "type":"Services"
        }
    ],
    "sg:phone":"+1 703 370 8300",
    "sg:postcode":"22182",
    "sg:province":"VA",
    "sg:tags":[
        "mover"
    ],
    "wof:name":"Federal Moving and Storage",
    "wof:placetype":"venue"
},
  "geometry": {"coordinates":[-77.24340100000001,38.931301],"type":"Point"}
}