{
  "type": "Feature",
  "properties": {
    "iso:country":"US",
    "sg:address":"12105 Drumore Ct",
    "sg:city":"Glen Allen",
    "sg:classifiers":[
        {
            "category":"Professional",
            "subcategory":"Business Services",
            "type":"Services"
        }
    ],
    "sg:phone":"+1 804 360 2728",
    "sg:postcode":"23059",
    "sg:province":"VA",
    "wof:name":"Ana Duo",
    "wof:placetype":"venue"
},
  "geometry": {"coordinates":[-77.61326699999999,37.704793],"type":"Point"}
}