{
  "type": "Feature",
  "properties": {
    "addr:full":"10 Club Ln Palmyra VA 22963",
    "addr:housenumber":"10",
    "addr:postcode":"22963",
    "addr:street":"Club Ln",
    "iso:country":"US",
    "sg:address":"10 Club Ln",
    "sg:city":"Palmyra",
    "sg:classifiers":[
        {
            "category":"Professional",
            "subcategory":"Computer Services",
            "type":"Services"
        }
    ],
    "sg:phone":"+1 434 591 0491",
    "sg:postcode":"22963",
    "sg:province":"VA",
    "sg:tags":[
        "datum"
    ],
    "wof:name":"Gleem",
    "wof:placetype":"venue"
},
  "geometry": {"coordinates":[-78.312583,37.921008],"type":"Point"}
}