{
  "type": "Feature",
  "properties": {
    "addr:full":"2908 Stuart Dr Falls Church VA 22042",
    "addr:housenumber":"2908",
    "addr:postcode":"22042",
    "addr:street":"Stuart Dr",
    "iso:country":"US",
    "sg:address":"2908 Stuart Dr",
    "sg:city":"Falls Church",
    "sg:classifiers":[
        {
            "category":"Food & Beverages",
            "subcategory":"Bakery",
            "type":"Retail Goods"
        }
    ],
    "sg:phone":"+1 703 641 0151",
    "sg:postcode":"22042",
    "sg:province":"VA",
    "sg:website":"www.onceuponacake.com",
    "wof:name":"Once Upon A Cake",
    "wof:placetype":"venue"
},
  "geometry": {"coordinates":[-77.19906899999999,38.872243],"type":"Point"}
}