{
  "type": "Feature",
  "properties": {
    "addr:full":"510 Pegasus Ct Winchester VA 22602",
    "addr:housenumber":"510",
    "addr:postcode":"22602",
    "addr:street":"Pegasus Ct",
    "iso:country":"US",
    "sg:address":"510 Pegasus Ct",
    "sg:city":"Winchester",
    "sg:classifiers":[
        {
            "category":"Professional",
            "subcategory":"Advertising",
            "type":"Services"
        },
        {
            "category":"Communications",
            "subcategory":"Radio Station",
            "type":"Services"
        }
    ],
    "sg:phone":"+1 540 667 9993",
    "sg:postcode":"22602",
    "sg:province":"VA",
    "sg:tags":[
        "broadcast",
        "advertising-broadcast",
        "film"
    ],
    "sg:website":"http://www.khsl.com",
    "wof:name":"Clear Channel Radio",
    "wof:placetype":"venue"
},
  "geometry": {"coordinates":[-78.150454,39.144834],"type":"Point"}
}