{
  "type": "Feature",
  "properties": {
    "addr:full":"1579 Lynnhaven Pkwy Virginia Beach VA 23453",
    "addr:housenumber":"1579",
    "addr:postcode":"23453",
    "addr:street":"Lynnhaven Pkwy",
    "iso:country":"US",
    "sg:address":"1579 Lynnhaven Pkwy",
    "sg:city":"Virginia Beach",
    "sg:classifiers":[
        {
            "category":"Food & Beverages",
            "subcategory":"Groceries & Convenience Stores",
            "type":"Retail Goods"
        }
    ],
    "sg:phone":"+1 757 368 9109",
    "sg:postcode":"23453",
    "sg:province":"VA",
    "wof:name":"Wawa",
    "wof:placetype":"venue"
},
  "geometry": {"coordinates":[-76.100702,36.795566],"type":"Point"}
}