{
  "type": "Feature",
  "properties": {
    "iso:country":"US",
    "sg:address":"7915 Jones Branch Dr",
    "sg:city":"Mc Lean",
    "sg:classifiers":[
        {
            "category":"Professional",
            "subcategory":"Computer Services",
            "type":"Services"
        }
    ],
    "sg:phone":"+1 703 917 4200",
    "sg:postcode":"22102",
    "sg:province":"VA",
    "sg:tags":[
        "security",
        "system"
    ],
    "sg:website":"www.atsintl.com",
    "wof:name":"ATSI",
    "wof:placetype":"venue"
},
  "geometry": {"coordinates":[-77.216537,38.927909],"type":"Point"}
}