{
  "type": "Feature",
  "properties": {
    "addr:full":"1612 Fox Downs Pl Richmond VA 23231",
    "addr:housenumber":"1612",
    "addr:postcode":"23231",
    "addr:street":"Fox Downs Pl",
    "iso:country":"US",
    "sg:address":"1612 Fox Downs Pl",
    "sg:city":"Richmond",
    "sg:classifiers":[
        {
            "category":"Shopping",
            "subcategory":"Gifts & Souvenirs",
            "type":"Retail Goods"
        }
    ],
    "sg:phone":"+1 804 236 1141",
    "sg:postcode":"23231",
    "sg:province":"VA",
    "wof:name":"Adrian Alexander Gifts",
    "wof:placetype":"venue"
},
  "geometry": {"coordinates":[-77.38862899999999,37.485546],"type":"Point"}
}