{
  "type": "Feature",
  "properties": {
    "addr:full":"927 S Walter Reed Dr Arlington VA 22204",
    "addr:housenumber":"927",
    "addr:postcode":"22204",
    "addr:street":"S Walter Reed Dr",
    "iso:country":"US",
    "sg:address":"927 S Walter Reed Dr",
    "sg:city":"Arlington",
    "sg:classifiers":[
        {
            "category":"Professional",
            "type":"Services"
        }
    ],
    "sg:phone":"+1 703 302 5140",
    "sg:postcode":"22204",
    "sg:province":"VA",
    "wof:name":"Bu Gata",
    "wof:placetype":"venue"
},
  "geometry": {"coordinates":[-77.086955,38.862625],"type":"Point"}
}