{
  "type": "Feature",
  "properties": {
    "addr:full":"145 Byrd St Orange VA 22960",
    "addr:housenumber":"145",
    "addr:postcode":"22960",
    "addr:street":"Byrd St",
    "iso:country":"US",
    "sg:address":"145 Byrd St",
    "sg:city":"Orange",
    "sg:classifiers":[
        {
            "category":"Shopping",
            "subcategory":"Gifts & Souvenirs",
            "type":"Retail Goods"
        }
    ],
    "sg:phone":"+1 540 672 3552",
    "sg:postcode":"22960",
    "sg:province":"VA",
    "sg:tags":[
        "shop"
    ],
    "wof:name":"Downtown Gifts",
    "wof:placetype":"venue"
},
  "geometry": {"coordinates":[-78.108395,38.244409],"type":"Point"}
}