{
  "type": "Feature",
  "properties": {
    "addr:full":"69 Cedar Hill Ln Lexington VA 24450",
    "addr:housenumber":"69",
    "addr:postcode":"24450",
    "addr:street":"Cedar Hill Ln",
    "iso:country":"US",
    "sg:address":"69 Cedar Hill Ln",
    "sg:city":"Lexington",
    "sg:classifiers":[
        {
            "category":"Professional",
            "subcategory":"Engineering",
            "type":"Services"
        }
    ],
    "sg:phone":"+1 540 463 6474",
    "sg:postcode":"24450",
    "sg:province":"VA",
    "sg:tags":[
        "engineer"
    ],
    "wof:name":"Mish Engineering Concepts",
    "wof:placetype":"venue"
},
  "geometry": {"coordinates":[-79.400128,37.81881],"type":"Point"}
}