{
  "type": "Feature",
  "properties": {
    "addr:full":"2752 Stoney Battery Rd Troutville VA 24175",
    "addr:housenumber":"2752",
    "addr:postcode":"24175",
    "addr:street":"Stoney Battery Rd",
    "iso:country":"US",
    "sg:address":"2752 Stoney Battery Rd",
    "sg:city":"Troutville",
    "sg:classifiers":[
        {
            "category":"Building & Trades",
            "subcategory":"Plumbing",
            "type":"Services"
        }
    ],
    "sg:phone":"+1 540 992 3963",
    "sg:postcode":"24175",
    "sg:province":"VA",
    "sg:tags":[
        "excavation",
        "contractor"
    ],
    "wof:name":"Cash Excavating",
    "wof:placetype":"venue"
},
  "geometry": {"coordinates":[-79.844015,37.436274],"type":"Point"}
}