{
  "type": "Feature",
  "properties": {
    "addr:full":"9206 Venture Ct Manassas VA 20111",
    "addr:housenumber":"9206",
    "addr:postcode":"20111",
    "addr:street":"Venture Ct",
    "iso:country":"US",
    "sg:address":"9206 Venture Ct",
    "sg:city":"Manassas",
    "sg:classifiers":[
        {
            "category":"Retail",
            "subcategory":"Auto Repair",
            "type":"Services"
        }
    ],
    "sg:phone":"+1 703 335 1796",
    "sg:postcode":"20111",
    "sg:province":"VA",
    "sg:tags":[
        "general"
    ],
    "wof:name":"Roman Auto Repair Inc",
    "wof:placetype":"venue"
},
  "geometry": {"coordinates":[-77.43867400000001,38.770253],"type":"Point"}
}