{
  "type": "Feature",
  "properties": {
    "addr:full":"7420 Fullerton Rd Ste 102 Springfield VA 22153",
    "addr:housenumber":"7420",
    "addr:postcode":"22153",
    "addr:street":"Fullerton Rd Ste 102",
    "iso:country":"US",
    "sg:address":"7420 Fullerton Rd Ste 102",
    "sg:city":"Springfield",
    "sg:classifiers":[
        {
            "category":"Home & Garden",
            "subcategory":"Building Materials",
            "type":"Retail Goods"
        },
        {
            "category":"Home & Garden",
            "subcategory":"Furniture",
            "type":"Retail Goods"
        }
    ],
    "sg:phone":"+1 703 644 9677",
    "sg:postcode":"22153",
    "sg:province":"VA",
    "sg:tags":[
        "equipment-household",
        "kitchen",
        "cabinet"
    ],
    "sg:website":"http://www.cai-cabinets.com",
    "wof:name":"Counterworks",
    "wof:placetype":"venue"
},
  "geometry": {"coordinates":[-77.199287,38.741402],"type":"Point"}
}