{
  "type": "Feature",
  "properties": {
    "addr:full":"12332 Chickasaw Ct Woodbridge VA 22192",
    "addr:housenumber":"12332",
    "addr:postcode":"22192",
    "addr:street":"Chickasaw Ct",
    "iso:country":"US",
    "sg:address":"12332 Chickasaw Ct",
    "sg:city":"Woodbridge",
    "sg:classifiers":[
        {
            "category":"Building & Trades",
            "subcategory":"Construction",
            "type":"Services"
        }
    ],
    "sg:phone":"+1 703 932 6468",
    "sg:postcode":"22192",
    "sg:province":"VA",
    "sg:tags":[
        "paving",
        "road",
        "contractor"
    ],
    "wof:name":"A&L Construction Specialties, Inc.",
    "wof:placetype":"venue"
},
  "geometry": {"coordinates":[-77.300799,38.686452],"type":"Point"}
}