{
  "type": "Feature",
  "properties": {
    "addr:full":"3318 Virginia St Exmore VA 23350",
    "addr:housenumber":"3318",
    "addr:postcode":"23350",
    "addr:street":"Virginia St",
    "iso:country":"US",
    "sg:address":"3318 Virginia St",
    "sg:city":"Exmore",
    "sg:classifiers":[
        {
            "category":"Shopping",
            "subcategory":"Hobbies, Toys, & Games",
            "type":"Retail Goods"
        }
    ],
    "sg:phone":"+1 757 414 0316",
    "sg:postcode":"23350",
    "sg:province":"VA",
    "sg:tags":[
        "supply"
    ],
    "wof:name":"Game Over",
    "wof:placetype":"venue"
},
  "geometry": {"coordinates":[-75.81567699999999,37.531652],"type":"Point"}
}