{
  "type": "Feature",
  "properties": {
    "iso:country":"US",
    "sg:address":"6121 Lincolnia Rd",
    "sg:city":"Alexandria",
    "sg:classifiers":[
        {
            "category":"Professional",
            "type":"Services"
        },
        {
            "category":"Professional",
            "subcategory":"Management & Consulting",
            "type":"Services"
        }
    ],
    "sg:phone":"+1 703 642 2380",
    "sg:postcode":"22312",
    "sg:province":"VA",
    "sg:tags":[
        "scientist",
        "business"
    ],
    "sg:website":"www.lochharbourgroup.com",
    "wof:name":"Loch Harbour Group Inc",
    "wof:placetype":"venue"
},
  "geometry": {"coordinates":[-77.13580399999999,38.818381],"type":"Point"}
}