{
  "type": "Feature",
  "properties": {
    "addr:full":"45195 Business Ct Sterling VA 20166",
    "addr:housenumber":"45195",
    "addr:postcode":"20166",
    "addr:street":"Business Ct",
    "iso:country":"US",
    "sg:address":"45195 Business Ct",
    "sg:city":"Sterling",
    "sg:classifiers":[
        {
            "category":"Professional",
            "subcategory":"Management & Consulting",
            "type":"Services"
        }
    ],
    "sg:phone":"+1 703 481 8115",
    "sg:postcode":"20166",
    "sg:province":"VA",
    "sg:tags":[
        "development",
        "company"
    ],
    "wof:name":"Bramelton Group LLC",
    "wof:placetype":"venue"
},
  "geometry": {"coordinates":[-77.43705199999999,38.98098],"type":"Point"}
}