{
  "type": "Feature",
  "properties": {
    "iso:country":"US",
    "sg:address":"16400 New Kent Hwy",
    "sg:city":"Lanexa",
    "sg:classifiers":[
        {
            "category":"Building & Trades",
            "subcategory":"Construction",
            "type":"Services"
        }
    ],
    "sg:phone":"+1 804 843 3517",
    "sg:postcode":"23089",
    "sg:province":"VA",
    "sg:tags":[
        "house"
    ],
    "wof:name":"Seeterlin Const Co",
    "wof:placetype":"venue"
},
  "geometry": {"coordinates":[-76.88592199999999,37.502414],"type":"Point"}
}