{
  "type": "Feature",
  "properties": {
    "iso:country":"US",
    "sg:address":"608 Hillview Pl SW",
    "sg:city":"Leesburg",
    "sg:classifiers":[
        {
            "category":"Local Transit",
            "type":"Transportation"
        }
    ],
    "sg:phone":"+1 703 779 8598",
    "sg:postcode":"20175",
    "sg:province":"VA",
    "sg:tags":[
        "passenger"
    ],
    "wof:name":"1st Class Limousine Corp",
    "wof:placetype":"venue"
},
  "geometry": {"coordinates":[-77.601755,39.089787],"type":"Point"}
}