{
  "type": "Feature",
  "properties": {
    "iso:country":"US",
    "sg:address":"2576 Nicky Ln",
    "sg:city":"Alexandria",
    "sg:classifiers":[
        {
            "category":"Social Services",
            "type":"Services"
        }
    ],
    "sg:phone":"+1 703 931 3922",
    "sg:postcode":"22311",
    "sg:province":"VA",
    "wof:name":"Institute For Care Givers Educ",
    "wof:placetype":"venue"
},
  "geometry": {"coordinates":[-77.121504,38.834796],"type":"Point"}
}