{
  "type": "Feature",
  "properties": {
    "iso:country":"US",
    "sg:address":"1114 Tanbark Dr",
    "sg:city":"Afton",
    "sg:classifiers":[
        {
            "category":"Building & Trades",
            "subcategory":"Construction",
            "type":"Services"
        },
        {
            "category":"Building & Trades",
            "subcategory":"Landscaping Services",
            "type":"Services"
        }
    ],
    "sg:phone":"+1 540 456 8116",
    "sg:postcode":"22920",
    "sg:province":"VA",
    "sg:tags":[
        "house",
        "landscape",
        "contractor"
    ],
    "wof:name":"Dan's Landscapades",
    "wof:placetype":"venue"
},
  "geometry": {"coordinates":[-78.845665,38.0006],"type":"Point"}
}