{
  "type": "Feature",
  "properties": {
    "addr:full":"600 Wolfe St Alexandria VA 22314",
    "addr:housenumber":"600",
    "addr:postcode":"22314",
    "addr:street":"Wolfe St",
    "iso:country":"US",
    "sg:address":"600 Wolfe St",
    "sg:city":"Alexandria",
    "sg:classifiers":[
        {
            "category":"Arts & Performance",
            "subcategory":"Theater",
            "type":"Entertainment"
        }
    ],
    "sg:phone":"+1 703 683 5778",
    "sg:postcode":"22314",
    "sg:province":"VA",
    "sg:tags":[
        "theatrical"
    ],
    "sg:website":"www.thelittletheatre.com",
    "wof:name":"Little Theatre Of Alexandria",
    "wof:placetype":"venue"
},
  "geometry": {"coordinates":[-77.047709,38.801635],"type":"Point"}
}