{
  "type": "Feature",
  "properties": {
    "addr:full":"445 Jefferson Davis Hwy Fredericksburg VA 22401",
    "addr:housenumber":"445",
    "addr:postcode":"22401",
    "addr:street":"Jefferson Davis Hwy",
    "iso:country":"US",
    "sg:address":"445 Jefferson Davis Hwy",
    "sg:city":"Fredericksburg",
    "sg:classifiers":[
        {
            "category":"Restaurant",
            "type":"Food & Drink"
        }
    ],
    "sg:phone":"+1 540 368 0550",
    "sg:postcode":"22401",
    "sg:province":"VA",
    "wof:name":"Royale Restaurant",
    "wof:placetype":"venue"
},
  "geometry": {"coordinates":[-77.47428499999999,38.315083],"type":"Point"}
}