{
  "type": "Feature",
  "properties": {
    "iso:country":"US",
    "sg:address":"14691 Deepwood Ln",
    "sg:city":"Nokesville",
    "sg:classifiers":[
        {
            "category":"Professional",
            "subcategory":"Computer Services",
            "type":"Services"
        }
    ],
    "sg:phone":"+1 703 627 9952",
    "sg:postcode":"20181",
    "sg:province":"VA",
    "sg:tags":[
        "design",
        "system"
    ],
    "wof:name":"Enterprise Ntwrk Sltons Prvder",
    "wof:placetype":"venue"
},
  "geometry": {"coordinates":[-77.535954,38.632303],"type":"Point"}
}