{
  "type": "Feature",
  "properties": {
    "iso:country":"US",
    "sg:address":"106 Featherbed Ln",
    "sg:city":"Winchester",
    "sg:classifiers":[
        {
            "category":"Shopping",
            "subcategory":"Books",
            "type":"Retail Goods"
        }
    ],
    "sg:phone":"+1 540 665 0866",
    "sg:postcode":"22601",
    "sg:province":"VA",
    "sg:tags":[
        "used",
        "merchandise"
    ],
    "wof:name":"Book Shelf The Inc",
    "wof:placetype":"venue"
},
  "geometry": {"coordinates":[-78.169562,39.165019],"type":"Point"}
}