{
  "type": "Feature",
  "properties": {
    "iso:country":"US",
    "sg:address":"1400 Crossways Blvd",
    "sg:city":"Chesapeake",
    "sg:classifiers":[
        {
            "category":"Health Services",
            "subcategory":"Clinic",
            "type":"Services"
        }
    ],
    "sg:phone":"+1 757 523 0666",
    "sg:postcode":"23320",
    "sg:province":"VA",
    "sg:tags":[
        "kidney",
        "dialysis",
        "center"
    ],
    "wof:name":"Cheapeake Dialysis",
    "wof:placetype":"venue"
},
  "geometry": {"coordinates":[-76.244646,36.771429],"type":"Point"}
}