{
  "type": "Feature",
  "properties": {
    "iso:country":"US",
    "sg:address":"8329 Shady Grove Cir",
    "sg:city":"Manassas",
    "sg:classifiers":[
        {
            "category":"Building & Trades",
            "subcategory":"Construction",
            "type":"Services"
        }
    ],
    "sg:phone":"+1 703 530 0611",
    "sg:postcode":"20110",
    "sg:province":"VA",
    "sg:tags":[
        "house"
    ],
    "wof:name":"Pena Bustillo Construction",
    "wof:placetype":"venue"
},
  "geometry": {"coordinates":[-77.471272,38.776967],"type":"Point"}
}