{
  "type": "Feature",
  "properties": {
    "iso:country":"US",
    "sg:address":"4295 Sears Country Rd",
    "sg:city":"Zanoni",
    "sg:classifiers":[
        {
            "category":"Home & Garden",
            "subcategory":"Building Materials",
            "type":"Retail Goods"
        }
    ],
    "sg:phone":"+1 804 694 4552",
    "sg:postcode":"23061",
    "sg:province":"VA",
    "sg:tags":[
        "glass",
        "window",
        "plate"
    ],
    "wof:name":"Binswanger Glass Co",
    "wof:placetype":"venue"
},
  "geometry": {"coordinates":[-76.603995,37.457732],"type":"Point"}
}