{
  "type": "Feature",
  "properties": {
    "iso:country":"US",
    "sg:address":"6300 Pewter Ave",
    "sg:city":"Richmond",
    "sg:classifiers":[
        {
            "category":"Real Estate",
            "subcategory":"Real Estate Operator",
            "type":"Services"
        }
    ],
    "sg:phone":"+1 804 276 6911",
    "sg:postcode":"23224",
    "sg:province":"VA",
    "sg:tags":[
        "apartment"
    ],
    "wof:name":"Rollingwood Apartments",
    "wof:placetype":"venue"
},
  "geometry": {"coordinates":[-77.51202499999999,37.464656],"type":"Point"}
}