{
  "type": "Feature",
  "properties": {
    "addr:full":"212 82nd St Virginia Beach VA 23451",
    "addr:housenumber":"212",
    "addr:postcode":"23451",
    "addr:street":"82Nd St",
    "iso:country":"US",
    "sg:address":"212 82nd St",
    "sg:city":"Virginia Beach",
    "sg:classifiers":[
        {
            "category":"Real Estate",
            "subcategory":"Real Estate Agent",
            "type":"Services"
        }
    ],
    "sg:phone":"+1 757 422 8177",
    "sg:postcode":"23451",
    "sg:province":"VA",
    "wof:name":"Ken Olive Real Estate",
    "wof:placetype":"venue"
},
  "geometry": {"coordinates":[-75.991968,36.907193],"type":"Point"}
}