{
  "type": "Feature",
  "properties": {
    "iso:country":"US",
    "sg:address":"5750 Union Mill Rd",
    "sg:city":"Clifton",
    "sg:classifiers":[
        {
            "category":"Shopping",
            "subcategory":"Bicycles & Sporting Goods",
            "type":"Retail Goods"
        }
    ],
    "sg:phone":"+1 703 266 8677",
    "sg:postcode":"20124",
    "sg:province":"VA",
    "wof:name":"Clifton Play It Again Sports",
    "wof:placetype":"venue"
},
  "geometry": {"coordinates":[-77.41175200000001,38.83313],"type":"Point"}
}