{
  "type": "Feature",
  "properties": {
    "addr:full":"1277 Jefferson Davis Hwy Fredericksburg VA 22401",
    "addr:housenumber":"1277",
    "addr:postcode":"22401",
    "addr:street":"Jefferson Davis Hwy",
    "iso:country":"US",
    "sg:address":"1277 Jefferson Davis Hwy",
    "sg:city":"Fredericksburg",
    "sg:classifiers":[
        {
            "category":"Personal",
            "subcategory":"Tanning Parlor",
            "type":"Services"
        },
        {
            "category":"Personal",
            "type":"Services"
        }
    ],
    "sg:phone":"+1 540 371 7566",
    "sg:postcode":"22401",
    "sg:province":"VA",
    "sg:tags":[
        "salon"
    ],
    "wof:name":"Apollo II Tanning Salons",
    "wof:placetype":"venue"
},
  "geometry": {"coordinates":[-77.480136,38.305942],"type":"Point"}
}