{
  "type": "Feature",
  "properties": {
    "addr:full":"9201 Prescott Ave Manassas VA 20110",
    "addr:housenumber":"9201",
    "addr:postcode":"20110",
    "addr:street":"Prescott Ave",
    "iso:country":"US",
    "sg:address":"9201 Prescott Ave",
    "sg:city":"Manassas",
    "sg:classifiers":[
        {
            "category":"Personal",
            "subcategory":"Beauty Salon",
            "type":"Services"
        }
    ],
    "sg:phone":"+1 703 366 3300",
    "sg:postcode":"20110",
    "sg:province":"VA",
    "wof:name":"Vanessa's Beauty Salon",
    "wof:placetype":"venue"
},
  "geometry": {"coordinates":[-77.46544799999999,38.754892],"type":"Point"}
}