{
  "type": "Feature",
  "properties": {
    "iso:country":"US",
    "sg:address":"1270 Diamond Springs Rd",
    "sg:city":"Virginia Beach",
    "sg:classifiers":[
        {
            "category":"Shopping",
            "subcategory":"Computers & Home Electronics",
            "type":"Retail Goods"
        }
    ],
    "sg:phone":"+1 757 460 3700",
    "sg:postcode":"23455",
    "sg:province":"VA",
    "sg:tags":[
        "repair"
    ],
    "wof:name":"Multilink Solutions Inc",
    "wof:placetype":"venue"
},
  "geometry": {"coordinates":[-76.17755099999999,36.884747],"type":"Point"}
}