{
  "type": "Feature",
  "properties": {
    "iso:country":"US",
    "sg:address":"9209 Center St",
    "sg:city":"Manassas",
    "sg:classifiers":[
        {
            "category":"Building & Trades",
            "subcategory":"Construction",
            "type":"Services"
        }
    ],
    "sg:phone":"+1 703 369 5362",
    "sg:postcode":"20110",
    "sg:province":"VA",
    "sg:tags":[
        "general",
        "contractor"
    ],
    "wof:name":"Campos Construction",
    "wof:placetype":"venue"
},
  "geometry": {"coordinates":[-77.474851,38.750715],"type":"Point"}
}