{
  "type": "Feature",
  "properties": {
    "addr:full":"995 Granny Smith Rd Linden VA 22642",
    "addr:housenumber":"995",
    "addr:postcode":"22642",
    "addr:street":"Granny Smith Rd",
    "iso:country":"US",
    "sg:address":"995 Granny Smith Rd",
    "sg:city":"Linden",
    "sg:classifiers":[
        {
            "category":"Retail",
            "subcategory":"Repair Shop",
            "type":"Services"
        }
    ],
    "sg:phone":"+1 540 635 2248",
    "sg:postcode":"22642",
    "sg:province":"VA",
    "sg:tags":[
        "machine",
        "shoe"
    ],
    "wof:name":"Joe Jones Shoe Machinery",
    "wof:placetype":"venue"
},
  "geometry": {"coordinates":[-78.092535,38.92145],"type":"Point"}
}