{
  "type": "Feature",
  "properties": {
    "iso:country":"US",
    "sg:address":"55 Colony Square Ct",
    "sg:city":"Newport News",
    "sg:classifiers":[
        {
            "category":"Professional",
            "type":"Services"
        }
    ],
    "sg:phone":"+1 757 369 5850",
    "sg:postcode":"23602",
    "sg:province":"VA",
    "sg:tags":[
        "establishment"
    ],
    "wof:name":"Edwards & Edwards",
    "wof:placetype":"venue"
},
  "geometry": {"coordinates":[-76.517251,37.114682],"type":"Point"}
}