{
  "type": "Feature",
  "properties": {
    "addr:full":"7068 Studley Rd Mechanicsville VA 23116",
    "addr:housenumber":"7068",
    "addr:postcode":"23116",
    "addr:street":"Studley Rd",
    "iso:country":"US",
    "sg:address":"7068 Studley Rd",
    "sg:city":"Mechanicsville",
    "sg:classifiers":[
        {
            "category":"Professional",
            "subcategory":"Testing Lab",
            "type":"Services"
        }
    ],
    "sg:phone":"+1 804 730 8220",
    "sg:postcode":"23116",
    "sg:province":"VA",
    "sg:tags":[
        "soil"
    ],
    "wof:name":"Geo Environmental Svc Inc",
    "wof:placetype":"venue"
},
  "geometry": {"coordinates":[-77.33868699999999,37.670194],"type":"Point"}
}