{
  "type": "Feature",
  "properties": {
    "iso:country":"US",
    "sg:address":"688 J Clyde Morris Blvd",
    "sg:city":"Newport News",
    "sg:classifiers":[
        {
            "category":"Wholesale",
            "subcategory":"Computers",
            "type":"Manufacturing & Wholesale Goods"
        }
    ],
    "sg:phone":"+1 757 595 1955",
    "sg:postcode":"23601",
    "sg:province":"VA",
    "sg:tags":[
        "equipment",
        "processing",
        "datum"
    ],
    "wof:name":"United Computer Ctr",
    "wof:placetype":"venue"
},
  "geometry": {"coordinates":[-76.468535,37.076285],"type":"Point"}
}