{
  "type": "Feature",
  "properties": {
    "addr:full":"1757 Cedar Creek Ln Lynchburg VA 24503",
    "addr:housenumber":"1757",
    "addr:postcode":"24503",
    "addr:street":"Cedar Creek Ln",
    "iso:country":"US",
    "sg:address":"1757 Cedar Creek Ln",
    "sg:city":"Lynchburg",
    "sg:classifiers":[
        {
            "category":"Professional",
            "subcategory":"Management & Consulting",
            "type":"Services"
        }
    ],
    "sg:phone":"+1 434 384 1323",
    "sg:postcode":"24503",
    "sg:province":"VA",
    "sg:website":"www.corporatetransitions.com",
    "wof:name":"Corporate Transitions By Alty",
    "wof:placetype":"venue"
},
  "geometry": {"coordinates":[-79.26168199999999,37.415688],"type":"Point"}
}