{
  "type": "Feature",
  "properties": {
    "iso:country":"US",
    "sg:address":"4320 Prince William Pkwy",
    "sg:city":"Woodbridge",
    "sg:classifiers":[
        {
            "category":"Real Estate",
            "subcategory":"Real Estate Agent",
            "type":"Services"
        }
    ],
    "sg:phone":"+1 703 580 7404",
    "sg:postcode":"22192",
    "sg:province":"VA",
    "wof:name":"Sears Realty Group Inc",
    "wof:placetype":"venue"
},
  "geometry": {"coordinates":[-77.34315700000001,38.675636],"type":"Point"}
}