{
  "type": "Feature",
  "properties": {
    "iso:country":"US",
    "sg:address":"2780 S Jefferson Davis Hwy",
    "sg:city":"Arlington",
    "sg:classifiers":[
        {
            "category":"Retail",
            "subcategory":"Auto Rental",
            "type":"Services"
        }
    ],
    "sg:phone":"+1 703 684 0086",
    "sg:postcode":"22202",
    "sg:province":"VA",
    "sg:tags":[
        "renting",
        "automobile"
    ],
    "wof:name":"Alamo Rent-A-Car",
    "wof:placetype":"venue"
},
  "geometry": {"coordinates":[-77.05290599999999,38.848148],"type":"Point"}
}