{
  "type": "Feature",
  "properties": {
    "addr:full":"801 Parkwood Dr Harrisonburg VA 22802",
    "addr:housenumber":"801",
    "addr:postcode":"22802",
    "addr:street":"Parkwood Dr",
    "iso:country":"US",
    "sg:address":"801 Parkwood Dr",
    "sg:city":"Harrisonburg",
    "sg:classifiers":[
        {
            "category":"Education",
            "subcategory":"School",
            "type":"Public Place"
        }
    ],
    "sg:phone":"+1 540 432 4500",
    "sg:postcode":"22802",
    "sg:province":"VA",
    "sg:tags":[
        "organization",
        "religious"
    ],
    "wof:name":"Emhs",
    "wof:placetype":"venue"
},
  "geometry": {"coordinates":[-78.87487,38.47142],"type":"Point"}
}