{
  "type": "Feature",
  "properties": {
    "addr:full":"11001 Winding Brook Ct Manassas VA 20111",
    "addr:housenumber":"11001",
    "addr:postcode":"20111",
    "addr:street":"Winding Brook Ct",
    "iso:country":"US",
    "sg:address":"11001 Winding Brook Ct",
    "sg:city":"Manassas",
    "sg:classifiers":[
        {
            "category":"Local Transit",
            "type":"Transportation"
        }
    ],
    "sg:phone":"+1 703 583 7733",
    "sg:postcode":"20111",
    "sg:province":"VA",
    "sg:tags":[
        "passenger"
    ],
    "wof:name":"Particular People Ride Inc",
    "wof:placetype":"venue"
},
  "geometry": {"coordinates":[-77.415097,38.714038],"type":"Point"}
}