{
  "type": "Feature",
  "properties": {
    "addr:full":"4017 28th St S Arlington VA 22206",
    "addr:housenumber":"4017",
    "addr:postcode":"22206",
    "addr:street":"28Th St S",
    "iso:country":"US",
    "sg:address":"4017 28th St S",
    "sg:city":"Arlington",
    "sg:classifiers":[
        {
            "category":"Shopping",
            "subcategory":"Books",
            "type":"Retail Goods"
        }
    ],
    "sg:phone":"+1 703 931 6949",
    "sg:postcode":"22206",
    "sg:province":"VA",
    "sg:tags":[
        "dealer"
    ],
    "sg:website":"www.bamm.com",
    "wof:name":"Books-A-Million",
    "wof:placetype":"venue"
},
  "geometry": {"coordinates":[-77.08848,38.840951],"type":"Point"}
}