{
  "type": "Feature",
  "properties": {
    "addr:full":"1875 Electric Rd Salem VA 24153",
    "addr:housenumber":"1875",
    "addr:postcode":"24153",
    "addr:street":"Electric Rd",
    "iso:country":"US",
    "sg:address":"1875 Electric Rd",
    "sg:city":"Salem",
    "sg:classifiers":[
        {
            "category":"Shopping",
            "subcategory":"Pharmacy",
            "type":"Retail Goods"
        }
    ],
    "sg:phone":"+1 540 387 1696",
    "sg:postcode":"24153",
    "sg:province":"VA",
    "sg:tags":[
        "drug",
        "store"
    ],
    "wof:name":"CVS",
    "wof:placetype":"venue"
},
  "geometry": {"coordinates":[-80.034401,37.267072],"type":"Point"}
}