{
  "type": "Feature",
  "properties": {
    "iso:country":"US",
    "sg:address":"125 Madison Cir",
    "sg:city":"Madison Heights",
    "sg:classifiers":[
        {
            "category":"Building & Trades",
            "subcategory":"Construction",
            "type":"Services"
        }
    ],
    "sg:phone":"+1 434 929 6786",
    "sg:postcode":"24572",
    "sg:province":"VA",
    "sg:tags":[
        "house"
    ],
    "wof:name":"Morgan & Sheilds Building Inc",
    "wof:placetype":"venue"
},
  "geometry": {"coordinates":[-79.134064,37.423013],"type":"Point"}
}