{
  "type": "Feature",
  "properties": {
    "addr:full":"11499 Smith Creek Rd Bristol VA 24202",
    "addr:housenumber":"11499",
    "addr:postcode":"24202",
    "addr:street":"Smith Creek Rd",
    "iso:country":"US",
    "sg:address":"11499 Smith Creek Rd",
    "sg:city":"Bristol",
    "sg:classifiers":[
        {
            "category":"Farming",
            "subcategory":"Livestock Farm",
            "type":"Manufacturing & Wholesale Goods"
        }
    ],
    "sg:phone":"+1 276 628 4930",
    "sg:postcode":"24202",
    "sg:province":"VA",
    "sg:tags":[
        "beef",
        "feedlot",
        "cattle"
    ],
    "wof:name":"Dened Inc",
    "wof:placetype":"venue"
},
  "geometry": {"coordinates":[-82.150958,36.750303],"type":"Point"}
}