{
  "type": "Feature",
  "properties": {
    "iso:country":"US",
    "sg:address":"6542 Morning Glen Ct",
    "sg:city":"Alexandria",
    "sg:classifiers":[
        {
            "category":"Utilities",
            "subcategory":"Natural Gas",
            "type":"Services"
        }
    ],
    "sg:phone":"+1 703 339 9869",
    "sg:postcode":"22315",
    "sg:province":"VA",
    "wof:name":"Washington Gas Co",
    "wof:placetype":"venue"
},
  "geometry": {"coordinates":[-77.166433,38.742413],"type":"Point"}
}