{
  "type": "Feature",
  "properties": {
    "iso:country":"US",
    "sg:address":"181 Holmes Cir",
    "sg:city":"Lynchburg",
    "sg:classifiers":[
        {
            "category":"Wholesale",
            "subcategory":"Stationery",
            "type":"Manufacturing & Wholesale Goods"
        }
    ],
    "sg:phone":"+1 434 385 9634",
    "sg:postcode":"24501",
    "sg:province":"VA",
    "sg:tags":[
        "computer",
        "business",
        "form",
        "supply"
    ],
    "wof:name":"Seven Hills Business Forms",
    "wof:placetype":"venue"
},
  "geometry": {"coordinates":[-79.21216699999999,37.408267],"type":"Point"}
}