{
  "type": "Feature",
  "properties": {
    "iso:country":"US",
    "sg:address":"1545 E Cary St",
    "sg:city":"Richmond",
    "sg:classifiers":[
        {
            "category":"Restaurant",
            "type":"Food & Drink"
        }
    ],
    "sg:phone":"+1 804 643 2582",
    "sg:postcode":"23219",
    "sg:province":"VA",
    "sg:tags":[
        "eating"
    ],
    "wof:name":"Canal Club",
    "wof:placetype":"venue"
},
  "geometry": {"coordinates":[-77.43087199999999,37.533492],"type":"Point"}
}