{
  "type": "Feature",
  "properties": {
    "addr:full":"1624 Laskin Rd Virginia Beach VA 23451",
    "addr:housenumber":"1624",
    "addr:postcode":"23451",
    "addr:street":"Laskin Rd",
    "iso:country":"US",
    "sg:address":"1624 Laskin Rd",
    "sg:city":"Virginia Beach",
    "sg:classifiers":[
        {
            "category":"Shopping",
            "subcategory":"Hobbies, Toys, & Games",
            "type":"Retail Goods"
        },
        {
            "category":"Manufacturing",
            "subcategory":"Toys & Sporting Goods",
            "type":"Manufacturing & Wholesale Goods"
        }
    ],
    "sg:phone":"+1 757 425 2377",
    "sg:postcode":"23451",
    "sg:province":"VA",
    "sg:tags":[
        "mfg"
    ],
    "sg:website":"www.learningexpress.com",
    "wof:name":"Learning Express",
    "wof:placetype":"venue"
},
  "geometry": {"coordinates":[-76.018654,36.851144],"type":"Point"}
}