{
  "type": "Feature",
  "properties": {
    "addr:full":"305 W Masonic View Ave Alexandria VA 22301",
    "addr:housenumber":"305",
    "addr:postcode":"22301",
    "addr:street":"W Masonic View Ave",
    "iso:country":"US",
    "sg:address":"305 W Masonic View Ave",
    "sg:city":"Alexandria",
    "sg:classifiers":[
        {
            "category":"Organizations",
            "subcategory":"Community Association",
            "type":"Services"
        }
    ],
    "sg:phone":"+1 703 739 6277",
    "sg:postcode":"22301",
    "sg:province":"VA",
    "sg:tags":[
        "skill",
        "training",
        "life"
    ],
    "wof:name":"Street Smart Inc",
    "wof:placetype":"venue"
},
  "geometry": {"coordinates":[-77.06738799999999,38.813899],"type":"Point"}
}