{
  "type": "Feature",
  "properties": {
    "addr:full":"703 Confederate Ave Portsmouth VA 23704",
    "addr:housenumber":"703",
    "addr:postcode":"23704",
    "addr:street":"Confederate Ave",
    "iso:country":"US",
    "sg:address":"703 Confederate Ave",
    "sg:city":"Portsmouth",
    "sg:classifiers":[
        {
            "category":"Home & Garden",
            "subcategory":"Household Appliances",
            "type":"Retail Goods"
        },
        {
            "category":"Building & Trades",
            "subcategory":"Plumbing",
            "type":"Services"
        },
        {
            "category":"Building & Trades",
            "subcategory":"Construction",
            "type":"Services"
        }
    ],
    "sg:phone":"+1 757 399 1714",
    "sg:postcode":"23704",
    "sg:province":"VA",
    "sg:tags":[
        "repair",
        "plumber",
        "systems-repairing",
        "system",
        "specialty",
        "equipment",
        "pump",
        "heating",
        "contractor",
        "heat",
        "air conditioning"
    ],
    "sg:website":"http://www.jfwhitlow.com",
    "wof:name":"Whitlow J F",
    "wof:placetype":"venue"
},
  "geometry": {"coordinates":[-76.32919099999999,36.833057],"type":"Point"}
}