{
  "type": "Feature",
  "properties": {
    "addr:full":"2741 Bandy Rd SE Roanoke VA 24014",
    "addr:housenumber":"2741",
    "addr:postcode":"24014",
    "addr:street":"Bandy Rd Se",
    "iso:country":"US",
    "sg:address":"2741 Bandy Rd SE",
    "sg:city":"Roanoke",
    "sg:classifiers":[
        {
            "category":"Building & Trades",
            "subcategory":"Plumbing",
            "type":"Services"
        }
    ],
    "sg:phone":"+1 540 427 4910",
    "sg:postcode":"24014",
    "sg:province":"VA",
    "sg:tags":[
        "conditioning",
        "air",
        "system",
        "contractor"
    ],
    "wof:name":"Service Co",
    "wof:placetype":"venue"
},
  "geometry": {"coordinates":[-79.921328,37.238922],"type":"Point"}
}