{
  "type": "Feature",
  "properties": {
    "addr:full":"345 W Freemason St Norfolk VA 23510",
    "addr:housenumber":"345",
    "addr:postcode":"23510",
    "addr:street":"W Freemason St",
    "iso:country":"US",
    "sg:address":"345 W Freemason St",
    "sg:city":"Norfolk",
    "sg:classifiers":[
        {
            "category":"Professional",
            "subcategory":"Computer Services",
            "type":"Services"
        }
    ],
    "sg:phone":"+1 757 668 6428",
    "sg:postcode":"23510",
    "sg:province":"VA",
    "sg:tags":[
        "web",
        "management",
        "develop",
        "medical",
        "so",
        "health",
        "software"
    ],
    "wof:name":"Welligent",
    "wof:placetype":"venue"
},
  "geometry": {"coordinates":[-76.294977,36.852007],"type":"Point"}
}