{
  "type": "Feature",
  "properties": {
    "iso:country":"US",
    "sg:address":"1 W Main St",
    "sg:city":"Radford",
    "sg:classifiers":[
        {
            "category":"Insurance",
            "subcategory":"Hazard Insurance",
            "type":"Services"
        }
    ],
    "sg:phone":"+1 540 639 4833",
    "sg:postcode":"24141",
    "sg:province":"VA",
    "sg:tags":[
        "carrier"
    ],
    "wof:name":"Bb &T Old Dominion Insuran Ce",
    "wof:placetype":"venue"
},
  "geometry": {"coordinates":[-80.56792799999999,37.138078],"type":"Point"}
}