{
  "type": "Feature",
  "properties": {
    "addr:full":"7101 W Broad St Henrico VA 23294",
    "addr:housenumber":"7101",
    "addr:postcode":"23294",
    "addr:street":"W Broad St",
    "iso:country":"US",
    "sg:address":"7101 W Broad St",
    "sg:city":"Henrico",
    "sg:classifiers":[
        {
            "category":"Banks & Credit Unions",
            "subcategory":"Bank",
            "type":"Services"
        },
        {
            "category":"Banks & Credit Unions",
            "subcategory":"Financial Services",
            "type":"Services"
        }
    ],
    "sg:phone":"+1 804 756 1300",
    "sg:postcode":"23294",
    "sg:province":"VA",
    "sg:tags":[
        "commercial",
        "loan",
        "saving",
        "mortgage"
    ],
    "sg:website":"https://www.wachovia.com/?DCMP=KNL-CPS-DS-Directory-0703&HBX_PK=Banks&HBX_OU=71",
    "wof:name":"Wachovia Bank",
    "wof:placetype":"venue"
},
  "geometry": {"coordinates":[-77.51956199999999,37.610748],"type":"Point"}
}