{
  "type": "Feature",
  "properties": {
    "addr:full":"7080 Mechanicsville Tpke Mechanicsville VA 23111",
    "addr:postcode":"7080;23111",
    "addr:street":"Tpke",
    "iso:country":"US",
    "sg:address":"7080 Mechanicsville Tpke",
    "sg:city":"Mechanicsville",
    "sg:classifiers":[
        {
            "category":"Retail",
            "subcategory":"Laundry & Dry Cleaning",
            "type":"Services"
        }
    ],
    "sg:phone":"+1 804 746 0672",
    "sg:postcode":"23111",
    "sg:province":"VA",
    "sg:tags":[
        "cleaners"
    ],
    "wof:name":"Hanover Cleaners",
    "wof:placetype":"venue"
},
  "geometry": {"coordinates":[-77.341019,37.611717],"type":"Point"}
}