{
  "type": "Feature",
  "properties": {
    "iso:country":"US",
    "sg:address":"22094 Whitetail Ridge Ln",
    "sg:city":"Middleburg",
    "sg:classifiers":[
        {
            "category":"Building & Trades",
            "subcategory":"Landscaping Services",
            "type":"Services"
        }
    ],
    "sg:phone":"+1 540 687 6829",
    "sg:postcode":"20117",
    "sg:province":"VA",
    "sg:tags":[
        "designer",
        "landscape"
    ],
    "wof:name":"Linda Wright Landscape Arch",
    "wof:placetype":"venue"
},
  "geometry": {"coordinates":[-77.704382,39.00427],"type":"Point"}
}