{
  "type": "Feature",
  "properties": {
    "addr:full":"130 Windy Hill Ln Winchester VA 22602",
    "addr:housenumber":"130",
    "addr:postcode":"22602",
    "addr:street":"Windy Hill Ln",
    "iso:country":"US",
    "sg:address":"130 Windy Hill Ln",
    "sg:city":"Winchester",
    "sg:classifiers":[
        {
            "category":"Building & Trades",
            "subcategory":"Plumbing",
            "type":"Services"
        }
    ],
    "sg:phone":"+1 540 662 9706",
    "sg:postcode":"22602",
    "sg:province":"VA",
    "sg:tags":[
        "conditioning",
        "air",
        "system",
        "contractor"
    ],
    "wof:name":"A 1 Cooling & Refrig Inc",
    "wof:placetype":"venue"
},
  "geometry": {"coordinates":[-78.16186399999999,39.155863],"type":"Point"}
}