{
  "type": "Feature",
  "properties": {
    "addr:full":"13705 Steeple Chase Ter Midlothian VA 23112",
    "addr:housenumber":"13705",
    "addr:postcode":"23112",
    "addr:street":"Steeple Chase Ter",
    "iso:country":"US",
    "sg:address":"13705 Steeple Chase Ter",
    "sg:city":"Midlothian",
    "sg:classifiers":[
        {
            "category":"Building & Trades",
            "subcategory":"Cleaning & Sanitation",
            "type":"Services"
        }
    ],
    "sg:phone":"+1 804 763 4817",
    "sg:postcode":"23112",
    "sg:province":"VA",
    "sg:tags":[
        "house"
    ],
    "wof:name":"Mid Atlantic Maid Svc",
    "wof:placetype":"venue"
},
  "geometry": {"coordinates":[-77.654551,37.44721],"type":"Point"}
}