{
  "type": "Feature",
  "properties": {
    "addr:full":"534 S Main St Marion VA 24354",
    "addr:housenumber":"534",
    "addr:postcode":"24354",
    "addr:street":"S Main St",
    "iso:country":"US",
    "sg:address":"534 S Main St",
    "sg:city":"Marion",
    "sg:classifiers":[
        {
            "category":"Restaurant",
            "type":"Food & Drink"
        }
    ],
    "sg:phone":"+1 276 783 2655",
    "sg:postcode":"24354",
    "sg:province":"VA",
    "sg:tags":[
        "pizza"
    ],
    "wof:name":"C J's Pizza",
    "wof:placetype":"venue"
},
  "geometry": {"coordinates":[-81.528136,36.828188],"type":"Point"}
}