{
  "type": "Feature",
  "properties": {
    "iso:country":"US",
    "sg:address":"190 Lakewood Forest Rd",
    "sg:city":"Moneta",
    "sg:classifiers":[
        {
            "category":"Building & Trades",
            "subcategory":"Construction",
            "type":"Services"
        }
    ],
    "sg:phone":"+1 540 721 0060",
    "sg:postcode":"24121",
    "sg:province":"VA",
    "sg:tags":[
        "house"
    ],
    "wof:name":"Smith Mountainlake Deck & Dock",
    "wof:placetype":"venue"
},
  "geometry": {"coordinates":[-79.69393599999999,37.106167],"type":"Point"}
}