{
  "type": "Feature",
  "properties": {
    "addr:full":"6156 Mechanicsville Tpke Mechanicsville VA 23111",
    "addr:postcode":"6156;23111",
    "addr:street":"Tpke",
    "iso:country":"US",
    "sg:address":"6156 Mechanicsville Tpke",
    "sg:city":"Mechanicsville",
    "sg:classifiers":[
        {
            "category":"Home & Garden",
            "subcategory":"Carpets & Floor Coverings",
            "type":"Retail Goods"
        }
    ],
    "sg:phone":"+1 804 730 3016",
    "sg:postcode":"23111",
    "sg:province":"VA",
    "sg:tags":[
        "installs"
    ],
    "wof:name":"L & M Carpet Tile & Interiors",
    "wof:placetype":"venue"
},
  "geometry": {"coordinates":[-77.311279,37.62277],"type":"Point"}
}