{
  "type": "Feature",
  "properties": {
    "addr:full":"6300 26th St N Arlington VA 22207",
    "addr:housenumber":"6300",
    "addr:postcode":"22207",
    "addr:street":"26Th St N",
    "iso:country":"US",
    "sg:address":"6300 26th St N",
    "sg:city":"Arlington",
    "sg:classifiers":[
        {
            "category":"Real Estate",
            "subcategory":"Real Estate Agent",
            "type":"Services"
        }
    ],
    "sg:phone":"+1 703 533 0835",
    "sg:postcode":"22207",
    "sg:province":"VA",
    "wof:name":"Reese Sedinger Real Estate LLC",
    "wof:placetype":"venue"
},
  "geometry": {"coordinates":[-77.155495,38.894557],"type":"Point"}
}