{
  "type": "Feature",
  "properties": {
    "addr:full":"14021 Lee Jackson Memorial Hwy Chantilly VA 20151",
    "addr:housenumber":"14021",
    "addr:postcode":"20151",
    "addr:street":"Lee Jackson Memorial Hwy",
    "iso:country":"US",
    "sg:address":"14021 Lee Jackson Memorial Hwy",
    "sg:city":"Chantilly",
    "sg:classifiers":[
        {
            "category":"Cinema",
            "subcategory":"Movie Rental",
            "type":"Entertainment"
        }
    ],
    "sg:phone":"+1 703 968 2791",
    "sg:postcode":"20151",
    "sg:province":"VA",
    "sg:tags":[
        "video",
        "game",
        "leasing"
    ],
    "wof:name":"MVC Late Night Video",
    "wof:placetype":"venue"
},
  "geometry": {"coordinates":[-77.433055,38.894842],"type":"Point"}
}