{
  "type": "Feature",
  "properties": {
    "addr:full":"417 Jefferson Davis Hwy Fredericksburg VA 22401",
    "addr:housenumber":"417",
    "addr:postcode":"22401",
    "addr:street":"Jefferson Davis Hwy",
    "iso:country":"US",
    "sg:address":"417 Jefferson Davis Hwy",
    "sg:city":"Fredericksburg",
    "sg:classifiers":[
        {
            "category":"Wholesale",
            "subcategory":"Electrical",
            "type":"Manufacturing & Wholesale Goods"
        }
    ],
    "sg:phone":"+1 540 373 8404",
    "sg:postcode":"22401",
    "sg:province":"VA",
    "sg:tags":[
        "equipment",
        "electric",
        "supply"
    ],
    "wof:name":"U S Lighting Showroom",
    "wof:placetype":"venue"
},
  "geometry": {"coordinates":[-77.47381900000001,38.315796],"type":"Point"}
}