{
  "type": "Feature",
  "properties": {
    "addr:full":"500 Ridge Cir Waynesboro VA 22980",
    "addr:housenumber":"500",
    "addr:postcode":"22980",
    "addr:street":"Ridge Cir",
    "iso:country":"US",
    "sg:address":"500 Ridge Cir",
    "sg:city":"Waynesboro",
    "sg:classifiers":[
        {
            "category":"Health Services",
            "subcategory":"Doctor",
            "type":"Services"
        }
    ],
    "sg:phone":"+1 540 943 5935",
    "sg:postcode":"22980",
    "sg:province":"VA",
    "wof:name":"Michael T Cunningham DDS",
    "wof:placetype":"venue"
},
  "geometry": {"coordinates":[-78.907259,38.065236],"type":"Point"}
}