{
  "type": "Feature",
  "properties": {
    "addr:full":"717 Princess St Alexandria VA 22314",
    "addr:housenumber":"717",
    "addr:postcode":"22314",
    "addr:street":"Princess St",
    "iso:country":"US",
    "sg:address":"717 Princess St",
    "sg:city":"Alexandria",
    "sg:classifiers":[
        {
            "category":"Organizations",
            "subcategory":"Professional Association",
            "type":"Services"
        }
    ],
    "sg:phone":"+1 703 683 5954",
    "sg:postcode":"22314",
    "sg:province":"VA",
    "wof:name":"Advertising Club Of Washington",
    "wof:placetype":"venue"
},
  "geometry": {"coordinates":[-77.047228,38.808666],"type":"Point"}
}