{
  "type": "Feature",
  "properties": {
    "addr:full":"6508 Backlick Rd Springfield VA 22150",
    "addr:housenumber":"6508",
    "addr:postcode":"22150",
    "addr:street":"Backlick Rd",
    "iso:country":"US",
    "sg:address":"6508 Backlick Rd",
    "sg:city":"Springfield",
    "sg:classifiers":[
        {
            "category":"Retail",
            "subcategory":"Laundry & Dry Cleaning",
            "type":"Services"
        }
    ],
    "sg:phone":"+1 703 451 2544",
    "sg:postcode":"22150",
    "sg:province":"VA",
    "sg:tags":[
        "drycleaning",
        "plant"
    ],
    "wof:name":"Presto Valet",
    "wof:placetype":"venue"
},
  "geometry": {"coordinates":[-77.18438999999999,38.778395],"type":"Point"}
}