{
  "type": "Feature",
  "properties": {
    "iso:country":"US",
    "sg:address":"5644 George Washington Memorial Hwy",
    "sg:city":"Gloucester",
    "sg:classifiers":[
        {
            "category":"Education",
            "subcategory":"School",
            "type":"Public Place"
        }
    ],
    "sg:phone":"+1 804 693 2127",
    "sg:postcode":"23061",
    "sg:province":"VA",
    "wof:name":"Gloucester School Trnsp",
    "wof:placetype":"venue"
},
  "geometry": {"coordinates":[-76.52408,37.359284],"type":"Point"}
}