{
  "type": "Feature",
  "properties": {
    "addr:full":"3120 Colvin St Alexandria VA 22314",
    "addr:housenumber":"3120",
    "addr:postcode":"22314",
    "addr:street":"Colvin St",
    "iso:country":"US",
    "sg:address":"3120 Colvin St",
    "sg:city":"Alexandria",
    "sg:classifiers":[
        {
            "category":"Professional",
            "subcategory":"Business Services",
            "type":"Services"
        }
    ],
    "sg:phone":"+1 703 751 1020",
    "sg:postcode":"22314",
    "sg:province":"VA",
    "sg:tags":[
        "repossessing"
    ],
    "wof:name":"Summs Recovery & Collections",
    "wof:placetype":"venue"
},
  "geometry": {"coordinates":[-77.08235999999999,38.806702],"type":"Point"}
}