{
  "type": "Feature",
  "properties": {
    "addr:full":"5455 Fox Rd Richmond VA 23250",
    "addr:housenumber":"5455",
    "addr:postcode":"23250",
    "addr:street":"Fox Rd",
    "iso:country":"US",
    "sg:address":"5455 Fox Rd",
    "sg:city":"Richmond",
    "sg:classifiers":[
        {
            "category":"Airport",
            "type":"Transportation"
        }
    ],
    "sg:phone":"+1 804 222 6864",
    "sg:postcode":"23250",
    "sg:province":"VA",
    "wof:name":"Quantum Aviation Svc",
    "wof:placetype":"venue"
},
  "geometry": {"coordinates":[-77.336246,37.501799],"type":"Point"}
}