{
  "type": "Feature",
  "properties": {
    "iso:country":"US",
    "sg:address":"800 Lake Caroline Dr",
    "sg:city":"Ruther Glen",
    "sg:classifiers":[
        {
            "category":"Building & Trades",
            "subcategory":"Construction",
            "type":"Services"
        }
    ],
    "sg:phone":"+1 804 448 4409",
    "sg:postcode":"22546",
    "sg:province":"VA",
    "sg:tags":[
        "home",
        "builder"
    ],
    "wof:name":"G D Excavating & Landscaping",
    "wof:placetype":"venue"
},
  "geometry": {"coordinates":[-77.510097,37.991348],"type":"Point"}
}