{
  "type": "Feature",
  "properties": {
    "addr:full":"2800 Annandale Rd Falls Church VA 22042",
    "addr:housenumber":"2800",
    "addr:postcode":"22042",
    "addr:street":"Annandale Rd",
    "iso:country":"US",
    "sg:address":"2800 Annandale Rd",
    "sg:city":"Falls Church",
    "sg:classifiers":[
        {
            "category":"Freight",
            "type":"Transportation"
        }
    ],
    "sg:phone":"+1 703 241 0249",
    "sg:postcode":"22042",
    "sg:province":"VA",
    "sg:tags":[
        "operator",
        "local",
        "trucking"
    ],
    "wof:name":"Gaskins Trucking Inc",
    "wof:placetype":"venue"
},
  "geometry": {"coordinates":[-77.174042,38.876718],"type":"Point"}
}