{
  "type": "Feature",
  "properties": {
    "addr:full":"12709 Getty Ln Spotsylvania VA 22551",
    "addr:housenumber":"12709",
    "addr:postcode":"22551",
    "addr:street":"Getty Ln",
    "iso:country":"US",
    "sg:address":"12709 Getty Ln",
    "sg:city":"Spotsylvania",
    "sg:classifiers":[
        {
            "category":"Personal",
            "type":"Services"
        }
    ],
    "sg:phone":"+1 540 972 5712",
    "sg:postcode":"22551",
    "sg:province":"VA",
    "sg:tags":[
        "home",
        "residential",
        "improvement"
    ],
    "wof:name":"D JS Home Improvements",
    "wof:placetype":"venue"
},
  "geometry": {"coordinates":[-77.73644899999999,38.302514],"type":"Point"}
}