{
  "type": "Feature",
  "properties": {
    "iso:country":"US",
    "sg:address":"10990 Air Park Rd",
    "sg:city":"Ashland",
    "sg:classifiers":[
        {
            "category":"Retail",
            "subcategory":"Repair Shop",
            "type":"Services"
        }
    ],
    "sg:phone":"+1 804 752 6070",
    "sg:postcode":"23005",
    "sg:province":"VA",
    "sg:tags":[
        "electrical"
    ],
    "wof:name":"Carter Power Systems",
    "wof:placetype":"venue"
},
  "geometry": {"coordinates":[-77.43509400000001,37.70191],"type":"Point"}
}