{
  "type": "Feature",
  "properties": {
    "addr:full":"12803 Trenadier Cir Midlothian VA 23113",
    "addr:housenumber":"12803",
    "addr:postcode":"23113",
    "addr:street":"Trenadier Cir",
    "iso:country":"US",
    "sg:address":"12803 Trenadier Cir",
    "sg:city":"Midlothian",
    "sg:classifiers":[
        {
            "category":"Communications",
            "type":"Services"
        }
    ],
    "sg:phone":"+1 804 897 8491",
    "sg:postcode":"23113",
    "sg:province":"VA",
    "sg:tags":[
        "communication"
    ],
    "wof:name":"Medical Communications",
    "wof:placetype":"venue"
},
  "geometry": {"coordinates":[-77.639487,37.526929],"type":"Point"}
}