{
  "type": "Feature",
  "properties": {
    "addr:full":"2810 Hawkins Mill Rd Lynchburg VA 24503",
    "addr:housenumber":"2810",
    "addr:postcode":"24503",
    "addr:street":"Hawkins Mill Rd",
    "iso:country":"US",
    "sg:address":"2810 Hawkins Mill Rd",
    "sg:city":"Lynchburg",
    "sg:classifiers":[
        {
            "category":"Retail",
            "subcategory":"Repair Shop",
            "type":"Services"
        }
    ],
    "sg:phone":"+1 434 384 7071",
    "sg:postcode":"24503",
    "sg:province":"VA",
    "wof:name":"Toms Locksmith Service",
    "wof:placetype":"venue"
},
  "geometry": {"coordinates":[-79.273278,37.412942],"type":"Point"}
}