{
  "type": "Feature",
  "properties": {
    "addr:full":"39 Enslow Dr Bassett VA 24055",
    "addr:housenumber":"39",
    "addr:postcode":"24055",
    "addr:street":"Enslow Dr",
    "iso:country":"US",
    "sg:address":"39 Enslow Dr",
    "sg:city":"Bassett",
    "sg:classifiers":[
        {
            "category":"Retail",
            "subcategory":"Auto Repair",
            "type":"Services"
        }
    ],
    "sg:phone":"+1 276 629 8071",
    "sg:postcode":"24055",
    "sg:province":"VA",
    "sg:tags":[
        "general"
    ],
    "wof:name":"Franks Auto Service",
    "wof:placetype":"venue"
},
  "geometry": {"coordinates":[-80.078627,36.750349],"type":"Point"}
}