{
  "type": "Feature",
  "properties": {
    "addr:full":"3000 Scherer Dr Richmond VA 23235",
    "addr:postcode":"3000;23235",
    "addr:street":"Scherer Dr",
    "iso:country":"US",
    "sg:address":"3000 Scherer Dr",
    "sg:city":"Richmond",
    "sg:classifiers":[
        {
            "category":"Professional",
            "subcategory":"Management & Consulting",
            "type":"Services"
        }
    ],
    "sg:phone":"+1 804 330 3888",
    "sg:postcode":"23235",
    "sg:province":"VA",
    "wof:name":"C M A T Consulting",
    "wof:placetype":"venue"
},
  "geometry": {"coordinates":[-77.55295099999999,37.540223],"type":"Point"}
}