{
  "type": "Feature",
  "properties": {
    "addr:full":"5244 Challedon Dr Virginia Beach VA 23462",
    "addr:housenumber":"5244",
    "addr:postcode":"23462",
    "addr:street":"Challedon Dr",
    "iso:country":"US",
    "sg:address":"5244 Challedon Dr",
    "sg:city":"Virginia Beach",
    "sg:classifiers":[
        {
            "category":"Professional",
            "type":"Services"
        }
    ],
    "sg:phone":"+1 757 456 0489",
    "sg:postcode":"23462",
    "sg:province":"VA",
    "sg:tags":[
        "establishment"
    ],
    "wof:name":"ESE",
    "wof:placetype":"venue"
},
  "geometry": {"coordinates":[-76.169078,36.826768],"type":"Point"}
}