{
  "type": "Feature",
  "properties": {
    "iso:country":"US",
    "sg:address":"32126 Busy St",
    "sg:city":"Boykins",
    "sg:classifiers":[
        {
            "category":"Food & Beverages",
            "subcategory":"Groceries & Convenience Stores",
            "type":"Retail Goods"
        }
    ],
    "sg:phone":"+1 757 654 0136",
    "sg:postcode":"23827",
    "sg:province":"VA",
    "sg:tags":[
        "grocer"
    ],
    "wof:name":"Butcher Block Inc",
    "wof:placetype":"venue"
},
  "geometry": {"coordinates":[-77.199996,36.584238],"type":"Point"}
}