{
  "type": "Feature",
  "properties": {
    "iso:country":"US",
    "sg:address":"4258 Germanna Hwy",
    "sg:city":"Locust Grove",
    "sg:classifiers":[
        {
            "category":"Manufacturing",
            "subcategory":"Wood Products",
            "type":"Manufacturing & Wholesale Goods"
        }
    ],
    "sg:phone":"+1 540 972 7780",
    "sg:postcode":"22508",
    "sg:province":"VA",
    "sg:tags":[
        "preserving"
    ],
    "wof:name":"Rocky Top Wood Preservers",
    "wof:placetype":"venue"
},
  "geometry": {"coordinates":[-77.746019,38.345729],"type":"Point"}
}