{
  "type": "Feature",
  "properties": {
    "addr:full":"110 Freeman Ave Chesapeake VA 23324",
    "addr:housenumber":"110",
    "addr:postcode":"23324",
    "addr:street":"Freeman Ave",
    "iso:country":"US",
    "sg:address":"110 Freeman Ave",
    "sg:city":"Chesapeake",
    "sg:classifiers":[
        {
            "category":"Wholesale",
            "subcategory":"Petroleum",
            "type":"Manufacturing & Wholesale Goods"
        }
    ],
    "sg:phone":"+1 757 543 3800",
    "sg:postcode":"23324",
    "sg:province":"VA",
    "sg:tags":[
        "bulk",
        "station"
    ],
    "wof:name":"Citgo",
    "wof:placetype":"venue"
},
  "geometry": {"coordinates":[-76.299802,36.78664],"type":"Point"}
}