{
  "type": "Feature",
  "properties": {
    "iso:country":"US",
    "sg:address":"3411 W Cary St",
    "sg:city":"Richmond",
    "sg:classifiers":[
        {
            "category":"Restaurant",
            "type":"Food & Drink"
        }
    ],
    "sg:phone":"+1 804 353 3411",
    "sg:postcode":"23221",
    "sg:province":"VA",
    "sg:tags":[
        "grill",
        "seafood",
        "steak",
        "bar",
        "house"
    ],
    "sg:website":"http://www.thewatergrill.com",
    "wof:name":"The Water Grill - Richmond",
    "wof:placetype":"venue"
},
  "geometry": {"coordinates":[-77.48457500000001,37.554555],"type":"Point"}
}