{
  "type": "Feature",
  "properties": {
    "addr:full":"4119 Medford Dr Annandale VA 22003",
    "addr:housenumber":"4119",
    "addr:postcode":"22003",
    "addr:street":"Medford Dr",
    "iso:country":"US",
    "sg:address":"4119 Medford Dr",
    "sg:city":"Annandale",
    "sg:classifiers":[
        {
            "category":"Personal",
            "subcategory":"Beauty Salon",
            "type":"Services"
        }
    ],
    "sg:phone":"+1 703 256 7356",
    "sg:postcode":"22003",
    "sg:province":"VA",
    "sg:tags":[
        "shop"
    ],
    "wof:name":"Touch of Beauty",
    "wof:placetype":"venue"
},
  "geometry": {"coordinates":[-77.203,38.833671],"type":"Point"}
}