{
  "type": "Feature",
  "properties": {
    "iso:country":"US",
    "sg:address":"6301 Banshire Dr",
    "sg:city":"Mechanicsville",
    "sg:classifiers":[
        {
            "category":"Professional",
            "subcategory":"Management & Consulting",
            "type":"Services"
        }
    ],
    "sg:phone":"+1 804 730 9268",
    "sg:postcode":"23111",
    "sg:province":"VA",
    "sg:tags":[
        "public",
        "relations",
        "writing"
    ],
    "wof:name":"Audrey T Hingley",
    "wof:placetype":"venue"
},
  "geometry": {"coordinates":[-77.322577,37.632964],"type":"Point"}
}