{
  "type": "Feature",
  "properties": {
    "iso:country":"US",
    "sg:address":"1900 W Washington St",
    "sg:city":"Petersburg",
    "sg:classifiers":[
        {
            "category":"Food & Beverages",
            "subcategory":"Groceries & Convenience Stores",
            "type":"Retail Goods"
        }
    ],
    "sg:phone":"+1 804 732 7933",
    "sg:postcode":"23803",
    "sg:province":"VA",
    "sg:tags":[
        "grocer"
    ],
    "wof:name":"Harrison's Grocery",
    "wof:placetype":"venue"
},
  "geometry": {"coordinates":[-77.43724400000001,37.218579],"type":"Point"}
}