{
  "type": "Feature",
  "properties": {
    "addr:full":"18059 Virgil H Goode Hwy Rocky Mount VA 24151",
    "addr:postcode":"18059;24151",
    "addr:street":"Goode Hwy",
    "iso:country":"US",
    "sg:address":"18059 Virgil H Goode Hwy",
    "sg:city":"Rocky Mount",
    "sg:classifiers":[
        {
            "category":"Travel",
            "subcategory":"Hotels & Motels",
            "type":"Entertainment"
        }
    ],
    "sg:phone":"+1 540 483 9757",
    "sg:postcode":"24151",
    "sg:province":"VA",
    "wof:name":"Budget Host Inn",
    "wof:placetype":"venue"
},
  "geometry": {"coordinates":[-79.87817800000001,37.045574],"type":"Point"}
}