{
  "type": "Feature",
  "properties": {
    "addr:full":"21266 Lahore Rd Orange VA 22960",
    "addr:postcode":"21266;22960",
    "addr:street":"Lahore Rd",
    "iso:country":"US",
    "sg:address":"21266 Lahore Rd",
    "sg:city":"Orange",
    "sg:classifiers":[
        {
            "category":"Retail",
            "subcategory":"Auto Repair",
            "type":"Services"
        }
    ],
    "sg:phone":"+1 540 854 9717",
    "sg:postcode":"22960",
    "sg:province":"VA",
    "sg:tags":[
        "repairing",
        "automobile"
    ],
    "wof:name":"Browns Auto",
    "wof:placetype":"venue"
},
  "geometry": {"coordinates":[-78.002601,38.202102],"type":"Point"}
}