{
  "type": "Feature",
  "properties": {
    "iso:country":"US",
    "sg:address":"1901 E Franklin St",
    "sg:city":"Richmond",
    "sg:classifiers":[
        {
            "category":"Home & Garden",
            "subcategory":"Building Materials",
            "type":"Retail Goods"
        }
    ],
    "sg:phone":"+1 804 780 0202",
    "sg:postcode":"23223",
    "sg:province":"VA",
    "wof:name":"Nolavax USA Inc",
    "wof:placetype":"venue"
},
  "geometry": {"coordinates":[-77.424995,37.532667],"type":"Point"}
}