{
  "type": "Feature",
  "properties": {
    "addr:full":"9875 Cave Hill Rd Mc Gaheysville VA 22840",
    "addr:housenumber":"9875",
    "addr:postcode":"22840",
    "addr:street":"Cave Hill Rd",
    "iso:country":"US",
    "sg:address":"9875 Cave Hill Rd",
    "sg:city":"Mc Gaheysville",
    "sg:classifiers":[
        {
            "category":"Travel",
            "subcategory":"Hotels & Motels",
            "type":"Entertainment"
        }
    ],
    "sg:phone":"+1 540 289 7441",
    "sg:postcode":"22840",
    "sg:province":"VA",
    "sg:tags":[
        "breakfast",
        "accommodation",
        "bed"
    ],
    "wof:name":"Cave Hill Farm Bed & Breakfast",
    "wof:placetype":"venue"
},
  "geometry": {"coordinates":[-78.72335699999999,38.358418],"type":"Point"}
}