{
  "type": "Feature",
  "properties": {
    "iso:country":"US",
    "sg:address":"95 Providence Ln",
    "sg:city":"Waynesboro",
    "sg:classifiers":[
        {
            "category":"Health Services",
            "subcategory":"Doctor",
            "type":"Services"
        }
    ],
    "sg:phone":"+1 540 943 0706",
    "sg:postcode":"22980",
    "sg:province":"VA",
    "sg:tags":[
        "physician",
        "surgeon"
    ],
    "wof:name":"Louis S Chaldares MD",
    "wof:placetype":"venue"
},
  "geometry": {"coordinates":[-78.936318,38.041327],"type":"Point"}
}