{
  "type": "Feature",
  "properties": {
    "addr:full":"23170 Thornhill Rd Orange VA 22960",
    "addr:postcode":"23170;22960",
    "addr:street":"Thornhill Rd",
    "iso:country":"US",
    "sg:address":"23170 Thornhill Rd",
    "sg:city":"Orange",
    "sg:classifiers":[
        {
            "category":"Building & Trades",
            "subcategory":"Construction",
            "type":"Services"
        }
    ],
    "sg:phone":"+1 540 854 4777",
    "sg:postcode":"22960",
    "sg:province":"VA",
    "sg:tags":[
        "residential"
    ],
    "wof:name":"Edward W Bowers Jr",
    "wof:placetype":"venue"
},
  "geometry": {"coordinates":[-77.967337,38.154678],"type":"Point"}
}