{
  "type": "Feature",
  "properties": {
    "addr:full":"1416 Black Walnut Ct Chesapeake VA 23322",
    "addr:housenumber":"1416",
    "addr:postcode":"23322",
    "addr:street":"Black Walnut Ct",
    "iso:country":"US",
    "sg:address":"1416 Black Walnut Ct",
    "sg:city":"Chesapeake",
    "sg:classifiers":[
        {
            "category":"Professional",
            "subcategory":"Business Services",
            "type":"Services"
        }
    ],
    "sg:phone":"+1 757 204 4280",
    "sg:postcode":"23322",
    "sg:province":"VA",
    "sg:tags":[
        "embroidery"
    ],
    "wof:name":"Jazzy Threads & Screen Prntng",
    "wof:placetype":"venue"
},
  "geometry": {"coordinates":[-76.14052700000001,36.654629],"type":"Point"}
}