{
  "type": "Feature",
  "properties": {
    "iso:country":"US",
    "sg:address":"1949 Lynnhaven Pkwy",
    "sg:city":"Virginia Beach",
    "sg:classifiers":[
        {
            "category":"Restaurant",
            "type":"Food & Drink"
        }
    ],
    "sg:phone":"+1 757 471 2100",
    "sg:postcode":"23453",
    "sg:province":"VA",
    "wof:name":"Captain K",
    "wof:placetype":"venue"
},
  "geometry": {"coordinates":[-76.118143,36.794278],"type":"Point"}
}