{
  "type": "Feature",
  "properties": {
    "addr:full":"700 S 6th Ave Hopewell VA 23860",
    "addr:housenumber":"700",
    "addr:postcode":"23860",
    "addr:street":"S 6Th Ave",
    "iso:country":"US",
    "sg:address":"700 S 6th Ave",
    "sg:city":"Hopewell",
    "sg:classifiers":[
        {
            "category":"Banks & Credit Unions",
            "subcategory":"Bank",
            "type":"Services"
        }
    ],
    "sg:phone":"+1 804 541 5589",
    "sg:postcode":"23860",
    "sg:province":"VA",
    "sg:tags":[
        "federally",
        "chartered"
    ],
    "wof:name":"Hopewell Chemical Federal CU",
    "wof:placetype":"venue"
},
  "geometry": {"coordinates":[-77.29012299999999,37.295055],"type":"Point"}
}