{
  "type": "Feature",
  "properties": {
    "addr:full":"2102 Hardy Rd Vinton VA 24179",
    "addr:housenumber":"2102",
    "addr:postcode":"24179",
    "addr:street":"Hardy Rd",
    "iso:country":"US",
    "sg:address":"2102 Hardy Rd",
    "sg:city":"Vinton",
    "sg:classifiers":[
        {
            "category":"Freight",
            "type":"Transportation"
        }
    ],
    "sg:phone":"+1 540 890 9414",
    "sg:postcode":"24179",
    "sg:province":"VA",
    "sg:tags":[
        "trucking"
    ],
    "wof:name":"Clement Brothers Trucking Inc",
    "wof:placetype":"venue"
},
  "geometry": {"coordinates":[-79.866258,37.267691],"type":"Point"}
}