{
  "type": "Feature",
  "properties": {
    "iso:country":"US",
    "sg:address":"2118 County Dr",
    "sg:city":"Petersburg",
    "sg:classifiers":[
        {
            "category":"Retail",
            "subcategory":"Auto Rental",
            "type":"Services"
        }
    ],
    "sg:phone":"+1 804 862 3392",
    "sg:postcode":"23803",
    "sg:province":"VA",
    "sg:tags":[
        "mobile",
        "home",
        "leasing"
    ],
    "wof:name":"A B Ford's Mobile Home Rntls",
    "wof:placetype":"venue"
},
  "geometry": {"coordinates":[-77.36774800000001,37.215786],"type":"Point"}
}