{
  "type": "Feature",
  "properties": {
    "addr:full":"3390 Harborwood Rd Salem VA 24153",
    "addr:housenumber":"3390",
    "addr:postcode":"24153",
    "addr:street":"Harborwood Rd",
    "iso:country":"US",
    "sg:address":"3390 Harborwood Rd",
    "sg:city":"Salem",
    "sg:classifiers":[
        {
            "category":"Shopping",
            "subcategory":"Computers & Home Electronics",
            "type":"Retail Goods"
        }
    ],
    "sg:phone":"+1 540 387 2719",
    "sg:postcode":"24153",
    "sg:province":"VA",
    "sg:tags":[
        "equipment",
        "dealer"
    ],
    "sg:website":"www.salemva.com",
    "wof:name":"A Computer Workshop Inc",
    "wof:placetype":"venue"
},
  "geometry": {"coordinates":[-80.105762,37.253504],"type":"Point"}
}