{
  "type": "Feature",
  "properties": {
    "iso:country":"US",
    "sg:address":"150 W Main St",
    "sg:city":"Danville",
    "sg:classifiers":[
        {
            "category":"Health Services",
            "subcategory":"Doctor",
            "type":"Services"
        }
    ],
    "sg:phone":"+1 434 799 3100",
    "sg:postcode":"24541",
    "sg:province":"VA",
    "sg:tags":[
        "physician",
        "surgeon"
    ],
    "wof:name":"Joel L Cohen MD",
    "wof:placetype":"venue"
},
  "geometry": {"coordinates":[-79.40712499999999,36.578914],"type":"Point"}
}