{
  "type": "Feature",
  "properties": {
    "iso:country":"US",
    "sg:address":"1315 Asbury Rd",
    "sg:city":"Richmond",
    "sg:classifiers":[
        {
            "category":"Professional",
            "type":"Services"
        }
    ],
    "sg:phone":"+1 804 740 5502",
    "sg:postcode":"23229",
    "sg:province":"VA",
    "wof:name":"F&F Inc",
    "wof:placetype":"venue"
},
  "geometry": {"coordinates":[-77.58646,37.605626],"type":"Point"}
}