{
  "type": "Feature",
  "properties": {
    "addr:full":"2640 Lacey Spring Rd Broadway VA 22815",
    "addr:housenumber":"2640",
    "addr:postcode":"22815",
    "addr:street":"Lacey Spring Rd",
    "iso:country":"US",
    "sg:address":"2640 Lacey Spring Rd",
    "sg:city":"Broadway",
    "sg:classifiers":[
        {
            "category":"Farming",
            "subcategory":"Livestock Farm",
            "type":"Manufacturing & Wholesale Goods"
        }
    ],
    "sg:phone":"+1 540 896 1239",
    "sg:postcode":"22815",
    "sg:province":"VA",
    "sg:tags":[
        "animal",
        "general"
    ],
    "wof:name":"Len Peters",
    "wof:placetype":"venue"
},
  "geometry": {"coordinates":[-78.803386,38.559883],"type":"Point"}
}