{
  "type": "Feature",
  "properties": {
    "addr:full":"34 Catoctin Cir SE Leesburg VA 20175",
    "addr:housenumber":"34",
    "addr:postcode":"20175",
    "addr:street":"Catoctin Cir Se",
    "iso:country":"US",
    "sg:address":"34 Catoctin Cir SE",
    "sg:city":"Leesburg",
    "sg:classifiers":[
        {
            "category":"Restaurant",
            "type":"Food & Drink"
        }
    ],
    "sg:menulink":"http://www.allmenus.com/va/leesburg/68708-vocelli-pizza/menu/",
    "sg:phone":"+1 800 707 1111",
    "sg:postcode":"20175",
    "sg:province":"VA",
    "sg:tags":[
        "american",
        "italian",
        "pizza"
    ],
    "wof:name":"Vocelli Pizza",
    "wof:placetype":"venue"
},
  "geometry": {"coordinates":[-77.565061,39.106934],"type":"Point"}
}