{
  "type": "Feature",
  "properties": {
    "iso:country":"US",
    "sg:address":"209 Fathom Cove",
    "sg:city":"Stafford",
    "sg:classifiers":[
        {
            "category":"Professional",
            "subcategory":"Computer Services",
            "type":"Services"
        }
    ],
    "sg:phone":"+1 540 720 1883",
    "sg:postcode":"22554",
    "sg:province":"VA",
    "sg:tags":[
        "prepackaged",
        "software"
    ],
    "wof:name":"Office Creations",
    "wof:placetype":"venue"
},
  "geometry": {"coordinates":[-77.370349,38.465674],"type":"Point"}
}