{
  "type": "Feature",
  "properties": {
    "addr:full":"13135 Lee Jackson Memorial Hwy Fairfax VA 22033",
    "addr:housenumber":"13135",
    "addr:postcode":"22033",
    "addr:street":"Lee Jackson Memorial Hwy",
    "iso:country":"US",
    "sg:address":"13135 Lee Jackson Memorial Hwy",
    "sg:city":"Fairfax",
    "sg:classifiers":[
        {
            "category":"Professional",
            "subcategory":"Employment Agencies",
            "type":"Services"
        }
    ],
    "sg:phone":"+1 703 803 0000",
    "sg:postcode":"22033",
    "sg:province":"VA",
    "sg:tags":[
        "consultant",
        "outplacement"
    ],
    "wof:name":"Employment Commission",
    "wof:placetype":"venue"
},
  "geometry": {"coordinates":[-77.39773,38.881024],"type":"Point"}
}