{
  "type": "Feature",
  "properties": {
    "addr:full":"1610 Carl D Silver Pkwy Fredericksburg VA 22401",
    "addr:housenumber":"1610",
    "addr:postcode":"22401",
    "addr:street":"Carl D Silver Pkwy",
    "iso:country":"US",
    "sg:address":"1610 Carl D Silver Pkwy",
    "sg:city":"Fredericksburg",
    "sg:classifiers":[
        {
            "category":"Retail",
            "subcategory":"Car Wash",
            "type":"Services"
        }
    ],
    "sg:phone":"+1 540 785 3737",
    "sg:postcode":"22401",
    "sg:province":"VA",
    "sg:tags":[
        "polishing",
        "carwash",
        "washing"
    ],
    "wof:name":"Sante Fe Car Wash & Social CLB",
    "wof:placetype":"venue"
},
  "geometry": {"coordinates":[-77.50946999999999,38.305187],"type":"Point"}
}