{
  "type": "Feature",
  "properties": {
    "iso:country":"US",
    "sg:address":"236 Old Courthouse Rd NE",
    "sg:city":"Vienna",
    "sg:classifiers":[
        {
            "category":"Professional",
            "subcategory":"Computer Services",
            "type":"Services"
        }
    ],
    "sg:phone":"+1 703 236 2600",
    "sg:postcode":"22180",
    "sg:province":"VA",
    "sg:tags":[
        "internet"
    ],
    "wof:name":"Data Bid Com",
    "wof:placetype":"venue"
},
  "geometry": {"coordinates":[-77.24391300000001,38.916632],"type":"Point"}
}