{
  "type": "Feature",
  "properties": {
    "addr:full":"4633 Sleepy Hole Rd Suffolk VA 23435",
    "addr:housenumber":"4633",
    "addr:postcode":"23435",
    "addr:street":"Sleepy Hole Rd",
    "iso:country":"US",
    "sg:address":"4633 Sleepy Hole Rd",
    "sg:city":"Suffolk",
    "sg:classifiers":[
        {
            "category":"Organizations",
            "subcategory":"Religious Organization",
            "type":"Services"
        }
    ],
    "sg:phone":"+1 757 538 3446",
    "sg:postcode":"23435",
    "sg:province":"VA",
    "wof:name":"New Emanuel Church of Christ",
    "wof:placetype":"venue"
},
  "geometry": {"coordinates":[-76.512691,36.832488],"type":"Point"}
}