{
  "type": "Feature",
  "properties": {
    "iso:country":"US",
    "sg:address":"131 Walker St",
    "sg:city":"Lexington",
    "sg:classifiers":[
        {
            "category":"Government",
            "subcategory":"Office",
            "type":"Public Place"
        }
    ],
    "sg:phone":"+1 540 463 7136",
    "sg:postcode":"24450",
    "sg:province":"VA",
    "sg:tags":[
        "administrative",
        "program",
        "health"
    ],
    "wof:name":"Officer Water Programs",
    "wof:placetype":"venue"
},
  "geometry": {"coordinates":[-79.436059,37.778373],"type":"Point"}
}