{
  "type": "Feature",
  "properties": {
    "iso:country":"US",
    "sg:address":"8897 Trottinridge Rd",
    "sg:city":"Chase City",
    "sg:classifiers":[
        {
            "category":"Home & Garden",
            "subcategory":"Garden Supply",
            "type":"Retail Goods"
        }
    ],
    "sg:phone":"+1 434 372 3548",
    "sg:postcode":"23924",
    "sg:province":"VA",
    "sg:tags":[
        "potted",
        "plant"
    ],
    "wof:name":"Grant Trees House",
    "wof:placetype":"venue"
},
  "geometry": {"coordinates":[-78.550336,36.780187],"type":"Point"}
}