{
  "type": "Feature",
  "properties": {
    "iso:country":"US",
    "sg:address":"29 N Augusta St",
    "sg:city":"Staunton",
    "sg:classifiers":[
        {
            "category":"Restaurant",
            "type":"Food & Drink"
        }
    ],
    "sg:phone":"+1 540 213 0606",
    "sg:postcode":"24401",
    "sg:province":"VA",
    "sg:tags":[
        "eating"
    ],
    "wof:name":"Dining Room",
    "wof:placetype":"venue"
},
  "geometry": {"coordinates":[-79.072588,38.1497],"type":"Point"}
}