{
  "type": "Feature",
  "properties": {
    "addr:full":"5415 Easton Dr Springfield VA 22151",
    "addr:housenumber":"5415",
    "addr:postcode":"22151",
    "addr:street":"Easton Dr",
    "iso:country":"US",
    "sg:address":"5415 Easton Dr",
    "sg:city":"Springfield",
    "sg:classifiers":[
        {
            "category":"Wholesale",
            "subcategory":"Computers",
            "type":"Manufacturing & Wholesale Goods"
        }
    ],
    "sg:phone":"+1 703 866 0000",
    "sg:postcode":"22151",
    "sg:province":"VA",
    "sg:tags":[
        "pr",
        "fiber",
        "optic",
        "communication",
        "datum",
        "distributor"
    ],
    "wof:name":"Combyte U S A",
    "wof:placetype":"venue"
},
  "geometry": {"coordinates":[-77.195243,38.804827],"type":"Point"}
}