{
  "type": "Feature",
  "properties": {
    "iso:country":"US",
    "sg:address":"1228 Southam Dr",
    "sg:city":"Richmond",
    "sg:classifiers":[
        {
            "category":"Building & Trades",
            "subcategory":"Plumbing",
            "type":"Services"
        }
    ],
    "sg:phone":"+1 804 833 3725",
    "sg:postcode":"23235",
    "sg:province":"VA",
    "sg:tags":[
        "plumbing",
        "control",
        "gas"
    ],
    "wof:name":"Mechanical Services LLC",
    "wof:placetype":"venue"
},
  "geometry": {"coordinates":[-77.53696600000001,37.516591],"type":"Point"}
}