{
  "type": "Feature",
  "properties": {
    "iso:country":"US",
    "sg:address":"9700 Salem Church Rd",
    "sg:city":"Richmond",
    "sg:classifiers":[
        {
            "category":"Education",
            "subcategory":"School",
            "type":"Public Place"
        }
    ],
    "sg:phone":"+1 804 768 6225",
    "sg:postcode":"23237",
    "sg:province":"VA",
    "wof:name":"Salem Church Middle School",
    "wof:placetype":"venue"
},
  "geometry": {"coordinates":[-77.486458,37.382351],"type":"Point"}
}