{
  "type": "Feature",
  "properties": {
    "addr:full":"5380 Weblin Farm Rd Virginia Beach VA 23455",
    "addr:housenumber":"5380",
    "addr:postcode":"23455",
    "addr:street":"Weblin Farm Rd",
    "iso:country":"US",
    "sg:address":"5380 Weblin Farm Rd",
    "sg:city":"Virginia Beach",
    "sg:classifiers":[
        {
            "category":"Arts & Performance",
            "subcategory":"Theater",
            "type":"Entertainment"
        }
    ],
    "sg:phone":"+1 757 499 6211",
    "sg:postcode":"23455",
    "sg:province":"VA",
    "sg:tags":[
        "musician"
    ],
    "wof:name":"Foreman Ballast Studio",
    "wof:placetype":"venue"
},
  "geometry": {"coordinates":[-76.16839,36.876682],"type":"Point"}
}