{
  "type": "Feature",
  "properties": {
    "addr:full":"1240 Harbor View Cir Colonial Beach VA 22443",
    "addr:housenumber":"1240",
    "addr:postcode":"22443",
    "addr:street":"Harbor View Cir Colonial",
    "iso:country":"US",
    "sg:address":"1240 Harbor View Cir",
    "sg:city":"Colonial Beach",
    "sg:classifiers":[
        {
            "category":"Building & Trades",
            "subcategory":"Construction",
            "type":"Services"
        }
    ],
    "sg:phone":"+1 804 224 2802",
    "sg:postcode":"22443",
    "sg:province":"VA",
    "sg:tags":[
        "excavation",
        "operator",
        "contractor",
        "local",
        "trucking"
    ],
    "wof:name":"William H Selph Hauling Inc",
    "wof:placetype":"venue"
},
  "geometry": {"coordinates":[-76.97148900000001,38.205526],"type":"Point"}
}