{
  "type": "Feature",
  "properties": {
    "addr:full":"3210 Atlantic Ave Virginia Beach VA 23451",
    "addr:housenumber":"3210",
    "addr:postcode":"23451",
    "addr:street":"Atlantic Ave",
    "iso:country":"US",
    "sg:address":"3210 Atlantic Ave",
    "sg:city":"Virginia Beach",
    "sg:classifiers":[
        {
            "category":"Real Estate",
            "subcategory":"Real Estate Operator",
            "type":"Services"
        }
    ],
    "sg:phone":"+1 757 428 4327",
    "sg:postcode":"23451",
    "sg:province":"VA",
    "sg:tags":[
        "property",
        "commercial"
    ],
    "wof:name":"Ocean Waves Ltd",
    "wof:placetype":"venue"
},
  "geometry": {"coordinates":[-75.978764,36.861142],"type":"Point"}
}