{
  "type": "Feature",
  "properties": {
    "addr:full":"223 Commerce St Smithfield VA 23430",
    "addr:housenumber":"223",
    "addr:postcode":"23430",
    "addr:street":"Commerce St",
    "iso:country":"US",
    "sg:address":"223 Commerce St",
    "sg:city":"Smithfield",
    "sg:classifiers":[
        {
            "category":"Arts & Performance",
            "subcategory":"Arts Center",
            "type":"Entertainment"
        }
    ],
    "sg:phone":"+1 757 357 2501",
    "sg:postcode":"23430",
    "sg:province":"VA",
    "sg:tags":[
        "performing"
    ],
    "wof:name":"Cotton Gin Theatre",
    "wof:placetype":"venue"
},
  "geometry": {"coordinates":[-76.630589,36.984812],"type":"Point"}
}