{
  "type": "Feature",
  "properties": {
    "iso:country":"US",
    "sg:address":"733 Sedgefield Dr",
    "sg:city":"Newport News",
    "sg:classifiers":[
        {
            "category":"Building & Trades",
            "subcategory":"Construction",
            "type":"Services"
        }
    ],
    "sg:phone":"+1 757 329 5810",
    "sg:postcode":"23605",
    "sg:province":"VA",
    "sg:tags":[
        "residential"
    ],
    "wof:name":"Atlantis Construction LLC",
    "wof:placetype":"venue"
},
  "geometry": {"coordinates":[-76.45357300000001,37.041949],"type":"Point"}
}