{
  "type": "Feature",
  "properties": {
    "addr:full":"5917 Harrison Rd Fredericksburg VA 22407",
    "addr:housenumber":"5917",
    "addr:postcode":"22407",
    "addr:street":"Harrison Rd",
    "iso:country":"US",
    "sg:address":"5917 Harrison Rd",
    "sg:city":"Fredericksburg",
    "sg:classifiers":[
        {
            "category":"Utilities",
            "subcategory":"Refuse",
            "type":"Services"
        }
    ],
    "sg:phone":"+1 540 786 8377",
    "sg:postcode":"22407",
    "sg:province":"VA",
    "sg:tags":[
        "system"
    ],
    "wof:name":"Spotsylvania County Landfill",
    "wof:placetype":"venue"
},
  "geometry": {"coordinates":[-77.53890199999999,38.269988],"type":"Point"}
}