{
  "type": "Feature",
  "properties": {
    "addr:full":"1201 Shawn Dr Virginia Beach VA 23453",
    "addr:housenumber":"1201",
    "addr:postcode":"23453",
    "addr:street":"Shawn Dr",
    "iso:country":"US",
    "sg:address":"1201 Shawn Dr",
    "sg:city":"Virginia Beach",
    "sg:classifiers":[
        {
            "category":"Building & Trades",
            "subcategory":"Plumbing",
            "type":"Services"
        }
    ],
    "sg:phone":"+1 757 430 4440",
    "sg:postcode":"23453",
    "sg:province":"VA",
    "sg:tags":[
        "heating",
        "contractor"
    ],
    "wof:name":"Bear Comfort Heating & Air",
    "wof:placetype":"venue"
},
  "geometry": {"coordinates":[-76.098293,36.799577],"type":"Point"}
}