{
  "type": "Feature",
  "properties": {
    "iso:country":"US",
    "sg:address":"4500 W Hundred Rd",
    "sg:city":"Chester",
    "sg:classifiers":[
        {
            "category":"Wholesale",
            "subcategory":"Auto Parts",
            "type":"Manufacturing & Wholesale Goods"
        }
    ],
    "sg:phone":"+1 804 748 6354",
    "sg:postcode":"23831",
    "sg:province":"VA",
    "sg:tags":[
        "supply"
    ],
    "wof:name":"NAPA Auto Parts",
    "wof:placetype":"venue"
},
  "geometry": {"coordinates":[-77.45039199999999,37.353649],"type":"Point"}
}