{
  "type": "Feature",
  "properties": {
    "addr:full":"5946 Centreville Crest Ln Centreville VA 20121",
    "addr:housenumber":"5946",
    "addr:postcode":"20121",
    "addr:street":"Centreville Crest Ln",
    "iso:country":"US",
    "sg:address":"5946 Centreville Crest Ln",
    "sg:city":"Centreville",
    "sg:classifiers":[
        {
            "category":"Shopping",
            "type":"Retail Goods"
        }
    ],
    "sg:phone":"+1 703 815 7754",
    "sg:postcode":"20121",
    "sg:province":"VA",
    "sg:tags":[
        "merchandise"
    ],
    "wof:name":"J Art Studio",
    "wof:placetype":"venue"
},
  "geometry": {"coordinates":[-77.43441300000001,38.836726],"type":"Point"}
}