{
  "type": "Feature",
  "properties": {
    "addr:full":"729 Woodland Dr Harrisonburg VA 22801",
    "addr:housenumber":"729",
    "addr:postcode":"22801",
    "addr:street":"Woodland Dr",
    "iso:country":"US",
    "sg:address":"729 Woodland Dr",
    "sg:city":"Harrisonburg",
    "sg:classifiers":[
        {
            "category":"Retail",
            "subcategory":"Portrait Studio",
            "type":"Services"
        }
    ],
    "sg:phone":"+1 540 746 4286",
    "sg:postcode":"22801",
    "sg:province":"VA",
    "sg:tags":[
        "photographer"
    ],
    "wof:name":"Jason Michael Photography",
    "wof:placetype":"venue"
},
  "geometry": {"coordinates":[-78.85667599999999,38.424069],"type":"Point"}
}