{
  "type": "Feature",
  "properties": {
    "addr:full":"4415 Lees Corner Rd Chantilly VA 20151",
    "addr:housenumber":"4415",
    "addr:postcode":"20151",
    "addr:street":"Lees Corner Rd",
    "iso:country":"US",
    "sg:address":"4415 Lees Corner Rd",
    "sg:city":"Chantilly",
    "sg:classifiers":[
        {
            "category":"Professional",
            "subcategory":"Management & Consulting",
            "type":"Services"
        }
    ],
    "sg:phone":"+1 703 263 0456",
    "sg:postcode":"20151",
    "sg:province":"VA",
    "sg:tags":[
        "business"
    ],
    "wof:name":"Telex Cmmnications E Coast Reg",
    "wof:placetype":"venue"
},
  "geometry": {"coordinates":[-77.42328999999999,38.877675],"type":"Point"}
}