{
  "type": "Feature",
  "properties": {
    "addr:full":"7533 Gary Rd Manassas VA 20109",
    "addr:housenumber":"7533",
    "addr:postcode":"20109",
    "addr:street":"Gary Rd",
    "iso:country":"US",
    "sg:address":"7533 Gary Rd",
    "sg:city":"Manassas",
    "sg:classifiers":[
        {
            "category":"Building & Trades",
            "subcategory":"Construction",
            "type":"Services"
        }
    ],
    "sg:phone":"+1 703 830 1506",
    "sg:postcode":"20109",
    "sg:province":"VA",
    "sg:tags":[
        "drywall",
        "painting",
        "contractor"
    ],
    "wof:name":"Johnson Drywall & Construction",
    "wof:placetype":"venue"
},
  "geometry": {"coordinates":[-77.50142099999999,38.801177],"type":"Point"}
}