{
  "type": "Feature",
  "properties": {
    "iso:country":"US",
    "sg:address":"Arlington National Cemetery Meade St and Marshall Dr",
    "sg:city":"Arlington",
    "sg:classifiers":[
        {
            "category":"Landmark",
            "subcategory":"Historic",
            "type":"Public Place"
        }
    ],
    "sg:postcode":"22111",
    "sg:province":"VA",
    "sg:tags":[
        "building",
        "historical"
    ],
    "wof:name":"Marine Corps War Memorial",
    "wof:placetype":"venue"
},
  "geometry": {"coordinates":[-77.071772,38.887661],"type":"Point"}
}