{
  "type": "Feature",
  "properties": {
    "addr:full":"1612 Ivy Ave Newport News VA 23607",
    "addr:housenumber":"1612",
    "addr:postcode":"23607",
    "addr:street":"Ivy Ave",
    "iso:country":"US",
    "sg:address":"1612 Ivy Ave",
    "sg:city":"Newport News",
    "sg:classifiers":[
        {
            "category":"Organizations",
            "subcategory":"Religious Organization",
            "type":"Services"
        }
    ],
    "sg:phone":"+1 757 244 0760",
    "sg:postcode":"23607",
    "sg:province":"VA",
    "wof:name":"United Bibleway Temple",
    "wof:placetype":"venue"
},
  "geometry": {"coordinates":[-76.415963,36.976833],"type":"Point"}
}