{
  "type": "Feature",
  "properties": {
    "iso:country":"US",
    "sg:address":"3840 Forestwood Ct",
    "sg:city":"Virginia Beach",
    "sg:classifiers":[
        {
            "category":"Professional",
            "subcategory":"Business Services",
            "type":"Services"
        }
    ],
    "sg:phone":"+1 757 927 5700",
    "sg:postcode":"23453",
    "sg:province":"VA",
    "wof:name":"Digital Hooks Recording Studio",
    "wof:placetype":"venue"
},
  "geometry": {"coordinates":[-76.10807699999999,36.803728],"type":"Point"}
}