{
  "type": "Feature",
  "properties": {
    "addr:full":"13101 Jefferson Davis Hwy Chester VA 23831",
    "addr:housenumber":"13101",
    "addr:postcode":"23831",
    "addr:street":"Jefferson Davis Hwy",
    "iso:country":"US",
    "sg:address":"13101 Jefferson Davis Hwy",
    "sg:city":"Chester",
    "sg:classifiers":[
        {
            "category":"Communications",
            "subcategory":"Radio Station",
            "type":"Services"
        }
    ],
    "sg:phone":"+1 804 796 4053",
    "sg:postcode":"23831",
    "sg:province":"VA",
    "sg:tags":[
        "broadcast",
        "fund",
        "raising",
        "social"
    ],
    "sg:website":"http://www.jtcc.edu",
    "wof:name":"J T C C Foundation",
    "wof:placetype":"venue"
},
  "geometry": {"coordinates":[-77.410759,37.347488],"type":"Point"}
}