{
  "type": "Feature",
  "properties": {
    "addr:full":"815 Railroad Ave Bedford VA 24523",
    "addr:housenumber":"815",
    "addr:postcode":"24523",
    "addr:street":"Railroad Ave",
    "iso:country":"US",
    "sg:address":"815 Railroad Ave",
    "sg:city":"Bedford",
    "sg:classifiers":[
        {
            "category":"Restaurant",
            "type":"Food & Drink"
        }
    ],
    "sg:phone":"+1 540 587 9366",
    "sg:postcode":"24523",
    "sg:province":"VA",
    "sg:tags":[
        "eating"
    ],
    "wof:name":"Fultons Restaurant",
    "wof:placetype":"venue"
},
  "geometry": {"coordinates":[-79.510293,37.334881],"type":"Point"}
}