{
  "type": "Feature",
  "properties": {
    "addr:full":"330 Old Jonesboro Rd Bristol VA 37620",
    "addr:housenumber":"330",
    "addr:postcode":"37620",
    "addr:street":"Old Jonesboro Rd",
    "iso:country":"US",
    "sg:address":"330 Old Jonesboro Rd",
    "sg:city":"Bristol",
    "sg:classifiers":[
        {
            "category":"Personal",
            "subcategory":"Beauty Salon",
            "type":"Services"
        }
    ],
    "sg:phone":"+1 423 878 7300",
    "sg:postcode":"37620",
    "sg:province":"VA",
    "wof:name":"Beauty Above & Above",
    "wof:placetype":"venue"
},
  "geometry": {"coordinates":[-82.161799,36.547431],"type":"Point"}
}