{
  "type": "Feature",
  "properties": {
    "addr:full":"2402 Oakville St Alexandria VA 22301",
    "addr:housenumber":"2402",
    "addr:postcode":"22301",
    "addr:street":"Oakville St",
    "iso:country":"US",
    "sg:address":"2402 Oakville St",
    "sg:city":"Alexandria",
    "sg:classifiers":[
        {
            "category":"Retail",
            "subcategory":"Auto Repair",
            "type":"Services"
        }
    ],
    "sg:phone":"+1 703 548 5111",
    "sg:postcode":"22301",
    "sg:province":"VA",
    "sg:tags":[
        "body",
        "shop",
        "painting",
        "repairing",
        "automobile"
    ],
    "wof:name":"Action Auto Body Inc",
    "wof:placetype":"venue"
},
  "geometry": {"coordinates":[-77.05120100000001,38.827999],"type":"Point"}
}