{
  "type": "Feature",
  "properties": {
    "addr:full":"633 Chestnut Grove Rd Winchester VA 22603",
    "addr:housenumber":"633",
    "addr:postcode":"22603",
    "addr:street":"Chestnut Grove Rd",
    "iso:country":"US",
    "sg:address":"633 Chestnut Grove Rd",
    "sg:city":"Winchester",
    "sg:classifiers":[
        {
            "category":"Professional",
            "subcategory":"Business Services",
            "type":"Services"
        }
    ],
    "sg:phone":"+1 540 888 3778",
    "sg:postcode":"22603",
    "sg:province":"VA",
    "sg:tags":[
        "excavating",
        "trucking"
    ],
    "wof:name":"Dehaven Excavating",
    "wof:placetype":"venue"
},
  "geometry": {"coordinates":[-78.238328,39.282604],"type":"Point"}
}