{
  "type": "Feature",
  "properties": {
    "iso:country":"US",
    "sg:address":"12120 Captiva Ct",
    "sg:city":"Reston",
    "sg:classifiers":[
        {
            "category":"Real Estate",
            "subcategory":"Real Estate Agent",
            "type":"Services"
        }
    ],
    "sg:phone":"+1 703 620 1663",
    "sg:postcode":"20191",
    "sg:province":"VA",
    "wof:name":"New Era Transportation Inc",
    "wof:placetype":"venue"
},
  "geometry": {"coordinates":[-77.366415,38.943085],"type":"Point"}
}