{
  "type": "Feature",
  "properties": {
    "iso:country":"US",
    "sg:address":"4110 Chain Bridge Rd",
    "sg:city":"Fairfax",
    "sg:classifiers":[
        {
            "category":"Government",
            "subcategory":"Police Station",
            "type":"Public Place"
        }
    ],
    "sg:phone":"+1 703 246 3261",
    "sg:postcode":"22030",
    "sg:province":"VA",
    "sg:tags":[
        "protection"
    ],
    "wof:name":"Sheriffs Dept",
    "wof:placetype":"venue"
},
  "geometry": {"coordinates":[-77.308352,38.843256],"type":"Point"}
}