{
  "type": "Feature",
  "properties": {
    "iso:country":"US",
    "sg:address":"1155 Ivy St",
    "sg:city":"Waynesboro",
    "sg:classifiers":[
        {
            "category":"Wholesale",
            "subcategory":"Home Furnishings",
            "type":"Manufacturing & Wholesale Goods"
        }
    ],
    "sg:phone":"+1 540 943 2911",
    "sg:postcode":"22980",
    "sg:province":"VA",
    "sg:tags":[
        "tile",
        "carpet",
        "floor",
        "vinyl",
        "covering"
    ],
    "wof:name":"Shenandoah Crpt Interiors Ltd",
    "wof:placetype":"venue"
},
  "geometry": {"coordinates":[-78.894531,38.076692],"type":"Point"}
}