{
  "type": "Feature",
  "properties": {
    "iso:country":"US",
    "sg:address":"1360 Beverly Rd",
    "sg:city":"Mc Lean",
    "sg:classifiers":[
        {
            "category":"Professional",
            "subcategory":"Computer Services",
            "type":"Services"
        },
        {
            "category":"Banks & Credit Unions",
            "subcategory":"Bank",
            "type":"Services"
        }
    ],
    "sg:phone":"+1 703 761 3148",
    "sg:postcode":"22101",
    "sg:province":"VA",
    "sg:tags":[
        "preparation",
        "for",
        "loan",
        "lender",
        "real estate",
        "document",
        "mortgage"
    ],
    "sg:website":"www.mbspro.com",
    "wof:name":"Mortgage Banking Systems",
    "wof:placetype":"venue"
},
  "geometry": {"coordinates":[-77.178983,38.93588],"type":"Point"}
}