{
  "type": "Feature",
  "properties": {
    "addr:full":"123 Shady Oak Ln Forest VA 24551",
    "addr:housenumber":"123",
    "addr:postcode":"24551",
    "addr:street":"Shady Oak Ln",
    "iso:country":"US",
    "sg:address":"123 Shady Oak Ln",
    "sg:city":"Forest",
    "sg:classifiers":[
        {
            "category":"Professional",
            "subcategory":"Detective & Security Services",
            "type":"Services"
        }
    ],
    "sg:phone":"+1 434 525 0355",
    "sg:postcode":"24551",
    "sg:province":"VA",
    "sg:tags":[
        "information",
        "bureau"
    ],
    "wof:name":"First Class Sweeping Serivice",
    "wof:placetype":"venue"
},
  "geometry": {"coordinates":[-79.290936,37.333274],"type":"Point"}
}