{
  "type": "Feature",
  "properties": {
    "addr:full":"279 S Main St Kilmarnock VA 22482",
    "addr:housenumber":"279",
    "addr:postcode":"22482",
    "addr:street":"S Main St",
    "iso:country":"US",
    "sg:address":"279 S Main St",
    "sg:city":"Kilmarnock",
    "sg:classifiers":[
        {
            "category":"Local Transit",
            "type":"Transportation"
        }
    ],
    "sg:phone":"+1 804 435 0141",
    "sg:postcode":"22482",
    "sg:province":"VA",
    "wof:name":"Bay Transit",
    "wof:placetype":"venue"
},
  "geometry": {"coordinates":[-76.37699600000001,37.702348],"type":"Point"}
}