{
  "type": "Feature",
  "properties": {
    "addr:full":"1200 N Timber Ridge Rd Cross Junction VA 22625",
    "addr:housenumber":"1200",
    "addr:postcode":"22625",
    "addr:street":"N Timber Ridge Rd",
    "iso:country":"US",
    "sg:address":"1200 N Timber Ridge Rd",
    "sg:city":"Cross Junction",
    "sg:classifiers":[
        {
            "category":"Retail",
            "subcategory":"Animal Services",
            "type":"Services"
        }
    ],
    "sg:phone":"+1 540 888 4868",
    "sg:postcode":"22625",
    "sg:province":"VA",
    "wof:name":"Heartland Retrivers",
    "wof:placetype":"venue"
},
  "geometry": {"coordinates":[-78.291149,39.427511],"type":"Point"}
}