{
  "type": "Feature",
  "properties": {
    "addr:full":"5340 Snead Rd Richmond VA 23224",
    "addr:housenumber":"5340",
    "addr:postcode":"23224",
    "addr:street":"Snead Rd",
    "iso:country":"US",
    "sg:address":"5340 Snead Rd",
    "sg:city":"Richmond",
    "sg:classifiers":[
        {
            "category":"Communications",
            "subcategory":"Film & Video Production",
            "type":"Services"
        },
        {
            "category":"Professional",
            "subcategory":"Art Services",
            "type":"Services"
        }
    ],
    "sg:phone":"+1 804 276 1801",
    "sg:postcode":"23224",
    "sg:province":"VA",
    "sg:tags":[
        "animation",
        "producer",
        "artist"
    ],
    "wof:name":"Van Allen Animation",
    "wof:placetype":"venue"
},
  "geometry": {"coordinates":[-77.493279,37.476398],"type":"Point"}
}