{
  "type": "Feature",
  "properties": {
    "addr:full":"8540 Terminal Rd Lorton VA 22079",
    "addr:housenumber":"8540",
    "addr:postcode":"22079",
    "addr:street":"Terminal Rd",
    "iso:country":"US",
    "sg:address":"8540 Terminal Rd",
    "sg:city":"Lorton",
    "sg:classifiers":[
        {
            "category":"Government",
            "subcategory":"Police Station",
            "type":"Public Place"
        }
    ],
    "sg:phone":"+1 703 632 6000",
    "sg:postcode":"22079",
    "sg:province":"VA",
    "sg:tags":[
        "protection"
    ],
    "wof:name":"FBI",
    "wof:placetype":"venue"
},
  "geometry": {"coordinates":[-77.197293,38.726528],"type":"Point"}
}