{
  "type": "Feature",
  "properties": {
    "addr:full":"450 Tye River Tpke Vesuvius VA 24483",
    "addr:housenumber":"450",
    "addr:postcode":"24483",
    "addr:street":"Tye River Tpke Vesuvius",
    "iso:country":"US",
    "sg:address":"450 Tye River Tpke",
    "sg:city":"Vesuvius",
    "sg:classifiers":[
        {
            "category":"Manufacturing",
            "subcategory":"Lumber",
            "type":"Manufacturing & Wholesale Goods"
        }
    ],
    "sg:phone":"+1 540 377 6317",
    "sg:postcode":"24483",
    "sg:province":"VA",
    "sg:tags":[
        "forestry"
    ],
    "wof:name":"Gary Harsh",
    "wof:placetype":"venue"
},
  "geometry": {"coordinates":[-79.194215,37.914955],"type":"Point"}
}