{
  "type": "Feature",
  "properties": {
    "iso:country":"US",
    "sg:address":"3430 Lauderdale Dr",
    "sg:city":"Richmond",
    "sg:classifiers":[
        {
            "category":"Health Services",
            "subcategory":"Doctor",
            "type":"Services"
        }
    ],
    "sg:phone":"+1 804 364 4400",
    "sg:postcode":"23233",
    "sg:province":"VA",
    "sg:tags":[
        "physician",
        "surgeon"
    ],
    "wof:name":"Associates In Pediatrics",
    "wof:placetype":"venue"
},
  "geometry": {"coordinates":[-77.628775,37.642973],"type":"Point"}
}