{
  "type": "Feature",
  "properties": {
    "addr:full":"96 Edward Wakefield Williamsburg VA 23185",
    "addr:housenumber":"96",
    "addr:postcode":"23185",
    "addr:street":"Edward Wakefield",
    "iso:country":"US",
    "sg:address":"96 Edward Wakefield",
    "sg:city":"Williamsburg",
    "sg:classifiers":[
        {
            "category":"Professional",
            "subcategory":"Lawyer & Legal Services",
            "type":"Services"
        }
    ],
    "sg:phone":"+1 757 565 4440",
    "sg:postcode":"23185",
    "sg:province":"VA",
    "wof:name":"Timothy M Murphy P C",
    "wof:placetype":"venue"
},
  "geometry": {"coordinates":[-76.67952099999999,37.243249],"type":"Point"}
}