{
  "type": "Feature",
  "properties": {
    "addr:full":"316 N Fairfax St Alexandria VA 22314",
    "addr:housenumber":"316",
    "addr:postcode":"22314",
    "addr:street":"N Fairfax St",
    "iso:country":"US",
    "sg:address":"316 N Fairfax St",
    "sg:city":"Alexandria",
    "sg:classifiers":[
        {
            "category":"Manufacturing",
            "subcategory":"Electronics",
            "type":"Manufacturing & Wholesale Goods"
        }
    ],
    "sg:phone":"+1 703 548 4588",
    "sg:postcode":"22314",
    "sg:province":"VA",
    "sg:tags":[
        "equipment",
        "electronic",
        "supplies-wholesale",
        "manufacturer"
    ],
    "wof:name":"Echo Core Lab",
    "wof:placetype":"venue"
},
  "geometry": {"coordinates":[-77.042012,38.806967],"type":"Point"}
}