{
  "type": "Feature",
  "properties": {
    "addr:full":"513 Chapman St Ashland VA 23005",
    "addr:housenumber":"513",
    "addr:postcode":"23005",
    "addr:street":"Chapman St",
    "iso:country":"US",
    "sg:address":"513 Chapman St",
    "sg:city":"Ashland",
    "sg:classifiers":[
        {
            "category":"Building & Trades",
            "subcategory":"Landscaping Services",
            "type":"Services"
        }
    ],
    "sg:phone":"+1 804 798 4245",
    "sg:postcode":"23005",
    "sg:province":"VA",
    "wof:name":"Bremners Lawn Care",
    "wof:placetype":"venue"
},
  "geometry": {"coordinates":[-77.49068200000001,37.766281],"type":"Point"}
}