{
  "type": "Feature",
  "properties": {
    "iso:country":"US",
    "sg:address":"22721 Airpark Dr",
    "sg:city":"Petersburg",
    "sg:classifiers":[
        {
            "category":"Wholesale",
            "subcategory":"Machinery & Supplies",
            "type":"Manufacturing & Wholesale Goods"
        }
    ],
    "sg:phone":"+1 804 733 2183",
    "sg:postcode":"23803",
    "sg:province":"VA",
    "sg:tags":[
        "equipment",
        "mac",
        "construction",
        "mfg"
    ],
    "wof:name":"Geith Inc",
    "wof:placetype":"venue"
},
  "geometry": {"coordinates":[-77.513232,37.187586],"type":"Point"}
}