{
  "type": "Feature",
  "properties": {
    "addr:full":"100 Springfield Rd Danville VA 24540",
    "addr:housenumber":"100",
    "addr:postcode":"24540",
    "addr:street":"Springfield Rd",
    "iso:country":"US",
    "sg:address":"100 Springfield Rd",
    "sg:city":"Danville",
    "sg:classifiers":[
        {
            "category":"Education",
            "subcategory":"School",
            "type":"Public Place"
        }
    ],
    "sg:phone":"+1 434 724 2666",
    "sg:postcode":"24540",
    "sg:province":"VA",
    "wof:name":"Twin Springs Elementary School",
    "wof:placetype":"venue"
},
  "geometry": {"coordinates":[-79.377314,36.626512],"type":"Point"}
}