{
  "type": "Feature",
  "properties": {
    "addr:full":"9400 Huron Ave Richmond VA 23294",
    "addr:housenumber":"9400",
    "addr:postcode":"23294",
    "addr:street":"Huron Ave",
    "iso:country":"US",
    "sg:address":"9400 Huron Ave",
    "sg:city":"Richmond",
    "sg:classifiers":[
        {
            "category":"Arts & Performance",
            "subcategory":"Theater",
            "type":"Entertainment"
        }
    ],
    "sg:phone":"+1 804 270 7335",
    "sg:postcode":"23294",
    "sg:province":"VA",
    "sg:tags":[
        "group"
    ],
    "wof:name":"Unowho Entertainment",
    "wof:placetype":"venue"
},
  "geometry": {"coordinates":[-77.555555,37.643045],"type":"Point"}
}