{
  "type": "Feature",
  "properties": {
    "addr:full":"401 Twinridge Ln Richmond VA 23235",
    "addr:housenumber":"401",
    "addr:postcode":"23235",
    "addr:street":"Twinridge Ln",
    "iso:country":"US",
    "sg:address":"401 Twinridge Ln",
    "sg:city":"Richmond",
    "sg:classifiers":[
        {
            "category":"Social Services",
            "type":"Services"
        }
    ],
    "sg:phone":"+1 804 272 1984",
    "sg:postcode":"23235",
    "sg:province":"VA",
    "wof:name":"Karriem Khadijah",
    "wof:placetype":"venue"
},
  "geometry": {"coordinates":[-77.548666,37.499902],"type":"Point"}
}