{
  "type": "Feature",
  "properties": {
    "addr:full":"590 Fulton Dr Strasburg VA 22657",
    "addr:housenumber":"590",
    "addr:postcode":"22657",
    "addr:street":"Fulton Dr",
    "iso:country":"US",
    "sg:address":"590 Fulton Dr",
    "sg:city":"Strasburg",
    "sg:classifiers":[
        {
            "category":"Recreation",
            "type":"Entertainment"
        }
    ],
    "sg:phone":"+1 540 465 3673",
    "sg:postcode":"22657",
    "sg:province":"VA",
    "sg:tags":[
        "club",
        "membership"
    ],
    "wof:name":"Powhatan Ruritan Club",
    "wof:placetype":"venue"
},
  "geometry": {"coordinates":[-78.342876,38.988712],"type":"Point"}
}