{
  "type": "Feature",
  "properties": {
    "addr:full":"4033 Stonehenge Way Fairfax VA 22030",
    "addr:housenumber":"4033",
    "addr:postcode":"22030",
    "addr:street":"Stonehenge Way",
    "iso:country":"US",
    "sg:address":"4033 Stonehenge Way",
    "sg:city":"Fairfax",
    "sg:classifiers":[
        {
            "category":"Building & Trades",
            "subcategory":"Cleaning & Sanitation",
            "type":"Services"
        }
    ],
    "sg:phone":"+1 703 591 0665",
    "sg:postcode":"22030",
    "sg:province":"VA",
    "sg:tags":[
        "maintenance"
    ],
    "wof:name":"Sunshine Building Contractors",
    "wof:placetype":"venue"
},
  "geometry": {"coordinates":[-77.34409100000001,38.860408],"type":"Point"}
}