{
  "type": "Feature",
  "properties": {
    "addr:full":"4101 Eisenhower Ave Alexandria VA 22304",
    "addr:housenumber":"4101",
    "addr:postcode":"22304",
    "addr:street":"Eisenhower Ave",
    "iso:country":"US",
    "sg:address":"4101 Eisenhower Ave",
    "sg:city":"Alexandria",
    "sg:classifiers":[
        {
            "category":"Organizations",
            "subcategory":"Non-profit Organization",
            "type":"Services"
        }
    ],
    "sg:phone":"+1 703 838 4775",
    "sg:postcode":"22304",
    "sg:province":"VA",
    "wof:name":"Alexandria City Animal Shelter",
    "wof:placetype":"venue"
},
  "geometry": {"coordinates":[-77.102536,38.804439],"type":"Point"}
}