{
  "type": "Feature",
  "properties": {
    "addr:full":"4120 Brookriver Dr Glen Allen VA 23060",
    "addr:housenumber":"4120",
    "addr:postcode":"23060",
    "addr:street":"Brookriver Dr",
    "iso:country":"US",
    "sg:address":"4120 Brookriver Dr",
    "sg:city":"Glen Allen",
    "sg:classifiers":[
        {
            "category":"Travel",
            "subcategory":"Hotels & Motels",
            "type":"Entertainment"
        }
    ],
    "sg:phone":"+1 804 364 2000",
    "sg:postcode":"23060",
    "sg:province":"VA",
    "wof:name":"Candlewood Suites",
    "wof:placetype":"venue"
},
  "geometry": {"coordinates":[-77.60003399999999,37.649484],"type":"Point"}
}