{
  "type": "Feature",
  "properties": {
    "iso:country":"US",
    "sg:address":"1507 Richmond Rd",
    "sg:city":"Williamsburg",
    "sg:classifiers":[
        {
            "category":"Shopping",
            "subcategory":"Gifts & Souvenirs",
            "type":"Retail Goods"
        }
    ],
    "sg:phone":"+1 757 253 8007",
    "sg:postcode":"23185",
    "sg:province":"VA",
    "sg:tags":[
        "shop"
    ],
    "wof:name":"Souvenirs N Stuff",
    "wof:placetype":"venue"
},
  "geometry": {"coordinates":[-76.723119,37.29073],"type":"Point"}
}