{
  "type": "Feature",
  "properties": {
    "addr:full":"8626 Centreville Rd Manassas VA 20110",
    "addr:housenumber":"8626",
    "addr:postcode":"20110",
    "addr:street":"Centreville Rd",
    "iso:country":"US",
    "sg:address":"8626 Centreville Rd",
    "sg:city":"Manassas",
    "sg:classifiers":[
        {
            "category":"Insurance",
            "subcategory":"Insurance Agent",
            "type":"Services"
        }
    ],
    "sg:phone":"+1 703 361 1960",
    "sg:postcode":"20110",
    "sg:province":"VA",
    "wof:name":"Cannon Insurance Agency Inc",
    "wof:placetype":"venue"
},
  "geometry": {"coordinates":[-77.455474,38.767475],"type":"Point"}
}