{
  "type": "Feature",
  "properties": {
    "iso:country":"US",
    "sg:address":"4620 Hillbrook Dr",
    "sg:city":"Annandale",
    "sg:classifiers":[
        {
            "category":"Professional",
            "subcategory":"Management & Consulting",
            "type":"Services"
        }
    ],
    "sg:phone":"+1 703 941 3712",
    "sg:postcode":"22003",
    "sg:province":"VA",
    "wof:name":"Carol L Erwin Consultant",
    "wof:placetype":"venue"
},
  "geometry": {"coordinates":[-77.18765399999999,38.823067],"type":"Point"}
}