{
  "type": "Feature",
  "properties": {
    "iso:country":"US",
    "sg:address":"9800 Flagler Rd",
    "sg:city":"Fort Belvoir",
    "sg:classifiers":[
        {
            "category":"Professional",
            "type":"Services"
        }
    ],
    "sg:phone":"+1 703 781 9008",
    "sg:postcode":"22060",
    "sg:province":"VA",
    "wof:name":"BT Americas Inc",
    "wof:placetype":"venue"
},
  "geometry": {"coordinates":[-77.13212900000001,38.689493],"type":"Point"}
}