{
  "type": "Feature",
  "properties": {
    "addr:full":"310 Old Ivy Way Ste 104 Charlottesville VA 22903",
    "addr:housenumber":"310",
    "addr:postcode":"22903",
    "addr:street":"Old Ivy Way Ste 104",
    "iso:country":"US",
    "sg:address":"310 Old Ivy Way Ste 104",
    "sg:city":"Charlottesville",
    "sg:classifiers":[
        {
            "category":"Health Services",
            "subcategory":"Doctor",
            "type":"Services"
        }
    ],
    "sg:phone":"+1 434 243 6950",
    "sg:postcode":"22903",
    "sg:province":"VA",
    "wof:name":"Ryan Eileen DO",
    "wof:placetype":"venue"
},
  "geometry": {"coordinates":[-78.517577,38.046374],"type":"Point"}
}