{
  "type": "Feature",
  "properties": {
    "iso:country":"US",
    "sg:address":"710 County St",
    "sg:city":"Portsmouth",
    "sg:classifiers":[
        {
            "category":"Professional",
            "type":"Services"
        }
    ],
    "sg:phone":"+1 757 397 5335",
    "sg:postcode":"23704",
    "sg:province":"VA",
    "sg:tags":[
        "establishment"
    ],
    "wof:name":"Institute For Cosmetology",
    "wof:placetype":"venue"
},
  "geometry": {"coordinates":[-76.305533,36.833746],"type":"Point"}
}