{
  "type": "Feature",
  "properties": {
    "addr:full":"237 Wheatley Rd Danville VA 24540",
    "addr:housenumber":"237",
    "addr:postcode":"24540",
    "addr:street":"Wheatley Rd",
    "iso:country":"US",
    "sg:address":"237 Wheatley Rd",
    "sg:city":"Danville",
    "sg:classifiers":[
        {
            "category":"Manufacturing",
            "subcategory":"Retail Goods",
            "type":"Manufacturing & Wholesale Goods"
        }
    ],
    "sg:phone":"+1 434 836 5437",
    "sg:postcode":"24540",
    "sg:province":"VA",
    "sg:tags":[
        "product",
        "mfg"
    ],
    "wof:name":"Mfg International USA Inc",
    "wof:placetype":"venue"
},
  "geometry": {"coordinates":[-79.400211,36.636756],"type":"Point"}
}