{
  "type": "Feature",
  "properties": {
    "addr:full":"581 Winesap Rd Roanoke VA 24019",
    "addr:housenumber":"581",
    "addr:postcode":"24019",
    "addr:street":"Winesap Rd",
    "iso:country":"US",
    "sg:address":"581 Winesap Rd",
    "sg:city":"Roanoke",
    "sg:classifiers":[
        {
            "category":"Professional",
            "subcategory":"Management & Consulting",
            "type":"Services"
        }
    ],
    "sg:phone":"+1 540 562 4279",
    "sg:postcode":"24019",
    "sg:province":"VA",
    "sg:tags":[
        "marketing",
        "program"
    ],
    "wof:name":"Powell's Marketing Consultants",
    "wof:placetype":"venue"
},
  "geometry": {"coordinates":[-79.890804,37.350538],"type":"Point"}
}