{
  "type": "Feature",
  "properties": {
    "addr:full":"8124 Sudley Rd Manassas VA 20109",
    "addr:housenumber":"8124",
    "addr:postcode":"20109",
    "addr:street":"Sudley Rd",
    "iso:country":"US",
    "sg:address":"8124 Sudley Rd",
    "sg:city":"Manassas",
    "sg:classifiers":[
        {
            "category":"Restaurant",
            "type":"Food & Drink"
        }
    ],
    "sg:phone":"+1 703 331 0000",
    "sg:postcode":"20109",
    "sg:province":"VA",
    "sg:tags":[
        "pakistani",
        "indian",
        "halal"
    ],
    "wof:name":"Kabobs and Currys",
    "wof:placetype":"venue"
},
  "geometry": {"coordinates":[-77.50978499999999,38.778996],"type":"Point"}
}