{
  "type": "Feature",
  "properties": {
    "iso:country":"US",
    "sg:address":"7881 Wintercress Ln",
    "sg:city":"Springfield",
    "sg:classifiers":[
        {
            "category":"Professional",
            "subcategory":"Management & Consulting",
            "type":"Services"
        }
    ],
    "sg:phone":"+1 703 302 7249",
    "sg:postcode":"22152",
    "sg:province":"VA",
    "sg:tags":[
        "instruction"
    ],
    "wof:name":"Umesh Agnihopri",
    "wof:placetype":"venue"
},
  "geometry": {"coordinates":[-77.213076,38.763842],"type":"Point"}
}