{
  "type": "Feature",
  "properties": {
    "addr:full":"4429 20th Rd N Arlington VA 22207",
    "addr:housenumber":"4429",
    "addr:postcode":"22207",
    "addr:street":"20Th Rd N",
    "iso:country":"US",
    "sg:address":"4429 20th Rd N",
    "sg:city":"Arlington",
    "sg:classifiers":[
        {
            "category":"Restaurant",
            "type":"Food & Drink"
        }
    ],
    "sg:phone":"+1 703 516 4222",
    "sg:postcode":"22207",
    "sg:province":"VA",
    "wof:name":"My Personal Chef",
    "wof:placetype":"venue"
},
  "geometry": {"coordinates":[-77.11590200000001,38.896118],"type":"Point"}
}