{
  "type": "Feature",
  "properties": {
    "iso:country":"US",
    "sg:address":"2618 Portsmouth Blvd",
    "sg:city":"Portsmouth",
    "sg:classifiers":[
        {
            "category":"Retail",
            "subcategory":"Auto Repair",
            "type":"Services"
        }
    ],
    "sg:phone":"+1 757 676 7077",
    "sg:postcode":"23704",
    "sg:province":"VA",
    "sg:tags":[
        "body"
    ],
    "wof:name":"Walden S Auto Trim & Upholstry",
    "wof:placetype":"venue"
},
  "geometry": {"coordinates":[-76.334087,36.816077],"type":"Point"}
}