{
  "type": "Feature",
  "properties": {
    "addr:full":"10712 Crestwood Dr Spotsylvania VA 22553",
    "addr:housenumber":"10712",
    "addr:postcode":"22553",
    "addr:street":"Crestwood Dr",
    "iso:country":"US",
    "sg:address":"10712 Crestwood Dr",
    "sg:city":"Spotsylvania",
    "sg:classifiers":[
        {
            "category":"Professional",
            "subcategory":"Art Services",
            "type":"Services"
        }
    ],
    "sg:phone":"+1 540 786 3829",
    "sg:postcode":"22553",
    "sg:province":"VA",
    "sg:tags":[
        "commercial",
        "design"
    ],
    "wof:name":"Bracken Archtctural Renderings",
    "wof:placetype":"venue"
},
  "geometry": {"coordinates":[-77.559814,38.249334],"type":"Point"}
}