{
  "type": "Feature",
  "properties": {
    "iso:country":"US",
    "sg:address":"11418 Links Dr",
    "sg:city":"Reston",
    "sg:classifiers":[
        {
            "category":"Restaurant",
            "type":"Food & Drink"
        }
    ],
    "sg:phone":"+1 703 742 3951",
    "sg:postcode":"20190",
    "sg:province":"VA",
    "sg:tags":[
        "eating"
    ],
    "wof:name":"Herndon Ice Hockey Club Inc",
    "wof:placetype":"venue"
},
  "geometry": {"coordinates":[-77.342876,38.958727],"type":"Point"}
}