{
  "type": "Feature",
  "properties": {
    "addr:full":"1121 Land of Promise Rd Chesapeake VA 23322",
    "addr:housenumber":"1121",
    "addr:postcode":"23322",
    "addr:street":"Land Of Promise Rd",
    "iso:country":"US",
    "sg:address":"1121 Land of Promise Rd",
    "sg:city":"Chesapeake",
    "sg:classifiers":[
        {
            "category":"Building & Trades",
            "subcategory":"Landscaping Services",
            "type":"Services"
        }
    ],
    "sg:phone":"+1 757 421 3754",
    "sg:postcode":"23322",
    "sg:province":"VA",
    "wof:name":"Harrisons Lawn Care",
    "wof:placetype":"venue"
},
  "geometry": {"coordinates":[-76.180094,36.674213],"type":"Point"}
}