{
  "type": "Feature",
  "properties": {
    "iso:country":"US",
    "sg:address":"6401 16th St",
    "sg:city":"Alexandria",
    "sg:classifiers":[
        {
            "category":"Professional",
            "subcategory":"Lawyer & Legal Services",
            "type":"Services"
        }
    ],
    "sg:phone":"+1 703 683 4200",
    "sg:postcode":"22307",
    "sg:province":"VA",
    "wof:name":"Paul Delaney Lyne",
    "wof:placetype":"venue"
},
  "geometry": {"coordinates":[-77.062039,38.778318],"type":"Point"}
}