{
  "type": "Feature",
  "properties": {
    "addr:full":"120 Oak Hill Dr Woodstock VA 22664",
    "addr:housenumber":"120",
    "addr:postcode":"22664",
    "addr:street":"Oak Hill Dr",
    "iso:country":"US",
    "sg:address":"120 Oak Hill Dr",
    "sg:city":"Woodstock",
    "sg:classifiers":[
        {
            "category":"Food & Beverages",
            "subcategory":"Groceries & Convenience Stores",
            "type":"Retail Goods"
        }
    ],
    "sg:phone":"+1 540 459 3537",
    "sg:postcode":"22664",
    "sg:province":"VA",
    "wof:name":"Market In Woodstock Ltd",
    "wof:placetype":"venue"
},
  "geometry": {"coordinates":[-78.540254,38.887123],"type":"Point"}
}