{
  "type": "Feature",
  "properties": {
    "addr:full":"10408 Lakeridge Pkwy Ashland VA 23005",
    "addr:housenumber":"10408",
    "addr:postcode":"23005",
    "addr:street":"Lakeridge Pkwy",
    "iso:country":"US",
    "sg:address":"10408 Lakeridge Pkwy",
    "sg:city":"Ashland",
    "sg:classifiers":[
        {
            "category":"Professional",
            "type":"Services"
        }
    ],
    "sg:phone":"+1 804 550 4970",
    "sg:postcode":"23005",
    "sg:province":"VA",
    "wof:name":"Echosphere Corp",
    "wof:placetype":"venue"
},
  "geometry": {"coordinates":[-77.453692,37.695579],"type":"Point"}
}