{
  "type": "Feature",
  "properties": {
    "addr:full":"1309 Botetourt Gardens Norfolk VA 23517",
    "addr:housenumber":"1309",
    "addr:postcode":"23517",
    "addr:street":"Botetourt Gardens",
    "iso:country":"US",
    "sg:address":"1309 Botetourt Gardens",
    "sg:city":"Norfolk",
    "sg:classifiers":[
        {
            "category":"Shopping",
            "subcategory":"Jewelry",
            "type":"Retail Goods"
        }
    ],
    "sg:phone":"+1 757 498 4277",
    "sg:postcode":"23517",
    "sg:province":"VA",
    "sg:tags":[
        "store"
    ],
    "wof:name":"Diamond and Jewelry Exchange",
    "wof:placetype":"venue"
},
  "geometry": {"coordinates":[-76.291,36.863615],"type":"Point"}
}