{
  "type": "Feature",
  "properties": {
    "addr:full":"9017 Swift Creek Rd Fairfax Station VA 22039",
    "addr:postcode":"9017;22039",
    "addr:street":"Swift Creek Rd",
    "iso:country":"US",
    "sg:address":"9017 Swift Creek Rd",
    "sg:city":"Fairfax Station",
    "sg:classifiers":[
        {
            "category":"Arts & Performance",
            "subcategory":"Theater",
            "type":"Entertainment"
        }
    ],
    "sg:phone":"+1 703 978 0272",
    "sg:postcode":"22039",
    "sg:province":"VA",
    "sg:tags":[
        "theatrical"
    ],
    "wof:name":"Transcontinental Talent Corp",
    "wof:placetype":"venue"
},
  "geometry": {"coordinates":[-77.290178,38.713296],"type":"Point"}
}