{
  "type": "Feature",
  "properties": {
    "addr:full":"1756 General Booth Blvd Virginia Beach VA 23454",
    "addr:housenumber":"1756",
    "addr:postcode":"23454",
    "addr:street":"General Booth Blvd",
    "iso:country":"US",
    "sg:address":"1756 General Booth Blvd",
    "sg:city":"Virginia Beach",
    "sg:classifiers":[
        {
            "category":"Restaurant",
            "type":"Food & Drink"
        }
    ],
    "sg:menulink":"http://www.allmenus.com/va/virginia-beach/85172-applebees/menu/",
    "sg:phone":"+1 757 721 6469",
    "sg:postcode":"23454",
    "sg:province":"VA",
    "sg:tags":[
        "burger",
        "american",
        "sandwich",
        "soup"
    ],
    "wof:name":"Applebee's",
    "wof:placetype":"venue"
},
  "geometry": {"coordinates":[-76.001459,36.780183],"type":"Point"}
}