{
  "type": "Feature",
  "properties": {
    "iso:country":"US",
    "sg:address":"5109 Long Beach Ct",
    "sg:city":"Virginia Beach",
    "sg:classifiers":[
        {
            "category":"Shopping",
            "subcategory":"Optical Goods",
            "type":"Retail Goods"
        }
    ],
    "sg:phone":"+1 757 490 9004",
    "sg:postcode":"23464",
    "sg:province":"VA",
    "wof:name":"Asap Eyeglass Repair Inc",
    "wof:placetype":"venue"
},
  "geometry": {"coordinates":[-76.16956500000001,36.791964],"type":"Point"}
}