{
  "type": "Feature",
  "properties": {
    "iso:country":"US",
    "sg:address":"29231 Lee Hwy",
    "sg:city":"Meadowview",
    "sg:classifiers":[
        {
            "category":"Restaurant",
            "type":"Food & Drink"
        }
    ],
    "sg:phone":"+1 276 944 4446",
    "sg:postcode":"24361",
    "sg:province":"VA",
    "sg:tags":[
        "delicatessen"
    ],
    "wof:name":"Miller's Market & Deli",
    "wof:placetype":"venue"
},
  "geometry": {"coordinates":[-81.855648,36.747386],"type":"Point"}
}