{
  "type": "Feature",
  "properties": {
    "iso:country":"US",
    "sg:address":"2 Poulas Ct",
    "sg:city":"Hampton",
    "sg:classifiers":[
        {
            "category":"Professional",
            "subcategory":"Computer Services",
            "type":"Services"
        }
    ],
    "sg:phone":"+1 757 850 4501",
    "sg:postcode":"23669",
    "sg:province":"VA",
    "sg:tags":[
        "consulting"
    ],
    "wof:name":"Keta Technologies LLC",
    "wof:placetype":"venue"
},
  "geometry": {"coordinates":[-76.33967800000001,37.067938],"type":"Point"}
}