{
  "type": "Feature",
  "properties": {
    "iso:country":"US",
    "sg:address":"9670 Farmside Pl",
    "sg:city":"Vienna",
    "sg:classifiers":[
        {
            "category":"Professional",
            "subcategory":"Management & Consulting",
            "type":"Services"
        }
    ],
    "sg:phone":"+1 703 757 6773",
    "sg:postcode":"22182",
    "sg:province":"VA",
    "wof:name":"Bozzuto & Associates",
    "wof:placetype":"venue"
},
  "geometry": {"coordinates":[-77.279675,38.959278],"type":"Point"}
}