{
  "type": "Feature",
  "properties": {
    "iso:country":"US",
    "sg:address":"11718 Church Rd",
    "sg:city":"Richmond",
    "sg:classifiers":[
        {
            "category":"Building & Trades",
            "subcategory":"Construction",
            "type":"Services"
        }
    ],
    "sg:phone":"+1 804 740 4071",
    "sg:postcode":"23233",
    "sg:province":"VA",
    "sg:tags":[
        "general"
    ],
    "sg:website":"www.dunkum.net",
    "wof:name":"Dunkum Inc",
    "wof:placetype":"venue"
},
  "geometry": {"coordinates":[-77.610407,37.634518],"type":"Point"}
}