{
  "type": "Feature",
  "properties": {
    "iso:country":"US",
    "sg:address":"4024 Granby St",
    "sg:city":"Norfolk",
    "sg:classifiers":[
        {
            "category":"Restaurant",
            "type":"Food & Drink"
        }
    ],
    "sg:phone":"+1 757 625 0363",
    "sg:postcode":"23504",
    "sg:province":"VA",
    "sg:tags":[
        "eating"
    ],
    "wof:name":"Veneziano Restaurant",
    "wof:placetype":"venue"
},
  "geometry": {"coordinates":[-76.28169200000001,36.883772],"type":"Point"}
}