{
  "type": "Feature",
  "properties": {
    "addr:full":"2801 Fairgate Rd Midlothian VA 23112",
    "addr:housenumber":"2801",
    "addr:postcode":"23112",
    "addr:street":"Fairgate Rd",
    "iso:country":"US",
    "sg:address":"2801 Fairgate Rd",
    "sg:city":"Midlothian",
    "sg:classifiers":[
        {
            "category":"Professional",
            "subcategory":"Computer Services",
            "type":"Services"
        }
    ],
    "sg:phone":"+1 804 744 4984",
    "sg:postcode":"23112",
    "sg:province":"VA",
    "sg:tags":[
        "consultant",
        "designer",
        "system"
    ],
    "wof:name":"G A Consutling Inc",
    "wof:placetype":"venue"
},
  "geometry": {"coordinates":[-77.66722900000001,37.448212],"type":"Point"}
}