{
  "type": "Feature",
  "properties": {
    "addr:full":"310 Patriot Ln Williamsburg VA 23185",
    "addr:housenumber":"310",
    "addr:postcode":"23185",
    "addr:street":"Patriot Ln",
    "iso:country":"US",
    "sg:address":"310 Patriot Ln",
    "sg:city":"Williamsburg",
    "sg:classifiers":[
        {
            "category":"Real Estate",
            "subcategory":"Real Estate Operator",
            "type":"Services"
        }
    ],
    "sg:phone":"+1 757 253 2844",
    "sg:postcode":"23185",
    "sg:province":"VA",
    "sg:tags":[
        "property",
        "lessor"
    ],
    "wof:name":"Betty S Walls & Associates",
    "wof:placetype":"venue"
},
  "geometry": {"coordinates":[-76.730952,37.306564],"type":"Point"}
}