{
  "type": "Feature",
  "properties": {
    "addr:full":"458 Southlake Blvd Richmond VA 23236",
    "addr:housenumber":"458",
    "addr:postcode":"23236",
    "addr:street":"Southlake Blvd",
    "iso:country":"US",
    "sg:address":"458 Southlake Blvd",
    "sg:city":"Richmond",
    "sg:classifiers":[
        {
            "category":"Wholesale",
            "subcategory":"Electrical",
            "type":"Manufacturing & Wholesale Goods"
        }
    ],
    "sg:phone":"+1 804 594 2890",
    "sg:postcode":"23236",
    "sg:province":"VA",
    "sg:tags":[
        "control",
        "correction",
        "distributes",
        "system"
    ],
    "wof:name":"Diversified Ctrl Systems LLC",
    "wof:placetype":"venue"
},
  "geometry": {"coordinates":[-77.60274200000001,37.499645],"type":"Point"}
}