{
  "type": "Feature",
  "properties": {
    "addr:full":"17143 12th St King George VA 22485",
    "addr:housenumber":"17143",
    "addr:postcode":"22485",
    "addr:street":"12Th St",
    "iso:country":"US",
    "sg:address":"17143 12th St",
    "sg:city":"King George",
    "sg:classifiers":[
        {
            "category":"Professional",
            "subcategory":"Computer Services",
            "type":"Services"
        }
    ],
    "sg:phone":"+1 540 226 4110",
    "sg:postcode":"22485",
    "sg:province":"VA",
    "sg:tags":[
        "prepackaged",
        "software"
    ],
    "wof:name":"Crystalview Technology Corp",
    "wof:placetype":"venue"
},
  "geometry": {"coordinates":[-77.048548,38.331421],"type":"Point"}
}