{
  "type": "Feature",
  "properties": {
    "iso:country":"US",
    "sg:address":"14290 Chapel Ln",
    "sg:city":"Leesburg",
    "sg:classifiers":[
        {
            "category":"Travel",
            "subcategory":"Bed & Breakfast",
            "type":"Entertainment"
        }
    ],
    "sg:phone":"+1 703 443 6730",
    "sg:postcode":"20176",
    "sg:province":"VA",
    "sg:tags":[
        "house"
    ],
    "wof:name":"Chapel View Farm",
    "wof:placetype":"venue"
},
  "geometry": {"coordinates":[-77.515051,39.219089],"type":"Point"}
}