{
  "type": "Feature",
  "properties": {
    "addr:full":"4802 Valley View Blvd NW Roanoke VA 24012",
    "addr:housenumber":"4802",
    "addr:postcode":"24012",
    "addr:street":"Valley View Blvd Nw",
    "iso:country":"US",
    "sg:address":"4802 Valley View Blvd NW",
    "sg:city":"Roanoke",
    "sg:classifiers":[
        {
            "category":"Restaurant",
            "type":"Food & Drink"
        }
    ],
    "sg:menulink":"http://www.allmenus.com/va/roanoke/9005-red-robin/menu/",
    "sg:phone":"+1 540 265 5930",
    "sg:postcode":"24012",
    "sg:province":"VA",
    "sg:tags":[
        "american"
    ],
    "wof:name":"Red Robin",
    "wof:placetype":"venue"
},
  "geometry": {"coordinates":[-79.96934299999999,37.309746],"type":"Point"}
}