{
  "type": "Feature",
  "properties": {
    "addr:full":"21828 Regents Park Cir Sterling VA 20166",
    "addr:housenumber":"21828",
    "addr:postcode":"20166",
    "addr:street":"Regents Park Cir",
    "iso:country":"US",
    "sg:address":"21828 Regents Park Cir",
    "sg:city":"Sterling",
    "sg:classifiers":[
        {
            "category":"Professional",
            "subcategory":"Management & Consulting",
            "type":"Services"
        }
    ],
    "sg:phone":"+1 703 303 2649",
    "sg:postcode":"20166",
    "sg:province":"VA",
    "sg:tags":[
        "web",
        "hosting",
        "business"
    ],
    "wof:name":"Consequent Solutions LLC",
    "wof:placetype":"venue"
},
  "geometry": {"coordinates":[-77.42219299999999,39.011593],"type":"Point"}
}