{
  "type": "Feature",
  "properties": {
    "addr:full":"1205 Dolley Madison Blvd Mc Lean VA 22101",
    "addr:housenumber":"1205",
    "addr:postcode":"22101",
    "addr:street":"Dolley Madison Blvd Mc Lean",
    "iso:country":"US",
    "sg:address":"1205 Dolley Madison Blvd",
    "sg:city":"Mc Lean",
    "sg:classifiers":[
        {
            "category":"Education",
            "subcategory":"Preschool",
            "type":"Public Place"
        },
        {
            "category":"Education",
            "subcategory":"School",
            "type":"Public Place"
        }
    ],
    "sg:phone":"+1 703 790 2767",
    "sg:postcode":"22101",
    "sg:province":"VA",
    "sg:tags":[
        "elementary"
    ],
    "wof:name":"Trinity Parents Day Out",
    "wof:placetype":"venue"
},
  "geometry": {"coordinates":[-77.16130099999999,38.941898],"type":"Point"}
}