{
  "type": "Feature",
  "properties": {
    "addr:full":"3504 Aldie Rd Catharpin VA 20143",
    "addr:postcode":"3504;20143",
    "addr:street":"Aldie Rd",
    "iso:country":"US",
    "sg:address":"3504 Aldie Rd",
    "sg:city":"Catharpin",
    "sg:classifiers":[
        {
            "category":"Farming",
            "subcategory":"Livestock Farm",
            "type":"Manufacturing & Wholesale Goods"
        }
    ],
    "sg:phone":"+1 703 754 2990",
    "sg:postcode":"20143",
    "sg:province":"VA",
    "sg:tags":[
        "specialty",
        "animal"
    ],
    "wof:name":"Honeysuckle Farm",
    "wof:placetype":"venue"
},
  "geometry": {"coordinates":[-77.558464,38.882237],"type":"Point"}
}