{
  "type": "Feature",
  "properties": {
    "addr:full":"14461 Walkbridge Ln Fulks Run VA 22830",
    "addr:housenumber":"14461",
    "addr:postcode":"22830",
    "addr:street":"Walkbridge Ln",
    "iso:country":"US",
    "sg:address":"14461 Walkbridge Ln",
    "sg:city":"Fulks Run",
    "sg:classifiers":[
        {
            "category":"Home & Garden",
            "subcategory":"Building Materials",
            "type":"Retail Goods"
        }
    ],
    "sg:phone":"+1 540 896 2807",
    "sg:postcode":"22830",
    "sg:province":"VA",
    "sg:tags":[
        "door"
    ],
    "wof:name":"Evers Rumer Doors",
    "wof:placetype":"venue"
},
  "geometry": {"coordinates":[-78.938543,38.654268],"type":"Point"}
}