{
  "type": "Feature",
  "properties": {
    "addr:full":"43866 Sandburg Sq Ashburn VA 20147",
    "addr:postcode":"43866;20147",
    "addr:street":"Sandburg Sq",
    "iso:country":"US",
    "sg:address":"43866 Sandburg Sq",
    "sg:city":"Ashburn",
    "sg:classifiers":[
        {
            "category":"Professional",
            "subcategory":"Management & Consulting",
            "type":"Services"
        }
    ],
    "sg:phone":"+1 703 999 4161",
    "sg:postcode":"20147",
    "sg:province":"VA",
    "wof:name":"Ridge Group Inc",
    "wof:placetype":"venue"
},
  "geometry": {"coordinates":[-77.48368000000001,39.024598],"type":"Point"}
}