{
  "type": "Feature",
  "properties": {
    "addr:full":"5751 Partlow Rd Partlow VA 22534",
    "addr:housenumber":"5751",
    "addr:postcode":"22534",
    "addr:street":"Partlow Rd",
    "iso:country":"US",
    "sg:address":"5751 Partlow Rd",
    "sg:city":"Partlow",
    "sg:classifiers":[
        {
            "category":"Building & Trades",
            "subcategory":"Construction",
            "type":"Services"
        }
    ],
    "sg:phone":"+1 540 582 2417",
    "sg:postcode":"22534",
    "sg:province":"VA",
    "sg:tags":[
        "hanging",
        "contractor"
    ],
    "wof:name":"Dogwood Interiors",
    "wof:placetype":"venue"
},
  "geometry": {"coordinates":[-77.638327,38.11485],"type":"Point"}
}