{
  "type": "Feature",
  "properties": {
    "addr:full":"3101 Warbro Rd Midlothian VA 23112",
    "addr:housenumber":"3101",
    "addr:postcode":"23112",
    "addr:street":"Warbro Rd",
    "iso:country":"US",
    "sg:address":"3101 Warbro Rd",
    "sg:city":"Midlothian",
    "sg:classifiers":[
        {
            "category":"Building & Trades",
            "subcategory":"Construction",
            "type":"Services"
        }
    ],
    "sg:phone":"+1 804 744 7701",
    "sg:postcode":"23112",
    "sg:province":"VA",
    "sg:tags":[
        "excavating",
        "work"
    ],
    "wof:name":"Shively Enterprises Inc",
    "wof:placetype":"venue"
},
  "geometry": {"coordinates":[-77.627503,37.448723],"type":"Point"}
}