{
  "type": "Feature",
  "properties": {
    "iso:country":"US",
    "sg:address":"6806 Patterson Ave",
    "sg:city":"Richmond",
    "sg:classifiers":[
        {
            "category":"Shopping",
            "subcategory":"Stationery & Office Supplies",
            "type":"Retail Goods"
        },
        {
            "category":"Wholesale",
            "subcategory":"Office Equipment",
            "type":"Manufacturing & Wholesale Goods"
        }
    ],
    "sg:phone":"+1 804 285 2472",
    "sg:postcode":"23226",
    "sg:province":"VA",
    "sg:tags":[
        "equipment-wholesale",
        "register",
        "autographic",
        "manufacturer",
        "furniture"
    ],
    "sg:website":"http://www.poscorp.com",
    "wof:name":"Professional Offices Services Of Richmond",
    "wof:placetype":"venue"
},
  "geometry": {"coordinates":[-77.52913100000001,37.589411],"type":"Point"}
}