{
  "type": "Feature",
  "properties": {
    "addr:full":"2330 Azalea Garden Rd Norfolk VA 23513",
    "addr:housenumber":"2330",
    "addr:postcode":"23513",
    "addr:street":"Azalea Garden Rd",
    "iso:country":"US",
    "sg:address":"2330 Azalea Garden Rd",
    "sg:city":"Norfolk",
    "sg:classifiers":[
        {
            "category":"Shopping",
            "subcategory":"Pharmacy",
            "type":"Retail Goods"
        }
    ],
    "sg:phone":"+1 757 853 7607",
    "sg:postcode":"23513",
    "sg:province":"VA",
    "sg:tags":[
        "drug",
        "store"
    ],
    "wof:name":"Eckerd",
    "wof:placetype":"venue"
},
  "geometry": {"coordinates":[-76.231354,36.87198],"type":"Point"}
}