{
  "type": "Feature",
  "properties": {
    "addr:full":"934 Clicks Ln New Market VA 22844",
    "addr:housenumber":"934",
    "addr:postcode":"22844",
    "addr:street":"Clicks Ln",
    "iso:country":"US",
    "sg:address":"934 Clicks Ln",
    "sg:city":"New Market",
    "sg:classifiers":[
        {
            "category":"Professional",
            "subcategory":"Computer Services",
            "type":"Services"
        }
    ],
    "sg:phone":"+1 540 740 8288",
    "sg:postcode":"22844",
    "sg:province":"VA",
    "sg:tags":[
        "internet"
    ],
    "wof:name":"Corlink Communications",
    "wof:placetype":"venue"
},
  "geometry": {"coordinates":[-78.67343,38.634318],"type":"Point"}
}