{
  "type": "Feature",
  "properties": {
    "iso:country":"US",
    "sg:address":"7503 Wexford Pl",
    "sg:city":"Alexandria",
    "sg:classifiers":[
        {
            "category":"Professional",
            "subcategory":"Management & Consulting",
            "type":"Services"
        }
    ],
    "sg:phone":"+1 703 719 6312",
    "sg:postcode":"22315",
    "sg:province":"VA",
    "wof:name":"Omni Text",
    "wof:placetype":"venue"
},
  "geometry": {"coordinates":[-77.13467,38.753946],"type":"Point"}
}