{
  "type": "Feature",
  "properties": {
    "iso:country":"US",
    "sg:address":"3467 Brookville Ln",
    "sg:city":"Woodbridge",
    "sg:classifiers":[
        {
            "category":"Arts & Performance",
            "subcategory":"Theater",
            "type":"Entertainment"
        }
    ],
    "sg:phone":"+1 703 583 6620",
    "sg:postcode":"22192",
    "sg:province":"VA",
    "sg:tags":[
        "group"
    ],
    "wof:name":"Some Odd Reason",
    "wof:placetype":"venue"
},
  "geometry": {"coordinates":[-77.31283500000001,38.658325],"type":"Point"}
}