{
  "type": "Feature",
  "properties": {
    "iso:country":"US",
    "sg:address":"4491 Willow Tree Ln",
    "sg:city":"King George",
    "sg:classifiers":[
        {
            "category":"Autos & Motor Vehicles",
            "subcategory":"Boat Sales",
            "type":"Retail Goods"
        }
    ],
    "sg:phone":"+1 540 663 2818",
    "sg:postcode":"22485",
    "sg:province":"VA",
    "sg:tags":[
        "equipment",
        "marine",
        "supply"
    ],
    "wof:name":"Richard's Marine Svc",
    "wof:placetype":"venue"
},
  "geometry": {"coordinates":[-77.064898,38.346358],"type":"Point"}
}