{
  "type": "Feature",
  "properties": {
    "iso:country":"US",
    "sg:address":"3201 S Military Hwy",
    "sg:city":"Chesapeake",
    "sg:classifiers":[
        {
            "category":"Building & Trades",
            "subcategory":"Construction",
            "type":"Services"
        }
    ],
    "sg:phone":"+1 757 487 2556",
    "sg:postcode":"23323",
    "sg:province":"VA",
    "sg:tags":[
        "company"
    ],
    "wof:name":"B & K Construction Co-Tidewatr",
    "wof:placetype":"venue"
},
  "geometry": {"coordinates":[-76.332916,36.772776],"type":"Point"}
}