{
  "type": "Feature",
  "properties": {
    "iso:country":"US",
    "sg:address":"308 1st St SW",
    "sg:city":"Roanoke",
    "sg:classifiers":[
        {
            "category":"Health Services",
            "subcategory":"Optometrist",
            "type":"Services"
        }
    ],
    "sg:phone":"+1 540 342 6294",
    "sg:postcode":"24011",
    "sg:province":"VA",
    "wof:name":"Veloso Optometrist PC",
    "wof:placetype":"venue"
},
  "geometry": {"coordinates":[-79.94235,37.270599],"type":"Point"}
}