{
  "type": "Feature",
  "properties": {
    "addr:full":"11150 Main St Fairfax VA 22030",
    "addr:housenumber":"11150",
    "addr:postcode":"22030",
    "addr:street":"Main St",
    "iso:country":"US",
    "sg:address":"11150 Main St",
    "sg:city":"Fairfax",
    "sg:classifiers":[
        {
            "category":"Government",
            "subcategory":"Office",
            "type":"Public Place"
        }
    ],
    "sg:phone":"+1 703 359 1100",
    "sg:postcode":"22030",
    "sg:province":"VA",
    "sg:tags":[
        "state",
        "resource"
    ],
    "sg:website":"www.vdbvi.org",
    "wof:name":"Dept-The Blind & Vision Imprd",
    "wof:placetype":"venue"
},
  "geometry": {"coordinates":[-77.330483,38.855413],"type":"Point"}
}