{
  "type": "Feature",
  "properties": {
    "iso:country":"US",
    "sg:address":"3400 Candlewood Dr",
    "sg:city":"Hampton",
    "sg:classifiers":[
        {
            "category":"Real Estate",
            "subcategory":"Real Estate Agent",
            "type":"Services"
        }
    ],
    "sg:phone":"+1 757 838 2662",
    "sg:postcode":"23666",
    "sg:province":"VA",
    "sg:tags":[
        "management"
    ],
    "wof:name":"Willie C Hicks",
    "wof:placetype":"venue"
},
  "geometry": {"coordinates":[-76.42223199999999,37.028875],"type":"Point"}
}