{
  "type": "Feature",
  "properties": {
    "addr:full":"300 Artillery Rd Yorktown VA 23692",
    "addr:housenumber":"300",
    "addr:postcode":"23692",
    "addr:street":"Artillery Rd",
    "iso:country":"US",
    "sg:address":"300 Artillery Rd",
    "sg:city":"Yorktown",
    "sg:classifiers":[
        {
            "category":"Professional",
            "type":"Services"
        }
    ],
    "sg:phone":"+1 757 898 3075",
    "sg:postcode":"23692",
    "sg:province":"VA",
    "wof:name":"Carolyn Rhoads Wood Sculpture",
    "wof:placetype":"venue"
},
  "geometry": {"coordinates":[-76.48405,37.210923],"type":"Point"}
}