{
  "type": "Feature",
  "properties": {
    "addr:full":"208 Clark St Farmville VA 23901",
    "addr:housenumber":"208",
    "addr:postcode":"23901",
    "addr:street":"Clark St",
    "iso:country":"US",
    "sg:address":"208 Clark St",
    "sg:city":"Farmville",
    "sg:classifiers":[
        {
            "category":"Real Estate",
            "subcategory":"Real Estate Operator",
            "type":"Services"
        }
    ],
    "sg:phone":"+1 434 315 5566",
    "sg:postcode":"23901",
    "sg:province":"VA",
    "sg:tags":[
        "apartment"
    ],
    "wof:name":"Longwood Village Apt",
    "wof:placetype":"venue"
},
  "geometry": {"coordinates":[-78.40057400000001,37.271143],"type":"Point"}
}