{
  "type": "Feature",
  "properties": {
    "addr:full":"337 Maple Avenue East Vienna VA 22180",
    "addr:housenumber":"337",
    "addr:postcode":"22180",
    "addr:street":"Maple Avenue East",
    "iso:country":"US",
    "sg:address":"337 Maple Avenue East",
    "sg:city":"Vienna",
    "sg:classifiers":[
        {
            "category":"Shopping",
            "subcategory":"Pharmacy",
            "type":"Retail Goods"
        }
    ],
    "sg:phone":"+1 703 938 2374",
    "sg:postcode":"22180",
    "sg:province":"VA",
    "sg:tags":[
        "drugstore"
    ],
    "sg:website":"www.cvs.com",
    "wof:name":"CVS Pharmacy",
    "wof:placetype":"venue"
},
  "geometry": {"coordinates":[-77.26000999999999,38.905712],"type":"Point"}
}