{
  "type": "Feature",
  "properties": {
    "addr:full":"3300 Riverside Dr Danville VA 24541",
    "addr:housenumber":"3300",
    "addr:postcode":"24541",
    "addr:street":"Riverside Dr",
    "iso:country":"US",
    "sg:address":"3300 Riverside Dr",
    "sg:city":"Danville",
    "sg:classifiers":[
        {
            "category":"Shopping",
            "subcategory":"Department Store",
            "type":"Retail Goods"
        }
    ],
    "sg:phone":"+1 434 791 0235",
    "sg:postcode":"24541",
    "sg:province":"VA",
    "sg:tags":[
        "shop"
    ],
    "wof:name":"Pier 1 Imports",
    "wof:placetype":"venue"
},
  "geometry": {"coordinates":[-79.425415,36.58544],"type":"Point"}
}