{
  "type": "Feature",
  "properties": {
    "addr:full":"34216 Constitution Hwy Locust Grove VA 22508",
    "addr:housenumber":"34216",
    "addr:postcode":"22508",
    "addr:street":"Constitution Hwy",
    "iso:country":"US",
    "sg:address":"34216 Constitution Hwy",
    "sg:city":"Locust Grove",
    "sg:classifiers":[
        {
            "category":"Building & Trades",
            "subcategory":"Construction",
            "type":"Services"
        }
    ],
    "sg:phone":"+1 540 854 9360",
    "sg:postcode":"22508",
    "sg:province":"VA",
    "sg:tags":[
        "home",
        "builder"
    ],
    "wof:name":"Fadely Homes",
    "wof:placetype":"venue"
},
  "geometry": {"coordinates":[-77.77734599999999,38.312426],"type":"Point"}
}