{
  "type": "Feature",
  "properties": {
    "iso:country":"US",
    "sg:address":"1008 Gilmer Ave NW",
    "sg:city":"Roanoke",
    "sg:classifiers":[
        {
            "category":"Building & Trades",
            "subcategory":"Construction",
            "type":"Services"
        }
    ],
    "sg:phone":"+1 703 754 7400",
    "sg:postcode":"24016",
    "sg:province":"VA",
    "sg:tags":[
        "industrial",
        "contractors-commercial"
    ],
    "wof:name":"C C Tekton",
    "wof:placetype":"venue"
},
  "geometry": {"coordinates":[-79.955642,37.279339],"type":"Point"}
}