{
  "type": "Feature",
  "properties": {
    "addr:full":"2100 Reston Pkwy Reston VA 20191",
    "addr:housenumber":"2100",
    "addr:postcode":"20191",
    "addr:street":"Reston Pkwy",
    "iso:country":"US",
    "sg:address":"2100 Reston Pkwy",
    "sg:city":"Reston",
    "sg:classifiers":[
        {
            "category":"Real Estate",
            "subcategory":"Real Estate Agent",
            "type":"Services"
        }
    ],
    "sg:phone":"+1 703 264 9676",
    "sg:postcode":"20191",
    "sg:province":"VA",
    "sg:tags":[
        "management"
    ],
    "wof:name":"Mc Shea Management Inc",
    "wof:placetype":"venue"
},
  "geometry": {"coordinates":[-77.361316,38.943023],"type":"Point"}
}