{
  "type": "Feature",
  "properties": {
    "addr:full":"67 Hartwood Church Rd Hartwood VA 22406",
    "addr:housenumber":"67",
    "addr:postcode":"22406",
    "addr:street":"Hartwood Church Rd",
    "iso:country":"US",
    "sg:address":"67 Hartwood Church Rd",
    "sg:city":"Hartwood",
    "sg:classifiers":[
        {
            "category":"Government",
            "subcategory":"Fire Station",
            "type":"Public Place"
        }
    ],
    "sg:phone":"+1 540 752 4322",
    "sg:postcode":"22406",
    "sg:province":"VA",
    "sg:tags":[
        "department"
    ],
    "wof:name":"Hartwood Fire Station",
    "wof:placetype":"venue"
},
  "geometry": {"coordinates":[-77.56748399999999,38.401634],"type":"Point"}
}