{
  "type": "Feature",
  "properties": {
    "iso:country":"US",
    "sg:address":"11730 Fairfax Woods Way",
    "sg:city":"Fairfax",
    "sg:classifiers":[
        {
            "category":"Professional",
            "type":"Services"
        }
    ],
    "sg:phone":"+1 703 359 7111",
    "sg:postcode":"22030",
    "sg:province":"VA",
    "wof:name":"Raymond Smith",
    "wof:placetype":"venue"
},
  "geometry": {"coordinates":[-77.353756,38.85769],"type":"Point"}
}