{
  "type": "Feature",
  "properties": {
    "addr:full":"12609 Misty Creek Ln Fairfax VA 22033",
    "addr:housenumber":"12609",
    "addr:postcode":"22033",
    "addr:street":"Misty Creek Ln",
    "iso:country":"US",
    "sg:address":"12609 Misty Creek Ln",
    "sg:city":"Fairfax",
    "sg:classifiers":[
        {
            "category":"Professional",
            "type":"Services"
        }
    ],
    "sg:phone":"+1 703 758 5812",
    "sg:postcode":"22033",
    "sg:province":"VA",
    "wof:name":"Center For Retirement Security",
    "wof:placetype":"venue"
},
  "geometry": {"coordinates":[-77.385065,38.888264],"type":"Point"}
}