{
  "type": "Feature",
  "properties": {
    "addr:full":"2121 W Mercury Blvd Hampton VA 23666",
    "addr:housenumber":"2121",
    "addr:postcode":"23666",
    "addr:street":"W Mercury Blvd",
    "iso:country":"US",
    "sg:address":"2121 W Mercury Blvd",
    "sg:city":"Hampton",
    "sg:classifiers":[
        {
            "category":"Home & Garden",
            "subcategory":"Building Materials",
            "type":"Retail Goods"
        },
        {
            "category":"Retail",
            "subcategory":"Auto Repair",
            "type":"Services"
        }
    ],
    "sg:phone":"+1 757 827 0444",
    "sg:postcode":"23666",
    "sg:province":"VA",
    "sg:tags":[
        "glass",
        "window",
        "plate",
        "replacement"
    ],
    "wof:name":"Safelite Auto Glass",
    "wof:placetype":"venue"
},
  "geometry": {"coordinates":[-76.400215,37.039019],"type":"Point"}
}