{
  "type": "Feature",
  "properties": {
    "addr:full":"11079 Saffold Way Reston VA 20190",
    "addr:housenumber":"11079",
    "addr:postcode":"20190",
    "addr:street":"Saffold Way",
    "iso:country":"US",
    "sg:address":"11079 Saffold Way",
    "sg:city":"Reston",
    "sg:classifiers":[
        {
            "category":"Real Estate",
            "subcategory":"Real Estate Operator",
            "type":"Services"
        }
    ],
    "sg:phone":"+1 703 708 7100",
    "sg:postcode":"20190",
    "sg:province":"VA",
    "sg:tags":[
        "building",
        "nonresidential"
    ],
    "wof:name":"WEBB Properties LLC",
    "wof:placetype":"venue"
},
  "geometry": {"coordinates":[-77.3283,38.972086],"type":"Point"}
}