{
  "type": "Feature",
  "properties": {
    "iso:country":"US",
    "sg:address":"6701 Northwestern Pike",
    "sg:city":"Gore",
    "sg:classifiers":[
        {
            "category":"Banks & Credit Unions",
            "subcategory":"Bank",
            "type":"Services"
        }
    ],
    "sg:phone":"+1 540 858 3010",
    "sg:postcode":"22637",
    "sg:province":"VA",
    "sg:tags":[
        "commercial"
    ],
    "wof:name":"Capon Valley Bank",
    "wof:placetype":"venue"
},
  "geometry": {"coordinates":[-78.317651,39.268305],"type":"Point"}
}