{
  "type": "Feature",
  "properties": {
    "addr:full":"781 Main St Danville VA 24541",
    "addr:housenumber":"781",
    "addr:postcode":"24541",
    "addr:street":"Main St",
    "iso:country":"US",
    "sg:address":"781 Main St",
    "sg:city":"Danville",
    "sg:classifiers":[
        {
            "category":"Organizations",
            "subcategory":"Religious Organization",
            "type":"Services"
        }
    ],
    "sg:phone":"+1 434 792 4321",
    "sg:postcode":"24541",
    "sg:province":"VA",
    "sg:tags":[
        "episcopal",
        "church"
    ],
    "wof:name":"Episcopal Church of Epiphany",
    "wof:placetype":"venue"
},
  "geometry": {"coordinates":[-79.39559,36.585794],"type":"Point"}
}