{
  "type": "Feature",
  "properties": {
    "addr:full":"679 Guinea Rd Farmville VA 23901",
    "addr:housenumber":"679",
    "addr:postcode":"23901",
    "addr:street":"Guinea Rd",
    "iso:country":"US",
    "sg:address":"679 Guinea Rd",
    "sg:city":"Farmville",
    "sg:classifiers":[
        {
            "category":"Retail",
            "subcategory":"Animal Services",
            "type":"Services"
        }
    ],
    "sg:phone":"+1 434 392 5566",
    "sg:postcode":"23901",
    "sg:province":"VA",
    "wof:name":"Twin Pines Kennel",
    "wof:placetype":"venue"
},
  "geometry": {"coordinates":[-78.314398,37.392069],"type":"Point"}
}