{
  "type": "Feature",
  "properties": {
    "addr:full":"300 Broad St Portsmouth VA 23707",
    "addr:housenumber":"300",
    "addr:postcode":"23707",
    "addr:street":"Broad St",
    "iso:country":"US",
    "sg:address":"300 Broad St",
    "sg:city":"Portsmouth",
    "sg:classifiers":[
        {
            "category":"Organizations",
            "subcategory":"Religious Organization",
            "type":"Services"
        }
    ],
    "sg:phone":"+1 757 397 6314",
    "sg:postcode":"23707",
    "sg:province":"VA",
    "wof:name":"Broad St Untd Methdst Church",
    "wof:placetype":"venue"
},
  "geometry": {"coordinates":[-76.33541700000001,36.84831],"type":"Point"}
}