{
  "type": "Feature",
  "properties": {
    "iso:country":"US",
    "sg:address":"3394 Kelly Ln Exd",
    "sg:city":"Roanoke",
    "sg:classifiers":[
        {
            "category":"Organizations",
            "subcategory":"Community Association",
            "type":"Services"
        }
    ],
    "sg:phone":"+1 540 774 5794",
    "sg:postcode":"24018",
    "sg:province":"VA",
    "wof:name":"Stonehenge Court Townhse",
    "wof:placetype":"venue"
},
  "geometry": {"coordinates":[-79.996298,37.216775],"type":"Point"}
}