{
  "type": "Feature",
  "properties": {
    "iso:country":"US",
    "sg:address":"3201 W Broad St",
    "sg:city":"Richmond",
    "sg:classifiers":[
        {
            "category":"Professional",
            "type":"Services"
        }
    ],
    "sg:phone":"+1 804 422 3030",
    "sg:postcode":"23230",
    "sg:province":"VA",
    "sg:tags":[
        "establishment"
    ],
    "wof:name":"Southern Autotronics",
    "wof:placetype":"venue"
},
  "geometry": {"coordinates":[-77.47479800000001,37.565964],"type":"Point"}
}