{
  "type": "Feature",
  "properties": {
    "addr:full":"727 Filer St Norfolk VA 23504",
    "addr:housenumber":"727",
    "addr:postcode":"23504",
    "addr:street":"Filer St",
    "iso:country":"US",
    "sg:address":"727 Filer St",
    "sg:city":"Norfolk",
    "sg:classifiers":[
        {
            "category":"Social Services",
            "subcategory":"Child Care",
            "type":"Services"
        }
    ],
    "sg:phone":"+1 757 227 6844",
    "sg:postcode":"23504",
    "sg:province":"VA",
    "sg:tags":[
        "day"
    ],
    "wof:name":"Cubbyhole Child Care Cente",
    "wof:placetype":"venue"
},
  "geometry": {"coordinates":[-76.259367,36.844444],"type":"Point"}
}