{
  "type": "Feature",
  "properties": {
    "addr:full":"711 Caroline St Fredericksburg VA 22401",
    "addr:housenumber":"711",
    "addr:postcode":"22401",
    "addr:street":"Caroline St",
    "iso:country":"US",
    "sg:address":"711 Caroline St",
    "sg:city":"Fredericksburg",
    "sg:classifiers":[
        {
            "category":"Travel",
            "subcategory":"Hotels & Motels",
            "type":"Entertainment"
        }
    ],
    "sg:phone":"+1 540 899 7606",
    "sg:postcode":"22401",
    "sg:province":"VA",
    "sg:tags":[
        "breakfast",
        "inn",
        "bed",
        "accommodation"
    ],
    "sg:website":"www.therichardjohnstoninn.com",
    "wof:name":"Richard Johnston Inn Inc",
    "wof:placetype":"venue"
},
  "geometry": {"coordinates":[-77.458268,38.301679],"type":"Point"}
}