{
  "type": "Feature",
  "properties": {
    "addr:full":"1311 Longlac Rd Virginia Beach VA 23464",
    "addr:housenumber":"1311",
    "addr:postcode":"23464",
    "addr:street":"Longlac Rd",
    "iso:country":"US",
    "sg:address":"1311 Longlac Rd",
    "sg:city":"Virginia Beach",
    "sg:classifiers":[
        {
            "category":"Building & Trades",
            "subcategory":"Construction",
            "type":"Services"
        }
    ],
    "sg:phone":"+1 757 965 3105",
    "sg:postcode":"23464",
    "sg:province":"VA",
    "sg:tags":[
        "house"
    ],
    "wof:name":"Stars & Stripes Construction",
    "wof:placetype":"venue"
},
  "geometry": {"coordinates":[-76.15018000000001,36.785367],"type":"Point"}
}