{
  "type": "Feature",
  "properties": {
    "addr:full":"808 N Mulberry St Richmond VA 23220",
    "addr:housenumber":"808",
    "addr:postcode":"23220",
    "addr:street":"N Mulberry St",
    "iso:country":"US",
    "sg:address":"808 N Mulberry St",
    "sg:city":"Richmond",
    "sg:classifiers":[
        {
            "category":"Freight",
            "type":"Transportation"
        }
    ],
    "sg:phone":"+1 804 353 7819",
    "sg:postcode":"23220",
    "sg:province":"VA",
    "sg:tags":[
        "general"
    ],
    "wof:name":"Paul Weiner",
    "wof:placetype":"venue"
},
  "geometry": {"coordinates":[-77.468289,37.561217],"type":"Point"}
}