{
  "type": "Feature",
  "properties": {
    "iso:country":"US",
    "sg:address":"2508 S Military Hwy",
    "sg:city":"Chesapeake",
    "sg:classifiers":[
        {
            "category":"Building & Trades",
            "subcategory":"Construction",
            "type":"Services"
        }
    ],
    "sg:phone":"+1 757 545 5790",
    "sg:postcode":"23320",
    "sg:province":"VA",
    "sg:tags":[
        "contractor"
    ],
    "wof:name":"Jrs Contracting Co Inc",
    "wof:placetype":"venue"
},
  "geometry": {"coordinates":[-76.282186,36.775541],"type":"Point"}
}