{
  "type": "Feature",
  "properties": {
    "iso:country":"US",
    "sg:address":"8009 Quail Hollow",
    "sg:city":"Suffolk",
    "sg:classifiers":[
        {
            "category":"Manufacturing",
            "subcategory":"Metals",
            "type":"Manufacturing & Wholesale Goods"
        }
    ],
    "sg:phone":"+1 757 238 3449",
    "sg:postcode":"23433",
    "sg:province":"VA",
    "sg:tags":[
        "steel"
    ],
    "wof:name":"Pacer Industries Inc",
    "wof:placetype":"venue"
},
  "geometry": {"coordinates":[-76.49082900000001,36.895483],"type":"Point"}
}