{
  "type": "Feature",
  "properties": {
    "iso:country":"US",
    "sg:address":"708 Starling Ave",
    "sg:city":"Martinsville",
    "sg:classifiers":[
        {
            "category":"Real Estate",
            "subcategory":"Architect",
            "type":"Services"
        }
    ],
    "sg:phone":"+1 276 638 3948",
    "sg:postcode":"24112",
    "sg:province":"VA",
    "wof:name":"Smith & Beasley Architects",
    "wof:placetype":"venue"
},
  "geometry": {"coordinates":[-79.870538,36.681088],"type":"Point"}
}