{
  "type": "Feature",
  "properties": {
    "addr:full":"7533 Gary Rd Manassas VA 20109",
    "addr:housenumber":"7533",
    "addr:postcode":"20109",
    "addr:street":"Gary Rd",
    "iso:country":"US",
    "sg:address":"7533 Gary Rd",
    "sg:city":"Manassas",
    "sg:classifiers":[
        {
            "category":"Building & Trades",
            "subcategory":"Locksmith",
            "type":"Services"
        }
    ],
    "sg:phone":"+1 703 656 9156",
    "sg:postcode":"20109",
    "sg:province":"VA",
    "sg:tags":[
        "key"
    ],
    "wof:name":"Anytime Anywhere Emergency Locksmith",
    "wof:placetype":"venue"
},
  "geometry": {"coordinates":[-77.50548499999999,38.799132],"type":"Point"}
}