{
  "type": "Feature",
  "properties": {
    "addr:full":"2174 Ferguson Ct Woodbridge VA 22191",
    "addr:housenumber":"2174",
    "addr:postcode":"22191",
    "addr:street":"Ferguson Ct",
    "iso:country":"US",
    "sg:address":"2174 Ferguson Ct",
    "sg:city":"Woodbridge",
    "sg:classifiers":[
        {
            "category":"Travel",
            "subcategory":"Travel Agent",
            "type":"Entertainment"
        }
    ],
    "sg:phone":"+1 703 730 6870",
    "sg:postcode":"22191",
    "sg:province":"VA",
    "sg:tags":[
        "agency"
    ],
    "wof:name":"J.C.Expedition Travel Company",
    "wof:placetype":"venue"
},
  "geometry": {"coordinates":[-77.274411,38.601825],"type":"Point"}
}