{
  "type": "Feature",
  "properties": {
    "addr:full":"1300 17th St N Arlington VA 22209",
    "addr:housenumber":"1300",
    "addr:postcode":"22209",
    "addr:street":"17Th St N",
    "iso:country":"US",
    "sg:address":"1300 17th St N",
    "sg:city":"Arlington",
    "sg:classifiers":[
        {
            "category":"Professional",
            "type":"Services"
        }
    ],
    "sg:phone":"+1 703 525 3273",
    "sg:postcode":"22209",
    "sg:province":"VA",
    "sg:tags":[
        "consultant",
        "computer",
        "system",
        "designer"
    ],
    "wof:name":"Captivate Network Inc",
    "wof:placetype":"venue"
},
  "geometry": {"coordinates":[-77.072739,38.894058],"type":"Point"}
}