{
  "type": "Feature",
  "properties": {
    "iso:country":"US",
    "sg:address":"44 S Cameron St",
    "sg:city":"Winchester",
    "sg:classifiers":[
        {
            "category":"Professional",
            "subcategory":"Engineering",
            "type":"Services"
        }
    ],
    "sg:phone":"+1 540 662 6623",
    "sg:postcode":"22601",
    "sg:province":"VA",
    "sg:tags":[
        "engineer"
    ],
    "wof:name":"Moffatt & Nichol Engineers",
    "wof:placetype":"venue"
},
  "geometry": {"coordinates":[-78.16421099999999,39.183267],"type":"Point"}
}