{
  "type": "Feature",
  "properties": {
    "addr:full":"1301 Main St Altavista VA 24517",
    "addr:housenumber":"1301",
    "addr:postcode":"24517",
    "addr:street":"Main St",
    "iso:country":"US",
    "sg:address":"1301 Main St",
    "sg:city":"Altavista",
    "sg:classifiers":[
        {
            "category":"Shopping",
            "subcategory":"Discount & Variety Stores",
            "type":"Retail Goods"
        }
    ],
    "sg:phone":"+1 434 369 6624",
    "sg:postcode":"24517",
    "sg:province":"VA",
    "wof:name":"Roses",
    "wof:placetype":"venue"
},
  "geometry": {"coordinates":[-79.273888,37.121933],"type":"Point"}
}