{
  "type": "Feature",
  "properties": {
    "addr:full":"653 Pine Forest Rd Bracey VA 23919",
    "addr:housenumber":"653",
    "addr:postcode":"23919",
    "addr:street":"Pine Forest Rd",
    "iso:country":"US",
    "sg:address":"653 Pine Forest Rd",
    "sg:city":"Bracey",
    "sg:classifiers":[
        {
            "category":"Building & Trades",
            "subcategory":"Construction",
            "type":"Services"
        }
    ],
    "sg:phone":"+1 434 636 2597",
    "sg:postcode":"23919",
    "sg:province":"VA",
    "sg:tags":[
        "excavation",
        "contractor"
    ],
    "wof:name":"My III Sons Land Clearing",
    "wof:placetype":"venue"
},
  "geometry": {"coordinates":[-78.110939,36.555228],"type":"Point"}
}