{
  "type": "Feature",
  "properties": {
    "iso:country":"US",
    "sg:address":"1272 Belvoir Ln",
    "sg:city":"Virginia Beach",
    "sg:classifiers":[
        {
            "category":"Health Services",
            "subcategory":"Health Practitioner",
            "type":"Services"
        }
    ],
    "sg:phone":"+1 757 679 2950",
    "sg:postcode":"23464",
    "sg:province":"VA",
    "sg:tags":[
        "psychology"
    ],
    "wof:name":"Alice L Twining",
    "wof:placetype":"venue"
},
  "geometry": {"coordinates":[-76.18377,36.798093],"type":"Point"}
}