{
  "type": "Feature",
  "properties": {
    "addr:full":"1825 12th St Lynchburg VA 24501",
    "addr:housenumber":"1825",
    "addr:postcode":"24501",
    "addr:street":"12Th St",
    "iso:country":"US",
    "sg:address":"1825 12th St",
    "sg:city":"Lynchburg",
    "sg:classifiers":[
        {
            "category":"Restaurant",
            "type":"Food & Drink"
        }
    ],
    "sg:phone":"+1 434 846 4941",
    "sg:postcode":"24501",
    "sg:province":"VA",
    "sg:tags":[
        "eating"
    ],
    "wof:name":"Local Pub",
    "wof:placetype":"venue"
},
  "geometry": {"coordinates":[-79.155907,37.403614],"type":"Point"}
}