{
  "type": "Feature",
  "properties": {
    "iso:country":"US",
    "sg:address":"8393 Cardova Cir",
    "sg:city":"Richmond",
    "sg:classifiers":[
        {
            "category":"Professional",
            "subcategory":"Business Services",
            "type":"Services"
        }
    ],
    "sg:phone":"+1 804 262 3947",
    "sg:postcode":"23227",
    "sg:province":"VA",
    "wof:name":"Community Ventures Inc",
    "wof:placetype":"venue"
},
  "geometry": {"coordinates":[-77.42983599999999,37.639576],"type":"Point"}
}