{
  "type": "Feature",
  "properties": {
    "addr:full":"450 N Mason St Harrisonburg VA 22802",
    "addr:housenumber":"450",
    "addr:postcode":"22802",
    "addr:street":"N Mason St",
    "iso:country":"US",
    "sg:address":"450 N Mason St",
    "sg:city":"Harrisonburg",
    "sg:classifiers":[
        {
            "category":"Shopping",
            "subcategory":"Discount & Variety Stores",
            "type":"Retail Goods"
        }
    ],
    "sg:phone":"+1 540 433 9186",
    "sg:postcode":"22802",
    "sg:province":"VA",
    "sg:tags":[
        "merchandise",
        "general"
    ],
    "wof:name":"Roses Department Store",
    "wof:placetype":"venue"
},
  "geometry": {"coordinates":[-78.86526000000001,38.454727],"type":"Point"}
}