{
  "type": "Feature",
  "properties": {
    "iso:country":"US",
    "sg:address":"4345 Ivymount Ct",
    "sg:city":"Annandale",
    "sg:classifiers":[
        {
            "category":"Personal",
            "type":"Services"
        }
    ],
    "sg:phone":"+1 703 354 8715",
    "sg:postcode":"22003",
    "sg:province":"VA",
    "wof:name":"Wwwconsumerswarecom",
    "wof:placetype":"venue"
},
  "geometry": {"coordinates":[-77.21410899999999,38.829037],"type":"Point"}
}