{
  "type": "Feature",
  "properties": {
    "addr:full":"53 Stanstead Rd Fredericksburg VA 22406",
    "addr:housenumber":"53",
    "addr:postcode":"22406",
    "addr:street":"Stanstead Rd",
    "iso:country":"US",
    "sg:address":"53 Stanstead Rd",
    "sg:city":"Fredericksburg",
    "sg:classifiers":[
        {
            "category":"Wholesale",
            "subcategory":"Auto Parts",
            "type":"Manufacturing & Wholesale Goods"
        }
    ],
    "sg:phone":"+1 540 368 0064",
    "sg:postcode":"22406",
    "sg:province":"VA",
    "sg:tags":[
        "truck",
        "accessory"
    ],
    "sg:website":"www.kandlchromeshop.com",
    "wof:name":"K & L Chrome Shop",
    "wof:placetype":"venue"
},
  "geometry": {"coordinates":[-77.495987,38.343571],"type":"Point"}
}