{
  "type": "Feature",
  "properties": {
    "addr:full":"500 Montgomery St Ste 525 Alexandria VA 22314",
    "addr:housenumber":"500",
    "addr:postcode":"22314",
    "addr:street":"Montgomery St Ste 525",
    "iso:country":"US",
    "sg:address":"500 Montgomery St Ste 525",
    "sg:city":"Alexandria",
    "sg:classifiers":[
        {
            "category":"Real Estate",
            "subcategory":"Real Estate Services",
            "type":"Services"
        },
        {
            "category":"Real Estate",
            "subcategory":"Real Estate Agent",
            "type":"Services"
        }
    ],
    "sg:phone":"+1 703 548 5542",
    "sg:postcode":"22314",
    "sg:province":"VA",
    "sg:tags":[
        "management"
    ],
    "wof:name":"Madison Place Corp",
    "wof:placetype":"venue"
},
  "geometry": {"coordinates":[-77.042778,38.81385],"type":"Point"}
}