{
  "type": "Feature",
  "properties": {
    "addr:full":"11 Oakridge Blvd Lynchburg VA 24501",
    "addr:housenumber":"11",
    "addr:postcode":"24501",
    "addr:street":"Oakridge Blvd",
    "iso:country":"US",
    "sg:address":"11 Oakridge Blvd",
    "sg:city":"Lynchburg",
    "sg:classifiers":[
        {
            "category":"Retail",
            "subcategory":"Repair Shop",
            "type":"Services"
        },
        {
            "category":"Shopping",
            "subcategory":"Computers & Home Electronics",
            "type":"Retail Goods"
        }
    ],
    "sg:phone":"+1 434 845 3631",
    "sg:postcode":"24501",
    "sg:province":"VA",
    "sg:tags":[
        "equipment",
        "television",
        "video",
        "satellite",
        "radio"
    ],
    "wof:name":"Fort Hill TV Sales & Service",
    "wof:placetype":"venue"
},
  "geometry": {"coordinates":[-79.172409,37.390822],"type":"Point"}
}