{
  "type": "Feature",
  "properties": {
    "addr:full":"2121 Colonial Ave Norfolk VA 23517",
    "addr:housenumber":"2121",
    "addr:postcode":"23517",
    "addr:street":"Colonial Ave",
    "iso:country":"US",
    "sg:address":"2121 Colonial Ave",
    "sg:city":"Norfolk",
    "sg:classifiers":[
        {
            "category":"Organizations",
            "subcategory":"Non-profit Organization",
            "type":"Services"
        }
    ],
    "sg:phone":"+1 757 499 4444",
    "sg:postcode":"23517",
    "sg:province":"VA",
    "sg:tags":[
        "alternative",
        "abortion"
    ],
    "wof:name":"Keim Center",
    "wof:placetype":"venue"
},
  "geometry": {"coordinates":[-76.291669,36.869628],"type":"Point"}
}