{
  "type": "Feature",
  "properties": {
    "iso:country":"US",
    "sg:address":"4584 Virginia Beach Blvd",
    "sg:city":"Virginia Beach",
    "sg:classifiers":[
        {
            "category":"Shopping",
            "subcategory":"Books",
            "type":"Retail Goods"
        }
    ],
    "sg:phone":"+1 757 490 1571",
    "sg:postcode":"23462",
    "sg:province":"VA",
    "sg:tags":[
        "dealer"
    ],
    "sg:website":"www.waldenbooks.com",
    "wof:name":"Waldenbooks",
    "wof:placetype":"venue"
},
  "geometry": {"coordinates":[-76.136278,36.843741],"type":"Point"}
}