{
  "type": "Feature",
  "properties": {
    "addr:full":"4013 Montclair Rd Richmond VA 23223",
    "addr:housenumber":"4013",
    "addr:postcode":"23223",
    "addr:street":"Montclair Rd",
    "iso:country":"US",
    "sg:address":"4013 Montclair Rd",
    "sg:city":"Richmond",
    "sg:classifiers":[
        {
            "category":"Shopping",
            "subcategory":"Clothing, Apparel, & Fashions",
            "type":"Retail Goods"
        }
    ],
    "sg:phone":"+1 804 329 8502",
    "sg:postcode":"23223",
    "sg:province":"VA",
    "sg:tags":[
        "designer"
    ],
    "wof:name":"Richard Hatcher",
    "wof:placetype":"venue"
},
  "geometry": {"coordinates":[-77.384739,37.57947],"type":"Point"}
}