{
  "type": "Feature",
  "properties": {
    "addr:full":"47546 Rippling Pl Sterling VA 20165",
    "addr:housenumber":"47546",
    "addr:postcode":"20165",
    "addr:street":"Rippling Pl",
    "iso:country":"US",
    "sg:address":"47546 Rippling Pl",
    "sg:city":"Sterling",
    "sg:classifiers":[
        {
            "category":"Personal",
            "type":"Services"
        }
    ],
    "sg:phone":"+1 703 450 7393",
    "sg:postcode":"20165",
    "sg:province":"VA",
    "wof:name":"Creative Works",
    "wof:placetype":"venue"
},
  "geometry": {"coordinates":[-77.35393000000001,39.04611],"type":"Point"}
}