{
  "type": "Feature",
  "properties": {
    "addr:full":"3413 South St Portsmouth VA 23707",
    "addr:housenumber":"3413",
    "addr:postcode":"23707",
    "addr:street":"South St",
    "iso:country":"US",
    "sg:address":"3413 South St",
    "sg:city":"Portsmouth",
    "sg:classifiers":[
        {
            "category":"Health Services",
            "subcategory":"Doctor",
            "type":"Services"
        }
    ],
    "sg:phone":"+1 757 393 9929",
    "sg:postcode":"23707",
    "sg:province":"VA",
    "wof:name":"Fredrick T Birsch DDS Ltd",
    "wof:placetype":"venue"
},
  "geometry": {"coordinates":[-76.344465,36.831202],"type":"Point"}
}