{
  "type": "Feature",
  "properties": {
    "addr:full":"1515 8th St Lynchburg VA 24501",
    "addr:housenumber":"1515",
    "addr:postcode":"24501",
    "addr:street":"8Th St",
    "iso:country":"US",
    "sg:address":"1515 8th St",
    "sg:city":"Lynchburg",
    "sg:classifiers":[
        {
            "category":"Organizations",
            "subcategory":"Religious Organization",
            "type":"Services"
        }
    ],
    "sg:phone":"+1 434 846 1570",
    "sg:postcode":"24501",
    "sg:province":"VA",
    "wof:name":"Temple of Deliverance",
    "wof:placetype":"venue"
},
  "geometry": {"coordinates":[-79.155777,37.408687],"type":"Point"}
}