{
  "type": "Feature",
  "properties": {
    "addr:full":"19181 James Madison Hwy Gordonsville VA 22942",
    "addr:housenumber":"19181",
    "addr:postcode":"22942",
    "addr:street":"James Madison Hwy",
    "iso:country":"US",
    "sg:address":"19181 James Madison Hwy",
    "sg:city":"Gordonsville",
    "sg:classifiers":[
        {
            "category":"Autos & Motor Vehicles",
            "subcategory":"Automobile Sales",
            "type":"Retail Goods"
        }
    ],
    "sg:phone":"+1 540 832 0544",
    "sg:postcode":"22942",
    "sg:province":"VA",
    "sg:tags":[
        "car",
        "used",
        "dealer"
    ],
    "wof:name":"Classic Cars",
    "wof:placetype":"venue"
},
  "geometry": {"coordinates":[-78.186087,38.144026],"type":"Point"}
}