{
  "type": "Feature",
  "properties": {
    "addr:full":"1804 Mount Pleasant Rd Chesapeake VA 23322",
    "addr:housenumber":"1804",
    "addr:postcode":"23322",
    "addr:street":"Mount Pleasant Rd",
    "iso:country":"US",
    "sg:address":"1804 Mount Pleasant Rd",
    "sg:city":"Chesapeake",
    "sg:classifiers":[
        {
            "category":"Building & Trades",
            "subcategory":"Construction",
            "type":"Services"
        }
    ],
    "sg:phone":"+1 757 572 0713",
    "sg:postcode":"23322",
    "sg:province":"VA",
    "sg:tags":[
        "house",
        "improvement",
        "home"
    ],
    "wof:name":"Finish Line Home Improvements",
    "wof:placetype":"venue"
},
  "geometry": {"coordinates":[-76.16174599999999,36.715709],"type":"Point"}
}