{
  "type": "Feature",
  "properties": {
    "addr:full":"1923 Hull St Richmond VA 23224",
    "addr:housenumber":"1923",
    "addr:postcode":"23224",
    "addr:street":"Hull St",
    "iso:country":"US",
    "sg:address":"1923 Hull St",
    "sg:city":"Richmond",
    "sg:classifiers":[
        {
            "category":"Personal",
            "subcategory":"Beauty Salon",
            "type":"Services"
        }
    ],
    "sg:phone":"+1 804 648 1803",
    "sg:postcode":"23224",
    "sg:province":"VA",
    "wof:name":"Fofana Aminata Hari Brading",
    "wof:placetype":"venue"
},
  "geometry": {"coordinates":[-77.450247,37.517119],"type":"Point"}
}