{
  "type": "Feature",
  "properties": {
    "iso:country":"US",
    "sg:address":"104 Hume Ave",
    "sg:city":"Alexandria",
    "sg:classifiers":[
        {
            "category":"Professional",
            "subcategory":"Research",
            "type":"Services"
        },
        {
            "category":"Retail",
            "subcategory":"Event Space",
            "type":"Services"
        },
        {
            "category":"Organizations",
            "subcategory":"Non-profit Organization",
            "type":"Services"
        }
    ],
    "sg:phone":"+1 703 683 7500",
    "sg:postcode":"22301",
    "sg:province":"VA",
    "sg:tags":[
        "analysis",
        "fund",
        "planning",
        "raising",
        "meeting",
        "market"
    ],
    "sg:website":"http://www.epiphanyproductions.com",
    "wof:name":"Epiphany Productions Inc",
    "wof:placetype":"venue"
},
  "geometry": {"coordinates":[-77.05914,38.830815],"type":"Point"}
}