{
  "type": "Feature",
  "properties": {
    "iso:country":"US",
    "sg:address":"4007 Summit St",
    "sg:city":"Lynchburg",
    "sg:classifiers":[
        {
            "category":"Professional",
            "subcategory":"Business Services",
            "type":"Services"
        }
    ],
    "sg:phone":"+1 434 384 6656",
    "sg:postcode":"24503",
    "sg:province":"VA",
    "wof:name":"Quality Home Inspection",
    "wof:placetype":"venue"
},
  "geometry": {"coordinates":[-79.20384900000001,37.438809],"type":"Point"}
}