{
  "type": "Feature",
  "properties": {
    "iso:country":"US",
    "sg:address":"5111 Witch Duck Ct",
    "sg:city":"Virginia Beach",
    "sg:classifiers":[
        {
            "category":"Building & Trades",
            "subcategory":"Pest Control",
            "type":"Services"
        }
    ],
    "sg:phone":"+1 757 497 0009",
    "sg:postcode":"23462",
    "sg:province":"VA",
    "sg:website":"www.safepestcontrol.com",
    "wof:name":"Safeguard Pest Control",
    "wof:placetype":"venue"
},
  "geometry": {"coordinates":[-76.154712,36.853006],"type":"Point"}
}