{
  "type": "Feature",
  "properties": {
    "iso:country":"US",
    "sg:address":"9505 Protest Ct",
    "sg:city":"Burke",
    "sg:classifiers":[
        {
            "category":"Professional",
            "subcategory":"Management & Consulting",
            "type":"Services"
        }
    ],
    "sg:phone":"+1 703 455 6699",
    "sg:postcode":"22015",
    "sg:province":"VA",
    "sg:tags":[
        "fuel"
    ],
    "wof:name":"ENG Age",
    "wof:placetype":"venue"
},
  "geometry": {"coordinates":[-77.274235,38.762661],"type":"Point"}
}