{
  "type": "Feature",
  "properties": {
    "addr:full":"173 Mount Pleasant Rd Chesapeake VA 23322",
    "addr:housenumber":"173",
    "addr:postcode":"23322",
    "addr:street":"Mount Pleasant Rd",
    "iso:country":"US",
    "sg:address":"173 Mount Pleasant Rd",
    "sg:city":"Chesapeake",
    "sg:classifiers":[
        {
            "category":"Organizations",
            "subcategory":"Religious Organization",
            "type":"Services"
        }
    ],
    "sg:phone":"+1 757 482 2639",
    "sg:postcode":"23322",
    "sg:province":"VA",
    "wof:name":"Great Bridge Evang Free Church",
    "wof:placetype":"venue"
},
  "geometry": {"coordinates":[-76.236724,36.712647],"type":"Point"}
}