{
  "type": "Feature",
  "properties": {
    "iso:country":"US",
    "sg:address":"6161 Kempsville Cir",
    "sg:city":"Norfolk",
    "sg:classifiers":[
        {
            "category":"Health Services",
            "subcategory":"Doctor",
            "type":"Services"
        }
    ],
    "sg:phone":"+1 757 628 8443",
    "sg:postcode":"23502",
    "sg:province":"VA",
    "sg:tags":[
        "medical"
    ],
    "wof:name":"Nuero Surgical Specialist",
    "wof:placetype":"venue"
},
  "geometry": {"coordinates":[-76.194186,36.850358],"type":"Point"}
}