{
  "type": "Feature",
  "properties": {
    "addr:full":"369 Brown's Store Rd Heathsville VA 22579",
    "addr:housenumber":"369",
    "addr:postcode":"22579",
    "addr:street":"Store Rd",
    "iso:country":"US",
    "sg:address":"369 Brown's Store Rd",
    "sg:city":"Heathsville",
    "sg:classifiers":[
        {
            "category":"Travel",
            "subcategory":"Hotels & Motels",
            "type":"Entertainment"
        }
    ],
    "sg:phone":"+1 804 580 3683",
    "sg:postcode":"22579",
    "sg:province":"VA",
    "sg:tags":[
        "operation"
    ],
    "wof:name":"Dove Cottage",
    "wof:placetype":"venue"
},
  "geometry": {"coordinates":[-76.416715,37.82169],"type":"Point"}
}