{
  "type": "Feature",
  "properties": {
    "iso:country":"US",
    "sg:address":"6401 Telegraph Rd",
    "sg:city":"Alexandria",
    "sg:classifiers":[
        {
            "category":"Building & Trades",
            "subcategory":"Plumbing",
            "type":"Services"
        }
    ],
    "sg:phone":"+1 703 960 7754",
    "sg:postcode":"22310",
    "sg:province":"VA",
    "sg:tags":[
        "repair",
        "air conditioning",
        "contractor"
    ],
    "wof:name":"Sunrize Services Inc",
    "wof:placetype":"venue"
},
  "geometry": {"coordinates":[-77.106903,38.779308],"type":"Point"}
}