{
  "type": "Feature",
  "properties": {
    "addr:full":"35577 Blue Hills Dr Glade Spring VA 24340",
    "addr:housenumber":"35577",
    "addr:postcode":"24340",
    "addr:street":"Blue Hills Dr",
    "iso:country":"US",
    "sg:address":"35577 Blue Hills Dr",
    "sg:city":"Glade Spring",
    "sg:classifiers":[
        {
            "category":"Manufacturing",
            "subcategory":"Printing",
            "type":"Manufacturing & Wholesale Goods"
        }
    ],
    "sg:phone":"+1 276 429 2560",
    "sg:postcode":"24340",
    "sg:province":"VA",
    "sg:tags":[
        "publishing"
    ],
    "wof:name":"Craig Hammond",
    "wof:placetype":"venue"
},
  "geometry": {"coordinates":[-81.75123499999999,36.798172],"type":"Point"}
}