{
  "type": "Feature",
  "properties": {
    "iso:country":"US",
    "sg:address":"181 N Main St",
    "sg:city":"Suffolk",
    "sg:classifiers":[
        {
            "category":"Real Estate",
            "subcategory":"Real Estate Operator",
            "type":"Services"
        }
    ],
    "sg:phone":"+1 757 539 2317",
    "sg:postcode":"23434",
    "sg:province":"VA",
    "sg:tags":[
        "apartment"
    ],
    "wof:name":"Suffolk Towers Apartments",
    "wof:placetype":"venue"
},
  "geometry": {"coordinates":[-76.58264699999999,36.729809],"type":"Point"}
}