{
  "type": "Feature",
  "properties": {
    "addr:full":"9091 Williamsville Rd Mechanicsville VA 23116",
    "addr:housenumber":"9091",
    "addr:postcode":"23116",
    "addr:street":"Williamsville Rd",
    "iso:country":"US",
    "sg:address":"9091 Williamsville Rd",
    "sg:city":"Mechanicsville",
    "sg:phone":"+1 804 779 2177",
    "sg:postcode":"23116",
    "sg:province":"VA",
    "sg:tags":[
        "farm",
        "grain",
        "cash"
    ],
    "wof:name":"Pecka Farm",
    "wof:placetype":"venue"
},
  "geometry": {"coordinates":[-77.289484,37.650108],"type":"Point"}
}