{
  "type": "Feature",
  "properties": {
    "addr:full":"1403 Greenbrier Pkwy Chesapeake VA 23320",
    "addr:housenumber":"1403",
    "addr:postcode":"23320",
    "addr:street":"Greenbrier Pkwy",
    "iso:country":"US",
    "sg:address":"1403 Greenbrier Pkwy",
    "sg:city":"Chesapeake",
    "sg:classifiers":[
        {
            "category":"Professional",
            "subcategory":"Computer Services",
            "type":"Services"
        }
    ],
    "sg:phone":"+1 757 233 1250",
    "sg:postcode":"23320",
    "sg:province":"VA",
    "sg:tags":[
        "technology",
        "internet"
    ],
    "wof:name":"Ascendant Internet Tech",
    "wof:placetype":"venue"
},
  "geometry": {"coordinates":[-76.230333,36.776802],"type":"Point"}
}