{
  "type": "Feature",
  "properties": {
    "iso:country":"US",
    "sg:address":"463 S Lynnhaven Rd",
    "sg:city":"Virginia Beach",
    "sg:classifiers":[
        {
            "category":"Personal",
            "subcategory":"Barber",
            "type":"Services"
        }
    ],
    "sg:phone":"+1 757 340 9454",
    "sg:postcode":"23452",
    "sg:province":"VA",
    "sg:tags":[
        "shop"
    ],
    "wof:name":"Tripp's Barber Shop",
    "wof:placetype":"venue"
},
  "geometry": {"coordinates":[-76.078464,36.823629],"type":"Point"}
}