{
  "type": "Feature",
  "properties": {
    "iso:country":"US",
    "sg:address":"2070 Chain Bridge Rd",
    "sg:city":"Vienna",
    "sg:classifiers":[
        {
            "category":"Real Estate",
            "subcategory":"Real Estate Services",
            "type":"Services"
        }
    ],
    "sg:phone":"+1 703 969 6100",
    "sg:postcode":"22182",
    "sg:province":"VA",
    "sg:website":"salebyron.com",
    "wof:name":"Ron Atabaki - Saab Realtors Group",
    "wof:placetype":"venue"
},
  "geometry": {"coordinates":[-77.237424,38.917938],"type":"Point"}
}