{
  "type": "Feature",
  "properties": {
    "addr:full":"1049 Campbell Ave SE Roanoke VA 24013",
    "addr:housenumber":"1049",
    "addr:postcode":"24013",
    "addr:street":"Campbell Ave Se",
    "iso:country":"US",
    "sg:address":"1049 Campbell Ave SE",
    "sg:city":"Roanoke",
    "sg:classifiers":[
        {
            "category":"Retail",
            "subcategory":"Auto Repair",
            "type":"Services"
        }
    ],
    "sg:phone":"+1 540 342 7041",
    "sg:postcode":"24013",
    "sg:province":"VA",
    "sg:tags":[
        "automotive"
    ],
    "wof:name":"Fay Boys Wrecker Service",
    "wof:placetype":"venue"
},
  "geometry": {"coordinates":[-79.926598,37.27457],"type":"Point"}
}