{
  "type": "Feature",
  "properties": {
    "iso:country":"US",
    "sg:address":"11555 Olde Tiverton Cir",
    "sg:city":"Reston",
    "sg:classifiers":[
        {
            "category":"Real Estate",
            "subcategory":"Real Estate Services",
            "type":"Services"
        }
    ],
    "sg:phone":"+1 877 812 8210",
    "sg:postcode":"20194",
    "sg:province":"VA",
    "sg:tags":[
        "apartment",
        "management",
        "rental",
        "finder"
    ],
    "sg:website":"http://www.StJohnsWoodApartments.com",
    "wof:name":"St.Johns Wood",
    "wof:placetype":"venue"
},
  "geometry": {"coordinates":[-77.34577299999999,38.980436],"type":"Point"}
}