{
  "type": "Feature",
  "properties": {
    "addr:full":"6314 Sweetbriar Dr Fredericksburg VA 22407",
    "addr:housenumber":"6314",
    "addr:postcode":"22407",
    "addr:street":"Sweetbriar Dr",
    "iso:country":"US",
    "sg:address":"6314 Sweetbriar Dr",
    "sg:city":"Fredericksburg",
    "sg:classifiers":[
        {
            "category":"Building & Trades",
            "subcategory":"Landscaping Services",
            "type":"Services"
        }
    ],
    "sg:phone":"+1 540 891 5539",
    "sg:postcode":"22407",
    "sg:province":"VA",
    "sg:tags":[
        "landscape",
        "contractor"
    ],
    "wof:name":"Pinehill Landscaping",
    "wof:placetype":"venue"
},
  "geometry": {"coordinates":[-77.54717100000001,38.227702],"type":"Point"}
}