{
  "type": "Feature",
  "properties": {
    "addr:full":"12144 E Lynchburg Salem Tpke Forest VA 24551",
    "addr:housenumber":"12144",
    "addr:postcode":"24551",
    "addr:street":"E Lynchburg;Tpke",
    "iso:country":"US",
    "sg:address":"12144 E Lynchburg Salem Tpke",
    "sg:city":"Forest",
    "sg:classifiers":[
        {
            "category":"Organizations",
            "subcategory":"Community Association",
            "type":"Services"
        }
    ],
    "sg:phone":"+1 434 525 2800",
    "sg:postcode":"24551",
    "sg:province":"VA",
    "sg:tags":[
        "club"
    ],
    "wof:name":"New London Club House Inc",
    "wof:placetype":"venue"
},
  "geometry": {"coordinates":[-79.308758,37.306081],"type":"Point"}
}