{
  "type": "Feature",
  "properties": {
    "addr:full":"1000 Pendleton St Alexandria VA 22314",
    "addr:housenumber":"1000",
    "addr:postcode":"22314",
    "addr:street":"Pendleton St",
    "iso:country":"US",
    "sg:address":"1000 Pendleton St",
    "sg:city":"Alexandria",
    "sg:classifiers":[
        {
            "category":"Professional",
            "subcategory":"Management & Consulting",
            "type":"Services"
        }
    ],
    "sg:phone":"+1 703 837 1113",
    "sg:postcode":"22314",
    "sg:province":"VA",
    "wof:name":"D A & Associates",
    "wof:placetype":"venue"
},
  "geometry": {"coordinates":[-77.05014199999999,38.811298],"type":"Point"}
}