{
  "type": "Feature",
  "properties": {
    "iso:country":"US",
    "sg:address":"11104 Devereux Station Ln",
    "sg:city":"Fairfax Station",
    "sg:classifiers":[
        {
            "category":"Professional",
            "type":"Services"
        }
    ],
    "sg:phone":"+1 703 250 0590",
    "sg:postcode":"22039",
    "sg:province":"VA",
    "wof:name":"Meta Biotherapeutics Inc",
    "wof:placetype":"venue"
},
  "geometry": {"coordinates":[-77.33014300000001,38.747557],"type":"Point"}
}