{
  "type": "Feature",
  "properties": {
    "addr:full":"907 W Glebe Rd Alexandria VA 22305",
    "addr:housenumber":"907",
    "addr:postcode":"22305",
    "addr:street":"W Glebe Rd",
    "iso:country":"US",
    "sg:address":"907 W Glebe Rd",
    "sg:city":"Alexandria",
    "sg:classifiers":[
        {
            "category":"Utilities",
            "subcategory":"Electric",
            "type":"Services"
        }
    ],
    "sg:phone":"+1 703 838 2241",
    "sg:postcode":"22305",
    "sg:province":"VA",
    "wof:name":"Dominion Virginia Power",
    "wof:placetype":"venue"
},
  "geometry": {"coordinates":[-77.076544,38.842939],"type":"Point"}
}