{
  "type": "Feature",
  "properties": {
    "addr:full":"4004 Walney Rd Chantilly VA 20151",
    "addr:housenumber":"4004",
    "addr:postcode":"20151",
    "addr:street":"Walney Rd",
    "iso:country":"US",
    "sg:address":"4004 Walney Rd",
    "sg:city":"Chantilly",
    "sg:classifiers":[
        {
            "category":"Home & Garden",
            "subcategory":"Building Materials",
            "type":"Retail Goods"
        }
    ],
    "sg:phone":"+1 703 378 9060",
    "sg:postcode":"20151",
    "sg:province":"VA",
    "sg:tags":[
        "windows",
        "carpentry",
        "contractor"
    ],
    "wof:name":"See Thru Windows",
    "wof:placetype":"venue"
},
  "geometry": {"coordinates":[-77.432113,38.892453],"type":"Point"}
}