{
  "type": "Feature",
  "properties": {
    "iso:country":"US",
    "sg:address":"12725 Taustin Ln",
    "sg:city":"Herndon",
    "sg:classifiers":[
        {
            "category":"Real Estate",
            "subcategory":"Real Estate Agent",
            "type":"Services"
        }
    ],
    "sg:phone":"+1 703 437 7386",
    "sg:postcode":"20170",
    "sg:province":"VA",
    "wof:name":"Bha Management",
    "wof:placetype":"venue"
},
  "geometry": {"coordinates":[-77.3946,38.983333],"type":"Point"}
}