{
  "type": "Feature",
  "properties": {
    "addr:full":"6441 Northanna Dr Springfield VA 22150",
    "addr:housenumber":"6441",
    "addr:postcode":"22150",
    "addr:street":"Northanna Dr",
    "iso:country":"US",
    "sg:address":"6441 Northanna Dr",
    "sg:city":"Springfield",
    "sg:classifiers":[
        {
            "category":"Professional",
            "subcategory":"Business Services",
            "type":"Services"
        }
    ],
    "sg:phone":"+1 703 719 6142",
    "sg:postcode":"22150",
    "sg:province":"VA",
    "wof:name":"Marathon",
    "wof:placetype":"venue"
},
  "geometry": {"coordinates":[-77.165165,38.789712],"type":"Point"}
}