{
  "type": "Feature",
  "properties": {
    "addr:full":"246 W Freemason St Norfolk VA 23510",
    "addr:housenumber":"246",
    "addr:postcode":"23510",
    "addr:street":"W Freemason St",
    "iso:country":"US",
    "sg:address":"246 W Freemason St",
    "sg:city":"Norfolk",
    "sg:classifiers":[
        {
            "category":"Real Estate",
            "subcategory":"Architect",
            "type":"Services"
        }
    ],
    "sg:phone":"+1 757 627 0896",
    "sg:postcode":"23510",
    "sg:province":"VA",
    "sg:tags":[
        "architectural"
    ],
    "sg:website":"www.livasgroup.com",
    "wof:name":"Livas Group Architects PC",
    "wof:placetype":"venue"
},
  "geometry": {"coordinates":[-76.293301,36.852243],"type":"Point"}
}