{
  "type": "Feature",
  "properties": {
    "addr:full":"9411 Lee Hwy Fairfax VA 22031",
    "addr:housenumber":"9411",
    "addr:postcode":"22031",
    "addr:street":"Lee Hwy",
    "iso:country":"US",
    "sg:address":"9411 Lee Hwy",
    "sg:city":"Fairfax",
    "sg:classifiers":[
        {
            "category":"Professional",
            "subcategory":"Computer Services",
            "type":"Services"
        }
    ],
    "sg:phone":"+1 703 359 5485",
    "sg:postcode":"22031",
    "sg:province":"VA",
    "sg:tags":[
        "programing",
        "related",
        "custom"
    ],
    "wof:name":"One Planet Group LLC",
    "wof:placetype":"venue"
},
  "geometry": {"coordinates":[-77.271675,38.86824],"type":"Point"}
}