{
  "type": "Feature",
  "properties": {
    "addr:full":"7 S 1st St Richmond VA 23219",
    "addr:housenumber":"7",
    "addr:postcode":"23219",
    "addr:street":"S 1St St",
    "iso:country":"US",
    "sg:address":"7 S 1st St",
    "sg:city":"Richmond",
    "sg:classifiers":[
        {
            "category":"Professional",
            "subcategory":"Lawyer & Legal Services",
            "type":"Services"
        }
    ],
    "sg:phone":"+1 804 643 7311",
    "sg:postcode":"23219",
    "sg:province":"VA",
    "wof:name":"Linka William T",
    "wof:placetype":"venue"
},
  "geometry": {"coordinates":[-77.44421,37.541661],"type":"Point"}
}