{
  "type": "Feature",
  "properties": {
    "addr:full":"7727 Wolford Way Lorton VA 22079",
    "addr:housenumber":"7727",
    "addr:postcode":"22079",
    "addr:street":"Wolford Way",
    "iso:country":"US",
    "sg:address":"7727 Wolford Way",
    "sg:city":"Lorton",
    "sg:classifiers":[
        {
            "category":"Professional",
            "subcategory":"Engineering",
            "type":"Services"
        }
    ],
    "sg:phone":"+1 703 339 2220",
    "sg:postcode":"22079",
    "sg:province":"VA",
    "sg:tags":[
        "concrete",
        "engineer",
        "placer"
    ],
    "wof:name":"Recon",
    "wof:placetype":"venue"
},
  "geometry": {"coordinates":[-77.207911,38.714489],"type":"Point"}
}