{
  "type": "Feature",
  "properties": {
    "iso:country":"US",
    "sg:address":"3527 Penn Forest Blvd",
    "sg:city":"Roanoke",
    "sg:classifiers":[
        {
            "category":"Banks & Credit Unions",
            "subcategory":"Investment Brokerage",
            "type":"Services"
        },
        {
            "category":"Professional",
            "subcategory":"Management & Consulting",
            "type":"Services"
        }
    ],
    "sg:phone":"+1 540 777 1300",
    "sg:postcode":"24018",
    "sg:province":"VA",
    "sg:tags":[
        "consultant",
        "planning",
        "financial"
    ],
    "wof:name":"Mc Lawhorn Financial Advisors",
    "wof:placetype":"venue"
},
  "geometry": {"coordinates":[-80.00012,37.22148],"type":"Point"}
}