{
  "type": "Feature",
  "properties": {
    "iso:country":"US",
    "sg:address":"3615 Alberta Dr",
    "sg:city":"Fredericksburg",
    "sg:classifiers":[
        {
            "category":"Shopping",
            "type":"Retail Goods"
        }
    ],
    "sg:phone":"+1 540 834 2442",
    "sg:postcode":"22408",
    "sg:province":"VA",
    "sg:tags":[
        "merchandise"
    ],
    "wof:name":"Xeta Technologies",
    "wof:placetype":"venue"
},
  "geometry": {"coordinates":[-77.462131,38.216556],"type":"Point"}
}