{
  "type": "Feature",
  "properties": {
    "addr:full":"8000 Towers Crescent Dr # 650 Vienna VA 22182",
    "addr:housenumber":"8000",
    "addr:postcode":"22182",
    "addr:street":"Towers Crescent Dr # 650",
    "iso:country":"US",
    "sg:address":"8000 Towers Crescent Dr # 650",
    "sg:city":"Vienna",
    "sg:classifiers":[
        {
            "category":"Banks & Credit Unions",
            "subcategory":"Investment Brokerage",
            "type":"Services"
        }
    ],
    "sg:phone":"+1 703 847 6264",
    "sg:postcode":"22182",
    "sg:province":"VA",
    "sg:tags":[
        "advisory"
    ],
    "wof:name":"Kenray Investment Management Corporation",
    "wof:placetype":"venue"
},
  "geometry": {"coordinates":[-77.219818,38.913712],"type":"Point"}
}