{
  "type": "Feature",
  "properties": {
    "addr:full":"233 Halifax St Petersburg VA 23803",
    "addr:housenumber":"233",
    "addr:postcode":"23803",
    "addr:street":"Halifax St",
    "iso:country":"US",
    "sg:address":"233 Halifax St",
    "sg:city":"Petersburg",
    "sg:classifiers":[
        {
            "category":"Social Services",
            "subcategory":"Child Care",
            "type":"Services"
        }
    ],
    "sg:phone":"+1 804 732 3000",
    "sg:postcode":"23803",
    "sg:province":"VA",
    "sg:tags":[
        "day"
    ],
    "wof:name":"Joy & Love Day Care Center",
    "wof:placetype":"venue"
},
  "geometry": {"coordinates":[-77.40626899999999,37.22265],"type":"Point"}
}