{
  "type": "Feature",
  "properties": {
    "iso:country":"US",
    "sg:address":"3807 S Four Mile Run Dr",
    "sg:city":"Arlington",
    "sg:classifiers":[
        {
            "category":"Building & Trades",
            "subcategory":"Construction",
            "type":"Services"
        }
    ],
    "sg:phone":"+1 571 236 2028",
    "sg:postcode":"22206",
    "sg:province":"VA",
    "sg:tags":[
        "insulation",
        "contractor"
    ],
    "wof:name":"M. & M. Insulation",
    "wof:placetype":"venue"
},
  "geometry": {"coordinates":[-77.091792,38.845821],"type":"Point"}
}