{
  "type": "Feature",
  "properties": {
    "addr:full":"12124 Westwood Hills Dr Herndon VA 20171",
    "addr:housenumber":"12124",
    "addr:postcode":"20171",
    "addr:street":"Westwood Hills Dr",
    "iso:country":"US",
    "sg:address":"12124 Westwood Hills Dr",
    "sg:city":"Herndon",
    "sg:classifiers":[
        {
            "category":"Professional",
            "subcategory":"Computer Services",
            "type":"Services"
        }
    ],
    "sg:phone":"+1 703 620 2748",
    "sg:postcode":"20171",
    "sg:province":"VA",
    "sg:tags":[
        "consultant",
        "designer",
        "datum",
        "system"
    ],
    "wof:name":"Designetics",
    "wof:placetype":"venue"
},
  "geometry": {"coordinates":[-77.366597,38.903586],"type":"Point"}
}