{
  "type": "Feature",
  "properties": {
    "iso:country":"US",
    "sg:address":"14301 Sullyfield Cir",
    "sg:city":"Chantilly",
    "sg:classifiers":[
        {
            "category":"Building & Trades",
            "subcategory":"Construction",
            "type":"Services"
        }
    ],
    "sg:phone":"+1 703 803 2273",
    "sg:postcode":"20151",
    "sg:province":"VA",
    "sg:tags":[
        "repairing",
        "remodeling",
        "contractor"
    ],
    "sg:website":"www.casedesign.com",
    "wof:name":"Case Design",
    "wof:placetype":"venue"
},
  "geometry": {"coordinates":[-77.439053,38.893656],"type":"Point"}
}