{
  "type": "Feature",
  "properties": {
    "iso:country":"US",
    "sg:address":"6201 Union Mill Rd",
    "sg:city":"Clifton",
    "sg:classifiers":[
        {
            "category":"Restaurant",
            "type":"Food & Drink"
        }
    ],
    "sg:phone":"+1 703 631 9099",
    "sg:postcode":"20124",
    "sg:province":"VA",
    "sg:tags":[
        "eating",
        "golf",
        "public",
        "course"
    ],
    "wof:name":"Twin Lakes Golf Course",
    "wof:placetype":"venue"
},
  "geometry": {"coordinates":[-77.41321000000001,38.821175],"type":"Point"}
}