{
  "type": "Feature",
  "properties": {
    "addr:full":"1211 Armory Dr Franklin VA 23851",
    "addr:housenumber":"1211",
    "addr:postcode":"23851",
    "addr:street":"Armory Dr",
    "iso:country":"US",
    "sg:address":"1211 Armory Dr",
    "sg:city":"Franklin",
    "sg:classifiers":[
        {
            "category":"Autos & Motor Vehicles",
            "subcategory":"Automobile Sales",
            "type":"Retail Goods"
        }
    ],
    "sg:phone":"+1 757 562 3151",
    "sg:postcode":"23851",
    "sg:province":"VA",
    "sg:tags":[
        "car",
        "dealer"
    ],
    "wof:name":"Champion Chevrolet Buick",
    "wof:placetype":"venue"
},
  "geometry": {"coordinates":[-76.943146,36.671113],"type":"Point"}
}