{
  "type": "Feature",
  "properties": {
    "addr:full":"7127 Merrimac Trl Williamsburg VA 23185",
    "addr:housenumber":"7127",
    "addr:postcode":"23185",
    "addr:street":"Merrimac Trl",
    "iso:country":"US",
    "sg:address":"7127 Merrimac Trl",
    "sg:city":"Williamsburg",
    "sg:classifiers":[
        {
            "category":"Restaurant",
            "type":"Food & Drink"
        }
    ],
    "sg:phone":"+1 757 229 3051",
    "sg:postcode":"23185",
    "sg:province":"VA",
    "sg:tags":[
        "dairy",
        "bar"
    ],
    "wof:name":"Anne Queen Dairy Snack Inc",
    "wof:placetype":"venue"
},
  "geometry": {"coordinates":[-76.673937,37.264084],"type":"Point"}
}