{
  "type": "Feature",
  "properties": {
    "addr:full":"982 Meadowood Trl Martinsville VA 24112",
    "addr:housenumber":"982",
    "addr:postcode":"24112",
    "addr:street":"Meadowood Trl",
    "iso:country":"US",
    "sg:address":"982 Meadowood Trl",
    "sg:city":"Martinsville",
    "sg:classifiers":[
        {
            "category":"Organizations",
            "subcategory":"Religious Organization",
            "type":"Services"
        }
    ],
    "sg:phone":"+1 276 957 2641",
    "sg:postcode":"24112",
    "sg:province":"VA",
    "wof:name":"Temple Of Spirit In Truth",
    "wof:placetype":"venue"
},
  "geometry": {"coordinates":[-79.957162,36.654309],"type":"Point"}
}