{
  "type": "Feature",
  "properties": {
    "addr:full":"1523 Gilmer Ave NW Roanoke VA 24017",
    "addr:housenumber":"1523",
    "addr:postcode":"24017",
    "addr:street":"Gilmer Ave Nw",
    "iso:country":"US",
    "sg:address":"1523 Gilmer Ave NW",
    "sg:city":"Roanoke",
    "sg:classifiers":[
        {
            "category":"Taxi",
            "type":"Transportation"
        }
    ],
    "sg:phone":"+1 540 400 0893",
    "sg:postcode":"24017",
    "sg:province":"VA",
    "sg:tags":[
        "taxicab"
    ],
    "wof:name":"North West Cab",
    "wof:placetype":"venue"
},
  "geometry": {"coordinates":[-79.96368200000001,37.281877],"type":"Point"}
}