{
  "type": "Feature",
  "properties": {
    "iso:country":"US",
    "sg:address":"4510 Andes Dr",
    "sg:city":"Fairfax",
    "sg:classifiers":[
        {
            "category":"Building & Trades",
            "subcategory":"Construction",
            "type":"Services"
        }
    ],
    "sg:phone":"+1 703 385 7757",
    "sg:postcode":"22030",
    "sg:province":"VA",
    "sg:tags":[
        "house"
    ],
    "wof:name":"Jt & JC Construction Inc",
    "wof:placetype":"venue"
},
  "geometry": {"coordinates":[-77.32920300000001,38.837691],"type":"Point"}
}