{
  "type": "Feature",
  "properties": {
    "addr:full":"821 Orange St Bedford VA 24523",
    "addr:housenumber":"821",
    "addr:postcode":"24523",
    "addr:street":"Orange St",
    "iso:country":"US",
    "sg:address":"821 Orange St",
    "sg:city":"Bedford",
    "sg:classifiers":[
        {
            "category":"Retail",
            "subcategory":"Auto Repair",
            "type":"Services"
        }
    ],
    "sg:phone":"+1 540 586 3078",
    "sg:postcode":"24523",
    "sg:province":"VA",
    "sg:tags":[
        "repairing",
        "automotive",
        "automobile"
    ],
    "wof:name":"Jimmy's Automotive",
    "wof:placetype":"venue"
},
  "geometry": {"coordinates":[-79.506428,37.334199],"type":"Point"}
}