{
  "type": "Feature",
  "properties": {
    "iso:country":"US",
    "sg:address":"712 W 20th St",
    "sg:city":"Norfolk",
    "sg:classifiers":[
        {
            "category":"Manufacturing",
            "subcategory":"Printing",
            "type":"Manufacturing & Wholesale Goods"
        }
    ],
    "sg:phone":"+1 757 627 3018",
    "sg:postcode":"23517",
    "sg:province":"VA",
    "sg:tags":[
        "offset"
    ],
    "wof:name":"Bay Printing Incorporated",
    "wof:placetype":"venue"
},
  "geometry": {"coordinates":[-76.296318,36.870166],"type":"Point"}
}