{
  "type": "Feature",
  "properties": {
    "iso:country":"US",
    "sg:address":"10900 Pegwell Dr",
    "sg:city":"Midlothian",
    "sg:classifiers":[
        {
            "category":"Manufacturing",
            "subcategory":"Metals",
            "type":"Manufacturing & Wholesale Goods"
        }
    ],
    "sg:phone":"+1 804 320 2368",
    "sg:postcode":"23113",
    "sg:province":"VA",
    "sg:tags":[
        "product",
        "fabricated",
        "mfg"
    ],
    "wof:name":"South Eastern Strapping",
    "wof:placetype":"venue"
},
  "geometry": {"coordinates":[-77.60329299999999,37.535956],"type":"Point"}
}