{
  "type": "Feature",
  "properties": {
    "addr:full":"172 Crest Rd Ruckersville VA 22968",
    "addr:housenumber":"172",
    "addr:postcode":"22968",
    "addr:street":"Crest Rd",
    "iso:country":"US",
    "sg:address":"172 Crest Rd",
    "sg:city":"Ruckersville",
    "sg:classifiers":[
        {
            "category":"Retail",
            "subcategory":"Animal Services",
            "type":"Services"
        }
    ],
    "sg:phone":"+1 434 985 8654",
    "sg:postcode":"22968",
    "sg:province":"VA",
    "wof:name":"Snips",
    "wof:placetype":"venue"
},
  "geometry": {"coordinates":[-78.423524,38.26602],"type":"Point"}
}