{
  "type": "Feature",
  "properties": {
    "addr:full":"333 Switchback Rd Christiansburg VA 24073",
    "addr:housenumber":"333",
    "addr:postcode":"24073",
    "addr:street":"Switchback Rd",
    "iso:country":"US",
    "sg:address":"333 Switchback Rd",
    "sg:city":"Christiansburg",
    "sg:classifiers":[
        {
            "category":"Professional",
            "subcategory":"Computer Services",
            "type":"Services"
        }
    ],
    "sg:phone":"+1 540 382 8247",
    "sg:postcode":"24073",
    "sg:province":"VA",
    "wof:name":"Kevin Martin Consulting",
    "wof:placetype":"venue"
},
  "geometry": {"coordinates":[-80.487674,37.161597],"type":"Point"}
}