{
  "type": "Feature",
  "properties": {
    "addr:full":"46 E Church St Martinsville VA 24112",
    "addr:housenumber":"46",
    "addr:postcode":"24112",
    "addr:street":"E Church St",
    "iso:country":"US",
    "sg:address":"46 E Church St",
    "sg:city":"Martinsville",
    "sg:classifiers":[
        {
            "category":"Food & Beverages",
            "subcategory":"Bakery",
            "type":"Retail Goods"
        }
    ],
    "sg:phone":"+1 276 638 1013",
    "sg:postcode":"24112",
    "sg:province":"VA",
    "sg:tags":[
        "baker"
    ],
    "wof:name":"Pie's By Freddy The Pie Man",
    "wof:placetype":"venue"
},
  "geometry": {"coordinates":[-79.87234599999999,36.690646],"type":"Point"}
}