{
  "type": "Feature",
  "properties": {
    "addr:full":"6105 Health Center Ln Fredericksburg VA 22407",
    "addr:housenumber":"6105",
    "addr:postcode":"22407",
    "addr:street":"Health Center Ln",
    "iso:country":"US",
    "sg:address":"6105 Health Center Ln",
    "sg:city":"Fredericksburg",
    "sg:classifiers":[
        {
            "category":"Health Services",
            "subcategory":"Hospital",
            "type":"Services"
        }
    ],
    "sg:phone":"+1 540 786 5666",
    "sg:postcode":"22407",
    "sg:province":"VA",
    "sg:tags":[
        "specialty"
    ],
    "sg:website":"www.medicorp.org",
    "wof:name":"Cancer Center Of Virginia",
    "wof:placetype":"venue"
},
  "geometry": {"coordinates":[-77.54491299999999,38.288509],"type":"Point"}
}