{
  "type": "Feature",
  "properties": {
    "iso:country":"US",
    "sg:address":"3215 Bridge Rd",
    "sg:city":"Suffolk",
    "sg:classifiers":[
        {
            "category":"Insurance",
            "subcategory":"Insurance Agent",
            "type":"Services"
        }
    ],
    "sg:phone":"+1 757 686 1775",
    "sg:postcode":"23435",
    "sg:province":"VA",
    "wof:name":"Drummond Agency",
    "wof:placetype":"venue"
},
  "geometry": {"coordinates":[-76.482519,36.863365],"type":"Point"}
}