{
  "type": "Feature",
  "properties": {
    "iso:country":"US",
    "sg:address":"12142 Richland Dr",
    "sg:city":"Catharpin",
    "sg:classifiers":[
        {
            "category":"Home & Garden",
            "subcategory":"Building Materials",
            "type":"Retail Goods"
        },
        {
            "category":"Manufacturing",
            "subcategory":"Tools & Machinery",
            "type":"Manufacturing & Wholesale Goods"
        }
    ],
    "sg:phone":"+1 703 754 0619",
    "sg:postcode":"20143",
    "sg:province":"VA",
    "sg:tags":[
        "m",
        "electrical",
        "door",
        "mfg"
    ],
    "wof:name":"Action Garage Doors",
    "wof:placetype":"venue"
},
  "geometry": {"coordinates":[-77.560063,38.856642],"type":"Point"}
}