{
  "type": "Feature",
  "properties": {
    "iso:country":"US",
    "sg:address":"1358 Magnolia Ave",
    "sg:city":"Norfolk",
    "sg:classifiers":[
        {
            "category":"Travel",
            "subcategory":"Travel Agent",
            "type":"Entertainment"
        }
    ],
    "sg:phone":"+1 757 440 0568",
    "sg:postcode":"23508",
    "sg:province":"VA",
    "sg:tags":[
        "cruise"
    ],
    "wof:name":"Cruise One",
    "wof:placetype":"venue"
},
  "geometry": {"coordinates":[-76.306636,36.895126],"type":"Point"}
}