{
  "type": "Feature",
  "properties": {
    "addr:full":"1211 King St Alexandria VA 22314",
    "addr:housenumber":"1211",
    "addr:postcode":"22314",
    "addr:street":"King St",
    "iso:country":"US",
    "sg:address":"1211 King St",
    "sg:city":"Alexandria",
    "sg:classifiers":[
        {
            "category":"Wholesale",
            "subcategory":"Medical Equipment & Supplies",
            "type":"Manufacturing & Wholesale Goods"
        }
    ],
    "sg:phone":"+1 703 684 2966",
    "sg:postcode":"22314",
    "sg:province":"VA",
    "sg:tags":[
        "distribution"
    ],
    "wof:name":"Evergreen Supply Inc",
    "wof:placetype":"venue"
},
  "geometry": {"coordinates":[-77.053454,38.805961],"type":"Point"}
}