{
  "type": "Feature",
  "properties": {
    "addr:full":"1204 Gallop Ave Chesapeake VA 23324",
    "addr:housenumber":"1204",
    "addr:postcode":"23324",
    "addr:street":"Gallop Ave",
    "iso:country":"US",
    "sg:address":"1204 Gallop Ave",
    "sg:city":"Chesapeake",
    "sg:classifiers":[
        {
            "category":"Building & Trades",
            "subcategory":"Plumbing",
            "type":"Services"
        }
    ],
    "sg:phone":"+1 757 543 3551",
    "sg:postcode":"23324",
    "sg:province":"VA",
    "sg:tags":[
        "heating",
        "contractor"
    ],
    "wof:name":"Indoor Air Systems Inc",
    "wof:placetype":"venue"
},
  "geometry": {"coordinates":[-76.27905800000001,36.780748],"type":"Point"}
}