{
  "type": "Feature",
  "properties": {
    "iso:country":"US",
    "sg:address":"814 Kempsville Road Suite 106",
    "sg:city":"Norfolk",
    "sg:classifiers":[
        {
            "category":"Professional",
            "subcategory":"Management & Consulting",
            "type":"Services"
        }
    ],
    "sg:phone":"+1 800 905 4335",
    "sg:postcode":"23502",
    "sg:province":"VA",
    "sg:website":"http://www.geeksoncall.com/",
    "wof:name":"1-800-905-GEEK",
    "wof:placetype":"venue"
},
  "geometry": {"coordinates":[-76.190933,36.848129],"type":"Point"}
}