{
  "type": "Feature",
  "properties": {
    "iso:country":"US",
    "sg:address":"14457 Salisbury Plain Ct",
    "sg:city":"Centreville",
    "sg:classifiers":[
        {
            "category":"Professional",
            "type":"Services"
        }
    ],
    "sg:phone":"+1 703 444 1043",
    "sg:postcode":"20120",
    "sg:province":"VA",
    "sg:tags":[
        "establishment"
    ],
    "wof:name":"A 1 Caurier",
    "wof:placetype":"venue"
},
  "geometry": {"coordinates":[-77.446257,38.846858],"type":"Point"}
}