{
  "type": "Feature",
  "properties": {
    "addr:full":"4245 Markham St Annandale VA 22003",
    "addr:housenumber":"4245",
    "addr:postcode":"22003",
    "addr:street":"Markham St",
    "iso:country":"US",
    "sg:address":"4245 Markham St",
    "sg:city":"Annandale",
    "sg:classifiers":[
        {
            "category":"Sports & Exercise",
            "subcategory":"Bowling",
            "type":"Entertainment"
        }
    ],
    "sg:phone":"+1 703 256 2211",
    "sg:postcode":"22003",
    "sg:province":"VA",
    "sg:tags":[
        "center"
    ],
    "wof:name":"AMF",
    "wof:placetype":"venue"
},
  "geometry": {"coordinates":[-77.19953700000001,38.831471],"type":"Point"}
}