{
  "type": "Feature",
  "properties": {
    "addr:full":"1290 Roanoke St Christiansburg VA 24073",
    "addr:housenumber":"1290",
    "addr:postcode":"24073",
    "addr:street":"Roanoke St",
    "iso:country":"US",
    "sg:address":"1290 Roanoke St",
    "sg:city":"Christiansburg",
    "sg:classifiers":[
        {
            "category":"Restaurant",
            "type":"Food & Drink"
        }
    ],
    "sg:phone":"+1 540 382 8970",
    "sg:postcode":"24073",
    "sg:province":"VA",
    "sg:tags":[
        "eating"
    ],
    "wof:name":"Stones Cafeteria",
    "wof:placetype":"venue"
},
  "geometry": {"coordinates":[-80.384496,37.134039],"type":"Point"}
}