{
  "type": "Feature",
  "properties": {
    "addr:full":"2301 Jefferson Davis Hwy Fredericksburg VA 22401",
    "addr:housenumber":"2301",
    "addr:postcode":"22401",
    "addr:street":"Jefferson Davis Hwy",
    "iso:country":"US",
    "sg:address":"2301 Jefferson Davis Hwy",
    "sg:city":"Fredericksburg",
    "sg:classifiers":[
        {
            "category":"Social Services",
            "subcategory":"Child Care",
            "type":"Services"
        }
    ],
    "sg:phone":"+1 540 374 5099",
    "sg:postcode":"22401",
    "sg:province":"VA",
    "wof:name":"Son Shine Childcare Ctr",
    "wof:placetype":"venue"
},
  "geometry": {"coordinates":[-77.489784,38.279811],"type":"Point"}
}