{
  "type": "Feature",
  "properties": {
    "addr:full":"2001 Library Rd Richmond VA 23231",
    "addr:housenumber":"2001",
    "addr:postcode":"23231",
    "addr:street":"Library Rd",
    "iso:country":"US",
    "sg:address":"2001 Library Rd",
    "sg:city":"Richmond",
    "sg:classifiers":[
        {
            "category":"Education",
            "subcategory":"Library",
            "type":"Public Place"
        }
    ],
    "sg:phone":"+1 804 222 3414",
    "sg:postcode":"23231",
    "sg:province":"VA",
    "wof:name":"Henirco County Public Library",
    "wof:placetype":"venue"
},
  "geometry": {"coordinates":[-77.37347699999999,37.473081],"type":"Point"}
}