{
  "type": "Feature",
  "properties": {
    "addr:full":"312 Montgomery St Alexandria VA 22314",
    "addr:housenumber":"312",
    "addr:postcode":"22314",
    "addr:street":"Montgomery St",
    "iso:country":"US",
    "sg:address":"312 Montgomery St",
    "sg:city":"Alexandria",
    "sg:classifiers":[
        {
            "category":"Manufacturing",
            "subcategory":"Lumber",
            "type":"Manufacturing & Wholesale Goods"
        }
    ],
    "sg:phone":"+1 703 548 0990",
    "sg:postcode":"22314",
    "sg:province":"VA",
    "sg:tags":[
        "forester"
    ],
    "sg:website":"www.acf-foresters.com",
    "wof:name":"Association-Consulting Frstrs",
    "wof:placetype":"venue"
},
  "geometry": {"coordinates":[-77.04159,38.813633],"type":"Point"}
}