{
  "type": "Feature",
  "properties": {
    "addr:full":"10901 Merchants Hope Rd Hopewell VA 23860",
    "addr:housenumber":"10901",
    "addr:postcode":"23860",
    "addr:street":"Merchants Hope Rd",
    "iso:country":"US",
    "sg:address":"10901 Merchants Hope Rd",
    "sg:city":"Hopewell",
    "sg:classifiers":[
        {
            "category":"Building & Trades",
            "subcategory":"Construction",
            "type":"Services"
        }
    ],
    "sg:phone":"+1 804 541 4266",
    "sg:postcode":"23860",
    "sg:province":"VA",
    "sg:tags":[
        "house"
    ],
    "wof:name":"A-1 Aluminum & Remodeling",
    "wof:placetype":"venue"
},
  "geometry": {"coordinates":[-77.21407600000001,37.263903],"type":"Point"}
}