{
  "type": "Feature",
  "properties": {
    "addr:full":"15399 Merry Cat Ln Belle Haven VA 23306",
    "addr:housenumber":"15399",
    "addr:postcode":"23306",
    "addr:street":"Merry Cat Ln",
    "iso:country":"US",
    "sg:address":"15399 Merry Cat Ln",
    "sg:city":"Belle Haven",
    "sg:classifiers":[
        {
            "category":"Health Services",
            "subcategory":"Chiropractor",
            "type":"Services"
        }
    ],
    "sg:phone":"+1 757 442 3444",
    "sg:postcode":"23306",
    "sg:province":"VA",
    "wof:name":"Eastern Shore Chiropractic",
    "wof:placetype":"venue"
},
  "geometry": {"coordinates":[-75.815664,37.545818],"type":"Point"}
}