{
  "type": "Feature",
  "properties": {
    "addr:full":"8631 Sanford Dr Richmond VA 23228",
    "addr:housenumber":"8631",
    "addr:postcode":"23228",
    "addr:street":"Sanford Dr",
    "iso:country":"US",
    "sg:address":"8631 Sanford Dr",
    "sg:city":"Richmond",
    "sg:classifiers":[
        {
            "category":"Retail",
            "subcategory":"Auto Repair",
            "type":"Services"
        }
    ],
    "sg:phone":"+1 804 264 8810",
    "sg:postcode":"23228",
    "sg:province":"VA",
    "sg:tags":[
        "repairing",
        "automotive",
        "automobile"
    ],
    "wof:name":"Fletcher's Tire & Auto",
    "wof:placetype":"venue"
},
  "geometry": {"coordinates":[-77.502584,37.627924],"type":"Point"}
}