{
  "type": "Feature",
  "properties": {
    "iso:country":"US",
    "sg:address":"1611 Garfield Dr",
    "sg:city":"Norfolk",
    "sg:classifiers":[
        {
            "category":"Professional",
            "type":"Services"
        }
    ],
    "sg:phone":"+1 757 226 8378",
    "sg:postcode":"23503",
    "sg:province":"VA",
    "sg:tags":[
        "establishment"
    ],
    "wof:name":"Radogna Shanisty",
    "wof:placetype":"venue"
},
  "geometry": {"coordinates":[-76.230825,36.930637],"type":"Point"}
}