{
  "type": "Feature",
  "properties": {
    "addr:full":"10887 Woodleaf Ln Great Falls VA 22066",
    "addr:housenumber":"10887",
    "addr:postcode":"22066",
    "addr:street":"Woodleaf Ln",
    "iso:country":"US",
    "sg:address":"10887 Woodleaf Ln",
    "sg:city":"Great Falls",
    "sg:classifiers":[
        {
            "category":"Professional",
            "subcategory":"Engineering",
            "type":"Services"
        }
    ],
    "sg:phone":"+1 703 450 4313",
    "sg:postcode":"22066",
    "sg:province":"VA",
    "wof:name":"James M Calm Engrg Conslt",
    "wof:placetype":"venue"
},
  "geometry": {"coordinates":[-77.31661200000001,39.028533],"type":"Point"}
}