{
  "type": "Feature",
  "properties": {
    "iso:country":"US",
    "sg:address":"233 S Van Dorn St",
    "sg:city":"Alexandria",
    "sg:classifiers":[
        {
            "category":"Banks & Credit Unions",
            "subcategory":"Bank",
            "type":"Services"
        }
    ],
    "sg:phone":"+1 703 461 1965",
    "sg:postcode":"22304",
    "sg:province":"VA",
    "sg:website":"www.firstvirginiabank.com",
    "wof:name":"B B & T",
    "wof:placetype":"venue"
},
  "geometry": {"coordinates":[-77.13251200000001,38.809846],"type":"Point"}
}