{
  "type": "Feature",
  "properties": {
    "addr:full":"8820 N Five Forks Rd Amelia Court Hse VA 23002",
    "addr:housenumber":"8820",
    "addr:postcode":"23002",
    "addr:street":"N Five Forks Rd Amelia Court",
    "iso:country":"US",
    "sg:address":"8820 N Five Forks Rd",
    "sg:city":"Amelia Court Hse",
    "sg:classifiers":[
        {
            "category":"Retail",
            "subcategory":"Auto Repair",
            "type":"Services"
        }
    ],
    "sg:phone":"+1 804 561 2835",
    "sg:postcode":"23002",
    "sg:province":"VA",
    "sg:tags":[
        "repairing",
        "automobile"
    ],
    "wof:name":"Jim's Automotive Svc",
    "wof:placetype":"venue"
},
  "geometry": {"coordinates":[-77.97899700000001,37.33625],"type":"Point"}
}