{
  "type": "Feature",
  "properties": {
    "addr:full":"4369 Electric Rd Roanoke VA 24018",
    "addr:housenumber":"4369",
    "addr:postcode":"24018",
    "addr:street":"Electric Rd",
    "iso:country":"US",
    "sg:address":"4369 Electric Rd",
    "sg:city":"Roanoke",
    "sg:classifiers":[
        {
            "category":"Restaurant",
            "type":"Food & Drink"
        }
    ],
    "sg:phone":"+1 540 774 0939",
    "sg:postcode":"24018",
    "sg:province":"VA",
    "wof:name":"Wendy's",
    "wof:placetype":"venue"
},
  "geometry": {"coordinates":[-79.976365,37.229152],"type":"Point"}
}