{
  "type": "Feature",
  "properties": {
    "addr:full":"1604 Leesville Rd Lynch Station VA 24571",
    "addr:housenumber":"1604",
    "addr:postcode":"24571",
    "addr:street":"Leesville Rd",
    "iso:country":"US",
    "sg:address":"1604 Leesville Rd",
    "sg:city":"Lynch Station",
    "sg:classifiers":[
        {
            "category":"Building & Trades",
            "subcategory":"Electrical",
            "type":"Services"
        }
    ],
    "sg:phone":"+1 434 369 4227",
    "sg:postcode":"24571",
    "sg:province":"VA",
    "sg:tags":[
        "electric",
        "contractor"
    ],
    "wof:name":"James E Dowdy Electric",
    "wof:placetype":"venue"
},
  "geometry": {"coordinates":[-79.38381699999999,37.138816],"type":"Point"}
}