{
  "type": "Feature",
  "properties": {
    "addr:full":"8075 Leesburg Pike Vienna VA 22182",
    "addr:housenumber":"8075",
    "addr:postcode":"22182",
    "addr:street":"Leesburg Pike",
    "iso:country":"US",
    "sg:address":"8075 Leesburg Pike",
    "sg:city":"Vienna",
    "sg:classifiers":[
        {
            "category":"Insurance",
            "subcategory":"Insurance Agent",
            "type":"Services"
        },
        {
            "category":"Insurance",
            "subcategory":"Life Insurance",
            "type":"Services"
        }
    ],
    "sg:phone":"+1 703 749 3700",
    "sg:postcode":"22182",
    "sg:province":"VA",
    "sg:tags":[
        "carrier"
    ],
    "wof:name":"New York Life",
    "wof:placetype":"venue"
},
  "geometry": {"coordinates":[-77.224324,38.913928],"type":"Point"}
}