{
  "type": "Feature",
  "properties": {
    "iso:country":"US",
    "sg:address":"1463 Johnston Willis Dr",
    "sg:city":"Richmond",
    "sg:classifiers":[
        {
            "category":"Health Services",
            "subcategory":"Doctor",
            "type":"Services"
        }
    ],
    "sg:phone":"+1 804 560 8782",
    "sg:postcode":"23235",
    "sg:province":"VA",
    "sg:tags":[
        "medical"
    ],
    "wof:name":"Mark E Johns MD Facc",
    "wof:placetype":"venue"
},
  "geometry": {"coordinates":[-77.597846,37.511937],"type":"Point"}
}