{
  "type": "Feature",
  "properties": {
    "addr:full":"303 N Main St Amherst VA 24521",
    "addr:housenumber":"303",
    "addr:postcode":"24521",
    "addr:street":"N Main St",
    "iso:country":"US",
    "sg:address":"303 N Main St",
    "sg:city":"Amherst",
    "sg:classifiers":[
        {
            "category":"Banks & Credit Unions",
            "subcategory":"Bank",
            "type":"Services"
        }
    ],
    "sg:phone":"+1 434 946 5511",
    "sg:postcode":"24521",
    "sg:province":"VA",
    "sg:tags":[
        "state"
    ],
    "wof:name":"First Virginia Bank-Southwest",
    "wof:placetype":"venue"
},
  "geometry": {"coordinates":[-79.04425999999999,37.589688],"type":"Point"}
}