{
  "type": "Feature",
  "properties": {
    "addr:full":"3018 Annandale Rd Falls Church VA 22042",
    "addr:housenumber":"3018",
    "addr:postcode":"22042",
    "addr:street":"Annandale Rd",
    "iso:country":"US",
    "sg:address":"3018 Annandale Rd",
    "sg:city":"Falls Church",
    "sg:classifiers":[
        {
            "category":"Restaurant",
            "type":"Food & Drink"
        }
    ],
    "sg:phone":"+1 703 533 2340",
    "sg:postcode":"22042",
    "sg:province":"VA",
    "sg:tags":[
        "eating"
    ],
    "wof:name":"Pho State",
    "wof:placetype":"venue"
},
  "geometry": {"coordinates":[-77.174646,38.869457],"type":"Point"}
}