{
  "type": "Feature",
  "properties": {
    "addr:full":"400 S Main St Culpeper VA 22701",
    "addr:housenumber":"400",
    "addr:postcode":"22701",
    "addr:street":"S Main St",
    "iso:country":"US",
    "sg:address":"400 S Main St",
    "sg:city":"Culpeper",
    "sg:classifiers":[
        {
            "category":"Professional",
            "subcategory":"Computer Services",
            "type":"Services"
        }
    ],
    "sg:phone":"+1 540 825 7488",
    "sg:postcode":"22701",
    "sg:province":"VA",
    "sg:tags":[
        "development",
        "programming",
        "software"
    ],
    "wof:name":"Apex Voice Communications",
    "wof:placetype":"venue"
},
  "geometry": {"coordinates":[-77.99684999999999,38.471368],"type":"Point"}
}