{
  "type": "Feature",
  "properties": {
    "addr:full":"8209 Watson St Mc Lean VA 22102",
    "addr:housenumber":"8209",
    "addr:postcode":"22102",
    "addr:street":"Watson St Mc Lean",
    "iso:country":"US",
    "sg:address":"8209 Watson St",
    "sg:city":"Mc Lean",
    "sg:classifiers":[
        {
            "category":"Building & Trades",
            "subcategory":"Construction",
            "type":"Services"
        }
    ],
    "sg:phone":"+1 703 448 0680",
    "sg:postcode":"22102",
    "sg:province":"VA",
    "sg:tags":[
        "contractor"
    ],
    "wof:name":"Edmar Construction Co Inc",
    "wof:placetype":"venue"
},
  "geometry": {"coordinates":[-77.227042,38.917684],"type":"Point"}
}