{
  "type": "Feature",
  "properties": {
    "addr:full":"2214 Station Rd Richmond VA 23234",
    "addr:housenumber":"2214",
    "addr:postcode":"23234",
    "addr:street":"Station Rd",
    "iso:country":"US",
    "sg:address":"2214 Station Rd",
    "sg:city":"Richmond",
    "sg:classifiers":[
        {
            "category":"Manufacturing",
            "subcategory":"Tools & Machinery",
            "type":"Manufacturing & Wholesale Goods"
        }
    ],
    "sg:phone":"+1 804 526 4455",
    "sg:postcode":"23234",
    "sg:province":"VA",
    "sg:tags":[
        "commercial",
        "refrigeration",
        "mfg"
    ],
    "wof:name":"Hill Phoenix Inc",
    "wof:placetype":"venue"
},
  "geometry": {"coordinates":[-77.435686,37.440653],"type":"Point"}
}