{
  "type": "Feature",
  "properties": {
    "iso:country":"US",
    "sg:address":"17541 Jefferson Davis Hwy",
    "sg:city":"Dumfries",
    "sg:classifiers":[
        {
            "category":"Autos & Motor Vehicles",
            "subcategory":"Automobile Sales",
            "type":"Retail Goods"
        }
    ],
    "sg:phone":"+1 703 221 8676",
    "sg:postcode":"22026",
    "sg:province":"VA",
    "sg:tags":[
        "bus",
        "rental"
    ],
    "sg:website":"www.lijo.com",
    "wof:name":"LIJO Inc",
    "wof:placetype":"venue"
},
  "geometry": {"coordinates":[-77.318634,38.571252],"type":"Point"}
}