{
  "type": "Feature",
  "properties": {
    "addr:full":"9695 Liberia Ave Manassas VA 20110",
    "addr:postcode":"9695;20110",
    "addr:street":"Liberia Ave",
    "iso:country":"US",
    "sg:address":"9695 Liberia Ave",
    "sg:city":"Manassas",
    "sg:classifiers":[
        {
            "category":"Fast Food",
            "type":"Food & Drink"
        },
        {
            "category":"Restaurant",
            "type":"Food & Drink"
        }
    ],
    "sg:phone":"+1 703 361 5440",
    "sg:postcode":"20110",
    "sg:province":"VA",
    "sg:tags":[
        "house",
        "american",
        "steak",
        "take",
        "barbecue"
    ],
    "sg:website":"http://www.longhornsteakhouse.com",
    "wof:name":"Longhorn Steakhouse",
    "wof:placetype":"venue"
},
  "geometry": {"coordinates":[-77.450357,38.744845],"type":"Point"}
}