{
  "type": "Feature",
  "properties": {
    "addr:full":"1780 Carl D Silver Pkwy Fredericksburg VA 22401",
    "addr:housenumber":"1780",
    "addr:postcode":"22401",
    "addr:street":"Carl D Silver Pkwy",
    "iso:country":"US",
    "sg:address":"1780 Carl D Silver Pkwy",
    "sg:city":"Fredericksburg",
    "sg:classifiers":[
        {
            "category":"Restaurant",
            "type":"Food & Drink"
        }
    ],
    "sg:menulink":"http://www.allmenus.com/va/fredericksburg/105375-ryans/menu/",
    "sg:phone":"+1 540 548 0051",
    "sg:postcode":"22401",
    "sg:province":"VA",
    "sg:tags":[
        "american"
    ],
    "wof:name":"Ryan's",
    "wof:placetype":"venue"
},
  "geometry": {"coordinates":[-77.510452,38.306259],"type":"Point"}
}