{
  "type": "Feature",
  "properties": {
    "addr:full":"3055 Carfax Rd St Paul VA 24230",
    "addr:postcode":"3055;24230",
    "addr:street":"Carfax Rd",
    "iso:country":"US",
    "sg:address":"3055 Carfax Rd",
    "sg:city":"St Paul",
    "sg:classifiers":[
        {
            "category":"Government",
            "subcategory":"Office",
            "type":"Public Place"
        }
    ],
    "sg:phone":"+1 276 762 0159",
    "sg:postcode":"24230",
    "sg:province":"VA",
    "sg:tags":[
        "county"
    ],
    "wof:name":"Wise County Regional Fltrtn",
    "wof:placetype":"venue"
},
  "geometry": {"coordinates":[-82.373335,36.904703],"type":"Point"}
}