{
  "type": "Feature",
  "properties": {
    "addr:full":"14109 Hackberry Rd Chester VA 23836",
    "addr:housenumber":"14109",
    "addr:postcode":"23836",
    "addr:street":"Hackberry Rd",
    "iso:country":"US",
    "sg:address":"14109 Hackberry Rd",
    "sg:city":"Chester",
    "sg:classifiers":[
        {
            "category":"Building & Trades",
            "subcategory":"Construction",
            "type":"Services"
        }
    ],
    "sg:phone":"+1 804 530 3257",
    "sg:postcode":"23836",
    "sg:province":"VA",
    "sg:tags":[
        "nonresidential"
    ],
    "wof:name":"West Construction",
    "wof:placetype":"venue"
},
  "geometry": {"coordinates":[-77.332145,37.335169],"type":"Point"}
}