{
  "type": "Feature",
  "properties": {
    "iso:country":"US",
    "sg:address":"248 N 1st St",
    "sg:city":"Hampton",
    "sg:classifiers":[
        {
            "category":"Health Services",
            "subcategory":"Doctor",
            "type":"Services"
        }
    ],
    "sg:phone":"+1 757 851 6565",
    "sg:postcode":"23664",
    "sg:province":"VA",
    "sg:tags":[
        "physician",
        "surgeon"
    ],
    "wof:name":"Ramzy N Nabih MD",
    "wof:placetype":"venue"
},
  "geometry": {"coordinates":[-76.28953199999999,37.044774],"type":"Point"}
}