{
  "type": "Feature",
  "properties": {
    "addr:full":"13559 Northumberland Hwy Heathsville VA 22473",
    "addr:housenumber":"13559",
    "addr:postcode":"22473",
    "addr:street":"Northumberland Hwy Heathsville",
    "iso:country":"US",
    "sg:address":"13559 Northumberland Hwy",
    "sg:city":"Heathsville",
    "sg:classifiers":[
        {
            "category":"Organizations",
            "subcategory":"Religious Organization",
            "type":"Services"
        }
    ],
    "sg:phone":"+1 804 580 2127",
    "sg:postcode":"22473",
    "sg:province":"VA",
    "sg:tags":[
        "church"
    ],
    "wof:name":"New Friendship Baptist Church",
    "wof:placetype":"venue"
},
  "geometry": {"coordinates":[-76.35972700000001,37.888156],"type":"Point"}
}