{
  "type": "Feature",
  "properties": {
    "addr:full":"8641 Breeden Ave Manassas VA 20110",
    "addr:postcode":"8641;20110",
    "addr:street":"Breeden Ave",
    "iso:country":"US",
    "sg:address":"8641 Breeden Ave",
    "sg:city":"Manassas",
    "sg:classifiers":[
        {
            "category":"Building & Trades",
            "subcategory":"Construction",
            "type":"Services"
        }
    ],
    "sg:phone":"+1 703 257 6398",
    "sg:postcode":"20110",
    "sg:province":"VA",
    "sg:tags":[
        "general",
        "contractor"
    ],
    "wof:name":"Mike Garcia Construction",
    "wof:placetype":"venue"
},
  "geometry": {"coordinates":[-77.458365,38.767744],"type":"Point"}
}