{
  "type": "Feature",
  "properties": {
    "iso:country":"US",
    "sg:address":"PO Box 10086",
    "sg:city":"Arlington",
    "sg:classifiers":[
        {
            "category":"Education",
            "subcategory":"School",
            "type":"Public Place"
        }
    ],
    "sg:phone":"+1 703 841 0080",
    "sg:postcode":"22210",
    "sg:province":"VA",
    "wof:name":"Cohen & Co",
    "wof:placetype":"venue"
},
  "geometry": {"coordinates":[-77.094902,38.885502],"type":"Point"}
}