{
  "type": "Feature",
  "properties": {
    "iso:country":"US",
    "sg:address":"1920 Colley Ave",
    "sg:city":"Norfolk",
    "sg:classifiers":[
        {
            "category":"Organizations",
            "subcategory":"Religious Organization",
            "type":"Services"
        }
    ],
    "sg:phone":"+1 757 626 0770",
    "sg:postcode":"23507",
    "sg:province":"VA",
    "wof:name":"Chabad of Tidewater",
    "wof:placetype":"venue"
},
  "geometry": {"coordinates":[-76.296584,36.870108],"type":"Point"}
}