{
  "type": "Feature",
  "properties": {
    "iso:country":"US",
    "sg:address":"25479 Hillman Hwy",
    "sg:city":"Abingdon",
    "sg:classifiers":[
        {
            "category":"Manufacturing",
            "subcategory":"Metals",
            "type":"Manufacturing & Wholesale Goods"
        }
    ],
    "sg:phone":"+1 276 628 9269",
    "sg:postcode":"24210",
    "sg:province":"VA",
    "sg:tags":[
        "steel"
    ],
    "sg:website":"www.naxs.net",
    "wof:name":"Abingdon Steel Inc",
    "wof:placetype":"venue"
},
  "geometry": {"coordinates":[-81.91837599999999,36.732588],"type":"Point"}
}