{
  "type": "Feature",
  "properties": {
    "addr:full":"1920 E Broad St Richmond VA 23223",
    "addr:housenumber":"1920",
    "addr:postcode":"23223",
    "addr:street":"E Broad St",
    "iso:country":"US",
    "sg:address":"1920 E Broad St",
    "sg:city":"Richmond",
    "sg:classifiers":[
        {
            "category":"Retail",
            "subcategory":"Auto Repair",
            "type":"Services"
        }
    ],
    "sg:phone":"+1 804 343 0005",
    "sg:postcode":"23223",
    "sg:province":"VA",
    "sg:tags":[
        "automotive"
    ],
    "wof:name":"Broad Street Towing",
    "wof:placetype":"venue"
},
  "geometry": {"coordinates":[-77.423467,37.534569],"type":"Point"}
}