{
  "type": "Feature",
  "properties": {
    "addr:full":"12715 Warwick Blvd Newport News VA 23606",
    "addr:housenumber":"12715",
    "addr:postcode":"23606",
    "addr:street":"Warwick Blvd",
    "iso:country":"US",
    "sg:address":"12715 Warwick Blvd",
    "sg:city":"Newport News",
    "sg:classifiers":[
        {
            "category":"Restaurant",
            "type":"Food & Drink"
        }
    ],
    "sg:phone":"+1 757 930 1100",
    "sg:postcode":"23606",
    "sg:province":"VA",
    "sg:tags":[
        "eating",
        "caterer"
    ],
    "wof:name":"Lingo's Custom Catering",
    "wof:placetype":"venue"
},
  "geometry": {"coordinates":[-76.499606,37.086066],"type":"Point"}
}