{
  "type": "Feature",
  "properties": {
    "addr:full":"712 Norfolk Ln Alexandria VA 22314",
    "addr:housenumber":"712",
    "addr:postcode":"22314",
    "addr:street":"Norfolk Ln",
    "iso:country":"US",
    "sg:address":"712 Norfolk Ln",
    "sg:city":"Alexandria",
    "sg:classifiers":[
        {
            "category":"Retail",
            "subcategory":"Portrait Studio",
            "type":"Services"
        }
    ],
    "sg:phone":"+1 703 628 3156",
    "sg:postcode":"22314",
    "sg:province":"VA",
    "sg:tags":[
        "photo"
    ],
    "wof:name":"Cook Photography LLC Dwayne",
    "wof:placetype":"venue"
},
  "geometry": {"coordinates":[-77.045924,38.823009],"type":"Point"}
}