{
  "type": "Feature",
  "properties": {
    "iso:country":"US",
    "sg:address":"5136 Hildebrand Rd NW",
    "sg:city":"Roanoke",
    "sg:classifiers":[
        {
            "category":"Retail",
            "subcategory":"Auto Repair",
            "type":"Services"
        }
    ],
    "sg:phone":"+1 540 366 7154",
    "sg:postcode":"24012",
    "sg:province":"VA",
    "sg:tags":[
        "transmission",
        "general"
    ],
    "wof:name":"Scruggs Transmission Service",
    "wof:placetype":"venue"
},
  "geometry": {"coordinates":[-79.95246899999999,37.321515],"type":"Point"}
}