{
  "type": "Feature",
  "properties": {
    "addr:full":"344 Cool Spring Rd White Stone VA 22578",
    "addr:housenumber":"344",
    "addr:postcode":"22578",
    "addr:street":"Cool Spring Rd",
    "iso:country":"US",
    "sg:address":"344 Cool Spring Rd",
    "sg:city":"White Stone",
    "sg:classifiers":[
        {
            "category":"Professional",
            "subcategory":"Management & Consulting",
            "type":"Services"
        }
    ],
    "sg:phone":"+1 804 435 3877",
    "sg:postcode":"22578",
    "sg:province":"VA",
    "sg:tags":[
        "business"
    ],
    "wof:name":"Edward A Tulis LLC",
    "wof:placetype":"venue"
},
  "geometry": {"coordinates":[-76.395026,37.633885],"type":"Point"}
}