{
  "type": "Feature",
  "properties": {
    "addr:full":"2756 Battlefield Blvd S Chesapeake VA 23322",
    "addr:housenumber":"2756",
    "addr:postcode":"23322",
    "addr:street":"Battlefield Blvd",
    "iso:country":"US",
    "sg:address":"2756 Battlefield Blvd S",
    "sg:city":"Chesapeake",
    "sg:classifiers":[
        {
            "category":"Retail",
            "subcategory":"Repair Shop",
            "type":"Services"
        },
        {
            "category":"Building & Trades",
            "subcategory":"Plumbing",
            "type":"Services"
        }
    ],
    "sg:phone":"+1 757 421 4981",
    "sg:postcode":"23322",
    "sg:province":"VA",
    "sg:tags":[
        "septic"
    ],
    "wof:name":"Z Artis Septic Tank Service",
    "wof:placetype":"venue"
},
  "geometry": {"coordinates":[-76.20920599999999,36.628787],"type":"Point"}
}