{
  "type": "Feature",
  "properties": {
    "addr:full":"8766 Frontier Rd Wise VA 24293",
    "addr:housenumber":"8766",
    "addr:postcode":"24293",
    "addr:street":"Frontier Rd",
    "iso:country":"US",
    "sg:address":"8766 Frontier Rd",
    "sg:city":"Wise",
    "sg:classifiers":[
        {
            "category":"Building & Trades",
            "subcategory":"Plumbing",
            "type":"Services"
        }
    ],
    "sg:phone":"+1 276 328 9573",
    "sg:postcode":"24293",
    "sg:province":"VA",
    "sg:tags":[
        "contractor"
    ],
    "wof:name":"Cantrell Ola & Eva",
    "wof:placetype":"venue"
},
  "geometry": {"coordinates":[-82.515429,37.057743],"type":"Point"}
}