{
  "type": "Feature",
  "properties": {
    "addr:full":"3105 Chatham Rd Richmond VA 23227",
    "addr:housenumber":"3105",
    "addr:postcode":"23227",
    "addr:street":"Chatham Rd",
    "iso:country":"US",
    "sg:address":"3105 Chatham Rd",
    "sg:city":"Richmond",
    "sg:classifiers":[
        {
            "category":"Organizations",
            "subcategory":"Religious Organization",
            "type":"Services"
        }
    ],
    "sg:phone":"+1 804 353 8351",
    "sg:postcode":"23227",
    "sg:province":"VA",
    "wof:name":"Ray of Hope Pentecostal",
    "wof:placetype":"venue"
},
  "geometry": {"coordinates":[-77.45971900000001,37.575428],"type":"Point"}
}