{
  "type": "Feature",
  "properties": {
    "addr:full":"14021 Steeplestone Rd Midlothian VA 23113",
    "addr:housenumber":"14021",
    "addr:postcode":"23113",
    "addr:street":"Steeplestone Rd",
    "iso:country":"US",
    "sg:address":"14021 Steeplestone Rd",
    "sg:city":"Midlothian",
    "sg:classifiers":[
        {
            "category":"Retail",
            "subcategory":"Laundry & Dry Cleaning",
            "type":"Services"
        }
    ],
    "sg:phone":"+1 804 379 1645",
    "sg:postcode":"23113",
    "sg:province":"VA",
    "sg:tags":[
        "cleaners"
    ],
    "wof:name":"Jin's Cleaners",
    "wof:placetype":"venue"
},
  "geometry": {"coordinates":[-77.665024,37.525791],"type":"Point"}
}