{
  "type": "Feature",
  "properties": {
    "iso:country":"US",
    "sg:address":"1100 W Grace St",
    "sg:city":"Richmond",
    "sg:classifiers":[
        {
            "category":"Organizations",
            "subcategory":"Religious Organization",
            "type":"Services"
        }
    ],
    "sg:phone":"+1 804 353 4413",
    "sg:postcode":"23220",
    "sg:province":"VA",
    "sg:tags":[
        "school"
    ],
    "wof:name":"Luther Memorial School",
    "wof:placetype":"venue"
},
  "geometry": {"coordinates":[-77.45689,37.553321],"type":"Point"}
}