{
  "type": "Feature",
  "properties": {
    "addr:full":"1202 Azalea Ave Richmond VA 23227",
    "addr:housenumber":"1202",
    "addr:postcode":"23227",
    "addr:street":"Azalea Ave",
    "iso:country":"US",
    "sg:address":"1202 Azalea Ave",
    "sg:city":"Richmond",
    "sg:classifiers":[
        {
            "category":"Restaurant",
            "type":"Food & Drink"
        }
    ],
    "sg:menulink":"http://www.allmenus.com/va/richmond/257391-red-house/menu/",
    "sg:phone":"+1 804 266 8333",
    "sg:postcode":"23227",
    "sg:province":"VA",
    "sg:tags":[
        "american",
        "asian",
        "chinese"
    ],
    "wof:name":"Red House",
    "wof:placetype":"venue"
},
  "geometry": {"coordinates":[-77.452985,37.601644],"type":"Point"}
}