{
  "type": "Feature",
  "properties": {
    "addr:full":"6165 Kendra Way Centreville VA 20121",
    "addr:housenumber":"6165",
    "addr:postcode":"20121",
    "addr:street":"Kendra Way",
    "iso:country":"US",
    "sg:address":"6165 Kendra Way",
    "sg:city":"Centreville",
    "sg:classifiers":[
        {
            "category":"Utilities",
            "subcategory":"Telephone",
            "type":"Services"
        }
    ],
    "sg:phone":"+1 703 266 1020",
    "sg:postcode":"20121",
    "sg:province":"VA",
    "sg:tags":[
        "communications"
    ],
    "wof:name":"Lenox Finds",
    "wof:placetype":"venue"
},
  "geometry": {"coordinates":[-77.437106,38.831452],"type":"Point"}
}