{
  "type": "Feature",
  "properties": {
    "addr:full":"897 Harrison St SE Leesburg VA 20175",
    "addr:housenumber":"897",
    "addr:postcode":"20175",
    "addr:street":"Harrison St Se",
    "iso:country":"US",
    "sg:address":"897 Harrison St SE",
    "sg:city":"Leesburg",
    "sg:classifiers":[
        {
            "category":"Professional",
            "subcategory":"Engineering",
            "type":"Services"
        }
    ],
    "sg:phone":"+1 703 777 0005",
    "sg:postcode":"20175",
    "sg:province":"VA",
    "sg:tags":[
        "engineer",
        "accounting",
        "management",
        "related",
        "research"
    ],
    "sg:website":"www.waterborne-env.com",
    "wof:name":"Waterborne Environmental Inc",
    "wof:placetype":"venue"
},
  "geometry": {"coordinates":[-77.558103,39.102682],"type":"Point"}
}