{
  "type": "Feature",
  "properties": {
    "addr:full":"6378 Church St Chincoteague VA 23336",
    "addr:housenumber":"6378",
    "addr:postcode":"23336",
    "addr:street":"Church St",
    "iso:country":"US",
    "sg:address":"6378 Church St",
    "sg:city":"Chincoteague",
    "sg:classifiers":[
        {
            "category":"Real Estate",
            "subcategory":"Real Estate Agent",
            "type":"Services"
        }
    ],
    "sg:phone":"+1 757 336 7653",
    "sg:postcode":"23336",
    "sg:province":"VA",
    "wof:name":"Patty Woodhurst",
    "wof:placetype":"venue"
},
  "geometry": {"coordinates":[-75.37155199999999,37.93157],"type":"Point"}
}