{
  "type": "Feature",
  "properties": {
    "addr:full":"14 E Custis Ave Alexandria VA 22301",
    "addr:housenumber":"14",
    "addr:postcode":"22301",
    "addr:street":"E Custis Ave",
    "iso:country":"US",
    "sg:address":"14 E Custis Ave",
    "sg:city":"Alexandria",
    "sg:classifiers":[
        {
            "category":"Farming",
            "subcategory":"Farm",
            "type":"Manufacturing & Wholesale Goods"
        }
    ],
    "sg:phone":"+1 703 683 0367",
    "sg:postcode":"22301",
    "sg:province":"VA",
    "wof:name":"Ring Ranch",
    "wof:placetype":"venue"
},
  "geometry": {"coordinates":[-77.061956,38.825102],"type":"Point"}
}