{
  "type": "Feature",
  "properties": {
    "iso:country":"US",
    "sg:address":"36 Jacobs Ln",
    "sg:city":"Fredericksburg",
    "sg:classifiers":[
        {
            "category":"Building & Trades",
            "subcategory":"Landscaping Services",
            "type":"Services"
        }
    ],
    "sg:phone":"+1 540 286 1833",
    "sg:postcode":"22406",
    "sg:province":"VA",
    "sg:tags":[
        "landscape",
        "contractor"
    ],
    "wof:name":"Action Lawn & Landscaping",
    "wof:placetype":"venue"
},
  "geometry": {"coordinates":[-77.54472,38.382342],"type":"Point"}
}