{
  "type": "Feature",
  "properties": {
    "iso:country":"US",
    "sg:address":"1410 Incarnation Dr",
    "sg:city":"Charlottesville",
    "sg:classifiers":[
        {
            "category":"Banks & Credit Unions",
            "subcategory":"Investment Brokerage",
            "type":"Services"
        }
    ],
    "sg:phone":"+1 434 296 4111",
    "sg:postcode":"22901",
    "sg:province":"VA",
    "sg:tags":[
        "advisory",
        "financial"
    ],
    "wof:name":"O'Leary Wealth Mgmt",
    "wof:placetype":"venue"
},
  "geometry": {"coordinates":[-78.477362,38.072832],"type":"Point"}
}