{
  "type": "Feature",
  "properties": {
    "addr:full":"1288 Hinkle Rd Kenbridge VA 23944",
    "addr:housenumber":"1288",
    "addr:postcode":"23944",
    "addr:street":"Hinkle Rd",
    "iso:country":"US",
    "sg:address":"1288 Hinkle Rd",
    "sg:city":"Kenbridge",
    "sg:classifiers":[
        {
            "category":"Home & Garden",
            "subcategory":"Furniture",
            "type":"Retail Goods"
        }
    ],
    "sg:phone":"+1 434 447 2401",
    "sg:postcode":"23944",
    "sg:province":"VA",
    "sg:tags":[
        "carpentry",
        "cabinet",
        "contractor"
    ],
    "wof:name":"Sweetwater Enterprises",
    "wof:placetype":"venue"
},
  "geometry": {"coordinates":[-78.098291,36.807123],"type":"Point"}
}