{
  "type": "Feature",
  "properties": {
    "iso:country":"US",
    "sg:address":"11911 Freedom Dr",
    "sg:city":"Reston",
    "sg:classifiers":[
        {
            "category":"Education",
            "subcategory":"College",
            "type":"Public Place"
        },
        {
            "category":"Education",
            "subcategory":"Special Training",
            "type":"Public Place"
        }
    ],
    "sg:phone":"+1 703 464 8400",
    "sg:postcode":"20190",
    "sg:province":"VA",
    "sg:tags":[
        "academic",
        "school",
        "educational"
    ],
    "wof:name":"College Board The",
    "wof:placetype":"venue"
},
  "geometry": {"coordinates":[-77.355525,38.959217],"type":"Point"}
}