{
  "type": "Feature",
  "properties": {
    "addr:full":"105 Loudoun St SW Leesburg VA 20175",
    "addr:housenumber":"105",
    "addr:postcode":"20175",
    "addr:street":"Loudoun St Sw",
    "iso:country":"US",
    "sg:address":"105 Loudoun St SW",
    "sg:city":"Leesburg",
    "sg:classifiers":[
        {
            "category":"Health Services",
            "subcategory":"Doctor",
            "type":"Services"
        }
    ],
    "sg:phone":"+1 703 777 1385",
    "sg:postcode":"20175",
    "sg:province":"VA",
    "sg:tags":[
        "medical"
    ],
    "wof:name":"Farooq Akbar MD",
    "wof:placetype":"venue"
},
  "geometry": {"coordinates":[-77.567491,39.114816],"type":"Point"}
}