{
  "type": "Feature",
  "properties": {
    "addr:full":"6738 Mitchell Rd Ridgeway VA 24148",
    "addr:housenumber":"6738",
    "addr:postcode":"24148",
    "addr:street":"Mitchell Rd",
    "iso:country":"US",
    "sg:address":"6738 Mitchell Rd",
    "sg:city":"Ridgeway",
    "sg:classifiers":[
        {
            "category":"Shopping",
            "subcategory":"Books",
            "type":"Retail Goods"
        }
    ],
    "sg:phone":"+1 276 956 2499",
    "sg:postcode":"24148",
    "sg:province":"VA",
    "wof:name":"Spiritual Fruit Christian Book",
    "wof:placetype":"venue"
},
  "geometry": {"coordinates":[-79.834588,36.583275],"type":"Point"}
}