{
  "type": "Feature",
  "properties": {
    "iso:country":"US",
    "sg:address":"10060 Village Hwy",
    "sg:city":"Concord",
    "sg:classifiers":[
        {
            "category":"Food & Beverages",
            "subcategory":"Groceries & Convenience Stores",
            "type":"Retail Goods"
        }
    ],
    "sg:phone":"+1 434 993 2106",
    "sg:postcode":"24538",
    "sg:province":"VA",
    "sg:tags":[
        "grocer"
    ],
    "wof:name":"Carson's Store",
    "wof:placetype":"venue"
},
  "geometry": {"coordinates":[-78.975281,37.345723],"type":"Point"}
}