{
  "type": "Feature",
  "properties": {
    "addr:full":"716 Eden Way N Chesapeake VA 23320",
    "addr:housenumber":"716",
    "addr:postcode":"23320",
    "addr:street":"Eden Way N",
    "iso:country":"US",
    "sg:address":"716 Eden Way N",
    "sg:city":"Chesapeake",
    "sg:classifiers":[
        {
            "category":"Freight",
            "type":"Transportation"
        }
    ],
    "sg:phone":"+1 757 413 9050",
    "sg:postcode":"23320",
    "sg:province":"VA",
    "sg:tags":[
        "commercial",
        "storage"
    ],
    "sg:website":"www.edenwaystorage.com",
    "wof:name":"AAAA Self Storage",
    "wof:placetype":"venue"
},
  "geometry": {"coordinates":[-76.240071,36.772573],"type":"Point"}
}