{
  "type": "Feature",
  "properties": {
    "addr:full":"14389 Potomac Mills Rd Woodbridge VA 22192",
    "addr:housenumber":"14389",
    "addr:postcode":"22192",
    "addr:street":"Potomac Mills Rd",
    "iso:country":"US",
    "sg:address":"14389 Potomac Mills Rd",
    "sg:city":"Woodbridge",
    "sg:classifiers":[
        {
            "category":"Cafe",
            "type":"Food & Drink"
        },
        {
            "category":"Restaurant",
            "type":"Food & Drink"
        }
    ],
    "sg:menulink":"http://www.allmenus.com/va/neabsco/16512-hard-times-cafe/menu/",
    "sg:phone":"+1 703 492 2950",
    "sg:postcode":"22192",
    "sg:province":"VA",
    "sg:tags":[
        "american"
    ],
    "wof:name":"Hard Times Cafe",
    "wof:placetype":"venue"
},
  "geometry": {"coordinates":[-77.29660199999999,38.635861],"type":"Point"}
}