{
  "type": "Feature",
  "properties": {
    "addr:full":"100 Sycamore St Danville VA 24541",
    "addr:housenumber":"100",
    "addr:postcode":"24541",
    "addr:street":"Sycamore St",
    "iso:country":"US",
    "sg:address":"100 Sycamore St",
    "sg:city":"Danville",
    "sg:classifiers":[
        {
            "category":"Organizations",
            "subcategory":"Religious Organization",
            "type":"Services"
        }
    ],
    "sg:phone":"+1 434 799 5541",
    "sg:postcode":"24541",
    "sg:province":"VA",
    "sg:tags":[
        "church"
    ],
    "wof:name":"Union Street Missionary Bptst",
    "wof:placetype":"venue"
},
  "geometry": {"coordinates":[-79.40171599999999,36.591294],"type":"Point"}
}