{
  "type": "Feature",
  "properties": {
    "addr:full":"11209 Richland Grove Dr Great Falls VA 22066",
    "addr:housenumber":"11209",
    "addr:postcode":"22066",
    "addr:street":"Richland Grove Dr",
    "iso:country":"US",
    "sg:address":"11209 Richland Grove Dr",
    "sg:city":"Great Falls",
    "sg:classifiers":[
        {
            "category":"Professional",
            "subcategory":"Computer Services",
            "type":"Services"
        }
    ],
    "sg:phone":"+1 703 444 5311",
    "sg:postcode":"22066",
    "sg:province":"VA",
    "sg:tags":[
        "related"
    ],
    "wof:name":"Hedlund Associates LLC",
    "wof:placetype":"venue"
},
  "geometry": {"coordinates":[-77.334379,39.039827],"type":"Point"}
}