{
  "type": "Feature",
  "properties": {
    "addr:full":"12105 Bundle Rd Chesterfield VA 23838",
    "addr:housenumber":"12105",
    "addr:postcode":"23838",
    "addr:street":"Bundle Rd",
    "iso:country":"US",
    "sg:address":"12105 Bundle Rd",
    "sg:city":"Chesterfield",
    "sg:classifiers":[
        {
            "category":"Professional",
            "type":"Services"
        }
    ],
    "sg:phone":"+1 804 790 1752",
    "sg:postcode":"23838",
    "sg:province":"VA",
    "wof:name":"Gilberts Wildlife Control Svc",
    "wof:placetype":"venue"
},
  "geometry": {"coordinates":[-77.60077099999999,37.337428],"type":"Point"}
}