{
  "type": "Feature",
  "properties": {
    "addr:full":"4501 Millenbeck Rd Richmond VA 23224",
    "addr:housenumber":"4501",
    "addr:postcode":"23224",
    "addr:street":"Millenbeck Rd",
    "iso:country":"US",
    "sg:address":"4501 Millenbeck Rd",
    "sg:city":"Richmond",
    "sg:classifiers":[
        {
            "category":"Recreation",
            "type":"Entertainment"
        }
    ],
    "sg:phone":"+1 804 233 0521",
    "sg:postcode":"23224",
    "sg:province":"VA",
    "wof:name":"Frat Order of Police",
    "wof:placetype":"venue"
},
  "geometry": {"coordinates":[-77.48085399999999,37.504021],"type":"Point"}
}