{
  "type": "Feature",
  "properties": {
    "addr:full":"3 Langley Ave Newport News VA 23601",
    "addr:housenumber":"3",
    "addr:postcode":"23601",
    "addr:street":"Langley Ave",
    "iso:country":"US",
    "sg:address":"3 Langley Ave",
    "sg:city":"Newport News",
    "sg:classifiers":[
        {
            "category":"Building & Trades",
            "subcategory":"Plumbing",
            "type":"Services"
        }
    ],
    "sg:phone":"+1 757 254 4813",
    "sg:postcode":"23601",
    "sg:province":"VA",
    "sg:tags":[
        "conditioning",
        "air",
        "system",
        "contractor"
    ],
    "wof:name":"Action Heating & Air Cond",
    "wof:placetype":"venue"
},
  "geometry": {"coordinates":[-76.471932,37.062767],"type":"Point"}
}