{
  "type": "Feature",
  "properties": {
    "addr:full":"2101 Pocahontas Trl Williamsburg VA 23185",
    "addr:housenumber":"2101",
    "addr:postcode":"23185",
    "addr:street":"Pocahontas Trl",
    "iso:country":"US",
    "sg:address":"2101 Pocahontas Trl",
    "sg:city":"Williamsburg",
    "sg:classifiers":[
        {
            "category":"Freight",
            "type":"Transportation"
        }
    ],
    "sg:phone":"+1 757 253 2520",
    "sg:postcode":"23185",
    "sg:province":"VA",
    "sg:tags":[
        "operator",
        "trucking"
    ],
    "wof:name":"Biagi Brothers Inc",
    "wof:placetype":"venue"
},
  "geometry": {"coordinates":[-76.641555,37.238326],"type":"Point"}
}