{
  "type": "Feature",
  "properties": {
    "addr:full":"2304 Woodhurst Ln Chesapeake VA 23322",
    "addr:housenumber":"2304",
    "addr:postcode":"23322",
    "addr:street":"Woodhurst Ln",
    "iso:country":"US",
    "sg:address":"2304 Woodhurst Ln",
    "sg:city":"Chesapeake",
    "sg:classifiers":[
        {
            "category":"Building & Trades",
            "subcategory":"Construction",
            "type":"Services"
        }
    ],
    "sg:phone":"+1 757 420 2402",
    "sg:postcode":"23322",
    "sg:province":"VA",
    "sg:tags":[
        "house"
    ],
    "wof:name":"Steve Freeman Contractor",
    "wof:placetype":"venue"
},
  "geometry": {"coordinates":[-76.346975,36.639827],"type":"Point"}
}