{
  "type": "Feature",
  "properties": {
    "addr:full":"2071 Jefferson Davis Hwy Stafford VA 22554",
    "addr:housenumber":"2071",
    "addr:postcode":"22554",
    "addr:street":"Jefferson Davis Hwy",
    "iso:country":"US",
    "sg:address":"2071 Jefferson Davis Hwy",
    "sg:city":"Stafford",
    "sg:classifiers":[
        {
            "category":"Personal",
            "type":"Services"
        }
    ],
    "sg:phone":"+1 540 288 3273",
    "sg:postcode":"22554",
    "sg:province":"VA",
    "sg:tags":[
        "therapist",
        "massage"
    ],
    "wof:name":"Elizabeth Collins",
    "wof:placetype":"venue"
},
  "geometry": {"coordinates":[-77.408596,38.41946],"type":"Point"}
}