{
  "type": "Feature",
  "properties": {
    "addr:full":"1204 Main St Lynchburg VA 24504",
    "addr:housenumber":"1204",
    "addr:postcode":"24504",
    "addr:street":"Main St",
    "iso:country":"US",
    "sg:address":"1204 Main St",
    "sg:city":"Lynchburg",
    "sg:classifiers":[
        {
            "category":"Shopping",
            "subcategory":"Used Merchandise",
            "type":"Retail Goods"
        }
    ],
    "sg:phone":"+1 434 846 5580",
    "sg:postcode":"24504",
    "sg:province":"VA",
    "wof:name":"Enchanted Inc",
    "wof:placetype":"venue"
},
  "geometry": {"coordinates":[-79.13933,37.411659],"type":"Point"}
}