{
  "type": "Feature",
  "properties": {
    "addr:full":"2200 Wake Forest Rd Blacksburg VA 24060",
    "addr:housenumber":"2200",
    "addr:postcode":"24060",
    "addr:street":"Wake Forest Rd",
    "iso:country":"US",
    "sg:address":"2200 Wake Forest Rd",
    "sg:city":"Blacksburg",
    "sg:classifiers":[
        {
            "category":"Organizations",
            "subcategory":"Religious Organization",
            "type":"Services"
        }
    ],
    "sg:phone":"+1 540 552 7968",
    "sg:postcode":"24060",
    "sg:province":"VA",
    "sg:tags":[
        "church"
    ],
    "wof:name":"New Pentecostal United Holy",
    "wof:placetype":"venue"
},
  "geometry": {"coordinates":[-80.568005,37.2232],"type":"Point"}
}