{
  "type": "Feature",
  "properties": {
    "addr:full":"6040 E Virginia Beach Blvd Norfolk VA 23502",
    "addr:housenumber":"6040",
    "addr:postcode":"23502",
    "addr:street":"E Virginia Beach Blvd",
    "iso:country":"US",
    "sg:address":"6040 E Virginia Beach Blvd",
    "sg:city":"Norfolk",
    "sg:classifiers":[
        {
            "category":"Banks & Credit Unions",
            "subcategory":"Bank",
            "type":"Services"
        }
    ],
    "sg:phone":"+1 757 459 2410",
    "sg:postcode":"23502",
    "sg:province":"VA",
    "sg:tags":[
        "depository",
        "banking",
        "check",
        "cashing"
    ],
    "wof:name":"Ace Cash Express",
    "wof:placetype":"venue"
},
  "geometry": {"coordinates":[-76.200199,36.855528],"type":"Point"}
}