{
  "type": "Feature",
  "properties": {
    "addr:full":"150 S Main St Harrisonburg VA 22801",
    "addr:housenumber":"150",
    "addr:postcode":"22801",
    "addr:street":"S Main St",
    "iso:country":"US",
    "sg:address":"150 S Main St",
    "sg:city":"Harrisonburg",
    "sg:classifiers":[
        {
            "category":"Shopping",
            "subcategory":"Clothing, Apparel, & Fashions",
            "type":"Retail Goods"
        }
    ],
    "sg:phone":"+1 540 434 2375",
    "sg:postcode":"22801",
    "sg:province":"VA",
    "sg:tags":[
        "shoes"
    ],
    "wof:name":"A & N Stores",
    "wof:placetype":"venue"
},
  "geometry": {"coordinates":[-78.868921,38.447755],"type":"Point"}
}