{
  "type": "Feature",
  "properties": {
    "iso:country":"US",
    "sg:address":"123 E Mellen St",
    "sg:city":"Hampton",
    "sg:classifiers":[
        {
            "category":"Shopping",
            "subcategory":"Clothing, Apparel, & Fashions",
            "type":"Retail Goods"
        }
    ],
    "sg:phone":"+1 757 723 6431",
    "sg:postcode":"23663",
    "sg:province":"VA",
    "sg:tags":[
        "uniform"
    ],
    "wof:name":"Mugler's Of Phoebus",
    "wof:placetype":"venue"
},
  "geometry": {"coordinates":[-76.32020199999999,37.016942],"type":"Point"}
}