{
  "type": "Feature",
  "properties": {
    "addr:full":"1 N 5th St Richmond VA 23219",
    "addr:housenumber":"1",
    "addr:postcode":"23219",
    "addr:street":"N 5Th St",
    "iso:country":"US",
    "sg:address":"1 N 5th St",
    "sg:city":"Richmond",
    "sg:classifiers":[
        {
            "category":"Professional",
            "subcategory":"Accounting & Tax Preparation",
            "type":"Services"
        }
    ],
    "sg:phone":"+1 804 421 9555",
    "sg:postcode":"23219",
    "sg:province":"VA",
    "sg:tags":[
        "accountant"
    ],
    "wof:name":"Christopher J OKeeffe CPA",
    "wof:placetype":"venue"
},
  "geometry": {"coordinates":[-77.43908399999999,37.54123],"type":"Point"}
}