{
  "type": "Feature",
  "properties": {
    "addr:full":"7135 Staples Mill Rd Henrico VA 23228",
    "addr:housenumber":"7135",
    "addr:postcode":"23228",
    "addr:street":"Staples Mill Rd",
    "iso:country":"US",
    "sg:address":"7135 Staples Mill Rd",
    "sg:city":"Henrico",
    "sg:classifiers":[
        {
            "category":"Personal",
            "subcategory":"Beauty Salon",
            "type":"Services"
        },
        {
            "category":"Personal",
            "subcategory":"Tanning Parlor",
            "type":"Services"
        }
    ],
    "sg:phone":"+1 804 266 7885",
    "sg:postcode":"23228",
    "sg:province":"VA",
    "sg:tags":[
        "hair",
        "stylist"
    ],
    "sg:website":"http://www.tanrichmond.com",
    "wof:name":"South Beach Tan & Body Inc",
    "wof:placetype":"venue"
},
  "geometry": {"coordinates":[-77.497719,37.61541],"type":"Point"}
}