{
  "type": "Feature",
  "properties": {
    "iso:country":"US",
    "sg:address":"520 W Franklin St",
    "sg:city":"Richmond",
    "sg:classifiers":[
        {
            "category":"Shopping",
            "subcategory":"Clothing, Apparel, & Fashions",
            "type":"Retail Goods"
        }
    ],
    "sg:phone":"+1 804 253 9233",
    "sg:postcode":"23220",
    "sg:province":"VA",
    "wof:name":"Seziques Menswear",
    "wof:placetype":"venue"
},
  "geometry": {"coordinates":[-77.448471,37.546942],"type":"Point"}
}