{
  "type": "Feature",
  "properties": {
    "iso:country":"US",
    "sg:address":"7171 Manor House Dr",
    "sg:city":"Warrenton",
    "sg:classifiers":[
        {
            "category":"Professional",
            "type":"Services"
        }
    ],
    "sg:phone":"+1 540 349 8534",
    "sg:postcode":"20187",
    "sg:province":"VA",
    "wof:name":"Orizon Inc",
    "wof:placetype":"venue"
},
  "geometry": {"coordinates":[-77.798711,38.740443],"type":"Point"}
}