{
  "type": "Feature",
  "properties": {
    "iso:country":"US",
    "sg:address":"1014 Park Ave",
    "sg:city":"Richmond",
    "sg:classifiers":[
        {
            "category":"Professional",
            "subcategory":"Art Services",
            "type":"Services"
        }
    ],
    "sg:phone":"+1 804 254 8183",
    "sg:postcode":"23220",
    "sg:province":"VA",
    "sg:tags":[
        "commercial",
        "design"
    ],
    "wof:name":"Oobust Illustrations",
    "wof:placetype":"venue"
},
  "geometry": {"coordinates":[-77.455777,37.549242],"type":"Point"}
}