{
  "type": "Feature",
  "properties": {
    "addr:full":"1107 Princess Anne Rd Virginia Beach VA 23457",
    "addr:housenumber":"1107",
    "addr:postcode":"23457",
    "addr:street":"Princess Anne Rd",
    "iso:country":"US",
    "sg:address":"1107 Princess Anne Rd",
    "sg:city":"Virginia Beach",
    "sg:classifiers":[
        {
            "category":"Government",
            "subcategory":"Post Office",
            "type":"Public Place"
        }
    ],
    "sg:phone":"+1 757 426 0167",
    "sg:postcode":"23457",
    "sg:province":"VA",
    "sg:tags":[
        "postal",
        "us"
    ],
    "wof:name":"Backbay Station",
    "wof:placetype":"venue"
},
  "geometry": {"coordinates":[-76.03275499999999,36.655582],"type":"Point"}
}