{
  "type": "Feature",
  "properties": {
    "iso:country":"US",
    "sg:address":"9308 Jenna Ct",
    "sg:city":"Springfield",
    "sg:classifiers":[
        {
            "category":"Recreation",
            "type":"Entertainment"
        }
    ],
    "sg:phone":"+1 703 569 7956",
    "sg:postcode":"22153",
    "sg:province":"VA",
    "wof:name":"Total Strength",
    "wof:placetype":"venue"
},
  "geometry": {"coordinates":[-77.265283,38.755446],"type":"Point"}
}