{
  "type": "Feature",
  "properties": {
    "addr:full":"127 E Church St Martinsville VA 24112",
    "addr:housenumber":"127",
    "addr:postcode":"24112",
    "addr:street":"E Church St",
    "iso:country":"US",
    "sg:address":"127 E Church St",
    "sg:city":"Martinsville",
    "sg:classifiers":[
        {
            "category":"Professional",
            "subcategory":"Management & Consulting",
            "type":"Services"
        }
    ],
    "sg:phone":"+1 276 632 7800",
    "sg:postcode":"24112",
    "sg:province":"VA",
    "sg:tags":[
        "retail",
        "direct",
        "sales"
    ],
    "wof:name":"Mountain Park Spring Water",
    "wof:placetype":"venue"
},
  "geometry": {"coordinates":[-79.870953,36.690473],"type":"Point"}
}