{
  "type": "Feature",
  "properties": {
    "iso:country":"US",
    "sg:address":"285 Piney Forest Rd",
    "sg:city":"Danville",
    "sg:classifiers":[
        {
            "category":"Shopping",
            "subcategory":"Computers & Home Electronics",
            "type":"Retail Goods"
        }
    ],
    "sg:phone":"+1 434 797 4500",
    "sg:postcode":"24540",
    "sg:province":"VA",
    "sg:tags":[
        "equipment",
        "dealer"
    ],
    "wof:name":"High Quality Computer Svc",
    "wof:placetype":"venue"
},
  "geometry": {"coordinates":[-79.413321,36.601009],"type":"Point"}
}