{
  "type": "Feature",
  "properties": {
    "addr:full":"6427 Little Sorrel Dr Mechanicsville VA 23111",
    "addr:housenumber":"6427",
    "addr:postcode":"23111",
    "addr:street":"Little Sorrel Dr",
    "iso:country":"US",
    "sg:address":"6427 Little Sorrel Dr",
    "sg:city":"Mechanicsville",
    "sg:classifiers":[
        {
            "category":"Building & Trades",
            "subcategory":"Electrical",
            "type":"Services"
        }
    ],
    "sg:phone":"+1 804 781 0300",
    "sg:postcode":"23111",
    "sg:province":"VA",
    "sg:tags":[
        "electric",
        "contractor"
    ],
    "wof:name":"Old Dominion Technical Svc",
    "wof:placetype":"venue"
},
  "geometry": {"coordinates":[-77.326903,37.607621],"type":"Point"}
}