{
  "type": "Feature",
  "properties": {
    "iso:country":"US",
    "sg:address":"1332 Titania Ln",
    "sg:city":"Mc Lean",
    "sg:classifiers":[
        {
            "category":"Professional",
            "subcategory":"Research",
            "type":"Services"
        }
    ],
    "sg:phone":"+1 703 556 0333",
    "sg:postcode":"22102",
    "sg:province":"VA",
    "sg:tags":[
        "commercial",
        "physical"
    ],
    "wof:name":"Robert Axtell Dr",
    "wof:placetype":"venue"
},
  "geometry": {"coordinates":[-77.219779,38.939096],"type":"Point"}
}