{
  "type": "Feature",
  "properties": {
    "addr:full":"947 Lyle St Bedford VA 24523",
    "addr:housenumber":"947",
    "addr:postcode":"24523",
    "addr:street":"Lyle St",
    "iso:country":"US",
    "sg:address":"947 Lyle St",
    "sg:city":"Bedford",
    "sg:classifiers":[
        {
            "category":"Organizations",
            "subcategory":"Religious Organization",
            "type":"Services"
        }
    ],
    "sg:phone":"+1 540 586 8010",
    "sg:postcode":"24523",
    "sg:province":"VA",
    "sg:tags":[
        "church"
    ],
    "wof:name":"Trinity Baptist Church Inc",
    "wof:placetype":"venue"
},
  "geometry": {"coordinates":[-79.511697,37.328295],"type":"Point"}
}