{
  "type": "Feature",
  "properties": {
    "iso:country":"US",
    "sg:address":"420 N Center Dr",
    "sg:city":"Norfolk",
    "sg:classifiers":[
        {
            "category":"Professional",
            "subcategory":"Detective & Security Services",
            "type":"Services"
        },
        {
            "category":"Professional",
            "subcategory":"Management & Consulting",
            "type":"Services"
        }
    ],
    "sg:phone":"+1 757 461 4343",
    "sg:postcode":"23502",
    "sg:province":"VA",
    "sg:tags":[
        "consultant",
        "system"
    ],
    "wof:name":"Securewest International Inc",
    "wof:placetype":"venue"
},
  "geometry": {"coordinates":[-76.185903,36.84775],"type":"Point"}
}