{
  "type": "Feature",
  "properties": {
    "addr:full":"20355 Potomac Landing Ter Sterling VA 20165",
    "addr:housenumber":"20355",
    "addr:postcode":"20165",
    "addr:street":"Potomac Landing Ter",
    "iso:country":"US",
    "sg:address":"20355 Potomac Landing Ter",
    "sg:city":"Sterling",
    "sg:classifiers":[
        {
            "category":"Manufacturing",
            "subcategory":"Printing",
            "type":"Manufacturing & Wholesale Goods"
        }
    ],
    "sg:phone":"+1 703 901 5637",
    "sg:postcode":"20165",
    "sg:province":"VA",
    "sg:tags":[
        "magazines-distributors"
    ],
    "wof:name":"Save Now",
    "wof:placetype":"venue"
},
  "geometry": {"coordinates":[-77.351463,39.052132],"type":"Point"}
}