{
  "type": "Feature",
  "properties": {
    "addr:full":"1929 N Westmoreland St Arlington VA 22213",
    "addr:housenumber":"1929",
    "addr:postcode":"22213",
    "addr:street":"N Westmoreland St",
    "iso:country":"US",
    "sg:address":"1929 N Westmoreland St",
    "sg:city":"Arlington",
    "sg:classifiers":[
        {
            "category":"Professional",
            "subcategory":"Art Services",
            "type":"Services"
        }
    ],
    "sg:phone":"+1 703 536 7089",
    "sg:postcode":"22213",
    "sg:province":"VA",
    "sg:tags":[
        "commercial",
        "design"
    ],
    "wof:name":"Aloha Parola Productions",
    "wof:placetype":"venue"
},
  "geometry": {"coordinates":[-77.160218,38.884591],"type":"Point"}
}