{
  "type": "Feature",
  "properties": {
    "addr:full":"107 Institute St Smithfield VA 23430",
    "addr:housenumber":"107",
    "addr:postcode":"23430",
    "addr:street":"Institute St",
    "iso:country":"US",
    "sg:address":"107 Institute St",
    "sg:city":"Smithfield",
    "sg:classifiers":[
        {
            "category":"Insurance",
            "subcategory":"Insurance Agent",
            "type":"Services"
        }
    ],
    "sg:phone":"+1 757 357 4364",
    "sg:postcode":"23430",
    "sg:province":"VA",
    "wof:name":"R E Clay Insurance",
    "wof:placetype":"venue"
},
  "geometry": {"coordinates":[-76.634297,36.981676],"type":"Point"}
}