{
  "type": "Feature",
  "properties": {
    "iso:country":"US",
    "sg:address":"3501 Providence Rd",
    "sg:city":"Hayes",
    "sg:classifiers":[
        {
            "category":"Organizations",
            "subcategory":"Religious Organization",
            "type":"Services"
        }
    ],
    "sg:phone":"+1 804 642 5812",
    "sg:postcode":"23072",
    "sg:province":"VA",
    "sg:tags":[
        "church"
    ],
    "sg:website":"www.providence-baptist.org",
    "wof:name":"Providence Baptist Church",
    "wof:placetype":"venue"
},
  "geometry": {"coordinates":[-76.52664799999999,37.31231],"type":"Point"}
}