{
  "type": "Feature",
  "properties": {
    "addr:full":"1726 Chesterford Way Mc Lean VA 22101",
    "addr:housenumber":"1726",
    "addr:postcode":"22101",
    "addr:street":"Chesterford Way Mc Lean",
    "iso:country":"US",
    "sg:address":"1726 Chesterford Way",
    "sg:city":"Mc Lean",
    "sg:classifiers":[
        {
            "category":"Professional",
            "subcategory":"Business Services",
            "type":"Services"
        }
    ],
    "sg:phone":"+1 703 821 8763",
    "sg:postcode":"22101",
    "sg:province":"VA",
    "wof:name":"Dubose Group",
    "wof:placetype":"venue"
},
  "geometry": {"coordinates":[-77.148884,38.922119],"type":"Point"}
}