{
  "type": "Feature",
  "properties": {
    "iso:country":"US",
    "sg:address":"5335 N Lee Hwy",
    "sg:city":"Arlington",
    "sg:classifiers":[
        {
            "category":"Real Estate",
            "subcategory":"Developer",
            "type":"Services"
        }
    ],
    "sg:phone":"+1 703 532 1177",
    "sg:postcode":"22207",
    "sg:province":"VA",
    "wof:name":"Barrett Co",
    "wof:placetype":"venue"
},
  "geometry": {"coordinates":[-77.137517,38.8964],"type":"Point"}
}