{
  "type": "Feature",
  "properties": {
    "iso:country":"US",
    "sg:address":"899 Harrison St SE",
    "sg:city":"Leesburg",
    "sg:classifiers":[
        {
            "category":"Health Services",
            "subcategory":"Health Practitioner",
            "type":"Services"
        }
    ],
    "sg:phone":"+1 703 777 9045",
    "sg:postcode":"20175",
    "sg:province":"VA",
    "sg:tags":[
        "psychologist"
    ],
    "wof:name":"James Toby Behrmann PHD",
    "wof:placetype":"venue"
},
  "geometry": {"coordinates":[-77.55795999999999,39.102723],"type":"Point"}
}