{
  "type": "Feature",
  "properties": {
    "iso:country":"US",
    "sg:address":"6046 US Hwy 58",
    "sg:city":"South Boston",
    "sg:classifiers":[
        {
            "category":"Food & Beverages",
            "subcategory":"Groceries & Convenience Stores",
            "type":"Retail Goods"
        }
    ],
    "sg:phone":"+1 434 572 4017",
    "sg:postcode":"24592",
    "sg:province":"NC",
    "sg:tags":[
        "station",
        "gas"
    ],
    "wof:name":"Smileys",
    "wof:placetype":"venue"
},
  "geometry": {"coordinates":[-78.808726,36.67113],"type":"Point"}
}