{
  "type": "Feature",
  "properties": {
    "addr:full":"636 S Main St Rocky Mount VA 24151",
    "addr:housenumber":"636",
    "addr:postcode":"24151",
    "addr:street":"S Main St",
    "iso:country":"US",
    "sg:address":"636 S Main St",
    "sg:city":"Rocky Mount",
    "sg:classifiers":[
        {
            "category":"Organizations",
            "subcategory":"Religious Organization",
            "type":"Services"
        }
    ],
    "sg:phone":"+1 540 483 7852",
    "sg:postcode":"24151",
    "sg:province":"VA",
    "wof:name":"Little Angels",
    "wof:placetype":"venue"
},
  "geometry": {"coordinates":[-79.8899,36.992093],"type":"Point"}
}