{
  "type": "Feature",
  "properties": {
    "addr:full":"311 Mechanic St Luray VA 22835",
    "addr:housenumber":"311",
    "addr:postcode":"22835",
    "addr:street":"Mechanic St",
    "iso:country":"US",
    "sg:address":"311 Mechanic St",
    "sg:city":"Luray",
    "sg:classifiers":[
        {
            "category":"Bus Charters",
            "type":"Transportation"
        }
    ],
    "sg:phone":"+1 540 743 4005",
    "sg:postcode":"22835",
    "sg:province":"VA",
    "sg:tags":[
        "tours",
        "operation",
        "local"
    ],
    "wof:name":"Richards Tours",
    "wof:placetype":"venue"
},
  "geometry": {"coordinates":[-78.465991,38.668129],"type":"Point"}
}