{
  "type": "Feature",
  "properties": {
    "addr:full":"134 Deep Creek Rd Newport News VA 23606",
    "addr:housenumber":"134",
    "addr:postcode":"23606",
    "addr:street":"Deep Creek Rd",
    "iso:country":"US",
    "sg:address":"134 Deep Creek Rd",
    "sg:city":"Newport News",
    "sg:classifiers":[
        {
            "category":"Retail",
            "subcategory":"Animal Services",
            "type":"Services"
        }
    ],
    "sg:phone":"+1 757 930 0444",
    "sg:postcode":"23606",
    "sg:province":"VA",
    "sg:tags":[
        "pet",
        "grooming",
        "washing"
    ],
    "wof:name":"Carroll's Gentle Guidance",
    "wof:placetype":"venue"
},
  "geometry": {"coordinates":[-76.502574,37.077645],"type":"Point"}
}