{
  "type": "Feature",
  "properties": {
    "addr:full":"1411 21st St S Arlington VA 22202",
    "addr:housenumber":"1411",
    "addr:postcode":"22202",
    "addr:street":"21St St S",
    "iso:country":"US",
    "sg:address":"1411 21st St S",
    "sg:city":"Arlington",
    "sg:classifiers":[
        {
            "category":"Professional",
            "subcategory":"Management & Consulting",
            "type":"Services"
        }
    ],
    "sg:phone":"+1 703 920 4585",
    "sg:postcode":"22202",
    "sg:province":"VA",
    "sg:tags":[
        "consultant",
        "educational"
    ],
    "wof:name":"Dorcas N Gracey",
    "wof:placetype":"venue"
},
  "geometry": {"coordinates":[-77.070367,38.854777],"type":"Point"}
}