{
  "type": "Feature",
  "properties": {
    "iso:country":"US",
    "sg:address":"10115 Orby Cantrell Hwy",
    "sg:city":"Pound",
    "sg:classifiers":[
        {
            "category":"Autos & Motor Vehicles",
            "subcategory":"Automobile Sales",
            "type":"Retail Goods"
        },
        {
            "category":"Autos & Motor Vehicles",
            "subcategory":"Motorcycle Sales",
            "type":"Retail Goods"
        }
    ],
    "sg:phone":"+1 276 796 4900",
    "sg:postcode":"24279",
    "sg:province":"VA",
    "sg:tags":[
        "a",
        "all",
        "used",
        "terrain",
        "retailer",
        "operates",
        "as",
        "new"
    ],
    "wof:name":"Mountain View Sports  Inc",
    "wof:placetype":"venue"
},
  "geometry": {"coordinates":[-82.599008,37.087129],"type":"Point"}
}