{
  "type": "Feature",
  "properties": {
    "addr:full":"2 Ingalls Cir Clifton Forge VA 24422",
    "addr:housenumber":"2",
    "addr:postcode":"24422",
    "addr:street":"Ingalls Cir",
    "iso:country":"US",
    "sg:address":"2 Ingalls Cir",
    "sg:city":"Clifton Forge",
    "sg:classifiers":[
        {
            "category":"Professional",
            "subcategory":"Business Services",
            "type":"Services"
        }
    ],
    "sg:phone":"+1 540 862 2471",
    "sg:postcode":"24422",
    "sg:province":"VA",
    "wof:name":"Precision Inventory Service",
    "wof:placetype":"venue"
},
  "geometry": {"coordinates":[-79.825402,37.829048],"type":"Point"}
}