{
  "type": "Feature",
  "properties": {
    "addr:full":"5016 Althea Dr Annandale VA 22003",
    "addr:housenumber":"5016",
    "addr:postcode":"22003",
    "addr:street":"Althea Dr",
    "iso:country":"US",
    "sg:address":"5016 Althea Dr",
    "sg:city":"Annandale",
    "sg:classifiers":[
        {
            "category":"Professional",
            "subcategory":"Management & Consulting",
            "type":"Services"
        }
    ],
    "sg:phone":"+1 703 323 5464",
    "sg:postcode":"22003",
    "sg:province":"VA",
    "wof:name":"Mandeville Associates",
    "wof:placetype":"venue"
},
  "geometry": {"coordinates":[-77.245879,38.814175],"type":"Point"}
}