{
  "type": "Feature",
  "properties": {
    "addr:full":"13714 Rosetree Ct Chantilly VA 20151",
    "addr:housenumber":"13714",
    "addr:postcode":"20151",
    "addr:street":"Rosetree Ct",
    "iso:country":"US",
    "sg:address":"13714 Rosetree Ct",
    "sg:city":"Chantilly",
    "sg:classifiers":[
        {
            "category":"Professional",
            "subcategory":"Management & Consulting",
            "type":"Services"
        }
    ],
    "sg:phone":"+1 703 689 0418",
    "sg:postcode":"20151",
    "sg:province":"VA",
    "sg:tags":[
        "business"
    ],
    "wof:name":"Independent Training Associate",
    "wof:placetype":"venue"
},
  "geometry": {"coordinates":[-77.421988,38.901061],"type":"Point"}
}