{
  "type": "Feature",
  "properties": {
    "addr:full":"4780 Longhill Rd Williamsburg VA 23188",
    "addr:housenumber":"4780",
    "addr:postcode":"23188",
    "addr:street":"Longhill Rd",
    "iso:country":"US",
    "sg:address":"4780 Longhill Rd",
    "sg:city":"Williamsburg",
    "sg:classifiers":[
        {
            "category":"Banks & Credit Unions",
            "subcategory":"Bank",
            "type":"Services"
        }
    ],
    "sg:phone":"+1 757 565 0593",
    "sg:postcode":"23188",
    "sg:province":"VA",
    "wof:name":"Citizens & Farmers Bank",
    "wof:placetype":"venue"
},
  "geometry": {"coordinates":[-76.75236599999999,37.307039],"type":"Point"}
}