{
  "type": "Feature",
  "properties": {
    "iso:country":"US",
    "sg:address":"5765 Burke Centre Pkwy",
    "sg:city":"Burke",
    "sg:classifiers":[
        {
            "category":"Professional",
            "subcategory":"Secretarial Services",
            "type":"Services"
        }
    ],
    "sg:phone":"+1 703 818 1930",
    "sg:postcode":"22015",
    "sg:province":"VA",
    "sg:tags":[
        "convention",
        "court",
        "reporter"
    ],
    "wof:name":"Commonwealth Court Reporters",
    "wof:placetype":"venue"
},
  "geometry": {"coordinates":[-77.31965,38.798548],"type":"Point"}
}