{
  "type": "Feature",
  "properties": {
    "addr:full":"2723 Blueberry Bank Chesapeake VA 23325",
    "addr:housenumber":"2723",
    "addr:postcode":"23325",
    "addr:street":"Blueberry Bank",
    "iso:country":"US",
    "sg:address":"2723 Blueberry Bank",
    "sg:city":"Chesapeake",
    "sg:classifiers":[
        {
            "category":"Building & Trades",
            "subcategory":"Cleaning & Sanitation",
            "type":"Services"
        }
    ],
    "sg:phone":"+1 757 545 7499",
    "sg:postcode":"23325",
    "sg:province":"VA",
    "sg:tags":[
        "janitor"
    ],
    "wof:name":"Service Master Commercial",
    "wof:placetype":"venue"
},
  "geometry": {"coordinates":[-76.25402800000001,36.804115],"type":"Point"}
}