{
  "type": "Feature",
  "properties": {
    "addr:full":"13904 Beechwood Point Rd Midlothian VA 23112",
    "addr:housenumber":"13904",
    "addr:postcode":"23112",
    "addr:street":"Beechwood Point Rd",
    "iso:country":"US",
    "sg:address":"13904 Beechwood Point Rd",
    "sg:city":"Midlothian",
    "sg:classifiers":[
        {
            "category":"Professional",
            "subcategory":"Management & Consulting",
            "type":"Services"
        }
    ],
    "sg:phone":"+1 804 739 6450",
    "sg:postcode":"23112",
    "sg:province":"VA",
    "sg:tags":[
        "market"
    ],
    "wof:name":"Emc2",
    "wof:placetype":"venue"
},
  "geometry": {"coordinates":[-77.668018,37.426285],"type":"Point"}
}