{
  "type": "Feature",
  "properties": {
    "iso:country":"US",
    "sg:address":"14513 Jefferson Davis Hwy",
    "sg:city":"Woodbridge",
    "sg:classifiers":[
        {
            "category":"Travel",
            "subcategory":"Travel Agent",
            "type":"Entertainment"
        }
    ],
    "sg:phone":"+1 703 492 5614",
    "sg:postcode":"22191",
    "sg:province":"VA",
    "sg:tags":[
        "agency",
        "bureau"
    ],
    "wof:name":"Vernon Travel & Services Inc",
    "wof:placetype":"venue"
},
  "geometry": {"coordinates":[-77.26858,38.63782],"type":"Point"}
}