{
  "type": "Feature",
  "properties": {
    "addr:full":"1520 Sams Cir Chesapeake VA 23320",
    "addr:housenumber":"1520",
    "addr:postcode":"23320",
    "addr:street":"Sams Cir",
    "iso:country":"US",
    "sg:address":"1520 Sams Cir",
    "sg:city":"Chesapeake",
    "sg:classifiers":[
        {
            "category":"Bars & Pubs",
            "type":"Food & Drink"
        }
    ],
    "sg:menulink":"http://www.allmenus.com/va/chesapeake/35639-applebees-neighborhood-grill--bar/menu/",
    "sg:phone":"+1 757 549 1020",
    "sg:postcode":"23320",
    "sg:province":"VA",
    "sg:tags":[
        "american"
    ],
    "wof:name":"Applebee's Neighborhood Grill & Bar",
    "wof:placetype":"venue"
},
  "geometry": {"coordinates":[-76.25152799999999,36.770973],"type":"Point"}
}