{
  "type": "Feature",
  "properties": {
    "addr:full":"3471 Old Halifax Rd South Boston VA 24592",
    "addr:housenumber":"3471",
    "addr:postcode":"24592",
    "addr:street":"Old Halifax Rd",
    "iso:country":"US",
    "sg:address":"3471 Old Halifax Rd",
    "sg:city":"South Boston",
    "sg:classifiers":[
        {
            "category":"Restaurant",
            "type":"Food & Drink"
        }
    ],
    "sg:menulink":"http://www.allmenus.com/va/scottsburg/147845-subway/menu/",
    "sg:phone":"+1 434 575 1987",
    "sg:postcode":"24592",
    "sg:province":"VA",
    "sg:tags":[
        "american",
        "sandwich"
    ],
    "wof:name":"Subway",
    "wof:placetype":"venue"
},
  "geometry": {"coordinates":[-78.910072,36.733752],"type":"Point"}
}