{
  "type": "Feature",
  "properties": {
    "addr:full":"102 Orchard Cir Hamilton VA 20158",
    "addr:housenumber":"102",
    "addr:postcode":"20158",
    "addr:street":"Orchard Cir",
    "iso:country":"US",
    "sg:address":"102 Orchard Cir",
    "sg:city":"Hamilton",
    "sg:classifiers":[
        {
            "category":"Building & Trades",
            "subcategory":"Plumbing",
            "type":"Services"
        }
    ],
    "sg:phone":"+1 540 338 2180",
    "sg:postcode":"20158",
    "sg:province":"VA",
    "sg:tags":[
        "contractor"
    ],
    "wof:name":"Eastern Htg & AC",
    "wof:placetype":"venue"
},
  "geometry": {"coordinates":[-77.659679,39.134505],"type":"Point"}
}