{
  "type": "Feature",
  "properties": {
    "iso:country":"US",
    "sg:address":"419 E 20th St",
    "sg:city":"Norfolk",
    "sg:classifiers":[
        {
            "category":"Retail",
            "subcategory":"Auto Repair",
            "type":"Services"
        }
    ],
    "sg:phone":"+1 757 624 9191",
    "sg:postcode":"23504",
    "sg:province":"VA",
    "sg:tags":[
        "truck"
    ],
    "wof:name":"Automotive Services Virginia",
    "wof:placetype":"venue"
},
  "geometry": {"coordinates":[-76.281091,36.86604],"type":"Point"}
}