{
  "type": "Feature",
  "properties": {
    "addr:full":"8964 Burke Lake Rd Springfield VA 22151",
    "addr:housenumber":"8964",
    "addr:postcode":"22151",
    "addr:street":"Burke Lake Rd",
    "iso:country":"US",
    "sg:address":"8964 Burke Lake Rd",
    "sg:city":"Springfield",
    "sg:classifiers":[
        {
            "category":"Personal",
            "subcategory":"Beauty Salon",
            "type":"Services"
        }
    ],
    "sg:phone":"+1 703 978 7424",
    "sg:postcode":"22151",
    "sg:province":"VA",
    "sg:tags":[
        "shop"
    ],
    "wof:name":"Headway Hair Designs",
    "wof:placetype":"venue"
},
  "geometry": {"coordinates":[-77.253209,38.809159],"type":"Point"}
}