{
  "type": "Feature",
  "properties": {
    "addr:full":"1450 Wilkes St Alexandria VA 22314",
    "addr:housenumber":"1450",
    "addr:postcode":"22314",
    "addr:street":"Wilkes St",
    "iso:country":"US",
    "sg:address":"1450 Wilkes St",
    "sg:city":"Alexandria",
    "sg:classifiers":[
        {
            "category":"Real Estate",
            "subcategory":"Developer",
            "type":"Services"
        }
    ],
    "sg:phone":"+1 703 825 0027",
    "sg:postcode":"22314",
    "sg:province":"VA",
    "sg:tags":[
        "national",
        "cemetery"
    ],
    "wof:name":"Alexandria National Cemetery",
    "wof:placetype":"venue"
},
  "geometry": {"coordinates":[-77.055628,38.80149],"type":"Point"}
}