{
  "type": "Feature",
  "properties": {
    "iso:country":"US",
    "sg:address":"11007 Leavells Rd",
    "sg:city":"Fredericksburg",
    "sg:classifiers":[
        {
            "category":"Organizations",
            "subcategory":"Religious Organization",
            "type":"Services"
        }
    ],
    "sg:phone":"+1 540 898 3324",
    "sg:postcode":"22407",
    "sg:province":"VA",
    "wof:name":"Immanuel Baptist Church",
    "wof:placetype":"venue"
},
  "geometry": {"coordinates":[-77.540159,38.259302],"type":"Point"}
}