{
  "type": "Feature",
  "properties": {
    "iso:country":"US",
    "sg:address":"203 Percussion Rd",
    "sg:city":"Williamsburg",
    "sg:classifiers":[
        {
            "category":"Wholesale",
            "subcategory":"Auto Parts",
            "type":"Manufacturing & Wholesale Goods"
        }
    ],
    "sg:phone":"+1 757 259 0336",
    "sg:postcode":"23185",
    "sg:province":"VA",
    "sg:tags":[
        "industrial",
        "supply"
    ],
    "wof:name":"J&J Distributing",
    "wof:placetype":"venue"
},
  "geometry": {"coordinates":[-76.676098,37.276098],"type":"Point"}
}