{
  "type": "Feature",
  "properties": {
    "addr:full":"527 Simmons Ln White Stone VA 22578",
    "addr:housenumber":"527",
    "addr:postcode":"22578",
    "addr:street":"Simmons Ln White Stone",
    "iso:country":"US",
    "sg:address":"527 Simmons Ln",
    "sg:city":"White Stone",
    "sg:classifiers":[
        {
            "category":"Retail",
            "subcategory":"Auto Repair",
            "type":"Services"
        }
    ],
    "sg:phone":"+1 804 435 1344",
    "sg:postcode":"22578",
    "sg:province":"VA",
    "sg:tags":[
        "body",
        "shop",
        "top",
        "paint"
    ],
    "wof:name":"Jamoat Custom Auto & Truck",
    "wof:placetype":"venue"
},
  "geometry": {"coordinates":[-76.37627500000001,37.687886],"type":"Point"}
}