{
  "type": "Feature",
  "properties": {
    "iso:country":"US",
    "sg:address":"2075 Ashmere Dr",
    "sg:city":"Charlottesville",
    "sg:classifiers":[
        {
            "category":"Shopping",
            "subcategory":"Clothing, Apparel, & Fashions",
            "type":"Retail Goods"
        }
    ],
    "sg:phone":"+1 434 984 3582",
    "sg:postcode":"22902",
    "sg:province":"VA",
    "wof:name":"Yogi Designs Inc",
    "wof:placetype":"venue"
},
  "geometry": {"coordinates":[-78.405575,37.97884],"type":"Point"}
}