{
  "type": "Feature",
  "properties": {
    "iso:country":"US",
    "sg:address":"12777 Tahiska Ln",
    "sg:city":"Newport News",
    "sg:classifiers":[
        {
            "category":"Health Services",
            "subcategory":"Clinic",
            "type":"Services"
        }
    ],
    "sg:phone":"+1 757 886 0927",
    "sg:postcode":"23602",
    "sg:province":"VA",
    "sg:tags":[
        "medical",
        "assistance"
    ],
    "wof:name":"Audrea P Davis",
    "wof:placetype":"venue"
},
  "geometry": {"coordinates":[-76.50627900000001,37.150471],"type":"Point"}
}