{
  "type": "Feature",
  "properties": {
    "addr:full":"2702 Build America Dr Hampton VA 23666",
    "addr:housenumber":"2702",
    "addr:postcode":"23666",
    "addr:street":"Build America Dr",
    "iso:country":"US",
    "sg:address":"2702 Build America Dr",
    "sg:city":"Hampton",
    "sg:classifiers":[
        {
            "category":"Manufacturing",
            "subcategory":"Printing",
            "type":"Manufacturing & Wholesale Goods"
        }
    ],
    "sg:phone":"+1 757 827 1111",
    "sg:postcode":"23666",
    "sg:province":"VA",
    "sg:tags":[
        "publisher"
    ],
    "wof:name":"Virginia Veteran",
    "wof:placetype":"venue"
},
  "geometry": {"coordinates":[-76.39998300000001,37.041003],"type":"Point"}
}