{
  "type": "Feature",
  "properties": {
    "iso:country":"US",
    "sg:address":"2251 Old Valley Pike",
    "sg:city":"New Market",
    "sg:classifiers":[
        {
            "category":"Travel",
            "subcategory":"Hotels & Motels",
            "type":"Entertainment"
        }
    ],
    "sg:phone":"+1 540 740 4136",
    "sg:postcode":"22844",
    "sg:province":"VA",
    "sg:tags":[
        "operation"
    ],
    "sg:website":"www.blueridgeinn.com",
    "wof:name":"Blue Ridge Inn",
    "wof:placetype":"venue"
},
  "geometry": {"coordinates":[-78.654352,38.680769],"type":"Point"}
}