{
  "type": "Feature",
  "properties": {
    "addr:full":"615 East St Blackstone VA 23824",
    "addr:housenumber":"615",
    "addr:postcode":"23824",
    "addr:street":"East St",
    "iso:country":"US",
    "sg:address":"615 East St",
    "sg:city":"Blackstone",
    "sg:classifiers":[
        {
            "category":"Education",
            "subcategory":"School",
            "type":"Public Place"
        }
    ],
    "sg:phone":"+1 434 292 5300",
    "sg:postcode":"23824",
    "sg:province":"VA",
    "wof:name":"Blackstone Primary School",
    "wof:placetype":"venue"
},
  "geometry": {"coordinates":[-77.994793,37.07057],"type":"Point"}
}