{
  "type": "Feature",
  "properties": {
    "addr:full":"2378 N Danville St Arlington VA 22207",
    "addr:housenumber":"2378",
    "addr:postcode":"22207",
    "addr:street":"N Danville St",
    "iso:country":"US",
    "sg:address":"2378 N Danville St",
    "sg:city":"Arlington",
    "sg:classifiers":[
        {
            "category":"Professional",
            "subcategory":"Lawyer & Legal Services",
            "type":"Services"
        }
    ],
    "sg:phone":"+1 703 524 3423",
    "sg:postcode":"22207",
    "sg:province":"VA",
    "sg:tags":[
        "attorney"
    ],
    "wof:name":"Robin Goodenough",
    "wof:placetype":"venue"
},
  "geometry": {"coordinates":[-77.093909,38.899772],"type":"Point"}
}