{
  "type": "Feature",
  "properties": {
    "addr:full":"2500 Chestnut Ave Newport News VA 23607",
    "addr:housenumber":"2500",
    "addr:postcode":"23607",
    "addr:street":"Chestnut Ave",
    "iso:country":"US",
    "sg:address":"2500 Chestnut Ave",
    "sg:city":"Newport News",
    "sg:classifiers":[
        {
            "category":"Organizations",
            "subcategory":"Religious Organization",
            "type":"Services"
        }
    ],
    "sg:phone":"+1 757 245 1594",
    "sg:postcode":"23607",
    "sg:province":"VA",
    "wof:name":"St Paul AME Church",
    "wof:placetype":"venue"
},
  "geometry": {"coordinates":[-76.406767,36.987935],"type":"Point"}
}