{
  "type": "Feature",
  "properties": {
    "addr:full":"1310 King St Alexandria VA 22314",
    "addr:housenumber":"1310",
    "addr:postcode":"22314",
    "addr:street":"King St",
    "iso:country":"US",
    "sg:address":"1310 King St",
    "sg:city":"Alexandria",
    "sg:classifiers":[
        {
            "category":"Autos & Motor Vehicles",
            "subcategory":"Automobile Sales",
            "type":"Retail Goods"
        }
    ],
    "sg:phone":"+1 703 548 4455",
    "sg:postcode":"22314",
    "sg:province":"VA",
    "sg:tags":[
        "used"
    ],
    "wof:name":"Kings Auto Inc",
    "wof:placetype":"venue"
},
  "geometry": {"coordinates":[-77.054559,38.805951],"type":"Point"}
}