{
  "type": "Feature",
  "properties": {
    "addr:full":"1316 Vincent Pl Mc Lean VA 22101",
    "addr:housenumber":"1316",
    "addr:postcode":"22101",
    "addr:street":"Vincent Pl Mc Lean",
    "iso:country":"US",
    "sg:address":"1316 Vincent Pl",
    "sg:city":"Mc Lean",
    "sg:classifiers":[
        {
            "category":"Real Estate",
            "subcategory":"Real Estate Agent",
            "type":"Services"
        }
    ],
    "sg:phone":"+1 703 847 9111",
    "sg:postcode":"22101",
    "sg:province":"VA",
    "wof:name":"Chase Realty Inc",
    "wof:placetype":"venue"
},
  "geometry": {"coordinates":[-77.180802,38.93675],"type":"Point"}
}