{
  "type": "Feature",
  "properties": {
    "addr:full":"725 W 34th St Norfolk VA 23508",
    "addr:housenumber":"725",
    "addr:postcode":"23508",
    "addr:street":"W 34Th St",
    "iso:country":"US",
    "sg:address":"725 W 34th St",
    "sg:city":"Norfolk",
    "sg:classifiers":[
        {
            "category":"Shopping",
            "subcategory":"Shoes",
            "type":"Retail Goods"
        }
    ],
    "sg:phone":"+1 757 321 0036",
    "sg:postcode":"23508",
    "sg:province":"VA",
    "wof:name":"Garnyb Boutique",
    "wof:placetype":"venue"
},
  "geometry": {"coordinates":[-76.29434500000001,36.877065],"type":"Point"}
}