{
  "type": "Feature",
  "properties": {
    "addr:full":"8359 Simmers Valley Rd Harrisonburg VA 22815",
    "addr:housenumber":"8359",
    "addr:postcode":"22815",
    "addr:street":"Simmers Valley Rd",
    "iso:country":"US",
    "sg:address":"8359 Simmers Valley Rd",
    "sg:city":"Harrisonburg",
    "sg:classifiers":[
        {
            "category":"Farming",
            "subcategory":"Vineyard",
            "type":"Manufacturing & Wholesale Goods"
        }
    ],
    "sg:phone":"+1 540 833 6000",
    "sg:postcode":"22815",
    "sg:province":"VA",
    "sg:tags":[
        "grape"
    ],
    "wof:name":"Landwirt Vineyard",
    "wof:placetype":"venue"
},
  "geometry": {"coordinates":[-78.800431,38.539556],"type":"Point"}
}