{
  "type": "Feature",
  "properties": {
    "addr:full":"200 William St Fredericksburg VA 22401",
    "addr:housenumber":"200",
    "addr:postcode":"22401",
    "addr:street":"William St",
    "iso:country":"US",
    "sg:address":"200 William St",
    "sg:city":"Fredericksburg",
    "sg:classifiers":[
        {
            "category":"Shopping",
            "subcategory":"Jewelry",
            "type":"Retail Goods"
        }
    ],
    "sg:phone":"+1 540 373 4421",
    "sg:postcode":"22401",
    "sg:province":"VA",
    "sg:tags":[
        "jeweler"
    ],
    "wof:name":"Crown Jewelers",
    "wof:placetype":"venue"
},
  "geometry": {"coordinates":[-77.459625,38.303705],"type":"Point"}
}