{
  "type": "Feature",
  "properties": {
    "addr:full":"7001 Silent Spring Ln Fredericksburg VA 22407",
    "addr:housenumber":"7001",
    "addr:postcode":"22407",
    "addr:street":"Silent Spring Ln",
    "iso:country":"US",
    "sg:address":"7001 Silent Spring Ln",
    "sg:city":"Fredericksburg",
    "sg:classifiers":[
        {
            "category":"Building & Trades",
            "subcategory":"Construction",
            "type":"Services"
        }
    ],
    "sg:phone":"+1 540 548 2151",
    "sg:postcode":"22407",
    "sg:province":"VA",
    "sg:tags":[
        "contractor"
    ],
    "wof:name":"Hazel Land Co",
    "wof:placetype":"venue"
},
  "geometry": {"coordinates":[-77.575777,38.262724],"type":"Point"}
}