{
  "type": "Feature",
  "properties": {
    "iso:country":"US",
    "sg:address":"442 N Main St",
    "sg:city":"Kilmarnock",
    "sg:classifiers":[
        {
            "category":"Food & Beverages",
            "subcategory":"Groceries & Convenience Stores",
            "type":"Retail Goods"
        }
    ],
    "sg:phone":"+1 804 435 6720",
    "sg:postcode":"22482",
    "sg:province":"VA",
    "wof:name":"Get & Zip Convenience Stores",
    "wof:placetype":"venue"
},
  "geometry": {"coordinates":[-76.391059,37.730998],"type":"Point"}
}