{
  "type": "Feature",
  "properties": {
    "iso:country":"US",
    "sg:address":"4400 University Dr",
    "sg:city":"Fairfax",
    "sg:classifiers":[
        {
            "category":"Manufacturing",
            "subcategory":"Buildings",
            "type":"Manufacturing & Wholesale Goods"
        },
        {
            "category":"Building & Trades",
            "subcategory":"Construction",
            "type":"Services"
        }
    ],
    "sg:phone":"+1 703 323 6981",
    "sg:postcode":"22030",
    "sg:province":"VA",
    "sg:tags":[
        "home",
        "builder",
        "contractor"
    ],
    "wof:name":"Balfour Beatty Construction",
    "wof:placetype":"venue"
},
  "geometry": {"coordinates":[-77.31076,38.83503],"type":"Point"}
}