{
  "type": "Feature",
  "properties": {
    "iso:country":"US",
    "sg:address":"10 Hazel Park Dr",
    "sg:city":"Fredericksburg",
    "sg:classifiers":[
        {
            "category":"Building & Trades",
            "subcategory":"Cleaning & Sanitation",
            "type":"Services"
        }
    ],
    "sg:phone":"+1 540 657 6464",
    "sg:postcode":"22405",
    "sg:province":"VA",
    "sg:tags":[
        "janitor"
    ],
    "wof:name":"Service Master Co",
    "wof:placetype":"venue"
},
  "geometry": {"coordinates":[-77.439514,38.38496],"type":"Point"}
}