{
  "type": "Feature",
  "properties": {
    "addr:full":"137 Laxton Rd Lynchburg VA 24502",
    "addr:housenumber":"137",
    "addr:postcode":"24502",
    "addr:street":"Laxton Rd",
    "iso:country":"US",
    "sg:address":"137 Laxton Rd",
    "sg:city":"Lynchburg",
    "sg:classifiers":[
        {
            "category":"Personal",
            "type":"Services"
        }
    ],
    "sg:phone":"+1 434 237 8000",
    "sg:postcode":"24502",
    "sg:province":"VA",
    "sg:tags":[
        "therapist",
        "massage"
    ],
    "wof:name":"Alternative Therapy Ctr",
    "wof:placetype":"venue"
},
  "geometry": {"coordinates":[-79.235766,37.346679],"type":"Point"}
}