{
  "type": "Feature",
  "properties": {
    "addr:full":"1200 Forest St Charlottesville VA 22903",
    "addr:housenumber":"1200",
    "addr:postcode":"22903",
    "addr:street":"Forest St",
    "iso:country":"US",
    "sg:address":"1200 Forest St",
    "sg:city":"Charlottesville",
    "sg:classifiers":[
        {
            "category":"Education",
            "subcategory":"School",
            "type":"Public Place"
        }
    ],
    "sg:phone":"+1 434 296 3090",
    "sg:postcode":"22903",
    "sg:province":"VA",
    "sg:tags":[
        "high",
        "middle",
        "elementary"
    ],
    "wof:name":"Albemarle County",
    "wof:placetype":"venue"
},
  "geometry": {"coordinates":[-78.48315100000001,38.040387],"type":"Point"}
}