{
  "type": "Feature",
  "properties": {
    "addr:full":"1510 Spradlin Ln Scottsville VA 24590",
    "addr:housenumber":"1510",
    "addr:postcode":"24590",
    "addr:street":"Spradlin Ln",
    "iso:country":"US",
    "sg:address":"1510 Spradlin Ln",
    "sg:city":"Scottsville",
    "sg:classifiers":[
        {
            "category":"Building & Trades",
            "subcategory":"Construction",
            "type":"Services"
        }
    ],
    "sg:phone":"+1 434 971 7828",
    "sg:postcode":"24590",
    "sg:province":"VA",
    "sg:tags":[
        "downspouts",
        "gutter"
    ],
    "wof:name":"B & K Guttering",
    "wof:placetype":"venue"
},
  "geometry": {"coordinates":[-78.448356,37.928921],"type":"Point"}
}