{
  "type": "Feature",
  "properties": {
    "iso:country":"US",
    "sg:address":"18019 Dumfries Shopping Plz",
    "sg:city":"Dumfries",
    "sg:classifiers":[
        {
            "category":"Personal",
            "subcategory":"Beauty Salon",
            "type":"Services"
        }
    ],
    "sg:phone":"+1 703 221 8502",
    "sg:postcode":"22026",
    "sg:province":"VA",
    "sg:tags":[
        "hair"
    ],
    "wof:name":"Styles Are US",
    "wof:placetype":"venue"
},
  "geometry": {"coordinates":[-77.328675,38.560978],"type":"Point"}
}