{
  "type": "Feature",
  "properties": {
    "iso:country":"US",
    "sg:address":"302 Lake St",
    "sg:city":"Saltville",
    "sg:classifiers":[
        {
            "category":"Government",
            "subcategory":"Office",
            "type":"Public Place"
        }
    ],
    "sg:phone":"+1 276 496 3235",
    "sg:postcode":"24301",
    "sg:province":"VA",
    "sg:tags":[
        "village"
    ],
    "wof:name":"Saltville Public Workshop",
    "wof:placetype":"venue"
},
  "geometry": {"coordinates":[-80.787149,37.042454],"type":"Point"}
}