{
  "type": "Feature",
  "properties": {
    "iso:country":"US",
    "sg:address":"405 S Hill Ave",
    "sg:city":"South Hill",
    "sg:classifiers":[
        {
            "category":"Shopping",
            "type":"Retail Goods"
        }
    ],
    "sg:phone":"+1 434 447 8423",
    "sg:postcode":"23970",
    "sg:province":"VA",
    "sg:tags":[
        "hearing",
        "equipment",
        "supply",
        "merchandise",
        "impaired"
    ],
    "wof:name":"Watkins Hearing Aid Center",
    "wof:placetype":"venue"
},
  "geometry": {"coordinates":[-78.13106000000001,36.723829],"type":"Point"}
}