{
  "type": "Feature",
  "properties": {
    "addr:full":"745 E 26th St Norfolk VA 23504",
    "addr:housenumber":"745",
    "addr:postcode":"23504",
    "addr:street":"E 26Th St",
    "iso:country":"US",
    "sg:address":"745 E 26th St",
    "sg:city":"Norfolk",
    "sg:phone":"+1 757 623 7073",
    "sg:postcode":"23504",
    "sg:province":"VA",
    "sg:tags":[
        "repair",
        "scale",
        "equipment"
    ],
    "wof:name":"Dixie Equipment Co",
    "wof:placetype":"venue"
},
  "geometry": {"coordinates":[-76.277922,36.87028],"type":"Point"}
}