{
  "type": "Feature",
  "properties": {
    "addr:full":"420 N Center Dr Norfolk VA 23502",
    "addr:housenumber":"420",
    "addr:postcode":"23502",
    "addr:street":"N Center Dr",
    "iso:country":"US",
    "sg:address":"420 N Center Dr",
    "sg:city":"Norfolk",
    "sg:classifiers":[
        {
            "category":"Arts & Performance",
            "subcategory":"Theater",
            "type":"Entertainment"
        }
    ],
    "sg:phone":"+1 757 466 7555",
    "sg:postcode":"23502",
    "sg:province":"VA",
    "sg:tags":[
        "theatrical"
    ],
    "wof:name":"Young Audiences of Virginia",
    "wof:placetype":"venue"
},
  "geometry": {"coordinates":[-76.185903,36.84775],"type":"Point"}
}