{
  "type": "Feature",
  "properties": {
    "addr:full":"1803 High St Portsmouth VA 23704",
    "addr:housenumber":"1803",
    "addr:postcode":"23704",
    "addr:street":"High St",
    "iso:country":"US",
    "sg:address":"1803 High St",
    "sg:city":"Portsmouth",
    "sg:classifiers":[
        {
            "category":"Retail",
            "subcategory":"Auto Repair",
            "type":"Services"
        }
    ],
    "sg:phone":"+1 757 393 6316",
    "sg:postcode":"23704",
    "sg:province":"VA",
    "sg:tags":[
        "repairing",
        "automobile",
        "general"
    ],
    "wof:name":"Ford Automotive Repair Center",
    "wof:placetype":"venue"
},
  "geometry": {"coordinates":[-76.321866,36.83475],"type":"Point"}
}