{
  "type": "Feature",
  "properties": {
    "addr:full":"3229 W State St Bristol VA 37620",
    "addr:housenumber":"3229",
    "addr:postcode":"37620",
    "addr:street":"W State St",
    "iso:country":"US",
    "sg:address":"3229 W State St",
    "sg:city":"Bristol",
    "sg:classifiers":[
        {
            "category":"Autos & Motor Vehicles",
            "subcategory":"Automobile Sales",
            "type":"Retail Goods"
        }
    ],
    "sg:phone":"+1 423 764 5441",
    "sg:postcode":"37620",
    "sg:province":"VA",
    "sg:tags":[
        "used"
    ],
    "wof:name":"Brookside Auto Sales",
    "wof:placetype":"venue"
},
  "geometry": {"coordinates":[-82.244147,36.59353],"type":"Point"}
}