{
  "type": "Feature",
  "properties": {
    "iso:country":"US",
    "sg:address":"5010 Sterling Rd",
    "sg:city":"Petersburg",
    "sg:classifiers":[
        {
            "category":"Building & Trades",
            "subcategory":"Electrical",
            "type":"Services"
        }
    ],
    "sg:phone":"+1 804 733 8873",
    "sg:postcode":"23803",
    "sg:province":"VA",
    "sg:tags":[
        "electrical",
        "contractor"
    ],
    "wof:name":"Nelson E Morton Elec Svcs",
    "wof:placetype":"venue"
},
  "geometry": {"coordinates":[-77.481281,37.202148],"type":"Point"}
}