{
  "type": "Feature",
  "properties": {
    "addr:full":"3600 South Pl Alexandria VA 22309",
    "addr:housenumber":"3600",
    "addr:postcode":"22309",
    "addr:street":"South Pl",
    "iso:country":"US",
    "sg:address":"3600 South Pl",
    "sg:city":"Alexandria",
    "sg:classifiers":[
        {
            "category":"Government",
            "subcategory":"Office",
            "type":"Public Place"
        }
    ],
    "sg:phone":"+1 703 780 3234",
    "sg:postcode":"22309",
    "sg:province":"VA",
    "sg:tags":[
        "government-united",
        "state"
    ],
    "wof:name":"Allen James R Gen Usaf Ret",
    "wof:placetype":"venue"
},
  "geometry": {"coordinates":[-77.095161,38.717369],"type":"Point"}
}