{
  "type": "Feature",
  "properties": {
    "addr:full":"402 Munsons Hill Ct Stafford VA 22554",
    "addr:housenumber":"402",
    "addr:postcode":"22554",
    "addr:street":"Munsons Hill Ct",
    "iso:country":"US",
    "sg:address":"402 Munsons Hill Ct",
    "sg:city":"Stafford",
    "sg:classifiers":[
        {
            "category":"Building & Trades",
            "subcategory":"Cleaning & Sanitation",
            "type":"Services"
        }
    ],
    "sg:phone":"+1 540 288 1600",
    "sg:postcode":"22554",
    "sg:province":"VA",
    "sg:tags":[
        "maintenance"
    ],
    "wof:name":"Victory Carpet & Cleaning Sv",
    "wof:placetype":"venue"
},
  "geometry": {"coordinates":[-77.401445,38.438487],"type":"Point"}
}