{
  "type": "Feature",
  "properties": {
    "addr:full":"430 Kentucky Ave SW Norton VA 24273",
    "addr:housenumber":"430",
    "addr:postcode":"24273",
    "addr:street":"Kentucky Ave Sw",
    "iso:country":"US",
    "sg:address":"430 Kentucky Ave SW",
    "sg:city":"Norton",
    "sg:classifiers":[
        {
            "category":"Social Services",
            "subcategory":"Job Training",
            "type":"Services"
        }
    ],
    "sg:phone":"+1 276 679 6000",
    "sg:postcode":"24273",
    "sg:province":"VA",
    "sg:tags":[
        "employment"
    ],
    "wof:name":"Rada Inc",
    "wof:placetype":"venue"
},
  "geometry": {"coordinates":[-82.622736,36.933025],"type":"Point"}
}