{
  "type": "Feature",
  "properties": {
    "iso:country":"US",
    "sg:address":"18170 Canby Rd",
    "sg:city":"Leesburg",
    "sg:classifiers":[
        {
            "category":"Building & Trades",
            "subcategory":"Construction",
            "type":"Services"
        }
    ],
    "sg:phone":"+1 703 777 7785",
    "sg:postcode":"20175",
    "sg:province":"VA",
    "sg:tags":[
        "home",
        "improvement"
    ],
    "wof:name":"Herndon Electrical Constr",
    "wof:placetype":"venue"
},
  "geometry": {"coordinates":[-77.631564,39.114383],"type":"Point"}
}