{
  "type": "Feature",
  "properties": {
    "addr:full":"164 George Washington Hwy S Chesapeake VA 23323",
    "addr:housenumber":"164",
    "addr:postcode":"23323",
    "addr:street":"George Washington Hwy",
    "iso:country":"US",
    "sg:address":"164 George Washington Hwy S",
    "sg:city":"Chesapeake",
    "sg:classifiers":[
        {
            "category":"Health Services",
            "subcategory":"Chiropractor",
            "type":"Services"
        }
    ],
    "sg:phone":"+1 757 558 8222",
    "sg:postcode":"23323",
    "sg:province":"VA",
    "wof:name":"First Choice Chiropractic",
    "wof:placetype":"venue"
},
  "geometry": {"coordinates":[-76.34554900000001,36.737183],"type":"Point"}
}