{
  "type": "Feature",
  "properties": {
    "addr:full":"21 Moss St N Martinsville VA 24112",
    "addr:housenumber":"21",
    "addr:postcode":"24112",
    "addr:street":"Moss St N",
    "iso:country":"US",
    "sg:address":"21 Moss St N",
    "sg:city":"Martinsville",
    "sg:classifiers":[
        {
            "category":"Social Services",
            "type":"Services"
        }
    ],
    "sg:phone":"+1 276 656 5260",
    "sg:postcode":"24112",
    "sg:province":"VA",
    "sg:tags":[
        "senior",
        "citizen"
    ],
    "wof:name":"Martinsville Senior Citizens",
    "wof:placetype":"venue"
},
  "geometry": {"coordinates":[-79.87562699999999,36.691541],"type":"Point"}
}