{
  "type": "Feature",
  "properties": {
    "addr:full":"1170 Rocky Ford Rd Powhatan VA 23139",
    "addr:housenumber":"1170",
    "addr:postcode":"23139",
    "addr:street":"Rocky Ford Rd",
    "iso:country":"US",
    "sg:address":"1170 Rocky Ford Rd",
    "sg:city":"Powhatan",
    "sg:classifiers":[
        {
            "category":"Food & Beverages",
            "subcategory":"Meat & Fish",
            "type":"Retail Goods"
        }
    ],
    "sg:phone":"+1 804 598 3358",
    "sg:postcode":"23139",
    "sg:province":"VA",
    "wof:name":"Jameson Rabbit Farm",
    "wof:placetype":"venue"
},
  "geometry": {"coordinates":[-77.868724,37.477501],"type":"Point"}
}