{
  "type": "Feature",
  "properties": {
    "addr:full":"9459 Poindexter Rd Louisa VA 23093",
    "addr:housenumber":"9459",
    "addr:postcode":"23093",
    "addr:street":"Poindexter Rd",
    "iso:country":"US",
    "sg:address":"9459 Poindexter Rd",
    "sg:city":"Louisa",
    "sg:classifiers":[
        {
            "category":"Organizations",
            "subcategory":"Religious Organization",
            "type":"Services"
        }
    ],
    "sg:phone":"+1 540 967 2446",
    "sg:postcode":"23093",
    "sg:province":"VA",
    "sg:tags":[
        "church"
    ],
    "wof:name":"Grace Freewill Baptist Church",
    "wof:placetype":"venue"
},
  "geometry": {"coordinates":[-78.08591300000001,38.048763],"type":"Point"}
}