{
  "type": "Feature",
  "properties": {
    "iso:country":"US",
    "sg:address":"417 W Main St",
    "sg:city":"Charlottesville",
    "sg:classifiers":[
        {
            "category":"Home & Garden",
            "subcategory":"Building Materials",
            "type":"Retail Goods"
        }
    ],
    "sg:phone":"+1 434 971 7512",
    "sg:postcode":"22903",
    "sg:province":"VA",
    "wof:name":"Century Exteriors",
    "wof:placetype":"venue"
},
  "geometry": {"coordinates":[-78.487469,38.030919],"type":"Point"}
}