{
  "type": "Feature",
  "properties": {
    "iso:country":"US",
    "sg:address":"1408 Williamson Rd NE",
    "sg:city":"Roanoke",
    "sg:classifiers":[
        {
            "category":"Shopping",
            "subcategory":"Books",
            "type":"Retail Goods"
        }
    ],
    "sg:phone":"+1 540 343 6023",
    "sg:postcode":"24012",
    "sg:province":"VA",
    "wof:name":"Palace Book Store Inc",
    "wof:placetype":"venue"
},
  "geometry": {"coordinates":[-79.93293799999999,37.284992],"type":"Point"}
}