{
  "type": "Feature",
  "properties": {
    "addr:full":"8127 Twin Creek Trl Mechanicsville VA 23111",
    "addr:housenumber":"8127",
    "addr:postcode":"23111",
    "addr:street":"Twin Creek Trl",
    "iso:country":"US",
    "sg:address":"8127 Twin Creek Trl",
    "sg:city":"Mechanicsville",
    "sg:classifiers":[
        {
            "category":"Retail",
            "subcategory":"Repair Shop",
            "type":"Services"
        },
        {
            "category":"Home & Garden",
            "subcategory":"Home Furnishings",
            "type":"Retail Goods"
        },
        {
            "category":"Building & Trades",
            "subcategory":"Construction",
            "type":"Services"
        }
    ],
    "sg:phone":"+1 804 559 0828",
    "sg:postcode":"23111",
    "sg:province":"VA",
    "sg:tags":[
        "enamel",
        "porcelain",
        "sinks-repair",
        "tile-contractors",
        "bathtub",
        "refinish"
    ],
    "wof:name":"Bath Works",
    "wof:placetype":"venue"
},
  "geometry": {"coordinates":[-77.177131,37.621565],"type":"Point"}
}