{
  "type": "Feature",
  "properties": {
    "iso:country":"US",
    "sg:address":"2200 Clarendon Blvd Ste P",
    "sg:city":"Arlington",
    "sg:classifiers":[
        {
            "category":"Health Services",
            "subcategory":"Optometrist",
            "type":"Services"
        }
    ],
    "sg:phone":"+1 703 527 6968",
    "sg:postcode":"22201",
    "sg:province":"VA",
    "wof:name":"Total Optometric Care",
    "wof:placetype":"venue"
},
  "geometry": {"coordinates":[-77.08648700000001,38.890442],"type":"Point"}
}