{
  "type": "Feature",
  "properties": {
    "addr:full":"2004 Wards Gap Rd Cana VA 24317",
    "addr:housenumber":"2004",
    "addr:postcode":"24317",
    "addr:street":"Wards Gap Rd",
    "iso:country":"US",
    "sg:address":"2004 Wards Gap Rd",
    "sg:city":"Cana",
    "sg:classifiers":[
        {
            "category":"Health Services",
            "subcategory":"Nursing And Care Facility",
            "type":"Services"
        }
    ],
    "sg:phone":"+1 276 755 4338",
    "sg:postcode":"24317",
    "sg:province":"VA",
    "sg:tags":[
        "home",
        "convalescent"
    ],
    "wof:name":"Cana Adult Home",
    "wof:placetype":"venue"
},
  "geometry": {"coordinates":[-80.614445,36.577852],"type":"Point"}
}