{
  "type": "Feature",
  "properties": {
    "addr:full":"2421 Maidens Rd Maidens VA 23102",
    "addr:housenumber":"2421",
    "addr:postcode":"23102",
    "addr:street":"Maidens Rd",
    "iso:country":"US",
    "sg:address":"2421 Maidens Rd",
    "sg:city":"Maidens",
    "sg:classifiers":[
        {
            "category":"Professional",
            "type":"Services"
        }
    ],
    "sg:phone":"+1 804 556 3562",
    "sg:postcode":"23102",
    "sg:province":"VA",
    "sg:tags":[
        "establishment"
    ],
    "wof:name":"Critter Keepers LLC",
    "wof:placetype":"venue"
},
  "geometry": {"coordinates":[-77.85391,37.716877],"type":"Point"}
}