{
  "type": "Feature",
  "properties": {
    "iso:country":"US",
    "sg:address":"13775 McLearen Rd",
    "sg:city":"Herndon",
    "sg:classifiers":[
        {
            "category":"Utilities",
            "subcategory":"Mobile Phone",
            "type":"Services"
        }
    ],
    "sg:phone":"+1 703 689 6000",
    "sg:postcode":"20171",
    "sg:province":"VA",
    "sg:tags":[
        "telephone",
        "cellular"
    ],
    "sg:website":"www.equant.com",
    "wof:name":"Sprint",
    "wof:placetype":"venue"
},
  "geometry": {"coordinates":[-77.41911399999999,38.925139],"type":"Point"}
}