{
  "type": "Feature",
  "properties": {
    "iso:country":"US",
    "sg:address":"1805 S Crystal Dr",
    "sg:city":"Arlington",
    "sg:classifiers":[
        {
            "category":"Professional",
            "subcategory":"Computer Services",
            "type":"Services"
        }
    ],
    "sg:phone":"+1 703 892 9462",
    "sg:postcode":"22202",
    "sg:province":"VA",
    "sg:tags":[
        "related"
    ],
    "wof:name":"4usolutionscom",
    "wof:placetype":"venue"
},
  "geometry": {"coordinates":[-77.049228,38.85614],"type":"Point"}
}