{
  "type": "Feature",
  "properties": {
    "addr:full":"4551 Cox Rd Glen Allen VA 23060",
    "addr:housenumber":"4551",
    "addr:postcode":"23060",
    "addr:street":"Cox Rd",
    "iso:country":"US",
    "sg:address":"4551 Cox Rd",
    "sg:city":"Glen Allen",
    "sg:classifiers":[
        {
            "category":"Banks & Credit Unions",
            "subcategory":"Financial Services",
            "type":"Services"
        }
    ],
    "sg:phone":"+1 804 217 5800",
    "sg:postcode":"23060",
    "sg:province":"VA",
    "sg:tags":[
        "trust",
        "investment",
        "real estate"
    ],
    "wof:name":"Dynex Capital Inc",
    "wof:placetype":"venue"
},
  "geometry": {"coordinates":[-77.57469399999999,37.660531],"type":"Point"}
}