{
  "type": "Feature",
  "properties": {
    "addr:full":"Tysons Corner Vienna VA 22182",
    "addr:postcode":"22182",
    "iso:country":"US",
    "sg:address":"Tysons Corner",
    "sg:city":"Vienna",
    "sg:classifiers":[
        {
            "category":"Social Services",
            "subcategory":"Job Training",
            "type":"Services"
        },
        {
            "category":"Professional",
            "subcategory":"Employment Agencies",
            "type":"Services"
        },
        {
            "category":"Health Services",
            "subcategory":"Chiropractor",
            "type":"Services"
        }
    ],
    "sg:phone":"+1 703 448 0050",
    "sg:postcode":"22182",
    "sg:province":"VA",
    "sg:tags":[
        "career",
        "counseling"
    ],
    "sg:website":"www.snellingva.com",
    "wof:name":"Snelling DC",
    "wof:placetype":"venue"
},
  "geometry": {"coordinates":[-77.221834,38.918039],"type":"Point"}
}