{
  "type": "Feature",
  "properties": {
    "addr:full":"713 Rutledge Ln Earlysville VA 22936",
    "addr:housenumber":"713",
    "addr:postcode":"22936",
    "addr:street":"Rutledge Ln",
    "iso:country":"US",
    "sg:address":"713 Rutledge Ln",
    "sg:city":"Earlysville",
    "sg:classifiers":[
        {
            "category":"Building & Trades",
            "subcategory":"Construction",
            "type":"Services"
        }
    ],
    "sg:phone":"+1 434 973 5938",
    "sg:postcode":"22936",
    "sg:province":"VA",
    "sg:tags":[
        "home",
        "general",
        "family",
        "contractor"
    ],
    "wof:name":"Bishop W E & J F Inc",
    "wof:placetype":"venue"
},
  "geometry": {"coordinates":[-78.475273,38.122835],"type":"Point"}
}