{
  "type": "Feature",
  "properties": {
    "addr:full":"1044 Austin Dr Chesapeake VA 23320",
    "addr:housenumber":"1044",
    "addr:postcode":"23320",
    "addr:street":"Austin Dr",
    "iso:country":"US",
    "sg:address":"1044 Austin Dr",
    "sg:city":"Chesapeake",
    "sg:classifiers":[
        {
            "category":"Professional",
            "subcategory":"Employment Agencies",
            "type":"Services"
        }
    ],
    "sg:phone":"+1 757 548 1085",
    "sg:postcode":"23320",
    "sg:province":"VA",
    "sg:tags":[
        "help",
        "supply"
    ],
    "wof:name":"Paulette & Kent Mack",
    "wof:placetype":"venue"
},
  "geometry": {"coordinates":[-76.221058,36.752137],"type":"Point"}
}