{
  "type": "Feature",
  "properties": {
    "addr:full":"7531 Hill Dr Richmond VA 23225",
    "addr:housenumber":"7531",
    "addr:postcode":"23225",
    "addr:street":"Hill Dr",
    "iso:country":"US",
    "sg:address":"7531 Hill Dr",
    "sg:city":"Richmond",
    "sg:classifiers":[
        {
            "category":"Building & Trades",
            "subcategory":"Construction",
            "type":"Services"
        }
    ],
    "sg:phone":"+1 804 320 0182",
    "sg:postcode":"23225",
    "sg:province":"VA",
    "sg:tags":[
        "builder",
        "general",
        "operative",
        "contractor"
    ],
    "wof:name":"Amrhein Construction Inc",
    "wof:placetype":"venue"
},
  "geometry": {"coordinates":[-77.523702,37.5509],"type":"Point"}
}