{
  "type": "Feature",
  "properties": {
    "addr:full":"1590 Buckeye Hollow Rd Saltville VA 24370",
    "addr:housenumber":"1590",
    "addr:postcode":"24370",
    "addr:street":"Buckeye Hollow Rd",
    "iso:country":"US",
    "sg:address":"1590 Buckeye Hollow Rd",
    "sg:city":"Saltville",
    "sg:classifiers":[
        {
            "category":"Organizations",
            "subcategory":"Religious Organization",
            "type":"Services"
        }
    ],
    "sg:phone":"+1 276 496 7594",
    "sg:postcode":"24370",
    "sg:province":"VA",
    "sg:tags":[
        "church"
    ],
    "wof:name":"Plasterco Church Of God",
    "wof:placetype":"venue"
},
  "geometry": {"coordinates":[-81.726473,36.86698],"type":"Point"}
}