{
  "type": "Feature",
  "properties": {
    "addr:full":"2155 Muse Field Rd Rocky Mount VA 24151",
    "addr:housenumber":"2155",
    "addr:postcode":"24151",
    "addr:street":"Muse Field Rd",
    "iso:country":"US",
    "sg:address":"2155 Muse Field Rd",
    "sg:city":"Rocky Mount",
    "sg:classifiers":[
        {
            "category":"Building & Trades",
            "subcategory":"Construction",
            "type":"Services"
        }
    ],
    "sg:phone":"+1 540 483 2915",
    "sg:postcode":"24151",
    "sg:province":"VA",
    "sg:tags":[
        "contractor"
    ],
    "wof:name":"Allen H Thurman Contractor",
    "wof:placetype":"venue"
},
  "geometry": {"coordinates":[-79.841151,37.005772],"type":"Point"}
}