{
  "type": "Feature",
  "properties": {
    "addr:full":"1202 Jamison Ave SE Roanoke VA 24013",
    "addr:housenumber":"1202",
    "addr:postcode":"24013",
    "addr:street":"Jamison Ave Se",
    "iso:country":"US",
    "sg:address":"1202 Jamison Ave SE",
    "sg:city":"Roanoke",
    "sg:classifiers":[
        {
            "category":"Organizations",
            "subcategory":"Labor Organization",
            "type":"Services"
        }
    ],
    "sg:phone":"+1 540 343 2621",
    "sg:postcode":"24013",
    "sg:province":"VA",
    "wof:name":"Carpenters & Millwrights",
    "wof:placetype":"venue"
},
  "geometry": {"coordinates":[-79.921948,37.270998],"type":"Point"}
}