{
  "type": "Feature",
  "properties": {
    "addr:full":"3244 Battlefield Blvd S Chesapeake VA 23322",
    "addr:housenumber":"3244",
    "addr:postcode":"23322",
    "addr:street":"Battlefield Blvd",
    "iso:country":"US",
    "sg:address":"3244 Battlefield Blvd S",
    "sg:city":"Chesapeake",
    "sg:classifiers":[
        {
            "category":"Wholesale",
            "subcategory":"Auto Parts",
            "type":"Manufacturing & Wholesale Goods"
        }
    ],
    "sg:phone":"+1 757 432 8813",
    "sg:postcode":"23322",
    "sg:province":"VA",
    "sg:tags":[
        "supply"
    ],
    "wof:name":"Tech of Hampton Roads",
    "wof:placetype":"venue"
},
  "geometry": {"coordinates":[-76.21168299999999,36.611879],"type":"Point"}
}