{
  "type": "Feature",
  "properties": {
    "addr:full":"8627 Beekman Pl Alexandria VA 22309",
    "addr:housenumber":"8627",
    "addr:postcode":"22309",
    "addr:street":"Beekman Pl",
    "iso:country":"US",
    "sg:address":"8627 Beekman Pl",
    "sg:city":"Alexandria",
    "sg:classifiers":[
        {
            "category":"Building & Trades",
            "subcategory":"Cleaning & Sanitation",
            "type":"Services"
        }
    ],
    "sg:phone":"+1 703 780 8528",
    "sg:postcode":"22309",
    "sg:province":"VA",
    "sg:tags":[
        "maintenance"
    ],
    "wof:name":"Maesoes Cleaning Service",
    "wof:placetype":"venue"
},
  "geometry": {"coordinates":[-77.125641,38.723718],"type":"Point"}
}