{
  "type": "Feature",
  "properties": {
    "iso:country":"US",
    "sg:address":"323 Wallace Ln",
    "sg:city":"Fredericksburg",
    "sg:classifiers":[
        {
            "category":"Wholesale",
            "subcategory":"Drugs",
            "type":"Manufacturing & Wholesale Goods"
        }
    ],
    "sg:phone":"+1 540 891 9497",
    "sg:postcode":"22408",
    "sg:province":"VA",
    "sg:tags":[
        "cosmetic"
    ],
    "wof:name":"Creative Scents",
    "wof:placetype":"venue"
},
  "geometry": {"coordinates":[-77.4987,38.264537],"type":"Point"}
}