{
  "type": "Feature",
  "properties": {
    "iso:country":"US",
    "sg:address":"19 W Cork St",
    "sg:city":"Winchester",
    "sg:classifiers":[
        {
            "category":"Professional",
            "subcategory":"Advertising",
            "type":"Services"
        }
    ],
    "sg:phone":"+1 540 662 5868",
    "sg:postcode":"22601",
    "sg:province":"VA",
    "wof:name":"Northern Virginia Daily",
    "wof:placetype":"venue"
},
  "geometry": {"coordinates":[-78.16695,39.182112],"type":"Point"}
}