{
  "type": "Feature",
  "properties": {
    "addr:full":"2728 Cedar Rd Chesapeake VA 23323",
    "addr:housenumber":"2728",
    "addr:postcode":"23323",
    "addr:street":"Cedar Rd",
    "iso:country":"US",
    "sg:address":"2728 Cedar Rd",
    "sg:city":"Chesapeake",
    "sg:classifiers":[
        {
            "category":"Social Services",
            "subcategory":"Child Care",
            "type":"Services"
        }
    ],
    "sg:phone":"+1 757 487 7432",
    "sg:postcode":"23323",
    "sg:province":"VA",
    "wof:name":"Ann & Michele's Child Care",
    "wof:placetype":"venue"
},
  "geometry": {"coordinates":[-76.334982,36.737021],"type":"Point"}
}