{
  "type": "Feature",
  "properties": {
    "iso:country":"US",
    "sg:address":"1110 Herndon Pkwy",
    "sg:city":"Herndon",
    "sg:classifiers":[
        {
            "category":"Professional",
            "subcategory":"Management & Consulting",
            "type":"Services"
        }
    ],
    "sg:phone":"+1 703 481 4424",
    "sg:postcode":"20170",
    "sg:province":"VA",
    "wof:name":"Mark Winkler Co",
    "wof:placetype":"venue"
},
  "geometry": {"coordinates":[-77.401445,38.965065],"type":"Point"}
}