{
  "type": "Feature",
  "properties": {
    "iso:country":"US",
    "sg:address":"515 King St",
    "sg:city":"Alexandria",
    "sg:classifiers":[
        {
            "category":"Professional",
            "subcategory":"Engineering",
            "type":"Services"
        }
    ],
    "sg:phone":"+1 703 739 7382",
    "sg:postcode":"22314",
    "sg:province":"VA",
    "sg:tags":[
        "engineer"
    ],
    "wof:name":"Rumpf Associates",
    "wof:placetype":"venue"
},
  "geometry": {"coordinates":[-77.045693,38.804968],"type":"Point"}
}