{
  "type": "Feature",
  "properties": {
    "addr:full":"8308 Halesworth Rd Richmond VA 23235",
    "addr:housenumber":"8308",
    "addr:postcode":"23235",
    "addr:street":"Halesworth Rd",
    "iso:country":"US",
    "sg:address":"8308 Halesworth Rd",
    "sg:city":"Richmond",
    "sg:classifiers":[
        {
            "category":"Professional",
            "type":"Services"
        }
    ],
    "sg:phone":"+1 804 272 1948",
    "sg:postcode":"23235",
    "sg:province":"VA",
    "wof:name":"A Place For Mom",
    "wof:placetype":"venue"
},
  "geometry": {"coordinates":[-77.548377,37.551883],"type":"Point"}
}