{
  "type": "Feature",
  "properties": {
    "iso:country":"US",
    "sg:address":"12514 Long Ridge Rd",
    "sg:city":"Weber City",
    "sg:classifiers":[
        {
            "category":"Freight",
            "type":"Transportation"
        }
    ],
    "sg:phone":"+1 276 386 7112",
    "sg:postcode":"24290",
    "sg:province":"VA",
    "sg:tags":[
        "distance",
        "product",
        "petroleum",
        "hauling",
        "long"
    ],
    "wof:name":"Big Break Food Store",
    "wof:placetype":"venue"
},
  "geometry": {"coordinates":[-82.570046,36.598975],"type":"Point"}
}