{
  "type": "Feature",
  "properties": {
    "addr:full":"126 Baker St Emporia VA 23847",
    "addr:housenumber":"126",
    "addr:postcode":"23847",
    "addr:street":"Baker St",
    "iso:country":"US",
    "sg:address":"126 Baker St",
    "sg:city":"Emporia",
    "sg:classifiers":[
        {
            "category":"Shopping",
            "subcategory":"Computers & Home Electronics",
            "type":"Retail Goods"
        }
    ],
    "sg:phone":"+1 434 634 3038",
    "sg:postcode":"23847",
    "sg:province":"VA",
    "sg:tags":[
        "repair",
        "television",
        "radio"
    ],
    "wof:name":"Short's Television Shop",
    "wof:placetype":"venue"
},
  "geometry": {"coordinates":[-77.537907,36.693592],"type":"Point"}
}