{
  "type": "Feature",
  "properties": {
    "addr:full":"128 Wausau St Tazewell VA 24651",
    "addr:housenumber":"128",
    "addr:postcode":"24651",
    "addr:street":"Wausau St",
    "iso:country":"US",
    "sg:address":"128 Wausau St",
    "sg:city":"Tazewell",
    "sg:classifiers":[
        {
            "category":"Farming",
            "subcategory":"Nursery",
            "type":"Manufacturing & Wholesale Goods"
        }
    ],
    "sg:phone":"+1 276 988 4625",
    "sg:postcode":"24651",
    "sg:province":"VA",
    "sg:tags":[
        "ornamental"
    ],
    "wof:name":"Buchanans Greenhouse",
    "wof:placetype":"venue"
},
  "geometry": {"coordinates":[-81.514365,37.119981],"type":"Point"}
}