{
  "type": "Feature",
  "properties": {
    "addr:full":"5812 Waterdale Ct Centreville VA 20121",
    "addr:housenumber":"5812",
    "addr:postcode":"20121",
    "addr:street":"Waterdale Ct",
    "iso:country":"US",
    "sg:address":"5812 Waterdale Ct",
    "sg:city":"Centreville",
    "sg:classifiers":[
        {
            "category":"Retail",
            "subcategory":"Animal Services",
            "type":"Services"
        }
    ],
    "sg:phone":"+1 703 830 6032",
    "sg:postcode":"20121",
    "sg:province":"VA",
    "wof:name":"Goin To Dogs Mobile Grooming",
    "wof:placetype":"venue"
},
  "geometry": {"coordinates":[-77.41983,38.833477],"type":"Point"}
}