{
  "type": "Feature",
  "properties": {
    "addr:full":"1256 Concord Ave Richmond VA 23228",
    "addr:housenumber":"1256",
    "addr:postcode":"23228",
    "addr:street":"Concord Ave",
    "iso:country":"US",
    "sg:address":"1256 Concord Ave",
    "sg:city":"Richmond",
    "sg:classifiers":[
        {
            "category":"Shopping",
            "subcategory":"Tobacco",
            "type":"Retail Goods"
        }
    ],
    "sg:phone":"+1 804 261 2100",
    "sg:postcode":"23228",
    "sg:province":"VA",
    "sg:tags":[
        "product"
    ],
    "wof:name":"Smoke Shop",
    "wof:placetype":"venue"
},
  "geometry": {"coordinates":[-77.460813,37.63625],"type":"Point"}
}