{
  "type": "Feature",
  "properties": {
    "addr:full":"2802 9th St S Arlington VA 22204",
    "addr:housenumber":"2802",
    "addr:postcode":"22204",
    "addr:street":"9Th St S",
    "iso:country":"US",
    "sg:address":"2802 9th St S",
    "sg:city":"Arlington",
    "sg:classifiers":[
        {
            "category":"Professional",
            "subcategory":"Business Services",
            "type":"Services"
        }
    ],
    "sg:phone":"+1 703 486 3999",
    "sg:postcode":"22204",
    "sg:province":"VA",
    "sg:tags":[
        "translation",
        "interpretation",
        "language"
    ],
    "wof:name":"Sidahmed  Awatif",
    "wof:placetype":"venue"
},
  "geometry": {"coordinates":[-77.085266,38.864395],"type":"Point"}
}