{
  "type": "Feature",
  "properties": {
    "iso:country":"US",
    "sg:address":"11198 Lee Hwy",
    "sg:city":"Fairfax",
    "sg:classifiers":[
        {
            "category":"Professional",
            "subcategory":"Business Services",
            "type":"Services"
        }
    ],
    "sg:phone":"+1 703 863 4191",
    "sg:postcode":"22030",
    "sg:province":"VA",
    "sg:tags":[
        "fax",
        "voice",
        "email",
        "broadcasting"
    ],
    "wof:name":"Ebgis",
    "wof:placetype":"venue"
},
  "geometry": {"coordinates":[-77.330534,38.852009],"type":"Point"}
}