{
  "type": "Feature",
  "properties": {
    "addr:full":"732 Thimble Shoals Blvd Newport News VA 23606",
    "addr:housenumber":"732",
    "addr:postcode":"23606",
    "addr:street":"Thimble Shoals Blvd",
    "iso:country":"US",
    "sg:address":"732 Thimble Shoals Blvd",
    "sg:city":"Newport News",
    "sg:classifiers":[
        {
            "category":"Banks & Credit Unions",
            "subcategory":"Bank",
            "type":"Services"
        }
    ],
    "sg:phone":"+1 757 595 8929",
    "sg:postcode":"23606",
    "sg:province":"VA",
    "sg:tags":[
        "broker",
        "mortgage"
    ],
    "wof:name":"Moneylink",
    "wof:placetype":"venue"
},
  "geometry": {"coordinates":[-76.467473,37.083624],"type":"Point"}
}