{
  "type": "Feature",
  "properties": {
    "addr:full":"842 S Main St Amherst VA 24521",
    "addr:housenumber":"842",
    "addr:postcode":"24521",
    "addr:street":"S Main St",
    "iso:country":"US",
    "sg:address":"842 S Main St",
    "sg:city":"Amherst",
    "sg:classifiers":[
        {
            "category":"Government",
            "subcategory":"Office",
            "type":"Public Place"
        }
    ],
    "sg:phone":"+1 434 946 9612",
    "sg:postcode":"24521",
    "sg:province":"VA",
    "sg:tags":[
        "state",
        "program",
        "health"
    ],
    "wof:name":"Centra Health Inc",
    "wof:placetype":"venue"
},
  "geometry": {"coordinates":[-79.059236,37.572171],"type":"Point"}
}