{
  "type": "Feature",
  "properties": {
    "addr:full":"730 E Church St Martinsville VA 24112",
    "addr:housenumber":"730",
    "addr:postcode":"24112",
    "addr:street":"E Church St",
    "iso:country":"US",
    "sg:address":"730 E Church St",
    "sg:city":"Martinsville",
    "sg:classifiers":[
        {
            "category":"Shopping",
            "subcategory":"Computers & Home Electronics",
            "type":"Retail Goods"
        }
    ],
    "sg:phone":"+1 276 632 3050",
    "sg:postcode":"24112",
    "sg:province":"VA",
    "sg:tags":[
        "equipment",
        "dealer"
    ],
    "wof:name":"Computer Workshop-Mrtnsvll",
    "wof:placetype":"venue"
},
  "geometry": {"coordinates":[-79.85533700000001,36.689478],"type":"Point"}
}