{
  "type": "Feature",
  "properties": {
    "iso:country":"US",
    "sg:address":"417 Page St",
    "sg:city":"Berryville",
    "sg:classifiers":[
        {
            "category":"Real Estate",
            "subcategory":"Real Estate Operator",
            "type":"Services"
        }
    ],
    "sg:phone":"+1 540 955 4161",
    "sg:postcode":"22611",
    "sg:province":"VA",
    "sg:tags":[
        "building",
        "apartment"
    ],
    "wof:name":"Orchard Court Apartments",
    "wof:placetype":"venue"
},
  "geometry": {"coordinates":[-77.97618900000001,39.151897],"type":"Point"}
}