{
  "type": "Feature",
  "properties": {
    "addr:full":"13615 Old Valley Pike Edinburg VA 22824",
    "addr:housenumber":"13615",
    "addr:postcode":"22824",
    "addr:street":"Old Valley Pike",
    "iso:country":"US",
    "sg:address":"13615 Old Valley Pike",
    "sg:city":"Edinburg",
    "sg:classifiers":[
        {
            "category":"Autos & Motor Vehicles",
            "subcategory":"Automobile Sales",
            "type":"Retail Goods"
        }
    ],
    "sg:phone":"+1 540 984 9500",
    "sg:postcode":"22824",
    "sg:province":"VA",
    "sg:tags":[
        "used"
    ],
    "wof:name":"Foltz Inc",
    "wof:placetype":"venue"
},
  "geometry": {"coordinates":[-78.59755800000001,38.791765],"type":"Point"}
}