{
  "type": "Feature",
  "properties": {
    "addr:full":"16489 Beaver Dam Rd Montpelier VA 23192",
    "addr:housenumber":"16489",
    "addr:postcode":"23192",
    "addr:street":"Beaver Dam Rd",
    "iso:country":"US",
    "sg:address":"16489 Beaver Dam Rd",
    "sg:city":"Montpelier",
    "sg:classifiers":[
        {
            "category":"Insurance",
            "subcategory":"Insurance Agent",
            "type":"Services"
        }
    ],
    "sg:phone":"+1 804 883 5400",
    "sg:postcode":"23192",
    "sg:province":"VA",
    "wof:name":"Cabe Insurance Agency",
    "wof:placetype":"venue"
},
  "geometry": {"coordinates":[-77.69278,37.864177],"type":"Point"}
}