{
  "type": "Feature",
  "properties": {
    "addr:full":"1307 Kingscross Rd Midlothian VA 23114",
    "addr:housenumber":"1307",
    "addr:postcode":"23114",
    "addr:street":"Kingscross Rd",
    "iso:country":"US",
    "sg:address":"1307 Kingscross Rd",
    "sg:city":"Midlothian",
    "sg:classifiers":[
        {
            "category":"Professional",
            "subcategory":"Management & Consulting",
            "type":"Services"
        }
    ],
    "sg:phone":"+1 804 379 8212",
    "sg:postcode":"23114",
    "sg:province":"VA",
    "wof:name":"Business Process Management",
    "wof:placetype":"venue"
},
  "geometry": {"coordinates":[-77.64583,37.479537],"type":"Point"}
}