{
  "type": "Feature",
  "properties": {
    "addr:full":"8600 Bridle Wood Dr Springfield VA 22152",
    "addr:housenumber":"8600",
    "addr:postcode":"22152",
    "addr:street":"Bridle Wood Dr",
    "iso:country":"US",
    "sg:address":"8600 Bridle Wood Dr",
    "sg:city":"Springfield",
    "sg:classifiers":[
        {
            "category":"Recreation",
            "type":"Entertainment"
        }
    ],
    "sg:phone":"+1 703 451 9815",
    "sg:postcode":"22152",
    "sg:province":"VA",
    "wof:name":"Orange Hunt Swim Club",
    "wof:placetype":"venue"
},
  "geometry": {"coordinates":[-77.246557,38.771524],"type":"Point"}
}