{
  "type": "Feature",
  "properties": {
    "addr:full":"1045 S Edgewood St Arlington VA 22204",
    "addr:housenumber":"1045",
    "addr:postcode":"22204",
    "addr:street":"S Edgewood St",
    "iso:country":"US",
    "sg:address":"1045 S Edgewood St",
    "sg:city":"Arlington",
    "sg:classifiers":[
        {
            "category":"Building & Trades",
            "subcategory":"Locksmith",
            "type":"Services"
        }
    ],
    "sg:phone":"+1 571 431 1908",
    "sg:postcode":"22204",
    "sg:province":"VA",
    "sg:tags":[
        "key"
    ],
    "wof:name":"Always Available Emergency Locksmith",
    "wof:placetype":"venue"
},
  "geometry": {"coordinates":[-77.086097,38.862272],"type":"Point"}
}