{
  "type": "Feature",
  "properties": {
    "iso:country":"US",
    "sg:address":"2701 Richelieu Ave SW",
    "sg:city":"Roanoke",
    "sg:classifiers":[
        {
            "category":"Building & Trades",
            "subcategory":"Construction",
            "type":"Services"
        }
    ],
    "sg:phone":"+1 540 343 9741",
    "sg:postcode":"24014",
    "sg:province":"VA",
    "sg:tags":[
        "contractor"
    ],
    "wof:name":"Worth Inc",
    "wof:placetype":"venue"
},
  "geometry": {"coordinates":[-79.94984599999999,37.24171],"type":"Point"}
}