{
  "type": "Feature",
  "properties": {
    "iso:country":"US",
    "sg:address":"5101 Lobaugh Dr",
    "sg:city":"Virginia Beach",
    "sg:classifiers":[
        {
            "category":"Banks & Credit Unions",
            "subcategory":"Investment Brokerage",
            "type":"Services"
        }
    ],
    "sg:phone":"+1 757 474 6300",
    "sg:postcode":"23464",
    "sg:province":"VA",
    "wof:name":"4 H Investment Mutual",
    "wof:placetype":"venue"
},
  "geometry": {"coordinates":[-76.156566,36.812093],"type":"Point"}
}