{
  "type": "Feature",
  "properties": {
    "iso:country":"US",
    "sg:address":"840 Warrenton Rd",
    "sg:city":"Fredericksburg",
    "sg:classifiers":[
        {
            "category":"Restaurant",
            "type":"Food & Drink"
        }
    ],
    "sg:phone":"+1 540 373 3911",
    "sg:postcode":"22406",
    "sg:province":"VA",
    "wof:name":"Don Narandas Restaurant",
    "wof:placetype":"venue"
},
  "geometry": {"coordinates":[-77.513154,38.356285],"type":"Point"}
}