{
  "type": "Feature",
  "properties": {
    "iso:country":"US",
    "sg:address":"16096 Simon Kenton Rd",
    "sg:city":"Haymarket",
    "sg:classifiers":[
        {
            "category":"Building & Trades",
            "subcategory":"Construction",
            "type":"Services"
        }
    ],
    "sg:phone":"+1 703 754 2671",
    "sg:postcode":"20169",
    "sg:province":"VA",
    "sg:tags":[
        "house",
        "contractor"
    ],
    "wof:name":"Harbinger Construction Co",
    "wof:placetype":"venue"
},
  "geometry": {"coordinates":[-77.673946,38.866241],"type":"Point"}
}