{
  "type": "Feature",
  "properties": {
    "iso:country":"US",
    "sg:address":"250 Peppers Ferry Rd NE",
    "sg:city":"Christiansburg",
    "sg:classifiers":[
        {
            "category":"Health Services",
            "subcategory":"Doctor",
            "type":"Services"
        }
    ],
    "sg:phone":"+1 540 381 5918",
    "sg:postcode":"24073",
    "sg:province":"VA",
    "sg:tags":[
        "medical"
    ],
    "wof:name":"Weaver Edgar N Jr Dr",
    "wof:placetype":"venue"
},
  "geometry": {"coordinates":[-80.419156,37.164114],"type":"Point"}
}