{
  "type": "Feature",
  "properties": {
    "addr:full":"850 N Randolph St Arlington VA 22203",
    "addr:housenumber":"850",
    "addr:postcode":"22203",
    "addr:street":"N Randolph St",
    "iso:country":"US",
    "sg:address":"850 N Randolph St",
    "sg:city":"Arlington",
    "sg:classifiers":[
        {
            "category":"Professional",
            "subcategory":"Lawyer & Legal Services",
            "type":"Services"
        }
    ],
    "sg:phone":"+1 703 528 7582",
    "sg:postcode":"22203",
    "sg:province":"VA",
    "wof:name":"Giovannoni Catherine M Lwyr",
    "wof:placetype":"venue"
},
  "geometry": {"coordinates":[-77.1092,38.880699],"type":"Point"}
}