{
  "type": "Feature",
  "properties": {
    "addr:full":"679 Leesville Rd Lynchburg VA 24502",
    "addr:housenumber":"679",
    "addr:postcode":"24502",
    "addr:street":"Leesville Rd",
    "iso:country":"US",
    "sg:address":"679 Leesville Rd",
    "sg:city":"Lynchburg",
    "sg:classifiers":[
        {
            "category":"Real Estate",
            "subcategory":"Real Estate Agent",
            "type":"Services"
        },
        {
            "category":"Real Estate",
            "subcategory":"Real Estate Operator",
            "type":"Services"
        }
    ],
    "sg:phone":"+1 434 237 0190",
    "sg:postcode":"24502",
    "sg:province":"VA",
    "sg:tags":[
        "apartment"
    ],
    "wof:name":"Burton Creek Apartments",
    "wof:placetype":"venue"
},
  "geometry": {"coordinates":[-79.20624599999999,37.34419],"type":"Point"}
}