{
  "type": "Feature",
  "properties": {
    "addr:full":"1605 Monument Ave Richmond VA 23220",
    "addr:housenumber":"1605",
    "addr:postcode":"23220",
    "addr:street":"Monument Ave",
    "iso:country":"US",
    "sg:address":"1605 Monument Ave",
    "sg:city":"Richmond",
    "sg:classifiers":[
        {
            "category":"Education",
            "subcategory":"Special Training",
            "type":"Public Place"
        }
    ],
    "sg:phone":"+1 804 353 1587",
    "sg:postcode":"23220",
    "sg:province":"VA",
    "sg:tags":[
        "reading",
        "instruction",
        "improvement"
    ],
    "sg:website":"www.readcenter.org",
    "wof:name":"READ Ctr",
    "wof:placetype":"venue"
},
  "geometry": {"coordinates":[-77.4597,37.553782],"type":"Point"}
}