{
  "type": "Feature",
  "properties": {
    "addr:full":"1725 S Jefferson Davis Hwy Arlington VA 22202",
    "addr:housenumber":"1725",
    "addr:postcode":"22202",
    "addr:street":"S Jefferson Davis Hwy",
    "iso:country":"US",
    "sg:address":"1725 S Jefferson Davis Hwy",
    "sg:city":"Arlington",
    "sg:classifiers":[
        {
            "category":"Professional",
            "subcategory":"Engineering",
            "type":"Services"
        }
    ],
    "sg:phone":"+1 703 892 5700",
    "sg:postcode":"22202",
    "sg:province":"VA",
    "sg:tags":[
        "engineer"
    ],
    "wof:name":"Support Systems Assoc Inc",
    "wof:placetype":"venue"
},
  "geometry": {"coordinates":[-77.05192700000001,38.859476],"type":"Point"}
}