{
  "type": "Feature",
  "properties": {
    "addr:full":"3800 Harding Dr Chesapeake VA 23321",
    "addr:housenumber":"3800",
    "addr:postcode":"23321",
    "addr:street":"Harding Dr",
    "iso:country":"US",
    "sg:address":"3800 Harding Dr",
    "sg:city":"Chesapeake",
    "sg:classifiers":[
        {
            "category":"Real Estate",
            "subcategory":"Real Estate Agent",
            "type":"Services"
        }
    ],
    "sg:phone":"+1 757 483 1288",
    "sg:postcode":"23321",
    "sg:province":"VA",
    "wof:name":"Twin Financial Group LLC",
    "wof:placetype":"venue"
},
  "geometry": {"coordinates":[-76.39400999999999,36.845613],"type":"Point"}
}