{
  "type": "Feature",
  "properties": {
    "addr:full":"11003 Hull Street Rd Midlothian VA 23112",
    "addr:housenumber":"11003",
    "addr:postcode":"23112",
    "addr:street":"Hull Street Rd",
    "iso:country":"US",
    "sg:address":"11003 Hull Street Rd",
    "sg:city":"Midlothian",
    "sg:classifiers":[
        {
            "category":"Retail",
            "subcategory":"Portrait Studio",
            "type":"Services"
        }
    ],
    "sg:phone":"+1 804 745 4931",
    "sg:postcode":"23112",
    "sg:province":"VA",
    "wof:name":"Olan Mills Studios",
    "wof:placetype":"venue"
},
  "geometry": {"coordinates":[-77.59918999999999,37.437536],"type":"Point"}
}