{
  "type": "Feature",
  "properties": {
    "iso:country":"US",
    "sg:address":"15195 Heathcoat Blvd Ste 334",
    "sg:city":"Haymarket",
    "sg:classifiers":[
        {
            "category":"Health Services",
            "subcategory":"Doctor",
            "type":"Services"
        }
    ],
    "sg:phone":"+1 703 369 9070",
    "sg:postcode":"20169",
    "sg:province":"VA",
    "sg:tags":[
        "medicine",
        "sport",
        "orthopedist"
    ],
    "wof:name":"Northern Virginia Orthopaedic Specialists",
    "wof:placetype":"venue"
},
  "geometry": {"coordinates":[-77.642286,38.820834],"type":"Point"}
}