{
  "type": "Feature",
  "properties": {
    "addr:full":"20 Willow Ln Stanardsville VA 22973",
    "addr:housenumber":"20",
    "addr:postcode":"22973",
    "addr:street":"Willow Ln",
    "iso:country":"US",
    "sg:address":"20 Willow Ln",
    "sg:city":"Stanardsville",
    "sg:classifiers":[
        {
            "category":"Professional",
            "subcategory":"Lawyer & Legal Services",
            "type":"Services"
        }
    ],
    "sg:phone":"+1 434 985 7744",
    "sg:postcode":"22973",
    "sg:province":"VA",
    "sg:tags":[
        "attorney"
    ],
    "wof:name":"David C Dickey",
    "wof:placetype":"venue"
},
  "geometry": {"coordinates":[-78.43882499999999,38.298372],"type":"Point"}
}