{
  "type": "Feature",
  "properties": {
    "addr:full":"18934 Blue Ridge Mountain Rd Bluemont VA 20135",
    "addr:housenumber":"18934",
    "addr:postcode":"20135",
    "addr:street":"Blue Ridge Mountain Rd",
    "iso:country":"US",
    "sg:address":"18934 Blue Ridge Mountain Rd",
    "sg:city":"Bluemont",
    "sg:classifiers":[
        {
            "category":"Professional",
            "type":"Services"
        }
    ],
    "sg:phone":"+1 540 955 4341",
    "sg:postcode":"20135",
    "sg:province":"VA",
    "wof:name":"Anthony F Grooms",
    "wof:placetype":"venue"
},
  "geometry": {"coordinates":[-77.854872,39.0991],"type":"Point"}
}