{
  "type": "Feature",
  "properties": {
    "addr:full":"10696 Fairfax Blvd Fairfax VA 22030",
    "addr:housenumber":"10696",
    "addr:postcode":"22030",
    "addr:street":"Fairfax Blvd",
    "iso:country":"US",
    "sg:address":"10696 Fairfax Blvd",
    "sg:city":"Fairfax",
    "sg:classifiers":[
        {
            "category":"Retail",
            "subcategory":"Veterinary Services",
            "type":"Services"
        }
    ],
    "sg:phone":"+1 888 312 5694",
    "sg:postcode":"22030",
    "sg:province":"VA",
    "sg:tags":[
        "emergency",
        "hospital",
        "specialty",
        "laboratories-veterinary",
        "clinic",
        "veterinarian"
    ],
    "sg:website":"http://local.ingenio.com/Listings/Details.aspx?NUM=a%3a9393342%3a13%3a4859924%3a14%3a0%3a7",
    "wof:name":"Pet Lovers Animal Hosp",
    "wof:placetype":"venue"
},
  "geometry": {"coordinates":[-77.31389299999999,38.855954],"type":"Point"}
}