{
  "type": "Feature",
  "properties": {
    "iso:country":"US",
    "sg:address":"6457 Autumn Glen Ct",
    "sg:city":"Alexandria",
    "sg:classifiers":[
        {
            "category":"Building & Trades",
            "subcategory":"Landscaping Services",
            "type":"Services"
        }
    ],
    "sg:phone":"+1 703 658 3980",
    "sg:postcode":"22312",
    "sg:province":"VA",
    "sg:tags":[
        "landscape",
        "contractor"
    ],
    "wof:name":"Twin Oaks Landscaping",
    "wof:placetype":"venue"
},
  "geometry": {"coordinates":[-77.15464900000001,38.822341],"type":"Point"}
}