{
  "type": "Feature",
  "properties": {
    "iso:country":"US",
    "sg:address":"10962 Dyke Rd",
    "sg:city":"Stanardsville",
    "sg:classifiers":[
        {
            "category":"Building & Trades",
            "subcategory":"Construction",
            "type":"Services"
        }
    ],
    "sg:phone":"+1 434 985 2457",
    "sg:postcode":"22973",
    "sg:province":"VA",
    "sg:tags":[
        "contractor"
    ],
    "wof:name":"William E Thacker Builders Inc",
    "wof:placetype":"venue"
},
  "geometry": {"coordinates":[-78.51531799999999,38.273917],"type":"Point"}
}