{
  "type": "Feature",
  "properties": {
    "addr:full":"1230 Rugby Blvd NW Roanoke VA 24017",
    "addr:housenumber":"1230",
    "addr:postcode":"24017",
    "addr:street":"Rugby Blvd Nw",
    "iso:country":"US",
    "sg:address":"1230 Rugby Blvd NW",
    "sg:city":"Roanoke",
    "sg:classifiers":[
        {
            "category":"Organizations",
            "subcategory":"Religious Organization",
            "type":"Services"
        }
    ],
    "sg:phone":"+1 540 343 7832",
    "sg:postcode":"24017",
    "sg:province":"VA",
    "sg:tags":[
        "church"
    ],
    "wof:name":"Abundant Grace Assembly Inc",
    "wof:placetype":"venue"
},
  "geometry": {"coordinates":[-79.957016,37.287541],"type":"Point"}
}