{
  "type": "Feature",
  "properties": {
    "addr:full":"2921 S Glebe Rd Arlington VA 22206",
    "addr:housenumber":"2921",
    "addr:postcode":"22206",
    "addr:street":"S Glebe Rd",
    "iso:country":"US",
    "sg:address":"2921 S Glebe Rd",
    "sg:city":"Arlington",
    "sg:classifiers":[
        {
            "category":"Building & Trades",
            "subcategory":"Locksmith",
            "type":"Services"
        }
    ],
    "sg:phone":"+1 703 842 7281",
    "sg:postcode":"22206",
    "sg:province":"VA",
    "sg:tags":[
        "key"
    ],
    "wof:name":"0 0 24 Hour 7 Day A Emergency Locksmith",
    "wof:placetype":"venue"
},
  "geometry": {"coordinates":[-77.06838999999999,38.844967],"type":"Point"}
}