{
  "type": "Feature",
  "properties": {
    "iso:country":"US",
    "sg:address":"6104 Bibbings Way",
    "sg:city":"Alexandria",
    "sg:classifiers":[
        {
            "category":"Professional",
            "subcategory":"Management & Consulting",
            "type":"Services"
        }
    ],
    "sg:phone":"+1 703 403 0907",
    "sg:postcode":"22315",
    "sg:province":"VA",
    "wof:name":"Y&R Group International",
    "wof:placetype":"venue"
},
  "geometry": {"coordinates":[-77.151775,38.755058],"type":"Point"}
}