{
  "type": "Feature",
  "properties": {
    "iso:country":"US",
    "sg:address":"5018 Browns Gap Tpke",
    "sg:city":"Crozet",
    "sg:classifiers":[
        {
            "category":"Building & Trades",
            "subcategory":"Landscaping Services",
            "type":"Services"
        }
    ],
    "sg:phone":"+1 434 823 9409",
    "sg:postcode":"22932",
    "sg:province":"VA",
    "wof:name":"Suncatcher Service",
    "wof:placetype":"venue"
},
  "geometry": {"coordinates":[-78.667393,38.189838],"type":"Point"}
}