{
  "type": "Feature",
  "properties": {
    "iso:country":"US",
    "sg:address":"1353 S Main St",
    "sg:city":"Marion",
    "sg:classifiers":[
        {
            "category":"Retail",
            "subcategory":"Veterinary Services",
            "type":"Services"
        }
    ],
    "sg:phone":"+1 276 783 5164",
    "sg:postcode":"24354",
    "sg:province":"VA",
    "sg:tags":[
        "veterinarian"
    ],
    "wof:name":"Smyth County Animal Hospital",
    "wof:placetype":"venue"
},
  "geometry": {"coordinates":[-81.53707900000001,36.824519],"type":"Point"}
}