{
  "type": "Feature",
  "properties": {
    "iso:country":"US",
    "sg:address":"12107 Elm Forest Way",
    "sg:city":"Fairfax",
    "sg:classifiers":[
        {
            "category":"Professional",
            "subcategory":"Computer Services",
            "type":"Services"
        }
    ],
    "sg:phone":"+1 703 631 8024",
    "sg:postcode":"22030",
    "sg:province":"VA",
    "sg:tags":[
        "information",
        "technology"
    ],
    "wof:name":"Pivotal Point Solutions Inc",
    "wof:placetype":"venue"
},
  "geometry": {"coordinates":[-77.366551,38.858015],"type":"Point"}
}