{
  "type": "Feature",
  "properties": {
    "addr:full":"503 Maple Ave W Vienna VA 22180",
    "addr:housenumber":"503",
    "addr:postcode":"22180",
    "addr:street":"Maple Ave W",
    "iso:country":"US",
    "sg:address":"503 Maple Ave W",
    "sg:city":"Vienna",
    "sg:classifiers":[
        {
            "category":"Personal",
            "type":"Services"
        }
    ],
    "sg:phone":"+1 703 368 5893",
    "sg:postcode":"22180",
    "sg:province":"VA",
    "sg:tags":[
        "wedding",
        "chapel"
    ],
    "wof:name":"ADG Events & Weddings",
    "wof:placetype":"venue"
},
  "geometry": {"coordinates":[-77.27496600000001,38.893902],"type":"Point"}
}