{
  "type": "Feature",
  "properties": {
    "addr:full":"1223 Pacels Way Chesapeake VA 23322",
    "addr:housenumber":"1223",
    "addr:postcode":"23322",
    "addr:street":"Pacels Way",
    "iso:country":"US",
    "sg:address":"1223 Pacels Way",
    "sg:city":"Chesapeake",
    "sg:classifiers":[
        {
            "category":"Shopping",
            "subcategory":"Jewelry",
            "type":"Retail Goods"
        }
    ],
    "sg:phone":"+1 757 482 0040",
    "sg:postcode":"23322",
    "sg:province":"VA",
    "wof:name":"Diamond Brokerage Svc",
    "wof:placetype":"venue"
},
  "geometry": {"coordinates":[-76.195741,36.6937],"type":"Point"}
}