{
  "type": "Feature",
  "properties": {
    "addr:full":"400 Sleepy Hollow Rd Richmond VA 23229",
    "addr:housenumber":"400",
    "addr:postcode":"23229",
    "addr:street":"Sleepy Hollow Rd",
    "iso:country":"US",
    "sg:address":"400 Sleepy Hollow Rd",
    "sg:city":"Richmond",
    "sg:classifiers":[
        {
            "category":"Professional",
            "subcategory":"Business Services",
            "type":"Services"
        }
    ],
    "sg:phone":"+1 804 750 2008",
    "sg:postcode":"23229",
    "sg:province":"VA",
    "wof:name":"Cam Com LLC",
    "wof:placetype":"venue"
},
  "geometry": {"coordinates":[-77.576374,37.584696],"type":"Point"}
}