{
  "type": "Feature",
  "properties": {
    "addr:full":"113 Cheadle Loop Rd Seaford VA 23696",
    "addr:housenumber":"113",
    "addr:postcode":"23696",
    "addr:street":"Cheadle Loop Rd",
    "iso:country":"US",
    "sg:address":"113 Cheadle Loop Rd",
    "sg:city":"Seaford",
    "sg:classifiers":[
        {
            "category":"Retail",
            "subcategory":"Repair Shop",
            "type":"Services"
        }
    ],
    "sg:phone":"+1 757 890 0689",
    "sg:postcode":"23696",
    "sg:province":"VA",
    "sg:tags":[
        "lock",
        "locksmith"
    ],
    "wof:name":"Bennie's Mobile Locksmith Svc",
    "wof:placetype":"venue"
},
  "geometry": {"coordinates":[-76.436706,37.187027],"type":"Point"}
}