{
  "type": "Feature",
  "properties": {
    "addr:full":"11033 Jefferson Ave Newport News VA 23601",
    "addr:housenumber":"11033",
    "addr:postcode":"23601",
    "addr:street":"Jefferson Ave",
    "iso:country":"US",
    "sg:address":"11033 Jefferson Ave",
    "sg:city":"Newport News",
    "sg:classifiers":[
        {
            "category":"Autos & Motor Vehicles",
            "subcategory":"Auto Supplies",
            "type":"Retail Goods"
        }
    ],
    "sg:phone":"+1 757 599 1380",
    "sg:postcode":"23601",
    "sg:province":"VA",
    "sg:tags":[
        "parts",
        "accessory"
    ],
    "sg:website":"www.autozone.com",
    "wof:name":"Autozone",
    "wof:placetype":"venue"
},
  "geometry": {"coordinates":[-76.464502,37.057049],"type":"Point"}
}