{
  "type": "Feature",
  "properties": {
    "addr:full":"208 87th St Virginia Beach VA 23451",
    "addr:housenumber":"208",
    "addr:postcode":"23451",
    "addr:street":"87Th St",
    "iso:country":"US",
    "sg:address":"208 87th St",
    "sg:city":"Virginia Beach",
    "sg:classifiers":[
        {
            "category":"Professional",
            "subcategory":"Business Services",
            "type":"Services"
        }
    ],
    "sg:phone":"+1 757 491 1770",
    "sg:postcode":"23451",
    "sg:province":"VA",
    "wof:name":"Kirsch Enterprises Inc",
    "wof:placetype":"venue"
},
  "geometry": {"coordinates":[-75.996228,36.911705],"type":"Point"}
}