{
  "type": "Feature",
  "properties": {
    "iso:country":"US",
    "sg:address":"1672 Virginia Beach Blvd",
    "sg:city":"Virginia Beach",
    "sg:classifiers":[
        {
            "category":"Food & Beverages",
            "subcategory":"Groceries & Convenience Stores",
            "type":"Retail Goods"
        }
    ],
    "sg:phone":"+1 757 491 1439",
    "sg:postcode":"23454",
    "sg:province":"VA",
    "wof:name":"7-Eleven",
    "wof:placetype":"venue"
},
  "geometry": {"coordinates":[-76.020235,36.842518],"type":"Point"}
}