{
  "type": "Feature",
  "properties": {
    "addr:full":"941 18th St Newport News VA 23607",
    "addr:housenumber":"941",
    "addr:postcode":"23607",
    "addr:street":"18Th St",
    "iso:country":"US",
    "sg:address":"941 18th St",
    "sg:city":"Newport News",
    "sg:classifiers":[
        {
            "category":"Building & Trades",
            "subcategory":"Construction",
            "type":"Services"
        }
    ],
    "sg:phone":"+1 757 244 0786",
    "sg:postcode":"23607",
    "sg:province":"VA",
    "sg:tags":[
        "house"
    ],
    "wof:name":"Blaine & Sons Home Improvement",
    "wof:placetype":"venue"
},
  "geometry": {"coordinates":[-76.407168,36.980569],"type":"Point"}
}