{
  "type": "Feature",
  "properties": {
    "addr:full":"1039 Sterling Rd Herndon VA 20170",
    "addr:housenumber":"1039",
    "addr:postcode":"20170",
    "addr:street":"Sterling Rd",
    "iso:country":"US",
    "sg:address":"1039 Sterling Rd",
    "sg:city":"Herndon",
    "sg:classifiers":[
        {
            "category":"Professional",
            "subcategory":"Employment Agencies",
            "type":"Services"
        }
    ],
    "sg:phone":"+1 703 467 9110",
    "sg:postcode":"20170",
    "sg:province":"VA",
    "sg:tags":[
        "help",
        "contractor"
    ],
    "wof:name":"Management Recruiters",
    "wof:placetype":"venue"
},
  "geometry": {"coordinates":[-77.397025,38.969423],"type":"Point"}
}