{
  "type": "Feature",
  "properties": {
    "addr:full":"501 N Main St Gordonsville VA 22942",
    "addr:housenumber":"501",
    "addr:postcode":"22942",
    "addr:street":"N Main St",
    "iso:country":"US",
    "sg:address":"501 N Main St",
    "sg:city":"Gordonsville",
    "sg:classifiers":[
        {
            "category":"Health Services",
            "subcategory":"Doctor",
            "type":"Services"
        }
    ],
    "sg:phone":"+1 540 832 2211",
    "sg:postcode":"22942",
    "sg:province":"VA",
    "sg:tags":[
        "physician",
        "surgeon"
    ],
    "wof:name":"David B Cox MD",
    "wof:placetype":"venue"
},
  "geometry": {"coordinates":[-78.189148,38.141704],"type":"Point"}
}