{
  "type": "Feature",
  "properties": {
    "iso:country":"US",
    "sg:address":"86 Carrollwood Dr",
    "sg:city":"Woodlawn",
    "sg:classifiers":[
        {
            "category":"Travel",
            "subcategory":"Campground",
            "type":"Entertainment"
        }
    ],
    "sg:phone":"+1 276 728 9312",
    "sg:postcode":"24381",
    "sg:province":"VA",
    "wof:name":"Carrollwood Campground",
    "wof:placetype":"venue"
},
  "geometry": {"coordinates":[-80.788483,36.739859],"type":"Point"}
}