{
  "type": "Feature",
  "properties": {
    "iso:country":"US",
    "sg:address":"1752 Timberwood Blvd",
    "sg:city":"Charlottesville",
    "sg:classifiers":[
        {
            "category":"Health Services",
            "subcategory":"Doctor",
            "type":"Services"
        }
    ],
    "sg:phone":"+1 434 974 6492",
    "sg:postcode":"22911",
    "sg:province":"VA",
    "sg:tags":[
        "dentist"
    ],
    "wof:name":"Kenneth G Rasmussen DDS",
    "wof:placetype":"venue"
},
  "geometry": {"coordinates":[-78.43653,38.124736],"type":"Point"}
}