{
  "type": "Feature",
  "properties": {
    "iso:country":"US",
    "sg:address":"202 E 9th St",
    "sg:city":"Richmond",
    "sg:classifiers":[
        {
            "category":"Government",
            "subcategory":"Office",
            "type":"Public Place"
        }
    ],
    "sg:phone":"+1 804 692 3200",
    "sg:postcode":"23224",
    "sg:province":"VA",
    "sg:tags":[
        "forest",
        "wildlife",
        "conservation",
        "mineral",
        "land"
    ],
    "wof:name":"VA Dept Mines Minerals & Enrgy",
    "wof:placetype":"venue"
},
  "geometry": {"coordinates":[-77.43908399999999,37.520011],"type":"Point"}
}