{
  "type": "Feature",
  "properties": {
    "addr:full":"9503 Babson Ct Fairfax VA 22032",
    "addr:housenumber":"9503",
    "addr:postcode":"22032",
    "addr:street":"Babson Ct",
    "iso:country":"US",
    "sg:address":"9503 Babson Ct",
    "sg:city":"Fairfax",
    "sg:classifiers":[
        {
            "category":"Professional",
            "subcategory":"Management & Consulting",
            "type":"Services"
        }
    ],
    "sg:phone":"+1 703 425 2850",
    "sg:postcode":"22032",
    "sg:province":"VA",
    "sg:tags":[
        "public",
        "relations",
        "government"
    ],
    "wof:name":"David W Thomas",
    "wof:placetype":"venue"
},
  "geometry": {"coordinates":[-77.272205,38.817992],"type":"Point"}
}