{
  "type": "Feature",
  "properties": {
    "iso:country":"US",
    "sg:address":"20522 Middlebury St",
    "sg:city":"Ashburn",
    "sg:classifiers":[
        {
            "category":"Professional",
            "subcategory":"Advertising",
            "type":"Services"
        }
    ],
    "sg:phone":"+1 703 929 9383",
    "sg:postcode":"20147",
    "sg:province":"VA",
    "sg:tags":[
        "specialty"
    ],
    "wof:name":"Monkeytime Promotions",
    "wof:placetype":"venue"
},
  "geometry": {"coordinates":[-77.517747,39.048283],"type":"Point"}
}