{
  "type": "Feature",
  "properties": {
    "iso:country":"US",
    "sg:address":"7805 Gants Hill Ln",
    "sg:city":"Fredericksburg",
    "sg:classifiers":[
        {
            "category":"Professional",
            "subcategory":"Business Services",
            "type":"Services"
        }
    ],
    "sg:phone":"+1 540 785 4365",
    "sg:postcode":"22407",
    "sg:province":"VA",
    "wof:name":"Technological Solutions",
    "wof:placetype":"venue"
},
  "geometry": {"coordinates":[-77.602301,38.278324],"type":"Point"}
}