{
  "type": "Feature",
  "properties": {
    "iso:country":"US",
    "sg:address":"22334 Tradewinds Dr",
    "sg:city":"Carrollton",
    "sg:classifiers":[
        {
            "category":"Real Estate",
            "subcategory":"Surveying",
            "type":"Services"
        }
    ],
    "sg:phone":"+1 757 356 5336",
    "sg:postcode":"23314",
    "sg:province":"VA",
    "sg:tags":[
        "planning",
        "land"
    ],
    "wof:name":"The On-Trac Family",
    "wof:placetype":"venue"
},
  "geometry": {"coordinates":[-76.535904,36.957513],"type":"Point"}
}