{
  "type": "Feature",
  "properties": {
    "addr:full":"21385 Virgil H Goode Hwy Rocky Mount VA 24151",
    "addr:postcode":"21385;24151",
    "addr:street":"Goode Hwy",
    "iso:country":"US",
    "sg:address":"21385 Virgil H Goode Hwy",
    "sg:city":"Rocky Mount",
    "sg:classifiers":[
        {
            "category":"Personal",
            "subcategory":"Beauty Salon",
            "type":"Services"
        }
    ],
    "sg:phone":"+1 540 334 5095",
    "sg:postcode":"24151",
    "sg:province":"VA",
    "wof:name":"Meade School Of Beauty",
    "wof:placetype":"venue"
},
  "geometry": {"coordinates":[-79.91124499999999,37.074966],"type":"Point"}
}