{
  "type": "Feature",
  "properties": {
    "addr:full":"36 Palmyra Church Rd Edinburg VA 22824",
    "addr:housenumber":"36",
    "addr:postcode":"22824",
    "addr:street":"Palmyra Church Rd",
    "iso:country":"US",
    "sg:address":"36 Palmyra Church Rd",
    "sg:city":"Edinburg",
    "sg:classifiers":[
        {
            "category":"Professional",
            "subcategory":"Business Services",
            "type":"Services"
        }
    ],
    "sg:phone":"+1 540 984 3133",
    "sg:postcode":"22824",
    "sg:province":"VA",
    "wof:name":"Greenhope Enterprises LLC",
    "wof:placetype":"venue"
},
  "geometry": {"coordinates":[-78.598252,38.781912],"type":"Point"}
}