{
  "type": "Feature",
  "properties": {
    "addr:full":"20 Forest Ave Radford VA 24141",
    "addr:housenumber":"20",
    "addr:postcode":"24141",
    "addr:street":"Forest Ave",
    "iso:country":"US",
    "sg:address":"20 Forest Ave",
    "sg:city":"Radford",
    "sg:classifiers":[
        {
            "category":"Government",
            "subcategory":"Office",
            "type":"Public Place"
        }
    ],
    "sg:phone":"+1 540 731 3657",
    "sg:postcode":"24141",
    "sg:province":"VA",
    "sg:tags":[
        "village"
    ],
    "wof:name":"Radford Sewer Dept",
    "wof:placetype":"venue"
},
  "geometry": {"coordinates":[-80.59118700000001,37.112015],"type":"Point"}
}