{
  "type": "Feature",
  "properties": {
    "iso:country":"US",
    "sg:address":"7400 Leesburg Pike",
    "sg:city":"Falls Church",
    "sg:classifiers":[
        {
            "category":"Professional",
            "subcategory":"Lawyer & Legal Services",
            "type":"Services"
        }
    ],
    "sg:phone":"+1 703 893 1064",
    "sg:postcode":"22043",
    "sg:province":"VA",
    "wof:name":"Law Offces Larry W Thomas Pllc",
    "wof:placetype":"venue"
},
  "geometry": {"coordinates":[-77.20280099999999,38.902615],"type":"Point"}
}