{
  "type": "Feature",
  "properties": {
    "iso:country":"US",
    "sg:address":"106 Robinson St",
    "sg:city":"Ashland",
    "sg:classifiers":[
        {
            "category":"Organizations",
            "subcategory":"Professional Association",
            "type":"Services"
        }
    ],
    "sg:phone":"+1 804 798 8130",
    "sg:postcode":"23005",
    "sg:province":"VA",
    "wof:name":"Hanover Association-Business",
    "wof:placetype":"venue"
},
  "geometry": {"coordinates":[-77.481329,37.758248],"type":"Point"}
}