{
  "type": "Feature",
  "properties": {
    "iso:country":"US",
    "sg:address":"13505 Hillendale Dr",
    "sg:city":"Woodbridge",
    "sg:classifiers":[
        {
            "category":"Organizations",
            "subcategory":"Professional Association",
            "type":"Services"
        }
    ],
    "sg:phone":"+1 703 670 5060",
    "sg:postcode":"22193",
    "sg:province":"VA",
    "sg:website":"www.arcgpw.org",
    "wof:name":"Muriel Humphrey Respite Day",
    "wof:placetype":"venue"
},
  "geometry": {"coordinates":[-77.34218799999999,38.656904],"type":"Point"}
}