{
  "type": "Feature",
  "properties": {
    "addr:full":"1415 W Cary St Richmond VA 23220",
    "addr:housenumber":"1415",
    "addr:postcode":"23220",
    "addr:street":"W Cary St",
    "iso:country":"US",
    "sg:address":"1415 W Cary St",
    "sg:city":"Richmond",
    "sg:classifiers":[
        {
            "category":"Organizations",
            "subcategory":"Religious Organization",
            "type":"Services"
        }
    ],
    "sg:phone":"+1 804 355 1044",
    "sg:postcode":"23220",
    "sg:province":"VA",
    "wof:name":"Fifth Baptist Church",
    "wof:placetype":"venue"
},
  "geometry": {"coordinates":[-77.459957,37.545763],"type":"Point"}
}