{
  "type": "Feature",
  "properties": {
    "addr:full":"4778 S Park Ct Woodbridge VA 22193",
    "addr:housenumber":"4778",
    "addr:postcode":"22193",
    "addr:street":"S Park Ct",
    "iso:country":"US",
    "sg:address":"4778 S Park Ct",
    "sg:city":"Woodbridge",
    "sg:classifiers":[
        {
            "category":"Retail",
            "subcategory":"Car Wash",
            "type":"Services"
        }
    ],
    "sg:phone":"+1 703 670 6047",
    "sg:postcode":"22193",
    "sg:province":"VA",
    "sg:tags":[
        "carwash"
    ],
    "wof:name":"Robs Enterprises",
    "wof:placetype":"venue"
},
  "geometry": {"coordinates":[-77.346546,38.638013],"type":"Point"}
}