{
  "type": "Feature",
  "properties": {
    "iso:country":"US",
    "sg:address":"1510 Lakeview Pkwy",
    "sg:city":"Locust Grove",
    "sg:classifiers":[
        {
            "category":"Building & Trades",
            "subcategory":"Construction",
            "type":"Services"
        }
    ],
    "sg:phone":"+1 540 972 5993",
    "sg:postcode":"22508",
    "sg:province":"VA",
    "sg:tags":[
        "house",
        "improvement",
        "home"
    ],
    "wof:name":"M R G Custom Carpentry",
    "wof:placetype":"venue"
},
  "geometry": {"coordinates":[-77.779225,38.331093],"type":"Point"}
}