{
  "type": "Feature",
  "properties": {
    "addr:full":"3620 Piney Rd Gretna VA 24557",
    "addr:housenumber":"3620",
    "addr:postcode":"24557",
    "addr:street":"Piney Rd",
    "iso:country":"US",
    "sg:address":"3620 Piney Rd",
    "sg:city":"Gretna",
    "sg:classifiers":[
        {
            "category":"Organizations",
            "subcategory":"Religious Organization",
            "type":"Services"
        }
    ],
    "sg:phone":"+1 434 656 3229",
    "sg:postcode":"24557",
    "sg:province":"VA",
    "sg:tags":[
        "church"
    ],
    "wof:name":"Piney Grove Missionary Baptist",
    "wof:placetype":"venue"
},
  "geometry": {"coordinates":[-79.430882,36.934685],"type":"Point"}
}