{
  "type": "Feature",
  "properties": {
    "addr:full":"7612 Georgetown Pike Mc Lean VA 22102",
    "addr:housenumber":"7612",
    "addr:postcode":"22102",
    "addr:street":"Georgetown Pike Mc Lean",
    "iso:country":"US",
    "sg:address":"7612 Georgetown Pike",
    "sg:city":"Mc Lean",
    "sg:classifiers":[
        {
            "category":"Professional",
            "subcategory":"Management & Consulting",
            "type":"Services"
        }
    ],
    "sg:phone":"+1 703 734 1680",
    "sg:postcode":"22102",
    "sg:province":"VA",
    "wof:name":"Dda Associates Inc",
    "wof:placetype":"venue"
},
  "geometry": {"coordinates":[-77.20820399999999,38.959278],"type":"Point"}
}