{
  "type": "Feature",
  "properties": {
    "addr:full":"153 S Birdneck Rd Virginia Beach VA 23451",
    "addr:housenumber":"153",
    "addr:postcode":"23451",
    "addr:street":"S Birdneck Rd",
    "iso:country":"US",
    "sg:address":"153 S Birdneck Rd",
    "sg:city":"Virginia Beach",
    "sg:classifiers":[
        {
            "category":"Professional",
            "type":"Services"
        }
    ],
    "sg:phone":"+1 757 425 7081",
    "sg:postcode":"23451",
    "sg:province":"VA",
    "sg:tags":[
        "establishment"
    ],
    "wof:name":"Sequel",
    "wof:placetype":"venue"
},
  "geometry": {"coordinates":[-75.999033,36.835142],"type":"Point"}
}