{
  "type": "Feature",
  "properties": {
    "iso:country":"US",
    "sg:address":"20558 Broad Run Dr",
    "sg:city":"Sterling",
    "sg:classifiers":[
        {
            "category":"Building & Trades",
            "subcategory":"Landscaping Services",
            "type":"Services"
        }
    ],
    "sg:phone":"+1 703 430 1438",
    "sg:postcode":"20165",
    "sg:province":"VA",
    "wof:name":"Mountain View Mowing",
    "wof:placetype":"venue"
},
  "geometry": {"coordinates":[-77.430088,39.047615],"type":"Point"}
}