{
  "type": "Feature",
  "properties": {
    "iso:country":"US",
    "sg:address":"743 Prospect Ave",
    "sg:city":"Charlottesville",
    "sg:classifiers":[
        {
            "category":"Building & Trades",
            "subcategory":"Construction",
            "type":"Services"
        }
    ],
    "sg:phone":"+1 434 977 5275",
    "sg:postcode":"22903",
    "sg:province":"VA",
    "sg:tags":[
        "contractor"
    ],
    "wof:name":"C A Masonry",
    "wof:placetype":"venue"
},
  "geometry": {"coordinates":[-78.496667,38.021815],"type":"Point"}
}