{
  "type": "Feature",
  "properties": {
    "iso:country":"US",
    "sg:address":"8221 Peridot Dr",
    "sg:city":"Mc Lean",
    "sg:classifiers":[
        {
            "category":"Real Estate",
            "subcategory":"Real Estate Operator",
            "type":"Services"
        }
    ],
    "sg:phone":"+1 703 790 1805",
    "sg:postcode":"22102",
    "sg:province":"VA",
    "sg:tags":[
        "building",
        "nonresidential"
    ],
    "wof:name":"Tristate Properties",
    "wof:placetype":"venue"
},
  "geometry": {"coordinates":[-77.228872,38.927031],"type":"Point"}
}