{
  "type": "Feature",
  "properties": {
    "addr:full":"35 Shady Ln Stafford VA 22554",
    "addr:housenumber":"35",
    "addr:postcode":"22554",
    "addr:street":"Shady Ln",
    "iso:country":"US",
    "sg:address":"35 Shady Ln",
    "sg:city":"Stafford",
    "sg:classifiers":[
        {
            "category":"Professional",
            "subcategory":"Research",
            "type":"Services"
        }
    ],
    "sg:phone":"+1 540 657 7755",
    "sg:postcode":"22554",
    "sg:province":"VA",
    "sg:tags":[
        "commercial",
        "physical"
    ],
    "wof:name":"Mid Atlantic Wetland Cons",
    "wof:placetype":"venue"
},
  "geometry": {"coordinates":[-77.371487,38.431599],"type":"Point"}
}