{
  "type": "Feature",
  "properties": {
    "addr:full":"2716 Enterprise Pkwy Richmond VA 23294",
    "addr:housenumber":"2716",
    "addr:postcode":"23294",
    "addr:street":"Enterprise Pkwy",
    "iso:country":"US",
    "sg:address":"2716 Enterprise Pkwy",
    "sg:city":"Richmond",
    "sg:classifiers":[
        {
            "category":"Banks & Credit Unions",
            "subcategory":"Bank",
            "type":"Services"
        }
    ],
    "sg:phone":"+1 804 935 8601",
    "sg:postcode":"23294",
    "sg:province":"VA",
    "sg:tags":[
        "loan",
        "real estate"
    ],
    "wof:name":"America's Mortgage Broker",
    "wof:placetype":"venue"
},
  "geometry": {"coordinates":[-77.52962599999999,37.624668],"type":"Point"}
}