{
  "type": "Feature",
  "properties": {
    "iso:country":"US",
    "sg:address":"400 Southlake Blvd",
    "sg:city":"Richmond",
    "sg:classifiers":[
        {
            "category":"Real Estate",
            "subcategory":"Real Estate Agent",
            "type":"Services"
        }
    ],
    "sg:phone":"+1 804 379 9250",
    "sg:postcode":"23236",
    "sg:province":"VA",
    "wof:name":"Southern Heritage Inc",
    "wof:placetype":"venue"
},
  "geometry": {"coordinates":[-77.606537,37.49966],"type":"Point"}
}