{
  "type": "Feature",
  "properties": {
    "iso:country":"US",
    "sg:address":"1222 Bells Rd",
    "sg:city":"Virginia Beach",
    "sg:classifiers":[
        {
            "category":"Shopping",
            "subcategory":"Hobbies, Toys, & Games",
            "type":"Retail Goods"
        }
    ],
    "sg:phone":"+1 757 491 8343",
    "sg:postcode":"23454",
    "sg:province":"VA",
    "sg:tags":[
        "craft"
    ],
    "wof:name":"Swivler Designs LTD",
    "wof:placetype":"venue"
},
  "geometry": {"coordinates":[-76.005647,36.819577],"type":"Point"}
}