{
  "type": "Feature",
  "properties": {
    "iso:country":"US",
    "sg:address":"5095 Westfields Blvd",
    "sg:city":"Centreville",
    "sg:classifiers":[
        {
            "category":"Retail",
            "subcategory":"Veterinary Services",
            "type":"Services"
        }
    ],
    "sg:phone":"+1 703 378 3028",
    "sg:postcode":"20120",
    "sg:province":"VA",
    "wof:name":"Calderwood Colleen",
    "wof:placetype":"venue"
},
  "geometry": {"coordinates":[-77.44837099999999,38.867973],"type":"Point"}
}