{
  "type": "Feature",
  "properties": {
    "addr:full":"145 E Market St Leesburg VA 20176",
    "addr:housenumber":"145",
    "addr:postcode":"20176",
    "addr:street":"E Market St",
    "iso:country":"US",
    "sg:address":"145 E Market St",
    "sg:city":"Leesburg",
    "sg:classifiers":[
        {
            "category":"Communications",
            "type":"Services"
        }
    ],
    "sg:phone":"+1 703 737 3716",
    "sg:postcode":"20176",
    "sg:province":"VA",
    "wof:name":"Proactive Communications",
    "wof:placetype":"venue"
},
  "geometry": {"coordinates":[-77.562468,39.114495],"type":"Point"}
}