{
  "type": "Feature",
  "properties": {
    "addr:full":"479 Clearview Cir Earlysville VA 22936",
    "addr:housenumber":"479",
    "addr:postcode":"22936",
    "addr:street":"Clearview Cir",
    "iso:country":"US",
    "sg:address":"479 Clearview Cir",
    "sg:city":"Earlysville",
    "sg:classifiers":[
        {
            "category":"Professional",
            "subcategory":"Management & Consulting",
            "type":"Services"
        }
    ],
    "sg:phone":"+1 434 973 8193",
    "sg:postcode":"22936",
    "sg:province":"VA",
    "sg:tags":[
        "business"
    ],
    "wof:name":"Carpenter Associates",
    "wof:placetype":"venue"
},
  "geometry": {"coordinates":[-78.515175,38.113887],"type":"Point"}
}