{
  "type": "Feature",
  "properties": {
    "addr:full":"4220 Annandale Rd Annandale VA 22003",
    "addr:housenumber":"4220",
    "addr:postcode":"22003",
    "addr:street":"Annandale Rd",
    "iso:country":"US",
    "sg:address":"4220 Annandale Rd",
    "sg:city":"Annandale",
    "sg:classifiers":[
        {
            "category":"Home & Garden",
            "subcategory":"Furniture",
            "type":"Retail Goods"
        }
    ],
    "sg:phone":"+1 703 256 9502",
    "sg:postcode":"22003",
    "sg:province":"VA",
    "sg:tags":[
        "used",
        "real estate"
    ],
    "wof:name":"Annandale Surplus",
    "wof:placetype":"venue"
},
  "geometry": {"coordinates":[-77.196827,38.832409],"type":"Point"}
}