{
  "type": "Feature",
  "properties": {
    "addr:full":"4505 Bexley Cir Virginia Beach VA 23455",
    "addr:housenumber":"4505",
    "addr:postcode":"23455",
    "addr:street":"Bexley Cir",
    "iso:country":"US",
    "sg:address":"4505 Bexley Cir",
    "sg:city":"Virginia Beach",
    "sg:classifiers":[
        {
            "category":"Health Services",
            "subcategory":"Health Practitioner",
            "type":"Services"
        }
    ],
    "sg:phone":"+1 757 464 0786",
    "sg:postcode":"23455",
    "sg:province":"VA",
    "sg:tags":[
        "nutrition",
        "specialist"
    ],
    "wof:name":"Bayside Medical Nutrition Svcs",
    "wof:placetype":"venue"
},
  "geometry": {"coordinates":[-76.129525,36.877579],"type":"Point"}
}