{
  "type": "Feature",
  "properties": {
    "addr:full":"5702 Cleburne Blvd Dublin VA 24084",
    "addr:housenumber":"5702",
    "addr:postcode":"24084",
    "addr:street":"Cleburne Blvd",
    "iso:country":"US",
    "sg:address":"5702 Cleburne Blvd",
    "sg:city":"Dublin",
    "sg:classifiers":[
        {
            "category":"Professional",
            "type":"Services"
        }
    ],
    "sg:phone":"+1 540 674 1692",
    "sg:postcode":"24084",
    "sg:province":"VA",
    "wof:name":"Rolo Shuttle Service Inc",
    "wof:placetype":"venue"
},
  "geometry": {"coordinates":[-80.69517500000001,37.125668],"type":"Point"}
}