{
  "type": "Feature",
  "properties": {
    "addr:full":"3430 N Valley Pike Harrisonburg VA 22802",
    "addr:housenumber":"3430",
    "addr:postcode":"22802",
    "addr:street":"N Valley Pike",
    "iso:country":"US",
    "sg:address":"3430 N Valley Pike",
    "sg:city":"Harrisonburg",
    "sg:classifiers":[
        {
            "category":"Shopping",
            "subcategory":"Bicycles & Sporting Goods",
            "type":"Retail Goods"
        }
    ],
    "sg:phone":"+1 540 433 3337",
    "sg:postcode":"22802",
    "sg:province":"VA",
    "sg:tags":[
        "equipment",
        "teach",
        "scuba",
        "diving"
    ],
    "wof:name":"Kathy's Scuba Inc",
    "wof:placetype":"venue"
},
  "geometry": {"coordinates":[-78.81585,38.48303],"type":"Point"}
}