{
  "type": "Feature",
  "properties": {
    "iso:country":"US",
    "sg:address":"169 Chestnut Ln",
    "sg:city":"Amherst",
    "sg:classifiers":[
        {
            "category":"Freight",
            "type":"Transportation"
        }
    ],
    "sg:phone":"+1 434 946 0700",
    "sg:postcode":"24521",
    "sg:province":"VA",
    "sg:tags":[
        "hauling",
        "trucking"
    ],
    "wof:name":"Countryline Inc",
    "wof:placetype":"venue"
},
  "geometry": {"coordinates":[-78.97877699999999,37.629109],"type":"Point"}
}