{
  "type": "Feature",
  "properties": {
    "addr:full":"1676 International Dr Mc Lean VA 22102",
    "addr:housenumber":"1676",
    "addr:postcode":"22102",
    "addr:street":"International Dr",
    "iso:country":"US",
    "sg:address":"1676 International Dr",
    "sg:city":"Mc Lean",
    "sg:classifiers":[
        {
            "category":"Professional",
            "subcategory":"Lawyer & Legal Services",
            "type":"Services"
        }
    ],
    "sg:phone":"+1 703 336 8800",
    "sg:postcode":"22102",
    "sg:province":"VA",
    "sg:tags":[
        "attorney"
    ],
    "wof:name":"Dombroff & Gilmore PC",
    "wof:placetype":"venue"
},
  "geometry": {"coordinates":[-77.22737600000001,38.92438],"type":"Point"}
}