{
  "type": "Feature",
  "properties": {
    "addr:full":"3205 Burnt Mill Rd Virginia Beach VA 23452",
    "addr:housenumber":"3205",
    "addr:postcode":"23452",
    "addr:street":"Burnt Mill Rd",
    "iso:country":"US",
    "sg:address":"3205 Burnt Mill Rd",
    "sg:city":"Virginia Beach",
    "sg:classifiers":[
        {
            "category":"Retail",
            "subcategory":"Laundry & Dry Cleaning",
            "type":"Services"
        }
    ],
    "sg:phone":"+1 757 368 9156",
    "sg:postcode":"23452",
    "sg:province":"VA",
    "sg:tags":[
        "cleaners",
        "rug",
        "carpet"
    ],
    "wof:name":"Pro Tect Carpet Systems",
    "wof:placetype":"venue"
},
  "geometry": {"coordinates":[-76.085275,36.81453],"type":"Point"}
}