{
  "type": "Feature",
  "properties": {
    "addr:full":"1301 S Joyce St Arlington VA 22202",
    "addr:housenumber":"1301",
    "addr:postcode":"22202",
    "addr:street":"S Joyce St",
    "iso:country":"US",
    "sg:address":"1301 S Joyce St",
    "sg:city":"Arlington",
    "sg:classifiers":[
        {
            "category":"Shopping",
            "subcategory":"Shoes",
            "type":"Retail Goods"
        }
    ],
    "sg:phone":"+1 703 412 0818",
    "sg:postcode":"22202",
    "sg:province":"VA",
    "sg:tags":[
        "store"
    ],
    "sg:website":"www.dswshoes.com",
    "wof:name":"DSW",
    "wof:placetype":"venue"
},
  "geometry": {"coordinates":[-77.063562,38.863097],"type":"Point"}
}