{
  "type": "Feature",
  "properties": {
    "addr:full":"12760 Black Forest Ln Woodbridge VA 22192",
    "addr:housenumber":"12760",
    "addr:postcode":"22192",
    "addr:street":"Black Forest Ln",
    "iso:country":"US",
    "sg:address":"12760 Black Forest Ln",
    "sg:city":"Woodbridge",
    "sg:classifiers":[
        {
            "category":"Professional",
            "subcategory":"Management & Consulting",
            "type":"Services"
        }
    ],
    "sg:phone":"+1 703 590 6235",
    "sg:postcode":"22192",
    "sg:province":"VA",
    "sg:tags":[
        "marketing"
    ],
    "wof:name":"Inter Pacific Unique Technique",
    "wof:placetype":"venue"
},
  "geometry": {"coordinates":[-77.34680400000001,38.676142],"type":"Point"}
}