{
  "type": "Feature",
  "properties": {
    "addr:full":"2201 Conte Dr Midlothian VA 23113",
    "addr:housenumber":"2201",
    "addr:postcode":"23113",
    "addr:street":"Conte Dr",
    "iso:country":"US",
    "sg:address":"2201 Conte Dr",
    "sg:city":"Midlothian",
    "sg:classifiers":[
        {
            "category":"Shopping",
            "type":"Retail Goods"
        }
    ],
    "sg:phone":"+1 804 794 4436",
    "sg:postcode":"23113",
    "sg:province":"VA",
    "sg:tags":[
        "art",
        "gallery",
        "dealer"
    ],
    "wof:name":"Chiaroscuro Art Svc",
    "wof:placetype":"venue"
},
  "geometry": {"coordinates":[-77.62044899999999,37.523942],"type":"Point"}
}