{
  "type": "Feature",
  "properties": {
    "addr:full":"149 E Main St Martinsville VA 24112",
    "addr:housenumber":"149",
    "addr:postcode":"24112",
    "addr:street":"E Main St",
    "iso:country":"US",
    "sg:address":"149 E Main St",
    "sg:city":"Martinsville",
    "sg:classifiers":[
        {
            "category":"Professional",
            "type":"Services"
        }
    ],
    "sg:phone":"+1 276 632 7151",
    "sg:postcode":"24112",
    "sg:province":"VA",
    "wof:name":"J C Bradford & Co",
    "wof:placetype":"venue"
},
  "geometry": {"coordinates":[-79.87042599999999,36.691049],"type":"Point"}
}