{
  "type": "Feature",
  "properties": {
    "iso:country":"US",
    "sg:address":"4660 Kenmore Ave Ste 1200",
    "sg:city":"Alexandria",
    "sg:classifiers":[
        {
            "category":"Health Services",
            "subcategory":"Doctor",
            "type":"Services"
        }
    ],
    "sg:phone":"+1 703 751 8111",
    "sg:postcode":"22304",
    "sg:province":"VA",
    "sg:tags":[
        "cardiologist"
    ],
    "wof:name":"Tanenbaum Mark P MD",
    "wof:placetype":"venue"
},
  "geometry": {"coordinates":[-77.110298,38.829601],"type":"Point"}
}