{
  "type": "Feature",
  "properties": {
    "addr:full":"11 Oak Shade Rd Sterling VA 20164",
    "addr:housenumber":"11",
    "addr:postcode":"20164",
    "addr:street":"Oak Shade Rd",
    "iso:country":"US",
    "sg:address":"11 Oak Shade Rd",
    "sg:city":"Sterling",
    "sg:classifiers":[
        {
            "category":"Retail",
            "subcategory":"Repair Shop",
            "type":"Services"
        }
    ],
    "sg:phone":"+1 703 450 5538",
    "sg:postcode":"20164",
    "sg:province":"VA",
    "sg:tags":[
        "reupholstery",
        "furniture"
    ],
    "wof:name":"Charles Kiss Erpn Antqs Uphlst",
    "wof:placetype":"venue"
},
  "geometry": {"coordinates":[-77.37008899999999,39.039593],"type":"Point"}
}