{
  "type": "Feature",
  "properties": {
    "iso:country":"US",
    "sg:address":"2109 W Great Neck Rd",
    "sg:city":"Virginia Beach",
    "sg:classifiers":[
        {
            "category":"Organizations",
            "subcategory":"Community Association",
            "type":"Services"
        }
    ],
    "sg:phone":"+1 757 496 9873",
    "sg:postcode":"23451",
    "sg:province":"VA",
    "sg:tags":[
        "club"
    ],
    "wof:name":"Freedom Boat Club",
    "wof:placetype":"venue"
},
  "geometry": {"coordinates":[-76.06957300000001,36.905082],"type":"Point"}
}