{
  "type": "Feature",
  "properties": {
    "addr:full":"801 Seabright Ter Midlothian VA 23114",
    "addr:housenumber":"801",
    "addr:postcode":"23114",
    "addr:street":"Seabright Ter",
    "iso:country":"US",
    "sg:address":"801 Seabright Ter",
    "sg:city":"Midlothian",
    "sg:classifiers":[
        {
            "category":"Shopping",
            "subcategory":"Computers & Home Electronics",
            "type":"Retail Goods"
        }
    ],
    "sg:phone":"+1 804 794 8288",
    "sg:postcode":"23114",
    "sg:province":"VA",
    "wof:name":"Matryx Systems Inc",
    "wof:placetype":"venue"
},
  "geometry": {"coordinates":[-77.63345099999999,37.485617],"type":"Point"}
}