{
  "type": "Feature",
  "properties": {
    "addr:full":"1 W Loudoun St Round Hill VA 20141",
    "addr:housenumber":"1",
    "addr:postcode":"20141",
    "addr:street":"W Loudoun St",
    "iso:country":"US",
    "sg:address":"1 W Loudoun St",
    "sg:city":"Round Hill",
    "sg:classifiers":[
        {
            "category":"Wholesale",
            "subcategory":"Non-durable Goods",
            "type":"Manufacturing & Wholesale Goods"
        }
    ],
    "sg:phone":"+1 703 858 3598",
    "sg:postcode":"20141",
    "sg:province":"VA",
    "sg:tags":[
        "advertising"
    ],
    "wof:name":"Meyer Marketing",
    "wof:placetype":"venue"
},
  "geometry": {"coordinates":[-77.768731,39.132638],"type":"Point"}
}