{
  "type": "Feature",
  "properties": {
    "addr:full":"567 Woodward Rd Sperryville VA 22740",
    "addr:housenumber":"567",
    "addr:postcode":"22740",
    "addr:street":"Woodward Rd",
    "iso:country":"US",
    "sg:address":"567 Woodward Rd",
    "sg:city":"Sperryville",
    "sg:classifiers":[
        {
            "category":"Organizations",
            "subcategory":"Non-profit Organization",
            "type":"Services"
        },
        {
            "category":"Education",
            "subcategory":"Dance Studio",
            "type":"Public Place"
        }
    ],
    "sg:phone":"+1 540 987 9234",
    "sg:postcode":"22740",
    "sg:province":"VA",
    "wof:name":"Workspace For Choreographers",
    "wof:placetype":"venue"
},
  "geometry": {"coordinates":[-78.24480699999999,38.652847],"type":"Point"}
}