{
  "type": "Feature",
  "properties": {
    "iso:country":"US",
    "sg:address":"1829 Jefferson Hwy",
    "sg:city":"Fishersville",
    "sg:classifiers":[
        {
            "category":"Restaurant",
            "type":"Food & Drink"
        }
    ],
    "sg:menulink":"http://www.allmenus.com/va/wayne/147640-subway/menu/",
    "sg:phone":"+1 540 943 9500",
    "sg:postcode":"22939",
    "sg:province":"VA",
    "sg:tags":[
        "american",
        "sandwich"
    ],
    "wof:name":"Subway",
    "wof:placetype":"venue"
},
  "geometry": {"coordinates":[-78.972182,38.100952],"type":"Point"}
}