{
  "type": "Feature",
  "properties": {
    "addr:full":"149 Executive Ct Danville VA 24541",
    "addr:housenumber":"149",
    "addr:postcode":"24541",
    "addr:street":"Executive Ct",
    "iso:country":"US",
    "sg:address":"149 Executive Ct",
    "sg:city":"Danville",
    "sg:classifiers":[
        {
            "category":"Social Services",
            "subcategory":"Job Training",
            "type":"Services"
        }
    ],
    "sg:phone":"+1 434 792 1123",
    "sg:postcode":"24541",
    "sg:province":"VA",
    "sg:tags":[
        "rehabilitation"
    ],
    "wof:name":"Rehab Management Inc",
    "wof:placetype":"venue"
},
  "geometry": {"coordinates":[-79.430443,36.591981],"type":"Point"}
}