{
  "type": "Feature",
  "properties": {
    "iso:country":"US",
    "sg:address":"3836 Churchville Rd",
    "sg:city":"Churchville",
    "sg:classifiers":[
        {
            "category":"Building & Trades",
            "subcategory":"Construction",
            "type":"Services"
        }
    ],
    "sg:phone":"+1 540 337 8065",
    "sg:postcode":"24421",
    "sg:province":"VA",
    "sg:tags":[
        "builder",
        "repairer",
        "chimney"
    ],
    "wof:name":"Pyramid Masonry & Chimney Co",
    "wof:placetype":"venue"
},
  "geometry": {"coordinates":[-79.163293,38.226316],"type":"Point"}
}