{
  "type": "Feature",
  "properties": {
    "addr:full":"604 S King St Leesburg VA 20175",
    "addr:housenumber":"604",
    "addr:postcode":"20175",
    "addr:street":"S King St",
    "iso:country":"US",
    "sg:address":"604 S King St",
    "sg:city":"Leesburg",
    "sg:classifiers":[
        {
            "category":"Real Estate",
            "subcategory":"Real Estate Agent",
            "type":"Services"
        },
        {
            "category":"Real Estate",
            "subcategory":"Real Estate Services",
            "type":"Services"
        }
    ],
    "sg:phone":"+1 703 777 9892",
    "sg:postcode":"20175",
    "sg:province":"VA",
    "sg:tags":[
        "company",
        "carrier",
        "insurance",
        "title"
    ],
    "wof:name":"Southern Title",
    "wof:placetype":"venue"
},
  "geometry": {"coordinates":[-77.56892999999999,39.105977],"type":"Point"}
}