{
  "type": "Feature",
  "properties": {
    "iso:country":"US",
    "sg:address":"3120 Chimney Lake Ln",
    "sg:city":"Goldvein",
    "sg:classifiers":[
        {
            "category":"Building & Trades",
            "subcategory":"Construction",
            "type":"Services"
        }
    ],
    "sg:phone":"+1 540 752 4948",
    "sg:postcode":"22720",
    "sg:province":"VA",
    "sg:tags":[
        "house"
    ],
    "wof:name":"P JS Inc",
    "wof:placetype":"venue"
},
  "geometry": {"coordinates":[-77.629389,38.515706],"type":"Point"}
}