{
  "type": "Feature",
  "properties": {
    "iso:country":"US",
    "sg:address":"535 E Main St",
    "sg:city":"Front Royal",
    "sg:classifiers":[
        {
            "category":"Freight",
            "type":"Transportation"
        }
    ],
    "sg:phone":"+1 540 636 2587",
    "sg:postcode":"22630",
    "sg:province":"VA",
    "sg:tags":[
        "special",
        "general"
    ],
    "wof:name":"Econo Storage",
    "wof:placetype":"venue"
},
  "geometry": {"coordinates":[-78.1872,38.917077],"type":"Point"}
}