{
  "type": "Feature",
  "properties": {
    "iso:country":"US",
    "sg:address":"4709 W Braddock Rd",
    "sg:city":"Alexandria",
    "sg:classifiers":[
        {
            "category":"Professional",
            "subcategory":"Business Services",
            "type":"Services"
        }
    ],
    "sg:phone":"+1 703 931 0821",
    "sg:postcode":"22311",
    "sg:province":"VA",
    "sg:tags":[
        "interpretation"
    ],
    "wof:name":"Robert Means",
    "wof:placetype":"venue"
},
  "geometry": {"coordinates":[-77.10918700000001,38.835402],"type":"Point"}
}