{
  "type": "Feature",
  "properties": {
    "addr:full":"510B S Van Dorn St Alexandria VA 22304",
    "addr:housenumber":"510b",
    "addr:postcode":"22304",
    "addr:street":"S;Dorn St",
    "iso:country":"US",
    "sg:address":"510B S Van Dorn St",
    "sg:city":"Alexandria",
    "sg:classifiers":[
        {
            "category":"Shopping",
            "subcategory":"Beauty & Cosmetics",
            "type":"Retail Goods"
        },
        {
            "category":"Personal",
            "subcategory":"Barber",
            "type":"Services"
        }
    ],
    "sg:phone":"+1 703 751 8558",
    "sg:postcode":"22304",
    "sg:province":"VA",
    "sg:tags":[
        "equipment",
        "perfume",
        "salons-equipment",
        "supply"
    ],
    "wof:name":"Wigs & Beauty Supplies",
    "wof:placetype":"venue"
},
  "geometry": {"coordinates":[-77.13319199999999,38.807226],"type":"Point"}
}