{
  "type": "Feature",
  "properties": {
    "addr:full":"2905 River Rd W Goochland VA 23063",
    "addr:housenumber":"2905",
    "addr:postcode":"23063",
    "addr:street":"River Rd W Goochland",
    "iso:country":"US",
    "sg:address":"2905 River Rd W",
    "sg:city":"Goochland",
    "sg:classifiers":[
        {
            "category":"Real Estate",
            "subcategory":"Real Estate Agent",
            "type":"Services"
        }
    ],
    "sg:phone":"+1 804 556 4777",
    "sg:postcode":"23063",
    "sg:province":"VA",
    "wof:name":"Carter Realty Co",
    "wof:placetype":"venue"
},
  "geometry": {"coordinates":[-77.885435,37.684148],"type":"Point"}
}