{
  "type": "Feature",
  "properties": {
    "addr:full":"1940 Stillhouse Rd Charlottesville VA 22901",
    "addr:housenumber":"1940",
    "addr:postcode":"22901",
    "addr:street":"Stillhouse Rd",
    "iso:country":"US",
    "sg:address":"1940 Stillhouse Rd",
    "sg:city":"Charlottesville",
    "sg:classifiers":[
        {
            "category":"Professional",
            "subcategory":"Management & Consulting",
            "type":"Services"
        }
    ],
    "sg:phone":"+1 434 245 9167",
    "sg:postcode":"22901",
    "sg:province":"VA",
    "sg:tags":[
        "consultant",
        "business"
    ],
    "wof:name":"Cook & Williams Communications",
    "wof:placetype":"venue"
},
  "geometry": {"coordinates":[-78.522037,38.084791],"type":"Point"}
}