{
  "type": "Feature",
  "properties": {
    "addr:full":"850 Chautauqua Ave Portsmouth VA 23707",
    "addr:housenumber":"850",
    "addr:postcode":"23707",
    "addr:street":"Chautauqua Ave",
    "iso:country":"US",
    "sg:address":"850 Chautauqua Ave",
    "sg:city":"Portsmouth",
    "sg:classifiers":[
        {
            "category":"Freight",
            "type":"Transportation"
        }
    ],
    "sg:phone":"+1 757 399 6321",
    "sg:postcode":"23707",
    "sg:province":"VA",
    "sg:tags":[
        "a",
        "as",
        "operates",
        "trucking"
    ],
    "wof:name":"Nationwide Intermodal Services",
    "wof:placetype":"venue"
},
  "geometry": {"coordinates":[-76.332386,36.840972],"type":"Point"}
}