{
  "type": "Feature",
  "properties": {
    "iso:country":"US",
    "sg:address":"211 S Main St",
    "sg:city":"Galax",
    "sg:classifiers":[
        {
            "category":"Home & Garden",
            "subcategory":"Hardware",
            "type":"Retail Goods"
        }
    ],
    "sg:phone":"+1 276 236 2352",
    "sg:postcode":"24333",
    "sg:province":"VA",
    "wof:name":"Matthew Hardware",
    "wof:placetype":"venue"
},
  "geometry": {"coordinates":[-80.924269,36.660915],"type":"Point"}
}