{
  "type": "Feature",
  "properties": {
    "addr:full":"700 12th St Radford VA 24141",
    "addr:housenumber":"700",
    "addr:postcode":"24141",
    "addr:street":"12Th St",
    "iso:country":"US",
    "sg:address":"700 12th St",
    "sg:city":"Radford",
    "sg:classifiers":[
        {
            "category":"Education",
            "subcategory":"School",
            "type":"Public Place"
        }
    ],
    "sg:phone":"+1 540 731 3652",
    "sg:postcode":"24141",
    "sg:province":"VA",
    "sg:tags":[
        "executive"
    ],
    "wof:name":"Mc Hard Elementary School",
    "wof:placetype":"venue"
},
  "geometry": {"coordinates":[-80.571263,37.121701],"type":"Point"}
}