{
  "type": "Feature",
  "properties": {
    "iso:country":"US",
    "sg:address":"2625 Chain Bridge Rd",
    "sg:city":"Vienna",
    "sg:classifiers":[
        {
            "category":"Manufacturing",
            "subcategory":"Pottery",
            "type":"Manufacturing & Wholesale Goods"
        }
    ],
    "sg:phone":"+1 703 938 6177",
    "sg:postcode":"22181",
    "sg:province":"VA",
    "sg:tags":[
        "pottery-wholesale",
        "manufacturer"
    ],
    "sg:website":"http://www.enoliver-pottery.com",
    "wof:name":"Creative Workshops",
    "wof:placetype":"venue"
},
  "geometry": {"coordinates":[-77.281003,38.888914],"type":"Point"}
}