{
  "type": "Feature",
  "properties": {
    "addr:full":"11166 Main St Fairfax VA 22030",
    "addr:housenumber":"11166",
    "addr:postcode":"22030",
    "addr:street":"Main St",
    "iso:country":"US",
    "sg:address":"11166 Main St",
    "sg:city":"Fairfax",
    "sg:classifiers":[
        {
            "category":"Health Services",
            "subcategory":"Doctor",
            "type":"Services"
        }
    ],
    "sg:phone":"+1 703 273 5500",
    "sg:postcode":"22030",
    "sg:province":"VA",
    "sg:tags":[
        "dentist"
    ],
    "wof:name":"Jan S Golec DDS",
    "wof:placetype":"venue"
},
  "geometry": {"coordinates":[-77.32970400000001,38.855172],"type":"Point"}
}