{
  "type": "Feature",
  "properties": {
    "addr:full":"42385 Ryan Rd Ashburn VA 20148",
    "addr:housenumber":"42385",
    "addr:postcode":"20148",
    "addr:street":"Ryan Rd",
    "iso:country":"US",
    "sg:address":"42385 Ryan Rd",
    "sg:city":"Ashburn",
    "sg:classifiers":[
        {
            "category":"Ice Cream",
            "type":"Food & Drink"
        }
    ],
    "sg:menulink":"http://www.allmenus.com/va/dulles/184429-cold-stone-creamery/menu/",
    "sg:phone":"+1 703 327 5595",
    "sg:postcode":"20148",
    "sg:province":"VA",
    "sg:tags":[
        "smoothy",
        "juice",
        "american"
    ],
    "wof:name":"Cold Stone Creamery",
    "wof:placetype":"venue"
},
  "geometry": {"coordinates":[-77.53707300000001,38.986208],"type":"Point"}
}