{
  "type": "Feature",
  "properties": {
    "addr:full":"1302 Rockland Ave NW Roanoke VA 24012",
    "addr:housenumber":"1302",
    "addr:postcode":"24012",
    "addr:street":"Rockland Ave Nw",
    "iso:country":"US",
    "sg:address":"1302 Rockland Ave NW",
    "sg:city":"Roanoke",
    "sg:classifiers":[
        {
            "category":"Insurance",
            "subcategory":"Insurance Agent",
            "type":"Services"
        }
    ],
    "sg:phone":"+1 540 366 9577",
    "sg:postcode":"24012",
    "sg:province":"VA",
    "wof:name":"Taylor Insurance",
    "wof:placetype":"venue"
},
  "geometry": {"coordinates":[-79.956926,37.294165],"type":"Point"}
}