{
  "type": "Feature",
  "properties": {
    "addr:full":"101 King Henry Ct Alexandria VA 22314",
    "addr:housenumber":"101",
    "addr:postcode":"22314",
    "addr:street":"King Henry Ct",
    "iso:country":"US",
    "sg:address":"101 King Henry Ct",
    "sg:city":"Alexandria",
    "sg:classifiers":[
        {
            "category":"Professional",
            "subcategory":"Management & Consulting",
            "type":"Services"
        }
    ],
    "sg:phone":"+1 703 549 6132",
    "sg:postcode":"22314",
    "sg:province":"VA",
    "wof:name":"New Leaf Consulting LLC",
    "wof:placetype":"venue"
},
  "geometry": {"coordinates":[-77.05198799999999,38.804908],"type":"Point"}
}