{
  "type": "Feature",
  "properties": {
    "iso:country":"US",
    "sg:address":"23009 Cobb House Rd",
    "sg:city":"Middleburg",
    "sg:classifiers":[
        {
            "category":"Food & Beverages",
            "subcategory":"Bakery",
            "type":"Retail Goods"
        }
    ],
    "sg:phone":"+1 540 687 5344",
    "sg:postcode":"20117",
    "sg:province":"VA",
    "wof:name":"Dunkin Doggies Ltd",
    "wof:placetype":"venue"
},
  "geometry": {"coordinates":[-77.672613,38.981747],"type":"Point"}
}