{
  "type": "Feature",
  "properties": {
    "addr:full":"14773 Wallace Pike Abingdon VA 24210",
    "addr:housenumber":"14773",
    "addr:postcode":"24210",
    "addr:street":"Wallace Pike",
    "iso:country":"US",
    "sg:address":"14773 Wallace Pike",
    "sg:city":"Abingdon",
    "sg:classifiers":[
        {
            "category":"Manufacturing",
            "subcategory":"Tools & Machinery",
            "type":"Manufacturing & Wholesale Goods"
        }
    ],
    "sg:phone":"+1 276 669 2816",
    "sg:postcode":"24210",
    "sg:province":"VA",
    "sg:tags":[
        "machine",
        "shop"
    ],
    "sg:website":"www.centralmachineshop.com",
    "wof:name":"Central Machine",
    "wof:placetype":"venue"
},
  "geometry": {"coordinates":[-82.106981,36.67922],"type":"Point"}
}