{
  "type": "Feature",
  "properties": {
    "addr:full":"1436 Greenbrier Pkwy Chesapeake VA 23320",
    "addr:housenumber":"1436",
    "addr:postcode":"23320",
    "addr:street":"Greenbrier Pkwy",
    "iso:country":"US",
    "sg:address":"1436 Greenbrier Pkwy",
    "sg:city":"Chesapeake",
    "sg:classifiers":[
        {
            "category":"Restaurant",
            "type":"Food & Drink"
        }
    ],
    "sg:phone":"+1 757 420 1900",
    "sg:postcode":"23320",
    "sg:province":"VA",
    "wof:name":"Pargos Restaurant",
    "wof:placetype":"venue"
},
  "geometry": {"coordinates":[-76.230926,36.777825],"type":"Point"}
}