{
  "type": "Feature",
  "properties": {
    "iso:country":"US",
    "sg:address":"39 State St",
    "sg:city":"Pulaski",
    "sg:classifiers":[
        {
            "category":"Government",
            "subcategory":"Office",
            "type":"Public Place"
        }
    ],
    "sg:phone":"+1 540 980 4009",
    "sg:postcode":"24301",
    "sg:province":"VA",
    "wof:name":"Pulaski County Caretaker",
    "wof:placetype":"venue"
},
  "geometry": {"coordinates":[-80.78921699999999,37.045541],"type":"Point"}
}