{
  "type": "Feature",
  "properties": {
    "addr:full":"1360 Beverly Rd Mc Lean VA 22101",
    "addr:housenumber":"1360",
    "addr:postcode":"22101",
    "addr:street":"Beverly Rd",
    "iso:country":"US",
    "sg:address":"1360 Beverly Rd",
    "sg:city":"Mc Lean",
    "sg:classifiers":[
        {
            "category":"Banks & Credit Unions",
            "subcategory":"Investment Brokerage",
            "type":"Services"
        }
    ],
    "sg:phone":"+1 703 748 9640",
    "sg:postcode":"22101",
    "sg:province":"VA",
    "sg:tags":[
        "security"
    ],
    "wof:name":"Raymond James",
    "wof:placetype":"venue"
},
  "geometry": {"coordinates":[-77.178983,38.93588],"type":"Point"}
}