{
  "type": "Feature",
  "properties": {
    "iso:country":"US",
    "sg:address":"14398 James River Rd",
    "sg:city":"Lovingston",
    "sg:classifiers":[
        {
            "category":"Professional",
            "subcategory":"Detective & Security Services",
            "type":"Services"
        }
    ],
    "sg:phone":"+1 434 263 4971",
    "sg:postcode":"22949",
    "sg:province":"VA",
    "sg:tags":[
        "guard",
        "patrol"
    ],
    "wof:name":"Beechwood Security",
    "wof:placetype":"venue"
},
  "geometry": {"coordinates":[-78.87149100000001,37.755565],"type":"Point"}
}