{
  "type": "Feature",
  "properties": {
    "addr:full":"880 S Military Hwy Virginia Beach VA 23464",
    "addr:housenumber":"880",
    "addr:postcode":"23464",
    "addr:street":"S Military Hwy",
    "iso:country":"US",
    "sg:address":"880 S Military Hwy",
    "sg:city":"Virginia Beach",
    "sg:classifiers":[
        {
            "category":"Food & Beverages",
            "subcategory":"Groceries & Convenience Stores",
            "type":"Retail Goods"
        }
    ],
    "sg:phone":"+1 757 523 0217",
    "sg:postcode":"23464",
    "sg:province":"VA",
    "sg:tags":[
        "grocer"
    ],
    "wof:name":"Food Lion",
    "wof:placetype":"venue"
},
  "geometry": {"coordinates":[-76.21414799999999,36.817567],"type":"Point"}
}