{
  "type": "Feature",
  "properties": {
    "iso:country":"US",
    "sg:address":"2904 W Clay St",
    "sg:city":"Richmond",
    "sg:classifiers":[
        {
            "category":"Professional",
            "subcategory":"Printing & Photocopies",
            "type":"Services"
        }
    ],
    "sg:phone":"+1 804 353 7292",
    "sg:postcode":"23230",
    "sg:province":"VA",
    "sg:tags":[
        "services-commercial",
        "duplicating",
        "copying"
    ],
    "sg:website":"http://www.dbanana.com",
    "wof:name":"Bisco Inc",
    "wof:placetype":"venue"
},
  "geometry": {"coordinates":[-77.46975399999999,37.564853],"type":"Point"}
}