{
  "type": "Feature",
  "properties": {
    "iso:country":"US",
    "sg:address":"1203 Lauderdale Dr",
    "sg:city":"Richmond",
    "sg:classifiers":[
        {
            "category":"Personal",
            "type":"Services"
        }
    ],
    "sg:phone":"+1 804 740 4087",
    "sg:postcode":"23238",
    "sg:province":"VA",
    "sg:tags":[
        "miscellaneous"
    ],
    "wof:name":"Vickie L O'Dell Svc",
    "wof:placetype":"venue"
},
  "geometry": {"coordinates":[-77.620504,37.600388],"type":"Point"}
}