{
  "type": "Feature",
  "properties": {
    "addr:full":"2293 Seminole Ln Charlottesville VA 22901",
    "addr:housenumber":"2293",
    "addr:postcode":"22901",
    "addr:street":"Seminole Ln",
    "iso:country":"US",
    "sg:address":"2293 Seminole Ln",
    "sg:city":"Charlottesville",
    "sg:classifiers":[
        {
            "category":"Autos & Motor Vehicles",
            "subcategory":"Auto Supplies",
            "type":"Retail Goods"
        }
    ],
    "sg:phone":"+1 434 978 2886",
    "sg:postcode":"22901",
    "sg:province":"VA",
    "wof:name":"Auto Concepts",
    "wof:placetype":"venue"
},
  "geometry": {"coordinates":[-78.463044,38.098065],"type":"Point"}
}