{
  "type": "Feature",
  "properties": {
    "addr:full":"638 River Bend Ct Newport News VA 23602",
    "addr:housenumber":"638",
    "addr:postcode":"23602",
    "addr:street":"River Bend Ct",
    "iso:country":"US",
    "sg:address":"638 River Bend Ct",
    "sg:city":"Newport News",
    "sg:classifiers":[
        {
            "category":"Real Estate",
            "subcategory":"Real Estate Operator",
            "type":"Services"
        }
    ],
    "sg:phone":"+1 757 881 9196",
    "sg:postcode":"23602",
    "sg:province":"VA",
    "sg:tags":[
        "apartment"
    ],
    "wof:name":"Waterman's Crossing Apartments",
    "wof:placetype":"venue"
},
  "geometry": {"coordinates":[-76.491049,37.110972],"type":"Point"}
}