{
  "type": "Feature",
  "properties": {
    "addr:full":"5632 Shell Rd Virginia Beach VA 23455",
    "addr:housenumber":"5632",
    "addr:postcode":"23455",
    "addr:street":"Shell Rd",
    "iso:country":"US",
    "sg:address":"5632 Shell Rd",
    "sg:city":"Virginia Beach",
    "sg:classifiers":[
        {
            "category":"Organizations",
            "subcategory":"Religious Organization",
            "type":"Services"
        }
    ],
    "sg:phone":"+1 757 464 0886",
    "sg:postcode":"23455",
    "sg:province":"VA",
    "wof:name":"Military Christian Ctr",
    "wof:placetype":"venue"
},
  "geometry": {"coordinates":[-76.17752900000001,36.886303],"type":"Point"}
}