{
  "type": "Feature",
  "properties": {
    "addr:full":"1756 Robindale Rd Richmond VA 23235",
    "addr:housenumber":"1756",
    "addr:postcode":"23235",
    "addr:street":"Robindale Rd",
    "iso:country":"US",
    "sg:address":"1756 Robindale Rd",
    "sg:city":"Richmond",
    "sg:classifiers":[
        {
            "category":"Personal",
            "type":"Services"
        }
    ],
    "sg:phone":"+1 804 323 3748",
    "sg:postcode":"23235",
    "sg:province":"VA",
    "sg:tags":[
        "handyman"
    ],
    "wof:name":"Austin and Paul Systems",
    "wof:placetype":"venue"
},
  "geometry": {"coordinates":[-77.575326,37.518089],"type":"Point"}
}