{
  "type": "Feature",
  "properties": {
    "iso:country":"US",
    "sg:address":"2603 Poinciana Dr",
    "sg:city":"Virginia Beach",
    "sg:classifiers":[
        {
            "category":"Professional",
            "subcategory":"Business Services",
            "type":"Services"
        }
    ],
    "sg:phone":"+1 757 481 6232",
    "sg:postcode":"23451",
    "sg:province":"VA",
    "sg:tags":[
        "interior",
        "planning",
        "commercial",
        "designer",
        "space"
    ],
    "wof:name":"Parrett Linda Associates",
    "wof:placetype":"venue"
},
  "geometry": {"coordinates":[-76.059819,36.910208],"type":"Point"}
}