{
  "type": "Feature",
  "properties": {
    "addr:full":"965 Cranston Dr Chesapeake VA 23320",
    "addr:housenumber":"965",
    "addr:postcode":"23320",
    "addr:street":"Cranston Dr",
    "iso:country":"US",
    "sg:address":"965 Cranston Dr",
    "sg:city":"Chesapeake",
    "sg:classifiers":[
        {
            "category":"Professional",
            "type":"Services"
        }
    ],
    "sg:phone":"+1 757 558 8800",
    "sg:postcode":"23320",
    "sg:province":"VA",
    "sg:tags":[
        "establishment"
    ],
    "wof:name":"Complete Sealcoat & Striping",
    "wof:placetype":"venue"
},
  "geometry": {"coordinates":[-76.21919,36.752557],"type":"Point"}
}