{
  "type": "Feature",
  "properties": {
    "addr:full":"14022 Meades Ct Fredericksburg VA 22407",
    "addr:housenumber":"14022",
    "addr:postcode":"22407",
    "addr:street":"Meades Ct",
    "iso:country":"US",
    "sg:address":"14022 Meades Ct",
    "sg:city":"Fredericksburg",
    "sg:classifiers":[
        {
            "category":"Professional",
            "subcategory":"Engineering",
            "type":"Services"
        }
    ],
    "sg:phone":"+1 540 786 6726",
    "sg:postcode":"22407",
    "sg:province":"VA",
    "sg:tags":[
        "construction",
        "engineer"
    ],
    "wof:name":"William Smayda",
    "wof:placetype":"venue"
},
  "geometry": {"coordinates":[-77.639223,38.343503],"type":"Point"}
}