{
  "type": "Feature",
  "properties": {
    "iso:country":"US",
    "sg:address":"567 Ayrshire Way",
    "sg:city":"Newport News",
    "sg:classifiers":[
        {
            "category":"Shopping",
            "subcategory":"Catalog Store",
            "type":"Retail Goods"
        }
    ],
    "sg:phone":"+1 757 570 2074",
    "sg:postcode":"23602",
    "sg:province":"VA",
    "sg:tags":[
        "mail",
        "house"
    ],
    "wof:name":"E Trinkets Inc",
    "wof:placetype":"venue"
},
  "geometry": {"coordinates":[-76.519762,37.134763],"type":"Point"}
}