{
  "type": "Feature",
  "properties": {
    "addr:full":"9101 Wrva Rd Richmond VA 23231",
    "addr:housenumber":"9101",
    "addr:postcode":"23231",
    "addr:street":"Wrva Rd",
    "iso:country":"US",
    "sg:address":"9101 Wrva Rd",
    "sg:city":"Richmond",
    "sg:classifiers":[
        {
            "category":"Building & Trades",
            "subcategory":"Electrical",
            "type":"Services"
        }
    ],
    "sg:phone":"+1 804 795 4100",
    "sg:postcode":"23231",
    "sg:province":"VA",
    "sg:tags":[
        "electrical",
        "contractor"
    ],
    "wof:name":"Plateau Electrical Constrctrs",
    "wof:placetype":"venue"
},
  "geometry": {"coordinates":[-77.32153099999999,37.411449],"type":"Point"}
}