{
  "type": "Feature",
  "properties": {
    "addr:full":"9212 Terrell Ln Hampton VA 23666",
    "addr:housenumber":"9212",
    "addr:postcode":"23666",
    "addr:street":"Terrell Ln",
    "iso:country":"US",
    "sg:address":"9212 Terrell Ln",
    "sg:city":"Hampton",
    "sg:classifiers":[
        {
            "category":"Health Services",
            "subcategory":"Medical Lab",
            "type":"Services"
        }
    ],
    "sg:phone":"+1 757 218 5186",
    "sg:postcode":"23666",
    "sg:province":"VA",
    "sg:tags":[
        "tech"
    ],
    "wof:name":"Bobbie M Rampy",
    "wof:placetype":"venue"
},
  "geometry": {"coordinates":[-76.39866000000001,37.053059],"type":"Point"}
}