{
  "type": "Feature",
  "properties": {
    "addr:full":"12751 Oak Lake Ct Midlothian VA 23112",
    "addr:housenumber":"12751",
    "addr:postcode":"23112",
    "addr:street":"Oak Lake Ct",
    "iso:country":"US",
    "sg:address":"12751 Oak Lake Ct",
    "sg:city":"Midlothian",
    "sg:classifiers":[
        {
            "category":"Building & Trades",
            "subcategory":"Construction",
            "type":"Services"
        }
    ],
    "sg:phone":"+1 804 744 7079",
    "sg:postcode":"23112",
    "sg:province":"VA",
    "sg:tags":[
        "work",
        "site"
    ],
    "wof:name":"Excalibur Construction Corp",
    "wof:placetype":"venue"
},
  "geometry": {"coordinates":[-77.62979799999999,37.456912],"type":"Point"}
}