{
  "type": "Feature",
  "properties": {
    "addr:full":"4901 Seminary Rd Ste 104 Alexandria VA 22311",
    "addr:housenumber":"4901",
    "addr:postcode":"22311",
    "addr:street":"Seminary Rd Ste 104",
    "iso:country":"US",
    "sg:address":"4901 Seminary Rd Ste 104",
    "sg:city":"Alexandria",
    "sg:classifiers":[
        {
            "category":"Professional",
            "subcategory":"Employment Agencies",
            "type":"Services"
        }
    ],
    "sg:phone":"+1 703 379 1600",
    "sg:postcode":"22311",
    "sg:province":"VA",
    "wof:name":"Dynquest Inc",
    "wof:placetype":"venue"
},
  "geometry": {"coordinates":[-77.115073,38.832231],"type":"Point"}
}