{
  "type": "Feature",
  "properties": {
    "addr:full":"45665 W Church Rd Ste 105 Sterling VA 20164",
    "addr:housenumber":"45665",
    "addr:postcode":"20164",
    "addr:street":"W Church Rd Ste 105",
    "iso:country":"US",
    "sg:address":"45665 W Church Rd Ste 105",
    "sg:city":"Sterling",
    "sg:classifiers":[
        {
            "category":"Personal",
            "subcategory":"Nail Salon",
            "type":"Services"
        }
    ],
    "sg:phone":"+1 703 421 4480",
    "sg:postcode":"20164",
    "sg:province":"VA",
    "wof:name":"Glamour Nail And Spa",
    "wof:placetype":"venue"
},
  "geometry": {"coordinates":[-77.42057,39.007315],"type":"Point"}
}