{
  "type": "Feature",
  "properties": {
    "addr:full":"1012 Steeples Ct Falls Church VA 22046",
    "addr:housenumber":"1012",
    "addr:postcode":"22046",
    "addr:street":"Steeples Ct",
    "iso:country":"US",
    "sg:address":"1012 Steeples Ct",
    "sg:city":"Falls Church",
    "sg:classifiers":[
        {
            "category":"Professional",
            "subcategory":"Business Services",
            "type":"Services"
        }
    ],
    "sg:phone":"+1 703 536 1848",
    "sg:postcode":"22046",
    "sg:province":"VA",
    "wof:name":"Morrison Group Inc",
    "wof:placetype":"venue"
},
  "geometry": {"coordinates":[-77.182856,38.892546],"type":"Point"}
}