{
  "type": "Feature",
  "properties": {
    "iso:country":"US",
    "sg:address":"2427 S Shirlington Rd",
    "sg:city":"Arlington",
    "sg:classifiers":[
        {
            "category":"Autos & Motor Vehicles",
            "subcategory":"Automobile Sales",
            "type":"Retail Goods"
        }
    ],
    "sg:phone":"+1 703 486 2226",
    "sg:postcode":"22206",
    "sg:province":"VA",
    "sg:tags":[
        "car"
    ],
    "wof:name":"Shirlington Auto Exchange",
    "wof:placetype":"venue"
},
  "geometry": {"coordinates":[-77.08380099999999,38.847698],"type":"Point"}
}