{
  "type": "Feature",
  "properties": {
    "iso:country":"US",
    "sg:address":"2051 Swans Neck Way",
    "sg:city":"Reston",
    "sg:classifiers":[
        {
            "category":"Education",
            "subcategory":"Special Training",
            "type":"Public Place"
        }
    ],
    "sg:phone":"+1 703 860 0091",
    "sg:postcode":"20191",
    "sg:province":"VA",
    "sg:tags":[
        "computer",
        "programing",
        "custom"
    ],
    "wof:name":"Rex Jaeschke",
    "wof:placetype":"venue"
},
  "geometry": {"coordinates":[-77.339032,38.937611],"type":"Point"}
}