{
  "type": "Feature",
  "properties": {
    "addr:full":"503 E Main St Richmond VA 23219",
    "addr:housenumber":"503",
    "addr:postcode":"23219",
    "addr:street":"E Main St",
    "iso:country":"US",
    "sg:address":"503 E Main St",
    "sg:city":"Richmond",
    "sg:classifiers":[
        {
            "category":"Retail",
            "subcategory":"Portrait Studio",
            "type":"Services"
        }
    ],
    "sg:phone":"+1 804 215 9337",
    "sg:postcode":"23219",
    "sg:province":"VA",
    "sg:tags":[
        "photographer",
        "photo"
    ],
    "wof:name":"Dupree's Photography",
    "wof:placetype":"venue"
},
  "geometry": {"coordinates":[-77.439059,37.539778],"type":"Point"}
}