{
  "type": "Feature",
  "properties": {
    "iso:country":"US",
    "sg:address":"17060 Cromwell Pl",
    "sg:city":"King George",
    "sg:classifiers":[
        {
            "category":"Real Estate",
            "subcategory":"Real Estate Operator",
            "type":"Services"
        }
    ],
    "sg:phone":"+1 540 775 0209",
    "sg:postcode":"22485",
    "sg:province":"VA",
    "sg:tags":[
        "building",
        "apartment"
    ],
    "wof:name":"Monmouth Woods Apartments",
    "wof:placetype":"venue"
},
  "geometry": {"coordinates":[-77.050436,38.358244],"type":"Point"}
}