{
  "type": "Feature",
  "properties": {
    "addr:full":"7089 Senn Way Mechanicsville VA 23111",
    "addr:housenumber":"7089",
    "addr:postcode":"23111",
    "addr:street":"Senn Way",
    "iso:country":"US",
    "sg:address":"7089 Senn Way",
    "sg:city":"Mechanicsville",
    "sg:classifiers":[
        {
            "category":"Building & Trades",
            "subcategory":"Construction",
            "type":"Services"
        }
    ],
    "sg:phone":"+1 804 559 3192",
    "sg:postcode":"23111",
    "sg:province":"VA",
    "sg:tags":[
        "transmitting",
        "tower",
        "maintenance"
    ],
    "wof:name":"Carr Enterprises Inc",
    "wof:placetype":"venue"
},
  "geometry": {"coordinates":[-77.36062200000001,37.59295],"type":"Point"}
}