{
  "type": "Feature",
  "properties": {
    "iso:country":"US",
    "sg:address":"10302 Conejo Ln",
    "sg:city":"Oakton",
    "sg:classifiers":[
        {
            "category":"Professional",
            "subcategory":"Art Services",
            "type":"Services"
        }
    ],
    "sg:phone":"+1 703 938 2027",
    "sg:postcode":"22124",
    "sg:province":"VA",
    "sg:tags":[
        "artist"
    ],
    "wof:name":"Agnes Toth Art & Designs",
    "wof:placetype":"venue"
},
  "geometry": {"coordinates":[-77.303926,38.899303],"type":"Point"}
}