{
  "type": "Feature",
  "properties": {
    "addr:full":"2826 Croix Ct Virginia Beach VA 23451",
    "addr:housenumber":"2826",
    "addr:postcode":"23451",
    "addr:street":"Croix Ct",
    "iso:country":"US",
    "sg:address":"2826 Croix Ct",
    "sg:city":"Virginia Beach",
    "sg:classifiers":[
        {
            "category":"Wholesale",
            "subcategory":"Computers",
            "type":"Manufacturing & Wholesale Goods"
        }
    ],
    "sg:phone":"+1 757 481 5198",
    "sg:postcode":"23451",
    "sg:province":"VA",
    "wof:name":"Mobile Computing Assoc",
    "wof:placetype":"venue"
},
  "geometry": {"coordinates":[-76.06755200000001,36.913203],"type":"Point"}
}