{
  "type": "Feature",
  "properties": {
    "addr:full":"1985 E Pembroke Ave Hampton VA 23663",
    "addr:housenumber":"1985",
    "addr:postcode":"23663",
    "addr:street":"E Pembroke Ave",
    "iso:country":"US",
    "sg:address":"1985 E Pembroke Ave",
    "sg:city":"Hampton",
    "sg:classifiers":[
        {
            "category":"Autos & Motor Vehicles",
            "subcategory":"Auto Supplies",
            "type":"Retail Goods"
        }
    ],
    "sg:phone":"+1 757 723 0735",
    "sg:postcode":"23663",
    "sg:province":"VA",
    "sg:tags":[
        "tire"
    ],
    "wof:name":"Tread Quarters Inc",
    "wof:placetype":"venue"
},
  "geometry": {"coordinates":[-76.30667,37.039802],"type":"Point"}
}