{
  "type": "Feature",
  "properties": {
    "addr:full":"15268 Carroll Bridge Rd Smithfield VA 23430",
    "addr:housenumber":"15268",
    "addr:postcode":"23430",
    "addr:street":"Carroll Bridge Rd",
    "iso:country":"US",
    "sg:address":"15268 Carroll Bridge Rd",
    "sg:city":"Smithfield",
    "sg:classifiers":[
        {
            "category":"Manufacturing",
            "subcategory":"Signs",
            "type":"Manufacturing & Wholesale Goods"
        }
    ],
    "sg:phone":"+1 757 357 5552",
    "sg:postcode":"23430",
    "sg:province":"VA",
    "sg:tags":[
        "specialty",
        "mfg"
    ],
    "wof:name":"Bay Area Signs",
    "wof:placetype":"venue"
},
  "geometry": {"coordinates":[-76.655878,36.929976],"type":"Point"}
}