{
  "type": "Feature",
  "properties": {
    "addr:full":"2900 Clarendon Blvd Arlington VA 22201",
    "addr:housenumber":"2900",
    "addr:postcode":"22201",
    "addr:street":"Clarendon Blvd",
    "iso:country":"US",
    "sg:address":"2900 Clarendon Blvd",
    "sg:city":"Arlington",
    "sg:classifiers":[
        {
            "category":"Parking",
            "type":"Transportation"
        },
        {
            "category":"Parking",
            "subcategory":"Garage",
            "type":"Transportation"
        }
    ],
    "sg:phone":"+1 703 812 4586",
    "sg:postcode":"22201",
    "sg:province":"VA",
    "sg:tags":[
        "attendant",
        "lot"
    ],
    "wof:name":"Colonial Parking Inc",
    "wof:placetype":"venue"
},
  "geometry": {"coordinates":[-77.09311700000001,38.887901],"type":"Point"}
}