{
  "type": "Feature",
  "properties": {
    "iso:country":"US",
    "sg:address":"819 James Madison Hwy",
    "sg:city":"Warrenton",
    "sg:classifiers":[
        {
            "category":"Freight",
            "type":"Transportation"
        }
    ],
    "sg:phone":"+1 540 349 9394",
    "sg:postcode":"20186",
    "sg:province":"VA",
    "sg:tags":[
        "equipment",
        "move",
        "computer"
    ],
    "wof:name":"Piedmont Trans Tech",
    "wof:placetype":"venue"
},
  "geometry": {"coordinates":[-77.787648,38.69698],"type":"Point"}
}