{
  "type": "Feature",
  "properties": {
    "addr:full":"5688 Brooks Mill Rd Wirtz VA 24184",
    "addr:housenumber":"5688",
    "addr:postcode":"24184",
    "addr:street":"Brooks Mill Rd",
    "iso:country":"US",
    "sg:address":"5688 Brooks Mill Rd",
    "sg:city":"Wirtz",
    "sg:classifiers":[
        {
            "category":"Autos & Motor Vehicles",
            "subcategory":"Automobile Sales",
            "type":"Retail Goods"
        }
    ],
    "sg:phone":"+1 540 721 3225",
    "sg:postcode":"24184",
    "sg:province":"VA",
    "sg:tags":[
        "used"
    ],
    "wof:name":"Als Auto Sales",
    "wof:placetype":"venue"
},
  "geometry": {"coordinates":[-79.758859,37.056777],"type":"Point"}
}