{
  "type": "Feature",
  "properties": {
    "iso:country":"US",
    "sg:address":"3322 Fendall Ave",
    "sg:city":"Richmond",
    "sg:classifiers":[
        {
            "category":"Organizations",
            "subcategory":"Religious Organization",
            "type":"Services"
        }
    ],
    "sg:phone":"+1 804 329 1769",
    "sg:postcode":"23222",
    "sg:province":"VA",
    "wof:name":"Highland Park United Methodist",
    "wof:placetype":"venue"
},
  "geometry": {"coordinates":[-77.435812,37.578664],"type":"Point"}
}