{
  "type": "Feature",
  "properties": {
    "iso:country":"US",
    "sg:address":"8230 Old Courthouse Rd",
    "sg:city":"Vienna",
    "sg:classifiers":[
        {
            "category":"Professional",
            "type":"Services"
        }
    ],
    "sg:phone":"+1 703 242 8773",
    "sg:postcode":"22182",
    "sg:province":"VA",
    "wof:name":"Green Oak LLC",
    "wof:placetype":"venue"
},
  "geometry": {"coordinates":[-77.231015,38.913726],"type":"Point"}
}