{
  "type": "Feature",
  "properties": {
    "addr:full":"8264 Powhickery Dr Mechanicsville VA 23116",
    "addr:housenumber":"8264",
    "addr:postcode":"23116",
    "addr:street":"Powhickery Dr",
    "iso:country":"US",
    "sg:address":"8264 Powhickery Dr",
    "sg:city":"Mechanicsville",
    "sg:classifiers":[
        {
            "category":"Wholesale",
            "subcategory":"Chemicals & Plastics",
            "type":"Manufacturing & Wholesale Goods"
        }
    ],
    "sg:phone":"+1 804 788 6178",
    "sg:postcode":"23116",
    "sg:province":"VA",
    "sg:tags":[
        "organic"
    ],
    "wof:name":"Ethyl Corporation",
    "wof:placetype":"venue"
},
  "geometry": {"coordinates":[-77.388603,37.666712],"type":"Point"}
}