{
  "type": "Feature",
  "properties": {
    "addr:full":"3900 Arcadia Ln Richmond VA 23233",
    "addr:housenumber":"3900",
    "addr:postcode":"23233",
    "addr:street":"Arcadia Ln",
    "iso:country":"US",
    "sg:address":"3900 Arcadia Ln",
    "sg:city":"Richmond",
    "sg:classifiers":[
        {
            "category":"Real Estate",
            "subcategory":"Real Estate Operator",
            "type":"Services"
        }
    ],
    "sg:phone":"+1 804 346 8724",
    "sg:postcode":"23233",
    "sg:province":"VA",
    "sg:tags":[
        "apartment"
    ],
    "wof:name":"Dominion West End",
    "wof:placetype":"venue"
},
  "geometry": {"coordinates":[-77.499044,37.612558],"type":"Point"}
}