{
  "type": "Feature",
  "properties": {
    "iso:country":"US",
    "sg:address":"308 W Main St",
    "sg:city":"Appalachia",
    "sg:classifiers":[
        {
            "category":"Utilities",
            "subcategory":"Cable",
            "type":"Services"
        }
    ],
    "sg:phone":"+1 276 565 2095",
    "sg:postcode":"24216",
    "sg:province":"VA",
    "sg:tags":[
        "television"
    ],
    "wof:name":"Adelphia",
    "wof:placetype":"venue"
},
  "geometry": {"coordinates":[-82.782561,36.905253],"type":"Point"}
}