{
  "type": "Feature",
  "properties": {
    "addr:full":"290 Hawksbill Ave Stanley VA 22851",
    "addr:housenumber":"290",
    "addr:postcode":"22851",
    "addr:street":"Hawksbill Ave",
    "iso:country":"US",
    "sg:address":"290 Hawksbill Ave",
    "sg:city":"Stanley",
    "sg:classifiers":[
        {
            "category":"Farming",
            "subcategory":"Livestock Farm",
            "type":"Manufacturing & Wholesale Goods"
        }
    ],
    "sg:phone":"+1 540 778 3061",
    "sg:postcode":"22851",
    "sg:province":"VA",
    "sg:tags":[
        "beef",
        "feedlot",
        "cattle"
    ],
    "wof:name":"Ike Turner",
    "wof:placetype":"venue"
},
  "geometry": {"coordinates":[-78.481059,38.598554],"type":"Point"}
}