{
  "type": "Feature",
  "properties": {
    "addr:full":"501 Central Dr Virginia Beach VA 23454",
    "addr:housenumber":"501",
    "addr:postcode":"23454",
    "addr:street":"Central Dr",
    "iso:country":"US",
    "sg:address":"501 Central Dr",
    "sg:city":"Virginia Beach",
    "sg:classifiers":[
        {
            "category":"Home & Garden",
            "subcategory":"Building Materials",
            "type":"Retail Goods"
        }
    ],
    "sg:phone":"+1 757 340 9000",
    "sg:postcode":"23454",
    "sg:province":"VA",
    "sg:tags":[
        "house"
    ],
    "sg:website":"www.paramountbuilders.com",
    "wof:name":"Paramount Builders Inc",
    "wof:placetype":"venue"
},
  "geometry": {"coordinates":[-76.05221899999999,36.824127],"type":"Point"}
}