{
  "type": "Feature",
  "properties": {
    "addr:full":"44 Kingston Dr Daleville VA 24083",
    "addr:housenumber":"44",
    "addr:postcode":"24083",
    "addr:street":"Kingston Dr",
    "iso:country":"US",
    "sg:address":"44 Kingston Dr",
    "sg:city":"Daleville",
    "sg:classifiers":[
        {
            "category":"Professional",
            "subcategory":"Business Services",
            "type":"Services"
        },
        {
            "category":"Professional",
            "subcategory":"Advertising",
            "type":"Services"
        }
    ],
    "sg:phone":"+1 540 966 0220",
    "sg:postcode":"24083",
    "sg:province":"VA",
    "sg:tags":[
        "mailing",
        "shipping"
    ],
    "wof:name":"UPS Store The",
    "wof:placetype":"venue"
},
  "geometry": {"coordinates":[-79.909916,37.396259],"type":"Point"}
}