{
  "type": "Feature",
  "properties": {
    "addr:full":"5441 Dale Blvd Woodbridge VA 22193",
    "addr:housenumber":"5441",
    "addr:postcode":"22193",
    "addr:street":"Dale Blvd",
    "iso:country":"US",
    "sg:address":"5441 Dale Blvd",
    "sg:city":"Woodbridge",
    "sg:classifiers":[
        {
            "category":"Shopping",
            "subcategory":"Discount & Variety Stores",
            "type":"Retail Goods"
        }
    ],
    "sg:phone":"+1 703 580 0165",
    "sg:postcode":"22193",
    "sg:province":"VA",
    "wof:name":"Dollar Wonder Inc",
    "wof:placetype":"venue"
},
  "geometry": {"coordinates":[-77.369888,38.659362],"type":"Point"}
}