{
  "type": "Feature",
  "properties": {
    "addr:full":"2125 Ivy Rd Charlottesville VA 22903",
    "addr:housenumber":"2125",
    "addr:postcode":"22903",
    "addr:street":"Ivy Rd",
    "iso:country":"US",
    "sg:address":"2125 Ivy Rd",
    "sg:city":"Charlottesville",
    "sg:classifiers":[
        {
            "category":"Restaurant",
            "type":"Food & Drink"
        }
    ],
    "sg:menulink":"http://www.allmenus.com/va/charlottesville/17979-pizza-hut/menu/",
    "sg:phone":"+1 434 979 5588",
    "sg:postcode":"22903",
    "sg:province":"VA",
    "sg:tags":[
        "american",
        "pizza"
    ],
    "wof:name":"Pizza Hut",
    "wof:placetype":"venue"
},
  "geometry": {"coordinates":[-78.513789,38.043957],"type":"Point"}
}