{
  "type": "Feature",
  "properties": {
    "addr:full":"106 Bryant Rd Lynchburg VA 24502",
    "addr:housenumber":"106",
    "addr:postcode":"24502",
    "addr:street":"Bryant Rd",
    "iso:country":"US",
    "sg:address":"106 Bryant Rd",
    "sg:city":"Lynchburg",
    "sg:classifiers":[
        {
            "category":"Wholesale",
            "subcategory":"Machinery & Supplies",
            "type":"Manufacturing & Wholesale Goods"
        }
    ],
    "sg:phone":"+1 434 239 3777",
    "sg:postcode":"24502",
    "sg:province":"VA",
    "sg:tags":[
        "equipment",
        "safety",
        "clothing"
    ],
    "wof:name":"B N Safety Footwear",
    "wof:placetype":"venue"
},
  "geometry": {"coordinates":[-79.239384,37.388062],"type":"Point"}
}