{
  "type": "Feature",
  "properties": {
    "addr:full":"21296 Mandalay Ln Abingdon VA 24211",
    "addr:housenumber":"21296",
    "addr:postcode":"24211",
    "addr:street":"Mandalay Ln",
    "iso:country":"US",
    "sg:address":"21296 Mandalay Ln",
    "sg:city":"Abingdon",
    "sg:classifiers":[
        {
            "category":"Food & Beverages",
            "subcategory":"Groceries & Convenience Stores",
            "type":"Retail Goods"
        }
    ],
    "sg:phone":"+1 276 623 0245",
    "sg:postcode":"24211",
    "sg:province":"VA",
    "wof:name":"A & M Express Inc",
    "wof:placetype":"venue"
},
  "geometry": {"coordinates":[-81.946938,36.647967],"type":"Point"}
}