{
  "type": "Feature",
  "properties": {
    "addr:full":"280 Donovan Rd Stanley VA 22851",
    "addr:housenumber":"280",
    "addr:postcode":"22851",
    "addr:street":"Donovan Rd",
    "iso:country":"US",
    "sg:address":"280 Donovan Rd",
    "sg:city":"Stanley",
    "sg:classifiers":[
        {
            "category":"Manufacturing",
            "subcategory":"Building Materials",
            "type":"Manufacturing & Wholesale Goods"
        }
    ],
    "sg:phone":"+1 540 778 2211",
    "sg:postcode":"22851",
    "sg:province":"VA",
    "wof:name":"Masonite Intl",
    "wof:placetype":"venue"
},
  "geometry": {"coordinates":[-78.510098,38.568014],"type":"Point"}
}