{
  "type": "Feature",
  "properties": {
    "addr:full":"7820 Marconi Ct Springfield VA 22153",
    "addr:housenumber":"7820",
    "addr:postcode":"22153",
    "addr:street":"Marconi Ct",
    "iso:country":"US",
    "sg:address":"7820 Marconi Ct",
    "sg:city":"Springfield",
    "sg:classifiers":[
        {
            "category":"Shopping",
            "subcategory":"Gifts & Souvenirs",
            "type":"Retail Goods"
        }
    ],
    "sg:phone":"+1 703 593 4887",
    "sg:postcode":"22153",
    "sg:province":"VA",
    "sg:tags":[
        "instrument"
    ],
    "wof:name":"Musiclink4ucom",
    "wof:placetype":"venue"
},
  "geometry": {"coordinates":[-77.214628,38.726827],"type":"Point"}
}