{
  "type": "Feature",
  "properties": {
    "addr:full":"10621 Braddock Rd Fairfax VA 22032",
    "addr:housenumber":"10621",
    "addr:postcode":"22032",
    "addr:street":"Braddock Rd",
    "iso:country":"US",
    "sg:address":"10621 Braddock Rd",
    "sg:city":"Fairfax",
    "sg:classifiers":[
        {
            "category":"Insurance",
            "subcategory":"Insurance Agent",
            "type":"Services"
        }
    ],
    "sg:phone":"+1 703 385 1771",
    "sg:postcode":"22032",
    "sg:province":"VA",
    "wof:name":"State Farm Insurance",
    "wof:placetype":"venue"
},
  "geometry": {"coordinates":[-77.315792,38.827096],"type":"Point"}
}