{
  "type": "Feature",
  "properties": {
    "iso:country":"US",
    "sg:address":"16017 Meridian Ave",
    "sg:city":"Chester",
    "sg:classifiers":[
        {
            "category":"Professional",
            "type":"Services"
        }
    ],
    "sg:phone":"+1 804 520 8428",
    "sg:postcode":"23831",
    "sg:province":"VA",
    "wof:name":"Mainly Mosaics",
    "wof:placetype":"venue"
},
  "geometry": {"coordinates":[-77.421346,37.300361],"type":"Point"}
}