{
  "type": "Feature",
  "properties": {
    "addr:full":"2111 Colonial Ave Norfolk VA 23517",
    "addr:housenumber":"2111",
    "addr:postcode":"23517",
    "addr:street":"Colonial Ave",
    "iso:country":"US",
    "sg:address":"2111 Colonial Ave",
    "sg:city":"Norfolk",
    "sg:classifiers":[
        {
            "category":"Retail",
            "subcategory":"Repair Shop",
            "type":"Services"
        }
    ],
    "sg:phone":"+1 757 625 2128",
    "sg:postcode":"23517",
    "sg:province":"VA",
    "wof:name":"Strip Joint Inc",
    "wof:placetype":"venue"
},
  "geometry": {"coordinates":[-76.291642,36.869707],"type":"Point"}
}