{
  "type": "Feature",
  "properties": {
    "addr:full":"2540 Holly Point Blvd Chesapeake VA 23325",
    "addr:housenumber":"2540",
    "addr:postcode":"23325",
    "addr:street":"Holly Point Blvd",
    "iso:country":"US",
    "sg:address":"2540 Holly Point Blvd",
    "sg:city":"Chesapeake",
    "sg:classifiers":[
        {
            "category":"Real Estate",
            "subcategory":"Real Estate Services",
            "type":"Services"
        }
    ],
    "sg:phone":"+1 866 427 6217",
    "sg:postcode":"23325",
    "sg:province":"VA",
    "sg:tags":[
        "apartment",
        "management",
        "rental",
        "finder"
    ],
    "sg:website":"http://virginiabeach.citysearch.com/profile/external/10581347/chesapeake_va/holly_point.html?publisher=yellowpages&reference_id=1&placement=ypwebsitemip",
    "wof:name":"Holly Point",
    "wof:placetype":"venue"
},
  "geometry": {"coordinates":[-76.253128,36.801838],"type":"Point"}
}