{
  "type": "Feature",
  "properties": {
    "addr:full":"4809 S Valley Pike Harrisonburg VA 22801",
    "addr:housenumber":"4809",
    "addr:postcode":"22801",
    "addr:street":"S Valley Pike",
    "iso:country":"US",
    "sg:address":"4809 S Valley Pike",
    "sg:city":"Harrisonburg",
    "sg:classifiers":[
        {
            "category":"Professional",
            "type":"Services"
        }
    ],
    "sg:phone":"+1 540 432 6446",
    "sg:postcode":"22801",
    "sg:province":"VA",
    "sg:tags":[
        "establishment"
    ],
    "wof:name":"Wastewater Solutions LLC",
    "wof:placetype":"venue"
},
  "geometry": {"coordinates":[-78.91936699999999,38.389647],"type":"Point"}
}