{
  "type": "Feature",
  "properties": {
    "addr:full":"14700 Midship Woods Ct Chesterfield VA 23832",
    "addr:postcode":"14700;23832",
    "addr:street":"Midship Woods Ct",
    "iso:country":"US",
    "sg:address":"14700 Midship Woods Ct",
    "sg:city":"Chesterfield",
    "sg:classifiers":[
        {
            "category":"Retail",
            "subcategory":"Animal Services",
            "type":"Services"
        }
    ],
    "sg:phone":"+1 804 739 3386",
    "sg:postcode":"23832",
    "sg:province":"VA",
    "sg:tags":[
        "pet",
        "boarding",
        "sitting"
    ],
    "wof:name":"Luv 'Um & Leave 'Um Pet Sitter",
    "wof:placetype":"venue"
},
  "geometry": {"coordinates":[-77.684652,37.396326],"type":"Point"}
}