{
  "type": "Feature",
  "properties": {
    "addr:full":"253 Monticello Ave Norfolk VA 23510",
    "addr:housenumber":"253",
    "addr:postcode":"23510",
    "addr:street":"Monticello Ave",
    "iso:country":"US",
    "sg:address":"253 Monticello Ave",
    "sg:city":"Norfolk",
    "sg:classifiers":[
        {
            "category":"Utilities",
            "subcategory":"Telephone",
            "type":"Services"
        }
    ],
    "sg:phone":"+1 757 873 4500",
    "sg:postcode":"23510",
    "sg:province":"VA",
    "sg:tags":[
        "wireless",
        "broadband",
        "fixed",
        "communications"
    ],
    "wof:name":"Continental Visinet Broadband",
    "wof:placetype":"venue"
},
  "geometry": {"coordinates":[-76.289749,36.849446],"type":"Point"}
}