{
  "type": "Feature",
  "properties": {
    "iso:country":"US",
    "sg:address":"1415 N George Mason Dr",
    "sg:city":"Arlington",
    "sg:classifiers":[
        {
            "category":"Communications",
            "type":"Services"
        }
    ],
    "sg:phone":"+1 703 525 5139",
    "sg:postcode":"22205",
    "sg:province":"VA",
    "sg:tags":[
        "communication"
    ],
    "wof:name":"River God Productions",
    "wof:placetype":"venue"
},
  "geometry": {"coordinates":[-77.127439,38.885889],"type":"Point"}
}