{
  "type": "Feature",
  "properties": {
    "addr:full":"802 Gilmer Ave NW Roanoke VA 24016",
    "addr:housenumber":"802",
    "addr:postcode":"24016",
    "addr:street":"Gilmer Ave Nw",
    "iso:country":"US",
    "sg:address":"802 Gilmer Ave NW",
    "sg:city":"Roanoke",
    "sg:classifiers":[
        {
            "category":"Food & Beverages",
            "subcategory":"Groceries & Convenience Stores",
            "type":"Retail Goods"
        }
    ],
    "sg:phone":"+1 540 343 1747",
    "sg:postcode":"24016",
    "sg:province":"VA",
    "wof:name":"Mac Matu Grocery",
    "wof:placetype":"venue"
},
  "geometry": {"coordinates":[-79.95246,37.278379],"type":"Point"}
}