{
  "type": "Feature",
  "properties": {
    "iso:country":"US",
    "sg:address":"3251 Darby Rd",
    "sg:city":"Keswick",
    "sg:classifiers":[
        {
            "category":"Real Estate",
            "subcategory":"Real Estate Services",
            "type":"Services"
        }
    ],
    "sg:phone":"+1 434 979 7243",
    "sg:postcode":"22947",
    "sg:province":"VA",
    "sg:tags":[
        "management",
        "property"
    ],
    "wof:name":"Sage Property Management",
    "wof:placetype":"venue"
},
  "geometry": {"coordinates":[-78.385468,38.001179],"type":"Point"}
}