{
  "type": "Feature",
  "properties": {
    "addr:full":"1410 Maple St Hopewell VA 23860",
    "addr:housenumber":"1410",
    "addr:postcode":"23860",
    "addr:street":"Maple St",
    "iso:country":"US",
    "sg:address":"1410 Maple St",
    "sg:city":"Hopewell",
    "sg:classifiers":[
        {
            "category":"Restaurant",
            "type":"Food & Drink"
        }
    ],
    "sg:phone":"+1 804 458 4241",
    "sg:postcode":"23860",
    "sg:province":"VA",
    "sg:tags":[
        "eating"
    ],
    "wof:name":"K&L Barbecue",
    "wof:placetype":"venue"
},
  "geometry": {"coordinates":[-77.297363,37.290862],"type":"Point"}
}