{
  "type": "Feature",
  "properties": {
    "addr:full":"20575 Quarterpath Trace Cir Sterling VA 20165",
    "addr:housenumber":"20575",
    "addr:postcode":"20165",
    "addr:street":"Quarterpath Trace Cir",
    "iso:country":"US",
    "sg:address":"20575 Quarterpath Trace Cir",
    "sg:city":"Sterling",
    "sg:classifiers":[
        {
            "category":"Professional",
            "subcategory":"Management & Consulting",
            "type":"Services"
        }
    ],
    "sg:phone":"+1 703 404 1913",
    "sg:postcode":"20165",
    "sg:province":"VA",
    "wof:name":"Destination Sls Mktg Group Ltd",
    "wof:placetype":"venue"
},
  "geometry": {"coordinates":[-77.368167,39.048218],"type":"Point"}
}