{
  "type": "Feature",
  "properties": {
    "addr:full":"1032 Heatherwood Dr Virginia Beach VA 23455",
    "addr:housenumber":"1032",
    "addr:postcode":"23455",
    "addr:street":"Heatherwood Dr",
    "iso:country":"US",
    "sg:address":"1032 Heatherwood Dr",
    "sg:city":"Virginia Beach",
    "sg:classifiers":[
        {
            "category":"Social Services",
            "type":"Services"
        }
    ],
    "sg:phone":"+1 757 497 2688",
    "sg:postcode":"23455",
    "sg:province":"VA",
    "sg:tags":[
        "youth",
        "organization",
        "center"
    ],
    "sg:website":"www.tidewaterbsa.com",
    "wof:name":"Boy Scouts Of America",
    "wof:placetype":"venue"
},
  "geometry": {"coordinates":[-76.16657600000001,36.870797],"type":"Point"}
}