{
  "type": "Feature",
  "properties": {
    "iso:country":"US",
    "sg:address":"3221 Pineridge Dr",
    "sg:city":"Chesapeake",
    "sg:classifiers":[
        {
            "category":"Organizations",
            "subcategory":"Community Association",
            "type":"Services"
        }
    ],
    "sg:phone":"+1 757 484 2270",
    "sg:postcode":"23321",
    "sg:province":"VA",
    "wof:name":"Merrimac Kiwanis Foundation",
    "wof:placetype":"venue"
},
  "geometry": {"coordinates":[-76.40422100000001,36.854789],"type":"Point"}
}