{
  "type": "Feature",
  "properties": {
    "addr:full":"1124 Pedigo Ln Vinton VA 24179",
    "addr:housenumber":"1124",
    "addr:postcode":"24179",
    "addr:street":"Pedigo Ln",
    "iso:country":"US",
    "sg:address":"1124 Pedigo Ln",
    "sg:city":"Vinton",
    "sg:classifiers":[
        {
            "category":"Professional",
            "subcategory":"Management & Consulting",
            "type":"Services"
        }
    ],
    "sg:phone":"+1 540 890 5542",
    "sg:postcode":"24179",
    "sg:province":"VA",
    "wof:name":"Nabisco",
    "wof:placetype":"venue"
},
  "geometry": {"coordinates":[-79.869544,37.261512],"type":"Point"}
}