{
  "type": "Feature",
  "properties": {
    "addr:full":"580 Lynnhaven Pkwy Virginia Beach VA 23452",
    "addr:housenumber":"580",
    "addr:postcode":"23452",
    "addr:street":"Lynnhaven Pkwy",
    "iso:country":"US",
    "sg:address":"580 Lynnhaven Pkwy",
    "sg:city":"Virginia Beach",
    "sg:classifiers":[
        {
            "category":"Travel",
            "subcategory":"Hotels & Motels",
            "type":"Entertainment"
        }
    ],
    "sg:phone":"+1 757 631 0744",
    "sg:postcode":"23452",
    "sg:province":"VA",
    "sg:website":"www.vsaresorts.com",
    "wof:name":"Vacation Sales Assoc",
    "wof:placetype":"venue"
},
  "geometry": {"coordinates":[-76.06719699999999,36.829615],"type":"Point"}
}