{
  "type": "Feature",
  "properties": {
    "addr:full":"1002 72nd St Newport News VA 23605",
    "addr:housenumber":"1002",
    "addr:postcode":"23605",
    "addr:street":"72Nd St",
    "iso:country":"US",
    "sg:address":"1002 72nd St",
    "sg:city":"Newport News",
    "sg:classifiers":[
        {
            "category":"Building & Trades",
            "subcategory":"Construction",
            "type":"Services"
        }
    ],
    "sg:phone":"+1 757 224 1437",
    "sg:postcode":"23605",
    "sg:province":"VA",
    "sg:tags":[
        "house"
    ],
    "wof:name":"Michael Faherty Construction",
    "wof:placetype":"venue"
},
  "geometry": {"coordinates":[-76.427881,37.016488],"type":"Point"}
}