{
  "type": "Feature",
  "properties": {
    "addr:full":"103 Green Spring Ln Brookneal VA 24528",
    "addr:housenumber":"103",
    "addr:postcode":"24528",
    "addr:street":"Green Spring Ln",
    "iso:country":"US",
    "sg:address":"103 Green Spring Ln",
    "sg:city":"Brookneal",
    "sg:classifiers":[
        {
            "category":"Organizations",
            "subcategory":"Religious Organization",
            "type":"Services"
        }
    ],
    "sg:phone":"+1 434 376 5100",
    "sg:postcode":"24528",
    "sg:province":"VA",
    "sg:tags":[
        "church"
    ],
    "wof:name":"Green Spring Baptist Church",
    "wof:placetype":"venue"
},
  "geometry": {"coordinates":[-78.947675,37.052091],"type":"Point"}
}