{
  "type": "Feature",
  "properties": {
    "iso:country":"US",
    "sg:address":"8901 Jacobs Rd",
    "sg:city":"Chesterfield",
    "sg:classifiers":[
        {
            "category":"Banks & Credit Unions",
            "subcategory":"Financial Services",
            "type":"Services"
        }
    ],
    "sg:phone":"+1 804 745 6042",
    "sg:postcode":"23832",
    "sg:province":"VA",
    "sg:tags":[
        "company",
        "holding"
    ],
    "wof:name":"S&L Holdings",
    "wof:placetype":"venue"
},
  "geometry": {"coordinates":[-77.552036,37.433409],"type":"Point"}
}