{
  "type": "Feature",
  "properties": {
    "iso:country":"US",
    "sg:address":"4701 Kenmore Ave",
    "sg:city":"Alexandria",
    "sg:classifiers":[
        {
            "category":"Building & Trades",
            "subcategory":"Construction",
            "type":"Services"
        }
    ],
    "sg:phone":"+1 703 823 3135",
    "sg:postcode":"22304",
    "sg:province":"VA",
    "sg:tags":[
        "tile",
        "dealer",
        "contractor"
    ],
    "wof:name":"Ceramic Tile & Flooring",
    "wof:placetype":"venue"
},
  "geometry": {"coordinates":[-77.11126,38.828354],"type":"Point"}
}