{
  "type": "Feature",
  "properties": {
    "addr:full":"3183 Back Creek Rd Gore VA 22637",
    "addr:housenumber":"3183",
    "addr:postcode":"22637",
    "addr:street":"Back Creek Rd",
    "iso:country":"US",
    "sg:address":"3183 Back Creek Rd",
    "sg:city":"Gore",
    "sg:classifiers":[
        {
            "category":"Professional",
            "subcategory":"Management & Consulting",
            "type":"Services"
        }
    ],
    "sg:phone":"+1 540 877 2650",
    "sg:postcode":"22637",
    "sg:province":"VA",
    "sg:tags":[
        "business"
    ],
    "wof:name":"J Arthur Webber & Associates",
    "wof:placetype":"venue"
},
  "geometry": {"coordinates":[-78.408512,39.203718],"type":"Point"}
}