{
  "type": "Feature",
  "properties": {
    "addr:full":"4107 Dodds Ridge Dr Richmond VA 23236",
    "addr:housenumber":"4107",
    "addr:postcode":"23236",
    "addr:street":"Dodds Ridge Dr",
    "iso:country":"US",
    "sg:address":"4107 Dodds Ridge Dr",
    "sg:city":"Richmond",
    "sg:classifiers":[
        {
            "category":"Retail",
            "subcategory":"Repair Shop",
            "type":"Services"
        }
    ],
    "sg:phone":"+1 804 283 2959",
    "sg:postcode":"23236",
    "sg:province":"VA",
    "sg:tags":[
        "equipment",
        "for"
    ],
    "wof:name":"T & S Mechanical LLC",
    "wof:placetype":"venue"
},
  "geometry": {"coordinates":[-77.559777,37.444619],"type":"Point"}
}