{
  "type": "Feature",
  "properties": {
    "iso:country":"US",
    "sg:address":"5241 New Kent Hwy",
    "sg:city":"Quinton",
    "sg:classifiers":[
        {
            "category":"Autos & Motor Vehicles",
            "subcategory":"Auto Supplies",
            "type":"Retail Goods"
        },
        {
            "category":"Retail",
            "subcategory":"Auto Repair",
            "type":"Services"
        }
    ],
    "sg:phone":"+1 804 932 4020",
    "sg:postcode":"23141",
    "sg:province":"VA",
    "sg:tags":[
        "tire"
    ],
    "wof:name":"New Kent Tire & Auto",
    "wof:placetype":"venue"
},
  "geometry": {"coordinates":[-77.119422,37.533676],"type":"Point"}
}