{
  "type": "Feature",
  "properties": {
    "iso:country":"US",
    "sg:address":"16 W Chapman St",
    "sg:city":"Alexandria",
    "sg:classifiers":[
        {
            "category":"Professional",
            "subcategory":"Business Services",
            "type":"Services"
        }
    ],
    "sg:phone":"+1 703 836 0151",
    "sg:postcode":"22301",
    "sg:province":"VA",
    "sg:tags":[
        "interior",
        "design"
    ],
    "wof:name":"Farrell Elizabeth",
    "wof:placetype":"venue"
},
  "geometry": {"coordinates":[-77.064453,38.813333],"type":"Point"}
}