{
  "type": "Feature",
  "properties": {
    "addr:full":"929 Meadowcreek Dr Richmond VA 23236",
    "addr:housenumber":"929",
    "addr:postcode":"23236",
    "addr:street":"Meadowcreek Dr",
    "iso:country":"US",
    "sg:address":"929 Meadowcreek Dr",
    "sg:city":"Richmond",
    "sg:classifiers":[
        {
            "category":"Professional",
            "subcategory":"Management & Consulting",
            "type":"Services"
        }
    ],
    "sg:phone":"+1 804 794 1758",
    "sg:postcode":"23236",
    "sg:province":"VA",
    "sg:tags":[
        "party",
        "planning"
    ],
    "wof:name":"Smoketree Community Building",
    "wof:placetype":"venue"
},
  "geometry": {"coordinates":[-77.624982,37.478961],"type":"Point"}
}