{
  "type": "Feature",
  "properties": {
    "iso:country":"US",
    "sg:address":"857 Shawnee Rd",
    "sg:city":"Waynesboro",
    "sg:classifiers":[
        {
            "category":"Professional",
            "subcategory":"Detective & Security Services",
            "type":"Services"
        }
    ],
    "sg:phone":"+1 540 949 0133",
    "sg:postcode":"22980",
    "sg:province":"VA",
    "sg:tags":[
        "background"
    ],
    "wof:name":"Robert F Herrmann",
    "wof:placetype":"venue"
},
  "geometry": {"coordinates":[-78.91743700000001,38.066811],"type":"Point"}
}