{
  "type": "Feature",
  "properties": {
    "addr:full":"11900 Martinsville Hwy Danville VA 24541",
    "addr:housenumber":"11900",
    "addr:postcode":"24541",
    "addr:street":"Martinsville Hwy",
    "iso:country":"US",
    "sg:address":"11900 Martinsville Hwy",
    "sg:city":"Danville",
    "sg:classifiers":[
        {
            "category":"Wholesale",
            "subcategory":"Motor Vehicles",
            "type":"Manufacturing & Wholesale Goods"
        }
    ],
    "sg:phone":"+1 434 685 4106",
    "sg:postcode":"24541",
    "sg:province":"VA",
    "sg:tags":[
        "automobile",
        "truck",
        "broker"
    ],
    "wof:name":"Eastcoast Auto Brokers",
    "wof:placetype":"venue"
},
  "geometry": {"coordinates":[-79.588945,36.614627],"type":"Point"}
}