{
  "type": "Feature",
  "properties": {
    "iso:country":"US",
    "sg:address":"3025 Peters Creek Rd NW",
    "sg:city":"Roanoke",
    "sg:classifiers":[
        {
            "category":"Organizations",
            "subcategory":"Religious Organization",
            "type":"Services"
        }
    ],
    "sg:phone":"+1 540 966 3726",
    "sg:postcode":"24019",
    "sg:province":"VA",
    "wof:name":"Calvary Tabernacle",
    "wof:placetype":"venue"
},
  "geometry": {"coordinates":[-80.001296,37.318954],"type":"Point"}
}