{
  "type": "Feature",
  "properties": {
    "iso:country":"US",
    "sg:address":"1805 Monument Ave",
    "sg:city":"Richmond",
    "sg:classifiers":[
        {
            "category":"Health Services",
            "subcategory":"Doctor",
            "type":"Services"
        },
        {
            "category":"Personal",
            "subcategory":"Beauty Salon",
            "type":"Services"
        },
        {
            "category":"Personal",
            "subcategory":"Hair Removal",
            "type":"Services"
        }
    ],
    "sg:phone":"+1 804 254 5774",
    "sg:postcode":"23220",
    "sg:province":"VA",
    "sg:tags":[
        "weaving",
        "replacement"
    ],
    "wof:name":"Long Island Hair Clinic",
    "wof:placetype":"venue"
},
  "geometry": {"coordinates":[-77.460548,37.553921],"type":"Point"}
}