{
  "type": "Feature",
  "properties": {
    "addr:full":"1509 Elm Ave Portsmouth VA 23704",
    "addr:housenumber":"1509",
    "addr:postcode":"23704",
    "addr:street":"Elm Ave",
    "iso:country":"US",
    "sg:address":"1509 Elm Ave",
    "sg:city":"Portsmouth",
    "sg:classifiers":[
        {
            "category":"Banks & Credit Unions",
            "subcategory":"Investment Brokerage",
            "type":"Services"
        }
    ],
    "sg:phone":"+1 757 397 7401",
    "sg:postcode":"23704",
    "sg:province":"VA",
    "sg:tags":[
        "advisory",
        "financial"
    ],
    "wof:name":"Diamond Financial Svc",
    "wof:placetype":"venue"
},
  "geometry": {"coordinates":[-76.31243499999999,36.826772],"type":"Point"}
}