{
  "type": "Feature",
  "properties": {
    "addr:full":"235 E Plume St Norfolk VA 23510",
    "addr:housenumber":"235",
    "addr:postcode":"23510",
    "addr:street":"E Plume St",
    "iso:country":"US",
    "sg:address":"235 E Plume St",
    "sg:city":"Norfolk",
    "sg:classifiers":[
        {
            "category":"Government",
            "subcategory":"Court House",
            "type":"Public Place"
        }
    ],
    "sg:phone":"+1 757 683 8254",
    "sg:postcode":"23510",
    "sg:province":"VA",
    "wof:name":"Virginia Court of Appeals",
    "wof:placetype":"venue"
},
  "geometry": {"coordinates":[-76.29039299999999,36.846854],"type":"Point"}
}