{
  "type": "Feature",
  "properties": {
    "addr:full":"802 Kyle Ave NE Roanoke VA 24012",
    "addr:housenumber":"802",
    "addr:postcode":"24012",
    "addr:street":"Kyle Ave Ne",
    "iso:country":"US",
    "sg:address":"802 Kyle Ave NE",
    "sg:city":"Roanoke",
    "sg:classifiers":[
        {
            "category":"Manufacturing",
            "subcategory":"Paper Products",
            "type":"Manufacturing & Wholesale Goods"
        }
    ],
    "sg:phone":"+1 540 344 3224",
    "sg:postcode":"24012",
    "sg:province":"VA",
    "sg:tags":[
        "box",
        "fiber",
        "mfg"
    ],
    "wof:name":"St Laurent Packaging Corp",
    "wof:placetype":"venue"
},
  "geometry": {"coordinates":[-79.925191,37.290548],"type":"Point"}
}