{
  "type": "Feature",
  "properties": {
    "addr:full":"9131 Centreville Rd Manassas VA 20110",
    "addr:housenumber":"9131",
    "addr:postcode":"20110",
    "addr:street":"Centreville Rd",
    "iso:country":"US",
    "sg:address":"9131 Centreville Rd",
    "sg:city":"Manassas",
    "sg:classifiers":[
        {
            "category":"Manufacturing",
            "subcategory":"Tools & Machinery",
            "type":"Manufacturing & Wholesale Goods"
        }
    ],
    "sg:phone":"+1 703 331 0100",
    "sg:postcode":"20110",
    "sg:province":"VA",
    "sg:tags":[
        "engine",
        "control",
        "mfg",
        "process",
        "ins",
        "equipment",
        "electrical"
    ],
    "sg:website":"www.electromotive-inc.com",
    "wof:name":"Electromotive Inc",
    "wof:placetype":"venue"
},
  "geometry": {"coordinates":[-77.46474000000001,38.756933],"type":"Point"}
}