{
  "type": "Feature",
  "properties": {
    "iso:country":"US",
    "sg:address":"801 Franklin St",
    "sg:city":"Charlottesville",
    "sg:classifiers":[
        {
            "category":"Wholesale",
            "subcategory":"Farm Supplies",
            "type":"Manufacturing & Wholesale Goods"
        }
    ],
    "sg:phone":"+1 434 295 4551",
    "sg:postcode":"22902",
    "sg:province":"VA",
    "sg:tags":[
        "auction",
        "livestock",
        "market"
    ],
    "wof:name":"Charlottesville Livestock Mrkt",
    "wof:placetype":"venue"
},
  "geometry": {"coordinates":[-78.466928,38.01836],"type":"Point"}
}