{
  "type": "Feature",
  "properties": {
    "iso:country":"US",
    "sg:address":"9125 W Broad St",
    "sg:city":"Richmond",
    "sg:classifiers":[
        {
            "category":"Shopping",
            "subcategory":"Clothing, Apparel, & Fashions",
            "type":"Retail Goods"
        }
    ],
    "sg:phone":"+1 804 273 6419",
    "sg:postcode":"23294",
    "sg:province":"VA",
    "sg:tags":[
        "maternity",
        "wear"
    ],
    "wof:name":"Mothers Work",
    "wof:placetype":"venue"
},
  "geometry": {"coordinates":[-77.550557,37.636524],"type":"Point"}
}