{
  "type": "Feature",
  "properties": {
    "addr:full":"4501 Fairfax Dr Arlington VA 22203",
    "addr:housenumber":"4501",
    "addr:postcode":"22203",
    "addr:street":"Fairfax Dr",
    "iso:country":"US",
    "sg:address":"4501 Fairfax Dr",
    "sg:city":"Arlington",
    "sg:classifiers":[
        {
            "category":"Professional",
            "subcategory":"Printing & Photocopies",
            "type":"Services"
        }
    ],
    "sg:phone":"+1 703 875 8017",
    "sg:postcode":"22203",
    "sg:province":"VA",
    "sg:tags":[
        "photocopying"
    ],
    "wof:name":"Kinkos",
    "wof:placetype":"venue"
},
  "geometry": {"coordinates":[-77.115826,38.882079],"type":"Point"}
}