{
  "type": "Feature",
  "properties": {
    "addr:full":"125 Surface Rd Saxe VA 23950",
    "addr:housenumber":"125",
    "addr:postcode":"23950",
    "addr:street":"Surface Rd",
    "iso:country":"US",
    "sg:address":"125 Surface Rd",
    "sg:city":"Saxe",
    "sg:classifiers":[
        {
            "category":"Professional",
            "subcategory":"Business Services",
            "type":"Services"
        }
    ],
    "sg:phone":"+1 434 454 7167",
    "sg:postcode":"23950",
    "sg:province":"VA",
    "sg:tags":[
        "legal",
        "mfg"
    ],
    "wof:name":"Public Service Center & Pdts",
    "wof:placetype":"venue"
},
  "geometry": {"coordinates":[-78.094731,36.756736],"type":"Point"}
}