{
  "type": "Feature",
  "properties": {
    "iso:country":"US",
    "sg:address":"19018 Woodsons Mill Rd",
    "sg:city":"Beaverdam",
    "sg:classifiers":[
        {
            "category":"Professional",
            "type":"Services"
        }
    ],
    "sg:phone":"+1 804 449 6158",
    "sg:postcode":"23015",
    "sg:province":"VA",
    "sg:tags":[
        "establishment"
    ],
    "wof:name":"Beaver Dam Depot",
    "wof:placetype":"venue"
},
  "geometry": {"coordinates":[-77.695986,37.922872],"type":"Point"}
}