{
  "type": "Feature",
  "properties": {
    "addr:full":"12007 Bay Colony Ct Chesterfield VA 23838",
    "addr:housenumber":"12007",
    "addr:postcode":"23838",
    "addr:street":"Bay Colony Ct",
    "iso:country":"US",
    "sg:address":"12007 Bay Colony Ct",
    "sg:city":"Chesterfield",
    "sg:classifiers":[
        {
            "category":"Professional",
            "subcategory":"Accounting & Tax Preparation",
            "type":"Services"
        }
    ],
    "sg:phone":"+1 804 739 9819",
    "sg:postcode":"23838",
    "sg:province":"VA",
    "sg:tags":[
        "accountant"
    ],
    "wof:name":"C & D Accounting & Tax Svc",
    "wof:placetype":"venue"
},
  "geometry": {"coordinates":[-77.672363,37.338585],"type":"Point"}
}