{
  "type": "Feature",
  "properties": {
    "addr:full":"569 Central Dr Virginia Beach VA 23454",
    "addr:housenumber":"569",
    "addr:postcode":"23454",
    "addr:street":"Central Dr",
    "iso:country":"US",
    "sg:address":"569 Central Dr",
    "sg:city":"Virginia Beach",
    "sg:classifiers":[
        {
            "category":"Building & Trades",
            "subcategory":"Construction",
            "type":"Services"
        }
    ],
    "sg:phone":"+1 757 216 7193",
    "sg:postcode":"23454",
    "sg:province":"VA",
    "sg:tags":[
        "steel",
        "fabrication",
        "welding"
    ],
    "wof:name":"Major Steel Building Inc",
    "wof:placetype":"venue"
},
  "geometry": {"coordinates":[-76.060372,36.822437],"type":"Point"}
}