{
  "type": "Feature",
  "properties": {
    "iso:country":"US",
    "sg:address":"1971 Ashley Ln SW",
    "sg:city":"Roanoke",
    "sg:classifiers":[
        {
            "category":"Organizations",
            "subcategory":"Community Association",
            "type":"Services"
        }
    ],
    "sg:phone":"+1 540 725 8731",
    "sg:postcode":"24018",
    "sg:province":"VA",
    "wof:name":"Optimist International",
    "wof:placetype":"venue"
},
  "geometry": {"coordinates":[-80.02964799999999,37.247775],"type":"Point"}
}