{
  "type": "Feature",
  "properties": {
    "addr:full":"6931 Lakeside Ave Richmond VA 23228",
    "addr:housenumber":"6931",
    "addr:postcode":"23228",
    "addr:street":"Lakeside Ave",
    "iso:country":"US",
    "sg:address":"6931 Lakeside Ave",
    "sg:city":"Richmond",
    "sg:classifiers":[
        {
            "category":"Personal",
            "subcategory":"Barber",
            "type":"Services"
        }
    ],
    "sg:phone":"+1 804 262 6993",
    "sg:postcode":"23228",
    "sg:province":"VA",
    "wof:name":"Community Barber Shop",
    "wof:placetype":"venue"
},
  "geometry": {"coordinates":[-77.470708,37.616423],"type":"Point"}
}