{
  "type": "Feature",
  "properties": {
    "addr:full":"838 W 40th St Norfolk VA 23508",
    "addr:housenumber":"838",
    "addr:postcode":"23508",
    "addr:street":"W 40Th St",
    "iso:country":"US",
    "sg:address":"838 W 40th St",
    "sg:city":"Norfolk",
    "sg:classifiers":[
        {
            "category":"Home & Garden",
            "subcategory":"Furniture",
            "type":"Retail Goods"
        }
    ],
    "sg:phone":"+1 757 423 4246",
    "sg:postcode":"23508",
    "sg:province":"VA",
    "sg:tags":[
        "equipment",
        "kitchen",
        "cabinet"
    ],
    "wof:name":"Hahn's Cabinets",
    "wof:placetype":"venue"
},
  "geometry": {"coordinates":[-76.297078,36.881515],"type":"Point"}
}