{
  "type": "Feature",
  "properties": {
    "iso:country":"US",
    "sg:address":"4920 Cleveland St",
    "sg:city":"Virginia Beach",
    "sg:classifiers":[
        {
            "category":"Home & Garden",
            "subcategory":"Building Materials",
            "type":"Retail Goods"
        },
        {
            "category":"Shopping",
            "type":"Retail Goods"
        }
    ],
    "sg:phone":"+1 757 473 1683",
    "sg:postcode":"23462",
    "sg:province":"VA",
    "sg:tags":[
        "plumbing",
        "fixture",
        "merchandise",
        "supply"
    ],
    "wof:name":"Comet Plumbing",
    "wof:placetype":"venue"
},
  "geometry": {"coordinates":[-76.14675699999999,36.842019],"type":"Point"}
}