{
  "type": "Feature",
  "properties": {
    "addr:full":"1214 Athens Ave Richmond VA 23227",
    "addr:housenumber":"1214",
    "addr:postcode":"23227",
    "addr:street":"Athens Ave",
    "iso:country":"US",
    "sg:address":"1214 Athens Ave",
    "sg:city":"Richmond",
    "sg:classifiers":[
        {
            "category":"Building & Trades",
            "subcategory":"Electrical",
            "type":"Services"
        }
    ],
    "sg:phone":"+1 804 672 8933",
    "sg:postcode":"23227",
    "sg:province":"VA",
    "sg:tags":[
        "electrical",
        "contractor"
    ],
    "wof:name":"Bon Air Electrical",
    "wof:placetype":"venue"
},
  "geometry": {"coordinates":[-77.462919,37.637827],"type":"Point"}
}