{
  "type": "Feature",
  "properties": {
    "addr:full":"1232 Lee Hwy Roanoke VA 24019",
    "addr:housenumber":"1232",
    "addr:postcode":"24019",
    "addr:street":"Lee Hwy",
    "iso:country":"US",
    "sg:address":"1232 Lee Hwy",
    "sg:city":"Roanoke",
    "sg:classifiers":[
        {
            "category":"Retail",
            "subcategory":"Repair Shop",
            "type":"Services"
        }
    ],
    "sg:phone":"+1 540 966 1010",
    "sg:postcode":"24019",
    "sg:province":"VA",
    "sg:tags":[
        "equipment"
    ],
    "wof:name":"Eastern Sales & Equipment Svc",
    "wof:placetype":"venue"
},
  "geometry": {"coordinates":[-79.911489,37.366729],"type":"Point"}
}