{
  "type": "Feature",
  "properties": {
    "iso:country":"US",
    "sg:address":"12468 Warwick Blvd",
    "sg:city":"Newport News",
    "sg:classifiers":[
        {
            "category":"Shopping",
            "subcategory":"Used Merchandise",
            "type":"Retail Goods"
        }
    ],
    "sg:phone":"+1 757 595 6789",
    "sg:postcode":"23606",
    "sg:province":"VA",
    "sg:tags":[
        "antique"
    ],
    "wof:name":"A Antiques & Estate Sales",
    "wof:placetype":"venue"
},
  "geometry": {"coordinates":[-76.49298899999999,37.070685],"type":"Point"}
}