{
  "type": "Feature",
  "properties": {
    "iso:country":"US",
    "sg:address":"6503 Wheat Mill Way",
    "sg:city":"Centreville",
    "sg:classifiers":[
        {
            "category":"Insurance",
            "subcategory":"Insurance Agent",
            "type":"Services"
        }
    ],
    "sg:phone":"+1 703 266 1133",
    "sg:postcode":"20121",
    "sg:province":"VA",
    "wof:name":"Allstate Insurance",
    "wof:placetype":"venue"
},
  "geometry": {"coordinates":[-77.442188,38.823305],"type":"Point"}
}