{
  "type": "Feature",
  "properties": {
    "addr:full":"5432 White Oak Cir Sandston VA 23150",
    "addr:housenumber":"5432",
    "addr:postcode":"23150",
    "addr:street":"White Oak Cir",
    "iso:country":"US",
    "sg:address":"5432 White Oak Cir",
    "sg:city":"Sandston",
    "sg:classifiers":[
        {
            "category":"Freight",
            "type":"Transportation"
        }
    ],
    "sg:phone":"+1 804 326 0932",
    "sg:postcode":"23150",
    "sg:province":"VA",
    "sg:tags":[
        "delivery"
    ],
    "wof:name":"D & M Delivery",
    "wof:placetype":"venue"
},
  "geometry": {"coordinates":[-77.191491,37.485024],"type":"Point"}
}