{
  "type": "Feature",
  "properties": {
    "iso:country":"US",
    "sg:address":"316 F St",
    "sg:city":"Arlington",
    "sg:classifiers":[
        {
            "category":"Health Services",
            "subcategory":"Doctor",
            "type":"Services"
        }
    ],
    "sg:phone":"+1 202 543 7979",
    "sg:postcode":"22201",
    "sg:province":"VA",
    "wof:name":"American Vaccine Centers",
    "wof:placetype":"venue"
},
  "geometry": {"coordinates":[-77.015349,38.897331],"type":"Point"}
}