{
  "type": "Feature",
  "properties": {
    "iso:country":"US",
    "sg:address":"4709 Belfield Ter",
    "sg:city":"Richmond",
    "sg:classifiers":[
        {
            "category":"Professional",
            "subcategory":"Business Services",
            "type":"Services"
        }
    ],
    "sg:phone":"+1 804 271 2491",
    "sg:postcode":"23237",
    "sg:province":"VA",
    "wof:name":"Wmg Assoc Inc",
    "wof:placetype":"venue"
},
  "geometry": {"coordinates":[-77.482704,37.415926],"type":"Point"}
}