{
  "type": "Feature",
  "properties": {
    "addr:full":"11635 W Broad St Richmond VA 23233",
    "addr:housenumber":"11635",
    "addr:postcode":"23233",
    "addr:street":"W Broad St",
    "iso:country":"US",
    "sg:address":"11635 W Broad St",
    "sg:city":"Richmond",
    "sg:classifiers":[
        {
            "category":"Shopping",
            "subcategory":"Gifts & Souvenirs",
            "type":"Retail Goods"
        }
    ],
    "sg:phone":"+1 804 364 8490",
    "sg:postcode":"23233",
    "sg:province":"VA",
    "wof:name":"J Fenton Gifts",
    "wof:placetype":"venue"
},
  "geometry": {"coordinates":[-77.61752,37.652347],"type":"Point"}
}