{
  "type": "Feature",
  "properties": {
    "iso:country":"US",
    "sg:address":"715 Piney Forest Rd",
    "sg:city":"Danville",
    "sg:classifiers":[
        {
            "category":"Building & Trades",
            "subcategory":"Equipment Rental",
            "type":"Services"
        }
    ],
    "sg:phone":"+1 434 792 2790",
    "sg:postcode":"24540",
    "sg:province":"VA",
    "sg:tags":[
        "leasing",
        "furniture"
    ],
    "wof:name":"Aarons Sales & Lease Ownership",
    "wof:placetype":"venue"
},
  "geometry": {"coordinates":[-79.405727,36.613773],"type":"Point"}
}