{
  "type": "Feature",
  "properties": {
    "addr:full":"20200 Sheffield Pl Petersburg VA 23803",
    "addr:housenumber":"20200",
    "addr:postcode":"23803",
    "addr:street":"Sheffield Pl",
    "iso:country":"US",
    "sg:address":"20200 Sheffield Pl",
    "sg:city":"Petersburg",
    "sg:classifiers":[
        {
            "category":"Real Estate",
            "subcategory":"Real Estate Agent",
            "type":"Services"
        }
    ],
    "sg:phone":"+1 804 526 5374",
    "sg:postcode":"23803",
    "sg:province":"VA",
    "wof:name":"Doris Mason",
    "wof:placetype":"venue"
},
  "geometry": {"coordinates":[-77.421487,37.243417],"type":"Point"}
}