{
  "type": "Feature",
  "properties": {
    "addr:full":"328 Alleghany Ave Lynchburg VA 24501",
    "addr:housenumber":"328",
    "addr:postcode":"24501",
    "addr:street":"Alleghany Ave",
    "iso:country":"US",
    "sg:address":"328 Alleghany Ave",
    "sg:city":"Lynchburg",
    "sg:classifiers":[
        {
            "category":"Building & Trades",
            "subcategory":"Construction",
            "type":"Services"
        }
    ],
    "sg:phone":"+1 434 847 6258",
    "sg:postcode":"24501",
    "sg:province":"VA",
    "sg:tags":[
        "hanging",
        "contractor"
    ],
    "wof:name":"D L Bryant",
    "wof:placetype":"venue"
},
  "geometry": {"coordinates":[-79.17377500000001,37.40362],"type":"Point"}
}