{
  "type": "Feature",
  "properties": {
    "iso:country":"US",
    "sg:address":"11350 Random Hills Rd",
    "sg:city":"Fairfax",
    "sg:classifiers":[
        {
            "category":"Government",
            "subcategory":"Office",
            "type":"Public Place"
        }
    ],
    "sg:phone":"+1 703 218 1965",
    "sg:postcode":"22030",
    "sg:province":"VA",
    "sg:tags":[
        "legislative",
        "body"
    ],
    "wof:name":"Federation of Govt Indstry Pro",
    "wof:placetype":"venue"
},
  "geometry": {"coordinates":[-77.33906500000001,38.857433],"type":"Point"}
}