{
  "type": "Feature",
  "properties": {
    "addr:full":"115 Monarch Dr Newport News VA 23602",
    "addr:housenumber":"115",
    "addr:postcode":"23602",
    "addr:street":"Monarch Dr",
    "iso:country":"US",
    "sg:address":"115 Monarch Dr",
    "sg:city":"Newport News",
    "sg:classifiers":[
        {
            "category":"Building & Trades",
            "subcategory":"Landscaping Services",
            "type":"Services"
        }
    ],
    "sg:phone":"+1 757 874 2897",
    "sg:postcode":"23602",
    "sg:province":"VA",
    "sg:tags":[
        "landscape"
    ],
    "wof:name":"Sonnyside Landscapes",
    "wof:placetype":"venue"
},
  "geometry": {"coordinates":[-76.525931,37.096602],"type":"Point"}
}