{
  "type": "Feature",
  "properties": {
    "iso:country":"US",
    "sg:address":"320 Williamsburg Rd",
    "sg:city":"Sterling",
    "sg:classifiers":[
        {
            "category":"Professional",
            "type":"Services"
        }
    ],
    "sg:phone":"+1 703 435 5865",
    "sg:postcode":"20164",
    "sg:province":"VA",
    "wof:name":"Porleng Him",
    "wof:placetype":"venue"
},
  "geometry": {"coordinates":[-77.413899,38.992623],"type":"Point"}
}