{
  "type": "Feature",
  "properties": {
    "addr:full":"2206 Executive Dr Hampton VA 23666",
    "addr:housenumber":"2206",
    "addr:postcode":"23666",
    "addr:street":"Executive Dr",
    "iso:country":"US",
    "sg:address":"2206 Executive Dr",
    "sg:city":"Hampton",
    "sg:classifiers":[
        {
            "category":"Shopping",
            "type":"Retail Goods"
        }
    ],
    "sg:phone":"+1 757 825 8288",
    "sg:postcode":"23666",
    "sg:province":"VA",
    "sg:tags":[
        "hearing",
        "equipment",
        "supply",
        "impaired"
    ],
    "wof:name":"Hampton Roads Ear Nose Throat",
    "wof:placetype":"venue"
},
  "geometry": {"coordinates":[-76.397267,37.048797],"type":"Point"}
}