{
  "type": "Feature",
  "properties": {
    "addr:full":"102 Sherwood Dr Colonial Heights VA 23834",
    "addr:housenumber":"102",
    "addr:postcode":"23834",
    "addr:street":"Sherwood Dr",
    "iso:country":"US",
    "sg:address":"102 Sherwood Dr",
    "sg:city":"Colonial Heights",
    "sg:classifiers":[
        {
            "category":"Personal",
            "subcategory":"Beauty Salon",
            "type":"Services"
        }
    ],
    "sg:phone":"+1 804 526 9059",
    "sg:postcode":"23834",
    "sg:province":"VA",
    "sg:tags":[
        "shop"
    ],
    "wof:name":"Hair Cuts By Sun",
    "wof:placetype":"venue"
},
  "geometry": {"coordinates":[-77.41820800000001,37.277213],"type":"Point"}
}