{
  "type": "Feature",
  "properties": {
    "addr:full":"6738 Main St Zanoni VA 23061",
    "addr:housenumber":"6738",
    "addr:postcode":"23061",
    "addr:street":"Main St",
    "iso:country":"US",
    "sg:address":"6738 Main St",
    "sg:city":"Zanoni",
    "sg:classifiers":[
        {
            "category":"Education",
            "subcategory":"Dance Studio",
            "type":"Public Place"
        }
    ],
    "sg:phone":"+1 804 694 5900",
    "sg:postcode":"23061",
    "sg:province":"VA",
    "sg:tags":[
        "instruction",
        "dancing"
    ],
    "wof:name":"Digg's School Of Dance",
    "wof:placetype":"venue"
},
  "geometry": {"coordinates":[-76.522149,37.412837],"type":"Point"}
}