{
  "type": "Feature",
  "properties": {
    "addr:full":"89 Tanglewood Rd Fries VA 24330",
    "addr:housenumber":"89",
    "addr:postcode":"24330",
    "addr:street":"Tanglewood Rd",
    "iso:country":"US",
    "sg:address":"89 Tanglewood Rd",
    "sg:city":"Fries",
    "sg:classifiers":[
        {
            "category":"Food & Beverages",
            "subcategory":"Groceries & Convenience Stores",
            "type":"Retail Goods"
        }
    ],
    "sg:phone":"+1 276 744 2441",
    "sg:postcode":"24330",
    "sg:province":"VA",
    "sg:tags":[
        "hardware",
        "station",
        "gasoline"
    ],
    "wof:name":"Green Valley Grocery & Hdwr",
    "wof:placetype":"venue"
},
  "geometry": {"coordinates":[-81.00466900000001,36.713671],"type":"Point"}
}