{
  "type": "Feature",
  "properties": {
    "addr:full":"1039 W Glebe Rd Alexandria VA 22305",
    "addr:housenumber":"1039",
    "addr:postcode":"22305",
    "addr:street":"W Glebe Rd",
    "iso:country":"US",
    "sg:address":"1039 W Glebe Rd",
    "sg:city":"Alexandria",
    "sg:classifiers":[
        {
            "category":"Restaurant",
            "type":"Food & Drink"
        }
    ],
    "sg:phone":"+1 703 836 3888",
    "sg:postcode":"22305",
    "sg:province":"VA",
    "sg:tags":[
        "chinese"
    ],
    "wof:name":"China Cafe",
    "wof:placetype":"venue"
},
  "geometry": {"coordinates":[-77.0765,38.842701],"type":"Point"}
}