{
  "type": "Feature",
  "properties": {
    "iso:country":"US",
    "sg:address":"9919 Southpoint Pkwy",
    "sg:city":"Fredericksburg",
    "sg:classifiers":[
        {
            "category":"Insurance",
            "subcategory":"Insurance Agent",
            "type":"Services"
        }
    ],
    "sg:phone":"+1 540 891 1075",
    "sg:postcode":"22407",
    "sg:province":"VA",
    "sg:tags":[
        "auto"
    ],
    "sg:website":"http://clickserve.dartsearch.net/link/click?lid=43000000277022585",
    "wof:name":"Allstate Insurance Company - William Wyant",
    "wof:placetype":"venue"
},
  "geometry": {"coordinates":[-77.503805,38.232981],"type":"Point"}
}