{
  "type": "Feature",
  "properties": {
    "addr:full":"1910 E Parham Rd Richmond VA 23228",
    "addr:housenumber":"1910",
    "addr:postcode":"23228",
    "addr:street":"E Parham Rd",
    "iso:country":"US",
    "sg:address":"1910 E Parham Rd",
    "sg:city":"Richmond",
    "sg:classifiers":[
        {
            "category":"Professional",
            "type":"Services"
        },
        {
            "category":"Professional",
            "subcategory":"Management & Consulting",
            "type":"Services"
        }
    ],
    "sg:phone":"+1 804 740 4200",
    "sg:postcode":"23228",
    "sg:province":"VA",
    "sg:tags":[
        "consultant",
        "business"
    ],
    "wof:name":"Delta Environmental Consultant",
    "wof:placetype":"venue"
},
  "geometry": {"coordinates":[-77.485089,37.63996],"type":"Point"}
}