{
  "type": "Feature",
  "properties": {
    "iso:country":"US",
    "sg:address":"13797 Warwick Blvd",
    "sg:city":"Newport News",
    "sg:classifiers":[
        {
            "category":"Restaurant",
            "type":"Food & Drink"
        }
    ],
    "sg:menulink":"http://www.allmenus.com/va/newport-news/147750-subway/menu/",
    "sg:phone":"+1 757 874 5806",
    "sg:postcode":"23602",
    "sg:province":"VA",
    "sg:tags":[
        "american",
        "sandwich"
    ],
    "wof:name":"Subway",
    "wof:placetype":"venue"
},
  "geometry": {"coordinates":[-76.531313,37.124582],"type":"Point"}
}