{
  "type": "Feature",
  "properties": {
    "addr:full":"10 S College Ave Salem VA 24153",
    "addr:housenumber":"10",
    "addr:postcode":"24153",
    "addr:street":"S College Ave",
    "iso:country":"US",
    "sg:address":"10 S College Ave",
    "sg:city":"Salem",
    "sg:classifiers":[
        {
            "category":"Shopping",
            "subcategory":"Jewelry",
            "type":"Retail Goods"
        }
    ],
    "sg:phone":"+1 540 389 4783",
    "sg:postcode":"24153",
    "sg:province":"VA",
    "sg:tags":[
        "jeweler"
    ],
    "wof:name":"R M Johnson & Sons Inc",
    "wof:placetype":"venue"
},
  "geometry": {"coordinates":[-80.05434700000001,37.292613],"type":"Point"}
}