{
  "type": "Feature",
  "properties": {
    "addr:full":"8214 Gunston Corner Ln Lorton VA 22079",
    "addr:housenumber":"8214",
    "addr:postcode":"22079",
    "addr:street":"Gunston Corner Ln",
    "iso:country":"US",
    "sg:address":"8214 Gunston Corner Ln",
    "sg:city":"Lorton",
    "sg:classifiers":[
        {
            "category":"Restaurant",
            "type":"Food & Drink"
        }
    ],
    "sg:phone":"+1 703 495 8884",
    "sg:postcode":"22079",
    "sg:province":"VA",
    "sg:tags":[
        "eating"
    ],
    "wof:name":"Gunston Wok",
    "wof:placetype":"venue"
},
  "geometry": {"coordinates":[-77.228224,38.704944],"type":"Point"}
}