{
  "type": "Feature",
  "properties": {
    "iso:country":"US",
    "sg:address":"14806 Blackburn Rd",
    "sg:city":"Woodbridge",
    "sg:classifiers":[
        {
            "category":"Organizations",
            "subcategory":"Religious Organization",
            "type":"Services"
        }
    ],
    "sg:phone":"+1 703 494 5400",
    "sg:postcode":"22191",
    "sg:province":"VA",
    "wof:name":"Cokesbury Untd Methdst Church",
    "wof:placetype":"venue"
},
  "geometry": {"coordinates":[-77.26751299999999,38.631841],"type":"Point"}
}