{
  "type": "Feature",
  "properties": {
    "addr:full":"834 Reading Rd Virginia Beach VA 23451",
    "addr:housenumber":"834",
    "addr:postcode":"23451",
    "addr:street":"Reading Rd",
    "iso:country":"US",
    "sg:address":"834 Reading Rd",
    "sg:city":"Virginia Beach",
    "sg:classifiers":[
        {
            "category":"Professional",
            "type":"Services"
        }
    ],
    "sg:phone":"+1 757 425 7914",
    "sg:postcode":"23451",
    "sg:province":"VA",
    "wof:name":"Mid Atlantic Instlrs",
    "wof:placetype":"venue"
},
  "geometry": {"coordinates":[-75.986884,36.79204],"type":"Point"}
}