{
  "type": "Feature",
  "properties": {
    "iso:country":"US",
    "sg:address":"111 E Criser Rd",
    "sg:city":"Front Royal",
    "sg:classifiers":[
        {
            "category":"Education",
            "subcategory":"School",
            "type":"Public Place"
        }
    ],
    "sg:phone":"+1 540 635 2171",
    "sg:postcode":"22630",
    "sg:province":"VA",
    "sg:tags":[
        "board"
    ],
    "wof:name":"School Textbook Fund",
    "wof:placetype":"venue"
},
  "geometry": {"coordinates":[-78.19420700000001,38.907686],"type":"Point"}
}