{
  "type": "Feature",
  "properties": {
    "addr:full":"6129 Brook Dr Falls Church VA 22044",
    "addr:housenumber":"6129",
    "addr:postcode":"22044",
    "addr:street":"Brook Dr",
    "iso:country":"US",
    "sg:address":"6129 Brook Dr",
    "sg:city":"Falls Church",
    "sg:classifiers":[
        {
            "category":"Professional",
            "subcategory":"Management & Consulting",
            "type":"Services"
        }
    ],
    "sg:phone":"+1 703 532 2860",
    "sg:postcode":"22044",
    "sg:province":"VA",
    "sg:tags":[
        "wholesale",
        "traffic",
        "telecommunication"
    ],
    "wof:name":"Simplified Solutions Inc",
    "wof:placetype":"venue"
},
  "geometry": {"coordinates":[-77.147738,38.867139],"type":"Point"}
}