{
  "type": "Feature",
  "properties": {
    "iso:country":"US",
    "sg:address":"3096 Meadowbridge Rd",
    "sg:city":"Richmond",
    "sg:classifiers":[
        {
            "category":"Restaurant",
            "type":"Food & Drink"
        }
    ],
    "sg:phone":"+1 804 329 0052",
    "sg:postcode":"23222",
    "sg:province":"VA",
    "sg:tags":[
        "eating"
    ],
    "wof:name":"S & S Soul Food Delight Inc",
    "wof:placetype":"venue"
},
  "geometry": {"coordinates":[-77.419928,37.572505],"type":"Point"}
}