{
  "type": "Feature",
  "properties": {
    "iso:country":"US",
    "sg:address":"301 High St",
    "sg:city":"Charlottesville",
    "sg:classifiers":[
        {
            "category":"Banks & Credit Unions",
            "subcategory":"Financial Services",
            "type":"Services"
        }
    ],
    "sg:phone":"+1 434 244 3300",
    "sg:postcode":"22902",
    "sg:province":"VA",
    "sg:tags":[
        "company",
        "holding",
        "real estate",
        "investment"
    ],
    "wof:name":"Maple Ridge Group Lc",
    "wof:placetype":"venue"
},
  "geometry": {"coordinates":[-78.482598,38.033462],"type":"Point"}
}