{
  "type": "Feature",
  "properties": {
    "addr:full":"175 Bumgarner Dr Forest VA 24551",
    "addr:housenumber":"175",
    "addr:postcode":"24551",
    "addr:street":"Bumgarner Dr",
    "iso:country":"US",
    "sg:address":"175 Bumgarner Dr",
    "sg:city":"Forest",
    "sg:classifiers":[
        {
            "category":"Wholesale",
            "subcategory":"Construction Materials",
            "type":"Manufacturing & Wholesale Goods"
        }
    ],
    "sg:phone":"+1 434 660 0087",
    "sg:postcode":"24551",
    "sg:province":"VA",
    "sg:tags":[
        "fence"
    ],
    "wof:name":"Custom Gate & Fence",
    "wof:placetype":"venue"
},
  "geometry": {"coordinates":[-79.268936,37.327952],"type":"Point"}
}