{
  "type": "Feature",
  "properties": {
    "addr:full":"317 Edwin Dr Virginia Beach VA 23462",
    "addr:housenumber":"317",
    "addr:postcode":"23462",
    "addr:street":"Edwin Dr",
    "iso:country":"US",
    "sg:address":"317 Edwin Dr",
    "sg:city":"Virginia Beach",
    "sg:classifiers":[
        {
            "category":"Health Services",
            "subcategory":"Doctor",
            "type":"Services"
        }
    ],
    "sg:phone":"+1 757 499 2100",
    "sg:postcode":"23462",
    "sg:province":"VA",
    "sg:tags":[
        "dentist"
    ],
    "sg:website":"www.partnersindentalhealth.com",
    "wof:name":"Partners In Dental Health PC",
    "wof:placetype":"venue"
},
  "geometry": {"coordinates":[-76.131066,36.826134],"type":"Point"}
}