{
  "type": "Feature",
  "properties": {
    "addr:full":"117 Fischer Dr Newport News VA 23602",
    "addr:housenumber":"117",
    "addr:postcode":"23602",
    "addr:street":"Fischer Dr",
    "iso:country":"US",
    "sg:address":"117 Fischer Dr",
    "sg:city":"Newport News",
    "sg:classifiers":[
        {
            "category":"Freight",
            "type":"Transportation"
        }
    ],
    "sg:phone":"+1 757 874 3113",
    "sg:postcode":"23602",
    "sg:province":"VA",
    "sg:tags":[
        "operator",
        "local",
        "trucking"
    ],
    "wof:name":"K T Hauling",
    "wof:placetype":"venue"
},
  "geometry": {"coordinates":[-76.53608800000001,37.118396],"type":"Point"}
}