{
  "type": "Feature",
  "properties": {
    "addr:full":"12445 Hedges Run Dr Woodbridge VA 22192",
    "addr:housenumber":"12445",
    "addr:postcode":"22192",
    "addr:street":"Hedges Run Dr",
    "iso:country":"US",
    "sg:address":"12445 Hedges Run Dr",
    "sg:city":"Woodbridge",
    "sg:classifiers":[
        {
            "category":"Banks & Credit Unions",
            "subcategory":"Bank",
            "type":"Services"
        }
    ],
    "sg:phone":"+1 703 494 1555",
    "sg:postcode":"22192",
    "sg:province":"VA",
    "sg:tags":[
        "federal",
        "savings",
        "institution"
    ],
    "wof:name":"Chevy Chase Bank F S B",
    "wof:placetype":"venue"
},
  "geometry": {"coordinates":[-77.31270000000001,38.685338],"type":"Point"}
}