{
  "type": "Feature",
  "properties": {
    "addr:full":"6387 Virginia Ave Bassett VA 24055",
    "addr:housenumber":"6387",
    "addr:postcode":"24055",
    "addr:street":"Virginia Ave",
    "iso:country":"US",
    "sg:address":"6387 Virginia Ave",
    "sg:city":"Bassett",
    "sg:classifiers":[
        {
            "category":"Organizations",
            "subcategory":"Religious Organization",
            "type":"Services"
        }
    ],
    "sg:phone":"+1 276 629 3918",
    "sg:postcode":"24055",
    "sg:province":"VA",
    "wof:name":"Day Star Ministries Chr-God",
    "wof:placetype":"venue"
},
  "geometry": {"coordinates":[-79.937533,36.754865],"type":"Point"}
}