{
  "type": "Feature",
  "properties": {
    "addr:full":"9745 Elmwood Rd Upperville VA 20184",
    "addr:housenumber":"9745",
    "addr:postcode":"20184",
    "addr:street":"Elmwood Rd",
    "iso:country":"US",
    "sg:address":"9745 Elmwood Rd",
    "sg:city":"Upperville",
    "sg:classifiers":[
        {
            "category":"Shopping",
            "subcategory":"Used Merchandise",
            "type":"Retail Goods"
        }
    ],
    "sg:phone":"+1 540 592 3021",
    "sg:postcode":"20184",
    "sg:province":"VA",
    "wof:name":"Yesterdays Riches",
    "wof:placetype":"venue"
},
  "geometry": {"coordinates":[-77.91069299999999,38.988423],"type":"Point"}
}