{
  "type": "Feature",
  "properties": {
    "addr:full":"3061 S Main St Harrisonburg VA 22801",
    "addr:housenumber":"3061",
    "addr:postcode":"22801",
    "addr:street":"S Main St",
    "iso:country":"US",
    "sg:address":"3061 S Main St",
    "sg:city":"Harrisonburg",
    "sg:classifiers":[
        {
            "category":"Professional",
            "subcategory":"Business Services",
            "type":"Services"
        },
        {
            "category":"Wholesale",
            "subcategory":"Durable Goods & Equipment",
            "type":"Manufacturing & Wholesale Goods"
        }
    ],
    "sg:phone":"+1 540 433 1634",
    "sg:postcode":"22801",
    "sg:province":"VA",
    "sg:tags":[
        "drafting"
    ],
    "wof:name":"Drafting Services & Supplies",
    "wof:placetype":"venue"
},
  "geometry": {"coordinates":[-78.90296499999999,38.411211],"type":"Point"}
}