{
  "type": "Feature",
  "properties": {
    "addr:full":"7200 Telegraph Square Dr Lorton VA 22079",
    "addr:housenumber":"7200",
    "addr:postcode":"22079",
    "addr:street":"Telegraph Square Dr",
    "iso:country":"US",
    "sg:address":"7200 Telegraph Square Dr",
    "sg:city":"Lorton",
    "sg:classifiers":[
        {
            "category":"Retail",
            "subcategory":"Repair Shop",
            "type":"Services"
        }
    ],
    "sg:phone":"+1 703 339 7765",
    "sg:postcode":"22079",
    "sg:province":"VA",
    "sg:tags":[
        "upholsterer"
    ],
    "wof:name":"B & B Upholstery & Furniture",
    "wof:placetype":"venue"
},
  "geometry": {"coordinates":[-77.193658,38.71704],"type":"Point"}
}