{
  "type": "Feature",
  "properties": {
    "addr:full":"3987 University Dr Fairfax VA 22030",
    "addr:housenumber":"3987",
    "addr:postcode":"22030",
    "addr:street":"University Dr",
    "iso:country":"US",
    "sg:address":"3987 University Dr",
    "sg:city":"Fairfax",
    "sg:classifiers":[
        {
            "category":"Professional",
            "subcategory":"Engineering",
            "type":"Services"
        }
    ],
    "sg:phone":"+1 703 524 4413",
    "sg:postcode":"22030",
    "sg:province":"VA",
    "wof:name":"Notaro Williams & Associates",
    "wof:placetype":"venue"
},
  "geometry": {"coordinates":[-77.304998,38.846699],"type":"Point"}
}