{
  "type": "Feature",
  "properties": {
    "iso:country":"US",
    "sg:address":"4314 Rockdale Rd",
    "sg:city":"Petersburg",
    "sg:classifiers":[
        {
            "category":"Building & Trades",
            "subcategory":"Construction",
            "type":"Services"
        }
    ],
    "sg:phone":"+1 804 862 2819",
    "sg:postcode":"23803",
    "sg:province":"VA",
    "sg:tags":[
        "contractor"
    ],
    "wof:name":"E Ann Jackson Inc",
    "wof:placetype":"venue"
},
  "geometry": {"coordinates":[-77.462777,37.212976],"type":"Point"}
}