{
  "type": "Feature",
  "properties": {
    "addr:full":"3322 Western Branch Blvd Chesapeake VA 23321",
    "addr:housenumber":"3322",
    "addr:postcode":"23321",
    "addr:street":"Western Branch Blvd",
    "iso:country":"US",
    "sg:address":"3322 Western Branch Blvd",
    "sg:city":"Chesapeake",
    "sg:classifiers":[
        {
            "category":"Autos & Motor Vehicles",
            "subcategory":"Auto Supplies",
            "type":"Retail Goods"
        },
        {
            "category":"Shopping",
            "subcategory":"Computers & Home Electronics",
            "type":"Retail Goods"
        }
    ],
    "sg:phone":"+1 757 484 6822",
    "sg:postcode":"23321",
    "sg:province":"VA",
    "sg:tags":[
        "automobile",
        "alarm"
    ],
    "wof:name":"Premier Autosound Inc",
    "wof:placetype":"venue"
},
  "geometry": {"coordinates":[-76.418256,36.865508],"type":"Point"}
}