{
  "type": "Feature",
  "properties": {
    "iso:country":"US",
    "sg:address":"1201 E Cary St",
    "sg:city":"Richmond",
    "sg:classifiers":[
        {
            "category":"Restaurant",
            "type":"Food & Drink"
        }
    ],
    "sg:menulink":"http://www.allmenus.com/va/richmond/13726-tobacoo-co/menu/",
    "sg:phone":"+1 804 782 9555",
    "sg:postcode":"23219",
    "sg:province":"VA",
    "sg:tags":[
        "american"
    ],
    "wof:name":"Tobacoo Co.",
    "wof:placetype":"venue"
},
  "geometry": {"coordinates":[-77.43424,37.535648],"type":"Point"}
}