{
  "type": "Feature",
  "properties": {
    "addr:full":"8201 Jefferson Davis Hwy Fredericksburg VA 22407",
    "addr:housenumber":"8201",
    "addr:postcode":"22407",
    "addr:street":"Jefferson Davis Hwy",
    "iso:country":"US",
    "sg:address":"8201 Jefferson Davis Hwy",
    "sg:city":"Fredericksburg",
    "sg:classifiers":[
        {
            "category":"Education",
            "subcategory":"School",
            "type":"Public Place"
        }
    ],
    "sg:phone":"+1 540 710 0419",
    "sg:postcode":"22407",
    "sg:province":"VA",
    "wof:name":"Massaponax High School",
    "wof:placetype":"venue"
},
  "geometry": {"coordinates":[-77.51437199999999,38.181565],"type":"Point"}
}