{
  "type": "Feature",
  "properties": {
    "addr:full":"2325 Trenthill Dr Bassett VA 24055",
    "addr:housenumber":"2325",
    "addr:postcode":"24055",
    "addr:street":"Trenthill Dr",
    "iso:country":"US",
    "sg:address":"2325 Trenthill Dr",
    "sg:city":"Bassett",
    "sg:classifiers":[
        {
            "category":"Shopping",
            "type":"Retail Goods"
        }
    ],
    "sg:phone":"+1 276 629 7275",
    "sg:postcode":"24055",
    "sg:province":"VA",
    "sg:tags":[
        "merchandise"
    ],
    "wof:name":"Honey Keatons Shop",
    "wof:placetype":"venue"
},
  "geometry": {"coordinates":[-80.005222,36.773494],"type":"Point"}
}