{
  "type": "Feature",
  "properties": {
    "iso:country":"US",
    "sg:address":"115 Ford St",
    "sg:city":"Chesapeake",
    "sg:classifiers":[
        {
            "category":"Organizations",
            "subcategory":"Religious Organization",
            "type":"Services"
        }
    ],
    "sg:phone":"+1 757 487 7678",
    "sg:postcode":"23323",
    "sg:province":"VA",
    "sg:tags":[
        "clergy"
    ],
    "wof:name":"Vincent Tucker Sr",
    "wof:placetype":"venue"
},
  "geometry": {"coordinates":[-76.312507,36.77102],"type":"Point"}
}