{
  "type": "Feature",
  "properties": {
    "addr:full":"20733 Virgil H Goode Hwy Rocky Mount VA 24151",
    "addr:housenumber":"20733;h",
    "addr:postcode":"24151",
    "addr:street":"Virgil;Goode Hwy",
    "iso:country":"US",
    "sg:address":"20733 Virgil H Goode Hwy",
    "sg:city":"Rocky Mount",
    "sg:classifiers":[
        {
            "category":"Restaurant",
            "type":"Food & Drink"
        }
    ],
    "sg:phone":"+1 540 334 2545",
    "sg:postcode":"24151",
    "sg:province":"VA",
    "wof:name":"T J's Fat Boys Bbq",
    "wof:placetype":"venue"
},
  "geometry": {"coordinates":[-79.903856,37.072939],"type":"Point"}
}