{
  "type": "Feature",
  "properties": {
    "iso:country":"US",
    "sg:address":"3746 Chain Bridge Rd",
    "sg:city":"Fairfax",
    "sg:classifiers":[
        {
            "category":"Travel",
            "subcategory":"Hotels & Motels",
            "type":"Entertainment"
        }
    ],
    "sg:phone":"+1 703 385 9024",
    "sg:postcode":"22030",
    "sg:province":"VA",
    "sg:tags":[
        "breakfast",
        "accommodation",
        "bed"
    ],
    "wof:name":"Stafford House",
    "wof:placetype":"venue"
},
  "geometry": {"coordinates":[-77.307823,38.851186],"type":"Point"}
}