{
  "type": "Feature",
  "properties": {
    "iso:country":"US",
    "sg:address":"6455 Shannon Station Ct",
    "sg:city":"Springfield",
    "sg:classifiers":[
        {
            "category":"Restaurant",
            "type":"Food & Drink"
        }
    ],
    "sg:phone":"+1 703 644 8592",
    "sg:postcode":"22152",
    "sg:province":"VA",
    "sg:tags":[
        "eating"
    ],
    "wof:name":"Dominos Pizza",
    "wof:placetype":"venue"
},
  "geometry": {"coordinates":[-77.25331,38.776099],"type":"Point"}
}