{
  "type": "Feature",
  "properties": {
    "addr:full":"109 N Bailey Ln Purcellville VA 20132",
    "addr:housenumber":"109",
    "addr:postcode":"20132",
    "addr:street":"N Bailey Ln",
    "iso:country":"US",
    "sg:address":"109 N Bailey Ln",
    "sg:city":"Purcellville",
    "sg:classifiers":[
        {
            "category":"Local Transit",
            "type":"Transportation"
        }
    ],
    "sg:phone":"+1 540 338 1610",
    "sg:postcode":"20132",
    "sg:province":"VA",
    "sg:tags":[
        "bus",
        "line"
    ],
    "wof:name":"Loudoun Transit",
    "wof:placetype":"venue"
},
  "geometry": {"coordinates":[-77.715738,39.143933],"type":"Point"}
}