{
  "type": "Feature",
  "properties": {
    "iso:country":"US",
    "sg:address":"4307 Boydton Plank Rd",
    "sg:city":"Brodnax",
    "sg:classifiers":[
        {
            "category":"Professional",
            "type":"Services"
        }
    ],
    "sg:phone":"+1 434 949 0190",
    "sg:postcode":"23920",
    "sg:province":"VA",
    "sg:tags":[
        "establishment"
    ],
    "wof:name":"Agrimicrobs Sales",
    "wof:placetype":"venue"
},
  "geometry": {"coordinates":[-77.96003399999999,36.804173],"type":"Point"}
}