{
  "type": "Feature",
  "properties": {
    "addr:full":"121 James Monroe Hwy Colonial Beach VA 22443",
    "addr:housenumber":"121",
    "addr:postcode":"beach;22443",
    "addr:street":"James Monroe Hwy Colonial",
    "iso:country":"US",
    "sg:address":"121 James Monroe Hwy",
    "sg:city":"Colonial Beach",
    "sg:classifiers":[
        {
            "category":"Government",
            "subcategory":"Fire Station",
            "type":"Public Place"
        }
    ],
    "sg:phone":"+1 804 224 0250",
    "sg:postcode":"22443",
    "sg:province":"VA",
    "sg:tags":[
        "department"
    ],
    "wof:name":"Oak Grove Volunteer Fire Dept",
    "wof:placetype":"venue"
},
  "geometry": {"coordinates":[-76.998154,38.184413],"type":"Point"}
}