{
  "type": "Feature",
  "properties": {
    "iso:country":"US",
    "sg:address":"8040 Villa Park Dr",
    "sg:city":"Richmond",
    "sg:classifiers":[
        {
            "category":"Wholesale",
            "subcategory":"Medical Equipment & Supplies",
            "type":"Manufacturing & Wholesale Goods"
        }
    ],
    "sg:phone":"+1 804 261 2492",
    "sg:postcode":"23228",
    "sg:province":"VA",
    "wof:name":"Thompson Dental Co Inc",
    "wof:placetype":"venue"
},
  "geometry": {"coordinates":[-77.46526,37.628146],"type":"Point"}
}