{
  "type": "Feature",
  "properties": {
    "addr:full":"3229 Collingwood St NE Roanoke VA 24012",
    "addr:housenumber":"3229",
    "addr:postcode":"24012",
    "addr:street":"Collingwood St Ne",
    "iso:country":"US",
    "sg:address":"3229 Collingwood St NE",
    "sg:city":"Roanoke",
    "sg:classifiers":[
        {
            "category":"Manufacturing",
            "subcategory":"Buildings",
            "type":"Manufacturing & Wholesale Goods"
        }
    ],
    "sg:phone":"+1 540 362 2789",
    "sg:postcode":"24012",
    "sg:province":"VA",
    "sg:tags":[
        "home",
        "log",
        "cabin"
    ],
    "wof:name":"Log Home Ctr",
    "wof:placetype":"venue"
},
  "geometry": {"coordinates":[-79.937282,37.305568],"type":"Point"}
}