{
  "type": "Feature",
  "properties": {
    "iso:country":"US",
    "sg:address":"2402 Plymouth St",
    "sg:city":"Blacksburg",
    "sg:classifiers":[
        {
            "category":"Building & Trades",
            "subcategory":"Equipment Rental",
            "type":"Services"
        }
    ],
    "sg:phone":"+1 540 552 9047",
    "sg:postcode":"24060",
    "sg:province":"VA",
    "wof:name":"Rader Cleaning Service",
    "wof:placetype":"venue"
},
  "geometry": {"coordinates":[-80.451015,37.218142],"type":"Point"}
}