{
  "type": "Feature",
  "properties": {
    "iso:country":"US",
    "sg:address":"2803 Fort Dr",
    "sg:city":"Alexandria",
    "sg:classifiers":[
        {
            "category":"Professional",
            "type":"Services"
        }
    ],
    "sg:phone":"+1 703 518 0689",
    "sg:postcode":"22303",
    "sg:province":"VA",
    "wof:name":"Flowers",
    "wof:placetype":"venue"
},
  "geometry": {"coordinates":[-77.07973,38.790599],"type":"Point"}
}