{
  "type": "Feature",
  "properties": {
    "iso:country":"US",
    "sg:address":"4068 Jermantown Rd",
    "sg:city":"Fairfax",
    "sg:classifiers":[
        {
            "category":"Retail",
            "subcategory":"Repair Shop",
            "type":"Services"
        }
    ],
    "sg:phone":"+1 703 842 5855",
    "sg:postcode":"22030",
    "sg:province":"VA",
    "sg:tags":[
        "lock",
        "locksmith"
    ],
    "wof:name":"24 Hour Locksmith",
    "wof:placetype":"venue"
},
  "geometry": {"coordinates":[-77.33257999999999,38.855576],"type":"Point"}
}