{
  "type": "Feature",
  "properties": {
    "iso:country":"US",
    "sg:address":"7787 Millfield Dr",
    "sg:city":"Warrenton",
    "sg:classifiers":[
        {
            "category":"Retail",
            "subcategory":"Repair Shop",
            "type":"Services"
        }
    ],
    "sg:phone":"+1 540 341 7993",
    "sg:postcode":"20187",
    "sg:province":"VA",
    "sg:tags":[
        "household",
        "appliance"
    ],
    "wof:name":"C & D Services",
    "wof:placetype":"venue"
},
  "geometry": {"coordinates":[-77.77833,38.71675],"type":"Point"}
}