{
  "type": "Feature",
  "properties": {
    "iso:country":"US",
    "sg:address":"1212 S Oakcrest Rd",
    "sg:city":"Arlington",
    "sg:classifiers":[
        {
            "category":"Professional",
            "subcategory":"Management & Consulting",
            "type":"Services"
        }
    ],
    "sg:phone":"+1 703 241 1739",
    "sg:postcode":"22202",
    "sg:province":"VA",
    "sg:tags":[
        "business"
    ],
    "wof:name":"Compower Grou (llc)",
    "wof:placetype":"venue"
},
  "geometry": {"coordinates":[-77.06627899999999,38.851398],"type":"Point"}
}