{
  "type": "Feature",
  "properties": {
    "addr:full":"20789 Great Falls Plz Sterling VA 20165",
    "addr:housenumber":"20789",
    "addr:postcode":"20165",
    "addr:street":"Plz",
    "iso:country":"US",
    "sg:address":"20789 Great Falls Plz",
    "sg:city":"Sterling",
    "sg:classifiers":[
        {
            "category":"Recreation",
            "type":"Entertainment"
        },
        {
            "category":"Sports & Exercise",
            "subcategory":"Gym",
            "type":"Entertainment"
        }
    ],
    "sg:phone":"+1 703 450 8626",
    "sg:postcode":"20165",
    "sg:province":"VA",
    "sg:tags":[
        "club",
        "health",
        "studio",
        "gymnasium"
    ],
    "wof:name":"Tiger Den Martial Arts",
    "wof:placetype":"venue"
},
  "geometry": {"coordinates":[-77.357916,39.040244],"type":"Point"}
}