{
  "type": "Feature",
  "properties": {
    "addr:full":"3300 Odd Fellows Rd Lynchburg VA 24501",
    "addr:postcode":"3300;24501",
    "addr:street":"Odd Fellows Rd",
    "iso:country":"US",
    "sg:address":"3300 Odd Fellows Rd",
    "sg:city":"Lynchburg",
    "sg:classifiers":[
        {
            "category":"Banks & Credit Unions",
            "subcategory":"Bank",
            "type":"Services"
        }
    ],
    "sg:phone":"+1 434 845 2481",
    "sg:postcode":"24501",
    "sg:province":"VA",
    "wof:name":"Lynchburg Postal Credit Union",
    "wof:placetype":"venue"
},
  "geometry": {"coordinates":[-79.16174100000001,37.382549],"type":"Point"}
}