{
  "type": "Feature",
  "properties": {
    "addr:full":"14890 Washington St Haymarket VA 20169",
    "addr:housenumber":"14890",
    "addr:postcode":"20169",
    "addr:street":"Washington St",
    "iso:country":"US",
    "sg:address":"14890 Washington St",
    "sg:city":"Haymarket",
    "sg:classifiers":[
        {
            "category":"Professional",
            "subcategory":"Lawyer & Legal Services",
            "type":"Services"
        }
    ],
    "sg:phone":"+1 571 261 5641",
    "sg:postcode":"20169",
    "sg:province":"VA",
    "wof:name":"Craig John M Atty",
    "wof:placetype":"venue"
},
  "geometry": {"coordinates":[-77.63456600000001,38.811466],"type":"Point"}
}