{
  "type": "Feature",
  "properties": {
    "addr:full":"5603 Gobind Ln Fairfax Station VA 22039",
    "addr:postcode":"5603;22039",
    "addr:street":"Gobind Ln",
    "iso:country":"US",
    "sg:address":"5603 Gobind Ln",
    "sg:city":"Fairfax Station",
    "sg:classifiers":[
        {
            "category":"Professional",
            "subcategory":"Business Services",
            "type":"Services"
        }
    ],
    "sg:phone":"+1 703 250 0343",
    "sg:postcode":"22039",
    "sg:province":"VA",
    "wof:name":"Jrd Enterprises",
    "wof:placetype":"venue"
},
  "geometry": {"coordinates":[-77.329752,38.803218],"type":"Point"}
}