{
  "type": "Feature",
  "properties": {
    "addr:full":"816 Whitehead Rd Richmond VA 23225",
    "addr:housenumber":"816",
    "addr:postcode":"23225",
    "addr:street":"Whitehead Rd",
    "iso:country":"US",
    "sg:address":"816 Whitehead Rd",
    "sg:city":"Richmond",
    "sg:classifiers":[
        {
            "category":"Organizations",
            "subcategory":"Religious Organization",
            "type":"Services"
        }
    ],
    "sg:phone":"+1 804 745 5137",
    "sg:postcode":"23225",
    "sg:province":"VA",
    "wof:name":"Church of Christ",
    "wof:placetype":"venue"
},
  "geometry": {"coordinates":[-77.507289,37.495287],"type":"Point"}
}