{
  "type": "Feature",
  "properties": {
    "addr:full":"541 Allens Mill Rd Yorktown VA 23692",
    "addr:housenumber":"541",
    "addr:postcode":"23692",
    "addr:street":"Allens Mill Rd",
    "iso:country":"US",
    "sg:address":"541 Allens Mill Rd",
    "sg:city":"Yorktown",
    "sg:classifiers":[
        {
            "category":"Recreation",
            "type":"Entertainment"
        }
    ],
    "sg:phone":"+1 757 898 5230",
    "sg:postcode":"23692",
    "sg:province":"VA",
    "sg:tags":[
        "club",
        "membership"
    ],
    "wof:name":"Sportsmans Hunt Club",
    "wof:placetype":"venue"
},
  "geometry": {"coordinates":[-76.447857,37.173126],"type":"Point"}
}