{
  "type": "Feature",
  "properties": {
    "iso:country":"US",
    "sg:address":"510 E Belt Blvd",
    "sg:city":"Richmond",
    "sg:classifiers":[
        {
            "category":"Insurance",
            "subcategory":"Hazard Insurance",
            "type":"Services"
        },
        {
            "category":"Insurance",
            "subcategory":"Insurance Agent",
            "type":"Services"
        },
        {
            "category":"Insurance",
            "subcategory":"Life Insurance",
            "type":"Services"
        },
        {
            "category":"Insurance",
            "subcategory":"Title Insurance",
            "type":"Services"
        }
    ],
    "sg:phone":"+1 804 232 7790",
    "sg:postcode":"23224",
    "sg:province":"VA",
    "sg:tags":[
        "auto",
        "homeowner"
    ],
    "sg:website":"http://www.nationwide.com/agent/Richmond-VIRGINIA-insurance-agent/r-edwin-sweeney-iii/office.html",
    "wof:name":"Ralph E Sweeney Iii Inc - Nationwide Insurance",
    "wof:placetype":"venue"
},
  "geometry": {"coordinates":[-77.47604699999999,37.504273],"type":"Point"}
}