{
  "type": "Feature",
  "properties": {
    "addr:full":"1252 Elden St Herndon VA 20170",
    "addr:housenumber":"1252",
    "addr:postcode":"20170",
    "addr:street":"Elden St",
    "iso:country":"US",
    "sg:address":"1252 Elden St",
    "sg:city":"Herndon",
    "sg:classifiers":[
        {
            "category":"Professional",
            "subcategory":"Detective & Security Services",
            "type":"Services"
        }
    ],
    "sg:phone":"+1 703 709 0311",
    "sg:postcode":"20170",
    "sg:province":"VA",
    "sg:tags":[
        "car"
    ],
    "wof:name":"K Investigations Inc",
    "wof:placetype":"venue"
},
  "geometry": {"coordinates":[-77.400477,38.96107],"type":"Point"}
}