{
  "type": "Feature",
  "properties": {
    "addr:full":"13206 Stable Brook Way Herndon VA 20171",
    "addr:housenumber":"13206",
    "addr:postcode":"20171",
    "addr:street":"Stable Brook Way",
    "iso:country":"US",
    "sg:address":"13206 Stable Brook Way",
    "sg:city":"Herndon",
    "sg:classifiers":[
        {
            "category":"Professional",
            "type":"Services"
        }
    ],
    "sg:phone":"+1 703 707 8664",
    "sg:postcode":"20171",
    "sg:province":"VA",
    "wof:name":"Trans Global Services LLC",
    "wof:placetype":"venue"
},
  "geometry": {"coordinates":[-77.40361300000001,38.939774],"type":"Point"}
}