{
  "type": "Feature",
  "properties": {
    "addr:full":"11960 Old Franklin Tpke Union Hall VA 24176",
    "addr:housenumber":"11960",
    "addr:postcode":"24176",
    "addr:street":"Old Franklin Tpke Union Hall",
    "iso:country":"US",
    "sg:address":"11960 Old Franklin Tpke",
    "sg:city":"Union Hall",
    "sg:classifiers":[
        {
            "category":"Restaurant",
            "type":"Food & Drink"
        }
    ],
    "sg:phone":"+1 540 576 3004",
    "sg:postcode":"24176",
    "sg:province":"VA",
    "wof:name":"LA Trattoria Italian Rstrnt",
    "wof:placetype":"venue"
},
  "geometry": {"coordinates":[-79.68588200000001,36.994083],"type":"Point"}
}