{
  "type": "Feature",
  "properties": {
    "iso:country":"US",
    "sg:address":"117 Oronoco St",
    "sg:city":"Alexandria",
    "sg:classifiers":[
        {
            "category":"Wholesale",
            "subcategory":"Books, Periodicals, & Newspapers",
            "type":"Manufacturing & Wholesale Goods"
        }
    ],
    "sg:phone":"+1 703 535 3250",
    "sg:postcode":"22314",
    "sg:province":"VA",
    "sg:tags":[
        "distributor",
        "publisher",
        "maps-designers"
    ],
    "wof:name":"Multiview Inc",
    "wof:placetype":"venue"
},
  "geometry": {"coordinates":[-77.03949299999999,38.808794],"type":"Point"}
}