{
  "type": "Feature",
  "properties": {
    "iso:country":"US",
    "sg:address":"1320 Lasalle Ave",
    "sg:city":"Hampton",
    "sg:classifiers":[
        {
            "category":"Government",
            "subcategory":"Office",
            "type":"Public Place"
        }
    ],
    "sg:phone":"+1 757 727 1140",
    "sg:postcode":"23669",
    "sg:province":"VA",
    "sg:tags":[
        "city",
        "program",
        "health"
    ],
    "wof:name":"Hampton Health Dept",
    "wof:placetype":"venue"
},
  "geometry": {"coordinates":[-76.362758,37.030616],"type":"Point"}
}