{
  "type": "Feature",
  "properties": {
    "addr:full":"15225 Ryland Chapel Rd Rixeyville VA 22737",
    "addr:housenumber":"15225",
    "addr:postcode":"22737",
    "addr:street":"Ryland Chapel Rd",
    "iso:country":"US",
    "sg:address":"15225 Ryland Chapel Rd",
    "sg:city":"Rixeyville",
    "sg:classifiers":[
        {
            "category":"Home & Garden",
            "subcategory":"Garden Supply",
            "type":"Retail Goods"
        }
    ],
    "sg:phone":"+1 540 937 4712",
    "sg:postcode":"22737",
    "sg:province":"VA",
    "wof:name":"Squirrellys Greenhouse",
    "wof:placetype":"venue"
},
  "geometry": {"coordinates":[-77.96901099999999,38.573286],"type":"Point"}
}