{
  "type": "Feature",
  "properties": {
    "iso:country":"US",
    "sg:address":"26396 Angus Ln",
    "sg:city":"Elkwood",
    "sg:classifiers":[
        {
            "category":"Farming",
            "subcategory":"Livestock Farm",
            "type":"Manufacturing & Wholesale Goods"
        }
    ],
    "sg:phone":"+1 540 399 1415",
    "sg:postcode":"22718",
    "sg:province":"VA",
    "sg:tags":[
        "feedlot",
        "field",
        "crop",
        "beef",
        "cattle"
    ],
    "wof:name":"Raymond Childress",
    "wof:placetype":"venue"
},
  "geometry": {"coordinates":[-77.769998,38.447313],"type":"Point"}
}