{
  "type": "Feature",
  "properties": {
    "iso:country":"US",
    "sg:address":"2033 Battlefield Blvd N",
    "sg:city":"Chesapeake",
    "sg:classifiers":[
        {
            "category":"Food & Beverages",
            "subcategory":"Groceries & Convenience Stores",
            "type":"Retail Goods"
        }
    ],
    "sg:phone":"+1 757 543 9876",
    "sg:postcode":"23320",
    "sg:province":"VA",
    "wof:name":"7-Eleven",
    "wof:placetype":"venue"
},
  "geometry": {"coordinates":[-76.260124,36.790664],"type":"Point"}
}