{
  "type": "Feature",
  "properties": {
    "addr:full":"14413 Wards Rd Lynchburg VA 24502",
    "addr:housenumber":"14413",
    "addr:postcode":"24502",
    "addr:street":"Wards Rd",
    "iso:country":"US",
    "sg:address":"14413 Wards Rd",
    "sg:city":"Lynchburg",
    "sg:classifiers":[
        {
            "category":"Professional",
            "subcategory":"Business Services",
            "type":"Services"
        }
    ],
    "sg:phone":"+1 434 237 3547",
    "sg:postcode":"24502",
    "sg:province":"VA",
    "wof:name":"Flips Graphix Design",
    "wof:placetype":"venue"
},
  "geometry": {"coordinates":[-79.18969300000001,37.324203],"type":"Point"}
}