{
  "type": "Feature",
  "properties": {
    "addr:full":"44045 Riverside Pkwy Leesburg VA 20176",
    "addr:housenumber":"44045",
    "addr:postcode":"20176",
    "addr:street":"Riverside Pkwy",
    "iso:country":"US",
    "sg:address":"44045 Riverside Pkwy",
    "sg:city":"Leesburg",
    "sg:classifiers":[
        {
            "category":"Shopping",
            "subcategory":"Gifts & Souvenirs",
            "type":"Retail Goods"
        }
    ],
    "sg:phone":"+1 703 858 6663",
    "sg:postcode":"20176",
    "sg:province":"VA",
    "wof:name":"Gift Shop Ladies Board",
    "wof:placetype":"venue"
},
  "geometry": {"coordinates":[-77.471778,39.071152],"type":"Point"}
}