{
  "type": "Feature",
  "properties": {
    "iso:country":"US",
    "sg:address":"502 Beech St",
    "sg:city":"Farmville",
    "sg:classifiers":[
        {
            "category":"Professional",
            "subcategory":"Research",
            "type":"Services"
        }
    ],
    "sg:phone":"+1 434 392 3465",
    "sg:postcode":"23901",
    "sg:province":"VA",
    "sg:tags":[
        "laboratory"
    ],
    "wof:name":"Laboratory Corp Of America",
    "wof:placetype":"venue"
},
  "geometry": {"coordinates":[-78.39709999999999,37.303474],"type":"Point"}
}