{
  "type": "Feature",
  "properties": {
    "iso:country":"US",
    "sg:address":"4512 Lantern Pl",
    "sg:city":"Alexandria",
    "sg:classifiers":[
        {
            "category":"Professional",
            "subcategory":"Business Services",
            "type":"Services"
        }
    ],
    "sg:phone":"+1 703 444 4780",
    "sg:postcode":"22306",
    "sg:province":"VA",
    "sg:tags":[
        "water",
        "treatment"
    ],
    "wof:name":"Pro Line Water",
    "wof:placetype":"venue"
},
  "geometry": {"coordinates":[-77.111941,38.765075],"type":"Point"}
}