{
  "type": "Feature",
  "properties": {
    "addr:full":"231 Mineral Ave Mineral VA 23117",
    "addr:housenumber":"231",
    "addr:postcode":"23117",
    "addr:street":"Mineral Ave",
    "iso:country":"US",
    "sg:address":"231 Mineral Ave",
    "sg:city":"Mineral",
    "sg:classifiers":[
        {
            "category":"Shopping",
            "type":"Retail Goods"
        }
    ],
    "sg:phone":"+1 540 894 0600",
    "sg:postcode":"23117",
    "sg:province":"VA",
    "sg:tags":[
        "merchandise",
        "animal"
    ],
    "sg:website":"www.petsunlimitedcom.com",
    "wof:name":"Pets Unlimited",
    "wof:placetype":"venue"
},
  "geometry": {"coordinates":[-77.90889,38.010159],"type":"Point"}
}