{
  "type": "Feature",
  "properties": {
    "iso:country":"US",
    "sg:address":"4441 Pissaro Dr",
    "sg:city":"Virginia Beach",
    "sg:classifiers":[
        {
            "category":"Building & Trades",
            "subcategory":"Construction",
            "type":"Services"
        }
    ],
    "sg:phone":"+1 757 467 4249",
    "sg:postcode":"23456",
    "sg:province":"VA",
    "sg:tags":[
        "builder",
        "operative"
    ],
    "wof:name":"Thomas J Moran",
    "wof:placetype":"venue"
},
  "geometry": {"coordinates":[-76.134458,36.790201],"type":"Point"}
}