{
  "type": "Feature",
  "properties": {
    "addr:full":"118 Runey Way Yorktown VA 23693",
    "addr:housenumber":"118",
    "addr:postcode":"23693",
    "addr:street":"Runey Way",
    "iso:country":"US",
    "sg:address":"118 Runey Way",
    "sg:city":"Yorktown",
    "sg:classifiers":[
        {
            "category":"Personal",
            "subcategory":"Tattoo Parlor",
            "type":"Services"
        }
    ],
    "sg:phone":"+1 757 896 0111",
    "sg:postcode":"23693",
    "sg:province":"VA",
    "sg:tags":[
        "tattooing"
    ],
    "sg:website":"www.permafaces.com",
    "wof:name":"Permafaces Permanent Makeup",
    "wof:placetype":"venue"
},
  "geometry": {"coordinates":[-76.462356,37.117803],"type":"Point"}
}