{
  "type": "Feature",
  "properties": {
    "addr:full":"3909 Carolina Ave Richmond VA 23222",
    "addr:housenumber":"3909",
    "addr:postcode":"23222",
    "addr:street":"Carolina Ave",
    "iso:country":"US",
    "sg:address":"3909 Carolina Ave",
    "sg:city":"Richmond",
    "sg:classifiers":[
        {
            "category":"Home & Garden",
            "subcategory":"Building Materials",
            "type":"Retail Goods"
        }
    ],
    "sg:phone":"+1 804 644 2630",
    "sg:postcode":"23222",
    "sg:province":"VA",
    "sg:tags":[
        "door"
    ],
    "wof:name":"General American Door Co",
    "wof:placetype":"venue"
},
  "geometry": {"coordinates":[-77.41482499999999,37.585132],"type":"Point"}
}