{
  "type": "Feature",
  "properties": {
    "iso:country":"US",
    "sg:address":"2705 New Ambler Ct",
    "sg:city":"Herndon",
    "sg:classifiers":[
        {
            "category":"Retail",
            "subcategory":"Repair Shop",
            "type":"Services"
        }
    ],
    "sg:phone":"+1 703 787 9695",
    "sg:postcode":"20171",
    "sg:province":"VA",
    "sg:tags":[
        "equipment"
    ],
    "wof:name":"CFS",
    "wof:placetype":"venue"
},
  "geometry": {"coordinates":[-77.394829,38.934352],"type":"Point"}
}