{
  "type": "Feature",
  "properties": {
    "addr:full":"3130 Chaparral Dr Roanoke VA 24018",
    "addr:housenumber":"3130",
    "addr:postcode":"24018",
    "addr:street":"Chaparral Dr",
    "iso:country":"US",
    "sg:address":"3130 Chaparral Dr",
    "sg:city":"Roanoke",
    "sg:classifiers":[
        {
            "category":"Real Estate",
            "subcategory":"Real Estate Agent",
            "type":"Services"
        }
    ],
    "sg:phone":"+1 540 297 3400",
    "sg:postcode":"24018",
    "sg:province":"VA",
    "sg:tags":[
        "consultant"
    ],
    "wof:name":"Homestead At The Lake LLC",
    "wof:placetype":"venue"
},
  "geometry": {"coordinates":[-79.991091,37.223694],"type":"Point"}
}