{
  "type": "Feature",
  "properties": {
    "addr:full":"309 McLaws Cir Williamsburg VA 23185",
    "addr:housenumber":"309",
    "addr:postcode":"23185",
    "addr:street":"Mclaws Cir",
    "iso:country":"US",
    "sg:address":"309 McLaws Cir",
    "sg:city":"Williamsburg",
    "sg:classifiers":[
        {
            "category":"Professional",
            "type":"Services"
        }
    ],
    "sg:phone":"+1 757 259 9222",
    "sg:postcode":"23185",
    "sg:province":"VA",
    "wof:name":"Cristall Art and Glass Studio",
    "wof:placetype":"venue"
},
  "geometry": {"coordinates":[-76.661241,37.244427],"type":"Point"}
}