{
  "type": "Feature",
  "properties": {
    "addr:full":"814 W 37th St Norfolk VA 23508",
    "addr:housenumber":"814",
    "addr:postcode":"23508",
    "addr:street":"W 37Th St",
    "iso:country":"US",
    "sg:address":"814 W 37th St",
    "sg:city":"Norfolk",
    "sg:classifiers":[
        {
            "category":"Social Services",
            "subcategory":"Adult Care",
            "type":"Services"
        }
    ],
    "sg:phone":"+1 757 623 6662",
    "sg:postcode":"23508",
    "sg:province":"VA",
    "sg:tags":[
        "residential"
    ],
    "wof:name":"Madonna Home Inc",
    "wof:placetype":"venue"
},
  "geometry": {"coordinates":[-76.296334,36.879278],"type":"Point"}
}