{
  "type": "Feature",
  "properties": {
    "addr:full":"1214 Holland Rd Suffolk VA 23434",
    "addr:housenumber":"1214",
    "addr:postcode":"23434",
    "addr:street":"Holland Rd",
    "iso:country":"US",
    "sg:address":"1214 Holland Rd",
    "sg:city":"Suffolk",
    "sg:classifiers":[
        {
            "category":"Organizations",
            "subcategory":"Religious Organization",
            "type":"Services"
        }
    ],
    "sg:phone":"+1 757 539 2829",
    "sg:postcode":"23434",
    "sg:province":"VA",
    "wof:name":"Church Of God Of Prophecy",
    "wof:placetype":"venue"
},
  "geometry": {"coordinates":[-76.61380200000001,36.729954],"type":"Point"}
}