{
  "type": "Feature",
  "properties": {
    "addr:full":"2251 Lake Terrace Dr Harrisonburg VA 22802",
    "addr:housenumber":"2251",
    "addr:postcode":"22802",
    "addr:street":"Lake Terrace Dr",
    "iso:country":"US",
    "sg:address":"2251 Lake Terrace Dr",
    "sg:city":"Harrisonburg",
    "sg:classifiers":[
        {
            "category":"Insurance",
            "subcategory":"Insurance Agent",
            "type":"Services"
        }
    ],
    "sg:phone":"+1 540 434 7858",
    "sg:postcode":"22802",
    "sg:province":"VA",
    "wof:name":"Aflac",
    "wof:placetype":"venue"
},
  "geometry": {"coordinates":[-78.871225,38.487723],"type":"Point"}
}