{
  "type": "Feature",
  "properties": {
    "iso:country":"US",
    "sg:address":"82 Ferguson Ln",
    "sg:city":"Newport News",
    "sg:classifiers":[
        {
            "category":"Health Services",
            "subcategory":"Health Practitioner",
            "type":"Services"
        }
    ],
    "sg:phone":"+1 757 594 9289",
    "sg:postcode":"23601",
    "sg:province":"VA",
    "sg:tags":[
        "technician",
        "dental",
        "hygienist"
    ],
    "wof:name":"Marilyn Dosier Martin",
    "wof:placetype":"venue"
},
  "geometry": {"coordinates":[-76.474766,37.067471],"type":"Point"}
}