{
  "type": "Feature",
  "properties": {
    "iso:country":"US",
    "sg:address":"6960 Birch St",
    "sg:city":"Falls Church",
    "sg:classifiers":[
        {
            "category":"Manufacturing",
            "subcategory":"Textiles",
            "type":"Manufacturing & Wholesale Goods"
        }
    ],
    "sg:phone":"+1 703 532 6556",
    "sg:postcode":"22046",
    "sg:province":"VA",
    "sg:tags":[
        "scarf"
    ],
    "wof:name":"Wrappa-Doodle",
    "wof:placetype":"venue"
},
  "geometry": {"coordinates":[-77.186072,38.895932],"type":"Point"}
}