{
  "type": "Feature",
  "properties": {
    "addr:full":"713 Lee Hwy Pulaski VA 24301",
    "addr:housenumber":"713",
    "addr:postcode":"24301",
    "addr:street":"Lee Hwy",
    "iso:country":"US",
    "sg:address":"713 Lee Hwy",
    "sg:city":"Pulaski",
    "sg:classifiers":[
        {
            "category":"Autos & Motor Vehicles",
            "subcategory":"Automobile Sales",
            "type":"Retail Goods"
        }
    ],
    "sg:phone":"+1 540 980 7000",
    "sg:postcode":"24301",
    "sg:province":"VA",
    "sg:tags":[
        "car",
        "used",
        "dealer"
    ],
    "wof:name":"Ike's Auto Sales",
    "wof:placetype":"venue"
},
  "geometry": {"coordinates":[-80.774007,37.053622],"type":"Point"}
}