{
  "type": "Feature",
  "properties": {
    "iso:country":"US",
    "sg:address":"812 Commonwealth Ave",
    "sg:city":"Bristol",
    "sg:classifiers":[
        {
            "category":"Restaurant",
            "type":"Food & Drink"
        }
    ],
    "sg:phone":"+1 276 669 6788",
    "sg:postcode":"24201",
    "sg:province":"VA",
    "wof:name":"China Luck Restaurant",
    "wof:placetype":"venue"
},
  "geometry": {"coordinates":[-82.192458,36.603646],"type":"Point"}
}