{
  "type": "Feature",
  "properties": {
    "addr:full":"239 N Sycamore St Petersburg VA 23803",
    "addr:housenumber":"239",
    "addr:postcode":"23803",
    "addr:street":"N Sycamore",
    "iso:country":"US",
    "sg:address":"239 N Sycamore St",
    "sg:city":"Petersburg",
    "sg:classifiers":[
        {
            "category":"Personal",
            "type":"Services"
        }
    ],
    "sg:phone":"+1 804 861 3534",
    "sg:postcode":"23803",
    "sg:province":"VA",
    "wof:name":"J&V Outreach Ministries",
    "wof:placetype":"venue"
},
  "geometry": {"coordinates":[-77.404385,37.230805],"type":"Point"}
}