{
  "type": "Feature",
  "properties": {
    "iso:country":"US",
    "sg:address":"14048 Eagle Chase Cir",
    "sg:city":"Chantilly",
    "sg:classifiers":[
        {
            "category":"Professional",
            "subcategory":"Management & Consulting",
            "type":"Services"
        }
    ],
    "sg:phone":"+1 571 338 2346",
    "sg:postcode":"20151",
    "sg:province":"VA",
    "sg:tags":[
        "lobbying"
    ],
    "wof:name":"Marcone Paul & Associates LLC",
    "wof:placetype":"venue"
},
  "geometry": {"coordinates":[-77.431175,38.877101],"type":"Point"}
}