{
  "type": "Feature",
  "properties": {
    "addr:full":"108 Whitewood Rd Charlottesville VA 22901",
    "addr:housenumber":"108",
    "addr:postcode":"22901",
    "addr:street":"Whitewood Rd",
    "iso:country":"US",
    "sg:address":"108 Whitewood Rd",
    "sg:city":"Charlottesville",
    "sg:classifiers":[
        {
            "category":"Health Services",
            "subcategory":"Clinic",
            "type":"Services"
        },
        {
            "category":"Health Services",
            "subcategory":"Health Practitioner",
            "type":"Services"
        }
    ],
    "sg:phone":"+1 434 963 0324",
    "sg:postcode":"22901",
    "sg:province":"VA",
    "sg:tags":[
        "nutritionist",
        "counseling",
        "mental"
    ],
    "wof:name":"Franke-Fuller Kirsten Lcsw",
    "wof:placetype":"venue"
},
  "geometry": {"coordinates":[-78.496002,38.074699],"type":"Point"}
}