{
  "type": "Feature",
  "properties": {
    "iso:country":"US",
    "sg:address":"1600 N Oak St",
    "sg:city":"Arlington",
    "sg:classifiers":[
        {
            "category":"Health Services",
            "subcategory":"Doctor",
            "type":"Services"
        }
    ],
    "sg:phone":"+1 703 243 0217",
    "sg:postcode":"22209",
    "sg:province":"VA",
    "wof:name":"Less Martin Dr",
    "wof:placetype":"venue"
},
  "geometry": {"coordinates":[-77.076599,38.893398],"type":"Point"}
}