{
  "type": "Feature",
  "properties": {
    "addr:full":"1426 Double Church Rd Stephens City VA 22655",
    "addr:housenumber":"1426",
    "addr:postcode":"22655",
    "addr:street":"Double Church Rd",
    "iso:country":"US",
    "sg:address":"1426 Double Church Rd",
    "sg:city":"Stephens City",
    "sg:classifiers":[
        {
            "category":"Wholesale",
            "subcategory":"Meat",
            "type":"Manufacturing & Wholesale Goods"
        }
    ],
    "sg:phone":"+1 540 869 1029",
    "sg:postcode":"22655",
    "sg:province":"VA",
    "sg:tags":[
        "house",
        "slaughter"
    ],
    "wof:name":"Gores Processing",
    "wof:placetype":"venue"
},
  "geometry": {"coordinates":[-78.19068799999999,39.055506],"type":"Point"}
}