{
  "type": "Feature",
  "properties": {
    "addr:full":"2933 Summerfield Rd Falls Church VA 22042",
    "addr:housenumber":"2933",
    "addr:postcode":"22042",
    "addr:street":"Summerfield Rd",
    "iso:country":"US",
    "sg:address":"2933 Summerfield Rd",
    "sg:city":"Falls Church",
    "sg:classifiers":[
        {
            "category":"Building & Trades",
            "subcategory":"Construction",
            "type":"Services"
        }
    ],
    "sg:phone":"+1 703 531 0148",
    "sg:postcode":"22042",
    "sg:province":"VA",
    "sg:tags":[
        "carpentry",
        "contractor"
    ],
    "wof:name":"Tocoa Carpentry Inc",
    "wof:placetype":"venue"
},
  "geometry": {"coordinates":[-77.17952099999999,38.870782],"type":"Point"}
}