{
  "type": "Feature",
  "properties": {
    "addr:full":"3640 Pine Grove Rd Stanley VA 22851",
    "addr:housenumber":"3640",
    "addr:postcode":"22851",
    "addr:street":"Pine Grove Rd",
    "iso:country":"US",
    "sg:address":"3640 Pine Grove Rd",
    "sg:city":"Stanley",
    "sg:classifiers":[
        {
            "category":"Farming",
            "subcategory":"Poultry Farm",
            "type":"Manufacturing & Wholesale Goods"
        }
    ],
    "sg:phone":"+1 540 778 1104",
    "sg:postcode":"22851",
    "sg:province":"VA",
    "sg:tags":[
        "egg"
    ],
    "wof:name":"James Seal Poultry",
    "wof:placetype":"venue"
},
  "geometry": {"coordinates":[-78.479,38.535718],"type":"Point"}
}