{
  "type": "Feature",
  "properties": {
    "addr:full":"8101 Staples Mill Rd Richmond VA 23228",
    "addr:housenumber":"8101",
    "addr:postcode":"23228",
    "addr:street":"Staples Mill Rd",
    "iso:country":"US",
    "sg:address":"8101 Staples Mill Rd",
    "sg:city":"Richmond",
    "sg:classifiers":[
        {
            "category":"Shopping",
            "subcategory":"Jewelry",
            "type":"Retail Goods"
        }
    ],
    "sg:phone":"+1 804 266 0600",
    "sg:postcode":"23228",
    "sg:province":"VA",
    "sg:tags":[
        "jeweler"
    ],
    "wof:name":"Beverly Hills Jewelers",
    "wof:placetype":"venue"
},
  "geometry": {"coordinates":[-77.504623,37.626419],"type":"Point"}
}