{
  "type": "Feature",
  "properties": {
    "addr:full":"8 S Crenshaw Ave Richmond VA 23221",
    "addr:housenumber":"8",
    "addr:postcode":"23221",
    "addr:street":"S Crenshaw Ave",
    "iso:country":"US",
    "sg:address":"8 S Crenshaw Ave",
    "sg:city":"Richmond",
    "sg:classifiers":[
        {
            "category":"Shopping",
            "subcategory":"Books",
            "type":"Retail Goods"
        }
    ],
    "sg:phone":"+1 804 257 7146",
    "sg:postcode":"23221",
    "sg:province":"VA",
    "sg:tags":[
        "store"
    ],
    "wof:name":"Quality Adult Books",
    "wof:placetype":"venue"
},
  "geometry": {"coordinates":[-77.485131,37.554828],"type":"Point"}
}