{
  "type": "Feature",
  "properties": {
    "iso:country":"US",
    "sg:address":"4011 Huntwood Rd",
    "sg:city":"Richmond",
    "sg:classifiers":[
        {
            "category":"Professional",
            "subcategory":"Employment Agencies",
            "type":"Services"
        }
    ],
    "sg:phone":"+1 804 674 7661",
    "sg:postcode":"23235",
    "sg:province":"VA",
    "sg:tags":[
        "help",
        "supply"
    ],
    "wof:name":"Ramsey Frank E Dr Facep",
    "wof:placetype":"venue"
},
  "geometry": {"coordinates":[-77.544933,37.452257],"type":"Point"}
}