{
  "type": "Feature",
  "properties": {
    "addr:full":"21414 Chesterfield Ave Petersburg VA 23803",
    "addr:housenumber":"21414",
    "addr:postcode":"23803",
    "addr:street":"Chesterfield Ave",
    "iso:country":"US",
    "sg:address":"21414 Chesterfield Ave",
    "sg:city":"Petersburg",
    "sg:classifiers":[
        {
            "category":"Government",
            "subcategory":"Post Office",
            "type":"Public Place"
        }
    ],
    "sg:phone":"+1 804 526 7541",
    "sg:postcode":"23803",
    "sg:province":"VA",
    "wof:name":"US Post Office",
    "wof:placetype":"venue"
},
  "geometry": {"coordinates":[-77.42099,37.233437],"type":"Point"}
}