{
  "type": "Feature",
  "properties": {
    "addr:full":"3023 Sugar Ln Vienna VA 22181",
    "addr:housenumber":"3023",
    "addr:postcode":"22181",
    "addr:street":"Sugar Ln",
    "iso:country":"US",
    "sg:address":"3023 Sugar Ln",
    "sg:city":"Vienna",
    "sg:classifiers":[
        {
            "category":"Professional",
            "subcategory":"Management & Consulting",
            "type":"Services"
        }
    ],
    "sg:phone":"+1 703 242 0312",
    "sg:postcode":"22181",
    "sg:province":"VA",
    "wof:name":"Tein",
    "wof:placetype":"venue"
},
  "geometry": {"coordinates":[-77.286289,38.87514],"type":"Point"}
}