{
  "type": "Feature",
  "properties": {
    "addr:full":"8100 Boone Blvd Vienna VA 22182",
    "addr:housenumber":"8100",
    "addr:postcode":"22182",
    "addr:street":"Boone Blvd",
    "iso:country":"US",
    "sg:address":"8100 Boone Blvd",
    "sg:city":"Vienna",
    "sg:classifiers":[
        {
            "category":"Professional",
            "subcategory":"Lawyer & Legal Services",
            "type":"Services"
        }
    ],
    "sg:phone":"+1 703 790 8750",
    "sg:postcode":"22182",
    "sg:province":"VA",
    "sg:tags":[
        "firm",
        "attorney",
        "law"
    ],
    "wof:name":"Wickwire Gavin PC",
    "wof:placetype":"venue"
},
  "geometry": {"coordinates":[-77.22763399999999,38.914172],"type":"Point"}
}