{
  "type": "Feature",
  "properties": {
    "addr:full":"872 General Puller Hwy Saluda VA 23149",
    "addr:housenumber":"872",
    "addr:postcode":"23149",
    "addr:street":"General Puller Hwy",
    "iso:country":"US",
    "sg:address":"872 General Puller Hwy",
    "sg:city":"Saluda",
    "sg:classifiers":[
        {
            "category":"Organizations",
            "subcategory":"Non-profit Organization",
            "type":"Services"
        }
    ],
    "sg:phone":"+1 804 758 9398",
    "sg:postcode":"23149",
    "sg:province":"VA",
    "sg:tags":[
        "information",
        "alcoholism",
        "treatment"
    ],
    "sg:website":"www.rvuc.com",
    "wof:name":"Middle Peninsula Northern Neck",
    "wof:placetype":"venue"
},
  "geometry": {"coordinates":[-76.59469199999999,37.605987],"type":"Point"}
}