{
  "type": "Feature",
  "properties": {
    "addr:full":"12449 Christanna Hwy Lawrenceville VA 23868",
    "addr:housenumber":"12449",
    "addr:postcode":"23868",
    "addr:street":"Christanna Hwy",
    "iso:country":"US",
    "sg:address":"12449 Christanna Hwy",
    "sg:city":"Lawrenceville",
    "sg:classifiers":[
        {
            "category":"Professional",
            "subcategory":"Business Services",
            "type":"Services"
        }
    ],
    "sg:phone":"+1 434 848 4064",
    "sg:postcode":"23868",
    "sg:province":"VA",
    "wof:name":"Bask Creative Design",
    "wof:placetype":"venue"
},
  "geometry": {"coordinates":[-77.855665,36.693064],"type":"Point"}
}