{
  "type": "Feature",
  "properties": {
    "iso:country":"US",
    "sg:address":"3011 Nutley St",
    "sg:city":"Fairfax",
    "sg:classifiers":[
        {
            "category":"Coffee & Tea",
            "type":"Food & Drink"
        }
    ],
    "sg:menulink":"http://www.allmenus.com/va/providence/111992-starbucks-coffee/menu/",
    "sg:phone":"+1 703 645 8788",
    "sg:postcode":"22031",
    "sg:province":"VA",
    "sg:tags":[
        "american"
    ],
    "wof:name":"Starbucks Coffee",
    "wof:placetype":"venue"
},
  "geometry": {"coordinates":[-77.262942,38.871726],"type":"Point"}
}