{
  "type": "Feature",
  "properties": {
    "iso:country":"US",
    "sg:address":"1308 Burlington Rd",
    "sg:city":"Virginia Beach",
    "sg:classifiers":[
        {
            "category":"Building & Trades",
            "subcategory":"Construction",
            "type":"Services"
        }
    ],
    "sg:phone":"+1 757 495 6936",
    "sg:postcode":"23464",
    "sg:province":"VA",
    "sg:tags":[
        "contractor"
    ],
    "wof:name":"Edwards Home Maintenance",
    "wof:placetype":"venue"
},
  "geometry": {"coordinates":[-76.16801700000001,36.800171],"type":"Point"}
}