{
  "type": "Feature",
  "properties": {
    "iso:country":"US",
    "sg:address":"11924 Second Branch Rd",
    "sg:city":"Chesterfield",
    "sg:classifiers":[
        {
            "category":"Building & Trades",
            "subcategory":"Construction",
            "type":"Services"
        }
    ],
    "sg:phone":"+1 804 790 0344",
    "sg:postcode":"23838",
    "sg:province":"VA",
    "sg:tags":[
        "house"
    ],
    "wof:name":"Settle Construction",
    "wof:placetype":"venue"
},
  "geometry": {"coordinates":[-77.62915099999999,37.342615],"type":"Point"}
}