{
  "type": "Feature",
  "properties": {
    "addr:full":"6535 Frontier Dr Springfield VA 22150",
    "addr:housenumber":"6535",
    "addr:postcode":"22150",
    "addr:street":"Frontier Dr",
    "iso:country":"US",
    "sg:address":"6535 Frontier Dr",
    "sg:city":"Springfield",
    "sg:classifiers":[
        {
            "category":"Retail",
            "subcategory":"Veterinary Services",
            "type":"Services"
        }
    ],
    "sg:phone":"+1 703 313 8429",
    "sg:postcode":"22150",
    "sg:province":"VA",
    "sg:tags":[
        "clinic",
        "hospital",
        "veterinarian",
        "specialty"
    ],
    "sg:website":"http://www.banfield.net/ypoffer/?source=yp",
    "wof:name":"Banfield the Pet Hospital",
    "wof:placetype":"venue"
},
  "geometry": {"coordinates":[-77.171671,38.777095],"type":"Point"}
}