{
  "type": "Feature",
  "properties": {
    "iso:country":"US",
    "sg:address":"8449 Leesburg Pike",
    "sg:city":"Vienna",
    "sg:classifiers":[
        {
            "category":"Shopping",
            "subcategory":"Hobbies, Toys, & Games",
            "type":"Retail Goods"
        }
    ],
    "sg:phone":"+1 703 893 2223",
    "sg:postcode":"22182",
    "sg:province":"VA",
    "sg:tags":[
        "toy",
        "store"
    ],
    "sg:website":"www.toysrus.com",
    "wof:name":"Toys R US",
    "wof:placetype":"venue"
},
  "geometry": {"coordinates":[-77.23870100000001,38.9254],"type":"Point"}
}