{
  "type": "Feature",
  "properties": {
    "addr:full":"8090-L Tysons Corner Ctr McLean VA 22102",
    "addr:housenumber":"8090-l",
    "addr:postcode":"22102",
    "addr:street":"Tysons Corner Ctr",
    "iso:country":"US",
    "sg:address":"8090-L Tysons Corner Ctr",
    "sg:city":"McLean",
    "sg:classifiers":[
        {
            "category":"Education",
            "subcategory":"Vocational School",
            "type":"Public Place"
        }
    ],
    "sg:phone":"+1 703 288 0008",
    "sg:postcode":"22102",
    "sg:province":"VA",
    "sg:tags":[
        "cosmetology"
    ],
    "sg:website":"www.paulmitchelltheschooltysonsc...",
    "wof:name":"Paul Mitchell The School",
    "wof:placetype":"venue"
},
  "geometry": {"coordinates":[-77.223196,38.914406],"type":"Point"}
}