{
  "type": "Feature",
  "properties": {
    "addr:full":"3719 Rolling Hill Ave NW Roanoke VA 24017",
    "addr:housenumber":"3719",
    "addr:postcode":"24017",
    "addr:street":"Rolling Hill Ave Nw",
    "iso:country":"US",
    "sg:address":"3719 Rolling Hill Ave NW",
    "sg:city":"Roanoke",
    "sg:classifiers":[
        {
            "category":"Social Services",
            "subcategory":"Child Care",
            "type":"Services"
        }
    ],
    "sg:phone":"+1 540 345 6361",
    "sg:postcode":"24017",
    "sg:province":"VA",
    "sg:tags":[
        "day"
    ],
    "wof:name":"R & R Daycare",
    "wof:placetype":"venue"
},
  "geometry": {"coordinates":[-80.002489,37.282296],"type":"Point"}
}