{
  "type": "Feature",
  "properties": {
    "addr:full":"920 Eastnor Ct Newport News VA 23608",
    "addr:housenumber":"920",
    "addr:postcode":"23608",
    "addr:street":"Eastnor Ct",
    "iso:country":"US",
    "sg:address":"920 Eastnor Ct",
    "sg:city":"Newport News",
    "sg:classifiers":[
        {
            "category":"Building & Trades",
            "subcategory":"Cleaning & Sanitation",
            "type":"Services"
        }
    ],
    "sg:phone":"+1 757 871 9800",
    "sg:postcode":"23608",
    "sg:province":"VA",
    "sg:tags":[
        "maintenance"
    ],
    "wof:name":"Fonvilles B Fclty Maint Consl",
    "wof:placetype":"venue"
},
  "geometry": {"coordinates":[-76.514021,37.153901],"type":"Point"}
}