{
  "type": "Feature",
  "properties": {
    "addr:full":"1359 Orange Rd Culpeper VA 22701",
    "addr:housenumber":"1359",
    "addr:postcode":"22701",
    "addr:street":"Orange Rd",
    "iso:country":"US",
    "sg:address":"1359 Orange Rd",
    "sg:city":"Culpeper",
    "sg:classifiers":[
        {
            "category":"Restaurant",
            "type":"Food & Drink"
        }
    ],
    "sg:phone":"+1 540 829 9966",
    "sg:postcode":"22701",
    "sg:province":"VA",
    "wof:name":"Country Cafe",
    "wof:placetype":"venue"
},
  "geometry": {"coordinates":[-77.997795,38.462824],"type":"Point"}
}