{
  "type": "Feature",
  "properties": {
    "iso:country":"US",
    "sg:address":"4017 W Lewis Rd",
    "sg:city":"Hampton",
    "sg:classifiers":[
        {
            "category":"Building & Trades",
            "subcategory":"Construction",
            "type":"Services"
        }
    ],
    "sg:phone":"+1 757 827 7666",
    "sg:postcode":"23666",
    "sg:province":"VA",
    "sg:tags":[
        "house"
    ],
    "wof:name":"Eternal",
    "wof:placetype":"venue"
},
  "geometry": {"coordinates":[-76.422303,37.022579],"type":"Point"}
}