{
  "type": "Feature",
  "properties": {
    "iso:country":"US",
    "sg:address":"4716 Washington Blvd",
    "sg:city":"Arlington",
    "sg:classifiers":[
        {
            "category":"Professional",
            "subcategory":"Lawyer & Legal Services",
            "type":"Services"
        }
    ],
    "sg:phone":"+1 703 525 4810",
    "sg:postcode":"22205",
    "sg:province":"VA",
    "wof:name":"Katz Craig D Lwyr",
    "wof:placetype":"venue"
},
  "geometry": {"coordinates":[-77.120796,38.885399],"type":"Point"}
}