{
  "type": "Feature",
  "properties": {
    "addr:full":"6356 Cavalier Corridor Falls Church VA 22044",
    "addr:housenumber":"6356",
    "addr:postcode":"22044",
    "addr:street":"Cavalier Corridor",
    "iso:country":"US",
    "sg:address":"6356 Cavalier Corridor",
    "sg:city":"Falls Church",
    "sg:classifiers":[
        {
            "category":"Professional",
            "subcategory":"Management & Consulting",
            "type":"Services"
        }
    ],
    "sg:phone":"+1 703 256 2067",
    "sg:postcode":"22044",
    "sg:province":"VA",
    "sg:tags":[
        "economic"
    ],
    "wof:name":"Datum International",
    "wof:placetype":"venue"
},
  "geometry": {"coordinates":[-77.15884800000001,38.849249],"type":"Point"}
}