{
  "type": "Feature",
  "properties": {
    "addr:full":"340 N Pleasant Valley Rd Winchester VA 22601",
    "addr:housenumber":"340",
    "addr:postcode":"22601",
    "addr:street":"N Pleasant Valley Rd",
    "iso:country":"US",
    "sg:address":"340 N Pleasant Valley Rd",
    "sg:city":"Winchester",
    "sg:classifiers":[
        {
            "category":"Government",
            "subcategory":"Post Office",
            "type":"Public Place"
        }
    ],
    "sg:phone":"+1 540 662 2553",
    "sg:postcode":"22601",
    "sg:province":"VA",
    "wof:name":"US Post Office",
    "wof:placetype":"venue"
},
  "geometry": {"coordinates":[-78.153316,39.185486],"type":"Point"}
}