{
  "type": "Feature",
  "properties": {
    "addr:full":"558 W Main St Stanley VA 22851",
    "addr:housenumber":"558",
    "addr:postcode":"22851",
    "addr:street":"W Main St",
    "iso:country":"US",
    "sg:address":"558 W Main St",
    "sg:city":"Stanley",
    "sg:classifiers":[
        {
            "category":"Food & Beverages",
            "subcategory":"Groceries & Convenience Stores",
            "type":"Retail Goods"
        }
    ],
    "sg:phone":"+1 540 778 2081",
    "sg:postcode":"22851",
    "sg:province":"VA",
    "sg:tags":[
        "grocer"
    ],
    "sg:website":"www.foodlion.com",
    "wof:name":"Food Lion",
    "wof:placetype":"venue"
},
  "geometry": {"coordinates":[-78.51306599999999,38.576843],"type":"Point"}
}