{
  "type": "Feature",
  "properties": {
    "addr:full":"14442 Minnieville Rd Woodbridge VA 22193",
    "addr:postcode":"14442;22193",
    "addr:street":"Minnieville Rd",
    "iso:country":"US",
    "sg:address":"14442 Minnieville Rd",
    "sg:city":"Woodbridge",
    "sg:classifiers":[
        {
            "category":"Building & Trades",
            "subcategory":"Construction",
            "type":"Services"
        }
    ],
    "sg:phone":"+1 703 670 3485",
    "sg:postcode":"22193",
    "sg:province":"VA",
    "sg:tags":[
        "carpentry",
        "contractor"
    ],
    "wof:name":"T&N Trim Inc",
    "wof:placetype":"venue"
},
  "geometry": {"coordinates":[-77.355098,38.635024],"type":"Point"}
}