{
  "type": "Feature",
  "properties": {
    "addr:full":"10660 Aviation Ln Manassas VA 20110",
    "addr:housenumber":"10660",
    "addr:postcode":"20110",
    "addr:street":"Aviation Ln",
    "iso:country":"US",
    "sg:address":"10660 Aviation Ln",
    "sg:city":"Manassas",
    "sg:classifiers":[
        {
            "category":"Manufacturing",
            "subcategory":"Aerospace",
            "type":"Manufacturing & Wholesale Goods"
        }
    ],
    "sg:phone":"+1 703 369 0500",
    "sg:postcode":"20110",
    "sg:province":"VA",
    "sg:tags":[
        "equipment",
        "aircraft",
        "parts"
    ],
    "sg:website":"www.capital-aviation.com",
    "wof:name":"Capital Aviation Instruments",
    "wof:placetype":"venue"
},
  "geometry": {"coordinates":[-77.514926,38.730511],"type":"Point"}
}