{
  "type": "Feature",
  "properties": {
    "addr:full":"4491 Holly Ave Fairfax VA 22030",
    "addr:housenumber":"4491",
    "addr:postcode":"22030",
    "addr:street":"Holly Ave",
    "iso:country":"US",
    "sg:address":"4491 Holly Ave",
    "sg:city":"Fairfax",
    "sg:classifiers":[
        {
            "category":"Cinema",
            "subcategory":"Movie Rental",
            "type":"Entertainment"
        }
    ],
    "sg:phone":"+1 703 802 8112",
    "sg:postcode":"22030",
    "sg:province":"VA",
    "sg:tags":[
        "video",
        "tape"
    ],
    "wof:name":"Dollar Video Stores Virginia",
    "wof:placetype":"venue"
},
  "geometry": {"coordinates":[-77.35906199999999,38.850285],"type":"Point"}
}