{
  "type": "Feature",
  "properties": {
    "iso:country":"US",
    "sg:address":"470 Denbigh Blvd",
    "sg:city":"Newport News",
    "sg:classifiers":[
        {
            "category":"Restaurant",
            "type":"Food & Drink"
        }
    ],
    "sg:menulink":"http://www.allmenus.com/va/newport-news/41599-chanellos-pizza/menu/",
    "sg:phone":"+1 757 989 0000",
    "sg:postcode":"23608",
    "sg:province":"VA",
    "sg:tags":[
        "american",
        "pizza"
    ],
    "wof:name":"Chanello's Pizza",
    "wof:placetype":"venue"
},
  "geometry": {"coordinates":[-76.53083599999999,37.132862],"type":"Point"}
}