{
  "type": "Feature",
  "properties": {
    "addr:full":"1055 Edwards Ferry Rd NE Leesburg VA 20176",
    "addr:housenumber":"1055",
    "addr:postcode":"20176",
    "addr:street":"Edwards Ferry Rd Ne",
    "iso:country":"US",
    "sg:address":"1055 Edwards Ferry Rd NE",
    "sg:city":"Leesburg",
    "sg:classifiers":[
        {
            "category":"Health Services",
            "subcategory":"Chiropractor",
            "type":"Services"
        }
    ],
    "sg:phone":"+1 703 443 0900",
    "sg:postcode":"20176",
    "sg:province":"VA",
    "wof:name":"Di Lorenzo Chiropractic",
    "wof:placetype":"venue"
},
  "geometry": {"coordinates":[-77.537891,39.113536],"type":"Point"}
}