{
  "type": "Feature",
  "properties": {
    "iso:country":"US",
    "sg:address":"1805 Library Street",
    "sg:city":"Reston",
    "sg:classifiers":[
        {
            "category":"Professional",
            "subcategory":"Computer Services",
            "type":"Services"
        }
    ],
    "sg:phone":"+1 703 709 9019",
    "sg:postcode":"20190",
    "sg:province":"VA",
    "sg:website":"http://www.learningtree.com/",
    "wof:name":"Learning Tree International",
    "wof:placetype":"venue"
},
  "geometry": {"coordinates":[-77.35862,38.957924],"type":"Point"}
}