{
  "type": "Feature",
  "properties": {
    "addr:full":"19304 Creek Field Cir Leesburg VA 20176",
    "addr:housenumber":"19304",
    "addr:postcode":"20176",
    "addr:street":"Creek Field Cir",
    "iso:country":"US",
    "sg:address":"19304 Creek Field Cir",
    "sg:city":"Leesburg",
    "sg:classifiers":[
        {
            "category":"Professional",
            "subcategory":"Business Services",
            "type":"Services"
        }
    ],
    "sg:phone":"+1 703 456 6014",
    "sg:postcode":"20176",
    "sg:province":"VA",
    "sg:tags":[
        "translation",
        "arabic"
    ],
    "wof:name":"Sayyad Osama",
    "wof:placetype":"venue"
},
  "geometry": {"coordinates":[-77.485038,39.083493],"type":"Point"}
}