{
  "type": "Feature",
  "properties": {
    "addr:full":"11122 Tattersall Trl Oakton VA 22124",
    "addr:housenumber":"11122",
    "addr:postcode":"22124",
    "addr:street":"Tattersall Trl",
    "iso:country":"US",
    "sg:address":"11122 Tattersall Trl",
    "sg:city":"Oakton",
    "sg:classifiers":[
        {
            "category":"Professional",
            "subcategory":"Computer Services",
            "type":"Services"
        }
    ],
    "sg:phone":"+1 703 591 5645",
    "sg:postcode":"22124",
    "sg:province":"VA",
    "sg:tags":[
        "consulting",
        "related"
    ],
    "wof:name":"Robert H Parker",
    "wof:placetype":"venue"
},
  "geometry": {"coordinates":[-77.32877000000001,38.875254],"type":"Point"}
}