{
  "type": "Feature",
  "properties": {
    "iso:country":"US",
    "sg:address":"1790 E Market St",
    "sg:city":"Harrisonburg",
    "sg:classifiers":[
        {
            "category":"Banks & Credit Unions",
            "subcategory":"Bank",
            "type":"Services"
        }
    ],
    "sg:phone":"+1 540 433 1211",
    "sg:postcode":"22801",
    "sg:province":"VA",
    "sg:tags":[
        "financing"
    ],
    "sg:website":"www.beneficial.com",
    "wof:name":"Beneficial Virginia Inc",
    "wof:placetype":"venue"
},
  "geometry": {"coordinates":[-78.84259299999999,38.431238],"type":"Point"}
}