{
  "type": "Feature",
  "properties": {
    "addr:full":"14746 Winterfield Ct Centreville VA 20120",
    "addr:housenumber":"14746",
    "addr:postcode":"20120",
    "addr:street":"Winterfield Ct",
    "iso:country":"US",
    "sg:address":"14746 Winterfield Ct",
    "sg:city":"Centreville",
    "sg:classifiers":[
        {
            "category":"Real Estate",
            "subcategory":"Real Estate Agent",
            "type":"Services"
        }
    ],
    "sg:phone":"+1 703 830 5376",
    "sg:postcode":"20120",
    "sg:province":"VA",
    "wof:name":"Westfield Appraisal Service",
    "wof:placetype":"venue"
},
  "geometry": {"coordinates":[-77.45625200000001,38.85136],"type":"Point"}
}