{
  "type": "Feature",
  "properties": {
    "addr:full":"13514 Minnieville Rd Woodbridge VA 22192",
    "addr:housenumber":"13514",
    "addr:postcode":"22192",
    "addr:street":"Minnieville Rd",
    "iso:country":"US",
    "sg:address":"13514 Minnieville Rd",
    "sg:city":"Woodbridge",
    "sg:classifiers":[
        {
            "category":"Manufacturing",
            "subcategory":"Printing",
            "type":"Manufacturing & Wholesale Goods"
        }
    ],
    "sg:phone":"+1 703 583 8399",
    "sg:postcode":"22192",
    "sg:province":"VA",
    "sg:tags":[
        "printer",
        "commercial"
    ],
    "wof:name":"L & G Lithographics",
    "wof:placetype":"venue"
},
  "geometry": {"coordinates":[-77.30736,38.655691],"type":"Point"}
}