{
  "type": "Feature",
  "properties": {
    "addr:full":"4527 17th St N Arlington VA 22207",
    "addr:housenumber":"4527",
    "addr:postcode":"22207",
    "addr:street":"17Th St N",
    "iso:country":"US",
    "sg:address":"4527 17th St N",
    "sg:city":"Arlington",
    "sg:classifiers":[
        {
            "category":"Personal",
            "type":"Services"
        }
    ],
    "sg:phone":"+1 703 525 0050",
    "sg:postcode":"22207",
    "sg:province":"VA",
    "wof:name":"National Genealogical Society",
    "wof:placetype":"venue"
},
  "geometry": {"coordinates":[-77.114756,38.891604],"type":"Point"}
}