{
  "type": "Feature",
  "properties": {
    "addr:full":"12999 Warwick Blvd Newport News VA 23602",
    "addr:housenumber":"12999",
    "addr:postcode":"23602",
    "addr:street":"Warwick Blvd",
    "iso:country":"US",
    "sg:address":"12999 Warwick Blvd",
    "sg:city":"Newport News",
    "sg:classifiers":[
        {
            "category":"Restaurant",
            "type":"Food & Drink"
        }
    ],
    "sg:phone":"+1 757 249 9022",
    "sg:postcode":"23602",
    "sg:province":"VA",
    "sg:tags":[
        "eating"
    ],
    "wof:name":"Dairy Queen",
    "wof:placetype":"venue"
},
  "geometry": {"coordinates":[-76.512181,37.103893],"type":"Point"}
}