{
  "type": "Feature",
  "properties": {
    "addr:full":"603 Main St Danville VA 24541",
    "addr:housenumber":"603",
    "addr:postcode":"24541",
    "addr:street":"Main St",
    "iso:country":"US",
    "sg:address":"603 Main St",
    "sg:city":"Danville",
    "sg:classifiers":[
        {
            "category":"Retail",
            "subcategory":"Repair Shop",
            "type":"Services"
        }
    ],
    "sg:phone":"+1 434 799 8463",
    "sg:postcode":"24541",
    "sg:province":"VA",
    "sg:tags":[
        "watch"
    ],
    "wof:name":"Watch Doctor Inc",
    "wof:placetype":"venue"
},
  "geometry": {"coordinates":[-79.394583,36.586822],"type":"Point"}
}