{
  "type": "Feature",
  "properties": {
    "iso:country":"US",
    "sg:address":"1108 E Main St",
    "sg:city":"Richmond",
    "sg:classifiers":[
        {
            "category":"Organizations",
            "subcategory":"Professional Association",
            "type":"Services"
        }
    ],
    "sg:phone":"+1 804 346 0522",
    "sg:postcode":"23219",
    "sg:province":"VA",
    "wof:name":"Richmond Area Municipal Contrs",
    "wof:placetype":"venue"
},
  "geometry": {"coordinates":[-77.434603,37.537308],"type":"Point"}
}