{
  "type": "Feature",
  "properties": {
    "iso:country":"US",
    "sg:address":"399 Pendleton St",
    "sg:city":"Alexandria",
    "sg:classifiers":[
        {
            "category":"Real Estate",
            "subcategory":"Real Estate Operator",
            "type":"Services"
        }
    ],
    "sg:phone":"+1 703 548 4946",
    "sg:postcode":"22314",
    "sg:province":"VA",
    "sg:tags":[
        "apartment"
    ],
    "wof:name":"Pendleton House Apartments",
    "wof:placetype":"venue"
},
  "geometry": {"coordinates":[-77.04132799999999,38.810179],"type":"Point"}
}