{
  "type": "Feature",
  "properties": {
    "addr:full":"9864 Daphna Rd Broadway VA 22815",
    "addr:housenumber":"9864",
    "addr:postcode":"22815",
    "addr:street":"Daphna Rd",
    "iso:country":"US",
    "sg:address":"9864 Daphna Rd",
    "sg:city":"Broadway",
    "sg:classifiers":[
        {
            "category":"Health Services",
            "subcategory":"Medical Lab",
            "type":"Services"
        }
    ],
    "sg:phone":"+1 540 896 9559",
    "sg:postcode":"22815",
    "sg:province":"VA",
    "sg:tags":[
        "laboratory",
        "dental"
    ],
    "wof:name":"J C Dental Lab",
    "wof:placetype":"venue"
},
  "geometry": {"coordinates":[-78.803467,38.566485],"type":"Point"}
}