{
  "type": "Feature",
  "properties": {
    "addr:full":"23228 Old Valley Pike Woodstock VA 22664",
    "addr:housenumber":"23228",
    "addr:postcode":"22664",
    "addr:street":"Old Valley Pike",
    "iso:country":"US",
    "sg:address":"23228 Old Valley Pike",
    "sg:city":"Woodstock",
    "sg:classifiers":[
        {
            "category":"Restaurant",
            "type":"Food & Drink"
        }
    ],
    "sg:phone":"+1 540 459 4747",
    "sg:postcode":"22664",
    "sg:province":"VA",
    "wof:name":"Double Overtime Sports Grille",
    "wof:placetype":"venue"
},
  "geometry": {"coordinates":[-78.479608,38.909867],"type":"Point"}
}