{
  "type": "Feature",
  "properties": {
    "addr:full":"3330 Virginia Beach Blvd Virginia Beach VA 23452",
    "addr:housenumber":"3330",
    "addr:postcode":"23452",
    "addr:street":"Virginia Beach Blvd",
    "iso:country":"US",
    "sg:address":"3330 Virginia Beach Blvd",
    "sg:city":"Virginia Beach",
    "sg:classifiers":[
        {
            "category":"Food & Beverages",
            "subcategory":"Groceries & Convenience Stores",
            "type":"Retail Goods"
        }
    ],
    "sg:phone":"+1 757 486 0040",
    "sg:postcode":"23452",
    "sg:province":"VA",
    "sg:website":"www.kroger.com",
    "wof:name":"Kroger",
    "wof:placetype":"venue"
},
  "geometry": {"coordinates":[-76.088853,36.841935],"type":"Point"}
}