{
  "type": "Feature",
  "properties": {
    "iso:country":"US",
    "sg:address":"2026 Plank Rd",
    "sg:city":"Fredericksburg",
    "sg:classifiers":[
        {
            "category":"Food & Beverages",
            "subcategory":"Groceries & Convenience Stores",
            "type":"Retail Goods"
        }
    ],
    "sg:phone":"+1 540 368 0085",
    "sg:postcode":"22401",
    "sg:province":"VA",
    "sg:tags":[
        "grocer"
    ],
    "wof:name":"Latino Market & Jewelry",
    "wof:placetype":"venue"
},
  "geometry": {"coordinates":[-77.495293,38.29578],"type":"Point"}
}