{
  "type": "Feature",
  "properties": {
    "iso:country":"US",
    "sg:address":"1404 Mud Pike",
    "sg:city":"Christiansburg",
    "sg:classifiers":[
        {
            "category":"Organizations",
            "subcategory":"Religious Organization",
            "type":"Services"
        }
    ],
    "sg:phone":"+1 540 382 7956",
    "sg:postcode":"24073",
    "sg:province":"VA",
    "sg:tags":[
        "church"
    ],
    "wof:name":"New Hope Church Of God",
    "wof:placetype":"venue"
},
  "geometry": {"coordinates":[-80.421322,37.118425],"type":"Point"}
}