{
  "type": "Feature",
  "properties": {
    "iso:country":"US",
    "sg:address":"104 Sunset Dr",
    "sg:city":"Amherst",
    "sg:classifiers":[
        {
            "category":"Organizations",
            "subcategory":"Religious Organization",
            "type":"Services"
        }
    ],
    "sg:phone":"+1 434 946 2524",
    "sg:postcode":"24521",
    "sg:province":"VA",
    "sg:tags":[
        "church"
    ],
    "wof:name":"Epiphany Anglican Church",
    "wof:placetype":"venue"
},
  "geometry": {"coordinates":[-79.060436,37.58049],"type":"Point"}
}