{
  "type": "Feature",
  "properties": {
    "addr:full":"300 Dicks Hollow Rd Winchester VA 22603",
    "addr:housenumber":"300",
    "addr:postcode":"22603",
    "addr:street":"Dicks Hollow Rd",
    "iso:country":"US",
    "sg:address":"300 Dicks Hollow Rd",
    "sg:city":"Winchester",
    "sg:classifiers":[
        {
            "category":"Building & Trades",
            "subcategory":"Construction",
            "type":"Services"
        }
    ],
    "sg:phone":"+1 540 877 1197",
    "sg:postcode":"22603",
    "sg:province":"VA",
    "sg:tags":[
        "contractor"
    ],
    "wof:name":"Bucher Roofing & Siding Co",
    "wof:placetype":"venue"
},
  "geometry": {"coordinates":[-78.245626,39.205214],"type":"Point"}
}