{
  "type": "Feature",
  "properties": {
    "addr:full":"13553 Midlothian Tpke Midlothian VA 23113",
    "addr:housenumber":"13553",
    "addr:postcode":"23113",
    "addr:street":"Midlothian Tpke",
    "iso:country":"US",
    "sg:address":"13553 Midlothian Tpke",
    "sg:city":"Midlothian",
    "sg:classifiers":[
        {
            "category":"Restaurant",
            "type":"Food & Drink"
        }
    ],
    "sg:menulink":"http://www.allmenus.com/va/midlothian/86101-little-caesars-pizza/menu/",
    "sg:phone":"+1 804 379 1999",
    "sg:postcode":"23113",
    "sg:province":"VA",
    "sg:tags":[
        "american",
        "pizza"
    ],
    "wof:name":"Little Caesar's Pizza",
    "wof:placetype":"venue"
},
  "geometry": {"coordinates":[-77.650694,37.503414],"type":"Point"}
}