{
  "type": "Feature",
  "properties": {
    "addr:full":"2961 Ellenwood Dr Fairfax VA 22031",
    "addr:housenumber":"2961",
    "addr:postcode":"22031",
    "addr:street":"Ellenwood Dr",
    "iso:country":"US",
    "sg:address":"2961 Ellenwood Dr",
    "sg:city":"Fairfax",
    "sg:classifiers":[
        {
            "category":"Professional",
            "subcategory":"Art Services",
            "type":"Services"
        }
    ],
    "sg:phone":"+1 703 280 5743",
    "sg:postcode":"22031",
    "sg:province":"VA",
    "sg:tags":[
        "photography",
        "commercial"
    ],
    "wof:name":"John Skowronski Photography",
    "wof:placetype":"venue"
},
  "geometry": {"coordinates":[-77.2557,38.870115],"type":"Point"}
}