{
  "type": "Feature",
  "properties": {
    "addr:full":"2184 Shiloh Church Rd Bedford VA 24523",
    "addr:housenumber":"2184",
    "addr:postcode":"24523",
    "addr:street":"Shiloh Church Rd",
    "iso:country":"US",
    "sg:address":"2184 Shiloh Church Rd",
    "sg:city":"Bedford",
    "sg:classifiers":[
        {
            "category":"Professional",
            "subcategory":"Advertising",
            "type":"Services"
        }
    ],
    "sg:phone":"+1 540 586 6789",
    "sg:postcode":"24523",
    "sg:province":"VA",
    "sg:tags":[
        "agency"
    ],
    "wof:name":"Adgraphics",
    "wof:placetype":"venue"
},
  "geometry": {"coordinates":[-79.46986099999999,37.325573],"type":"Point"}
}