{
  "type": "Feature",
  "properties": {
    "iso:country":"US",
    "sg:address":"8229 Boone Blvd Ste 885",
    "sg:city":"Vienna",
    "sg:classifiers":[
        {
            "category":"Insurance",
            "subcategory":"Insurance Agent",
            "type":"Services"
        },
        {
            "category":"Insurance",
            "subcategory":"Hazard Insurance",
            "type":"Services"
        }
    ],
    "sg:phone":"+1 703 821 1620",
    "sg:postcode":"22182",
    "sg:province":"VA",
    "sg:tags":[
        "property",
        "commercial",
        "casualty",
        "business"
    ],
    "sg:website":"http://www.thehartford.com",
    "wof:name":"Capitol Underwriters Ltd",
    "wof:placetype":"venue"
},
  "geometry": {"coordinates":[-77.22849100000001,38.914648],"type":"Point"}
}