{
  "type": "Feature",
  "properties": {
    "addr:full":"9300 Burge Ave Richmond VA 23237",
    "addr:postcode":"9300;23237",
    "addr:street":"Burge Ave",
    "iso:country":"US",
    "sg:address":"9300 Burge Ave",
    "sg:city":"Richmond",
    "sg:classifiers":[
        {
            "category":"Building & Trades",
            "subcategory":"Equipment Rental",
            "type":"Services"
        }
    ],
    "sg:phone":"+1 804 271 6473",
    "sg:postcode":"23237",
    "sg:province":"VA",
    "sg:tags":[
        "heavy",
        "construction",
        "contractor"
    ],
    "sg:website":"www.hertzequip.com",
    "wof:name":"Hertz Equipment Rental Corp",
    "wof:placetype":"venue"
},
  "geometry": {"coordinates":[-77.42260899999999,37.401319],"type":"Point"}
}