{
  "type": "Feature",
  "properties": {
    "iso:country":"US",
    "sg:address":"12122 Monument Dr Unit 250",
    "sg:city":"Fairfax",
    "sg:classifiers":[
        {
            "category":"Real Estate",
            "subcategory":"Real Estate Services",
            "type":"Services"
        },
        {
            "category":"Building & Trades",
            "subcategory":"Cleaning & Sanitation",
            "type":"Services"
        }
    ],
    "sg:phone":"+1 703 537 0088",
    "sg:postcode":"22033",
    "sg:province":"VA",
    "sg:tags":[
        "maintenance",
        "cleaners-interior"
    ],
    "wof:name":"R&K's Cleaning Inc.",
    "wof:placetype":"venue"
},
  "geometry": {"coordinates":[-77.367627,38.863291],"type":"Point"}
}