{
  "type": "Feature",
  "properties": {
    "addr:full":"5211 Leeward Ln Alexandria VA 22315",
    "addr:housenumber":"5211",
    "addr:postcode":"22315",
    "addr:street":"Leeward Ln",
    "iso:country":"US",
    "sg:address":"5211 Leeward Ln",
    "sg:city":"Alexandria",
    "sg:classifiers":[
        {
            "category":"Education",
            "subcategory":"Special Training",
            "type":"Public Place"
        }
    ],
    "sg:phone":"+1 703 922 5085",
    "sg:postcode":"22315",
    "sg:province":"VA",
    "sg:tags":[
        "book"
    ],
    "wof:name":"Great Ideas",
    "wof:placetype":"venue"
},
  "geometry": {"coordinates":[-77.12643300000001,38.768736],"type":"Point"}
}