{
  "type": "Feature",
  "properties": {
    "addr:full":"5403 Overland Ct Centreville VA 20120",
    "addr:housenumber":"5403",
    "addr:postcode":"20120",
    "addr:street":"Overland Ct",
    "iso:country":"US",
    "sg:address":"5403 Overland Ct",
    "sg:city":"Centreville",
    "sg:classifiers":[
        {
            "category":"Shopping",
            "subcategory":"Hobbies, Toys, & Games",
            "type":"Retail Goods"
        }
    ],
    "sg:phone":"+1 703 815 1211",
    "sg:postcode":"20120",
    "sg:province":"VA",
    "sg:tags":[
        "product",
        "ceramic"
    ],
    "wof:name":"Alor International Quality",
    "wof:placetype":"venue"
},
  "geometry": {"coordinates":[-77.460257,38.863463],"type":"Point"}
}