{
  "type": "Feature",
  "properties": {
    "addr:full":"1131 Glendale Rd Galax VA 24333",
    "addr:housenumber":"1131",
    "addr:postcode":"24333",
    "addr:street":"Glendale Rd",
    "iso:country":"US",
    "sg:address":"1131 Glendale Rd",
    "sg:city":"Galax",
    "sg:classifiers":[
        {
            "category":"Wholesale",
            "subcategory":"Auto Parts",
            "type":"Manufacturing & Wholesale Goods"
        }
    ],
    "sg:phone":"+1 276 236 2030",
    "sg:postcode":"24333",
    "sg:province":"VA",
    "sg:tags":[
        "tire"
    ],
    "sg:website":"www.sstire.com",
    "wof:name":"S & S Tire",
    "wof:placetype":"venue"
},
  "geometry": {"coordinates":[-80.889436,36.688552],"type":"Point"}
}