{
  "type": "Feature",
  "properties": {
    "addr:full":"1669 N Quaker Ln Alexandria VA 22302",
    "addr:housenumber":"1669",
    "addr:postcode":"22302",
    "addr:street":"N Quaker Ln",
    "iso:country":"US",
    "sg:address":"1669 N Quaker Ln",
    "sg:city":"Alexandria",
    "sg:classifiers":[
        {
            "category":"Retail",
            "subcategory":"Laundry & Dry Cleaning",
            "type":"Services"
        }
    ],
    "sg:phone":"+1 703 998 6221",
    "sg:postcode":"22302",
    "sg:province":"VA",
    "sg:tags":[
        "drycleaning",
        "plant",
        "power"
    ],
    "wof:name":"K&H Cleaners",
    "wof:placetype":"venue"
},
  "geometry": {"coordinates":[-77.08519,38.830999],"type":"Point"}
}