{
  "type": "Feature",
  "properties": {
    "addr:full":"4821 Rocking Horse Ln Charles City VA 23030",
    "addr:housenumber":"4821",
    "addr:postcode":"23030",
    "addr:street":"Rocking Horse Ln",
    "iso:country":"US",
    "sg:address":"4821 Rocking Horse Ln",
    "sg:city":"Charles City",
    "sg:classifiers":[
        {
            "category":"Building & Trades",
            "subcategory":"Construction",
            "type":"Services"
        }
    ],
    "sg:phone":"+1 804 829 5920",
    "sg:postcode":"23030",
    "sg:province":"VA",
    "sg:tags":[
        "contractor"
    ],
    "wof:name":"Adkins Siding Window Co",
    "wof:placetype":"venue"
},
  "geometry": {"coordinates":[-77.183407,37.439672],"type":"Point"}
}