{
  "type": "Feature",
  "properties": {
    "iso:country":"US",
    "sg:address":"9625 Line Fence Rd",
    "sg:city":"Hayes",
    "sg:phone":"+1 804 642 6845",
    "sg:postcode":"23072",
    "sg:province":"VA",
    "sg:tags":[
        "farm",
        "corn",
        "soybean"
    ],
    "wof:name":"Elliott Hogg",
    "wof:placetype":"venue"
},
  "geometry": {"coordinates":[-76.42532199999999,37.283019],"type":"Point"}
}