{
  "type": "Feature",
  "properties": {
    "iso:country":"US",
    "sg:address":"6791 Powhatan Dr",
    "sg:city":"Hayes",
    "sg:classifiers":[
        {
            "category":"Building & Trades",
            "subcategory":"Construction",
            "type":"Services"
        }
    ],
    "sg:phone":"+1 804 642 9446",
    "sg:postcode":"23072",
    "sg:province":"VA",
    "sg:tags":[
        "excavating",
        "contractor"
    ],
    "wof:name":"R L Cooke Excavating",
    "wof:placetype":"venue"
},
  "geometry": {"coordinates":[-76.523158,37.293737],"type":"Point"}
}