{
  "type": "Feature",
  "properties": {
    "addr:full":"13 Charles St Luray VA 22835",
    "addr:housenumber":"13",
    "addr:postcode":"22835",
    "addr:street":"Charles St",
    "iso:country":"US",
    "sg:address":"13 Charles St",
    "sg:city":"Luray",
    "sg:classifiers":[
        {
            "category":"Shopping",
            "subcategory":"Gifts & Souvenirs",
            "type":"Retail Goods"
        }
    ],
    "sg:phone":"+1 540 743 7799",
    "sg:postcode":"22835",
    "sg:province":"VA",
    "wof:name":"Roachs Shop",
    "wof:placetype":"venue"
},
  "geometry": {"coordinates":[-78.421922,38.650783],"type":"Point"}
}