{
  "type": "Feature",
  "properties": {
    "addr:full":"1314 S Main St Blacksburg VA 24060",
    "addr:housenumber":"1314",
    "addr:postcode":"24060",
    "addr:street":"S Main St",
    "iso:country":"US",
    "sg:address":"1314 S Main St",
    "sg:city":"Blacksburg",
    "sg:classifiers":[
        {
            "category":"Shopping",
            "type":"Retail Goods"
        }
    ],
    "sg:phone":"+1 540 953 1655",
    "sg:postcode":"24060",
    "sg:province":"VA",
    "sg:tags":[
        "merchandise"
    ],
    "wof:name":"Original Frameworks",
    "wof:placetype":"venue"
},
  "geometry": {"coordinates":[-80.40175600000001,37.217586],"type":"Point"}
}