{
  "type": "Feature",
  "properties": {
    "iso:country":"US",
    "sg:address":"3117 Annandale Rd",
    "sg:city":"Falls Church",
    "sg:classifiers":[
        {
            "category":"Building & Trades",
            "subcategory":"Construction",
            "type":"Services"
        }
    ],
    "sg:phone":"+1 703 534 1537",
    "sg:postcode":"22042",
    "sg:province":"VA",
    "sg:tags":[
        "contractor"
    ],
    "wof:name":"City Construction Inc",
    "wof:placetype":"venue"
},
  "geometry": {"coordinates":[-77.175326,38.865662],"type":"Point"}
}