{
  "type": "Feature",
  "properties": {
    "addr:full":"220 Sweeney Blvd Hampton VA 23665",
    "addr:housenumber":"220",
    "addr:postcode":"23665",
    "addr:street":"Sweeney Blvd",
    "iso:country":"US",
    "sg:address":"220 Sweeney Blvd",
    "sg:city":"Hampton",
    "sg:classifiers":[
        {
            "category":"Government",
            "subcategory":"Office",
            "type":"Public Place"
        }
    ],
    "sg:phone":"+1 757 764 5705",
    "sg:postcode":"23665",
    "sg:province":"VA",
    "sg:tags":[
        "national",
        "security"
    ],
    "wof:name":"Security Forces",
    "wof:placetype":"venue"
},
  "geometry": {"coordinates":[-76.344224,37.084426],"type":"Point"}
}