{
  "type": "Feature",
  "properties": {
    "addr:full":"61 Old Sawmill Rd Blue Ridge VA 24064",
    "addr:housenumber":"61",
    "addr:postcode":"24064",
    "addr:street":"Old Sawmill Rd",
    "iso:country":"US",
    "sg:address":"61 Old Sawmill Rd",
    "sg:city":"Blue Ridge",
    "sg:classifiers":[
        {
            "category":"Building & Trades",
            "subcategory":"Construction",
            "type":"Services"
        }
    ],
    "sg:phone":"+1 540 977 1888",
    "sg:postcode":"24064",
    "sg:province":"VA",
    "sg:tags":[
        "house"
    ],
    "wof:name":"B R I",
    "wof:placetype":"venue"
},
  "geometry": {"coordinates":[-79.79929199999999,37.351174],"type":"Point"}
}