{
  "type": "Feature",
  "properties": {
    "addr:full":"10900 Warwick Blvd Newport News VA 23601",
    "addr:housenumber":"10900",
    "addr:postcode":"23601",
    "addr:street":"Warwick Blvd",
    "iso:country":"US",
    "sg:address":"10900 Warwick Blvd",
    "sg:city":"Newport News",
    "sg:classifiers":[
        {
            "category":"Restaurant",
            "type":"Food & Drink"
        }
    ],
    "sg:menulink":"http://www.allmenus.com/va/newport-news/46881-bills-seafood-house/menu/",
    "sg:phone":"+1 757 898 4903",
    "sg:postcode":"23601",
    "sg:province":"VA",
    "sg:tags":[
        "seafood",
        "american"
    ],
    "wof:name":"Bill's Seafood House",
    "wof:placetype":"venue"
},
  "geometry": {"coordinates":[-76.472104,37.042376],"type":"Point"}
}