{
  "type": "Feature",
  "properties": {
    "iso:country":"US",
    "sg:address":"195 Orapax Rd",
    "sg:city":"Kilmarnock",
    "sg:classifiers":[
        {
            "category":"Shopping",
            "subcategory":"Beauty & Cosmetics",
            "type":"Retail Goods"
        }
    ],
    "sg:phone":"+1 804 435 9996",
    "sg:postcode":"22482",
    "sg:province":"VA",
    "sg:tags":[
        "merchandise"
    ],
    "wof:name":"Yvonne Glass",
    "wof:placetype":"venue"
},
  "geometry": {"coordinates":[-76.346143,37.702633],"type":"Point"}
}