{
  "type": "Feature",
  "properties": {
    "addr:full":"9335 Fletchers Chapel Rd King George VA 22485",
    "addr:housenumber":"9335",
    "addr:postcode":"22485",
    "addr:street":"Fletchers Chapel Rd",
    "iso:country":"US",
    "sg:address":"9335 Fletchers Chapel Rd",
    "sg:city":"King George",
    "sg:classifiers":[
        {
            "category":"Professional",
            "subcategory":"Management & Consulting",
            "type":"Services"
        }
    ],
    "sg:phone":"+1 540 775 9455",
    "sg:postcode":"22485",
    "sg:province":"VA",
    "sg:tags":[
        "business"
    ],
    "wof:name":"McCroskey Bus Consulting Svcs",
    "wof:placetype":"venue"
},
  "geometry": {"coordinates":[-77.323176,38.285608],"type":"Point"}
}