{
  "type": "Feature",
  "properties": {
    "iso:country":"US",
    "sg:address":"141 Spencer Ter SE",
    "sg:city":"Leesburg",
    "sg:classifiers":[
        {
            "category":"Professional",
            "subcategory":"Engineering",
            "type":"Services"
        }
    ],
    "sg:phone":"+1 703 779 2152",
    "sg:postcode":"20175",
    "sg:province":"VA",
    "sg:tags":[
        "consultant"
    ],
    "wof:name":"Blaustein and Associated",
    "wof:placetype":"venue"
},
  "geometry": {"coordinates":[-77.540048,39.091114],"type":"Point"}
}