{
  "type": "Feature",
  "properties": {
    "iso:country":"US",
    "sg:address":"990 Amber Ridge Rd",
    "sg:city":"Charlottesville",
    "sg:classifiers":[
        {
            "category":"Professional",
            "subcategory":"Research",
            "type":"Services"
        }
    ],
    "sg:phone":"+1 434 243 2705",
    "sg:postcode":"22901",
    "sg:province":"VA",
    "sg:tags":[
        "researcher"
    ],
    "wof:name":"Gubareva Larisa",
    "wof:placetype":"venue"
},
  "geometry": {"coordinates":[-78.663506,38.065333],"type":"Point"}
}