{
  "type": "Feature",
  "properties": {
    "iso:country":"US",
    "sg:address":"5 Fort Evans Rd SE",
    "sg:city":"Leesburg",
    "sg:classifiers":[
        {
            "category":"Banks & Credit Unions",
            "subcategory":"Bank",
            "type":"Services"
        }
    ],
    "sg:phone":"+1 703 777 3133",
    "sg:postcode":"20175",
    "sg:province":"VA",
    "sg:tags":[
        "depository",
        "banking"
    ],
    "wof:name":"Leesburg Checks Cashed",
    "wof:placetype":"venue"
},
  "geometry": {"coordinates":[-77.549239,39.10717],"type":"Point"}
}