{
  "type": "Feature",
  "properties": {
    "iso:country":"US",
    "sg:address":"2318 Deepwater Terminal Rd",
    "sg:city":"Richmond",
    "sg:classifiers":[
        {
            "category":"Manufacturing",
            "subcategory":"Tools & Machinery",
            "type":"Manufacturing & Wholesale Goods"
        }
    ],
    "sg:phone":"+1 804 359 3223",
    "sg:postcode":"23234",
    "sg:province":"VA",
    "sg:tags":[
        "control"
    ],
    "wof:name":"Hajoca Corp",
    "wof:placetype":"venue"
},
  "geometry": {"coordinates":[-77.431737,37.491822],"type":"Point"}
}