{
  "type": "Feature",
  "properties": {
    "addr:full":"10032 Main St 250 Fairfax VA 22031",
    "addr:housenumber":"10032;250",
    "addr:postcode":"22031",
    "addr:street":"Main St",
    "iso:country":"US",
    "sg:address":"10032 Main St 250",
    "sg:city":"Fairfax",
    "sg:classifiers":[
        {
            "category":"Health Services",
            "subcategory":"Chiropractor",
            "type":"Services"
        }
    ],
    "sg:phone":"+1 202 345 2000",
    "sg:postcode":"22031",
    "sg:province":"VA",
    "sg:tags":[
        "chiropractic"
    ],
    "wof:name":"Jennifer M Lee Ltd",
    "wof:placetype":"venue"
},
  "geometry": {"coordinates":[-77.293931,38.844094],"type":"Point"}
}