{
  "type": "Feature",
  "properties": {
    "iso:country":"US",
    "sg:address":"6030 Ice Pond Ln",
    "sg:city":"Hanover",
    "sg:classifiers":[
        {
            "category":"Building & Trades",
            "subcategory":"Construction",
            "type":"Services"
        }
    ],
    "sg:phone":"+1 804 730 7664",
    "sg:postcode":"23069",
    "sg:province":"VA",
    "sg:tags":[
        "house"
    ],
    "wof:name":"Branel Construction",
    "wof:placetype":"venue"
},
  "geometry": {"coordinates":[-77.302581,37.687699],"type":"Point"}
}