{
  "type": "Feature",
  "properties": {
    "addr:full":"7400 Allan Ave Falls Church VA 22046",
    "addr:housenumber":"7400",
    "addr:postcode":"22046",
    "addr:street":"Allan Ave",
    "iso:country":"US",
    "sg:address":"7400 Allan Ave",
    "sg:city":"Falls Church",
    "sg:classifiers":[
        {
            "category":"Building & Trades",
            "subcategory":"Landscaping Services",
            "type":"Services"
        }
    ],
    "sg:phone":"+1 703 698 0299",
    "sg:postcode":"22046",
    "sg:province":"VA",
    "wof:name":"Delatorre Landscaping",
    "wof:placetype":"venue"
},
  "geometry": {"coordinates":[-77.202922,38.88757],"type":"Point"}
}