{
  "type": "Feature",
  "properties": {
    "addr:full":"8817 Portner Ave Manassas VA 20110",
    "addr:housenumber":"8817",
    "addr:postcode":"20110",
    "addr:street":"Portner Ave",
    "iso:country":"US",
    "sg:address":"8817 Portner Ave",
    "sg:city":"Manassas",
    "sg:classifiers":[
        {
            "category":"Real Estate",
            "subcategory":"Real Estate Operator",
            "type":"Services"
        }
    ],
    "sg:phone":"+1 703 368 2195",
    "sg:postcode":"20110",
    "sg:province":"VA",
    "sg:tags":[
        "building",
        "apartment"
    ],
    "wof:name":"Deer Park Apartments",
    "wof:placetype":"venue"
},
  "geometry": {"coordinates":[-77.464781,38.762339],"type":"Point"}
}