{
  "type": "Feature",
  "properties": {
    "iso:country":"US",
    "sg:address":"1510 Spring Gate Dr",
    "sg:city":"Mc Lean",
    "sg:classifiers":[
        {
            "category":"Real Estate",
            "subcategory":"Real Estate Agent",
            "type":"Services"
        }
    ],
    "sg:phone":"+1 703 442 0000",
    "sg:postcode":"22102",
    "sg:province":"VA",
    "wof:name":"Gates of McClean",
    "wof:placetype":"venue"
},
  "geometry": {"coordinates":[-77.21084500000001,38.92724],"type":"Point"}
}