{
  "type": "Feature",
  "properties": {
    "addr:full":"8901 Jefferson Davis Hwy Fredericksburg VA 22407",
    "addr:housenumber":"8901",
    "addr:postcode":"22407",
    "addr:street":"Jefferson Davis Hwy",
    "iso:country":"US",
    "sg:address":"8901 Jefferson Davis Hwy",
    "sg:city":"Fredericksburg",
    "sg:classifiers":[
        {
            "category":"Retail",
            "subcategory":"Auto Repair",
            "type":"Services"
        }
    ],
    "sg:phone":"+1 804 224 5300",
    "sg:postcode":"22407",
    "sg:province":"VA",
    "sg:tags":[
        "body",
        "automobile",
        "painting"
    ],
    "wof:name":"Pro Auto LLC",
    "wof:placetype":"venue"
},
  "geometry": {"coordinates":[-77.507238,38.201423],"type":"Point"}
}