{
  "type": "Feature",
  "properties": {
    "addr:full":"100 Executive Dr Sterling VA 20166",
    "addr:housenumber":"100",
    "addr:postcode":"20166",
    "addr:street":"Executive Dr",
    "iso:country":"US",
    "sg:address":"100 Executive Dr",
    "sg:city":"Sterling",
    "sg:classifiers":[
        {
            "category":"Retail",
            "subcategory":"Repair Shop",
            "type":"Services"
        }
    ],
    "sg:phone":"+1 703 842 5750",
    "sg:postcode":"20166",
    "sg:province":"VA",
    "sg:tags":[
        "lock",
        "locksmith"
    ],
    "wof:name":"1 All Day Emergency",
    "wof:placetype":"venue"
},
  "geometry": {"coordinates":[-77.444954,38.985541],"type":"Point"}
}