{
  "type": "Feature",
  "properties": {
    "addr:full":"2705 Willow Brook Rd Bumpass VA 23024",
    "addr:housenumber":"2705",
    "addr:postcode":"23024",
    "addr:street":"Willow Brook Rd",
    "iso:country":"US",
    "sg:address":"2705 Willow Brook Rd",
    "sg:city":"Bumpass",
    "sg:classifiers":[
        {
            "category":"Building & Trades",
            "subcategory":"Landscaping Services",
            "type":"Services"
        }
    ],
    "sg:phone":"+1 540 872 2600",
    "sg:postcode":"23024",
    "sg:province":"VA",
    "sg:tags":[
        "tree"
    ],
    "wof:name":"Great Dane Tree Service",
    "wof:placetype":"venue"
},
  "geometry": {"coordinates":[-77.790342,37.852057],"type":"Point"}
}