{
  "type": "Feature",
  "properties": {
    "addr:full":"321 N 23rd St Richmond VA 23223",
    "addr:housenumber":"321",
    "addr:postcode":"23223",
    "addr:street":"N 23Rd St",
    "iso:country":"US",
    "sg:address":"321 N 23rd St",
    "sg:city":"Richmond",
    "sg:classifiers":[
        {
            "category":"Professional",
            "subcategory":"Lawyer & Legal Services",
            "type":"Services"
        }
    ],
    "sg:phone":"+1 804 648 3325",
    "sg:postcode":"23223",
    "sg:province":"VA",
    "sg:tags":[
        "attorney"
    ],
    "wof:name":"Lambert & Assoc",
    "wof:placetype":"venue"
},
  "geometry": {"coordinates":[-77.419884,37.533384],"type":"Point"}
}