{
  "type": "Feature",
  "properties": {
    "addr:full":"4604 Quartz Rock Ct Chantilly VA 20151",
    "addr:housenumber":"4604",
    "addr:postcode":"20151",
    "addr:street":"Quartz Rock Ct",
    "iso:country":"US",
    "sg:address":"4604 Quartz Rock Ct",
    "sg:city":"Chantilly",
    "sg:classifiers":[
        {
            "category":"Shopping",
            "type":"Retail Goods"
        }
    ],
    "sg:phone":"+1 703 802 0697",
    "sg:postcode":"20151",
    "sg:province":"VA",
    "sg:tags":[
        "cosmetic",
        "perfume"
    ],
    "wof:name":"Mary Kay Cosmetics",
    "wof:placetype":"venue"
},
  "geometry": {"coordinates":[-77.41185,38.863329],"type":"Point"}
}