{
  "type": "Feature",
  "properties": {
    "iso:country":"US",
    "sg:address":"6235 Little River Tpke",
    "sg:city":"Alexandria",
    "sg:classifiers":[
        {
            "category":"Retail",
            "subcategory":"Laundry & Dry Cleaning",
            "type":"Services"
        }
    ],
    "sg:phone":"+1 703 914 4999",
    "sg:postcode":"22312",
    "sg:province":"VA",
    "sg:tags":[
        "cleaners"
    ],
    "wof:name":"Grand Cleaners",
    "wof:placetype":"venue"
},
  "geometry": {"coordinates":[-77.141555,38.817637],"type":"Point"}
}