{
  "type": "Feature",
  "properties": {
    "addr:full":"19296 Bethel Rd Abingdon VA 24211",
    "addr:housenumber":"19296",
    "addr:postcode":"24211",
    "addr:street":"Bethel Rd",
    "iso:country":"US",
    "sg:address":"19296 Bethel Rd",
    "sg:city":"Abingdon",
    "sg:classifiers":[
        {
            "category":"Organizations",
            "subcategory":"Religious Organization",
            "type":"Services"
        }
    ],
    "sg:phone":"+1 276 628 9054",
    "sg:postcode":"24211",
    "sg:province":"VA",
    "sg:tags":[
        "church"
    ],
    "wof:name":"Bethel Presbyterian Manse",
    "wof:placetype":"venue"
},
  "geometry": {"coordinates":[-81.881158,36.677322],"type":"Point"}
}