{
  "type": "Feature",
  "properties": {
    "addr:full":"7280 Berwick Rd Richmond VA 23225",
    "addr:housenumber":"7280",
    "addr:postcode":"23225",
    "addr:street":"Berwick Rd",
    "iso:country":"US",
    "sg:address":"7280 Berwick Rd",
    "sg:city":"Richmond",
    "sg:classifiers":[
        {
            "category":"Building & Trades",
            "subcategory":"Construction",
            "type":"Services"
        }
    ],
    "sg:phone":"+1 804 230 0066",
    "sg:postcode":"23225",
    "sg:province":"VA",
    "sg:tags":[
        "industrial",
        "contractor"
    ],
    "wof:name":"Kenneth W Lester General Contr",
    "wof:placetype":"venue"
},
  "geometry": {"coordinates":[-77.527816,37.54076],"type":"Point"}
}