{
  "type": "Feature",
  "properties": {
    "addr:full":"7228 Columbia Pike Annandale VA 22003",
    "addr:housenumber":"7228",
    "addr:postcode":"22003",
    "addr:street":"Columbia Pike",
    "iso:country":"US",
    "sg:address":"7228 Columbia Pike",
    "sg:city":"Annandale",
    "sg:classifiers":[
        {
            "category":"Personal",
            "subcategory":"Beauty Salon",
            "type":"Services"
        }
    ],
    "sg:phone":"+1 703 941 3887",
    "sg:postcode":"22003",
    "sg:province":"VA",
    "wof:name":"Hair We R In Annandale",
    "wof:placetype":"venue"
},
  "geometry": {"coordinates":[-77.19618800000001,38.830576],"type":"Point"}
}