{
  "type": "Feature",
  "properties": {
    "addr:full":"487 W Reservoir Rd Woodstock VA 22664",
    "addr:housenumber":"487",
    "addr:postcode":"22664",
    "addr:street":"W Reservoir Rd",
    "iso:country":"US",
    "sg:address":"487 W Reservoir Rd",
    "sg:city":"Woodstock",
    "sg:classifiers":[
        {
            "category":"Shopping",
            "type":"Retail Goods"
        }
    ],
    "sg:phone":"+1 540 975 0005",
    "sg:postcode":"22664",
    "sg:province":"VA",
    "sg:tags":[
        "merchandise"
    ],
    "wof:name":"Cfw Wireless Communications",
    "wof:placetype":"venue"
},
  "geometry": {"coordinates":[-78.532606,38.872589],"type":"Point"}
}