{
  "type": "Feature",
  "properties": {
    "iso:country":"US",
    "sg:address":"1205 Mount Pleasant Dr",
    "sg:city":"Suffolk",
    "sg:classifiers":[
        {
            "category":"Wholesale",
            "subcategory":"Medical Equipment & Supplies",
            "type":"Manufacturing & Wholesale Goods"
        }
    ],
    "sg:phone":"+1 757 934 0739",
    "sg:postcode":"23434",
    "sg:province":"VA",
    "wof:name":"Rose One Systems Inc",
    "wof:placetype":"venue"
},
  "geometry": {"coordinates":[-76.608688,36.736181],"type":"Point"}
}