{
  "type": "Feature",
  "properties": {
    "addr:full":"2606 Lusters Gate Rd Blacksburg VA 24060",
    "addr:housenumber":"2606",
    "addr:postcode":"24060",
    "addr:street":"Lusters Gate Rd",
    "iso:country":"US",
    "sg:address":"2606 Lusters Gate Rd",
    "sg:city":"Blacksburg",
    "sg:classifiers":[
        {
            "category":"Retail",
            "subcategory":"Auto Repair",
            "type":"Services"
        }
    ],
    "sg:phone":"+1 540 552 2795",
    "sg:postcode":"24060",
    "sg:province":"VA",
    "sg:tags":[
        "carwash",
        "general"
    ],
    "wof:name":"Rays Magic Wash",
    "wof:placetype":"venue"
},
  "geometry": {"coordinates":[-80.364104,37.240979],"type":"Point"}
}