{
  "type": "Feature",
  "properties": {
    "addr:full":"6449 Williamson Rd Roanoke VA 24019",
    "addr:housenumber":"6449",
    "addr:postcode":"24019",
    "addr:street":"Williamson Rd",
    "iso:country":"US",
    "sg:address":"6449 Williamson Rd",
    "sg:city":"Roanoke",
    "sg:classifiers":[
        {
            "category":"Shopping",
            "subcategory":"Bicycles & Sporting Goods",
            "type":"Retail Goods"
        }
    ],
    "sg:phone":"+1 540 366 2520",
    "sg:postcode":"24019",
    "sg:province":"VA",
    "wof:name":"Gone Fishin",
    "wof:placetype":"venue"
},
  "geometry": {"coordinates":[-79.95512100000001,37.335303],"type":"Point"}
}