{
  "type": "Feature",
  "properties": {
    "addr:full":"501 W Main St Wise VA 24293",
    "addr:housenumber":"501",
    "addr:postcode":"24293",
    "addr:street":"W Main St",
    "iso:country":"US",
    "sg:address":"501 W Main St",
    "sg:city":"Wise",
    "sg:classifiers":[
        {
            "category":"Government",
            "subcategory":"Police Station",
            "type":"Public Place"
        }
    ],
    "sg:phone":"+1 276 328 9369",
    "sg:postcode":"24293",
    "sg:province":"VA",
    "sg:tags":[
        "department"
    ],
    "wof:name":"Wise Police Dept",
    "wof:placetype":"venue"
},
  "geometry": {"coordinates":[-82.585599,36.981684],"type":"Point"}
}