{
  "type": "Feature",
  "properties": {
    "addr:full":"5957 E Virginia Beach Blvd Norfolk VA 23502",
    "addr:housenumber":"5957",
    "addr:postcode":"23502",
    "addr:street":"E Virginia Beach Blvd",
    "iso:country":"US",
    "sg:address":"5957 E Virginia Beach Blvd",
    "sg:city":"Norfolk",
    "sg:classifiers":[
        {
            "category":"Professional",
            "type":"Services"
        },
        {
            "category":"Professional",
            "subcategory":"Business Services",
            "type":"Services"
        },
        {
            "category":"Professional",
            "subcategory":"Printing & Photocopies",
            "type":"Services"
        },
        {
            "category":"Shopping",
            "subcategory":"Stationery & Office Supplies",
            "type":"Retail Goods"
        },
        {
            "category":"Manufacturing",
            "subcategory":"Printing",
            "type":"Manufacturing & Wholesale Goods"
        },
        {
            "category":"Manufacturing",
            "subcategory":"Signs",
            "type":"Manufacturing & Wholesale Goods"
        }
    ],
    "sg:phone":"+1 757 461 7136",
    "sg:postcode":"23502",
    "sg:province":"VA",
    "sg:tags":[
        "machine",
        "document",
        "duplicating",
        "shipping",
        "materials-shipping",
        "packaging",
        "packing",
        "imaging",
        "copying",
        "digital",
        "copy"
    ],
    "sg:website":"http://www.fedex.com/Dropoff/start?FY11-FXO-YELLOWPAGES",
    "wof:name":"FedEx Office Print & Ship Center",
    "wof:placetype":"venue"
},
  "geometry": {"coordinates":[-76.201477,36.855431],"type":"Point"}
}