{
  "type": "Feature",
  "properties": {
    "addr:full":"2409 Beacon Ln Richmond VA 23230",
    "addr:housenumber":"2409",
    "addr:postcode":"23230",
    "addr:street":"Beacon Ln",
    "iso:country":"US",
    "sg:address":"2409 Beacon Ln",
    "sg:city":"Richmond",
    "sg:classifiers":[
        {
            "category":"Retail",
            "subcategory":"Repair Shop",
            "type":"Services"
        }
    ],
    "sg:phone":"+1 804 285 9284",
    "sg:postcode":"23230",
    "sg:province":"VA",
    "sg:tags":[
        "good",
        "fur",
        "mfg"
    ],
    "wof:name":"Woodson S Taxidermy",
    "wof:placetype":"venue"
},
  "geometry": {"coordinates":[-77.49938400000001,37.596009],"type":"Point"}
}