{
  "type": "Feature",
  "properties": {
    "iso:country":"US",
    "sg:address":"37768 Chappelle Hill Rd",
    "sg:city":"Purcellville",
    "sg:classifiers":[
        {
            "category":"Travel",
            "subcategory":"Hotels & Motels",
            "type":"Entertainment"
        }
    ],
    "sg:phone":"+1 540 338 4548",
    "sg:postcode":"20132",
    "sg:province":"VA",
    "sg:tags":[
        "breakfast",
        "accommodation",
        "bed"
    ],
    "wof:name":"Creek Crossing Farm",
    "wof:placetype":"venue"
},
  "geometry": {"coordinates":[-77.708414,39.105089],"type":"Point"}
}