{
  "type": "Feature",
  "properties": {
    "addr:full":"1295 S Boston Rd Danville VA 24540",
    "addr:housenumber":"1295",
    "addr:postcode":"24540",
    "addr:street":"S Boston Rd",
    "iso:country":"US",
    "sg:address":"1295 S Boston Rd",
    "sg:city":"Danville",
    "sg:classifiers":[
        {
            "category":"Banks & Credit Unions",
            "subcategory":"Investment Brokerage",
            "type":"Services"
        }
    ],
    "sg:phone":"+1 434 791 2595",
    "sg:postcode":"24540",
    "sg:province":"VA",
    "sg:tags":[
        "security"
    ],
    "wof:name":"Edward Jones Investments",
    "wof:placetype":"venue"
},
  "geometry": {"coordinates":[-79.346538,36.581589],"type":"Point"}
}