{
  "type": "Feature",
  "properties": {
    "iso:country":"US",
    "sg:address":"535 Westfield Rd",
    "sg:city":"Charlottesville",
    "sg:classifiers":[
        {
            "category":"Health Services",
            "subcategory":"Health Practitioner",
            "type":"Services"
        }
    ],
    "sg:phone":"+1 434 975 1946",
    "sg:postcode":"22901",
    "sg:province":"VA",
    "sg:tags":[
        "psychologist"
    ],
    "wof:name":"Cognitive Behavioral Health",
    "wof:placetype":"venue"
},
  "geometry": {"coordinates":[-78.484544,38.073085],"type":"Point"}
}