{
  "type": "Feature",
  "properties": {
    "addr:full":"2637 Riner Rd Christiansburg VA 24073",
    "addr:housenumber":"2637",
    "addr:postcode":"24073",
    "addr:street":"Riner Rd",
    "iso:country":"US",
    "sg:address":"2637 Riner Rd",
    "sg:city":"Christiansburg",
    "sg:classifiers":[
        {
            "category":"Retail",
            "subcategory":"Veterinary Services",
            "type":"Services"
        }
    ],
    "sg:phone":"+1 540 382 1100",
    "sg:postcode":"24073",
    "sg:province":"VA",
    "sg:tags":[
        "veterinarian"
    ],
    "wof:name":"Appalachian Veterinary Svc",
    "wof:placetype":"venue"
},
  "geometry": {"coordinates":[-80.451142,37.088124],"type":"Point"}
}