{
  "type": "Feature",
  "properties": {
    "addr:full":"1300 Main St Lynchburg VA 24504",
    "addr:housenumber":"1300",
    "addr:postcode":"24504",
    "addr:street":"Main St",
    "iso:country":"US",
    "sg:address":"1300 Main St",
    "sg:city":"Lynchburg",
    "sg:classifiers":[
        {
            "category":"Shopping",
            "subcategory":"Used Merchandise",
            "type":"Retail Goods"
        }
    ],
    "sg:phone":"+1 434 845 0555",
    "sg:postcode":"24504",
    "sg:province":"VA",
    "sg:tags":[
        "antique"
    ],
    "wof:name":"Estate Specialist",
    "wof:placetype":"venue"
},
  "geometry": {"coordinates":[-79.138729,37.410863],"type":"Point"}
}