{
  "type": "Feature",
  "properties": {
    "addr:full":"736 Middle Ground Blvd Newport News VA 23606",
    "addr:housenumber":"736",
    "addr:postcode":"23606",
    "addr:street":"Middle Ground Blvd",
    "iso:country":"US",
    "sg:address":"736 Middle Ground Blvd",
    "sg:city":"Newport News",
    "sg:classifiers":[
        {
            "category":"Building & Trades",
            "subcategory":"Construction",
            "type":"Services"
        }
    ],
    "sg:phone":"+1 757 873 3762",
    "sg:postcode":"23606",
    "sg:province":"VA",
    "sg:tags":[
        "commercial",
        "contractor"
    ],
    "wof:name":"Epoc Construction Inc",
    "wof:placetype":"venue"
},
  "geometry": {"coordinates":[-76.48128800000001,37.089257],"type":"Point"}
}