{
  "type": "Feature",
  "properties": {
    "addr:full":"1917 Princess Anne St Fredericksburg VA 22401",
    "addr:housenumber":"1917",
    "addr:postcode":"22401",
    "addr:street":"Princess Anne St",
    "iso:country":"US",
    "sg:address":"1917 Princess Anne St",
    "sg:city":"Fredericksburg",
    "sg:classifiers":[
        {
            "category":"Restaurant",
            "type":"Food & Drink"
        }
    ],
    "sg:phone":"+1 540 371 0300",
    "sg:postcode":"22401",
    "sg:province":"VA",
    "wof:name":"Central Station",
    "wof:placetype":"venue"
},
  "geometry": {"coordinates":[-77.466568,38.311919],"type":"Point"}
}