{
  "type": "Feature",
  "properties": {
    "addr:full":"487 McLaws Cir Williamsburg VA 23185",
    "addr:housenumber":"487",
    "addr:postcode":"23185",
    "addr:street":"Mclaws Cir",
    "iso:country":"US",
    "sg:address":"487 McLaws Cir",
    "sg:city":"Williamsburg",
    "sg:classifiers":[
        {
            "category":"Professional",
            "subcategory":"Accounting & Tax Preparation",
            "type":"Services"
        }
    ],
    "sg:phone":"+1 757 259 0432",
    "sg:postcode":"23185",
    "sg:province":"VA",
    "sg:tags":[
        "accountant"
    ],
    "wof:name":"Clifton L Brigham CPA",
    "wof:placetype":"venue"
},
  "geometry": {"coordinates":[-76.66275,37.24856],"type":"Point"}
}