{
  "type": "Feature",
  "properties": {
    "addr:full":"4110 Main St Chincoteague VA 23336",
    "addr:housenumber":"4110",
    "addr:postcode":"23336",
    "addr:street":"Main St",
    "iso:country":"US",
    "sg:address":"4110 Main St",
    "sg:city":"Chincoteague",
    "sg:classifiers":[
        {
            "category":"Organizations",
            "subcategory":"Community Association",
            "type":"Services"
        }
    ],
    "sg:phone":"+1 757 336 1544",
    "sg:postcode":"23336",
    "sg:province":"VA",
    "wof:name":"Accomack Lodge",
    "wof:placetype":"venue"
},
  "geometry": {"coordinates":[-75.37575200000001,37.934398],"type":"Point"}
}