{
  "type": "Feature",
  "properties": {
    "addr:full":"60 Old Meribeth Rd Hampton VA 23669",
    "addr:housenumber":"60",
    "addr:postcode":"23669",
    "addr:street":"Old Meribeth Rd",
    "iso:country":"US",
    "sg:address":"60 Old Meribeth Rd",
    "sg:city":"Hampton",
    "sg:classifiers":[
        {
            "category":"Professional",
            "subcategory":"Engineering",
            "type":"Services"
        }
    ],
    "sg:phone":"+1 757 825 6497",
    "sg:postcode":"23669",
    "sg:province":"VA",
    "wof:name":"McSmith Engineering",
    "wof:placetype":"venue"
},
  "geometry": {"coordinates":[-76.338475,37.069022],"type":"Point"}
}