{
  "type": "Feature",
  "properties": {
    "iso:country":"US",
    "sg:address":"2428 Dew Meadow Ct",
    "sg:city":"Herndon",
    "sg:classifiers":[
        {
            "category":"Professional",
            "subcategory":"Management & Consulting",
            "type":"Services"
        }
    ],
    "sg:phone":"+1 571 241 7316",
    "sg:postcode":"20171",
    "sg:province":"VA",
    "wof:name":"S G Consulting",
    "wof:placetype":"venue"
},
  "geometry": {"coordinates":[-77.407552,38.949262],"type":"Point"}
}