{
  "type": "Feature",
  "properties": {
    "addr:full":"23138 Main St Courtland VA 23837",
    "addr:housenumber":"23138",
    "addr:postcode":"23837",
    "addr:street":"Main St",
    "iso:country":"US",
    "sg:address":"23138 Main St",
    "sg:city":"Courtland",
    "sg:classifiers":[
        {
            "category":"Food & Beverages",
            "subcategory":"Groceries & Convenience Stores",
            "type":"Retail Goods"
        }
    ],
    "sg:phone":"+1 757 653 9177",
    "sg:postcode":"23837",
    "sg:province":"VA",
    "sg:tags":[
        "market"
    ],
    "wof:name":"Southland Corp Market",
    "wof:placetype":"venue"
},
  "geometry": {"coordinates":[-77.05193300000001,36.7061],"type":"Point"}
}