{
  "type": "Feature",
  "properties": {
    "addr:full":"7304 Beverly St Annandale VA 22003",
    "addr:housenumber":"7304",
    "addr:postcode":"22003",
    "addr:street":"Beverly St",
    "iso:country":"US",
    "sg:address":"7304 Beverly St",
    "sg:city":"Annandale",
    "sg:classifiers":[
        {
            "category":"Freight",
            "type":"Transportation"
        }
    ],
    "sg:phone":"+1 703 941 3210",
    "sg:postcode":"22003",
    "sg:province":"VA",
    "sg:tags":[
        "delivery"
    ],
    "wof:name":"My Courier",
    "wof:placetype":"venue"
},
  "geometry": {"coordinates":[-77.19653700000001,38.819414],"type":"Point"}
}