{
  "type": "Feature",
  "properties": {
    "iso:country":"US",
    "sg:address":"819 W 21st St",
    "sg:city":"Norfolk",
    "sg:classifiers":[
        {
            "category":"Freight",
            "type":"Transportation"
        }
    ],
    "sg:phone":"+1 757 533 9668",
    "sg:postcode":"23517",
    "sg:province":"VA",
    "sg:tags":[
        "forwarders"
    ],
    "wof:name":"Kuehne & Nagel Inc",
    "wof:placetype":"venue"
},
  "geometry": {"coordinates":[-76.297934,36.871558],"type":"Point"}
}