{
  "type": "Feature",
  "properties": {
    "addr:full":"1901 N Fort Myer Dr Arlington VA 22209",
    "addr:housenumber":"1901",
    "addr:postcode":"22209",
    "addr:street":"N Fort Myer Dr",
    "iso:country":"US",
    "sg:address":"1901 N Fort Myer Dr",
    "sg:city":"Arlington",
    "sg:classifiers":[
        {
            "category":"Travel",
            "subcategory":"Travel Agent",
            "type":"Entertainment"
        }
    ],
    "sg:phone":"+1 703 522 4057",
    "sg:postcode":"22209",
    "sg:province":"VA",
    "sg:tags":[
        "agency",
        "bureau"
    ],
    "wof:name":"Renaissance Travel",
    "wof:placetype":"venue"
},
  "geometry": {"coordinates":[-77.072517,38.897729],"type":"Point"}
}