{
  "type": "Feature",
  "properties": {
    "iso:country":"US",
    "sg:address":"4007 Old Calverton Rd",
    "sg:city":"Calverton",
    "sg:classifiers":[
        {
            "category":"Manufacturing",
            "subcategory":"Printing",
            "type":"Manufacturing & Wholesale Goods"
        }
    ],
    "sg:phone":"+1 540 788 4826",
    "sg:postcode":"20138",
    "sg:province":"VA",
    "sg:tags":[
        "printer"
    ],
    "wof:name":"Calverton Press",
    "wof:placetype":"venue"
},
  "geometry": {"coordinates":[-77.662693,38.635079],"type":"Point"}
}