{
  "type": "Feature",
  "properties": {
    "addr:full":"1831 Grayland St Blacksburg VA 24060",
    "addr:housenumber":"1831",
    "addr:postcode":"24060",
    "addr:street":"Grayland St",
    "iso:country":"US",
    "sg:address":"1831 Grayland St",
    "sg:city":"Blacksburg",
    "sg:classifiers":[
        {
            "category":"Education",
            "subcategory":"School",
            "type":"Public Place"
        }
    ],
    "sg:phone":"+1 540 818 1292",
    "sg:postcode":"24060",
    "sg:province":"VA",
    "sg:tags":[
        "educational",
        "program"
    ],
    "wof:name":"Usmle",
    "wof:placetype":"venue"
},
  "geometry": {"coordinates":[-80.397389,37.210498],"type":"Point"}
}