{
  "type": "Feature",
  "properties": {
    "addr:full":"11731 Mapsico Rd Charles City VA 23030",
    "addr:housenumber":"11731",
    "addr:postcode":"23030",
    "addr:street":"Mapsico Rd",
    "iso:country":"US",
    "sg:address":"11731 Mapsico Rd",
    "sg:city":"Charles City",
    "sg:classifiers":[
        {
            "category":"Freight",
            "type":"Transportation"
        }
    ],
    "sg:phone":"+1 804 829 2747",
    "sg:postcode":"23030",
    "sg:province":"VA",
    "sg:tags":[
        "operator",
        "local",
        "trucking"
    ],
    "wof:name":"Nb Christian Jr Trucking Inc",
    "wof:placetype":"venue"
},
  "geometry": {"coordinates":[-77.043655,37.327973],"type":"Point"}
}