{
  "type": "Feature",
  "properties": {
    "addr:full":"2700 Mistwood Forest Dr Chester VA 23831",
    "addr:postcode":"2700;23831",
    "addr:street":"Mistwood Forest Dr",
    "iso:country":"US",
    "sg:address":"2700 Mistwood Forest Dr",
    "sg:city":"Chester",
    "sg:classifiers":[
        {
            "category":"Freight",
            "type":"Transportation"
        }
    ],
    "sg:phone":"+1 804 717 2445",
    "sg:postcode":"23831",
    "sg:province":"VA",
    "sg:tags":[
        "operator",
        "local",
        "trucking"
    ],
    "wof:name":"Kw Trucking Inc",
    "wof:placetype":"venue"
},
  "geometry": {"coordinates":[-77.41907399999999,37.32713],"type":"Point"}
}