{
  "type": "Feature",
  "properties": {
    "addr:full":"900 S Walter Reed Dr Arlington VA 22204",
    "addr:housenumber":"900",
    "addr:postcode":"22204",
    "addr:street":"S Walter Reed Dr",
    "iso:country":"US",
    "sg:address":"900 S Walter Reed Dr",
    "sg:city":"Arlington",
    "sg:classifiers":[
        {
            "category":"Manufacturing",
            "subcategory":"Printing",
            "type":"Manufacturing & Wholesale Goods"
        }
    ],
    "sg:phone":"+1 703 521 3230",
    "sg:postcode":"22204",
    "sg:province":"VA",
    "sg:tags":[
        "publisher"
    ],
    "wof:name":"Patent Publishing LLC",
    "wof:placetype":"venue"
},
  "geometry": {"coordinates":[-77.08714999999999,38.863223],"type":"Point"}
}