{
  "type": "Feature",
  "properties": {
    "iso:country":"US",
    "sg:address":"2600 Washington Ave",
    "sg:city":"Newport News",
    "sg:classifiers":[
        {
            "category":"Manufacturing",
            "subcategory":"Printing",
            "type":"Manufacturing & Wholesale Goods"
        }
    ],
    "sg:phone":"+1 757 244 5654",
    "sg:postcode":"23607",
    "sg:province":"VA",
    "sg:tags":[
        "newspaper"
    ],
    "wof:name":"Hampton Roads Voice Newspaper",
    "wof:placetype":"venue"
},
  "geometry": {"coordinates":[-76.430885,36.978662],"type":"Point"}
}