{
  "type": "Feature",
  "properties": {
    "iso:country":"US",
    "sg:address":"2921 S Columbia Pike",
    "sg:city":"Arlington",
    "sg:classifiers":[
        {
            "category":"Restaurant",
            "type":"Food & Drink"
        }
    ],
    "sg:phone":"+1 703 920 6161",
    "sg:postcode":"22204",
    "sg:province":"VA",
    "sg:tags":[
        "eating"
    ],
    "wof:name":"Oriental Restaurant",
    "wof:placetype":"venue"
},
  "geometry": {"coordinates":[-77.087767,38.862454],"type":"Point"}
}