{
  "type": "Feature",
  "properties": {
    "iso:country":"US",
    "sg:address":"4620 22nd St N",
    "sg:city":"Arlington",
    "sg:classifiers":[
        {
            "category":"Real Estate",
            "subcategory":"Architect",
            "type":"Services"
        }
    ],
    "sg:phone":"+1 703 524 8086",
    "sg:postcode":"22207",
    "sg:province":"VA",
    "wof:name":"Donald James C Archt",
    "wof:placetype":"venue"
},
  "geometry": {"coordinates":[-77.120598,38.899399],"type":"Point"}
}