{
  "type": "Feature",
  "properties": {
    "addr:full":"945 Wiggington Rd Lynchburg VA 24502",
    "addr:housenumber":"945",
    "addr:postcode":"24502",
    "addr:street":"Wiggington Rd",
    "iso:country":"US",
    "sg:address":"945 Wiggington Rd",
    "sg:city":"Lynchburg",
    "sg:classifiers":[
        {
            "category":"Retail",
            "subcategory":"Auto Repair",
            "type":"Services"
        }
    ],
    "sg:phone":"+1 434 385 6027",
    "sg:postcode":"24502",
    "sg:province":"VA",
    "sg:tags":[
        "general"
    ],
    "wof:name":"Bells Automotive Service",
    "wof:placetype":"venue"
},
  "geometry": {"coordinates":[-79.238291,37.418221],"type":"Point"}
}