{
  "type": "Feature",
  "properties": {
    "iso:country":"US",
    "sg:address":"7835 Honeysuckle Rd",
    "sg:city":"Bent Mountain",
    "sg:classifiers":[
        {
            "category":"Professional",
            "subcategory":"Business Services",
            "type":"Services"
        }
    ],
    "sg:phone":"+1 540 929 4820",
    "sg:postcode":"24059",
    "sg:province":"VA",
    "sg:tags":[
        "investigation"
    ],
    "wof:name":"Rhyn C Tryal",
    "wof:placetype":"venue"
},
  "geometry": {"coordinates":[-80.14756300000001,37.198818],"type":"Point"}
}