{
  "type": "Feature",
  "properties": {
    "iso:country":"US",
    "sg:address":"3702 Morgan Trail Dr",
    "sg:city":"Chesterfield",
    "sg:classifiers":[
        {
            "category":"Retail",
            "subcategory":"Repair Shop",
            "type":"Services"
        }
    ],
    "sg:phone":"+1 804 334 8228",
    "sg:postcode":"23832",
    "sg:province":"VA",
    "wof:name":"Cleanworks Inc",
    "wof:placetype":"venue"
},
  "geometry": {"coordinates":[-77.53152,37.456378],"type":"Point"}
}