{
  "type": "Feature",
  "properties": {
    "addr:full":"6231 Leesburg Pike Falls Church VA 22044",
    "addr:housenumber":"6231",
    "addr:postcode":"22044",
    "addr:street":"Leesburg Pike",
    "iso:country":"US",
    "sg:address":"6231 Leesburg Pike",
    "sg:city":"Falls Church",
    "sg:classifiers":[
        {
            "category":"Restaurant",
            "type":"Food & Drink"
        }
    ],
    "sg:phone":"+1 703 241 1569",
    "sg:postcode":"22044",
    "sg:province":"VA",
    "sg:tags":[
        "eating"
    ],
    "wof:name":"Benitos Tax Service",
    "wof:placetype":"venue"
},
  "geometry": {"coordinates":[-77.152809,38.868144],"type":"Point"}
}