{
  "type": "Feature",
  "properties": {
    "addr:full":"2327 E Washington St Petersburg VA 23803",
    "addr:housenumber":"2327",
    "addr:postcode":"23803",
    "addr:street":"E Washington",
    "iso:country":"US",
    "sg:address":"2327 E Washington St",
    "sg:city":"Petersburg",
    "sg:classifiers":[
        {
            "category":"Retail",
            "subcategory":"Auto Repair",
            "type":"Services"
        }
    ],
    "sg:phone":"+1 804 861 5609",
    "sg:postcode":"23803",
    "sg:province":"VA",
    "sg:tags":[
        "repairing",
        "automobile",
        "general"
    ],
    "wof:name":"Young S Foreign Car Repair",
    "wof:placetype":"venue"
},
  "geometry": {"coordinates":[-77.36356499999999,37.239898],"type":"Point"}
}