{
  "type": "Feature",
  "properties": {
    "iso:country":"US",
    "sg:address":"11513 Frederick Farms Cir",
    "sg:city":"Midlothian",
    "sg:classifiers":[
        {
            "category":"Building & Trades",
            "subcategory":"Construction",
            "type":"Services"
        }
    ],
    "sg:phone":"+1 804 744 0500",
    "sg:postcode":"23112",
    "sg:province":"VA",
    "sg:tags":[
        "home",
        "improvement"
    ],
    "wof:name":"Alan Wooten Painting",
    "wof:placetype":"venue"
},
  "geometry": {"coordinates":[-77.60413800000001,37.433721],"type":"Point"}
}