{
  "type": "Feature",
  "properties": {
    "iso:country":"US",
    "sg:address":"5217 Williamson Rd NE",
    "sg:city":"Roanoke",
    "sg:classifiers":[
        {
            "category":"Home & Garden",
            "subcategory":"Furniture",
            "type":"Retail Goods"
        }
    ],
    "sg:phone":"+1 540 561 0901",
    "sg:postcode":"24012",
    "sg:province":"VA",
    "sg:website":"www.wooden-things.net",
    "wof:name":"Wooden Things Unfinished Furn",
    "wof:placetype":"venue"
},
  "geometry": {"coordinates":[-79.95419699999999,37.321756],"type":"Point"}
}