{
  "type": "Feature",
  "properties": {
    "iso:country":"US",
    "sg:address":"710 E Little Creek Rd",
    "sg:city":"Norfolk",
    "sg:classifiers":[
        {
            "category":"Professional",
            "subcategory":"Accounting & Tax Preparation",
            "type":"Services"
        }
    ],
    "sg:phone":"+1 757 961 5796",
    "sg:postcode":"23518",
    "sg:province":"VA",
    "wof:name":"All About the Numbers",
    "wof:placetype":"venue"
},
  "geometry": {"coordinates":[-76.25353699999999,36.916079],"type":"Point"}
}