{
  "type": "Feature",
  "properties": {
    "addr:full":"8367 Sudley Rd Manassas VA 20109",
    "addr:housenumber":"8367",
    "addr:postcode":"20109",
    "addr:street":"Sudley Rd",
    "iso:country":"US",
    "sg:address":"8367 Sudley Rd",
    "sg:city":"Manassas",
    "sg:classifiers":[
        {
            "category":"Banks & Credit Unions",
            "subcategory":"Financial Services",
            "type":"Services"
        }
    ],
    "sg:phone":"+1 703 335 9196",
    "sg:postcode":"20109",
    "sg:province":"VA",
    "sg:tags":[
        "broker",
        "mortgage"
    ],
    "sg:website":"www.citifinancial.com",
    "wof:name":"Citifinancial",
    "wof:placetype":"venue"
},
  "geometry": {"coordinates":[-77.502098,38.775002],"type":"Point"}
}