{
  "type": "Feature",
  "properties": {
    "iso:country":"US",
    "sg:address":"4113 Hoffman Dr",
    "sg:city":"Woodbridge",
    "sg:classifiers":[
        {
            "category":"Building & Trades",
            "subcategory":"Construction",
            "type":"Services"
        }
    ],
    "sg:phone":"+1 703 590 6167",
    "sg:postcode":"22193",
    "sg:province":"VA",
    "sg:tags":[
        "hanging",
        "contractor"
    ],
    "wof:name":"Painting By John Wolfe Inc",
    "wof:placetype":"venue"
},
  "geometry": {"coordinates":[-77.33301299999999,38.661652],"type":"Point"}
}