{
  "type": "Feature",
  "properties": {
    "addr:full":"319 Apache Run Max Meadows VA 24360",
    "addr:housenumber":"319",
    "addr:postcode":"24360",
    "addr:street":"Apache Run",
    "iso:country":"US",
    "sg:address":"319 Apache Run",
    "sg:city":"Max Meadows",
    "sg:classifiers":[
        {
            "category":"Social Services",
            "subcategory":"Child Care",
            "type":"Services"
        }
    ],
    "sg:phone":"+1 276 637 3892",
    "sg:postcode":"24360",
    "sg:province":"VA",
    "sg:tags":[
        "day"
    ],
    "wof:name":"Teddy Bear Day Care",
    "wof:placetype":"venue"
},
  "geometry": {"coordinates":[-80.943579,36.931521],"type":"Point"}
}