{
  "type": "Feature",
  "properties": {
    "addr:full":"5751 Stubbs Bridge Rd Mineral VA 23117",
    "addr:housenumber":"5751",
    "addr:postcode":"23117",
    "addr:street":"Stubbs Bridge Rd",
    "iso:country":"US",
    "sg:address":"5751 Stubbs Bridge Rd",
    "sg:city":"Mineral",
    "sg:classifiers":[
        {
            "category":"Building & Trades",
            "subcategory":"Construction",
            "type":"Services"
        }
    ],
    "sg:phone":"+1 540 854 6325",
    "sg:postcode":"23117",
    "sg:province":"VA",
    "sg:tags":[
        "house"
    ],
    "wof:name":"Frank Talley Construction",
    "wof:placetype":"venue"
},
  "geometry": {"coordinates":[-77.86845099999999,38.120548],"type":"Point"}
}