{
  "type": "Feature",
  "properties": {
    "addr:full":"1525 N Wilson Blvd Arlington VA 22209",
    "addr:housenumber":"1525",
    "addr:postcode":"22209",
    "addr:street":"N Wilson Blvd",
    "iso:country":"US",
    "sg:address":"1525 N Wilson Blvd",
    "sg:city":"Arlington",
    "sg:classifiers":[
        {
            "category":"Professional",
            "subcategory":"Engineering",
            "type":"Services"
        }
    ],
    "sg:phone":"+1 703 516 9685",
    "sg:postcode":"22209",
    "sg:province":"VA",
    "wof:name":"Ryan Dean Cons & Designers",
    "wof:placetype":"venue"
},
  "geometry": {"coordinates":[-77.07607,38.894573],"type":"Point"}
}