{
  "type": "Feature",
  "properties": {
    "addr:full":"21 Fort Evans Rd SE Leesburg VA 20175",
    "addr:housenumber":"21",
    "addr:postcode":"20175",
    "addr:street":"Fort Evans Rd Se",
    "iso:country":"US",
    "sg:address":"21 Fort Evans Rd SE",
    "sg:city":"Leesburg",
    "sg:classifiers":[
        {
            "category":"Retail",
            "subcategory":"Auto Repair",
            "type":"Services"
        }
    ],
    "sg:phone":"+1 703 779 7862",
    "sg:postcode":"20175",
    "sg:province":"VA",
    "sg:tags":[
        "repairing",
        "automobile"
    ],
    "wof:name":"Leesburg Automotive",
    "wof:placetype":"venue"
},
  "geometry": {"coordinates":[-77.549429,39.106977],"type":"Point"}
}