{
  "type": "Feature",
  "properties": {
    "addr:full":"1318 Pavilion Club Way Reston VA 20194",
    "addr:housenumber":"1318",
    "addr:postcode":"20194",
    "addr:street":"Pavilion Club Way",
    "iso:country":"US",
    "sg:address":"1318 Pavilion Club Way",
    "sg:city":"Reston",
    "sg:classifiers":[
        {
            "category":"Education",
            "subcategory":"Special Training",
            "type":"Public Place"
        }
    ],
    "sg:phone":"+1 703 904 3724",
    "sg:postcode":"20194",
    "sg:province":"VA",
    "sg:tags":[
        "instruction",
        "music"
    ],
    "wof:name":"NYM Assoc LTD",
    "wof:placetype":"venue"
},
  "geometry": {"coordinates":[-77.335048,38.981358],"type":"Point"}
}