{
  "type": "Feature",
  "properties": {
    "addr:full":"1907 Woodgate Ln McLean VA 22101",
    "addr:housenumber":"1907",
    "addr:postcode":"22101",
    "addr:street":"Woodgate Ln",
    "iso:country":"US",
    "sg:address":"1907 Woodgate Ln",
    "sg:city":"McLean",
    "sg:classifiers":[
        {
            "category":"Professional",
            "subcategory":"Lawyer & Legal Services",
            "type":"Services"
        }
    ],
    "sg:phone":"+1 703 356 2479",
    "sg:postcode":"22101",
    "sg:province":"VA",
    "wof:name":"Fricker John E Atty",
    "wof:placetype":"venue"
},
  "geometry": {"coordinates":[-77.186544,38.914138],"type":"Point"}
}