{
  "type": "Feature",
  "properties": {
    "addr:full":"7402 Richmond Rd Williamsburg VA 23188",
    "addr:housenumber":"7402",
    "addr:postcode":"23188",
    "addr:street":"Richmond Rd",
    "iso:country":"US",
    "sg:address":"7402 Richmond Rd",
    "sg:city":"Williamsburg",
    "sg:classifiers":[
        {
            "category":"Organizations",
            "subcategory":"Membership Organization",
            "type":"Services"
        }
    ],
    "sg:phone":"+1 757 564 7390",
    "sg:postcode":"23188",
    "sg:province":"VA",
    "wof:name":"Norge Community Club",
    "wof:placetype":"venue"
},
  "geometry": {"coordinates":[-76.770515,37.367995],"type":"Point"}
}