{
  "type": "Feature",
  "properties": {
    "iso:country":"US",
    "sg:address":"1048 Queen St",
    "sg:city":"Portsmouth",
    "sg:classifiers":[
        {
            "category":"Organizations",
            "subcategory":"Religious Organization",
            "type":"Services"
        }
    ],
    "sg:phone":"+1 757 484 7484",
    "sg:postcode":"23704",
    "sg:province":"VA",
    "wof:name":"True Vine Pentecostal Holiness",
    "wof:placetype":"venue"
},
  "geometry": {"coordinates":[-76.309691,36.836008],"type":"Point"}
}