{
  "type": "Feature",
  "properties": {
    "addr:full":"7623 Huntmaster Ln Mc Lean VA 22102",
    "addr:housenumber":"7623",
    "addr:postcode":"22102",
    "addr:street":"Huntmaster Ln Mc Lean",
    "iso:country":"US",
    "sg:address":"7623 Huntmaster Ln",
    "sg:city":"Mc Lean",
    "sg:classifiers":[
        {
            "category":"Professional",
            "subcategory":"Business Services",
            "type":"Services"
        }
    ],
    "sg:phone":"+1 703 848 0361",
    "sg:postcode":"22102",
    "sg:province":"VA",
    "sg:tags":[
        "consulting"
    ],
    "wof:name":"Stratgic Orgnization Solutions",
    "wof:placetype":"venue"
},
  "geometry": {"coordinates":[-77.21078900000001,38.941471],"type":"Point"}
}