{
  "type": "Feature",
  "properties": {
    "addr:full":"2707 Atlantic Ave Virginia Beach VA 23451",
    "addr:housenumber":"2707",
    "addr:postcode":"23451",
    "addr:street":"Atlantic Ave",
    "iso:country":"US",
    "sg:address":"2707 Atlantic Ave",
    "sg:city":"Virginia Beach",
    "sg:classifiers":[
        {
            "category":"Travel",
            "subcategory":"Hotels & Motels",
            "type":"Entertainment"
        }
    ],
    "sg:phone":"+1 757 428 3970",
    "sg:postcode":"23451",
    "sg:province":"VA",
    "wof:name":"Econo Lodge",
    "wof:placetype":"venue"
},
  "geometry": {"coordinates":[-75.977299,36.856327],"type":"Point"}
}