{
  "type": "Feature",
  "properties": {
    "addr:full":"4231 Ferguson Ln Richmond VA 23234",
    "addr:housenumber":"4231",
    "addr:postcode":"23234",
    "addr:street":"Ferguson Ln",
    "iso:country":"US",
    "sg:address":"4231 Ferguson Ln",
    "sg:city":"Richmond",
    "sg:classifiers":[
        {
            "category":"Professional",
            "subcategory":"Business Services",
            "type":"Services"
        }
    ],
    "sg:phone":"+1 804 523 1000",
    "sg:postcode":"23234",
    "sg:province":"VA",
    "sg:tags":[
        "paging",
        "answering"
    ],
    "wof:name":"24 7 Answer Svc",
    "wof:placetype":"venue"
},
  "geometry": {"coordinates":[-77.479195,37.47749],"type":"Point"}
}