{
  "type": "Feature",
  "properties": {
    "iso:country":"US",
    "sg:address":"620 Valor Ct",
    "sg:city":"Chesapeake",
    "sg:classifiers":[
        {
            "category":"Health Services",
            "subcategory":"Health Practitioner",
            "type":"Services"
        }
    ],
    "sg:phone":"+1 757 482 8797",
    "sg:postcode":"23322",
    "sg:province":"VA",
    "sg:tags":[
        "dental",
        "hygienist"
    ],
    "wof:name":"Maria Birmingham",
    "wof:placetype":"venue"
},
  "geometry": {"coordinates":[-76.205067,36.684161],"type":"Point"}
}