{
  "type": "Feature",
  "properties": {
    "addr:full":"3905 Deep Rock Rd Richmond VA 23233",
    "addr:housenumber":"3905",
    "addr:postcode":"23233",
    "addr:street":"Deep Rock Rd",
    "iso:country":"US",
    "sg:address":"3905 Deep Rock Rd",
    "sg:city":"Richmond",
    "sg:classifiers":[
        {
            "category":"Wholesale",
            "subcategory":"Hardware",
            "type":"Manufacturing & Wholesale Goods"
        },
        {
            "category":"Building & Trades",
            "subcategory":"Plumbing",
            "type":"Services"
        }
    ],
    "sg:phone":"+1 804 217 7861",
    "sg:postcode":"23233",
    "sg:province":"VA",
    "sg:tags":[
        "mfg",
        "rep",
        "system",
        "air",
        "handler",
        "fan",
        "conditioning",
        "conservation",
        "contractor",
        "energy"
    ],
    "sg:website":"www.breeden-collier.com",
    "wof:name":"Breeden & Collier Company Inc",
    "wof:placetype":"venue"
},
  "geometry": {"coordinates":[-77.573289,37.643388],"type":"Point"}
}