{
  "type": "Feature",
  "properties": {
    "addr:full":"6911 Richmond Hwy Alexandria VA 22306",
    "addr:housenumber":"6911",
    "addr:postcode":"22306",
    "addr:street":"Richmond Hwy",
    "iso:country":"US",
    "sg:address":"6911 Richmond Hwy",
    "sg:city":"Alexandria",
    "sg:classifiers":[
        {
            "category":"Travel",
            "subcategory":"Travel Agent",
            "type":"Entertainment"
        }
    ],
    "sg:phone":"+1 703 765 4400",
    "sg:postcode":"22306",
    "sg:province":"VA",
    "sg:tags":[
        "agency",
        "bureau"
    ],
    "wof:name":"Teleport Va",
    "wof:placetype":"venue"
},
  "geometry": {"coordinates":[-77.082667,38.768161],"type":"Point"}
}