{
  "type": "Feature",
  "properties": {
    "addr:full":"15405 Merry Cat Ln Belle Haven VA 23306",
    "addr:housenumber":"15405",
    "addr:postcode":"23306",
    "addr:street":"Merry Cat Ln",
    "iso:country":"US",
    "sg:address":"15405 Merry Cat Ln",
    "sg:city":"Belle Haven",
    "sg:classifiers":[
        {
            "category":"Social Services",
            "type":"Services"
        }
    ],
    "sg:phone":"+1 757 442 9334",
    "sg:postcode":"23306",
    "sg:province":"VA",
    "wof:name":"Commonwealth Support Systems",
    "wof:placetype":"venue"
},
  "geometry": {"coordinates":[-75.81554800000001,37.545681],"type":"Point"}
}