{
  "type": "Feature",
  "properties": {
    "addr:full":"1414 Franklin Rd SW Roanoke VA 24016",
    "addr:housenumber":"1414",
    "addr:postcode":"24016",
    "addr:street":"Franklin Rd Sw",
    "iso:country":"US",
    "sg:address":"1414 Franklin Rd SW",
    "sg:city":"Roanoke",
    "sg:classifiers":[
        {
            "category":"Insurance",
            "subcategory":"Insurance Agent",
            "type":"Services"
        }
    ],
    "sg:phone":"+1 540 343 7855",
    "sg:postcode":"24016",
    "sg:province":"VA",
    "wof:name":"D & S Life Agency Inc",
    "wof:placetype":"venue"
},
  "geometry": {"coordinates":[-79.947,37.260621],"type":"Point"}
}