{
  "type": "Feature",
  "properties": {
    "addr:full":"5359 Main St Stephens City VA 22655",
    "addr:housenumber":"5359",
    "addr:postcode":"22655",
    "addr:street":"Main St",
    "iso:country":"US",
    "sg:address":"5359 Main St",
    "sg:city":"Stephens City",
    "sg:classifiers":[
        {
            "category":"Manufacturing",
            "subcategory":"Tools & Machinery",
            "type":"Manufacturing & Wholesale Goods"
        }
    ],
    "sg:phone":"+1 540 869 8620",
    "sg:postcode":"22655",
    "sg:province":"VA",
    "sg:tags":[
        "aids",
        "hearing"
    ],
    "wof:name":"H & H Electrical Svc",
    "wof:placetype":"venue"
},
  "geometry": {"coordinates":[-78.217556,39.084052],"type":"Point"}
}