{
  "type": "Feature",
  "properties": {
    "addr:full":"1226 Union Church Rd Halifax VA 24558",
    "addr:housenumber":"1226",
    "addr:postcode":"24558",
    "addr:street":"Union Church Rd",
    "iso:country":"US",
    "sg:address":"1226 Union Church Rd",
    "sg:city":"Halifax",
    "sg:classifiers":[
        {
            "category":"Professional",
            "type":"Services"
        }
    ],
    "sg:phone":"+1 434 476 2562",
    "sg:postcode":"24558",
    "sg:province":"VA",
    "wof:name":"Janice Dunaway",
    "wof:placetype":"venue"
},
  "geometry": {"coordinates":[-79.007456,36.740319],"type":"Point"}
}