{
  "type": "Feature",
  "properties": {
    "addr:full":"6430 Brandon Ave Springfield VA 22150",
    "addr:housenumber":"6430",
    "addr:postcode":"22150",
    "addr:street":"Brandon Ave",
    "iso:country":"US",
    "sg:address":"6430 Brandon Ave",
    "sg:city":"Springfield",
    "sg:classifiers":[
        {
            "category":"Restaurant",
            "type":"Food & Drink"
        }
    ],
    "sg:menulink":"http://www.allmenus.com/va/lee/116376-quiznos-sub/menu/",
    "sg:phone":"+1 703 569 7511",
    "sg:postcode":"22150",
    "sg:province":"VA",
    "sg:tags":[
        "wrap",
        "american",
        "sandwich"
    ],
    "wof:name":"Quiznos Sub",
    "wof:placetype":"venue"
},
  "geometry": {"coordinates":[-77.183072,38.780416],"type":"Point"}
}