{
  "type": "Feature",
  "properties": {
    "addr:full":"11205 Boxwood Rd Fredericksburg VA 22408",
    "addr:housenumber":"11205",
    "addr:postcode":"22408",
    "addr:street":"Boxwood Rd",
    "iso:country":"US",
    "sg:address":"11205 Boxwood Rd",
    "sg:city":"Fredericksburg",
    "sg:classifiers":[
        {
            "category":"Professional",
            "subcategory":"Business Services",
            "type":"Services"
        }
    ],
    "sg:phone":"+1 540 891 7880",
    "sg:postcode":"22408",
    "sg:province":"VA",
    "wof:name":"Pett Enterprises Inc",
    "wof:placetype":"venue"
},
  "geometry": {"coordinates":[-77.506748,38.266584],"type":"Point"}
}