{
  "type": "Feature",
  "properties": {
    "iso:country":"US",
    "sg:address":"3118 Washington Blvd",
    "sg:city":"Arlington",
    "sg:classifiers":[
        {
            "category":"Government",
            "subcategory":"Post Office",
            "type":"Public Place"
        }
    ],
    "sg:phone":"+1 800 275 8777",
    "sg:postcode":"22201",
    "sg:province":"VA",
    "sg:website":"www.usps.com/",
    "wof:name":"U.S. Post Office",
    "wof:placetype":"venue"
},
  "geometry": {"coordinates":[-77.095366,38.885805],"type":"Point"}
}