{
  "type": "Feature",
  "properties": {
    "iso:country":"US",
    "sg:address":"4501 Fairfax Dr",
    "sg:city":"Arlington",
    "sg:classifiers":[
        {
            "category":"Professional",
            "type":"Services"
        },
        {
            "category":"Professional",
            "subcategory":"Business Services",
            "type":"Services"
        },
        {
            "category":"Freight",
            "type":"Transportation"
        },
        {
            "category":"Professional",
            "subcategory":"Printing & Photocopies",
            "type":"Services"
        },
        {
            "category":"Shopping",
            "subcategory":"Stationery & Office Supplies",
            "type":"Retail Goods"
        },
        {
            "category":"Manufacturing",
            "subcategory":"Printing",
            "type":"Manufacturing & Wholesale Goods"
        },
        {
            "category":"Manufacturing",
            "subcategory":"Signs",
            "type":"Manufacturing & Wholesale Goods"
        }
    ],
    "sg:phone":"+1 703 875 8017",
    "sg:postcode":"22203",
    "sg:province":"VA",
    "sg:tags":[
        "machine",
        "document",
        "duplicating",
        "shipping",
        "materials-shipping",
        "packaging",
        "packing",
        "imaging",
        "copying",
        "digital",
        "copy"
    ],
    "sg:website":"www.fedex.com/us/office/",
    "wof:name":"FedEx Office Print & Ship Center",
    "wof:placetype":"venue"
},
  "geometry": {"coordinates":[-77.115589,38.882591],"type":"Point"}
}