{
  "type": "Feature",
  "properties": {
    "iso:country":"US",
    "sg:address":"2 W Main St",
    "sg:city":"Richmond",
    "sg:classifiers":[
        {
            "category":"Social Services",
            "subcategory":"Child Care",
            "type":"Services"
        }
    ],
    "sg:phone":"+1 804 783 9622",
    "sg:postcode":"23220",
    "sg:province":"VA",
    "sg:tags":[
        "center",
        "day"
    ],
    "wof:name":"Downtown YMCA Day Care Center",
    "wof:placetype":"venue"
},
  "geometry": {"coordinates":[-77.44528,37.543589],"type":"Point"}
}