{
  "type": "Feature",
  "properties": {
    "iso:country":"US",
    "sg:address":"2976 Cody Rd",
    "sg:city":"Gretna",
    "sg:phone":"+1 434 335 5394",
    "sg:postcode":"24557",
    "sg:province":"VA",
    "sg:tags":[
        "tobacco",
        "beef",
        "farm",
        "crop",
        "field",
        "cattle",
        "feedlot"
    ],
    "wof:name":"James Tucker",
    "wof:placetype":"venue"
},
  "geometry": {"coordinates":[-79.11188799999999,36.983552],"type":"Point"}
}