{
  "type": "Feature",
  "properties": {
    "addr:full":"11854 Sunrise Valley Dr Reston VA 20191",
    "addr:housenumber":"11854",
    "addr:postcode":"20191",
    "addr:street":"Sunrise Valley Dr",
    "iso:country":"US",
    "sg:address":"11854 Sunrise Valley Dr",
    "sg:city":"Reston",
    "sg:classifiers":[
        {
            "category":"Autos & Motor Vehicles",
            "subcategory":"Fuel & Gas Station",
            "type":"Retail Goods"
        }
    ],
    "sg:phone":"+1 703 860 5996",
    "sg:postcode":"20191",
    "sg:province":"VA",
    "sg:website":"http://www.exxon.mobil.com",
    "wof:name":"Sunrise Valley Exxon On Run",
    "wof:placetype":"venue"
},
  "geometry": {"coordinates":[-77.35659,38.946964],"type":"Point"}
}