{
  "type": "Feature",
  "properties": {
    "addr:full":"317 Robinhood Rd Franklin VA 23851",
    "addr:housenumber":"317",
    "addr:postcode":"23851",
    "addr:street":"Robinhood Rd",
    "iso:country":"US",
    "sg:address":"317 Robinhood Rd",
    "sg:city":"Franklin",
    "sg:classifiers":[
        {
            "category":"Organizations",
            "subcategory":"Religious Organization",
            "type":"Services"
        }
    ],
    "sg:phone":"+1 757 569 1087",
    "sg:postcode":"23851",
    "sg:province":"VA",
    "wof:name":"Henry Blunt Rev",
    "wof:placetype":"venue"
},
  "geometry": {"coordinates":[-76.953513,36.688157],"type":"Point"}
}