{
  "type": "Feature",
  "properties": {
    "addr:full":"3735 Franklin Rd SW Roanoke VA 24014",
    "addr:housenumber":"3735",
    "addr:postcode":"24014",
    "addr:street":"Franklin Rd Sw",
    "iso:country":"US",
    "sg:address":"3735 Franklin Rd SW",
    "sg:city":"Roanoke",
    "sg:classifiers":[
        {
            "category":"Professional",
            "subcategory":"Management & Consulting",
            "type":"Services"
        },
        {
            "category":"Insurance",
            "subcategory":"Hazard Insurance",
            "type":"Services"
        },
        {
            "category":"Banks & Credit Unions",
            "subcategory":"Financial Services",
            "type":"Services"
        },
        {
            "category":"Insurance",
            "subcategory":"Insurance Agent",
            "type":"Services"
        }
    ],
    "sg:phone":"+1 540 982 0923",
    "sg:postcode":"24014",
    "sg:province":"VA",
    "sg:tags":[
        "consultant",
        "financing",
        "planning",
        "analyst"
    ],
    "wof:name":"Overstreet & Associates",
    "wof:placetype":"venue"
},
  "geometry": {"coordinates":[-79.95416299999999,37.206495],"type":"Point"}
}