{
  "type": "Feature",
  "properties": {
    "addr:full":"129 N Grace St Chase City VA 23924",
    "addr:housenumber":"129",
    "addr:postcode":"23924",
    "addr:street":"N Grace St",
    "iso:country":"US",
    "sg:address":"129 N Grace St",
    "sg:city":"Chase City",
    "sg:classifiers":[
        {
            "category":"Social Services",
            "subcategory":"Child Care",
            "type":"Services"
        }
    ],
    "sg:phone":"+1 434 372 1500",
    "sg:postcode":"23924",
    "sg:province":"VA",
    "wof:name":"Latasha's Daycare",
    "wof:placetype":"venue"
},
  "geometry": {"coordinates":[-78.45916800000001,36.798135],"type":"Point"}
}