{
  "type": "Feature",
  "properties": {
    "addr:full":"1683 Dutch Hollow Rd Middlebrook VA 24472",
    "addr:housenumber":"1683",
    "addr:postcode":"24472",
    "addr:street":"Dutch Hollow Rd",
    "iso:country":"US",
    "sg:address":"1683 Dutch Hollow Rd",
    "sg:city":"Middlebrook",
    "sg:classifiers":[
        {
            "category":"Farming",
            "subcategory":"Livestock Farm",
            "type":"Manufacturing & Wholesale Goods"
        }
    ],
    "sg:phone":"+1 540 377 5549",
    "sg:postcode":"24472",
    "sg:province":"VA",
    "sg:tags":[
        "feedlot",
        "field",
        "crop",
        "beef",
        "cattle"
    ],
    "wof:name":"Windbrook Farm",
    "wof:placetype":"venue"
},
  "geometry": {"coordinates":[-79.34450200000001,37.999888],"type":"Point"}
}