{
  "type": "Feature",
  "properties": {
    "iso:country":"US",
    "sg:address":"915 Rainbow Forest Dr",
    "sg:city":"Lynchburg",
    "sg:classifiers":[
        {
            "category":"Professional",
            "subcategory":"Business Services",
            "type":"Services"
        }
    ],
    "sg:phone":"+1 434 239 1157",
    "sg:postcode":"24502",
    "sg:province":"VA",
    "wof:name":"Joycelyn G Arthur Bookkeeping",
    "wof:placetype":"venue"
},
  "geometry": {"coordinates":[-79.251113,37.342954],"type":"Point"}
}