{
  "type": "Feature",
  "properties": {
    "addr:full":"571 Walnut Dr Fredericksburg VA 22405",
    "addr:housenumber":"571",
    "addr:postcode":"22405",
    "addr:street":"Walnut Dr",
    "iso:country":"US",
    "sg:address":"571 Walnut Dr",
    "sg:city":"Fredericksburg",
    "sg:classifiers":[
        {
            "category":"Professional",
            "type":"Services"
        }
    ],
    "sg:phone":"+1 540 373 1487",
    "sg:postcode":"22405",
    "sg:province":"VA",
    "wof:name":"After The Winners Circle Inc",
    "wof:placetype":"venue"
},
  "geometry": {"coordinates":[-77.427036,38.340142],"type":"Point"}
}