{
  "type": "Feature",
  "properties": {
    "addr:full":"203 S Main St Woodstock VA 22664",
    "addr:housenumber":"203",
    "addr:postcode":"22664",
    "addr:street":"S Main St",
    "iso:country":"US",
    "sg:address":"203 S Main St",
    "sg:city":"Woodstock",
    "sg:classifiers":[
        {
            "category":"Food & Beverages",
            "subcategory":"Groceries & Convenience Stores",
            "type":"Retail Goods"
        }
    ],
    "sg:phone":"+1 540 459 5999",
    "sg:postcode":"22664",
    "sg:province":"VA",
    "wof:name":"M&R Mart",
    "wof:placetype":"venue"
},
  "geometry": {"coordinates":[-78.506406,38.880282],"type":"Point"}
}