{
  "type": "Feature",
  "properties": {
    "addr:full":"1232 Sylvan Rd SE Roanoke VA 24014",
    "addr:housenumber":"1232",
    "addr:postcode":"24014",
    "addr:street":"Sylvan Rd Se",
    "iso:country":"US",
    "sg:address":"1232 Sylvan Rd SE",
    "sg:city":"Roanoke",
    "sg:classifiers":[
        {
            "category":"Professional",
            "subcategory":"Business Services",
            "type":"Services"
        }
    ],
    "sg:phone":"+1 540 427 2150",
    "sg:postcode":"24014",
    "sg:province":"VA",
    "wof:name":"Kepley & Blackwell Intr Design",
    "wof:placetype":"venue"
},
  "geometry": {"coordinates":[-79.934676,37.255048],"type":"Point"}
}