{
  "type": "Feature",
  "properties": {
    "addr:full":"1697 Ringgold Depot Rd Ringgold VA 24586",
    "addr:housenumber":"1697",
    "addr:postcode":"24586",
    "addr:street":"Ringgold Depot Rd",
    "iso:country":"US",
    "sg:address":"1697 Ringgold Depot Rd",
    "sg:city":"Ringgold",
    "sg:classifiers":[
        {
            "category":"Organizations",
            "subcategory":"Religious Organization",
            "type":"Services"
        }
    ],
    "sg:phone":"+1 434 822 5662",
    "sg:postcode":"24586",
    "sg:province":"VA",
    "wof:name":"Mt Zion Baptist Church",
    "wof:placetype":"venue"
},
  "geometry": {"coordinates":[-79.276838,36.594094],"type":"Point"}
}