{
  "type": "Feature",
  "properties": {
    "iso:country":"US",
    "sg:address":"7200 Olivet Church Rd",
    "sg:city":"New Kent",
    "sg:classifiers":[
        {
            "category":"Freight",
            "type":"Transportation"
        }
    ],
    "sg:phone":"+1 804 932 3895",
    "sg:postcode":"23141",
    "sg:province":"VA",
    "sg:tags":[
        "operator",
        "local",
        "trucking"
    ],
    "wof:name":"M Walton Delivery",
    "wof:placetype":"venue"
},
  "geometry": {"coordinates":[-77.057531,37.503566],"type":"Point"}
}