{
  "type": "Feature",
  "properties": {
    "addr:full":"7672 Great Dover St Gainesville VA 20155",
    "addr:housenumber":"7672",
    "addr:postcode":"20155",
    "addr:street":"Great Dover St",
    "iso:country":"US",
    "sg:address":"7672 Great Dover St",
    "sg:city":"Gainesville",
    "sg:classifiers":[
        {
            "category":"Real Estate",
            "subcategory":"Real Estate Agent",
            "type":"Services"
        }
    ],
    "sg:phone":"+1 703 753 9295",
    "sg:postcode":"20155",
    "sg:province":"VA",
    "wof:name":"Richmond American Homes",
    "wof:placetype":"venue"
},
  "geometry": {"coordinates":[-77.655626,38.791453],"type":"Point"}
}