{
  "type": "Feature",
  "properties": {
    "addr:full":"5910 McGuin Dr Alexandria VA 22310",
    "addr:housenumber":"5910",
    "addr:postcode":"22310",
    "addr:street":"Mcguin Dr",
    "iso:country":"US",
    "sg:address":"5910 McGuin Dr",
    "sg:city":"Alexandria",
    "sg:classifiers":[
        {
            "category":"Building & Trades",
            "subcategory":"Construction",
            "type":"Services"
        }
    ],
    "sg:phone":"+1 703 822 0625",
    "sg:postcode":"22310",
    "sg:province":"VA",
    "sg:tags":[
        "contractor"
    ],
    "wof:name":"Shirley Contracting Corp",
    "wof:placetype":"venue"
},
  "geometry": {"coordinates":[-77.140004,38.797069],"type":"Point"}
}