{
  "type": "Feature",
  "properties": {
    "addr:full":"3101 N Hampton Dr Alexandria VA 22302",
    "addr:housenumber":"3101",
    "addr:postcode":"22302",
    "addr:street":"N Hampton Dr",
    "iso:country":"US",
    "sg:address":"3101 N Hampton Dr",
    "sg:city":"Alexandria",
    "sg:classifiers":[
        {
            "category":"Communications",
            "type":"Services"
        }
    ],
    "sg:phone":"+1 703 623 9226",
    "sg:postcode":"22302",
    "sg:province":"VA",
    "sg:tags":[
        "web",
        "design"
    ],
    "sg:website":"www.fuenteswebdesign.com",
    "wof:name":"Fuentes Web Design",
    "wof:placetype":"venue"
},
  "geometry": {"coordinates":[-77.105689,38.83713],"type":"Point"}
}