{
  "type": "Feature",
  "properties": {
    "iso:country":"US",
    "sg:address":"7336 Riley Rd",
    "sg:city":"Warrenton",
    "sg:classifiers":[
        {
            "category":"Organizations",
            "subcategory":"Religious Organization",
            "type":"Services"
        }
    ],
    "sg:phone":"+1 540 349 0125",
    "sg:postcode":"20187",
    "sg:province":"VA",
    "sg:website":"www.covenantbc.org",
    "wof:name":"Covenant Baptist Church",
    "wof:placetype":"venue"
},
  "geometry": {"coordinates":[-77.71598,38.733584],"type":"Point"}
}