{
  "type": "Feature",
  "properties": {
    "addr:full":"218 Sommerville Way Seaford VA 23696",
    "addr:housenumber":"218",
    "addr:postcode":"23696",
    "addr:street":"Sommerville Way",
    "iso:country":"US",
    "sg:address":"218 Sommerville Way",
    "sg:city":"Seaford",
    "sg:classifiers":[
        {
            "category":"Professional",
            "subcategory":"Employment Agencies",
            "type":"Services"
        }
    ],
    "sg:phone":"+1 757 898 8319",
    "sg:postcode":"23696",
    "sg:province":"VA",
    "sg:tags":[
        "help",
        "supply"
    ],
    "wof:name":"Hancock Marine & Indus Svc",
    "wof:placetype":"venue"
},
  "geometry": {"coordinates":[-76.438698,37.195556],"type":"Point"}
}