{
  "type": "Feature",
  "properties": {
    "addr:full":"9613 Champion Ct Manassas VA 20110",
    "addr:housenumber":"9613",
    "addr:postcode":"20110",
    "addr:street":"Champion Ct",
    "iso:country":"US",
    "sg:address":"9613 Champion Ct",
    "sg:city":"Manassas",
    "sg:classifiers":[
        {
            "category":"Health Services",
            "subcategory":"Doctor",
            "type":"Services"
        }
    ],
    "sg:phone":"+1 703 368 4713",
    "sg:postcode":"20110",
    "sg:province":"VA",
    "sg:tags":[
        "dentist"
    ],
    "wof:name":"Freidank and Freidank",
    "wof:placetype":"venue"
},
  "geometry": {"coordinates":[-77.48532299999999,38.766658],"type":"Point"}
}