{
  "type": "Feature",
  "properties": {
    "addr:full":"18 Edinburgh Ln Hampton VA 23669",
    "addr:housenumber":"18",
    "addr:postcode":"23669",
    "addr:street":"Edinburgh Ln",
    "iso:country":"US",
    "sg:address":"18 Edinburgh Ln",
    "sg:city":"Hampton",
    "sg:classifiers":[
        {
            "category":"Building & Trades",
            "subcategory":"Construction",
            "type":"Services"
        }
    ],
    "sg:phone":"+1 757 850 4542",
    "sg:postcode":"23669",
    "sg:province":"VA",
    "sg:tags":[
        "carpentry",
        "contractor"
    ],
    "wof:name":"Denis Flynn Custom Trim Inc",
    "wof:placetype":"venue"
},
  "geometry": {"coordinates":[-76.313838,37.08277],"type":"Point"}
}