{
  "type": "Feature",
  "properties": {
    "addr:full":"1126 George Washington Memorial Hwy Yorktown VA 23693",
    "addr:housenumber":"1126",
    "addr:postcode":"23693",
    "addr:street":"George Washington Memorial Hwy",
    "iso:country":"US",
    "sg:address":"1126 George Washington Memorial Hwy",
    "sg:city":"Yorktown",
    "sg:classifiers":[
        {
            "category":"Insurance",
            "subcategory":"Insurance Agent",
            "type":"Services"
        }
    ],
    "sg:phone":"+1 757 595 6983",
    "sg:postcode":"23693",
    "sg:province":"VA",
    "wof:name":"Gillilland Insurance Agency",
    "wof:placetype":"venue"
},
  "geometry": {"coordinates":[-76.457913,37.10186],"type":"Point"}
}