{
  "type": "Feature",
  "properties": {
    "addr:full":"206 5th St Broadway VA 22815",
    "addr:housenumber":"206",
    "addr:postcode":"22815",
    "addr:street":"5Th St",
    "iso:country":"US",
    "sg:address":"206 5th St",
    "sg:city":"Broadway",
    "sg:classifiers":[
        {
            "category":"Building & Trades",
            "subcategory":"Construction",
            "type":"Services"
        }
    ],
    "sg:phone":"+1 540 896 2245",
    "sg:postcode":"22815",
    "sg:province":"VA",
    "sg:tags":[
        "water",
        "well",
        "drilling"
    ],
    "wof:name":"Williams Well Drilling Inc",
    "wof:placetype":"venue"
},
  "geometry": {"coordinates":[-78.79739499999999,38.600428],"type":"Point"}
}