{
  "type": "Feature",
  "properties": {
    "addr:full":"20569 Timberlake Rd Lynchburg VA 24502",
    "addr:housenumber":"20569",
    "addr:postcode":"24502",
    "addr:street":"Timberlake Rd",
    "iso:country":"US",
    "sg:address":"20569 Timberlake Rd",
    "sg:city":"Lynchburg",
    "sg:classifiers":[
        {
            "category":"Food & Beverages",
            "subcategory":"Groceries & Convenience Stores",
            "type":"Retail Goods"
        },
        {
            "category":"Autos & Motor Vehicles",
            "subcategory":"Fuel & Gas Station",
            "type":"Retail Goods"
        }
    ],
    "sg:phone":"+1 434 832 0594",
    "sg:postcode":"24502",
    "sg:province":"VA",
    "sg:tags":[
        "station",
        "oil"
    ],
    "wof:name":"Food Land Express Mart",
    "wof:placetype":"venue"
},
  "geometry": {"coordinates":[-79.23791,37.340038],"type":"Point"}
}