{
  "type": "Feature",
  "properties": {
    "addr:full":"410 Elden St Herndon VA 20170",
    "addr:housenumber":"410",
    "addr:postcode":"20170",
    "addr:street":"Elden St",
    "iso:country":"US",
    "sg:address":"410 Elden St",
    "sg:city":"Herndon",
    "sg:classifiers":[
        {
            "category":"Restaurant",
            "type":"Food & Drink"
        }
    ],
    "sg:phone":"+1 703 471 2000",
    "sg:postcode":"20170",
    "sg:province":"VA",
    "sg:tags":[
        "thai",
        "sushi",
        "bar",
        "asian",
        "pan"
    ],
    "sg:website":"http://www.threethaisushi.com/home.html",
    "wof:name":"Three Thai Sushi",
    "wof:placetype":"venue"
},
  "geometry": {"coordinates":[-77.375328,38.967801],"type":"Point"}
}