{
  "type": "Feature",
  "properties": {
    "iso:country":"US",
    "sg:address":"1727 King St",
    "sg:city":"Alexandria",
    "sg:classifiers":[
        {
            "category":"Professional",
            "subcategory":"Lawyer & Legal Services",
            "type":"Services"
        }
    ],
    "sg:phone":"+1 703 739 2247",
    "sg:postcode":"22314",
    "sg:province":"VA",
    "sg:tags":[
        "attorney"
    ],
    "wof:name":"Andrew Bodendorf Law Office",
    "wof:placetype":"venue"
},
  "geometry": {"coordinates":[-77.058245,38.806572],"type":"Point"}
}