{
  "type": "Feature",
  "properties": {
    "iso:country":"US",
    "sg:address":"25719 Simmons Ave",
    "sg:city":"Petersburg",
    "sg:classifiers":[
        {
            "category":"Building & Trades",
            "subcategory":"Construction",
            "type":"Services"
        }
    ],
    "sg:phone":"+1 804 862 4040",
    "sg:postcode":"23803",
    "sg:province":"VA",
    "sg:tags":[
        "roofing",
        "contractor"
    ],
    "wof:name":"Walter D WITT Roofing & Gutter",
    "wof:placetype":"venue"
},
  "geometry": {"coordinates":[-77.46636100000001,37.203783],"type":"Point"}
}