{
  "type": "Feature",
  "properties": {
    "addr:full":"2918 Timbercrest Ct Midlothian VA 23112",
    "addr:housenumber":"2918",
    "addr:postcode":"23112",
    "addr:street":"Timbercrest Ct",
    "iso:country":"US",
    "sg:address":"2918 Timbercrest Ct",
    "sg:city":"Midlothian",
    "sg:classifiers":[
        {
            "category":"Restaurant",
            "type":"Food & Drink"
        }
    ],
    "sg:phone":"+1 804 744 2652",
    "sg:postcode":"23112",
    "sg:province":"VA",
    "sg:tags":[
        "caterer"
    ],
    "wof:name":"Martha's Heavenly Wings",
    "wof:placetype":"venue"
},
  "geometry": {"coordinates":[-77.615092,37.448824],"type":"Point"}
}