{
  "type": "Feature",
  "properties": {
    "iso:country":"US",
    "sg:address":"108 S Columbus St",
    "sg:city":"Alexandria",
    "sg:classifiers":[
        {
            "category":"Real Estate",
            "subcategory":"Real Estate Services",
            "type":"Services"
        },
        {
            "category":"Real Estate",
            "subcategory":"Surveying",
            "type":"Services"
        }
    ],
    "sg:phone":"+1 703 683 1813",
    "sg:postcode":"22314",
    "sg:province":"VA",
    "sg:tags":[
        "industrial",
        "appraisers-commercial",
        "appraiser"
    ],
    "wof:name":"De Hart & Deming",
    "wof:placetype":"venue"
},
  "geometry": {"coordinates":[-77.048109,38.805134],"type":"Point"}
}