{
  "type": "Feature",
  "properties": {
    "addr:full":"5121 Lipsner Ct Annandale VA 22003",
    "addr:housenumber":"5121",
    "addr:postcode":"22003",
    "addr:street":"Lipsner Ct",
    "iso:country":"US",
    "sg:address":"5121 Lipsner Ct",
    "sg:city":"Annandale",
    "sg:classifiers":[
        {
            "category":"Professional",
            "type":"Services"
        }
    ],
    "sg:phone":"+1 703 425 6740",
    "sg:postcode":"22003",
    "sg:province":"VA",
    "wof:name":"Vern Merson",
    "wof:placetype":"venue"
},
  "geometry": {"coordinates":[-77.255725,38.811718],"type":"Point"}
}