{
  "type": "Feature",
  "properties": {
    "iso:country":"US",
    "sg:address":"100 Marclay Dr",
    "sg:city":"Williamsburg",
    "sg:classifiers":[
        {
            "category":"Manufacturing",
            "subcategory":"Tools & Machinery",
            "type":"Manufacturing & Wholesale Goods"
        }
    ],
    "sg:phone":"+1 757 784 3867",
    "sg:postcode":"23185",
    "sg:province":"VA",
    "sg:tags":[
        "equipment",
        "system",
        "automation"
    ],
    "wof:name":"Innovation Systems Inc",
    "wof:placetype":"venue"
},
  "geometry": {"coordinates":[-76.721374,37.24435],"type":"Point"}
}