{
  "type": "Feature",
  "properties": {
    "addr:full":"36 Beverly Hills Dr Newport News VA 23606",
    "addr:housenumber":"36",
    "addr:postcode":"23606",
    "addr:street":"Beverly Hills Dr",
    "iso:country":"US",
    "sg:address":"36 Beverly Hills Dr",
    "sg:city":"Newport News",
    "sg:classifiers":[
        {
            "category":"Real Estate",
            "subcategory":"Real Estate Agent",
            "type":"Services"
        }
    ],
    "sg:phone":"+1 757 595 9120",
    "sg:postcode":"23606",
    "sg:province":"VA",
    "wof:name":"Coenen Real Estate Properties",
    "wof:placetype":"venue"
},
  "geometry": {"coordinates":[-76.524022,37.0648],"type":"Point"}
}