{
  "type": "Feature",
  "properties": {
    "addr:full":"118 E Broad St Falls Church VA 22046",
    "addr:housenumber":"118",
    "addr:postcode":"22046",
    "addr:street":"E Broad St",
    "iso:country":"US",
    "sg:address":"118 E Broad St",
    "sg:city":"Falls Church",
    "sg:classifiers":[
        {
            "category":"Professional",
            "subcategory":"Accounting & Tax Preparation",
            "type":"Services"
        }
    ],
    "sg:phone":"+1 703 241 2080",
    "sg:postcode":"22046",
    "sg:province":"VA",
    "wof:name":"Carl C Shade CPA",
    "wof:placetype":"venue"
},
  "geometry": {"coordinates":[-77.170503,38.881757],"type":"Point"}
}