{
  "type": "Feature",
  "properties": {
    "addr:full":"1102 Lewisetta Rd Lottsburg VA 22511",
    "addr:housenumber":"1102",
    "addr:postcode":"22511",
    "addr:street":"Lewisetta Rd",
    "iso:country":"US",
    "sg:address":"1102 Lewisetta Rd",
    "sg:city":"Lottsburg",
    "sg:classifiers":[
        {
            "category":"Place Of Worship",
            "subcategory":"Church",
            "type":"Public Place"
        },
        {
            "category":"Place Of Worship",
            "type":"Public Place"
        },
        {
            "category":"Organizations",
            "subcategory":"Religious Organization",
            "type":"Services"
        }
    ],
    "sg:phone":"+1 804 529 7723",
    "sg:postcode":"22511",
    "sg:province":"VA",
    "sg:tags":[
        "churches-pentecostal-independent",
        "churches-pentecostal"
    ],
    "wof:name":"Calvary Pentecostal Churc",
    "wof:placetype":"venue"
},
  "geometry": {"coordinates":[-76.52597299999999,37.982847],"type":"Point"}
}