{
  "type": "Feature",
  "properties": {
    "iso:country":"US",
    "sg:address":"10831 W Broad St",
    "sg:city":"Glen Allen",
    "sg:classifiers":[
        {
            "category":"Professional",
            "subcategory":"Computer Services",
            "type":"Services"
        }
    ],
    "sg:phone":"+1 804 741 2805",
    "sg:postcode":"23060",
    "sg:province":"VA",
    "sg:tags":[
        "datum"
    ],
    "wof:name":"Digital Webware",
    "wof:placetype":"venue"
},
  "geometry": {"coordinates":[-77.581659,37.646467],"type":"Point"}
}