{
  "type": "Feature",
  "properties": {
    "addr:full":"3102 9th Rd N Arlington VA 22201",
    "addr:housenumber":"3102",
    "addr:postcode":"22201",
    "addr:street":"9Th Rd N",
    "iso:country":"US",
    "sg:address":"3102 9th Rd N",
    "sg:city":"Arlington",
    "sg:classifiers":[
        {
            "category":"Professional",
            "type":"Services"
        }
    ],
    "sg:phone":"+1 703 528 2686",
    "sg:postcode":"22201",
    "sg:province":"VA",
    "sg:tags":[
        "motion",
        "technician",
        "picture"
    ],
    "wof:name":"Zen Violence Films",
    "wof:placetype":"venue"
},
  "geometry": {"coordinates":[-77.094627,38.883628],"type":"Point"}
}