{
  "type": "Feature",
  "properties": {
    "iso:country":"US",
    "sg:address":"110 Maycox Ave",
    "sg:city":"Norfolk",
    "sg:classifiers":[
        {
            "category":"Professional",
            "subcategory":"Engineering",
            "type":"Services"
        }
    ],
    "sg:phone":"+1 757 440 0045",
    "sg:postcode":"23505",
    "sg:province":"VA",
    "sg:tags":[
        "engineer"
    ],
    "wof:name":"Stan Tec Consulting Group Inc",
    "wof:placetype":"venue"
},
  "geometry": {"coordinates":[-76.27331,36.913443],"type":"Point"}
}