{
  "type": "Feature",
  "properties": {
    "addr:full":"13780 Warwick Blvd Newport News VA 23602",
    "addr:housenumber":"13780",
    "addr:postcode":"23602",
    "addr:street":"Warwick Blvd",
    "iso:country":"US",
    "sg:address":"13780 Warwick Blvd",
    "sg:city":"Newport News",
    "sg:classifiers":[
        {
            "category":"Health Services",
            "subcategory":"Optometrist",
            "type":"Services"
        }
    ],
    "sg:phone":"+1 757 877 3956",
    "sg:postcode":"23602",
    "sg:province":"VA",
    "wof:name":"Hampton Roads Eye Assoc",
    "wof:placetype":"venue"
},
  "geometry": {"coordinates":[-76.530467,37.124505],"type":"Point"}
}