{
  "type": "Feature",
  "properties": {
    "addr:full":"1000 Old Denbigh Blvd Newport News VA 23602",
    "addr:housenumber":"1000",
    "addr:postcode":"23602",
    "addr:street":"Old Denbigh Blvd",
    "iso:country":"US",
    "sg:address":"1000 Old Denbigh Blvd",
    "sg:city":"Newport News",
    "sg:classifiers":[
        {
            "category":"Health Services",
            "subcategory":"Doctor",
            "type":"Services"
        }
    ],
    "sg:phone":"+1 757 872 7003",
    "sg:postcode":"23602",
    "sg:province":"VA",
    "sg:tags":[
        "medical"
    ],
    "wof:name":"Denbigh Internal Medicine",
    "wof:placetype":"venue"
},
  "geometry": {"coordinates":[-76.50762,37.149071],"type":"Point"}
}