{
  "type": "Feature",
  "properties": {
    "iso:country":"US",
    "sg:address":"18501 Brocks Gap Rd",
    "sg:city":"Fulks Run",
    "sg:classifiers":[
        {
            "category":"Building & Trades",
            "subcategory":"Construction",
            "type":"Services"
        }
    ],
    "sg:phone":"+1 540 896 6705",
    "sg:postcode":"22830",
    "sg:province":"VA",
    "sg:tags":[
        "contractor"
    ],
    "wof:name":"Bernhart's Contracting",
    "wof:placetype":"venue"
},
  "geometry": {"coordinates":[-78.901861,38.658619],"type":"Point"}
}