{
  "type": "Feature",
  "properties": {
    "iso:country":"US",
    "sg:address":"3330 N Washington Blvd",
    "sg:city":"Arlington",
    "sg:classifiers":[
        {
            "category":"Restaurant",
            "type":"Food & Drink"
        }
    ],
    "sg:phone":"+1 703 816 8880",
    "sg:postcode":"22201",
    "sg:province":"VA",
    "sg:tags":[
        "delivery",
        "eating"
    ],
    "wof:name":"Partners In Dining Arlington",
    "wof:placetype":"venue"
},
  "geometry": {"coordinates":[-77.099914,38.885893],"type":"Point"}
}