{
  "type": "Feature",
  "properties": {
    "addr:full":"6820 Hamilton Rd Lorton VA 22079",
    "addr:housenumber":"6820",
    "addr:postcode":"22079",
    "addr:street":"Hamilton Rd",
    "iso:country":"US",
    "sg:address":"6820 Hamilton Rd",
    "sg:city":"Lorton",
    "sg:classifiers":[
        {
            "category":"Building & Trades",
            "subcategory":"Cleaning & Sanitation",
            "type":"Services"
        },
        {
            "category":"Home & Garden",
            "subcategory":"Home Furnishings",
            "type":"Retail Goods"
        },
        {
            "category":"Home & Garden",
            "subcategory":"Building Materials",
            "type":"Retail Goods"
        },
        {
            "category":"Building & Trades",
            "subcategory":"Construction",
            "type":"Services"
        },
        {
            "category":"Home & Garden",
            "subcategory":"Furniture",
            "type":"Retail Goods"
        }
    ],
    "sg:phone":"+1 866 909 9492",
    "sg:postcode":"22079",
    "sg:province":"VA",
    "sg:tags":[
        "sunroom",
        "repair",
        "deck",
        "carpenter",
        "contractor",
        "roofing",
        "solarium",
        "improvement",
        "treatment",
        "maintenance",
        "remodeling",
        "specialty",
        "cabinet",
        "downspouts",
        "plastering",
        "gutter",
        "altering",
        "shutter",
        "siding",
        "tile-contractors",
        "drywall",
        "fence-sales"
    ],
    "wof:name":"Mac",
    "wof:placetype":"venue"
},
  "geometry": {"coordinates":[-77.175951,38.731241],"type":"Point"}
}