{
  "type": "Feature",
  "properties": {
    "addr:full":"12519 Mount Blanco Ct Chester VA 23836",
    "addr:housenumber":"12519",
    "addr:postcode":"23836",
    "addr:street":"Mount Blanco Ct",
    "iso:country":"US",
    "sg:address":"12519 Mount Blanco Ct",
    "sg:city":"Chester",
    "sg:classifiers":[
        {
            "category":"Professional",
            "type":"Services"
        }
    ],
    "sg:phone":"+1 804 530 3672",
    "sg:postcode":"23836",
    "sg:province":"VA",
    "wof:name":"Vance Uniformed Protection Svc",
    "wof:placetype":"venue"
},
  "geometry": {"coordinates":[-77.314482,37.360022],"type":"Point"}
}