{
  "type": "Feature",
  "properties": {
    "addr:full":"8692 Young Ct Springfield VA 22153",
    "addr:housenumber":"8692",
    "addr:postcode":"22153",
    "addr:street":"Young Ct",
    "iso:country":"US",
    "sg:address":"8692 Young Ct",
    "sg:city":"Springfield",
    "sg:classifiers":[
        {
            "category":"Professional",
            "subcategory":"Computer Services",
            "type":"Services"
        }
    ],
    "sg:phone":"+1 703 866 4254",
    "sg:postcode":"22153",
    "sg:province":"VA",
    "sg:tags":[
        "related"
    ],
    "wof:name":"Platte River Systems LLC",
    "wof:placetype":"venue"
},
  "geometry": {"coordinates":[-77.233357,38.747439],"type":"Point"}
}