{
  "type": "Feature",
  "properties": {
    "addr:full":"1635 N George Mason Dr Arlington VA 22205",
    "addr:housenumber":"1635",
    "addr:postcode":"22205",
    "addr:street":"N George Mason Dr",
    "iso:country":"US",
    "sg:address":"1635 N George Mason Dr",
    "sg:city":"Arlington",
    "sg:classifiers":[
        {
            "category":"Shopping",
            "subcategory":"Optician",
            "type":"Retail Goods"
        }
    ],
    "sg:phone":"+1 703 524 5888",
    "sg:postcode":"22205",
    "sg:province":"VA",
    "sg:tags":[
        "eyewear"
    ],
    "sg:website":"www.specsbybauer.com",
    "wof:name":"Bauer's Optical",
    "wof:placetype":"venue"
},
  "geometry": {"coordinates":[-77.128045,38.888196],"type":"Point"}
}