{
  "type": "Feature",
  "properties": {
    "addr:full":"1229 Waterwheel Dr Moneta VA 24121",
    "addr:housenumber":"1229",
    "addr:postcode":"24121",
    "addr:street":"Waterwheel Dr",
    "iso:country":"US",
    "sg:address":"1229 Waterwheel Dr",
    "sg:city":"Moneta",
    "sg:classifiers":[
        {
            "category":"Recreation",
            "subcategory":"Marina",
            "type":"Entertainment"
        }
    ],
    "sg:phone":"+1 540 297 5142",
    "sg:postcode":"24121",
    "sg:province":"VA",
    "wof:name":"Marina Waterwheel",
    "wof:placetype":"venue"
},
  "geometry": {"coordinates":[-79.66107,37.148588],"type":"Point"}
}