{
  "type": "Feature",
  "properties": {
    "iso:country":"US",
    "sg:address":"321 Wallace St",
    "sg:city":"Fredericksburg",
    "sg:classifiers":[
        {
            "category":"Freight",
            "type":"Transportation"
        }
    ],
    "sg:phone":"+1 540 373 0042",
    "sg:postcode":"22401",
    "sg:province":"VA",
    "sg:tags":[
        "consultant"
    ],
    "wof:name":"East Coast Resources Brokerage",
    "wof:placetype":"venue"
},
  "geometry": {"coordinates":[-77.472724,38.317978],"type":"Point"}
}