{
  "type": "Feature",
  "properties": {
    "addr:full":"20078 Isle of Wight Industrial Park Rd Smithfield VA 23430",
    "addr:housenumber":"20078",
    "addr:postcode":"23430",
    "addr:street":"Isle Of Wight Industrial Park Rd",
    "iso:country":"US",
    "sg:address":"20078 Isle of Wight Industrial Park Rd",
    "sg:city":"Smithfield",
    "sg:classifiers":[
        {
            "category":"Manufacturing",
            "subcategory":"Metals",
            "type":"Manufacturing & Wholesale Goods"
        }
    ],
    "sg:phone":"+1 757 623 0862",
    "sg:postcode":"23430",
    "sg:province":"VA",
    "sg:tags":[
        "steel",
        "fabrication"
    ],
    "wof:name":"Southern Structural Steel Inc",
    "wof:placetype":"venue"
},
  "geometry": {"coordinates":[-76.580901,36.900694],"type":"Point"}
}