{
  "type": "Feature",
  "properties": {
    "addr:full":"326 Hogart St Franklin VA 23851",
    "addr:housenumber":"326",
    "addr:postcode":"23851",
    "addr:street":"Hogart St",
    "iso:country":"US",
    "sg:address":"326 Hogart St",
    "sg:city":"Franklin",
    "sg:classifiers":[
        {
            "category":"Social Services",
            "subcategory":"Child Care",
            "type":"Services"
        }
    ],
    "sg:phone":"+1 757 562 0800",
    "sg:postcode":"23851",
    "sg:province":"VA",
    "sg:tags":[
        "day"
    ],
    "wof:name":"Kyani Daycare",
    "wof:placetype":"venue"
},
  "geometry": {"coordinates":[-76.937034,36.667459],"type":"Point"}
}