{
  "type": "Feature",
  "properties": {
    "iso:country":"US",
    "sg:address":"7700 E Parham Rd",
    "sg:city":"Richmond",
    "sg:classifiers":[
        {
            "category":"Health Services",
            "subcategory":"Hospital",
            "type":"Services"
        }
    ],
    "sg:phone":"+1 804 747 5600",
    "sg:postcode":"23294",
    "sg:province":"VA",
    "wof:name":"Henrico Doctor's Hospital",
    "wof:placetype":"venue"
},
  "geometry": {"coordinates":[-77.523349,37.62982],"type":"Point"}
}