{
  "type": "Feature",
  "properties": {
    "addr:full":"720 Nurney Dr Newport News VA 23601",
    "addr:housenumber":"720",
    "addr:postcode":"23601",
    "addr:street":"Nurney Dr",
    "iso:country":"US",
    "sg:address":"720 Nurney Dr",
    "sg:city":"Newport News",
    "sg:classifiers":[
        {
            "category":"Building & Trades",
            "subcategory":"Electrical",
            "type":"Services"
        }
    ],
    "sg:phone":"+1 757 591 8884",
    "sg:postcode":"23601",
    "sg:province":"VA",
    "sg:tags":[
        "electrical",
        "contractor"
    ],
    "wof:name":"Mullins Electric",
    "wof:placetype":"venue"
},
  "geometry": {"coordinates":[-76.453208,37.078119],"type":"Point"}
}