{
  "type": "Feature",
  "properties": {
    "addr:full":"5429 Welaka Rd Norfolk VA 23502",
    "addr:housenumber":"5429",
    "addr:postcode":"23502",
    "addr:street":"Welaka Rd",
    "iso:country":"US",
    "sg:address":"5429 Welaka Rd",
    "sg:city":"Norfolk",
    "sg:classifiers":[
        {
            "category":"Health Services",
            "subcategory":"Clinic",
            "type":"Services"
        }
    ],
    "sg:phone":"+1 757 466 0445",
    "sg:postcode":"23502",
    "sg:province":"VA",
    "wof:name":"Associates In Medical Billing",
    "wof:placetype":"venue"
},
  "geometry": {"coordinates":[-76.215889,36.840556],"type":"Point"}
}