{
  "type": "Feature",
  "properties": {
    "addr:full":"3075 Ps Business Center Dr Woodbridge VA 22192",
    "addr:postcode":"3075;22192",
    "addr:street":"Ps Business Center Dr",
    "iso:country":"US",
    "sg:address":"3075 Ps Business Center Dr",
    "sg:city":"Woodbridge",
    "sg:classifiers":[
        {
            "category":"Professional",
            "subcategory":"Computer Services",
            "type":"Services"
        }
    ],
    "sg:phone":"+1 703 897 9362",
    "sg:postcode":"22192",
    "sg:province":"VA",
    "wof:name":"Unlimited Access Inc",
    "wof:placetype":"venue"
},
  "geometry": {"coordinates":[-77.303421,38.653755],"type":"Point"}
}