{
  "type": "Feature",
  "properties": {
    "iso:country":"US",
    "sg:address":"5003 Westfields Blvd",
    "sg:city":"Centreville",
    "sg:classifiers":[
        {
            "category":"Government",
            "subcategory":"Post Office",
            "type":"Public Place"
        }
    ],
    "sg:phone":"+1 703 961 9184",
    "sg:postcode":"20120",
    "sg:province":"VA",
    "sg:tags":[
        "postal",
        "us"
    ],
    "wof:name":"US Post Office",
    "wof:placetype":"venue"
},
  "geometry": {"coordinates":[-77.448292,38.86649],"type":"Point"}
}