{
  "type": "Feature",
  "properties": {
    "addr:full":"1741 Westwind Way Mc Lean VA 22102",
    "addr:postcode":"1741;22102",
    "addr:street":"Westwind Way Mc Lean",
    "iso:country":"US",
    "sg:address":"1741 Westwind Way",
    "sg:city":"Mc Lean",
    "sg:classifiers":[
        {
            "category":"Retail",
            "subcategory":"Laundry & Dry Cleaning",
            "type":"Services"
        }
    ],
    "sg:phone":"+1 703 506 0321",
    "sg:postcode":"22102",
    "sg:province":"VA",
    "sg:tags":[
        "garment",
        "pressing",
        "agent",
        "cleaners"
    ],
    "wof:name":"Royal Cleaning",
    "wof:placetype":"venue"
},
  "geometry": {"coordinates":[-77.198598,38.922715],"type":"Point"}
}