{
  "type": "Feature",
  "properties": {
    "addr:full":"2671 Brownsburg Tpke Brownsburg VA 24415",
    "addr:housenumber":"2671",
    "addr:postcode":"24415",
    "addr:street":"Tpke",
    "iso:country":"US",
    "sg:address":"2671 Brownsburg Tpke",
    "sg:city":"Brownsburg",
    "sg:classifiers":[
        {
            "category":"Professional",
            "subcategory":"Lawyer & Legal Services",
            "type":"Services"
        }
    ],
    "sg:phone":"+1 540 348 5698",
    "sg:postcode":"24415",
    "sg:province":"VA",
    "sg:tags":[
        "attorney"
    ],
    "wof:name":"Richard G Anderson",
    "wof:placetype":"venue"
},
  "geometry": {"coordinates":[-79.31972,37.927735],"type":"Point"}
}