{
  "type": "Feature",
  "properties": {
    "iso:country":"US",
    "sg:address":"10227 Rogers Dr",
    "sg:city":"Nassawadox",
    "sg:classifiers":[
        {
            "category":"Restaurant",
            "type":"Food & Drink"
        }
    ],
    "sg:phone":"+1 757 442 7831",
    "sg:postcode":"23413",
    "sg:province":"VA",
    "wof:name":"Little Italy Restaurant",
    "wof:placetype":"venue"
},
  "geometry": {"coordinates":[-75.855735,37.473183],"type":"Point"}
}