{
  "type": "Feature",
  "properties": {
    "addr:full":"3091 Lauderdale Dr Richmond VA 23233",
    "addr:housenumber":"3091",
    "addr:postcode":"23233",
    "addr:street":"Lauderdale Dr",
    "iso:country":"US",
    "sg:address":"3091 Lauderdale Dr",
    "sg:city":"Richmond",
    "sg:classifiers":[
        {
            "category":"Shopping",
            "subcategory":"Pharmacy",
            "type":"Retail Goods"
        }
    ],
    "sg:phone":"+1 804 360 7596",
    "sg:postcode":"23233",
    "sg:province":"VA",
    "sg:tags":[
        "drug",
        "store"
    ],
    "wof:name":"CVS",
    "wof:placetype":"venue"
},
  "geometry": {"coordinates":[-77.63370500000001,37.637193],"type":"Point"}
}