{
  "type": "Feature",
  "properties": {
    "addr:full":"11073 Washington Hwy Glen Allen VA 23059",
    "addr:housenumber":"11073",
    "addr:postcode":"23059",
    "addr:street":"Washington Hwy",
    "iso:country":"US",
    "sg:address":"11073 Washington Hwy",
    "sg:city":"Glen Allen",
    "sg:classifiers":[
        {
            "category":"Retail",
            "subcategory":"Auto Repair",
            "type":"Services"
        }
    ],
    "sg:phone":"+1 804 752 6079",
    "sg:postcode":"23059",
    "sg:province":"VA",
    "sg:tags":[
        "engine",
        "truck",
        "consisting",
        "maintenance"
    ],
    "wof:name":"Truck Force The",
    "wof:placetype":"venue"
},
  "geometry": {"coordinates":[-77.46510000000001,37.703838],"type":"Point"}
}