{
  "type": "Feature",
  "properties": {
    "addr:full":"3300 Roanoke Ave Newport News VA 23607",
    "addr:housenumber":"3300",
    "addr:postcode":"23607",
    "addr:street":"Roanoke Ave",
    "iso:country":"US",
    "sg:address":"3300 Roanoke Ave",
    "sg:city":"Newport News",
    "sg:classifiers":[
        {
            "category":"Organizations",
            "subcategory":"Religious Organization",
            "type":"Services"
        }
    ],
    "sg:phone":"+1 757 247 0461",
    "sg:postcode":"23607",
    "sg:province":"VA",
    "sg:tags":[
        "church"
    ],
    "wof:name":"Glorious Church-The Lord Jesus",
    "wof:placetype":"venue"
},
  "geometry": {"coordinates":[-76.412623,36.991975],"type":"Point"}
}