{
  "type": "Feature",
  "properties": {
    "addr:full":"7918 Jones Branch Dr #750 Fairfax County VA 22102",
    "addr:housenumber":"7918;750",
    "addr:postcode":"22102",
    "addr:street":"Jones Branch Dr #",
    "iso:country":"US",
    "sg:address":"7918 Jones Branch Dr #750",
    "sg:city":"Fairfax County",
    "sg:classifiers":[
        {
            "category":"Health Services",
            "subcategory":"Clinic",
            "type":"Services"
        }
    ],
    "sg:phone":"+1 703 934 7935",
    "sg:postcode":"22102",
    "sg:province":"VA",
    "sg:tags":[
        "medical"
    ],
    "sg:website":"www.LogicMark.com",
    "wof:name":"LogicMark, LLC",
    "wof:placetype":"venue"
},
  "geometry": {"coordinates":[-77.216542,38.92547],"type":"Point"}
}