{
  "type": "Feature",
  "properties": {
    "iso:country":"US",
    "sg:address":"300 W Main St",
    "sg:city":"Luray",
    "sg:classifiers":[
        {
            "category":"Building & Trades",
            "subcategory":"Plumbing",
            "type":"Services"
        }
    ],
    "sg:phone":"+1 540 743 5121",
    "sg:postcode":"22835",
    "sg:province":"VA",
    "sg:tags":[
        "plumbing",
        "electrical",
        "heating",
        "contractor"
    ],
    "wof:name":"Campbells Plumbing",
    "wof:placetype":"venue"
},
  "geometry": {"coordinates":[-78.466043,38.6656],"type":"Point"}
}