{
  "type": "Feature",
  "properties": {
    "addr:full":"1501 Lee Hwy Ste 102 Arlington VA 22209",
    "addr:housenumber":"1501",
    "addr:postcode":"22209",
    "addr:street":"Lee Hwy Ste 102",
    "iso:country":"US",
    "sg:address":"1501 Lee Hwy Ste 102",
    "sg:city":"Arlington",
    "sg:classifiers":[
        {
            "category":"Professional",
            "subcategory":"Accounting & Tax Preparation",
            "type":"Services"
        }
    ],
    "sg:phone":"+1 703 524 0900",
    "sg:postcode":"22209",
    "sg:province":"VA",
    "sg:tags":[
        "accountant"
    ],
    "wof:name":"Devlin John P CPA",
    "wof:placetype":"venue"
},
  "geometry": {"coordinates":[-77.075401,38.898998],"type":"Point"}
}