{
  "type": "Feature",
  "properties": {
    "addr:full":"238 W Broad St Falls Church VA 22046",
    "addr:housenumber":"238",
    "addr:postcode":"22046",
    "addr:street":"W Broad St",
    "iso:country":"US",
    "sg:address":"238 W Broad St",
    "sg:city":"Falls Church",
    "sg:classifiers":[
        {
            "category":"Restaurant",
            "type":"Food & Drink"
        }
    ],
    "sg:menulink":"http://www.allmenus.com/va/falls-church/277457-maneki-neko-japanese-restaurant/menu/",
    "sg:phone":"+1 703 534 8666",
    "sg:postcode":"22046",
    "sg:province":"VA",
    "sg:tags":[
        "japanese",
        "asian"
    ],
    "wof:name":"Maneki Neko Japanese Restaurant",
    "wof:placetype":"venue"
},
  "geometry": {"coordinates":[-77.17277199999999,38.883365],"type":"Point"}
}