{
  "type": "Feature",
  "properties": {
    "addr:full":"12531 Dillingham Sq Woodbridge VA 22192",
    "addr:housenumber":"12531",
    "addr:postcode":"22192",
    "addr:street":"Dillingham Sq",
    "iso:country":"US",
    "sg:address":"12531 Dillingham Sq",
    "sg:city":"Woodbridge",
    "sg:classifiers":[
        {
            "category":"Restaurant",
            "type":"Food & Drink"
        }
    ],
    "sg:menulink":"http://www.allmenus.com/va/occoquan/70983-jerrys-subs--pizza/menu/",
    "sg:phone":"+1 703 590 2477",
    "sg:postcode":"22192",
    "sg:province":"VA",
    "sg:tags":[
        "sandwich",
        "salad",
        "cheesesteaks",
        "soup",
        "american",
        "wrap",
        "wing",
        "pizza"
    ],
    "wof:name":"Jerry's Subs & Pizza",
    "wof:placetype":"venue"
},
  "geometry": {"coordinates":[-77.319458,38.682951],"type":"Point"}
}