{
  "type": "Feature",
  "properties": {
    "addr:full":"211 Appomattox St Farmville VA 23901",
    "addr:housenumber":"211",
    "addr:postcode":"23901",
    "addr:street":"Appomattox St",
    "iso:country":"US",
    "sg:address":"211 Appomattox St",
    "sg:city":"Farmville",
    "sg:classifiers":[
        {
            "category":"Organizations",
            "subcategory":"Religious Organization",
            "type":"Services"
        }
    ],
    "sg:phone":"+1 434 392 8432",
    "sg:postcode":"23901",
    "sg:province":"VA",
    "sg:tags":[
        "clergy"
    ],
    "wof:name":"Elmer N Hassell",
    "wof:placetype":"venue"
},
  "geometry": {"coordinates":[-78.39824400000001,37.303752],"type":"Point"}
}