{
  "type": "Feature",
  "properties": {
    "iso:country":"US",
    "sg:address":"2844 N Shore Dr",
    "sg:city":"Suffolk",
    "sg:classifiers":[
        {
            "category":"Health Services",
            "subcategory":"Health Practitioner",
            "type":"Services"
        }
    ],
    "sg:phone":"+1 757 641 1295",
    "sg:postcode":"23435",
    "sg:province":"VA",
    "sg:tags":[
        "nurse"
    ],
    "wof:name":"Nancy Sinibali",
    "wof:placetype":"venue"
},
  "geometry": {"coordinates":[-76.49826299999999,36.865993],"type":"Point"}
}