{
  "type": "Feature",
  "properties": {
    "addr:full":"43802 Bent Creek Ter Leesburg VA 20176",
    "addr:housenumber":"43802",
    "addr:postcode":"20176",
    "addr:street":"Bent Creek Ter",
    "iso:country":"US",
    "sg:address":"43802 Bent Creek Ter",
    "sg:city":"Leesburg",
    "sg:classifiers":[
        {
            "category":"Professional",
            "subcategory":"Management & Consulting",
            "type":"Services"
        }
    ],
    "sg:phone":"+1 703 669 9630",
    "sg:postcode":"20176",
    "sg:province":"VA",
    "sg:tags":[
        "resource",
        "human"
    ],
    "wof:name":"Vicky Durham & Associates",
    "wof:placetype":"venue"
},
  "geometry": {"coordinates":[-77.483367,39.102506],"type":"Point"}
}