{
  "type": "Feature",
  "properties": {
    "iso:country":"US",
    "sg:address":"7525 Whitepine Rd",
    "sg:city":"Richmond",
    "sg:classifiers":[
        {
            "category":"Building & Trades",
            "subcategory":"Construction",
            "type":"Services"
        }
    ],
    "sg:phone":"+1 804 275 8524",
    "sg:postcode":"23237",
    "sg:province":"VA",
    "sg:tags":[
        "dwelling",
        "family",
        "contractor"
    ],
    "wof:name":"S & K Builders Inc",
    "wof:placetype":"venue"
},
  "geometry": {"coordinates":[-77.522475,37.398564],"type":"Point"}
}