{
  "type": "Feature",
  "properties": {
    "addr:full":"12113 Club Commons Dr Glen Allen VA 23059",
    "addr:housenumber":"12113",
    "addr:postcode":"23059",
    "addr:street":"Club Commons Dr",
    "iso:country":"US",
    "sg:address":"12113 Club Commons Dr",
    "sg:city":"Glen Allen",
    "sg:classifiers":[
        {
            "category":"Recreation",
            "type":"Entertainment"
        }
    ],
    "sg:phone":"+1 804 364 1656",
    "sg:postcode":"23059",
    "sg:province":"VA",
    "sg:tags":[
        "club",
        "membership"
    ],
    "wof:name":"Club Commons Assoc",
    "wof:placetype":"venue"
},
  "geometry": {"coordinates":[-77.60938,37.702811],"type":"Point"}
}