{
  "type": "Feature",
  "properties": {
    "iso:country":"US",
    "sg:address":"5520 Liber Ct",
    "sg:city":"Gainesville",
    "sg:classifiers":[
        {
            "category":"Manufacturing",
            "subcategory":"Toys & Sporting Goods",
            "type":"Manufacturing & Wholesale Goods"
        }
    ],
    "sg:phone":"+1 703 753 1861",
    "sg:postcode":"20155",
    "sg:province":"VA",
    "sg:tags":[
        "mfg"
    ],
    "wof:name":"Moon Bounce Inc",
    "wof:placetype":"venue"
},
  "geometry": {"coordinates":[-77.600454,38.849041],"type":"Point"}
}