{
  "type": "Feature",
  "properties": {
    "iso:country":"US",
    "sg:address":"4180 Sontag Rd",
    "sg:city":"Rocky Mount",
    "sg:classifiers":[
        {
            "category":"Farming",
            "subcategory":"Livestock Farm",
            "type":"Manufacturing & Wholesale Goods"
        }
    ],
    "sg:phone":"+1 540 483 4488",
    "sg:postcode":"24151",
    "sg:province":"VA",
    "sg:tags":[
        "beef",
        "feedlot",
        "cattle"
    ],
    "wof:name":"Leland Mitchell",
    "wof:placetype":"venue"
},
  "geometry": {"coordinates":[-79.83815,36.922868],"type":"Point"}
}