{
  "type": "Feature",
  "properties": {
    "addr:full":"10 S Market St Salem VA 24153",
    "addr:housenumber":"10",
    "addr:postcode":"24153",
    "addr:street":"S Market St",
    "iso:country":"US",
    "sg:address":"10 S Market St",
    "sg:city":"Salem",
    "sg:classifiers":[
        {
            "category":"Travel",
            "subcategory":"Hotels & Motels",
            "type":"Entertainment"
        }
    ],
    "sg:phone":"+1 540 389 2424",
    "sg:postcode":"24153",
    "sg:province":"VA",
    "wof:name":"Holiday Inn",
    "wof:placetype":"venue"
},
  "geometry": {"coordinates":[-80.05642400000001,37.292255],"type":"Point"}
}