{
  "type": "Feature",
  "properties": {
    "addr:full":"419 Brooke Dr Danville VA 24540",
    "addr:housenumber":"419",
    "addr:postcode":"24540",
    "addr:street":"Brooke Dr",
    "iso:country":"US",
    "sg:address":"419 Brooke Dr",
    "sg:city":"Danville",
    "sg:classifiers":[
        {
            "category":"Banks & Credit Unions",
            "subcategory":"Investment Brokerage",
            "type":"Services"
        }
    ],
    "sg:phone":"+1 434 793 1868",
    "sg:postcode":"24540",
    "sg:province":"VA",
    "sg:tags":[
        "advisory"
    ],
    "wof:name":"Long Financial Services",
    "wof:placetype":"venue"
},
  "geometry": {"coordinates":[-79.393109,36.62333],"type":"Point"}
}