{
  "type": "Feature",
  "properties": {
    "addr:full":"1801 Ducatus Dr Midlothian VA 23113",
    "addr:housenumber":"1801",
    "addr:postcode":"23113",
    "addr:street":"Ducatus Dr",
    "iso:country":"US",
    "sg:address":"1801 Ducatus Dr",
    "sg:city":"Midlothian",
    "sg:classifiers":[
        {
            "category":"Building & Trades",
            "subcategory":"Construction",
            "type":"Services"
        }
    ],
    "sg:phone":"+1 804 379 5904",
    "sg:postcode":"23113",
    "sg:province":"VA",
    "sg:tags":[
        "house"
    ],
    "wof:name":"Sherlock Homes Construction Co",
    "wof:placetype":"venue"
},
  "geometry": {"coordinates":[-77.640528,37.514899],"type":"Point"}
}