{
  "type": "Feature",
  "properties": {
    "addr:full":"8283 Greensboro Dr Mc Lean VA 22102",
    "addr:housenumber":"8283",
    "addr:postcode":"22102",
    "addr:street":"Greensboro Dr",
    "iso:country":"US",
    "sg:address":"8283 Greensboro Dr",
    "sg:city":"Mc Lean",
    "sg:classifiers":[
        {
            "category":"Real Estate",
            "subcategory":"Real Estate Services",
            "type":"Services"
        }
    ],
    "sg:phone":"+1 703 714 0590",
    "sg:postcode":"22102",
    "sg:province":"VA",
    "sg:tags":[
        "management",
        "property"
    ],
    "wof:name":"Marshall Property Llc",
    "wof:placetype":"venue"
},
  "geometry": {"coordinates":[-77.229176,38.922164],"type":"Point"}
}