{
  "type": "Feature",
  "properties": {
    "iso:country":"US",
    "sg:address":"7044 Lee Park Rd",
    "sg:city":"Mechanicsville",
    "sg:classifiers":[
        {
            "category":"Social Services",
            "subcategory":"Child Care",
            "type":"Services"
        }
    ],
    "sg:phone":"+1 804 569 9000",
    "sg:postcode":"23111",
    "sg:province":"VA",
    "wof:name":"Discovery Child Dev Ctr",
    "wof:placetype":"venue"
},
  "geometry": {"coordinates":[-77.338002,37.616063],"type":"Point"}
}