{
  "type": "Feature",
  "properties": {
    "addr:full":"327 W 21st St Norfolk VA 23517",
    "addr:housenumber":"327",
    "addr:postcode":"23517",
    "addr:street":"W 21St St",
    "iso:country":"US",
    "sg:address":"327 W 21st St",
    "sg:city":"Norfolk",
    "sg:classifiers":[
        {
            "category":"Health Services",
            "subcategory":"Doctor",
            "type":"Services"
        }
    ],
    "sg:phone":"+1 757 624 1834",
    "sg:postcode":"23517",
    "sg:province":"VA",
    "sg:tags":[
        "dentist"
    ],
    "wof:name":"C Gary Clayton DDS",
    "wof:placetype":"venue"
},
  "geometry": {"coordinates":[-76.289524,36.868502],"type":"Point"}
}