{
  "type": "Feature",
  "properties": {
    "addr:full":"7619 Little River Tpke Annandale VA 22003",
    "addr:housenumber":"7619",
    "addr:postcode":"22003",
    "addr:street":"Little River Tpke",
    "iso:country":"US",
    "sg:address":"7619 Little River Tpke",
    "sg:city":"Annandale",
    "sg:classifiers":[
        {
            "category":"Banks & Credit Unions",
            "subcategory":"Bank",
            "type":"Services"
        }
    ],
    "sg:phone":"+1 703 750 3282",
    "sg:postcode":"22003",
    "sg:province":"VA",
    "sg:tags":[
        "broker",
        "mortgage"
    ],
    "wof:name":"Bank of America NA",
    "wof:placetype":"venue"
},
  "geometry": {"coordinates":[-77.21040600000001,38.832628],"type":"Point"}
}