{
  "type": "Feature",
  "properties": {
    "iso:country":"US",
    "sg:address":"601 N Main St",
    "sg:city":"Harrisonburg",
    "sg:classifiers":[
        {
            "category":"Professional",
            "subcategory":"Advertising",
            "type":"Services"
        }
    ],
    "sg:phone":"+1 540 432 5581",
    "sg:postcode":"22802",
    "sg:province":"VA",
    "sg:tags":[
        "agency"
    ],
    "wof:name":"Advertising Unlimited Inc",
    "wof:placetype":"venue"
},
  "geometry": {"coordinates":[-78.864813,38.455881],"type":"Point"}
}