{
  "type": "Feature",
  "properties": {
    "addr:full":"2903 Arlington Dr Alexandria VA 22306",
    "addr:housenumber":"2903",
    "addr:postcode":"22306",
    "addr:street":"Arlington Dr",
    "iso:country":"US",
    "sg:address":"2903 Arlington Dr",
    "sg:city":"Alexandria",
    "sg:classifiers":[
        {
            "category":"Shopping",
            "subcategory":"Gifts & Souvenirs",
            "type":"Retail Goods"
        }
    ],
    "sg:phone":"+1 703 768 4502",
    "sg:postcode":"22306",
    "sg:province":"VA",
    "sg:tags":[
        "shop"
    ],
    "wof:name":"Edith's Gift Shop",
    "wof:placetype":"venue"
},
  "geometry": {"coordinates":[-77.083451,38.754471],"type":"Point"}
}