{
  "type": "Feature",
  "properties": {
    "addr:full":"4260 Crossings Blvd Prince George VA 23875",
    "addr:housenumber":"4260",
    "addr:postcode":"23875",
    "addr:street":"Crossings Blvd",
    "iso:country":"US",
    "sg:address":"4260 Crossings Blvd",
    "sg:city":"Prince George",
    "sg:classifiers":[
        {
            "category":"Professional",
            "subcategory":"Engineering",
            "type":"Services"
        }
    ],
    "sg:phone":"+1 804 458 8685",
    "sg:postcode":"23875",
    "sg:province":"VA",
    "sg:tags":[
        "engineer"
    ],
    "sg:website":"www.timmons.com",
    "wof:name":"Timmons Group Inc",
    "wof:placetype":"venue"
},
  "geometry": {"coordinates":[-77.32733,37.258477],"type":"Point"}
}