{
  "type": "Feature",
  "properties": {
    "iso:country":"US",
    "sg:address":"2721 Merrilee Dr",
    "sg:city":"Fairfax",
    "sg:classifiers":[
        {
            "category":"Professional",
            "subcategory":"Business Services",
            "type":"Services"
        },
        {
            "category":"Home & Garden",
            "subcategory":"Furniture",
            "type":"Retail Goods"
        }
    ],
    "sg:phone":"+1 703 208 2208",
    "sg:postcode":"22031",
    "sg:province":"VA",
    "sg:tags":[
        "personal",
        "bureau",
        "broker",
        "agent",
        "cabinet"
    ],
    "sg:website":"www.kleppingerdesign.com",
    "wof:name":"Kleppinger Design Group LLC",
    "wof:placetype":"venue"
},
  "geometry": {"coordinates":[-77.23084799999999,38.87834],"type":"Point"}
}