{
  "type": "Feature",
  "properties": {
    "addr:full":"255 E Marshall St Wytheville VA 24382",
    "addr:housenumber":"255",
    "addr:postcode":"24382",
    "addr:street":"E Marshall St",
    "iso:country":"US",
    "sg:address":"255 E Marshall St",
    "sg:city":"Wytheville",
    "sg:classifiers":[
        {
            "category":"Manufacturing",
            "subcategory":"Metals",
            "type":"Manufacturing & Wholesale Goods"
        }
    ],
    "sg:phone":"+1 276 228 7739",
    "sg:postcode":"24382",
    "sg:province":"VA",
    "sg:tags":[
        "treating",
        "heat"
    ],
    "wof:name":"Southwest Spec Heat Treat Inc",
    "wof:placetype":"venue"
},
  "geometry": {"coordinates":[-81.075031,36.944099],"type":"Point"}
}