{
  "type": "Feature",
  "properties": {
    "iso:country":"US",
    "sg:address":"8905 Bluegate Dr",
    "sg:city":"Fairfax",
    "sg:classifiers":[
        {
            "category":"Wholesale",
            "subcategory":"Jewelry",
            "type":"Manufacturing & Wholesale Goods"
        }
    ],
    "sg:phone":"+1 703 573 2666",
    "sg:postcode":"22031",
    "sg:province":"VA",
    "sg:tags":[
        "jeweler"
    ],
    "wof:name":"Damar Universal",
    "wof:placetype":"venue"
},
  "geometry": {"coordinates":[-77.25321099999999,38.87526],"type":"Point"}
}