{
  "type": "Feature",
  "properties": {
    "iso:country":"US",
    "sg:address":"10043 Midlothian Tpke",
    "sg:city":"Richmond",
    "sg:classifiers":[
        {
            "category":"Real Estate",
            "subcategory":"Real Estate Services",
            "type":"Services"
        }
    ],
    "sg:phone":"+1 804 320 9666",
    "sg:postcode":"23235",
    "sg:province":"VA",
    "sg:tags":[
        "company",
        "abstract",
        "title"
    ],
    "wof:name":"New Guardian Title Svc",
    "wof:placetype":"venue"
},
  "geometry": {"coordinates":[-77.58129700000001,37.505768],"type":"Point"}
}