{
  "type": "Feature",
  "properties": {
    "addr:full":"1035 N Main St Hillsville VA 24343",
    "addr:housenumber":"1035",
    "addr:postcode":"24343",
    "addr:street":"N Main St",
    "iso:country":"US",
    "sg:address":"1035 N Main St",
    "sg:city":"Hillsville",
    "sg:classifiers":[
        {
            "category":"Retail",
            "subcategory":"Funeral Services",
            "type":"Services"
        }
    ],
    "sg:phone":"+1 276 728 2041",
    "sg:postcode":"24343",
    "sg:province":"VA",
    "sg:tags":[
        "director",
        "home"
    ],
    "wof:name":"Vaughan-Guynn-Mc Grady Chapel",
    "wof:placetype":"venue"
},
  "geometry": {"coordinates":[-80.73832,36.768743],"type":"Point"}
}