{
  "type": "Feature",
  "properties": {
    "addr:full":"2122 Colonial Ave SW Roanoke VA 24015",
    "addr:housenumber":"2122",
    "addr:postcode":"24015",
    "addr:street":"Colonial Ave Sw",
    "iso:country":"US",
    "sg:address":"2122 Colonial Ave SW",
    "sg:city":"Roanoke",
    "sg:classifiers":[
        {
            "category":"Building & Trades",
            "subcategory":"Landscaping Services",
            "type":"Services"
        }
    ],
    "sg:phone":"+1 540 342 8031",
    "sg:postcode":"24015",
    "sg:province":"VA",
    "sg:tags":[
        "tree"
    ],
    "wof:name":"Etter Stump Removal",
    "wof:placetype":"venue"
},
  "geometry": {"coordinates":[-79.956502,37.254435],"type":"Point"}
}