{
  "type": "Feature",
  "properties": {
    "addr:full":"11449 Robious Rd Richmond VA 23235",
    "addr:housenumber":"11449",
    "addr:postcode":"23235",
    "addr:street":"Robious Rd",
    "iso:country":"US",
    "sg:address":"11449 Robious Rd",
    "sg:city":"Richmond",
    "sg:classifiers":[
        {
            "category":"Social Services",
            "subcategory":"Child Care",
            "type":"Services"
        }
    ],
    "sg:phone":"+1 804 323 3250",
    "sg:postcode":"23235",
    "sg:province":"VA",
    "wof:name":"LA Petite Academy",
    "wof:placetype":"venue"
},
  "geometry": {"coordinates":[-77.608845,37.520989],"type":"Point"}
}