{
  "type": "Feature",
  "properties": {
    "addr:full":"907 Brandon Quay Chesapeake VA 23320",
    "addr:housenumber":"907",
    "addr:postcode":"23320",
    "addr:street":"Brandon Quay",
    "iso:country":"US",
    "sg:address":"907 Brandon Quay",
    "sg:city":"Chesapeake",
    "sg:classifiers":[
        {
            "category":"Professional",
            "type":"Services"
        }
    ],
    "sg:phone":"+1 757 436 1402",
    "sg:postcode":"23320",
    "sg:province":"VA",
    "wof:name":"Denise Robinson",
    "wof:placetype":"venue"
},
  "geometry": {"coordinates":[-76.221474,36.756422],"type":"Point"}
}