{
  "type": "Feature",
  "properties": {
    "iso:country":"US",
    "sg:address":"3403 Skipping Rock Ct",
    "sg:city":"Richmond",
    "sg:classifiers":[
        {
            "category":"Freight",
            "type":"Transportation"
        }
    ],
    "sg:phone":"+1 804 675 0406",
    "sg:postcode":"23234",
    "sg:province":"VA",
    "sg:tags":[
        "courier"
    ],
    "wof:name":"Independent Courier Co Inc",
    "wof:placetype":"venue"
},
  "geometry": {"coordinates":[-77.49540399999999,37.46801],"type":"Point"}
}