{
  "type": "Feature",
  "properties": {
    "iso:country":"US",
    "sg:address":"415 Bear Creek Rd",
    "sg:city":"Atkins",
    "sg:classifiers":[
        {
            "category":"Manufacturing",
            "subcategory":"Glass & Minerals",
            "type":"Manufacturing & Wholesale Goods"
        }
    ],
    "sg:phone":"+1 276 782 3500",
    "sg:postcode":"24311",
    "sg:province":"VA",
    "sg:tags":[
        "manufactured",
        "stone",
        "crushed"
    ],
    "wof:name":"Bear Creek Quarry",
    "wof:placetype":"venue"
},
  "geometry": {"coordinates":[-81.440952,36.869489],"type":"Point"}
}