{
  "type": "Feature",
  "properties": {
    "addr:full":"1605 S Tidwells Rd Montross VA 22520",
    "addr:housenumber":"1605",
    "addr:postcode":"22520",
    "addr:street":"S Tidwells Rd",
    "iso:country":"US",
    "sg:address":"1605 S Tidwells Rd",
    "sg:city":"Montross",
    "sg:classifiers":[
        {
            "category":"Wholesale",
            "subcategory":"Seafood",
            "type":"Manufacturing & Wholesale Goods"
        }
    ],
    "sg:phone":"+1 804 472 3870",
    "sg:postcode":"22520",
    "sg:province":"VA",
    "wof:name":"S & W Seafood",
    "wof:placetype":"venue"
},
  "geometry": {"coordinates":[-76.653379,38.109724],"type":"Point"}
}