{
  "type": "Feature",
  "properties": {
    "addr:full":"9230 Kings Hwy King George VA 22485",
    "addr:housenumber":"9230",
    "addr:postcode":"22485",
    "addr:street":"Kings Hwy",
    "iso:country":"US",
    "sg:address":"9230 Kings Hwy",
    "sg:city":"King George",
    "sg:classifiers":[
        {
            "category":"Home & Garden",
            "subcategory":"Garden Supply",
            "type":"Retail Goods"
        }
    ],
    "sg:phone":"+1 540 775 8383",
    "sg:postcode":"22485",
    "sg:province":"VA",
    "sg:tags":[
        "nurseryman"
    ],
    "wof:name":"Green Acres Nursery LLC",
    "wof:placetype":"venue"
},
  "geometry": {"coordinates":[-77.187532,38.269131],"type":"Point"}
}