{
  "type": "Feature",
  "properties": {
    "iso:country":"US",
    "sg:address":"690 Berkmar Cir",
    "sg:city":"Charlottesville",
    "sg:classifiers":[
        {
            "category":"Real Estate",
            "subcategory":"Real Estate Agent",
            "type":"Services"
        }
    ],
    "sg:phone":"+1 434 220 3454",
    "sg:postcode":"22901",
    "sg:province":"VA",
    "wof:name":"Central Virginia Real Estate Inc",
    "wof:placetype":"venue"
},
  "geometry": {"coordinates":[-78.47821,38.084544],"type":"Point"}
}