{
  "type": "Feature",
  "properties": {
    "addr:full":"11030 James Monroe Hwy Culpeper VA 22701",
    "addr:housenumber":"11030",
    "addr:postcode":"22701",
    "addr:street":"James Monroe Hwy",
    "iso:country":"US",
    "sg:address":"11030 James Monroe Hwy",
    "sg:city":"Culpeper",
    "sg:classifiers":[
        {
            "category":"Autos & Motor Vehicles",
            "subcategory":"Automobile Sales",
            "type":"Retail Goods"
        }
    ],
    "sg:phone":"+1 540 547 3900",
    "sg:postcode":"22701",
    "sg:province":"VA",
    "sg:tags":[
        "car",
        "dealership",
        "dealer"
    ],
    "sg:website":"www.chryslerofculpeper.com",
    "wof:name":"Chrysler of Culpepper",
    "wof:placetype":"venue"
},
  "geometry": {"coordinates":[-78.04482299999999,38.45707],"type":"Point"}
}