{
  "type": "Feature",
  "properties": {
    "addr:full":"4350 Pouncey Tract Rd Glen Allen VA 23060",
    "addr:housenumber":"4350",
    "addr:postcode":"23060",
    "addr:street":"Pouncey Tract Rd",
    "iso:country":"US",
    "sg:address":"4350 Pouncey Tract Rd",
    "sg:city":"Glen Allen",
    "sg:classifiers":[
        {
            "category":"Recreation",
            "type":"Entertainment"
        }
    ],
    "sg:phone":"+1 804 364 1477",
    "sg:postcode":"23060",
    "sg:province":"VA",
    "sg:tags":[
        "club",
        "membership",
        "s"
    ],
    "wof:name":"Skate Nation Plus",
    "wof:placetype":"venue"
},
  "geometry": {"coordinates":[-77.61178700000001,37.657337],"type":"Point"}
}