{
  "type": "Feature",
  "properties": {
    "iso:country":"US",
    "sg:address":"7978 Forbes Pl",
    "sg:city":"Springfield",
    "sg:classifiers":[
        {
            "category":"Retail",
            "subcategory":"Auto Repair",
            "type":"Services"
        }
    ],
    "sg:phone":"+1 703 321 8981",
    "sg:postcode":"22151",
    "sg:province":"VA",
    "sg:tags":[
        "general"
    ],
    "wof:name":"Capitol Car Care",
    "wof:placetype":"venue"
},
  "geometry": {"coordinates":[-77.220128,38.808224],"type":"Point"}
}