{
  "type": "Feature",
  "properties": {
    "iso:country":"US",
    "sg:address":"800 E Main St",
    "sg:city":"Wytheville",
    "sg:classifiers":[
        {
            "category":"Social Services",
            "type":"Services"
        }
    ],
    "sg:phone":"+1 276 223 3274",
    "sg:postcode":"24382",
    "sg:province":"VA",
    "wof:name":"Youth Services",
    "wof:placetype":"venue"
},
  "geometry": {"coordinates":[-81.07052299999999,36.951739],"type":"Point"}
}