{
  "type": "Feature",
  "properties": {
    "addr:full":"312 S Main St Lexington VA 24450",
    "addr:housenumber":"312",
    "addr:postcode":"24450",
    "addr:street":"S Main St",
    "iso:country":"US",
    "sg:address":"312 S Main St",
    "sg:city":"Lexington",
    "sg:classifiers":[
        {
            "category":"Shopping",
            "type":"Retail Goods"
        }
    ],
    "sg:phone":"+1 540 463 7994",
    "sg:postcode":"24450",
    "sg:province":"VA",
    "sg:tags":[
        "merchandise"
    ],
    "wof:name":"Virginia Global Communications",
    "wof:placetype":"venue"
},
  "geometry": {"coordinates":[-79.445052,37.782194],"type":"Point"}
}