{
  "type": "Feature",
  "properties": {
    "addr:full":"4907 Commerce Dr Fredericksburg VA 22408",
    "addr:housenumber":"4907",
    "addr:postcode":"22408",
    "addr:street":"Commerce Dr",
    "iso:country":"US",
    "sg:address":"4907 Commerce Dr",
    "sg:city":"Fredericksburg",
    "sg:classifiers":[
        {
            "category":"Wholesale",
            "subcategory":"Stationery",
            "type":"Manufacturing & Wholesale Goods"
        }
    ],
    "sg:phone":"+1 540 455 4961",
    "sg:postcode":"22408",
    "sg:province":"VA",
    "sg:tags":[
        "supply"
    ],
    "wof:name":"Lasting Images",
    "wof:placetype":"venue"
},
  "geometry": {"coordinates":[-77.503068,38.258008],"type":"Point"}
}