{
  "type": "Feature",
  "properties": {
    "addr:full":"4701 Sadler Green Pl Glen Allen VA 23060",
    "addr:housenumber":"4701",
    "addr:postcode":"23060",
    "addr:street":"Sadler Green Pl",
    "iso:country":"US",
    "sg:address":"4701 Sadler Green Pl",
    "sg:city":"Glen Allen",
    "sg:classifiers":[
        {
            "category":"Real Estate",
            "subcategory":"Real Estate Agent",
            "type":"Services"
        }
    ],
    "sg:phone":"+1 804 270 0064",
    "sg:postcode":"23060",
    "sg:province":"VA",
    "wof:name":"Sadler Green Sales Center",
    "wof:placetype":"venue"
},
  "geometry": {"coordinates":[-77.58750499999999,37.664501],"type":"Point"}
}