{
  "type": "Feature",
  "properties": {
    "addr:full":"6815 Colburn Dr Annandale VA 22003",
    "addr:housenumber":"6815",
    "addr:postcode":"22003",
    "addr:street":"Colburn Dr",
    "iso:country":"US",
    "sg:address":"6815 Colburn Dr",
    "sg:city":"Annandale",
    "sg:classifiers":[
        {
            "category":"Professional",
            "subcategory":"Management & Consulting",
            "type":"Services"
        }
    ],
    "sg:phone":"+1 703 642 5282",
    "sg:postcode":"22003",
    "sg:province":"VA",
    "wof:name":"Trade Show Strategies",
    "wof:placetype":"venue"
},
  "geometry": {"coordinates":[-77.181719,38.812983],"type":"Point"}
}