{
  "type": "Feature",
  "properties": {
    "iso:country":"US",
    "sg:address":"1468 Wi Powell Rd",
    "sg:city":"Dry Fork",
    "sg:classifiers":[
        {
            "category":"Retail",
            "subcategory":"Animal Services",
            "type":"Services"
        }
    ],
    "sg:phone":"+1 434 724 4661",
    "sg:postcode":"24549",
    "sg:province":"VA",
    "sg:tags":[
        "pet",
        "boarding",
        "sitting"
    ],
    "wof:name":"Royal Woodvine Kennels",
    "wof:placetype":"venue"
},
  "geometry": {"coordinates":[-79.47310899999999,36.727173],"type":"Point"}
}