{
  "type": "Feature",
  "properties": {
    "addr:full":"315 Spring St Herndon VA 20170",
    "addr:housenumber":"315",
    "addr:postcode":"20170",
    "addr:street":"Spring St",
    "iso:country":"US",
    "sg:address":"315 Spring St",
    "sg:city":"Herndon",
    "sg:classifiers":[
        {
            "category":"Retail",
            "subcategory":"Laundry & Dry Cleaning",
            "type":"Services"
        }
    ],
    "sg:phone":"+1 703 435 7966",
    "sg:postcode":"20170",
    "sg:province":"VA",
    "sg:tags":[
        "drycleaning",
        "plant"
    ],
    "wof:name":"Bobs Cleaners & Tailors",
    "wof:placetype":"venue"
},
  "geometry": {"coordinates":[-77.37473799999999,38.958866],"type":"Point"}
}