{
  "type": "Feature",
  "properties": {
    "addr:full":"110 Bridle Ln Newport News VA 23608",
    "addr:housenumber":"110",
    "addr:postcode":"23608",
    "addr:street":"Bridle Ln",
    "iso:country":"US",
    "sg:address":"110 Bridle Ln",
    "sg:city":"Newport News",
    "sg:classifiers":[
        {
            "category":"Retail",
            "subcategory":"Portrait Studio",
            "type":"Services"
        }
    ],
    "sg:phone":"+1 757 877 8589",
    "sg:postcode":"23608",
    "sg:province":"VA",
    "sg:tags":[
        "photo"
    ],
    "wof:name":"Coyotes Den Photos",
    "wof:placetype":"venue"
},
  "geometry": {"coordinates":[-76.534702,37.174153],"type":"Point"}
}