{
  "type": "Feature",
  "properties": {
    "addr:full":"3430 Greentree Dr Falls Church VA 22041",
    "addr:housenumber":"3430",
    "addr:postcode":"22041",
    "addr:street":"Greentree Dr;Va",
    "iso:country":"US",
    "sg:address":"3430 Greentree Dr",
    "sg:city":"Falls Church",
    "sg:classifiers":[
        {
            "category":"Professional",
            "subcategory":"Management & Consulting",
            "type":"Services"
        }
    ],
    "sg:phone":"+1 703 998 6544",
    "sg:postcode":"22041",
    "sg:province":"VA",
    "sg:tags":[
        "technical",
        "consultant"
    ],
    "wof:name":"Barbara L Yoon",
    "wof:placetype":"venue"
},
  "geometry": {"coordinates":[-77.14916599999999,38.849927],"type":"Point"}
}