{
  "type": "Feature",
  "properties": {
    "iso:country":"US",
    "sg:address":"44 Rens Rd",
    "sg:city":"Poquoson",
    "sg:classifiers":[
        {
            "category":"Building & Trades",
            "subcategory":"Cleaning & Sanitation",
            "type":"Services"
        }
    ],
    "sg:phone":"+1 757 868 8136",
    "sg:postcode":"23662",
    "sg:province":"VA",
    "sg:tags":[
        "ventilating",
        "system"
    ],
    "wof:name":"Ventilation Purification",
    "wof:placetype":"venue"
},
  "geometry": {"coordinates":[-76.379244,37.134276],"type":"Point"}
}