{
  "type": "Feature",
  "properties": {
    "iso:country":"US",
    "sg:address":"21 E Main St",
    "sg:city":"Richmond",
    "sg:classifiers":[
        {
            "category":"Shopping",
            "type":"Retail Goods"
        }
    ],
    "sg:phone":"+1 804 644 6440",
    "sg:postcode":"23219",
    "sg:province":"VA",
    "sg:tags":[
        "merchandise"
    ],
    "wof:name":"Framework Studio LLC",
    "wof:placetype":"venue"
},
  "geometry": {"coordinates":[-77.44371700000001,37.542564],"type":"Point"}
}