{
  "type": "Feature",
  "properties": {
    "iso:country":"US",
    "sg:address":"2524 Columbia Pike",
    "sg:city":"Arlington",
    "sg:classifiers":[
        {
            "category":"Building & Trades",
            "subcategory":"Locksmith",
            "type":"Services"
        }
    ],
    "sg:phone":"+1 703 253 9361",
    "sg:postcode":"22204",
    "sg:province":"VA",
    "sg:tags":[
        "key"
    ],
    "wof:name":"Arlington Locksmith & Lockout Service",
    "wof:placetype":"venue"
},
  "geometry": {"coordinates":[-77.084548,38.863041],"type":"Point"}
}