{
  "type": "Feature",
  "properties": {
    "iso:country":"US",
    "sg:address":"105 Delaware Ave",
    "sg:city":"Hamilton",
    "sg:classifiers":[
        {
            "category":"Building & Trades",
            "subcategory":"Plumbing",
            "type":"Services"
        }
    ],
    "sg:phone":"+1 540 338 6007",
    "sg:postcode":"20158",
    "sg:province":"VA",
    "sg:tags":[
        "septic",
        "contractor"
    ],
    "wof:name":"Loudoun Septic Tank Service",
    "wof:placetype":"venue"
},
  "geometry": {"coordinates":[-77.668162,39.139676],"type":"Point"}
}