{
  "type": "Feature",
  "properties": {
    "addr:full":"3833 Freezeland Rd Linden VA 22642",
    "addr:housenumber":"3833",
    "addr:postcode":"22642",
    "addr:street":"Freezeland Rd",
    "iso:country":"US",
    "sg:address":"3833 Freezeland Rd",
    "sg:city":"Linden",
    "sg:classifiers":[
        {
            "category":"Building & Trades",
            "subcategory":"Construction",
            "type":"Services"
        }
    ],
    "sg:phone":"+1 540 622 6912",
    "sg:postcode":"22642",
    "sg:province":"VA",
    "sg:tags":[
        "house"
    ],
    "wof:name":"Dga Home Improvements Inc",
    "wof:placetype":"venue"
},
  "geometry": {"coordinates":[-78.039587,38.940384],"type":"Point"}
}