{
  "type": "Feature",
  "properties": {
    "addr:full":"7660 E Parham Rd Richmond VA 23294",
    "addr:housenumber":"7660",
    "addr:postcode":"23294",
    "addr:street":"E Parham Rd",
    "iso:country":"US",
    "sg:address":"7660 E Parham Rd",
    "sg:city":"Richmond",
    "sg:classifiers":[
        {
            "category":"Health Services",
            "subcategory":"Doctor",
            "type":"Services"
        }
    ],
    "sg:phone":"+1 804 965 0690",
    "sg:postcode":"23294",
    "sg:province":"VA",
    "sg:tags":[
        "physician",
        "surgeon"
    ],
    "wof:name":"Arthur S Harrow MD",
    "wof:placetype":"venue"
},
  "geometry": {"coordinates":[-77.52479200000001,37.630046],"type":"Point"}
}