{
  "type": "Feature",
  "properties": {
    "addr:full":"9521 Jefferson Davis Hwy Richmond VA 23237",
    "addr:housenumber":"9521",
    "addr:postcode":"23237",
    "addr:street":"Jefferson Davis Hwy",
    "iso:country":"US",
    "sg:address":"9521 Jefferson Davis Hwy",
    "sg:city":"Richmond",
    "sg:classifiers":[
        {
            "category":"Wholesale",
            "subcategory":"Machinery & Supplies",
            "type":"Manufacturing & Wholesale Goods"
        }
    ],
    "sg:phone":"+1 804 275 7848",
    "sg:postcode":"23237",
    "sg:province":"VA",
    "sg:tags":[
        "hardware",
        "rope",
        "industrial",
        "mfg"
    ],
    "wof:name":"Chesterfield Trading Company",
    "wof:placetype":"venue"
},
  "geometry": {"coordinates":[-77.429385,37.394565],"type":"Point"}
}