{
  "type": "Feature",
  "properties": {
    "addr:full":"5335 Gainsborough Dr Fairfax VA 22032",
    "addr:housenumber":"5335",
    "addr:postcode":"22032",
    "addr:street":"Gainsborough Dr",
    "iso:country":"US",
    "sg:address":"5335 Gainsborough Dr",
    "sg:city":"Fairfax",
    "sg:classifiers":[
        {
            "category":"Professional",
            "subcategory":"Engineering",
            "type":"Services"
        }
    ],
    "sg:phone":"+1 703 321 8956",
    "sg:postcode":"22032",
    "sg:province":"VA",
    "sg:tags":[
        "engineer"
    ],
    "wof:name":"Sontz Engineering",
    "wof:placetype":"venue"
},
  "geometry": {"coordinates":[-77.290662,38.805735],"type":"Point"}
}