{
  "type": "Feature",
  "properties": {
    "iso:country":"US",
    "sg:address":"5211 Port Royal Rd",
    "sg:city":"Springfield",
    "sg:classifiers":[
        {
            "category":"Professional",
            "subcategory":"Business Services",
            "type":"Services"
        }
    ],
    "sg:phone":"+1 703 321 1882",
    "sg:postcode":"22151",
    "sg:province":"VA",
    "wof:name":"Free Enterprise Institute",
    "wof:placetype":"venue"
},
  "geometry": {"coordinates":[-77.21983,38.809362],"type":"Point"}
}