{
  "type": "Feature",
  "properties": {
    "addr:full":"4018 Oak Moss Ct Chesapeake VA 23321",
    "addr:housenumber":"4018",
    "addr:postcode":"23321",
    "addr:street":"Oak Moss Ct",
    "iso:country":"US",
    "sg:address":"4018 Oak Moss Ct",
    "sg:city":"Chesapeake",
    "sg:classifiers":[
        {
            "category":"Professional",
            "subcategory":"Accounting & Tax Preparation",
            "type":"Services"
        }
    ],
    "sg:phone":"+1 757 465 4131",
    "sg:postcode":"23321",
    "sg:province":"VA",
    "wof:name":"Medical Systems Diversifi",
    "wof:placetype":"venue"
},
  "geometry": {"coordinates":[-76.407951,36.829816],"type":"Point"}
}