{
  "type": "Feature",
  "properties": {
    "addr:full":"1423 Stewart Ave Chesapeake VA 23324",
    "addr:housenumber":"1423",
    "addr:postcode":"23324",
    "addr:street":"Stewart Ave",
    "iso:country":"US",
    "sg:address":"1423 Stewart Ave",
    "sg:city":"Chesapeake",
    "sg:classifiers":[
        {
            "category":"Building & Trades",
            "subcategory":"Electrical",
            "type":"Services"
        }
    ],
    "sg:phone":"+1 757 494 7816",
    "sg:postcode":"23324",
    "sg:province":"VA",
    "sg:tags":[
        "electric",
        "contractor"
    ],
    "wof:name":"Blake's Electric Svc",
    "wof:placetype":"venue"
},
  "geometry": {"coordinates":[-76.275932,36.811108],"type":"Point"}
}