{
  "type": "Feature",
  "properties": {
    "addr:full":"43794 Abbott Pl Ashburn VA 20147",
    "addr:housenumber":"43794",
    "addr:postcode":"20147",
    "addr:street":"Abbott Pl",
    "iso:country":"US",
    "sg:address":"43794 Abbott Pl",
    "sg:city":"Ashburn",
    "sg:classifiers":[
        {
            "category":"Professional",
            "subcategory":"Management & Consulting",
            "type":"Services"
        }
    ],
    "sg:phone":"+1 703 627 5090",
    "sg:postcode":"20147",
    "sg:province":"VA",
    "sg:tags":[
        "business"
    ],
    "wof:name":"Piedmont Consulting Inc",
    "wof:placetype":"venue"
},
  "geometry": {"coordinates":[-77.485159,39.021228],"type":"Point"}
}