{
  "type": "Feature",
  "properties": {
    "addr:full":"1003 Cottonwood Dr Blacksburg VA 24060",
    "addr:housenumber":"1003",
    "addr:postcode":"24060",
    "addr:street":"Cottonwood Dr",
    "iso:country":"US",
    "sg:address":"1003 Cottonwood Dr",
    "sg:city":"Blacksburg",
    "sg:classifiers":[
        {
            "category":"Professional",
            "subcategory":"Computer Services",
            "type":"Services"
        }
    ],
    "sg:phone":"+1 540 250 1300",
    "sg:postcode":"24060",
    "sg:province":"VA",
    "sg:tags":[
        "project",
        "engineering",
        "design",
        "software"
    ],
    "wof:name":"Acumenia Inc",
    "wof:placetype":"venue"
},
  "geometry": {"coordinates":[-80.401869,37.265996],"type":"Point"}
}