{
  "type": "Feature",
  "properties": {
    "addr:full":"9577 Foursquare Rd Windsor VA 23487",
    "addr:postcode":"23487",
    "addr:street":"Foursquare Rd",
    "iso:country":"US",
    "sg:address":"9577 Foursquare Rd",
    "sg:city":"Windsor",
    "sg:phone":"+1 757 357 2321",
    "sg:postcode":"23487",
    "sg:province":"VA",
    "sg:tags":[
        "farm",
        "field",
        "corn",
        "soybean",
        "crop"
    ],
    "wof:name":"Nurney John",
    "wof:placetype":"venue"
},
  "geometry": {"coordinates":[-76.756854,36.933209],"type":"Point"}
}