{
  "type": "Feature",
  "properties": {
    "iso:country":"US",
    "sg:address":"8229 Boone Blvd Ste 200",
    "sg:city":"Vienna",
    "sg:classifiers":[
        {
            "category":"Professional",
            "subcategory":"Computer Services",
            "type":"Services"
        }
    ],
    "sg:phone":"+1 703 637 7000",
    "sg:postcode":"22182",
    "sg:province":"VA",
    "sg:tags":[
        "repair"
    ],
    "wof:name":"Onsite Access",
    "wof:placetype":"venue"
},
  "geometry": {"coordinates":[-77.228897,38.914902],"type":"Point"}
}