{
  "type": "Feature",
  "properties": {
    "addr:full":"1801 Chamberlayne Ave Richmond VA 23222",
    "addr:housenumber":"1801",
    "addr:postcode":"23222",
    "addr:street":"Chamberlayne Ave",
    "iso:country":"US",
    "sg:address":"1801 Chamberlayne Ave",
    "sg:city":"Richmond",
    "sg:classifiers":[
        {
            "category":"Autos & Motor Vehicles",
            "subcategory":"Automobile Sales",
            "type":"Retail Goods"
        }
    ],
    "sg:phone":"+1 804 672 4873",
    "sg:postcode":"23222",
    "sg:province":"VA",
    "sg:tags":[
        "dealers-used",
        "car",
        "used",
        "cars-wholesale",
        "new"
    ],
    "wof:name":"Standard Auto Group",
    "wof:placetype":"venue"
},
  "geometry": {"coordinates":[-77.44252,37.559399],"type":"Point"}
}