{
  "type": "Feature",
  "properties": {
    "iso:country":"US",
    "sg:address":"700 S Birdneck Rd",
    "sg:city":"Virginia Beach",
    "sg:classifiers":[
        {
            "category":"Recreation",
            "type":"Entertainment"
        }
    ],
    "sg:phone":"+1 757 422 6419",
    "sg:postcode":"23451",
    "sg:province":"VA",
    "sg:tags":[
        "park",
        "eating",
        "amusement"
    ],
    "wof:name":"Motorworld of Virginia Beach",
    "wof:placetype":"venue"
},
  "geometry": {"coordinates":[-75.99803,36.816405],"type":"Point"}
}