{
  "type": "Feature",
  "properties": {
    "iso:country":"US",
    "sg:address":"1524 Spring Vale Ave",
    "sg:city":"Mc Lean",
    "sg:classifiers":[
        {
            "category":"Professional",
            "subcategory":"Management & Consulting",
            "type":"Services"
        }
    ],
    "sg:phone":"+1 703 734 0878",
    "sg:postcode":"22101",
    "sg:province":"VA",
    "sg:tags":[
        "consultant",
        "telecommunication"
    ],
    "wof:name":"Communications Resources Inc",
    "wof:placetype":"venue"
},
  "geometry": {"coordinates":[-77.184046,38.930523],"type":"Point"}
}