{
  "type": "Feature",
  "properties": {
    "iso:country":"US",
    "sg:address":"6845 Elm St Ste 600",
    "sg:city":"McLean",
    "sg:classifiers":[
        {
            "category":"Health Services",
            "subcategory":"Doctor",
            "type":"Services"
        }
    ],
    "sg:phone":"+1 703 748 9880",
    "sg:postcode":"22101",
    "sg:province":"VA",
    "sg:tags":[
        "obstetrician",
        "gynecologist"
    ],
    "wof:name":"Drs. Armstrong, Bannon, & Lawson OB/GYN",
    "wof:placetype":"venue"
},
  "geometry": {"coordinates":[-77.180211,38.93619],"type":"Point"}
}