{
  "type": "Feature",
  "properties": {
    "addr:full":"500 Hospital Dr Warrenton VA 20186",
    "addr:housenumber":"500",
    "addr:postcode":"20186",
    "addr:street":"Hospital Dr",
    "iso:country":"US",
    "sg:address":"500 Hospital Dr",
    "sg:city":"Warrenton",
    "sg:classifiers":[
        {
            "category":"Health Services",
            "subcategory":"Hospital",
            "type":"Services"
        }
    ],
    "sg:phone":"+1 540 347 2550",
    "sg:postcode":"20186",
    "sg:province":"VA",
    "sg:tags":[
        "general"
    ],
    "wof:name":"Fauquier Hospital Inc",
    "wof:placetype":"venue"
},
  "geometry": {"coordinates":[-77.808998,38.711204],"type":"Point"}
}