{
  "type": "Feature",
  "properties": {
    "addr:full":"101 Pelham Dr Waynesboro VA 22980",
    "addr:housenumber":"101",
    "addr:postcode":"22980",
    "addr:street":"Pelham Dr",
    "iso:country":"US",
    "sg:address":"101 Pelham Dr",
    "sg:city":"Waynesboro",
    "sg:classifiers":[
        {
            "category":"Health Services",
            "subcategory":"Doctor",
            "type":"Services"
        }
    ],
    "sg:phone":"+1 540 943 9703",
    "sg:postcode":"22980",
    "sg:province":"VA",
    "wof:name":"Diane Chaldares DDS",
    "wof:placetype":"venue"
},
  "geometry": {"coordinates":[-78.92863699999999,38.083743],"type":"Point"}
}