{
  "type": "Feature",
  "properties": {
    "addr:full":"1207 Town Springs Rd Chilhowie VA 24319",
    "addr:housenumber":"1207",
    "addr:postcode":"24319",
    "addr:street":"Town Springs Rd",
    "iso:country":"US",
    "sg:address":"1207 Town Springs Rd",
    "sg:city":"Chilhowie",
    "sg:classifiers":[
        {
            "category":"Retail",
            "subcategory":"Repair Shop",
            "type":"Services"
        }
    ],
    "sg:phone":"+1 276 646 5206",
    "sg:postcode":"24319",
    "sg:province":"VA",
    "sg:tags":[
        "related"
    ],
    "wof:name":"Shumate Brothers Sm Eng Repair",
    "wof:placetype":"venue"
},
  "geometry": {"coordinates":[-81.640221,36.71385],"type":"Point"}
}