{
  "type": "Feature",
  "properties": {
    "iso:country":"US",
    "sg:address":"3927 Victory Blvd",
    "sg:city":"Portsmouth",
    "sg:classifiers":[
        {
            "category":"Sports & Exercise",
            "subcategory":"Gym",
            "type":"Entertainment"
        }
    ],
    "sg:phone":"+1 757 405 0099",
    "sg:postcode":"23701",
    "sg:province":"VA",
    "sg:tags":[
        "fitness",
        "physical",
        "facility"
    ],
    "wof:name":"New Millennium Fitness Inc",
    "wof:placetype":"venue"
},
  "geometry": {"coordinates":[-76.357094,36.808323],"type":"Point"}
}