{
  "type": "Feature",
  "properties": {
    "addr:full":"7840 Gold Flint Dr Clifton VA 20124",
    "addr:housenumber":"7840",
    "addr:postcode":"20124",
    "addr:street":"Gold Flint Dr",
    "iso:country":"US",
    "sg:address":"7840 Gold Flint Dr",
    "sg:city":"Clifton",
    "sg:classifiers":[
        {
            "category":"Real Estate",
            "subcategory":"Developer",
            "type":"Services"
        }
    ],
    "sg:phone":"+1 703 968 0699",
    "sg:postcode":"20124",
    "sg:province":"VA",
    "wof:name":"Shw Development Corp",
    "wof:placetype":"venue"
},
  "geometry": {"coordinates":[-77.394425,38.765594],"type":"Point"}
}