{
  "type": "Feature",
  "properties": {
    "iso:country":"US",
    "sg:address":"1320 Old Chain Bridge Rd",
    "sg:city":"Mc Lean",
    "sg:classifiers":[
        {
            "category":"Banks & Credit Unions",
            "subcategory":"Bank",
            "type":"Services"
        }
    ],
    "sg:phone":"+1 703 356 2265",
    "sg:postcode":"22101",
    "sg:province":"VA",
    "sg:website":"www.unitedbank-dcmetro.com",
    "wof:name":"United Bank",
    "wof:placetype":"venue"
},
  "geometry": {"coordinates":[-77.176697,38.9398],"type":"Point"}
}