{
  "type": "Feature",
  "properties": {
    "addr:full":"101 Taylorwood Rd Galax VA 24333",
    "addr:housenumber":"101",
    "addr:postcode":"24333",
    "addr:street":"Taylorwood Rd",
    "iso:country":"US",
    "sg:address":"101 Taylorwood Rd",
    "sg:city":"Galax",
    "sg:classifiers":[
        {
            "category":"Personal",
            "subcategory":"Beauty Salon",
            "type":"Services"
        }
    ],
    "sg:phone":"+1 276 236 3911",
    "sg:postcode":"24333",
    "sg:province":"VA",
    "wof:name":"A New You Salon Spa",
    "wof:placetype":"venue"
},
  "geometry": {"coordinates":[-80.89368,36.681678],"type":"Point"}
}