{
  "type": "Feature",
  "properties": {
    "iso:country":"US",
    "sg:address":"7300 Beulah St",
    "sg:city":"Alexandria",
    "sg:classifiers":[
        {
            "category":"Shopping",
            "subcategory":"Used Merchandise",
            "type":"Retail Goods"
        }
    ],
    "sg:phone":"+1 703 719 9366",
    "sg:postcode":"22315",
    "sg:province":"VA",
    "sg:tags":[
        "shop",
        "consignment",
        "store"
    ],
    "wof:name":"Kids Again",
    "wof:placetype":"venue"
},
  "geometry": {"coordinates":[-77.15955099999999,38.760128],"type":"Point"}
}