{
  "type": "Feature",
  "properties": {
    "iso:country":"US",
    "sg:address":"2155 Apperson Dr",
    "sg:city":"Salem",
    "sg:classifiers":[
        {
            "category":"Health Services",
            "subcategory":"Doctor",
            "type":"Services"
        }
    ],
    "sg:phone":"+1 540 776 5646",
    "sg:postcode":"24153",
    "sg:province":"VA",
    "sg:tags":[
        "medical"
    ],
    "wof:name":"John E Sadler III",
    "wof:placetype":"venue"
},
  "geometry": {"coordinates":[-80.019609,37.264517],"type":"Point"}
}