{
  "type": "Feature",
  "properties": {
    "addr:full":"10953 Lute Ct Manassas VA 20109",
    "addr:housenumber":"10953",
    "addr:postcode":"20109",
    "addr:street":"Lute Ct",
    "iso:country":"US",
    "sg:address":"10953 Lute Ct",
    "sg:city":"Manassas",
    "sg:classifiers":[
        {
            "category":"Manufacturing",
            "subcategory":"Food",
            "type":"Manufacturing & Wholesale Goods"
        }
    ],
    "sg:phone":"+1 703 368 1249",
    "sg:postcode":"20109",
    "sg:province":"VA",
    "sg:tags":[
        "preparation",
        "mfg"
    ],
    "wof:name":"Riveras Tortillas",
    "wof:placetype":"venue"
},
  "geometry": {"coordinates":[-77.522543,38.800834],"type":"Point"}
}