{
  "type": "Feature",
  "properties": {
    "addr:full":"22204 Stablehouse Dr Sterling VA 20164",
    "addr:housenumber":"22204",
    "addr:postcode":"20164",
    "addr:street":"Stablehouse Dr",
    "iso:country":"US",
    "sg:address":"22204 Stablehouse Dr",
    "sg:city":"Sterling",
    "sg:classifiers":[
        {
            "category":"Professional",
            "subcategory":"Engineering",
            "type":"Services"
        }
    ],
    "sg:phone":"+1 703 404 2758",
    "sg:postcode":"20164",
    "sg:province":"VA",
    "wof:name":"Techedge Engineering Solutions",
    "wof:placetype":"venue"
},
  "geometry": {"coordinates":[-77.426051,39.004885],"type":"Point"}
}