{
  "type": "Feature",
  "properties": {
    "addr:full":"2200 N Wilson Blvd Arlington VA 22201",
    "addr:housenumber":"2200",
    "addr:postcode":"22201",
    "addr:street":"N Wilson Blvd",
    "iso:country":"US",
    "sg:address":"2200 N Wilson Blvd",
    "sg:city":"Arlington",
    "sg:classifiers":[
        {
            "category":"Professional",
            "subcategory":"Business Services",
            "type":"Services"
        }
    ],
    "sg:phone":"+1 703 243 0970",
    "sg:postcode":"22201",
    "sg:province":"VA",
    "wof:name":"W R A P Inc",
    "wof:placetype":"venue"
},
  "geometry": {"coordinates":[-77.086145,38.891096],"type":"Point"}
}