{
  "type": "Feature",
  "properties": {
    "iso:country":"US",
    "sg:address":"1513 Mount Cross Rd",
    "sg:city":"Danville",
    "sg:classifiers":[
        {
            "category":"Personal",
            "subcategory":"Beauty Salon",
            "type":"Services"
        }
    ],
    "sg:phone":"+1 434 792 3600",
    "sg:postcode":"24540",
    "sg:province":"VA",
    "sg:tags":[
        "shop"
    ],
    "wof:name":"New Reflections",
    "wof:placetype":"venue"
},
  "geometry": {"coordinates":[-79.43923599999999,36.613187],"type":"Point"}
}