{
  "type": "Feature",
  "properties": {
    "addr:full":"8301 Hungary Spring Rd Richmond VA 23228",
    "addr:postcode":"8301;23228",
    "addr:street":"Spring Rd",
    "iso:country":"US",
    "sg:address":"8301 Hungary Spring Rd",
    "sg:city":"Richmond",
    "sg:classifiers":[
        {
            "category":"Restaurant",
            "type":"Food & Drink"
        }
    ],
    "sg:menulink":"http://www.allmenus.com/va/brookland/147813-subway/menu/",
    "sg:phone":"+1 804 262 3000",
    "sg:postcode":"23228",
    "sg:province":"VA",
    "sg:tags":[
        "american",
        "sandwich"
    ],
    "wof:name":"Subway",
    "wof:placetype":"venue"
},
  "geometry": {"coordinates":[-77.51854899999999,37.633842],"type":"Point"}
}