{
  "type": "Feature",
  "properties": {
    "addr:full":"1 S Mallory St Hampton VA 23663",
    "addr:housenumber":"1",
    "addr:postcode":"23663",
    "addr:street":"S Mallory St",
    "iso:country":"US",
    "sg:address":"1 S Mallory St",
    "sg:city":"Hampton",
    "sg:classifiers":[
        {
            "category":"Social Services",
            "type":"Services"
        }
    ],
    "sg:phone":"+1 757 722 4707",
    "sg:postcode":"23663",
    "sg:province":"VA",
    "sg:tags":[
        "organization",
        "welfare"
    ],
    "sg:website":"www.lfsva.org",
    "wof:name":"Lutheran Family Svc Of Va",
    "wof:placetype":"venue"
},
  "geometry": {"coordinates":[-76.32228499999999,37.018614],"type":"Point"}
}