{
  "type": "Feature",
  "properties": {
    "addr:full":"7844 Richmond Hwy Alexandria VA 22306",
    "addr:housenumber":"7844",
    "addr:postcode":"22306",
    "addr:street":"Richmond Hwy",
    "iso:country":"US",
    "sg:address":"7844 Richmond Hwy",
    "sg:city":"Alexandria",
    "sg:classifiers":[
        {
            "category":"Home & Garden",
            "subcategory":"Hardware",
            "type":"Retail Goods"
        }
    ],
    "sg:phone":"+1 703 360 2125",
    "sg:postcode":"22306",
    "sg:province":"VA",
    "wof:name":"Sears Hardware Stores",
    "wof:placetype":"venue"
},
  "geometry": {"coordinates":[-77.083776,38.745034],"type":"Point"}
}