{
  "type": "Feature",
  "properties": {
    "addr:full":"220 Bypass Rd Williamsburg VA 23185",
    "addr:housenumber":"220",
    "addr:postcode":"23185",
    "addr:street":"Bypass Rd",
    "iso:country":"US",
    "sg:address":"220 Bypass Rd",
    "sg:city":"Williamsburg",
    "sg:classifiers":[
        {
            "category":"Travel",
            "subcategory":"Hotels & Motels",
            "type":"Entertainment"
        }
    ],
    "sg:phone":"+1 757 259 1700",
    "sg:postcode":"23185",
    "sg:province":"VA",
    "wof:name":"Sleep Inn",
    "wof:placetype":"venue"
},
  "geometry": {"coordinates":[-76.716891,37.285013],"type":"Point"}
}