{
  "type": "Feature",
  "properties": {
    "addr:full":"16183 Richardson Ave Abingdon VA 24210",
    "addr:housenumber":"16183",
    "addr:postcode":"24210",
    "addr:street":"Richardson Ave",
    "iso:country":"US",
    "sg:address":"16183 Richardson Ave",
    "sg:city":"Abingdon",
    "sg:classifiers":[
        {
            "category":"Insurance",
            "subcategory":"Life Insurance",
            "type":"Services"
        }
    ],
    "sg:phone":"+1 276 628 2397",
    "sg:postcode":"24210",
    "sg:province":"VA",
    "sg:tags":[
        "carrier"
    ],
    "wof:name":"National Assoc of Insuran",
    "wof:placetype":"venue"
},
  "geometry": {"coordinates":[-82.026865,36.71562],"type":"Point"}
}