{
  "type": "Feature",
  "properties": {
    "iso:country":"US",
    "sg:address":"8307 Rozell Rd",
    "sg:city":"Woodford",
    "sg:classifiers":[
        {
            "category":"Building & Trades",
            "subcategory":"Electrical",
            "type":"Services"
        }
    ],
    "sg:phone":"+1 804 633 0267",
    "sg:postcode":"22580",
    "sg:province":"VA",
    "sg:tags":[
        "electrical",
        "contractor"
    ],
    "wof:name":"Sr Cabling Services",
    "wof:placetype":"venue"
},
  "geometry": {"coordinates":[-77.430227,38.149457],"type":"Point"}
}