{
  "type": "Feature",
  "properties": {
    "iso:country":"US",
    "sg:address":"6162 John Barton Payne Rd",
    "sg:city":"Marshall",
    "sg:classifiers":[
        {
            "category":"Building & Trades",
            "subcategory":"Electrical",
            "type":"Services"
        }
    ],
    "sg:phone":"+1 540 364 4980",
    "sg:postcode":"20115",
    "sg:province":"VA",
    "sg:tags":[
        "electrical",
        "contractor"
    ],
    "wof:name":"RCI Electric",
    "wof:placetype":"venue"
},
  "geometry": {"coordinates":[-77.94439300000001,38.783868],"type":"Point"}
}