{
  "type": "Feature",
  "properties": {
    "iso:country":"US",
    "sg:address":"9002 Peabody St",
    "sg:city":"Manassas",
    "sg:classifiers":[
        {
            "category":"Building & Trades",
            "subcategory":"Plumbing",
            "type":"Services"
        }
    ],
    "sg:phone":"+1 703 369 2828",
    "sg:postcode":"20110",
    "sg:province":"VA",
    "sg:tags":[
        "septic"
    ],
    "wof:name":"Aits Septic Repair Svc",
    "wof:placetype":"venue"
},
  "geometry": {"coordinates":[-77.47851900000001,38.758931],"type":"Point"}
}