{
  "type": "Feature",
  "properties": {
    "addr:full":"1531 Colonial Dr Woodbridge VA 22192",
    "addr:housenumber":"1531",
    "addr:postcode":"22192",
    "addr:street":"Colonial Dr",
    "iso:country":"US",
    "sg:address":"1531 Colonial Dr",
    "sg:city":"Woodbridge",
    "sg:classifiers":[
        {
            "category":"Retail",
            "subcategory":"Laundry & Dry Cleaning",
            "type":"Services"
        }
    ],
    "sg:phone":"+1 703 380 1283",
    "sg:postcode":"22192",
    "sg:province":"VA",
    "sg:tags":[
        "cleaner",
        "rug",
        "carpet"
    ],
    "sg:website":"http://www.kangaroocarpetcleaning.com",
    "wof:name":"Kangaroo Carpet Cleaning",
    "wof:placetype":"venue"
},
  "geometry": {"coordinates":[-77.261792,38.67779],"type":"Point"}
}