{
  "type": "Feature",
  "properties": {
    "addr:full":"3050 Berkmar Dr Charlottesville VA 22901",
    "addr:housenumber":"3050",
    "addr:postcode":"22901",
    "addr:street":"Berkmar Dr",
    "iso:country":"US",
    "sg:address":"3050 Berkmar Dr",
    "sg:city":"Charlottesville",
    "sg:classifiers":[
        {
            "category":"Retail",
            "subcategory":"Veterinary Services",
            "type":"Services"
        }
    ],
    "sg:phone":"+1 434 973 4341",
    "sg:postcode":"22901",
    "sg:province":"VA",
    "sg:tags":[
        "boarding/pet",
        "sitting",
        "pet",
        "hospital",
        "specialty",
        "veterinarian",
        "animal"
    ],
    "sg:website":"www.villageah.com",
    "wof:name":"Village Animal Hospital",
    "wof:placetype":"venue"
},
  "geometry": {"coordinates":[-78.478897,38.083302],"type":"Point"}
}