{
  "type": "Feature",
  "properties": {
    "addr:full":"8201 Greensboro Dr Mc Lean VA 22102",
    "addr:housenumber":"8201",
    "addr:postcode":"22102",
    "addr:street":"Greensboro Dr",
    "iso:country":"US",
    "sg:address":"8201 Greensboro Dr",
    "sg:city":"Mc Lean",
    "sg:classifiers":[
        {
            "category":"Professional",
            "subcategory":"Business Services",
            "type":"Services"
        }
    ],
    "sg:phone":"+1 703 556 0872",
    "sg:postcode":"22102",
    "sg:province":"VA",
    "sg:website":"www.ahaa.org",
    "wof:name":"ANS",
    "wof:placetype":"venue"
},
  "geometry": {"coordinates":[-77.229164,38.922306],"type":"Point"}
}