{
  "type": "Feature",
  "properties": {
    "addr:full":"213 River Park Dr Great Falls VA 22066",
    "addr:housenumber":"213",
    "addr:postcode":"22066",
    "addr:street":"River Park Dr",
    "iso:country":"US",
    "sg:address":"213 River Park Dr",
    "sg:city":"Great Falls",
    "sg:classifiers":[
        {
            "category":"Real Estate",
            "subcategory":"Real Estate Agent",
            "type":"Services"
        }
    ],
    "sg:phone":"+1 703 757 0462",
    "sg:postcode":"22066",
    "sg:province":"VA",
    "sg:tags":[
        "agency",
        "employment"
    ],
    "wof:name":"Kathryn G Chmura & Assoc",
    "wof:placetype":"venue"
},
  "geometry": {"coordinates":[-77.28577799999999,39.029952],"type":"Point"}
}