{
  "type": "Feature",
  "properties": {
    "iso:country":"US",
    "sg:address":"120 Riverside Dr",
    "sg:city":"Suffolk",
    "sg:classifiers":[
        {
            "category":"Health Services",
            "subcategory":"Doctor",
            "type":"Services"
        }
    ],
    "sg:phone":"+1 757 483 3716",
    "sg:postcode":"23435",
    "sg:province":"VA",
    "sg:tags":[
        "medical"
    ],
    "wof:name":"Mohan L Chaudhuri MD",
    "wof:placetype":"venue"
},
  "geometry": {"coordinates":[-76.48575599999999,36.878991],"type":"Point"}
}