{
  "type": "Feature",
  "properties": {
    "iso:country":"US",
    "sg:address":"12441 Warwick Blvd",
    "sg:city":"Newport News",
    "sg:classifiers":[
        {
            "category":"Restaurant",
            "type":"Food & Drink"
        }
    ],
    "sg:phone":"+1 757 596 5180",
    "sg:postcode":"23606",
    "sg:province":"VA",
    "sg:tags":[
        "eating"
    ],
    "wof:name":"Savannah Restaurant & Lounge",
    "wof:placetype":"venue"
},
  "geometry": {"coordinates":[-76.493118,37.068844],"type":"Point"}
}