{
  "type": "Feature",
  "properties": {
    "addr:full":"1682 Harvest Green Ct Reston VA 20194",
    "addr:housenumber":"1682",
    "addr:postcode":"20194",
    "addr:street":"Harvest Green Ct",
    "iso:country":"US",
    "sg:address":"1682 Harvest Green Ct",
    "sg:city":"Reston",
    "sg:classifiers":[
        {
            "category":"Freight",
            "type":"Transportation"
        }
    ],
    "sg:phone":"+1 703 437 5574",
    "sg:postcode":"20194",
    "sg:province":"VA",
    "sg:tags":[
        "special"
    ],
    "wof:name":"Addictive Records",
    "wof:placetype":"venue"
},
  "geometry": {"coordinates":[-77.353013,38.97517],"type":"Point"}
}