{
  "type": "Feature",
  "properties": {
    "addr:full":"2315 Seminole Ln Charlottesville VA 22901",
    "addr:housenumber":"2315",
    "addr:postcode":"22901",
    "addr:street":"Seminole Ln",
    "iso:country":"US",
    "sg:address":"2315 Seminole Ln",
    "sg:city":"Charlottesville",
    "sg:classifiers":[
        {
            "category":"Personal",
            "subcategory":"Beauty Salon",
            "type":"Services"
        }
    ],
    "sg:phone":"+1 434 978 2046",
    "sg:postcode":"22901",
    "sg:province":"VA",
    "wof:name":"Merle Norman Cosmetics",
    "wof:placetype":"venue"
},
  "geometry": {"coordinates":[-78.463302,38.0978],"type":"Point"}
}