{
  "type": "Feature",
  "properties": {
    "addr:full":"13307 Warwick Blvd Newport News VA 23602",
    "addr:housenumber":"13307",
    "addr:postcode":"23602",
    "addr:street":"Warwick Blvd",
    "iso:country":"US",
    "sg:address":"13307 Warwick Blvd",
    "sg:city":"Newport News",
    "sg:classifiers":[
        {
            "category":"Banks & Credit Unions",
            "subcategory":"Bank",
            "type":"Services"
        }
    ],
    "sg:phone":"+1 757 746 1040",
    "sg:postcode":"23602",
    "sg:province":"VA",
    "sg:tags":[
        "state"
    ],
    "wof:name":"South Trust Bank",
    "wof:placetype":"venue"
},
  "geometry": {"coordinates":[-76.52036099999999,37.115483],"type":"Point"}
}