{
  "type": "Feature",
  "properties": {
    "addr:full":"44812 Ashlar Ter Ashburn VA 20147",
    "addr:housenumber":"44812",
    "addr:postcode":"20147",
    "addr:street":"Ashlar Ter",
    "iso:country":"US",
    "sg:address":"44812 Ashlar Ter",
    "sg:city":"Ashburn",
    "sg:classifiers":[
        {
            "category":"Health Services",
            "subcategory":"Clinic",
            "type":"Services"
        },
        {
            "category":"Health Services",
            "subcategory":"Chiropractor",
            "type":"Services"
        }
    ],
    "sg:phone":"+1 571 748 5575",
    "sg:postcode":"20147",
    "sg:province":"VA",
    "sg:tags":[
        "medical",
        "chiropractic"
    ],
    "sg:website":"http://washingtondc.citysearch.com/profile/external/653772960/ashburn_va/nova_spine_injury_center.html?publisher=yellowpages&reference_id=15&placement=ypwebsitemip",
    "wof:name":"NOVA Spine & Injury Center",
    "wof:placetype":"venue"
},
  "geometry": {"coordinates":[-77.45093799999999,39.06573],"type":"Point"}
}