{
  "type": "Feature",
  "properties": {
    "addr:full":"527 Carter Rd Louisa VA 23093",
    "addr:housenumber":"527",
    "addr:postcode":"23093",
    "addr:street":"Carter Rd",
    "iso:country":"US",
    "sg:address":"527 Carter Rd",
    "sg:city":"Louisa",
    "sg:classifiers":[
        {
            "category":"Building & Trades",
            "subcategory":"Cleaning & Sanitation",
            "type":"Services"
        }
    ],
    "sg:phone":"+1 540 967 4742",
    "sg:postcode":"23093",
    "sg:province":"VA",
    "sg:tags":[
        "janitorial"
    ],
    "wof:name":"Millennium Cleaning Services",
    "wof:placetype":"venue"
},
  "geometry": {"coordinates":[-78.18335999999999,37.967078],"type":"Point"}
}