{
  "type": "Feature",
  "properties": {
    "addr:full":"6405 10th St Alexandria VA 22307",
    "addr:housenumber":"6405",
    "addr:postcode":"22307",
    "addr:street":"10Th St",
    "iso:country":"US",
    "sg:address":"6405 10th St",
    "sg:city":"Alexandria",
    "sg:classifiers":[
        {
            "category":"Professional",
            "subcategory":"Management & Consulting",
            "type":"Services"
        }
    ],
    "sg:phone":"+1 703 765 3026",
    "sg:postcode":"22307",
    "sg:province":"VA",
    "wof:name":"CBA Management Consulting LLC",
    "wof:placetype":"venue"
},
  "geometry": {"coordinates":[-77.0539,38.778129],"type":"Point"}
}