{
  "type": "Feature",
  "properties": {
    "addr:full":"11030 Richardson Rd Ashland VA 23005",
    "addr:housenumber":"11030",
    "addr:postcode":"23005",
    "addr:street":"Richardson Rd",
    "iso:country":"US",
    "sg:address":"11030 Richardson Rd",
    "sg:city":"Ashland",
    "sg:classifiers":[
        {
            "category":"Professional",
            "subcategory":"Management & Consulting",
            "type":"Services"
        }
    ],
    "sg:phone":"+1 804 752 2653",
    "sg:postcode":"23005",
    "sg:province":"VA",
    "sg:tags":[
        "telecommunication"
    ],
    "wof:name":"Innovative Telecommunications",
    "wof:placetype":"venue"
},
  "geometry": {"coordinates":[-77.440258,37.699573],"type":"Point"}
}