{
  "type": "Feature",
  "properties": {
    "addr:full":"6447 Overlook Dr Alexandria VA 22312",
    "addr:housenumber":"6447",
    "addr:postcode":"22312",
    "addr:street":"Overlook Dr",
    "iso:country":"US",
    "sg:address":"6447 Overlook Dr",
    "sg:city":"Alexandria",
    "sg:classifiers":[
        {
            "category":"Museum",
            "type":"Entertainment"
        }
    ],
    "sg:phone":"+1 571 338 0670",
    "sg:postcode":"22312",
    "sg:province":"VA",
    "sg:tags":[
        "gallery"
    ],
    "wof:name":"Goldman Gallery LLC",
    "wof:placetype":"venue"
},
  "geometry": {"coordinates":[-77.158146,38.826629],"type":"Point"}
}