{
  "type": "Feature",
  "properties": {
    "iso:country":"US",
    "sg:address":"6321 Hopkins Rd",
    "sg:city":"Richmond",
    "sg:classifiers":[
        {
            "category":"Building & Trades",
            "subcategory":"Construction",
            "type":"Services"
        }
    ],
    "sg:phone":"+1 804 271 1828",
    "sg:postcode":"23234",
    "sg:province":"VA",
    "sg:tags":[
        "contractor"
    ],
    "wof:name":"Michael T Bowles",
    "wof:placetype":"venue"
},
  "geometry": {"coordinates":[-77.47295,37.434385],"type":"Point"}
}