{
  "type": "Feature",
  "properties": {
    "iso:country":"US",
    "sg:address":"40747 Stoneburner Mill Ln",
    "sg:city":"Lovettsville",
    "sg:classifiers":[
        {
            "category":"Organizations",
            "subcategory":"Religious Organization",
            "type":"Services"
        }
    ],
    "sg:phone":"+1 540 822 4050",
    "sg:postcode":"20180",
    "sg:province":"VA",
    "wof:name":"Assembly Cope Products",
    "wof:placetype":"venue"
},
  "geometry": {"coordinates":[-77.58726799999999,39.251532],"type":"Point"}
}