{
  "type": "Feature",
  "properties": {
    "addr:full":"4336 Virginia Beach Blvd Virginia Beach VA 23452",
    "addr:housenumber":"4336",
    "addr:postcode":"23452",
    "addr:street":"Virginia Beach Blvd",
    "iso:country":"US",
    "sg:address":"4336 Virginia Beach Blvd",
    "sg:city":"Virginia Beach",
    "sg:classifiers":[
        {
            "category":"Utilities",
            "subcategory":"Mobile Phone",
            "type":"Services"
        }
    ],
    "sg:phone":"+1 757 285 8000",
    "sg:postcode":"23452",
    "sg:province":"VA",
    "sg:tags":[
        "telephone",
        "cellular"
    ],
    "wof:name":"Cingular Wireless",
    "wof:placetype":"venue"
},
  "geometry": {"coordinates":[-76.122838,36.843547],"type":"Point"}
}