{
  "type": "Feature",
  "properties": {
    "iso:country":"US",
    "sg:address":"6207 Nethercombe Ct",
    "sg:city":"Mc Lean",
    "sg:classifiers":[
        {
            "category":"Retail",
            "subcategory":"Repair Shop",
            "type":"Services"
        }
    ],
    "sg:phone":"+1 703 821 6611",
    "sg:postcode":"22101",
    "sg:province":"VA",
    "wof:name":"Air Services Inc",
    "wof:placetype":"venue"
},
  "geometry": {"coordinates":[-77.150886,38.923566],"type":"Point"}
}