{
  "type": "Feature",
  "properties": {
    "iso:country":"US",
    "sg:address":"112 Carriage Hill Dr",
    "sg:city":"Pulaski",
    "sg:classifiers":[
        {
            "category":"Real Estate",
            "subcategory":"Real Estate Operator",
            "type":"Services"
        }
    ],
    "sg:phone":"+1 540 980 2518",
    "sg:postcode":"24301",
    "sg:province":"VA",
    "sg:tags":[
        "building",
        "apartment"
    ],
    "wof:name":"Carriage Hill Apartments",
    "wof:placetype":"venue"
},
  "geometry": {"coordinates":[-80.77327,37.061462],"type":"Point"}
}