{
  "type": "Feature",
  "properties": {
    "addr:full":"3630 Nellie Jones Rd La Crosse VA 23950",
    "addr:housenumber":"3630",
    "addr:postcode":"23950",
    "addr:street":"Nellie Jones Rd",
    "iso:country":"US",
    "sg:address":"3630 Nellie Jones Rd",
    "sg:city":"La Crosse",
    "sg:classifiers":[
        {
            "category":"Organizations",
            "subcategory":"Community Association",
            "type":"Services"
        }
    ],
    "sg:phone":"+1 434 636 2984",
    "sg:postcode":"23950",
    "sg:province":"VA",
    "sg:tags":[
        "club"
    ],
    "wof:name":"Lake Gaston Hunt Club",
    "wof:placetype":"venue"
},
  "geometry": {"coordinates":[-78.078649,36.594698],"type":"Point"}
}