{
  "type": "Feature",
  "properties": {
    "addr:full":"6107 Havenview Dr Mechanicsville VA 23111",
    "addr:housenumber":"6107",
    "addr:postcode":"23111",
    "addr:street":"Havenview Dr",
    "iso:country":"US",
    "sg:address":"6107 Havenview Dr",
    "sg:city":"Mechanicsville",
    "sg:classifiers":[
        {
            "category":"Local Transit",
            "type":"Transportation"
        }
    ],
    "sg:phone":"+1 804 901 5212",
    "sg:postcode":"23111",
    "sg:province":"VA",
    "sg:tags":[
        "public"
    ],
    "wof:name":"Trc Services Inc",
    "wof:placetype":"venue"
},
  "geometry": {"coordinates":[-77.30898000000001,37.618001],"type":"Point"}
}