{
  "type": "Feature",
  "properties": {
    "addr:full":"3400 Ridge Rd Quinton VA 23141",
    "addr:housenumber":"3400",
    "addr:postcode":"23141",
    "addr:street":"Ridge Rd",
    "iso:country":"US",
    "sg:address":"3400 Ridge Rd",
    "sg:city":"Quinton",
    "sg:classifiers":[
        {
            "category":"Real Estate",
            "subcategory":"Real Estate Agent",
            "type":"Services"
        }
    ],
    "sg:phone":"+1 804 932 4113",
    "sg:postcode":"23141",
    "sg:province":"VA",
    "wof:name":"Barbara Alexander Realty",
    "wof:placetype":"venue"
},
  "geometry": {"coordinates":[-77.16802800000001,37.50019],"type":"Point"}
}