{
  "type": "Feature",
  "properties": {
    "iso:country":"US",
    "sg:address":"10125 Woodthorne Ct",
    "sg:city":"Richmond",
    "sg:classifiers":[
        {
            "category":"Professional",
            "subcategory":"Business Services",
            "type":"Services"
        }
    ],
    "sg:phone":"+1 804 741 6367",
    "sg:postcode":"23238",
    "sg:province":"VA",
    "wof:name":"Estate Sales With Grace",
    "wof:placetype":"venue"
},
  "geometry": {"coordinates":[-77.59424199999999,37.608511],"type":"Point"}
}