{
  "type": "Feature",
  "properties": {
    "iso:country":"US",
    "sg:address":"800 Dana Rae Ct",
    "sg:city":"Newport News",
    "sg:classifiers":[
        {
            "category":"Real Estate",
            "subcategory":"Real Estate Operator",
            "type":"Services"
        }
    ],
    "sg:phone":"+1 757 896 6380",
    "sg:postcode":"23605",
    "sg:province":"VA",
    "sg:tags":[
        "building",
        "apartment"
    ],
    "wof:name":"Chestnut Square Apartments",
    "wof:placetype":"venue"
},
  "geometry": {"coordinates":[-76.424117,37.021626],"type":"Point"}
}