{
  "type": "Feature",
  "properties": {
    "addr:full":"604 Roanoke St Salem VA 24153",
    "addr:housenumber":"604",
    "addr:postcode":"24153",
    "addr:street":"Roanoke St",
    "iso:country":"US",
    "sg:address":"604 Roanoke St",
    "sg:city":"Salem",
    "sg:classifiers":[
        {
            "category":"Professional",
            "subcategory":"Computer Services",
            "type":"Services"
        }
    ],
    "sg:phone":"+1 540 387 4487",
    "sg:postcode":"24153",
    "sg:province":"VA",
    "sg:tags":[
        "prepackaged",
        "software"
    ],
    "wof:name":"Salem Software Service",
    "wof:placetype":"venue"
},
  "geometry": {"coordinates":[-80.067532,37.287266],"type":"Point"}
}