{
  "type": "Feature",
  "properties": {
    "iso:country":"US",
    "sg:address":"128 Campbell Ave SW",
    "sg:city":"Roanoke",
    "sg:classifiers":[
        {
            "category":"Restaurant",
            "type":"Food & Drink"
        }
    ],
    "sg:phone":"+1 540 343 6900",
    "sg:postcode":"24011",
    "sg:province":"VA",
    "wof:name":"Zak's Cafe",
    "wof:placetype":"venue"
},
  "geometry": {"coordinates":[-79.94387,37.271665],"type":"Point"}
}