{
  "type": "Feature",
  "properties": {
    "addr:full":"16343 Bucks Branch Ln Montpelier VA 23192",
    "addr:housenumber":"16343",
    "addr:postcode":"23192",
    "addr:street":"Bucks Branch Ln",
    "iso:country":"US",
    "sg:address":"16343 Bucks Branch Ln",
    "sg:city":"Montpelier",
    "sg:classifiers":[
        {
            "category":"Building & Trades",
            "subcategory":"Construction",
            "type":"Services"
        }
    ],
    "sg:phone":"+1 804 883 7217",
    "sg:postcode":"23192",
    "sg:province":"VA",
    "sg:tags":[
        "contractor"
    ],
    "wof:name":"Windhams Custom Tile",
    "wof:placetype":"venue"
},
  "geometry": {"coordinates":[-77.666038,37.865031],"type":"Point"}
}