{
  "type": "Feature",
  "properties": {
    "addr:full":"1000 Sully Rd Sterling VA 20166",
    "addr:housenumber":"1000",
    "addr:postcode":"20166",
    "addr:street":"Sully Rd",
    "iso:country":"US",
    "sg:address":"1000 Sully Rd",
    "sg:city":"Sterling",
    "sg:classifiers":[
        {
            "category":"Bars & Pubs",
            "type":"Food & Drink"
        }
    ],
    "sg:phone":"+1 703 471 9787",
    "sg:postcode":"20166",
    "sg:province":"VA",
    "sg:tags":[
        "lounge",
        "cocktail"
    ],
    "wof:name":"Cockpit Lounge",
    "wof:placetype":"venue"
},
  "geometry": {"coordinates":[-77.430511,38.986751],"type":"Point"}
}