{
  "type": "Feature",
  "properties": {
    "addr:full":"9909 Oak Branch Dr Vienna VA 22181",
    "addr:housenumber":"9909",
    "addr:postcode":"22181",
    "addr:street":"Oak Branch Dr",
    "iso:country":"US",
    "sg:address":"9909 Oak Branch Dr",
    "sg:city":"Vienna",
    "sg:classifiers":[
        {
            "category":"Professional",
            "subcategory":"Art Services",
            "type":"Services"
        }
    ],
    "sg:phone":"+1 703 938 2882",
    "sg:postcode":"22181",
    "sg:province":"VA",
    "sg:tags":[
        "commercial",
        "design"
    ],
    "wof:name":"Paula Federman",
    "wof:placetype":"venue"
},
  "geometry": {"coordinates":[-77.288771,38.890569],"type":"Point"}
}