{
  "type": "Feature",
  "properties": {
    "addr:full":"15485 Beaverdam School Rd Beaverdam VA 23015",
    "addr:housenumber":"15485",
    "addr:postcode":"23015",
    "addr:street":"Beaverdam School Rd",
    "iso:country":"US",
    "sg:address":"15485 Beaverdam School Rd",
    "sg:city":"Beaverdam",
    "sg:classifiers":[
        {
            "category":"Education",
            "subcategory":"School",
            "type":"Public Place"
        }
    ],
    "sg:phone":"+1 804 449 6373",
    "sg:postcode":"23015",
    "sg:province":"VA",
    "sg:website":"www.hanover.k12.va.us",
    "wof:name":"Beaverdam Elementary School",
    "wof:placetype":"venue"
},
  "geometry": {"coordinates":[-77.64136499999999,37.933901],"type":"Point"}
}