{
  "type": "Feature",
  "properties": {
    "iso:country":"US",
    "sg:address":"101 Walnut Rd",
    "sg:city":"Danville",
    "sg:classifiers":[
        {
            "category":"Manufacturing",
            "subcategory":"Wood Products",
            "type":"Manufacturing & Wholesale Goods"
        }
    ],
    "sg:phone":"+1 434 822 1005",
    "sg:postcode":"24541",
    "sg:province":"VA",
    "sg:tags":[
        "mfg"
    ],
    "wof:name":"Stx Machine & Fabrication",
    "wof:placetype":"venue"
},
  "geometry": {"coordinates":[-79.52860099999999,36.567243],"type":"Point"}
}