{
  "type": "Feature",
  "properties": {
    "addr:full":"4 Brinks Ct Sterling VA 20165",
    "addr:housenumber":"4",
    "addr:postcode":"20165",
    "addr:street":"Brinks Ct",
    "iso:country":"US",
    "sg:address":"4 Brinks Ct",
    "sg:city":"Sterling",
    "sg:classifiers":[
        {
            "category":"Professional",
            "subcategory":"Business Services",
            "type":"Services"
        }
    ],
    "sg:phone":"+1 703 404 2426",
    "sg:postcode":"20165",
    "sg:province":"VA",
    "sg:tags":[
        "water",
        "treatment"
    ],
    "wof:name":"Multi-Pure Drinking Water Sys",
    "wof:placetype":"venue"
},
  "geometry": {"coordinates":[-77.421999,39.054891],"type":"Point"}
}