{
  "type": "Feature",
  "properties": {
    "addr:full":"43 Deshazo Ln Fredericksburg VA 22405",
    "addr:housenumber":"43",
    "addr:postcode":"22405",
    "addr:street":"Deshazo Ln",
    "iso:country":"US",
    "sg:address":"43 Deshazo Ln",
    "sg:city":"Fredericksburg",
    "sg:classifiers":[
        {
            "category":"Professional",
            "subcategory":"Management & Consulting",
            "type":"Services"
        }
    ],
    "sg:phone":"+1 540 654 5468",
    "sg:postcode":"22405",
    "sg:province":"VA",
    "sg:tags":[
        "business"
    ],
    "wof:name":"Wire Co LLC",
    "wof:placetype":"venue"
},
  "geometry": {"coordinates":[-77.374472,38.299756],"type":"Point"}
}