{
  "type": "Feature",
  "properties": {
    "addr:full":"3209 Ingram Dr Haymarket VA 20169",
    "addr:housenumber":"3209",
    "addr:postcode":"20169",
    "addr:street":"Ingram Dr",
    "iso:country":"US",
    "sg:address":"3209 Ingram Dr",
    "sg:city":"Haymarket",
    "sg:classifiers":[
        {
            "category":"Health Services",
            "subcategory":"Doctor",
            "type":"Services"
        }
    ],
    "sg:phone":"+1 703 522 2600",
    "sg:postcode":"20169",
    "sg:province":"VA",
    "wof:name":"Aurelio A Roca DDS",
    "wof:placetype":"venue"
},
  "geometry": {"coordinates":[-77.628978,38.89149],"type":"Point"}
}