{
  "type": "Feature",
  "properties": {
    "addr:full":"5335 Holmes Run Pkwy Alexandria VA 22304",
    "addr:housenumber":"5335",
    "addr:postcode":"22304",
    "addr:street":"Holmes Run Pkwy",
    "iso:country":"US",
    "sg:address":"5335 Holmes Run Pkwy",
    "sg:city":"Alexandria",
    "sg:classifiers":[
        {
            "category":"Professional",
            "subcategory":"Management & Consulting",
            "type":"Services"
        }
    ],
    "sg:phone":"+1 703 370 0998",
    "sg:postcode":"22304",
    "sg:province":"VA",
    "sg:tags":[
        "business"
    ],
    "wof:name":"One World LLC",
    "wof:placetype":"venue"
},
  "geometry": {"coordinates":[-77.123834,38.818036],"type":"Point"}
}