{
  "type": "Feature",
  "properties": {
    "iso:country":"US",
    "sg:address":"12106 Timber Trail Dr",
    "sg:city":"Midlothian",
    "sg:classifiers":[
        {
            "category":"Building & Trades",
            "subcategory":"Construction",
            "type":"Services"
        }
    ],
    "sg:phone":"+1 804 249 7325",
    "sg:postcode":"23112",
    "sg:province":"VA",
    "sg:tags":[
        "product",
        "asphalt"
    ],
    "wof:name":"KDM Seal Coating",
    "wof:placetype":"venue"
},
  "geometry": {"coordinates":[-77.61539999999999,37.417],"type":"Point"}
}