{
  "type": "Feature",
  "properties": {
    "iso:country":"US",
    "sg:address":"220 Webbs Mill Rd N",
    "sg:city":"Floyd",
    "sg:classifiers":[
        {
            "category":"Professional",
            "subcategory":"Computer Services",
            "type":"Services"
        }
    ],
    "sg:phone":"+1 540 745 4101",
    "sg:postcode":"24091",
    "sg:province":"VA",
    "sg:tags":[
        "internet"
    ],
    "wof:name":"Citizens Internet Svc",
    "wof:placetype":"venue"
},
  "geometry": {"coordinates":[-80.322295,36.915887],"type":"Point"}
}