{
  "type": "Feature",
  "properties": {
    "iso:country":"US",
    "sg:address":"13300 Lora Lynn Rd",
    "sg:city":"Chester",
    "sg:classifiers":[
        {
            "category":"Retail",
            "subcategory":"Auto Repair",
            "type":"Services"
        }
    ],
    "sg:phone":"+1 804 748 9039",
    "sg:postcode":"23831",
    "sg:province":"VA",
    "sg:tags":[
        "general"
    ],
    "wof:name":"Scruggs & Chappell Auto Repair",
    "wof:placetype":"venue"
},
  "geometry": {"coordinates":[-77.44681799999999,37.339276],"type":"Point"}
}