{
  "type": "Feature",
  "properties": {
    "iso:country":"US",
    "sg:address":"500 E Virginia Ave",
    "sg:city":"Crewe",
    "sg:classifiers":[
        {
            "category":"Insurance",
            "subcategory":"Insurance Agent",
            "type":"Services"
        }
    ],
    "sg:phone":"+1 434 645 7670",
    "sg:postcode":"23930",
    "sg:province":"VA",
    "wof:name":"Moncure Insurance Agency Inc",
    "wof:placetype":"venue"
},
  "geometry": {"coordinates":[-78.120701,37.17079],"type":"Point"}
}