{
  "type": "Feature",
  "properties": {
    "addr:full":"12116 Springwoods Dr Woodbridge VA 22192",
    "addr:housenumber":"12116",
    "addr:postcode":"22192",
    "addr:street":"Springwoods Dr",
    "iso:country":"US",
    "sg:address":"12116 Springwoods Dr",
    "sg:city":"Woodbridge",
    "sg:classifiers":[
        {
            "category":"Professional",
            "subcategory":"Art Services",
            "type":"Services"
        }
    ],
    "sg:phone":"+1 703 897 8868",
    "sg:postcode":"22192",
    "sg:province":"VA",
    "sg:tags":[
        "commercial",
        "design"
    ],
    "wof:name":"3rd Angle Graphics",
    "wof:placetype":"venue"
},
  "geometry": {"coordinates":[-77.32565,38.69328],"type":"Point"}
}