{
  "type": "Feature",
  "properties": {
    "addr:full":"8500 Glazebrook Ave Richmond VA 23228",
    "addr:housenumber":"8500",
    "addr:postcode":"23228",
    "addr:street":"Glazebrook Ave",
    "iso:country":"US",
    "sg:address":"8500 Glazebrook Ave",
    "sg:city":"Richmond",
    "sg:classifiers":[
        {
            "category":"Food & Beverages",
            "subcategory":"Specialty",
            "type":"Retail Goods"
        }
    ],
    "sg:phone":"+1 804 266 9600",
    "sg:postcode":"23228",
    "sg:province":"VA",
    "sg:tags":[
        "coffee"
    ],
    "wof:name":"Filter Fresh",
    "wof:placetype":"venue"
},
  "geometry": {"coordinates":[-77.504947,37.629355],"type":"Point"}
}