{
  "type": "Feature",
  "properties": {
    "iso:country":"US",
    "sg:address":"21100 Dulles Town Cir",
    "sg:city":"Sterling",
    "sg:classifiers":[
        {
            "category":"Restaurant",
            "type":"Food & Drink"
        }
    ],
    "sg:menulink":"http://www.allmenus.com/va/potomac/223200-flamers-charbroiled-burgers/menu/",
    "sg:phone":"+1 703 404 6807",
    "sg:postcode":"20166",
    "sg:province":"VA",
    "sg:tags":[
        "burger",
        "american"
    ],
    "wof:name":"Flamers Charbroiled Burgers",
    "wof:placetype":"venue"
},
  "geometry": {"coordinates":[-77.420329,39.032767],"type":"Point"}
}