{
  "type": "Feature",
  "properties": {
    "addr:full":"1800 Park Ave Chesapeake VA 23324",
    "addr:housenumber":"1800",
    "addr:postcode":"23324",
    "addr:street":"Park Ave",
    "iso:country":"US",
    "sg:address":"1800 Park Ave",
    "sg:city":"Chesapeake",
    "sg:classifiers":[
        {
            "category":"Retail",
            "subcategory":"Auto Repair",
            "type":"Services"
        }
    ],
    "sg:phone":"+1 757 545 9394",
    "sg:postcode":"23324",
    "sg:province":"VA",
    "sg:tags":[
        "general"
    ],
    "wof:name":"Sports & Imports",
    "wof:placetype":"venue"
},
  "geometry": {"coordinates":[-76.265047,36.813787],"type":"Point"}
}