{
  "type": "Feature",
  "properties": {
    "iso:country":"US",
    "sg:address":"2044 Munden Point Rd",
    "sg:city":"Virginia Beach",
    "sg:classifiers":[
        {
            "category":"Professional",
            "type":"Services"
        }
    ],
    "sg:phone":"+1 757 426 2878",
    "sg:postcode":"23457",
    "sg:province":"VA",
    "sg:tags":[
        "establishment"
    ],
    "wof:name":"Fincham Rozier & Assoc",
    "wof:placetype":"venue"
},
  "geometry": {"coordinates":[-76.031583,36.579128],"type":"Point"}
}