{
  "type": "Feature",
  "properties": {
    "addr:full":"21272 Lankford Hwy Parksley VA 23421",
    "addr:housenumber":"21272",
    "addr:postcode":"23421",
    "addr:street":"Lankford Hwy",
    "iso:country":"US",
    "sg:address":"21272 Lankford Hwy",
    "sg:city":"Parksley",
    "sg:classifiers":[
        {
            "category":"Food & Beverages",
            "subcategory":"Bakery",
            "type":"Retail Goods"
        }
    ],
    "sg:phone":"+1 757 665 7773",
    "sg:postcode":"23421",
    "sg:province":"VA",
    "wof:name":"Juscakes",
    "wof:placetype":"venue"
},
  "geometry": {"coordinates":[-75.6315,37.748945],"type":"Point"}
}