{
  "type": "Feature",
  "properties": {
    "iso:country":"US",
    "sg:address":"107 S Main St",
    "sg:city":"Emporia",
    "sg:classifiers":[
        {
            "category":"Autos & Motor Vehicles",
            "subcategory":"Fuel & Gas Station",
            "type":"Retail Goods"
        }
    ],
    "sg:phone":"+1 434 634 3591",
    "sg:postcode":"23847",
    "sg:province":"VA",
    "sg:tags":[
        "station",
        "gasoline",
        "oil"
    ],
    "wof:name":"Emporia Union 76",
    "wof:placetype":"venue"
},
  "geometry": {"coordinates":[-77.541207,36.68987],"type":"Point"}
}