{
  "type": "Feature",
  "properties": {
    "addr:full":"2231 Wheatland Dr Manakin Sabot VA 23103",
    "addr:housenumber":"2231",
    "addr:postcode":"23103",
    "addr:street":"Wheatland Dr",
    "iso:country":"US",
    "sg:address":"2231 Wheatland Dr",
    "sg:city":"Manakin Sabot",
    "sg:classifiers":[
        {
            "category":"Professional",
            "subcategory":"Computer Services",
            "type":"Services"
        }
    ],
    "sg:phone":"+1 804 370 1253",
    "sg:postcode":"23103",
    "sg:province":"VA",
    "sg:tags":[
        "related"
    ],
    "wof:name":"Thunderbolt Technologies LLC",
    "wof:placetype":"venue"
},
  "geometry": {"coordinates":[-77.72064,37.691104],"type":"Point"}
}