{
  "type": "Feature",
  "properties": {
    "iso:country":"US",
    "sg:address":"1266 Smith Creek Rd",
    "sg:city":"Christiansburg",
    "sg:classifiers":[
        {
            "category":"Shopping",
            "subcategory":"Bicycles & Sporting Goods",
            "type":"Retail Goods"
        }
    ],
    "sg:phone":"+1 540 818 6472",
    "sg:postcode":"24073",
    "sg:province":"VA",
    "sg:tags":[
        "equipment",
        "golf"
    ],
    "wof:name":"Lee Chrystie Golf",
    "wof:placetype":"venue"
},
  "geometry": {"coordinates":[-80.42491800000001,37.092167],"type":"Point"}
}