{
  "type": "Feature",
  "properties": {
    "iso:country":"US",
    "sg:address":"3141 Fairview Park Dr",
    "sg:city":"Falls Church",
    "sg:classifiers":[
        {
            "category":"Real Estate",
            "subcategory":"Real Estate Agent",
            "type":"Services"
        }
    ],
    "sg:phone":"+1 703 207 5263",
    "sg:postcode":"22042",
    "sg:province":"VA",
    "wof:name":"KANE Property Co Inc",
    "wof:placetype":"venue"
},
  "geometry": {"coordinates":[-77.215121,38.860555],"type":"Point"}
}