{
  "type": "Feature",
  "properties": {
    "iso:country":"US",
    "sg:address":"403 Broad St",
    "sg:city":"South Boston",
    "sg:classifiers":[
        {
            "category":"Government",
            "subcategory":"Office",
            "type":"Public Place"
        }
    ],
    "sg:phone":"+1 434 575 4245",
    "sg:postcode":"24592",
    "sg:province":"NC",
    "sg:tags":[
        "village"
    ],
    "wof:name":"Building Inspector",
    "wof:placetype":"venue"
},
  "geometry": {"coordinates":[-78.899868,36.69785],"type":"Point"}
}