{
  "type": "Feature",
  "properties": {
    "addr:full":"6800 Paragon Pl Richmond VA 23230",
    "addr:housenumber":"6800",
    "addr:postcode":"23230",
    "addr:street":"Paragon Pl",
    "iso:country":"US",
    "sg:address":"6800 Paragon Pl",
    "sg:city":"Richmond",
    "sg:classifiers":[
        {
            "category":"Real Estate",
            "subcategory":"Real Estate Agent",
            "type":"Services"
        }
    ],
    "sg:phone":"+1 804 262 1178",
    "sg:postcode":"23230",
    "sg:province":"VA",
    "sg:tags":[
        "relocation"
    ],
    "wof:name":"Capital Relocation Group Inc",
    "wof:placetype":"venue"
},
  "geometry": {"coordinates":[-77.51485,37.60861],"type":"Point"}
}