{
  "type": "Feature",
  "properties": {
    "iso:country":"US",
    "sg:address":"4900 Vintner Ln",
    "sg:city":"Richmond",
    "sg:classifiers":[
        {
            "category":"Professional",
            "subcategory":"Management & Consulting",
            "type":"Services"
        }
    ],
    "sg:phone":"+1 804 714 0124",
    "sg:postcode":"23234",
    "sg:province":"VA",
    "wof:name":"K & G Enterprise Inc",
    "wof:placetype":"venue"
},
  "geometry": {"coordinates":[-77.49444200000001,37.448495],"type":"Point"}
}