{
  "type": "Feature",
  "properties": {
    "addr:full":"12871 Gordon Blvd Woodbridge VA 22192",
    "addr:housenumber":"12871",
    "addr:postcode":"22192",
    "addr:street":"Gordon Blvd",
    "iso:country":"US",
    "sg:address":"12871 Gordon Blvd",
    "sg:city":"Woodbridge",
    "sg:classifiers":[
        {
            "category":"Autos & Motor Vehicles",
            "subcategory":"Fuel & Gas Station",
            "type":"Retail Goods"
        },
        {
            "category":"Food & Beverages",
            "subcategory":"Groceries & Convenience Stores",
            "type":"Retail Goods"
        }
    ],
    "sg:phone":"+1 703 491 9563",
    "sg:postcode":"22192",
    "sg:province":"VA",
    "sg:website":"http://www.shell.com",
    "wof:name":"Belmont Bay Shell",
    "wof:placetype":"venue"
},
  "geometry": {"coordinates":[-77.254341,38.674229],"type":"Point"}
}