{
  "type": "Feature",
  "properties": {
    "addr:full":"8725 Pebble Ln Manassas VA 20111",
    "addr:housenumber":"8725",
    "addr:postcode":"20111",
    "addr:street":"Pebble Ln",
    "iso:country":"US",
    "sg:address":"8725 Pebble Ln",
    "sg:city":"Manassas",
    "sg:classifiers":[
        {
            "category":"Retail",
            "subcategory":"Laundry & Dry Cleaning",
            "type":"Services"
        }
    ],
    "sg:phone":"+1 703 369 5675",
    "sg:postcode":"20111",
    "sg:province":"VA",
    "wof:name":"S G Summers Prof Carpet Clrs",
    "wof:placetype":"venue"
},
  "geometry": {"coordinates":[-77.461337,38.793395],"type":"Point"}
}