{
  "type": "Feature",
  "properties": {
    "addr:full":"7 Corners Falls Church VA 22041",
    "addr:postcode":"22041",
    "addr:street":"7 Corners",
    "iso:country":"US",
    "sg:address":"7 Corners",
    "sg:city":"Falls Church",
    "sg:classifiers":[
        {
            "category":"Home & Garden",
            "subcategory":"Carpets & Floor Coverings",
            "type":"Retail Goods"
        }
    ],
    "sg:phone":"+1 703 237 2277",
    "sg:postcode":"22041",
    "sg:province":"VA",
    "sg:tags":[
        "mattress"
    ],
    "wof:name":"Mattress Warehouse",
    "wof:placetype":"venue"
},
  "geometry": {"coordinates":[-77.131699,38.844601],"type":"Point"}
}