{
  "type": "Feature",
  "properties": {
    "addr:full":"8 Elmhurst St Newport News VA 23603",
    "addr:housenumber":"8",
    "addr:postcode":"23603",
    "addr:street":"Elmhurst St",
    "iso:country":"US",
    "sg:address":"8 Elmhurst St",
    "sg:city":"Newport News",
    "sg:classifiers":[
        {
            "category":"Restaurant",
            "type":"Food & Drink"
        }
    ],
    "sg:menulink":"http://www.allmenus.com/va/newport-news/42446-hong-kong/menu/",
    "sg:phone":"+1 757 888 8888",
    "sg:postcode":"23603",
    "sg:province":"VA",
    "sg:tags":[
        "asian",
        "chinese"
    ],
    "wof:name":"Hong Kong",
    "wof:placetype":"venue"
},
  "geometry": {"coordinates":[-76.572982,37.193584],"type":"Point"}
}