{
  "type": "Feature",
  "properties": {
    "iso:country":"US",
    "sg:address":"10459 Edgewood Dr",
    "sg:city":"King George",
    "sg:classifiers":[
        {
            "category":"Building & Trades",
            "subcategory":"Construction",
            "type":"Services"
        }
    ],
    "sg:phone":"+1 540 775 7996",
    "sg:postcode":"22485",
    "sg:province":"VA",
    "sg:tags":[
        "house"
    ],
    "wof:name":"Thomas M Burrell Inc",
    "wof:placetype":"venue"
},
  "geometry": {"coordinates":[-77.129631,38.265834],"type":"Point"}
}