{
  "type": "Feature",
  "properties": {
    "iso:country":"US",
    "sg:address":"3102 Plank Rd",
    "sg:city":"Fredericksburg",
    "sg:classifiers":[
        {
            "category":"Shopping",
            "type":"Retail Goods"
        }
    ],
    "sg:phone":"+1 540 785 0123",
    "sg:postcode":"22407",
    "sg:province":"VA",
    "sg:tags":[
        "telephone",
        "cellular"
    ],
    "wof:name":"Mid Atlantic Protel",
    "wof:placetype":"venue"
},
  "geometry": {"coordinates":[-77.517805,38.294267],"type":"Point"}
}