{
  "type": "Feature",
  "properties": {
    "addr:full":"7833 Sudley Rd Manassas VA 20109",
    "addr:housenumber":"7833",
    "addr:postcode":"20109",
    "addr:street":"Sudley Rd",
    "iso:country":"US",
    "sg:address":"7833 Sudley Rd",
    "sg:city":"Manassas",
    "sg:classifiers":[
        {
            "category":"Travel",
            "subcategory":"Travel Agent",
            "type":"Entertainment"
        }
    ],
    "sg:phone":"+1 703 330 1888",
    "sg:postcode":"20109",
    "sg:province":"VA",
    "sg:tags":[
        "agency",
        "bureau"
    ],
    "wof:name":"Cruise Holidays",
    "wof:placetype":"venue"
},
  "geometry": {"coordinates":[-77.513524,38.786897],"type":"Point"}
}