{
  "type": "Feature",
  "properties": {
    "addr:full":"313 Bowen Dr Fredericksburg VA 22407",
    "addr:housenumber":"313",
    "addr:postcode":"22407",
    "addr:street":"Bowen Dr",
    "iso:country":"US",
    "sg:address":"313 Bowen Dr",
    "sg:city":"Fredericksburg",
    "sg:classifiers":[
        {
            "category":"Retail",
            "subcategory":"Auto Repair",
            "type":"Services"
        }
    ],
    "sg:phone":"+1 540 834 5556",
    "sg:postcode":"22407",
    "sg:province":"VA",
    "sg:tags":[
        "repairing",
        "automobile"
    ],
    "wof:name":"JKJ Transport & Auto Repair",
    "wof:placetype":"venue"
},
  "geometry": {"coordinates":[-77.51773799999999,38.230611],"type":"Point"}
}