{
  "type": "Feature",
  "properties": {
    "addr:full":"586 Virginian Dr Norfolk VA 23505",
    "addr:housenumber":"586",
    "addr:postcode":"23505",
    "addr:street":"Virginian Dr",
    "iso:country":"US",
    "sg:address":"586 Virginian Dr",
    "sg:city":"Norfolk",
    "sg:classifiers":[
        {
            "category":"Organizations",
            "subcategory":"Professional Association",
            "type":"Services"
        }
    ],
    "sg:phone":"+1 757 531 1300",
    "sg:postcode":"23505",
    "sg:province":"VA",
    "sg:tags":[
        "better",
        "bureau",
        "business"
    ],
    "wof:name":"Bettr Bsnss Bur Grtr Hmptn RDS",
    "wof:placetype":"venue"
},
  "geometry": {"coordinates":[-76.259317,36.905448],"type":"Point"}
}