{
  "type": "Feature",
  "properties": {
    "addr:full":"1109 Panhandle Rd Bentonville VA 22610",
    "addr:housenumber":"1109",
    "addr:postcode":"22610",
    "addr:street":"Panhandle Rd",
    "iso:country":"US",
    "sg:address":"1109 Panhandle Rd",
    "sg:city":"Bentonville",
    "sg:classifiers":[
        {
            "category":"Wholesale",
            "subcategory":"Machinery & Supplies",
            "type":"Manufacturing & Wholesale Goods"
        }
    ],
    "sg:phone":"+1 540 636 1190",
    "sg:postcode":"22610",
    "sg:province":"VA",
    "sg:tags":[
        "equipment",
        "irrigation",
        "system"
    ],
    "wof:name":"Irrigation Services Inc",
    "wof:placetype":"venue"
},
  "geometry": {"coordinates":[-78.329323,38.855171],"type":"Point"}
}