{
  "type": "Feature",
  "properties": {
    "iso:country":"US",
    "sg:address":"431 Pleasant Valley Rd",
    "sg:city":"Harrisonburg",
    "sg:classifiers":[
        {
            "category":"Wholesale",
            "subcategory":"Electrical",
            "type":"Manufacturing & Wholesale Goods"
        }
    ],
    "sg:phone":"+1 540 434 1919",
    "sg:postcode":"22801",
    "sg:province":"VA",
    "sg:tags":[
        "equipment",
        "electric",
        "supply"
    ],
    "wof:name":"Motion Industries Inc",
    "wof:placetype":"venue"
},
  "geometry": {"coordinates":[-78.90003400000001,38.402037],"type":"Point"}
}