{
  "type": "Feature",
  "properties": {
    "addr:full":"14900 Pepper Ct Woodbridge VA 22193",
    "addr:housenumber":"14900",
    "addr:postcode":"22193",
    "addr:street":"Pepper Ct",
    "iso:country":"US",
    "sg:address":"14900 Pepper Ct",
    "sg:city":"Woodbridge",
    "sg:classifiers":[
        {
            "category":"Building & Trades",
            "subcategory":"Construction",
            "type":"Services"
        }
    ],
    "sg:phone":"+1 703 670 9632",
    "sg:postcode":"22193",
    "sg:province":"VA",
    "sg:tags":[
        "interior",
        "commercial",
        "alteration",
        "exterior"
    ],
    "wof:name":"D & J Liller Inc",
    "wof:placetype":"venue"
},
  "geometry": {"coordinates":[-77.334734,38.630109],"type":"Point"}
}