{
  "type": "Feature",
  "properties": {
    "iso:country":"US",
    "sg:address":"108 W Southwerk St",
    "sg:city":"Winchester",
    "sg:classifiers":[
        {
            "category":"Professional",
            "type":"Services"
        }
    ],
    "sg:phone":"+1 540 665 1856",
    "sg:postcode":"22601",
    "sg:province":"VA",
    "wof:name":"Chris Moats",
    "wof:placetype":"venue"
},
  "geometry": {"coordinates":[-78.17204,39.174034],"type":"Point"}
}