{
  "type": "Feature",
  "properties": {
    "iso:country":"US",
    "sg:address":"1727 Peters Creek Rd NW",
    "sg:city":"Roanoke",
    "sg:classifiers":[
        {
            "category":"Education",
            "subcategory":"Vocational School",
            "type":"Public Place"
        }
    ],
    "sg:phone":"+1 540 562 2575",
    "sg:postcode":"24017",
    "sg:province":"VA",
    "sg:tags":[
        "real estate"
    ],
    "wof:name":"Moseley-Dickinson Schools-Rea",
    "wof:placetype":"venue"
},
  "geometry": {"coordinates":[-80.007041,37.304726],"type":"Point"}
}