{
  "type": "Feature",
  "properties": {
    "addr:full":"5828 Merriman Rd Roanoke VA 24018",
    "addr:housenumber":"5828",
    "addr:postcode":"24018",
    "addr:street":"Merriman Rd",
    "iso:country":"US",
    "sg:address":"5828 Merriman Rd",
    "sg:city":"Roanoke",
    "sg:classifiers":[
        {
            "category":"Real Estate",
            "subcategory":"Real Estate Agent",
            "type":"Services"
        }
    ],
    "sg:phone":"+1 540 989 8493",
    "sg:postcode":"24018",
    "sg:province":"VA",
    "sg:tags":[
        "consultant"
    ],
    "wof:name":"Rudy Cox Inc Realtors",
    "wof:placetype":"venue"
},
  "geometry": {"coordinates":[-80.00961,37.208097],"type":"Point"}
}