{
  "type": "Feature",
  "properties": {
    "iso:country":"US",
    "sg:address":"9540 Hagan Rd",
    "sg:city":"Glen Allen",
    "sg:classifiers":[
        {
            "category":"Building & Trades",
            "subcategory":"Construction",
            "type":"Services"
        }
    ],
    "sg:phone":"+1 804 747 1550",
    "sg:postcode":"23060",
    "sg:province":"VA",
    "sg:tags":[
        "painting",
        "painter",
        "contractor"
    ],
    "wof:name":"C M Richardson Co Inc",
    "wof:placetype":"venue"
},
  "geometry": {"coordinates":[-77.51956300000001,37.643458],"type":"Point"}
}