{
  "type": "Feature",
  "properties": {
    "addr:full":"103 Wall St SE Roanoke VA 24011",
    "addr:housenumber":"103",
    "addr:postcode":"24011",
    "addr:street":"Wall St Se",
    "iso:country":"US",
    "sg:address":"103 Wall St SE",
    "sg:city":"Roanoke",
    "sg:classifiers":[
        {
            "category":"Restaurant",
            "type":"Food & Drink"
        }
    ],
    "sg:phone":"+1 540 345 2180",
    "sg:postcode":"24011",
    "sg:province":"VA",
    "sg:tags":[
        "eating"
    ],
    "wof:name":"Red Coyote Mexican Grill",
    "wof:placetype":"venue"
},
  "geometry": {"coordinates":[-79.939407,37.27182],"type":"Point"}
}