{
  "type": "Feature",
  "properties": {
    "addr:full":"9408 Battle St Manassas VA 20110",
    "addr:housenumber":"9408",
    "addr:postcode":"20110",
    "addr:street":"Battle St",
    "iso:country":"US",
    "sg:address":"9408 Battle St",
    "sg:city":"Manassas",
    "sg:classifiers":[
        {
            "category":"Shopping",
            "type":"Retail Goods"
        }
    ],
    "sg:phone":"+1 703 361 6066",
    "sg:postcode":"20110",
    "sg:province":"VA",
    "sg:tags":[
        "coin",
        "dealer",
        "supply"
    ],
    "wof:name":"Rebel Coin Co",
    "wof:placetype":"venue"
},
  "geometry": {"coordinates":[-77.472612,38.751496],"type":"Point"}
}