{
  "type": "Feature",
  "properties": {
    "addr:full":"5391 Cape Henry Ave Norfolk VA 23513",
    "addr:housenumber":"5391",
    "addr:postcode":"23513",
    "addr:street":"Cape Henry Ave",
    "iso:country":"US",
    "sg:address":"5391 Cape Henry Ave",
    "sg:city":"Norfolk",
    "sg:classifiers":[
        {
            "category":"Retail",
            "subcategory":"Repair Shop",
            "type":"Services"
        }
    ],
    "sg:phone":"+1 757 855 8521",
    "sg:postcode":"23513",
    "sg:province":"VA",
    "sg:tags":[
        "welding"
    ],
    "wof:name":"Semo Welding Inc",
    "wof:placetype":"venue"
},
  "geometry": {"coordinates":[-76.21853900000001,36.87642],"type":"Point"}
}