{
  "type": "Feature",
  "properties": {
    "addr:full":"3716 Old Forest Rd Lynchburg VA 24501",
    "addr:housenumber":"3716",
    "addr:postcode":"24501",
    "addr:street":"Old Forest Rd",
    "iso:country":"US",
    "sg:address":"3716 Old Forest Rd",
    "sg:city":"Lynchburg",
    "sg:classifiers":[
        {
            "category":"Insurance",
            "subcategory":"Insurance Agent",
            "type":"Services"
        }
    ],
    "sg:phone":"+1 434 385 6167",
    "sg:postcode":"24501",
    "sg:province":"VA",
    "wof:name":"State Farm Insurance",
    "wof:placetype":"venue"
},
  "geometry": {"coordinates":[-79.22069399999999,37.404993],"type":"Point"}
}