{
  "type": "Feature",
  "properties": {
    "addr:full":"3005 Peters Creek Rd NW Roanoke VA 24019",
    "addr:housenumber":"3005",
    "addr:postcode":"24019",
    "addr:street":"Peters Creek Rd Nw",
    "iso:country":"US",
    "sg:address":"3005 Peters Creek Rd NW",
    "sg:city":"Roanoke",
    "sg:classifiers":[
        {
            "category":"Health Services",
            "subcategory":"Doctor",
            "type":"Services"
        }
    ],
    "sg:phone":"+1 540 562 3166",
    "sg:postcode":"24019",
    "sg:province":"VA",
    "wof:name":"Donnie E Mayhew DDS",
    "wof:placetype":"venue"
},
  "geometry": {"coordinates":[-80.001446,37.318805],"type":"Point"}
}