{
  "type": "Feature",
  "properties": {
    "iso:country":"US",
    "sg:address":"240 Hartmans Mill Rd",
    "sg:city":"Charlottesville",
    "sg:classifiers":[
        {
            "category":"Building & Trades",
            "subcategory":"Landscaping Services",
            "type":"Services"
        }
    ],
    "sg:phone":"+1 434 296 0026",
    "sg:postcode":"22902",
    "sg:province":"VA",
    "sg:tags":[
        "landscape",
        "contractor"
    ],
    "wof:name":"Land Power Landscaping & Mntnc",
    "wof:placetype":"venue"
},
  "geometry": {"coordinates":[-78.48961,38.020878],"type":"Point"}
}