{
  "type": "Feature",
  "properties": {
    "iso:country":"US",
    "sg:address":"6305 Castle Pl",
    "sg:city":"Falls Church",
    "sg:classifiers":[
        {
            "category":"Health Services",
            "subcategory":"Doctor",
            "type":"Services"
        }
    ],
    "sg:phone":"+1 703 534 2584",
    "sg:postcode":"22044",
    "sg:province":"VA",
    "sg:tags":[
        "physician",
        "surgeon",
        "medical"
    ],
    "wof:name":"Falls Church Family Care PC",
    "wof:placetype":"venue"
},
  "geometry": {"coordinates":[-77.15654499999999,38.871033],"type":"Point"}
}