{
  "type": "Feature",
  "properties": {
    "addr:full":"8821 Henson Rd Richmond VA 23236",
    "addr:housenumber":"8821",
    "addr:postcode":"23236",
    "addr:street":"Henson Rd",
    "iso:country":"US",
    "sg:address":"8821 Henson Rd",
    "sg:city":"Richmond",
    "sg:classifiers":[
        {
            "category":"Building & Trades",
            "subcategory":"Construction",
            "type":"Services"
        }
    ],
    "sg:phone":"+1 804 276 8287",
    "sg:postcode":"23236",
    "sg:province":"VA",
    "sg:tags":[
        "painting",
        "contractor"
    ],
    "wof:name":"George Northey Painting Inc",
    "wof:placetype":"venue"
},
  "geometry": {"coordinates":[-77.569254,37.470989],"type":"Point"}
}