{
  "type": "Feature",
  "properties": {
    "iso:country":"US",
    "sg:address":"9610 Grant Ave",
    "sg:city":"Manassas",
    "sg:classifiers":[
        {
            "category":"Shopping",
            "subcategory":"Music",
            "type":"Retail Goods"
        }
    ],
    "sg:phone":"+1 703 392 5939",
    "sg:postcode":"20110",
    "sg:province":"VA",
    "wof:name":"Casa De Musica",
    "wof:placetype":"venue"
},
  "geometry": {"coordinates":[-77.474458,38.746856],"type":"Point"}
}