{
  "type": "Feature",
  "properties": {
    "addr:full":"1710 Beatrice Ln Chesapeake VA 23323",
    "addr:housenumber":"1710",
    "addr:postcode":"23323",
    "addr:street":"Beatrice Ln",
    "iso:country":"US",
    "sg:address":"1710 Beatrice Ln",
    "sg:city":"Chesapeake",
    "sg:classifiers":[
        {
            "category":"Professional",
            "type":"Services"
        }
    ],
    "sg:phone":"+1 757 547 9438",
    "sg:postcode":"23323",
    "sg:province":"VA",
    "wof:name":"Jrv Corp",
    "wof:placetype":"venue"
},
  "geometry": {"coordinates":[-76.300714,36.666866],"type":"Point"}
}