{
  "type": "Feature",
  "properties": {
    "iso:country":"US",
    "sg:address":"11911 Freedom Dr",
    "sg:city":"Reston",
    "sg:classifiers":[
        {
            "category":"Professional",
            "subcategory":"Management & Consulting",
            "type":"Services"
        }
    ],
    "sg:phone":"+1 703 480 1620",
    "sg:postcode":"20190",
    "sg:province":"VA",
    "sg:tags":[
        "auto",
        "company",
        "providing",
        "call",
        "telecommunication"
    ],
    "wof:name":"Contact Solutions Inc",
    "wof:placetype":"venue"
},
  "geometry": {"coordinates":[-77.355525,38.959217],"type":"Point"}
}