{
  "type": "Feature",
  "properties": {
    "addr:full":"9200 Midlothian Tpke Richmond VA 23235",
    "addr:housenumber":"9200",
    "addr:postcode":"23235",
    "addr:street":"Midlothian Tpke",
    "iso:country":"US",
    "sg:address":"9200 Midlothian Tpke",
    "sg:city":"Richmond",
    "sg:classifiers":[
        {
            "category":"Food & Beverages",
            "subcategory":"Groceries & Convenience Stores",
            "type":"Retail Goods"
        }
    ],
    "sg:phone":"+1 804 320 4188",
    "sg:postcode":"23235",
    "sg:province":"VA",
    "wof:name":"Rennie's",
    "wof:placetype":"venue"
},
  "geometry": {"coordinates":[-77.56739399999999,37.497419],"type":"Point"}
}