{
  "type": "Feature",
  "properties": {
    "iso:country":"US",
    "sg:address":"14150 Newbrook Dr",
    "sg:city":"Chantilly",
    "sg:classifiers":[
        {
            "category":"Wholesale",
            "subcategory":"Medical Equipment & Supplies",
            "type":"Manufacturing & Wholesale Goods"
        }
    ],
    "sg:phone":"+1 703 796 0134",
    "sg:postcode":"20151",
    "sg:province":"VA",
    "wof:name":"Medical Equipment Group",
    "wof:placetype":"venue"
},
  "geometry": {"coordinates":[-77.434445,38.872417],"type":"Point"}
}