{
  "type": "Feature",
  "properties": {
    "addr:full":"7800 Heritage Dr Annandale VA 22003",
    "addr:housenumber":"7800",
    "addr:postcode":"22003",
    "addr:street":"Heritage Dr",
    "iso:country":"US",
    "sg:address":"7800 Heritage Dr",
    "sg:city":"Annandale",
    "sg:classifiers":[
        {
            "category":"Professional",
            "type":"Services"
        }
    ],
    "sg:phone":"+1 703 642 5256",
    "sg:postcode":"22003",
    "sg:province":"VA",
    "wof:name":"Srss Inc",
    "wof:placetype":"venue"
},
  "geometry": {"coordinates":[-77.214304,38.820378],"type":"Point"}
}