{
  "type": "Feature",
  "properties": {
    "addr:full":"605 Harpersville Rd Newport News VA 23601",
    "addr:housenumber":"605",
    "addr:postcode":"23601",
    "addr:street":"Harpersville Rd",
    "iso:country":"US",
    "sg:address":"605 Harpersville Rd",
    "sg:city":"Newport News",
    "sg:classifiers":[
        {
            "category":"Organizations",
            "subcategory":"Religious Organization",
            "type":"Services"
        }
    ],
    "sg:phone":"+1 757 596 9674",
    "sg:postcode":"23601",
    "sg:province":"VA",
    "sg:tags":[
        "church"
    ],
    "wof:name":"Asbury Wesleyan Church",
    "wof:placetype":"venue"
},
  "geometry": {"coordinates":[-76.459047,37.070336],"type":"Point"}
}