{
  "type": "Feature",
  "properties": {
    "addr:full":"3210 Old Forest Rd Lynchburg VA 24501",
    "addr:housenumber":"3210",
    "addr:postcode":"24501",
    "addr:street":"Old Forest Rd",
    "iso:country":"US",
    "sg:address":"3210 Old Forest Rd",
    "sg:city":"Lynchburg",
    "sg:classifiers":[
        {
            "category":"Retail",
            "subcategory":"Car Wash",
            "type":"Services"
        }
    ],
    "sg:phone":"+1 434 385 5905",
    "sg:postcode":"24501",
    "sg:province":"VA",
    "sg:tags":[
        "polishing",
        "carwash",
        "washing"
    ],
    "wof:name":"Water Works Car Wash",
    "wof:placetype":"venue"
},
  "geometry": {"coordinates":[-79.209711,37.41452],"type":"Point"}
}