{
  "type": "Feature",
  "properties": {
    "addr:full":"4301 Brambleton Ave Roanoke VA 24018",
    "addr:housenumber":"4301",
    "addr:postcode":"24018",
    "addr:street":"Brambleton Ave",
    "iso:country":"US",
    "sg:address":"4301 Brambleton Ave",
    "sg:city":"Roanoke",
    "sg:classifiers":[
        {
            "category":"Restaurant",
            "type":"Food & Drink"
        }
    ],
    "sg:phone":"+1 540 774 7446",
    "sg:postcode":"24018",
    "sg:province":"VA",
    "sg:tags":[
        "italian"
    ],
    "wof:name":"Titos Italian Restaurant, Inc",
    "wof:placetype":"venue"
},
  "geometry": {"coordinates":[-80.009581,37.228181],"type":"Point"}
}