{
  "type": "Feature",
  "properties": {
    "addr:full":"1822 Portsmouth Blvd Portsmouth VA 23704",
    "addr:housenumber":"1822",
    "addr:postcode":"23704",
    "addr:street":"Portsmouth Blvd",
    "iso:country":"US",
    "sg:address":"1822 Portsmouth Blvd",
    "sg:city":"Portsmouth",
    "sg:classifiers":[
        {
            "category":"Retail",
            "subcategory":"Funeral Services",
            "type":"Services"
        }
    ],
    "sg:phone":"+1 757 399 4661",
    "sg:postcode":"23704",
    "sg:province":"VA",
    "sg:tags":[
        "director",
        "home"
    ],
    "wof:name":"Corprew Funeral Home Inc",
    "wof:placetype":"venue"
},
  "geometry": {"coordinates":[-76.322074,36.817821],"type":"Point"}
}