{
  "type": "Feature",
  "properties": {
    "iso:country":"US",
    "sg:address":"815 Pecan Point Rd",
    "sg:city":"Norfolk",
    "sg:classifiers":[
        {
            "category":"Real Estate",
            "subcategory":"Real Estate Operator",
            "type":"Services"
        }
    ],
    "sg:phone":"+1 757 461 1515",
    "sg:postcode":"23502",
    "sg:province":"VA",
    "sg:tags":[
        "apartment"
    ],
    "wof:name":"Olympic Village Apartments",
    "wof:placetype":"venue"
},
  "geometry": {"coordinates":[-76.22177600000001,36.854297],"type":"Point"}
}