{
  "type": "Feature",
  "properties": {
    "addr:full":"5334 Grayson Tpke Crockett VA 24323",
    "addr:housenumber":"5334",
    "addr:postcode":"24323",
    "addr:street":"Grayson Tpke",
    "iso:country":"US",
    "sg:address":"5334 Grayson Tpke",
    "sg:city":"Crockett",
    "sg:classifiers":[
        {
            "category":"Farming",
            "subcategory":"Livestock Farm",
            "type":"Manufacturing & Wholesale Goods"
        }
    ],
    "sg:phone":"+1 276 686 5650",
    "sg:postcode":"24323",
    "sg:province":"VA",
    "sg:tags":[
        "beef",
        "feedlot",
        "cattle"
    ],
    "wof:name":"Sugar Run Farm",
    "wof:placetype":"venue"
},
  "geometry": {"coordinates":[-81.18343400000001,36.851768],"type":"Point"}
}