{
  "type": "Feature",
  "properties": {
    "addr:full":"66 Morris Ave Reedville VA 22539",
    "addr:housenumber":"66",
    "addr:postcode":"22539",
    "addr:street":"Morris Ave",
    "iso:country":"US",
    "sg:address":"66 Morris Ave",
    "sg:city":"Reedville",
    "sg:classifiers":[
        {
            "category":"Building & Trades",
            "subcategory":"Construction",
            "type":"Services"
        }
    ],
    "sg:phone":"+1 804 453 3215",
    "sg:postcode":"22539",
    "sg:province":"VA",
    "sg:tags":[
        "house"
    ],
    "wof:name":"D Bromley",
    "wof:placetype":"venue"
},
  "geometry": {"coordinates":[-76.274822,37.847405],"type":"Point"}
}