{
  "type": "Feature",
  "properties": {
    "addr:full":"901 E 3rd St Farmville VA 23901",
    "addr:housenumber":"901",
    "addr:postcode":"23901",
    "addr:street":"E 3Rd St",
    "iso:country":"US",
    "sg:address":"901 E 3rd St",
    "sg:city":"Farmville",
    "sg:classifiers":[
        {
            "category":"Professional",
            "subcategory":"Art Services",
            "type":"Services"
        }
    ],
    "sg:phone":"+1 434 315 5515",
    "sg:postcode":"23901",
    "sg:province":"VA",
    "sg:tags":[
        "commercial",
        "design"
    ],
    "wof:name":"American Graphix",
    "wof:placetype":"venue"
},
  "geometry": {"coordinates":[-78.381601,37.29708],"type":"Point"}
}