{
  "type": "Feature",
  "properties": {
    "addr:full":"2000 Kraft Dr Blacksburg VA 24060",
    "addr:housenumber":"2000",
    "addr:postcode":"24060",
    "addr:street":"Kraft Dr",
    "iso:country":"US",
    "sg:address":"2000 Kraft Dr",
    "sg:city":"Blacksburg",
    "sg:classifiers":[
        {
            "category":"Professional",
            "type":"Services"
        }
    ],
    "sg:phone":"+1 540 953 1538",
    "sg:postcode":"24060",
    "sg:province":"VA",
    "sg:tags":[
        "establishment"
    ],
    "wof:name":"Wessex Inc",
    "wof:placetype":"venue"
},
  "geometry": {"coordinates":[-80.409482,37.201372],"type":"Point"}
}