{
  "type": "Feature",
  "properties": {
    "iso:country":"US",
    "sg:address":"10109 Daniels Run Way",
    "sg:city":"Fairfax",
    "sg:classifiers":[
        {
            "category":"Professional",
            "subcategory":"Engineering",
            "type":"Services"
        }
    ],
    "sg:phone":"+1 703 352 8060",
    "sg:postcode":"22030",
    "sg:province":"VA",
    "sg:tags":[
        "engineer"
    ],
    "wof:name":"J T Ten",
    "wof:placetype":"venue"
},
  "geometry": {"coordinates":[-77.294984,38.850024],"type":"Point"}
}