{
  "type": "Feature",
  "properties": {
    "iso:country":"US",
    "sg:address":"305 Carolina Rd",
    "sg:city":"Suffolk",
    "sg:classifiers":[
        {
            "category":"Wholesale",
            "subcategory":"Machinery & Supplies",
            "type":"Manufacturing & Wholesale Goods"
        }
    ],
    "sg:phone":"+1 757 539 4448",
    "sg:postcode":"23434",
    "sg:province":"VA",
    "sg:tags":[
        "fastener",
        "mill"
    ],
    "wof:name":"GE Supply Logistics LLC",
    "wof:placetype":"venue"
},
  "geometry": {"coordinates":[-76.58728600000001,36.724535],"type":"Point"}
}