{
  "type": "Feature",
  "properties": {
    "iso:country":"US",
    "sg:address":"149 E Little Creek Rd",
    "sg:city":"Norfolk",
    "sg:classifiers":[
        {
            "category":"Shopping",
            "subcategory":"Gifts & Souvenirs",
            "type":"Retail Goods"
        },
        {
            "category":"Shopping",
            "subcategory":"Clothing, Apparel, & Fashions",
            "type":"Retail Goods"
        }
    ],
    "sg:phone":"+1 757 583 4334",
    "sg:postcode":"23505",
    "sg:province":"VA",
    "sg:tags":[
        "novelty"
    ],
    "wof:name":"Leather and Lace",
    "wof:placetype":"venue"
},
  "geometry": {"coordinates":[-76.270763,36.914797],"type":"Point"}
}