{
  "type": "Feature",
  "properties": {
    "addr:full":"214 N Main St Farmville VA 23901",
    "addr:housenumber":"214",
    "addr:postcode":"23901",
    "addr:street":"N Main St",
    "iso:country":"US",
    "sg:address":"214 N Main St",
    "sg:city":"Farmville",
    "sg:classifiers":[
        {
            "category":"Food & Beverages",
            "subcategory":"Specialty",
            "type":"Retail Goods"
        }
    ],
    "sg:phone":"+1 434 392 5559",
    "sg:postcode":"23901",
    "sg:province":"VA",
    "wof:name":"Cafe Zelia",
    "wof:placetype":"venue"
},
  "geometry": {"coordinates":[-78.39145600000001,37.303567],"type":"Point"}
}