{
  "type": "Feature",
  "properties": {
    "iso:country":"US",
    "sg:address":"424 Commerce Rd",
    "sg:city":"Staunton",
    "sg:classifiers":[
        {
            "category":"Health Services",
            "subcategory":"Doctor",
            "type":"Services"
        }
    ],
    "sg:phone":"+1 540 886 4866",
    "sg:postcode":"24401",
    "sg:province":"VA",
    "sg:tags":[
        "physician",
        "surgeon"
    ],
    "wof:name":"Shenandoah Diabetes Ctr",
    "wof:placetype":"venue"
},
  "geometry": {"coordinates":[-79.057946,38.153104],"type":"Point"}
}