{
  "type": "Feature",
  "properties": {
    "addr:full":"1912 Shady Cove Ct Chesapeake VA 23320",
    "addr:housenumber":"1912",
    "addr:postcode":"23320",
    "addr:street":"Shady Cove Ct",
    "iso:country":"US",
    "sg:address":"1912 Shady Cove Ct",
    "sg:city":"Chesapeake",
    "sg:classifiers":[
        {
            "category":"Restaurant",
            "type":"Food & Drink"
        }
    ],
    "sg:phone":"+1 757 479 4741",
    "sg:postcode":"23320",
    "sg:province":"VA",
    "sg:tags":[
        "eating"
    ],
    "wof:name":"Virginia Italian Ices Inc",
    "wof:placetype":"venue"
},
  "geometry": {"coordinates":[-76.19035,36.759679],"type":"Point"}
}