{
  "type": "Feature",
  "properties": {
    "iso:country":"US",
    "sg:address":"6607 W Franklin St",
    "sg:city":"Richmond",
    "sg:classifiers":[
        {
            "category":"Insurance",
            "subcategory":"Insurance Agent",
            "type":"Services"
        }
    ],
    "sg:phone":"+1 804 285 3285",
    "sg:postcode":"23226",
    "sg:province":"VA",
    "wof:name":"Lanier Financial Assoc",
    "wof:placetype":"venue"
},
  "geometry": {"coordinates":[-77.525047,37.591173],"type":"Point"}
}