{
  "type": "Feature",
  "properties": {
    "addr:full":"10440 Balls Ford Rd Manassas VA 20109",
    "addr:housenumber":"10440",
    "addr:postcode":"20109",
    "addr:street":"Balls Ford Rd",
    "iso:country":"US",
    "sg:address":"10440 Balls Ford Rd",
    "sg:city":"Manassas",
    "sg:classifiers":[
        {
            "category":"Building & Trades",
            "subcategory":"Construction",
            "type":"Services"
        }
    ],
    "sg:phone":"+1 703 361 4483",
    "sg:postcode":"20109",
    "sg:province":"VA",
    "sg:tags":[
        "roofing",
        "contractor"
    ],
    "wof:name":"Apex Roofing Inc",
    "wof:placetype":"venue"
},
  "geometry": {"coordinates":[-77.512002,38.800567],"type":"Point"}
}