{
  "type": "Feature",
  "properties": {
    "addr:full":"14329 Western Riders Ln Glen Allen VA 23059",
    "addr:housenumber":"14329",
    "addr:postcode":"23059",
    "addr:street":"Western Riders Ln",
    "iso:country":"US",
    "sg:address":"14329 Western Riders Ln",
    "sg:city":"Glen Allen",
    "sg:classifiers":[
        {
            "category":"Organizations",
            "subcategory":"Religious Organization",
            "type":"Services"
        }
    ],
    "sg:phone":"+1 804 798 2714",
    "sg:postcode":"23059",
    "sg:province":"VA",
    "wof:name":"New Way Missions",
    "wof:placetype":"venue"
},
  "geometry": {"coordinates":[-77.59721500000001,37.709512],"type":"Point"}
}