{
  "type": "Feature",
  "properties": {
    "addr:full":"4603 Marble Rock Ct Chantilly VA 20151",
    "addr:housenumber":"4603",
    "addr:postcode":"20151",
    "addr:street":"Marble Rock Ct",
    "iso:country":"US",
    "sg:address":"4603 Marble Rock Ct",
    "sg:city":"Chantilly",
    "sg:classifiers":[
        {
            "category":"Professional",
            "type":"Services"
        }
    ],
    "sg:phone":"+1 703 815 5513",
    "sg:postcode":"20151",
    "sg:province":"VA",
    "sg:tags":[
        "broadcaster",
        "radio"
    ],
    "wof:name":"Tadayon Ahmad",
    "wof:placetype":"venue"
},
  "geometry": {"coordinates":[-77.412682,38.86242],"type":"Point"}
}