{
  "type": "Feature",
  "properties": {
    "addr:full":"7210 Old Keene Mill Rd Springfield VA 22150",
    "addr:housenumber":"7210",
    "addr:postcode":"22150",
    "addr:street":"Old Keene Mill Rd",
    "iso:country":"US",
    "sg:address":"7210 Old Keene Mill Rd",
    "sg:city":"Springfield",
    "sg:classifiers":[
        {
            "category":"Real Estate",
            "subcategory":"Real Estate Agent",
            "type":"Services"
        }
    ],
    "sg:phone":"+1 703 569 9700",
    "sg:postcode":"22150",
    "sg:province":"VA",
    "sg:website":"www.weichert.com",
    "wof:name":"Weichert Realtors",
    "wof:placetype":"venue"
},
  "geometry": {"coordinates":[-77.192787,38.778109],"type":"Point"}
}