{
  "type": "Feature",
  "properties": {
    "iso:country":"US",
    "sg:address":"6017 Brunswick St",
    "sg:city":"Springfield",
    "sg:classifiers":[
        {
            "category":"Social Services",
            "subcategory":"Child Care",
            "type":"Services"
        }
    ],
    "sg:phone":"+1 703 569 6173",
    "sg:postcode":"22150",
    "sg:province":"VA",
    "sg:tags":[
        "nursery",
        "day"
    ],
    "wof:name":"Rachel E Ersoz",
    "wof:placetype":"venue"
},
  "geometry": {"coordinates":[-77.188473,38.788186],"type":"Point"}
}