{
  "type": "Feature",
  "properties": {
    "addr:full":"1401 Jefferson Park Ave Charlottesville VA 22901",
    "addr:housenumber":"1401",
    "addr:postcode":"22901",
    "addr:street":"Jefferson Park Ave",
    "iso:country":"US",
    "sg:address":"1401 Jefferson Park Ave",
    "sg:city":"Charlottesville",
    "sg:classifiers":[
        {
            "category":"Health Services",
            "subcategory":"Doctor",
            "type":"Services"
        }
    ],
    "sg:phone":"+1 434 924 2465",
    "sg:postcode":"22901",
    "sg:province":"VA",
    "wof:name":"Mahapatra Srijoy MD",
    "wof:placetype":"venue"
},
  "geometry": {"coordinates":[-78.50186600000001,38.032314],"type":"Point"}
}