{
  "type": "Feature",
  "properties": {
    "addr:full":"249 Jess Sine Rd Woodstock VA 22664",
    "addr:housenumber":"249",
    "addr:postcode":"22664",
    "addr:street":"Jess Sine Rd",
    "iso:country":"US",
    "sg:address":"249 Jess Sine Rd",
    "sg:city":"Woodstock",
    "sg:classifiers":[
        {
            "category":"Professional",
            "type":"Services"
        }
    ],
    "sg:phone":"+1 540 459 2077",
    "sg:postcode":"22664",
    "sg:province":"VA",
    "sg:tags":[
        "establishment"
    ],
    "wof:name":"Logicon ICASE",
    "wof:placetype":"venue"
},
  "geometry": {"coordinates":[-78.48980899999999,38.912008],"type":"Point"}
}