{
  "type": "Feature",
  "properties": {
    "addr:full":"5012 Vayo Ave Richmond VA 23234",
    "addr:housenumber":"5012",
    "addr:postcode":"23234",
    "addr:street":"Vayo Ave",
    "iso:country":"US",
    "sg:address":"5012 Vayo Ave",
    "sg:city":"Richmond",
    "sg:classifiers":[
        {
            "category":"Recreation",
            "type":"Entertainment"
        }
    ],
    "sg:phone":"+1 804 721 8205",
    "sg:postcode":"23234",
    "sg:province":"VA",
    "wof:name":"Skateland of Richmond",
    "wof:placetype":"venue"
},
  "geometry": {"coordinates":[-77.448026,37.454294],"type":"Point"}
}