{
  "type": "Feature",
  "properties": {
    "addr:full":"1101 18th St S Arlington VA 22202",
    "addr:housenumber":"1101",
    "addr:postcode":"22202",
    "addr:street":"18Th St S",
    "iso:country":"US",
    "sg:address":"1101 18th St S",
    "sg:city":"Arlington",
    "sg:classifiers":[
        {
            "category":"Professional",
            "subcategory":"Business Services",
            "type":"Services"
        }
    ],
    "sg:phone":"+1 703 979 1010",
    "sg:postcode":"22202",
    "sg:province":"VA",
    "sg:tags":[
        "interior",
        "consultant",
        "design",
        "decorator"
    ],
    "wof:name":"IDC Interior Design & Constr",
    "wof:placetype":"venue"
},
  "geometry": {"coordinates":[-77.066715,38.856791],"type":"Point"}
}