{
  "type": "Feature",
  "properties": {
    "addr:full":"530 1st St Alexandria VA 22314",
    "addr:housenumber":"530",
    "addr:postcode":"22314",
    "addr:street":"1St St",
    "iso:country":"US",
    "sg:address":"530 1st St",
    "sg:city":"Alexandria",
    "sg:classifiers":[
        {
            "category":"Food & Beverages",
            "subcategory":"Groceries & Convenience Stores",
            "type":"Retail Goods"
        }
    ],
    "sg:phone":"+1 703 739 0751",
    "sg:postcode":"22314",
    "sg:province":"VA",
    "sg:tags":[
        "grocer"
    ],
    "sg:website":"www.giantfood.com/",
    "wof:name":"Giant Food",
    "wof:placetype":"venue"
},
  "geometry": {"coordinates":[-77.043299,38.815069],"type":"Point"}
}