{
  "type": "Feature",
  "properties": {
    "iso:country":"US",
    "sg:address":"905 Battlefield Blvd N",
    "sg:city":"Chesapeake",
    "sg:classifiers":[
        {
            "category":"Health Services",
            "subcategory":"Clinic",
            "type":"Services"
        }
    ],
    "sg:phone":"+1 757 548 4021",
    "sg:postcode":"23320",
    "sg:province":"VA",
    "sg:tags":[
        "specialty",
        "outpatient"
    ],
    "wof:name":"Novacare Pa Inc",
    "wof:placetype":"venue"
},
  "geometry": {"coordinates":[-76.247805,36.754688],"type":"Point"}
}