{
  "type": "Feature",
  "properties": {
    "addr:full":"49 Ballou St Clarksville VA 23927",
    "addr:housenumber":"49",
    "addr:postcode":"23927",
    "addr:street":"Ballou St",
    "iso:country":"US",
    "sg:address":"49 Ballou St",
    "sg:city":"Clarksville",
    "sg:classifiers":[
        {
            "category":"Building & Trades",
            "subcategory":"Pest Control",
            "type":"Services"
        }
    ],
    "sg:phone":"+1 434 575 1818",
    "sg:postcode":"23927",
    "sg:province":"VA",
    "wof:name":"American Exterminating",
    "wof:placetype":"venue"
},
  "geometry": {"coordinates":[-78.541569,36.608251],"type":"Point"}
}