{
  "type": "Feature",
  "properties": {
    "addr:full":"751 Thimble Shoals Blvd Newport News VA 23606",
    "addr:housenumber":"751",
    "addr:postcode":"23606",
    "addr:street":"Thimble Shoals Blvd",
    "iso:country":"US",
    "sg:address":"751 Thimble Shoals Blvd",
    "sg:city":"Newport News",
    "sg:classifiers":[
        {
            "category":"Real Estate",
            "subcategory":"Real Estate Agent",
            "type":"Services"
        }
    ],
    "sg:phone":"+1 757 873 0339",
    "sg:postcode":"23606",
    "sg:province":"VA",
    "wof:name":"Michael Carpenter",
    "wof:placetype":"venue"
},
  "geometry": {"coordinates":[-76.46647900000001,37.082446],"type":"Point"}
}