{
  "type": "Feature",
  "properties": {
    "addr:full":"1228 Progressive Dr Chesapeake VA 23320",
    "addr:housenumber":"1228",
    "addr:postcode":"23320",
    "addr:street":"Progressive Dr",
    "iso:country":"US",
    "sg:address":"1228 Progressive Dr",
    "sg:city":"Chesapeake",
    "sg:classifiers":[
        {
            "category":"Professional",
            "subcategory":"Accounting & Tax Preparation",
            "type":"Services"
        }
    ],
    "sg:phone":"+1 757 436 4602",
    "sg:postcode":"23320",
    "sg:province":"VA",
    "sg:tags":[
        "business"
    ],
    "wof:name":"Archer & Associates PC",
    "wof:placetype":"venue"
},
  "geometry": {"coordinates":[-76.23011,36.765878],"type":"Point"}
}