{
  "type": "Feature",
  "properties": {
    "addr:full":"504 S Van Dorn St Ste D Alexandria VA 22304",
    "addr:housenumber":"504",
    "addr:postcode":"22304",
    "addr:street":"S Van Dorn St Ste D",
    "iso:country":"US",
    "sg:address":"504 S Van Dorn St Ste D",
    "sg:city":"Alexandria",
    "sg:classifiers":[
        {
            "category":"Coffee & Tea",
            "type":"Food & Drink"
        },
        {
            "category":"Donuts",
            "subcategory":"None",
            "type":"Food & Drink"
        }
    ],
    "sg:phone":"+1 703 751 7863",
    "sg:postcode":"22304",
    "sg:province":"VA",
    "sg:tags":[
        "shop",
        "espresso",
        "restaurant"
    ],
    "sg:website":"http://www.dunkindonuts.com",
    "wof:name":"Dunkin' Donuts",
    "wof:placetype":"venue"
},
  "geometry": {"coordinates":[-77.133111,38.807456],"type":"Point"}
}