{
  "type": "Feature",
  "properties": {
    "addr:full":"8361 W Main St Marshall VA 20115",
    "addr:housenumber":"8361",
    "addr:postcode":"20115",
    "addr:street":"W Main St",
    "iso:country":"US",
    "sg:address":"8361 W Main St",
    "sg:city":"Marshall",
    "sg:classifiers":[
        {
            "category":"Government",
            "subcategory":"Post Office",
            "type":"Public Place"
        }
    ],
    "sg:phone":"+1 540 364 9491",
    "sg:postcode":"20115",
    "sg:province":"VA",
    "sg:tags":[
        "postal",
        "us"
    ],
    "wof:name":"Marshall Main Office",
    "wof:placetype":"venue"
},
  "geometry": {"coordinates":[-77.85686200000001,38.864892],"type":"Point"}
}