{
  "type": "Feature",
  "properties": {
    "iso:country":"US",
    "sg:address":"13131 Willoughby Point Dr",
    "sg:city":"Fairfax",
    "sg:classifiers":[
        {
            "category":"Autos & Motor Vehicles",
            "subcategory":"Automobile Sales",
            "type":"Retail Goods"
        }
    ],
    "sg:phone":"+1 703 818 1739",
    "sg:postcode":"22033",
    "sg:province":"VA",
    "sg:tags":[
        "used"
    ],
    "wof:name":"Jimmys Auto",
    "wof:placetype":"venue"
},
  "geometry": {"coordinates":[-77.40288,38.890633],"type":"Point"}
}