{
  "type": "Feature",
  "properties": {
    "iso:country":"US",
    "sg:address":"120 W Blue Ridge St",
    "sg:city":"Stuart",
    "sg:classifiers":[
        {
            "category":"Real Estate",
            "subcategory":"Real Estate Agent",
            "type":"Services"
        }
    ],
    "sg:phone":"+1 276 694 2001",
    "sg:postcode":"24171",
    "sg:province":"VA",
    "wof:name":"Blue Ridge Real Estate Co",
    "wof:placetype":"venue"
},
  "geometry": {"coordinates":[-80.269879,36.642618],"type":"Point"}
}