{
  "type": "Feature",
  "properties": {
    "addr:full":"533 Craghead St Danville VA 24541",
    "addr:housenumber":"533",
    "addr:postcode":"24541",
    "addr:street":"Craghead St",
    "iso:country":"US",
    "sg:address":"533 Craghead St",
    "sg:city":"Danville",
    "sg:classifiers":[
        {
            "category":"Shopping",
            "subcategory":"Clothing, Apparel, & Fashions",
            "type":"Retail Goods"
        }
    ],
    "sg:phone":"+1 434 792 7467",
    "sg:postcode":"24541",
    "sg:province":"VA",
    "wof:name":"T & E Urban Wear",
    "wof:placetype":"venue"
},
  "geometry": {"coordinates":[-79.387638,36.58594],"type":"Point"}
}