{
  "type": "Feature",
  "properties": {
    "iso:country":"US",
    "sg:address":"16638 E Summit Ave",
    "sg:city":"Elkton",
    "sg:classifiers":[
        {
            "category":"Building & Trades",
            "subcategory":"Construction",
            "type":"Services"
        }
    ],
    "sg:phone":"+1 540 298 8155",
    "sg:postcode":"22827",
    "sg:province":"VA",
    "sg:tags":[
        "builder",
        "deck"
    ],
    "wof:name":"Deck Raiders",
    "wof:placetype":"venue"
},
  "geometry": {"coordinates":[-78.61352100000001,38.401352],"type":"Point"}
}