{
  "type": "Feature",
  "properties": {
    "iso:country":"US",
    "sg:address":"5980 13th St",
    "sg:city":"Fort Belvoir",
    "sg:classifiers":[
        {
            "category":"Building & Trades",
            "subcategory":"Equipment Rental",
            "type":"Services"
        }
    ],
    "sg:phone":"+1 703 781 0480",
    "sg:postcode":"22060",
    "sg:province":"VA",
    "sg:tags":[
        "car",
        "passenger"
    ],
    "wof:name":"Enterprise Lsg Co of St Louis",
    "wof:placetype":"venue"
},
  "geometry": {"coordinates":[-77.14321,38.69548],"type":"Point"}
}