{
  "type": "Feature",
  "properties": {
    "iso:country":"US",
    "sg:address":"9508 Braddock Rd",
    "sg:city":"Fairfax",
    "sg:classifiers":[
        {
            "category":"Social Services",
            "subcategory":"Child Care",
            "type":"Services"
        }
    ],
    "sg:phone":"+1 703 425 8071",
    "sg:postcode":"22032",
    "sg:province":"VA",
    "sg:tags":[
        "day"
    ],
    "wof:name":"Albas Family Daycare",
    "wof:placetype":"venue"
},
  "geometry": {"coordinates":[-77.272212,38.816361],"type":"Point"}
}