{
  "type": "Feature",
  "properties": {
    "addr:full":"5223 S Laburnum Ave Richmond VA 23231",
    "addr:housenumber":"5223",
    "addr:postcode":"23231",
    "addr:street":"S Laburnum Ave",
    "iso:country":"US",
    "sg:address":"5223 S Laburnum Ave",
    "sg:city":"Richmond",
    "sg:classifiers":[
        {
            "category":"Retail",
            "subcategory":"Laundry & Dry Cleaning",
            "type":"Services"
        }
    ],
    "sg:phone":"+1 804 222 5099",
    "sg:postcode":"23231",
    "sg:province":"VA",
    "sg:tags":[
        "cleaners",
        "power"
    ],
    "wof:name":"Hawthorne Laundry & Dry Clnrs",
    "wof:placetype":"venue"
},
  "geometry": {"coordinates":[-77.349932,37.517212],"type":"Point"}
}