{
  "type": "Feature",
  "properties": {
    "iso:country":"US",
    "sg:address":"300 Falling Rock Dr",
    "sg:city":"Stuarts Draft",
    "sg:classifiers":[
        {
            "category":"Home & Garden",
            "subcategory":"Building Materials",
            "type":"Retail Goods"
        }
    ],
    "sg:phone":"+1 540 337 2249",
    "sg:postcode":"24477",
    "sg:province":"VA",
    "sg:tags":[
        "glass",
        "leaded"
    ],
    "wof:name":"Ann's Stained Glass Windows",
    "wof:placetype":"venue"
},
  "geometry": {"coordinates":[-79.03581800000001,37.997094],"type":"Point"}
}