{
  "type": "Feature",
  "properties": {
    "addr:full":"4241 32nd Rd S Arlington VA 22206",
    "addr:housenumber":"4241",
    "addr:postcode":"22206",
    "addr:street":"32Nd Rd S",
    "iso:country":"US",
    "sg:address":"4241 32nd Rd S",
    "sg:city":"Arlington",
    "sg:classifiers":[
        {
            "category":"Building & Trades",
            "subcategory":"Construction",
            "type":"Services"
        }
    ],
    "sg:phone":"+1 703 524 0088",
    "sg:postcode":"22206",
    "sg:province":"VA",
    "sg:tags":[
        "resurfacing",
        "laying",
        "refinishing",
        "floor"
    ],
    "wof:name":"Personal Pride Floor Svc",
    "wof:placetype":"venue"
},
  "geometry": {"coordinates":[-77.088014,38.83603],"type":"Point"}
}