{
  "type": "Feature",
  "properties": {
    "addr:full":"923 W Atlantic St Emporia VA 23847",
    "addr:housenumber":"923",
    "addr:postcode":"23847",
    "addr:street":"W Atlantic St",
    "iso:country":"US",
    "sg:address":"923 W Atlantic St",
    "sg:city":"Emporia",
    "sg:classifiers":[
        {
            "category":"Restaurant",
            "type":"Food & Drink"
        }
    ],
    "sg:menulink":"http://www.allmenus.com/va/emporia/153134-bojangles/menu/",
    "sg:phone":"+1 803 336 0446",
    "sg:postcode":"23847",
    "sg:province":"VA",
    "sg:tags":[
        "chicken",
        "sandwich",
        "american"
    ],
    "wof:name":"Bojangle's",
    "wof:placetype":"venue"
},
  "geometry": {"coordinates":[-77.55237700000001,36.703718],"type":"Point"}
}