{
  "type": "Feature",
  "properties": {
    "addr:full":"12 S Van Dorn St Alexandria VA 22304",
    "addr:housenumber":"12",
    "addr:postcode":"22304",
    "addr:street":"S Van Dorn St",
    "iso:country":"US",
    "sg:address":"12 S Van Dorn St",
    "sg:city":"Alexandria",
    "sg:classifiers":[
        {
            "category":"Building & Trades",
            "subcategory":"Construction",
            "type":"Services"
        }
    ],
    "sg:phone":"+1 703 212 8912",
    "sg:postcode":"22304",
    "sg:province":"VA",
    "sg:tags":[
        "house"
    ],
    "wof:name":"Alex APT Homes",
    "wof:placetype":"venue"
},
  "geometry": {"coordinates":[-77.12958500000001,38.814093],"type":"Point"}
}