{
  "type": "Feature",
  "properties": {
    "iso:country":"US",
    "sg:address":"320 Maple Ave W",
    "sg:city":"Vienna",
    "sg:classifiers":[
        {
            "category":"Restaurant",
            "type":"Food & Drink"
        }
    ],
    "sg:menulink":"http://www.allmenus.com/va/hunter-mill/116382-quiznos-sub/menu/",
    "sg:phone":"+1 703 242 9102",
    "sg:postcode":"22180",
    "sg:province":"VA",
    "sg:tags":[
        "wrap",
        "american",
        "sandwich"
    ],
    "wof:name":"Quiznos Sub",
    "wof:placetype":"venue"
},
  "geometry": {"coordinates":[-77.269778,38.897922],"type":"Point"}
}