{
  "type": "Feature",
  "properties": {
    "iso:country":"US",
    "sg:address":"124 Artillery Rd",
    "sg:city":"Winchester",
    "sg:classifiers":[
        {
            "category":"Professional",
            "subcategory":"Detective & Security Services",
            "type":"Services"
        }
    ],
    "sg:phone":"+1 540 723 6730",
    "sg:postcode":"22602",
    "sg:province":"VA",
    "sg:tags":[
        "private",
        "investigator"
    ],
    "wof:name":"Herbert D Williams III",
    "wof:placetype":"venue"
},
  "geometry": {"coordinates":[-78.10718,39.183856],"type":"Point"}
}