{
  "type": "Feature",
  "properties": {
    "addr:full":"13914 Big Yankee Ln Centreville VA 20121",
    "addr:housenumber":"13914",
    "addr:postcode":"20121",
    "addr:street":"Big Yankee Ln",
    "iso:country":"US",
    "sg:address":"13914 Big Yankee Ln",
    "sg:city":"Centreville",
    "sg:classifiers":[
        {
            "category":"Professional",
            "subcategory":"Management & Consulting",
            "type":"Services"
        }
    ],
    "sg:phone":"+1 703 266 2791",
    "sg:postcode":"20121",
    "sg:province":"VA",
    "sg:tags":[
        "business"
    ],
    "wof:name":"MA Vangelder Inc",
    "wof:placetype":"venue"
},
  "geometry": {"coordinates":[-77.4269,38.826921],"type":"Point"}
}