{
  "type": "Feature",
  "properties": {
    "addr:full":"3843 Plaza Dr Fairfax VA 22030",
    "addr:housenumber":"3843",
    "addr:postcode":"22030",
    "addr:street":"Plaza Dr",
    "iso:country":"US",
    "sg:address":"3843 Plaza Dr",
    "sg:city":"Fairfax",
    "sg:classifiers":[
        {
            "category":"Real Estate",
            "subcategory":"Real Estate Agent",
            "type":"Services"
        }
    ],
    "sg:phone":"+1 703 273 5678",
    "sg:postcode":"22030",
    "sg:province":"VA",
    "wof:name":"First Dominion Real Estate",
    "wof:placetype":"venue"
},
  "geometry": {"coordinates":[-77.30148800000001,38.848473],"type":"Point"}
}