{
  "type": "Feature",
  "properties": {
    "addr:full":"5728 Patterson Ave Richmond VA 23226",
    "addr:housenumber":"5728",
    "addr:postcode":"23226",
    "addr:street":"Patterson Ave",
    "iso:country":"US",
    "sg:address":"5728 Patterson Ave",
    "sg:city":"Richmond",
    "sg:classifiers":[
        {
            "category":"Food & Beverages",
            "subcategory":"Bakery",
            "type":"Retail Goods"
        }
    ],
    "sg:phone":"+1 804 282 4413",
    "sg:postcode":"23226",
    "sg:province":"VA",
    "wof:name":"Westhampton Pastry Shop Inc",
    "wof:placetype":"venue"
},
  "geometry": {"coordinates":[-77.51384899999999,37.579052],"type":"Point"}
}