{
  "type": "Feature",
  "properties": {
    "iso:country":"US",
    "sg:address":"4505 Haygood Rd",
    "sg:city":"Virginia Beach",
    "sg:classifiers":[
        {
            "category":"Restaurant",
            "type":"Food & Drink"
        }
    ],
    "sg:menulink":"http://www.allmenus.com/va/virginia-beach/83483-papa-johns-pizza/menu/",
    "sg:phone":"+1 757 460 4900",
    "sg:postcode":"23455",
    "sg:province":"VA",
    "sg:tags":[
        "american",
        "pizza"
    ],
    "wof:name":"Papa John's Pizza",
    "wof:placetype":"venue"
},
  "geometry": {"coordinates":[-76.13458799999999,36.875395],"type":"Point"}
}