{
  "type": "Feature",
  "properties": {
    "iso:country":"US",
    "sg:address":"3559 Argonne Ave",
    "sg:city":"Norfolk",
    "sg:classifiers":[
        {
            "category":"Freight",
            "type":"Transportation"
        }
    ],
    "sg:phone":"+1 757 857 7843",
    "sg:postcode":"23509",
    "sg:province":"VA",
    "sg:tags":[
        "bulk",
        "storage"
    ],
    "wof:name":"VCI",
    "wof:placetype":"venue"
},
  "geometry": {"coordinates":[-76.25430299999999,36.882093],"type":"Point"}
}