{
  "type": "Feature",
  "properties": {
    "addr:full":"150 Kingsley Ln Norfolk VA 23505",
    "addr:housenumber":"150",
    "addr:postcode":"23505",
    "addr:street":"Kingsley Ln",
    "iso:country":"US",
    "sg:address":"150 Kingsley Ln",
    "sg:city":"Norfolk",
    "sg:classifiers":[
        {
            "category":"Health Services",
            "subcategory":"Doctor",
            "type":"Services"
        }
    ],
    "sg:phone":"+1 757 889 5432",
    "sg:postcode":"23505",
    "sg:province":"VA",
    "sg:tags":[
        "physician",
        "surgeon"
    ],
    "wof:name":"Evms",
    "wof:placetype":"venue"
},
  "geometry": {"coordinates":[-76.281302,36.898358],"type":"Point"}
}