{
  "type": "Feature",
  "properties": {
    "iso:country":"US",
    "sg:address":"13200 Willow Run Dr",
    "sg:city":"Elkwood",
    "sg:classifiers":[
        {
            "category":"Farming",
            "subcategory":"Nursery",
            "type":"Manufacturing & Wholesale Goods"
        }
    ],
    "sg:phone":"+1 540 825 8812",
    "sg:postcode":"22718",
    "sg:province":"VA",
    "sg:tags":[
        "greenhouse"
    ],
    "wof:name":"Willow Run Co",
    "wof:placetype":"venue"
},
  "geometry": {"coordinates":[-77.849519,38.51821],"type":"Point"}
}