{
  "type": "Feature",
  "properties": {
    "iso:country":"US",
    "sg:address":"1677 Crystal Square Arc",
    "sg:city":"Arlington",
    "sg:phone":"+1 703 413 6289",
    "sg:postcode":"22202",
    "sg:province":"VA",
    "sg:website":"http://www.shipshatch.com",
    "wof:name":"The Ship's Hatch",
    "wof:placetype":"venue"
},
  "geometry": {"coordinates":[-77.049869,38.860196],"type":"Point"}
}