{
  "type": "Feature",
  "properties": {
    "addr:full":"10700 Zion Dr Fairfax VA 22032",
    "addr:housenumber":"10700",
    "addr:postcode":"22032",
    "addr:street":"Zion Dr",
    "iso:country":"US",
    "sg:address":"10700 Zion Dr",
    "sg:city":"Fairfax",
    "sg:classifiers":[
        {
            "category":"Building & Trades",
            "subcategory":"Construction",
            "type":"Services"
        }
    ],
    "sg:phone":"+1 703 503 1143",
    "sg:postcode":"22032",
    "sg:province":"VA",
    "sg:tags":[
        "house"
    ],
    "wof:name":"Mark Peluso",
    "wof:placetype":"venue"
},
  "geometry": {"coordinates":[-77.312811,38.811088],"type":"Point"}
}