{
  "type": "Feature",
  "properties": {
    "iso:country":"US",
    "sg:address":"1149 Coleman Rd",
    "sg:city":"Scottsburg",
    "sg:classifiers":[
        {
            "category":"Retail",
            "subcategory":"Auto Repair",
            "type":"Services"
        }
    ],
    "sg:phone":"+1 434 454 7531",
    "sg:postcode":"24589",
    "sg:province":"VA",
    "sg:tags":[
        "general"
    ],
    "wof:name":"Emswiler Diesel Inc",
    "wof:placetype":"venue"
},
  "geometry": {"coordinates":[-78.781875,36.727812],"type":"Point"}
}