{
  "type": "Feature",
  "properties": {
    "addr:full":"4321 Old Union Rd Fork Union VA 23030",
    "addr:housenumber":"4321",
    "addr:postcode":"23030",
    "addr:street":"Old Union Rd",
    "iso:country":"US",
    "sg:address":"4321 Old Union Rd",
    "sg:city":"Fork Union",
    "sg:classifiers":[
        {
            "category":"Personal",
            "subcategory":"Beauty Salon",
            "type":"Services"
        }
    ],
    "sg:phone":"+1 434 842 9131",
    "sg:postcode":"23030",
    "sg:province":"VA",
    "sg:tags":[
        "shop"
    ],
    "wof:name":"New You",
    "wof:placetype":"venue"
},
  "geometry": {"coordinates":[-77.188745,37.448558],"type":"Point"}
}