{
  "type": "Feature",
  "properties": {
    "addr:full":"142 Cabbel Dr Manassas VA 20111",
    "addr:housenumber":"142",
    "addr:postcode":"20111",
    "addr:street":"Cabbel Dr",
    "iso:country":"US",
    "sg:address":"142 Cabbel Dr",
    "sg:city":"Manassas",
    "sg:classifiers":[
        {
            "category":"Building & Trades",
            "subcategory":"Construction",
            "type":"Services"
        }
    ],
    "sg:phone":"+1 703 368 7181",
    "sg:postcode":"20111",
    "sg:province":"VA",
    "sg:tags":[
        "carpentry",
        "contractor"
    ],
    "wof:name":"Glens Carpentery",
    "wof:placetype":"venue"
},
  "geometry": {"coordinates":[-77.456802,38.775539],"type":"Point"}
}