{
  "type": "Feature",
  "properties": {
    "iso:country":"US",
    "sg:address":"2808 Cofer Rd",
    "sg:city":"Richmond",
    "sg:classifiers":[
        {
            "category":"Wholesale",
            "subcategory":"Auto Parts",
            "type":"Manufacturing & Wholesale Goods"
        }
    ],
    "sg:phone":"+1 804 291 1955",
    "sg:postcode":"23224",
    "sg:province":"VA",
    "sg:tags":[
        "tire"
    ],
    "sg:website":"www.carrolltire.com",
    "wof:name":"Carroll Tire Company",
    "wof:placetype":"venue"
},
  "geometry": {"coordinates":[-77.45517,37.493041],"type":"Point"}
}