{
  "type": "Feature",
  "properties": {
    "iso:country":"US",
    "sg:address":"7885 Callaway Rd",
    "sg:city":"Callaway",
    "sg:classifiers":[
        {
            "category":"Personal",
            "subcategory":"Beauty Salon",
            "type":"Services"
        }
    ],
    "sg:phone":"+1 540 483 8793",
    "sg:postcode":"24067",
    "sg:province":"VA",
    "wof:name":"Cut & Do Hair Salon",
    "wof:placetype":"venue"
},
  "geometry": {"coordinates":[-80.04611199999999,37.012841],"type":"Point"}
}