{
  "type": "Feature",
  "properties": {
    "iso:country":"US",
    "sg:address":"3324 Chaparral Dr",
    "sg:city":"Roanoke",
    "sg:classifiers":[
        {
            "category":"Personal",
            "subcategory":"Massage",
            "type":"Services"
        }
    ],
    "sg:phone":"+1 540 819 8325",
    "sg:postcode":"24018",
    "sg:province":"VA",
    "wof:name":"Jean Saade Therapies",
    "wof:placetype":"venue"
},
  "geometry": {"coordinates":[-79.993156,37.220219],"type":"Point"}
}