{
  "type": "Feature",
  "properties": {
    "addr:full":"1386 Lawrenceville Plank Rd Lawrenceville VA 23868",
    "addr:housenumber":"1386",
    "addr:postcode":"23868",
    "addr:street":"Lawrenceville Plank Rd",
    "iso:country":"US",
    "sg:address":"1386 Lawrenceville Plank Rd",
    "sg:city":"Lawrenceville",
    "sg:classifiers":[
        {
            "category":"Manufacturing",
            "subcategory":"Printing",
            "type":"Manufacturing & Wholesale Goods"
        }
    ],
    "sg:phone":"+1 434 848 3865",
    "sg:postcode":"23868",
    "sg:province":"VA",
    "sg:tags":[
        "printer"
    ],
    "wof:name":"Brunswick Printing & Publish",
    "wof:placetype":"venue"
},
  "geometry": {"coordinates":[-77.84075199999999,36.764402],"type":"Point"}
}