{
  "type": "Feature",
  "properties": {
    "addr:full":"2407 Brentwood Pl Alexandria VA 22306",
    "addr:housenumber":"2407",
    "addr:postcode":"22306",
    "addr:street":"Brentwood Pl",
    "iso:country":"US",
    "sg:address":"2407 Brentwood Pl",
    "sg:city":"Alexandria",
    "sg:classifiers":[
        {
            "category":"Professional",
            "subcategory":"Computer Services",
            "type":"Services"
        }
    ],
    "sg:phone":"+1 703 768 4804",
    "sg:postcode":"22306",
    "sg:province":"VA",
    "sg:tags":[
        "related"
    ],
    "wof:name":"AJW Assoc",
    "wof:placetype":"venue"
},
  "geometry": {"coordinates":[-77.074583,38.748047],"type":"Point"}
}