{
  "type": "Feature",
  "properties": {
    "iso:country":"US",
    "sg:address":"527 J Clyde Morris Blvd",
    "sg:city":"Newport News",
    "sg:classifiers":[
        {
            "category":"Manufacturing",
            "subcategory":"Tools & Machinery",
            "type":"Manufacturing & Wholesale Goods"
        }
    ],
    "sg:phone":"+1 757 591 2439",
    "sg:postcode":"23601",
    "sg:province":"VA",
    "sg:tags":[
        "machine",
        "shop"
    ],
    "wof:name":"Triad Machine Shop",
    "wof:placetype":"venue"
},
  "geometry": {"coordinates":[-76.480982,37.070555],"type":"Point"}
}