{
  "type": "Feature",
  "properties": {
    "addr:full":"2209 Oak Ave Buena Vista VA 24416",
    "addr:housenumber":"2209",
    "addr:postcode":"24416",
    "addr:street":"Oak Ave",
    "iso:country":"US",
    "sg:address":"2209 Oak Ave",
    "sg:city":"Buena Vista",
    "sg:classifiers":[
        {
            "category":"Professional",
            "type":"Services"
        }
    ],
    "sg:phone":"+1 540 261 4942",
    "sg:postcode":"24416",
    "sg:province":"VA",
    "wof:name":"National Majorette Associ",
    "wof:placetype":"venue"
},
  "geometry": {"coordinates":[-79.346889,37.735033],"type":"Point"}
}