{
  "type": "Feature",
  "properties": {
    "addr:full":"1850 Apple Blossom Dr Winchester VA 22601",
    "addr:housenumber":"1850",
    "addr:postcode":"22601",
    "addr:street":"Apple Blossom Dr",
    "iso:country":"US",
    "sg:address":"1850 Apple Blossom Dr",
    "sg:city":"Winchester",
    "sg:classifiers":[
        {
            "category":"Banks & Credit Unions",
            "subcategory":"Financial Services",
            "type":"Services"
        }
    ],
    "sg:phone":"+1 540 535 0294",
    "sg:postcode":"22601",
    "sg:province":"VA",
    "sg:tags":[
        "international",
        "trade"
    ],
    "wof:name":"Spring Trading",
    "wof:placetype":"venue"
},
  "geometry": {"coordinates":[-78.162706,39.167041],"type":"Point"}
}