{
  "type": "Feature",
  "properties": {
    "addr:full":"8516 Bucyrus Ct Manassas VA 20110",
    "addr:postcode":"8516;20110",
    "addr:street":"Bucyrus Ct",
    "iso:country":"US",
    "sg:address":"8516 Bucyrus Ct",
    "sg:city":"Manassas",
    "sg:classifiers":[
        {
            "category":"Building & Trades",
            "subcategory":"Construction",
            "type":"Services"
        }
    ],
    "sg:phone":"+1 703 530 9742",
    "sg:postcode":"20110",
    "sg:province":"VA",
    "sg:tags":[
        "control",
        "erosion"
    ],
    "wof:name":"Hull's Erosion Control",
    "wof:placetype":"venue"
},
  "geometry": {"coordinates":[-77.453757,38.762667],"type":"Point"}
}