{
  "type": "Feature",
  "properties": {
    "addr:full":"355 Rio Rd W Charlottesville VA 22901",
    "addr:housenumber":"355",
    "addr:postcode":"22901",
    "addr:street":"Rio Rd W",
    "iso:country":"US",
    "sg:address":"355 Rio Rd W",
    "sg:city":"Charlottesville",
    "sg:classifiers":[
        {
            "category":"Personal",
            "subcategory":"Beauty Salon",
            "type":"Services"
        }
    ],
    "sg:phone":"+1 434 296 2175",
    "sg:postcode":"22901",
    "sg:province":"VA",
    "sg:tags":[
        "shop"
    ],
    "wof:name":"First Imperssions",
    "wof:placetype":"venue"
},
  "geometry": {"coordinates":[-78.487432,38.084371],"type":"Point"}
}