{
  "type": "Feature",
  "properties": {
    "iso:country":"US",
    "sg:address":"8380 Alban Rd",
    "sg:city":"Springfield",
    "sg:classifiers":[
        {
            "category":"Real Estate",
            "subcategory":"Real Estate Agent",
            "type":"Services"
        }
    ],
    "sg:phone":"+1 703 339 4741",
    "sg:postcode":"22150",
    "sg:province":"VA",
    "wof:name":"P S Business Center Properties",
    "wof:placetype":"venue"
},
  "geometry": {"coordinates":[-77.19892900000001,38.730772],"type":"Point"}
}