{
  "type": "Feature",
  "properties": {
    "addr:full":"13101 Lee Hwy Fairfax VA 22030",
    "addr:housenumber":"13101",
    "addr:postcode":"22030",
    "addr:street":"Lee Hwy",
    "iso:country":"US",
    "sg:address":"13101 Lee Hwy",
    "sg:city":"Fairfax",
    "sg:classifiers":[
        {
            "category":"Building & Trades",
            "subcategory":"Construction",
            "type":"Services"
        }
    ],
    "sg:phone":"+1 703 222 6245",
    "sg:postcode":"22030",
    "sg:province":"VA",
    "sg:tags":[
        "contractor"
    ],
    "wof:name":"MBC Design Build Inc",
    "wof:placetype":"venue"
},
  "geometry": {"coordinates":[-77.399492,38.84018],"type":"Point"}
}