{
  "type": "Feature",
  "properties": {
    "addr:full":"12067 Trumbull Way Reston VA 20190",
    "addr:housenumber":"12067",
    "addr:postcode":"20190",
    "addr:street":"Trumbull Way",
    "iso:country":"US",
    "sg:address":"12067 Trumbull Way",
    "sg:city":"Reston",
    "sg:classifiers":[
        {
            "category":"Professional",
            "subcategory":"Computer Services",
            "type":"Services"
        }
    ],
    "sg:phone":"+1 703 568 3640",
    "sg:postcode":"20190",
    "sg:province":"VA",
    "sg:tags":[
        "application",
        "support",
        "internet"
    ],
    "wof:name":"Gyris Lls",
    "wof:placetype":"venue"
},
  "geometry": {"coordinates":[-77.36293499999999,38.956635],"type":"Point"}
}