{
  "type": "Feature",
  "properties": {
    "iso:country":"US",
    "sg:address":"4149 Stonebridge Lndg",
    "sg:city":"Chesapeake",
    "sg:classifiers":[
        {
            "category":"Restaurant",
            "type":"Food & Drink"
        }
    ],
    "sg:phone":"+1 757 673 0072",
    "sg:postcode":"23321",
    "sg:province":"VA",
    "sg:tags":[
        "seafood"
    ],
    "wof:name":"Scale ODe Whale Restaurant",
    "wof:placetype":"venue"
},
  "geometry": {"coordinates":[-76.40417600000001,36.830556],"type":"Point"}
}