{
  "type": "Feature",
  "properties": {
    "addr:full":"4434 Thomas Nelson Hwy Arrington VA 22922",
    "addr:housenumber":"4434",
    "addr:postcode":"22922",
    "addr:street":"Thomas Nelson Hwy",
    "iso:country":"US",
    "sg:address":"4434 Thomas Nelson Hwy",
    "sg:city":"Arrington",
    "sg:classifiers":[
        {
            "category":"Organizations",
            "subcategory":"Religious Organization",
            "type":"Services"
        }
    ],
    "sg:phone":"+1 434 263 7744",
    "sg:postcode":"22922",
    "sg:province":"VA",
    "wof:name":"Woodland Baptist Church",
    "wof:placetype":"venue"
},
  "geometry": {"coordinates":[-78.93277399999999,37.708304],"type":"Point"}
}