{
  "type": "Feature",
  "properties": {
    "addr:full":"9580 Summer Breeze Rd Warrenton VA 20186",
    "addr:housenumber":"9580",
    "addr:postcode":"20186",
    "addr:street":"Summer Breeze Rd",
    "iso:country":"US",
    "sg:address":"9580 Summer Breeze Rd",
    "sg:city":"Warrenton",
    "sg:classifiers":[
        {
            "category":"Building & Trades",
            "subcategory":"Electrical",
            "type":"Services"
        }
    ],
    "sg:phone":"+1 540 428 1930",
    "sg:postcode":"20186",
    "sg:province":"VA",
    "sg:tags":[
        "electric",
        "contractor"
    ],
    "wof:name":"Residential Electrical Svc Inc",
    "wof:placetype":"venue"
},
  "geometry": {"coordinates":[-77.835317,38.639649],"type":"Point"}
}