{
  "type": "Feature",
  "properties": {
    "addr:full":"10592 Redoubt Rd Manassas VA 20110",
    "addr:housenumber":"10592",
    "addr:postcode":"20110",
    "addr:street":"Redoubt Rd",
    "iso:country":"US",
    "sg:address":"10592 Redoubt Rd",
    "sg:city":"Manassas",
    "sg:classifiers":[
        {
            "category":"Shopping",
            "subcategory":"Bicycles & Sporting Goods",
            "type":"Retail Goods"
        }
    ],
    "sg:phone":"+1 703 365 9941",
    "sg:postcode":"20110",
    "sg:province":"VA",
    "sg:tags":[
        "gun",
        "gunsmith"
    ],
    "wof:name":"Guns & Ammo Warehouse Inc",
    "wof:placetype":"venue"
},
  "geometry": {"coordinates":[-77.526157,38.732011],"type":"Point"}
}