{
  "type": "Feature",
  "properties": {
    "iso:country":"US",
    "sg:address":"11414 Waples Mill Rd",
    "sg:city":"Oakton",
    "sg:classifiers":[
        {
            "category":"Shopping",
            "subcategory":"Computers & Home Electronics",
            "type":"Retail Goods"
        }
    ],
    "sg:phone":"+1 703 218 9880",
    "sg:postcode":"22124",
    "sg:province":"VA",
    "sg:tags":[
        "software"
    ],
    "wof:name":"Landtech Support Svc",
    "wof:placetype":"venue"
},
  "geometry": {"coordinates":[-77.34214299999999,38.877774],"type":"Point"}
}