{
  "type": "Feature",
  "properties": {
    "iso:country":"US",
    "sg:address":"209 Sherwood Forest",
    "sg:city":"Williamsburg",
    "sg:classifiers":[
        {
            "category":"Professional",
            "subcategory":"Business Services",
            "type":"Services"
        }
    ],
    "sg:phone":"+1 757 564 8445",
    "sg:postcode":"23188",
    "sg:province":"VA",
    "wof:name":"Cox Limited Partnership Mary Y",
    "wof:placetype":"venue"
},
  "geometry": {"coordinates":[-76.682255,37.384045],"type":"Point"}
}