{
  "type": "Feature",
  "properties": {
    "addr:full":"4373 Dale Blvd Dale City VA 22193",
    "addr:housenumber":"4373",
    "addr:postcode":"22193",
    "addr:street":"Dale Blvd",
    "iso:country":"US",
    "sg:address":"4373 Dale Blvd",
    "sg:city":"Dale City",
    "sg:classifiers":[
        {
            "category":"Wholesale",
            "subcategory":"Stationery",
            "type":"Manufacturing & Wholesale Goods"
        },
        {
            "category":"Shopping",
            "subcategory":"Stationery & Office Supplies",
            "type":"Retail Goods"
        }
    ],
    "sg:phone":"+1 703 670 2406",
    "sg:postcode":"22193",
    "sg:province":"VA",
    "sg:tags":[
        "school"
    ],
    "wof:name":"Jackie's Teacher Store",
    "wof:placetype":"venue"
},
  "geometry": {"coordinates":[-77.342235,38.649642],"type":"Point"}
}