{
  "type": "Feature",
  "properties": {
    "iso:country":"US",
    "sg:address":"120 S Jefferson St",
    "sg:city":"Richmond",
    "sg:classifiers":[
        {
            "category":"Government",
            "subcategory":"Fire Station",
            "type":"Public Place"
        }
    ],
    "sg:phone":"+1 804 646 8238",
    "sg:postcode":"23220",
    "sg:province":"VA",
    "sg:tags":[
        "department"
    ],
    "wof:name":"Richmond Fire Station",
    "wof:placetype":"venue"
},
  "geometry": {"coordinates":[-77.44767400000001,37.542599],"type":"Point"}
}