{
  "type": "Feature",
  "properties": {
    "iso:country":"US",
    "sg:address":"6545 Oakwood Dr",
    "sg:city":"Falls Church",
    "sg:classifiers":[
        {
            "category":"Health Services",
            "subcategory":"Doctor",
            "type":"Services"
        }
    ],
    "sg:phone":"+1 703 256 3702",
    "sg:postcode":"22041",
    "sg:province":"VA",
    "sg:tags":[
        "clinic",
        "medical"
    ],
    "wof:name":"James A Burwell MD",
    "wof:placetype":"venue"
},
  "geometry": {"coordinates":[-77.170052,38.840709],"type":"Point"}
}