{
  "type": "Feature",
  "properties": {
    "addr:full":"1509 W 3rd St Farmville VA 23901",
    "addr:housenumber":"1509",
    "addr:postcode":"23901",
    "addr:street":"W 3Rd St",
    "iso:country":"US",
    "sg:address":"1509 W 3rd St",
    "sg:city":"Farmville",
    "sg:classifiers":[
        {
            "category":"Health Services",
            "subcategory":"Medical Lab",
            "type":"Services"
        }
    ],
    "sg:phone":"+1 434 315 0306",
    "sg:postcode":"23901",
    "sg:province":"VA",
    "sg:tags":[
        "laboratory"
    ],
    "wof:name":"Open Mri of Southern Virginia",
    "wof:placetype":"venue"
},
  "geometry": {"coordinates":[-78.415778,37.306652],"type":"Point"}
}