{
  "type": "Feature",
  "properties": {
    "addr:full":"3132 Salem Tpke NW Roanoke VA 24017",
    "addr:housenumber":"3132",
    "addr:postcode":"24017",
    "addr:street":"Salem Tpke Nw",
    "iso:country":"US",
    "sg:address":"3132 Salem Tpke NW",
    "sg:city":"Roanoke",
    "sg:classifiers":[
        {
            "category":"Building & Trades",
            "subcategory":"Construction",
            "type":"Services"
        }
    ],
    "sg:phone":"+1 540 985 5655",
    "sg:postcode":"24017",
    "sg:province":"VA",
    "sg:tags":[
        "paving",
        "contractor"
    ],
    "wof:name":"Diamond Paving & Seal Coating",
    "wof:placetype":"venue"
},
  "geometry": {"coordinates":[-79.988231,37.285614],"type":"Point"}
}