{
  "type": "Feature",
  "properties": {
    "iso:country":"US",
    "sg:address":"242 Mustang Trl",
    "sg:city":"Virginia Beach",
    "sg:classifiers":[
        {
            "category":"Professional",
            "subcategory":"Engineering",
            "type":"Services"
        },
        {
            "category":"Real Estate",
            "subcategory":"Surveying",
            "type":"Services"
        }
    ],
    "sg:phone":"+1 757 431 1041",
    "sg:postcode":"23452",
    "sg:province":"VA",
    "sg:tags":[
        "surveyor"
    ],
    "sg:website":"www.wplsite.com",
    "wof:name":"WPL",
    "wof:placetype":"venue"
},
  "geometry": {"coordinates":[-76.067273,36.840003],"type":"Point"}
}