{
  "type": "Feature",
  "properties": {
    "addr:full":"6161 Plank Rd Fredericksburg VA 22407",
    "addr:housenumber":"6161",
    "addr:postcode":"22407",
    "addr:street":"Plank Rd",
    "iso:country":"US",
    "sg:address":"6161 Plank Rd",
    "sg:city":"Fredericksburg",
    "sg:classifiers":[
        {
            "category":"Home & Garden",
            "subcategory":"Garden Supply",
            "type":"Retail Goods"
        }
    ],
    "sg:phone":"+1 540 786 1719",
    "sg:postcode":"22407",
    "sg:province":"VA",
    "wof:name":"Countryside Nursery & Grdn Ctr",
    "wof:placetype":"venue"
},
  "geometry": {"coordinates":[-77.59529000000001,38.295463],"type":"Point"}
}