{
  "type": "Feature",
  "properties": {
    "iso:country":"US",
    "sg:address":"13452 Silver Hill Rd",
    "sg:city":"Sumerduck",
    "sg:classifiers":[
        {
            "category":"Wholesale",
            "subcategory":"Durable Goods & Equipment",
            "type":"Manufacturing & Wholesale Goods"
        }
    ],
    "sg:phone":"+1 540 439 4657",
    "sg:postcode":"22742",
    "sg:province":"VA",
    "wof:name":"Angell & Sons Firewood Dlvry",
    "wof:placetype":"venue"
},
  "geometry": {"coordinates":[-77.695916,38.475442],"type":"Point"}
}