{
  "type": "Feature",
  "properties": {
    "addr:full":"510 E Main St Charlottesville VA 22902",
    "addr:housenumber":"510",
    "addr:postcode":"22902",
    "addr:street":"E Main St",
    "iso:country":"US",
    "sg:address":"510 E Main St",
    "sg:city":"Charlottesville",
    "sg:classifiers":[
        {
            "category":"Wholesale",
            "subcategory":"Stationery",
            "type":"Manufacturing & Wholesale Goods"
        }
    ],
    "sg:phone":"+1 434 295 0384",
    "sg:postcode":"22902",
    "sg:province":"VA",
    "sg:tags":[
        "card"
    ],
    "wof:name":"Lee's Hallmark Card Shop",
    "wof:placetype":"venue"
},
  "geometry": {"coordinates":[-78.47840100000001,38.029701],"type":"Point"}
}