{
  "type": "Feature",
  "properties": {
    "addr:full":"410 N Church St Woodstock VA 22664",
    "addr:housenumber":"410",
    "addr:postcode":"22664",
    "addr:street":"N Church St",
    "iso:country":"US",
    "sg:address":"410 N Church St",
    "sg:city":"Woodstock",
    "sg:classifiers":[
        {
            "category":"Real Estate",
            "subcategory":"Real Estate Agent",
            "type":"Services"
        }
    ],
    "sg:phone":"+1 540 459 2603",
    "sg:postcode":"22664",
    "sg:province":"VA",
    "wof:name":"Fdf Properties LLC",
    "wof:placetype":"venue"
},
  "geometry": {"coordinates":[-78.50076900000001,38.884834],"type":"Point"}
}