{
  "type": "Feature",
  "properties": {
    "addr:full":"220 High St Charlottesville VA 22902",
    "addr:housenumber":"220",
    "addr:postcode":"22902",
    "addr:street":"High St",
    "iso:country":"US",
    "sg:address":"220 High St",
    "sg:city":"Charlottesville",
    "sg:classifiers":[
        {
            "category":"Real Estate",
            "subcategory":"Surveying",
            "type":"Services"
        }
    ],
    "sg:phone":"+1 434 296 6942",
    "sg:postcode":"22902",
    "sg:province":"VA",
    "sg:tags":[
        "surveyor"
    ],
    "wof:name":"KIRK Hughes & Assoc",
    "wof:placetype":"venue"
},
  "geometry": {"coordinates":[-78.481745,38.033305],"type":"Point"}
}