{
  "type": "Feature",
  "properties": {
    "addr:full":"5725 Edsall Rd Alexandria VA 22304",
    "addr:housenumber":"5725",
    "addr:postcode":"22304",
    "addr:street":"Edsall Rd",
    "iso:country":"US",
    "sg:address":"5725 Edsall Rd",
    "sg:city":"Alexandria",
    "sg:classifiers":[
        {
            "category":"Banks & Credit Unions",
            "subcategory":"Financial Services",
            "type":"Services"
        },
        {
            "category":"Banks & Credit Unions",
            "subcategory":"Atm",
            "type":"Services"
        },
        {
            "category":"Food & Beverages",
            "subcategory":"Groceries & Convenience Stores",
            "type":"Retail Goods"
        }
    ],
    "sg:phone":"+1 703 461 1904",
    "sg:postcode":"22304",
    "sg:province":"VA",
    "sg:tags":[
        "money",
        "location",
        "order"
    ],
    "sg:website":"http://www.7-eleven.com",
    "wof:name":"7-Eleven",
    "wof:placetype":"venue"
},
  "geometry": {"coordinates":[-77.1313,38.807658],"type":"Point"}
}