{
  "type": "Feature",
  "properties": {
    "addr:full":"611 W 24th St Richmond VA 23225",
    "addr:housenumber":"611",
    "addr:postcode":"23225",
    "addr:street":"W 24Th St",
    "iso:country":"US",
    "sg:address":"611 W 24th St",
    "sg:city":"Richmond",
    "sg:classifiers":[
        {
            "category":"Manufacturing",
            "subcategory":"Wood Products",
            "type":"Manufacturing & Wholesale Goods"
        },
        {
            "category":"Home & Garden",
            "subcategory":"Furniture",
            "type":"Retail Goods"
        }
    ],
    "sg:phone":"+1 804 231 1289",
    "sg:postcode":"23225",
    "sg:province":"VA",
    "sg:tags":[
        "manufacturer",
        "cabinets-wholesale",
        "cabinet"
    ],
    "wof:name":"Cabco Cabinets & Fixture Co",
    "wof:placetype":"venue"
},
  "geometry": {"coordinates":[-77.458307,37.521573],"type":"Point"}
}