{
  "type": "Feature",
  "properties": {
    "addr:full":"12388 Warwick Blvd Newport News VA 23606",
    "addr:housenumber":"12388",
    "addr:postcode":"23606",
    "addr:street":"Warwick Blvd",
    "iso:country":"US",
    "sg:address":"12388 Warwick Blvd",
    "sg:city":"Newport News",
    "sg:classifiers":[
        {
            "category":"Manufacturing",
            "subcategory":"Metals",
            "type":"Manufacturing & Wholesale Goods"
        },
        {
            "category":"Building & Trades",
            "subcategory":"Construction",
            "type":"Services"
        }
    ],
    "sg:phone":"+1 757 595 8807",
    "sg:postcode":"23606",
    "sg:province":"VA",
    "sg:tags":[
        "painting",
        "industrial",
        "coating"
    ],
    "wof:name":"Phillips Industrial Service",
    "wof:placetype":"venue"
},
  "geometry": {"coordinates":[-76.49224,37.06724],"type":"Point"}
}