{
  "type": "Feature",
  "properties": {
    "iso:country":"US",
    "sg:address":"33 James Falls Dr",
    "sg:city":"Richmond",
    "sg:classifiers":[
        {
            "category":"Government",
            "subcategory":"Office",
            "type":"Public Place"
        }
    ],
    "sg:phone":"+1 804 828 2787",
    "sg:postcode":"23221",
    "sg:province":"VA",
    "sg:tags":[
        "educator"
    ],
    "wof:name":"Richard Eric Toscan",
    "wof:placetype":"venue"
},
  "geometry": {"coordinates":[-77.48769,37.538748],"type":"Point"}
}