{
  "type": "Feature",
  "properties": {
    "iso:country":"US",
    "sg:address":"316 N Underwood St",
    "sg:city":"Falls Church",
    "sg:classifiers":[
        {
            "category":"Professional",
            "subcategory":"Management & Consulting",
            "type":"Services"
        }
    ],
    "sg:phone":"+1 703 536 2439",
    "sg:postcode":"22046",
    "sg:province":"VA",
    "sg:tags":[
        "consultant",
        "educational"
    ],
    "wof:name":"Joel Kuipers",
    "wof:placetype":"venue"
},
  "geometry": {"coordinates":[-77.157348,38.881047],"type":"Point"}
}