{
  "type": "Feature",
  "properties": {
    "addr:full":"11360 Manor St Exmore VA 23350",
    "addr:housenumber":"11360",
    "addr:postcode":"23350",
    "addr:street":"Manor St",
    "iso:country":"US",
    "sg:address":"11360 Manor St",
    "sg:city":"Exmore",
    "sg:classifiers":[
        {
            "category":"Real Estate",
            "subcategory":"Developer",
            "type":"Services"
        }
    ],
    "sg:phone":"+1 757 442 3797",
    "sg:postcode":"23350",
    "sg:province":"VA",
    "wof:name":"New Road Community Dev Group",
    "wof:placetype":"venue"
},
  "geometry": {"coordinates":[-75.83213600000001,37.533115],"type":"Point"}
}