{
  "type": "Feature",
  "properties": {
    "iso:country":"US",
    "sg:address":"306 Turner Rd",
    "sg:city":"Richmond",
    "sg:classifiers":[
        {
            "category":"Recreation",
            "type":"Entertainment"
        },
        {
            "category":"Education",
            "subcategory":"Special Training",
            "type":"Public Place"
        }
    ],
    "sg:phone":"+1 804 745 4060",
    "sg:postcode":"23225",
    "sg:province":"VA",
    "sg:tags":[
        "karate",
        "judo",
        "instr"
    ],
    "wof:name":"Chesterfield Kung Fu Academy",
    "wof:placetype":"venue"
},
  "geometry": {"coordinates":[-77.53665599999999,37.497479],"type":"Point"}
}