{
  "type": "Feature",
  "properties": {
    "addr:full":"3605 Barcroft View Ter Falls Church VA 22041",
    "addr:housenumber":"3605",
    "addr:postcode":"22041",
    "addr:street":"Barcroft View Ter",
    "iso:country":"US",
    "sg:address":"3605 Barcroft View Ter",
    "sg:city":"Falls Church",
    "sg:classifiers":[
        {
            "category":"Education",
            "subcategory":"Special Training",
            "type":"Public Place"
        }
    ],
    "sg:phone":"+1 703 933 7022",
    "sg:postcode":"22041",
    "sg:province":"VA",
    "sg:tags":[
        "dari",
        "instructor",
        "language"
    ],
    "wof:name":"Atmar Nafisa",
    "wof:placetype":"venue"
},
  "geometry": {"coordinates":[-77.13734700000001,38.846725],"type":"Point"}
}