{
  "type": "Feature",
  "properties": {
    "addr:full":"19 N Rowland St Richmond VA 23220",
    "addr:housenumber":"19",
    "addr:postcode":"23220",
    "addr:street":"N Rowland St",
    "iso:country":"US",
    "sg:address":"19 N Rowland St",
    "sg:city":"Richmond",
    "sg:classifiers":[
        {
            "category":"Building & Trades",
            "subcategory":"Landscaping Services",
            "type":"Services"
        }
    ],
    "sg:phone":"+1 804 358 7898",
    "sg:postcode":"23220",
    "sg:province":"VA",
    "sg:tags":[
        "tree"
    ],
    "wof:name":"A B C Tree Service",
    "wof:placetype":"venue"
},
  "geometry": {"coordinates":[-77.46698600000001,37.549867],"type":"Point"}
}