{
  "type": "Feature",
  "properties": {
    "iso:country":"US",
    "sg:address":"8804 Patterson Ave",
    "sg:city":"Richmond",
    "sg:classifiers":[
        {
            "category":"Health Services",
            "subcategory":"Doctor",
            "type":"Services"
        }
    ],
    "sg:phone":"+1 804 754 2125",
    "sg:postcode":"23229",
    "sg:province":"VA",
    "wof:name":"Cruickshanks RE DDS Office",
    "wof:placetype":"venue"
},
  "geometry": {"coordinates":[-77.573257,37.595192],"type":"Point"}
}