{
  "type": "Feature",
  "properties": {
    "addr:full":"9 Forrest St Alexandria VA 22305",
    "addr:housenumber":"9",
    "addr:postcode":"22305",
    "addr:street":"Forrest St",
    "iso:country":"US",
    "sg:address":"9 Forrest St",
    "sg:city":"Alexandria",
    "sg:classifiers":[
        {
            "category":"Professional",
            "subcategory":"Computer Services",
            "type":"Services"
        }
    ],
    "sg:phone":"+1 703 969 6404",
    "sg:postcode":"22305",
    "sg:province":"VA",
    "sg:tags":[
        "development",
        "security",
        "network",
        "research"
    ],
    "wof:name":"Pikewerks Corp",
    "wof:placetype":"venue"
},
  "geometry": {"coordinates":[-77.062116,38.830026],"type":"Point"}
}