{
  "type": "Feature",
  "properties": {
    "iso:country":"US",
    "sg:address":"130 Park St SE",
    "sg:city":"Vienna",
    "sg:classifiers":[
        {
            "category":"Professional",
            "subcategory":"Engineering",
            "type":"Services"
        },
        {
            "category":"Professional",
            "subcategory":"Management & Consulting",
            "type":"Services"
        }
    ],
    "sg:phone":"+1 703 255 1300",
    "sg:postcode":"22180",
    "sg:province":"VA",
    "sg:tags":[
        "engineer"
    ],
    "wof:name":"David Miller & Associates",
    "wof:placetype":"venue"
},
  "geometry": {"coordinates":[-77.261321,38.902515],"type":"Point"}
}