{
  "type": "Feature",
  "properties": {
    "iso:country":"US",
    "sg:address":"4611 Duke St",
    "sg:city":"Alexandria",
    "sg:classifiers":[
        {
            "category":"Shopping",
            "subcategory":"Clothing, Apparel, & Fashions",
            "type":"Retail Goods"
        },
        {
            "category":"Retail",
            "subcategory":"Laundry & Dry Cleaning",
            "type":"Services"
        }
    ],
    "sg:phone":"+1 703 751 1223",
    "sg:postcode":"22304",
    "sg:province":"VA",
    "sg:tags":[
        "cleaner",
        "tailor"
    ],
    "wof:name":"Duke Cleaners",
    "wof:placetype":"venue"
},
  "geometry": {"coordinates":[-77.111625,38.812039],"type":"Point"}
}