{
  "type": "Feature",
  "properties": {
    "iso:country":"US",
    "sg:address":"4250 Stepney Dr",
    "sg:city":"Gainesville",
    "sg:classifiers":[
        {
            "category":"Professional",
            "subcategory":"Management & Consulting",
            "type":"Services"
        }
    ],
    "sg:phone":"+1 703 754 9160",
    "sg:postcode":"20155",
    "sg:province":"VA",
    "wof:name":"Turnstone Technologies Inc",
    "wof:placetype":"venue"
},
  "geometry": {"coordinates":[-77.614677,38.865778],"type":"Point"}
}