{
  "type": "Feature",
  "properties": {
    "addr:full":"308 Orange Ave NE Roanoke VA 24016",
    "addr:housenumber":"308",
    "addr:postcode":"24016",
    "addr:street":"Orange Ave Ne",
    "iso:country":"US",
    "sg:address":"308 Orange Ave NE",
    "sg:city":"Roanoke",
    "sg:classifiers":[
        {
            "category":"Travel",
            "subcategory":"Hotels & Motels",
            "type":"Entertainment"
        }
    ],
    "sg:phone":"+1 540 343 2413",
    "sg:postcode":"24016",
    "sg:province":"VA",
    "sg:tags":[
        "operation"
    ],
    "wof:name":"Econo Lodge",
    "wof:placetype":"venue"
},
  "geometry": {"coordinates":[-79.934394,37.282414],"type":"Point"}
}