{
  "type": "Feature",
  "properties": {
    "iso:country":"US",
    "sg:address":"1316 E Cary St",
    "sg:city":"Richmond",
    "sg:classifiers":[
        {
            "category":"Professional",
            "type":"Services"
        }
    ],
    "sg:phone":"+1 804 644 3622",
    "sg:postcode":"23219",
    "sg:province":"VA",
    "sg:tags":[
        "establishment"
    ],
    "wof:name":"Narcello Balboa",
    "wof:placetype":"venue"
},
  "geometry": {"coordinates":[-77.433432,37.535263],"type":"Point"}
}