{
  "type": "Feature",
  "properties": {
    "addr:full":"6 Center Dr Norfolk VA 23502",
    "addr:housenumber":"6",
    "addr:postcode":"23502",
    "addr:street":"Center Dr",
    "iso:country":"US",
    "sg:address":"6 Center Dr",
    "sg:city":"Norfolk",
    "sg:classifiers":[
        {
            "category":"Manufacturing",
            "subcategory":"Printing",
            "type":"Manufacturing & Wholesale Goods"
        }
    ],
    "sg:phone":"+1 757 455 9580",
    "sg:postcode":"23502",
    "sg:province":"VA",
    "sg:tags":[
        "directory",
        "publisher"
    ],
    "wof:name":"Harris Publishing Nat Tele",
    "wof:placetype":"venue"
},
  "geometry": {"coordinates":[-76.18970899999999,36.846488],"type":"Point"}
}