{
  "type": "Feature",
  "properties": {
    "iso:country":"US",
    "sg:address":"3858 Green Spring Ave NW",
    "sg:city":"Roanoke",
    "sg:classifiers":[
        {
            "category":"Organizations",
            "subcategory":"Religious Organization",
            "type":"Services"
        }
    ],
    "sg:phone":"+1 540 344 6343",
    "sg:postcode":"24017",
    "sg:province":"VA",
    "sg:tags":[
        "clergy"
    ],
    "wof:name":"Frank W Feather",
    "wof:placetype":"venue"
},
  "geometry": {"coordinates":[-80.0051,37.284324],"type":"Point"}
}