{
  "type": "Feature",
  "properties": {
    "iso:country":"US",
    "sg:address":"1 High St",
    "sg:city":"Portsmouth",
    "sg:classifiers":[
        {
            "category":"Banks & Credit Unions",
            "subcategory":"Bank",
            "type":"Services"
        }
    ],
    "sg:phone":"+1 757 397 3777",
    "sg:postcode":"23704",
    "sg:province":"VA",
    "sg:tags":[
        "mortgage"
    ],
    "wof:name":"1st Metropolitan Mortage",
    "wof:placetype":"venue"
},
  "geometry": {"coordinates":[-76.296888,36.835422],"type":"Point"}
}