{
  "type": "Feature",
  "properties": {
    "addr:full":"2374 Goodrich Fork Rd Wakefield VA 23888",
    "addr:housenumber":"2374",
    "addr:postcode":"23888",
    "addr:street":"Goodrich Fork Rd",
    "iso:country":"US",
    "sg:address":"2374 Goodrich Fork Rd",
    "sg:city":"Wakefield",
    "sg:phone":"+1 757 899 4421",
    "sg:postcode":"23888",
    "sg:province":"VA",
    "sg:tags":[
        "farm",
        "field",
        "crop"
    ],
    "wof:name":"Wayne A Lowe",
    "wof:placetype":"venue"
},
  "geometry": {"coordinates":[-76.902101,36.975008],"type":"Point"}
}