{
  "type": "Feature",
  "properties": {
    "iso:country":"US",
    "sg:address":"965 Honest Point Rd",
    "sg:city":"Lottsburg",
    "sg:classifiers":[
        {
            "category":"Restaurant",
            "type":"Food & Drink"
        },
        {
            "category":"Food & Beverages",
            "subcategory":"Meat & Fish",
            "type":"Retail Goods"
        }
    ],
    "sg:phone":"+1 804 529 6837",
    "sg:postcode":"22511",
    "sg:province":"VA",
    "sg:tags":[
        "seafood",
        "seafood-wholesale"
    ],
    "wof:name":"Keyser Brother's Inc",
    "wof:placetype":"venue"
},
  "geometry": {"coordinates":[-76.47803999999999,37.986961],"type":"Point"}
}