{
  "type": "Feature",
  "properties": {
    "iso:country":"US",
    "sg:address":"2045 N 15th St.",
    "sg:city":"Arlington",
    "sg:classifiers":[
        {
            "category":"Professional",
            "type":"Services"
        },
        {
            "category":"Retail",
            "subcategory":"Repair Shop",
            "type":"Services"
        },
        {
            "category":"Professional",
            "subcategory":"Detective & Security Services",
            "type":"Services"
        }
    ],
    "sg:phone":"+1 703 243 6690",
    "sg:postcode":"22201",
    "sg:province":"VA",
    "sg:tags":[
        "tracing",
        "bond",
        "bail",
        "skip"
    ],
    "sg:website":"www.marcusbailbond.com",
    "wof:name":"Marcus Bail Bond",
    "wof:placetype":"venue"
},
  "geometry": {"coordinates":[-77.084203,38.890949],"type":"Point"}
}