{
  "type": "Feature",
  "properties": {
    "addr:full":"15219 Edgegrove Rd Purcellville VA 20132",
    "addr:postcode":"15219;20132",
    "addr:street":"Edgegrove Rd",
    "iso:country":"US",
    "sg:address":"15219 Edgegrove Rd",
    "sg:city":"Purcellville",
    "sg:classifiers":[
        {
            "category":"Insurance",
            "subcategory":"Insurance Agent",
            "type":"Services"
        }
    ],
    "sg:phone":"+1 540 668 7250",
    "sg:postcode":"20132",
    "sg:province":"VA",
    "wof:name":"Sid Patterson Insurance",
    "wof:placetype":"venue"
},
  "geometry": {"coordinates":[-77.75621700000001,39.196501],"type":"Point"}
}