{
  "type": "Feature",
  "properties": {
    "iso:country":"US",
    "sg:address":"406 N Patrick St",
    "sg:city":"Alexandria",
    "sg:classifiers":[
        {
            "category":"Restaurant",
            "type":"Food & Drink"
        }
    ],
    "sg:phone":"+1 703 836 6661",
    "sg:postcode":"22314",
    "sg:province":"VA",
    "wof:name":"Christie's Cafe",
    "wof:placetype":"venue"
},
  "geometry": {"coordinates":[-77.04939,38.809983],"type":"Point"}
}