{
  "type": "Feature",
  "properties": {
    "addr:full":"13002 Grey Friars Pl Herndon VA 20171",
    "addr:housenumber":"13002",
    "addr:postcode":"20171",
    "addr:street":"Grey Friars Pl",
    "iso:country":"US",
    "sg:address":"13002 Grey Friars Pl",
    "sg:city":"Herndon",
    "sg:classifiers":[
        {
            "category":"Professional",
            "subcategory":"Management & Consulting",
            "type":"Services"
        }
    ],
    "sg:phone":"+1 703 758 1081",
    "sg:postcode":"20171",
    "sg:province":"VA",
    "sg:tags":[
        "consultant",
        "business"
    ],
    "wof:name":"Sensa Solutions",
    "wof:placetype":"venue"
},
  "geometry": {"coordinates":[-77.399208,38.913405],"type":"Point"}
}