{
  "type": "Feature",
  "properties": {
    "iso:country":"US",
    "sg:address":"3311 Mill Race Rd",
    "sg:city":"Richmond",
    "sg:classifiers":[
        {
            "category":"Retail",
            "subcategory":"Laundry & Dry Cleaning",
            "type":"Services"
        }
    ],
    "sg:phone":"+1 804 714 0485",
    "sg:postcode":"23234",
    "sg:province":"VA",
    "wof:name":"A Touch of Class Carpet Clng",
    "wof:placetype":"venue"
},
  "geometry": {"coordinates":[-77.455951,37.453309],"type":"Point"}
}