{
  "type": "Feature",
  "properties": {
    "addr:full":"100 Ashwood Pl Forest VA 24541",
    "addr:housenumber":"100",
    "addr:postcode":"24541",
    "addr:street":"Ashwood Pl",
    "iso:country":"US",
    "sg:address":"100 Ashwood Pl",
    "sg:city":"Forest",
    "sg:classifiers":[
        {
            "category":"Education",
            "subcategory":"School",
            "type":"Public Place"
        }
    ],
    "sg:phone":"+1 434 525 6630",
    "sg:postcode":"24541",
    "sg:province":"VA",
    "wof:name":"Forest Middle School",
    "wof:placetype":"venue"
},
  "geometry": {"coordinates":[-79.46060799999999,36.560067],"type":"Point"}
}