{
  "type": "Feature",
  "properties": {
    "iso:country":"US",
    "sg:address":"6716 Patterson Ave",
    "sg:city":"Richmond",
    "sg:classifiers":[
        {
            "category":"Real Estate",
            "subcategory":"Real Estate Agent",
            "type":"Services"
        }
    ],
    "sg:phone":"+1 804 288 9108",
    "sg:postcode":"23226",
    "sg:province":"VA",
    "wof:name":"LAS Realty",
    "wof:placetype":"venue"
},
  "geometry": {"coordinates":[-77.527551,37.58833],"type":"Point"}
}