{
  "type": "Feature",
  "properties": {
    "iso:country":"US",
    "sg:address":"300 N Main St",
    "sg:city":"Hopewell",
    "sg:classifiers":[
        {
            "category":"Government",
            "subcategory":"Police Station",
            "type":"Public Place"
        }
    ],
    "sg:phone":"+1 804 541 2275",
    "sg:postcode":"23860",
    "sg:province":"VA",
    "sg:tags":[
        "department"
    ],
    "wof:name":"Hopewell Police Dept",
    "wof:placetype":"venue"
},
  "geometry": {"coordinates":[-77.287357,37.303889],"type":"Point"}
}