{
  "type": "Feature",
  "properties": {
    "addr:full":"4000 BURKE STATION RD FAIRFAX VA 22032",
    "addr:housenumber":"4000",
    "addr:postcode":"22032",
    "addr:street":"Burke Station Rd",
    "iso:country":"US",
    "sg:address":"4000 BURKE STATION RD",
    "sg:city":"FAIRFAX",
    "sg:classifiers":[
        {
            "category":"Animal Shelter",
            "type":"Public Place"
        },
        {
            "category":"Retail",
            "subcategory":"Veterinary Services",
            "type":"Services"
        },
        {
            "category":"Retail",
            "subcategory":"Pet Boarding",
            "type":"Services"
        }
    ],
    "sg:phone":"+1 703 273 5110",
    "sg:postcode":"22032",
    "sg:province":"VA",
    "sg:tags":[
        "hospital",
        "specialty",
        "clinic",
        "veterinarian",
        "kennel"
    ],
    "sg:website":"http://lrvc1.com",
    "wof:name":"Little River Veterinary Clinic",
    "wof:placetype":"venue"
},
  "geometry": {"coordinates":[-77.288071,38.843231],"type":"Point"}
}