{
  "type": "Feature",
  "properties": {
    "addr:full":"7202 Brook Rd Richmond VA 23227",
    "addr:housenumber":"7202",
    "addr:postcode":"23227",
    "addr:street":"Brook Rd",
    "iso:country":"US",
    "sg:address":"7202 Brook Rd",
    "sg:city":"Richmond",
    "sg:classifiers":[
        {
            "category":"Taxi",
            "type":"Transportation"
        }
    ],
    "sg:phone":"+1 804 266 0328",
    "sg:postcode":"23227",
    "sg:province":"VA",
    "wof:name":"Old Dominion Taxa Cab",
    "wof:placetype":"venue"
},
  "geometry": {"coordinates":[-77.457465,37.6206],"type":"Point"}
}