{
  "type": "Feature",
  "properties": {
    "iso:country":"US",
    "sg:address":"301 Dabbs House Rd # 228",
    "sg:city":"Richmond",
    "sg:classifiers":[
        {
            "category":"Personal",
            "subcategory":"Nail Salon",
            "type":"Services"
        }
    ],
    "sg:phone":"+1 804 783 2008",
    "sg:postcode":"23223",
    "sg:province":"VA",
    "wof:name":"Selma Nails",
    "wof:placetype":"venue"
},
  "geometry": {"coordinates":[-77.381699,37.54137],"type":"Point"}
}