{
  "type": "Feature",
  "properties": {
    "addr:full":"1809 Plaza Dr Winchester VA 22601",
    "addr:housenumber":"1809",
    "addr:postcode":"22601",
    "addr:street":"Plaza Dr",
    "iso:country":"US",
    "sg:address":"1809 Plaza Dr",
    "sg:city":"Winchester",
    "sg:classifiers":[
        {
            "category":"Health Services",
            "subcategory":"Chiropractor",
            "type":"Services"
        }
    ],
    "sg:phone":"+1 540 667 7300",
    "sg:postcode":"22601",
    "sg:province":"VA",
    "wof:name":"Kotkin Chiropractic Ctr",
    "wof:placetype":"venue"
},
  "geometry": {"coordinates":[-78.174972,39.166337],"type":"Point"}
}