{
  "type": "Feature",
  "properties": {
    "addr:full":"1390 Old Chain Bridge Rd Mc Lean VA 22101",
    "addr:housenumber":"1390",
    "addr:postcode":"22101",
    "addr:street":"Old Chain Bridge Rd Mc Lean",
    "iso:country":"US",
    "sg:address":"1390 Old Chain Bridge Rd",
    "sg:city":"Mc Lean",
    "sg:classifiers":[
        {
            "category":"Organizations",
            "subcategory":"Membership Organization",
            "type":"Services"
        }
    ],
    "sg:phone":"+1 703 757 4435",
    "sg:postcode":"22101",
    "sg:province":"VA",
    "wof:name":"Societas",
    "wof:placetype":"venue"
},
  "geometry": {"coordinates":[-77.17585200000001,38.937306],"type":"Point"}
}