{
  "type": "Feature",
  "properties": {
    "iso:country":"US",
    "sg:address":"1020 Fishermans Rd",
    "sg:city":"Norfolk",
    "sg:classifiers":[
        {
            "category":"Banks & Credit Unions",
            "subcategory":"Bank",
            "type":"Services"
        },
        {
            "category":"Banks & Credit Unions",
            "subcategory":"Financial Services",
            "type":"Services"
        }
    ],
    "sg:phone":"+1 757 480 7520",
    "sg:postcode":"23503",
    "sg:province":"VA",
    "sg:tags":[
        "commercial",
        "financing",
        "saving",
        "loan"
    ],
    "sg:website":"http://www.bbt.com",
    "wof:name":"BB & T",
    "wof:placetype":"venue"
},
  "geometry": {"coordinates":[-76.24306900000001,36.929867],"type":"Point"}
}