{
  "type": "Feature",
  "properties": {
    "addr:full":"9018 W Broad St Richmond VA 23294",
    "addr:housenumber":"9018",
    "addr:postcode":"23294",
    "addr:street":"W Broad St",
    "iso:country":"US",
    "sg:address":"9018 W Broad St",
    "sg:city":"Richmond",
    "sg:classifiers":[
        {
            "category":"Retail",
            "subcategory":"Repair Shop",
            "type":"Services"
        }
    ],
    "sg:phone":"+1 804 747 8249",
    "sg:postcode":"23294",
    "sg:province":"VA",
    "sg:tags":[
        "appliance",
        "household",
        "electrical"
    ],
    "wof:name":"Hoover Company",
    "wof:placetype":"venue"
},
  "geometry": {"coordinates":[-77.549342,37.636337],"type":"Point"}
}