{
  "type": "Feature",
  "properties": {
    "addr:full":"5948 Founders Hill Dr Alexandria VA 22310",
    "addr:housenumber":"5948",
    "addr:postcode":"22310",
    "addr:street":"Founders Hill Dr",
    "iso:country":"US",
    "sg:address":"5948 Founders Hill Dr",
    "sg:city":"Alexandria",
    "sg:classifiers":[
        {
            "category":"Professional",
            "subcategory":"Business Services",
            "type":"Services"
        }
    ],
    "sg:phone":"+1 703 313 9748",
    "sg:postcode":"22310",
    "sg:province":"VA",
    "wof:name":"Mason Enterprises LLC",
    "wof:placetype":"venue"
},
  "geometry": {"coordinates":[-77.140061,38.789254],"type":"Point"}
}