{
  "type": "Feature",
  "properties": {
    "iso:country":"US",
    "sg:address":"916 Main St",
    "sg:city":"Altavista",
    "sg:classifiers":[
        {
            "category":"Home & Garden",
            "subcategory":"Household Appliances",
            "type":"Retail Goods"
        }
    ],
    "sg:phone":"+1 434 369 6770",
    "sg:postcode":"24517",
    "sg:province":"VA",
    "sg:tags":[
        "television"
    ],
    "wof:name":"Virginia TV & Appliance Co",
    "wof:placetype":"venue"
},
  "geometry": {"coordinates":[-79.284031,37.11296],"type":"Point"}
}