{
  "type": "Feature",
  "properties": {
    "iso:country":"US",
    "sg:address":"6111 Knollwood Dr",
    "sg:city":"Falls Church",
    "sg:classifiers":[
        {
            "category":"Education",
            "subcategory":"School",
            "type":"Public Place"
        }
    ],
    "sg:phone":"+1 703 575 6800",
    "sg:postcode":"22041",
    "sg:province":"VA",
    "wof:name":"Bailey's Elementary School",
    "wof:placetype":"venue"
},
  "geometry": {"coordinates":[-77.14430299999999,38.85245],"type":"Point"}
}