{
  "type": "Feature",
  "properties": {
    "addr:full":"2098 River Rd Hayes VA 23072",
    "addr:housenumber":"2098",
    "addr:postcode":"23072",
    "addr:street":"River Rd",
    "iso:country":"US",
    "sg:address":"2098 River Rd",
    "sg:city":"Hayes",
    "sg:classifiers":[
        {
            "category":"Building & Trades",
            "subcategory":"Construction",
            "type":"Services"
        }
    ],
    "sg:phone":"+1 804 642 6013",
    "sg:postcode":"23072",
    "sg:province":"VA",
    "sg:tags":[
        "insulation",
        "heat",
        "contractor"
    ],
    "wof:name":"Demco Construction Inc",
    "wof:placetype":"venue"
},
  "geometry": {"coordinates":[-76.505191,37.269978],"type":"Point"}
}