{
  "type": "Feature",
  "properties": {
    "iso:country":"US",
    "sg:address":"2114 Ballentine Blvd",
    "sg:city":"Norfolk",
    "sg:classifiers":[
        {
            "category":"Manufacturing",
            "subcategory":"Printing",
            "type":"Manufacturing & Wholesale Goods"
        }
    ],
    "sg:phone":"+1 757 625 7782",
    "sg:postcode":"23504",
    "sg:province":"VA",
    "sg:tags":[
        "commercial",
        "lithographic"
    ],
    "wof:name":"Star Printing Co Inc",
    "wof:placetype":"venue"
},
  "geometry": {"coordinates":[-76.24992399999999,36.86111],"type":"Point"}
}