{
  "type": "Feature",
  "properties": {
    "addr:full":"2685 Jacks Mountain Rd Gladehill VA 24092",
    "addr:housenumber":"2685",
    "addr:postcode":"24092",
    "addr:street":"Jacks Mountain Rd",
    "iso:country":"US",
    "sg:address":"2685 Jacks Mountain Rd",
    "sg:city":"Gladehill",
    "sg:phone":"+1 540 576 2843",
    "sg:postcode":"24092",
    "sg:province":"VA",
    "sg:tags":[
        "farm",
        "corn"
    ],
    "wof:name":"Ned Cundiff",
    "wof:placetype":"venue"
},
  "geometry": {"coordinates":[-79.714686,36.959464],"type":"Point"}
}