{
  "type": "Feature",
  "properties": {
    "iso:country":"US",
    "sg:address":"133 Kings Way N",
    "sg:city":"Hampton",
    "sg:classifiers":[
        {
            "category":"Professional",
            "subcategory":"Engineering",
            "type":"Services"
        }
    ],
    "sg:phone":"+1 757 224 0105",
    "sg:postcode":"23669",
    "sg:province":"VA",
    "sg:tags":[
        "engineer"
    ],
    "wof:name":"Technical Services Group",
    "wof:placetype":"venue"
},
  "geometry": {"coordinates":[-76.344748,37.027266],"type":"Point"}
}