{
  "type": "Feature",
  "properties": {
    "addr:full":"120 Holdsworth Rd Williamsburg VA 23185",
    "addr:housenumber":"120",
    "addr:postcode":"23185",
    "addr:street":"Holdsworth Rd",
    "iso:country":"US",
    "sg:address":"120 Holdsworth Rd",
    "sg:city":"Williamsburg",
    "sg:classifiers":[
        {
            "category":"Professional",
            "subcategory":"Accounting & Tax Preparation",
            "type":"Services"
        }
    ],
    "sg:phone":"+1 757 229 9330",
    "sg:postcode":"23185",
    "sg:province":"VA",
    "sg:tags":[
        "return"
    ],
    "wof:name":"James E Smith Tax Consult",
    "wof:placetype":"venue"
},
  "geometry": {"coordinates":[-76.672943,37.243555],"type":"Point"}
}