{
  "type": "Feature",
  "properties": {
    "addr:full":"1750 Crystal Drive Arlington VA 22202",
    "addr:housenumber":"1750",
    "addr:postcode":"22202",
    "addr:street":"Crystal Drive",
    "iso:country":"US",
    "sg:address":"1750 Crystal Drive",
    "sg:city":"Arlington",
    "sg:classifiers":[
        {
            "category":"Restaurant",
            "type":"Food & Drink"
        }
    ],
    "sg:phone":"+1 703 418 1444",
    "sg:postcode":"22202",
    "sg:province":"VA",
    "sg:tags":[
        "house",
        "seafood",
        "steak",
        "steakhouse",
        "american"
    ],
    "sg:website":"www.mortons.com",
    "wof:name":"Morton's the Steakhouse",
    "wof:placetype":"venue"
},
  "geometry": {"coordinates":[-77.049228,38.858165],"type":"Point"}
}