{
  "type": "Feature",
  "properties": {
    "addr:full":"611 Broad St Harrisonburg VA 22802",
    "addr:housenumber":"611",
    "addr:postcode":"22802",
    "addr:street":"Broad St",
    "iso:country":"US",
    "sg:address":"611 Broad St",
    "sg:city":"Harrisonburg",
    "sg:classifiers":[
        {
            "category":"Social Services",
            "subcategory":"Child Care",
            "type":"Services"
        }
    ],
    "sg:phone":"+1 540 434 3969",
    "sg:postcode":"22802",
    "sg:province":"VA",
    "sg:tags":[
        "day"
    ],
    "wof:name":"First Baptist Church",
    "wof:placetype":"venue"
},
  "geometry": {"coordinates":[-78.862793,38.455391],"type":"Point"}
}