{
  "type": "Feature",
  "properties": {
    "iso:country":"US",
    "sg:address":"3022 Hickory Woods Dr NE",
    "sg:city":"Roanoke",
    "sg:classifiers":[
        {
            "category":"Building & Trades",
            "subcategory":"Construction",
            "type":"Services"
        }
    ],
    "sg:phone":"+1 540 344 6202",
    "sg:postcode":"24012",
    "sg:province":"VA",
    "sg:tags":[
        "hanging",
        "contractor"
    ],
    "wof:name":"Doug Leigh Painting",
    "wof:placetype":"venue"
},
  "geometry": {"coordinates":[-79.896691,37.295831],"type":"Point"}
}