{
  "type": "Feature",
  "properties": {
    "addr:full":"8200 Cub Den Ct Clifton VA 20124",
    "addr:housenumber":"8200",
    "addr:postcode":"20124",
    "addr:street":"Cub Den Ct",
    "iso:country":"US",
    "sg:address":"8200 Cub Den Ct",
    "sg:city":"Clifton",
    "sg:classifiers":[
        {
            "category":"Personal",
            "type":"Services"
        },
        {
            "category":"Building & Trades",
            "subcategory":"Cleaning & Sanitation",
            "type":"Services"
        }
    ],
    "sg:phone":"+1 703 830 3690",
    "sg:postcode":"20124",
    "sg:province":"VA",
    "sg:tags":[
        "butlers'",
        "cleaning-industrial",
        "maids'",
        "contractor"
    ],
    "wof:name":"A Clean Touch",
    "wof:placetype":"venue"
},
  "geometry": {"coordinates":[-77.365959,38.739689],"type":"Point"}
}