{
  "type": "Feature",
  "properties": {
    "iso:country":"US",
    "sg:address":"9907 Georgetown Pike",
    "sg:city":"Great Falls",
    "sg:classifiers":[
        {
            "category":"Banks & Credit Unions",
            "subcategory":"Financial Services",
            "type":"Services"
        }
    ],
    "sg:phone":"+1 703 757 6155",
    "sg:postcode":"22066",
    "sg:province":"VA",
    "sg:tags":[
        "investor"
    ],
    "wof:name":"Prager Sealy & Company",
    "wof:placetype":"venue"
},
  "geometry": {"coordinates":[-77.29010599999999,38.998288],"type":"Point"}
}