{
  "type": "Feature",
  "properties": {
    "addr:full":"194 Glendobbin Ln Winchester VA 22603",
    "addr:housenumber":"194",
    "addr:postcode":"22603",
    "addr:street":"Glendobbin Ln",
    "iso:country":"US",
    "sg:address":"194 Glendobbin Ln",
    "sg:city":"Winchester",
    "sg:classifiers":[
        {
            "category":"Building & Trades",
            "subcategory":"Landscaping Services",
            "type":"Services"
        }
    ],
    "sg:phone":"+1 540 888 9391",
    "sg:postcode":"22603",
    "sg:province":"VA",
    "wof:name":"Artistic Exteriors LLC",
    "wof:placetype":"venue"
},
  "geometry": {"coordinates":[-78.1683,39.232341],"type":"Point"}
}