{
  "type": "Feature",
  "properties": {
    "addr:full":"2034 Banister Rd Petersburg VA 23805",
    "addr:housenumber":"2034",
    "addr:postcode":"23805",
    "addr:street":"Banister Rd",
    "iso:country":"US",
    "sg:address":"2034 Banister Rd",
    "sg:city":"Petersburg",
    "sg:classifiers":[
        {
            "category":"Health Services",
            "subcategory":"Clinic",
            "type":"Services"
        }
    ],
    "sg:phone":"+1 804 863 0755",
    "sg:postcode":"23805",
    "sg:province":"VA",
    "sg:tags":[
        "home",
        "care"
    ],
    "wof:name":"Anderson Enterprises",
    "wof:placetype":"venue"
},
  "geometry": {"coordinates":[-77.412024,37.199001],"type":"Point"}
}