{
  "type": "Feature",
  "properties": {
    "addr:full":"338 School St Emporia VA 23847",
    "addr:housenumber":"338",
    "addr:postcode":"23847",
    "addr:street":"School St",
    "iso:country":"US",
    "sg:address":"338 School St",
    "sg:city":"Emporia",
    "sg:classifiers":[
        {
            "category":"Food & Beverages",
            "subcategory":"Groceries & Convenience Stores",
            "type":"Retail Goods"
        }
    ],
    "sg:phone":"+1 434 634 3345",
    "sg:postcode":"23847",
    "sg:province":"VA",
    "sg:tags":[
        "grocer"
    ],
    "wof:name":"Star Value Super Market",
    "wof:placetype":"venue"
},
  "geometry": {"coordinates":[-77.543665,36.686941],"type":"Point"}
}