{
  "type": "Feature",
  "properties": {
    "iso:country":"US",
    "sg:address":"1240 N Pitt St",
    "sg:city":"Alexandria",
    "sg:classifiers":[
        {
            "category":"Professional",
            "subcategory":"Business Services",
            "type":"Services"
        },
        {
            "category":"Professional",
            "subcategory":"Advertising",
            "type":"Services"
        }
    ],
    "sg:phone":"+1 703 299 1760",
    "sg:postcode":"22314",
    "sg:province":"VA",
    "sg:tags":[
        "medium",
        "buying"
    ],
    "sg:website":"www.xroadsmedia.com",
    "wof:name":"Crossroads Media LLC",
    "wof:placetype":"venue"
},
  "geometry": {"coordinates":[-77.041961,38.818025],"type":"Point"}
}