{
  "type": "Feature",
  "properties": {
    "addr:full":"103 Commonwealth Blvd W Martinsville VA 24112",
    "addr:housenumber":"103",
    "addr:postcode":"24112",
    "addr:street":"Commonwealth Blvd W",
    "iso:country":"US",
    "sg:address":"103 Commonwealth Blvd W",
    "sg:city":"Martinsville",
    "sg:classifiers":[
        {
            "category":"Shopping",
            "subcategory":"Optical Goods",
            "type":"Retail Goods"
        }
    ],
    "sg:phone":"+1 276 632 6457",
    "sg:postcode":"24112",
    "sg:province":"VA",
    "sg:tags":[
        "lens",
        "contact"
    ],
    "sg:website":"http://www.walgreens.com/default.jsp?ec=iyp_yellowpages_trademark",
    "wof:name":"Walgreens Pharmacies",
    "wof:placetype":"venue"
},
  "geometry": {"coordinates":[-79.875761,36.695848],"type":"Point"}
}