{
  "type": "Feature",
  "properties": {
    "addr:full":"8136 Old Keene Mill Rd A209 Springfield VA 22152",
    "addr:housenumber":"8136",
    "addr:postcode":"22152",
    "addr:street":"Old Keene Mill Rd",
    "iso:country":"US",
    "sg:address":"8136 Old Keene Mill Rd A209",
    "sg:city":"Springfield",
    "sg:classifiers":[
        {
            "category":"Place Of Worship",
            "subcategory":"Church",
            "type":"Public Place"
        },
        {
            "category":"Place Of Worship",
            "type":"Public Place"
        }
    ],
    "sg:phone":"+1 703 913 8560",
    "sg:postcode":"22152",
    "sg:province":"VA",
    "sg:tags":[
        "churches-interdenominational",
        "churches-various",
        "denomination"
    ],
    "wof:name":"New World Unity Church",
    "wof:placetype":"venue"
},
  "geometry": {"coordinates":[-77.226213,38.780621],"type":"Point"}
}