{
  "type": "Feature",
  "properties": {
    "addr:full":"829 Monty Rd Boones Mill VA 24065",
    "addr:housenumber":"829",
    "addr:postcode":"24065",
    "addr:street":"Monty Rd Boones",
    "iso:country":"US",
    "sg:address":"829 Monty Rd",
    "sg:city":"Boones Mill",
    "sg:classifiers":[
        {
            "category":"Building & Trades",
            "subcategory":"Construction",
            "type":"Services"
        }
    ],
    "sg:phone":"+1 540 334 4124",
    "sg:postcode":"24065",
    "sg:province":"VA",
    "sg:tags":[
        "house"
    ],
    "wof:name":"Wilcox Builders Inc",
    "wof:placetype":"venue"
},
  "geometry": {"coordinates":[-79.98093799999999,37.094841],"type":"Point"}
}