{
  "type": "Feature",
  "properties": {
    "addr:full":"7879 Wellington Dr Warrenton VA 20186",
    "addr:housenumber":"7879",
    "addr:postcode":"20186",
    "addr:street":"Wellington Dr",
    "iso:country":"US",
    "sg:address":"7879 Wellington Dr",
    "sg:city":"Warrenton",
    "sg:classifiers":[
        {
            "category":"Insurance",
            "subcategory":"Life Insurance",
            "type":"Services"
        }
    ],
    "sg:phone":"+1 540 347 9880",
    "sg:postcode":"20186",
    "sg:province":"VA",
    "sg:tags":[
        "carrier"
    ],
    "wof:name":"Mony Life",
    "wof:placetype":"venue"
},
  "geometry": {"coordinates":[-77.829458,38.724486],"type":"Point"}
}