{
  "type": "Feature",
  "properties": {
    "iso:country":"US",
    "sg:address":"21190 N Bayside Rd",
    "sg:city":"Cape Charles",
    "sg:classifiers":[
        {
            "category":"Professional",
            "subcategory":"Accounting & Tax Preparation",
            "type":"Services"
        }
    ],
    "sg:phone":"+1 757 331 3858",
    "sg:postcode":"23310",
    "sg:province":"VA",
    "sg:tags":[
        "return",
        "filing"
    ],
    "wof:name":"Shore Accounting & Tax Svc",
    "wof:placetype":"venue"
},
  "geometry": {"coordinates":[-75.971163,37.287759],"type":"Point"}
}