{
  "type": "Feature",
  "properties": {
    "addr:full":"2151 Broad Street Rd Maidens VA 23102",
    "addr:housenumber":"2151",
    "addr:postcode":"23102",
    "addr:street":"Broad Street Rd",
    "iso:country":"US",
    "sg:address":"2151 Broad Street Rd",
    "sg:city":"Maidens",
    "sg:classifiers":[
        {
            "category":"Wholesale",
            "subcategory":"Durable Goods & Equipment",
            "type":"Manufacturing & Wholesale Goods"
        }
    ],
    "sg:phone":"+1 804 556 5135",
    "sg:postcode":"23102",
    "sg:province":"VA",
    "sg:tags":[
        "representative",
        "manufacturer"
    ],
    "wof:name":"Cambpell & Assoc",
    "wof:placetype":"venue"
},
  "geometry": {"coordinates":[-77.836304,37.730897],"type":"Point"}
}