{
  "type": "Feature",
  "properties": {
    "addr:full":"5443 Heredity Ln Gainesville VA 20155",
    "addr:housenumber":"5443",
    "addr:postcode":"20155",
    "addr:street":"Heredity Ln",
    "iso:country":"US",
    "sg:address":"5443 Heredity Ln",
    "sg:city":"Gainesville",
    "sg:classifiers":[
        {
            "category":"Banks & Credit Unions",
            "subcategory":"Bank",
            "type":"Services"
        }
    ],
    "sg:phone":"+1 571 248 0186",
    "sg:postcode":"20155",
    "sg:province":"VA",
    "wof:name":"United First Financial",
    "wof:placetype":"venue"
},
  "geometry": {"coordinates":[-77.598055,38.838142],"type":"Point"}
}