{
  "type": "Feature",
  "properties": {
    "addr:full":"7347 Lee Hwy Fairlawn VA 24141",
    "addr:housenumber":"7347",
    "addr:postcode":"24141",
    "addr:street":"Lee Hwy",
    "iso:country":"US",
    "sg:address":"7347 Lee Hwy",
    "sg:city":"Fairlawn",
    "sg:classifiers":[
        {
            "category":"Banks & Credit Unions",
            "subcategory":"Bank",
            "type":"Services"
        }
    ],
    "sg:phone":"+1 540 633 0214",
    "sg:postcode":"24141",
    "sg:province":"VA",
    "sg:tags":[
        "cashing",
        "check"
    ],
    "wof:name":"Check Into Cash",
    "wof:placetype":"venue"
},
  "geometry": {"coordinates":[-80.58318,37.144616],"type":"Point"}
}