{
  "type": "Feature",
  "properties": {
    "addr:full":"312 S Washington St Alexandria VA 22314",
    "addr:housenumber":"312",
    "addr:postcode":"22314",
    "addr:street":"S Washington St",
    "iso:country":"US",
    "sg:address":"312 S Washington St",
    "sg:city":"Alexandria",
    "sg:classifiers":[
        {
            "category":"Health Services",
            "subcategory":"Doctor",
            "type":"Services"
        }
    ],
    "sg:phone":"+1 703 548 4300",
    "sg:postcode":"22314",
    "sg:province":"VA",
    "sg:tags":[
        "physician",
        "surgeon"
    ],
    "wof:name":"T S Van MD",
    "wof:placetype":"venue"
},
  "geometry": {"coordinates":[-77.047612,38.801764],"type":"Point"}
}