{
  "type": "Feature",
  "properties": {
    "iso:country":"US",
    "sg:address":"5758 Union Mill Rd",
    "sg:city":"Clifton",
    "sg:classifiers":[
        {
            "category":"Personal",
            "subcategory":"Beauty Salon",
            "type":"Services"
        }
    ],
    "sg:phone":"+1 703 830 5964",
    "sg:postcode":"20124",
    "sg:province":"VA",
    "sg:tags":[
        "shop"
    ],
    "wof:name":"Creative Hairdressers",
    "wof:placetype":"venue"
},
  "geometry": {"coordinates":[-77.41184800000001,38.832995],"type":"Point"}
}