{
  "type": "Feature",
  "properties": {
    "iso:country":"US",
    "sg:address":"2212 Mount Vernon Ave",
    "sg:city":"Alexandria",
    "sg:classifiers":[
        {
            "category":"Professional",
            "subcategory":"Accounting & Tax Preparation",
            "type":"Services"
        }
    ],
    "sg:phone":"+1 703 549 8842",
    "sg:postcode":"22301",
    "sg:province":"VA",
    "sg:tags":[
        "bookkeeping",
        "general"
    ],
    "wof:name":"Christianson Accounting Svcs",
    "wof:placetype":"venue"
},
  "geometry": {"coordinates":[-77.058708,38.826021],"type":"Point"}
}