{
  "type": "Feature",
  "properties": {
    "addr:full":"8136 Mechanicsville Tpke Mechanicsville VA 23111",
    "addr:housenumber":"8136",
    "addr:postcode":"23111",
    "addr:street":"Mechanicsville Tpke",
    "iso:country":"US",
    "sg:address":"8136 Mechanicsville Tpke",
    "sg:city":"Mechanicsville",
    "sg:classifiers":[
        {
            "category":"Autos & Motor Vehicles",
            "subcategory":"Automobile Sales",
            "type":"Retail Goods"
        }
    ],
    "sg:phone":"+1 804 569 6330",
    "sg:postcode":"23111",
    "sg:province":"VA",
    "sg:tags":[
        "dealers-used",
        "car",
        "used",
        "cars-wholesale",
        "new"
    ],
    "wof:name":"Dave's Auto Sales",
    "wof:placetype":"venue"
},
  "geometry": {"coordinates":[-77.37829499999999,37.59893],"type":"Point"}
}