{
  "type": "Feature",
  "properties": {
    "addr:full":"2116 Berkmar Dr Charlottesville VA 22901",
    "addr:housenumber":"2116",
    "addr:postcode":"22901",
    "addr:street":"Berkmar Dr",
    "iso:country":"US",
    "sg:address":"2116 Berkmar Dr",
    "sg:city":"Charlottesville",
    "sg:classifiers":[
        {
            "category":"Retail",
            "subcategory":"Auto Repair",
            "type":"Services"
        }
    ],
    "sg:phone":"+1 434 973 7084",
    "sg:postcode":"22901",
    "sg:province":"VA",
    "sg:tags":[
        "repairing",
        "automobile"
    ],
    "wof:name":"S & E Car Care",
    "wof:placetype":"venue"
},
  "geometry": {"coordinates":[-78.478741,38.081815],"type":"Point"}
}