{
  "type": "Feature",
  "properties": {
    "addr:full":"4664 King St Alexandria VA 22302",
    "addr:housenumber":"4664",
    "addr:postcode":"22302",
    "addr:street":"King St",
    "iso:country":"US",
    "sg:address":"4664 King St",
    "sg:city":"Alexandria",
    "sg:classifiers":[
        {
            "category":"Professional",
            "subcategory":"Art Services",
            "type":"Services"
        }
    ],
    "sg:phone":"+1 703 349 2045",
    "sg:postcode":"22302",
    "sg:province":"VA",
    "sg:tags":[
        "graphic",
        "design"
    ],
    "wof:name":"Sign A Rama",
    "wof:placetype":"venue"
},
  "geometry": {"coordinates":[-77.108709,38.841993],"type":"Point"}
}