{
  "type": "Feature",
  "properties": {
    "iso:country":"US",
    "sg:address":"1413 Chain Bridge Rd",
    "sg:city":"McLean",
    "sg:classifiers":[
        {
            "category":"Autos & Motor Vehicles",
            "subcategory":"Fuel & Gas Station",
            "type":"Retail Goods"
        }
    ],
    "sg:phone":"+1 703 893 2905",
    "sg:postcode":"22101",
    "sg:province":"VA",
    "sg:website":"www.sunoco.com",
    "wof:name":"Sunoco Ultra Service Center",
    "wof:placetype":"venue"
},
  "geometry": {"coordinates":[-77.177125,38.934277],"type":"Point"}
}