{
  "type": "Feature",
  "properties": {
    "addr:full":"305 E St Hampton VA 23661",
    "addr:housenumber":"305",
    "addr:postcode":"23661",
    "addr:street":"E St",
    "iso:country":"US",
    "sg:address":"305 E St",
    "sg:city":"Hampton",
    "sg:classifiers":[
        {
            "category":"Manufacturing",
            "subcategory":"Metals",
            "type":"Manufacturing & Wholesale Goods"
        }
    ],
    "sg:phone":"+1 757 245 7331",
    "sg:postcode":"23661",
    "sg:province":"VA",
    "sg:tags":[
        "cylinder"
    ],
    "wof:name":"Hy Mark",
    "wof:placetype":"venue"
},
  "geometry": {"coordinates":[-76.409683,37.011768],"type":"Point"}
}