{
  "type": "Feature",
  "properties": {
    "iso:country":"US",
    "sg:address":"423 Wessex Dr",
    "sg:city":"Chesapeake",
    "sg:classifiers":[
        {
            "category":"Personal",
            "subcategory":"Beauty Salon",
            "type":"Services"
        }
    ],
    "sg:phone":"+1 757 547 8582",
    "sg:postcode":"23322",
    "sg:province":"VA",
    "sg:tags":[
        "shop"
    ],
    "wof:name":"Nancy C Salch Beautician",
    "wof:placetype":"venue"
},
  "geometry": {"coordinates":[-76.26716,36.706196],"type":"Point"}
}