{
  "type": "Feature",
  "properties": {
    "iso:country":"US",
    "sg:address":"4138 Fox Hollow Rd",
    "sg:city":"Delaplane",
    "sg:classifiers":[
        {
            "category":"Manufacturing",
            "subcategory":"Printing",
            "type":"Manufacturing & Wholesale Goods"
        }
    ],
    "sg:phone":"+1 540 364 6021",
    "sg:postcode":"20144",
    "sg:province":"VA",
    "sg:tags":[
        "book"
    ],
    "wof:name":"EPM Publications Inc",
    "wof:placetype":"venue"
},
  "geometry": {"coordinates":[-77.951584,38.868195],"type":"Point"}
}