{
  "type": "Feature",
  "properties": {
    "iso:country":"US",
    "sg:address":"13201 Gateway Center Dr",
    "sg:city":"Gainesville",
    "sg:classifiers":[
        {
            "category":"Cinema",
            "subcategory":"Movie Rental",
            "type":"Entertainment"
        }
    ],
    "sg:phone":"+1 571 248 6444",
    "sg:postcode":"20155",
    "sg:province":"VA",
    "sg:tags":[
        "game",
        "video"
    ],
    "wof:name":"Granite Telecomm Vc",
    "wof:placetype":"venue"
},
  "geometry": {"coordinates":[-77.60542100000001,38.796011],"type":"Point"}
}