{
  "type": "Feature",
  "properties": {
    "iso:country":"US",
    "sg:address":"17405 Warwick Blvd",
    "sg:city":"Newport News",
    "sg:classifiers":[
        {
            "category":"Food & Beverages",
            "subcategory":"Groceries & Convenience Stores",
            "type":"Retail Goods"
        }
    ],
    "sg:phone":"+1 757 887 8014",
    "sg:postcode":"23603",
    "sg:province":"VA",
    "wof:name":"Lee Hall Food Mart",
    "wof:placetype":"venue"
},
  "geometry": {"coordinates":[-76.572942,37.193205],"type":"Point"}
}