{
  "type": "Feature",
  "properties": {
    "addr:full":"1232 Springwell Pl Newport News VA 23608",
    "addr:housenumber":"1232",
    "addr:postcode":"23608",
    "addr:street":"Springwell Pl",
    "iso:country":"US",
    "sg:address":"1232 Springwell Pl",
    "sg:city":"Newport News",
    "sg:classifiers":[
        {
            "category":"Arts & Performance",
            "subcategory":"Theater",
            "type":"Entertainment"
        }
    ],
    "sg:phone":"+1 757 286 1114",
    "sg:postcode":"23608",
    "sg:province":"VA",
    "sg:tags":[
        "musician",
        "pastoral"
    ],
    "wof:name":"C C Gilbert",
    "wof:placetype":"venue"
},
  "geometry": {"coordinates":[-76.50948699999999,37.157421],"type":"Point"}
}