{
  "type": "Feature",
  "properties": {
    "addr:full":"8320 Old Cavalry Dr Mechanicsville VA 23111",
    "addr:housenumber":"8320",
    "addr:postcode":"23111",
    "addr:street":"Old Cavalry Dr",
    "iso:country":"US",
    "sg:address":"8320 Old Cavalry Dr",
    "sg:city":"Mechanicsville",
    "sg:classifiers":[
        {
            "category":"Real Estate",
            "subcategory":"Real Estate Agent",
            "type":"Services"
        }
    ],
    "sg:phone":"+1 804 779 3363",
    "sg:postcode":"23111",
    "sg:province":"VA",
    "wof:name":"Otto Long Jr",
    "wof:placetype":"venue"
},
  "geometry": {"coordinates":[-77.307396,37.632249],"type":"Point"}
}