{
  "type": "Feature",
  "properties": {
    "iso:country":"US",
    "sg:address":"5752 Princess Anne Rd",
    "sg:city":"Virginia Beach",
    "sg:classifiers":[
        {
            "category":"Social Services",
            "subcategory":"Adult Care",
            "type":"Services"
        }
    ],
    "sg:phone":"+1 757 461 5098",
    "sg:postcode":"23462",
    "sg:province":"VA",
    "sg:tags":[
        "foster"
    ],
    "wof:name":"Community Solutions",
    "wof:placetype":"venue"
},
  "geometry": {"coordinates":[-76.187538,36.842143],"type":"Point"}
}