{
  "type": "Feature",
  "properties": {
    "addr:full":"1136 S High St Harrisonburg VA 22801",
    "addr:housenumber":"1136",
    "addr:postcode":"22801",
    "addr:street":"S High St",
    "iso:country":"US",
    "sg:address":"1136 S High St",
    "sg:city":"Harrisonburg",
    "sg:classifiers":[
        {
            "category":"Wholesale",
            "subcategory":"Hardware",
            "type":"Manufacturing & Wholesale Goods"
        }
    ],
    "sg:phone":"+1 540 434 8413",
    "sg:postcode":"22801",
    "sg:province":"VA",
    "sg:tags":[
        "plumbing",
        "fixture",
        "supply"
    ],
    "wof:name":"Shank Wholesalers Inc",
    "wof:placetype":"venue"
},
  "geometry": {"coordinates":[-78.891392,38.436605],"type":"Point"}
}