{
  "type": "Feature",
  "properties": {
    "iso:country":"US",
    "sg:address":"808 W 35th St",
    "sg:city":"Norfolk",
    "sg:classifiers":[
        {
            "category":"Home & Garden",
            "subcategory":"Building Materials",
            "type":"Retail Goods"
        }
    ],
    "sg:phone":"+1 757 622 1644",
    "sg:postcode":"23508",
    "sg:province":"VA",
    "sg:tags":[
        "lumber"
    ],
    "wof:name":"Taylors Do It Center",
    "wof:placetype":"venue"
},
  "geometry": {"coordinates":[-76.296421,36.877826],"type":"Point"}
}