{
  "type": "Feature",
  "properties": {
    "addr:full":"4010 George Washington Hwy Portsmouth VA 23702",
    "addr:housenumber":"4010",
    "addr:postcode":"23702",
    "addr:street":"George Washington Hwy",
    "iso:country":"US",
    "sg:address":"4010 George Washington Hwy",
    "sg:city":"Portsmouth",
    "sg:classifiers":[
        {
            "category":"Restaurant",
            "type":"Food & Drink"
        }
    ],
    "sg:phone":"+1 757 393 3343",
    "sg:postcode":"23702",
    "sg:province":"VA",
    "wof:name":"El Noplito Mexican Restaurant",
    "wof:placetype":"venue"
},
  "geometry": {"coordinates":[-76.320396,36.806073],"type":"Point"}
}