{
  "type": "Feature",
  "properties": {
    "addr:full":"4900 McAllister Dr Chester VA 23831",
    "addr:housenumber":"4900",
    "addr:postcode":"23831",
    "addr:street":"Mcallister Dr",
    "iso:country":"US",
    "sg:address":"4900 McAllister Dr",
    "sg:city":"Chester",
    "sg:classifiers":[
        {
            "category":"Building & Trades",
            "subcategory":"Plumbing",
            "type":"Services"
        }
    ],
    "sg:phone":"+1 804 520 7256",
    "sg:postcode":"23831",
    "sg:province":"VA",
    "sg:tags":[
        "conditioning",
        "air",
        "system",
        "contractor"
    ],
    "wof:name":"Iron Bridge Heating & Air Cond",
    "wof:placetype":"venue"
},
  "geometry": {"coordinates":[-77.458309,37.363524],"type":"Point"}
}