{
  "type": "Feature",
  "properties": {
    "addr:full":"8166 Richmond Hwy Alexandria VA 22309",
    "addr:housenumber":"8166",
    "addr:postcode":"22309",
    "addr:street":"Richmond Hwy",
    "iso:country":"US",
    "sg:address":"8166 Richmond Hwy",
    "sg:city":"Alexandria",
    "sg:classifiers":[
        {
            "category":"Restaurant",
            "type":"Food & Drink"
        }
    ],
    "sg:phone":"+1 703 360 0220",
    "sg:postcode":"22309",
    "sg:province":"VA",
    "wof:name":"Elsies Magic Skillet Rstrnt",
    "wof:placetype":"venue"
},
  "geometry": {"coordinates":[-77.094982,38.735734],"type":"Point"}
}