{
  "type": "Feature",
  "properties": {
    "addr:full":"745 Chatham Hill Rd Marion VA 24354",
    "addr:housenumber":"745",
    "addr:postcode":"24354",
    "addr:street":"Chatham Hill Rd",
    "iso:country":"US",
    "sg:address":"745 Chatham Hill Rd",
    "sg:city":"Marion",
    "sg:phone":"+1 276 783 4702",
    "sg:postcode":"24354",
    "sg:province":"VA",
    "sg:tags":[
        "farm",
        "tobacco"
    ],
    "wof:name":"Clifton Anderson",
    "wof:placetype":"venue"
},
  "geometry": {"coordinates":[-81.52122,36.843824],"type":"Point"}
}