{
  "type": "Feature",
  "properties": {
    "iso:country":"US",
    "sg:address":"802 W Pembroke Ave",
    "sg:city":"Hampton",
    "sg:classifiers":[
        {
            "category":"Manufacturing",
            "subcategory":"Glass & Minerals",
            "type":"Manufacturing & Wholesale Goods"
        }
    ],
    "sg:phone":"+1 757 722 2591",
    "sg:postcode":"23669",
    "sg:province":"VA",
    "sg:tags":[
        "concrete",
        "brick",
        "prod",
        "block"
    ],
    "sg:website":"www.pembrokeconstruction.com",
    "wof:name":"Pembroke Stone Mart",
    "wof:placetype":"venue"
},
  "geometry": {"coordinates":[-76.361733,37.028001],"type":"Point"}
}