{
  "type": "Feature",
  "properties": {
    "iso:country":"US",
    "sg:address":"3985 Mud Pike",
    "sg:city":"Christiansburg",
    "sg:classifiers":[
        {
            "category":"Building & Trades",
            "subcategory":"Construction",
            "type":"Services"
        }
    ],
    "sg:phone":"+1 540 639 1615",
    "sg:postcode":"24073",
    "sg:province":"VA",
    "sg:tags":[
        "general",
        "contractor"
    ],
    "wof:name":"Hughes & Son Welding & Fbrctn",
    "wof:placetype":"venue"
},
  "geometry": {"coordinates":[-80.507288,37.101134],"type":"Point"}
}