{
  "type": "Feature",
  "properties": {
    "addr:full":"9116 Kelford Ct Lorton VA 22079",
    "addr:housenumber":"9116",
    "addr:postcode":"22079",
    "addr:street":"Kelford Ct",
    "iso:country":"US",
    "sg:address":"9116 Kelford Ct",
    "sg:city":"Lorton",
    "sg:classifiers":[
        {
            "category":"Professional",
            "subcategory":"Business Services",
            "type":"Services"
        }
    ],
    "sg:phone":"+1 703 690 2328",
    "sg:postcode":"22079",
    "sg:province":"VA",
    "wof:name":"Kleinschmidt Associates",
    "wof:placetype":"venue"
},
  "geometry": {"coordinates":[-77.229716,38.707269],"type":"Point"}
}