{
  "type": "Feature",
  "properties": {
    "addr:full":"5334 Distributor Dr Richmond VA 23225",
    "addr:postcode":"5334;23225",
    "addr:street":"Distributor Dr",
    "iso:country":"US",
    "sg:address":"5334 Distributor Dr",
    "sg:city":"Richmond",
    "sg:classifiers":[
        {
            "category":"Home & Garden",
            "subcategory":"Building Materials",
            "type":"Retail Goods"
        }
    ],
    "sg:phone":"+1 804 232 5164",
    "sg:postcode":"23225",
    "sg:province":"VA",
    "sg:tags":[
        "door",
        "sales"
    ],
    "wof:name":"Southern Specialty Corporation",
    "wof:placetype":"venue"
},
  "geometry": {"coordinates":[-77.499498,37.508418],"type":"Point"}
}