{
  "type": "Feature",
  "properties": {
    "addr:full":"4408 Lee Ave Virginia Beach VA 23455",
    "addr:housenumber":"4408",
    "addr:postcode":"23455",
    "addr:street":"Lee Ave",
    "iso:country":"US",
    "sg:address":"4408 Lee Ave",
    "sg:city":"Virginia Beach",
    "sg:classifiers":[
        {
            "category":"Professional",
            "subcategory":"Management & Consulting",
            "type":"Services"
        }
    ],
    "sg:phone":"+1 757 572 8016",
    "sg:postcode":"23455",
    "sg:province":"VA",
    "wof:name":"Frognfed Inc",
    "wof:placetype":"venue"
},
  "geometry": {"coordinates":[-76.124318,36.913449],"type":"Point"}
}