{
  "type": "Feature",
  "properties": {
    "iso:country":"US",
    "sg:address":"10323 Sarajevo Ct",
    "sg:city":"Manassas",
    "sg:classifiers":[
        {
            "category":"Professional",
            "subcategory":"Management & Consulting",
            "type":"Services"
        },
        {
            "category":"Banks & Credit Unions",
            "subcategory":"Bank",
            "type":"Services"
        }
    ],
    "sg:phone":"+1 703 330 0700",
    "sg:postcode":"20110",
    "sg:province":"VA",
    "sg:tags":[
        "loan"
    ],
    "wof:name":"All Americian Financing",
    "wof:placetype":"venue"
},
  "geometry": {"coordinates":[-77.468757,38.730926],"type":"Point"}
}