{
  "type": "Feature",
  "properties": {
    "iso:country":"US",
    "sg:address":"6575 Frontier Dr",
    "sg:city":"Springfield",
    "sg:classifiers":[
        {
            "category":"Personal",
            "subcategory":"Day Spa",
            "type":"Services"
        },
        {
            "category":"Personal",
            "subcategory":"Nail Salon",
            "type":"Services"
        }
    ],
    "sg:phone":"+1 703 313 8889",
    "sg:postcode":"22150",
    "sg:province":"VA",
    "wof:name":"Escape Nails and Day Spa",
    "wof:placetype":"venue"
},
  "geometry": {"coordinates":[-77.171448,38.776364],"type":"Point"}
}