{
  "type": "Feature",
  "properties": {
    "addr:full":"916 Buckingham Dr Chesapeake VA 23320",
    "addr:housenumber":"916",
    "addr:postcode":"23320",
    "addr:street":"Buckingham Dr",
    "iso:country":"US",
    "sg:address":"916 Buckingham Dr",
    "sg:city":"Chesapeake",
    "sg:classifiers":[
        {
            "category":"Retail",
            "subcategory":"Repair Shop",
            "type":"Services"
        }
    ],
    "sg:phone":"+1 757 547 7396",
    "sg:postcode":"23320",
    "sg:province":"VA",
    "sg:tags":[
        "electrical"
    ],
    "wof:name":"Lovitt TV & Appliance Repair",
    "wof:placetype":"venue"
},
  "geometry": {"coordinates":[-76.240118,36.75243],"type":"Point"}
}