{
  "type": "Feature",
  "properties": {
    "addr:full":"10535 Crestwood Dr Manassas VA 20109",
    "addr:housenumber":"10535",
    "addr:postcode":"20109",
    "addr:street":"Crestwood Dr",
    "iso:country":"US",
    "sg:address":"10535 Crestwood Dr",
    "sg:city":"Manassas",
    "sg:classifiers":[
        {
            "category":"Health Services",
            "subcategory":"Doctor",
            "type":"Services"
        }
    ],
    "sg:phone":"+1 703 257 2070",
    "sg:postcode":"20109",
    "sg:province":"VA",
    "sg:tags":[
        "physician",
        "surgeon"
    ],
    "wof:name":"Advance Urgent Care Walk In",
    "wof:placetype":"venue"
},
  "geometry": {"coordinates":[-77.51058999999999,38.779456],"type":"Point"}
}