{
  "type": "Feature",
  "properties": {
    "addr:full":"116 E Franklin St Richmond VA 23219",
    "addr:housenumber":"116",
    "addr:postcode":"23219",
    "addr:street":"E Franklin St",
    "iso:country":"US",
    "sg:address":"116 E Franklin St",
    "sg:city":"Richmond",
    "sg:classifiers":[
        {
            "category":"Banks & Credit Unions",
            "subcategory":"Investment Brokerage",
            "type":"Services"
        }
    ],
    "sg:phone":"+1 804 343 1801",
    "sg:postcode":"23219",
    "sg:province":"VA",
    "sg:tags":[
        "security"
    ],
    "wof:name":"Frierson Investments",
    "wof:placetype":"venue"
},
  "geometry": {"coordinates":[-77.44184799999999,37.542987],"type":"Point"}
}