{
  "type": "Feature",
  "properties": {
    "iso:country":"US",
    "sg:address":"110 Legion St",
    "sg:city":"Weber City",
    "sg:classifiers":[
        {
            "category":"Real Estate",
            "subcategory":"Surveying",
            "type":"Services"
        }
    ],
    "sg:phone":"+1 276 386 3199",
    "sg:postcode":"24290",
    "sg:province":"VA",
    "wof:name":"Reed Land Surveys",
    "wof:placetype":"venue"
},
  "geometry": {"coordinates":[-82.55354199999999,36.626999],"type":"Point"}
}