{
  "type": "Feature",
  "properties": {
    "addr:full":"2669 Alameda Dr Virginia Beach VA 23456",
    "addr:housenumber":"2669",
    "addr:postcode":"23456",
    "addr:street":"Alameda Dr",
    "iso:country":"US",
    "sg:address":"2669 Alameda Dr",
    "sg:city":"Virginia Beach",
    "sg:classifiers":[
        {
            "category":"Building & Trades",
            "subcategory":"Landscaping Services",
            "type":"Services"
        }
    ],
    "sg:phone":"+1 757 650 1205",
    "sg:postcode":"23456",
    "sg:province":"VA",
    "wof:name":"Professional Grounds MGT",
    "wof:placetype":"venue"
},
  "geometry": {"coordinates":[-76.08367,36.735885],"type":"Point"}
}