{
  "type": "Feature",
  "properties": {
    "iso:country":"US",
    "sg:address":"5999 Burke Commons Rd",
    "sg:city":"Burke",
    "sg:classifiers":[
        {
            "category":"Insurance",
            "subcategory":"Hazard Insurance",
            "type":"Services"
        },
        {
            "category":"Insurance",
            "subcategory":"Health Insurance",
            "type":"Services"
        }
    ],
    "sg:phone":"+1 703 249 7700",
    "sg:postcode":"22015",
    "sg:province":"VA",
    "sg:tags":[
        "maintenance"
    ],
    "sg:website":"http://www.kaiserpermanente.org",
    "wof:name":"Kaiser Foundation Health Plan",
    "wof:placetype":"venue"
},
  "geometry": {"coordinates":[-77.29901099999999,38.79166],"type":"Point"}
}