{
  "type": "Feature",
  "properties": {
    "addr:full":"13763 Royal Red Ter Chantilly VA 20151",
    "addr:housenumber":"13763",
    "addr:postcode":"20151",
    "addr:street":"Royal Red Ter",
    "iso:country":"US",
    "sg:address":"13763 Royal Red Ter",
    "sg:city":"Chantilly",
    "sg:classifiers":[
        {
            "category":"Wholesale",
            "subcategory":"Durable Goods & Equipment",
            "type":"Manufacturing & Wholesale Goods"
        }
    ],
    "sg:phone":"+1 703 378 0151",
    "sg:postcode":"20151",
    "sg:province":"VA",
    "sg:tags":[
        "environmental",
        "ecological",
        "prod"
    ],
    "wof:name":"Spiramid",
    "wof:placetype":"venue"
},
  "geometry": {"coordinates":[-77.424177,38.869168],"type":"Point"}
}