{
  "type": "Feature",
  "properties": {
    "addr:full":"1906 Electric Rd Roanoke VA 24018",
    "addr:housenumber":"1906",
    "addr:postcode":"24018",
    "addr:street":"Electric Rd",
    "iso:country":"US",
    "sg:address":"1906 Electric Rd",
    "sg:city":"Roanoke",
    "sg:classifiers":[
        {
            "category":"Banks & Credit Unions",
            "subcategory":"Investment Brokerage",
            "type":"Services"
        }
    ],
    "sg:phone":"+1 540 725 3160",
    "sg:postcode":"24018",
    "sg:province":"VA",
    "sg:tags":[
        "security"
    ],
    "wof:name":"Morgan Stanley",
    "wof:placetype":"venue"
},
  "geometry": {"coordinates":[-80.03445499999999,37.248044],"type":"Point"}
}