{
  "type": "Feature",
  "properties": {
    "addr:full":"2704 George Mason Pl Alexandria VA 22305",
    "addr:housenumber":"2704",
    "addr:postcode":"22305",
    "addr:street":"George Mason Pl",
    "iso:country":"US",
    "sg:address":"2704 George Mason Pl",
    "sg:city":"Alexandria",
    "sg:classifiers":[
        {
            "category":"Professional",
            "subcategory":"Management & Consulting",
            "type":"Services"
        }
    ],
    "sg:phone":"+1 703 980 0706",
    "sg:postcode":"22305",
    "sg:province":"VA",
    "sg:tags":[
        "defense"
    ],
    "wof:name":"Triad Consulting  Inc",
    "wof:placetype":"venue"
},
  "geometry": {"coordinates":[-77.071274,38.829487],"type":"Point"}
}