{
  "type": "Feature",
  "properties": {
    "iso:country":"US",
    "sg:address":"4566 Eisenhower Ave",
    "sg:city":"Alexandria",
    "sg:classifiers":[
        {
            "category":"Building & Trades",
            "subcategory":"Landscaping Services",
            "type":"Services"
        }
    ],
    "sg:phone":"+1 703 823 5523",
    "sg:postcode":"22304",
    "sg:province":"VA",
    "sg:tags":[
        "landscape",
        "contractor"
    ],
    "wof:name":"Somerset Landscaping Company",
    "wof:placetype":"venue"
},
  "geometry": {"coordinates":[-77.11157,38.804466],"type":"Point"}
}