{
  "type": "Feature",
  "properties": {
    "addr:full":"84 Executive Cir Roanoke VA 24012",
    "addr:housenumber":"84",
    "addr:postcode":"24012",
    "addr:street":"Executive Cir",
    "iso:country":"US",
    "sg:address":"84 Executive Cir",
    "sg:city":"Roanoke",
    "sg:classifiers":[
        {
            "category":"Farming",
            "subcategory":"Dairy Farm",
            "type":"Manufacturing & Wholesale Goods"
        }
    ],
    "sg:phone":"+1 540 977 1900",
    "sg:postcode":"24012",
    "sg:province":"VA",
    "wof:name":"Dairy Farmers Of America",
    "wof:placetype":"venue"
},
  "geometry": {"coordinates":[-79.866365,37.330582],"type":"Point"}
}