{
  "type": "Feature",
  "properties": {
    "iso:country":"US",
    "sg:address":"1445 Emerson Ave",
    "sg:city":"Mc Lean",
    "sg:classifiers":[
        {
            "category":"Professional",
            "subcategory":"Business Services",
            "type":"Services"
        }
    ],
    "sg:phone":"+1 703 448 7772",
    "sg:postcode":"22101",
    "sg:province":"VA",
    "wof:name":"Blackrock Financial Group",
    "wof:placetype":"venue"
},
  "geometry": {"coordinates":[-77.17781600000001,38.933512],"type":"Point"}
}