{
  "type": "Feature",
  "properties": {
    "addr:full":"398 Mossy Creek Rd Mount Solon VA 22843",
    "addr:housenumber":"398",
    "addr:postcode":"22843",
    "addr:street":"Mossy Creek Rd",
    "iso:country":"US",
    "sg:address":"398 Mossy Creek Rd",
    "sg:city":"Mount Solon",
    "sg:classifiers":[
        {
            "category":"Farming",
            "subcategory":"Livestock Farm",
            "type":"Manufacturing & Wholesale Goods"
        }
    ],
    "sg:phone":"+1 540 350 2584",
    "sg:postcode":"22843",
    "sg:province":"VA",
    "sg:tags":[
        "beef",
        "feedlot",
        "cattle"
    ],
    "wof:name":"Mossy Creek Farms",
    "wof:placetype":"venue"
},
  "geometry": {"coordinates":[-79.07658499999999,38.345998],"type":"Point"}
}