{
  "type": "Feature",
  "properties": {
    "addr:full":"4796 Stone Rd Virginia Beach VA 23457",
    "addr:housenumber":"4796",
    "addr:postcode":"23457",
    "addr:street":"Stone Rd",
    "iso:country":"US",
    "sg:address":"4796 Stone Rd",
    "sg:city":"Virginia Beach",
    "sg:classifiers":[
        {
            "category":"Wholesale",
            "subcategory":"Medical Equipment & Supplies",
            "type":"Manufacturing & Wholesale Goods"
        }
    ],
    "sg:phone":"+1 757 721 0704",
    "sg:postcode":"23457",
    "sg:province":"VA",
    "sg:tags":[
        "industrial",
        "computer"
    ],
    "wof:name":"Office Support Unlimited",
    "wof:placetype":"venue"
},
  "geometry": {"coordinates":[-76.00387499999999,36.636252],"type":"Point"}
}