{
  "type": "Feature",
  "properties": {
    "addr:full":"46775 Melrose Ct Sterling VA 20164",
    "addr:housenumber":"46775",
    "addr:postcode":"20164",
    "addr:street":"Melrose Ct",
    "iso:country":"US",
    "sg:address":"46775 Melrose Ct",
    "sg:city":"Sterling",
    "sg:classifiers":[
        {
            "category":"Professional",
            "subcategory":"Art Services",
            "type":"Services"
        }
    ],
    "sg:phone":"+1 703 948 9557",
    "sg:postcode":"20164",
    "sg:province":"VA",
    "sg:tags":[
        "copy",
        "writer"
    ],
    "wof:name":"Write Now LLC",
    "wof:placetype":"venue"
},
  "geometry": {"coordinates":[-77.37933700000001,39.008045],"type":"Point"}
}