{
  "type": "Feature",
  "properties": {
    "iso:country":"US",
    "sg:address":"8000 Belcherwood Rd",
    "sg:city":"Chesterfield",
    "sg:classifiers":[
        {
            "category":"Building & Trades",
            "subcategory":"Plumbing",
            "type":"Services"
        }
    ],
    "sg:phone":"+1 804 790 1741",
    "sg:postcode":"23832",
    "sg:province":"VA",
    "sg:tags":[
        "contractor"
    ],
    "wof:name":"Shupes Plumbing & Gas Piping",
    "wof:placetype":"venue"
},
  "geometry": {"coordinates":[-77.605082,37.386565],"type":"Point"}
}