{
  "type": "Feature",
  "properties": {
    "iso:country":"US",
    "sg:address":"301 Mill St",
    "sg:city":"Occoquan",
    "sg:classifiers":[
        {
            "category":"Restaurant",
            "type":"Food & Drink"
        }
    ],
    "sg:phone":"+1 703 491 1888",
    "sg:postcode":"22125",
    "sg:province":"VA",
    "sg:tags":[
        "grill",
        "bar"
    ],
    "wof:name":"Virginia Grill",
    "wof:placetype":"venue"
},
  "geometry": {"coordinates":[-77.260338,38.684021],"type":"Point"}
}