{
  "type": "Feature",
  "properties": {
    "iso:country":"US",
    "sg:address":"2045 Beacon Pl",
    "sg:city":"Reston",
    "sg:classifiers":[
        {
            "category":"Professional",
            "subcategory":"Business Services",
            "type":"Services"
        }
    ],
    "sg:phone":"+1 703 758 1053",
    "sg:postcode":"20191",
    "sg:province":"VA",
    "wof:name":"Cox Lita",
    "wof:placetype":"venue"
},
  "geometry": {"coordinates":[-77.32705,38.934912],"type":"Point"}
}