{
  "type": "Feature",
  "properties": {
    "addr:full":"908 Bickerton Ct Newport News VA 23608",
    "addr:housenumber":"908",
    "addr:postcode":"23608",
    "addr:street":"Bickerton Ct",
    "iso:country":"US",
    "sg:address":"908 Bickerton Ct",
    "sg:city":"Newport News",
    "sg:classifiers":[
        {
            "category":"Restaurant",
            "type":"Food & Drink"
        }
    ],
    "sg:phone":"+1 757 872 8377",
    "sg:postcode":"23608",
    "sg:province":"VA",
    "sg:tags":[
        "eating"
    ],
    "wof:name":"Schlotzsky S Deli Agency",
    "wof:placetype":"venue"
},
  "geometry": {"coordinates":[-76.51850899999999,37.163026],"type":"Point"}
}