{
  "type": "Feature",
  "properties": {
    "iso:country":"US",
    "sg:address":"4516 W Hundred Rd",
    "sg:city":"Chester",
    "sg:classifiers":[
        {
            "category":"Professional",
            "subcategory":"Management & Consulting",
            "type":"Services"
        }
    ],
    "sg:phone":"+1 804 717 5626",
    "sg:postcode":"23831",
    "sg:province":"VA",
    "wof:name":"S H S Personnel",
    "wof:placetype":"venue"
},
  "geometry": {"coordinates":[-77.44989,37.354128],"type":"Point"}
}