{
  "type": "Feature",
  "properties": {
    "iso:country":"US",
    "sg:address":"1243 Jefferson Davis Hwy",
    "sg:city":"Fredericksburg",
    "sg:classifiers":[
        {
            "category":"Restaurant",
            "type":"Food & Drink"
        }
    ],
    "sg:phone":"+1 540 288 0900",
    "sg:postcode":"22405",
    "sg:province":"VA",
    "wof:name":"Aldo's Italian & Pizza",
    "wof:placetype":"venue"
},
  "geometry": {"coordinates":[-77.44473000000001,38.383503],"type":"Point"}
}