{
  "type": "Feature",
  "properties": {
    "addr:full":"1825 Wenonah Ave Pearisburg VA 24134",
    "addr:housenumber":"1825",
    "addr:postcode":"24134",
    "addr:street":"Wenonah Ave",
    "iso:country":"US",
    "sg:address":"1825 Wenonah Ave",
    "sg:city":"Pearisburg",
    "sg:classifiers":[
        {
            "category":"Education",
            "subcategory":"School",
            "type":"Public Place"
        }
    ],
    "sg:phone":"+1 540 921 1711",
    "sg:postcode":"24134",
    "sg:province":"VA",
    "wof:name":"Giles Highschool",
    "wof:placetype":"venue"
},
  "geometry": {"coordinates":[-80.705769,37.326761],"type":"Point"}
}