{
  "type": "Feature",
  "properties": {
    "addr:full":"301 W Watts St Gretna VA 24557",
    "addr:housenumber":"301",
    "addr:postcode":"24557",
    "addr:street":"W Watts St",
    "iso:country":"US",
    "sg:address":"301 W Watts St",
    "sg:city":"Gretna",
    "sg:classifiers":[
        {
            "category":"Professional",
            "subcategory":"Secretarial Services",
            "type":"Services"
        }
    ],
    "sg:phone":"+1 434 656 8750",
    "sg:postcode":"24557",
    "sg:province":"VA",
    "sg:tags":[
        "transcription",
        "medical"
    ],
    "wof:name":"Edwards Transportation",
    "wof:placetype":"venue"
},
  "geometry": {"coordinates":[-79.36734199999999,36.951851],"type":"Point"}
}