{
  "type": "Feature",
  "properties": {
    "addr:full":"755 Lee Hwy Marion VA 24354",
    "addr:housenumber":"755",
    "addr:postcode":"24354",
    "addr:street":"Lee Hwy",
    "iso:country":"US",
    "sg:address":"755 Lee Hwy",
    "sg:city":"Marion",
    "sg:classifiers":[
        {
            "category":"Shopping",
            "subcategory":"Tobacco",
            "type":"Retail Goods"
        }
    ],
    "sg:phone":"+1 276 646 2663",
    "sg:postcode":"24354",
    "sg:province":"VA",
    "sg:tags":[
        "cigarette",
        "cigar",
        "dealer"
    ],
    "wof:name":"Tobacco & Gift Shop",
    "wof:placetype":"venue"
},
  "geometry": {"coordinates":[-81.640086,36.810894],"type":"Point"}
}