{
  "type": "Feature",
  "properties": {
    "addr:full":"9923 Longford Ct Vienna VA 22181",
    "addr:housenumber":"9923",
    "addr:postcode":"22181",
    "addr:street":"Longford Ct",
    "iso:country":"US",
    "sg:address":"9923 Longford Ct",
    "sg:city":"Vienna",
    "sg:classifiers":[
        {
            "category":"Building & Trades",
            "subcategory":"Construction",
            "type":"Services"
        }
    ],
    "sg:phone":"+1 703 281 7669",
    "sg:postcode":"22181",
    "sg:province":"VA",
    "sg:tags":[
        "nonresidential"
    ],
    "wof:name":"Mjk Construction Inc",
    "wof:placetype":"venue"
},
  "geometry": {"coordinates":[-77.286154,38.878415],"type":"Point"}
}