{
  "type": "Feature",
  "properties": {
    "addr:full":"181 N Loudoun St Winchester VA 22601",
    "addr:housenumber":"181",
    "addr:postcode":"22601",
    "addr:street":"N Loudoun St",
    "iso:country":"US",
    "sg:address":"181 N Loudoun St",
    "sg:city":"Winchester",
    "sg:classifiers":[
        {
            "category":"Restaurant",
            "type":"Food & Drink"
        }
    ],
    "sg:phone":"+1 540 667 8006",
    "sg:postcode":"22601",
    "sg:province":"VA",
    "sg:tags":[
        "eating"
    ],
    "wof:name":"Violino Ristorante Italiano",
    "wof:placetype":"venue"
},
  "geometry": {"coordinates":[-78.164974,39.185947],"type":"Point"}
}