{
  "type": "Feature",
  "properties": {
    "iso:country":"US",
    "sg:address":"1615 Wood Ave",
    "sg:city":"Chesapeake",
    "sg:classifiers":[
        {
            "category":"Organizations",
            "subcategory":"Religious Organization",
            "type":"Services"
        }
    ],
    "sg:phone":"+1 757 523 8909",
    "sg:postcode":"23325",
    "sg:province":"VA",
    "wof:name":"FSHS Church Of Grace",
    "wof:placetype":"venue"
},
  "geometry": {"coordinates":[-76.226844,36.810074],"type":"Point"}
}