{
  "type": "Feature",
  "properties": {
    "addr:full":"116 Edwards Ferry Rd NE # C Leesburg VA 20176",
    "addr:housenumber":"116",
    "addr:postcode":"20176",
    "addr:street":"Edwards Ferry Rd Ne # C",
    "iso:country":"US",
    "sg:address":"116 Edwards Ferry Rd NE # C",
    "sg:city":"Leesburg",
    "sg:classifiers":[
        {
            "category":"Health Services",
            "subcategory":"Doctor",
            "type":"Services"
        }
    ],
    "sg:phone":"+1 703 777 5111",
    "sg:postcode":"20176",
    "sg:province":"VA",
    "sg:tags":[
        "physician",
        "surgeon"
    ],
    "sg:website":"http://www.lpfw.yourmd.com",
    "wof:name":"Loudoun Physicians for Women",
    "wof:placetype":"venue"
},
  "geometry": {"coordinates":[-77.562399,39.114854],"type":"Point"}
}