{
  "type": "Feature",
  "properties": {
    "iso:country":"US",
    "sg:address":"235 Benns Rd",
    "sg:city":"Newport News",
    "sg:classifiers":[
        {
            "category":"Recreation",
            "type":"Entertainment"
        }
    ],
    "sg:phone":"+1 757 595 1647",
    "sg:postcode":"23601",
    "sg:province":"VA",
    "sg:tags":[
        "club",
        "membership",
        "merchandise"
    ],
    "wof:name":"Robinson-Bruton Recreational",
    "wof:placetype":"venue"
},
  "geometry": {"coordinates":[-76.455725,37.075334],"type":"Point"}
}