{
  "type": "Feature",
  "properties": {
    "addr:full":"231 Powers Ct Newport News VA 23601",
    "addr:housenumber":"231",
    "addr:postcode":"23601",
    "addr:street":"Powers Ct",
    "iso:country":"US",
    "sg:address":"231 Powers Ct",
    "sg:city":"Newport News",
    "sg:classifiers":[
        {
            "category":"Professional",
            "type":"Services"
        }
    ],
    "sg:phone":"+1 757 595 7009",
    "sg:postcode":"23601",
    "sg:province":"VA",
    "sg:tags":[
        "establishment"
    ],
    "wof:name":"Ubeda & Ubeda",
    "wof:placetype":"venue"
},
  "geometry": {"coordinates":[-76.446641,37.082681],"type":"Point"}
}