{
  "type": "Feature",
  "properties": {
    "addr:full":"535 Independence Pkwy Chesapeake VA 23320",
    "addr:housenumber":"535",
    "addr:postcode":"23320",
    "addr:street":"Independence Pkwy",
    "iso:country":"US",
    "sg:address":"535 Independence Pkwy",
    "sg:city":"Chesapeake",
    "sg:classifiers":[
        {
            "category":"Health Services",
            "subcategory":"Clinic",
            "type":"Services"
        }
    ],
    "sg:phone":"+1 757 382 4980",
    "sg:postcode":"23320",
    "sg:province":"VA",
    "sg:tags":[
        "specialty",
        "outpatient"
    ],
    "wof:name":"Sentara Home Care",
    "wof:placetype":"venue"
},
  "geometry": {"coordinates":[-76.26091,36.761552],"type":"Point"}
}