{
  "type": "Feature",
  "properties": {
    "iso:country":"US",
    "sg:address":"20789 Great Falls Plz",
    "sg:city":"Sterling",
    "sg:classifiers":[
        {
            "category":"Restaurant",
            "type":"Food & Drink"
        }
    ],
    "sg:menulink":"http://www.allmenus.com/va/sugarland-run/269476-hooked/menu/",
    "sg:phone":"+1 703 421 0404",
    "sg:postcode":"20165",
    "sg:province":"VA",
    "sg:tags":[
        "seafood",
        "american"
    ],
    "wof:name":"Hooked",
    "wof:placetype":"venue"
},
  "geometry": {"coordinates":[-77.358357,39.040144],"type":"Point"}
}