{
  "type": "Feature",
  "properties": {
    "iso:country":"US",
    "sg:address":"929 Downshire Chase",
    "sg:city":"Virginia Beach",
    "sg:classifiers":[
        {
            "category":"Health Services",
            "subcategory":"Doctor",
            "type":"Services"
        }
    ],
    "sg:phone":"+1 757 499 0009",
    "sg:postcode":"23452",
    "sg:province":"VA",
    "sg:tags":[
        "medical"
    ],
    "wof:name":"Tomeu E J MD & Associates PC",
    "wof:placetype":"venue"
},
  "geometry": {"coordinates":[-76.081531,36.873316],"type":"Point"}
}