{
  "type": "Feature",
  "properties": {
    "addr:full":"325 N Great Neck Rd Virginia Beach VA 23454",
    "addr:housenumber":"325",
    "addr:postcode":"23454",
    "addr:street":"N Great Neck Rd",
    "iso:country":"US",
    "sg:address":"325 N Great Neck Rd",
    "sg:city":"Virginia Beach",
    "sg:classifiers":[
        {
            "category":"Food & Beverages",
            "subcategory":"Groceries & Convenience Stores",
            "type":"Retail Goods"
        }
    ],
    "sg:phone":"+1 757 486 5169",
    "sg:postcode":"23454",
    "sg:province":"VA",
    "wof:name":"7-Eleven",
    "wof:placetype":"venue"
},
  "geometry": {"coordinates":[-76.048327,36.841736],"type":"Point"}
}