{
  "type": "Feature",
  "properties": {
    "iso:country":"US",
    "sg:address":"1400 S Edgewood St",
    "sg:city":"Arlington",
    "sg:classifiers":[
        {
            "category":"Professional",
            "subcategory":"Management & Consulting",
            "type":"Services"
        }
    ],
    "sg:phone":"+1 703 521 4536",
    "sg:postcode":"22204",
    "sg:province":"VA",
    "sg:tags":[
        "consultant",
        "business"
    ],
    "wof:name":"Purposeinc",
    "wof:placetype":"venue"
},
  "geometry": {"coordinates":[-77.085061,38.858495],"type":"Point"}
}