{
  "type": "Feature",
  "properties": {
    "iso:country":"US",
    "sg:address":"309 E St",
    "sg:city":"Hampton",
    "sg:classifiers":[
        {
            "category":"Wholesale",
            "subcategory":"Non-durable Goods",
            "type":"Manufacturing & Wholesale Goods"
        }
    ],
    "sg:phone":"+1 757 825 1339",
    "sg:postcode":"23661",
    "sg:province":"VA",
    "sg:tags":[
        "merchandise",
        "general"
    ],
    "wof:name":"A & D Wholesale",
    "wof:placetype":"venue"
},
  "geometry": {"coordinates":[-76.40964200000001,37.011585],"type":"Point"}
}