{
  "type": "Feature",
  "properties": {
    "addr:full":"2001 International Dr Mc Lean VA 22102",
    "addr:housenumber":"2001",
    "addr:postcode":"22102",
    "addr:street":"International Dr",
    "iso:country":"US",
    "sg:address":"2001 International Dr",
    "sg:city":"Mc Lean",
    "sg:classifiers":[
        {
            "category":"Utilities",
            "subcategory":"Mobile Phone",
            "type":"Services"
        }
    ],
    "sg:phone":"+1 703 821 1000",
    "sg:postcode":"22102",
    "sg:province":"VA",
    "sg:tags":[
        "communication",
        "radiotelephone"
    ],
    "wof:name":"Allcel",
    "wof:placetype":"venue"
},
  "geometry": {"coordinates":[-77.226696,38.923917],"type":"Point"}
}