{
  "type": "Feature",
  "properties": {
    "addr:full":"635 25th St S Arlington VA 22202",
    "addr:housenumber":"635",
    "addr:postcode":"22202",
    "addr:street":"25Th St S",
    "iso:country":"US",
    "sg:address":"635 25th St S",
    "sg:city":"Arlington",
    "sg:classifiers":[
        {
            "category":"Organizations",
            "subcategory":"Non-profit Organization",
            "type":"Services"
        }
    ],
    "sg:phone":"+1 703 684 4635",
    "sg:postcode":"22202",
    "sg:province":"VA",
    "wof:name":"Art For Humanity Inc",
    "wof:placetype":"venue"
},
  "geometry": {"coordinates":[-77.056799,38.851528],"type":"Point"}
}