{
  "type": "Feature",
  "properties": {
    "addr:full":"90 Indian Springs Trl Maurertown VA 22644",
    "addr:housenumber":"90",
    "addr:postcode":"22644",
    "addr:street":"Indian Springs Trl",
    "iso:country":"US",
    "sg:address":"90 Indian Springs Trl",
    "sg:city":"Maurertown",
    "sg:classifiers":[
        {
            "category":"Building & Trades",
            "subcategory":"Construction",
            "type":"Services"
        }
    ],
    "sg:phone":"+1 540 436 9101",
    "sg:postcode":"22644",
    "sg:province":"VA",
    "sg:tags":[
        "excavation",
        "contractor"
    ],
    "wof:name":"Plums Construction Corp",
    "wof:placetype":"venue"
},
  "geometry": {"coordinates":[-78.41498799999999,38.912626],"type":"Point"}
}