{
  "type": "Feature",
  "properties": {
    "addr:full":"1113 Spruce St Martinsville VA 24112",
    "addr:housenumber":"1113",
    "addr:postcode":"24112",
    "addr:street":"Spruce St",
    "iso:country":"US",
    "sg:address":"1113 Spruce St",
    "sg:city":"Martinsville",
    "sg:classifiers":[
        {
            "category":"Personal",
            "subcategory":"Beauty Salon",
            "type":"Services"
        }
    ],
    "sg:phone":"+1 276 632 4261",
    "sg:postcode":"24112",
    "sg:province":"VA",
    "sg:tags":[
        "shop"
    ],
    "wof:name":"Allens Beauty Center",
    "wof:placetype":"venue"
},
  "geometry": {"coordinates":[-79.852541,36.679591],"type":"Point"}
}