{
  "type": "Feature",
  "properties": {
    "iso:country":"US",
    "sg:address":"4937 Old Buckingham Rd",
    "sg:city":"Powhatan",
    "sg:classifiers":[
        {
            "category":"Building & Trades",
            "subcategory":"Construction",
            "type":"Services"
        }
    ],
    "sg:phone":"+1 804 598 3961",
    "sg:postcode":"23139",
    "sg:province":"VA",
    "sg:tags":[
        "concrete",
        "contractor"
    ],
    "wof:name":"Nam Veteran Concrete Ltd",
    "wof:placetype":"venue"
},
  "geometry": {"coordinates":[-77.99598,37.523365],"type":"Point"}
}