{
  "type": "Feature",
  "properties": {
    "addr:full":"31717 Old Saltworks Rd Meadowview VA 24361",
    "addr:housenumber":"31717",
    "addr:postcode":"24361",
    "addr:street":"Old Saltworks Rd",
    "iso:country":"US",
    "sg:address":"31717 Old Saltworks Rd",
    "sg:city":"Meadowview",
    "sg:classifiers":[
        {
            "category":"Real Estate",
            "subcategory":"Surveying",
            "type":"Services"
        }
    ],
    "sg:phone":"+1 276 944 5774",
    "sg:postcode":"24361",
    "sg:province":"VA",
    "wof:name":"Maiden Gale W Land Surveyor",
    "wof:placetype":"venue"
},
  "geometry": {"coordinates":[-81.815241,36.832383],"type":"Point"}
}