{
  "type": "Feature",
  "properties": {
    "iso:country":"US",
    "sg:address":"2715 Clarkes Landing Dr",
    "sg:city":"Oakton",
    "sg:classifiers":[
        {
            "category":"Building & Trades",
            "subcategory":"Construction",
            "type":"Services"
        }
    ],
    "sg:phone":"+1 703 321 0080",
    "sg:postcode":"22124",
    "sg:province":"VA",
    "sg:tags":[
        "painter"
    ],
    "wof:name":"Ferrari Enterprise",
    "wof:placetype":"venue"
},
  "geometry": {"coordinates":[-77.338667,38.904011],"type":"Point"}
}