{
  "type": "Feature",
  "properties": {
    "iso:country":"US",
    "sg:address":"131 Kings Way N",
    "sg:city":"Hampton",
    "sg:classifiers":[
        {
            "category":"Banks & Credit Unions",
            "subcategory":"Bank",
            "type":"Services"
        }
    ],
    "sg:phone":"+1 757 723 9311",
    "sg:postcode":"23669",
    "sg:province":"VA",
    "sg:tags":[
        "loan",
        "real estate"
    ],
    "wof:name":"Addison Mortgage Svc Inc",
    "wof:placetype":"venue"
},
  "geometry": {"coordinates":[-76.34475500000001,37.0273],"type":"Point"}
}