{
  "type": "Feature",
  "properties": {
    "iso:country":"US",
    "sg:address":"7917 Old Falls Rd",
    "sg:city":"Mc Lean",
    "sg:classifiers":[
        {
            "category":"Professional",
            "subcategory":"Management & Consulting",
            "type":"Services"
        }
    ],
    "sg:phone":"+1 703 356 2887",
    "sg:postcode":"22102",
    "sg:province":"VA",
    "wof:name":"Behaviorial Management Inc",
    "wof:placetype":"venue"
},
  "geometry": {"coordinates":[-77.218643,38.942546],"type":"Point"}
}