{
  "type": "Feature",
  "properties": {
    "addr:full":"500 Walden Ct Falls Church VA 22046",
    "addr:housenumber":"500",
    "addr:postcode":"22046",
    "addr:street":"Walden Ct",
    "iso:country":"US",
    "sg:address":"500 Walden Ct",
    "sg:city":"Falls Church",
    "sg:classifiers":[
        {
            "category":"Sports & Exercise",
            "subcategory":"Bowling",
            "type":"Entertainment"
        }
    ],
    "sg:phone":"+1 703 241 7072",
    "sg:postcode":"22046",
    "sg:province":"VA",
    "sg:tags":[
        "center"
    ],
    "wof:name":"Sarah D Bowling",
    "wof:placetype":"venue"
},
  "geometry": {"coordinates":[-77.17073499999999,38.890941],"type":"Point"}
}