{
  "type": "Feature",
  "properties": {
    "addr:full":"31 Joynes Rd Hampton VA 23666",
    "addr:housenumber":"31",
    "addr:postcode":"23666",
    "addr:street":"Joynes Rd",
    "iso:country":"US",
    "sg:address":"31 Joynes Rd",
    "sg:city":"Hampton",
    "sg:classifiers":[
        {
            "category":"Organizations",
            "subcategory":"Religious Organization",
            "type":"Services"
        }
    ],
    "sg:phone":"+1 757 826 4661",
    "sg:postcode":"23666",
    "sg:province":"VA",
    "wof:name":"Church of God",
    "wof:placetype":"venue"
},
  "geometry": {"coordinates":[-76.407894,37.026412],"type":"Point"}
}