{
  "type": "Feature",
  "properties": {
    "addr:full":"4128 Cardinal Crest Dr Woodbridge VA 22193",
    "addr:housenumber":"4128",
    "addr:postcode":"22193",
    "addr:street":"Cardinal Crest Dr",
    "iso:country":"US",
    "sg:address":"4128 Cardinal Crest Dr",
    "sg:city":"Woodbridge",
    "sg:classifiers":[
        {
            "category":"Manufacturing",
            "subcategory":"Tools & Machinery",
            "type":"Manufacturing & Wholesale Goods"
        }
    ],
    "sg:phone":"+1 703 975 1324",
    "sg:postcode":"22193",
    "sg:province":"VA",
    "sg:tags":[
        "compact",
        "vending",
        "mach"
    ],
    "wof:name":"D & J Vending Services",
    "wof:placetype":"venue"
},
  "geometry": {"coordinates":[-77.33400399999999,38.622086],"type":"Point"}
}