{
  "type": "Feature",
  "properties": {
    "iso:country":"US",
    "sg:address":"12023 Trossack Rd",
    "sg:city":"Herndon",
    "sg:classifiers":[
        {
            "category":"Professional",
            "subcategory":"Management & Consulting",
            "type":"Services"
        }
    ],
    "sg:phone":"+1 703 456 0016",
    "sg:postcode":"20170",
    "sg:province":"VA",
    "sg:tags":[
        "consultant",
        "business"
    ],
    "wof:name":"Q A Concepts",
    "wof:placetype":"venue"
},
  "geometry": {"coordinates":[-77.361276,38.983963],"type":"Point"}
}