{
  "type": "Feature",
  "properties": {
    "iso:country":"US",
    "sg:address":"2520 Flint Hill Rd",
    "sg:city":"Vienna",
    "sg:classifiers":[
        {
            "category":"Building & Trades",
            "subcategory":"Construction",
            "type":"Services"
        }
    ],
    "sg:phone":"+1 703 255 2661",
    "sg:postcode":"22181",
    "sg:province":"VA",
    "sg:tags":[
        "contractor"
    ],
    "wof:name":"Mj Siding Construction",
    "wof:placetype":"venue"
},
  "geometry": {"coordinates":[-77.281954,38.89404],"type":"Point"}
}