{
  "type": "Feature",
  "properties": {
    "addr:full":"115 Cascade Dr Vinton VA 24179",
    "addr:housenumber":"115",
    "addr:postcode":"24179",
    "addr:street":"Cascade Dr",
    "iso:country":"US",
    "sg:address":"115 Cascade Dr",
    "sg:city":"Vinton",
    "sg:classifiers":[
        {
            "category":"Home & Garden",
            "subcategory":"Home Furnishings",
            "type":"Retail Goods"
        }
    ],
    "sg:phone":"+1 540 890 1724",
    "sg:postcode":"24179",
    "sg:province":"VA",
    "wof:name":"Bdr Enterprises Inc",
    "wof:placetype":"venue"
},
  "geometry": {"coordinates":[-79.811814,37.275675],"type":"Point"}
}