{
  "type": "Feature",
  "properties": {
    "iso:country":"US",
    "sg:address":"509 Nottoway Ave",
    "sg:city":"Blackstone",
    "sg:classifiers":[
        {
            "category":"Real Estate",
            "subcategory":"Real Estate Agent",
            "type":"Services"
        }
    ],
    "sg:phone":"+1 434 292 4291",
    "sg:postcode":"23824",
    "sg:province":"VA",
    "wof:name":"Nottoway Manor",
    "wof:placetype":"venue"
},
  "geometry": {"coordinates":[-78.006086,37.07998],"type":"Point"}
}