{
  "type": "Feature",
  "properties": {
    "addr:full":"485 McLaws Cir Williamsburg VA 23185",
    "addr:housenumber":"485",
    "addr:postcode":"23185",
    "addr:street":"Mclaws Cir",
    "iso:country":"US",
    "sg:address":"485 McLaws Cir",
    "sg:city":"Williamsburg",
    "sg:classifiers":[
        {
            "category":"Professional",
            "subcategory":"Lawyer & Legal Services",
            "type":"Services"
        }
    ],
    "sg:phone":"+1 757 259 5700",
    "sg:postcode":"23185",
    "sg:province":"VA",
    "wof:name":"Jones Blechman Woltz & Kelly",
    "wof:placetype":"venue"
},
  "geometry": {"coordinates":[-76.662846,37.248567],"type":"Point"}
}