{
  "type": "Feature",
  "properties": {
    "addr:full":"4965 Cox Rd Glen Allen VA 23060",
    "addr:housenumber":"4965",
    "addr:postcode":"23060",
    "addr:street":"Cox Rd",
    "iso:country":"US",
    "sg:address":"4965 Cox Rd",
    "sg:city":"Glen Allen",
    "sg:classifiers":[
        {
            "category":"Real Estate",
            "subcategory":"Architect",
            "type":"Services"
        }
    ],
    "sg:phone":"+1 804 747 6220",
    "sg:postcode":"23060",
    "sg:province":"VA",
    "sg:tags":[
        "firm",
        "urban",
        "planning"
    ],
    "wof:name":"Nicholson and Wade Arch",
    "wof:placetype":"venue"
},
  "geometry": {"coordinates":[-77.568851,37.667741],"type":"Point"}
}