{
  "type": "Feature",
  "properties": {
    "addr:full":"2495 Angeline Dr Herndon VA 20171",
    "addr:housenumber":"2495",
    "addr:postcode":"20171",
    "addr:street":"Angeline Dr",
    "iso:country":"US",
    "sg:address":"2495 Angeline Dr",
    "sg:city":"Herndon",
    "sg:classifiers":[
        {
            "category":"Real Estate",
            "subcategory":"Real Estate Agent",
            "type":"Services"
        }
    ],
    "sg:phone":"+1 703 793 1938",
    "sg:postcode":"20171",
    "sg:province":"VA",
    "wof:name":"Jade Realty Co",
    "wof:placetype":"venue"
},
  "geometry": {"coordinates":[-77.410055,38.947546],"type":"Point"}
}