{
  "type": "Feature",
  "properties": {
    "addr:full":"2605 S Clark St Arlington VA 22202",
    "addr:housenumber":"2605",
    "addr:postcode":"22202",
    "addr:street":"S Clark St",
    "iso:country":"US",
    "sg:address":"2605 S Clark St",
    "sg:city":"Arlington",
    "sg:classifiers":[
        {
            "category":"Airline",
            "type":"Transportation"
        }
    ],
    "sg:phone":"+1 703 417 8000",
    "sg:postcode":"22202",
    "sg:province":"VA",
    "sg:tags":[
        "airport"
    ],
    "sg:website":"www.metwashairports.com/reagan",
    "wof:name":"Ronald Reagan Washington National Airport",
    "wof:placetype":"venue"
},
  "geometry": {"coordinates":[-77.042913,38.849735],"type":"Point"}
}