{
  "type": "Feature",
  "properties": {
    "addr:full":"419 Holiday Ct Warrenton VA 22724",
    "addr:housenumber":"419",
    "addr:postcode":"22724",
    "addr:street":"Holiday Ct",
    "iso:country":"US",
    "sg:address":"419 Holiday Ct",
    "sg:city":"Warrenton",
    "sg:classifiers":[
        {
            "category":"Sports & Exercise",
            "subcategory":"Gym",
            "type":"Entertainment"
        }
    ],
    "sg:phone":"+1 540 937 7234",
    "sg:postcode":"22724",
    "sg:province":"VA",
    "sg:tags":[
        "yoga"
    ],
    "sg:website":"www.yogawarrenton.com",
    "wof:name":"Warrenton Yoga",
    "wof:placetype":"venue"
},
  "geometry": {"coordinates":[-77.783704,38.721239],"type":"Point"}
}