{
  "type": "Feature",
  "properties": {
    "addr:full":"3200 Warbro Rd Midlothian VA 23112",
    "addr:housenumber":"3200",
    "addr:postcode":"23112",
    "addr:street":"Warbro Rd",
    "iso:country":"US",
    "sg:address":"3200 Warbro Rd",
    "sg:city":"Midlothian",
    "sg:classifiers":[
        {
            "category":"Wholesale",
            "subcategory":"Scrap",
            "type":"Manufacturing & Wholesale Goods"
        }
    ],
    "sg:phone":"+1 804 763 4763",
    "sg:postcode":"23112",
    "sg:province":"VA",
    "sg:tags":[
        "recycling",
        "center"
    ],
    "wof:name":"Grind-All",
    "wof:placetype":"venue"
},
  "geometry": {"coordinates":[-77.62683,37.446302],"type":"Point"}
}