{
  "type": "Feature",
  "properties": {
    "addr:full":"922 W 21st St Norfolk VA 23517",
    "addr:housenumber":"922",
    "addr:postcode":"23517",
    "addr:street":"W 21St St",
    "iso:country":"US",
    "sg:address":"922 W 21st St",
    "sg:city":"Norfolk",
    "sg:classifiers":[
        {
            "category":"Education",
            "subcategory":"School",
            "type":"Public Place"
        }
    ],
    "sg:phone":"+1 757 628 3300",
    "sg:postcode":"23517",
    "sg:province":"VA",
    "wof:name":"Norfolk Skills Ctr",
    "wof:placetype":"venue"
},
  "geometry": {"coordinates":[-76.298185,36.871793],"type":"Point"}
}