{
  "type": "Feature",
  "properties": {
    "addr:full":"160 Bay Ct Winchester VA 22602",
    "addr:housenumber":"160",
    "addr:postcode":"22602",
    "addr:street":"Bay Ct",
    "iso:country":"US",
    "sg:address":"160 Bay Ct",
    "sg:city":"Winchester",
    "sg:classifiers":[
        {
            "category":"Professional",
            "subcategory":"Management & Consulting",
            "type":"Services"
        }
    ],
    "sg:phone":"+1 540 667 7757",
    "sg:postcode":"22602",
    "sg:province":"VA",
    "sg:tags":[
        "business"
    ],
    "wof:name":"Murtagh Associates",
    "wof:placetype":"venue"
},
  "geometry": {"coordinates":[-78.12279700000001,39.119206],"type":"Point"}
}