{
  "type": "Feature",
  "properties": {
    "addr:full":"360 Herndon Pkwy Herndon VA 20170",
    "addr:housenumber":"360",
    "addr:postcode":"20170",
    "addr:street":"Herndon Pkwy",
    "iso:country":"US",
    "sg:address":"360 Herndon Pkwy",
    "sg:city":"Herndon",
    "sg:classifiers":[
        {
            "category":"Professional",
            "subcategory":"Management & Consulting",
            "type":"Services"
        }
    ],
    "sg:phone":"+1 703 834 1040",
    "sg:postcode":"20170",
    "sg:province":"VA",
    "sg:tags":[
        "consultant",
        "business"
    ],
    "wof:name":"Research Management Corp",
    "wof:placetype":"venue"
},
  "geometry": {"coordinates":[-77.371706,38.963757],"type":"Point"}
}