{
  "type": "Feature",
  "properties": {
    "iso:country":"US",
    "sg:address":"279 Tandem Ln",
    "sg:city":"Charlottesville",
    "sg:classifiers":[
        {
            "category":"Education",
            "subcategory":"School",
            "type":"Public Place"
        }
    ],
    "sg:phone":"+1 434 296 1303",
    "sg:postcode":"22902",
    "sg:province":"VA",
    "sg:website":"www.tandemfs.org",
    "wof:name":"Tandem Friends School",
    "wof:placetype":"venue"
},
  "geometry": {"coordinates":[-78.48719800000001,37.9967],"type":"Point"}
}