{
  "type": "Feature",
  "properties": {
    "addr:full":"10201 Robious Rd Richmond VA 23235",
    "addr:housenumber":"10201",
    "addr:postcode":"23235",
    "addr:street":"Robious Rd",
    "iso:country":"US",
    "sg:address":"10201 Robious Rd",
    "sg:city":"Richmond",
    "sg:classifiers":[
        {
            "category":"Organizations",
            "subcategory":"Religious Organization",
            "type":"Services"
        }
    ],
    "sg:phone":"+1 804 560 7500",
    "sg:postcode":"23235",
    "sg:province":"VA",
    "sg:tags":[
        "church"
    ],
    "sg:website":"www.ljkc.org",
    "wof:name":"Jesus Lord Korean Church",
    "wof:placetype":"venue"
},
  "geometry": {"coordinates":[-77.586394,37.510052],"type":"Point"}
}