{
  "type": "Feature",
  "properties": {
    "iso:country":"US",
    "sg:address":"4716 Ruffin Rd",
    "sg:city":"Prince George",
    "sg:classifiers":[
        {
            "category":"Organizations",
            "subcategory":"Religious Organization",
            "type":"Services"
        }
    ],
    "sg:phone":"+1 804 458 1999",
    "sg:postcode":"23875",
    "sg:province":"VA",
    "wof:name":"Charity Baptist Church",
    "wof:placetype":"venue"
},
  "geometry": {"coordinates":[-77.23750699999999,37.249102],"type":"Point"}
}