{
  "type": "Feature",
  "properties": {
    "iso:country":"US",
    "sg:address":"109 N Main St",
    "sg:city":"Stuart",
    "sg:classifiers":[
        {
            "category":"Shopping",
            "subcategory":"Books",
            "type":"Retail Goods"
        }
    ],
    "sg:phone":"+1 276 694 0101",
    "sg:postcode":"24171",
    "sg:province":"VA",
    "sg:tags":[
        "dealer"
    ],
    "wof:name":"Green Pastures Christian Books",
    "wof:placetype":"venue"
},
  "geometry": {"coordinates":[-80.270072,36.641623],"type":"Point"}
}