{
  "type": "Feature",
  "properties": {
    "iso:country":"US",
    "sg:address":"1010 Stonegate Dr",
    "sg:city":"Salem",
    "sg:classifiers":[
        {
            "category":"Restaurant",
            "type":"Food & Drink"
        }
    ],
    "sg:phone":"+1 540 389 5533",
    "sg:postcode":"24153",
    "sg:province":"VA",
    "wof:name":"Teaberrys On Main",
    "wof:placetype":"venue"
},
  "geometry": {"coordinates":[-80.068606,37.305506],"type":"Point"}
}