{
  "type": "Feature",
  "properties": {
    "iso:country":"US",
    "sg:address":"424 Mill Branch Rd",
    "sg:city":"Long Island",
    "sg:classifiers":[
        {
            "category":"Building & Trades",
            "subcategory":"Construction",
            "type":"Services"
        }
    ],
    "sg:phone":"+1 434 324 4625",
    "sg:postcode":"24569",
    "sg:province":"VA",
    "sg:tags":[
        "house"
    ],
    "wof:name":"Dawson Home Improvements",
    "wof:placetype":"venue"
},
  "geometry": {"coordinates":[-79.17215,37.050442],"type":"Point"}
}