{
  "type": "Feature",
  "properties": {
    "addr:full":"401 Holland Ln Alexandria VA 22314",
    "addr:housenumber":"401",
    "addr:postcode":"22314",
    "addr:street":"Holland Ln",
    "iso:country":"US",
    "sg:address":"401 Holland Ln",
    "sg:city":"Alexandria",
    "sg:classifiers":[
        {
            "category":"Manufacturing",
            "subcategory":"Watercraft",
            "type":"Manufacturing & Wholesale Goods"
        }
    ],
    "sg:phone":"+1 703 549 6648",
    "sg:postcode":"22314",
    "sg:province":"VA",
    "wof:name":"Anglers Craft Boat Builders",
    "wof:placetype":"venue"
},
  "geometry": {"coordinates":[-77.059922,38.802358],"type":"Point"}
}