{
  "type": "Feature",
  "properties": {
    "iso:country":"US",
    "sg:address":"545 Cameo Ter",
    "sg:city":"Chesapeake",
    "sg:classifiers":[
        {
            "category":"Travel",
            "subcategory":"Travel Agent",
            "type":"Entertainment"
        }
    ],
    "sg:phone":"+1 757 549 9322",
    "sg:postcode":"23320",
    "sg:province":"VA",
    "sg:tags":[
        "agency",
        "cruise"
    ],
    "wof:name":"Cruise Consultants Chesapeake",
    "wof:placetype":"venue"
},
  "geometry": {"coordinates":[-76.255152,36.750252],"type":"Point"}
}