{
  "type": "Feature",
  "properties": {
    "iso:country":"US",
    "sg:address":"5819 Ironhorse Rd",
    "sg:city":"Richmond",
    "sg:classifiers":[
        {
            "category":"Professional",
            "type":"Services"
        }
    ],
    "sg:phone":"+1 804 743 0750",
    "sg:postcode":"23234",
    "sg:province":"VA",
    "wof:name":"Strong Structural Steel",
    "wof:placetype":"venue"
},
  "geometry": {"coordinates":[-77.500697,37.436245],"type":"Point"}
}