{
  "type": "Feature",
  "properties": {
    "addr:full":"4098 Main St Chincoteague VA 23336",
    "addr:housenumber":"4098",
    "addr:postcode":"23336",
    "addr:street":"Main St",
    "iso:country":"US",
    "sg:address":"4098 Main St",
    "sg:city":"Chincoteague",
    "sg:classifiers":[
        {
            "category":"Shopping",
            "subcategory":"Gifts & Souvenirs",
            "type":"Retail Goods"
        }
    ],
    "sg:phone":"+1 757 336 3606",
    "sg:postcode":"23336",
    "sg:province":"VA",
    "wof:name":"Virginia Hospitality Shop",
    "wof:placetype":"venue"
},
  "geometry": {"coordinates":[-75.376829,37.93407],"type":"Point"}
}