{
  "type": "Feature",
  "properties": {
    "iso:country":"US",
    "sg:address":"297 Constitution Dr",
    "sg:city":"Virginia Beach",
    "sg:classifiers":[
        {
            "category":"Banks & Credit Unions",
            "subcategory":"Bank",
            "type":"Services"
        }
    ],
    "sg:phone":"+1 757 473 2500",
    "sg:postcode":"23462",
    "sg:province":"VA",
    "wof:name":"Townebank",
    "wof:placetype":"venue"
},
  "geometry": {"coordinates":[-76.13101899999999,36.84335],"type":"Point"}
}