{
  "type": "Feature",
  "properties": {
    "addr:full":"1700 Memorial Ave Lynchburg VA 24501",
    "addr:housenumber":"1700",
    "addr:postcode":"24501",
    "addr:street":"Memorial Ave",
    "iso:country":"US",
    "sg:address":"1700 Memorial Ave",
    "sg:city":"Lynchburg",
    "sg:classifiers":[
        {
            "category":"Professional",
            "subcategory":"Computer Services",
            "type":"Services"
        }
    ],
    "sg:phone":"+1 434 846 5300",
    "sg:postcode":"24501",
    "sg:province":"VA",
    "sg:tags":[
        "internet"
    ],
    "wof:name":"Barker Jennings Corp",
    "wof:placetype":"venue"
},
  "geometry": {"coordinates":[-79.160318,37.409609],"type":"Point"}
}