{
  "type": "Feature",
  "properties": {
    "addr:full":"2101 W Main St Waynesboro VA 22980",
    "addr:housenumber":"2101",
    "addr:postcode":"22980",
    "addr:street":"W Main St",
    "iso:country":"US",
    "sg:address":"2101 W Main St",
    "sg:city":"Waynesboro",
    "sg:classifiers":[
        {
            "category":"Retail",
            "subcategory":"Auto Repair",
            "type":"Services"
        }
    ],
    "sg:phone":"+1 540 943 3825",
    "sg:postcode":"22980",
    "sg:province":"VA",
    "sg:tags":[
        "wrecker"
    ],
    "wof:name":"Drumheller's Towing & Recovery",
    "wof:placetype":"venue"
},
  "geometry": {"coordinates":[-78.915415,38.077019],"type":"Point"}
}