{
  "type": "Feature",
  "properties": {
    "addr:full":"11 Blacksmith Ct Stafford VA 22554",
    "addr:housenumber":"11",
    "addr:postcode":"22554",
    "addr:street":"Blacksmith Ct",
    "iso:country":"US",
    "sg:address":"11 Blacksmith Ct",
    "sg:city":"Stafford",
    "sg:classifiers":[
        {
            "category":"Personal",
            "subcategory":"Beauty Salon",
            "type":"Services"
        }
    ],
    "sg:phone":"+1 540 657 1800",
    "sg:postcode":"22554",
    "sg:province":"VA",
    "wof:name":"Salon Eleven",
    "wof:placetype":"venue"
},
  "geometry": {"coordinates":[-77.425837,38.445105],"type":"Point"}
}