{
  "type": "Feature",
  "properties": {
    "addr:full":"1207 Stable Gate Ct McLean VA 22102",
    "addr:housenumber":"1207",
    "addr:postcode":"22102",
    "addr:street":"Stable Gate Ct",
    "iso:country":"US",
    "sg:address":"1207 Stable Gate Ct",
    "sg:city":"McLean",
    "sg:classifiers":[
        {
            "category":"Professional",
            "subcategory":"Lawyer & Legal Services",
            "type":"Services"
        }
    ],
    "sg:phone":"+1 703 821 8369",
    "sg:postcode":"22102",
    "sg:province":"VA",
    "wof:name":"Knight G Lloyd Patnt Atty",
    "wof:placetype":"venue"
},
  "geometry": {"coordinates":[-77.21220099999999,38.941865],"type":"Point"}
}