{
  "type": "Feature",
  "properties": {
    "addr:full":"3900 Wards Rd Lynchburg VA 24502",
    "addr:housenumber":"3900",
    "addr:postcode":"24502",
    "addr:street":"Wards Rd",
    "iso:country":"US",
    "sg:address":"3900 Wards Rd",
    "sg:city":"Lynchburg",
    "sg:classifiers":[
        {
            "category":"Restaurant",
            "type":"Food & Drink"
        }
    ],
    "sg:menulink":"http://www.allmenus.com/va/lynchburg/188036-mcdonalds/menu/",
    "sg:phone":"+1 434 239 0446",
    "sg:postcode":"24502",
    "sg:province":"VA",
    "sg:tags":[
        "burger",
        "american"
    ],
    "wof:name":"McDonald's",
    "wof:placetype":"venue"
},
  "geometry": {"coordinates":[-79.185401,37.353721],"type":"Point"}
}