{
  "type": "Feature",
  "properties": {
    "addr:full":"11693 Mckimmey Ln Lovettsville VA 20180",
    "addr:housenumber":"11693",
    "addr:postcode":"20180",
    "addr:street":"Mckimmey Ln",
    "iso:country":"US",
    "sg:address":"11693 Mckimmey Ln",
    "sg:city":"Lovettsville",
    "sg:classifiers":[
        {
            "category":"Manufacturing",
            "subcategory":"Tools & Machinery",
            "type":"Manufacturing & Wholesale Goods"
        },
        {
            "category":"Retail",
            "subcategory":"Auto Repair",
            "type":"Services"
        }
    ],
    "sg:phone":"+1 540 822 9178",
    "sg:postcode":"20180",
    "sg:province":"VA",
    "sg:tags":[
        "engines-rebuild",
        "repairing",
        "lawn",
        "mowers-sharpening",
        "exchange"
    ],
    "wof:name":"Jamie's Small Engine Repair Inc",
    "wof:placetype":"venue"
},
  "geometry": {"coordinates":[-77.57566799999999,39.290853],"type":"Point"}
}