{
  "type": "Feature",
  "properties": {
    "iso:country":"US",
    "sg:address":"11037 Pierson Dr",
    "sg:city":"Fredericksburg",
    "sg:classifiers":[
        {
            "category":"Freight",
            "type":"Transportation"
        }
    ],
    "sg:phone":"+1 540 373 8559",
    "sg:postcode":"22408",
    "sg:province":"VA",
    "sg:tags":[
        "commercial",
        "storage"
    ],
    "wof:name":"Discount Mini Storage",
    "wof:placetype":"venue"
},
  "geometry": {"coordinates":[-77.43721499999999,38.261024],"type":"Point"}
}