{
  "type": "Feature",
  "properties": {
    "iso:country":"US",
    "sg:address":"815 Battlefield Blvd S",
    "sg:city":"Chesapeake",
    "sg:classifiers":[
        {
            "category":"Organizations",
            "subcategory":"Non-profit Organization",
            "type":"Services"
        },
        {
            "category":"Professional",
            "subcategory":"Management & Consulting",
            "type":"Services"
        }
    ],
    "sg:phone":"+1 757 546 5502",
    "sg:postcode":"23322",
    "sg:province":"VA",
    "sg:tags":[
        "to",
        "train",
        "safety",
        "public",
        "establish"
    ],
    "wof:name":"Project Lifesaver Intl Hq",
    "wof:placetype":"venue"
},
  "geometry": {"coordinates":[-76.23355100000001,36.698264],"type":"Point"}
}