{
  "type": "Feature",
  "properties": {
    "addr:full":"330 E Bayview Blvd Norfolk VA 23503",
    "addr:housenumber":"330",
    "addr:postcode":"23503",
    "addr:street":"E Bayview Blvd",
    "iso:country":"US",
    "sg:address":"330 E Bayview Blvd",
    "sg:city":"Norfolk",
    "sg:classifiers":[
        {
            "category":"Professional",
            "subcategory":"Engineering",
            "type":"Services"
        }
    ],
    "sg:phone":"+1 757 480 1312",
    "sg:postcode":"23503",
    "sg:province":"VA",
    "wof:name":"Ori",
    "wof:placetype":"venue"
},
  "geometry": {"coordinates":[-76.256129,36.932871],"type":"Point"}
}