{
  "type": "Feature",
  "properties": {
    "addr:full":"64 W Wind Rd Fincastle VA 24090",
    "addr:housenumber":"64",
    "addr:postcode":"24090",
    "addr:street":"W Wind Rd",
    "iso:country":"US",
    "sg:address":"64 W Wind Rd",
    "sg:city":"Fincastle",
    "sg:classifiers":[
        {
            "category":"Manufacturing",
            "subcategory":"Rubber & Plastics",
            "type":"Manufacturing & Wholesale Goods"
        }
    ],
    "sg:phone":"+1 802 773 9111",
    "sg:postcode":"24090",
    "sg:province":"VA",
    "sg:tags":[
        "product",
        "mfg"
    ],
    "sg:website":"http://www.carris.com",
    "wof:name":"Carris Reels Inc",
    "wof:placetype":"venue"
},
  "geometry": {"coordinates":[-79.848428,37.5574],"type":"Point"}
}