{
  "type": "Feature",
  "properties": {
    "iso:country":"US",
    "sg:address":"2246 Walnut Ave",
    "sg:city":"Buena Vista",
    "sg:classifiers":[
        {
            "category":"Organizations",
            "subcategory":"Religious Organization",
            "type":"Services"
        }
    ],
    "sg:phone":"+1 540 261 3929",
    "sg:postcode":"24416",
    "sg:province":"VA",
    "wof:name":"Christ Episcopal Church",
    "wof:placetype":"venue"
},
  "geometry": {"coordinates":[-79.35009100000001,37.735371],"type":"Point"}
}