{
  "type": "Feature",
  "properties": {
    "iso:country":"US",
    "sg:address":"1401 Guerriere St",
    "sg:city":"Chesapeake",
    "sg:classifiers":[
        {
            "category":"Shopping",
            "type":"Retail Goods"
        }
    ],
    "sg:phone":"+1 757 366 0042",
    "sg:postcode":"23324",
    "sg:province":"VA",
    "sg:tags":[
        "sunglasses",
        "accessory"
    ],
    "wof:name":"Sunglass Hut International",
    "wof:placetype":"venue"
},
  "geometry": {"coordinates":[-76.271171,36.817506],"type":"Point"}
}