{
  "type": "Feature",
  "properties": {
    "iso:country":"US",
    "sg:address":"11821 Blue Spruce Rd",
    "sg:city":"Reston",
    "sg:classifiers":[
        {
            "category":"Building & Trades",
            "subcategory":"Construction",
            "type":"Services"
        }
    ],
    "sg:phone":"+1 703 620 4645",
    "sg:postcode":"20191",
    "sg:province":"VA",
    "sg:tags":[
        "contractor"
    ],
    "wof:name":"Corner Post Construction Inc",
    "wof:placetype":"venue"
},
  "geometry": {"coordinates":[-77.35685700000001,38.920014],"type":"Point"}
}