{
  "type": "Feature",
  "properties": {
    "addr:full":"300 E Main St Norfolk VA 23510",
    "addr:housenumber":"300",
    "addr:postcode":"23510",
    "addr:street":"E Main St",
    "iso:country":"US",
    "sg:address":"300 E Main St",
    "sg:city":"Norfolk",
    "sg:classifiers":[
        {
            "category":"Real Estate",
            "subcategory":"Surveying",
            "type":"Services"
        }
    ],
    "sg:phone":"+1 757 442 4418",
    "sg:postcode":"23510",
    "sg:province":"VA",
    "sg:tags":[
        "surveyor"
    ],
    "wof:name":"Eastern Shore Surveyors",
    "wof:placetype":"venue"
},
  "geometry": {"coordinates":[-76.289526,36.84583],"type":"Point"}
}