{
  "type": "Feature",
  "properties": {
    "addr:full":"3025 Berkmar Dr Charlottesville VA 22901",
    "addr:housenumber":"3025",
    "addr:postcode":"22901",
    "addr:street":"Berkmar Dr",
    "iso:country":"US",
    "sg:address":"3025 Berkmar Dr",
    "sg:city":"Charlottesville",
    "sg:classifiers":[
        {
            "category":"Health Services",
            "subcategory":"Doctor",
            "type":"Services"
        }
    ],
    "sg:phone":"+1 434 973 7540",
    "sg:postcode":"22901",
    "sg:province":"VA",
    "wof:name":"Viglione Haines & Associates",
    "wof:placetype":"venue"
},
  "geometry": {"coordinates":[-78.479084,38.083425],"type":"Point"}
}