{
  "type": "Feature",
  "properties": {
    "addr:full":"115 W Park Dr Charlottesville VA 22901",
    "addr:housenumber":"115",
    "addr:postcode":"22901",
    "addr:street":"W Park Dr",
    "iso:country":"US",
    "sg:address":"115 W Park Dr",
    "sg:city":"Charlottesville",
    "sg:classifiers":[
        {
            "category":"Real Estate",
            "subcategory":"Real Estate Agent",
            "type":"Services"
        }
    ],
    "sg:phone":"+1 434 979 0822",
    "sg:postcode":"22901",
    "sg:province":"VA",
    "wof:name":"Kathy Maxa Real Estate",
    "wof:placetype":"venue"
},
  "geometry": {"coordinates":[-78.504921,38.063316],"type":"Point"}
}