{
  "type": "Feature",
  "properties": {
    "addr:full":"2532 Log Cabin Rd Maidens VA 23102",
    "addr:housenumber":"2532",
    "addr:postcode":"23102",
    "addr:street":"Log Cabin Rd",
    "iso:country":"US",
    "sg:address":"2532 Log Cabin Rd",
    "sg:city":"Maidens",
    "sg:classifiers":[
        {
            "category":"Personal",
            "subcategory":"Beauty Salon",
            "type":"Services"
        }
    ],
    "sg:phone":"+1 804 556 6845",
    "sg:postcode":"23102",
    "sg:province":"VA",
    "sg:tags":[
        "shop"
    ],
    "wof:name":"Styles Unlimited",
    "wof:placetype":"venue"
},
  "geometry": {"coordinates":[-77.862776,37.707009],"type":"Point"}
}