{
  "type": "Feature",
  "properties": {
    "iso:country":"US",
    "sg:address":"2308 Beach Haven Dr",
    "sg:city":"Virginia Beach",
    "sg:classifiers":[
        {
            "category":"Professional",
            "subcategory":"Management & Consulting",
            "type":"Services"
        }
    ],
    "sg:phone":"+1 757 481 5182",
    "sg:postcode":"23451",
    "sg:province":"VA",
    "wof:name":"Meritime Admiralty Consulting",
    "wof:placetype":"venue"
},
  "geometry": {"coordinates":[-76.080541,36.910955],"type":"Point"}
}