{
  "type": "Feature",
  "properties": {
    "addr:full":"400 E Broad St Falls Church VA 22046",
    "addr:housenumber":"400",
    "addr:postcode":"22046",
    "addr:street":"E Broad St",
    "iso:country":"US",
    "sg:address":"400 E Broad St",
    "sg:city":"Falls Church",
    "sg:classifiers":[
        {
            "category":"Professional",
            "subcategory":"Management & Consulting",
            "type":"Services"
        }
    ],
    "sg:phone":"+1 703 534 1963",
    "sg:postcode":"22046",
    "sg:province":"VA",
    "wof:name":"A & P Management Services",
    "wof:placetype":"venue"
},
  "geometry": {"coordinates":[-77.16454299999999,38.878017],"type":"Point"}
}