{
  "type": "Feature",
  "properties": {
    "iso:country":"US",
    "sg:address":"7391 Lee Hwy",
    "sg:city":"Falls Church",
    "sg:classifiers":[
        {
            "category":"Restaurant",
            "type":"Food & Drink"
        }
    ],
    "sg:menulink":"http://www.allmenus.com/va/providence/192286-wendys/menu/",
    "sg:phone":"+1 703 560 2561",
    "sg:postcode":"22042",
    "sg:province":"VA",
    "sg:tags":[
        "burger",
        "american",
        "soup"
    ],
    "wof:name":"Wendy's",
    "wof:placetype":"venue"
},
  "geometry": {"coordinates":[-77.197045,38.8759],"type":"Point"}
}