{
  "type": "Feature",
  "properties": {
    "iso:country":"US",
    "sg:address":"3515 Colonial Ave",
    "sg:city":"Norfolk",
    "sg:classifiers":[
        {
            "category":"Building & Trades",
            "subcategory":"Plumbing",
            "type":"Services"
        }
    ],
    "sg:phone":"+1 757 625 0157",
    "sg:postcode":"23508",
    "sg:province":"VA",
    "sg:tags":[
        "plumbing",
        "contractor"
    ],
    "wof:name":"Superior Plumbing LLC",
    "wof:placetype":"venue"
},
  "geometry": {"coordinates":[-76.28859,36.878823],"type":"Point"}
}