{
  "type": "Feature",
  "properties": {
    "addr:full":"1360 Farmers Market Dr Hillsville VA 24343",
    "addr:housenumber":"1360",
    "addr:postcode":"24343",
    "addr:street":"Dr",
    "iso:country":"US",
    "sg:address":"1360 Farmers Market Dr",
    "sg:city":"Hillsville",
    "sg:classifiers":[
        {
            "category":"Utilities",
            "subcategory":"Telephone",
            "type":"Services"
        }
    ],
    "sg:phone":"+1 276 728 3471",
    "sg:postcode":"24343",
    "sg:province":"VA",
    "sg:tags":[
        "telecommunication"
    ],
    "wof:name":"American Tower Corp",
    "wof:placetype":"venue"
},
  "geometry": {"coordinates":[-80.764252,36.731372],"type":"Point"}
}