{
  "type": "Feature",
  "properties": {
    "addr:full":"2500 Danieltown Rd Goochland VA 23063",
    "addr:housenumber":"2500",
    "addr:postcode":"23063",
    "addr:street":"Danieltown Rd",
    "iso:country":"US",
    "sg:address":"2500 Danieltown Rd",
    "sg:city":"Goochland",
    "sg:classifiers":[
        {
            "category":"Building & Trades",
            "subcategory":"Landscaping Services",
            "type":"Services"
        }
    ],
    "sg:phone":"+1 804 833 2953",
    "sg:postcode":"23063",
    "sg:province":"VA",
    "sg:tags":[
        "landscape"
    ],
    "wof:name":"H & H",
    "wof:placetype":"venue"
},
  "geometry": {"coordinates":[-78.040958,37.738236],"type":"Point"}
}