{
  "type": "Feature",
  "properties": {
    "addr:full":"3213 Broad Rock Blvd Richmond VA 23224",
    "addr:housenumber":"3213",
    "addr:postcode":"23224",
    "addr:street":"Broad Rock Blvd",
    "iso:country":"US",
    "sg:address":"3213 Broad Rock Blvd",
    "sg:city":"Richmond",
    "sg:classifiers":[
        {
            "category":"Building & Trades",
            "subcategory":"Construction",
            "type":"Services"
        }
    ],
    "sg:phone":"+1 804 231 2339",
    "sg:postcode":"23224",
    "sg:province":"VA",
    "sg:tags":[
        "roofing",
        "contractor"
    ],
    "wof:name":"L Willard Council Roofing Inc",
    "wof:placetype":"venue"
},
  "geometry": {"coordinates":[-77.482619,37.472171],"type":"Point"}
}