{
  "type": "Feature",
  "properties": {
    "addr:full":"7501 Porch Rd Warrenton VA 20187",
    "addr:housenumber":"7501",
    "addr:postcode":"20187",
    "addr:street":"Porch Rd",
    "iso:country":"US",
    "sg:address":"7501 Porch Rd",
    "sg:city":"Warrenton",
    "sg:classifiers":[
        {
            "category":"Building & Trades",
            "subcategory":"Construction",
            "type":"Services"
        }
    ],
    "sg:phone":"+1 540 351 0375",
    "sg:postcode":"20187",
    "sg:province":"VA",
    "sg:tags":[
        "light",
        "remodeling",
        "contractor"
    ],
    "wof:name":"Welcome Home Solutions",
    "wof:placetype":"venue"
},
  "geometry": {"coordinates":[-77.749354,38.725834],"type":"Point"}
}