{
  "type": "Feature",
  "properties": {
    "addr:full":"3035 Braxton Woods Ct Fairfax VA 22031",
    "addr:housenumber":"3035",
    "addr:postcode":"22031",
    "addr:street":"Braxton Woods Ct",
    "iso:country":"US",
    "sg:address":"3035 Braxton Woods Ct",
    "sg:city":"Fairfax",
    "sg:classifiers":[
        {
            "category":"Recreation",
            "type":"Entertainment"
        }
    ],
    "sg:phone":"+1 703 593 1004",
    "sg:postcode":"22031",
    "sg:province":"VA",
    "wof:name":"Capital Soccer Training",
    "wof:placetype":"venue"
},
  "geometry": {"coordinates":[-77.25875000000001,38.871241],"type":"Point"}
}