{
  "type": "Feature",
  "properties": {
    "iso:country":"US",
    "sg:address":"9 Settlers Way",
    "sg:city":"Stafford",
    "sg:classifiers":[
        {
            "category":"Building & Trades",
            "subcategory":"Plumbing",
            "type":"Services"
        }
    ],
    "sg:phone":"+1 703 494 0225",
    "sg:postcode":"22554",
    "sg:province":"VA",
    "sg:tags":[
        "heating",
        "contractor"
    ],
    "wof:name":"Global Air Inc",
    "wof:placetype":"venue"
},
  "geometry": {"coordinates":[-77.42236699999999,38.462321],"type":"Point"}
}