{
  "type": "Feature",
  "properties": {
    "addr:full":"2811 W Cary St Richmond VA 23221",
    "addr:housenumber":"2811",
    "addr:postcode":"23221",
    "addr:street":"W Cary St",
    "iso:country":"US",
    "sg:address":"2811 W Cary St",
    "sg:city":"Richmond",
    "sg:classifiers":[
        {
            "category":"Restaurant",
            "type":"Food & Drink"
        }
    ],
    "sg:phone":"+1 804 340 1814",
    "sg:postcode":"23221",
    "sg:province":"VA",
    "sg:tags":[
        "management"
    ],
    "wof:name":"Stix Bar & Grill",
    "wof:placetype":"venue"
},
  "geometry": {"coordinates":[-77.477187,37.551826],"type":"Point"}
}