{
  "type": "Feature",
  "properties": {
    "iso:country":"US",
    "sg:address":"5203 Ninian Ave",
    "sg:city":"Alexandria",
    "sg:classifiers":[
        {
            "category":"Utilities",
            "subcategory":"Refuse",
            "type":"Services"
        }
    ],
    "sg:phone":"+1 703 971 4010",
    "sg:postcode":"22310",
    "sg:province":"VA",
    "sg:tags":[
        "garbage",
        "collection"
    ],
    "wof:name":"Virginia Trash Svc",
    "wof:placetype":"venue"
},
  "geometry": {"coordinates":[-77.12532299999999,38.788798],"type":"Point"}
}