{
  "type": "Feature",
  "properties": {
    "addr:full":"1608 Montmorency Dr Vienna VA 22182",
    "addr:housenumber":"1608",
    "addr:postcode":"22182",
    "addr:street":"Montmorency Dr",
    "iso:country":"US",
    "sg:address":"1608 Montmorency Dr",
    "sg:city":"Vienna",
    "sg:classifiers":[
        {
            "category":"Banks & Credit Unions",
            "subcategory":"Financial Services",
            "type":"Services"
        }
    ],
    "sg:phone":"+1 703 242 0256",
    "sg:postcode":"22182",
    "sg:province":"VA",
    "sg:tags":[
        "company",
        "holding"
    ],
    "wof:name":"Remote Technology Solution",
    "wof:placetype":"venue"
},
  "geometry": {"coordinates":[-77.255515,38.930461],"type":"Point"}
}