{
  "type": "Feature",
  "properties": {
    "addr:full":"120 Franklin Ct Danville VA 24540",
    "addr:housenumber":"120",
    "addr:postcode":"24540",
    "addr:street":"Franklin Ct",
    "iso:country":"US",
    "sg:address":"120 Franklin Ct",
    "sg:city":"Danville",
    "sg:classifiers":[
        {
            "category":"Organizations",
            "subcategory":"Religious Organization",
            "type":"Services"
        }
    ],
    "sg:phone":"+1 434 836 5683",
    "sg:postcode":"24540",
    "sg:province":"VA",
    "sg:tags":[
        "clergy"
    ],
    "wof:name":"Garnett W Johnson",
    "wof:placetype":"venue"
},
  "geometry": {"coordinates":[-79.391898,36.630288],"type":"Point"}
}