{
  "type": "Feature",
  "properties": {
    "addr:full":"2400 Memorial Ave Lynchburg VA 24501",
    "addr:housenumber":"2400",
    "addr:postcode":"24501",
    "addr:street":"Memorial Ave",
    "iso:country":"US",
    "sg:address":"2400 Memorial Ave",
    "sg:city":"Lynchburg",
    "sg:classifiers":[
        {
            "category":"Retail",
            "subcategory":"Laundry & Dry Cleaning",
            "type":"Services"
        }
    ],
    "sg:phone":"+1 434 846 8046",
    "sg:postcode":"24501",
    "sg:province":"VA",
    "wof:name":"Thanh Custom Tailors",
    "wof:placetype":"venue"
},
  "geometry": {"coordinates":[-79.167233,37.403423],"type":"Point"}
}