{
  "type": "Feature",
  "properties": {
    "addr:full":"1811 Main St Victoria VA 23974",
    "addr:housenumber":"1811",
    "addr:postcode":"23974",
    "addr:street":"Main St",
    "iso:country":"US",
    "sg:address":"1811 Main St",
    "sg:city":"Victoria",
    "sg:classifiers":[
        {
            "category":"Government",
            "subcategory":"Office",
            "type":"Public Place"
        }
    ],
    "sg:phone":"+1 434 696 2698",
    "sg:postcode":"23974",
    "sg:province":"VA",
    "wof:name":"Lunenburg Cnty Victim Witness",
    "wof:placetype":"venue"
},
  "geometry": {"coordinates":[-78.227073,36.994597],"type":"Point"}
}