{
  "type": "Feature",
  "properties": {
    "addr:full":"11812 Main St Fredericksburg VA 22408",
    "addr:housenumber":"11812",
    "addr:postcode":"22408",
    "addr:street":"Main St",
    "iso:country":"US",
    "sg:address":"11812 Main St",
    "sg:city":"Fredericksburg",
    "sg:classifiers":[
        {
            "category":"Freight",
            "type":"Transportation"
        }
    ],
    "sg:phone":"+1 540 373 8830",
    "sg:postcode":"22408",
    "sg:province":"VA",
    "sg:tags":[
        "moving",
        "company",
        "storage"
    ],
    "wof:name":"B & G Relocator Inc",
    "wof:placetype":"venue"
},
  "geometry": {"coordinates":[-77.447242,38.275878],"type":"Point"}
}