{
  "type": "Feature",
  "properties": {
    "addr:full":"9531 Cosby Mill Rd Quinton VA 23141",
    "addr:housenumber":"9531",
    "addr:postcode":"23141",
    "addr:street":"Cosby Mill Rd",
    "iso:country":"US",
    "sg:address":"9531 Cosby Mill Rd",
    "sg:city":"Quinton",
    "sg:classifiers":[
        {
            "category":"Building & Trades",
            "subcategory":"Construction",
            "type":"Services"
        }
    ],
    "sg:phone":"+1 804 932 3720",
    "sg:postcode":"23141",
    "sg:province":"VA",
    "sg:tags":[
        "contractor"
    ],
    "wof:name":"Parsley Brothers Construction",
    "wof:placetype":"venue"
},
  "geometry": {"coordinates":[-77.162678,37.54773],"type":"Point"}
}