{
  "type": "Feature",
  "properties": {
    "addr:full":"354 Campbell Hwy Rustburg VA 24588",
    "addr:housenumber":"354",
    "addr:postcode":"24588",
    "addr:street":"Campbell Hwy",
    "iso:country":"US",
    "sg:address":"354 Campbell Hwy",
    "sg:city":"Rustburg",
    "sg:classifiers":[
        {
            "category":"Wholesale",
            "subcategory":"Machinery & Supplies",
            "type":"Manufacturing & Wholesale Goods"
        }
    ],
    "sg:phone":"+1 434 332 3000",
    "sg:postcode":"24588",
    "sg:province":"VA",
    "sg:tags":[
        "repairing"
    ],
    "wof:name":"Scott Brothers",
    "wof:placetype":"venue"
},
  "geometry": {"coordinates":[-79.104533,37.28245],"type":"Point"}
}