{
  "type": "Feature",
  "properties": {
    "iso:country":"US",
    "sg:address":"8810 S Boones Trail Rd",
    "sg:city":"Richmond",
    "sg:classifiers":[
        {
            "category":"Retail",
            "subcategory":"Auto Repair",
            "type":"Services"
        }
    ],
    "sg:phone":"+1 804 232 2771",
    "sg:postcode":"23236",
    "sg:province":"VA",
    "sg:tags":[
        "general"
    ],
    "wof:name":"Dantzlers Auto Sales & Repair",
    "wof:placetype":"venue"
},
  "geometry": {"coordinates":[-77.554721,37.441002],"type":"Point"}
}