{
  "type": "Feature",
  "properties": {
    "addr:full":"106 Governors Dr Williamsburg VA 23185",
    "addr:housenumber":"106",
    "addr:postcode":"23185",
    "addr:street":"Governors Dr",
    "iso:country":"US",
    "sg:address":"106 Governors Dr",
    "sg:city":"Williamsburg",
    "sg:classifiers":[
        {
            "category":"Professional",
            "subcategory":"Business Services",
            "type":"Services"
        }
    ],
    "sg:phone":"+1 757 229 9563",
    "sg:postcode":"23185",
    "sg:province":"VA",
    "wof:name":"Stonecutter Designs",
    "wof:placetype":"venue"
},
  "geometry": {"coordinates":[-76.73008,37.259388],"type":"Point"}
}