{
  "type": "Feature",
  "properties": {
    "addr:full":"103 Hopewell St Hopewell VA 23860",
    "addr:housenumber":"103",
    "addr:postcode":"23860",
    "addr:street":"Hopewell St",
    "iso:country":"US",
    "sg:address":"103 Hopewell St",
    "sg:city":"Hopewell",
    "sg:classifiers":[
        {
            "category":"Government",
            "subcategory":"Office",
            "type":"Public Place"
        }
    ],
    "sg:phone":"+1 804 541 2296",
    "sg:postcode":"23860",
    "sg:province":"VA",
    "sg:tags":[
        "executive"
    ],
    "wof:name":"City Garage",
    "wof:placetype":"venue"
},
  "geometry": {"coordinates":[-77.28334099999999,37.304],"type":"Point"}
}