{
  "type": "Feature",
  "properties": {
    "iso:country":"US",
    "sg:address":"1200 Chesapeake Ave",
    "sg:city":"Chesapeake",
    "sg:classifiers":[
        {
            "category":"Social Services",
            "type":"Services"
        }
    ],
    "sg:phone":"+1 757 545 4911",
    "sg:postcode":"23324",
    "sg:province":"VA",
    "sg:tags":[
        "organization",
        "welfare"
    ],
    "wof:name":"Widowed Person Svc",
    "wof:placetype":"venue"
},
  "geometry": {"coordinates":[-76.271714,36.814378],"type":"Point"}
}