{
  "type": "Feature",
  "properties": {
    "addr:full":"702 Chalfonte Dr Alexandria VA 22305",
    "addr:housenumber":"702",
    "addr:postcode":"22305",
    "addr:street":"Chalfonte Dr",
    "iso:country":"US",
    "sg:address":"702 Chalfonte Dr",
    "sg:city":"Alexandria",
    "sg:classifiers":[
        {
            "category":"Professional",
            "subcategory":"Management & Consulting",
            "type":"Services"
        }
    ],
    "sg:phone":"+1 703 683 6466",
    "sg:postcode":"22305",
    "sg:province":"VA",
    "sg:tags":[
        "business"
    ],
    "wof:name":"F B Systems Inc",
    "wof:placetype":"venue"
},
  "geometry": {"coordinates":[-77.072579,38.835944],"type":"Point"}
}