{
  "type": "Feature",
  "properties": {
    "iso:country":"US",
    "sg:address":"501 Front St",
    "sg:city":"Norfolk",
    "sg:classifiers":[
        {
            "category":"Professional",
            "subcategory":"Management & Consulting",
            "type":"Services"
        }
    ],
    "sg:phone":"+1 757 622 7382",
    "sg:postcode":"23510",
    "sg:province":"VA",
    "sg:tags":[
        "marketing",
        "program"
    ],
    "sg:website":"www.peta.org",
    "wof:name":"People For Ethical Treatment",
    "wof:placetype":"venue"
},
  "geometry": {"coordinates":[-76.300163,36.854746],"type":"Point"}
}