{
  "type": "Feature",
  "properties": {
    "addr:full":"601 W City Point Rd Hopewell VA 23860",
    "addr:housenumber":"601",
    "addr:postcode":"23860",
    "addr:street":"W City Point Rd",
    "iso:country":"US",
    "sg:address":"601 W City Point Rd",
    "sg:city":"Hopewell",
    "sg:classifiers":[
        {
            "category":"Shopping",
            "subcategory":"Pharmacy",
            "type":"Retail Goods"
        }
    ],
    "sg:phone":"+1 804 458 9555",
    "sg:postcode":"23860",
    "sg:province":"VA",
    "wof:name":"Central Drug Inc",
    "wof:placetype":"venue"
},
  "geometry": {"coordinates":[-77.29264499999999,37.301307],"type":"Point"}
}