{
  "type": "Feature",
  "properties": {
    "addr:full":"22590 Cedar Green Rd Sterling VA 20166",
    "addr:housenumber":"22590",
    "addr:postcode":"20166",
    "addr:street":"Cedar Green Rd",
    "iso:country":"US",
    "sg:address":"22590 Cedar Green Rd",
    "sg:city":"Sterling",
    "sg:classifiers":[
        {
            "category":"Organizations",
            "subcategory":"Religious Organization",
            "type":"Services"
        }
    ],
    "sg:phone":"+1 703 375 0000",
    "sg:postcode":"20166",
    "sg:province":"VA",
    "wof:name":"Metro Morning Star",
    "wof:placetype":"venue"
},
  "geometry": {"coordinates":[-77.43362399999999,38.995433],"type":"Point"}
}