{
  "type": "Feature",
  "properties": {
    "iso:country":"US",
    "sg:address":"5714 Center Ln",
    "sg:city":"Falls Church",
    "sg:classifiers":[
        {
            "category":"Professional",
            "type":"Services"
        }
    ],
    "sg:phone":"+1 703 845 9502",
    "sg:postcode":"22041",
    "sg:province":"VA",
    "sg:tags":[
        "establishment"
    ],
    "wof:name":"Nick Zavolas Ta",
    "wof:placetype":"venue"
},
  "geometry": {"coordinates":[-77.130297,38.847561],"type":"Point"}
}