{
  "type": "Feature",
  "properties": {
    "iso:country":"US",
    "sg:address":"1725 Park Ave SW",
    "sg:city":"Norton",
    "sg:classifiers":[
        {
            "category":"Government",
            "subcategory":"Office",
            "type":"Public Place"
        }
    ],
    "sg:phone":"+1 276 679 9417",
    "sg:postcode":"24273",
    "sg:province":"VA",
    "sg:tags":[
        "state",
        "resource"
    ],
    "wof:name":"Unemployment Insurance Svc",
    "wof:placetype":"venue"
},
  "geometry": {"coordinates":[-82.64877799999999,36.930707],"type":"Point"}
}