{
  "type": "Feature",
  "properties": {
    "addr:full":"574 Ridge Rd Fairfield VA 24435",
    "addr:housenumber":"574",
    "addr:postcode":"24435",
    "addr:street":"Ridge Rd",
    "iso:country":"US",
    "sg:address":"574 Ridge Rd",
    "sg:city":"Fairfield",
    "sg:classifiers":[
        {
            "category":"Building & Trades",
            "subcategory":"Construction",
            "type":"Services"
        }
    ],
    "sg:phone":"+1 540 348 5143",
    "sg:postcode":"24435",
    "sg:province":"VA",
    "sg:tags":[
        "contractor"
    ],
    "wof:name":"Swisher Fencing",
    "wof:placetype":"venue"
},
  "geometry": {"coordinates":[-79.286288,37.887511],"type":"Point"}
}