{
  "type": "Feature",
  "properties": {
    "addr:full":"317 Cleveland Ave Lynchburg VA 24503",
    "addr:housenumber":"317",
    "addr:postcode":"24503",
    "addr:street":"Cleveland Ave",
    "iso:country":"US",
    "sg:address":"317 Cleveland Ave",
    "sg:city":"Lynchburg",
    "sg:classifiers":[
        {
            "category":"Building & Trades",
            "subcategory":"Construction",
            "type":"Services"
        }
    ],
    "sg:phone":"+1 434 846 7858",
    "sg:postcode":"24503",
    "sg:province":"VA",
    "sg:tags":[
        "restoration",
        "preservation"
    ],
    "sg:website":"www.lynchburgrestoration.com",
    "wof:name":"Lynchburg Restoration Inc",
    "wof:placetype":"venue"
},
  "geometry": {"coordinates":[-79.165752,37.433768],"type":"Point"}
}