{
  "type": "Feature",
  "properties": {
    "addr:full":"13 N 5th St Richmond VA 23219",
    "addr:housenumber":"13",
    "addr:postcode":"23219",
    "addr:street":"N 5Th St",
    "iso:country":"US",
    "sg:address":"13 N 5th St",
    "sg:city":"Richmond",
    "sg:classifiers":[
        {
            "category":"Parking",
            "type":"Transportation"
        }
    ],
    "sg:phone":"+1 804 780 1691",
    "sg:postcode":"23219",
    "sg:province":"VA",
    "sg:tags":[
        "garage"
    ],
    "wof:name":"Monument City Parking Inc",
    "wof:placetype":"venue"
},
  "geometry": {"coordinates":[-77.43910200000001,37.541079],"type":"Point"}
}