{
  "type": "Feature",
  "properties": {
    "addr:full":"5105 Overlook Park Annandale VA 22003",
    "addr:housenumber":"5105",
    "addr:postcode":"22003",
    "addr:street":"Overlook Park",
    "iso:country":"US",
    "sg:address":"5105 Overlook Park",
    "sg:city":"Annandale",
    "sg:classifiers":[
        {
            "category":"Professional",
            "type":"Services"
        }
    ],
    "sg:phone":"+1 703 764 0913",
    "sg:postcode":"22003",
    "sg:province":"VA",
    "wof:name":"Sean Trent",
    "wof:placetype":"venue"
},
  "geometry": {"coordinates":[-77.23103399999999,38.813287],"type":"Point"}
}