{
  "type": "Feature",
  "properties": {
    "addr:full":"2786 Martinsburg Pike Stephenson VA 22656",
    "addr:housenumber":"2786",
    "addr:postcode":"22656",
    "addr:street":"Martinsburg Pike",
    "iso:country":"US",
    "sg:address":"2786 Martinsburg Pike",
    "sg:city":"Stephenson",
    "sg:classifiers":[
        {
            "category":"Building & Trades",
            "subcategory":"Construction",
            "type":"Services"
        }
    ],
    "sg:phone":"+1 540 662 4008",
    "sg:postcode":"22656",
    "sg:province":"VA",
    "sg:tags":[
        "general",
        "contractor"
    ],
    "wof:name":"APAC Virginia Inc",
    "wof:placetype":"venue"
},
  "geometry": {"coordinates":[-78.10845500000001,39.238983],"type":"Point"}
}