{
  "type": "Feature",
  "properties": {
    "iso:country":"US",
    "sg:address":"6121 Lincolnia Rd",
    "sg:city":"Alexandria",
    "sg:classifiers":[
        {
            "category":"Professional",
            "subcategory":"Management & Consulting",
            "type":"Services"
        }
    ],
    "sg:phone":"+1 703 256 8900",
    "sg:postcode":"22312",
    "sg:province":"VA",
    "sg:tags":[
        "consultant",
        "training"
    ],
    "sg:website":"www.navtechgps.com",
    "wof:name":"Navtech Seminars & Gps Supply",
    "wof:placetype":"venue"
},
  "geometry": {"coordinates":[-77.13580399999999,38.818381],"type":"Point"}
}