{
  "type": "Feature",
  "properties": {
    "iso:country":"US",
    "sg:address":"500 E Main St",
    "sg:city":"Norfolk",
    "sg:classifiers":[
        {
            "category":"Education",
            "subcategory":"Special Training",
            "type":"Public Place"
        }
    ],
    "sg:phone":"+1 757 314 4466",
    "sg:postcode":"23510",
    "sg:province":"VA",
    "sg:tags":[
        "general",
        "government"
    ],
    "wof:name":"Institute For Defense Analyses",
    "wof:placetype":"venue"
},
  "geometry": {"coordinates":[-76.28848499999999,36.845811],"type":"Point"}
}