{
  "type": "Feature",
  "properties": {
    "iso:country":"US",
    "sg:address":"1464 S Military Hwy",
    "sg:city":"Chesapeake",
    "sg:classifiers":[
        {
            "category":"Retail",
            "subcategory":"Auto Repair",
            "type":"Services"
        }
    ],
    "sg:phone":"+1 757 420 2846",
    "sg:postcode":"23320",
    "sg:province":"VA",
    "sg:tags":[
        "muffler",
        "exhaust",
        "brake",
        "system"
    ],
    "wof:name":"Stan's Muffler & Brake",
    "wof:placetype":"venue"
},
  "geometry": {"coordinates":[-76.233735,36.798024],"type":"Point"}
}