{
  "type": "Feature",
  "properties": {
    "iso:country":"US",
    "sg:address":"5408 Port Royal Rd",
    "sg:city":"Springfield",
    "sg:classifiers":[
        {
            "category":"Manufacturing",
            "subcategory":"Printing",
            "type":"Manufacturing & Wholesale Goods"
        }
    ],
    "sg:phone":"+1 703 321 8400",
    "sg:postcode":"22151",
    "sg:province":"VA",
    "sg:tags":[
        "printer"
    ],
    "wof:name":"X Ray Visions LLC",
    "wof:placetype":"venue"
},
  "geometry": {"coordinates":[-77.214775,38.804134],"type":"Point"}
}