{
  "type": "Feature",
  "properties": {
    "addr:full":"306 E Broad St Richmond VA 23219",
    "addr:housenumber":"306",
    "addr:postcode":"23219",
    "addr:street":"E Broad St",
    "iso:country":"US",
    "sg:address":"306 E Broad St",
    "sg:city":"Richmond",
    "sg:classifiers":[
        {
            "category":"Restaurant",
            "type":"Food & Drink"
        }
    ],
    "sg:phone":"+1 804 644 6916",
    "sg:postcode":"23219",
    "sg:province":"VA",
    "sg:tags":[
        "eating"
    ],
    "wof:name":"King's Fish & Chicken",
    "wof:placetype":"venue"
},
  "geometry": {"coordinates":[-77.43840299999999,37.543518],"type":"Point"}
}