{
  "type": "Feature",
  "properties": {
    "iso:country":"US",
    "sg:address":"12039 Creekbend Dr",
    "sg:city":"Reston",
    "sg:classifiers":[
        {
            "category":"Professional",
            "subcategory":"Engineering",
            "type":"Services"
        }
    ],
    "sg:phone":"+1 571 203 0330",
    "sg:postcode":"20194",
    "sg:province":"VA",
    "sg:tags":[
        "engineer"
    ],
    "wof:name":"Scientech Inc",
    "wof:placetype":"venue"
},
  "geometry": {"coordinates":[-77.36514,38.97715],"type":"Point"}
}