{
  "type": "Feature",
  "properties": {
    "iso:country":"US",
    "sg:address":"5510 Cherokee Ave",
    "sg:city":"Alexandria",
    "sg:classifiers":[
        {
            "category":"Professional",
            "subcategory":"Business Services",
            "type":"Services"
        },
        {
            "category":"Professional",
            "subcategory":"Art Services",
            "type":"Services"
        }
    ],
    "sg:phone":"+1 703 642 6505",
    "sg:postcode":"22312",
    "sg:province":"VA",
    "sg:tags":[
        "facility",
        "commercial",
        "motion",
        "design",
        "convention",
        "prod",
        "meeting"
    ],
    "sg:website":"www.lmpdg.com",
    "wof:name":"L & M Production Design Group",
    "wof:placetype":"venue"
},
  "geometry": {"coordinates":[-77.165696,38.804136],"type":"Point"}
}