{
  "type": "Feature",
  "properties": {
    "addr:full":"2500 John Milton Dr Herndon VA 20171",
    "addr:housenumber":"2500",
    "addr:postcode":"20171",
    "addr:street":"John Milton Dr",
    "iso:country":"US",
    "sg:address":"2500 John Milton Dr",
    "sg:city":"Herndon",
    "sg:classifiers":[
        {
            "category":"Personal",
            "subcategory":"Beauty Salon",
            "type":"Services"
        }
    ],
    "sg:phone":"+1 703 860 0480",
    "sg:postcode":"20171",
    "sg:province":"VA",
    "wof:name":"Hair Cuttery",
    "wof:placetype":"venue"
},
  "geometry": {"coordinates":[-77.37735499999999,38.927468],"type":"Point"}
}