{
  "type": "Feature",
  "properties": {
    "addr:full":"74 Dishpan Ln Stafford VA 22554",
    "addr:housenumber":"74",
    "addr:postcode":"22554",
    "addr:street":"Dishpan Ln",
    "iso:country":"US",
    "sg:address":"74 Dishpan Ln",
    "sg:city":"Stafford",
    "sg:classifiers":[
        {
            "category":"Professional",
            "type":"Services"
        }
    ],
    "sg:phone":"+1 540 659 0130",
    "sg:postcode":"22554",
    "sg:province":"VA",
    "sg:tags":[
        "sculptor"
    ],
    "wof:name":"VIA Gambaro Studios Inc",
    "wof:placetype":"venue"
},
  "geometry": {"coordinates":[-77.395475,38.398202],"type":"Point"}
}