{
  "type": "Feature",
  "properties": {
    "iso:country":"US",
    "sg:address":"101 E Oldtown St",
    "sg:city":"Galax",
    "sg:classifiers":[
        {
            "category":"Cafe",
            "type":"Food & Drink"
        }
    ],
    "sg:menulink":"http://www.allmenus.com/va/galax/286066-crawdaddys-cajun-cafe/menu/",
    "sg:phone":"+1 276 236 2384",
    "sg:postcode":"24333",
    "sg:province":"VA",
    "sg:tags":[
        "american",
        "creole",
        "cajun"
    ],
    "wof:name":"Crawdaddy's Cajun Cafe",
    "wof:placetype":"venue"
},
  "geometry": {"coordinates":[-80.92438,36.661065],"type":"Point"}
}