{
  "type": "Feature",
  "properties": {
    "addr:full":"108 Main St Smithfield VA 23430",
    "addr:housenumber":"108",
    "addr:postcode":"23430",
    "addr:street":"Main St",
    "iso:country":"US",
    "sg:address":"108 Main St",
    "sg:city":"Smithfield",
    "sg:classifiers":[
        {
            "category":"Shopping",
            "type":"Retail Goods"
        }
    ],
    "sg:phone":"+1 757 357 7891",
    "sg:postcode":"23430",
    "sg:province":"VA",
    "sg:tags":[
        "outdoor",
        "lighting",
        "specialty"
    ],
    "wof:name":"Christmas Store",
    "wof:placetype":"venue"
},
  "geometry": {"coordinates":[-76.631134,36.982311],"type":"Point"}
}