{
  "type": "Feature",
  "properties": {
    "addr:full":"565 E Main St Wytheville VA 24382",
    "addr:housenumber":"565",
    "addr:postcode":"24382",
    "addr:street":"E Main St",
    "iso:country":"US",
    "sg:address":"565 E Main St",
    "sg:city":"Wytheville",
    "sg:classifiers":[
        {
            "category":"Utilities",
            "subcategory":"Cable",
            "type":"Services"
        }
    ],
    "sg:phone":"+1 276 228 6144",
    "sg:postcode":"24382",
    "sg:province":"VA",
    "sg:tags":[
        "television"
    ],
    "wof:name":"Charter Cmmnctons Holdings LLC",
    "wof:placetype":"venue"
},
  "geometry": {"coordinates":[-81.071067,36.951951],"type":"Point"}
}