{
  "type": "Feature",
  "properties": {
    "iso:country":"US",
    "sg:address":"196 Van Buren St",
    "sg:city":"Herndon",
    "sg:classifiers":[
        {
            "category":"Professional",
            "subcategory":"Advertising",
            "type":"Services"
        }
    ],
    "sg:phone":"+1 703 450 5777",
    "sg:postcode":"20170",
    "sg:province":"VA",
    "sg:tags":[
        "international",
        "mailing"
    ],
    "wof:name":"First Cnada Drect Mailing Svcs",
    "wof:placetype":"venue"
},
  "geometry": {"coordinates":[-77.388375,38.956373],"type":"Point"}
}