{
  "type": "Feature",
  "properties": {
    "addr:full":"204 Garrisonville Rd Stafford VA 22554",
    "addr:housenumber":"204",
    "addr:postcode":"22554",
    "addr:street":"Garrisonville Rd",
    "iso:country":"US",
    "sg:address":"204 Garrisonville Rd",
    "sg:city":"Stafford",
    "sg:classifiers":[
        {
            "category":"Retail",
            "subcategory":"Auto Repair",
            "type":"Services"
        }
    ],
    "sg:phone":"+1 540 720 3497",
    "sg:postcode":"22554",
    "sg:province":"VA",
    "sg:tags":[
        "automotive"
    ],
    "wof:name":"Jiffy Lube",
    "wof:placetype":"venue"
},
  "geometry": {"coordinates":[-77.414852,38.471736],"type":"Point"}
}