{
  "type": "Feature",
  "properties": {
    "iso:country":"US",
    "sg:address":"4810 Oak Level Rd",
    "sg:city":"Bassett",
    "sg:classifiers":[
        {
            "category":"Building & Trades",
            "subcategory":"Electrical",
            "type":"Services"
        }
    ],
    "sg:phone":"+1 276 629 5113",
    "sg:postcode":"24055",
    "sg:province":"VA",
    "sg:tags":[
        "electrical",
        "contractor"
    ],
    "wof:name":"Leon Ratliff Electric",
    "wof:placetype":"venue"
},
  "geometry": {"coordinates":[-79.945376,36.770277],"type":"Point"}
}