{
  "type": "Feature",
  "properties": {
    "addr:full":"584 Wolf Gap Rd Edinburg VA 22824",
    "addr:housenumber":"584",
    "addr:postcode":"22824",
    "addr:street":"Wolf Gap Rd",
    "iso:country":"US",
    "sg:address":"584 Wolf Gap Rd",
    "sg:city":"Edinburg",
    "sg:classifiers":[
        {
            "category":"Building & Trades",
            "subcategory":"Construction",
            "type":"Services"
        }
    ],
    "sg:phone":"+1 540 984 9222",
    "sg:postcode":"22824",
    "sg:province":"VA",
    "sg:tags":[
        "house"
    ],
    "wof:name":"Final Touch Construction",
    "wof:placetype":"venue"
},
  "geometry": {"coordinates":[-78.63036700000001,38.882226],"type":"Point"}
}