{
  "type": "Feature",
  "properties": {
    "addr:full":"11200 Leadbetter Rd Ashland VA 23005",
    "addr:housenumber":"11200",
    "addr:postcode":"23005",
    "addr:street":"Leadbetter Rd",
    "iso:country":"US",
    "sg:address":"11200 Leadbetter Rd",
    "sg:city":"Ashland",
    "sg:classifiers":[
        {
            "category":"Professional",
            "subcategory":"Computer Services",
            "type":"Services"
        }
    ],
    "sg:phone":"+1 804 798 8558",
    "sg:postcode":"23005",
    "sg:province":"VA",
    "wof:name":"Tabb Computer Svc",
    "wof:placetype":"venue"
},
  "geometry": {"coordinates":[-77.44325000000001,37.709001],"type":"Point"}
}