{
  "type": "Feature",
  "properties": {
    "addr:full":"1310 Whitby Rd Richmond VA 23227",
    "addr:housenumber":"1310",
    "addr:postcode":"23227",
    "addr:street":"Whitby Rd",
    "iso:country":"US",
    "sg:address":"1310 Whitby Rd",
    "sg:city":"Richmond",
    "sg:classifiers":[
        {
            "category":"Social Services",
            "subcategory":"Job Training",
            "type":"Services"
        }
    ],
    "sg:phone":"+1 804 354 9953",
    "sg:postcode":"23227",
    "sg:province":"VA",
    "wof:name":"Ntc/Resource Center",
    "wof:placetype":"venue"
},
  "geometry": {"coordinates":[-77.45324100000001,37.574255],"type":"Point"}
}