{
  "type": "Feature",
  "properties": {
    "addr:full":"1017 Southam Dr Richmond VA 23235",
    "addr:housenumber":"1017",
    "addr:postcode":"23235",
    "addr:street":"Southam Dr",
    "iso:country":"US",
    "sg:address":"1017 Southam Dr",
    "sg:city":"Richmond",
    "sg:classifiers":[
        {
            "category":"Organizations",
            "subcategory":"Community Association",
            "type":"Services"
        }
    ],
    "sg:phone":"+1 804 272 0810",
    "sg:postcode":"23235",
    "sg:province":"VA",
    "wof:name":"Scottish Society of Richmond",
    "wof:placetype":"venue"
},
  "geometry": {"coordinates":[-77.539906,37.51232],"type":"Point"}
}