{
  "type": "Feature",
  "properties": {
    "iso:country":"US",
    "sg:address":"8300 Sudley Rd",
    "sg:city":"Manassas",
    "sg:classifiers":[
        {
            "category":"Shopping",
            "subcategory":"Bicycles & Sporting Goods",
            "type":"Retail Goods"
        }
    ],
    "sg:phone":"+1 703 330 1958",
    "sg:postcode":"20109",
    "sg:province":"VA",
    "wof:name":"Champs Sports",
    "wof:placetype":"venue"
},
  "geometry": {"coordinates":[-77.502818,38.774966],"type":"Point"}
}