{
  "type": "Feature",
  "properties": {
    "iso:country":"US",
    "sg:address":"908 Cedar Creek Grade",
    "sg:city":"Winchester",
    "sg:classifiers":[
        {
            "category":"Home & Garden",
            "subcategory":"Garden Supply",
            "type":"Retail Goods"
        }
    ],
    "sg:phone":"+1 540 869 2115",
    "sg:postcode":"22601",
    "sg:province":"VA",
    "sg:tags":[
        "nursery"
    ],
    "wof:name":"Hortons Nursery Inc",
    "wof:placetype":"venue"
},
  "geometry": {"coordinates":[-78.191287,39.163407],"type":"Point"}
}