{
  "type": "Feature",
  "properties": {
    "iso:country":"US",
    "sg:address":"9751 Center St",
    "sg:city":"Manassas",
    "sg:classifiers":[
        {
            "category":"Retail",
            "subcategory":"Repair Shop",
            "type":"Services"
        }
    ],
    "sg:phone":"+1 703 530 9220",
    "sg:postcode":"20110",
    "sg:province":"VA",
    "sg:tags":[
        "equipment",
        "industrial"
    ],
    "wof:name":"B & L Lawn Mower Co",
    "wof:placetype":"venue"
},
  "geometry": {"coordinates":[-77.48953400000001,38.753365],"type":"Point"}
}