{
  "type": "Feature",
  "properties": {
    "addr:full":"1574 Roanoke Blvd Salem VA 24153",
    "addr:housenumber":"1574",
    "addr:postcode":"24153",
    "addr:street":"Roanoke Blvd",
    "iso:country":"US",
    "sg:address":"1574 Roanoke Blvd",
    "sg:city":"Salem",
    "sg:classifiers":[
        {
            "category":"Social Services",
            "subcategory":"Child Care",
            "type":"Services"
        }
    ],
    "sg:phone":"+1 540 387 1523",
    "sg:postcode":"24153",
    "sg:province":"VA",
    "sg:tags":[
        "day"
    ],
    "sg:website":"www.salemmontessori.org",
    "wof:name":"Salem Montessori School",
    "wof:placetype":"venue"
},
  "geometry": {"coordinates":[-80.031963,37.277678],"type":"Point"}
}