{
  "type": "Feature",
  "properties": {
    "addr:full":"1681 Big Spring Dr Elliston VA 24087",
    "addr:housenumber":"1681",
    "addr:postcode":"24087",
    "addr:street":"Big Spring Dr",
    "iso:country":"US",
    "sg:address":"1681 Big Spring Dr",
    "sg:city":"Elliston",
    "sg:classifiers":[
        {
            "category":"Government",
            "subcategory":"Post Office",
            "type":"Public Place"
        }
    ],
    "sg:phone":"+1 540 000 1111",
    "sg:postcode":"24087",
    "sg:province":"VA",
    "wof:name":"US Post Office",
    "wof:placetype":"venue"
},
  "geometry": {"coordinates":[-80.23297100000001,37.215968],"type":"Point"}
}