{
  "type": "Feature",
  "properties": {
    "addr:full":"700 N Fairfax St Alexandria VA 22314",
    "addr:housenumber":"700",
    "addr:postcode":"22314",
    "addr:street":"N Fairfax St",
    "iso:country":"US",
    "sg:address":"700 N Fairfax St",
    "sg:city":"Alexandria",
    "sg:classifiers":[
        {
            "category":"Recreation",
            "type":"Entertainment"
        }
    ],
    "sg:phone":"+1 703 548 3303",
    "sg:postcode":"22314",
    "sg:province":"VA",
    "wof:name":"Interntnal Exhbtons Fundations",
    "wof:placetype":"venue"
},
  "geometry": {"coordinates":[-77.04083199999999,38.812458],"type":"Point"}
}