{
  "type": "Feature",
  "properties": {
    "iso:country":"US",
    "sg:address":"2917 Nicholas Ave NE",
    "sg:city":"Roanoke",
    "sg:classifiers":[
        {
            "category":"Wholesale",
            "subcategory":"Machinery & Supplies",
            "type":"Manufacturing & Wholesale Goods"
        }
    ],
    "sg:phone":"+1 540 342 7871",
    "sg:postcode":"24012",
    "sg:province":"VA",
    "sg:tags":[
        "carnival"
    ],
    "sg:website":"www.seskate.com",
    "wof:name":"Southeastern Skate Supply",
    "wof:placetype":"venue"
},
  "geometry": {"coordinates":[-79.902317,37.30519],"type":"Point"}
}