{
  "type": "Feature",
  "properties": {
    "iso:country":"US",
    "sg:address":"3809 Piping Rock Ln",
    "sg:city":"Virginia Beach",
    "sg:classifiers":[
        {
            "category":"Real Estate",
            "subcategory":"Real Estate Agent",
            "type":"Services"
        }
    ],
    "sg:phone":"+1 757 340 4060",
    "sg:postcode":"23452",
    "sg:province":"VA",
    "sg:tags":[
        "security"
    ],
    "wof:name":"Louis Weinstein",
    "wof:placetype":"venue"
},
  "geometry": {"coordinates":[-76.105007,36.821064],"type":"Point"}
}