{
  "type": "Feature",
  "properties": {
    "addr:full":"702 E Main St Radford VA 24141",
    "addr:housenumber":"702",
    "addr:postcode":"24141",
    "addr:street":"E Main St",
    "iso:country":"US",
    "sg:address":"702 E Main St",
    "sg:city":"Radford",
    "sg:classifiers":[
        {
            "category":"Bars & Pubs",
            "type":"Food & Drink"
        },
        {
            "category":"Restaurant",
            "type":"Food & Drink"
        }
    ],
    "sg:phone":"+1 540 639 2345",
    "sg:postcode":"24141",
    "sg:province":"VA",
    "sg:tags":[
        "brew",
        "asian",
        "chinese",
        "pan"
    ],
    "wof:name":"Canton Restaurant",
    "wof:placetype":"venue"
},
  "geometry": {"coordinates":[-80.545907,37.137873],"type":"Point"}
}