{
  "type": "Feature",
  "properties": {
    "iso:country":"US",
    "sg:address":"501 S Hill Ave",
    "sg:city":"South Hill",
    "sg:classifiers":[
        {
            "category":"Insurance",
            "subcategory":"Insurance Agent",
            "type":"Services"
        }
    ],
    "sg:phone":"+1 434 447 3089",
    "sg:postcode":"23970",
    "sg:province":"VA",
    "wof:name":"AFLAC",
    "wof:placetype":"venue"
},
  "geometry": {"coordinates":[-78.131534,36.722659],"type":"Point"}
}