{
  "type": "Feature",
  "properties": {
    "addr:full":"1775 Tower Rd Norlina VA 27563",
    "addr:housenumber":"1775",
    "addr:postcode":"27563",
    "addr:street":"Tower Rd",
    "iso:country":"US",
    "sg:address":"1775 Tower Rd",
    "sg:city":"Norlina",
    "sg:classifiers":[
        {
            "category":"Retail",
            "subcategory":"Auto Repair",
            "type":"Services"
        }
    ],
    "sg:phone":"+1   ",
    "sg:postcode":"27563",
    "sg:province":"VA",
    "sg:tags":[
        "body"
    ],
    "wof:name":"Auto Body By Fred Appraisal Sv",
    "wof:placetype":"venue"
},
  "geometry": {"coordinates":[-78.239918,36.348511],"type":"Point"}
}