{
  "type": "Feature",
  "properties": {
    "addr:full":"1108 E Bay Shore Dr Virginia Beach VA 23451",
    "addr:housenumber":"1108",
    "addr:postcode":"23451",
    "addr:street":"E Bay Shore Dr",
    "iso:country":"US",
    "sg:address":"1108 E Bay Shore Dr",
    "sg:city":"Virginia Beach",
    "sg:classifiers":[
        {
            "category":"Health Services",
            "subcategory":"Doctor",
            "type":"Services"
        }
    ],
    "sg:phone":"+1 757 422 9246",
    "sg:postcode":"23451",
    "sg:province":"VA",
    "sg:tags":[
        "physician",
        "surgeon"
    ],
    "wof:name":"John A Byrd MD",
    "wof:placetype":"venue"
},
  "geometry": {"coordinates":[-75.99531500000001,36.872002],"type":"Point"}
}