{
  "type": "Feature",
  "properties": {
    "addr:full":"211 Water Country Pkwy Williamsburg VA 23185",
    "addr:housenumber":"211",
    "addr:postcode":"23185",
    "addr:street":"Water Country Pkwy",
    "iso:country":"US",
    "sg:address":"211 Water Country Pkwy",
    "sg:city":"Williamsburg",
    "sg:classifiers":[
        {
            "category":"Real Estate",
            "subcategory":"Developer",
            "type":"Services"
        }
    ],
    "sg:phone":"+1 757 564 3503",
    "sg:postcode":"23185",
    "sg:province":"VA",
    "wof:name":"FCR Group Inc",
    "wof:placetype":"venue"
},
  "geometry": {"coordinates":[-76.642521,37.261832],"type":"Point"}
}