{
  "type": "Feature",
  "properties": {
    "addr:full":"11017 Becontree Lake Dr Reston VA 20190",
    "addr:housenumber":"11017",
    "addr:postcode":"20190",
    "addr:street":"Becontree Lake Dr",
    "iso:country":"US",
    "sg:address":"11017 Becontree Lake Dr",
    "sg:city":"Reston",
    "sg:classifiers":[
        {
            "category":"Professional",
            "subcategory":"Management & Consulting",
            "type":"Services"
        }
    ],
    "sg:phone":"+1 703 790 8870",
    "sg:postcode":"20190",
    "sg:province":"VA",
    "wof:name":"Elite Transportation Service",
    "wof:placetype":"venue"
},
  "geometry": {"coordinates":[-77.326019,38.965745],"type":"Point"}
}