{
  "type": "Feature",
  "properties": {
    "addr:full":"1300 17th St N Ste 1847 Arlington VA 22209",
    "addr:housenumber":"1300",
    "addr:postcode":"22209",
    "addr:street":"17Th St N Ste 1847",
    "iso:country":"US",
    "sg:address":"1300 17th St N Ste 1847",
    "sg:city":"Arlington",
    "sg:classifiers":[
        {
            "category":"Organizations",
            "subcategory":"Community Association",
            "type":"Services"
        }
    ],
    "sg:phone":"+1 703 841 3277",
    "sg:postcode":"22209",
    "sg:province":"VA",
    "sg:tags":[
        "club"
    ],
    "wof:name":"American National Lighting Group",
    "wof:placetype":"venue"
},
  "geometry": {"coordinates":[-77.072739,38.894058],"type":"Point"}
}