{
  "type": "Feature",
  "properties": {
    "addr:full":"9702 Gayton Rd Ste 111 Henrico VA 23238",
    "addr:housenumber":"9702",
    "addr:postcode":"23238",
    "addr:street":"Gayton Rd Ste 111",
    "iso:country":"US",
    "sg:address":"9702 Gayton Rd Ste 111",
    "sg:city":"Henrico",
    "sg:classifiers":[
        {
            "category":"Real Estate",
            "subcategory":"Real Estate Services",
            "type":"Services"
        }
    ],
    "sg:phone":"+1 804 741 1883",
    "sg:postcode":"23238",
    "sg:province":"VA",
    "sg:tags":[
        "management"
    ],
    "wof:name":"Rick Curry",
    "wof:placetype":"venue"
},
  "geometry": {"coordinates":[-77.591796,37.603808],"type":"Point"}
}