{
  "type": "Feature",
  "properties": {
    "addr:full":"6006 Loretto St Springfield VA 22150",
    "addr:housenumber":"6006",
    "addr:postcode":"22150",
    "addr:street":"Loretto St",
    "iso:country":"US",
    "sg:address":"6006 Loretto St",
    "sg:city":"Springfield",
    "sg:classifiers":[
        {
            "category":"Restaurant",
            "type":"Food & Drink"
        }
    ],
    "sg:phone":"+1 703 866 2773",
    "sg:postcode":"22150",
    "sg:province":"VA",
    "sg:tags":[
        "eating"
    ],
    "wof:name":"Whats Brewing Coffee",
    "wof:placetype":"venue"
},
  "geometry": {"coordinates":[-77.205645,38.786742],"type":"Point"}
}