{
  "type": "Feature",
  "properties": {
    "addr:full":"1243 Maple View Dr Charlottesville VA 22902",
    "addr:housenumber":"1243",
    "addr:postcode":"22902",
    "addr:street":"Maple View Dr",
    "iso:country":"US",
    "sg:address":"1243 Maple View Dr",
    "sg:city":"Charlottesville",
    "sg:classifiers":[
        {
            "category":"Professional",
            "type":"Services"
        }
    ],
    "sg:phone":"+1 434 984 2144",
    "sg:postcode":"22902",
    "sg:province":"VA",
    "wof:name":"Belles Lettres Inc",
    "wof:placetype":"venue"
},
  "geometry": {"coordinates":[-78.485793,38.001567],"type":"Point"}
}