{
  "type": "Feature",
  "properties": {
    "iso:country":"US",
    "sg:address":"8550 Leesburg Pike",
    "sg:city":"Vienna",
    "sg:classifiers":[
        {
            "category":"Insurance",
            "subcategory":"Insurance Agent",
            "type":"Services"
        }
    ],
    "sg:phone":"+1 703 288 0038",
    "sg:postcode":"22182",
    "sg:province":"VA",
    "wof:name":"Geico Corp",
    "wof:placetype":"venue"
},
  "geometry": {"coordinates":[-77.241349,38.929016],"type":"Point"}
}