{
  "type": "Feature",
  "properties": {
    "addr:full":"123 S Columbus St Alexandria VA 22314",
    "addr:housenumber":"123",
    "addr:postcode":"22314",
    "addr:street":"S Columbus St",
    "iso:country":"US",
    "sg:address":"123 S Columbus St",
    "sg:city":"Alexandria",
    "sg:classifiers":[
        {
            "category":"Professional",
            "subcategory":"Lawyer & Legal Services",
            "type":"Services"
        }
    ],
    "sg:phone":"+1 703 299 1040",
    "sg:postcode":"22314",
    "sg:province":"VA",
    "sg:tags":[
        "attorney"
    ],
    "wof:name":"James K Lay Law Offices",
    "wof:placetype":"venue"
},
  "geometry": {"coordinates":[-77.048388,38.804338],"type":"Point"}
}