{
  "type": "Feature",
  "properties": {
    "addr:full":"350 Maple Ave W Vienna VA 22180",
    "addr:housenumber":"350",
    "addr:postcode":"22180",
    "addr:street":"Maple Ave W",
    "iso:country":"US",
    "sg:address":"350 Maple Ave W",
    "sg:city":"Vienna",
    "sg:classifiers":[
        {
            "category":"Food & Beverages",
            "subcategory":"Groceries & Convenience Stores",
            "type":"Retail Goods"
        }
    ],
    "sg:phone":"+1 703 319 0730",
    "sg:postcode":"22180",
    "sg:province":"VA",
    "sg:tags":[
        "grocers-specialty"
    ],
    "wof:name":"Taiasian Food Market",
    "wof:placetype":"venue"
},
  "geometry": {"coordinates":[-77.27089700000001,38.897018],"type":"Point"}
}