{
  "type": "Feature",
  "properties": {
    "iso:country":"US",
    "sg:address":"8310 Midlothian Tpke",
    "sg:city":"Richmond",
    "sg:classifiers":[
        {
            "category":"Professional",
            "subcategory":"Lawyer & Legal Services",
            "type":"Services"
        }
    ],
    "sg:phone":"+1 804 327 5761",
    "sg:postcode":"23235",
    "sg:province":"VA",
    "sg:tags":[
        "litigation",
        "tort",
        "attorney"
    ],
    "wof:name":"Picard, Barbara S - Cawthorn Picard & Rowe",
    "wof:placetype":"venue"
},
  "geometry": {"coordinates":[-77.551123,37.496269],"type":"Point"}
}