{
  "type": "Feature",
  "properties": {
    "iso:country":"US",
    "sg:address":"4620 Kenmore Ave",
    "sg:city":"Alexandria",
    "sg:classifiers":[
        {
            "category":"Sports & Exercise",
            "subcategory":"Gym",
            "type":"Entertainment"
        }
    ],
    "sg:phone":"+1 703 212 0123",
    "sg:postcode":"22304",
    "sg:province":"VA",
    "sg:website":"planetfitness.com/ClubOffers.asp...",
    "wof:name":"Planet Fitness",
    "wof:placetype":"venue"
},
  "geometry": {"coordinates":[-77.108982,38.829562],"type":"Point"}
}