{
  "type": "Feature",
  "properties": {
    "iso:country":"US",
    "sg:address":"507 N Military Hwy",
    "sg:city":"Norfolk",
    "sg:classifiers":[
        {
            "category":"Shopping",
            "subcategory":"Photographic Equipment",
            "type":"Retail Goods"
        }
    ],
    "sg:phone":"+1 757 461 2461",
    "sg:postcode":"23502",
    "sg:province":"VA",
    "sg:tags":[
        "repair",
        "supply"
    ],
    "wof:name":"Ritz Camera",
    "wof:placetype":"venue"
},
  "geometry": {"coordinates":[-76.210262,36.848986],"type":"Point"}
}