{
  "type": "Feature",
  "properties": {
    "addr:full":"3523 Mcdaniel Dr Salem VA 24153",
    "addr:housenumber":"3523",
    "addr:postcode":"24153",
    "addr:street":"Mcdaniel Dr",
    "iso:country":"US",
    "sg:address":"3523 Mcdaniel Dr",
    "sg:city":"Salem",
    "sg:classifiers":[
        {
            "category":"Health Services",
            "subcategory":"Dentist",
            "type":"Services"
        }
    ],
    "sg:phone":"+1 540 380 4667",
    "sg:postcode":"24153",
    "sg:province":"VA",
    "wof:name":"Clark Martin",
    "wof:placetype":"venue"
},
  "geometry": {"coordinates":[-80.118589,37.281455],"type":"Point"}
}