{
  "type": "Feature",
  "properties": {
    "iso:country":"US",
    "sg:address":"12363 Strong Ct",
    "sg:city":"Fairfax",
    "sg:classifiers":[
        {
            "category":"Professional",
            "subcategory":"Computer Services",
            "type":"Services"
        }
    ],
    "sg:phone":"+1 703 339 7221",
    "sg:postcode":"22033",
    "sg:province":"VA",
    "sg:tags":[
        "datum"
    ],
    "wof:name":"Fetch Media",
    "wof:placetype":"venue"
},
  "geometry": {"coordinates":[-77.372539,38.866114],"type":"Point"}
}