{
  "type": "Feature",
  "properties": {
    "addr:full":"2900 41st St Fort Lee VA 23801",
    "addr:housenumber":"2900",
    "addr:postcode":"23801",
    "addr:street":"41St St",
    "iso:country":"US",
    "sg:address":"2900 41st St",
    "sg:city":"Fort Lee",
    "sg:classifiers":[
        {
            "category":"Manufacturing",
            "subcategory":"Printing",
            "type":"Manufacturing & Wholesale Goods"
        }
    ],
    "sg:phone":"+1 804 734 2315",
    "sg:postcode":"23801",
    "sg:province":"VA",
    "sg:tags":[
        "lithographic",
        "commercial",
        "photocopying"
    ],
    "wof:name":"Field Printing",
    "wof:placetype":"venue"
},
  "geometry": {"coordinates":[-77.336488,37.216021],"type":"Point"}
}