{
  "type": "Feature",
  "properties": {
    "addr:full":"4301 Soundview Ln Chesterfield VA 23832",
    "addr:housenumber":"4301",
    "addr:postcode":"23832",
    "addr:street":"Soundview Ln",
    "iso:country":"US",
    "sg:address":"4301 Soundview Ln",
    "sg:city":"Chesterfield",
    "sg:classifiers":[
        {
            "category":"Professional",
            "type":"Services"
        }
    ],
    "sg:phone":"+1 804 745 8086",
    "sg:postcode":"23832",
    "sg:province":"VA",
    "wof:name":"Movingadvicecom",
    "wof:placetype":"venue"
},
  "geometry": {"coordinates":[-77.537488,37.451316],"type":"Point"}
}