{
  "type": "Feature",
  "properties": {
    "iso:country":"US",
    "sg:address":"735 W Princess Anne Rd",
    "sg:city":"Norfolk",
    "sg:classifiers":[
        {
            "category":"Communications",
            "subcategory":"Film & Video Production",
            "type":"Services"
        }
    ],
    "sg:phone":"+1 757 626 3189",
    "sg:postcode":"23517",
    "sg:province":"VA",
    "sg:tags":[
        "taping"
    ],
    "sg:website":"www.videoprojectstudio.com",
    "wof:name":"Video Project Studio",
    "wof:placetype":"venue"
},
  "geometry": {"coordinates":[-76.29856599999999,36.865433],"type":"Point"}
}