{
  "type": "Feature",
  "properties": {
    "addr:full":"2401 S Columbia Pike Arlington VA 22204",
    "addr:housenumber":"2401",
    "addr:postcode":"22204",
    "addr:street":"S Columbia Pike",
    "iso:country":"US",
    "sg:address":"2401 S Columbia Pike",
    "sg:city":"Arlington",
    "sg:classifiers":[
        {
            "category":"Personal",
            "subcategory":"Beauty Salon",
            "type":"Services"
        }
    ],
    "sg:phone":"+1 703 486 0418",
    "sg:postcode":"22204",
    "sg:province":"VA",
    "sg:tags":[
        "shop",
        "manicuring"
    ],
    "wof:name":"Red Nails",
    "wof:placetype":"venue"
},
  "geometry": {"coordinates":[-77.08410000000001,38.863305],"type":"Point"}
}