{
  "type": "Feature",
  "properties": {
    "iso:country":"US",
    "sg:address":"6361 Main St",
    "sg:city":"Zanoni",
    "sg:classifiers":[
        {
            "category":"Government",
            "subcategory":"Office",
            "type":"Public Place"
        }
    ],
    "sg:phone":"+1 804 693 5370",
    "sg:postcode":"23061",
    "sg:province":"VA",
    "wof:name":"Gloucester Clean Community",
    "wof:placetype":"venue"
},
  "geometry": {"coordinates":[-76.535162,37.41637],"type":"Point"}
}