{
  "type": "Feature",
  "properties": {
    "addr:full":"339 Copper Hill Dr Charlottesville VA 22902",
    "addr:housenumber":"339",
    "addr:postcode":"22902",
    "addr:street":"Copper Hill Dr",
    "iso:country":"US",
    "sg:address":"339 Copper Hill Dr",
    "sg:city":"Charlottesville",
    "sg:classifiers":[
        {
            "category":"Health Services",
            "subcategory":"Health Practitioner",
            "type":"Services"
        }
    ],
    "sg:phone":"+1 434 977 7186",
    "sg:postcode":"22902",
    "sg:province":"VA",
    "sg:tags":[
        "therapy",
        "physical"
    ],
    "sg:website":"alexandertechniquecenter.com",
    "wof:name":"The Attic",
    "wof:placetype":"venue"
},
  "geometry": {"coordinates":[-78.511962,37.99001],"type":"Point"}
}