{
  "type": "Feature",
  "properties": {
    "addr:full":"3816 Mine Rd Fredericksburg VA 22408",
    "addr:housenumber":"3816",
    "addr:postcode":"22408",
    "addr:street":"Mine Rd",
    "iso:country":"US",
    "sg:address":"3816 Mine Rd",
    "sg:city":"Fredericksburg",
    "sg:classifiers":[
        {
            "category":"Organizations",
            "subcategory":"Community Association",
            "type":"Services"
        }
    ],
    "sg:phone":"+1 540 891 0491",
    "sg:postcode":"22408",
    "sg:province":"VA",
    "sg:tags":[
        "fraternal"
    ],
    "wof:name":"Fraternal Order Of Police",
    "wof:placetype":"venue"
},
  "geometry": {"coordinates":[-77.465053,38.249751],"type":"Point"}
}