{
  "type": "Feature",
  "properties": {
    "addr:full":"5033 Richmond Tappahannock Hwy Aylett VA 23009",
    "addr:housenumber":"5033",
    "addr:postcode":"23009",
    "addr:street":"Richmond Tappahannock Hwy Aylett",
    "iso:country":"US",
    "sg:address":"5033 Richmond Tappahannock Hwy",
    "sg:city":"Aylett",
    "sg:classifiers":[
        {
            "category":"Food & Beverages",
            "subcategory":"Groceries & Convenience Stores",
            "type":"Retail Goods"
        }
    ],
    "sg:phone":"+1 804 769 2512",
    "sg:postcode":"23009",
    "sg:province":"VA",
    "wof:name":"Rennie Petroleum Corp",
    "wof:placetype":"venue"
},
  "geometry": {"coordinates":[-77.132177,37.746996],"type":"Point"}
}