{
  "type": "Feature",
  "properties": {
    "iso:country":"US",
    "sg:address":"1401 N Washington St",
    "sg:city":"Highland Springs",
    "sg:classifiers":[
        {
            "category":"Retail",
            "subcategory":"Repair Shop",
            "type":"Services"
        }
    ],
    "sg:phone":"+1 804 428 7070",
    "sg:postcode":"23075",
    "sg:province":"VA",
    "sg:tags":[
        "lock",
        "locksmith"
    ],
    "wof:name":"A Abacus Auto Unlock",
    "wof:placetype":"venue"
},
  "geometry": {"coordinates":[-77.308037,37.547532],"type":"Point"}
}