{
  "type": "Feature",
  "properties": {
    "iso:country":"US",
    "sg:address":"11611 Brendonridge Ln",
    "sg:city":"Richmond",
    "sg:classifiers":[
        {
            "category":"Retail",
            "subcategory":"Laundry & Dry Cleaning",
            "type":"Services"
        }
    ],
    "sg:phone":"+1 804 741 8478",
    "sg:postcode":"23238",
    "sg:province":"VA",
    "sg:tags":[
        "cleaners",
        "rug",
        "carpet"
    ],
    "wof:name":"Master's Touch Carpet Care",
    "wof:placetype":"venue"
},
  "geometry": {"coordinates":[-77.625631,37.609077],"type":"Point"}
}