{
  "type": "Feature",
  "properties": {
    "addr:full":"2332 Portland Ave NW Roanoke VA 24017",
    "addr:housenumber":"2332",
    "addr:postcode":"24017",
    "addr:street":"Portland Ave Nw",
    "iso:country":"US",
    "sg:address":"2332 Portland Ave NW",
    "sg:city":"Roanoke",
    "sg:classifiers":[
        {
            "category":"Social Services",
            "subcategory":"Child Care",
            "type":"Services"
        }
    ],
    "sg:phone":"+1 540 562 1060",
    "sg:postcode":"24017",
    "sg:province":"VA",
    "sg:tags":[
        "day"
    ],
    "wof:name":"Germaines Loveable Tots",
    "wof:placetype":"venue"
},
  "geometry": {"coordinates":[-79.99713300000001,37.315578],"type":"Point"}
}