{
  "type": "Feature",
  "properties": {
    "iso:country":"US",
    "sg:address":"2644 N Ohio St",
    "sg:city":"Arlington",
    "sg:classifiers":[
        {
            "category":"Shopping",
            "subcategory":"Shoes",
            "type":"Retail Goods"
        }
    ],
    "sg:phone":"+1 703 536 7738",
    "sg:postcode":"22207",
    "sg:province":"VA",
    "sg:tags":[
        "distance",
        "prepaid",
        "long",
        "communication"
    ],
    "wof:name":"Less Pay Communications",
    "wof:placetype":"venue"
},
  "geometry": {"coordinates":[-77.151143,38.897421],"type":"Point"}
}