{
  "type": "Feature",
  "properties": {
    "iso:country":"US",
    "sg:address":"21430 Cedar Dr Ste 108",
    "sg:city":"Sterling",
    "sg:classifiers":[
        {
            "category":"Restaurant",
            "type":"Food & Drink"
        }
    ],
    "sg:phone":"+1 571 323 5550",
    "sg:postcode":"20164",
    "sg:province":"VA",
    "wof:name":"Dream Dinner",
    "wof:placetype":"venue"
},
  "geometry": {"coordinates":[-77.377735,39.018461],"type":"Point"}
}