{
  "type": "Feature",
  "properties": {
    "iso:country":"US",
    "sg:address":"13110 Willow Stream Ln",
    "sg:city":"Fairfax",
    "sg:classifiers":[
        {
            "category":"Professional",
            "type":"Services"
        }
    ],
    "sg:phone":"+1 703 968 8192",
    "sg:postcode":"22033",
    "sg:province":"VA",
    "wof:name":"Erik S Geho",
    "wof:placetype":"venue"
},
  "geometry": {"coordinates":[-77.40099499999999,38.854103],"type":"Point"}
}