{
  "type": "Feature",
  "properties": {
    "iso:country":"US",
    "sg:address":"7541 Denver Ct",
    "sg:city":"Annandale",
    "sg:classifiers":[
        {
            "category":"Professional",
            "subcategory":"Business Services",
            "type":"Services"
        }
    ],
    "sg:phone":"+1 703 798 6495",
    "sg:postcode":"22003",
    "sg:province":"VA",
    "wof:name":"Thomas Gangi",
    "wof:placetype":"venue"
},
  "geometry": {"coordinates":[-77.20348,38.827616],"type":"Point"}
}