{
  "type": "Feature",
  "properties": {
    "addr:full":"18 N Mallory St Hampton VA 23663",
    "addr:housenumber":"18",
    "addr:postcode":"23663",
    "addr:street":"N Mallory St",
    "iso:country":"US",
    "sg:address":"18 N Mallory St",
    "sg:city":"Hampton",
    "sg:classifiers":[
        {
            "category":"Manufacturing",
            "subcategory":"Pottery",
            "type":"Manufacturing & Wholesale Goods"
        },
        {
            "category":"Home & Garden",
            "subcategory":"Home Furnishings",
            "type":"Retail Goods"
        }
    ],
    "sg:phone":"+1 757 727 9139",
    "sg:postcode":"23663",
    "sg:province":"VA",
    "sg:tags":[
        "product",
        "mfg"
    ],
    "wof:name":"Michelle Erickson Pottery Inc",
    "wof:placetype":"venue"
},
  "geometry": {"coordinates":[-76.319765,37.020121],"type":"Point"}
}