{
  "type": "Feature",
  "properties": {
    "iso:country":"US",
    "sg:address":"1927 Brunswick Dr",
    "sg:city":"Alberta",
    "sg:classifiers":[
        {
            "category":"Wholesale",
            "subcategory":"Machinery & Supplies",
            "type":"Manufacturing & Wholesale Goods"
        }
    ],
    "sg:phone":"+1 434 949 7379",
    "sg:postcode":"23821",
    "sg:province":"VA",
    "sg:tags":[
        "equipment",
        "establishment"
    ],
    "wof:name":"Mary N Short",
    "wof:placetype":"venue"
},
  "geometry": {"coordinates":[-77.95481599999999,36.835811],"type":"Point"}
}