{
  "type": "Feature",
  "properties": {
    "iso:country":"US",
    "sg:address":"14115 Lovers Ln",
    "sg:city":"Culpeper",
    "sg:classifiers":[
        {
            "category":"Real Estate",
            "subcategory":"Real Estate Operator",
            "type":"Services"
        }
    ],
    "sg:phone":"+1 540 825 1213",
    "sg:postcode":"22701",
    "sg:province":"VA",
    "sg:tags":[
        "building",
        "parks"
    ],
    "wof:name":"Culpeper Business Ctr",
    "wof:placetype":"venue"
},
  "geometry": {"coordinates":[-77.99373799999999,38.444862],"type":"Point"}
}