{
  "type": "Feature",
  "properties": {
    "iso:country":"US",
    "sg:address":"11331 Bus Center Dr",
    "sg:city":"Richmond",
    "sg:classifiers":[
        {
            "category":"Real Estate",
            "subcategory":"Real Estate Agent",
            "type":"Services"
        }
    ],
    "sg:phone":"+1 804 897 3954",
    "sg:postcode":"23236",
    "sg:province":"VA",
    "sg:tags":[
        "operation",
        "relocation"
    ],
    "sg:website":"www.oakwood.com",
    "wof:name":"Oakwood Corporate Housing",
    "wof:placetype":"venue"
},
  "geometry": {"coordinates":[-77.60653000000001,37.500635],"type":"Point"}
}