{
  "type": "Feature",
  "properties": {
    "addr:full":"13411 Elliot An Ct Herndon VA 20171",
    "addr:housenumber":"13411",
    "addr:postcode":"20171",
    "addr:street":"Elliot An Ct",
    "iso:country":"US",
    "sg:address":"13411 Elliot An Ct",
    "sg:city":"Herndon",
    "sg:classifiers":[
        {
            "category":"Banks & Credit Unions",
            "subcategory":"Bank",
            "type":"Services"
        }
    ],
    "sg:phone":"+1 703 435 9186",
    "sg:postcode":"20171",
    "sg:province":"VA",
    "sg:tags":[
        "machine",
        "teller",
        "automated"
    ],
    "wof:name":"Expresslink Atm",
    "wof:placetype":"venue"
},
  "geometry": {"coordinates":[-77.41037799999999,38.919257],"type":"Point"}
}