{
  "type": "Feature",
  "properties": {
    "addr:full":"319 18th St Virginia Beach VA 23451",
    "addr:housenumber":"319",
    "addr:postcode":"23451",
    "addr:street":"18Th St",
    "iso:country":"US",
    "sg:address":"319 18th St",
    "sg:city":"Virginia Beach",
    "sg:classifiers":[
        {
            "category":"Government",
            "subcategory":"Court House",
            "type":"Public Place"
        }
    ],
    "sg:phone":"+1 757 437 4860",
    "sg:postcode":"23451",
    "sg:province":"VA",
    "sg:tags":[
        "city"
    ],
    "wof:name":"Virginia Beach Magistrate",
    "wof:placetype":"venue"
},
  "geometry": {"coordinates":[-75.977344,36.845927],"type":"Point"}
}