{
  "type": "Feature",
  "properties": {
    "addr:full":"5610 Southpoint Centre Blvd Fredericksburg VA 22407",
    "addr:housenumber":"5610",
    "addr:postcode":"22407",
    "addr:street":"Southpoint Centre Blvd",
    "iso:country":"US",
    "sg:address":"5610 Southpoint Centre Blvd",
    "sg:city":"Fredericksburg",
    "sg:classifiers":[
        {
            "category":"Building & Trades",
            "subcategory":"Construction",
            "type":"Services"
        }
    ],
    "sg:phone":"+1 540 891 1234",
    "sg:postcode":"22407",
    "sg:province":"VA",
    "sg:tags":[
        "contractor"
    ],
    "sg:website":"www.potterhome.com",
    "wof:name":"Potter Homes",
    "wof:placetype":"venue"
},
  "geometry": {"coordinates":[-77.50161,38.229496],"type":"Point"}
}