{
  "type": "Feature",
  "properties": {
    "addr:full":"312 E Market St Leesburg VA 20176",
    "addr:housenumber":"312",
    "addr:postcode":"20176",
    "addr:street":"E Market St",
    "iso:country":"US",
    "sg:address":"312 E Market St",
    "sg:city":"Leesburg",
    "sg:classifiers":[
        {
            "category":"Shopping",
            "subcategory":"Stationery & Office Supplies",
            "type":"Retail Goods"
        }
    ],
    "sg:phone":"+1 703 779 2447",
    "sg:postcode":"20176",
    "sg:province":"VA",
    "wof:name":"Stamp Gallery",
    "wof:placetype":"venue"
},
  "geometry": {"coordinates":[-77.55915400000001,39.112515],"type":"Point"}
}