{
  "type": "Feature",
  "properties": {
    "addr:full":"4242 Old Buckingham Rd Powhatan VA 23139",
    "addr:housenumber":"4242",
    "addr:postcode":"23139",
    "addr:street":"Old Buckingham Rd",
    "iso:country":"US",
    "sg:address":"4242 Old Buckingham Rd",
    "sg:city":"Powhatan",
    "sg:classifiers":[
        {
            "category":"Retail",
            "subcategory":"Repair Shop",
            "type":"Services"
        }
    ],
    "sg:phone":"+1 804 598 2402",
    "sg:postcode":"23139",
    "sg:province":"VA",
    "sg:tags":[
        "repairing",
        "lawn",
        "mower"
    ],
    "wof:name":"Clarke's Lawn Mower Svc",
    "wof:placetype":"venue"
},
  "geometry": {"coordinates":[-77.94520300000001,37.545132],"type":"Point"}
}