{
  "type": "Feature",
  "properties": {
    "addr:full":"7522 County Complex Rd Hanover VA 23069",
    "addr:housenumber":"7522",
    "addr:postcode":"23069",
    "addr:street":"County Complex Rd",
    "iso:country":"US",
    "sg:address":"7522 County Complex Rd",
    "sg:city":"Hanover",
    "sg:classifiers":[
        {
            "category":"Government",
            "subcategory":"Police Station",
            "type":"Public Place"
        }
    ],
    "sg:phone":"+1 804 537 6005",
    "sg:postcode":"23069",
    "sg:province":"VA",
    "sg:tags":[
        "sheriff"
    ],
    "wof:name":"Hanover County Sheriff",
    "wof:placetype":"venue"
},
  "geometry": {"coordinates":[-77.366957,37.764859],"type":"Point"}
}