{
  "type": "Feature",
  "properties": {
    "iso:country":"US",
    "sg:address":"3634 Sewells Point Rd",
    "sg:city":"Norfolk",
    "sg:classifiers":[
        {
            "category":"Personal",
            "subcategory":"Beauty Salon",
            "type":"Services"
        }
    ],
    "sg:phone":"+1 757 855 2442",
    "sg:postcode":"23513",
    "sg:province":"VA",
    "wof:name":"Before & After Hair Designs",
    "wof:placetype":"venue"
},
  "geometry": {"coordinates":[-76.23699000000001,36.887601],"type":"Point"}
}