{
  "type": "Feature",
  "properties": {
    "iso:country":"US",
    "sg:address":"1501 Farm Credit Drive",
    "sg:city":"McLean",
    "sg:classifiers":[
        {
            "category":"Fast Food",
            "type":"Food & Drink"
        }
    ],
    "sg:postcode":"22102",
    "sg:province":"VA",
    "wof:name":"Farm Credit Admisitration Building Cafeteria",
    "wof:placetype":"venue"
},
  "geometry": {"coordinates":[-77.201775,38.931827],"type":"Point"}
}