{
  "type": "Feature",
  "properties": {
    "addr:full":"34 E Queens Way Hampton VA 23669",
    "addr:housenumber":"34",
    "addr:postcode":"23669",
    "addr:street":"E Queens Way",
    "iso:country":"US",
    "sg:address":"34 E Queens Way",
    "sg:city":"Hampton",
    "sg:classifiers":[
        {
            "category":"Banks & Credit Unions",
            "subcategory":"Investment Brokerage",
            "type":"Services"
        }
    ],
    "sg:phone":"+1 757 722 2535",
    "sg:postcode":"23669",
    "sg:province":"VA",
    "sg:tags":[
        "advisory",
        "security"
    ],
    "wof:name":"Wachovia Securities LLC",
    "wof:placetype":"venue"
},
  "geometry": {"coordinates":[-76.34327500000001,37.025728],"type":"Point"}
}