{
  "type": "Feature",
  "properties": {
    "iso:country":"US",
    "sg:address":"212 Barrett St",
    "sg:city":"Danville",
    "sg:classifiers":[
        {
            "category":"Wholesale",
            "subcategory":"Vending Machines",
            "type":"Manufacturing & Wholesale Goods"
        }
    ],
    "sg:phone":"+1 434 792 8509",
    "sg:postcode":"24541",
    "sg:province":"VA",
    "sg:tags":[
        "operator"
    ],
    "wof:name":"Williams Vending Co",
    "wof:placetype":"venue"
},
  "geometry": {"coordinates":[-79.449671,36.584738],"type":"Point"}
}