{
  "type": "Feature",
  "properties": {
    "iso:country":"US",
    "sg:address":"5197 Shore Dr",
    "sg:city":"Virginia Beach",
    "sg:classifiers":[
        {
            "category":"Restaurant",
            "type":"Food & Drink"
        }
    ],
    "sg:menulink":"http://www.allmenus.com/va/virginia-beach/166169-arbys/menu/",
    "sg:phone":"+1 757 464 6108",
    "sg:postcode":"23455",
    "sg:province":"VA",
    "sg:tags":[
        "burger",
        "american"
    ],
    "wof:name":"Arby's",
    "wof:placetype":"venue"
},
  "geometry": {"coordinates":[-76.15152399999999,36.906081],"type":"Point"}
}