{
  "type": "Feature",
  "properties": {
    "addr:full":"10985 Richardson Rd Ashland VA 23005",
    "addr:housenumber":"10985",
    "addr:postcode":"23005",
    "addr:street":"Richardson Rd",
    "iso:country":"US",
    "sg:address":"10985 Richardson Rd",
    "sg:city":"Ashland",
    "sg:classifiers":[
        {
            "category":"Professional",
            "subcategory":"Lawyer & Legal Services",
            "type":"Services"
        }
    ],
    "sg:phone":"+1 804 550 2106",
    "sg:postcode":"23005",
    "sg:province":"VA",
    "sg:tags":[
        "plan"
    ],
    "wof:name":"Chalkley & Witmeyer Llp",
    "wof:placetype":"venue"
},
  "geometry": {"coordinates":[-77.44156,37.694701],"type":"Point"}
}