{
  "type": "Feature",
  "properties": {
    "addr:full":"27 Biscayne Pl Sterling VA 20164",
    "addr:housenumber":"27",
    "addr:postcode":"20164",
    "addr:street":"Biscayne Pl",
    "iso:country":"US",
    "sg:address":"27 Biscayne Pl",
    "sg:city":"Sterling",
    "sg:classifiers":[
        {
            "category":"Building & Trades",
            "subcategory":"Construction",
            "type":"Services"
        }
    ],
    "sg:phone":"+1 703 444 2121",
    "sg:postcode":"20164",
    "sg:province":"VA",
    "sg:tags":[
        "painter"
    ],
    "wof:name":"Brush Up",
    "wof:placetype":"venue"
},
  "geometry": {"coordinates":[-77.36591799999999,39.035378],"type":"Point"}
}