{
  "type": "Feature",
  "properties": {
    "iso:country":"US",
    "sg:address":"447 Whitacre Rd",
    "sg:city":"Gore",
    "sg:classifiers":[
        {
            "category":"Professional",
            "subcategory":"Management & Consulting",
            "type":"Services"
        }
    ],
    "sg:phone":"+1 540 888 0008",
    "sg:postcode":"22637",
    "sg:province":"VA",
    "sg:tags":[
        "consultant",
        "business"
    ],
    "wof:name":"Cosmic Consulting",
    "wof:placetype":"venue"
},
  "geometry": {"coordinates":[-78.350503,39.284786],"type":"Point"}
}