{
  "type": "Feature",
  "properties": {
    "iso:country":"US",
    "sg:address":"821 Lake Kilby Rd",
    "sg:city":"Suffolk",
    "sg:classifiers":[
        {
            "category":"Building & Trades",
            "subcategory":"Construction",
            "type":"Services"
        }
    ],
    "sg:phone":"+1 757 925 0533",
    "sg:postcode":"23434",
    "sg:province":"VA",
    "sg:tags":[
        "house"
    ],
    "wof:name":"Rhr Construction",
    "wof:placetype":"venue"
},
  "geometry": {"coordinates":[-76.62409599999999,36.750856],"type":"Point"}
}