{
  "type": "Feature",
  "properties": {
    "iso:country":"US",
    "sg:address":"9800 Jim Morris Rd",
    "sg:city":"Fredericksburg",
    "sg:classifiers":[
        {
            "category":"Real Estate",
            "subcategory":"Real Estate Agent",
            "type":"Services"
        }
    ],
    "sg:phone":"+1 540 899 2116",
    "sg:postcode":"22408",
    "sg:province":"VA",
    "wof:name":"Dorothy Fuggion Real Estate",
    "wof:placetype":"venue"
},
  "geometry": {"coordinates":[-77.427227,38.22817],"type":"Point"}
}