{
  "type": "Feature",
  "properties": {
    "addr:full":"1607 Maurice Dr Woodbridge VA 22191",
    "addr:housenumber":"1607",
    "addr:postcode":"22191",
    "addr:street":"Maurice Dr",
    "iso:country":"US",
    "sg:address":"1607 Maurice Dr",
    "sg:city":"Woodbridge",
    "sg:classifiers":[
        {
            "category":"Building & Trades",
            "subcategory":"Construction",
            "type":"Services"
        }
    ],
    "sg:phone":"+1 703 497 4200",
    "sg:postcode":"22191",
    "sg:province":"VA",
    "sg:tags":[
        "repairing",
        "remodeling",
        "contractor"
    ],
    "wof:name":"Montebello Enterpsrises",
    "wof:placetype":"venue"
},
  "geometry": {"coordinates":[-77.26431100000001,38.657043],"type":"Point"}
}