{
  "type": "Feature",
  "properties": {
    "iso:country":"US",
    "sg:address":"5305 Moultrie Rd",
    "sg:city":"Springfield",
    "sg:classifiers":[
        {
            "category":"Building & Trades",
            "subcategory":"Construction",
            "type":"Services"
        }
    ],
    "sg:phone":"+1 571 214 7015",
    "sg:postcode":"22151",
    "sg:province":"VA",
    "sg:tags":[
        "siding",
        "contractor"
    ],
    "wof:name":"Green State Construction",
    "wof:placetype":"venue"
},
  "geometry": {"coordinates":[-77.225532,38.804638],"type":"Point"}
}