{
  "type": "Feature",
  "properties": {
    "iso:country":"US",
    "sg:address":"1115 Independence Blvd",
    "sg:city":"Virginia Beach",
    "sg:classifiers":[
        {
            "category":"Restaurant",
            "type":"Food & Drink"
        }
    ],
    "sg:phone":"+1 757 460 3771",
    "sg:postcode":"23455",
    "sg:province":"VA",
    "wof:name":"Subway Sandwiches & Salads",
    "wof:placetype":"venue"
},
  "geometry": {"coordinates":[-76.13459400000001,36.875378],"type":"Point"}
}