{
  "type": "Feature",
  "properties": {
    "addr:full":"21563 Cascades Pkwy Sterling VA 20166",
    "addr:housenumber":"21563",
    "addr:postcode":"20166",
    "addr:street":"Cascades Pkwy",
    "iso:country":"US",
    "sg:address":"21563 Cascades Pkwy",
    "sg:city":"Sterling",
    "sg:classifiers":[
        {
            "category":"Building & Trades",
            "subcategory":"Plumbing",
            "type":"Services"
        }
    ],
    "sg:phone":"+1 703 444 8855",
    "sg:postcode":"20166",
    "sg:province":"VA",
    "sg:tags":[
        "contractor"
    ],
    "wof:name":"Robco Plumbing Inc",
    "wof:placetype":"venue"
},
  "geometry": {"coordinates":[-77.412385,39.016315],"type":"Point"}
}