{
  "type": "Feature",
  "properties": {
    "addr:full":"800 N Blvd Richmond VA 23220",
    "addr:housenumber":"800",
    "addr:postcode":"23220",
    "addr:street":"N Blvd",
    "iso:country":"US",
    "sg:address":"800 N Blvd",
    "sg:city":"Richmond",
    "sg:classifiers":[
        {
            "category":"Health Services",
            "subcategory":"Nursing And Care Facility",
            "type":"Services"
        }
    ],
    "sg:phone":"+1 804 355 7880",
    "sg:postcode":"23220",
    "sg:province":"VA",
    "sg:tags":[
        "home",
        "convalescent"
    ],
    "wof:name":"Cole's Retirement Home",
    "wof:placetype":"venue"
},
  "geometry": {"coordinates":[-77.470292,37.562505],"type":"Point"}
}