{
  "type": "Feature",
  "properties": {
    "iso:country":"US",
    "sg:address":"1095 Golden Eagle Dr",
    "sg:city":"Moneta",
    "sg:classifiers":[
        {
            "category":"Education",
            "subcategory":"School",
            "type":"Public Place"
        }
    ],
    "sg:phone":"+1 540 297 7151",
    "sg:postcode":"24121",
    "sg:province":"VA",
    "sg:website":"www.eagleshome.org",
    "wof:name":"Staunton River High School",
    "wof:placetype":"venue"
},
  "geometry": {"coordinates":[-79.623248,37.240912],"type":"Point"}
}