{
  "type": "Feature",
  "properties": {
    "addr:full":"1330 Plantation Rd NE Roanoke VA 24012",
    "addr:housenumber":"1330",
    "addr:postcode":"24012",
    "addr:street":"Plantation Rd Ne",
    "iso:country":"US",
    "sg:address":"1330 Plantation Rd NE",
    "sg:city":"Roanoke",
    "sg:classifiers":[
        {
            "category":"Health Services",
            "subcategory":"Clinic",
            "type":"Services"
        }
    ],
    "sg:phone":"+1 540 344 6652",
    "sg:postcode":"24012",
    "sg:province":"VA",
    "sg:tags":[
        "kidney",
        "dialysis",
        "center"
    ],
    "wof:name":"Roanoke Vly Artfl Kidney Ctr",
    "wof:placetype":"venue"
},
  "geometry": {"coordinates":[-79.92986999999999,37.283561],"type":"Point"}
}