{
  "type": "Feature",
  "properties": {
    "iso:country":"US",
    "sg:address":"1201 Sydenham Ct",
    "sg:city":"Virginia Beach",
    "sg:classifiers":[
        {
            "category":"Professional",
            "type":"Services"
        }
    ],
    "sg:phone":"+1 757 474 4774",
    "sg:postcode":"23464",
    "sg:province":"VA",
    "wof:name":"Front Row Services",
    "wof:placetype":"venue"
},
  "geometry": {"coordinates":[-76.147576,36.781309],"type":"Point"}
}