{
  "type": "Feature",
  "properties": {
    "iso:country":"US",
    "sg:address":"11559 Daphna Rd",
    "sg:city":"Broadway",
    "sg:classifiers":[
        {
            "category":"Farming",
            "subcategory":"Poultry Farm",
            "type":"Manufacturing & Wholesale Goods"
        }
    ],
    "sg:phone":"+1 540 896 7093",
    "sg:postcode":"22815",
    "sg:province":"VA",
    "sg:tags":[
        "hatchery",
        "processing"
    ],
    "wof:name":"Tyson",
    "wof:placetype":"venue"
},
  "geometry": {"coordinates":[-78.79501,38.586898],"type":"Point"}
}