{
  "type": "Feature",
  "properties": {
    "addr:full":"3281 Germanna Hwy Locust Grove VA 22508",
    "addr:housenumber":"3281",
    "addr:postcode":"22508",
    "addr:street":"Germanna Hwy",
    "iso:country":"US",
    "sg:address":"3281 Germanna Hwy",
    "sg:city":"Locust Grove",
    "sg:classifiers":[
        {
            "category":"Autos & Motor Vehicles",
            "subcategory":"Boat Sales",
            "type":"Retail Goods"
        }
    ],
    "sg:phone":"+1 540 423 1049",
    "sg:postcode":"22508",
    "sg:province":"VA",
    "sg:tags":[
        "dealer",
        "sales"
    ],
    "wof:name":"Lake Of The Woods Marine",
    "wof:placetype":"venue"
},
  "geometry": {"coordinates":[-77.76031399999999,38.35894],"type":"Point"}
}