{
  "type": "Feature",
  "properties": {
    "iso:country":"US",
    "sg:address":"1111 Rossford Rd",
    "sg:city":"Richmond",
    "sg:classifiers":[
        {
            "category":"Professional",
            "subcategory":"Business Services",
            "type":"Services"
        }
    ],
    "sg:phone":"+1 804 262 3222",
    "sg:postcode":"23227",
    "sg:province":"VA",
    "wof:name":"Four Woods Enterprises Inc",
    "wof:placetype":"venue"
},
  "geometry": {"coordinates":[-77.446093,37.631431],"type":"Point"}
}