{
  "type": "Feature",
  "properties": {
    "iso:country":"US",
    "sg:address":"3710 Lee Hwy",
    "sg:city":"Arlington",
    "sg:classifiers":[
        {
            "category":"Social Services",
            "subcategory":"Job Training",
            "type":"Services"
        },
        {
            "category":"Health Services",
            "subcategory":"Health Practitioner",
            "type":"Services"
        },
        {
            "category":"Social Services",
            "subcategory":"Retirement Home",
            "type":"Services"
        }
    ],
    "sg:phone":"+1 703 243 7640",
    "sg:postcode":"22207",
    "sg:province":"VA",
    "sg:tags":[
        "nursing",
        "homes-skilled",
        "facility",
        "addiction-information",
        "convalescent",
        "treatment",
        "gambling"
    ],
    "sg:website":"http://www.mfa.net",
    "wof:name":"Cherrydale Hlth Rehabiliation",
    "wof:placetype":"venue"
},
  "geometry": {"coordinates":[-77.105389,38.896189],"type":"Point"}
}