{
  "type": "Feature",
  "properties": {
    "addr:full":"9910 Minburn St Great Falls VA 22066",
    "addr:housenumber":"9910",
    "addr:postcode":"22066",
    "addr:street":"Minburn St",
    "iso:country":"US",
    "sg:address":"9910 Minburn St",
    "sg:city":"Great Falls",
    "sg:classifiers":[
        {
            "category":"Professional",
            "subcategory":"Computer Services",
            "type":"Services"
        }
    ],
    "sg:phone":"+1 703 757 7015",
    "sg:postcode":"22066",
    "sg:province":"VA",
    "sg:tags":[
        "development",
        "integration",
        "software"
    ],
    "wof:name":"Gabello Engineering",
    "wof:placetype":"venue"
},
  "geometry": {"coordinates":[-77.29255499999999,38.991665],"type":"Point"}
}