{
  "type": "Feature",
  "properties": {
    "iso:country":"US",
    "sg:address":"173 Fastener Dr",
    "sg:city":"Lynchburg",
    "sg:classifiers":[
        {
            "category":"Shopping",
            "subcategory":"Computers & Home Electronics",
            "type":"Retail Goods"
        }
    ],
    "sg:phone":"+1 434 525 0085",
    "sg:postcode":"24502",
    "sg:province":"VA",
    "sg:tags":[
        "equipment",
        "electronic",
        "supply"
    ],
    "sg:website":"www.us-wire-harness.com",
    "wof:name":"Trans World Connections LTD",
    "wof:placetype":"venue"
},
  "geometry": {"coordinates":[-79.27027099999999,37.310606],"type":"Point"}
}