{
  "type": "Feature",
  "properties": {
    "addr:full":"1813 Bellamy Pl Glen Allen VA 23059",
    "addr:housenumber":"1813",
    "addr:postcode":"23059",
    "addr:street":"Bellamy Pl",
    "iso:country":"US",
    "sg:address":"1813 Bellamy Pl",
    "sg:city":"Glen Allen",
    "sg:classifiers":[
        {
            "category":"Freight",
            "type":"Transportation"
        }
    ],
    "sg:phone":"+1 804 264 6114",
    "sg:postcode":"23059",
    "sg:province":"VA",
    "sg:tags":[
        "operator",
        "local",
        "trucking"
    ],
    "wof:name":"Alpha Hauling Inc",
    "wof:placetype":"venue"
},
  "geometry": {"coordinates":[-77.469869,37.666796],"type":"Point"}
}