{
  "type": "Feature",
  "properties": {
    "iso:country":"US",
    "sg:address":"7153 Pine Ridge Rd",
    "sg:city":"Marshall",
    "sg:classifiers":[
        {
            "category":"Professional",
            "subcategory":"Management & Consulting",
            "type":"Services"
        }
    ],
    "sg:phone":"+1 540 347 2033",
    "sg:postcode":"20115",
    "sg:province":"VA",
    "wof:name":"Innovative Bus Transitions LLC",
    "wof:placetype":"venue"
},
  "geometry": {"coordinates":[-77.880172,38.744052],"type":"Point"}
}