{
  "type": "Feature",
  "properties": {
    "iso:country":"US",
    "sg:address":"215 Kings Hwy",
    "sg:city":"Fredericksburg",
    "sg:classifiers":[
        {
            "category":"Personal",
            "subcategory":"Barber",
            "type":"Services"
        }
    ],
    "sg:phone":"+1 540 899 3006",
    "sg:postcode":"22405",
    "sg:province":"VA",
    "sg:tags":[
        "shop"
    ],
    "wof:name":"Tom's Barber Shop",
    "wof:placetype":"venue"
},
  "geometry": {"coordinates":[-77.44711,38.298902],"type":"Point"}
}