{
  "type": "Feature",
  "properties": {
    "addr:full":"4422 Stage Rd Concord VA 24538",
    "addr:housenumber":"4422",
    "addr:postcode":"24538",
    "addr:street":"Stage Rd",
    "iso:country":"US",
    "sg:address":"4422 Stage Rd",
    "sg:city":"Concord",
    "sg:classifiers":[
        {
            "category":"Building & Trades",
            "subcategory":"Construction",
            "type":"Services"
        }
    ],
    "sg:phone":"+1 434 993 0755",
    "sg:postcode":"24538",
    "sg:province":"VA",
    "sg:tags":[
        "concrete",
        "contractor"
    ],
    "wof:name":"R & R Concrete & Wall Forming",
    "wof:placetype":"venue"
},
  "geometry": {"coordinates":[-78.996154,37.382809],"type":"Point"}
}