{
  "type": "Feature",
  "properties": {
    "addr:full":"4780 Walbern Ct Chantilly VA 20151",
    "addr:postcode":"4780;20151",
    "addr:street":"Walbern Ct",
    "iso:country":"US",
    "sg:address":"4780 Walbern Ct",
    "sg:city":"Chantilly",
    "sg:classifiers":[
        {
            "category":"Professional",
            "subcategory":"Computer Services",
            "type":"Services"
        }
    ],
    "sg:phone":"+1 703 263 1546",
    "sg:postcode":"20151",
    "sg:province":"VA",
    "sg:tags":[
        "consulting"
    ],
    "wof:name":"Usm Business Systems Inc",
    "wof:placetype":"venue"
},
  "geometry": {"coordinates":[-77.43071999999999,38.872361],"type":"Point"}
}