{
  "type": "Feature",
  "properties": {
    "iso:country":"US",
    "sg:address":"14021 Steeplestone Rd",
    "sg:city":"Midlothian",
    "sg:classifiers":[
        {
            "category":"Shopping",
            "subcategory":"Clothing, Apparel, & Fashions",
            "type":"Retail Goods"
        }
    ],
    "sg:phone":"+1 804 794 0333",
    "sg:postcode":"23113",
    "sg:province":"VA",
    "sg:tags":[
        "high",
        "p",
        "handbag",
        "end",
        "jewelry"
    ],
    "wof:name":"Posh LLC",
    "wof:placetype":"venue"
},
  "geometry": {"coordinates":[-77.665024,37.525791],"type":"Point"}
}