{
  "type": "Feature",
  "properties": {
    "addr:full":"411 Westover Hills Blvd Richmond VA 23225",
    "addr:housenumber":"411",
    "addr:postcode":"23225",
    "addr:street":"Westover Hills Blvd",
    "iso:country":"US",
    "sg:address":"411 Westover Hills Blvd",
    "sg:city":"Richmond",
    "sg:classifiers":[
        {
            "category":"Professional",
            "type":"Services"
        }
    ],
    "sg:phone":"+1 804 231 4218",
    "sg:postcode":"23225",
    "sg:province":"VA",
    "wof:name":"D & L Collections Mus Svc LLC",
    "wof:placetype":"venue"
},
  "geometry": {"coordinates":[-77.488872,37.515141],"type":"Point"}
}