{
  "type": "Feature",
  "properties": {
    "addr:full":"14132 Old Richmond Rd Keeling VA 24566",
    "addr:housenumber":"14132",
    "addr:postcode":"24566",
    "addr:street":"Old Richmond Rd",
    "iso:country":"US",
    "sg:address":"14132 Old Richmond Rd",
    "sg:city":"Keeling",
    "sg:classifiers":[
        {
            "category":"Building & Trades",
            "subcategory":"Plumbing",
            "type":"Services"
        }
    ],
    "sg:phone":"+1 434 793 9830",
    "sg:postcode":"24566",
    "sg:province":"VA",
    "sg:tags":[
        "conditioning",
        "air",
        "system",
        "contractor"
    ],
    "wof:name":"Stevens Heating & Air Cond",
    "wof:placetype":"venue"
},
  "geometry": {"coordinates":[-79.230492,36.721869],"type":"Point"}
}