{
  "type": "Feature",
  "properties": {
    "addr:full":"509 N Meadow St Richmond VA 23220",
    "addr:housenumber":"509",
    "addr:postcode":"23220",
    "addr:street":"N Meadow St",
    "iso:country":"US",
    "sg:address":"509 N Meadow St",
    "sg:city":"Richmond",
    "sg:classifiers":[
        {
            "category":"Real Estate",
            "subcategory":"Real Estate Operator",
            "type":"Services"
        }
    ],
    "sg:phone":"+1 804 358 3097",
    "sg:postcode":"23220",
    "sg:province":"VA",
    "sg:tags":[
        "building",
        "apartment"
    ],
    "wof:name":"Virginia Lee Properties Inc",
    "wof:placetype":"venue"
},
  "geometry": {"coordinates":[-77.462309,37.554882],"type":"Point"}
}