{
  "type": "Feature",
  "properties": {
    "iso:country":"US",
    "sg:address":"421 W Main St",
    "sg:city":"Charlottesville",
    "sg:classifiers":[
        {
            "category":"Home & Garden",
            "subcategory":"Furniture",
            "type":"Retail Goods"
        }
    ],
    "sg:phone":"+1 434 295 3410",
    "sg:postcode":"22903",
    "sg:province":"VA",
    "sg:tags":[
        "bedding",
        "mattress"
    ],
    "wof:name":"Atlantic Futons",
    "wof:placetype":"venue"
},
  "geometry": {"coordinates":[-78.487297,38.030701],"type":"Point"}
}