{
  "type": "Feature",
  "properties": {
    "addr:full":"225 Alphin Ln Lexington VA 24450",
    "addr:housenumber":"225",
    "addr:postcode":"24450",
    "addr:street":"Alphin Ln",
    "iso:country":"US",
    "sg:address":"225 Alphin Ln",
    "sg:city":"Lexington",
    "sg:classifiers":[
        {
            "category":"Professional",
            "type":"Services"
        }
    ],
    "sg:phone":"+1 540 463 9125",
    "sg:postcode":"24450",
    "sg:province":"VA",
    "wof:name":"Butterfly Pine Corp",
    "wof:placetype":"venue"
},
  "geometry": {"coordinates":[-79.41946799999999,37.806804],"type":"Point"}
}