{
  "type": "Feature",
  "properties": {
    "iso:country":"US",
    "sg:address":"6803 Whittier Ave",
    "sg:city":"Mc Lean",
    "sg:classifiers":[
        {
            "category":"Utilities",
            "subcategory":"Telephone",
            "type":"Services"
        }
    ],
    "sg:phone":"+1 703 847 0040",
    "sg:postcode":"22101",
    "sg:province":"VA",
    "sg:tags":[
        "communications"
    ],
    "wof:name":"NCM",
    "wof:placetype":"venue"
},
  "geometry": {"coordinates":[-77.17779299999999,38.931047],"type":"Point"}
}