{
  "type": "Feature",
  "properties": {
    "addr:full":"2009 14th St N Arlington VA 22201",
    "addr:housenumber":"2009",
    "addr:postcode":"22201",
    "addr:street":"14Th St N",
    "iso:country":"US",
    "sg:address":"2009 14th St N",
    "sg:city":"Arlington",
    "sg:classifiers":[
        {
            "category":"Professional",
            "subcategory":"Lawyer & Legal Services",
            "type":"Services"
        }
    ],
    "sg:phone":"+1 703 522 4500",
    "sg:postcode":"22201",
    "sg:province":"VA",
    "sg:tags":[
        "attorney"
    ],
    "wof:name":"Radigan & Garnett",
    "wof:placetype":"venue"
},
  "geometry": {"coordinates":[-77.08175,38.889761],"type":"Point"}
}