{
  "type": "Feature",
  "properties": {
    "addr:full":"14411 Orangeburg Way Chesterfield VA 23838",
    "addr:housenumber":"14411",
    "addr:postcode":"23838",
    "addr:street":"Orangeburg Way",
    "iso:country":"US",
    "sg:address":"14411 Orangeburg Way",
    "sg:city":"Chesterfield",
    "sg:classifiers":[
        {
            "category":"Professional",
            "subcategory":"Advertising",
            "type":"Services"
        }
    ],
    "sg:phone":"+1 804 748 1601",
    "sg:postcode":"23838",
    "sg:province":"VA",
    "sg:tags":[
        "mail",
        "direct"
    ],
    "wof:name":"ADM",
    "wof:placetype":"venue"
},
  "geometry": {"coordinates":[-77.489334,37.317212],"type":"Point"}
}