{
  "type": "Feature",
  "properties": {
    "addr:full":"7450 Little River Tpke Annandale VA 22003",
    "addr:housenumber":"7450",
    "addr:postcode":"22003",
    "addr:street":"Little River Tpke",
    "iso:country":"US",
    "sg:address":"7450 Little River Tpke",
    "sg:city":"Annandale",
    "sg:classifiers":[
        {
            "category":"Personal",
            "subcategory":"Beauty Salon",
            "type":"Services"
        }
    ],
    "sg:phone":"+1 703 891 1186",
    "sg:postcode":"22003",
    "sg:province":"VA",
    "sg:tags":[
        "shop"
    ],
    "wof:name":"Sister Hair Salon Inc",
    "wof:placetype":"venue"
},
  "geometry": {"coordinates":[-77.201898,38.831516],"type":"Point"}
}