{
  "type": "Feature",
  "properties": {
    "addr:full":"2125 Hilliard Rd Richmond VA 23228",
    "addr:housenumber":"2125",
    "addr:postcode":"23228",
    "addr:street":"Hilliard Rd",
    "iso:country":"US",
    "sg:address":"2125 Hilliard Rd",
    "sg:city":"Richmond",
    "sg:classifiers":[
        {
            "category":"Health Services",
            "subcategory":"Nursing And Care Facility",
            "type":"Services"
        }
    ],
    "sg:phone":"+1 804 266 9666",
    "sg:postcode":"23228",
    "sg:province":"VA",
    "sg:tags":[
        "skilled"
    ],
    "wof:name":"Manorcare Health Services",
    "wof:placetype":"venue"
},
  "geometry": {"coordinates":[-77.473384,37.616642],"type":"Point"}
}