{
  "type": "Feature",
  "properties": {
    "iso:country":"US",
    "sg:address":"8091 Sudley Rd",
    "sg:city":"Manassas",
    "sg:classifiers":[
        {
            "category":"Banks & Credit Unions",
            "subcategory":"Bank",
            "type":"Services"
        }
    ],
    "sg:phone":"+1 703 366 1600",
    "sg:postcode":"20109",
    "sg:province":"VA",
    "sg:tags":[
        "state",
        "commercial"
    ],
    "wof:name":"Fauquier Bank The",
    "wof:placetype":"venue"
},
  "geometry": {"coordinates":[-77.511308,38.781688],"type":"Point"}
}