{
  "type": "Feature",
  "properties": {
    "addr:full":"406 Court St Lovingston VA 22949",
    "addr:housenumber":"406",
    "addr:postcode":"22949",
    "addr:street":"Court St",
    "iso:country":"US",
    "sg:address":"406 Court St",
    "sg:city":"Lovingston",
    "sg:classifiers":[
        {
            "category":"Manufacturing",
            "subcategory":"Lumber",
            "type":"Manufacturing & Wholesale Goods"
        }
    ],
    "sg:phone":"+1 434 263 4232",
    "sg:postcode":"22949",
    "sg:province":"VA",
    "sg:tags":[
        "government"
    ],
    "wof:name":"Forestry Dept",
    "wof:placetype":"venue"
},
  "geometry": {"coordinates":[-78.869792,37.759619],"type":"Point"}
}