{
  "type": "Feature",
  "properties": {
    "iso:country":"US",
    "sg:address":"6815 Wild Rose Ct",
    "sg:city":"Springfield",
    "sg:classifiers":[
        {
            "category":"Wholesale",
            "subcategory":"Machinery & Supplies",
            "type":"Manufacturing & Wholesale Goods"
        }
    ],
    "sg:phone":"+1 703 569 2175",
    "sg:postcode":"22152",
    "sg:province":"VA",
    "sg:tags":[
        "rubber"
    ],
    "wof:name":"Willingham Hose Rbr & Sup Co",
    "wof:placetype":"venue"
},
  "geometry": {"coordinates":[-77.208466,38.767154],"type":"Point"}
}