{
  "type": "Feature",
  "properties": {
    "iso:country":"US",
    "sg:address":"620 S Main St",
    "sg:city":"Rocky Mount",
    "sg:classifiers":[
        {
            "category":"Insurance",
            "subcategory":"Insurance Agent",
            "type":"Services"
        }
    ],
    "sg:phone":"+1 540 483 5121",
    "sg:postcode":"24151",
    "sg:province":"VA",
    "wof:name":"Hogue Insurance",
    "wof:placetype":"venue"
},
  "geometry": {"coordinates":[-79.889869,36.992196],"type":"Point"}
}