{
  "type": "Feature",
  "properties": {
    "addr:full":"35599 Sunny Ridge Rd Round Hill VA 20141",
    "addr:housenumber":"35599",
    "addr:postcode":"20141",
    "addr:street":"Sunny Ridge Rd",
    "iso:country":"US",
    "sg:address":"35599 Sunny Ridge Rd",
    "sg:city":"Round Hill",
    "sg:classifiers":[
        {
            "category":"Building & Trades",
            "subcategory":"Construction",
            "type":"Services"
        }
    ],
    "sg:phone":"+1 540 751 2161",
    "sg:postcode":"20141",
    "sg:province":"VA",
    "sg:tags":[
        "home",
        "builder"
    ],
    "wof:name":"Equity Homes",
    "wof:placetype":"venue"
},
  "geometry": {"coordinates":[-77.77467300000001,39.171908],"type":"Point"}
}