{
  "type": "Feature",
  "properties": {
    "addr:full":"1005 Railroad Ave Franklin VA 23851",
    "addr:housenumber":"1005",
    "addr:postcode":"23851",
    "addr:street":"Railroad Ave",
    "iso:country":"US",
    "sg:address":"1005 Railroad Ave",
    "sg:city":"Franklin",
    "sg:classifiers":[
        {
            "category":"Personal",
            "subcategory":"Beauty Salon",
            "type":"Services"
        }
    ],
    "sg:phone":"+1 757 562 6470",
    "sg:postcode":"23851",
    "sg:province":"VA",
    "sg:tags":[
        "shop"
    ],
    "wof:name":"Shaquilia Styling",
    "wof:placetype":"venue"
},
  "geometry": {"coordinates":[-76.92900299999999,36.672851],"type":"Point"}
}