{
  "type": "Feature",
  "properties": {
    "iso:country":"US",
    "sg:address":"1933 E Pembroke Ave",
    "sg:city":"Hampton",
    "sg:classifiers":[
        {
            "category":"Food & Beverages",
            "subcategory":"Groceries & Convenience Stores",
            "type":"Retail Goods"
        }
    ],
    "sg:phone":"+1 757 723 3645",
    "sg:postcode":"23663",
    "sg:province":"VA",
    "sg:tags":[
        "grocer"
    ],
    "wof:name":"Save-A-Lot Food Store",
    "wof:placetype":"venue"
},
  "geometry": {"coordinates":[-76.308178,37.039403],"type":"Point"}
}