{
  "type": "Feature",
  "properties": {
    "iso:country":"US",
    "sg:address":"4925 State Park Rd",
    "sg:city":"Dublin",
    "sg:classifiers":[
        {
            "category":"Travel",
            "subcategory":"Campground",
            "type":"Entertainment"
        }
    ],
    "sg:phone":"+1 540 674 5561",
    "sg:postcode":"24084",
    "sg:province":"VA",
    "sg:tags":[
        "trailer"
    ],
    "wof:name":"Mc Guires Campground",
    "wof:placetype":"venue"
},
  "geometry": {"coordinates":[-80.640089,37.080477],"type":"Point"}
}