{
  "type": "Feature",
  "properties": {
    "addr:full":"9590 Courthouse Rd Lancaster VA 22503",
    "addr:housenumber":"9590",
    "addr:postcode":"22503",
    "addr:street":"Courthouse Rd",
    "iso:country":"US",
    "sg:address":"9590 Courthouse Rd",
    "sg:city":"Lancaster",
    "sg:phone":"+1 804 462 5479",
    "sg:postcode":"22503",
    "sg:province":"VA",
    "sg:tags":[
        "farm",
        "corn",
        "wheat",
        "soybean"
    ],
    "wof:name":"Gill Farm",
    "wof:placetype":"venue"
},
  "geometry": {"coordinates":[-76.475168,37.792098],"type":"Point"}
}