{
  "type": "Feature",
  "properties": {
    "iso:country":"US",
    "sg:address":"2001 N Adams St",
    "sg:city":"Arlington",
    "sg:classifiers":[
        {
            "category":"Professional",
            "type":"Services"
        }
    ],
    "sg:phone":"+1 703 522 4165",
    "sg:postcode":"22201",
    "sg:province":"VA",
    "wof:name":"Boz LLC",
    "wof:placetype":"venue"
},
  "geometry": {"coordinates":[-77.08914,38.897605],"type":"Point"}
}