{
  "type": "Feature",
  "properties": {
    "iso:country":"US",
    "sg:address":"451 E Belt Blvd",
    "sg:city":"Richmond",
    "sg:classifiers":[
        {
            "category":"Shopping",
            "subcategory":"Clothing, Apparel, & Fashions",
            "type":"Retail Goods"
        }
    ],
    "sg:phone":"+1 804 852 4226",
    "sg:postcode":"23224",
    "sg:province":"VA",
    "sg:tags":[
        "store"
    ],
    "wof:name":"Denim Xchange Ram Inc",
    "wof:placetype":"venue"
},
  "geometry": {"coordinates":[-77.477593,37.504941],"type":"Point"}
}