{
  "type": "Feature",
  "properties": {
    "iso:country":"US",
    "sg:address":"6556 Old Carriage Dr",
    "sg:city":"Alexandria",
    "sg:phone":"+1 571 235 2261",
    "sg:postcode":"22315",
    "sg:province":"VA",
    "sg:tags":[
        "vending",
        "broker"
    ],
    "sg:website":"www.vendinglounge.com",
    "wof:name":"Vendinglounge.Com Inc",
    "wof:placetype":"venue"
},
  "geometry": {"coordinates":[-77.169928,38.742079],"type":"Point"}
}