{
  "type": "Feature",
  "properties": {
    "addr:full":"6269 Leesburg Pike Falls Church VA 22044",
    "addr:housenumber":"6269",
    "addr:postcode":"22044",
    "addr:street":"Leesburg Pike",
    "iso:country":"US",
    "sg:address":"6269 Leesburg Pike",
    "sg:city":"Falls Church",
    "sg:classifiers":[
        {
            "category":"Professional",
            "subcategory":"Lawyer & Legal Services",
            "type":"Services"
        }
    ],
    "sg:phone":"+1 703 536 6999",
    "sg:postcode":"22044",
    "sg:province":"VA",
    "sg:tags":[
        "attorney"
    ],
    "wof:name":"Nancy M Vizer Law Office",
    "wof:placetype":"venue"
},
  "geometry": {"coordinates":[-77.151814,38.866664],"type":"Point"}
}