{
  "type": "Feature",
  "properties": {
    "iso:country":"US",
    "sg:address":"2324 E Little Creek Rd",
    "sg:city":"Norfolk",
    "sg:classifiers":[
        {
            "category":"Personal",
            "subcategory":"Beauty Salon",
            "type":"Services"
        }
    ],
    "sg:phone":"+1 757 588 3800",
    "sg:postcode":"23518",
    "sg:province":"VA",
    "sg:tags":[
        "shop"
    ],
    "wof:name":"No 1 Kuts",
    "wof:placetype":"venue"
},
  "geometry": {"coordinates":[-76.219382,36.915263],"type":"Point"}
}