{
  "type": "Feature",
  "properties": {
    "iso:country":"US",
    "sg:address":"10649 Spotsylvania Ave",
    "sg:city":"Fredericksburg",
    "sg:classifiers":[
        {
            "category":"Restaurant",
            "type":"Food & Drink"
        }
    ],
    "sg:phone":"+1 540 785 0788",
    "sg:postcode":"22408",
    "sg:province":"VA",
    "sg:tags":[
        "eating"
    ],
    "wof:name":"Pub The",
    "wof:placetype":"venue"
},
  "geometry": {"coordinates":[-77.495054,38.247435],"type":"Point"}
}