{
  "type": "Feature",
  "properties": {
    "iso:country":"US",
    "sg:address":"1111 Thompson Cir",
    "sg:city":"Fort Eustis",
    "sg:classifiers":[
        {
            "category":"Professional",
            "subcategory":"Computer Services",
            "type":"Services"
        }
    ],
    "sg:phone":"+1 757 820 0677",
    "sg:postcode":"23604",
    "sg:province":"VA",
    "sg:tags":[
        "repair"
    ],
    "wof:name":"Mr CS Computers",
    "wof:placetype":"venue"
},
  "geometry": {"coordinates":[-76.57170499999999,37.149947],"type":"Point"}
}