{
  "type": "Feature",
  "properties": {
    "addr:full":"13209 Forest Light Ct Richmond VA 23233",
    "addr:housenumber":"13209",
    "addr:postcode":"23233",
    "addr:street":"Forest Light Ct",
    "iso:country":"US",
    "sg:address":"13209 Forest Light Ct",
    "sg:city":"Richmond",
    "sg:classifiers":[
        {
            "category":"Professional",
            "subcategory":"Management & Consulting",
            "type":"Services"
        }
    ],
    "sg:phone":"+1 804 360 1110",
    "sg:postcode":"23233",
    "sg:province":"VA",
    "wof:name":"National Consulting Group Inc",
    "wof:placetype":"venue"
},
  "geometry": {"coordinates":[-77.630003,37.648592],"type":"Point"}
}