{
  "type": "Feature",
  "properties": {
    "addr:full":"1396 Armory Dr Franklin VA 23851",
    "addr:housenumber":"1396",
    "addr:postcode":"23851",
    "addr:street":"Armory Dr",
    "iso:country":"US",
    "sg:address":"1396 Armory Dr",
    "sg:city":"Franklin",
    "sg:classifiers":[
        {
            "category":"Restaurant",
            "type":"Food & Drink"
        }
    ],
    "sg:menulink":"http://www.allmenus.com/va/franklin/36744-applebees/menu/",
    "sg:phone":"+1 757 516 6053",
    "sg:postcode":"23851",
    "sg:province":"VA",
    "sg:tags":[
        "burger",
        "american",
        "sandwich",
        "soup"
    ],
    "wof:name":"Applebee's",
    "wof:placetype":"venue"
},
  "geometry": {"coordinates":[-76.94987999999999,36.668921],"type":"Point"}
}