{
  "type": "Feature",
  "properties": {
    "addr:full":"1801 Reymet Rd Richmond VA 23237",
    "addr:housenumber":"1801",
    "addr:postcode":"23237",
    "addr:street":"Reymet Rd",
    "iso:country":"US",
    "sg:address":"1801 Reymet Rd",
    "sg:city":"Richmond",
    "sg:classifiers":[
        {
            "category":"Professional",
            "subcategory":"Research",
            "type":"Services"
        }
    ],
    "sg:phone":"+1 804 743 6124",
    "sg:postcode":"23237",
    "sg:province":"VA",
    "sg:tags":[
        "facility"
    ],
    "wof:name":"Reynolds Bellwood Tech Ctr",
    "wof:placetype":"venue"
},
  "geometry": {"coordinates":[-77.4135,37.391535],"type":"Point"}
}