{
  "type": "Feature",
  "properties": {
    "iso:country":"US",
    "sg:address":"4638 34th St S",
    "sg:city":"Arlington",
    "sg:classifiers":[
        {
            "category":"Arts & Performance",
            "subcategory":"Theater",
            "type":"Entertainment"
        }
    ],
    "sg:phone":"+1 703 820 9589",
    "sg:postcode":"22206",
    "sg:province":"VA",
    "sg:tags":[
        "theatrical",
        "production"
    ],
    "wof:name":"Ann Timmons",
    "wof:placetype":"venue"
},
  "geometry": {"coordinates":[-77.093272,38.834339],"type":"Point"}
}