{
  "type": "Feature",
  "properties": {
    "iso:country":"US",
    "sg:address":"9410 Lagovista Ct",
    "sg:city":"Great Falls",
    "sg:classifiers":[
        {
            "category":"Professional",
            "subcategory":"Business Services",
            "type":"Services"
        }
    ],
    "sg:phone":"+1 703 759 3040",
    "sg:postcode":"22066",
    "sg:province":"VA",
    "wof:name":"Karber Enterprises Inc",
    "wof:placetype":"venue"
},
  "geometry": {"coordinates":[-77.267336,39.008435],"type":"Point"}
}