{
  "type": "Feature",
  "properties": {
    "addr:full":"2 Loudoun St SW Leesburg VA 20175",
    "addr:housenumber":"2",
    "addr:postcode":"20175",
    "addr:street":"Loudoun St Sw",
    "iso:country":"US",
    "sg:address":"2 Loudoun St SW",
    "sg:city":"Leesburg",
    "sg:classifiers":[
        {
            "category":"Retail",
            "subcategory":"Repair Shop",
            "type":"Services"
        }
    ],
    "sg:phone":"+1 703 779 0172",
    "sg:postcode":"20175",
    "sg:province":"VA",
    "sg:tags":[
        "related"
    ],
    "wof:name":"Natura Lawn Of America",
    "wof:placetype":"venue"
},
  "geometry": {"coordinates":[-77.566631,39.114664],"type":"Point"}
}