{
  "type": "Feature",
  "properties": {
    "iso:country":"US",
    "sg:address":"2441 Kerr Dr",
    "sg:city":"Virginia Beach",
    "sg:classifiers":[
        {
            "category":"Restaurant",
            "type":"Food & Drink"
        }
    ],
    "sg:phone":"+1 757 426 6540",
    "sg:postcode":"23454",
    "sg:province":"VA",
    "sg:tags":[
        "eating"
    ],
    "wof:name":"Bojangles",
    "wof:placetype":"venue"
},
  "geometry": {"coordinates":[-75.999501,36.759876],"type":"Point"}
}