{
  "type": "Feature",
  "properties": {
    "addr:full":"519 Aspen Dr Herndon VA 20170",
    "addr:housenumber":"519",
    "addr:postcode":"20170",
    "addr:street":"Aspen Dr",
    "iso:country":"US",
    "sg:address":"519 Aspen Dr",
    "sg:city":"Herndon",
    "sg:classifiers":[
        {
            "category":"Banks & Credit Unions",
            "subcategory":"Bank",
            "type":"Services"
        }
    ],
    "sg:phone":"+1 703 868 2848",
    "sg:postcode":"20170",
    "sg:province":"VA",
    "sg:tags":[
        "broker",
        "mortgage"
    ],
    "wof:name":"Bycos LLC",
    "wof:placetype":"venue"
},
  "geometry": {"coordinates":[-77.38355,38.961133],"type":"Point"}
}