{
  "type": "Feature",
  "properties": {
    "addr:full":"2623 Hemple St Chesapeake VA 23324",
    "addr:housenumber":"2623",
    "addr:postcode":"23324",
    "addr:street":"Hemple St",
    "iso:country":"US",
    "sg:address":"2623 Hemple St",
    "sg:city":"Chesapeake",
    "sg:classifiers":[
        {
            "category":"Professional",
            "subcategory":"Business Services",
            "type":"Services"
        }
    ],
    "sg:phone":"+1 757 227 6260",
    "sg:postcode":"23324",
    "sg:province":"VA",
    "sg:tags":[
        "drafting"
    ],
    "wof:name":"Advance Drafting & Design LTD",
    "wof:placetype":"venue"
},
  "geometry": {"coordinates":[-76.257654,36.79415],"type":"Point"}
}