{
  "type": "Feature",
  "properties": {
    "addr:full":"1018 Caverns Rd Quicksburg VA 22847",
    "addr:housenumber":"1018",
    "addr:postcode":"22847",
    "addr:street":"Caverns Rd",
    "iso:country":"US",
    "sg:address":"1018 Caverns Rd",
    "sg:city":"Quicksburg",
    "sg:classifiers":[
        {
            "category":"Education",
            "subcategory":"School",
            "type":"Public Place"
        }
    ],
    "sg:phone":"+1 540 477 2953",
    "sg:postcode":"22847",
    "sg:province":"VA",
    "sg:tags":[
        "middle"
    ],
    "sg:website":"http://www.shenandoahtravel.org",
    "wof:name":"North Fork Middle School",
    "wof:placetype":"venue"
},
  "geometry": {"coordinates":[-78.661169,38.706517],"type":"Point"}
}