{
  "type": "Feature",
  "properties": {
    "addr:full":"429 Avondale Dr Sterling VA 20164",
    "addr:housenumber":"429",
    "addr:postcode":"20164",
    "addr:street":"Avondale Dr",
    "iso:country":"US",
    "sg:address":"429 Avondale Dr",
    "sg:city":"Sterling",
    "sg:classifiers":[
        {
            "category":"Professional",
            "subcategory":"Computer Services",
            "type":"Services"
        }
    ],
    "sg:phone":"+1 703 450 8809",
    "sg:postcode":"20164",
    "sg:province":"VA",
    "sg:tags":[
        "internet",
        "software"
    ],
    "wof:name":"Optiview Technologies",
    "wof:placetype":"venue"
},
  "geometry": {"coordinates":[-77.37275699999999,39.040567],"type":"Point"}
}