{
  "type": "Feature",
  "properties": {
    "iso:country":"US",
    "sg:address":"1080 Sentry Dr",
    "sg:city":"Chesapeake",
    "sg:classifiers":[
        {
            "category":"Government",
            "subcategory":"Police Station",
            "type":"Public Place"
        }
    ],
    "sg:phone":"+1 757 487 0886",
    "sg:postcode":"23323",
    "sg:province":"VA",
    "sg:tags":[
        "department"
    ],
    "wof:name":"Chesapeake Police Training",
    "wof:placetype":"venue"
},
  "geometry": {"coordinates":[-76.338919,36.695739],"type":"Point"}
}