{
  "type": "Feature",
  "properties": {
    "iso:country":"US",
    "sg:address":"95 Tide Mill Ln",
    "sg:city":"Hampton",
    "sg:classifiers":[
        {
            "category":"Organizations",
            "subcategory":"Community Association",
            "type":"Services"
        }
    ],
    "sg:phone":"+1 757 838 7366",
    "sg:postcode":"23666",
    "sg:province":"VA",
    "sg:tags":[
        "membership",
        "fraternal",
        "civic"
    ],
    "wof:name":"Elks Lodge Hampton 366",
    "wof:placetype":"venue"
},
  "geometry": {"coordinates":[-76.369902,37.057773],"type":"Point"}
}