{
  "type": "Feature",
  "properties": {
    "addr:full":"2608 Morse Ln Woodbridge VA 22192",
    "addr:housenumber":"2608",
    "addr:postcode":"22192",
    "addr:street":"Morse Ln",
    "iso:country":"US",
    "sg:address":"2608 Morse Ln",
    "sg:city":"Woodbridge",
    "sg:classifiers":[
        {
            "category":"Home & Garden",
            "subcategory":"Household Appliances",
            "type":"Retail Goods"
        },
        {
            "category":"Building & Trades",
            "subcategory":"Construction",
            "type":"Services"
        },
        {
            "category":"Professional",
            "subcategory":"Engineering",
            "type":"Services"
        }
    ],
    "sg:phone":"+1 703 491 2771",
    "sg:postcode":"22192",
    "sg:province":"VA",
    "sg:tags":[
        "purifying",
        "system",
        "specialty",
        "equipment",
        "heating",
        "cleaning",
        "contractor",
        "air conditioning"
    ],
    "sg:website":"http://find.americanstandardair.com/customer-care-dealer-415304?utm_source=YP&utm_medium=banner&utm_campaign=TL",
    "wof:name":"Brennan's Heating & A/C Service",
    "wof:placetype":"venue"
},
  "geometry": {"coordinates":[-77.29128300000001,38.654018],"type":"Point"}
}