{
  "type": "Feature",
  "properties": {
    "addr:full":"545 W Main St Abingdon VA 24210",
    "addr:housenumber":"545",
    "addr:postcode":"24210",
    "addr:street":"W Main St",
    "iso:country":"US",
    "sg:address":"545 W Main St",
    "sg:city":"Abingdon",
    "sg:classifiers":[
        {
            "category":"Government",
            "subcategory":"Office",
            "type":"Public Place"
        }
    ],
    "sg:phone":"+1 276 628 3441",
    "sg:postcode":"24210",
    "sg:province":"VA",
    "sg:tags":[
        "liquor",
        "store"
    ],
    "wof:name":"VA Dept Alcoholic Bev Ctrl",
    "wof:placetype":"venue"
},
  "geometry": {"coordinates":[-81.988685,36.706333],"type":"Point"}
}