{
  "type": "Feature",
  "properties": {
    "iso:country":"US",
    "sg:address":"9006 Copperleaf Ln",
    "sg:city":"Fairfax Station",
    "sg:classifiers":[
        {
            "category":"Professional",
            "subcategory":"Business Services",
            "type":"Services"
        }
    ],
    "sg:phone":"+1 703 690 9542",
    "sg:postcode":"22039",
    "sg:province":"VA",
    "wof:name":"Parallel Systems Service",
    "wof:placetype":"venue"
},
  "geometry": {"coordinates":[-77.253152,38.730617],"type":"Point"}
}