{
  "type": "Feature",
  "properties": {
    "iso:country":"US",
    "sg:address":"472 Redd Dr",
    "sg:city":"Independence",
    "sg:classifiers":[
        {
            "category":"Farming",
            "subcategory":"Farm",
            "type":"Manufacturing & Wholesale Goods"
        }
    ],
    "sg:phone":"+1 276 773 3958",
    "sg:postcode":"24348",
    "sg:province":"VA",
    "sg:tags":[
        "crop",
        "general"
    ],
    "wof:name":"Dannelly Farms LLC",
    "wof:placetype":"venue"
},
  "geometry": {"coordinates":[-81.108126,36.620757],"type":"Point"}
}