{
  "type": "Feature",
  "properties": {
    "iso:country":"US",
    "sg:address":"4141 N Henderson Rd Ste 8",
    "sg:city":"Arlington",
    "sg:classifiers":[
        {
            "category":"Manufacturing",
            "subcategory":"Metals",
            "type":"Manufacturing & Wholesale Goods"
        },
        {
            "category":"Manufacturing",
            "subcategory":"Building Materials",
            "type":"Manufacturing & Wholesale Goods"
        }
    ],
    "sg:phone":"+1 703 973 3799",
    "sg:postcode":"22203",
    "sg:province":"VA",
    "sg:tags":[
        "windows-metal",
        "window",
        "door",
        "storm"
    ],
    "wof:name":"American Replacement Co",
    "wof:placetype":"venue"
},
  "geometry": {"coordinates":[-77.10900700000001,38.875495],"type":"Point"}
}