{
  "type": "Feature",
  "properties": {
    "addr:full":"12525 Jefferson Ave Newport News VA 23602",
    "addr:housenumber":"12525",
    "addr:postcode":"23602",
    "addr:street":"Jefferson Ave",
    "iso:country":"US",
    "sg:address":"12525 Jefferson Ave",
    "sg:city":"Newport News",
    "sg:classifiers":[
        {
            "category":"Autos & Motor Vehicles",
            "subcategory":"Automobile Sales",
            "type":"Retail Goods"
        }
    ],
    "sg:phone":"+1 757 886 1700",
    "sg:postcode":"23602",
    "sg:province":"VA",
    "sg:tags":[
        "new",
        "used",
        "car"
    ],
    "sg:website":"www.suttlemotors.com",
    "wof:name":"Suttle Motor Corp",
    "wof:placetype":"venue"
},
  "geometry": {"coordinates":[-76.510346,37.125905],"type":"Point"}
}