{
  "type": "Feature",
  "properties": {
    "iso:country":"US",
    "sg:address":"6208 Narragansett Dr",
    "sg:city":"Lynchburg",
    "sg:classifiers":[
        {
            "category":"Manufacturing",
            "subcategory":"Building Materials",
            "type":"Manufacturing & Wholesale Goods"
        },
        {
            "category":"Building & Trades",
            "subcategory":"Construction",
            "type":"Services"
        }
    ],
    "sg:phone":"+1 434 942 4316",
    "sg:postcode":"24502",
    "sg:province":"VA",
    "sg:tags":[
        "mfg",
        "general",
        "contractor"
    ],
    "wof:name":"Bittmann Woodworks LLC",
    "wof:placetype":"venue"
},
  "geometry": {"coordinates":[-79.19959900000001,37.376497],"type":"Point"}
}