{
  "type": "Feature",
  "properties": {
    "iso:country":"US",
    "sg:address":"16 S Van Dorn St",
    "sg:city":"Alexandria",
    "sg:classifiers":[
        {
            "category":"Building & Trades",
            "subcategory":"Construction",
            "type":"Services"
        }
    ],
    "sg:phone":"+1 703 212 7531",
    "sg:postcode":"22304",
    "sg:province":"VA",
    "sg:tags":[
        "house"
    ],
    "wof:name":"Holmes Construction",
    "wof:placetype":"venue"
},
  "geometry": {"coordinates":[-77.131877,38.811274],"type":"Point"}
}