{
  "type": "Feature",
  "properties": {
    "addr:full":"44067 John Mosby Hwy Chantilly VA 20152",
    "addr:housenumber":"44067",
    "addr:postcode":"20152",
    "addr:street":"John Mosby Hwy",
    "iso:country":"US",
    "sg:address":"44067 John Mosby Hwy",
    "sg:city":"Chantilly",
    "sg:classifiers":[
        {
            "category":"Retail",
            "subcategory":"Animal Services",
            "type":"Services"
        }
    ],
    "sg:phone":"+1 703 471 9617",
    "sg:postcode":"20152",
    "sg:province":"VA",
    "wof:name":"Pleasant Valley Kennel",
    "wof:placetype":"venue"
},
  "geometry": {"coordinates":[-77.47891300000001,38.913168],"type":"Point"}
}