{
  "type": "Feature",
  "properties": {
    "addr:full":"310 Kentucky Ave SW Norton VA 24273",
    "addr:housenumber":"310",
    "addr:postcode":"24273",
    "addr:street":"Kentucky Ave Sw",
    "iso:country":"US",
    "sg:address":"310 Kentucky Ave SW",
    "sg:city":"Norton",
    "sg:classifiers":[
        {
            "category":"Wholesale",
            "subcategory":"Machinery & Supplies",
            "type":"Manufacturing & Wholesale Goods"
        }
    ],
    "sg:phone":"+1 276 679 1010",
    "sg:postcode":"24273",
    "sg:province":"VA",
    "sg:tags":[
        "equipment"
    ],
    "wof:name":"Carter Machinery Company Inc",
    "wof:placetype":"venue"
},
  "geometry": {"coordinates":[-82.620043,36.933814],"type":"Point"}
}