{
  "type": "Feature",
  "properties": {
    "addr:full":"21060 Whitfield Pl Sterling VA 20165",
    "addr:housenumber":"21060",
    "addr:postcode":"20165",
    "addr:street":"Whitfield Pl",
    "iso:country":"US",
    "sg:address":"21060 Whitfield Pl",
    "sg:city":"Sterling",
    "sg:classifiers":[
        {
            "category":"Organizations",
            "subcategory":"Membership Organization",
            "type":"Services"
        }
    ],
    "sg:phone":"+1 703 430 2397",
    "sg:postcode":"20165",
    "sg:province":"VA",
    "wof:name":"Loudon Senior Center",
    "wof:placetype":"venue"
},
  "geometry": {"coordinates":[-77.394862,39.03442],"type":"Point"}
}