{
  "type": "Feature",
  "properties": {
    "iso:country":"US",
    "sg:address":"12528 Warwick Blvd",
    "sg:city":"Newport News",
    "sg:classifiers":[
        {
            "category":"Health Services",
            "subcategory":"Doctor",
            "type":"Services"
        }
    ],
    "sg:phone":"+1 757 591 8515",
    "sg:postcode":"23606",
    "sg:province":"VA",
    "wof:name":"Menges Martin J Jr",
    "wof:placetype":"venue"
},
  "geometry": {"coordinates":[-76.49640599999999,37.079177],"type":"Point"}
}