{
  "type": "Feature",
  "properties": {
    "addr:full":"2800 Chapelwood Ln Henrico VA 23233",
    "addr:housenumber":"2800",
    "addr:postcode":"23233",
    "addr:street":"Chapelwood Ln",
    "iso:country":"US",
    "sg:address":"2800 Chapelwood Ln",
    "sg:city":"Henrico",
    "sg:phone":"+1 804 754 8556",
    "sg:postcode":"23233",
    "sg:province":"VA",
    "wof:name":"Star Cab",
    "wof:placetype":"venue"
},
  "geometry": {"coordinates":[-77.609459,37.635601],"type":"Point"}
}