{
  "type": "Feature",
  "properties": {
    "iso:country":"US",
    "sg:address":"13298 Leafcrest Ln",
    "sg:city":"Fairfax",
    "sg:classifiers":[
        {
            "category":"Professional",
            "subcategory":"Management & Consulting",
            "type":"Services"
        }
    ],
    "sg:phone":"+1 703 378 9812",
    "sg:postcode":"22033",
    "sg:province":"VA",
    "sg:tags":[
        "business"
    ],
    "wof:name":"D B Associates",
    "wof:placetype":"venue"
},
  "geometry": {"coordinates":[-77.401664,38.880801],"type":"Point"}
}