{
  "type": "Feature",
  "properties": {
    "iso:country":"US",
    "sg:address":"11321 Genito Rd",
    "sg:city":"Midlothian",
    "sg:classifiers":[
        {
            "category":"Retail",
            "subcategory":"Auto Repair",
            "type":"Services"
        }
    ],
    "sg:phone":"+1 804 744 3959",
    "sg:postcode":"23112",
    "sg:province":"VA",
    "sg:tags":[
        "automotive",
        "center",
        "lubrication"
    ],
    "wof:name":"Jiffy Lube",
    "wof:placetype":"venue"
},
  "geometry": {"coordinates":[-77.602704,37.43811],"type":"Point"}
}