{
  "type": "Feature",
  "properties": {
    "addr:full":"550 Buck Mountain Rd Earlysville VA 22936",
    "addr:housenumber":"550",
    "addr:postcode":"22936",
    "addr:street":"Buck Mountain Rd",
    "iso:country":"US",
    "sg:address":"550 Buck Mountain Rd",
    "sg:city":"Earlysville",
    "sg:classifiers":[
        {
            "category":"Organizations",
            "subcategory":"Religious Organization",
            "type":"Services"
        }
    ],
    "sg:phone":"+1 434 978 3819",
    "sg:postcode":"22936",
    "sg:province":"VA",
    "sg:website":"www.chestnutgrovebaptist.org",
    "wof:name":"Chestnut Grove Baptist Church",
    "wof:placetype":"venue"
},
  "geometry": {"coordinates":[-78.49420000000001,38.174822],"type":"Point"}
}