{
  "type": "Feature",
  "properties": {
    "addr:full":"111 Jarratt Ave Jarratt VA 23867",
    "addr:housenumber":"111",
    "addr:postcode":"23867",
    "addr:street":"Jarratt Ave",
    "iso:country":"US",
    "sg:address":"111 Jarratt Ave",
    "sg:city":"Jarratt",
    "sg:classifiers":[
        {
            "category":"Wholesale",
            "subcategory":"Hardware",
            "type":"Manufacturing & Wholesale Goods"
        },
        {
            "category":"Home & Garden",
            "subcategory":"Garden Supply",
            "type":"Retail Goods"
        },
        {
            "category":"Retail",
            "subcategory":"Repair Shop",
            "type":"Services"
        }
    ],
    "sg:phone":"+1 434 535 8137",
    "sg:postcode":"23867",
    "sg:province":"VA",
    "sg:tags":[
        "renting",
        "lawn",
        "outdoor",
        "power",
        "landscaping",
        "equipment-sales",
        "equipment",
        "saw"
    ],
    "sg:website":"http://www.stihlusa.com/",
    "wof:name":"Jarratt Hardware",
    "wof:placetype":"venue"
},
  "geometry": {"coordinates":[-77.466675,36.812925],"type":"Point"}
}