{
  "type": "Feature",
  "properties": {
    "addr:full":"8136 Larkin Ln Vienna VA 22027",
    "addr:housenumber":"8136",
    "addr:postcode":"22027",
    "addr:street":"Larkin Ln",
    "iso:country":"US",
    "sg:address":"8136 Larkin Ln",
    "sg:city":"Vienna",
    "sg:classifiers":[
        {
            "category":"Building & Trades",
            "subcategory":"Construction",
            "type":"Services"
        }
    ],
    "sg:phone":"+1 571 295 8122",
    "sg:postcode":"22027",
    "sg:province":"VA",
    "sg:tags":[
        "contractor"
    ],
    "wof:name":"PK Services",
    "wof:placetype":"venue"
},
  "geometry": {"coordinates":[-77.226,38.899163],"type":"Point"}
}