{
  "type": "Feature",
  "properties": {
    "iso:country":"US",
    "sg:address":"3186 Prestwood Rd",
    "sg:city":"Alberta",
    "sg:classifiers":[
        {
            "category":"Real Estate",
            "subcategory":"Real Estate Operator",
            "type":"Services"
        }
    ],
    "sg:phone":"+1 434 949 7584",
    "sg:postcode":"23821",
    "sg:province":"VA",
    "sg:tags":[
        "property",
        "lessor"
    ],
    "wof:name":"Richard Davis",
    "wof:placetype":"venue"
},
  "geometry": {"coordinates":[-77.87834100000001,36.84229],"type":"Point"}
}