{
  "type": "Feature",
  "properties": {
    "addr:full":"1837 Monet Ct Virginia Beach VA 23453",
    "addr:housenumber":"1837",
    "addr:postcode":"23453",
    "addr:street":"Monet Ct",
    "iso:country":"US",
    "sg:address":"1837 Monet Ct",
    "sg:city":"Virginia Beach",
    "sg:classifiers":[
        {
            "category":"Building & Trades",
            "subcategory":"Construction",
            "type":"Services"
        }
    ],
    "sg:phone":"+1 757 468 4242",
    "sg:postcode":"23453",
    "sg:province":"VA",
    "sg:tags":[
        "commercial"
    ],
    "wof:name":"A To Z Enterprises",
    "wof:placetype":"venue"
},
  "geometry": {"coordinates":[-76.08298600000001,36.778233],"type":"Point"}
}