{
  "type": "Feature",
  "properties": {
    "iso:country":"US",
    "sg:address":"8 E Federal St",
    "sg:city":"Middleburg",
    "sg:classifiers":[
        {
            "category":"Health Services",
            "subcategory":"Doctor",
            "type":"Services"
        }
    ],
    "sg:phone":"+1 540 687 6789",
    "sg:postcode":"20117",
    "sg:province":"VA",
    "sg:tags":[
        "physician",
        "surgeon"
    ],
    "wof:name":"Noel Schweig MD",
    "wof:placetype":"venue"
},
  "geometry": {"coordinates":[-77.733864,38.968766],"type":"Point"}
}