{
  "type": "Feature",
  "properties": {
    "addr:full":"4301 Monument Ave Richmond VA 23230",
    "addr:housenumber":"4301",
    "addr:postcode":"23230",
    "addr:street":"Monument Ave",
    "iso:country":"US",
    "sg:address":"4301 Monument Ave",
    "sg:city":"Richmond",
    "sg:classifiers":[
        {
            "category":"Professional",
            "type":"Services"
        }
    ],
    "sg:phone":"+1 904 353 3500",
    "sg:postcode":"23230",
    "sg:province":"VA",
    "wof:name":"Distinctive Collections Ltd",
    "wof:placetype":"venue"
},
  "geometry": {"coordinates":[-77.490284,37.571982],"type":"Point"}
}