{
  "type": "Feature",
  "properties": {
    "addr:full":"9419 Braddock Rd Fairfax VA 22032",
    "addr:housenumber":"9419",
    "addr:postcode":"22032",
    "addr:street":"Braddock Rd",
    "iso:country":"US",
    "sg:address":"9419 Braddock Rd",
    "sg:city":"Fairfax",
    "sg:classifiers":[
        {
            "category":"Banks & Credit Unions",
            "subcategory":"Bank",
            "type":"Services"
        }
    ],
    "sg:phone":"+1 703 323 0222",
    "sg:postcode":"22032",
    "sg:province":"VA",
    "wof:name":"Apple Federal Credit Union",
    "wof:placetype":"venue"
},
  "geometry": {"coordinates":[-77.271309,38.815906],"type":"Point"}
}