{
  "type": "Feature",
  "properties": {
    "iso:country":"US",
    "sg:address":"5548 Old Warson Dr",
    "sg:city":"Richmond",
    "sg:classifiers":[
        {
            "category":"Professional",
            "subcategory":"Computer Services",
            "type":"Services"
        }
    ],
    "sg:phone":"+1 804 751 0937",
    "sg:postcode":"23237",
    "sg:province":"VA",
    "sg:tags":[
        "development",
        "on",
        "design"
    ],
    "wof:name":"Dawn Resources",
    "wof:placetype":"venue"
},
  "geometry": {"coordinates":[-77.481539,37.381431],"type":"Point"}
}