{
  "type": "Feature",
  "properties": {
    "addr:full":"7137 Little River Tpke Annandale VA 22003",
    "addr:housenumber":"7137",
    "addr:postcode":"22003",
    "addr:street":"Little River Tpke",
    "iso:country":"US",
    "sg:address":"7137 Little River Tpke",
    "sg:city":"Annandale",
    "sg:classifiers":[
        {
            "category":"Shopping",
            "subcategory":"Jewelry",
            "type":"Retail Goods"
        }
    ],
    "sg:phone":"+1 703 354 1038",
    "sg:postcode":"22003",
    "sg:province":"VA",
    "sg:tags":[
        "jeweler"
    ],
    "wof:name":"Goldsmith Lambros Inc",
    "wof:placetype":"venue"
},
  "geometry": {"coordinates":[-77.192966,38.829814],"type":"Point"}
}