{
  "type": "Feature",
  "properties": {
    "iso:country":"US",
    "sg:address":"5746 Churchland Blvd",
    "sg:city":"Portsmouth",
    "sg:classifiers":[
        {
            "category":"Shopping",
            "subcategory":"Florist",
            "type":"Retail Goods"
        }
    ],
    "sg:phone":"+1 757 484 8484",
    "sg:postcode":"23703",
    "sg:province":"VA",
    "wof:name":"Norfolk Florist & Gifts",
    "wof:placetype":"venue"
},
  "geometry": {"coordinates":[-76.39305299999999,36.862086],"type":"Point"}
}