{
  "type": "Feature",
  "properties": {
    "addr:full":"100 E Broadway Ave Hopewell VA 23860",
    "addr:housenumber":"100",
    "addr:postcode":"23860",
    "addr:street":"E Broadway Ave",
    "iso:country":"US",
    "sg:address":"100 E Broadway Ave",
    "sg:city":"Hopewell",
    "sg:classifiers":[
        {
            "category":"Government",
            "subcategory":"Court House",
            "type":"Public Place"
        }
    ],
    "sg:phone":"+1 804 541 2255",
    "sg:postcode":"23860",
    "sg:province":"VA",
    "sg:tags":[
        "city",
        "counsel"
    ],
    "wof:name":"Hopewell Commonwealth Attorney",
    "wof:placetype":"venue"
},
  "geometry": {"coordinates":[-77.28652099999999,37.304038],"type":"Point"}
}