{
  "type": "Feature",
  "properties": {
    "addr:full":"6560 Backlick Rd Springfield VA 22150",
    "addr:housenumber":"6560",
    "addr:postcode":"22150",
    "addr:street":"Backlick Rd",
    "iso:country":"US",
    "sg:address":"6560 Backlick Rd",
    "sg:city":"Springfield",
    "sg:classifiers":[
        {
            "category":"Utilities",
            "subcategory":"Telephone",
            "type":"Services"
        },
        {
            "category":"Manufacturing",
            "subcategory":"Electronics",
            "type":"Manufacturing & Wholesale Goods"
        }
    ],
    "sg:phone":"+1 703 866 0017",
    "sg:postcode":"22150",
    "sg:province":"VA",
    "sg:tags":[
        "equipment",
        "telecommunications-equipment",
        "system",
        "supply"
    ],
    "wof:name":"Francis J Megan",
    "wof:placetype":"venue"
},
  "geometry": {"coordinates":[-77.183774,38.776464],"type":"Point"}
}