{
  "type": "Feature",
  "properties": {
    "addr:full":"2604 Ballentine Blvd Norfolk VA 23509",
    "addr:housenumber":"2604",
    "addr:postcode":"23509",
    "addr:street":"Ballentine Blvd",
    "iso:country":"US",
    "sg:address":"2604 Ballentine Blvd",
    "sg:city":"Norfolk",
    "sg:classifiers":[
        {
            "category":"Personal",
            "subcategory":"Beauty Salon",
            "type":"Services"
        }
    ],
    "sg:phone":"+1 757 857 0879",
    "sg:postcode":"23509",
    "sg:province":"VA",
    "sg:tags":[
        "shop"
    ],
    "wof:name":"Strictly Business Unisex Salon",
    "wof:placetype":"venue"
},
  "geometry": {"coordinates":[-76.251993,36.869531],"type":"Point"}
}