{
  "type": "Feature",
  "properties": {
    "addr:full":"1700 S Main St Blacksburg VA 24060",
    "addr:housenumber":"1700",
    "addr:postcode":"24060",
    "addr:street":"S Main St",
    "iso:country":"US",
    "sg:address":"1700 S Main St",
    "sg:city":"Blacksburg",
    "sg:classifiers":[
        {
            "category":"Food & Beverages",
            "subcategory":"Groceries & Convenience Stores",
            "type":"Retail Goods"
        }
    ],
    "sg:phone":"+1 540 552 0516",
    "sg:postcode":"24060",
    "sg:province":"VA",
    "wof:name":"LA Fabulosa",
    "wof:placetype":"venue"
},
  "geometry": {"coordinates":[-80.39975699999999,37.211427],"type":"Point"}
}