{
  "type": "Feature",
  "properties": {
    "addr:full":"14910 Feeder Ln Woodbridge VA 22193",
    "addr:housenumber":"14910",
    "addr:postcode":"22193",
    "addr:street":"Feeder Ln",
    "iso:country":"US",
    "sg:address":"14910 Feeder Ln",
    "sg:city":"Woodbridge",
    "sg:classifiers":[
        {
            "category":"Social Services",
            "subcategory":"Child Care",
            "type":"Services"
        }
    ],
    "sg:phone":"+1 703 878 3371",
    "sg:postcode":"22193",
    "sg:province":"VA",
    "wof:name":"Minnieland Private Day School",
    "wof:placetype":"venue"
},
  "geometry": {"coordinates":[-77.34784000000001,38.629817],"type":"Point"}
}