{
  "type": "Feature",
  "properties": {
    "addr:full":"5219 Easton Dr Springfield VA 22151",
    "addr:housenumber":"5219",
    "addr:postcode":"22151",
    "addr:street":"Easton Dr",
    "iso:country":"US",
    "sg:address":"5219 Easton Dr",
    "sg:city":"Springfield",
    "sg:classifiers":[
        {
            "category":"Communications",
            "subcategory":"Radio Station",
            "type":"Services"
        }
    ],
    "sg:phone":"+1 703 813 5750",
    "sg:postcode":"22151",
    "sg:province":"VA",
    "sg:tags":[
        "broadcasting"
    ],
    "wof:name":"Mohammed Bouzghaia",
    "wof:placetype":"venue"
},
  "geometry": {"coordinates":[-77.195194,38.807976],"type":"Point"}
}