{
  "type": "Feature",
  "properties": {
    "iso:country":"US",
    "sg:address":"4300 Portsmouth Blvd",
    "sg:city":"Portsmouth",
    "sg:classifiers":[
        {
            "category":"Food & Beverages",
            "subcategory":"Liquor & Beverages",
            "type":"Retail Goods"
        }
    ],
    "sg:phone":"+1 757 465 6850",
    "sg:postcode":"23701",
    "sg:province":"VA",
    "wof:name":"Virginia State Liquor Store",
    "wof:placetype":"venue"
},
  "geometry": {"coordinates":[-76.362342,36.816245],"type":"Point"}
}