{
  "type": "Feature",
  "properties": {
    "iso:country":"US",
    "sg:address":"6383 Little River Tpke",
    "sg:city":"Alexandria",
    "sg:classifiers":[
        {
            "category":"Real Estate",
            "subcategory":"Real Estate Agent",
            "type":"Services"
        }
    ],
    "sg:phone":"+1 703 451 4544",
    "sg:postcode":"22312",
    "sg:province":"VA",
    "sg:website":"www.gfhrealty.com",
    "wof:name":"GFH Realty",
    "wof:placetype":"venue"
},
  "geometry": {"coordinates":[-77.150597,38.819591],"type":"Point"}
}