{
  "type": "Feature",
  "properties": {
    "iso:country":"US",
    "sg:address":"7 Langley Ct",
    "sg:city":"Portsmouth",
    "sg:classifiers":[
        {
            "category":"Health Services",
            "subcategory":"Clinic",
            "type":"Services"
        }
    ],
    "sg:phone":"+1 757 558 4715",
    "sg:postcode":"23701",
    "sg:province":"VA",
    "sg:tags":[
        "home"
    ],
    "wof:name":"Special Touch Home Care",
    "wof:placetype":"venue"
},
  "geometry": {"coordinates":[-76.356758,36.799319],"type":"Point"}
}