{
  "type": "Feature",
  "properties": {
    "addr:full":"10821 Courthouse Rd Fredericksburg VA 22407",
    "addr:housenumber":"10821",
    "addr:postcode":"22407",
    "addr:street":"Courthouse Rd",
    "iso:country":"US",
    "sg:address":"10821 Courthouse Rd",
    "sg:city":"Fredericksburg",
    "sg:classifiers":[
        {
            "category":"Professional",
            "subcategory":"Business Services",
            "type":"Services"
        }
    ],
    "sg:phone":"+1 540 891 6198",
    "sg:postcode":"22407",
    "sg:province":"VA",
    "wof:name":"Security By Design",
    "wof:placetype":"venue"
},
  "geometry": {"coordinates":[-77.501238,38.25326],"type":"Point"}
}