{
  "type": "Feature",
  "properties": {
    "addr:full":"3107 Old Hilliard Rd Richmond VA 23228",
    "addr:housenumber":"3107",
    "addr:postcode":"23228",
    "addr:street":"Old Hilliard Rd",
    "iso:country":"US",
    "sg:address":"3107 Old Hilliard Rd",
    "sg:city":"Richmond",
    "sg:classifiers":[
        {
            "category":"Autos & Motor Vehicles",
            "subcategory":"Automobile Sales",
            "type":"Retail Goods"
        }
    ],
    "sg:phone":"+1 804 249 5990",
    "sg:postcode":"23228",
    "sg:province":"VA",
    "sg:tags":[
        "used"
    ],
    "wof:name":"Integrity Motors",
    "wof:placetype":"venue"
},
  "geometry": {"coordinates":[-77.496075,37.612642],"type":"Point"}
}