{
  "type": "Feature",
  "properties": {
    "addr:full":"12601 Jefferson Davis Hwy Chester VA 23831",
    "addr:housenumber":"12601",
    "addr:postcode":"23831",
    "addr:street":"Jefferson Davis Hwy",
    "iso:country":"US",
    "sg:address":"12601 Jefferson Davis Hwy",
    "sg:city":"Chester",
    "sg:classifiers":[
        {
            "category":"Manufacturing",
            "subcategory":"Food",
            "type":"Manufacturing & Wholesale Goods"
        }
    ],
    "sg:phone":"+1 804 379 7300",
    "sg:postcode":"23831",
    "sg:province":"VA",
    "sg:tags":[
        "bakery",
        "prod",
        "cookie"
    ],
    "sg:website":"www.ukrops.com",
    "wof:name":"Ukrop's Cafe & Grill",
    "wof:placetype":"venue"
},
  "geometry": {"coordinates":[-77.41255099999999,37.353061],"type":"Point"}
}