{
  "type": "Feature",
  "properties": {
    "addr:full":"1340 Roanoke Arch Chesapeake VA 23322",
    "addr:housenumber":"1340",
    "addr:postcode":"23322",
    "addr:street":"Roanoke Arch",
    "iso:country":"US",
    "sg:address":"1340 Roanoke Arch",
    "sg:city":"Chesapeake",
    "sg:classifiers":[
        {
            "category":"Professional",
            "subcategory":"Business Services",
            "type":"Services"
        }
    ],
    "sg:phone":"+1 757 482 6982",
    "sg:postcode":"23322",
    "sg:province":"VA",
    "wof:name":"Structural Solutions",
    "wof:placetype":"venue"
},
  "geometry": {"coordinates":[-76.192618,36.7099],"type":"Point"}
}