{
  "type": "Feature",
  "properties": {
    "iso:country":"US",
    "sg:address":"410 9th St NW",
    "sg:city":"Charlottesville",
    "sg:classifiers":[
        {
            "category":"Professional",
            "subcategory":"Art Services",
            "type":"Services"
        }
    ],
    "sg:phone":"+1 434 296 4779",
    "sg:postcode":"22903",
    "sg:province":"VA",
    "sg:tags":[
        "commercial",
        "graphic",
        "design"
    ],
    "wof:name":"Michael Beck Design",
    "wof:placetype":"venue"
},
  "geometry": {"coordinates":[-78.489965,38.036196],"type":"Point"}
}