{
  "type": "Feature",
  "properties": {
    "addr:full":"140 Costello Dr Winchester VA 22602",
    "addr:housenumber":"140",
    "addr:postcode":"22602",
    "addr:street":"Costello Dr",
    "iso:country":"US",
    "sg:address":"140 Costello Dr",
    "sg:city":"Winchester",
    "sg:classifiers":[
        {
            "category":"Travel",
            "subcategory":"Hotels & Motels",
            "type":"Entertainment"
        }
    ],
    "sg:phone":"+1 540 667 7636",
    "sg:postcode":"22602",
    "sg:province":"VA",
    "wof:name":"Sleep Inn & Suites",
    "wof:placetype":"venue"
},
  "geometry": {"coordinates":[-78.15187299999999,39.15525],"type":"Point"}
}