{
  "type": "Feature",
  "properties": {
    "addr:full":"1707 Abbey Oak Dr Vienna VA 22182",
    "addr:housenumber":"1707",
    "addr:postcode":"22182",
    "addr:street":"Abbey Oak Dr",
    "iso:country":"US",
    "sg:address":"1707 Abbey Oak Dr",
    "sg:city":"Vienna",
    "sg:classifiers":[
        {
            "category":"Professional",
            "subcategory":"Research",
            "type":"Services"
        }
    ],
    "sg:phone":"+1 703 242 8984",
    "sg:postcode":"22182",
    "sg:province":"VA",
    "sg:tags":[
        "nonphysical",
        "commercial"
    ],
    "wof:name":"Bovarov Spiro",
    "wof:placetype":"venue"
},
  "geometry": {"coordinates":[-77.28999899999999,38.937346],"type":"Point"}
}