{
  "type": "Feature",
  "properties": {
    "addr:full":"1001 Henson Ave Pearisburg VA 24134",
    "addr:housenumber":"1001",
    "addr:postcode":"24134",
    "addr:street":"Henson Ave",
    "iso:country":"US",
    "sg:address":"1001 Henson Ave",
    "sg:city":"Pearisburg",
    "sg:classifiers":[
        {
            "category":"Education",
            "subcategory":"School",
            "type":"Public Place"
        }
    ],
    "sg:phone":"+1 540 921 1363",
    "sg:postcode":"24134",
    "sg:province":"VA",
    "wof:name":"Macy Mc Claugherty Elementary",
    "wof:placetype":"venue"
},
  "geometry": {"coordinates":[-80.72668,37.323991],"type":"Point"}
}