{
  "type": "Feature",
  "properties": {
    "addr:full":"5112 Dominion Dr Suffolk VA 23435",
    "addr:housenumber":"5112",
    "addr:postcode":"23435",
    "addr:street":"Dominion Dr",
    "iso:country":"US",
    "sg:address":"5112 Dominion Dr",
    "sg:city":"Suffolk",
    "sg:classifiers":[
        {
            "category":"Wholesale",
            "subcategory":"Durable Goods & Equipment",
            "type":"Manufacturing & Wholesale Goods"
        }
    ],
    "sg:phone":"+1 757 683 5061",
    "sg:postcode":"23435",
    "sg:province":"VA",
    "sg:tags":[
        "development",
        "instrument",
        "retail",
        "scientific",
        "sales"
    ],
    "wof:name":"Micron Optical Systems Inc",
    "wof:placetype":"venue"
},
  "geometry": {"coordinates":[-76.498683,36.847548],"type":"Point"}
}