{
  "type": "Feature",
  "properties": {
    "iso:country":"US",
    "sg:address":"1820 S High St",
    "sg:city":"Harrisonburg",
    "sg:classifiers":[
        {
            "category":"Manufacturing",
            "subcategory":"Wood Products",
            "type":"Manufacturing & Wholesale Goods"
        },
        {
            "category":"Manufacturing",
            "subcategory":"Tools & Machinery",
            "type":"Manufacturing & Wholesale Goods"
        }
    ],
    "sg:phone":"+1 540 434 2959",
    "sg:postcode":"22801",
    "sg:province":"VA",
    "sg:tags":[
        "windmill",
        "mfg"
    ],
    "wof:name":"Kelley Windmills",
    "wof:placetype":"venue"
},
  "geometry": {"coordinates":[-78.90227299999999,38.432338],"type":"Point"}
}