{
  "type": "Feature",
  "properties": {
    "addr:full":"9747 Water Oak Dr Fairfax VA 22031",
    "addr:housenumber":"9747",
    "addr:postcode":"22031",
    "addr:street":"Water Oak Dr",
    "iso:country":"US",
    "sg:address":"9747 Water Oak Dr",
    "sg:city":"Fairfax",
    "sg:classifiers":[
        {
            "category":"Professional",
            "subcategory":"Management & Consulting",
            "type":"Services"
        }
    ],
    "sg:phone":"+1 703 242 8142",
    "sg:postcode":"22031",
    "sg:province":"VA",
    "sg:tags":[
        "business"
    ],
    "wof:name":"Micronet Science Inc",
    "wof:placetype":"venue"
},
  "geometry": {"coordinates":[-77.28525999999999,38.872724],"type":"Point"}
}