{
  "type": "Feature",
  "properties": {
    "addr:full":"4791 Walton Ln Roanoke VA 24018",
    "addr:housenumber":"4791",
    "addr:postcode":"24018",
    "addr:street":"Walton Ln",
    "iso:country":"US",
    "sg:address":"4791 Walton Ln",
    "sg:city":"Roanoke",
    "sg:classifiers":[
        {
            "category":"Arts & Performance",
            "subcategory":"Theater",
            "type":"Entertainment"
        }
    ],
    "sg:phone":"+1 540 989 4677",
    "sg:postcode":"24018",
    "sg:province":"VA",
    "sg:tags":[
        "group"
    ],
    "wof:name":"Good Times Entertainment",
    "wof:placetype":"venue"
},
  "geometry": {"coordinates":[-80.04720399999999,37.251235],"type":"Point"}
}