{
  "type": "Feature",
  "properties": {
    "addr:full":"4717 Ewell Rd Fredericksburg VA 22408",
    "addr:housenumber":"4717",
    "addr:postcode":"22408",
    "addr:street":"Ewell Rd",
    "iso:country":"US",
    "sg:address":"4717 Ewell Rd",
    "sg:city":"Fredericksburg",
    "sg:classifiers":[
        {
            "category":"Utilities",
            "subcategory":"Refuse",
            "type":"Services"
        }
    ],
    "sg:phone":"+1 540 898 8000",
    "sg:postcode":"22408",
    "sg:province":"VA",
    "sg:tags":[
        "recycling"
    ],
    "wof:name":"J & E Recycling LLC",
    "wof:placetype":"venue"
},
  "geometry": {"coordinates":[-77.502914,38.253211],"type":"Point"}
}