{
  "type": "Feature",
  "properties": {
    "addr:full":"205 N Shields Ave Richmond VA 23220",
    "addr:housenumber":"205",
    "addr:postcode":"23220",
    "addr:street":"N Shields Ave",
    "iso:country":"US",
    "sg:address":"205 N Shields Ave",
    "sg:city":"Richmond",
    "sg:classifiers":[
        {
            "category":"Restaurant",
            "type":"Food & Drink"
        }
    ],
    "sg:phone":"+1 804 355 2282",
    "sg:postcode":"23220",
    "sg:province":"VA",
    "sg:tags":[
        "eating"
    ],
    "wof:name":"Joe's Inn",
    "wof:placetype":"venue"
},
  "geometry": {"coordinates":[-77.46639999999999,37.55337],"type":"Point"}
}