{
  "type": "Feature",
  "properties": {
    "addr:full":"2463 Beech Ave Buena Vista VA 24416",
    "addr:housenumber":"2463",
    "addr:postcode":"24416",
    "addr:street":"Beech Ave",
    "iso:country":"US",
    "sg:address":"2463 Beech Ave",
    "sg:city":"Buena Vista",
    "sg:classifiers":[
        {
            "category":"Shopping",
            "subcategory":"Florist",
            "type":"Retail Goods"
        }
    ],
    "sg:phone":"+1 540 261 6300",
    "sg:postcode":"24416",
    "sg:province":"VA",
    "wof:name":"Flowers & Things",
    "wof:placetype":"venue"
},
  "geometry": {"coordinates":[-79.35495899999999,37.739155],"type":"Point"}
}