{
  "type": "Feature",
  "properties": {
    "iso:country":"US",
    "sg:address":"1349 Electric Ct",
    "sg:city":"Virginia Beach",
    "sg:classifiers":[
        {
            "category":"Restaurant",
            "type":"Food & Drink"
        }
    ],
    "sg:phone":"+1 757 491 2655",
    "sg:postcode":"23451",
    "sg:province":"VA",
    "sg:tags":[
        "eating"
    ],
    "wof:name":"Malbons Catering",
    "wof:placetype":"venue"
},
  "geometry": {"coordinates":[-75.992267,36.792251],"type":"Point"}
}