{
  "type": "Feature",
  "properties": {
    "addr:full":"2800 Franklin St Salem VA 24153",
    "addr:housenumber":"2800",
    "addr:postcode":"24153",
    "addr:street":"Franklin St",
    "iso:country":"US",
    "sg:address":"2800 Franklin St",
    "sg:city":"Salem",
    "sg:classifiers":[
        {
            "category":"Home & Garden",
            "subcategory":"Garden Supply",
            "type":"Retail Goods"
        }
    ],
    "sg:phone":"+1 540 330 8473",
    "sg:postcode":"24153",
    "sg:province":"VA",
    "sg:tags":[
        "lawn",
        "mower"
    ],
    "wof:name":"Yard Equipment Svc",
    "wof:placetype":"venue"
},
  "geometry": {"coordinates":[-80.06449499999999,37.264196],"type":"Point"}
}