{
  "type": "Feature",
  "properties": {
    "iso:country":"US",
    "sg:address":"1901 Beauregard St",
    "sg:city":"Alexandria",
    "sg:classifiers":[
        {
            "category":"Professional",
            "subcategory":"Management & Consulting",
            "type":"Services"
        }
    ],
    "sg:phone":"+1 703 998 1640",
    "sg:postcode":"22311",
    "sg:province":"VA",
    "sg:tags":[
        "consultant",
        "business"
    ],
    "sg:website":"www.alionscience.com",
    "wof:name":"Alliance Science Technology",
    "wof:placetype":"venue"
},
  "geometry": {"coordinates":[-77.11979599999999,38.833773],"type":"Point"}
}