{
  "type": "Feature",
  "properties": {
    "addr:full":"4232 Bonniebank Rd Richmond VA 23234",
    "addr:housenumber":"4232",
    "addr:postcode":"23234",
    "addr:street":"Bonniebank Rd",
    "iso:country":"US",
    "sg:address":"4232 Bonniebank Rd",
    "sg:city":"Richmond",
    "sg:classifiers":[
        {
            "category":"Social Services",
            "subcategory":"Child Care",
            "type":"Services"
        }
    ],
    "sg:phone":"+1 804 271 0188",
    "sg:postcode":"23234",
    "sg:province":"VA",
    "sg:tags":[
        "center"
    ],
    "wof:name":"Meadowbrook Child Care Center",
    "wof:placetype":"venue"
},
  "geometry": {"coordinates":[-77.47503500000001,37.444769],"type":"Point"}
}