{
  "type": "Feature",
  "properties": {
    "iso:country":"US",
    "sg:address":"120 Woodstock Dr",
    "sg:city":"Charlottesville",
    "sg:classifiers":[
        {
            "category":"Real Estate",
            "subcategory":"Real Estate Agent",
            "type":"Services"
        }
    ],
    "sg:phone":"+1 434 296 5444",
    "sg:postcode":"22901",
    "sg:province":"VA",
    "wof:name":"Lindsay Milby Inc",
    "wof:placetype":"venue"
},
  "geometry": {"coordinates":[-78.50264300000001,38.062738],"type":"Point"}
}