{
  "type": "Feature",
  "properties": {
    "addr:full":"233 Hydraulic Ridge Rd Charlottesville VA 22901",
    "addr:housenumber":"233",
    "addr:postcode":"22901",
    "addr:street":"Hydraulic Ridge Rd",
    "iso:country":"US",
    "sg:address":"233 Hydraulic Ridge Rd",
    "sg:city":"Charlottesville",
    "sg:classifiers":[
        {
            "category":"Health Services",
            "subcategory":"Dentist",
            "type":"Services"
        }
    ],
    "sg:phone":"+1 434 975 7435",
    "sg:postcode":"22901",
    "sg:province":"VA",
    "sg:tags":[
        "orthodontist"
    ],
    "wof:name":"Inouye David K DMD",
    "wof:placetype":"venue"
},
  "geometry": {"coordinates":[-78.49831500000001,38.074596],"type":"Point"}
}