{
  "type": "Feature",
  "properties": {
    "addr:full":"497 Cumberland St Bristol VA 24201",
    "addr:housenumber":"497",
    "addr:postcode":"24201",
    "addr:street":"Cumberland St",
    "iso:country":"US",
    "sg:address":"497 Cumberland St",
    "sg:city":"Bristol",
    "sg:classifiers":[
        {
            "category":"Government",
            "subcategory":"Office",
            "type":"Public Place"
        }
    ],
    "sg:phone":"+1 276 821 6100",
    "sg:postcode":"24201",
    "sg:province":"VA",
    "sg:tags":[
        "village"
    ],
    "sg:website":"www.bristolva.org",
    "wof:name":"Bristol City Of Virginia",
    "wof:placetype":"venue"
},
  "geometry": {"coordinates":[-82.18107999999999,36.596624],"type":"Point"}
}