{
  "type": "Feature",
  "properties": {
    "iso:country":"US",
    "sg:address":"10117 Richmond Hwy",
    "sg:city":"Lorton",
    "sg:classifiers":[
        {
            "category":"Autos & Motor Vehicles",
            "subcategory":"Boat Sales",
            "type":"Retail Goods"
        }
    ],
    "sg:phone":"+1 703 339 6200",
    "sg:postcode":"22079",
    "sg:province":"VA",
    "sg:tags":[
        "dealer"
    ],
    "wof:name":"Hillcrest Marine Inc",
    "wof:placetype":"venue"
},
  "geometry": {"coordinates":[-77.225495,38.681202],"type":"Point"}
}