{
  "type": "Feature",
  "properties": {
    "addr:full":"105 Landmark Dr Stuart VA 24171",
    "addr:housenumber":"105",
    "addr:postcode":"24171",
    "addr:street":"Landmark Dr",
    "iso:country":"US",
    "sg:address":"105 Landmark Dr",
    "sg:city":"Stuart",
    "sg:classifiers":[
        {
            "category":"Health Services",
            "subcategory":"Nursing And Care Facility",
            "type":"Services"
        }
    ],
    "sg:phone":"+1 276 694 7161",
    "sg:postcode":"24171",
    "sg:province":"VA",
    "sg:tags":[
        "home",
        "convalescent"
    ],
    "sg:website":"www.thelandmarkgroupllc.com",
    "wof:name":"Blue Ridge Nursing Ctr",
    "wof:placetype":"venue"
},
  "geometry": {"coordinates":[-80.260442,36.636328],"type":"Point"}
}