{
  "type": "Feature",
  "properties": {
    "iso:country":"US",
    "sg:address":"6133 Spring Garden Rd",
    "sg:city":"Blairs",
    "sg:classifiers":[
        {
            "category":"Building & Trades",
            "subcategory":"Construction",
            "type":"Services"
        }
    ],
    "sg:phone":"+1 434 489 6888",
    "sg:postcode":"24527",
    "sg:province":"VA",
    "sg:tags":[
        "house"
    ],
    "wof:name":"Heritage Home Improvement",
    "wof:placetype":"venue"
},
  "geometry": {"coordinates":[-79.32400699999999,36.756439],"type":"Point"}
}