{
  "type": "Feature",
  "properties": {
    "addr:full":"623 S Main St Emporia VA 23847",
    "addr:housenumber":"623",
    "addr:postcode":"23847",
    "addr:street":"S Main St",
    "iso:country":"US",
    "sg:address":"623 S Main St",
    "sg:city":"Emporia",
    "sg:classifiers":[
        {
            "category":"Shopping",
            "subcategory":"Florist",
            "type":"Retail Goods"
        }
    ],
    "sg:phone":"+1 434 348 7777",
    "sg:postcode":"23847",
    "sg:province":"VA",
    "wof:name":"Best Buds",
    "wof:placetype":"venue"
},
  "geometry": {"coordinates":[-77.546001,36.679805],"type":"Point"}
}