{
  "type": "Feature",
  "properties": {
    "iso:country":"US",
    "sg:address":"309 Cherokee Dr",
    "sg:city":"Blacksburg",
    "sg:classifiers":[
        {
            "category":"Professional",
            "subcategory":"Research",
            "type":"Services"
        }
    ],
    "sg:phone":"+1 540 953 1555",
    "sg:postcode":"24060",
    "sg:province":"VA",
    "sg:tags":[
        "environmental",
        "ecological"
    ],
    "sg:website":"www.rasint.com",
    "wof:name":"Resources & Systems Intl Inc",
    "wof:placetype":"venue"
},
  "geometry": {"coordinates":[-80.42062,37.249904],"type":"Point"}
}