{
  "type": "Feature",
  "properties": {
    "addr:full":"101 S Jefferson St Roanoke VA 24011",
    "addr:housenumber":"101",
    "addr:postcode":"24011",
    "addr:street":"S Jefferson St",
    "iso:country":"US",
    "sg:address":"101 S Jefferson St",
    "sg:city":"Roanoke",
    "sg:classifiers":[
        {
            "category":"Health Services",
            "subcategory":"Clinic",
            "type":"Services"
        }
    ],
    "sg:phone":"+1 540 344 4400",
    "sg:postcode":"24011",
    "sg:province":"VA",
    "wof:name":"GML Medical Resources",
    "wof:placetype":"venue"
},
  "geometry": {"coordinates":[-79.94055299999999,37.271826],"type":"Point"}
}