{
  "type": "Feature",
  "properties": {
    "addr:full":"8358 Danville Pike Hillsville VA 24343",
    "addr:housenumber":"8358",
    "addr:postcode":"24343",
    "addr:street":"Danville Pike",
    "iso:country":"US",
    "sg:address":"8358 Danville Pike",
    "sg:city":"Hillsville",
    "sg:classifiers":[
        {
            "category":"Restaurant",
            "type":"Food & Drink"
        }
    ],
    "sg:phone":"+1 276 398 4148",
    "sg:postcode":"24343",
    "sg:province":"VA",
    "wof:name":"Crooked Oak Restaurant",
    "wof:placetype":"venue"
},
  "geometry": {"coordinates":[-80.601269,36.719395],"type":"Point"}
}