{
  "type": "Feature",
  "properties": {
    "iso:country":"US",
    "sg:address":"5616 Ox Rd",
    "sg:city":"Fairfax Station",
    "sg:classifiers":[
        {
            "category":"Retail",
            "subcategory":"Laundry & Dry Cleaning",
            "type":"Services"
        }
    ],
    "sg:phone":"+1 703 250 0438",
    "sg:postcode":"22039",
    "sg:province":"VA",
    "sg:tags":[
        "cleaners",
        "plant",
        "drycleaning",
        "rug",
        "except"
    ],
    "wof:name":"Regal Custom Cleaners",
    "wof:placetype":"venue"
},
  "geometry": {"coordinates":[-77.326016,38.804081],"type":"Point"}
}