{
  "type": "Feature",
  "properties": {
    "iso:country":"US",
    "sg:address":"8332 Richmond Hwy",
    "sg:city":"Alexandria",
    "sg:classifiers":[
        {
            "category":"Professional",
            "subcategory":"Management & Consulting",
            "type":"Services"
        }
    ],
    "sg:phone":"+1 703 360 1961",
    "sg:postcode":"22309",
    "sg:province":"VA",
    "sg:tags":[
        "consultant",
        "security",
        "system",
        "business"
    ],
    "wof:name":"Jenkins Security Consultants I",
    "wof:placetype":"venue"
},
  "geometry": {"coordinates":[-77.10332099999999,38.731601],"type":"Point"}
}