{
  "type": "Feature",
  "properties": {
    "addr:full":"546 Upper Poore Valley Rd Saltville VA 24370",
    "addr:housenumber":"546",
    "addr:postcode":"24370",
    "addr:street":"Upper Poore Valley Rd",
    "iso:country":"US",
    "sg:address":"546 Upper Poore Valley Rd",
    "sg:city":"Saltville",
    "sg:classifiers":[
        {
            "category":"Organizations",
            "subcategory":"Labor Organization",
            "type":"Services"
        }
    ],
    "sg:phone":"+1 276 496 3462",
    "sg:postcode":"24370",
    "sg:province":"VA",
    "sg:tags":[
        "contracting",
        "electrical"
    ],
    "wof:name":"Jf Contractors LLC",
    "wof:placetype":"venue"
},
  "geometry": {"coordinates":[-81.73537,36.915193],"type":"Point"}
}