{
  "type": "Feature",
  "properties": {
    "addr:full":"5641 Pickwick Rd Centreville VA 20120",
    "addr:housenumber":"5641",
    "addr:postcode":"20120",
    "addr:street":"Pickwick Rd",
    "iso:country":"US",
    "sg:address":"5641 Pickwick Rd",
    "sg:city":"Centreville",
    "sg:classifiers":[
        {
            "category":"Home & Garden",
            "subcategory":"Mobile Homes",
            "type":"Retail Goods"
        }
    ],
    "sg:phone":"+1 703 815 6423",
    "sg:postcode":"20120",
    "sg:province":"VA",
    "wof:name":"Sully Manor Sales",
    "wof:placetype":"venue"
},
  "geometry": {"coordinates":[-77.423051,38.838955],"type":"Point"}
}