{
  "type": "Feature",
  "properties": {
    "addr:full":"105 Riverview Rd Hurt VA 24563",
    "addr:housenumber":"105",
    "addr:postcode":"24563",
    "addr:street":"Riverview Rd",
    "iso:country":"US",
    "sg:address":"105 Riverview Rd",
    "sg:city":"Hurt",
    "sg:classifiers":[
        {
            "category":"Organizations",
            "subcategory":"Religious Organization",
            "type":"Services"
        }
    ],
    "sg:phone":"+1 434 324 7032",
    "sg:postcode":"24563",
    "sg:province":"VA",
    "wof:name":"Hurt United Methodist Church",
    "wof:placetype":"venue"
},
  "geometry": {"coordinates":[-79.294156,37.10037],"type":"Point"}
}