{
  "type": "Feature",
  "properties": {
    "addr:full":"4867 Baxter Rd Virginia Beach VA 23462",
    "addr:housenumber":"4867",
    "addr:postcode":"23462",
    "addr:street":"Baxter Rd",
    "iso:country":"US",
    "sg:address":"4867 Baxter Rd",
    "sg:city":"Virginia Beach",
    "sg:classifiers":[
        {
            "category":"Personal",
            "subcategory":"Beauty Salon",
            "type":"Services"
        },
        {
            "category":"Personal",
            "subcategory":"Barber",
            "type":"Services"
        }
    ],
    "sg:phone":"+1 757 497 4309",
    "sg:postcode":"23462",
    "sg:province":"VA",
    "sg:tags":[
        "shop"
    ],
    "wof:name":"Mane Attraction",
    "wof:placetype":"venue"
},
  "geometry": {"coordinates":[-76.149045,36.823674],"type":"Point"}
}