{
  "type": "Feature",
  "properties": {
    "addr:full":"14281 Washington Hwy Ashland VA 23005",
    "addr:housenumber":"14281",
    "addr:postcode":"23005",
    "addr:street":"Washington Hwy",
    "iso:country":"US",
    "sg:address":"14281 Washington Hwy",
    "sg:city":"Ashland",
    "sg:classifiers":[
        {
            "category":"Manufacturing",
            "subcategory":"Lumber",
            "type":"Manufacturing & Wholesale Goods"
        }
    ],
    "sg:phone":"+1 804 798 6121",
    "sg:postcode":"23005",
    "sg:province":"VA",
    "sg:tags":[
        "company",
        "logging"
    ],
    "wof:name":"Falling Creek Log Yard",
    "wof:placetype":"venue"
},
  "geometry": {"coordinates":[-77.47201800000001,37.796228],"type":"Point"}
}