{
  "type": "Feature",
  "properties": {
    "iso:country":"US",
    "sg:address":"6064 Franconia Rd",
    "sg:city":"Alexandria",
    "sg:classifiers":[
        {
            "category":"Shopping",
            "subcategory":"Computers & Home Electronics",
            "type":"Retail Goods"
        }
    ],
    "sg:phone":"+1 703 971 2058",
    "sg:postcode":"22310",
    "sg:province":"VA",
    "sg:tags":[
        "equipment",
        "dealer"
    ],
    "wof:name":"A B Computer Express",
    "wof:placetype":"venue"
},
  "geometry": {"coordinates":[-77.145644,38.782316],"type":"Point"}
}