{
  "type": "Feature",
  "properties": {
    "addr:full":"10109 Nedra Dr Great Falls VA 22066",
    "addr:housenumber":"10109",
    "addr:postcode":"22066",
    "addr:street":"Nedra Dr",
    "iso:country":"US",
    "sg:address":"10109 Nedra Dr",
    "sg:city":"Great Falls",
    "sg:classifiers":[
        {
            "category":"Freight",
            "type":"Transportation"
        }
    ],
    "sg:phone":"+1 703 757 0553",
    "sg:postcode":"22066",
    "sg:province":"VA",
    "sg:tags":[
        "delivery"
    ],
    "wof:name":"Special Delivery",
    "wof:placetype":"venue"
},
  "geometry": {"coordinates":[-77.29510999999999,38.997182],"type":"Point"}
}