{
  "type": "Feature",
  "properties": {
    "addr:full":"17385 Lankford Hwy Parksley VA 23421",
    "addr:housenumber":"17385",
    "addr:postcode":"23421",
    "addr:street":"Lankford Hwy",
    "iso:country":"US",
    "sg:address":"17385 Lankford Hwy",
    "sg:city":"Parksley",
    "sg:classifiers":[
        {
            "category":"Health Services",
            "subcategory":"Doctor",
            "type":"Services"
        }
    ],
    "sg:phone":"+1 757 665 5996",
    "sg:postcode":"23421",
    "sg:province":"VA",
    "sg:tags":[
        "physician",
        "surgeon"
    ],
    "wof:name":"Shore Medical Ctr",
    "wof:placetype":"venue"
},
  "geometry": {"coordinates":[-75.60212,37.793416],"type":"Point"}
}