{
  "type": "Feature",
  "properties": {
    "addr:full":"3707 14th St S Arlington VA 22204",
    "addr:housenumber":"3707",
    "addr:postcode":"22204",
    "addr:street":"14Th St S",
    "iso:country":"US",
    "sg:address":"3707 14th St S",
    "sg:city":"Arlington",
    "sg:classifiers":[
        {
            "category":"Building & Trades",
            "subcategory":"Construction",
            "type":"Services"
        }
    ],
    "sg:phone":"+1 703 920 6696",
    "sg:postcode":"22204",
    "sg:province":"VA",
    "sg:tags":[
        "industrial",
        "supply",
        "contractor",
        "equipment",
        "contractors-commercial",
        "drywall"
    ],
    "wof:name":"Allwine & Associates, Inc.",
    "wof:placetype":"venue"
},
  "geometry": {"coordinates":[-77.096019,38.856122],"type":"Point"}
}