{
  "type": "Feature",
  "properties": {
    "addr:full":"7000 Spring Garden Dr Springfield VA 22150",
    "addr:housenumber":"7000",
    "addr:postcode":"22150",
    "addr:street":"Spring Garden Dr",
    "iso:country":"US",
    "sg:address":"7000 Spring Garden Dr",
    "sg:city":"Springfield",
    "sg:classifiers":[
        {
            "category":"Home & Garden",
            "subcategory":"Household Appliances",
            "type":"Retail Goods"
        }
    ],
    "sg:phone":"+1 703 569 5014",
    "sg:postcode":"22150",
    "sg:province":"VA",
    "sg:tags":[
        "installs",
        "major"
    ],
    "wof:name":"Bettys Maytag Home Appl Ctr",
    "wof:placetype":"venue"
},
  "geometry": {"coordinates":[-77.186949,38.772588],"type":"Point"}
}