{
  "type": "Feature",
  "properties": {
    "addr:full":"3136 Colchester Brook Ln Fairfax VA 22031",
    "addr:housenumber":"3136",
    "addr:postcode":"22031",
    "addr:street":"Colchester Brook Ln",
    "iso:country":"US",
    "sg:address":"3136 Colchester Brook Ln",
    "sg:city":"Fairfax",
    "sg:classifiers":[
        {
            "category":"Education",
            "subcategory":"Special Training",
            "type":"Public Place"
        }
    ],
    "sg:phone":"+1 703 280 1362",
    "sg:postcode":"22031",
    "sg:province":"VA",
    "sg:tags":[
        "culture",
        "exchange"
    ],
    "wof:name":"T J Exchange Co LLC",
    "wof:placetype":"venue"
},
  "geometry": {"coordinates":[-77.26079900000001,38.864596],"type":"Point"}
}