{
  "type": "Feature",
  "properties": {
    "iso:country":"US",
    "sg:address":"3040 High St",
    "sg:city":"Portsmouth",
    "sg:classifiers":[
        {
            "category":"Retail",
            "subcategory":"Auto Repair",
            "type":"Services"
        }
    ],
    "sg:phone":"+1 757 399 8555",
    "sg:postcode":"23707",
    "sg:province":"VA",
    "sg:tags":[
        "automotive"
    ],
    "wof:name":"Als Brake Service",
    "wof:placetype":"venue"
},
  "geometry": {"coordinates":[-76.338374,36.834534],"type":"Point"}
}