{
  "type": "Feature",
  "properties": {
    "addr:full":"314 S Fairfax St Alexandria VA 22314",
    "addr:housenumber":"314",
    "addr:postcode":"22314",
    "addr:street":"S Fairfax St",
    "iso:country":"US",
    "sg:address":"314 S Fairfax St",
    "sg:city":"Alexandria",
    "sg:classifiers":[
        {
            "category":"Real Estate",
            "subcategory":"Real Estate Operator",
            "type":"Services"
        }
    ],
    "sg:phone":"+1 703 836 1843",
    "sg:postcode":"22314",
    "sg:province":"VA",
    "sg:tags":[
        "building",
        "nonresidential"
    ],
    "wof:name":"HPD Properties Inc",
    "wof:placetype":"venue"
},
  "geometry": {"coordinates":[-77.04319,38.801233],"type":"Point"}
}