{
  "type": "Feature",
  "properties": {
    "addr:full":"512 Cardinal Glen Cir Sterling VA 20164",
    "addr:housenumber":"512",
    "addr:postcode":"20164",
    "addr:street":"Cardinal Glen Cir",
    "iso:country":"US",
    "sg:address":"512 Cardinal Glen Cir",
    "sg:city":"Sterling",
    "sg:classifiers":[
        {
            "category":"Shopping",
            "subcategory":"Clothing, Apparel, & Fashions",
            "type":"Retail Goods"
        }
    ],
    "sg:phone":"+1 703 430 9400",
    "sg:postcode":"20164",
    "sg:province":"VA",
    "wof:name":"McKim Timothy",
    "wof:placetype":"venue"
},
  "geometry": {"coordinates":[-77.383656,39.022709],"type":"Point"}
}