{
  "type": "Feature",
  "properties": {
    "iso:country":"US",
    "sg:address":"10612 Winslow Dr",
    "sg:city":"Fairfax Station",
    "sg:classifiers":[
        {
            "category":"Shopping",
            "subcategory":"Computers & Home Electronics",
            "type":"Retail Goods"
        }
    ],
    "sg:phone":"+1 703 239 1053",
    "sg:postcode":"22039",
    "sg:province":"VA",
    "sg:tags":[
        "software"
    ],
    "wof:name":"3lc Software",
    "wof:placetype":"venue"
},
  "geometry": {"coordinates":[-77.31554800000001,38.781711],"type":"Point"}
}