{
  "type": "Feature",
  "properties": {
    "addr:full":"613 Broad St Altavista VA 24517",
    "addr:housenumber":"613",
    "addr:postcode":"24517",
    "addr:street":"Broad St",
    "iso:country":"US",
    "sg:address":"613 Broad St",
    "sg:city":"Altavista",
    "sg:classifiers":[
        {
            "category":"Personal",
            "subcategory":"Beauty Salon",
            "type":"Services"
        }
    ],
    "sg:phone":"+1 434 369 5750",
    "sg:postcode":"24517",
    "sg:province":"VA",
    "sg:tags":[
        "shop"
    ],
    "wof:name":"Styling Boutique Beauty Shop",
    "wof:placetype":"venue"
},
  "geometry": {"coordinates":[-79.290575,37.109355],"type":"Point"}
}