{
  "type": "Feature",
  "properties": {
    "addr:full":"1707 Osage St Ste 404 Alexandria VA 22302",
    "addr:housenumber":"1707",
    "addr:postcode":"22302",
    "addr:street":"Osage St Ste 404",
    "iso:country":"US",
    "sg:address":"1707 Osage St Ste 404",
    "sg:city":"Alexandria",
    "sg:classifiers":[
        {
            "category":"Health Services",
            "subcategory":"Doctor",
            "type":"Services"
        }
    ],
    "sg:phone":"+1 703 379 7215",
    "sg:postcode":"22302",
    "sg:province":"VA",
    "wof:name":"Morena Giovanna MD",
    "wof:placetype":"venue"
},
  "geometry": {"coordinates":[-77.08518100000001,38.828256],"type":"Point"}
}