{
  "type": "Feature",
  "properties": {
    "addr:full":"100 Shockoe Slip Richmond VA 23219",
    "addr:housenumber":"100",
    "addr:postcode":"23219",
    "iso:country":"US",
    "sg:address":"100 Shockoe Slip",
    "sg:city":"Richmond",
    "sg:classifiers":[
        {
            "category":"Real Estate",
            "subcategory":"Real Estate Agent",
            "type":"Services"
        },
        {
            "category":"Real Estate",
            "subcategory":"Real Estate Operator",
            "type":"Services"
        }
    ],
    "sg:phone":"+1 804 344 4445",
    "sg:postcode":"23219",
    "sg:province":"VA",
    "sg:tags":[
        "building",
        "nonresidential"
    ],
    "wof:name":"Medalist Properties",
    "wof:placetype":"venue"
},
  "geometry": {"coordinates":[-77.43395099999999,37.535002],"type":"Point"}
}