{
  "type": "Feature",
  "properties": {
    "iso:country":"US",
    "sg:address":"14390 Chantilly Crossing Ln ",
    "sg:city":"Chantilly",
    "sg:classifiers":[
        {
            "category":"Restaurant",
            "type":"Food & Drink"
        }
    ],
    "sg:menulink":"http://www.allmenus.com/va/sully/106988-soup-man/menu/",
    "sg:phone":"+1 703 885 5544",
    "sg:postcode":"20151",
    "sg:province":"VA",
    "sg:tags":[
        "soup",
        "american",
        "salad"
    ],
    "wof:name":"Soup Man",
    "wof:placetype":"venue"
},
  "geometry": {"coordinates":[-77.445455,38.900444],"type":"Point"}
}