{
  "type": "Feature",
  "properties": {
    "iso:country":"US",
    "sg:address":"99 Canal Center Plz",
    "sg:city":"Alexandria",
    "sg:classifiers":[
        {
            "category":"Organizations",
            "subcategory":"Non-profit Organization",
            "type":"Services"
        }
    ],
    "sg:phone":"+1 703 684 9444",
    "sg:postcode":"22314",
    "sg:province":"VA",
    "sg:website":"www.horatioalger.com",
    "wof:name":"Horatio Alger Assn-Distinguish",
    "wof:placetype":"venue"
},
  "geometry": {"coordinates":[-77.03928399999999,38.814582],"type":"Point"}
}