{
  "type": "Feature",
  "properties": {
    "iso:country":"US",
    "sg:address":"424 Market St",
    "sg:city":"Suffolk",
    "sg:classifiers":[
        {
            "category":"Professional",
            "subcategory":"Lawyer & Legal Services",
            "type":"Services"
        }
    ],
    "sg:phone":"+1 757 539 1322",
    "sg:postcode":"23434",
    "sg:province":"VA",
    "sg:tags":[
        "attorney"
    ],
    "wof:name":"John D Eure Jr",
    "wof:placetype":"venue"
},
  "geometry": {"coordinates":[-76.587225,36.731122],"type":"Point"}
}