{
  "type": "Feature",
  "properties": {
    "addr:full":"709 E Main St Luray VA 22835",
    "addr:housenumber":"709",
    "addr:postcode":"22835",
    "addr:street":"E Main St",
    "iso:country":"US",
    "sg:address":"709 E Main St",
    "sg:city":"Luray",
    "sg:classifiers":[
        {
            "category":"Restaurant",
            "type":"Food & Drink"
        }
    ],
    "sg:phone":"+1 540 743 3775",
    "sg:postcode":"22835",
    "sg:province":"VA",
    "sg:tags":[
        "mexican"
    ],
    "wof:name":"rancho viejo mexican grill & cantina",
    "wof:placetype":"venue"
},
  "geometry": {"coordinates":[-78.448334,38.665445],"type":"Point"}
}