{
  "type": "Feature",
  "properties": {
    "addr:full":"2370 Reed Creek Dr Draper VA 24324",
    "addr:housenumber":"2370",
    "addr:postcode":"24324",
    "addr:street":"Reed Creek Dr",
    "iso:country":"US",
    "sg:address":"2370 Reed Creek Dr",
    "sg:city":"Draper",
    "sg:phone":"+1 276 637 3469",
    "sg:postcode":"24324",
    "sg:province":"VA",
    "sg:tags":[
        "farm",
        "field",
        "crop"
    ],
    "wof:name":"S Lawrence",
    "wof:placetype":"venue"
},
  "geometry": {"coordinates":[-80.829688,36.926606],"type":"Point"}
}