{
  "type": "Feature",
  "properties": {
    "iso:country":"US",
    "sg:address":"631 Kings View Ct",
    "sg:city":"Hampton",
    "sg:classifiers":[
        {
            "category":"Professional",
            "subcategory":"Business Services",
            "type":"Services"
        }
    ],
    "sg:phone":"+1 757 851 3437",
    "sg:postcode":"23669",
    "sg:province":"VA",
    "wof:name":"Tenneco David Ellis",
    "wof:placetype":"venue"
},
  "geometry": {"coordinates":[-76.31120199999999,37.060411],"type":"Point"}
}