{
  "type": "Feature",
  "properties": {
    "addr:full":"7293 Shady Grove Rd Mechanicsville VA 23111",
    "addr:housenumber":"7293",
    "addr:postcode":"23111",
    "addr:street":"Shady Grove Rd",
    "iso:country":"US",
    "sg:address":"7293 Shady Grove Rd",
    "sg:city":"Mechanicsville",
    "sg:classifiers":[
        {
            "category":"Professional",
            "subcategory":"Accounting & Tax Preparation",
            "type":"Services"
        }
    ],
    "sg:phone":"+1 804 746 4950",
    "sg:postcode":"23111",
    "sg:province":"VA",
    "sg:tags":[
        "accountant"
    ],
    "wof:name":"Rosen & Underdown",
    "wof:placetype":"venue"
},
  "geometry": {"coordinates":[-77.371595,37.605329],"type":"Point"}
}