{
  "type": "Feature",
  "properties": {
    "addr:full":"5722 E Lee Hwy Max Meadows VA 24360",
    "addr:housenumber":"5722",
    "addr:postcode":"24360",
    "addr:street":"E Lee Hwy",
    "iso:country":"US",
    "sg:address":"5722 E Lee Hwy",
    "sg:city":"Max Meadows",
    "sg:classifiers":[
        {
            "category":"Autos & Motor Vehicles",
            "subcategory":"Fuel & Gas Station",
            "type":"Retail Goods"
        }
    ],
    "sg:phone":"+1 276 637 3118",
    "sg:postcode":"24360",
    "sg:province":"VA",
    "sg:tags":[
        "truck",
        "stop"
    ],
    "wof:name":"I-81 Auto & Truck Stop Inc",
    "wof:placetype":"venue"
},
  "geometry": {"coordinates":[-80.88118799999999,36.95333],"type":"Point"}
}