{
  "type": "Feature",
  "properties": {
    "addr:full":"10 Lee Ave Highland Springs VA 23075",
    "addr:housenumber":"10",
    "addr:postcode":"23075",
    "addr:street":"Lee Ave",
    "iso:country":"US",
    "sg:address":"10 Lee Ave",
    "sg:city":"Highland Springs",
    "sg:classifiers":[
        {
            "category":"Professional",
            "subcategory":"Business Services",
            "type":"Services"
        }
    ],
    "sg:phone":"+1 804 737 4909",
    "sg:postcode":"23075",
    "sg:province":"VA",
    "wof:name":"Masonry Specialist Inc",
    "wof:placetype":"venue"
},
  "geometry": {"coordinates":[-77.332032,37.552401],"type":"Point"}
}