{
  "type": "Feature",
  "properties": {
    "addr:full":"3185 N Valley Pike Harrisonburg VA 22802",
    "addr:housenumber":"3185",
    "addr:postcode":"22802",
    "addr:street":"N Valley Pike",
    "iso:country":"US",
    "sg:address":"3185 N Valley Pike",
    "sg:city":"Harrisonburg",
    "sg:classifiers":[
        {
            "category":"Autos & Motor Vehicles",
            "subcategory":"Automobile Sales",
            "type":"Retail Goods"
        }
    ],
    "sg:phone":"+1 540 434 6716",
    "sg:postcode":"22802",
    "sg:province":"VA",
    "sg:tags":[
        "truck"
    ],
    "sg:website":"www.highwaymotorsinc.com",
    "wof:name":"Highway Motors Inc",
    "wof:placetype":"venue"
},
  "geometry": {"coordinates":[-78.815713,38.483369],"type":"Point"}
}