{
  "type": "Feature",
  "properties": {
    "addr:full":"6207 Treywood Ln Manassas VA 20112",
    "addr:housenumber":"6207",
    "addr:postcode":"20112",
    "addr:street":"Treywood Ln",
    "iso:country":"US",
    "sg:address":"6207 Treywood Ln",
    "sg:city":"Manassas",
    "sg:classifiers":[
        {
            "category":"Professional",
            "subcategory":"Engineering",
            "type":"Services"
        },
        {
            "category":"Manufacturing",
            "subcategory":"Electronics",
            "type":"Manufacturing & Wholesale Goods"
        }
    ],
    "sg:phone":"+1 703 794 0172",
    "sg:postcode":"20112",
    "sg:province":"VA",
    "sg:tags":[
        "control",
        "system",
        "automation",
        "electronic",
        "controls-manufacturers",
        "engineer"
    ],
    "wof:name":"Electrical Control And Design, Inc.",
    "wof:placetype":"venue"
},
  "geometry": {"coordinates":[-77.39510900000001,38.687765],"type":"Point"}
}