{
  "type": "Feature",
  "properties": {
    "addr:full":"14519 Potomac Mills Rd Woodbridge VA 22192",
    "addr:housenumber":"14519",
    "addr:postcode":"22192",
    "addr:street":"Potomac Mills Rd",
    "iso:country":"US",
    "sg:address":"14519 Potomac Mills Rd",
    "sg:city":"Woodbridge",
    "sg:classifiers":[
        {
            "category":"Personal",
            "subcategory":"Nail Salon",
            "type":"Services"
        }
    ],
    "sg:phone":"+1 703 490 0737",
    "sg:postcode":"22192",
    "sg:province":"VA",
    "wof:name":"Famous Nails",
    "wof:placetype":"venue"
},
  "geometry": {"coordinates":[-77.29711,38.635787],"type":"Point"}
}