{
  "type": "Feature",
  "properties": {
    "addr:full":"4240 Dominion Blvd Glen Allen VA 23060",
    "addr:housenumber":"4240",
    "addr:postcode":"23060",
    "addr:street":"Dominion Blvd",
    "iso:country":"US",
    "sg:address":"4240 Dominion Blvd",
    "sg:city":"Glen Allen",
    "sg:classifiers":[
        {
            "category":"Travel",
            "subcategory":"Hotels & Motels",
            "type":"Entertainment"
        }
    ],
    "sg:phone":"+1 804 965 9500",
    "sg:postcode":"23060",
    "sg:province":"VA",
    "sg:website":"www.marriott.com",
    "wof:name":"Richmond Marriott West",
    "wof:placetype":"venue"
},
  "geometry": {"coordinates":[-77.585328,37.652206],"type":"Point"}
}