{
  "type": "Feature",
  "properties": {
    "addr:full":"300 Piney Forest Rd Danville VA 24540",
    "addr:housenumber":"300",
    "addr:postcode":"24540",
    "addr:street":"Piney Forest Rd",
    "iso:country":"US",
    "sg:address":"300 Piney Forest Rd",
    "sg:city":"Danville",
    "sg:classifiers":[
        {
            "category":"Health Services",
            "subcategory":"Doctor",
            "type":"Services"
        }
    ],
    "sg:phone":"+1 434 799 1100",
    "sg:postcode":"24540",
    "sg:province":"VA",
    "sg:tags":[
        "dentist"
    ],
    "wof:name":"Martha C Cutright DDS",
    "wof:placetype":"venue"
},
  "geometry": {"coordinates":[-79.41325500000001,36.601185],"type":"Point"}
}