{
  "type": "Feature",
  "properties": {
    "addr:full":"521 Madison Ave NW Roanoke VA 24016",
    "addr:housenumber":"521",
    "addr:postcode":"24016",
    "addr:street":"Madison Ave Nw",
    "iso:country":"US",
    "sg:address":"521 Madison Ave NW",
    "sg:city":"Roanoke",
    "sg:classifiers":[
        {
            "category":"Organizations",
            "subcategory":"Religious Organization",
            "type":"Services"
        }
    ],
    "sg:phone":"+1 540 345 3520",
    "sg:postcode":"24016",
    "sg:province":"VA",
    "wof:name":"Sweet Union Baptist Church",
    "wof:placetype":"venue"
},
  "geometry": {"coordinates":[-79.948594,37.280987],"type":"Point"}
}