{
  "type": "Feature",
  "properties": {
    "iso:country":"US",
    "sg:address":"11020 Bulloch Dr",
    "sg:city":"Manassas",
    "sg:classifiers":[
        {
            "category":"Home & Garden",
            "subcategory":"Furniture",
            "type":"Retail Goods"
        }
    ],
    "sg:phone":"+1 703 330 7998",
    "sg:postcode":"20109",
    "sg:province":"VA",
    "wof:name":"Room Store",
    "wof:placetype":"venue"
},
  "geometry": {"coordinates":[-77.522126,38.804945],"type":"Point"}
}