{
  "type": "Feature",
  "properties": {
    "addr:full":"13410 Richmond Rd Warsaw VA 22572",
    "addr:housenumber":"13410",
    "addr:postcode":"22572",
    "addr:street":"Richmond Rd",
    "iso:country":"US",
    "sg:address":"13410 Richmond Rd",
    "sg:city":"Warsaw",
    "sg:classifiers":[
        {
            "category":"Manufacturing",
            "subcategory":"Metals",
            "type":"Manufacturing & Wholesale Goods"
        },
        {
            "category":"Building & Trades",
            "subcategory":"Construction",
            "type":"Services"
        }
    ],
    "sg:phone":"+1 804 333 4483",
    "sg:postcode":"22572",
    "sg:province":"VA",
    "sg:tags":[
        "prefabricated",
        "mfg"
    ],
    "wof:name":"Jewell's Buildings",
    "wof:placetype":"venue"
},
  "geometry": {"coordinates":[-76.626943,37.949213],"type":"Point"}
}