{
  "type": "Feature",
  "properties": {
    "addr:full":"10671 Braddock Rd Fairfax VA 22032",
    "addr:housenumber":"10671",
    "addr:postcode":"22032",
    "addr:street":"Braddock Rd",
    "iso:country":"US",
    "sg:address":"10671 Braddock Rd",
    "sg:city":"Fairfax",
    "sg:classifiers":[
        {
            "category":"Personal",
            "subcategory":"Beauty Salon",
            "type":"Services"
        }
    ],
    "sg:phone":"+1 703 591 1131",
    "sg:postcode":"22032",
    "sg:province":"VA",
    "sg:tags":[
        "hair"
    ],
    "wof:name":"Hair Masters",
    "wof:placetype":"venue"
},
  "geometry": {"coordinates":[-77.313633,38.826144],"type":"Point"}
}