{
  "type": "Feature",
  "properties": {
    "addr:full":"4795 Bethlehem Rd Richmond VA 23230",
    "addr:housenumber":"4795",
    "addr:postcode":"23230",
    "addr:street":"Bethlehem Rd",
    "iso:country":"US",
    "sg:address":"4795 Bethlehem Rd",
    "sg:city":"Richmond",
    "sg:classifiers":[
        {
            "category":"Building & Trades",
            "subcategory":"Electrical",
            "type":"Services"
        }
    ],
    "sg:phone":"+1 804 254 9400",
    "sg:postcode":"23230",
    "sg:province":"VA",
    "sg:tags":[
        "electric",
        "specialty",
        "solution",
        "contractor",
        "lighting",
        "electrical"
    ],
    "sg:website":"www.elsrichmond.com",
    "wof:name":"Electrical & Light Solutions",
    "wof:placetype":"venue"
},
  "geometry": {"coordinates":[-77.486087,37.591554],"type":"Point"}
}