{
  "type": "Feature",
  "properties": {
    "iso:country":"US",
    "sg:address":"2820 Hollymead Dr",
    "sg:city":"Charlottesville",
    "sg:classifiers":[
        {
            "category":"Professional",
            "subcategory":"Employment Agencies",
            "type":"Services"
        }
    ],
    "sg:phone":"+1 434 974 7259",
    "sg:postcode":"22911",
    "sg:province":"VA",
    "sg:tags":[
        "consultant",
        "search",
        "executive"
    ],
    "wof:name":"Amercian Recruiters",
    "wof:placetype":"venue"
},
  "geometry": {"coordinates":[-78.439922,38.113826],"type":"Point"}
}