{
  "type": "Feature",
  "properties": {
    "addr:full":"1483 Brunswick Dr Alberta VA 23821",
    "addr:housenumber":"1483",
    "addr:postcode":"23821",
    "addr:street":"Brunswick Dr",
    "iso:country":"US",
    "sg:address":"1483 Brunswick Dr",
    "sg:city":"Alberta",
    "sg:classifiers":[
        {
            "category":"Organizations",
            "subcategory":"Religious Organization",
            "type":"Services"
        }
    ],
    "sg:phone":"+1 434 949 0531",
    "sg:postcode":"23821",
    "sg:province":"VA",
    "sg:tags":[
        "church"
    ],
    "wof:name":"St Paul AME Zion Church",
    "wof:placetype":"venue"
},
  "geometry": {"coordinates":[-77.95641500000001,36.82948],"type":"Point"}
}