{
  "type": "Feature",
  "properties": {
    "addr:full":"8300 Quarry Rd Manassas VA 20110",
    "addr:housenumber":"8300",
    "addr:postcode":"20110",
    "addr:street":"Quarry Rd",
    "iso:country":"US",
    "sg:address":"8300 Quarry Rd",
    "sg:city":"Manassas",
    "sg:classifiers":[
        {
            "category":"Retail",
            "subcategory":"Auto Rental",
            "type":"Services"
        }
    ],
    "sg:phone":"+1 703 257 0321",
    "sg:postcode":"20110",
    "sg:province":"VA",
    "sg:tags":[
        "renting",
        "automobile"
    ],
    "wof:name":"Hertz Rent A Car",
    "wof:placetype":"venue"
},
  "geometry": {"coordinates":[-77.450226,38.755616],"type":"Point"}
}