{
  "type": "Feature",
  "properties": {
    "iso:country":"US",
    "sg:address":"13025 Elm Tree Dr",
    "sg:city":"Herndon",
    "sg:classifiers":[
        {
            "category":"Real Estate",
            "subcategory":"Real Estate Operator",
            "type":"Services"
        }
    ],
    "sg:phone":"+1 703 435 1900",
    "sg:postcode":"20171",
    "sg:province":"VA",
    "sg:tags":[
        "apartment"
    ],
    "wof:name":"Woodland Park Apartments",
    "wof:placetype":"venue"
},
  "geometry": {"coordinates":[-77.39752300000001,38.948871],"type":"Point"}
}