{
  "type": "Feature",
  "properties": {
    "iso:country":"US",
    "sg:address":"1625 Prince St",
    "sg:city":"Alexandria",
    "sg:classifiers":[
        {
            "category":"Freight",
            "type":"Transportation"
        }
    ],
    "sg:phone":"+1 703 317 2140",
    "sg:postcode":"22314",
    "sg:province":"VA",
    "sg:tags":[
        "consultant"
    ],
    "sg:website":"www.tianet.org",
    "wof:name":"Transportation Intermediaries",
    "wof:placetype":"venue"
},
  "geometry": {"coordinates":[-77.05840600000001,38.805434],"type":"Point"}
}