{
  "type": "Feature",
  "properties": {
    "iso:country":"US",
    "sg:address":"1804 N George Mason Dr",
    "sg:city":"Arlington",
    "sg:classifiers":[
        {
            "category":"Professional",
            "subcategory":"Detective & Security Services",
            "type":"Services"
        }
    ],
    "sg:phone":"+1 703 241 2734",
    "sg:postcode":"22205",
    "sg:province":"VA",
    "sg:tags":[
        "hr",
        "federal",
        "provides",
        "related",
        "for"
    ],
    "wof:name":"Southwind Enterprises Inc",
    "wof:placetype":"venue"
},
  "geometry": {"coordinates":[-77.129738,38.891404],"type":"Point"}
}