{
  "type": "Feature",
  "properties": {
    "addr:full":"1207 E Lee Hwy Chilhowie VA 24319",
    "addr:housenumber":"1207",
    "addr:postcode":"24319",
    "addr:street":"E Lee Hwy",
    "iso:country":"US",
    "sg:address":"1207 E Lee Hwy",
    "sg:city":"Chilhowie",
    "sg:classifiers":[
        {
            "category":"Shopping",
            "subcategory":"Jewelry",
            "type":"Retail Goods"
        }
    ],
    "sg:phone":"+1 276 646 8651",
    "sg:postcode":"24319",
    "sg:province":"VA",
    "sg:tags":[
        "jeweler"
    ],
    "wof:name":"Goodman Jewelers",
    "wof:placetype":"venue"
},
  "geometry": {"coordinates":[-81.673288,36.806065],"type":"Point"}
}