{
  "type": "Feature",
  "properties": {
    "iso:country":"US",
    "sg:address":"11204 Lee Hwy",
    "sg:city":"Fairfax",
    "sg:classifiers":[
        {
            "category":"Manufacturing",
            "subcategory":"Tools & Machinery",
            "type":"Manufacturing & Wholesale Goods"
        }
    ],
    "sg:phone":"+1 703 591 7877",
    "sg:postcode":"22030",
    "sg:province":"VA",
    "sg:tags":[
        "equipment",
        "fiber",
        "system",
        "optics-components"
    ],
    "sg:website":"http://www.ltronfiber.com",
    "wof:name":"L-Tron",
    "wof:placetype":"venue"
},
  "geometry": {"coordinates":[-77.33148199999999,38.851891],"type":"Point"}
}