{
  "type": "Feature",
  "properties": {
    "iso:country":"US",
    "sg:address":"513 Declaration Rd",
    "sg:city":"Virginia Beach",
    "sg:classifiers":[
        {
            "category":"Professional",
            "subcategory":"Business Services",
            "type":"Services"
        }
    ],
    "sg:phone":"+1 757 473 3405",
    "sg:postcode":"23462",
    "sg:province":"VA",
    "wof:name":"Betis Enterprises LLC",
    "wof:placetype":"venue"
},
  "geometry": {"coordinates":[-76.139231,36.85243],"type":"Point"}
}