{
  "type": "Feature",
  "properties": {
    "addr:full":"1150 Rose Hill Dr Charlottesville VA 22903",
    "addr:housenumber":"1150",
    "addr:postcode":"22903",
    "addr:street":"Rose Hill Dr",
    "iso:country":"US",
    "sg:address":"1150 Rose Hill Dr",
    "sg:city":"Charlottesville",
    "sg:classifiers":[
        {
            "category":"Home & Garden",
            "subcategory":"Building Materials",
            "type":"Retail Goods"
        }
    ],
    "sg:phone":"+1 434 977 2990",
    "sg:postcode":"22903",
    "sg:province":"VA",
    "sg:tags":[
        "equipment",
        "fixture",
        "lighting"
    ],
    "sg:website":"www.ecksupply.com",
    "wof:name":"Eck Lighting Center",
    "wof:placetype":"venue"
},
  "geometry": {"coordinates":[-78.483902,38.0429],"type":"Point"}
}