{
  "type": "Feature",
  "properties": {
    "addr:full":"926 S Market St Salem VA 24153",
    "addr:housenumber":"926",
    "addr:postcode":"24153",
    "addr:street":"S Market St",
    "iso:country":"US",
    "sg:address":"926 S Market St",
    "sg:city":"Salem",
    "sg:classifiers":[
        {
            "category":"Retail",
            "subcategory":"Auto Repair",
            "type":"Services"
        }
    ],
    "sg:phone":"+1 540 387 9165",
    "sg:postcode":"24153",
    "sg:province":"VA",
    "sg:tags":[
        "repairing",
        "automobile",
        "automotive",
        "general"
    ],
    "wof:name":"Maiden & Sons Garage Inc",
    "wof:placetype":"venue"
},
  "geometry": {"coordinates":[-80.054079,37.282337],"type":"Point"}
}