{
  "type": "Feature",
  "properties": {
    "addr:full":"5796 Three Notched Rd Crozet VA 22932",
    "addr:housenumber":"5796",
    "addr:postcode":"22932",
    "addr:street":"Three Notched Rd",
    "iso:country":"US",
    "sg:address":"5796 Three Notched Rd",
    "sg:city":"Crozet",
    "sg:classifiers":[
        {
            "category":"Wholesale",
            "subcategory":"Construction Materials",
            "type":"Manufacturing & Wholesale Goods"
        }
    ],
    "sg:phone":"+1 434 823 2066",
    "sg:postcode":"22932",
    "sg:province":"VA",
    "sg:tags":[
        "marble"
    ],
    "wof:name":"Aquafit USA",
    "wof:placetype":"venue"
},
  "geometry": {"coordinates":[-78.69777999999999,38.069163],"type":"Point"}
}