{
  "type": "Feature",
  "properties": {
    "iso:country":"US",
    "sg:address":"21640 Frame Sq",
    "sg:city":"Ashburn",
    "sg:classifiers":[
        {
            "category":"Professional",
            "subcategory":"Computer Services",
            "type":"Services"
        }
    ],
    "sg:phone":"+1 703 858 5869",
    "sg:postcode":"20148",
    "sg:province":"VA",
    "sg:tags":[
        "consulting",
        "software"
    ],
    "wof:name":"Hyperdigm Research LLC",
    "wof:placetype":"venue"
},
  "geometry": {"coordinates":[-77.507144,39.018087],"type":"Point"}
}