{
  "type": "Feature",
  "properties": {
    "addr:full":"5190 W Military Hwy Chesapeake VA 23321",
    "addr:housenumber":"5190",
    "addr:postcode":"23321",
    "addr:street":"W Military Hwy",
    "iso:country":"US",
    "sg:address":"5190 W Military Hwy",
    "sg:city":"Chesapeake",
    "sg:classifiers":[
        {
            "category":"Social Services",
            "type":"Services"
        }
    ],
    "sg:phone":"+1 757 488 0800",
    "sg:postcode":"23321",
    "sg:province":"VA",
    "wof:name":"Ukraine Adoption Group",
    "wof:placetype":"venue"
},
  "geometry": {"coordinates":[-76.43938,36.778849],"type":"Point"}
}