{
  "type": "Feature",
  "properties": {
    "addr:full":"7061 Hayters Gap Rd Saltville VA 24370",
    "addr:housenumber":"7061",
    "addr:postcode":"24370",
    "addr:street":"Hayters Gap Rd",
    "iso:country":"US",
    "sg:address":"7061 Hayters Gap Rd",
    "sg:city":"Saltville",
    "sg:classifiers":[
        {
            "category":"Freight",
            "type":"Transportation"
        }
    ],
    "sg:phone":"+1 276 944 3867",
    "sg:postcode":"24370",
    "sg:province":"VA",
    "sg:tags":[
        "operator",
        "local",
        "trucking"
    ],
    "wof:name":"C L Trucking",
    "wof:placetype":"venue"
},
  "geometry": {"coordinates":[-81.920484,36.846348],"type":"Point"}
}