{
  "type": "Feature",
  "properties": {
    "addr:full":"1893 Billingsgate Cir Richmond VA 23238",
    "addr:housenumber":"1893",
    "addr:postcode":"23238",
    "addr:street":"Billingsgate Cir",
    "iso:country":"US",
    "sg:address":"1893 Billingsgate Cir",
    "sg:city":"Richmond",
    "sg:classifiers":[
        {
            "category":"Wholesale",
            "subcategory":"Construction Materials",
            "type":"Manufacturing & Wholesale Goods"
        }
    ],
    "sg:phone":"+1 804 754 7380",
    "sg:postcode":"23238",
    "sg:province":"VA",
    "sg:tags":[
        "lumber"
    ],
    "wof:name":"Hanover Forest Products Inc",
    "wof:placetype":"venue"
},
  "geometry": {"coordinates":[-77.596738,37.614001],"type":"Point"}
}