{
  "type": "Feature",
  "properties": {
    "addr:full":"1310 Round Oak Ct Mc Lean VA 22101",
    "addr:housenumber":"1310",
    "addr:postcode":"22101",
    "addr:street":"Round Oak Ct Mc Lean",
    "iso:country":"US",
    "sg:address":"1310 Round Oak Ct",
    "sg:city":"Mc Lean",
    "sg:classifiers":[
        {
            "category":"Professional",
            "subcategory":"Lawyer & Legal Services",
            "type":"Services"
        }
    ],
    "sg:phone":"+1 703 243 4686",
    "sg:postcode":"22101",
    "sg:province":"VA",
    "wof:name":"Tankel Jerome K Atty",
    "wof:placetype":"venue"
},
  "geometry": {"coordinates":[-77.131203,38.936401],"type":"Point"}
}