{
  "type": "Feature",
  "properties": {
    "addr:full":"10833 Hull Street Rd Midlothian VA 23112",
    "addr:housenumber":"10833",
    "addr:postcode":"23112",
    "addr:street":"Hull Street Rd",
    "iso:country":"US",
    "sg:address":"10833 Hull Street Rd",
    "sg:city":"Midlothian",
    "sg:classifiers":[
        {
            "category":"Personal",
            "subcategory":"Beauty Salon",
            "type":"Services"
        }
    ],
    "sg:phone":"+1 804 276 2460",
    "sg:postcode":"23112",
    "sg:province":"VA",
    "sg:tags":[
        "fabrics-wholesale",
        "manufacturer"
    ],
    "wof:name":"Georgeette's Braid And Weave",
    "wof:placetype":"venue"
},
  "geometry": {"coordinates":[-77.595732,37.438829],"type":"Point"}
}