{
  "type": "Feature",
  "properties": {
    "iso:country":"US",
    "sg:address":"1300 Kempsville Rd",
    "sg:city":"Chesapeake",
    "sg:classifiers":[
        {
            "category":"Health Services",
            "subcategory":"Doctor",
            "type":"Services"
        }
    ],
    "sg:phone":"+1 757 474 1117",
    "sg:postcode":"23320",
    "sg:province":"VA",
    "wof:name":"Carl P Roy DDS",
    "wof:placetype":"venue"
},
  "geometry": {"coordinates":[-76.20420799999999,36.761001],"type":"Point"}
}