{
  "type": "Feature",
  "properties": {
    "addr:full":"25173 New Market Rd Courtland VA 23837",
    "addr:housenumber":"25173",
    "addr:postcode":"23837",
    "addr:street":"New Market Rd",
    "iso:country":"US",
    "sg:address":"25173 New Market Rd",
    "sg:city":"Courtland",
    "sg:classifiers":[
        {
            "category":"Building & Trades",
            "subcategory":"Equipment Rental",
            "type":"Services"
        }
    ],
    "sg:phone":"+1 757 569 7970",
    "sg:postcode":"23837",
    "sg:province":"VA",
    "sg:tags":[
        "camping"
    ],
    "wof:name":"Southern Tent Corp",
    "wof:placetype":"venue"
},
  "geometry": {"coordinates":[-76.992447,36.676848],"type":"Point"}
}