{
  "type": "Feature",
  "properties": {
    "addr:full":"2403 William and Mary Dr Alexandria VA 22308",
    "addr:housenumber":"2403",
    "addr:postcode":"22308",
    "addr:street":"William And Mary Dr",
    "iso:country":"US",
    "sg:address":"2403 William and Mary Dr",
    "sg:city":"Alexandria",
    "sg:classifiers":[
        {
            "category":"Banks & Credit Unions",
            "subcategory":"Bank",
            "type":"Services"
        }
    ],
    "sg:phone":"+1 703 360 7638",
    "sg:postcode":"22308",
    "sg:province":"VA",
    "sg:tags":[
        "federal",
        "travel",
        "agency"
    ],
    "wof:name":"Japan Over Seas",
    "wof:placetype":"venue"
},
  "geometry": {"coordinates":[-77.069321,38.734823],"type":"Point"}
}