{
  "type": "Feature",
  "properties": {
    "addr:full":"6526 Osprey Point Ln Alexandria VA 22315",
    "addr:housenumber":"6526",
    "addr:postcode":"22315",
    "addr:street":"Osprey Point Ln",
    "iso:country":"US",
    "sg:address":"6526 Osprey Point Ln",
    "sg:city":"Alexandria",
    "sg:classifiers":[
        {
            "category":"Shopping",
            "type":"Retail Goods"
        }
    ],
    "sg:phone":"+1 703 541 0875",
    "sg:postcode":"22315",
    "sg:province":"VA",
    "sg:tags":[
        "craft",
        "gallery",
        "dealer"
    ],
    "wof:name":"Dbd Creations Inc",
    "wof:placetype":"venue"
},
  "geometry": {"coordinates":[-77.166875,38.752213],"type":"Point"}
}