{
  "type": "Feature",
  "properties": {
    "addr:full":"6401 Muster Ct Centreville VA 20121",
    "addr:housenumber":"6401",
    "addr:postcode":"20121",
    "addr:street":"Muster Ct",
    "iso:country":"US",
    "sg:address":"6401 Muster Ct",
    "sg:city":"Centreville",
    "sg:classifiers":[
        {
            "category":"Shopping",
            "subcategory":"Catalog Store",
            "type":"Retail Goods"
        }
    ],
    "sg:phone":"+1 703 449 8197",
    "sg:postcode":"20121",
    "sg:province":"VA",
    "sg:tags":[
        "mail",
        "house"
    ],
    "wof:name":"Paramount Gallery Inc",
    "wof:placetype":"venue"
},
  "geometry": {"coordinates":[-77.445601,38.823738],"type":"Point"}
}