{
  "type": "Feature",
  "properties": {
    "iso:country":"US",
    "sg:address":"1324 Richmond Rd",
    "sg:city":"Williamsburg",
    "sg:classifiers":[
        {
            "category":"Restaurant",
            "type":"Food & Drink"
        }
    ],
    "sg:phone":"+1 757 253 0722",
    "sg:postcode":"23185",
    "sg:province":"VA",
    "sg:tags":[
        "caterer"
    ],
    "wof:name":"Creative Cuisines",
    "wof:placetype":"venue"
},
  "geometry": {"coordinates":[-76.720494,37.285424],"type":"Point"}
}