{
  "type": "Feature",
  "properties": {
    "addr:full":"5127b Leesburg Pike Falls Church VA 22041",
    "addr:housenumber":"5127b",
    "addr:postcode":"22041",
    "addr:street":"Leesburg Pike",
    "iso:country":"US",
    "sg:address":"5127b Leesburg Pike",
    "sg:city":"Falls Church",
    "sg:classifiers":[
        {
            "category":"Restaurant",
            "type":"Food & Drink"
        }
    ],
    "sg:menulink":"http://www.allmenus.com/va/mason/188077-mcdonalds/menu/",
    "sg:postcode":"22041",
    "sg:province":"VA",
    "sg:tags":[
        "burger",
        "american"
    ],
    "wof:name":"McDonald's",
    "wof:placetype":"venue"
},
  "geometry": {"coordinates":[-77.11765699999999,38.845831],"type":"Point"}
}