{
  "type": "Feature",
  "properties": {
    "addr:full":"118 E Little Creek Rd Norfolk VA 23505",
    "addr:housenumber":"118",
    "addr:postcode":"23505",
    "addr:street":"E Little Creek Rd",
    "iso:country":"US",
    "sg:address":"118 E Little Creek Rd",
    "sg:city":"Norfolk",
    "sg:classifiers":[
        {
            "category":"Shopping",
            "type":"Retail Goods"
        }
    ],
    "sg:phone":"+1 757 583 6316",
    "sg:postcode":"23505",
    "sg:province":"VA",
    "sg:tags":[
        "wedding",
        "supply"
    ],
    "wof:name":"Bridal Shop",
    "wof:placetype":"venue"
},
  "geometry": {"coordinates":[-76.27105400000001,36.914905],"type":"Point"}
}