{
  "type": "Feature",
  "properties": {
    "addr:full":"105 Vicar Pl Danville VA 24540",
    "addr:housenumber":"105",
    "addr:postcode":"24540",
    "addr:street":"Vicar Pl",
    "iso:country":"US",
    "sg:address":"105 Vicar Pl",
    "sg:city":"Danville",
    "sg:classifiers":[
        {
            "category":"Banks & Credit Unions",
            "subcategory":"Bank",
            "type":"Services"
        }
    ],
    "sg:phone":"+1 434 836 3399",
    "sg:postcode":"24540",
    "sg:province":"VA",
    "sg:tags":[
        "loan",
        "real estate"
    ],
    "wof:name":"Countrywide Home Loans",
    "wof:placetype":"venue"
},
  "geometry": {"coordinates":[-79.399621,36.640317],"type":"Point"}
}