{
  "type": "Feature",
  "properties": {
    "addr:full":"312 Brown St Martinsville VA 24112",
    "addr:housenumber":"312",
    "addr:postcode":"24112",
    "addr:street":"Brown St",
    "iso:country":"US",
    "sg:address":"312 Brown St",
    "sg:city":"Martinsville",
    "sg:classifiers":[
        {
            "category":"Government",
            "subcategory":"Jail",
            "type":"Public Place"
        }
    ],
    "sg:phone":"+1 276 634 2910",
    "sg:postcode":"24112",
    "sg:province":"VA",
    "sg:tags":[
        "institute",
        "correctional"
    ],
    "wof:name":"Anchor Group Home",
    "wof:placetype":"venue"
},
  "geometry": {"coordinates":[-79.86568200000001,36.686557],"type":"Point"}
}