{
  "type": "Feature",
  "properties": {
    "iso:country":"US",
    "sg:address":"16 Marvin Dr",
    "sg:city":"Newport News",
    "sg:classifiers":[
        {
            "category":"Professional",
            "subcategory":"Management & Consulting",
            "type":"Services"
        }
    ],
    "sg:phone":"+1 757 877 0355",
    "sg:postcode":"23608",
    "sg:province":"VA",
    "sg:tags":[
        "promotion",
        "sales"
    ],
    "wof:name":"Onward Promos",
    "wof:placetype":"venue"
},
  "geometry": {"coordinates":[-76.55852400000001,37.151888],"type":"Point"}
}