{
  "type": "Feature",
  "properties": {
    "iso:country":"US",
    "sg:address":"1025 5th St SW",
    "sg:city":"Charlottesville",
    "sg:classifiers":[
        {
            "category":"Wholesale",
            "subcategory":"Auto Parts",
            "type":"Manufacturing & Wholesale Goods"
        }
    ],
    "sg:phone":"+1 434 979 0667",
    "sg:postcode":"22902",
    "sg:province":"VA",
    "sg:tags":[
        "automobile"
    ],
    "wof:name":"Powell's Mobile Repair Svc",
    "wof:placetype":"venue"
},
  "geometry": {"coordinates":[-78.495153,38.019973],"type":"Point"}
}