{
  "type": "Feature",
  "properties": {
    "iso:country":"US",
    "sg:address":"8710 Hampton Blvd",
    "sg:city":"Norfolk",
    "sg:classifiers":[
        {
            "category":"Freight",
            "type":"Transportation"
        }
    ],
    "sg:phone":"+1 757 423 4353",
    "sg:postcode":"23505",
    "sg:province":"VA",
    "sg:tags":[
        "commercial",
        "storage"
    ],
    "wof:name":"Jack Rabbit Self Storage",
    "wof:placetype":"venue"
},
  "geometry": {"coordinates":[-76.317791,36.931443],"type":"Point"}
}