{
  "type": "Feature",
  "properties": {
    "iso:country":"US",
    "sg:address":"4265 Americana Dr",
    "sg:city":"Annandale",
    "sg:classifiers":[
        {
            "category":"Professional",
            "type":"Services"
        }
    ],
    "sg:phone":"+1 703 914 1989",
    "sg:postcode":"22003",
    "sg:province":"VA",
    "wof:name":"Fu Loh Corp",
    "wof:placetype":"venue"
},
  "geometry": {"coordinates":[-77.21714900000001,38.832073],"type":"Point"}
}