{
  "type": "Feature",
  "properties": {
    "addr:full":"2938 Indian River Rd Virginia Beach VA 23456",
    "addr:housenumber":"2938",
    "addr:postcode":"23456",
    "addr:street":"Indian River Rd",
    "iso:country":"US",
    "sg:address":"2938 Indian River Rd",
    "sg:city":"Virginia Beach",
    "sg:classifiers":[
        {
            "category":"Professional",
            "subcategory":"Management & Consulting",
            "type":"Services"
        }
    ],
    "sg:phone":"+1 757 426 7727",
    "sg:postcode":"23456",
    "sg:province":"VA",
    "sg:tags":[
        "business"
    ],
    "wof:name":"Vbs Independent Consulting",
    "wof:placetype":"venue"
},
  "geometry": {"coordinates":[-76.076224,36.7265],"type":"Point"}
}