{
  "type": "Feature",
  "properties": {
    "iso:country":"US",
    "sg:address":"4701 Holly Ave",
    "sg:city":"Fairfax",
    "sg:classifiers":[
        {
            "category":"Restaurant",
            "type":"Food & Drink"
        }
    ],
    "sg:phone":"+1 703 802 6919",
    "sg:postcode":"22030",
    "sg:province":"VA",
    "sg:tags":[
        "eating"
    ],
    "wof:name":"Some Guys From Jersey LLC",
    "wof:placetype":"venue"
},
  "geometry": {"coordinates":[-77.35832499999999,38.846308],"type":"Point"}
}