{
  "type": "Feature",
  "properties": {
    "addr:full":"1856 Hanback Rd Gordonsville VA 22942",
    "addr:housenumber":"1856",
    "addr:postcode":"22942",
    "addr:street":"Hanback Rd",
    "iso:country":"US",
    "sg:address":"1856 Hanback Rd",
    "sg:city":"Gordonsville",
    "sg:classifiers":[
        {
            "category":"Manufacturing",
            "subcategory":"Lumber",
            "type":"Manufacturing & Wholesale Goods"
        }
    ],
    "sg:phone":"+1 540 832 3128",
    "sg:postcode":"22942",
    "sg:province":"VA",
    "sg:tags":[
        "logging"
    ],
    "wof:name":"Atkins Clearing & Trucking",
    "wof:placetype":"venue"
},
  "geometry": {"coordinates":[-78.15318600000001,38.132643],"type":"Point"}
}