{
  "type": "Feature",
  "properties": {
    "addr:full":"2805 Meadow Dr Chesapeake VA 23321",
    "addr:housenumber":"2805",
    "addr:postcode":"23321",
    "addr:street":"Meadow Dr",
    "iso:country":"US",
    "sg:address":"2805 Meadow Dr",
    "sg:city":"Chesapeake",
    "sg:classifiers":[
        {
            "category":"Professional",
            "type":"Services"
        }
    ],
    "sg:phone":"+1 757 484 6226",
    "sg:postcode":"23321",
    "sg:province":"VA",
    "wof:name":"Morris W Branch",
    "wof:placetype":"venue"
},
  "geometry": {"coordinates":[-76.40379,36.839881],"type":"Point"}
}