{
  "type": "Feature",
  "properties": {
    "iso:country":"US",
    "sg:address":"161 E Lee Hwy",
    "sg:city":"Warrenton",
    "sg:classifiers":[
        {
            "category":"Shopping",
            "type":"Retail Goods"
        }
    ],
    "sg:phone":"+1 540 341 0298",
    "sg:postcode":"20186",
    "sg:province":"VA",
    "sg:tags":[
        "merchandise"
    ],
    "wof:name":"Kids Haven Consignment",
    "wof:placetype":"venue"
},
  "geometry": {"coordinates":[-77.78652,38.727633],"type":"Point"}
}