{
  "type": "Feature",
  "properties": {
    "iso:country":"US",
    "sg:address":"310 E Brunswick St",
    "sg:city":"Sterling",
    "sg:classifiers":[
        {
            "category":"Professional",
            "subcategory":"Secretarial Services",
            "type":"Services"
        }
    ],
    "sg:phone":"+1 703 444 8636",
    "sg:postcode":"20164",
    "sg:province":"VA",
    "sg:tags":[
        "reporting"
    ],
    "wof:name":"Collins Associates",
    "wof:placetype":"venue"
},
  "geometry": {"coordinates":[-77.38405899999999,39.019005],"type":"Point"}
}