{
  "type": "Feature",
  "properties": {
    "addr:full":"209 Lily's Way Winchester VA 22602",
    "addr:housenumber":"209",
    "addr:postcode":"22602",
    "addr:street":"Lily'S Way",
    "iso:country":"US",
    "sg:address":"209 Lily's Way",
    "sg:city":"Winchester",
    "sg:classifiers":[
        {
            "category":"Freight",
            "type":"Transportation"
        }
    ],
    "sg:phone":"+1 540 665 9424",
    "sg:postcode":"22602",
    "sg:province":"VA",
    "sg:tags":[
        "operator",
        "local",
        "trucking"
    ],
    "wof:name":"John C Oconnell IV Trucking",
    "wof:placetype":"venue"
},
  "geometry": {"coordinates":[-78.118093,39.174656],"type":"Point"}
}