{
  "type": "Feature",
  "properties": {
    "iso:country":"US",
    "sg:address":"319 Maple Ave",
    "sg:city":"Richmond",
    "sg:classifiers":[
        {
            "category":"Organizations",
            "subcategory":"Community Association",
            "type":"Services"
        }
    ],
    "sg:phone":"+1 804 288 5166",
    "sg:postcode":"23226",
    "sg:province":"VA",
    "sg:tags":[
        "sorority",
        "fraternity"
    ],
    "wof:name":"Masonic Lodge 347",
    "wof:placetype":"venue"
},
  "geometry": {"coordinates":[-77.519819,37.572973],"type":"Point"}
}