{
  "type": "Feature",
  "properties": {
    "iso:country":"US",
    "sg:address":"3015 Peters Creek Rd NW",
    "sg:city":"Roanoke",
    "sg:classifiers":[
        {
            "category":"Health Services",
            "subcategory":"Clinic",
            "type":"Services"
        }
    ],
    "sg:phone":"+1 540 562 1900",
    "sg:postcode":"24019",
    "sg:province":"VA",
    "sg:tags":[
        "home",
        "care"
    ],
    "wof:name":"Home Instead Senior Care",
    "wof:placetype":"venue"
},
  "geometry": {"coordinates":[-80.001543,37.318699],"type":"Point"}
}