{
  "type": "Feature",
  "properties": {
    "addr:full":"6711 Peters Creek Rd NW Roanoke VA 24019",
    "addr:housenumber":"6711",
    "addr:postcode":"24019",
    "addr:street":"Peters Creek Rd Nw",
    "iso:country":"US",
    "sg:address":"6711 Peters Creek Rd NW",
    "sg:city":"Roanoke",
    "sg:classifiers":[
        {
            "category":"Professional",
            "subcategory":"Computer Services",
            "type":"Services"
        }
    ],
    "sg:phone":"+1 540 362 1907",
    "sg:postcode":"24019",
    "sg:province":"VA",
    "sg:tags":[
        "maintenance"
    ],
    "wof:name":"Decisionone",
    "wof:placetype":"venue"
},
  "geometry": {"coordinates":[-79.95854,37.345543],"type":"Point"}
}