{
  "type": "Feature",
  "properties": {
    "addr:full":"206 E Clay St Richmond VA 23219",
    "addr:housenumber":"206",
    "addr:postcode":"23219",
    "addr:street":"E Clay St",
    "iso:country":"US",
    "sg:address":"206 E Clay St",
    "sg:city":"Richmond",
    "sg:classifiers":[
        {
            "category":"Shopping",
            "subcategory":"Optical Goods",
            "type":"Retail Goods"
        }
    ],
    "sg:phone":"+1 804 920 1021",
    "sg:postcode":"23219",
    "sg:province":"VA",
    "sg:tags":[
        "optician"
    ],
    "wof:name":"Eye Wear Plus",
    "wof:placetype":"venue"
},
  "geometry": {"coordinates":[-77.437628,37.545832],"type":"Point"}
}