{
  "type": "Feature",
  "properties": {
    "iso:country":"US",
    "sg:address":"3424 Signal Hill Ave NW",
    "sg:city":"Roanoke",
    "sg:classifiers":[
        {
            "category":"Building & Trades",
            "subcategory":"Construction",
            "type":"Services"
        }
    ],
    "sg:phone":"+1 540 354 9061",
    "sg:postcode":"24017",
    "sg:province":"VA",
    "sg:tags":[
        "house"
    ],
    "wof:name":"D&D Home Improvement",
    "wof:placetype":"venue"
},
  "geometry": {"coordinates":[-79.99466,37.28045],"type":"Point"}
}