{
  "type": "Feature",
  "properties": {
    "addr:full":"13402 Countyline Church Rd Woodford VA 22580",
    "addr:housenumber":"13402",
    "addr:postcode":"22580",
    "addr:street":"Countyline Church Rd",
    "iso:country":"US",
    "sg:address":"13402 Countyline Church Rd",
    "sg:city":"Woodford",
    "sg:classifiers":[
        {
            "category":"Building & Trades",
            "subcategory":"Construction",
            "type":"Services"
        }
    ],
    "sg:phone":"+1 804 448 4090",
    "sg:postcode":"22580",
    "sg:province":"VA",
    "sg:tags":[
        "house",
        "c",
        "hanging",
        "painter",
        "contractor"
    ],
    "wof:name":"Advanced Painting",
    "wof:placetype":"venue"
},
  "geometry": {"coordinates":[-77.54316300000001,38.079267],"type":"Point"}
}