{
  "type": "Feature",
  "properties": {
    "iso:country":"US",
    "sg:address":"901 Prince Edward St",
    "sg:city":"Fredericksburg",
    "sg:classifiers":[
        {
            "category":"Local Transit",
            "type":"Transportation"
        }
    ],
    "sg:phone":"+1 540 891 8838",
    "sg:postcode":"22401",
    "sg:province":"VA",
    "sg:tags":[
        "passenger"
    ],
    "wof:name":"Elegant Affairs Limousine Serv",
    "wof:placetype":"venue"
},
  "geometry": {"coordinates":[-77.462716,38.302478],"type":"Point"}
}