{
  "type": "Feature",
  "properties": {
    "iso:country":"US",
    "sg:address":"2941 Walmsley Blvd",
    "sg:city":"Richmond",
    "sg:classifiers":[
        {
            "category":"Wholesale",
            "subcategory":"Electrical",
            "type":"Manufacturing & Wholesale Goods"
        }
    ],
    "sg:phone":"+1 804 743 1488",
    "sg:postcode":"23234",
    "sg:province":"VA",
    "sg:tags":[
        "supply",
        "sign"
    ],
    "wof:name":"CMO Supply Inc",
    "wof:placetype":"venue"
},
  "geometry": {"coordinates":[-77.450158,37.460577],"type":"Point"}
}