{
  "type": "Feature",
  "properties": {
    "iso:country":"US",
    "sg:address":"5573 Colt Ln",
    "sg:city":"Warrenton",
    "sg:classifiers":[
        {
            "category":"Professional",
            "subcategory":"Management & Consulting",
            "type":"Services"
        }
    ],
    "sg:phone":"+1 540 351 0695",
    "sg:postcode":"20187",
    "sg:province":"VA",
    "sg:tags":[
        "business"
    ],
    "wof:name":"Tsi Consulting Inc",
    "wof:placetype":"venue"
},
  "geometry": {"coordinates":[-77.750292,38.674555],"type":"Point"}
}