{
  "type": "Feature",
  "properties": {
    "iso:country":"US",
    "sg:address":"2231 Wheelwright Ct",
    "sg:city":"Reston",
    "sg:classifiers":[
        {
            "category":"Professional",
            "type":"Services"
        }
    ],
    "sg:phone":"+1 703 476 2148",
    "sg:postcode":"20191",
    "sg:province":"VA",
    "wof:name":"Quebecor World",
    "wof:placetype":"venue"
},
  "geometry": {"coordinates":[-77.35307400000001,38.935492],"type":"Point"}
}