{
  "type": "Feature",
  "properties": {
    "addr:full":"26 Maxwell Rd Richmond VA 23226",
    "addr:housenumber":"26",
    "addr:postcode":"23226",
    "addr:street":"Maxwell Rd",
    "iso:country":"US",
    "sg:address":"26 Maxwell Rd",
    "sg:city":"Richmond",
    "sg:classifiers":[
        {
            "category":"Real Estate",
            "subcategory":"Real Estate Operator",
            "type":"Services"
        }
    ],
    "sg:phone":"+1 804 562 7373",
    "sg:postcode":"23226",
    "sg:province":"VA",
    "sg:tags":[
        "building",
        "nonresidential"
    ],
    "wof:name":"Ottley Properties Inc",
    "wof:placetype":"venue"
},
  "geometry": {"coordinates":[-77.50404899999999,37.567169],"type":"Point"}
}