{
  "type": "Feature",
  "properties": {
    "iso:country":"US",
    "sg:address":"4121 Cox Rd",
    "sg:city":"Glen Allen",
    "sg:classifiers":[
        {
            "category":"Wholesale",
            "subcategory":"Stationery",
            "type":"Manufacturing & Wholesale Goods"
        }
    ],
    "sg:phone":"+1 804 270 6307",
    "sg:postcode":"23060",
    "sg:province":"VA",
    "sg:tags":[
        "business",
        "form",
        "system"
    ],
    "wof:name":"Moore Business Forms & Systems",
    "wof:placetype":"venue"
},
  "geometry": {"coordinates":[-77.58145,37.650652],"type":"Point"}
}