{
  "type": "Feature",
  "properties": {
    "iso:country":"US",
    "sg:address":"1307 12th St",
    "sg:city":"Lynchburg",
    "sg:classifiers":[
        {
            "category":"Retail",
            "subcategory":"Auto Repair",
            "type":"Services"
        }
    ],
    "sg:phone":"+1 434 528 5333",
    "sg:postcode":"24504",
    "sg:province":"VA",
    "sg:tags":[
        "repairing",
        "automobile"
    ],
    "wof:name":"T D's Auto Repair",
    "wof:placetype":"venue"
},
  "geometry": {"coordinates":[-79.15106,37.406344],"type":"Point"}
}