{
  "type": "Feature",
  "properties": {
    "iso:country":"US",
    "sg:address":"120 Gordon Rd",
    "sg:city":"Falls Church",
    "sg:classifiers":[
        {
            "category":"Retail",
            "subcategory":"Auto Repair",
            "type":"Services"
        }
    ],
    "sg:phone":"+1 703 533 1737",
    "sg:postcode":"22046",
    "sg:province":"VA",
    "sg:tags":[
        "body",
        "automobile",
        "painting"
    ],
    "wof:name":"Early's Auto Body Inc",
    "wof:placetype":"venue"
},
  "geometry": {"coordinates":[-77.189717,38.893575],"type":"Point"}
}