{
  "type": "Feature",
  "properties": {
    "iso:country":"US",
    "sg:address":"6706 Montour Dr",
    "sg:city":"Falls Church",
    "sg:classifiers":[
        {
            "category":"Wholesale",
            "subcategory":"Machinery & Supplies",
            "type":"Manufacturing & Wholesale Goods"
        }
    ],
    "sg:phone":"+1 703 536 3556",
    "sg:postcode":"22043",
    "sg:province":"VA",
    "sg:tags":[
        "equipment",
        "establishment"
    ],
    "wof:name":"J & R Unlimited",
    "wof:placetype":"venue"
},
  "geometry": {"coordinates":[-77.17824899999999,38.903332],"type":"Point"}
}