{
  "type": "Feature",
  "properties": {
    "addr:full":"5 Rosecroft Dr Fredericksburg VA 22407",
    "addr:housenumber":"5",
    "addr:postcode":"22407",
    "addr:street":"Rosecroft Dr",
    "iso:country":"US",
    "sg:address":"5 Rosecroft Dr",
    "sg:city":"Fredericksburg",
    "sg:classifiers":[
        {
            "category":"Retail",
            "subcategory":"Photofinishing",
            "type":"Services"
        }
    ],
    "sg:phone":"+1 540 548 2988",
    "sg:postcode":"22407",
    "sg:province":"VA",
    "sg:tags":[
        "laboratory"
    ],
    "wof:name":"Record Photo & Pub Affrs",
    "wof:placetype":"venue"
},
  "geometry": {"coordinates":[-77.54892100000001,38.321852],"type":"Point"}
}