{
  "type": "Feature",
  "properties": {
    "addr:full":"11724 Lotus Ln Lovettsville VA 20180",
    "addr:housenumber":"11724",
    "addr:postcode":"20180",
    "addr:street":"Lotus Ln",
    "iso:country":"US",
    "sg:address":"11724 Lotus Ln",
    "sg:city":"Lovettsville",
    "sg:classifiers":[
        {
            "category":"Building & Trades",
            "subcategory":"Landscaping Services",
            "type":"Services"
        }
    ],
    "sg:phone":"+1 540 822 3043",
    "sg:postcode":"20180",
    "sg:province":"VA",
    "sg:tags":[
        "landscape"
    ],
    "wof:name":"Virginia Landscapes Inc",
    "wof:placetype":"venue"
},
  "geometry": {"coordinates":[-77.642095,39.290173],"type":"Point"}
}