{
  "type": "Feature",
  "properties": {
    "addr:full":"109 Autumn Ln Troutville VA 24175",
    "addr:housenumber":"109",
    "addr:postcode":"24175",
    "addr:street":"Autumn Ln",
    "iso:country":"US",
    "sg:address":"109 Autumn Ln",
    "sg:city":"Troutville",
    "sg:classifiers":[
        {
            "category":"Building & Trades",
            "subcategory":"Cleaning & Sanitation",
            "type":"Services"
        }
    ],
    "sg:phone":"+1 540 977 4944",
    "sg:postcode":"24175",
    "sg:province":"VA",
    "sg:tags":[
        "maintenance"
    ],
    "wof:name":"Rocks Building Services Inc",
    "wof:placetype":"venue"
},
  "geometry": {"coordinates":[-79.843788,37.361925],"type":"Point"}
}