{
  "type": "Feature",
  "properties": {
    "iso:country":"US",
    "sg:address":"1143 Lake Monticello Rd",
    "sg:city":"Palmyra",
    "sg:classifiers":[
        {
            "category":"Retail",
            "subcategory":"Laundry & Dry Cleaning",
            "type":"Services"
        }
    ],
    "sg:phone":"+1 434 591 0867",
    "sg:postcode":"22963",
    "sg:province":"VA",
    "wof:name":"Central Vrginia Crpt Clg L L C",
    "wof:placetype":"venue"
},
  "geometry": {"coordinates":[-78.34093900000001,37.932244],"type":"Point"}
}