{
  "type": "Feature",
  "properties": {
    "iso:country":"US",
    "sg:address":"99 Campbell Hwy",
    "sg:city":"Rustburg",
    "sg:classifiers":[
        {
            "category":"Retail",
            "subcategory":"Auto Repair",
            "type":"Services"
        }
    ],
    "sg:phone":"+1 434 332 5269",
    "sg:postcode":"24588",
    "sg:province":"VA",
    "sg:tags":[
        "repairing",
        "automobile"
    ],
    "wof:name":"Rustburg Auto Svc",
    "wof:placetype":"venue"
},
  "geometry": {"coordinates":[-79.10064800000001,37.27941],"type":"Point"}
}