{
  "type": "Feature",
  "properties": {
    "addr:full":"3827 Gaskins Rd Richmond VA 23233",
    "addr:housenumber":"3827",
    "addr:postcode":"23233",
    "addr:street":"Gaskins Rd",
    "iso:country":"US",
    "sg:address":"3827 Gaskins Rd",
    "sg:city":"Richmond",
    "sg:classifiers":[
        {
            "category":"Shopping",
            "subcategory":"Computers & Home Electronics",
            "type":"Retail Goods"
        }
    ],
    "sg:phone":"+1 804 270 4900",
    "sg:postcode":"23233",
    "sg:province":"VA",
    "wof:name":"Dataline Inc",
    "wof:placetype":"venue"
},
  "geometry": {"coordinates":[-77.568676,37.643916],"type":"Point"}
}