{
  "type": "Feature",
  "properties": {
    "iso:country":"US",
    "sg:address":"24 Wolfe St",
    "sg:city":"Winchester",
    "sg:classifiers":[
        {
            "category":"Professional",
            "type":"Services"
        }
    ],
    "sg:phone":"+1 540 545 4005",
    "sg:postcode":"22601",
    "sg:province":"VA",
    "wof:name":"Last Chance",
    "wof:placetype":"venue"
},
  "geometry": {"coordinates":[-78.167379,39.183444],"type":"Point"}
}