{
  "type": "Feature",
  "properties": {
    "iso:country":"US",
    "sg:address":"6610 Heidi Ct",
    "sg:city":"Mc Lean",
    "sg:classifiers":[
        {
            "category":"Personal",
            "type":"Services"
        }
    ],
    "sg:phone":"+1 703 883 8922",
    "sg:postcode":"22101",
    "sg:province":"VA",
    "sg:tags":[
        "legal"
    ],
    "wof:name":"Elder Help Inc",
    "wof:placetype":"venue"
},
  "geometry": {"coordinates":[-77.169726,38.95852],"type":"Point"}
}