{
  "type": "Feature",
  "properties": {
    "iso:country":"US",
    "sg:address":"1415 S Main St",
    "sg:city":"Farmville",
    "sg:classifiers":[
        {
            "category":"Health Services",
            "subcategory":"Health Practitioner",
            "type":"Services"
        }
    ],
    "sg:phone":"+1 434 392 7421",
    "sg:postcode":"23901",
    "sg:province":"VA",
    "sg:tags":[
        "therapist",
        "physical"
    ],
    "wof:name":"Center For Rehab & Sports Mdcn",
    "wof:placetype":"venue"
},
  "geometry": {"coordinates":[-78.395607,37.283037],"type":"Point"}
}