{
  "type": "Feature",
  "properties": {
    "addr:full":"3139 Golansky Blvd Woodbridge VA 22192",
    "addr:housenumber":"3139",
    "addr:postcode":"22192",
    "addr:street":"Golansky Blvd",
    "iso:country":"US",
    "sg:address":"3139 Golansky Blvd",
    "sg:city":"Woodbridge",
    "sg:phone":"+1 703 580 8300",
    "sg:postcode":"22192",
    "sg:province":"VA",
    "sg:website":"http://www.vocellipizza.com",
    "wof:name":"Vocelli Pizza",
    "wof:placetype":"venue"
},
  "geometry": {"coordinates":[-77.306427,38.651459],"type":"Point"}
}