{
  "type": "Feature",
  "properties": {
    "addr:full":"500 John Marshall Dr NE Vienna VA 22180",
    "addr:housenumber":"500",
    "addr:postcode":"22180",
    "addr:street":"John Marshall Dr Ne",
    "iso:country":"US",
    "sg:address":"500 John Marshall Dr NE",
    "sg:city":"Vienna",
    "sg:classifiers":[
        {
            "category":"Education",
            "subcategory":"Special Training",
            "type":"Public Place"
        }
    ],
    "sg:phone":"+1 703 359 0090",
    "sg:postcode":"22180",
    "sg:province":"VA",
    "sg:tags":[
        "instruction",
        "driving"
    ],
    "wof:name":"Advantage Driving School",
    "wof:placetype":"venue"
},
  "geometry": {"coordinates":[-77.26764799999999,38.914257],"type":"Point"}
}