{
  "type": "Feature",
  "properties": {
    "addr:full":"129 Maple Ave W Vienna VA 22180",
    "addr:housenumber":"129",
    "addr:postcode":"22180",
    "addr:street":"Maple Ave W",
    "iso:country":"US",
    "sg:address":"129 Maple Ave W",
    "sg:city":"Vienna",
    "sg:classifiers":[
        {
            "category":"Home & Garden",
            "subcategory":"Furniture",
            "type":"Retail Goods"
        }
    ],
    "sg:phone":"+1 703 255 0312",
    "sg:postcode":"22180",
    "sg:province":"VA",
    "sg:tags":[
        "mattress"
    ],
    "wof:name":"Mattress Discounters 1147",
    "wof:placetype":"venue"
},
  "geometry": {"coordinates":[-77.267009,38.900343],"type":"Point"}
}