{
  "type": "Feature",
  "properties": {
    "iso:country":"US",
    "sg:address":"924 W Broad St",
    "sg:city":"Falls Church",
    "sg:classifiers":[
        {
            "category":"Restaurant",
            "type":"Food & Drink"
        }
    ],
    "sg:phone":"+1 703 536 4566",
    "sg:postcode":"22046",
    "sg:province":"VA",
    "sg:tags":[
        "serving",
        "alcoholic",
        "afghan",
        "beverage"
    ],
    "wof:name":"Panjshir Restaurant",
    "wof:placetype":"venue"
},
  "geometry": {"coordinates":[-77.18434600000001,38.890851],"type":"Point"}
}