{
  "type": "Feature",
  "properties": {
    "addr:full":"1068 Coltons Mill Rd Bedford VA 24523",
    "addr:housenumber":"1068",
    "addr:postcode":"24523",
    "addr:street":"Coltons Mill Rd",
    "iso:country":"US",
    "sg:address":"1068 Coltons Mill Rd",
    "sg:city":"Bedford",
    "sg:classifiers":[
        {
            "category":"Wholesale",
            "subcategory":"Farm Supplies",
            "type":"Manufacturing & Wholesale Goods"
        }
    ],
    "sg:phone":"+1 540 586 9577",
    "sg:postcode":"24523",
    "sg:province":"VA",
    "sg:tags":[
        "feed"
    ],
    "wof:name":"Rock Haven Mills",
    "wof:placetype":"venue"
},
  "geometry": {"coordinates":[-79.466381,37.463709],"type":"Point"}
}