{
  "type": "Feature",
  "properties": {
    "addr:full":"12914 Jefferson Ave Newport News VA 23608",
    "addr:housenumber":"12914",
    "addr:postcode":"23608",
    "addr:street":"Jefferson Ave",
    "iso:country":"US",
    "sg:address":"12914 Jefferson Ave",
    "sg:city":"Newport News",
    "sg:classifiers":[
        {
            "category":"Wholesale",
            "subcategory":"Auto Parts",
            "type":"Manufacturing & Wholesale Goods"
        }
    ],
    "sg:phone":"+1 757 874 2822",
    "sg:postcode":"23608",
    "sg:province":"VA",
    "sg:tags":[
        "supply"
    ],
    "wof:name":"NAPA Auto Parts",
    "wof:placetype":"venue"
},
  "geometry": {"coordinates":[-76.529582,37.150666],"type":"Point"}
}