{
  "type": "Feature",
  "properties": {
    "addr:full":"20119 Ivan Rd Petersburg VA 23803",
    "addr:housenumber":"20119",
    "addr:postcode":"23803",
    "addr:street":"Ivan Rd",
    "iso:country":"US",
    "sg:address":"20119 Ivan Rd",
    "sg:city":"Petersburg",
    "sg:classifiers":[
        {
            "category":"Professional",
            "type":"Services"
        }
    ],
    "sg:phone":"+1 804 590 0155",
    "sg:postcode":"23803",
    "sg:province":"VA",
    "wof:name":"Razz Bearys",
    "wof:placetype":"venue"
},
  "geometry": {"coordinates":[-77.545714,37.232696],"type":"Point"}
}