{
  "type": "Feature",
  "properties": {
    "iso:country":"US",
    "sg:address":"7112 Hesperides Dr",
    "sg:city":"Warrenton",
    "sg:classifiers":[
        {
            "category":"Professional",
            "subcategory":"Management & Consulting",
            "type":"Services"
        }
    ],
    "sg:phone":"+1 540 349 8288",
    "sg:postcode":"20186",
    "sg:province":"VA",
    "sg:tags":[
        "marketing",
        "program"
    ],
    "wof:name":"Century Marketing & Comm Inc",
    "wof:placetype":"venue"
},
  "geometry": {"coordinates":[-77.831018,38.745369],"type":"Point"}
}