{
  "type": "Feature",
  "properties": {
    "iso:country":"US",
    "sg:address":"3905 Railroad Ave",
    "sg:city":"Fairfax",
    "sg:classifiers":[
        {
            "category":"Building & Trades",
            "subcategory":"Plumbing",
            "type":"Services"
        }
    ],
    "sg:phone":"+1 703 359 8957",
    "sg:postcode":"22030",
    "sg:province":"VA",
    "sg:tags":[
        "conditioning",
        "air",
        "system",
        "contractor"
    ],
    "wof:name":"Garneski's Air Conditioning",
    "wof:placetype":"venue"
},
  "geometry": {"coordinates":[-77.311666,38.849145],"type":"Point"}
}