{
  "type": "Feature",
  "properties": {
    "addr:full":"6035 N Wilson Blvd Arlington VA 22205",
    "addr:housenumber":"6035",
    "addr:postcode":"22205",
    "addr:street":"N Wilson Blvd",
    "iso:country":"US",
    "sg:address":"6035 N Wilson Blvd",
    "sg:city":"Arlington",
    "sg:classifiers":[
        {
            "category":"Food & Beverages",
            "subcategory":"Groceries & Convenience Stores",
            "type":"Retail Goods"
        }
    ],
    "sg:phone":"+1 703 533 3354",
    "sg:postcode":"22205",
    "sg:province":"VA",
    "sg:tags":[
        "delicatessen"
    ],
    "wof:name":"ISS",
    "wof:placetype":"venue"
},
  "geometry": {"coordinates":[-77.139218,38.873929],"type":"Point"}
}