{
  "type": "Feature",
  "properties": {
    "addr:full":"23379 Commerce Dr Accomac VA 23301",
    "addr:housenumber":"23379",
    "addr:postcode":"23301",
    "addr:street":"Commerce Dr",
    "iso:country":"US",
    "sg:address":"23379 Commerce Dr",
    "sg:city":"Accomac",
    "sg:classifiers":[
        {
            "category":"Health Services",
            "subcategory":"Health Practitioner",
            "type":"Services"
        }
    ],
    "sg:phone":"+1 757 787 8284",
    "sg:postcode":"23301",
    "sg:province":"VA",
    "sg:tags":[
        "therapist",
        "speech"
    ],
    "wof:name":"Shore Rehab",
    "wof:placetype":"venue"
},
  "geometry": {"coordinates":[-75.668464,37.728849],"type":"Point"}
}