{
  "type": "Feature",
  "properties": {
    "addr:full":"4584 Virginia Beach Blvd Virginia Beach VA 23462",
    "addr:housenumber":"4584",
    "addr:postcode":"23462",
    "addr:street":"Virginia Beach Blvd",
    "iso:country":"US",
    "sg:address":"4584 Virginia Beach Blvd",
    "sg:city":"Virginia Beach",
    "sg:classifiers":[
        {
            "category":"Shopping",
            "subcategory":"Jewelry",
            "type":"Retail Goods"
        }
    ],
    "sg:phone":"+1 757 497 3559",
    "sg:postcode":"23462",
    "sg:province":"VA",
    "sg:tags":[
        "jeweler"
    ],
    "wof:name":"Zales Jewelers 226",
    "wof:placetype":"venue"
},
  "geometry": {"coordinates":[-76.136278,36.843741],"type":"Point"}
}