{
  "type": "Feature",
  "properties": {
    "iso:country":"US",
    "sg:address":"590 Grove St",
    "sg:city":"Herndon",
    "sg:classifiers":[
        {
            "category":"Professional",
            "type":"Services"
        }
    ],
    "sg:phone":"+1 703 927 1091",
    "sg:postcode":"20170",
    "sg:province":"VA",
    "sg:tags":[
        "establishment"
    ],
    "wof:name":"Platinum Seal Enterprises",
    "wof:placetype":"venue"
},
  "geometry": {"coordinates":[-77.37982,38.967285],"type":"Point"}
}