{
  "type": "Feature",
  "properties": {
    "addr:full":"1301 N King St Hampton VA 23669",
    "addr:housenumber":"1301",
    "addr:postcode":"23669",
    "addr:street":"N King St",
    "iso:country":"US",
    "sg:address":"1301 N King St",
    "sg:city":"Hampton",
    "sg:classifiers":[
        {
            "category":"Professional",
            "subcategory":"Accounting & Tax Preparation",
            "type":"Services"
        }
    ],
    "sg:phone":"+1 757 722 1040",
    "sg:postcode":"23669",
    "sg:province":"VA",
    "sg:tags":[
        "return",
        "filing"
    ],
    "wof:name":"Liberty Tax Svc",
    "wof:placetype":"venue"
},
  "geometry": {"coordinates":[-76.34720900000001,37.054731],"type":"Point"}
}