{
  "type": "Feature",
  "properties": {
    "addr:full":"3201 Greenland Ave NW Roanoke VA 24012",
    "addr:housenumber":"3201",
    "addr:postcode":"24012",
    "addr:street":"Greenland Ave Nw",
    "iso:country":"US",
    "sg:address":"3201 Greenland Ave NW",
    "sg:city":"Roanoke",
    "sg:classifiers":[
        {
            "category":"Professional",
            "type":"Services"
        }
    ],
    "sg:phone":"+1 540 563 2904",
    "sg:postcode":"24012",
    "sg:province":"VA",
    "wof:name":"Nailfoot",
    "wof:placetype":"venue"
},
  "geometry": {"coordinates":[-79.94686900000001,37.296574],"type":"Point"}
}