{
  "type": "Feature",
  "properties": {
    "iso:country":"US",
    "sg:address":"7906 Ashland Ave",
    "sg:city":"Manassas",
    "sg:classifiers":[
        {
            "category":"Shopping",
            "type":"Retail Goods"
        }
    ],
    "sg:phone":"+1 703 335 9088",
    "sg:postcode":"20109",
    "sg:province":"VA",
    "sg:tags":[
        "merchandise"
    ],
    "wof:name":"Picture Perfect",
    "wof:placetype":"venue"
},
  "geometry": {"coordinates":[-77.504064,38.783778],"type":"Point"}
}