{
  "type": "Feature",
  "properties": {
    "addr:full":"11510 Franklin St Ferrum VA 24088",
    "addr:housenumber":"11510",
    "addr:postcode":"24088",
    "addr:street":"Franklin St",
    "iso:country":"US",
    "sg:address":"11510 Franklin St",
    "sg:city":"Ferrum",
    "sg:classifiers":[
        {
            "category":"Wholesale",
            "subcategory":"Scrap",
            "type":"Manufacturing & Wholesale Goods"
        }
    ],
    "sg:phone":"+1 540 365 6200",
    "sg:postcode":"24088",
    "sg:province":"VA",
    "sg:tags":[
        "recycling",
        "center"
    ],
    "wof:name":"Timberland Mulch & Tree Farm",
    "wof:placetype":"venue"
},
  "geometry": {"coordinates":[-80.05340700000001,36.92298],"type":"Point"}
}