{
  "type": "Feature",
  "properties": {
    "iso:country":"US",
    "sg:address":"3312 S 28th St Apt 102",
    "sg:city":"Alexandria",
    "sg:classifiers":[
        {
            "category":"Real Estate",
            "subcategory":"Architect",
            "type":"Services"
        }
    ],
    "sg:phone":"+1 703 845 0031",
    "sg:postcode":"22302",
    "sg:province":"VA",
    "wof:name":"Int'l Architects & Partners Ltd",
    "wof:placetype":"venue"
},
  "geometry": {"coordinates":[-77.10639999999999,38.839298],"type":"Point"}
}