{
  "type": "Feature",
  "properties": {
    "addr:full":"3959 Pender Dr Fairfax VA 22030",
    "addr:housenumber":"3959",
    "addr:postcode":"22030",
    "addr:street":"Pender Dr",
    "iso:country":"US",
    "sg:address":"3959 Pender Dr",
    "sg:city":"Fairfax",
    "sg:classifiers":[
        {
            "category":"Professional",
            "subcategory":"Management & Consulting",
            "type":"Services"
        }
    ],
    "sg:phone":"+1 703 359 2660",
    "sg:postcode":"22030",
    "sg:province":"VA",
    "wof:name":"Emond Berger LLC",
    "wof:placetype":"venue"
},
  "geometry": {"coordinates":[-77.33271499999999,38.861093],"type":"Point"}
}