{
  "type": "Feature",
  "properties": {
    "iso:country":"US",
    "sg:address":"3417 Deerlope Trl",
    "sg:city":"Williamsburg",
    "sg:classifiers":[
        {
            "category":"Shopping",
            "subcategory":"Bicycles & Sporting Goods",
            "type":"Retail Goods"
        }
    ],
    "sg:phone":"+1 757 221 7015",
    "sg:postcode":"23188",
    "sg:province":"VA",
    "wof:name":"Sports Anvil Inc",
    "wof:placetype":"venue"
},
  "geometry": {"coordinates":[-76.770324,37.257324],"type":"Point"}
}