{
  "type": "Feature",
  "properties": {
    "iso:country":"US",
    "sg:address":"206 Ogden Rd",
    "sg:city":"Altavista",
    "sg:classifiers":[
        {
            "category":"Retail",
            "subcategory":"Animal Services",
            "type":"Services"
        }
    ],
    "sg:phone":"+1 434 309 1224",
    "sg:postcode":"24517",
    "sg:province":"VA",
    "wof:name":"Pampered Pooch",
    "wof:placetype":"venue"
},
  "geometry": {"coordinates":[-79.290954,37.13011],"type":"Point"}
}