{
  "type": "Feature",
  "properties": {
    "iso:country":"US",
    "sg:address":"3218 Duke St",
    "sg:city":"Alexandria",
    "sg:classifiers":[
        {
            "category":"Wholesale",
            "subcategory":"Furniture",
            "type":"Manufacturing & Wholesale Goods"
        }
    ],
    "sg:phone":"+1 703 461 8030",
    "sg:postcode":"22314",
    "sg:province":"VA",
    "wof:name":"Healthy Back Store",
    "wof:placetype":"venue"
},
  "geometry": {"coordinates":[-77.08484199999999,38.807771],"type":"Point"}
}