{
  "type": "Feature",
  "properties": {
    "addr:full":"8875 Dunstable Loop Bristow VA 20136",
    "addr:housenumber":"8875",
    "addr:postcode":"20136",
    "addr:street":"Dunstable Loop",
    "iso:country":"US",
    "sg:address":"8875 Dunstable Loop",
    "sg:city":"Bristow",
    "sg:classifiers":[
        {
            "category":"Shopping",
            "subcategory":"Tobacco",
            "type":"Retail Goods"
        }
    ],
    "sg:phone":"+1 703 530 8185",
    "sg:postcode":"20136",
    "sg:province":"VA",
    "sg:tags":[
        "product"
    ],
    "wof:name":"Magnifiscent Cigars",
    "wof:placetype":"venue"
},
  "geometry": {"coordinates":[-77.563205,38.766882],"type":"Point"}
}