{
  "type": "Feature",
  "properties": {
    "iso:country":"US",
    "sg:address":"1 Hemlock Ct",
    "sg:city":"Fredericksburg",
    "sg:classifiers":[
        {
            "category":"Professional",
            "subcategory":"Computer Services",
            "type":"Services"
        }
    ],
    "sg:phone":"+1 540 785 4585",
    "sg:postcode":"22407",
    "sg:province":"VA",
    "sg:tags":[
        "development",
        "company",
        "software"
    ],
    "wof:name":"JRM Enterprises Inc",
    "wof:placetype":"venue"
},
  "geometry": {"coordinates":[-77.57963599999999,38.343201],"type":"Point"}
}