{
  "type": "Feature",
  "properties": {
    "addr:full":"6320 Augusta Dr Springfield VA 22150",
    "addr:housenumber":"6320",
    "addr:postcode":"22150",
    "addr:street":"Augusta Dr",
    "iso:country":"US",
    "sg:address":"6320 Augusta Dr",
    "sg:city":"Springfield",
    "sg:classifiers":[
        {
            "category":"Organizations",
            "subcategory":"Professional Association",
            "type":"Services"
        }
    ],
    "sg:phone":"+1 703 923 0010",
    "sg:postcode":"22150",
    "sg:province":"VA",
    "sg:website":"www.peatc.org",
    "wof:name":"Parent Educational Advocacy",
    "wof:placetype":"venue"
},
  "geometry": {"coordinates":[-77.180959,38.78084],"type":"Point"}
}