{
  "type": "Feature",
  "properties": {
    "iso:country":"US",
    "sg:address":"3432 Brookwood Dr",
    "sg:city":"Fairfax",
    "sg:classifiers":[
        {
            "category":"Professional",
            "subcategory":"Business Services",
            "type":"Services"
        }
    ],
    "sg:phone":"+1 703 352 1020",
    "sg:postcode":"22030",
    "sg:province":"VA",
    "wof:name":"Little River Drum Group",
    "wof:placetype":"venue"
},
  "geometry": {"coordinates":[-77.29045499999999,38.857834],"type":"Point"}
}