{
  "type": "Feature",
  "properties": {
    "addr:full":"607 Twinridge Ln Richmond VA 23235",
    "addr:housenumber":"607",
    "addr:postcode":"23235",
    "addr:street":"Twinridge Ln",
    "iso:country":"US",
    "sg:address":"607 Twinridge Ln",
    "sg:city":"Richmond",
    "sg:classifiers":[
        {
            "category":"Professional",
            "subcategory":"Accounting & Tax Preparation",
            "type":"Services"
        }
    ],
    "sg:phone":"+1 804 272 1428",
    "sg:postcode":"23235",
    "sg:province":"VA",
    "sg:tags":[
        "accountant"
    ],
    "wof:name":"Paul M Kessler Accounting",
    "wof:placetype":"venue"
},
  "geometry": {"coordinates":[-77.548979,37.501132],"type":"Point"}
}