{
  "type": "Feature",
  "properties": {
    "addr:full":"907 N Royal Ave Front Royal VA 22630",
    "addr:housenumber":"907",
    "addr:postcode":"22630",
    "addr:street":"N Royal Ave",
    "iso:country":"US",
    "sg:address":"907 N Royal Ave",
    "sg:city":"Front Royal",
    "sg:classifiers":[
        {
            "category":"Real Estate",
            "subcategory":"Real Estate Agent",
            "type":"Services"
        }
    ],
    "sg:phone":"+1 540 636 7700",
    "sg:postcode":"22630",
    "sg:province":"VA",
    "sg:tags":[
        "business"
    ],
    "wof:name":"Coldwell Banker",
    "wof:placetype":"venue"
},
  "geometry": {"coordinates":[-78.194106,38.930388],"type":"Point"}
}