{
  "type": "Feature",
  "properties": {
    "iso:country":"US",
    "sg:address":"2116 S Nelson St",
    "sg:city":"Arlington",
    "sg:classifiers":[
        {
            "category":"Organizations",
            "subcategory":"Religious Organization",
            "type":"Services"
        }
    ],
    "sg:phone":"+1 703 778 1550",
    "sg:postcode":"22204",
    "sg:province":"VA",
    "sg:tags":[
        "church"
    ],
    "wof:name":"Bangadesh Islamic Ctr",
    "wof:placetype":"venue"
},
  "geometry": {"coordinates":[-77.09089299999999,38.850945],"type":"Point"}
}