{
  "type": "Feature",
  "properties": {
    "addr:full":"240 Madison Cir Madison Heights VA 24572",
    "addr:housenumber":"240",
    "addr:postcode":"24572",
    "addr:street":"Madison Cir",
    "iso:country":"US",
    "sg:address":"240 Madison Cir",
    "sg:city":"Madison Heights",
    "sg:classifiers":[
        {
            "category":"Farming",
            "subcategory":"Farm",
            "type":"Manufacturing & Wholesale Goods"
        }
    ],
    "sg:phone":"+1 434 384 3954",
    "sg:postcode":"24572",
    "sg:province":"VA",
    "sg:tags":[
        "crop",
        "general"
    ],
    "wof:name":"Mitchell George",
    "wof:placetype":"venue"
},
  "geometry": {"coordinates":[-79.13247200000001,37.424367],"type":"Point"}
}