{
  "type": "Feature",
  "properties": {
    "iso:country":"US",
    "sg:address":"4512 Virginia Beach Blvd",
    "sg:city":"Virginia Beach",
    "sg:classifiers":[
        {
            "category":"Organizations",
            "subcategory":"Professional Association",
            "type":"Services"
        }
    ],
    "sg:phone":"+1 757 490 1221",
    "sg:postcode":"23462",
    "sg:province":"VA",
    "sg:tags":[
        "chamber",
        "commerce"
    ],
    "wof:name":"Hampton Roads Chamber Commerce",
    "wof:placetype":"venue"
},
  "geometry": {"coordinates":[-76.13148700000001,36.843671],"type":"Point"}
}