{
  "type": "Feature",
  "properties": {
    "iso:country":"US",
    "sg:address":"14252 Madrigal Dr",
    "sg:city":"Woodbridge",
    "sg:classifiers":[
        {
            "category":"Building & Trades",
            "subcategory":"Construction",
            "type":"Services"
        }
    ],
    "sg:phone":"+1 703 897 9579",
    "sg:postcode":"22193",
    "sg:province":"VA",
    "sg:tags":[
        "hanging",
        "contractor"
    ],
    "wof:name":"Dream Scape",
    "wof:placetype":"venue"
},
  "geometry": {"coordinates":[-77.31581799999999,38.645866],"type":"Point"}
}