{
  "type": "Feature",
  "properties": {
    "iso:country":"US",
    "sg:address":"12704 Pickett Ct",
    "sg:city":"Spotsylvania",
    "sg:classifiers":[
        {
            "category":"Recreation",
            "type":"Entertainment"
        }
    ],
    "sg:phone":"+1 540 972 0082",
    "sg:postcode":"22551",
    "sg:province":"VA",
    "sg:tags":[
        "entertainers-family",
        "business"
    ],
    "wof:name":"Sharon A Watkin",
    "wof:placetype":"venue"
},
  "geometry": {"coordinates":[-77.732721,38.304978],"type":"Point"}
}