{
  "type": "Feature",
  "properties": {
    "iso:country":"US",
    "sg:address":"5269 Cleveland St",
    "sg:city":"Virginia Beach",
    "sg:classifiers":[
        {
            "category":"Building & Trades",
            "subcategory":"Construction",
            "type":"Services"
        },
        {
            "category":"Wholesale",
            "subcategory":"Electrical",
            "type":"Manufacturing & Wholesale Goods"
        }
    ],
    "sg:phone":"+1 757 518 8100",
    "sg:postcode":"23462",
    "sg:province":"VA",
    "sg:tags":[
        "fiber",
        "assembly",
        "optic",
        "cable",
        "tool",
        "kit",
        "connector",
        "optics"
    ],
    "sg:website":"www.kitcofo.com",
    "wof:name":"Kitco Fiber Optics Inc",
    "wof:placetype":"venue"
},
  "geometry": {"coordinates":[-76.163527,36.842867],"type":"Point"}
}