{
  "type": "Feature",
  "properties": {
    "addr:full":"1500 Rustling Cedar Ln Richmond VA 23231",
    "addr:housenumber":"1500",
    "addr:postcode":"23231",
    "addr:street":"Rustling Cedar Ln",
    "iso:country":"US",
    "sg:address":"1500 Rustling Cedar Ln",
    "sg:city":"Richmond",
    "sg:classifiers":[
        {
            "category":"Building & Trades",
            "subcategory":"Construction",
            "type":"Services"
        }
    ],
    "sg:phone":"+1 804 795 2179",
    "sg:postcode":"23231",
    "sg:province":"VA",
    "sg:tags":[
        "home",
        "builder"
    ],
    "wof:name":"Searsons Inc",
    "wof:placetype":"venue"
},
  "geometry": {"coordinates":[-77.393473,37.412157],"type":"Point"}
}