{
  "type": "Feature",
  "properties": {
    "addr:full":"2566 Stuarts Draft Hwy Stuarts Draft VA 24477",
    "addr:housenumber":"2566",
    "addr:postcode":"24477",
    "addr:street":"Stuarts Draft Hwy",
    "iso:country":"US",
    "sg:address":"2566 Stuarts Draft Hwy",
    "sg:city":"Stuarts Draft",
    "sg:classifiers":[
        {
            "category":"Restaurant",
            "type":"Food & Drink"
        }
    ],
    "sg:menulink":"http://www.allmenus.com/va/south-river/166162-arbys/menu/",
    "sg:phone":"+1 540 337 3962",
    "sg:postcode":"24477",
    "sg:province":"VA",
    "sg:tags":[
        "burger",
        "american"
    ],
    "wof:name":"Arby's",
    "wof:placetype":"venue"
},
  "geometry": {"coordinates":[-79.010991,38.042421],"type":"Point"}
}