{
  "type": "Feature",
  "properties": {
    "addr:full":"6163 Cedar Springs Rd Speedwell VA 24374",
    "addr:housenumber":"6163",
    "addr:postcode":"24374",
    "addr:street":"Cedar Springs Rd",
    "iso:country":"US",
    "sg:address":"6163 Cedar Springs Rd",
    "sg:city":"Speedwell",
    "sg:classifiers":[
        {
            "category":"Organizations",
            "subcategory":"Religious Organization",
            "type":"Services"
        }
    ],
    "sg:phone":"+1 276 621 5258",
    "sg:postcode":"24374",
    "sg:province":"VA",
    "wof:name":"Friendship Ministries",
    "wof:placetype":"venue"
},
  "geometry": {"coordinates":[-81.19126199999999,36.814169],"type":"Point"}
}