{
  "type": "Feature",
  "properties": {
    "addr:full":"3032 Richmond Rd Williamsburg VA 23185",
    "addr:housenumber":"3032",
    "addr:postcode":"23185",
    "addr:street":"Richmond Rd",
    "iso:country":"US",
    "sg:address":"3032 Richmond Rd",
    "sg:city":"Williamsburg",
    "sg:classifiers":[
        {
            "category":"Home & Garden",
            "subcategory":"Furniture",
            "type":"Retail Goods"
        }
    ],
    "sg:phone":"+1 757 564 0300",
    "sg:postcode":"23185",
    "sg:province":"VA",
    "wof:name":"Crawford House",
    "wof:placetype":"venue"
},
  "geometry": {"coordinates":[-76.729512,37.306053],"type":"Point"}
}