{
  "type": "Feature",
  "properties": {
    "iso:country":"US",
    "sg:address":"448 Newtown Rd",
    "sg:city":"Virginia Beach",
    "sg:classifiers":[
        {
            "category":"Restaurant",
            "type":"Food & Drink"
        }
    ],
    "sg:phone":"+1 757 518 0307",
    "sg:postcode":"23462",
    "sg:province":"VA",
    "wof:name":"Saigon I",
    "wof:placetype":"venue"
},
  "geometry": {"coordinates":[-76.178573,36.851453],"type":"Point"}
}