{
  "type": "Feature",
  "properties": {
    "addr:full":"100 Griffin St Fort Monroe VA 23693",
    "addr:housenumber":"100",
    "addr:postcode":"23693",
    "addr:street":"Griffin St",
    "iso:country":"US",
    "sg:address":"100 Griffin St",
    "sg:city":"Fort Monroe",
    "sg:classifiers":[
        {
            "category":"Banks & Credit Unions",
            "subcategory":"Bank",
            "type":"Services"
        }
    ],
    "sg:phone":"+1 757 728 1272",
    "sg:postcode":"23693",
    "sg:province":"VA",
    "sg:tags":[
        "national"
    ],
    "wof:name":"Old Point Nat Bnk of Phoebus",
    "wof:placetype":"venue"
},
  "geometry": {"coordinates":[-76.402502,37.110298],"type":"Point"}
}