{
  "type": "Feature",
  "properties": {
    "addr:full":"2383 Clover Creek Rd Huddleston VA 24104",
    "addr:housenumber":"2383",
    "addr:postcode":"24104",
    "addr:street":"Clover Creek Rd",
    "iso:country":"US",
    "sg:address":"2383 Clover Creek Rd",
    "sg:city":"Huddleston",
    "sg:classifiers":[
        {
            "category":"Retail",
            "subcategory":"Auto Repair",
            "type":"Services"
        }
    ],
    "sg:phone":"+1 540 297 4843",
    "sg:postcode":"24104",
    "sg:province":"VA",
    "sg:tags":[
        "repairing",
        "automobile"
    ],
    "sg:website":"www.wrightsservice.com",
    "wof:name":"Wright's Service Ctr",
    "wof:placetype":"venue"
},
  "geometry": {"coordinates":[-79.521745,37.122441],"type":"Point"}
}