{
  "type": "Feature",
  "properties": {
    "addr:full":"3401 Crossings Way Cir Midlothian VA 23113",
    "addr:housenumber":"3401",
    "addr:postcode":"23113",
    "addr:street":"Crossings Way Cir",
    "iso:country":"US",
    "sg:address":"3401 Crossings Way Cir",
    "sg:city":"Midlothian",
    "sg:classifiers":[
        {
            "category":"Restaurant",
            "type":"Food & Drink"
        }
    ],
    "sg:phone":"+1 804 378 9009",
    "sg:postcode":"23113",
    "sg:province":"VA",
    "wof:name":"Stir The Pot",
    "wof:placetype":"venue"
},
  "geometry": {"coordinates":[-77.67394299999999,37.544022],"type":"Point"}
}