{
  "type": "Feature",
  "properties": {
    "addr:full":"3922 Oakdale Cir Triangle VA 22172",
    "addr:housenumber":"3922",
    "addr:postcode":"22172",
    "addr:street":"Oakdale Cir",
    "iso:country":"US",
    "sg:address":"3922 Oakdale Cir",
    "sg:city":"Triangle",
    "sg:classifiers":[
        {
            "category":"Building & Trades",
            "subcategory":"Construction",
            "type":"Services"
        }
    ],
    "sg:phone":"+1 703 441 9493",
    "sg:postcode":"22172",
    "sg:province":"VA",
    "sg:tags":[
        "repairing",
        "house",
        "contractor",
        "remodeling",
        "nonresidential"
    ],
    "wof:name":"S D S Remodeling",
    "wof:placetype":"venue"
},
  "geometry": {"coordinates":[-77.329184,38.555138],"type":"Point"}
}