{
  "type": "Feature",
  "properties": {
    "addr:full":"12074 James Madison St Remington VA 22734",
    "addr:housenumber":"12074",
    "addr:postcode":"22734",
    "addr:street":"James Madison St",
    "iso:country":"US",
    "sg:address":"12074 James Madison St",
    "sg:city":"Remington",
    "sg:classifiers":[
        {
            "category":"Education",
            "subcategory":"School",
            "type":"Public Place"
        }
    ],
    "sg:phone":"+1 540 439 3213",
    "sg:postcode":"22734",
    "sg:province":"VA",
    "wof:name":"M M Pierce Elementary School",
    "wof:placetype":"venue"
},
  "geometry": {"coordinates":[-77.80578199999999,38.538557],"type":"Point"}
}