{
  "type": "Feature",
  "properties": {
    "addr:full":"12389 Calvert St Culpeper VA 22701",
    "addr:housenumber":"12389",
    "addr:postcode":"22701",
    "addr:street":"Calvert St",
    "iso:country":"US",
    "sg:address":"12389 Calvert St",
    "sg:city":"Culpeper",
    "sg:classifiers":[
        {
            "category":"Building & Trades",
            "subcategory":"Pest Control",
            "type":"Services"
        }
    ],
    "sg:phone":"+1 540 825 2808",
    "sg:postcode":"22701",
    "sg:province":"VA",
    "wof:name":"Custom Pest Control",
    "wof:placetype":"venue"
},
  "geometry": {"coordinates":[-78.01809,38.530954],"type":"Point"}
}