{
  "type": "Feature",
  "properties": {
    "addr:full":"4309 Woodward Ct Chantilly VA 20151",
    "addr:housenumber":"4309",
    "addr:postcode":"20151",
    "addr:street":"Woodward Ct",
    "iso:country":"US",
    "sg:address":"4309 Woodward Ct",
    "sg:city":"Chantilly",
    "sg:classifiers":[
        {
            "category":"Banks & Credit Unions",
            "subcategory":"Bank",
            "type":"Services"
        }
    ],
    "sg:phone":"+1 703 218 6244",
    "sg:postcode":"20151",
    "sg:province":"VA",
    "wof:name":"Peru Directo",
    "wof:placetype":"venue"
},
  "geometry": {"coordinates":[-77.42814300000001,38.882556],"type":"Point"}
}