{
  "type": "Feature",
  "properties": {
    "iso:country":"US",
    "sg:address":"951 E Byrd St",
    "sg:city":"Richmond",
    "sg:classifiers":[
        {
            "category":"Banks & Credit Unions",
            "subcategory":"Investment Brokerage",
            "type":"Services"
        }
    ],
    "sg:phone":"+1 804 698 5700",
    "sg:postcode":"23219",
    "sg:province":"VA",
    "sg:tags":[
        "advisory",
        "security"
    ],
    "wof:name":"UBS Financial Services Inc",
    "wof:placetype":"venue"
},
  "geometry": {"coordinates":[-77.438103,37.535187],"type":"Point"}
}