{
  "type": "Feature",
  "properties": {
    "iso:country":"US",
    "sg:address":"1207 Headquarters Rd",
    "sg:city":"Edinburg",
    "sg:classifiers":[
        {
            "category":"Wholesale",
            "subcategory":"Farm Supplies",
            "type":"Manufacturing & Wholesale Goods"
        }
    ],
    "sg:phone":"+1 540 984 4790",
    "sg:postcode":"22824",
    "sg:province":"VA",
    "wof:name":"Lindamoods Dairy & Farm Sups",
    "wof:placetype":"venue"
},
  "geometry": {"coordinates":[-78.65122700000001,38.814771],"type":"Point"}
}