{
  "type": "Feature",
  "properties": {
    "addr:full":"113 Mystic Ln NW Willis VA 24380",
    "addr:housenumber":"113",
    "addr:postcode":"24380",
    "addr:street":"Mystic Ln Nw",
    "iso:country":"US",
    "sg:address":"113 Mystic Ln NW",
    "sg:city":"Willis",
    "sg:classifiers":[
        {
            "category":"Building & Trades",
            "subcategory":"Plumbing",
            "type":"Services"
        }
    ],
    "sg:phone":"+1 540 789 7300",
    "sg:postcode":"24380",
    "sg:province":"VA",
    "sg:tags":[
        "contractor"
    ],
    "wof:name":"Ridgeway Plumbing",
    "wof:placetype":"venue"
},
  "geometry": {"coordinates":[-80.50201199999999,36.917151],"type":"Point"}
}