{
  "type": "Feature",
  "properties": {
    "addr:full":"2030 Upper Lake Dr Reston VA 20191",
    "addr:housenumber":"2030",
    "addr:postcode":"20191",
    "addr:street":"Upper Lake Dr",
    "iso:country":"US",
    "sg:address":"2030 Upper Lake Dr",
    "sg:city":"Reston",
    "sg:classifiers":[
        {
            "category":"Professional",
            "subcategory":"Accounting & Tax Preparation",
            "type":"Services"
        }
    ],
    "sg:phone":"+1 703 860 0191",
    "sg:postcode":"20191",
    "sg:province":"VA",
    "wof:name":"John Sullivan CPA",
    "wof:placetype":"venue"
},
  "geometry": {"coordinates":[-77.33336300000001,38.942028],"type":"Point"}
}