{
  "type": "Feature",
  "properties": {
    "addr:full":"4736 Treely Rd Chester VA 23831",
    "addr:housenumber":"4736",
    "addr:postcode":"23831",
    "addr:street":"Treely Rd",
    "iso:country":"US",
    "sg:address":"4736 Treely Rd",
    "sg:city":"Chester",
    "sg:classifiers":[
        {
            "category":"Health Services",
            "subcategory":"Doctor",
            "type":"Services"
        }
    ],
    "sg:phone":"+1 804 520 0685",
    "sg:postcode":"23831",
    "sg:province":"VA",
    "sg:tags":[
        "clinic"
    ],
    "wof:name":"House Calls Plus Inc",
    "wof:placetype":"venue"
},
  "geometry": {"coordinates":[-77.447682,37.312895],"type":"Point"}
}