{
  "type": "Feature",
  "properties": {
    "iso:country":"US",
    "sg:address":"4721 Walmsley Blvd",
    "sg:city":"Richmond",
    "sg:classifiers":[
        {
            "category":"Shopping",
            "subcategory":"Pharmacy",
            "type":"Retail Goods"
        }
    ],
    "sg:phone":"+1 804 275 4632",
    "sg:postcode":"23234",
    "sg:province":"VA",
    "wof:name":"CVS",
    "wof:placetype":"venue"
},
  "geometry": {"coordinates":[-77.48267300000001,37.470086],"type":"Point"}
}