{
  "type": "Feature",
  "properties": {
    "addr:full":"3005 Williamson Rd Lynchburg VA 24520",
    "addr:housenumber":"3005",
    "addr:postcode":"24520",
    "addr:street":"Williamson Rd",
    "iso:country":"US",
    "sg:address":"3005 Williamson Rd",
    "sg:city":"Lynchburg",
    "sg:classifiers":[
        {
            "category":"Building & Trades",
            "subcategory":"Construction",
            "type":"Services"
        }
    ],
    "sg:phone":"+1 434 528 5910",
    "sg:postcode":"24520",
    "sg:province":"VA",
    "sg:tags":[
        "siding",
        "contractor"
    ],
    "wof:name":"Windows Direct Of Lynchburg",
    "wof:placetype":"venue"
},
  "geometry": {"coordinates":[-79.140255,36.557383],"type":"Point"}
}