{
  "type": "Feature",
  "properties": {
    "addr:full":"327 Helmuth Ln Alexandria VA 22304",
    "addr:housenumber":"327",
    "addr:postcode":"22304",
    "addr:street":"Helmuth Ln",
    "iso:country":"US",
    "sg:address":"327 Helmuth Ln",
    "sg:city":"Alexandria",
    "sg:classifiers":[
        {
            "category":"Professional",
            "subcategory":"Business Services",
            "type":"Services"
        }
    ],
    "sg:phone":"+1 703 823 6263",
    "sg:postcode":"22304",
    "sg:province":"VA",
    "wof:name":"Oovoo Design",
    "wof:placetype":"venue"
},
  "geometry": {"coordinates":[-77.122153,38.807306],"type":"Point"}
}