{
  "type": "Feature",
  "properties": {
    "addr:full":"100 E South St Charlottesville VA 22902",
    "addr:housenumber":"100 e",
    "addr:postcode":"22902",
    "addr:street":"South St",
    "iso:country":"US",
    "sg:address":"100 E South St",
    "sg:city":"Charlottesville",
    "sg:classifiers":[
        {
            "category":"Health Services",
            "subcategory":"Clinic",
            "type":"Services"
        }
    ],
    "sg:phone":"+1 434 971 4747",
    "sg:postcode":"22902",
    "sg:province":"VA",
    "sg:tags":[
        "counseling",
        "mental"
    ],
    "wof:name":"Crosby Michael Lcsw",
    "wof:placetype":"venue"
},
  "geometry": {"coordinates":[-78.482201,38.029301],"type":"Point"}
}