{
  "type": "Feature",
  "properties": {
    "iso:country":"US",
    "sg:address":"18243 Forest Rd",
    "sg:city":"Lynchburg",
    "sg:classifiers":[
        {
            "category":"Restaurant",
            "type":"Food & Drink"
        }
    ],
    "sg:menulink":"http://www.allmenus.com/va/jefferson/80447-dominos-pizza/menu/",
    "sg:phone":"+1 434 385 0404",
    "sg:postcode":"24502",
    "sg:province":"VA",
    "sg:tags":[
        "american",
        "wing",
        "pizza"
    ],
    "wof:name":"Domino's Pizza",
    "wof:placetype":"venue"
},
  "geometry": {"coordinates":[-79.246629,37.380103],"type":"Point"}
}