{
  "type": "Feature",
  "properties": {
    "addr:full":"2727 Electric Rd Roanoke VA 24018",
    "addr:housenumber":"2727",
    "addr:postcode":"24018",
    "addr:street":"Electric Rd",
    "iso:country":"US",
    "sg:address":"2727 Electric Rd",
    "sg:city":"Roanoke",
    "sg:classifiers":[
        {
            "category":"Food & Beverages",
            "subcategory":"Groceries & Convenience Stores",
            "type":"Retail Goods"
        }
    ],
    "sg:phone":"+1 540 774 0300",
    "sg:postcode":"24018",
    "sg:province":"VA",
    "wof:name":"Caldwell Branded Food Group",
    "wof:placetype":"venue"
},
  "geometry": {"coordinates":[-80.02014699999999,37.233497],"type":"Point"}
}