{
  "type": "Feature",
  "properties": {
    "addr:full":"2025 S Boston Rd Danville VA 24540",
    "addr:housenumber":"2025",
    "addr:postcode":"24540",
    "addr:street":"S Boston Rd",
    "iso:country":"US",
    "sg:address":"2025 S Boston Rd",
    "sg:city":"Danville",
    "sg:classifiers":[
        {
            "category":"Autos & Motor Vehicles",
            "subcategory":"Automobile Sales",
            "type":"Retail Goods"
        }
    ],
    "sg:phone":"+1 434 822 6666",
    "sg:postcode":"24540",
    "sg:province":"VA",
    "sg:tags":[
        "car",
        "dealer"
    ],
    "wof:name":"Frank Guerrant Auto Sales",
    "wof:placetype":"venue"
},
  "geometry": {"coordinates":[-79.320798,36.581087],"type":"Point"}
}