{
  "type": "Feature",
  "properties": {
    "addr:full":"1420 Beverly Rd Ste 220 Mc Lean VA 22101",
    "addr:housenumber":"1420",
    "addr:postcode":"22101",
    "addr:street":"Beverly Rd Ste 220 Mc Lean",
    "iso:country":"US",
    "sg:address":"1420 Beverly Rd Ste 220",
    "sg:city":"Mc Lean",
    "sg:classifiers":[
        {
            "category":"Organizations",
            "subcategory":"Religious Organization",
            "type":"Services"
        }
    ],
    "sg:phone":"+1 703 760 9222",
    "sg:postcode":"22101",
    "sg:province":"VA",
    "sg:website":"www.church-of-christ.org",
    "wof:name":"Washington DC Church of Christ",
    "wof:placetype":"venue"
},
  "geometry": {"coordinates":[-77.180702,38.934299],"type":"Point"}
}