{
  "type": "Feature",
  "properties": {
    "iso:country":"US",
    "sg:address":"1024 Tyler St",
    "sg:city":"Herndon",
    "sg:classifiers":[
        {
            "category":"Professional",
            "subcategory":"Art Services",
            "type":"Services"
        }
    ],
    "sg:phone":"+1 703 471 1381",
    "sg:postcode":"20170",
    "sg:province":"VA",
    "sg:tags":[
        "commercial",
        "design"
    ],
    "wof:name":"S G Graphics",
    "wof:placetype":"venue"
},
  "geometry": {"coordinates":[-77.38026499999999,38.980649],"type":"Point"}
}