{
  "type": "Feature",
  "properties": {
    "iso:country":"US",
    "sg:address":"7571 Centreville Rd",
    "sg:city":"Manassas",
    "sg:classifiers":[
        {
            "category":"Shopping",
            "subcategory":"Used Merchandise",
            "type":"Retail Goods"
        },
        {
            "category":"Retail",
            "subcategory":"Repair Shop",
            "type":"Services"
        }
    ],
    "sg:phone":"+1 703 392 3615",
    "sg:postcode":"20111",
    "sg:province":"VA",
    "sg:tags":[
        "antique",
        "restoring"
    ],
    "wof:name":"Village Variety Shop",
    "wof:placetype":"venue"
},
  "geometry": {"coordinates":[-77.44802,38.791075],"type":"Point"}
}