{
  "type": "Feature",
  "properties": {
    "iso:country":"US",
    "sg:address":"11911 Hull Street Rd",
    "sg:city":"Midlothian",
    "sg:classifiers":[
        {
            "category":"Autos & Motor Vehicles",
            "subcategory":"Auto Supplies",
            "type":"Retail Goods"
        },
        {
            "category":"Wholesale",
            "subcategory":"Auto Parts",
            "type":"Manufacturing & Wholesale Goods"
        }
    ],
    "sg:phone":"+1 804 744 8565",
    "sg:postcode":"23112",
    "sg:province":"VA",
    "sg:tags":[
        "truck",
        "accessory"
    ],
    "wof:name":"Ken Browns Truck Outfitters",
    "wof:placetype":"venue"
},
  "geometry": {"coordinates":[-77.614007,37.432281],"type":"Point"}
}