{
  "type": "Feature",
  "properties": {
    "iso:country":"US",
    "sg:address":"3028 Bandy Rd",
    "sg:city":"Roanoke",
    "sg:classifiers":[
        {
            "category":"Building & Trades",
            "subcategory":"Electrical",
            "type":"Services"
        }
    ],
    "sg:phone":"+1 540 427 1000",
    "sg:postcode":"24014",
    "sg:province":"VA",
    "sg:tags":[
        "industrial",
        "electrician",
        "contractors-commercial",
        "electric"
    ],
    "wof:name":"Jeffco Electric Services Inc",
    "wof:placetype":"venue"
},
  "geometry": {"coordinates":[-79.920303,37.238263],"type":"Point"}
}