{
  "type": "Feature",
  "properties": {
    "addr:full":"1149 Montague Island Rd Jamaica VA 23079",
    "addr:housenumber":"1149",
    "addr:postcode":"23079",
    "addr:street":"Montague Island Rd",
    "iso:country":"US",
    "sg:address":"1149 Montague Island Rd",
    "sg:city":"Jamaica",
    "sg:classifiers":[
        {
            "category":"Building & Trades",
            "subcategory":"Landscaping Services",
            "type":"Services"
        }
    ],
    "sg:phone":"+1 804 758 0372",
    "sg:postcode":"23079",
    "sg:province":"VA",
    "sg:tags":[
        "lawn",
        "care"
    ],
    "wof:name":"Lewis Lawn Care",
    "wof:placetype":"venue"
},
  "geometry": {"coordinates":[-76.643753,37.748954],"type":"Point"}
}