{
  "type": "Feature",
  "properties": {
    "iso:country":"US",
    "sg:address":"4409 George Washington Hwy",
    "sg:city":"Portsmouth",
    "sg:classifiers":[
        {
            "category":"Health Services",
            "subcategory":"Doctor",
            "type":"Services"
        }
    ],
    "sg:phone":"+1 757 485 2222",
    "sg:postcode":"23702",
    "sg:province":"VA",
    "sg:tags":[
        "dentist"
    ],
    "wof:name":"Francis Lesinski DDS PC",
    "wof:placetype":"venue"
},
  "geometry": {"coordinates":[-76.324061,36.800263],"type":"Point"}
}