{
  "type": "Feature",
  "properties": {
    "addr:full":"7070 Daffodil Rd Mechanicsville VA 23111",
    "addr:housenumber":"7070",
    "addr:postcode":"23111",
    "addr:street":"Daffodil Rd",
    "iso:country":"US",
    "sg:address":"7070 Daffodil Rd",
    "sg:city":"Mechanicsville",
    "sg:classifiers":[
        {
            "category":"Retail",
            "subcategory":"Repair Shop",
            "type":"Services"
        }
    ],
    "sg:phone":"+1 804 559 2645",
    "sg:postcode":"23111",
    "sg:province":"VA",
    "sg:tags":[
        "antique",
        "restoration",
        "furniture"
    ],
    "wof:name":"Hanover Furniture Repair CP",
    "wof:placetype":"venue"
},
  "geometry": {"coordinates":[-77.341959,37.593557],"type":"Point"}
}