{
  "type": "Feature",
  "properties": {
    "iso:country":"US",
    "sg:address":"9512 Iron Bridge Rd",
    "sg:city":"Chesterfield",
    "sg:classifiers":[
        {
            "category":"Professional",
            "subcategory":"Lawyer & Legal Services",
            "type":"Services"
        }
    ],
    "sg:phone":"+1 804 796 7511",
    "sg:postcode":"23832",
    "sg:province":"VA",
    "sg:tags":[
        "attorney"
    ],
    "wof:name":"J Thomas Steger",
    "wof:placetype":"venue"
},
  "geometry": {"coordinates":[-77.51499,37.381623],"type":"Point"}
}