{
  "type": "Feature",
  "properties": {
    "addr:full":"8391 Richmond Rd Toano VA 23168",
    "addr:housenumber":"8391",
    "addr:postcode":"23168",
    "addr:street":"Richmond Rd",
    "iso:country":"US",
    "sg:address":"8391 Richmond Rd",
    "sg:city":"Toano",
    "sg:classifiers":[
        {
            "category":"Retail",
            "subcategory":"Veterinary Services",
            "type":"Services"
        }
    ],
    "sg:phone":"+1 757 566 2224",
    "sg:postcode":"23168",
    "sg:province":"VA",
    "sg:tags":[
        "veterinarian"
    ],
    "sg:website":"http://www.acah.com",
    "wof:name":"Anderson's Corner Animal Hospital",
    "wof:placetype":"venue"
},
  "geometry": {"coordinates":[-76.804974,37.394339],"type":"Point"}
}