{
  "type": "Feature",
  "properties": {
    "addr:full":"15390 Reva Rd Reva VA 22735",
    "addr:postcode":"15390;22735",
    "addr:street":"Reva Rd",
    "iso:country":"US",
    "sg:address":"15390 Reva Rd",
    "sg:city":"Reva",
    "sg:classifiers":[
        {
            "category":"Organizations",
            "subcategory":"Religious Organization",
            "type":"Services"
        }
    ],
    "sg:phone":"+1 540 547 9792",
    "sg:postcode":"22735",
    "sg:province":"VA",
    "sg:tags":[
        "church"
    ],
    "wof:name":"Canaan Baptist Church",
    "wof:placetype":"venue"
},
  "geometry": {"coordinates":[-78.137297,38.493521],"type":"Point"}
}