{
  "type": "Feature",
  "properties": {
    "addr:full":"1213 George Washington Memorial Hwy Yorktown VA 23693",
    "addr:housenumber":"1213",
    "addr:postcode":"23693",
    "addr:street":"George Washington Memorial Hwy",
    "iso:country":"US",
    "sg:address":"1213 George Washington Memorial Hwy",
    "sg:city":"Yorktown",
    "sg:classifiers":[
        {
            "category":"Professional",
            "subcategory":"Computer Services",
            "type":"Services"
        }
    ],
    "sg:phone":"+1 757 591 5300",
    "sg:postcode":"23693",
    "sg:province":"VA",
    "wof:name":"Hampton Roads Online",
    "wof:placetype":"venue"
},
  "geometry": {"coordinates":[-76.458516,37.10066],"type":"Point"}
}