{
  "type": "Feature",
  "properties": {
    "addr:full":"331 Douglas Dr Damascus VA 24236",
    "addr:housenumber":"331",
    "addr:postcode":"24236",
    "addr:street":"Douglas Dr",
    "iso:country":"US",
    "sg:address":"331 Douglas Dr",
    "sg:city":"Damascus",
    "sg:classifiers":[
        {
            "category":"Restaurant",
            "type":"Food & Drink"
        }
    ],
    "sg:phone":"+1 276 475 3226",
    "sg:postcode":"24236",
    "sg:province":"VA",
    "sg:tags":[
        "shop",
        "coffee"
    ],
    "wof:name":"Damascus Coffee House & Gifts",
    "wof:placetype":"venue"
},
  "geometry": {"coordinates":[-81.783297,36.631566],"type":"Point"}
}