{
  "type": "Feature",
  "properties": {
    "iso:country":"US",
    "sg:address":"4721 Jefferson Davis Hwy",
    "sg:city":"Richmond",
    "sg:classifiers":[
        {
            "category":"Autos & Motor Vehicles",
            "subcategory":"Fuel & Gas Station",
            "type":"Retail Goods"
        }
    ],
    "sg:phone":"+1 804 271 4175",
    "sg:postcode":"23234",
    "sg:province":"VA",
    "sg:tags":[
        "station",
        "gasoline"
    ],
    "wof:name":"Hess",
    "wof:placetype":"venue"
},
  "geometry": {"coordinates":[-77.442368,37.461365],"type":"Point"}
}