{
  "type": "Feature",
  "properties": {
    "addr:full":"4859 Finlay St Richmond VA 23231",
    "addr:housenumber":"4859",
    "addr:postcode":"23231",
    "addr:street":"Finlay St",
    "iso:country":"US",
    "sg:address":"4859 Finlay St",
    "sg:city":"Richmond",
    "sg:classifiers":[
        {
            "category":"Health Services",
            "subcategory":"Doctor",
            "type":"Services"
        }
    ],
    "sg:phone":"+1 804 222 6069",
    "sg:postcode":"23231",
    "sg:province":"VA",
    "sg:tags":[
        "dentist"
    ],
    "wof:name":"Great Expressions",
    "wof:placetype":"venue"
},
  "geometry": {"coordinates":[-77.34727100000001,37.522227],"type":"Point"}
}