{
  "type": "Feature",
  "properties": {
    "addr:full":"2732 Virginia Beach Blvd Virginia Beach VA 23452",
    "addr:housenumber":"2732",
    "addr:postcode":"23452",
    "addr:street":"Virginia Beach Blvd",
    "iso:country":"US",
    "sg:address":"2732 Virginia Beach Blvd",
    "sg:city":"Virginia Beach",
    "sg:classifiers":[
        {
            "category":"Shopping",
            "subcategory":"Bicycles & Sporting Goods",
            "type":"Retail Goods"
        }
    ],
    "sg:phone":"+1 757 486 9525",
    "sg:postcode":"23452",
    "sg:province":"VA",
    "sg:tags":[
        "equipment",
        "exercise"
    ],
    "wof:name":"Fitness Resource",
    "wof:placetype":"venue"
},
  "geometry": {"coordinates":[-76.066682,36.843073],"type":"Point"}
}