{
  "type": "Feature",
  "properties": {
    "addr:full":"744 Greenwich Dr Roanoke VA 24019",
    "addr:housenumber":"744",
    "addr:postcode":"24019",
    "addr:street":"Greenwich Dr",
    "iso:country":"US",
    "sg:address":"744 Greenwich Dr",
    "sg:city":"Roanoke",
    "sg:classifiers":[
        {
            "category":"Professional",
            "subcategory":"Computer Services",
            "type":"Services"
        }
    ],
    "sg:phone":"+1 540 366 4205",
    "sg:postcode":"24019",
    "sg:province":"VA",
    "sg:tags":[
        "internet"
    ],
    "wof:name":"Focal Point Web Design",
    "wof:placetype":"venue"
},
  "geometry": {"coordinates":[-79.938787,37.334599],"type":"Point"}
}