{
  "type": "Feature",
  "properties": {
    "addr:full":"3431 Allerton Ct Dumfries VA 22026",
    "addr:housenumber":"3431",
    "addr:postcode":"22026",
    "addr:street":"Allerton Ct",
    "iso:country":"US",
    "sg:address":"3431 Allerton Ct",
    "sg:city":"Dumfries",
    "sg:classifiers":[
        {
            "category":"Food & Beverages",
            "subcategory":"Fruits & Vegetables",
            "type":"Retail Goods"
        }
    ],
    "sg:phone":"+1 703 221 0178",
    "sg:postcode":"22026",
    "sg:province":"VA",
    "wof:name":"N & H Produce Inc",
    "wof:placetype":"venue"
},
  "geometry": {"coordinates":[-77.315467,38.581793],"type":"Point"}
}