{
  "type": "Feature",
  "properties": {
    "addr:full":"5606 Willoughby Newton Dr Centreville VA 20120",
    "addr:housenumber":"5606",
    "addr:postcode":"20120",
    "addr:street":"Willoughby Newton Dr",
    "iso:country":"US",
    "sg:address":"5606 Willoughby Newton Dr",
    "sg:city":"Centreville",
    "sg:classifiers":[
        {
            "category":"Recreation",
            "type":"Entertainment"
        }
    ],
    "sg:phone":"+1 703 631 9309",
    "sg:postcode":"20120",
    "sg:province":"VA",
    "sg:tags":[
        "club",
        "membership"
    ],
    "wof:name":"Willoughby Ridge Pool",
    "wof:placetype":"venue"
},
  "geometry": {"coordinates":[-77.429991,38.844493],"type":"Point"}
}