{
  "type": "Feature",
  "properties": {
    "addr:full":"2311 N Lexington St Arlington VA 22205",
    "addr:housenumber":"2311",
    "addr:postcode":"22205",
    "addr:street":"N Lexington St",
    "iso:country":"US",
    "sg:address":"2311 N Lexington St",
    "sg:city":"Arlington",
    "sg:classifiers":[
        {
            "category":"Professional",
            "subcategory":"Lawyer & Legal Services",
            "type":"Services"
        }
    ],
    "sg:phone":"+1 703 533 0684",
    "sg:postcode":"22205",
    "sg:province":"VA",
    "sg:tags":[
        "attorney"
    ],
    "wof:name":"Pope & Pope Law Offices",
    "wof:placetype":"venue"
},
  "geometry": {"coordinates":[-77.143238,38.893645],"type":"Point"}
}