{
  "type": "Feature",
  "properties": {
    "addr:full":"586 E Pine St La Crosse VA 23950",
    "addr:housenumber":"586",
    "addr:postcode":"23950",
    "addr:street":"E Pine St",
    "iso:country":"US",
    "sg:address":"586 E Pine St",
    "sg:city":"La Crosse",
    "sg:classifiers":[
        {
            "category":"Insurance",
            "subcategory":"Insurance Agent",
            "type":"Services"
        }
    ],
    "sg:phone":"+1 434 757 7249",
    "sg:postcode":"23950",
    "sg:province":"VA",
    "wof:name":"American Life Line Med Trnsprt",
    "wof:placetype":"venue"
},
  "geometry": {"coordinates":[-78.08536700000001,36.697861],"type":"Point"}
}