{
  "type": "Feature",
  "properties": {
    "iso:country":"US",
    "sg:address":"6600 James Madison Hwy",
    "sg:city":"Haymarket",
    "sg:classifiers":[
        {
            "category":"Retail",
            "subcategory":"Storage",
            "type":"Services"
        }
    ],
    "sg:phone":"+1 703 754 0445",
    "sg:postcode":"20169",
    "sg:province":"VA",
    "sg:tags":[
        "self"
    ],
    "sg:website":"www.haymarketss.com",
    "wof:name":"Haymarket Self Storage",
    "wof:placetype":"venue"
},
  "geometry": {"coordinates":[-77.64269899999999,38.81274],"type":"Point"}
}