{
  "type": "Feature",
  "properties": {
    "iso:country":"US",
    "sg:address":"735 Brookside Dr",
    "sg:city":"Newport News",
    "sg:classifiers":[
        {
            "category":"Manufacturing",
            "subcategory":"Retail Goods",
            "type":"Manufacturing & Wholesale Goods"
        }
    ],
    "sg:phone":"+1 757 369 0800",
    "sg:postcode":"23602",
    "sg:province":"VA",
    "sg:tags":[
        "product",
        "mfg"
    ],
    "wof:name":"Cofield Enterprises Inc",
    "wof:placetype":"venue"
},
  "geometry": {"coordinates":[-76.497454,37.117543],"type":"Point"}
}