{
  "type": "Feature",
  "properties": {
    "addr:full":"216 Champions Path Yorktown VA 23693",
    "addr:housenumber":"216",
    "addr:postcode":"23693",
    "addr:street":"Champions Path",
    "iso:country":"US",
    "sg:address":"216 Champions Path",
    "sg:city":"Yorktown",
    "sg:classifiers":[
        {
            "category":"Real Estate",
            "subcategory":"Real Estate Agent",
            "type":"Services"
        }
    ],
    "sg:phone":"+1 757 886 3022",
    "sg:postcode":"23693",
    "sg:province":"VA",
    "sg:tags":[
        "property",
        "management"
    ],
    "wof:name":"Lee Real Estate",
    "wof:placetype":"venue"
},
  "geometry": {"coordinates":[-76.404214,37.114564],"type":"Point"}
}