{
  "type": "Feature",
  "properties": {
    "iso:country":"US",
    "sg:address":"553 Logan Pl",
    "sg:city":"Newport News",
    "sg:classifiers":[
        {
            "category":"Professional",
            "subcategory":"Computer Services",
            "type":"Services"
        }
    ],
    "sg:phone":"+1 804 644 1040",
    "sg:postcode":"23601",
    "sg:province":"VA",
    "sg:tags":[
        "internet"
    ],
    "wof:name":"Cyberactive Solution Inc",
    "wof:placetype":"venue"
},
  "geometry": {"coordinates":[-76.470555,37.048866],"type":"Point"}
}