{
  "type": "Feature",
  "properties": {
    "addr:full":"3536 Brambleton Ave Ste 5 Roanoke VA 24018",
    "addr:housenumber":"3536",
    "addr:postcode":"24018",
    "addr:street":"Brambleton Ave Ste 5",
    "iso:country":"US",
    "sg:address":"3536 Brambleton Ave Ste 5",
    "sg:city":"Roanoke",
    "sg:classifiers":[
        {
            "category":"Personal",
            "subcategory":"Massage",
            "type":"Services"
        },
        {
            "category":"Health Services",
            "subcategory":"Hospital",
            "type":"Services"
        },
        {
            "category":"Health Services",
            "subcategory":"Health Practitioner",
            "type":"Services"
        },
        {
            "category":"Health Services",
            "subcategory":"Clinic",
            "type":"Services"
        }
    ],
    "sg:phone":"+1 540 989 8680",
    "sg:postcode":"24018",
    "sg:province":"VA",
    "sg:tags":[
        "therapist",
        "therapy",
        "treatment",
        "sleep",
        "disorders-information",
        "physical"
    ],
    "wof:name":"Alive & Well",
    "wof:placetype":"venue"
},
  "geometry": {"coordinates":[-80.00118500000001,37.237313],"type":"Point"}
}