{
  "type": "Feature",
  "properties": {
    "iso:country":"US",
    "sg:address":"1 Holiday Ct",
    "sg:city":"Staunton",
    "sg:classifiers":[
        {
            "category":"Personal",
            "subcategory":"Beauty Salon",
            "type":"Services"
        }
    ],
    "sg:phone":"+1 540 886 0700",
    "sg:postcode":"24401",
    "sg:province":"VA",
    "sg:tags":[
        "shop"
    ],
    "wof:name":"Klassy Kuts",
    "wof:placetype":"venue"
},
  "geometry": {"coordinates":[-79.075203,38.152958],"type":"Point"}
}