{
  "type": "Feature",
  "properties": {
    "addr:full":"708 N Main St Culpeper VA 22701",
    "addr:housenumber":"708",
    "addr:postcode":"22701",
    "addr:street":"N Main St",
    "iso:country":"US",
    "sg:address":"708 N Main St",
    "sg:city":"Culpeper",
    "sg:classifiers":[
        {
            "category":"Retail",
            "subcategory":"Laundry & Dry Cleaning",
            "type":"Services"
        }
    ],
    "sg:phone":"+1 540 825 8421",
    "sg:postcode":"22701",
    "sg:province":"VA",
    "sg:tags":[
        "drycleaning",
        "plant",
        "power",
        "cleaners"
    ],
    "wof:name":"Culpeper Cleaners Inc",
    "wof:placetype":"venue"
},
  "geometry": {"coordinates":[-77.994348,38.478208],"type":"Point"}
}