{
  "type": "Feature",
  "properties": {
    "iso:country":"US",
    "sg:address":"305 Greenway Ln",
    "sg:city":"Richmond",
    "sg:classifiers":[
        {
            "category":"Real Estate",
            "subcategory":"Developer",
            "type":"Services"
        }
    ],
    "sg:phone":"+1 804 288 1506",
    "sg:postcode":"23226",
    "sg:province":"VA",
    "sg:tags":[
        "legal"
    ],
    "wof:name":"David Lowman",
    "wof:placetype":"venue"
},
  "geometry": {"coordinates":[-77.50937999999999,37.572744],"type":"Point"}
}