{
  "type": "Feature",
  "properties": {
    "iso:country":"US",
    "sg:address":"9240 Ashland Woods Ln",
    "sg:city":"Lorton",
    "sg:classifiers":[
        {
            "category":"Professional",
            "subcategory":"Secretarial Services",
            "type":"Services"
        }
    ],
    "sg:phone":"+1 703 994 9904",
    "sg:postcode":"22079",
    "sg:province":"VA",
    "sg:tags":[
        "support",
        "administrative"
    ],
    "wof:name":"Martinez Rozella",
    "wof:placetype":"venue"
},
  "geometry": {"coordinates":[-77.207554,38.708492],"type":"Point"}
}