{
  "type": "Feature",
  "properties": {
    "addr:full":"1624 N 41st St Mc Lean VA 22101",
    "addr:housenumber":"1624",
    "addr:postcode":"22101",
    "addr:street":"N 41St St Mc Lean",
    "iso:country":"US",
    "sg:address":"1624 N 41st St",
    "sg:city":"Mc Lean",
    "sg:classifiers":[
        {
            "category":"Professional",
            "subcategory":"Engineering",
            "type":"Services"
        }
    ],
    "sg:phone":"+1 703 532 2489",
    "sg:postcode":"22101",
    "sg:province":"VA",
    "wof:name":"Birken Jayme",
    "wof:placetype":"venue"
},
  "geometry": {"coordinates":[-77.133804,38.923737],"type":"Point"}
}