{
  "type": "Feature",
  "properties": {
    "addr:full":"3600 Devilwood Ct Fairfax VA 22030",
    "addr:housenumber":"3600",
    "addr:postcode":"22030",
    "addr:street":"Devilwood Ct",
    "iso:country":"US",
    "sg:address":"3600 Devilwood Ct",
    "sg:city":"Fairfax",
    "sg:classifiers":[
        {
            "category":"Professional",
            "subcategory":"Management & Consulting",
            "type":"Services"
        }
    ],
    "sg:phone":"+1 703 385 4334",
    "sg:postcode":"22030",
    "sg:province":"VA",
    "sg:tags":[
        "consultant",
        "business"
    ],
    "wof:name":"Lyceum",
    "wof:placetype":"venue"
},
  "geometry": {"coordinates":[-77.283355,38.859699],"type":"Point"}
}