{
  "type": "Feature",
  "properties": {
    "addr:full":"1429 Flynn Ct Herndon VA 20170",
    "addr:housenumber":"1429",
    "addr:postcode":"20170",
    "addr:street":"Flynn Ct",
    "iso:country":"US",
    "sg:address":"1429 Flynn Ct",
    "sg:city":"Herndon",
    "sg:classifiers":[
        {
            "category":"Real Estate",
            "subcategory":"Real Estate Agent",
            "type":"Services"
        }
    ],
    "sg:phone":"+1 703 444 0603",
    "sg:postcode":"20170",
    "sg:province":"VA",
    "wof:name":"Stowe Justis Inc",
    "wof:placetype":"venue"
},
  "geometry": {"coordinates":[-77.379254,38.996252],"type":"Point"}
}