{
  "type": "Feature",
  "properties": {
    "addr:full":"9034 Mann Dr Mechanicsville VA 23116",
    "addr:housenumber":"9034",
    "addr:postcode":"23116",
    "addr:street":"Mann Dr",
    "iso:country":"US",
    "sg:address":"9034 Mann Dr",
    "sg:city":"Mechanicsville",
    "sg:classifiers":[
        {
            "category":"Professional",
            "subcategory":"Business Services",
            "type":"Services"
        }
    ],
    "sg:phone":"+1 804 730 2084",
    "sg:postcode":"23116",
    "sg:province":"VA",
    "wof:name":"Aid Assoc For Lutherans",
    "wof:placetype":"venue"
},
  "geometry": {"coordinates":[-77.383206,37.644788],"type":"Point"}
}