{
  "type": "Feature",
  "properties": {
    "addr:full":"3302 Peace Valley Ln Falls Church VA 22044",
    "addr:housenumber":"3302",
    "addr:postcode":"22044",
    "addr:street":"Peace Valley Ln",
    "iso:country":"US",
    "sg:address":"3302 Peace Valley Ln",
    "sg:city":"Falls Church",
    "sg:classifiers":[
        {
            "category":"Real Estate",
            "subcategory":"Real Estate Operator",
            "type":"Services"
        }
    ],
    "sg:phone":"+1 703 856 4019",
    "sg:postcode":"22044",
    "sg:province":"VA",
    "sg:tags":[
        "building",
        "nonresidential"
    ],
    "wof:name":"Premier Properties LLC",
    "wof:placetype":"venue"
},
  "geometry": {"coordinates":[-77.151259,38.857475],"type":"Point"}
}