{
  "type": "Feature",
  "properties": {
    "iso:country":"US",
    "sg:address":"225 E Shirley Ave",
    "sg:city":"Warrenton",
    "sg:classifiers":[
        {
            "category":"Retail",
            "subcategory":"Auto Repair",
            "type":"Services"
        }
    ],
    "sg:phone":"+1 540 347 7090",
    "sg:postcode":"20186",
    "sg:province":"VA",
    "sg:tags":[
        "glass",
        "replacement"
    ],
    "wof:name":"Cherrydale-Harmon Autoglass",
    "wof:placetype":"venue"
},
  "geometry": {"coordinates":[-77.793395,38.704966],"type":"Point"}
}