{
  "type": "Feature",
  "properties": {
    "iso:country":"US",
    "sg:address":"2021 Germander Way",
    "sg:city":"Woodbridge",
    "sg:classifiers":[
        {
            "category":"Freight",
            "type":"Transportation"
        }
    ],
    "sg:phone":"+1 703 926 0903",
    "sg:postcode":"22192",
    "sg:province":"VA",
    "sg:tags":[
        "operator",
        "local",
        "trucking"
    ],
    "wof:name":"J B Trucking",
    "wof:placetype":"venue"
},
  "geometry": {"coordinates":[-77.274697,38.670985],"type":"Point"}
}