{
  "type": "Feature",
  "properties": {
    "iso:country":"US",
    "sg:address":"1241 Settlersway Ln",
    "sg:city":"Goode",
    "sg:classifiers":[
        {
            "category":"Communications",
            "type":"Services"
        }
    ],
    "sg:phone":"+1 540 586 3287",
    "sg:postcode":"24556",
    "sg:province":"VA",
    "wof:name":"Mayhew's Radio Svc",
    "wof:placetype":"venue"
},
  "geometry": {"coordinates":[-79.42593599999999,37.365285],"type":"Point"}
}