{
  "type": "Feature",
  "properties": {
    "iso:country":"US",
    "sg:address":"304 Albemarle Dr",
    "sg:city":"Chesapeake",
    "sg:classifiers":[
        {
            "category":"Utilities",
            "subcategory":"Water",
            "type":"Services"
        },
        {
            "category":"Utilities",
            "type":"Services"
        },
        {
            "category":"Government",
            "subcategory":"Office",
            "type":"Public Place"
        }
    ],
    "sg:phone":"+1 757 382 8967",
    "sg:postcode":"23322",
    "sg:province":"VA",
    "sg:tags":[
        "consultant",
        "township",
        "management",
        "government-city",
        "village"
    ],
    "wof:name":"Public Information Officer",
    "wof:placetype":"venue"
},
  "geometry": {"coordinates":[-76.24708200000001,36.717336],"type":"Point"}
}