{
  "type": "Feature",
  "properties": {
    "iso:country":"US",
    "sg:address":"3300 Mayflower Dr",
    "sg:city":"Lynchburg",
    "sg:classifiers":[
        {
            "category":"Wholesale",
            "subcategory":"Electrical",
            "type":"Manufacturing & Wholesale Goods"
        }
    ],
    "sg:phone":"+1 434 847 0014",
    "sg:postcode":"24501",
    "sg:province":"VA",
    "sg:tags":[
        "battery"
    ],
    "wof:name":"Hall Battery & Auto Repair",
    "wof:placetype":"venue"
},
  "geometry": {"coordinates":[-79.159953,37.380503],"type":"Point"}
}