{
  "type": "Feature",
  "properties": {
    "iso:country":"US",
    "sg:address":"10909 Granada Rd",
    "sg:city":"Richmond",
    "sg:classifiers":[
        {
            "category":"Building & Trades",
            "subcategory":"Cleaning & Sanitation",
            "type":"Services"
        }
    ],
    "sg:phone":"+1 804 320 1982",
    "sg:postcode":"23235",
    "sg:province":"VA",
    "sg:tags":[
        "maintenance"
    ],
    "wof:name":"Clean UPS Janitorial Services",
    "wof:placetype":"venue"
},
  "geometry": {"coordinates":[-77.59649899999999,37.51775],"type":"Point"}
}