{
  "type": "Feature",
  "properties": {
    "addr:full":"5303 Montgomery St Springfield VA 22151",
    "addr:housenumber":"5303",
    "addr:postcode":"22151",
    "addr:street":"Montgomery St",
    "iso:country":"US",
    "sg:address":"5303 Montgomery St",
    "sg:city":"Springfield",
    "sg:classifiers":[
        {
            "category":"Personal",
            "subcategory":"Shoe Repair & Shine",
            "type":"Services"
        }
    ],
    "sg:phone":"+1 703 354 1209",
    "sg:postcode":"22151",
    "sg:province":"VA",
    "sg:tags":[
        "parlor"
    ],
    "wof:name":"Van Dorn Shoe Repair",
    "wof:placetype":"venue"
},
  "geometry": {"coordinates":[-77.175962,38.806511],"type":"Point"}
}