{
  "type": "Feature",
  "properties": {
    "addr:full":"45910 Old Ox Rd Sterling VA 20166",
    "addr:housenumber":"45910",
    "addr:postcode":"20166",
    "addr:street":"Old Ox Rd",
    "iso:country":"US",
    "sg:address":"45910 Old Ox Rd",
    "sg:city":"Sterling",
    "sg:classifiers":[
        {
            "category":"Wholesale",
            "subcategory":"Medical Equipment & Supplies",
            "type":"Manufacturing & Wholesale Goods"
        }
    ],
    "sg:phone":"+1 703 471 4282",
    "sg:postcode":"20166",
    "sg:province":"VA",
    "sg:tags":[
        "hospital"
    ],
    "wof:name":"Burger's Cabinet Shop",
    "wof:placetype":"venue"
},
  "geometry": {"coordinates":[-77.426958,38.979197],"type":"Point"}
}