{
  "type": "Feature",
  "properties": {
    "addr:full":"1905 Holland Rd Suffolk VA 23434",
    "addr:housenumber":"1905",
    "addr:postcode":"23434",
    "addr:street":"Holland Rd",
    "iso:country":"US",
    "sg:address":"1905 Holland Rd",
    "sg:city":"Suffolk",
    "sg:classifiers":[
        {
            "category":"Autos & Motor Vehicles",
            "subcategory":"Automobile Sales",
            "type":"Retail Goods"
        }
    ],
    "sg:phone":"+1 757 923 4400",
    "sg:postcode":"23434",
    "sg:province":"VA",
    "sg:tags":[
        "used"
    ],
    "wof:name":"Key It Up Auto Sales",
    "wof:placetype":"venue"
},
  "geometry": {"coordinates":[-76.655081,36.718579],"type":"Point"}
}