{
  "type": "Feature",
  "properties": {
    "addr:full":"10052 Portsmouth Rd Manassas VA 20109",
    "addr:housenumber":"10052",
    "addr:postcode":"20109",
    "addr:street":"Portsmouth Rd",
    "iso:country":"US",
    "sg:address":"10052 Portsmouth Rd",
    "sg:city":"Manassas",
    "sg:classifiers":[
        {
            "category":"Real Estate",
            "subcategory":"Real Estate Operator",
            "type":"Services"
        }
    ],
    "sg:phone":"+1 703 257 1260",
    "sg:postcode":"20109",
    "sg:province":"VA",
    "sg:tags":[
        "apartment"
    ],
    "wof:name":"Westgate Apartments",
    "wof:placetype":"venue"
},
  "geometry": {"coordinates":[-77.499791,38.781901],"type":"Point"}
}