{
  "type": "Feature",
  "properties": {
    "addr:full":"14101 Parke Long Ct Chantilly VA 20151",
    "addr:housenumber":"14101",
    "addr:postcode":"20151",
    "addr:street":"Parke Long Ct",
    "iso:country":"US",
    "sg:address":"14101 Parke Long Ct",
    "sg:city":"Chantilly",
    "sg:classifiers":[
        {
            "category":"Building & Trades",
            "subcategory":"Construction",
            "type":"Services"
        }
    ],
    "sg:phone":"+1 703 817 1661",
    "sg:postcode":"20151",
    "sg:province":"VA",
    "sg:tags":[
        "general",
        "contractor"
    ],
    "wof:name":"Velasquez Contractors",
    "wof:placetype":"venue"
},
  "geometry": {"coordinates":[-77.43689500000001,38.892238],"type":"Point"}
}