{
  "type": "Feature",
  "properties": {
    "addr:full":"13762 Penwith Ct Chantilly VA 20151",
    "addr:postcode":"13762;20151",
    "addr:street":"Penwith Ct",
    "iso:country":"US",
    "sg:address":"13762 Penwith Ct",
    "sg:city":"Chantilly",
    "sg:classifiers":[
        {
            "category":"Autos & Motor Vehicles",
            "subcategory":"Automobile Sales",
            "type":"Retail Goods"
        },
        {
            "category":"Personal",
            "type":"Services"
        },
        {
            "category":"Retail",
            "subcategory":"Storage",
            "type":"Services"
        },
        {
            "category":"Retail",
            "subcategory":"Auto Repair",
            "type":"Services"
        },
        {
            "category":"Utilities",
            "type":"Services"
        }
    ],
    "sg:phone":"+1 571 269 3974",
    "sg:postcode":"20151",
    "sg:province":"VA",
    "sg:tags":[
        "equipment",
        "towing",
        "road",
        "salvage",
        "service-automotive"
    ],
    "sg:website":"http://www.mhtowing.net",
    "wof:name":"M H Towing",
    "wof:placetype":"venue"
},
  "geometry": {"coordinates":[-77.42043700000001,38.885059],"type":"Point"}
}