{
  "type": "Feature",
  "properties": {
    "addr:full":"2560 Sheila Ln Richmond VA 23225",
    "addr:housenumber":"2560",
    "addr:postcode":"23225",
    "addr:street":"Sheila Ln",
    "iso:country":"US",
    "sg:address":"2560 Sheila Ln",
    "sg:city":"Richmond",
    "sg:classifiers":[
        {
            "category":"Retail",
            "subcategory":"Laundry & Dry Cleaning",
            "type":"Services"
        }
    ],
    "sg:phone":"+1 804 272 5975",
    "sg:postcode":"23225",
    "sg:province":"VA",
    "sg:tags":[
        "cleaners"
    ],
    "wof:name":"Puritan Cleaners",
    "wof:placetype":"venue"
},
  "geometry": {"coordinates":[-77.53294,37.536054],"type":"Point"}
}