{
  "type": "Feature",
  "properties": {
    "addr:full":"8391 Arabian Ln Catawba VA 24070",
    "addr:housenumber":"8391",
    "addr:postcode":"24070",
    "addr:street":"Arabian Ln",
    "iso:country":"US",
    "sg:address":"8391 Arabian Ln",
    "sg:city":"Catawba",
    "sg:classifiers":[
        {
            "category":"Professional",
            "subcategory":"Secretarial Services",
            "type":"Services"
        }
    ],
    "sg:phone":"+1 540 384 6365",
    "sg:postcode":"24070",
    "sg:province":"VA",
    "sg:tags":[
        "reporting"
    ],
    "wof:name":"Barrister Court Reporters Inc",
    "wof:placetype":"venue"
},
  "geometry": {"coordinates":[-80.226788,37.343663],"type":"Point"}
}