{
  "type": "Feature",
  "properties": {
    "iso:country":"US",
    "sg:address":"1616 Laskin Rd",
    "sg:city":"Virginia Beach",
    "sg:classifiers":[
        {
            "category":"Shopping",
            "subcategory":"Department Store",
            "type":"Retail Goods"
        }
    ],
    "sg:phone":"+1 757 428 9355",
    "sg:postcode":"23451",
    "sg:province":"VA",
    "wof:name":"Stein Mart",
    "wof:placetype":"venue"
},
  "geometry": {"coordinates":[-76.01824499999999,36.851153],"type":"Point"}
}