{
  "type": "Feature",
  "properties": {
    "addr:full":"103 S Pantops Dr Ste 203 Charlottesville VA 22911",
    "addr:housenumber":"103",
    "addr:postcode":"22911",
    "addr:street":"S Pantops Dr Ste 203",
    "iso:country":"US",
    "sg:address":"103 S Pantops Dr Ste 203",
    "sg:city":"Charlottesville",
    "sg:classifiers":[
        {
            "category":"Wholesale",
            "subcategory":"Computers",
            "type":"Manufacturing & Wholesale Goods"
        }
    ],
    "sg:phone":"+1 434 817 3030",
    "sg:postcode":"22911",
    "sg:province":"VA",
    "wof:name":"Soltech Group",
    "wof:placetype":"venue"
},
  "geometry": {"coordinates":[-78.44789900000001,38.023998],"type":"Point"}
}