{
  "type": "Feature",
  "properties": {
    "addr:full":"8808 Pear Tree Village Ct Alexandria VA 22309",
    "addr:housenumber":"8808",
    "addr:postcode":"22309",
    "addr:street":"Pear Tree Village Ct",
    "iso:country":"US",
    "sg:address":"8808 Pear Tree Village Ct",
    "sg:city":"Alexandria",
    "sg:classifiers":[
        {
            "category":"Real Estate",
            "subcategory":"Architect",
            "type":"Services"
        }
    ],
    "sg:phone":"+1 703 371 8779",
    "sg:postcode":"22309",
    "sg:province":"VA",
    "wof:name":"Kelso & Easter Architects",
    "wof:placetype":"venue"
},
  "geometry": {"coordinates":[-77.12456400000001,38.718669],"type":"Point"}
}