{
  "type": "Feature",
  "properties": {
    "iso:country":"US",
    "sg:address":"408 Rye Hollow Rd",
    "sg:city":"Pearisburg",
    "sg:classifiers":[
        {
            "category":"Building & Trades",
            "subcategory":"Construction",
            "type":"Services"
        }
    ],
    "sg:phone":"+1 540 921 3121",
    "sg:postcode":"24134",
    "sg:province":"VA",
    "sg:tags":[
        "house"
    ],
    "wof:name":"Spiegel Construction",
    "wof:placetype":"venue"
},
  "geometry": {"coordinates":[-80.688607,37.277732],"type":"Point"}
}