{
  "type": "Feature",
  "properties": {
    "addr:full":"8106 Guinevere Dr Annandale VA 22003",
    "addr:housenumber":"8106",
    "addr:postcode":"22003",
    "addr:street":"Guinevere Dr",
    "iso:country":"US",
    "sg:address":"8106 Guinevere Dr",
    "sg:city":"Annandale",
    "sg:classifiers":[
        {
            "category":"Professional",
            "subcategory":"Management & Consulting",
            "type":"Services"
        }
    ],
    "sg:phone":"+1 703 876 0920",
    "sg:postcode":"22003",
    "sg:province":"VA",
    "wof:name":"McMillan Hill & Associates",
    "wof:placetype":"venue"
},
  "geometry": {"coordinates":[-77.22636799999999,38.848773],"type":"Point"}
}