{
  "type": "Feature",
  "properties": {
    "addr:full":"1117 Emmet St N Charlottesville VA 22903",
    "addr:housenumber":"1117",
    "addr:postcode":"22903",
    "addr:street":"Emmet St N",
    "iso:country":"US",
    "sg:address":"1117 Emmet St N",
    "sg:city":"Charlottesville",
    "sg:classifiers":[
        {
            "category":"Shopping",
            "subcategory":"Department Store",
            "type":"Retail Goods"
        }
    ],
    "sg:phone":"+1 434 984 0167",
    "sg:postcode":"22903",
    "sg:province":"VA",
    "sg:website":"www.oldnavy.com",
    "wof:name":"Old Navy",
    "wof:placetype":"venue"
},
  "geometry": {"coordinates":[-78.50009900000001,38.051998],"type":"Point"}
}