{
  "type": "Feature",
  "properties": {
    "addr:full":"4802 Harvest Glen Ct Fredericksburg VA 22408",
    "addr:housenumber":"4802",
    "addr:postcode":"22408",
    "addr:street":"Harvest Glen Ct",
    "iso:country":"US",
    "sg:address":"4802 Harvest Glen Ct",
    "sg:city":"Fredericksburg",
    "sg:classifiers":[
        {
            "category":"Shopping",
            "subcategory":"Hobbies, Toys, & Games",
            "type":"Retail Goods"
        }
    ],
    "sg:phone":"+1 540 898 5557",
    "sg:postcode":"22408",
    "sg:province":"VA",
    "wof:name":"Jintana",
    "wof:placetype":"venue"
},
  "geometry": {"coordinates":[-77.49869200000001,38.277332],"type":"Point"}
}