{
  "type": "Feature",
  "properties": {
    "iso:country":"US",
    "sg:address":"296 N Witchduck Rd",
    "sg:city":"Virginia Beach",
    "sg:classifiers":[
        {
            "category":"Shopping",
            "type":"Retail Goods"
        }
    ],
    "sg:phone":"+1 757 499 0720",
    "sg:postcode":"23462",
    "sg:province":"VA",
    "sg:tags":[
        "theatrical",
        "merchandise"
    ],
    "wof:name":"Dr Bobs Theatricity Inc",
    "wof:placetype":"venue"
},
  "geometry": {"coordinates":[-76.156508,36.845411],"type":"Point"}
}