{
  "type": "Feature",
  "properties": {
    "addr:full":"15784 Stewartsville Rd Vinton VA 24179",
    "addr:postcode":"15784;24179",
    "addr:street":"Stewartsville Rd",
    "iso:country":"US",
    "sg:address":"15784 Stewartsville Rd",
    "sg:city":"Vinton",
    "sg:classifiers":[
        {
            "category":"Building & Trades",
            "subcategory":"Construction",
            "type":"Services"
        }
    ],
    "sg:phone":"+1 540 890 8910",
    "sg:postcode":"24179",
    "sg:province":"VA",
    "sg:tags":[
        "general",
        "contractor"
    ],
    "wof:name":"Emlex Construction Co Inc",
    "wof:placetype":"venue"
},
  "geometry": {"coordinates":[-79.80864,37.271481],"type":"Point"}
}