{
  "type": "Feature",
  "properties": {
    "addr:full":"2301 Mechanicsville Tpke Richmond VA 23223",
    "addr:housenumber":"2301",
    "addr:postcode":"23223",
    "addr:street":"Mechanicsville Tpke",
    "iso:country":"US",
    "sg:address":"2301 Mechanicsville Tpke",
    "sg:city":"Richmond",
    "sg:classifiers":[
        {
            "category":"Food & Beverages",
            "subcategory":"Groceries & Convenience Stores",
            "type":"Retail Goods"
        }
    ],
    "sg:phone":"+1 804 782 9326",
    "sg:postcode":"23223",
    "sg:province":"VA",
    "wof:name":"Fas Stop Henrico Co",
    "wof:placetype":"venue"
},
  "geometry": {"coordinates":[-77.40870700000001,37.557968],"type":"Point"}
}