{
  "type": "Feature",
  "properties": {
    "addr:full":"25501 Frosty Meadow Ln Aldie VA 20105",
    "addr:postcode":"25501;20105",
    "addr:street":"Frosty Meadow Ln",
    "iso:country":"US",
    "sg:address":"25501 Frosty Meadow Ln",
    "sg:city":"Aldie",
    "sg:classifiers":[
        {
            "category":"Building & Trades",
            "subcategory":"Plumbing",
            "type":"Services"
        }
    ],
    "sg:phone":"+1 703 906 1312",
    "sg:postcode":"20105",
    "sg:province":"VA",
    "wof:name":"Bright Side Plumbing",
    "wof:placetype":"venue"
},
  "geometry": {"coordinates":[-77.606475,38.914212],"type":"Point"}
}