{
  "type": "Feature",
  "properties": {
    "addr:full":"975 Hilton Heights Rd Charlottesville VA 22901",
    "addr:housenumber":"975",
    "addr:postcode":"22901",
    "addr:street":"Hilton Heights Rd",
    "iso:country":"US",
    "sg:address":"975 Hilton Heights Rd",
    "sg:city":"Charlottesville",
    "sg:classifiers":[
        {
            "category":"Utilities",
            "subcategory":"Mobile Phone",
            "type":"Services"
        }
    ],
    "sg:phone":"+1 434 973 5022",
    "sg:postcode":"22901",
    "sg:province":"VA",
    "sg:tags":[
        "telephone",
        "cellular"
    ],
    "wof:name":"Alltel Communications",
    "wof:placetype":"venue"
},
  "geometry": {"coordinates":[-78.46579199999999,38.097995],"type":"Point"}
}