{
  "type": "Feature",
  "properties": {
    "addr:full":"19590 Virgil H Goode Hwy Rocky Mount VA 24151",
    "addr:housenumber":"19590;h",
    "addr:postcode":"24151",
    "addr:street":"Virgil;Goode Hwy",
    "iso:country":"US",
    "sg:address":"19590 Virgil H Goode Hwy",
    "sg:city":"Rocky Mount",
    "sg:classifiers":[
        {
            "category":"Autos & Motor Vehicles",
            "subcategory":"Automobile Sales",
            "type":"Retail Goods"
        }
    ],
    "sg:phone":"+1 540 482 0324",
    "sg:postcode":"24151",
    "sg:province":"VA",
    "sg:tags":[
        "car",
        "dealer"
    ],
    "wof:name":"Lake Country Motors",
    "wof:placetype":"venue"
},
  "geometry": {"coordinates":[-79.883448,37.056933],"type":"Point"}
}