{
  "type": "Feature",
  "properties": {
    "addr:full":"11911 Freedom Dr Reston VA 20190",
    "addr:housenumber":"11911",
    "addr:postcode":"20190",
    "addr:street":"Freedom Dr",
    "iso:country":"US",
    "sg:address":"11911 Freedom Dr",
    "sg:city":"Reston",
    "sg:classifiers":[
        {
            "category":"Professional",
            "subcategory":"Computer Services",
            "type":"Services"
        }
    ],
    "sg:phone":"+1 703 467 9010",
    "sg:postcode":"20190",
    "sg:province":"VA",
    "sg:tags":[
        "prepackaged",
        "software"
    ],
    "wof:name":"Telelogic North America Inc",
    "wof:placetype":"venue"
},
  "geometry": {"coordinates":[-77.355525,38.959217],"type":"Point"}
}