{
  "type": "Feature",
  "properties": {
    "addr:full":"2545 Lee Hwy Troutville VA 24175",
    "addr:housenumber":"2545",
    "addr:postcode":"24175",
    "addr:street":"Lee Hwy",
    "iso:country":"US",
    "sg:address":"2545 Lee Hwy",
    "sg:city":"Troutville",
    "sg:classifiers":[
        {
            "category":"Travel",
            "subcategory":"Hotels & Motels",
            "type":"Entertainment"
        }
    ],
    "sg:phone":"+1 540 992 5600",
    "sg:postcode":"24175",
    "sg:province":"VA",
    "sg:website":"www.choicehotels.com",
    "wof:name":"Comfort Inn",
    "wof:placetype":"venue"
},
  "geometry": {"coordinates":[-79.902891,37.381493],"type":"Point"}
}