{
  "type": "Feature",
  "properties": {
    "addr:full":"18116 Triangle Shopping Plz Dumfries VA 22026",
    "addr:housenumber":"18116",
    "addr:postcode":"22026",
    "addr:street":"Triangle Shopping Plz",
    "iso:country":"US",
    "sg:address":"18116 Triangle Shopping Plz",
    "sg:city":"Dumfries",
    "sg:classifiers":[
        {
            "category":"Banks & Credit Unions",
            "subcategory":"Bank",
            "type":"Services"
        }
    ],
    "sg:phone":"+1 703 221 2136",
    "sg:postcode":"22026",
    "sg:province":"VA",
    "sg:tags":[
        "national",
        "commercial"
    ],
    "wof:name":"One Valley Bank",
    "wof:placetype":"venue"
},
  "geometry": {"coordinates":[-77.33210200000001,38.559869],"type":"Point"}
}