{
  "type": "Feature",
  "properties": {
    "iso:country":"US",
    "sg:address":"2793 Jefferson Davis Hwy",
    "sg:city":"Arlington",
    "sg:classifiers":[
        {
            "category":"Building & Trades",
            "subcategory":"Locksmith",
            "type":"Services"
        }
    ],
    "sg:phone":"+1 202 621 2164",
    "sg:postcode":"22202",
    "sg:province":"VA",
    "sg:tags":[
        "key"
    ],
    "wof:name":"Deffinate Locksmith",
    "wof:placetype":"venue"
},
  "geometry": {"coordinates":[-77.051931,38.84885],"type":"Point"}
}