{
  "type": "Feature",
  "properties": {
    "addr:full":"4936 Rowe Ridge Rd NW Roanoke VA 24017",
    "addr:housenumber":"4936",
    "addr:postcode":"24017",
    "addr:street":"Rowe Ridge Rd Nw",
    "iso:country":"US",
    "sg:address":"4936 Rowe Ridge Rd NW",
    "sg:city":"Roanoke",
    "sg:classifiers":[
        {
            "category":"Professional",
            "subcategory":"Art Services",
            "type":"Services"
        }
    ],
    "sg:phone":"+1 540 342 5920",
    "sg:postcode":"24017",
    "sg:province":"VA",
    "sg:tags":[
        "photographer"
    ],
    "wof:name":"Mobile Photo",
    "wof:placetype":"venue"
},
  "geometry": {"coordinates":[-80.01851499999999,37.288755],"type":"Point"}
}