{
  "type": "Feature",
  "properties": {
    "addr:full":"2446 Shenandoah Ave NW Roanoke VA 24017",
    "addr:housenumber":"2446",
    "addr:postcode":"24017",
    "addr:street":"Shenandoah Ave Nw",
    "iso:country":"US",
    "sg:address":"2446 Shenandoah Ave NW",
    "sg:city":"Roanoke",
    "sg:classifiers":[
        {
            "category":"Restaurant",
            "type":"Food & Drink"
        }
    ],
    "sg:phone":"+1 540 556 8611",
    "sg:postcode":"24017",
    "sg:province":"VA",
    "sg:tags":[
        "eating"
    ],
    "wof:name":"Katrinas Place",
    "wof:placetype":"venue"
},
  "geometry": {"coordinates":[-79.978858,37.282452],"type":"Point"}
}