{
  "type": "Feature",
  "properties": {
    "addr:full":"406 Winterham Dr Abingdon VA 24211",
    "addr:housenumber":"406",
    "addr:postcode":"24211",
    "addr:street":"Winterham Dr",
    "iso:country":"US",
    "sg:address":"406 Winterham Dr",
    "sg:city":"Abingdon",
    "sg:classifiers":[
        {
            "category":"Professional",
            "subcategory":"Management & Consulting",
            "type":"Services"
        }
    ],
    "sg:phone":"+1 276 676 2112",
    "sg:postcode":"24211",
    "sg:province":"VA",
    "sg:tags":[
        "business"
    ],
    "wof:name":"Edwards Ventures LLC",
    "wof:placetype":"venue"
},
  "geometry": {"coordinates":[-81.95825000000001,36.697934],"type":"Point"}
}