{
  "type": "Feature",
  "properties": {
    "addr:full":"3110 Bethany Rd Boones Mill VA 24067",
    "addr:housenumber":"3110",
    "addr:postcode":"24067",
    "addr:street":"Bethany Rd Boones",
    "iso:country":"US",
    "sg:address":"3110 Bethany Rd",
    "sg:city":"Boones Mill",
    "sg:classifiers":[
        {
            "category":"Retail",
            "subcategory":"Auto Repair",
            "type":"Services"
        }
    ],
    "sg:phone":"+1 540 483 0172",
    "sg:postcode":"24067",
    "sg:province":"VA",
    "sg:tags":[
        "automotive"
    ],
    "wof:name":"Custer Gene Front",
    "wof:placetype":"venue"
},
  "geometry": {"coordinates":[-80.052733,37.053341],"type":"Point"}
}