{
  "type": "Feature",
  "properties": {
    "iso:country":"US",
    "sg:address":"510 Babbtown Rd",
    "sg:city":"Suffolk",
    "sg:classifiers":[
        {
            "category":"Professional",
            "subcategory":"Art Services",
            "type":"Services"
        }
    ],
    "sg:phone":"+1 757 539 3932",
    "sg:postcode":"23434",
    "sg:province":"VA",
    "sg:tags":[
        "photography",
        "commercial"
    ],
    "wof:name":"Photography By Laura Inc",
    "wof:placetype":"venue"
},
  "geometry": {"coordinates":[-76.624397,36.641556],"type":"Point"}
}