{
  "type": "Feature",
  "properties": {
    "addr:full":"660 Phoenix Dr Virginia Beach VA 23452",
    "addr:housenumber":"660",
    "addr:postcode":"23452",
    "addr:street":"Phoenix Dr",
    "iso:country":"US",
    "sg:address":"660 Phoenix Dr",
    "sg:city":"Virginia Beach",
    "sg:classifiers":[
        {
            "category":"Restaurant",
            "type":"Food & Drink"
        }
    ],
    "sg:menulink":"http://www.allmenus.com/va/virginia-beach/152038-baja-fresh-mexican-grill/menu/",
    "sg:phone":"+1 757 431 1211",
    "sg:postcode":"23452",
    "sg:province":"VA",
    "sg:tags":[
        "mexican"
    ],
    "wof:name":"Baja Fresh Mexican Grill",
    "wof:placetype":"venue"
},
  "geometry": {"coordinates":[-76.06852499999999,36.824388],"type":"Point"}
}