{
  "type": "Feature",
  "properties": {
    "addr:full":"6352 Edward St Norfolk VA 23513",
    "addr:housenumber":"6352",
    "addr:postcode":"23513",
    "addr:street":"Edward St",
    "iso:country":"US",
    "sg:address":"6352 Edward St",
    "sg:city":"Norfolk",
    "sg:classifiers":[
        {
            "category":"Wholesale",
            "subcategory":"Stationery",
            "type":"Manufacturing & Wholesale Goods"
        }
    ],
    "sg:phone":"+1 757 853 8841",
    "sg:postcode":"23513",
    "sg:province":"VA",
    "sg:tags":[
        "paper"
    ],
    "wof:name":"Ocean Shipping Services",
    "wof:placetype":"venue"
},
  "geometry": {"coordinates":[-76.23165899999999,36.896919],"type":"Point"}
}