{
  "type": "Feature",
  "properties": {
    "iso:country":"US",
    "sg:address":"1700 N Mallory St",
    "sg:city":"Hampton",
    "sg:classifiers":[
        {
            "category":"Travel",
            "subcategory":"Hotels & Motels",
            "type":"Entertainment"
        }
    ],
    "sg:phone":"+1 757 851 8551",
    "sg:postcode":"23664",
    "sg:province":"VA",
    "sg:tags":[
        "operation"
    ],
    "wof:name":"Golden Sands Motel",
    "wof:placetype":"venue"
},
  "geometry": {"coordinates":[-76.29585899999999,37.039186],"type":"Point"}
}