{
  "type": "Feature",
  "properties": {
    "addr:full":"1824 University Cir Charlottesville VA 22903",
    "addr:housenumber":"1824",
    "addr:postcode":"22903",
    "addr:street":"University Cir",
    "iso:country":"US",
    "sg:address":"1824 University Cir",
    "sg:city":"Charlottesville",
    "sg:classifiers":[
        {
            "category":"Organizations",
            "subcategory":"Religious Organization",
            "type":"Services"
        }
    ],
    "sg:phone":"+1 434 970 7836",
    "sg:postcode":"22903",
    "sg:province":"VA",
    "wof:name":"Gesher",
    "wof:placetype":"venue"
},
  "geometry": {"coordinates":[-78.503518,38.043488],"type":"Point"}
}