{
  "type": "Feature",
  "properties": {
    "iso:country":"US",
    "sg:address":"3813 4th St N",
    "sg:city":"Arlington",
    "sg:classifiers":[
        {
            "category":"Farming",
            "subcategory":"Livestock Farm",
            "type":"Manufacturing & Wholesale Goods"
        }
    ],
    "sg:phone":"+1 703 243 5787",
    "sg:postcode":"22203",
    "sg:province":"VA",
    "sg:tags":[
        "specialty",
        "animal"
    ],
    "wof:name":"Sarajen Maine Coon Cats",
    "wof:placetype":"venue"
},
  "geometry": {"coordinates":[-77.10413200000001,38.876012],"type":"Point"}
}