{
  "type": "Feature",
  "properties": {
    "iso:country":"US",
    "sg:address":"262 Broadview Ave",
    "sg:city":"Warrenton",
    "sg:classifiers":[
        {
            "category":"Personal",
            "subcategory":"Beauty Salon",
            "type":"Services"
        }
    ],
    "sg:phone":"+1 540 349 3241",
    "sg:postcode":"20186",
    "sg:province":"VA",
    "wof:name":"Warrenton Plaza Hair Designs",
    "wof:placetype":"venue"
},
  "geometry": {"coordinates":[-77.80544500000001,38.72247],"type":"Point"}
}