{
  "type": "Feature",
  "properties": {
    "iso:country":"US",
    "sg:address":"4572 Virginia Beach Blvd",
    "sg:city":"Virginia Beach",
    "sg:classifiers":[
        {
            "category":"Restaurant",
            "type":"Food & Drink"
        }
    ],
    "sg:phone":"+1 757 499 7360",
    "sg:postcode":"23462",
    "sg:province":"VA",
    "sg:tags":[
        "eating"
    ],
    "sg:website":"www.whitehorsepub.com",
    "wof:name":"White Horse Pub",
    "wof:placetype":"venue"
},
  "geometry": {"coordinates":[-76.134181,36.843708],"type":"Point"}
}