{
  "type": "Feature",
  "properties": {
    "addr:full":"6104 Gardenia Ct Alexandria VA 22310",
    "addr:housenumber":"6104",
    "addr:postcode":"22310",
    "addr:street":"Gardenia Ct",
    "iso:country":"US",
    "sg:address":"6104 Gardenia Ct",
    "sg:city":"Alexandria",
    "sg:classifiers":[
        {
            "category":"Restaurant",
            "type":"Food & Drink"
        }
    ],
    "sg:phone":"+1 703 313 0704",
    "sg:postcode":"22310",
    "sg:province":"VA",
    "wof:name":"Chips Blue",
    "wof:placetype":"venue"
},
  "geometry": {"coordinates":[-77.13787000000001,38.785973],"type":"Point"}
}