{
  "type": "Feature",
  "properties": {
    "iso:country":"US",
    "sg:address":"44073 Saxony Ter",
    "sg:city":"Ashburn",
    "sg:classifiers":[
        {
            "category":"Health Services",
            "subcategory":"Health Practitioner",
            "type":"Services"
        }
    ],
    "sg:phone":"+1 703 723 9988",
    "sg:postcode":"20147",
    "sg:province":"VA",
    "wof:name":"Lisa Zoppetti PHD",
    "wof:placetype":"venue"
},
  "geometry": {"coordinates":[-77.476071,39.028127],"type":"Point"}
}