{
  "type": "Feature",
  "properties": {
    "addr:full":"11940 Rothbury Dr Richmond VA 23236",
    "addr:housenumber":"11940",
    "addr:postcode":"23236",
    "addr:street":"Rothbury Dr",
    "iso:country":"US",
    "sg:address":"11940 Rothbury Dr",
    "sg:city":"Richmond",
    "sg:classifiers":[
        {
            "category":"Professional",
            "subcategory":"Lawyer & Legal Services",
            "type":"Services"
        }
    ],
    "sg:phone":"+1 804 794 6847",
    "sg:postcode":"23236",
    "sg:province":"VA",
    "sg:tags":[
        "attorney",
        "practice"
    ],
    "wof:name":"L Neil Steverson Lwyr Res",
    "wof:placetype":"venue"
},
  "geometry": {"coordinates":[-77.622033,37.49747],"type":"Point"}
}