{
  "type": "Feature",
  "properties": {
    "addr:full":"5715 Richmond Rd Williamsburg VA 23188",
    "addr:housenumber":"5715",
    "addr:postcode":"23188",
    "addr:street":"Richmond Rd",
    "iso:country":"US",
    "sg:address":"5715 Richmond Rd",
    "sg:city":"Williamsburg",
    "sg:classifiers":[
        {
            "category":"Shopping",
            "type":"Retail Goods"
        }
    ],
    "sg:phone":"+1 757 564 8888",
    "sg:postcode":"23188",
    "sg:province":"VA",
    "sg:tags":[
        "factory",
        "outlet"
    ],
    "wof:name":"Tommy Hilfiger USA Inc",
    "wof:placetype":"venue"
},
  "geometry": {"coordinates":[-76.736397,37.321537],"type":"Point"}
}