{
  "type": "Feature",
  "properties": {
    "iso:country":"US",
    "sg:address":"801 Butler St",
    "sg:city":"Chesapeake",
    "sg:classifiers":[
        {
            "category":"Building & Trades",
            "subcategory":"Plumbing",
            "type":"Services"
        }
    ],
    "sg:phone":"+1 757 485 7425",
    "sg:postcode":"23323",
    "sg:province":"VA",
    "sg:tags":[
        "conditioning",
        "air",
        "system",
        "contractor"
    ],
    "wof:name":"Rick's Heating & A/C Inc",
    "wof:placetype":"venue"
},
  "geometry": {"coordinates":[-76.339652,36.772148],"type":"Point"}
}