{
  "type": "Feature",
  "properties": {
    "addr:full":"938 Francis Rd Glen Allen VA 23059",
    "addr:housenumber":"938",
    "addr:postcode":"23059",
    "addr:street":"Francis Rd",
    "iso:country":"US",
    "sg:address":"938 Francis Rd",
    "sg:city":"Glen Allen",
    "sg:classifiers":[
        {
            "category":"Building & Trades",
            "subcategory":"Landscaping Services",
            "type":"Services"
        }
    ],
    "sg:phone":"+1 804 264 0678",
    "sg:postcode":"23059",
    "sg:province":"VA",
    "sg:tags":[
        "landscape",
        "contractor"
    ],
    "wof:name":"Source One Grounds Maintenance",
    "wof:placetype":"venue"
},
  "geometry": {"coordinates":[-77.459817,37.662854],"type":"Point"}
}