{
  "type": "Feature",
  "properties": {
    "addr:full":"2428 Sunset Dr Chesapeake VA 23323",
    "addr:housenumber":"2428",
    "addr:postcode":"23323",
    "addr:street":"Sunset Dr",
    "iso:country":"US",
    "sg:address":"2428 Sunset Dr",
    "sg:city":"Chesapeake",
    "sg:classifiers":[
        {
            "category":"Building & Trades",
            "subcategory":"Plumbing",
            "type":"Services"
        }
    ],
    "sg:phone":"+1 757 487 0515",
    "sg:postcode":"23323",
    "sg:province":"VA",
    "sg:tags":[
        "conditioning",
        "air",
        "system",
        "contractor"
    ],
    "wof:name":"Posey's Heating & Air Cond",
    "wof:placetype":"venue"
},
  "geometry": {"coordinates":[-76.334937,36.7759],"type":"Point"}
}