{
  "type": "Feature",
  "properties": {
    "addr:full":"149 Chestnut Grove Rd Mouth Of Wilson VA 24363",
    "addr:housenumber":"149",
    "addr:postcode":"24363",
    "addr:street":"Chestnut Grove Rd",
    "iso:country":"US",
    "sg:address":"149 Chestnut Grove Rd",
    "sg:city":"Mouth Of Wilson",
    "sg:classifiers":[
        {
            "category":"Building & Trades",
            "subcategory":"Construction",
            "type":"Services"
        }
    ],
    "sg:phone":"+1 276 579 2114",
    "sg:postcode":"24363",
    "sg:province":"VA",
    "sg:tags":[
        "welding",
        "contractor"
    ],
    "wof:name":"H Welding",
    "wof:placetype":"venue"
},
  "geometry": {"coordinates":[-81.38071600000001,36.625361],"type":"Point"}
}