{
  "type": "Feature",
  "properties": {
    "addr:full":"305 S Washington St Alexandria VA 22314",
    "addr:housenumber":"305",
    "addr:postcode":"22314",
    "addr:street":"S Washington St",
    "iso:country":"US",
    "sg:address":"305 S Washington St",
    "sg:city":"Alexandria",
    "sg:classifiers":[
        {
            "category":"Retail",
            "subcategory":"Repair Shop",
            "type":"Services"
        }
    ],
    "sg:phone":"+1 703 842 5900",
    "sg:postcode":"22314",
    "sg:province":"VA",
    "sg:tags":[
        "lock",
        "locksmith"
    ],
    "wof:name":"1 All Day Emergency",
    "wof:placetype":"venue"
},
  "geometry": {"coordinates":[-77.047775,38.801694],"type":"Point"}
}