{
  "type": "Feature",
  "properties": {
    "addr:full":"3594 Griffin St Portsmouth VA 23707",
    "addr:housenumber":"3594",
    "addr:postcode":"23707",
    "addr:street":"Griffin St",
    "iso:country":"US",
    "sg:address":"3594 Griffin St",
    "sg:city":"Portsmouth",
    "sg:classifiers":[
        {
            "category":"Retail",
            "subcategory":"Repair Shop",
            "type":"Services"
        }
    ],
    "sg:phone":"+1 757 397 1983",
    "sg:postcode":"23707",
    "sg:province":"VA",
    "sg:tags":[
        "television"
    ],
    "wof:name":"Davis TV Inc",
    "wof:placetype":"venue"
},
  "geometry": {"coordinates":[-76.344928,36.829027],"type":"Point"}
}