{
  "type": "Feature",
  "properties": {
    "addr:full":"1719 Birch Trail Cir Chesapeake VA 23320",
    "addr:housenumber":"1719",
    "addr:postcode":"23320",
    "addr:street":"Birch Trail Cir",
    "iso:country":"US",
    "sg:address":"1719 Birch Trail Cir",
    "sg:city":"Chesapeake",
    "sg:classifiers":[
        {
            "category":"Railroad",
            "type":"Transportation"
        }
    ],
    "sg:phone":"+1 757 420 2950",
    "sg:postcode":"23320",
    "sg:province":"VA",
    "wof:name":"Norfolk Ventures Inc",
    "wof:placetype":"venue"
},
  "geometry": {"coordinates":[-76.22345300000001,36.787583],"type":"Point"}
}