{
  "type": "Feature",
  "properties": {
    "addr:full":"4834 Lee Hwy Arlington VA 22207",
    "addr:housenumber":"4834",
    "addr:postcode":"22207",
    "addr:street":"Lee Hwy",
    "iso:country":"US",
    "sg:address":"4834 Lee Hwy",
    "sg:city":"Arlington",
    "sg:classifiers":[
        {
            "category":"Restaurant",
            "type":"Food & Drink"
        }
    ],
    "sg:menulink":"http://www.allmenus.com/va/arlington/188069-mcdonalds/menu/",
    "sg:phone":"+1 703 525 3225",
    "sg:postcode":"22207",
    "sg:province":"VA",
    "sg:tags":[
        "burger",
        "american"
    ],
    "wof:name":"McDonald's",
    "wof:placetype":"venue"
},
  "geometry": {"coordinates":[-77.126446,38.896527],"type":"Point"}
}