{
  "type": "Feature",
  "properties": {
    "addr:full":"1516 W Main St Salem VA 24153",
    "addr:housenumber":"1516",
    "addr:postcode":"24153",
    "addr:street":"W Main St",
    "iso:country":"US",
    "sg:address":"1516 W Main St",
    "sg:city":"Salem",
    "sg:classifiers":[
        {
            "category":"Retail",
            "subcategory":"Car Wash",
            "type":"Services"
        },
        {
            "category":"Retail",
            "subcategory":"Auto Repair",
            "type":"Services"
        }
    ],
    "sg:phone":"+1 540 375 2153",
    "sg:postcode":"24153",
    "sg:province":"VA",
    "sg:tags":[
        "body",
        "repairing",
        "automobile",
        "detailing",
        "dent",
        "removal",
        "painting"
    ],
    "sg:website":"http://www.certifiedcollisionrepair.com",
    "wof:name":"Certified Collision Repair",
    "wof:placetype":"venue"
},
  "geometry": {"coordinates":[-80.183525,37.239134],"type":"Point"}
}