{
  "type": "Feature",
  "properties": {
    "addr:full":"16096 Fancy Gap Hwy Cana VA 24317",
    "addr:housenumber":"16096",
    "addr:postcode":"24317",
    "addr:street":"Fancy Gap Hwy Cana",
    "iso:country":"US",
    "sg:address":"16096 Fancy Gap Hwy",
    "sg:city":"Cana",
    "sg:classifiers":[
        {
            "category":"Personal",
            "subcategory":"Beauty Salon",
            "type":"Services"
        }
    ],
    "sg:phone":"+1 276 755 4000",
    "sg:postcode":"24317",
    "sg:province":"VA",
    "sg:tags":[
        "school"
    ],
    "wof:name":"Cana Virginia Beauty School",
    "wof:placetype":"venue"
},
  "geometry": {"coordinates":[-80.655722,36.570577],"type":"Point"}
}