{
  "type": "Feature",
  "properties": {
    "addr:full":"912 Stoneleigh Rd Chesapeake VA 23322",
    "addr:housenumber":"912",
    "addr:postcode":"23322",
    "addr:street":"Stoneleigh Rd",
    "iso:country":"US",
    "sg:address":"912 Stoneleigh Rd",
    "sg:city":"Chesapeake",
    "sg:classifiers":[
        {
            "category":"Manufacturing",
            "subcategory":"Metals",
            "type":"Manufacturing & Wholesale Goods"
        }
    ],
    "sg:phone":"+1 757 482 9292",
    "sg:postcode":"23322",
    "sg:province":"VA",
    "wof:name":"Metal Industries",
    "wof:placetype":"venue"
},
  "geometry": {"coordinates":[-76.192109,36.685428],"type":"Point"}
}