{
  "type": "Feature",
  "properties": {
    "addr:full":"5513 Vine St Alexandria VA 22310",
    "addr:housenumber":"5513",
    "addr:postcode":"22310",
    "addr:street":"Vine St",
    "iso:country":"US",
    "sg:address":"5513 Vine St",
    "sg:city":"Alexandria",
    "sg:classifiers":[
        {
            "category":"Building & Trades",
            "subcategory":"Construction",
            "type":"Services"
        }
    ],
    "sg:phone":"+1 703 971 5200",
    "sg:postcode":"22310",
    "sg:province":"VA",
    "sg:tags":[
        "painter"
    ],
    "wof:name":"Higham Co Inc",
    "wof:placetype":"venue"
},
  "geometry": {"coordinates":[-77.131827,38.79782],"type":"Point"}
}