{
  "type": "Feature",
  "properties": {
    "addr:full":"5911 Oakland Park Dr Burke VA 22015",
    "addr:housenumber":"5911",
    "addr:postcode":"22015",
    "addr:street":"Oakland Park Dr",
    "iso:country":"US",
    "sg:address":"5911 Oakland Park Dr",
    "sg:city":"Burke",
    "sg:classifiers":[
        {
            "category":"Professional",
            "subcategory":"Research",
            "type":"Services"
        }
    ],
    "sg:phone":"+1 703 425 5016",
    "sg:postcode":"22015",
    "sg:province":"VA",
    "sg:tags":[
        "training"
    ],
    "wof:name":"William T Bowers",
    "wof:placetype":"venue"
},
  "geometry": {"coordinates":[-77.32093,38.790242],"type":"Point"}
}