{
  "type": "Feature",
  "properties": {
    "addr:full":"11120 Nash Rd Chesterfield VA 23838",
    "addr:housenumber":"11120",
    "addr:postcode":"23838",
    "addr:street":"Nash Rd",
    "iso:country":"US",
    "sg:address":"11120 Nash Rd",
    "sg:city":"Chesterfield",
    "sg:classifiers":[
        {
            "category":"Manufacturing",
            "subcategory":"Tools & Machinery",
            "type":"Manufacturing & Wholesale Goods"
        }
    ],
    "sg:phone":"+1 804 796 3399",
    "sg:postcode":"23838",
    "sg:province":"VA",
    "sg:tags":[
        "mfg",
        "aircraft",
        "parts",
        "simulator"
    ],
    "wof:name":"Advanced Graphics Tech Llc",
    "wof:placetype":"venue"
},
  "geometry": {"coordinates":[-77.53888000000001,37.352684],"type":"Point"}
}