{
  "type": "Feature",
  "properties": {
    "iso:country":"US",
    "sg:address":"7125 Leesburg Pike",
    "sg:city":"Falls Church",
    "sg:classifiers":[
        {
            "category":"Home & Garden",
            "subcategory":"Garden Supply",
            "type":"Retail Goods"
        }
    ],
    "sg:phone":"+1 703 534 5292",
    "sg:postcode":"22043",
    "sg:province":"VA",
    "sg:tags":[
        "center"
    ],
    "wof:name":"Sam's Farm",
    "wof:placetype":"venue"
},
  "geometry": {"coordinates":[-77.19383000000001,38.896766],"type":"Point"}
}