{
  "type": "Feature",
  "properties": {
    "addr:full":"2200 N Westmoreland St Arlington VA 22213",
    "addr:housenumber":"2200",
    "addr:postcode":"22213",
    "addr:street":"N Westmoreland St",
    "iso:country":"US",
    "sg:address":"2200 N Westmoreland St",
    "sg:city":"Arlington",
    "sg:classifiers":[
        {
            "category":"Real Estate",
            "subcategory":"Real Estate Operator",
            "type":"Services"
        }
    ],
    "sg:phone":"+1 703 237 0055",
    "sg:postcode":"22213",
    "sg:province":"VA",
    "sg:tags":[
        "condominium"
    ],
    "wof:name":"Westlee Condominiums",
    "wof:placetype":"venue"
},
  "geometry": {"coordinates":[-77.16189199999999,38.885728],"type":"Point"}
}