{
  "type": "Feature",
  "properties": {
    "iso:country":"US",
    "sg:address":"190 E Main St",
    "sg:city":"Abingdon",
    "sg:classifiers":[
        {
            "category":"Professional",
            "type":"Services"
        }
    ],
    "sg:phone":"+1 276 676 0360",
    "sg:postcode":"24210",
    "sg:province":"VA",
    "sg:tags":[
        "establishment"
    ],
    "wof:name":"Victory 2001",
    "wof:placetype":"venue"
},
  "geometry": {"coordinates":[-81.970242,36.712032],"type":"Point"}
}