{
  "type": "Feature",
  "properties": {
    "iso:country":"US",
    "sg:address":"207 Tyler Von Way",
    "sg:city":"Fredericksburg",
    "sg:classifiers":[
        {
            "category":"Retail",
            "subcategory":"Auto Repair",
            "type":"Services"
        }
    ],
    "sg:phone":"+1 540 288 1249",
    "sg:postcode":"22405",
    "sg:province":"VA",
    "sg:tags":[
        "repairing",
        "automobile"
    ],
    "wof:name":"Action Auto Works",
    "wof:placetype":"venue"
},
  "geometry": {"coordinates":[-77.442874,38.384152],"type":"Point"}
}