{
  "type": "Feature",
  "properties": {
    "iso:country":"US",
    "sg:address":"152 Moose Rd",
    "sg:city":"Woodstock",
    "sg:classifiers":[
        {
            "category":"Organizations",
            "subcategory":"Community Association",
            "type":"Services"
        }
    ],
    "sg:phone":"+1 540 459 5995",
    "sg:postcode":"22664",
    "sg:province":"VA",
    "sg:tags":[
        "fraternal"
    ],
    "wof:name":"Loyal Order Of Moose",
    "wof:placetype":"venue"
},
  "geometry": {"coordinates":[-78.493408,38.892009],"type":"Point"}
}