{
  "type": "Feature",
  "properties": {
    "addr:full":"404 S Henry St Williamsburg VA 23185",
    "addr:housenumber":"404",
    "addr:postcode":"23185",
    "addr:street":"S Henry St",
    "iso:country":"US",
    "sg:address":"404 S Henry St",
    "sg:city":"Williamsburg",
    "sg:classifiers":[
        {
            "category":"Home & Garden",
            "subcategory":"Building Materials",
            "type":"Retail Goods"
        }
    ],
    "sg:phone":"+1 757 220 8392",
    "sg:postcode":"23185",
    "sg:province":"VA",
    "sg:tags":[
        "glass",
        "leaded"
    ],
    "wof:name":"Art Glass Co",
    "wof:placetype":"venue"
},
  "geometry": {"coordinates":[-76.70592000000001,37.267489],"type":"Point"}
}