{
  "type": "Feature",
  "properties": {
    "iso:country":"US",
    "sg:address":"5555 Lee Highway",
    "sg:city":"Arlington",
    "sg:classifiers":[
        {
            "category":"Restaurant",
            "type":"Food & Drink"
        }
    ],
    "sg:phone":"+1 703 532 0990",
    "sg:postcode":"22207",
    "sg:province":"VA",
    "sg:tags":[
        "italian",
        "pizza"
    ],
    "sg:website":"www.joesplacepizzaandpasta.com",
    "wof:name":"Joe's Place Pizza & Pasta",
    "wof:placetype":"venue"
},
  "geometry": {"coordinates":[-77.139743,38.895888],"type":"Point"}
}