{
  "type": "Feature",
  "properties": {
    "iso:country":"US",
    "sg:address":"2224 Wintergreen Dr",
    "sg:city":"Chesapeake",
    "sg:classifiers":[
        {
            "category":"Professional",
            "subcategory":"Engineering",
            "type":"Services"
        }
    ],
    "sg:phone":"+1 757 487 1943",
    "sg:postcode":"23323",
    "sg:province":"VA",
    "wof:name":"Toler & Associates",
    "wof:placetype":"venue"
},
  "geometry": {"coordinates":[-76.32750900000001,36.789236],"type":"Point"}
}