{
  "type": "Feature",
  "properties": {
    "iso:country":"US",
    "sg:address":"115 Central Ave",
    "sg:city":"Cedar Bluff",
    "sg:classifiers":[
        {
            "category":"Government",
            "subcategory":"Office",
            "type":"Public Place"
        }
    ],
    "sg:phone":"+1 276 964 4889",
    "sg:postcode":"24609",
    "sg:province":"VA",
    "sg:tags":[
        "village"
    ],
    "wof:name":"Cedar Bluff Sewage Dept",
    "wof:placetype":"venue"
},
  "geometry": {"coordinates":[-81.764149,37.087666],"type":"Point"}
}