{
  "type": "Feature",
  "properties": {
    "addr:full":"7216 Hull Street Rd Richmond VA 23235",
    "addr:housenumber":"7216",
    "addr:postcode":"23235",
    "addr:street":"Hull Street Rd",
    "iso:country":"US",
    "sg:address":"7216 Hull Street Rd",
    "sg:city":"Richmond",
    "sg:classifiers":[
        {
            "category":"Personal",
            "subcategory":"Beauty Salon",
            "type":"Services"
        }
    ],
    "sg:phone":"+1 804 674 1000",
    "sg:postcode":"23235",
    "sg:province":"VA",
    "wof:name":"Carolyn's Creative Touch",
    "wof:placetype":"venue"
},
  "geometry": {"coordinates":[-77.527294,37.471928],"type":"Point"}
}