{
  "type": "Feature",
  "properties": {
    "iso:country":"US",
    "sg:address":"8814 Fargo Rd",
    "sg:city":"Richmond",
    "sg:classifiers":[
        {
            "category":"Manufacturing",
            "subcategory":"Tools & Machinery",
            "type":"Manufacturing & Wholesale Goods"
        }
    ],
    "sg:phone":"+1 804 673 1933",
    "sg:postcode":"23229",
    "sg:province":"VA",
    "sg:tags":[
        "computer",
        "maintenance",
        "sales",
        "related",
        "mfg"
    ],
    "wof:name":"H N Bull Information Systems",
    "wof:placetype":"venue"
},
  "geometry": {"coordinates":[-77.56459599999999,37.607361],"type":"Point"}
}