{
  "type": "Feature",
  "properties": {
    "iso:country":"US",
    "sg:address":"6205 Mechanicsville Tpke",
    "sg:city":"Mechanicsville",
    "sg:classifiers":[
        {
            "category":"Retail",
            "subcategory":"Photofinishing",
            "type":"Services"
        }
    ],
    "sg:phone":"+1 804 746 0723",
    "sg:postcode":"23111",
    "sg:province":"VA",
    "sg:tags":[
        "photo",
        "finishing"
    ],
    "wof:name":"Fotomat Corp",
    "wof:placetype":"venue"
},
  "geometry": {"coordinates":[-77.312248,37.621542],"type":"Point"}
}