{
  "type": "Feature",
  "properties": {
    "addr:full":"228 E 5th St N Big Stone Gap VA 24219",
    "addr:housenumber":"228",
    "addr:postcode":"24219",
    "addr:street":"E 5Th St N",
    "iso:country":"US",
    "sg:address":"228 E 5th St N",
    "sg:city":"Big Stone Gap",
    "sg:classifiers":[
        {
            "category":"Banks & Credit Unions",
            "subcategory":"Bank",
            "type":"Services"
        }
    ],
    "sg:phone":"+1 276 523 2057",
    "sg:postcode":"24219",
    "sg:province":"VA",
    "wof:name":"Powell Valley National Bank",
    "wof:placetype":"venue"
},
  "geometry": {"coordinates":[-82.77631599999999,36.869639],"type":"Point"}
}