{
  "type": "Feature",
  "properties": {
    "iso:country":"US",
    "sg:address":"13050 Fair Lakes Shopping Ctr",
    "sg:city":"Fairfax",
    "sg:classifiers":[
        {
            "category":"Restaurant",
            "type":"Food & Drink"
        }
    ],
    "sg:menulink":"http://www.allmenus.com/va/sully/10360-don-pablos/menu/",
    "sg:phone":"+1 703 222 9770",
    "sg:postcode":"22033",
    "sg:province":"VA",
    "sg:tags":[
        "sandwich",
        "mexican",
        "salad",
        "soup",
        "american",
        "wrap",
        "tex-mex"
    ],
    "wof:name":"Don Pablo's",
    "wof:placetype":"venue"
},
  "geometry": {"coordinates":[-77.395003,38.856286],"type":"Point"}
}