{
  "type": "Feature",
  "properties": {
    "addr:full":"3819 S George Mason Dr Baileys Crossrds VA 22041",
    "addr:housenumber":"3819",
    "addr:postcode":"22041",
    "addr:street":"S George Mason Dr",
    "iso:country":"US",
    "sg:address":"3819 S George Mason Dr",
    "sg:city":"Baileys Crossrds",
    "sg:classifiers":[
        {
            "category":"Personal",
            "subcategory":"Tanning Parlor",
            "type":"Services"
        }
    ],
    "sg:phone":"+1 703 578 3400",
    "sg:postcode":"22041",
    "sg:province":"VA",
    "sg:tags":[
        "salon"
    ],
    "wof:name":"Keywest Tanning",
    "wof:placetype":"venue"
},
  "geometry": {"coordinates":[-77.121152,38.841067],"type":"Point"}
}