{
  "type": "Feature",
  "properties": {
    "addr:full":"8886 Rixlew Ln Manassas VA 20109",
    "addr:housenumber":"8886",
    "addr:postcode":"20109",
    "addr:street":"Rixlew Ln",
    "iso:country":"US",
    "sg:address":"8886 Rixlew Ln",
    "sg:city":"Manassas",
    "sg:classifiers":[
        {
            "category":"Real Estate",
            "subcategory":"Real Estate Operator",
            "type":"Services"
        }
    ],
    "sg:phone":"+1 703 330 3349",
    "sg:postcode":"20109",
    "sg:province":"VA",
    "sg:tags":[
        "building",
        "parks"
    ],
    "wof:name":"Wellington Business Ctr III",
    "wof:placetype":"venue"
},
  "geometry": {"coordinates":[-77.506975,38.762949],"type":"Point"}
}