{
  "type": "Feature",
  "properties": {
    "addr:full":"1003 Virginia Ave Bluefield VA 24605",
    "addr:housenumber":"1003",
    "addr:postcode":"24605",
    "addr:street":"Virginia Ave",
    "iso:country":"US",
    "sg:address":"1003 Virginia Ave",
    "sg:city":"Bluefield",
    "sg:classifiers":[
        {
            "category":"Insurance",
            "subcategory":"Insurance Agent",
            "type":"Services"
        }
    ],
    "sg:phone":"+1 276 322 2305",
    "sg:postcode":"24605",
    "sg:province":"VA",
    "wof:name":"Insurance Pros Agency Inc",
    "wof:placetype":"venue"
},
  "geometry": {"coordinates":[-81.28205,37.252769],"type":"Point"}
}