{
  "type": "Feature",
  "properties": {
    "iso:country":"US",
    "sg:address":"530 Blackwell Rd",
    "sg:city":"Warrenton",
    "sg:classifiers":[
        {
            "category":"Banks & Credit Unions",
            "subcategory":"Bank",
            "type":"Services"
        }
    ],
    "sg:phone":"+1 540 341 8612",
    "sg:postcode":"20186",
    "sg:province":"VA",
    "wof:name":"First Virginia Bank",
    "wof:placetype":"venue"
},
  "geometry": {"coordinates":[-77.790497,38.7262],"type":"Point"}
}