{
  "type": "Feature",
  "properties": {
    "iso:country":"US",
    "sg:address":"1310 W Main St",
    "sg:city":"Salem",
    "sg:classifiers":[
        {
            "category":"Restaurant",
            "type":"Food & Drink"
        }
    ],
    "sg:phone":"+1 540 389 8618",
    "sg:postcode":"24153",
    "sg:province":"VA",
    "sg:tags":[
        "asian",
        "chinese",
        "pan"
    ],
    "sg:website":"http://www.chinawokky.com",
    "wof:name":"China Wok",
    "wof:placetype":"venue"
},
  "geometry": {"coordinates":[-80.183525,37.239134],"type":"Point"}
}