{
  "type": "Feature",
  "properties": {
    "addr:full":"11707 Nokesville Rd Bristow VA 20136",
    "addr:postcode":"11707;20136",
    "addr:street":"Nokesville Rd",
    "iso:country":"US",
    "sg:address":"11707 Nokesville Rd",
    "sg:city":"Bristow",
    "sg:classifiers":[
        {
            "category":"Food & Beverages",
            "subcategory":"Groceries & Convenience Stores",
            "type":"Retail Goods"
        }
    ],
    "sg:phone":"+1 703 396 8801",
    "sg:postcode":"20136",
    "sg:province":"VA",
    "wof:name":"J J Market",
    "wof:placetype":"venue"
},
  "geometry": {"coordinates":[-77.547096,38.7313],"type":"Point"}
}