{
  "type": "Feature",
  "properties": {
    "iso:country":"US",
    "sg:address":"1201 S Rosemont Rd",
    "sg:city":"Virginia Beach",
    "sg:classifiers":[
        {
            "category":"Organizations",
            "subcategory":"Religious Organization",
            "type":"Services"
        }
    ],
    "sg:phone":"+1 757 427 5087",
    "sg:postcode":"23452",
    "sg:province":"VA",
    "sg:tags":[
        "baptist",
        "church"
    ],
    "wof:name":"Green Run Baptist Church",
    "wof:placetype":"venue"
},
  "geometry": {"coordinates":[-76.09907699999999,36.79945],"type":"Point"}
}