{
  "type": "Feature",
  "properties": {
    "iso:country":"US",
    "sg:address":"944 Capitol Landing Rd R",
    "sg:city":"Williamsburg",
    "sg:classifiers":[
        {
            "category":"Insurance",
            "subcategory":"Insurance Agent",
            "type":"Services"
        },
        {
            "category":"Insurance",
            "subcategory":"Hazard Insurance",
            "type":"Services"
        }
    ],
    "sg:phone":"+1 757 253 5604",
    "sg:postcode":"23185",
    "sg:province":"VA",
    "sg:tags":[
        "auto",
        "analyst",
        "consultant"
    ],
    "wof:name":"COMMONWEALTH INS CTR - Progressive Insurance",
    "wof:placetype":"venue"
},
  "geometry": {"coordinates":[-76.686977,37.285508],"type":"Point"}
}