{
  "type": "Feature",
  "properties": {
    "addr:full":"4300 Prince William Pkwy Woodbridge VA 22192",
    "addr:housenumber":"4300",
    "addr:postcode":"22192",
    "addr:street":"Prince William Pkwy",
    "iso:country":"US",
    "sg:address":"4300 Prince William Pkwy",
    "sg:city":"Woodbridge",
    "sg:classifiers":[
        {
            "category":"Shopping",
            "subcategory":"Gifts & Souvenirs",
            "type":"Retail Goods"
        }
    ],
    "sg:phone":"+1 703 680 2548",
    "sg:postcode":"22192",
    "sg:province":"VA",
    "sg:tags":[
        "shop",
        "card"
    ],
    "wof:name":"Parcel Plus",
    "wof:placetype":"venue"
},
  "geometry": {"coordinates":[-77.343536,38.675839],"type":"Point"}
}