{
  "type": "Feature",
  "properties": {
    "addr:full":"7248 Virginia Ave Bassett VA 24055",
    "addr:housenumber":"7248",
    "addr:postcode":"24055",
    "addr:street":"Virginia Ave",
    "iso:country":"US",
    "sg:address":"7248 Virginia Ave",
    "sg:city":"Bassett",
    "sg:classifiers":[
        {
            "category":"Shopping",
            "type":"Retail Goods"
        }
    ],
    "sg:phone":"+1 276 629 5500",
    "sg:postcode":"24055",
    "sg:province":"VA",
    "sg:tags":[
        "monument"
    ],
    "wof:name":"Granite Memorial Svc",
    "wof:placetype":"venue"
},
  "geometry": {"coordinates":[-79.933616,36.793092],"type":"Point"}
}