{
  "type": "Feature",
  "properties": {
    "addr:full":"9417 West St Manassas VA 20110",
    "addr:housenumber":"9417",
    "addr:postcode":"20110",
    "addr:street":"West St",
    "iso:country":"US",
    "sg:address":"9417 West St",
    "sg:city":"Manassas",
    "sg:classifiers":[
        {
            "category":"Restaurant",
            "type":"Food & Drink"
        }
    ],
    "sg:menulink":"http://www.allmenus.com/va/manassas/151444-fosters-grille/menu/",
    "sg:phone":"+1 703 257 7272",
    "sg:postcode":"20110",
    "sg:province":"VA",
    "sg:tags":[
        "american"
    ],
    "wof:name":"Foster's Grille",
    "wof:placetype":"venue"
},
  "geometry": {"coordinates":[-77.47323900000001,38.750381],"type":"Point"}
}