{
  "type": "Feature",
  "properties": {
    "addr:full":"307 McGowan Dr Fredericksburg VA 22408",
    "addr:housenumber":"307",
    "addr:postcode":"22408",
    "addr:street":"Mcgowan Dr",
    "iso:country":"US",
    "sg:address":"307 McGowan Dr",
    "sg:city":"Fredericksburg",
    "sg:classifiers":[
        {
            "category":"Building & Trades",
            "subcategory":"Electrical",
            "type":"Services"
        }
    ],
    "sg:phone":"+1 540 898 7507",
    "sg:postcode":"22408",
    "sg:province":"VA",
    "sg:tags":[
        "electric",
        "contractor"
    ],
    "wof:name":"D & M Electrical Svc",
    "wof:placetype":"venue"
},
  "geometry": {"coordinates":[-77.50569,38.249024],"type":"Point"}
}