{
  "type": "Feature",
  "properties": {
    "addr:full":"1791 Richmond Road Charlottesville VA 22911",
    "addr:housenumber":"1791",
    "addr:postcode":"22911",
    "addr:street":"Richmond Road",
    "iso:country":"US",
    "sg:address":"1791 Richmond Road",
    "sg:city":"Charlottesville",
    "sg:classifiers":[
        {
            "category":"Restaurant",
            "type":"Food & Drink"
        }
    ],
    "sg:phone":"+1 434 984 3333",
    "sg:postcode":"22911",
    "sg:province":"VA",
    "sg:website":"www.topekas.com",
    "wof:name":"Topeka's Steakhouse",
    "wof:placetype":"venue"
},
  "geometry": {"coordinates":[-78.435074,38.024036],"type":"Point"}
}