{
  "type": "Feature",
  "properties": {
    "addr:full":"9850 Furnace Rd Lorton VA 22079",
    "addr:housenumber":"9850",
    "addr:postcode":"22079",
    "addr:street":"Furnace Rd",
    "iso:country":"US",
    "sg:address":"9850 Furnace Rd",
    "sg:city":"Lorton",
    "sg:classifiers":[
        {
            "category":"Professional",
            "type":"Services"
        }
    ],
    "sg:phone":"+1 703 690 5965",
    "sg:postcode":"22079",
    "sg:province":"VA",
    "sg:tags":[
        "establishment"
    ],
    "wof:name":"Michigan Cogeneration Systems",
    "wof:placetype":"venue"
},
  "geometry": {"coordinates":[-77.23764199999999,38.691323],"type":"Point"}
}