{
  "type": "Feature",
  "properties": {
    "iso:country":"US",
    "sg:address":"127 Robin Ln",
    "sg:city":"Suffolk",
    "sg:classifiers":[
        {
            "category":"Building & Trades",
            "subcategory":"Landscaping Services",
            "type":"Services"
        }
    ],
    "sg:phone":"+1 757 714 2725",
    "sg:postcode":"23434",
    "sg:province":"VA",
    "sg:tags":[
        "lawn"
    ],
    "wof:name":"Affordable Landscapes & Irrgtn.",
    "wof:placetype":"venue"
},
  "geometry": {"coordinates":[-76.65780700000001,36.712981],"type":"Point"}
}