{
  "type": "Feature",
  "properties": {
    "iso:country":"US",
    "sg:address":"1239 S Blue Ridge Ave",
    "sg:city":"Culpeper",
    "sg:classifiers":[
        {
            "category":"Food & Beverages",
            "subcategory":"Meat & Fish",
            "type":"Retail Goods"
        }
    ],
    "sg:phone":"+1 540 948 4209",
    "sg:postcode":"22701",
    "sg:province":"VA",
    "wof:name":"Buffalo Hill",
    "wof:placetype":"venue"
},
  "geometry": {"coordinates":[-78.002066,38.465321],"type":"Point"}
}