{
  "type": "Feature",
  "properties": {
    "iso:country":"US",
    "sg:address":"1313 E Main St",
    "sg:city":"Richmond",
    "sg:classifiers":[
        {
            "category":"Professional",
            "subcategory":"Engineering",
            "type":"Services"
        }
    ],
    "sg:phone":"+1 804 343 0161",
    "sg:postcode":"23219",
    "sg:province":"VA",
    "sg:tags":[
        "provides"
    ],
    "wof:name":"Bovis Lend Lease Consulting",
    "wof:placetype":"venue"
},
  "geometry": {"coordinates":[-77.432152,37.535618],"type":"Point"}
}