{
  "type": "Feature",
  "properties": {
    "iso:country":"US",
    "sg:address":"14068 Hawkeye Run Ct",
    "sg:city":"Bristow",
    "sg:classifiers":[
        {
            "category":"Social Services",
            "subcategory":"Child Care",
            "type":"Services"
        }
    ],
    "sg:phone":"+1 703 257 1362",
    "sg:postcode":"20136",
    "sg:province":"VA",
    "wof:name":"Dorothy's Babies Inc",
    "wof:placetype":"venue"
},
  "geometry": {"coordinates":[-77.55340700000001,38.746411],"type":"Point"}
}