{
  "type": "Feature",
  "properties": {
    "addr:full":"19829 Memory Ln Sterling VA 20165",
    "addr:housenumber":"19829",
    "addr:postcode":"20165",
    "addr:street":"Memory Ln",
    "iso:country":"US",
    "sg:address":"19829 Memory Ln",
    "sg:city":"Sterling",
    "sg:classifiers":[
        {
            "category":"Professional",
            "type":"Services"
        }
    ],
    "sg:phone":"+1 703 771 2220",
    "sg:postcode":"20165",
    "sg:province":"VA",
    "sg:tags":[
        "establishment"
    ],
    "wof:name":"Dragonslayer Applications Inc",
    "wof:placetype":"venue"
},
  "geometry": {"coordinates":[-77.43074300000001,39.06595],"type":"Point"}
}