{
  "type": "Feature",
  "properties": {
    "iso:country":"US",
    "sg:address":"154 Creekside Ln",
    "sg:city":"Winchester",
    "sg:classifiers":[
        {
            "category":"Health Services",
            "subcategory":"Doctor",
            "type":"Services"
        }
    ],
    "sg:phone":"+1 540 722 6700",
    "sg:postcode":"22602",
    "sg:province":"VA",
    "wof:name":"Julie Staggers DDS Ms",
    "wof:placetype":"venue"
},
  "geometry": {"coordinates":[-78.191247,39.140483],"type":"Point"}
}