{
  "type": "Feature",
  "properties": {
    "iso:country":"US",
    "sg:address":"4714 Marshall Ave",
    "sg:city":"Newport News",
    "sg:classifiers":[
        {
            "category":"Health Services",
            "subcategory":"Doctor",
            "type":"Services"
        }
    ],
    "sg:phone":"+1 757 380 8709",
    "sg:postcode":"23607",
    "sg:province":"VA",
    "sg:tags":[
        "dental",
        "private",
        "community",
        "center"
    ],
    "wof:name":"48th Street Physicians",
    "wof:placetype":"venue"
},
  "geometry": {"coordinates":[-76.424588,36.998029],"type":"Point"}
}