{
  "type": "Feature",
  "properties": {
    "addr:full":"6700 Clark Rd Powhatan VA 23139",
    "addr:housenumber":"6700",
    "addr:postcode":"23139",
    "addr:street":"Clark Rd",
    "iso:country":"US",
    "sg:address":"6700 Clark Rd",
    "sg:city":"Powhatan",
    "sg:classifiers":[
        {
            "category":"Professional",
            "subcategory":"Employment Agencies",
            "type":"Services"
        }
    ],
    "sg:phone":"+1 804 492 3459",
    "sg:postcode":"23139",
    "sg:province":"VA",
    "sg:tags":[
        "help",
        "supply"
    ],
    "wof:name":"Vrs Cleaning Service",
    "wof:placetype":"venue"
},
  "geometry": {"coordinates":[-78.127139,37.471292],"type":"Point"}
}