{
  "type": "Feature",
  "properties": {
    "iso:country":"US",
    "sg:address":"1673 Dylan Dr",
    "sg:city":"Virginia Beach",
    "sg:classifiers":[
        {
            "category":"Freight",
            "type":"Transportation"
        }
    ],
    "sg:phone":"+1 757 479 1650",
    "sg:postcode":"23464",
    "sg:province":"VA",
    "sg:tags":[
        "operator",
        "local",
        "trucking"
    ],
    "wof:name":"Cliffs Trucking",
    "wof:placetype":"venue"
},
  "geometry": {"coordinates":[-76.185659,36.787588],"type":"Point"}
}