{
  "type": "Feature",
  "properties": {
    "iso:country":"US",
    "sg:address":"9225 Derwent Dr",
    "sg:city":"Mechanicsville",
    "sg:classifiers":[
        {
            "category":"Home & Garden",
            "subcategory":"Hardware",
            "type":"Retail Goods"
        }
    ],
    "sg:phone":"+1 804 746 7004",
    "sg:postcode":"23116",
    "sg:province":"VA",
    "wof:name":"Pro Tools",
    "wof:placetype":"venue"
},
  "geometry": {"coordinates":[-77.356675,37.65052],"type":"Point"}
}