{
  "type": "Feature",
  "properties": {
    "addr:full":"11530 Porter Rd Orange VA 22960",
    "addr:housenumber":"11530",
    "addr:postcode":"22960",
    "addr:street":"Porter Rd",
    "iso:country":"US",
    "sg:address":"11530 Porter Rd",
    "sg:city":"Orange",
    "sg:classifiers":[
        {
            "category":"Government",
            "subcategory":"Office",
            "type":"Public Place"
        }
    ],
    "sg:phone":"+1 540 672 9315",
    "sg:postcode":"22960",
    "sg:province":"VA",
    "wof:name":"Orange County Landfill",
    "wof:placetype":"venue"
},
  "geometry": {"coordinates":[-78.03059,38.23928],"type":"Point"}
}