{
  "type": "Feature",
  "properties": {
    "addr:full":"14877 Dumfries Rd Manassas VA 20112",
    "addr:housenumber":"14877",
    "addr:postcode":"20112",
    "addr:street":"Dumfries Rd",
    "iso:country":"US",
    "sg:address":"14877 Dumfries Rd",
    "sg:city":"Manassas",
    "sg:classifiers":[
        {
            "category":"Government",
            "subcategory":"Office",
            "type":"Public Place"
        }
    ],
    "sg:phone":"+1 703 791 7866",
    "sg:postcode":"20112",
    "sg:province":"VA",
    "wof:name":"Prince William County Pub Work",
    "wof:placetype":"venue"
},
  "geometry": {"coordinates":[-77.41944599999999,38.631457],"type":"Point"}
}