{
  "type": "Feature",
  "properties": {
    "iso:country":"US",
    "sg:address":"5901 Clear Springs Ct",
    "sg:city":"Virginia Beach",
    "sg:classifiers":[
        {
            "category":"Manufacturing",
            "subcategory":"Tools & Machinery",
            "type":"Manufacturing & Wholesale Goods"
        }
    ],
    "sg:phone":"+1 757 420 6585",
    "sg:postcode":"23464",
    "sg:province":"VA",
    "sg:tags":[
        "analytical",
        "instrument",
        "mfg"
    ],
    "wof:name":"Atlantic Moisture Control",
    "wof:placetype":"venue"
},
  "geometry": {"coordinates":[-76.203632,36.805735],"type":"Point"}
}