{
  "type": "Feature",
  "properties": {
    "iso:country":"US",
    "sg:address":"600 Jarman Rd",
    "sg:city":"Chesapeake",
    "sg:classifiers":[
        {
            "category":"Health Services",
            "subcategory":"Doctor",
            "type":"Services"
        }
    ],
    "sg:phone":"+1 757 424 7800",
    "sg:postcode":"23320",
    "sg:province":"VA",
    "sg:tags":[
        "physician",
        "surgeon"
    ],
    "wof:name":"Sports Med",
    "wof:placetype":"venue"
},
  "geometry": {"coordinates":[-76.233189,36.778524],"type":"Point"}
}