{
  "type": "Feature",
  "properties": {
    "addr:full":"21 Clearview Dr Cana VA 24317",
    "addr:housenumber":"21",
    "addr:postcode":"24317",
    "addr:street":"Clearview Dr",
    "iso:country":"US",
    "sg:address":"21 Clearview Dr",
    "sg:city":"Cana",
    "sg:classifiers":[
        {
            "category":"Retail",
            "subcategory":"Laundry & Dry Cleaning",
            "type":"Services"
        }
    ],
    "sg:phone":"+1 276 755 2606",
    "sg:postcode":"24317",
    "sg:province":"VA",
    "sg:tags":[
        "cleaners",
        "rug",
        "carpet"
    ],
    "wof:name":"Proklean Steam Cleaning Svcs",
    "wof:placetype":"venue"
},
  "geometry": {"coordinates":[-80.665125,36.587589],"type":"Point"}
}