{
  "type": "Feature",
  "properties": {
    "addr:full":"2112 W Laburnum Ave Richmond VA 23227",
    "addr:housenumber":"2112",
    "addr:postcode":"23227",
    "addr:street":"W Laburnum Ave",
    "iso:country":"US",
    "sg:address":"2112 W Laburnum Ave",
    "sg:city":"Richmond",
    "sg:classifiers":[
        {
            "category":"Social Services",
            "type":"Services"
        }
    ],
    "sg:phone":"+1 804 353 5008",
    "sg:postcode":"23227",
    "sg:province":"VA",
    "sg:tags":[
        "organization",
        "welfare"
    ],
    "wof:name":"National Multiple Sclerosis",
    "wof:placetype":"venue"
},
  "geometry": {"coordinates":[-77.472127,37.583884],"type":"Point"}
}