{
  "type": "Feature",
  "properties": {
    "addr:full":"301 W 10th St Buena Vista VA 24416",
    "addr:housenumber":"301",
    "addr:postcode":"24416",
    "addr:street":"W 10Th St",
    "iso:country":"US",
    "sg:address":"301 W 10th St",
    "sg:city":"Buena Vista",
    "sg:classifiers":[
        {
            "category":"Government",
            "subcategory":"Office",
            "type":"Public Place"
        }
    ],
    "sg:phone":"+1 540 261 8606",
    "sg:postcode":"24416",
    "sg:province":"VA",
    "sg:tags":[
        "village"
    ],
    "wof:name":"Buena Vista Waste Water Trmnt",
    "wof:placetype":"venue"
},
  "geometry": {"coordinates":[-79.364976,37.724408],"type":"Point"}
}