{
  "type": "Feature",
  "properties": {
    "addr:full":"6739 Stephens Rd Wise VA 24293",
    "addr:housenumber":"6739",
    "addr:postcode":"24293",
    "addr:street":"Stephens Rd",
    "iso:country":"US",
    "sg:address":"6739 Stephens Rd",
    "sg:city":"Wise",
    "sg:classifiers":[
        {
            "category":"Freight",
            "type":"Transportation"
        }
    ],
    "sg:phone":"+1 276 328 2194",
    "sg:postcode":"24293",
    "sg:province":"VA",
    "sg:tags":[
        "trucking"
    ],
    "wof:name":"M D Transport Inc",
    "wof:placetype":"venue"
},
  "geometry": {"coordinates":[-82.595912,36.997009],"type":"Point"}
}