{
  "type": "Feature",
  "properties": {
    "addr:full":"404 Kents Ridge Rd Richlands VA 24641",
    "addr:housenumber":"404",
    "addr:postcode":"24641",
    "addr:street":"Kents Ridge Rd",
    "iso:country":"US",
    "sg:address":"404 Kents Ridge Rd",
    "sg:city":"Richlands",
    "sg:classifiers":[
        {
            "category":"Retail",
            "subcategory":"Laundry & Dry Cleaning",
            "type":"Services"
        }
    ],
    "sg:phone":"+1 276 964 7458",
    "sg:postcode":"24641",
    "sg:province":"VA",
    "sg:tags":[
        "building",
        "maintenance"
    ],
    "wof:name":"American Carpet Care Inc",
    "wof:placetype":"venue"
},
  "geometry": {"coordinates":[-81.808013,37.090578],"type":"Point"}
}