{
  "type": "Feature",
  "properties": {
    "addr:full":"7 Kidd Ln Front Royal VA 22630",
    "addr:housenumber":"7",
    "addr:postcode":"22630",
    "addr:street":"Kidd Ln",
    "iso:country":"US",
    "sg:address":"7 Kidd Ln",
    "sg:city":"Front Royal",
    "sg:classifiers":[
        {
            "category":"Recreation",
            "type":"Entertainment"
        }
    ],
    "sg:phone":"+1 540 635 7554",
    "sg:postcode":"22630",
    "sg:province":"VA",
    "sg:tags":[
        "arts",
        "facility",
        "instruction",
        "martial",
        "fitness",
        "physical"
    ],
    "wof:name":"Front Royal Karate & Judo Club",
    "wof:placetype":"venue"
},
  "geometry": {"coordinates":[-78.19222600000001,38.918323],"type":"Point"}
}