{
  "type": "Feature",
  "properties": {
    "addr:full":"1701 W Main St Radford VA 24141",
    "addr:housenumber":"1701",
    "addr:postcode":"24141",
    "addr:street":"W Main St",
    "iso:country":"US",
    "sg:address":"1701 W Main St",
    "sg:city":"Radford",
    "sg:classifiers":[
        {
            "category":"Manufacturing",
            "subcategory":"Metals",
            "type":"Manufacturing & Wholesale Goods"
        }
    ],
    "sg:phone":"+1 540 731 0500",
    "sg:postcode":"24141",
    "sg:province":"VA",
    "sg:tags":[
        "gray",
        "ductile",
        "foundry",
        "iron"
    ],
    "wof:name":"New River Castings",
    "wof:placetype":"venue"
},
  "geometry": {"coordinates":[-80.59026,37.119785],"type":"Point"}
}