{
  "type": "Feature",
  "properties": {
    "addr:full":"2740 Jasmine Ter Charlottesville VA 22911",
    "addr:housenumber":"2740",
    "addr:postcode":"22911",
    "addr:street":"Jasmine Ter",
    "iso:country":"US",
    "sg:address":"2740 Jasmine Ter",
    "sg:city":"Charlottesville",
    "sg:classifiers":[
        {
            "category":"Education",
            "subcategory":"Special Training",
            "type":"Public Place"
        }
    ],
    "sg:phone":"+1 434 924 7844",
    "sg:postcode":"22911",
    "sg:province":"VA",
    "wof:name":"Stanley C Trent",
    "wof:placetype":"venue"
},
  "geometry": {"coordinates":[-78.444063,38.110203],"type":"Point"}
}