{
  "type": "Feature",
  "properties": {
    "iso:country":"US",
    "sg:address":"627 Dice St",
    "sg:city":"Charlottesville",
    "sg:classifiers":[
        {
            "category":"Professional",
            "subcategory":"Testing Lab",
            "type":"Services"
        }
    ],
    "sg:phone":"+1 434 295 1716",
    "sg:postcode":"22903",
    "sg:province":"VA",
    "sg:tags":[
        "biological",
        "laboratory"
    ],
    "wof:name":"Aqua Air Laboratories Inc",
    "wof:placetype":"venue"
},
  "geometry": {"coordinates":[-78.49047,38.029559],"type":"Point"}
}