{
  "type": "Feature",
  "properties": {
    "addr:full":"3582 Evington Rd Evington VA 24550",
    "addr:postcode":"3582;24550",
    "addr:street":"Evington Rd",
    "iso:country":"US",
    "sg:address":"3582 Evington Rd",
    "sg:city":"Evington",
    "sg:classifiers":[
        {
            "category":"Manufacturing",
            "subcategory":"Building Materials",
            "type":"Manufacturing & Wholesale Goods"
        }
    ],
    "sg:phone":"+1 434 525 6988",
    "sg:postcode":"24550",
    "sg:province":"VA",
    "sg:tags":[
        "mfg",
        "wood",
        "kitchen",
        "cabinet"
    ],
    "wof:name":"Precision Millwork & Cabinets",
    "wof:placetype":"venue"
},
  "geometry": {"coordinates":[-79.314555,37.27681],"type":"Point"}
}