{
  "type": "Feature",
  "properties": {
    "iso:country":"US",
    "sg:address":"7601 W Broad St",
    "sg:city":"Richmond",
    "sg:classifiers":[
        {
            "category":"Shopping",
            "type":"Retail Goods"
        },
        {
            "category":"Wholesale",
            "subcategory":"Sporting Goods",
            "type":"Manufacturing & Wholesale Goods"
        }
    ],
    "sg:phone":"+1 804 672 2984",
    "sg:postcode":"23294",
    "sg:province":"VA",
    "sg:tags":[
        "equipment",
        "swimming",
        "pool",
        "supply"
    ],
    "wof:name":"Leslies Swimming Pool Supplies",
    "wof:placetype":"venue"
},
  "geometry": {"coordinates":[-77.52409299999999,37.619177],"type":"Point"}
}