{
  "type": "Feature",
  "properties": {
    "addr:full":"2842 Rockfish Valley Hwy Nellysford VA 22958",
    "addr:housenumber":"2842",
    "addr:postcode":"22958",
    "addr:street":"Rockfish Valley Hwy Nellysford",
    "iso:country":"US",
    "sg:address":"2842 Rockfish Valley Hwy",
    "sg:city":"Nellysford",
    "sg:classifiers":[
        {
            "category":"Restaurant",
            "type":"Food & Drink"
        }
    ],
    "sg:phone":"+1 434 361 2131",
    "sg:postcode":"22958",
    "sg:province":"VA",
    "sg:tags":[
        "eating"
    ],
    "wof:name":"Rockfish River Grill",
    "wof:placetype":"venue"
},
  "geometry": {"coordinates":[-78.877504,37.88772],"type":"Point"}
}