{
  "type": "Feature",
  "properties": {
    "addr:full":"2403 Buckingham Ave Richmond VA 23228",
    "addr:housenumber":"2403",
    "addr:postcode":"23228",
    "addr:street":"Buckingham Ave",
    "iso:country":"US",
    "sg:address":"2403 Buckingham Ave",
    "sg:city":"Richmond",
    "sg:classifiers":[
        {
            "category":"Retail",
            "subcategory":"Animal Services",
            "type":"Services"
        }
    ],
    "sg:phone":"+1 804 266 3104",
    "sg:postcode":"23228",
    "sg:province":"VA",
    "wof:name":"Gone To Dogs MBL Pet Grooming",
    "wof:placetype":"venue"
},
  "geometry": {"coordinates":[-77.477338,37.601132],"type":"Point"}
}