{
  "type": "Feature",
  "properties": {
    "iso:country":"US",
    "sg:address":"1635 Washington Plz N",
    "sg:city":"Reston",
    "sg:classifiers":[
        {
            "category":"Personal",
            "subcategory":"Beauty Salon",
            "type":"Services"
        }
    ],
    "sg:phone":"+1 703 707 8484",
    "sg:postcode":"20190",
    "sg:province":"VA",
    "wof:name":"Salon Chakra",
    "wof:placetype":"venue"
},
  "geometry": {"coordinates":[-77.341838,38.969069],"type":"Point"}
}