{
  "type": "Feature",
  "properties": {
    "addr:full":"1833 Seminole Trl Charlottesville VA 22901",
    "addr:housenumber":"1833",
    "addr:postcode":"22901",
    "addr:street":"Seminole Trl",
    "iso:country":"US",
    "sg:address":"1833 Seminole Trl",
    "sg:city":"Charlottesville",
    "sg:classifiers":[
        {
            "category":"Professional",
            "subcategory":"Art Services",
            "type":"Services"
        }
    ],
    "sg:phone":"+1 434 973 1844",
    "sg:postcode":"22901",
    "sg:province":"VA",
    "sg:tags":[
        "graphic",
        "designer"
    ],
    "wof:name":"Remco Graphics Svc",
    "wof:placetype":"venue"
},
  "geometry": {"coordinates":[-78.471789,38.084925],"type":"Point"}
}