{
  "type": "Feature",
  "properties": {
    "addr:full":"1194 Big Bethel Rd Hampton VA 23666",
    "addr:housenumber":"1194",
    "addr:postcode":"23666",
    "addr:street":"Big Bethel Rd",
    "iso:country":"US",
    "sg:address":"1194 Big Bethel Rd",
    "sg:city":"Hampton",
    "sg:classifiers":[
        {
            "category":"Cinema",
            "subcategory":"Movie Rental",
            "type":"Entertainment"
        }
    ],
    "sg:phone":"+1 757 896 0086",
    "sg:postcode":"23666",
    "sg:province":"VA",
    "sg:tags":[
        "video",
        "tape"
    ],
    "wof:name":"Hollywood Video",
    "wof:placetype":"venue"
},
  "geometry": {"coordinates":[-76.428015,37.055864],"type":"Point"}
}