{
  "type": "Feature",
  "properties": {
    "addr:full":"8521 Centreville Rd Manassas Park VA 20111",
    "addr:housenumber":"8521",
    "addr:postcode":"20111",
    "addr:street":"Centreville Rd;Park",
    "iso:country":"US",
    "sg:address":"8521 Centreville Rd",
    "sg:city":"Manassas Park",
    "sg:classifiers":[
        {
            "category":"Food & Beverages",
            "subcategory":"Groceries & Convenience Stores",
            "type":"Retail Goods"
        }
    ],
    "sg:phone":"+1 703 368 1640",
    "sg:postcode":"20111",
    "sg:province":"VA",
    "wof:name":"7-Eleven",
    "wof:placetype":"venue"
},
  "geometry": {"coordinates":[-77.45226,38.772392],"type":"Point"}
}