{
  "type": "Feature",
  "properties": {
    "addr:full":"10207 Hillside Ln Fredericksburg VA 22408",
    "addr:housenumber":"10207",
    "addr:postcode":"22408",
    "addr:street":"Hillside Ln",
    "iso:country":"US",
    "sg:address":"10207 Hillside Ln",
    "sg:city":"Fredericksburg",
    "sg:classifiers":[
        {
            "category":"Professional",
            "subcategory":"Art Services",
            "type":"Services"
        }
    ],
    "sg:phone":"+1 540 898 7436",
    "sg:postcode":"22408",
    "sg:province":"VA",
    "sg:tags":[
        "photography"
    ],
    "wof:name":"Bennett Photography",
    "wof:placetype":"venue"
},
  "geometry": {"coordinates":[-77.48809199999999,38.244661],"type":"Point"}
}