{
  "type": "Feature",
  "properties": {
    "addr:full":"1904 Byrd Ave Richmond VA 23230",
    "addr:housenumber":"1904",
    "addr:postcode":"23230",
    "addr:street":"Byrd Ave",
    "iso:country":"US",
    "sg:address":"1904 Byrd Ave",
    "sg:city":"Richmond",
    "sg:classifiers":[
        {
            "category":"Professional",
            "subcategory":"Lawyer & Legal Services",
            "type":"Services"
        }
    ],
    "sg:phone":"+1 804 282 5970",
    "sg:postcode":"23230",
    "sg:province":"VA",
    "wof:name":"Walker Robinson PC",
    "wof:placetype":"venue"
},
  "geometry": {"coordinates":[-77.500497,37.584854],"type":"Point"}
}