{
  "type": "Feature",
  "properties": {
    "addr:full":"706 Chinaberry Dr Richmond VA 23225",
    "addr:housenumber":"706",
    "addr:postcode":"23225",
    "addr:street":"Chinaberry Dr",
    "iso:country":"US",
    "sg:address":"706 Chinaberry Dr",
    "sg:city":"Richmond",
    "sg:classifiers":[
        {
            "category":"Building & Trades",
            "subcategory":"Construction",
            "type":"Services"
        }
    ],
    "sg:phone":"+1 804 837 1443",
    "sg:postcode":"23225",
    "sg:province":"VA",
    "sg:tags":[
        "painter"
    ],
    "wof:name":"A & G Discount Painters",
    "wof:placetype":"venue"
},
  "geometry": {"coordinates":[-77.534735,37.506816],"type":"Point"}
}