{
  "type": "Feature",
  "properties": {
    "iso:country":"US",
    "sg:address":"220 Trott Cir",
    "sg:city":"Martinsville",
    "sg:classifiers":[
        {
            "category":"Education",
            "subcategory":"School",
            "type":"Public Place"
        }
    ],
    "sg:phone":"+1 276 957 2226",
    "sg:postcode":"24112",
    "sg:province":"VA",
    "wof:name":"Carver Elementary School",
    "wof:placetype":"venue"
},
  "geometry": {"coordinates":[-79.940303,36.673079],"type":"Point"}
}