{
  "type": "Feature",
  "properties": {
    "addr:full":"1100 Grand Hamptons Dr Herndon VA 20170",
    "addr:housenumber":"1100",
    "addr:postcode":"20170",
    "addr:street":"Grand Hamptons Dr",
    "iso:country":"US",
    "sg:address":"1100 Grand Hamptons Dr",
    "sg:city":"Herndon",
    "sg:classifiers":[
        {
            "category":"Professional",
            "subcategory":"Management & Consulting",
            "type":"Services"
        }
    ],
    "sg:phone":"+1 703 433 9733",
    "sg:postcode":"20170",
    "sg:province":"VA",
    "wof:name":"Scrip Pharmacy Solutions",
    "wof:placetype":"venue"
},
  "geometry": {"coordinates":[-77.368083,39.00709],"type":"Point"}
}