{
  "type": "Feature",
  "properties": {
    "iso:country":"US",
    "sg:address":"9900 Lee Hwy",
    "sg:city":"Fairfax",
    "sg:classifiers":[
        {
            "category":"Shopping",
            "subcategory":"Computers & Home Electronics",
            "type":"Retail Goods"
        }
    ],
    "sg:phone":"+1 703 246 9360",
    "sg:postcode":"22030",
    "sg:province":"VA",
    "sg:tags":[
        "software"
    ],
    "wof:name":"Inforeliance Corp",
    "wof:placetype":"venue"
},
  "geometry": {"coordinates":[-77.285355,38.863444],"type":"Point"}
}