{
  "type": "Feature",
  "properties": {
    "iso:country":"US",
    "sg:address":"4941 Nine Mile Rd",
    "sg:city":"Richmond",
    "sg:classifiers":[
        {
            "category":"Shopping",
            "subcategory":"Optical Goods",
            "type":"Retail Goods"
        }
    ],
    "sg:phone":"+1 804 222 0557",
    "sg:postcode":"23223",
    "sg:province":"VA",
    "wof:name":"Bertram M Brown",
    "wof:placetype":"venue"
},
  "geometry": {"coordinates":[-77.36992600000001,37.544155],"type":"Point"}
}