{
  "type": "Feature",
  "properties": {
    "addr:full":"15059 Conference Center Dr Chantilly VA 20151",
    "addr:housenumber":"15059",
    "addr:postcode":"20151",
    "addr:street":"Conference Center Dr",
    "iso:country":"US",
    "sg:address":"15059 Conference Center Dr",
    "sg:city":"Chantilly",
    "sg:classifiers":[
        {
            "category":"Professional",
            "subcategory":"Research",
            "type":"Services"
        }
    ],
    "sg:phone":"+1 703 263 3380",
    "sg:postcode":"20151",
    "sg:province":"VA",
    "sg:tags":[
        "commercial",
        "physical"
    ],
    "wof:name":"Ball Corp",
    "wof:placetype":"venue"
},
  "geometry": {"coordinates":[-77.45997199999999,38.8797],"type":"Point"}
}