{
  "type": "Feature",
  "properties": {
    "addr:full":"11627 W Broad St Henrico VA 23233",
    "addr:housenumber":"11627",
    "addr:postcode":"23233",
    "addr:street":"W Broad St",
    "iso:country":"US",
    "sg:address":"11627 W Broad St",
    "sg:city":"Henrico",
    "sg:classifiers":[
        {
            "category":"Shopping",
            "subcategory":"Crafts & Fabrics",
            "type":"Retail Goods"
        },
        {
            "category":"Manufacturing",
            "subcategory":"Pottery",
            "type":"Manufacturing & Wholesale Goods"
        }
    ],
    "sg:phone":"+1 804 364 0180",
    "sg:postcode":"23233",
    "sg:province":"VA",
    "sg:tags":[
        "ceramic",
        "art",
        "supply",
        "products-decorative",
        "instruction",
        "ceramics-equipment"
    ],
    "sg:website":"http://www.colormemine.com",
    "wof:name":"Color Me Mine",
    "wof:placetype":"venue"
},
  "geometry": {"coordinates":[-77.616647,37.652359],"type":"Point"}
}