{
  "type": "Feature",
  "properties": {
    "iso:country":"US",
    "sg:address":"406 Cowardin Ave",
    "sg:city":"Richmond",
    "sg:classifiers":[
        {
            "category":"Restaurant",
            "type":"Food & Drink"
        }
    ],
    "sg:phone":"+1 804 612 3194",
    "sg:postcode":"23224",
    "sg:province":"VA",
    "wof:name":"Bamboo",
    "wof:placetype":"venue"
},
  "geometry": {"coordinates":[-77.451207,37.522279],"type":"Point"}
}