{
  "type": "Feature",
  "properties": {
    "iso:country":"US",
    "sg:address":"1428 Kempsville Rd",
    "sg:city":"Chesapeake",
    "sg:classifiers":[
        {
            "category":"Professional",
            "subcategory":"Lawyer & Legal Services",
            "type":"Services"
        }
    ],
    "sg:phone":"+1 757 547 5155",
    "sg:postcode":"23320",
    "sg:province":"VA",
    "sg:tags":[
        "attorney"
    ],
    "wof:name":"Terrence P Martin",
    "wof:placetype":"venue"
},
  "geometry": {"coordinates":[-76.203622,36.76407],"type":"Point"}
}