{
  "type": "Feature",
  "properties": {
    "iso:country":"US",
    "sg:address":"109 Hillcrest Ave",
    "sg:city":"Independence",
    "sg:classifiers":[
        {
            "category":"Place Of Worship",
            "subcategory":"Church",
            "type":"Public Place"
        },
        {
            "category":"Place Of Worship",
            "type":"Public Place"
        }
    ],
    "sg:phone":"+1 276 773 2446",
    "sg:postcode":"24348",
    "sg:province":"VA",
    "sg:tags":[
        "churches-baptist-general",
        "churches-baptist"
    ],
    "wof:name":"First Baptist Church Of Independence",
    "wof:placetype":"venue"
},
  "geometry": {"coordinates":[-81.14510300000001,36.622471],"type":"Point"}
}