{
  "type": "Feature",
  "properties": {
    "iso:country":"US",
    "sg:address":"132 New York Ave",
    "sg:city":"Harrisonburg",
    "sg:classifiers":[
        {
            "category":"Recreation",
            "type":"Entertainment"
        }
    ],
    "sg:phone":"+1 540 568 6777",
    "sg:postcode":"22801",
    "sg:province":"VA",
    "sg:tags":[
        "club",
        "membership"
    ],
    "wof:name":"Shenandoah Mtn Touring LLC",
    "wof:placetype":"venue"
},
  "geometry": {"coordinates":[-78.880325,38.440343],"type":"Point"}
}