{
  "type": "Feature",
  "properties": {
    "addr:full":"56 Hammocks Dr Rocky Mount VA 24151",
    "addr:housenumber":"56",
    "addr:postcode":"24151",
    "addr:street":"Hammocks Dr",
    "iso:country":"US",
    "sg:address":"56 Hammocks Dr",
    "sg:city":"Rocky Mount",
    "sg:classifiers":[
        {
            "category":"Building & Trades",
            "subcategory":"Construction",
            "type":"Services"
        }
    ],
    "sg:phone":"+1 540 489 4693",
    "sg:postcode":"24151",
    "sg:province":"VA",
    "sg:tags":[
        "house"
    ],
    "wof:name":"BRB Enterprises",
    "wof:placetype":"venue"
},
  "geometry": {"coordinates":[-79.87570700000001,37.045236],"type":"Point"}
}