{
  "type": "Feature",
  "properties": {
    "addr:full":"917 W Grace St Richmond VA 23220",
    "addr:housenumber":"917",
    "addr:postcode":"23220",
    "addr:street":"W Grace St",
    "iso:country":"US",
    "sg:address":"917 W Grace St",
    "sg:city":"Richmond",
    "sg:classifiers":[
        {
            "category":"Cafe",
            "type":"Food & Drink"
        },
        {
            "category":"Restaurant",
            "type":"Food & Drink"
        }
    ],
    "sg:menulink":"http://www.allmenus.com/va/richmond/285200-ipanema-cafe/menu/",
    "sg:phone":"+1 804 213 0190",
    "sg:postcode":"23220",
    "sg:province":"VA",
    "sg:tags":[
        "vegetarian",
        "american"
    ],
    "wof:name":"Ipanema Cafe",
    "wof:placetype":"venue"
},
  "geometry": {"coordinates":[-77.45250900000001,37.550243],"type":"Point"}
}