{
  "type": "Feature",
  "properties": {
    "addr:full":"300 Pantops Ctr Charlottesville VA 22911",
    "addr:housenumber":"300",
    "addr:postcode":"22911",
    "addr:street":"Pantops Ctr",
    "iso:country":"US",
    "sg:address":"300 Pantops Ctr",
    "sg:city":"Charlottesville",
    "sg:classifiers":[
        {
            "category":"Restaurant",
            "type":"Food & Drink"
        }
    ],
    "sg:menulink":"http://www.allmenus.com/va/rivanna/147575-subway/menu/",
    "sg:phone":"+1 434 984 0652",
    "sg:postcode":"22911",
    "sg:province":"VA",
    "sg:tags":[
        "american",
        "sandwich"
    ],
    "wof:name":"Subway",
    "wof:placetype":"venue"
},
  "geometry": {"coordinates":[-78.456557,38.031796],"type":"Point"}
}