{
  "type": "Feature",
  "properties": {
    "addr:full":"320 Braehead Dr Fredericksburg VA 22401",
    "addr:housenumber":"320",
    "addr:postcode":"22401",
    "addr:street":"Braehead Dr",
    "iso:country":"US",
    "sg:address":"320 Braehead Dr",
    "sg:city":"Fredericksburg",
    "sg:classifiers":[
        {
            "category":"Organizations",
            "subcategory":"Community Association",
            "type":"Services"
        }
    ],
    "sg:phone":"+1 540 373 9086",
    "sg:postcode":"22401",
    "sg:province":"VA",
    "wof:name":"First Catholc Slovak Union U S",
    "wof:placetype":"venue"
},
  "geometry": {"coordinates":[-77.47363799999999,38.276612],"type":"Point"}
}