{
  "type": "Feature",
  "properties": {
    "addr:full":"6432 Overbrook St Falls Church VA 22043",
    "addr:housenumber":"6432",
    "addr:postcode":"22043",
    "addr:street":"Overbrook St",
    "iso:country":"US",
    "sg:address":"6432 Overbrook St",
    "sg:city":"Falls Church",
    "sg:classifiers":[
        {
            "category":"Building & Trades",
            "subcategory":"Construction",
            "type":"Services"
        }
    ],
    "sg:phone":"+1 703 237 2217",
    "sg:postcode":"22043",
    "sg:province":"VA",
    "sg:tags":[
        "repairing",
        "remodeling",
        "contractor"
    ],
    "wof:name":"Barber's Home Repair & Imprvmt",
    "wof:placetype":"venue"
},
  "geometry": {"coordinates":[-77.16082900000001,38.90397],"type":"Point"}
}