{
  "type": "Feature",
  "properties": {
    "iso:country":"US",
    "sg:address":"2200 Opitz Blvd",
    "sg:city":"Woodbridge",
    "sg:classifiers":[
        {
            "category":"Banks & Credit Unions",
            "subcategory":"Investment Brokerage",
            "type":"Services"
        },
        {
            "category":"Professional",
            "subcategory":"Management & Consulting",
            "type":"Services"
        }
    ],
    "sg:phone":"+1 703 494 6215",
    "sg:postcode":"22191",
    "sg:province":"VA",
    "sg:tags":[
        "consultant",
        "planning",
        "financial"
    ],
    "wof:name":"Accountables",
    "wof:placetype":"venue"
},
  "geometry": {"coordinates":[-77.277597,38.633026],"type":"Point"}
}