{
  "type": "Feature",
  "properties": {
    "addr:full":"321 W Farmington Rd Virginia Beach VA 23454",
    "addr:housenumber":"321",
    "addr:postcode":"23454",
    "addr:street":"W Farmington Rd",
    "iso:country":"US",
    "sg:address":"321 W Farmington Rd",
    "sg:city":"Virginia Beach",
    "sg:classifiers":[
        {
            "category":"Shopping",
            "subcategory":"Hobbies, Toys, & Games",
            "type":"Retail Goods"
        }
    ],
    "sg:phone":"+1 757 486 1408",
    "sg:postcode":"23454",
    "sg:province":"VA",
    "sg:website":"www.toymeister.com",
    "wof:name":"Toymeister",
    "wof:placetype":"venue"
},
  "geometry": {"coordinates":[-76.045489,36.844031],"type":"Point"}
}