{
  "type": "Feature",
  "properties": {
    "iso:country":"US",
    "sg:address":"8028 Kidwell Town Ct",
    "sg:city":"Vienna",
    "sg:classifiers":[
        {
            "category":"Health Services",
            "subcategory":"Doctor",
            "type":"Services"
        }
    ],
    "sg:phone":"+1 267 253 1079",
    "sg:postcode":"22182",
    "sg:province":"VA",
    "wof:name":"David Asgari",
    "wof:placetype":"venue"
},
  "geometry": {"coordinates":[-77.22239500000001,38.909854],"type":"Point"}
}