{
  "type": "Feature",
  "properties": {
    "addr:full":"1323 Merrie Ridge Rd Mc Lean VA 22101",
    "addr:housenumber":"1323",
    "addr:postcode":"22101",
    "addr:street":"Merrie Ridge Rd",
    "iso:country":"US",
    "sg:address":"1323 Merrie Ridge Rd",
    "sg:city":"Mc Lean",
    "sg:classifiers":[
        {
            "category":"Museum",
            "type":"Entertainment"
        }
    ],
    "sg:phone":"+1 703 525 7616",
    "sg:postcode":"22101",
    "sg:province":"VA",
    "sg:tags":[
        "gallery"
    ],
    "wof:name":"Smithsonian Institution",
    "wof:placetype":"venue"
},
  "geometry": {"coordinates":[-77.129435,38.935477],"type":"Point"}
}