{
  "type": "Feature",
  "properties": {
    "addr:full":"725 W Broad St Richmond VA 23220",
    "addr:housenumber":"725",
    "addr:postcode":"23220",
    "addr:street":"W Broad St",
    "iso:country":"US",
    "sg:address":"725 W Broad St",
    "sg:city":"Richmond",
    "sg:classifiers":[
        {
            "category":"Recreation",
            "type":"Entertainment"
        }
    ],
    "sg:phone":"+1 804 249 6509",
    "sg:postcode":"23220",
    "sg:province":"VA",
    "sg:tags":[
        "karate",
        "judo",
        "instr"
    ],
    "wof:name":"Richmond Brazilian Jiu-Jitsu",
    "wof:placetype":"venue"
},
  "geometry": {"coordinates":[-77.449094,37.549749],"type":"Point"}
}