{
  "type": "Feature",
  "properties": {
    "addr:full":"2215 Riverside Rd Marion VA 24354",
    "addr:housenumber":"2215",
    "addr:postcode":"24354",
    "addr:street":"Riverside Rd",
    "iso:country":"US",
    "sg:address":"2215 Riverside Rd",
    "sg:city":"Marion",
    "sg:classifiers":[
        {
            "category":"Food & Beverages",
            "subcategory":"Groceries & Convenience Stores",
            "type":"Retail Goods"
        }
    ],
    "sg:phone":"+1 276 783 7863",
    "sg:postcode":"24354",
    "sg:province":"VA",
    "sg:tags":[
        "station",
        "gasoline"
    ],
    "wof:name":"Blevins Grocery",
    "wof:placetype":"venue"
},
  "geometry": {"coordinates":[-81.592073,36.785407],"type":"Point"}
}