{
  "type": "Feature",
  "properties": {
    "addr:full":"1205 Crozet Ave Crozet VA 22932",
    "addr:housenumber":"1205",
    "addr:postcode":"22932",
    "addr:street":"Crozet Ave",
    "iso:country":"US",
    "sg:address":"1205 Crozet Ave",
    "sg:city":"Crozet",
    "sg:classifiers":[
        {
            "category":"Building & Trades",
            "subcategory":"Landscaping Services",
            "type":"Services"
        }
    ],
    "sg:phone":"+1 434 823 4021",
    "sg:postcode":"22932",
    "sg:province":"VA",
    "sg:tags":[
        "tree"
    ],
    "wof:name":"Arbor Life Prof Tree Care",
    "wof:placetype":"venue"
},
  "geometry": {"coordinates":[-78.699574,38.080885],"type":"Point"}
}