{
  "type": "Feature",
  "properties": {
    "iso:country":"US",
    "sg:address":"4769 Hermitage Rd",
    "sg:city":"Virginia Beach",
    "sg:classifiers":[
        {
            "category":"Professional",
            "subcategory":"Management & Consulting",
            "type":"Services"
        }
    ],
    "sg:phone":"+1 757 412 1170",
    "sg:postcode":"23455",
    "sg:province":"VA",
    "sg:tags":[
        "personnel",
        "consultant"
    ],
    "wof:name":"Mc Nulty Management Group",
    "wof:placetype":"venue"
},
  "geometry": {"coordinates":[-76.138165,36.895568],"type":"Point"}
}