{
  "type": "Feature",
  "properties": {
    "iso:country":"US",
    "sg:address":"12 Shop Rd",
    "sg:city":"Lexington",
    "sg:classifiers":[
        {
            "category":"Taxi",
            "type":"Transportation"
        }
    ],
    "sg:phone":"+1 540 464 3198",
    "sg:postcode":"24450",
    "sg:province":"VA",
    "sg:tags":[
        "taxicab"
    ],
    "wof:name":"Frank's Cab Co",
    "wof:placetype":"venue"
},
  "geometry": {"coordinates":[-79.425956,37.78923],"type":"Point"}
}