{
  "type": "Feature",
  "properties": {
    "addr:full":"1218 Colonial Rd Mc Lean VA 22101",
    "addr:housenumber":"1218",
    "addr:postcode":"22101",
    "addr:street":"Colonial Rd",
    "iso:country":"US",
    "sg:address":"1218 Colonial Rd",
    "sg:city":"Mc Lean",
    "sg:classifiers":[
        {
            "category":"Health Services",
            "subcategory":"Optometrist",
            "type":"Services"
        }
    ],
    "sg:phone":"+1 703 442 4544",
    "sg:postcode":"22101",
    "sg:province":"VA",
    "wof:name":"Flocos Dr Grge J Optmetrist Od",
    "wof:placetype":"venue"
},
  "geometry": {"coordinates":[-77.17741100000001,38.943296],"type":"Point"}
}