{
  "type": "Feature",
  "properties": {
    "addr:full":"306 Libbie Ave Richmond VA 23226",
    "addr:housenumber":"306",
    "addr:postcode":"23226",
    "addr:street":"Libbie Ave",
    "iso:country":"US",
    "sg:address":"306 Libbie Ave",
    "sg:city":"Richmond",
    "sg:classifiers":[
        {
            "category":"Food & Beverages",
            "subcategory":"Specialty",
            "type":"Retail Goods"
        }
    ],
    "sg:phone":"+1 804 726 6062",
    "sg:postcode":"23226",
    "sg:province":"VA",
    "wof:name":"Corner Store/Low Carb Shoppe",
    "wof:placetype":"venue"
},
  "geometry": {"coordinates":[-77.518237,37.573913],"type":"Point"}
}