{
  "type": "Feature",
  "properties": {
    "iso:country":"US",
    "sg:address":"2120 N Military Rd",
    "sg:city":"Arlington",
    "sg:classifiers":[
        {
            "category":"Shopping",
            "subcategory":"Computers & Home Electronics",
            "type":"Retail Goods"
        }
    ],
    "sg:phone":"+1 703 558 0300",
    "sg:postcode":"22207",
    "sg:province":"VA",
    "sg:tags":[
        "software"
    ],
    "wof:name":"Info Managers Of America",
    "wof:placetype":"venue"
},
  "geometry": {"coordinates":[-77.108845,38.897519],"type":"Point"}
}