{
  "type": "Feature",
  "properties": {
    "addr:full":"1015 W Main St Waverly VA 23890",
    "addr:housenumber":"1015",
    "addr:postcode":"23890",
    "addr:street":"W Main St",
    "iso:country":"US",
    "sg:address":"1015 W Main St",
    "sg:city":"Waverly",
    "sg:classifiers":[
        {
            "category":"Social Services",
            "type":"Services"
        }
    ],
    "sg:phone":"+1 804 834 2010",
    "sg:postcode":"23890",
    "sg:province":"VA",
    "wof:name":"Saxifrage",
    "wof:placetype":"venue"
},
  "geometry": {"coordinates":[-77.11773100000001,37.026788],"type":"Point"}
}