{
  "type": "Feature",
  "properties": {
    "addr:full":"1168 Peters Creek Rd NW Roanoke VA 24017",
    "addr:housenumber":"1168",
    "addr:postcode":"24017",
    "addr:street":"Peters Creek Rd Nw",
    "iso:country":"US",
    "sg:address":"1168 Peters Creek Rd NW",
    "sg:city":"Roanoke",
    "sg:classifiers":[
        {
            "category":"Autos & Motor Vehicles",
            "subcategory":"Auto Supplies",
            "type":"Retail Goods"
        }
    ],
    "sg:phone":"+1 540 562 4371",
    "sg:postcode":"24017",
    "sg:province":"VA",
    "sg:tags":[
        "automobile",
        "parts"
    ],
    "sg:website":"www.advance.com",
    "wof:name":"Advance Auto Parts Inc",
    "wof:placetype":"venue"
},
  "geometry": {"coordinates":[-80.007801,37.298544],"type":"Point"}
}