{
  "type": "Feature",
  "properties": {
    "addr:full":"781 Ledford Ln Smithfield VA 23430",
    "addr:housenumber":"781",
    "addr:postcode":"23430",
    "addr:street":"Ledford Ln",
    "iso:country":"US",
    "sg:address":"781 Ledford Ln",
    "sg:city":"Smithfield",
    "sg:classifiers":[
        {
            "category":"Building & Trades",
            "subcategory":"Construction",
            "type":"Services"
        }
    ],
    "sg:phone":"+1 757 357 2074",
    "sg:postcode":"23430",
    "sg:province":"VA",
    "sg:tags":[
        "house",
        "contractor"
    ],
    "wof:name":"Henderson Cr Co",
    "wof:placetype":"venue"
},
  "geometry": {"coordinates":[-76.591492,36.966089],"type":"Point"}
}