{
  "type": "Feature",
  "properties": {
    "iso:country":"US",
    "sg:address":"9522 Narragansett Pl",
    "sg:city":"Vienna",
    "sg:classifiers":[
        {
            "category":"Communications",
            "subcategory":"Film & Video Production",
            "type":"Services"
        }
    ],
    "sg:phone":"+1 703 281 1808",
    "sg:postcode":"22180",
    "sg:province":"VA",
    "sg:tags":[
        "make",
        "artist"
    ],
    "wof:name":"Ann Hundley",
    "wof:placetype":"venue"
},
  "geometry": {"coordinates":[-77.27115000000001,38.913244],"type":"Point"}
}