{
  "type": "Feature",
  "properties": {
    "addr:full":"1345 Kempsville Rd Virginia Beach VA 23464",
    "addr:housenumber":"1345",
    "addr:postcode":"23464",
    "addr:street":"Kempsville Rd",
    "iso:country":"US",
    "sg:address":"1345 Kempsville Rd",
    "sg:city":"Virginia Beach",
    "sg:classifiers":[
        {
            "category":"Cinema",
            "subcategory":"Movie Rental",
            "type":"Entertainment"
        }
    ],
    "sg:phone":"+1 757 420 5554",
    "sg:postcode":"23464",
    "sg:province":"VA",
    "sg:tags":[
        "leasing",
        "video",
        "disc",
        "tape"
    ],
    "sg:website":"www.blockbuster.com",
    "wof:name":"Blockbuster Video",
    "wof:placetype":"venue"
},
  "geometry": {"coordinates":[-76.174498,36.798744],"type":"Point"}
}