{
  "type": "Feature",
  "properties": {
    "iso:country":"US",
    "sg:address":"1306 Concord St",
    "sg:city":"Selma",
    "sg:classifiers":[
        {
            "category":"Professional",
            "subcategory":"Computer Services",
            "type":"Services"
        }
    ],
    "sg:phone":"+1 540 862 7957",
    "sg:postcode":"24474",
    "sg:province":"VA",
    "sg:tags":[
        "datum"
    ],
    "wof:name":"Tracie Smith",
    "wof:placetype":"venue"
},
  "geometry": {"coordinates":[-79.849378,37.802299],"type":"Point"}
}