{
  "type": "Feature",
  "properties": {
    "iso:country":"US",
    "sg:address":"987 Meadow View Rd",
    "sg:city":"Bristol",
    "sg:classifiers":[
        {
            "category":"Autos & Motor Vehicles",
            "subcategory":"Automobile Sales",
            "type":"Retail Goods"
        }
    ],
    "sg:phone":"+1 423 652 2933",
    "sg:postcode":"37620",
    "sg:province":"VA",
    "sg:tags":[
        "used"
    ],
    "wof:name":"Bryans Auto Sales & Service",
    "wof:placetype":"venue"
},
  "geometry": {"coordinates":[-82.26016,36.578025],"type":"Point"}
}