{
  "type": "Feature",
  "properties": {
    "iso:country":"US",
    "sg:address":"7441 Willoughby Ln",
    "sg:city":"Manassas",
    "sg:classifiers":[
        {
            "category":"Professional",
            "subcategory":"Business Services",
            "type":"Services"
        }
    ],
    "sg:phone":"+1 703 335 9748",
    "sg:postcode":"20109",
    "sg:province":"VA",
    "wof:name":"Valhalla Financial Group",
    "wof:placetype":"venue"
},
  "geometry": {"coordinates":[-77.52752700000001,38.794694],"type":"Point"}
}