{
  "type": "Feature",
  "properties": {
    "iso:country":"US",
    "sg:address":"38 Murray Ct",
    "sg:city":"Roanoke",
    "sg:classifiers":[
        {
            "category":"Real Estate",
            "subcategory":"Real Estate Agent",
            "type":"Services"
        }
    ],
    "sg:phone":"+1 540 977 1777",
    "sg:postcode":"24019",
    "sg:province":"VA",
    "wof:name":"Owens & Company Realtors",
    "wof:placetype":"venue"
},
  "geometry": {"coordinates":[-79.90848,37.351381],"type":"Point"}
}