{
  "type": "Feature",
  "properties": {
    "iso:country":"US",
    "sg:address":"807 Woodberry Rd",
    "sg:city":"Richmond",
    "sg:classifiers":[
        {
            "category":"Autos & Motor Vehicles",
            "subcategory":"Fuel & Gas Station",
            "type":"Retail Goods"
        }
    ],
    "sg:phone":"+1 804 282 7990",
    "sg:postcode":"23229",
    "sg:province":"VA",
    "sg:tags":[
        "station",
        "gasoline"
    ],
    "wof:name":"Luck Stone Inc",
    "wof:placetype":"venue"
},
  "geometry": {"coordinates":[-77.540797,37.592045],"type":"Point"}
}