{
  "type": "Feature",
  "properties": {
    "iso:country":"US",
    "sg:address":"6826 Atmore Dr",
    "sg:city":"Richmond",
    "sg:classifiers":[
        {
            "category":"Retail",
            "subcategory":"Auto Repair",
            "type":"Services"
        }
    ],
    "sg:phone":"+1 804 275 8733",
    "sg:postcode":"23225",
    "sg:province":"VA",
    "sg:tags":[
        "towing"
    ],
    "wof:name":"On Tha Way Towing",
    "wof:placetype":"venue"
},
  "geometry": {"coordinates":[-77.522761,37.504001],"type":"Point"}
}