{
  "type": "Feature",
  "properties": {
    "iso:country":"US",
    "sg:address":"6263 Portsmouth Blvd",
    "sg:city":"Portsmouth",
    "sg:classifiers":[
        {
            "category":"Health Services",
            "subcategory":"Doctor",
            "type":"Services"
        }
    ],
    "sg:phone":"+1 757 488 1285",
    "sg:postcode":"23701",
    "sg:province":"VA",
    "wof:name":"Couch Mary Jean",
    "wof:placetype":"venue"
},
  "geometry": {"coordinates":[-76.38946,36.821066],"type":"Point"}
}