{
  "type": "Feature",
  "properties": {
    "addr:full":"261 Oak Park Rd Madison VA 22727",
    "addr:housenumber":"261",
    "addr:postcode":"22727",
    "addr:street":"Oak Park Rd",
    "iso:country":"US",
    "sg:address":"261 Oak Park Rd",
    "sg:city":"Madison",
    "sg:classifiers":[
        {
            "category":"Building & Trades",
            "subcategory":"Construction",
            "type":"Services"
        }
    ],
    "sg:phone":"+1 540 948 5900",
    "sg:postcode":"22727",
    "sg:province":"VA",
    "sg:tags":[
        "contractor"
    ],
    "wof:name":"P J Williams Co",
    "wof:placetype":"venue"
},
  "geometry": {"coordinates":[-78.25162899999999,38.376095],"type":"Point"}
}