{
  "type": "Feature",
  "properties": {
    "addr:full":"1730 George Washington Memorial Hwy Yorktown VA 23693",
    "addr:housenumber":"1730",
    "addr:postcode":"23693",
    "addr:street":"George Washington Memorial Hwy",
    "iso:country":"US",
    "sg:address":"1730 George Washington Memorial Hwy",
    "sg:city":"Yorktown",
    "sg:classifiers":[
        {
            "category":"Personal",
            "subcategory":"Beauty Salon",
            "type":"Services"
        }
    ],
    "sg:phone":"+1 757 595 0104",
    "sg:postcode":"23693",
    "sg:province":"VA",
    "sg:tags":[
        "shop"
    ],
    "wof:name":"Beauty & Imaging Center",
    "wof:placetype":"venue"
},
  "geometry": {"coordinates":[-76.45583999999999,37.108009],"type":"Point"}
}