{
  "type": "Feature",
  "properties": {
    "addr:full":"1870 Amherst St Winchester VA 22601",
    "addr:housenumber":"1870",
    "addr:postcode":"22601",
    "addr:street":"Amherst St",
    "iso:country":"US",
    "sg:address":"1870 Amherst St",
    "sg:city":"Winchester",
    "sg:classifiers":[
        {
            "category":"Health Services",
            "subcategory":"Doctor",
            "type":"Services"
        }
    ],
    "sg:phone":"+1 540 667 4546",
    "sg:postcode":"22601",
    "sg:province":"VA",
    "sg:tags":[
        "physician",
        "surgeon"
    ],
    "wof:name":"Winchester Women's Spec",
    "wof:placetype":"venue"
},
  "geometry": {"coordinates":[-78.196916,39.191236],"type":"Point"}
}