{
  "type": "Feature",
  "properties": {
    "iso:country":"US",
    "sg:address":"4 Woodrum Pl",
    "sg:city":"Poquoson",
    "sg:classifiers":[
        {
            "category":"Shopping",
            "subcategory":"Jewelry",
            "type":"Retail Goods"
        }
    ],
    "sg:phone":"+1 757 868 5291",
    "sg:postcode":"23662",
    "sg:province":"VA",
    "wof:name":"Premier Design Jewelry",
    "wof:placetype":"venue"
},
  "geometry": {"coordinates":[-76.399716,37.136774],"type":"Point"}
}