{
  "type": "Feature",
  "properties": {
    "iso:country":"US",
    "sg:address":"6123 Oaklawn Ln",
    "sg:city":"Woodbridge",
    "sg:classifiers":[
        {
            "category":"Building & Trades",
            "subcategory":"Electrical",
            "type":"Services"
        }
    ],
    "sg:phone":"+1 703 670 0520",
    "sg:postcode":"22193",
    "sg:province":"VA",
    "sg:tags":[
        "industrial",
        "electrician",
        "contractors-commercial",
        "electric"
    ],
    "wof:name":"Structured Wiring Solutions",
    "wof:placetype":"venue"
},
  "geometry": {"coordinates":[-77.391908,38.665847],"type":"Point"}
}