{
  "type": "Feature",
  "properties": {
    "addr:full":"1800 Wilson Blvd Arlington VA 22201",
    "addr:housenumber":"1800",
    "addr:postcode":"22201",
    "addr:street":"Wilson Blvd",
    "iso:country":"US",
    "sg:address":"1800 Wilson Blvd",
    "sg:city":"Arlington",
    "sg:classifiers":[
        {
            "category":"Building & Trades",
            "subcategory":"Construction",
            "type":"Services"
        }
    ],
    "sg:phone":"+1 703 312 8653",
    "sg:postcode":"22201",
    "sg:province":"VA",
    "sg:tags":[
        "contractor"
    ],
    "wof:name":"Hollady Corporation",
    "wof:placetype":"venue"
},
  "geometry": {"coordinates":[-77.07957500000001,38.893375],"type":"Point"}
}