{
  "type": "Feature",
  "properties": {
    "addr:full":"36 Horsepen Rd Farmville VA 23901",
    "addr:housenumber":"36",
    "addr:postcode":"23901",
    "addr:street":"Horsepen Rd",
    "iso:country":"US",
    "sg:address":"36 Horsepen Rd",
    "sg:city":"Farmville",
    "sg:classifiers":[
        {
            "category":"Wholesale",
            "subcategory":"Sporting Goods",
            "type":"Manufacturing & Wholesale Goods"
        },
        {
            "category":"Building & Trades",
            "subcategory":"Construction",
            "type":"Services"
        }
    ],
    "sg:phone":"+1 434 392 6680",
    "sg:postcode":"23901",
    "sg:province":"VA",
    "sg:tags":[
        "equipment",
        "swimming",
        "pool",
        "contractor"
    ],
    "wof:name":"Scott Reese Construction",
    "wof:placetype":"venue"
},
  "geometry": {"coordinates":[-78.285101,37.418745],"type":"Point"}
}