{
  "type": "Feature",
  "properties": {
    "addr:full":"212 N Main St Bowling Green VA 22427",
    "addr:housenumber":"212",
    "addr:postcode":"22427",
    "addr:street":"N Main St",
    "iso:country":"US",
    "sg:address":"212 N Main St",
    "sg:city":"Bowling Green",
    "sg:classifiers":[
        {
            "category":"Banks & Credit Unions",
            "subcategory":"Financial Services",
            "type":"Services"
        }
    ],
    "sg:phone":"+1 804 633 5031",
    "sg:postcode":"22427",
    "sg:province":"VA",
    "sg:tags":[
        "company",
        "holding"
    ],
    "sg:website":"www.unionbankandtrust.com",
    "wof:name":"Union Bankshares Corp",
    "wof:placetype":"venue"
},
  "geometry": {"coordinates":[-77.34773,38.051781],"type":"Point"}
}