{
  "type": "Feature",
  "properties": {
    "iso:country":"US",
    "sg:address":"8338 Leesburg Pike",
    "sg:city":"Vienna",
    "sg:classifiers":[
        {
            "category":"Home & Garden",
            "subcategory":"Furniture",
            "type":"Retail Goods"
        }
    ],
    "sg:phone":"+1 703 848 4999",
    "sg:postcode":"22182",
    "sg:province":"VA",
    "wof:name":"Patio Place",
    "wof:placetype":"venue"
},
  "geometry": {"coordinates":[-77.234088,38.921577],"type":"Point"}
}