{
  "type": "Feature",
  "properties": {
    "addr:full":"4507 Nine Mile Rd Richmond VA 23223",
    "addr:housenumber":"4507",
    "addr:postcode":"23223",
    "addr:street":"Nine Mile Rd",
    "iso:country":"US",
    "sg:address":"4507 Nine Mile Rd",
    "sg:city":"Richmond",
    "sg:classifiers":[
        {
            "category":"Autos & Motor Vehicles",
            "subcategory":"Auto Supplies",
            "type":"Retail Goods"
        }
    ],
    "sg:phone":"+1 804 222 8105",
    "sg:postcode":"23223",
    "sg:province":"VA",
    "wof:name":"Pep Boys",
    "wof:placetype":"venue"
},
  "geometry": {"coordinates":[-77.3729,37.541925],"type":"Point"}
}