{
  "type": "Feature",
  "properties": {
    "addr:full":"6621 Shepherdstown Rd Warrenton VA 20187",
    "addr:postcode":"6621;20187",
    "addr:street":"Shepherdstown Rd",
    "iso:country":"US",
    "sg:address":"6621 Shepherdstown Rd",
    "sg:city":"Warrenton",
    "sg:classifiers":[
        {
            "category":"Manufacturing",
            "subcategory":"Metals",
            "type":"Manufacturing & Wholesale Goods"
        }
    ],
    "sg:phone":"+1 540 428 4361",
    "sg:postcode":"20187",
    "sg:province":"VA",
    "wof:name":"Bevs Engraving",
    "wof:placetype":"venue"
},
  "geometry": {"coordinates":[-77.69118400000001,38.759108],"type":"Point"}
}