{
  "type": "Feature",
  "properties": {
    "addr:full":"1214 Amherst Ave Richmond VA 23227",
    "addr:housenumber":"1214",
    "addr:postcode":"23227",
    "addr:street":"Amherst Ave",
    "iso:country":"US",
    "sg:address":"1214 Amherst Ave",
    "sg:city":"Richmond",
    "sg:classifiers":[
        {
            "category":"Wholesale",
            "subcategory":"Groceries",
            "type":"Manufacturing & Wholesale Goods"
        }
    ],
    "sg:phone":"+1 804 262 5476",
    "sg:postcode":"23227",
    "sg:province":"VA",
    "sg:tags":[
        "baker"
    ],
    "wof:name":"Bob's Cheesecakes-Distinction",
    "wof:placetype":"venue"
},
  "geometry": {"coordinates":[-77.45358899999999,37.590091],"type":"Point"}
}