{
  "type": "Feature",
  "properties": {
    "addr:full":"6567 Springfield Blvd Springfield VA 22150",
    "addr:housenumber":"6567",
    "addr:postcode":"22150",
    "addr:street":"Springfield Blvd",
    "iso:country":"US",
    "sg:address":"6567 Springfield Blvd",
    "sg:city":"Springfield",
    "sg:classifiers":[
        {
            "category":"Shopping",
            "type":"Retail Goods"
        }
    ],
    "sg:phone":"+1 703 719 9393",
    "sg:postcode":"22150",
    "sg:province":"VA",
    "sg:tags":[
        "merchandise"
    ],
    "wof:name":"Virginia Art Expo",
    "wof:placetype":"venue"
},
  "geometry": {"coordinates":[-77.18517199999999,38.777938],"type":"Point"}
}