{
  "type": "Feature",
  "properties": {
    "addr:full":"13609 Carriage Ford Rd Nokesville VA 20181",
    "addr:housenumber":"13609",
    "addr:postcode":"20181",
    "addr:street":"Carriage Ford Rd",
    "iso:country":"US",
    "sg:address":"13609 Carriage Ford Rd",
    "sg:city":"Nokesville",
    "sg:classifiers":[
        {
            "category":"Health Services",
            "subcategory":"Clinic",
            "type":"Services"
        }
    ],
    "sg:phone":"+1 703 594 3153",
    "sg:postcode":"20181",
    "sg:province":"VA",
    "wof:name":"Lactation Cnslt Prince William",
    "wof:placetype":"venue"
},
  "geometry": {"coordinates":[-77.584292,38.654545],"type":"Point"}
}