{
  "type": "Feature",
  "properties": {
    "addr:full":"11002 General Puller Hwy Hartfield VA 23071",
    "addr:housenumber":"11002",
    "addr:postcode":"23071",
    "addr:street":"General Puller Hwy",
    "iso:country":"US",
    "sg:address":"11002 General Puller Hwy",
    "sg:city":"Hartfield",
    "sg:classifiers":[
        {
            "category":"Real Estate",
            "subcategory":"Surveying",
            "type":"Services"
        }
    ],
    "sg:phone":"+1 804 776 9772",
    "sg:postcode":"23071",
    "sg:province":"VA",
    "sg:tags":[
        "surveyor"
    ],
    "wof:name":"Dalton D Brownley Jr-Land",
    "wof:placetype":"venue"
},
  "geometry": {"coordinates":[-76.447284,37.552012],"type":"Point"}
}