{
  "type": "Feature",
  "properties": {
    "addr:full":"706 W Abingdon Ct Alexandria VA 22314",
    "addr:housenumber":"706",
    "addr:postcode":"22314",
    "addr:street":"W Abingdon Ct",
    "iso:country":"US",
    "sg:address":"706 W Abingdon Ct",
    "sg:city":"Alexandria",
    "sg:classifiers":[
        {
            "category":"Autos & Motor Vehicles",
            "subcategory":"Automobile Sales",
            "type":"Retail Goods"
        }
    ],
    "sg:phone":"+1 703 999 5880",
    "sg:postcode":"22314",
    "sg:province":"VA",
    "wof:name":"Keady Olds & Maier Pllc",
    "wof:placetype":"venue"
},
  "geometry": {"coordinates":[-77.04475499999999,38.817574],"type":"Point"}
}