{
  "type": "Feature",
  "properties": {
    "addr:full":"17432 Frog Level Rd Ruther Glen VA 22546",
    "addr:housenumber":"17432",
    "addr:postcode":"22546",
    "addr:street":"Frog Level Rd",
    "iso:country":"US",
    "sg:address":"17432 Frog Level Rd",
    "sg:city":"Ruther Glen",
    "sg:classifiers":[
        {
            "category":"Freight",
            "type":"Transportation"
        }
    ],
    "sg:phone":"+1 804 994 2390",
    "sg:postcode":"22546",
    "sg:province":"VA",
    "sg:tags":[
        "local",
        "without",
        "storage",
        "hauling",
        "trucking"
    ],
    "wof:name":"Barlow F M Jr Hauling Inc",
    "wof:placetype":"venue"
},
  "geometry": {"coordinates":[-77.340991,37.855824],"type":"Point"}
}