{
  "type": "Feature",
  "properties": {
    "addr:full":"113 Front St E Coeburn VA 24230",
    "addr:housenumber":"113",
    "addr:postcode":"24230",
    "addr:street":"Front St E",
    "iso:country":"US",
    "sg:address":"113 Front St E",
    "sg:city":"Coeburn",
    "sg:classifiers":[
        {
            "category":"Shopping",
            "subcategory":"Discount & Variety Stores",
            "type":"Retail Goods"
        }
    ],
    "sg:phone":"+1 276 395 2322",
    "sg:postcode":"24230",
    "sg:province":"VA",
    "wof:name":"Hillbilly Pride Variety Shop",
    "wof:placetype":"venue"
},
  "geometry": {"coordinates":[-82.468056,36.943625],"type":"Point"}
}