{
  "type": "Feature",
  "properties": {
    "addr:full":"301 N Ripley St Apt 1227 Alexandria VA 22304",
    "addr:housenumber":"301;1227",
    "addr:postcode":"22304",
    "addr:street":"N Ripley St Apt",
    "iso:country":"US",
    "sg:address":"301 N Ripley St Apt 1227",
    "sg:city":"Alexandria",
    "sg:classifiers":[
        {
            "category":"Professional",
            "subcategory":"Computer Services",
            "type":"Services"
        }
    ],
    "sg:phone":"+1 703 801 8635",
    "sg:postcode":"22304",
    "sg:province":"VA",
    "sg:tags":[
        "publisher",
        "developer",
        "software"
    ],
    "wof:name":"G-Systems Management",
    "wof:placetype":"venue"
},
  "geometry": {"coordinates":[-77.126668,38.816451],"type":"Point"}
}