{
  "type": "Feature",
  "properties": {
    "iso:country":"US",
    "sg:address":"1469 Proescher St",
    "sg:city":"Norfolk",
    "sg:classifiers":[
        {
            "category":"Education",
            "subcategory":"Special Training",
            "type":"Public Place"
        }
    ],
    "sg:phone":"+1 757 747 9616",
    "sg:postcode":"23504",
    "sg:province":"VA",
    "sg:tags":[
        "tutoring"
    ],
    "wof:name":"Computer Tutoring Enterprises",
    "wof:placetype":"venue"
},
  "geometry": {"coordinates":[-76.273363,36.861416],"type":"Point"}
}