{
  "type": "Feature",
  "properties": {
    "iso:country":"US",
    "sg:address":"100 Washington St",
    "sg:city":"Portsmouth",
    "sg:classifiers":[
        {
            "category":"Professional",
            "subcategory":"Management & Consulting",
            "type":"Services"
        }
    ],
    "sg:phone":"+1 757 399 5359",
    "sg:postcode":"23704",
    "sg:province":"VA",
    "sg:tags":[
        "real estate"
    ],
    "wof:name":"Ghb Enterprises",
    "wof:placetype":"venue"
},
  "geometry": {"coordinates":[-76.304288,36.842408],"type":"Point"}
}