{
  "type": "Feature",
  "properties": {
    "iso:country":"US",
    "sg:address":"1803 Quivers Ky",
    "sg:city":"Chesapeake",
    "sg:classifiers":[
        {
            "category":"Building & Trades",
            "subcategory":"Construction",
            "type":"Services"
        }
    ],
    "sg:phone":"+1 757 547 3239",
    "sg:postcode":"23321",
    "sg:province":"VA",
    "sg:tags":[
        "nonresidential"
    ],
    "wof:name":"RE and Associates",
    "wof:placetype":"venue"
},
  "geometry": {"coordinates":[-76.432163,36.80934],"type":"Point"}
}