{
  "type": "Feature",
  "properties": {
    "addr:full":"1401 Belle Haven Rd Alexandria VA 22307",
    "addr:housenumber":"1401",
    "addr:postcode":"22307",
    "addr:street":"Belle Haven Rd",
    "iso:country":"US",
    "sg:address":"1401 Belle Haven Rd",
    "sg:city":"Alexandria",
    "sg:classifiers":[
        {
            "category":"Food & Beverages",
            "subcategory":"Groceries & Convenience Stores",
            "type":"Retail Goods"
        }
    ],
    "sg:phone":"+1 703 768 1310",
    "sg:postcode":"22307",
    "sg:province":"VA",
    "sg:tags":[
        "grocer",
        "eat",
        "alcoholic"
    ],
    "wof:name":"Pat's Market",
    "wof:placetype":"venue"
},
  "geometry": {"coordinates":[-77.05802199999999,38.780568],"type":"Point"}
}