{
  "type": "Feature",
  "properties": {
    "iso:country":"US",
    "sg:address":"1871 Seminole Trl",
    "sg:city":"Charlottesville",
    "sg:classifiers":[
        {
            "category":"Restaurant",
            "type":"Food & Drink"
        }
    ],
    "sg:phone":"+1 434 964 0038",
    "sg:postcode":"22901",
    "sg:province":"VA",
    "wof:name":"Tajmahal Restaurant",
    "wof:placetype":"venue"
},
  "geometry": {"coordinates":[-78.470596,38.087502],"type":"Point"}
}