{
  "type": "Feature",
  "properties": {
    "iso:country":"US",
    "sg:address":"8304 Old Courthouse Rd Ste D",
    "sg:city":"Vienna",
    "sg:classifiers":[
        {
            "category":"Personal",
            "subcategory":"Skin Care",
            "type":"Services"
        }
    ],
    "sg:phone":"+1 703 848 8884",
    "sg:postcode":"22182",
    "sg:province":"VA",
    "sg:website":"www.healthbeautyspa.com",
    "wof:name":"Ximena Skin Care Clinic",
    "wof:placetype":"venue"
},
  "geometry": {"coordinates":[-77.231774,38.914108],"type":"Point"}
}