{
  "type": "Feature",
  "properties": {
    "addr:full":"1700 N Moore St Ste 2100 Arlington VA 22209",
    "addr:housenumber":"1700",
    "addr:postcode":"22209",
    "addr:street":"N Moore St Ste 2100",
    "iso:country":"US",
    "sg:address":"1700 N Moore St Ste 2100",
    "sg:city":"Arlington",
    "sg:classifiers":[
        {
            "category":"Professional",
            "subcategory":"Computer Services",
            "type":"Services"
        }
    ],
    "sg:phone":"+1 703 248 4800",
    "sg:postcode":"22209",
    "sg:province":"VA",
    "sg:tags":[
        "equipment",
        "rooms-installation"
    ],
    "sg:website":"http://www.cscenterprises.com",
    "wof:name":"Computer Sciences Corporation",
    "wof:placetype":"venue"
},
  "geometry": {"coordinates":[-77.071472,38.89513],"type":"Point"}
}