{
  "type": "Feature",
  "properties": {
    "addr:full":"12705 Jefferson Ave Newport News VA 23602",
    "addr:housenumber":"12705",
    "addr:postcode":"23602",
    "addr:street":"Jefferson Ave",
    "iso:country":"US",
    "sg:address":"12705 Jefferson Ave",
    "sg:city":"Newport News",
    "sg:classifiers":[
        {
            "category":"Restaurant",
            "type":"Food & Drink"
        }
    ],
    "sg:menulink":"http://www.allmenus.com/va/newport-news/187932-mcdonalds/menu/",
    "sg:phone":"+1 757 833 3459",
    "sg:postcode":"23602",
    "sg:province":"VA",
    "sg:tags":[
        "burger",
        "american"
    ],
    "wof:name":"McDonald's",
    "wof:placetype":"venue"
},
  "geometry": {"coordinates":[-76.518621,37.136633],"type":"Point"}
}