{
  "type": "Feature",
  "properties": {
    "iso:country":"US",
    "sg:address":"4182 Lord Culpeper Ln",
    "sg:city":"Fairfax",
    "sg:classifiers":[
        {
            "category":"Utilities",
            "subcategory":"Telephone",
            "type":"Services"
        },
        {
            "category":"Professional",
            "subcategory":"Research",
            "type":"Services"
        }
    ],
    "sg:phone":"+1 703 359 1400",
    "sg:postcode":"22030",
    "sg:province":"VA",
    "sg:tags":[
        "accessory",
        "internet"
    ],
    "wof:name":"Pruetip LLC",
    "wof:placetype":"venue"
},
  "geometry": {"coordinates":[-77.311306,38.841406],"type":"Point"}
}