{
  "type": "Feature",
  "properties": {
    "iso:country":"US",
    "sg:address":"6425 Rose Hill Dr",
    "sg:city":"Alexandria",
    "sg:classifiers":[
        {
            "category":"Social Services",
            "subcategory":"Child Care",
            "type":"Services"
        }
    ],
    "sg:phone":"+1 703 719 6354",
    "sg:postcode":"22310",
    "sg:province":"VA",
    "sg:tags":[
        "day"
    ],
    "wof:name":"Maria Day Care Home",
    "wof:placetype":"venue"
},
  "geometry": {"coordinates":[-77.11232699999999,38.776522],"type":"Point"}
}