{
  "type": "Feature",
  "properties": {
    "addr:full":"4101 Plantation Rd NE Roanoke VA 24012",
    "addr:housenumber":"4101",
    "addr:postcode":"24012",
    "addr:street":"Plantation Rd Ne",
    "iso:country":"US",
    "sg:address":"4101 Plantation Rd NE",
    "sg:city":"Roanoke",
    "sg:classifiers":[
        {
            "category":"Autos & Motor Vehicles",
            "subcategory":"Fuel & Gas Station",
            "type":"Retail Goods"
        }
    ],
    "sg:phone":"+1 540 366 6135",
    "sg:postcode":"24012",
    "sg:province":"VA",
    "sg:tags":[
        "grocery",
        "station",
        "gasoline"
    ],
    "wof:name":"Turbo Food Mart",
    "wof:placetype":"venue"
},
  "geometry": {"coordinates":[-79.933199,37.313591],"type":"Point"}
}