{
  "type": "Feature",
  "properties": {
    "addr:full":"209 S Locust St Floyd VA 24091",
    "addr:housenumber":"209",
    "addr:postcode":"24091",
    "addr:street":"S Locust St",
    "iso:country":"US",
    "sg:address":"209 S Locust St",
    "sg:city":"Floyd",
    "sg:classifiers":[
        {
            "category":"Recreation",
            "type":"Entertainment"
        }
    ],
    "sg:phone":"+1 540 745 3378",
    "sg:postcode":"24091",
    "sg:province":"VA",
    "sg:tags":[
        "carnival"
    ],
    "wof:name":"Across The Way Production",
    "wof:placetype":"venue"
},
  "geometry": {"coordinates":[-80.319993,36.910499],"type":"Point"}
}