{
  "type": "Feature",
  "properties": {
    "addr:full":"5533 Scotts Pond Dr Williamsburg VA 23188",
    "addr:housenumber":"5533",
    "addr:postcode":"23188",
    "addr:street":"Scotts Pond Dr",
    "iso:country":"US",
    "sg:address":"5533 Scotts Pond Dr",
    "sg:city":"Williamsburg",
    "sg:classifiers":[
        {
            "category":"Professional",
            "subcategory":"Business Services",
            "type":"Services"
        }
    ],
    "sg:phone":"+1 757 565 0795",
    "sg:postcode":"23188",
    "sg:province":"VA",
    "wof:name":"Lorraine A Hopkins",
    "wof:placetype":"venue"
},
  "geometry": {"coordinates":[-76.743989,37.317521],"type":"Point"}
}