{
  "type": "Feature",
  "properties": {
    "addr:full":"105 N 2nd Ave Hopewell VA 23860",
    "addr:housenumber":"105",
    "addr:postcode":"23860",
    "addr:street":"N 2Nd Ave",
    "iso:country":"US",
    "sg:address":"105 N 2nd Ave",
    "sg:city":"Hopewell",
    "sg:classifiers":[
        {
            "category":"Personal",
            "type":"Services"
        }
    ],
    "sg:phone":"+1 804 458 9813",
    "sg:postcode":"23860",
    "sg:province":"VA",
    "sg:tags":[
        "bankruptcy"
    ],
    "wof:name":"Bruce Clark Law Offices",
    "wof:placetype":"venue"
},
  "geometry": {"coordinates":[-77.28828799999999,37.301618],"type":"Point"}
}