{
  "type": "Feature",
  "properties": {
    "addr:full":"11729 Flemish Mill Ct Oakton VA 22124",
    "addr:housenumber":"11729",
    "addr:postcode":"22124",
    "addr:street":"Flemish Mill Ct",
    "iso:country":"US",
    "sg:address":"11729 Flemish Mill Ct",
    "sg:city":"Oakton",
    "sg:classifiers":[
        {
            "category":"Wholesale",
            "subcategory":"Durable Goods & Equipment",
            "type":"Manufacturing & Wholesale Goods"
        },
        {
            "category":"Shopping",
            "subcategory":"Gifts & Souvenirs",
            "type":"Retail Goods"
        }
    ],
    "sg:phone":"+1 703 620 4435",
    "sg:postcode":"22124",
    "sg:province":"VA",
    "sg:tags":[
        "importer"
    ],
    "wof:name":"A Foreign Affair",
    "wof:placetype":"venue"
},
  "geometry": {"coordinates":[-77.35216,38.879965],"type":"Point"}
}