{
  "type": "Feature",
  "properties": {
    "addr:full":"2236 Queen St Portsmouth VA 23704",
    "addr:housenumber":"2236",
    "addr:postcode":"23704",
    "addr:street":"Queen St",
    "iso:country":"US",
    "sg:address":"2236 Queen St",
    "sg:city":"Portsmouth",
    "sg:classifiers":[
        {
            "category":"Health Services",
            "subcategory":"Doctor",
            "type":"Services"
        }
    ],
    "sg:phone":"+1 757 825 1732",
    "sg:postcode":"23704",
    "sg:province":"VA",
    "sg:tags":[
        "physician",
        "surgeon"
    ],
    "wof:name":"Joselito B Morales MD",
    "wof:placetype":"venue"
},
  "geometry": {"coordinates":[-76.327927,36.835587],"type":"Point"}
}