{
  "type": "Feature",
  "properties": {
    "addr:full":"132 Peaceful Ln Clifton Forge VA 24422",
    "addr:housenumber":"132",
    "addr:postcode":"24422",
    "addr:street":"Peaceful Ln",
    "iso:country":"US",
    "sg:address":"132 Peaceful Ln",
    "sg:city":"Clifton Forge",
    "sg:classifiers":[
        {
            "category":"Building & Trades",
            "subcategory":"Construction",
            "type":"Services"
        }
    ],
    "sg:phone":"+1 540 863 3084",
    "sg:postcode":"24422",
    "sg:province":"VA",
    "sg:tags":[
        "erectors",
        "machinery",
        "contractor"
    ],
    "wof:name":"Pals Services Inc",
    "wof:placetype":"venue"
},
  "geometry": {"coordinates":[-79.802126,37.787236],"type":"Point"}
}