{
  "type": "Feature",
  "properties": {
    "iso:country":"US",
    "sg:address":"205 Yoakum Pkwy Unit 1226",
    "sg:city":"Alexandria",
    "sg:classifiers":[
        {
            "category":"Social Services",
            "type":"Services"
        },
        {
            "category":"Professional",
            "subcategory":"Employment Agencies",
            "type":"Services"
        }
    ],
    "sg:phone":"+1 703 370 9666",
    "sg:postcode":"22304",
    "sg:province":"VA",
    "sg:tags":[
        "workers'",
        "placement",
        "volunteer"
    ],
    "wof:name":"Eyes For The World Eunice K Fiorito Foundation Lt",
    "wof:placetype":"venue"
},
  "geometry": {"coordinates":[-77.139804,38.812735],"type":"Point"}
}