{
  "type": "Feature",
  "properties": {
    "addr:full":"348 Newtown Rd Virginia Beach VA 23462",
    "addr:housenumber":"348",
    "addr:postcode":"23462",
    "addr:street":"Newtown Rd",
    "iso:country":"US",
    "sg:address":"348 Newtown Rd",
    "sg:city":"Virginia Beach",
    "sg:classifiers":[
        {
            "category":"Retail",
            "subcategory":"Auto Repair",
            "type":"Services"
        }
    ],
    "sg:phone":"+1 757 497 2604",
    "sg:postcode":"23462",
    "sg:province":"VA",
    "sg:tags":[
        "automotive",
        "center",
        "lubrication"
    ],
    "wof:name":"Jiffy Lube",
    "wof:placetype":"venue"
},
  "geometry": {"coordinates":[-76.179821,36.849137],"type":"Point"}
}