{
  "type": "Feature",
  "properties": {
    "addr:full":"3052 Stony Point Rd Richmond VA 23235",
    "addr:housenumber":"3052",
    "addr:postcode":"23235",
    "addr:street":"Stony Point Rd",
    "iso:country":"US",
    "sg:address":"3052 Stony Point Rd",
    "sg:city":"Richmond",
    "sg:classifiers":[
        {
            "category":"Shopping",
            "subcategory":"Jewelry",
            "type":"Retail Goods"
        }
    ],
    "sg:phone":"+1 804 320 8413",
    "sg:postcode":"23235",
    "sg:province":"VA",
    "sg:tags":[
        "wholesale"
    ],
    "wof:name":"Lastovica Jewelers",
    "wof:placetype":"venue"
},
  "geometry": {"coordinates":[-77.562263,37.537488],"type":"Point"}
}