{
  "type": "Feature",
  "properties": {
    "addr:full":"1850A Town Center Pkwy # 314 Reston VA 20190",
    "addr:housenumber":"1850a",
    "addr:postcode":"20190",
    "addr:street":"Town Center Pkwy # 314",
    "iso:country":"US",
    "sg:address":"1850A Town Center Pkwy # 314",
    "sg:city":"Reston",
    "sg:classifiers":[
        {
            "category":"Health Services",
            "subcategory":"Doctor",
            "type":"Services"
        }
    ],
    "sg:phone":"+1 703 481 5212",
    "sg:postcode":"20190",
    "sg:province":"VA",
    "sg:tags":[
        "medicine",
        "physician",
        "surgeon",
        "internal",
        "surgeons"
    ],
    "wof:name":"Internal Medicine Grp Of N Virginia, Ltd.",
    "wof:placetype":"venue"
},
  "geometry": {"coordinates":[-77.363365,38.959087],"type":"Point"}
}