{
  "type": "Feature",
  "properties": {
    "iso:country":"US",
    "sg:address":"1108 E Main St",
    "sg:city":"Richmond",
    "sg:classifiers":[
        {
            "category":"Professional",
            "subcategory":"Lawyer & Legal Services",
            "type":"Services"
        }
    ],
    "sg:phone":"+1 804 643 8737",
    "sg:postcode":"23219",
    "sg:province":"VA",
    "wof:name":"Allan W Smith Atty",
    "wof:placetype":"venue"
},
  "geometry": {"coordinates":[-77.434603,37.537308],"type":"Point"}
}