{
  "type": "Feature",
  "properties": {
    "addr:full":"114 N Main St Culpeper VA 22701",
    "addr:housenumber":"114",
    "addr:postcode":"22701",
    "addr:street":"N Main St",
    "iso:country":"US",
    "sg:address":"114 N Main St",
    "sg:city":"Culpeper",
    "sg:classifiers":[
        {
            "category":"Professional",
            "subcategory":"Lawyer & Legal Services",
            "type":"Services"
        }
    ],
    "sg:phone":"+1 540 825 2000",
    "sg:postcode":"22701",
    "sg:province":"VA",
    "sg:tags":[
        "attorney"
    ],
    "wof:name":"Elliott H De Jarnette",
    "wof:placetype":"venue"
},
  "geometry": {"coordinates":[-77.995977,38.47392],"type":"Point"}
}