{
  "type": "Feature",
  "properties": {
    "addr:full":"2010 Hessian Rd Charlottesville VA 22903",
    "addr:housenumber":"2010",
    "addr:postcode":"22903",
    "addr:street":"Hessian Rd",
    "iso:country":"US",
    "sg:address":"2010 Hessian Rd",
    "sg:city":"Charlottesville",
    "sg:classifiers":[
        {
            "category":"Professional",
            "type":"Services"
        }
    ],
    "sg:phone":"+1 434 296 8018",
    "sg:postcode":"22903",
    "sg:province":"VA",
    "wof:name":"Pinaealple Promutions",
    "wof:placetype":"venue"
},
  "geometry": {"coordinates":[-78.49725599999999,38.051873],"type":"Point"}
}