{
  "type": "Feature",
  "properties": {
    "iso:country":"US",
    "sg:address":"2806 Popkins Ln",
    "sg:city":"Alexandria",
    "sg:classifiers":[
        {
            "category":"Building & Trades",
            "subcategory":"Construction",
            "type":"Services"
        }
    ],
    "sg:phone":"+1 703 768 4661",
    "sg:postcode":"22306",
    "sg:province":"VA",
    "sg:tags":[
        "home",
        "improvement"
    ],
    "wof:name":"Home Solutions Connection Inc",
    "wof:placetype":"venue"
},
  "geometry": {"coordinates":[-77.082151,38.765351],"type":"Point"}
}