{
  "type": "Feature",
  "properties": {
    "iso:country":"US",
    "sg:address":"6023 Madison Overlook Ct",
    "sg:city":"Falls Church",
    "sg:classifiers":[
        {
            "category":"Professional",
            "subcategory":"Management & Consulting",
            "type":"Services"
        }
    ],
    "sg:phone":"+1 703 845 7712",
    "sg:postcode":"22041",
    "sg:province":"VA",
    "sg:tags":[
        "business"
    ],
    "wof:name":"Barrington/Chappell",
    "wof:placetype":"venue"
},
  "geometry": {"coordinates":[-77.13957600000001,38.844569],"type":"Point"}
}