{
  "type": "Feature",
  "properties": {
    "addr:full":"3401 Coleshill Ln Chesapeake VA 23321",
    "addr:housenumber":"3401",
    "addr:postcode":"23321",
    "addr:street":"Coleshill Ln",
    "iso:country":"US",
    "sg:address":"3401 Coleshill Ln",
    "sg:city":"Chesapeake",
    "sg:classifiers":[
        {
            "category":"Health Services",
            "subcategory":"Doctor",
            "type":"Services"
        }
    ],
    "sg:phone":"+1 757 337 0539",
    "sg:postcode":"23321",
    "sg:province":"VA",
    "sg:tags":[
        "medical",
        "family"
    ],
    "wof:name":"Debnath Chinmayee Owner",
    "wof:placetype":"venue"
},
  "geometry": {"coordinates":[-76.41681800000001,36.848991],"type":"Point"}
}