{
  "type": "Feature",
  "properties": {
    "iso:country":"US",
    "sg:address":"327 Cedar Bluff Rd",
    "sg:city":"Charlottesville",
    "sg:classifiers":[
        {
            "category":"Health Services",
            "subcategory":"Health Practitioner",
            "type":"Services"
        }
    ],
    "sg:phone":"+1 434 977 5720",
    "sg:postcode":"22901",
    "sg:province":"VA",
    "sg:tags":[
        "nutritionist"
    ],
    "wof:name":"Ultra Nutrition Intl Inc",
    "wof:placetype":"venue"
},
  "geometry": {"coordinates":[-78.489469,38.099968],"type":"Point"}
}