{
  "type": "Feature",
  "properties": {
    "addr:full":"618 Virginia Ave Clarksville VA 23927",
    "addr:housenumber":"618",
    "addr:postcode":"23927",
    "addr:street":"Virginia Ave",
    "iso:country":"US",
    "sg:address":"618 Virginia Ave",
    "sg:city":"Clarksville",
    "sg:classifiers":[
        {
            "category":"Professional",
            "subcategory":"Business Services",
            "type":"Services"
        }
    ],
    "sg:phone":"+1 434 374 5111",
    "sg:postcode":"23927",
    "sg:province":"VA",
    "sg:tags":[
        "embroidery"
    ],
    "wof:name":"Stitches Corporate & Custom",
    "wof:placetype":"venue"
},
  "geometry": {"coordinates":[-78.558713,36.62347],"type":"Point"}
}