{
  "type": "Feature",
  "properties": {
    "addr:full":"1523 Wilborn Ave South Boston VA 24592",
    "addr:housenumber":"1523",
    "addr:postcode":"24592",
    "addr:street":"Wilborn Ave",
    "iso:country":"US",
    "sg:address":"1523 Wilborn Ave",
    "sg:city":"South Boston",
    "sg:classifiers":[
        {
            "category":"Food & Beverages",
            "subcategory":"Groceries & Convenience Stores",
            "type":"Retail Goods"
        }
    ],
    "sg:phone":"+1 434 575 7002",
    "sg:postcode":"24592",
    "sg:province":"VA",
    "sg:tags":[
        "grocer"
    ],
    "wof:name":"Southside Foods",
    "wof:placetype":"venue"
},
  "geometry": {"coordinates":[-78.909778,36.706206],"type":"Point"}
}