{
  "type": "Feature",
  "properties": {
    "addr:full":"3811 Hyde Park Dr Roanoke VA 24018",
    "addr:housenumber":"3811",
    "addr:postcode":"24018",
    "addr:street":"Hyde Park Dr",
    "iso:country":"US",
    "sg:address":"3811 Hyde Park Dr",
    "sg:city":"Roanoke",
    "sg:classifiers":[
        {
            "category":"Building & Trades",
            "subcategory":"Equipment Rental",
            "type":"Services"
        }
    ],
    "sg:phone":"+1 540 774 8971",
    "sg:postcode":"24018",
    "sg:province":"VA",
    "wof:name":"Fun Times Rentals & Producti",
    "wof:placetype":"venue"
},
  "geometry": {"coordinates":[-80.016102,37.242942],"type":"Point"}
}