{
  "type": "Feature",
  "properties": {
    "addr:full":"9288 Warwick Blvd Newport News VA 23607",
    "addr:housenumber":"9288",
    "addr:postcode":"23607",
    "addr:street":"Warwick Blvd",
    "iso:country":"US",
    "sg:address":"9288 Warwick Blvd",
    "sg:city":"Newport News",
    "sg:classifiers":[
        {
            "category":"Social Services",
            "subcategory":"Child Care",
            "type":"Services"
        }
    ],
    "sg:phone":"+1 757 247 3360",
    "sg:postcode":"23607",
    "sg:province":"VA",
    "wof:name":"Warwick Kid's Academy",
    "wof:placetype":"venue"
},
  "geometry": {"coordinates":[-76.453774,37.023103],"type":"Point"}
}