{
  "type": "Feature",
  "properties": {
    "addr:full":"3901 Betsy Cres Virginia Beach VA 23453",
    "addr:housenumber":"3901",
    "addr:postcode":"23453",
    "addr:street":"Betsy Cres",
    "iso:country":"US",
    "sg:address":"3901 Betsy Cres",
    "sg:city":"Virginia Beach",
    "sg:classifiers":[
        {
            "category":"Shopping",
            "subcategory":"Gifts & Souvenirs",
            "type":"Retail Goods"
        }
    ],
    "sg:phone":"+1 757 471 2626",
    "sg:postcode":"23453",
    "sg:province":"VA",
    "wof:name":"Baskets Bears & Bags",
    "wof:placetype":"venue"
},
  "geometry": {"coordinates":[-76.115965,36.795156],"type":"Point"}
}