{
  "type": "Feature",
  "properties": {
    "iso:country":"US",
    "sg:address":"4724 George Washington Memorial Hwy",
    "sg:city":"Yorktown",
    "sg:classifiers":[
        {
            "category":"Restaurant",
            "type":"Food & Drink"
        }
    ],
    "sg:phone":"+1 757 898 7044",
    "sg:postcode":"23692",
    "sg:province":"VA",
    "sg:tags":[
        "eating"
    ],
    "wof:name":"Madisons Prime Rib",
    "wof:placetype":"venue"
},
  "geometry": {"coordinates":[-76.459979,37.150736],"type":"Point"}
}