{
  "type": "Feature",
  "properties": {
    "addr:full":"2000 Holiday Dr Charlottesville VA 22901",
    "addr:housenumber":"2000",
    "addr:postcode":"22901",
    "addr:street":"Holiday Dr",
    "iso:country":"US",
    "sg:address":"2000 Holiday Dr",
    "sg:city":"Charlottesville",
    "sg:classifiers":[
        {
            "category":"Social Services",
            "type":"Services"
        }
    ],
    "sg:phone":"+1 434 975 0097",
    "sg:postcode":"22901",
    "sg:province":"VA",
    "sg:tags":[
        "organization",
        "welfare"
    ],
    "wof:name":"Epsilon Group",
    "wof:placetype":"venue"
},
  "geometry": {"coordinates":[-78.492499,38.058138],"type":"Point"}
}