{
  "type": "Feature",
  "properties": {
    "iso:country":"US",
    "sg:address":"6913 Bethnal Ct",
    "sg:city":"Springfield",
    "sg:classifiers":[
        {
            "category":"Building & Trades",
            "subcategory":"Construction",
            "type":"Services"
        }
    ],
    "sg:phone":"+1 703 451 5175",
    "sg:postcode":"22150",
    "sg:province":"VA",
    "sg:tags":[
        "house",
        "remodeling"
    ],
    "wof:name":"New Comb Amigos",
    "wof:placetype":"venue"
},
  "geometry": {"coordinates":[-77.19117199999999,38.765488],"type":"Point"}
}