{
  "type": "Feature",
  "properties": {
    "iso:country":"US",
    "sg:address":"400 Westfield Rd",
    "sg:city":"Charlottesville",
    "sg:classifiers":[
        {
            "category":"Utilities",
            "subcategory":"Telephone",
            "type":"Services"
        }
    ],
    "sg:phone":"+1 434 817 8189",
    "sg:postcode":"22901",
    "sg:province":"VA",
    "sg:tags":[
        "communications"
    ],
    "wof:name":"Adelphia",
    "wof:placetype":"venue"
},
  "geometry": {"coordinates":[-78.483447,38.071318],"type":"Point"}
}