{
  "type": "Feature",
  "properties": {
    "addr:full":"980 Hopeman Pkwy Waynesboro VA 22980",
    "addr:housenumber":"980",
    "addr:postcode":"22980",
    "addr:street":"Hopeman Pkwy",
    "iso:country":"US",
    "sg:address":"980 Hopeman Pkwy",
    "sg:city":"Waynesboro",
    "sg:classifiers":[
        {
            "category":"Retail",
            "subcategory":"Auto Rental",
            "type":"Services"
        }
    ],
    "sg:phone":"+1 540 941 8011",
    "sg:postcode":"22980",
    "sg:province":"VA",
    "sg:tags":[
        "renting",
        "truck",
        "leasing"
    ],
    "wof:name":"U-Haul Co",
    "wof:placetype":"venue"
},
  "geometry": {"coordinates":[-78.883331,38.087072],"type":"Point"}
}