{
  "type": "Feature",
  "properties": {
    "iso:country":"US",
    "sg:address":"833 Marvin Ave",
    "sg:city":"Norfolk",
    "sg:classifiers":[
        {
            "category":"Organizations",
            "subcategory":"Religious Organization",
            "type":"Services"
        }
    ],
    "sg:phone":"+1 757 587 0401",
    "sg:postcode":"23518",
    "sg:province":"VA",
    "wof:name":"Colonial Heights Church Christ",
    "wof:placetype":"venue"
},
  "geometry": {"coordinates":[-76.24781900000001,36.925772],"type":"Point"}
}