{
  "type": "Feature",
  "properties": {
    "addr:full":"459 Bonifay Dr Hampton VA 23666",
    "addr:housenumber":"459",
    "addr:postcode":"23666",
    "addr:street":"Bonifay Dr",
    "iso:country":"US",
    "sg:address":"459 Bonifay Dr",
    "sg:city":"Hampton",
    "sg:classifiers":[
        {
            "category":"Professional",
            "subcategory":"Business Services",
            "type":"Services"
        }
    ],
    "sg:phone":"+1 757 838 4513",
    "sg:postcode":"23666",
    "sg:province":"VA",
    "sg:tags":[
        "specialty",
        "mfg"
    ],
    "wof:name":"Morris Glenn G",
    "wof:placetype":"venue"
},
  "geometry": {"coordinates":[-76.436823,37.035595],"type":"Point"}
}