{
  "type": "Feature",
  "properties": {
    "addr:full":"709 1st St Radford VA 24141",
    "addr:housenumber":"709",
    "addr:postcode":"24141",
    "addr:street":"1St St",
    "iso:country":"US",
    "sg:address":"709 1st St",
    "sg:city":"Radford",
    "sg:classifiers":[
        {
            "category":"Home & Garden",
            "subcategory":"Building Materials",
            "type":"Retail Goods"
        }
    ],
    "sg:phone":"+1 540 639 2131",
    "sg:postcode":"24141",
    "sg:province":"VA",
    "sg:tags":[
        "paint",
        "floor",
        "covering"
    ],
    "wof:name":"Sherwin-Williams Paints",
    "wof:placetype":"venue"
},
  "geometry": {"coordinates":[-80.580748,37.130566],"type":"Point"}
}