{
  "type": "Feature",
  "properties": {
    "addr:full":"4870 Bethel Church Rd Evington VA 24550",
    "addr:housenumber":"4870",
    "addr:postcode":"24550",
    "addr:street":"Bethel Church Rd",
    "iso:country":"US",
    "sg:address":"4870 Bethel Church Rd",
    "sg:city":"Evington",
    "sg:classifiers":[
        {
            "category":"Autos & Motor Vehicles",
            "subcategory":"Automobile Sales",
            "type":"Retail Goods"
        }
    ],
    "sg:phone":"+1 434 525 6119",
    "sg:postcode":"24550",
    "sg:province":"VA",
    "sg:tags":[
        "used"
    ],
    "wof:name":"Clinks Auto Sales",
    "wof:placetype":"venue"
},
  "geometry": {"coordinates":[-79.33009,37.262573],"type":"Point"}
}