{
  "type": "Feature",
  "properties": {
    "iso:country":"US",
    "sg:address":"11861 Canon Blvd",
    "sg:city":"Newport News",
    "sg:classifiers":[
        {
            "category":"Education",
            "subcategory":"Vocational School",
            "type":"Public Place"
        }
    ],
    "sg:phone":"+1 757 873 8884",
    "sg:postcode":"23606",
    "sg:province":"VA",
    "sg:tags":[
        "real estate"
    ],
    "wof:name":"Alpha College Of Real Estate",
    "wof:placetype":"venue"
},
  "geometry": {"coordinates":[-76.470584,37.088229],"type":"Point"}
}