{
  "type": "Feature",
  "properties": {
    "iso:country":"US",
    "sg:address":"7229 Forest Ave",
    "sg:city":"Richmond",
    "sg:classifiers":[
        {
            "category":"Banks & Credit Unions",
            "subcategory":"Bank",
            "type":"Services"
        }
    ],
    "sg:phone":"+1 804 673 0944",
    "sg:postcode":"23226",
    "sg:province":"VA",
    "sg:tags":[
        "mortgage"
    ],
    "wof:name":"SunTrust",
    "wof:placetype":"venue"
},
  "geometry": {"coordinates":[-77.52829,37.605155],"type":"Point"}
}