{
  "type": "Feature",
  "properties": {
    "addr:full":"3710 Indian River Rd Chesapeake VA 23325",
    "addr:housenumber":"3710",
    "addr:postcode":"23325",
    "addr:street":"Indian River Rd",
    "iso:country":"US",
    "sg:address":"3710 Indian River Rd",
    "sg:city":"Chesapeake",
    "sg:classifiers":[
        {
            "category":"Professional",
            "subcategory":"Business Services",
            "type":"Services"
        }
    ],
    "sg:phone":"+1 757 578 3500",
    "sg:postcode":"23325",
    "sg:province":"VA",
    "sg:tags":[
        "publishing"
    ],
    "wof:name":"Contract Publishing Inc",
    "wof:placetype":"venue"
},
  "geometry": {"coordinates":[-76.236244,36.823266],"type":"Point"}
}