{
  "type": "Feature",
  "properties": {
    "addr:full":"1136 Sperryville Pike Culpeper VA 22701",
    "addr:housenumber":"1136",
    "addr:postcode":"22701",
    "addr:street":"Sperryville Pike",
    "iso:country":"US",
    "sg:address":"1136 Sperryville Pike",
    "sg:city":"Culpeper",
    "sg:classifiers":[
        {
            "category":"Organizations",
            "subcategory":"Religious Organization",
            "type":"Services"
        }
    ],
    "sg:phone":"+1 540 825 2866",
    "sg:postcode":"22701",
    "sg:province":"VA",
    "wof:name":"Culpeper Free Methodist Church",
    "wof:placetype":"venue"
},
  "geometry": {"coordinates":[-78.01526800000001,38.483318],"type":"Point"}
}