{
  "type": "Feature",
  "properties": {
    "iso:country":"US",
    "sg:address":"5733 Yewing Way",
    "sg:city":"Gainesville",
    "sg:classifiers":[
        {
            "category":"Professional",
            "subcategory":"Management & Consulting",
            "type":"Services"
        }
    ],
    "sg:phone":"+1 703 754 6404",
    "sg:postcode":"20155",
    "sg:province":"VA",
    "wof:name":"Haddow C McClain & Associates",
    "wof:placetype":"venue"
},
  "geometry": {"coordinates":[-77.603514,38.847452],"type":"Point"}
}