{
  "type": "Feature",
  "properties": {
    "iso:country":"US",
    "sg:address":"2421 N Nelson St",
    "sg:city":"Arlington",
    "sg:classifiers":[
        {
            "category":"Building & Trades",
            "subcategory":"Construction",
            "type":"Services"
        }
    ],
    "sg:phone":"+1 703 465 2716",
    "sg:postcode":"22207",
    "sg:province":"VA",
    "sg:tags":[
        "house"
    ],
    "wof:name":"Uriona Construction Co Inc",
    "wof:placetype":"venue"
},
  "geometry": {"coordinates":[-77.102289,38.902942],"type":"Point"}
}