{
  "type": "Feature",
  "properties": {
    "addr:full":"7780 Grayson Pkwy Galax VA 24333",
    "addr:housenumber":"7780",
    "addr:postcode":"24333",
    "addr:street":"Grayson Pkwy",
    "iso:country":"US",
    "sg:address":"7780 Grayson Pkwy",
    "sg:city":"Galax",
    "sg:classifiers":[
        {
            "category":"Freight",
            "type":"Transportation"
        }
    ],
    "sg:phone":"+1 276 236 4737",
    "sg:postcode":"24333",
    "sg:province":"VA",
    "sg:tags":[
        "commercial",
        "storage"
    ],
    "wof:name":"Baywood Mini Storage",
    "wof:placetype":"venue"
},
  "geometry": {"coordinates":[-81.022764,36.613643],"type":"Point"}
}