{
  "type": "Feature",
  "properties": {
    "addr:full":"974 Maiden St Abingdon VA 24210",
    "addr:housenumber":"974",
    "addr:postcode":"24210",
    "addr:street":"Maiden St",
    "iso:country":"US",
    "sg:address":"974 Maiden St",
    "sg:city":"Abingdon",
    "sg:classifiers":[
        {
            "category":"Freight",
            "type":"Transportation"
        }
    ],
    "sg:phone":"+1 276 676 4539",
    "sg:postcode":"24210",
    "sg:province":"VA",
    "sg:tags":[
        "operator",
        "trucking"
    ],
    "wof:name":"L T Hart Transportation Inc",
    "wof:placetype":"venue"
},
  "geometry": {"coordinates":[-82.00681400000001,36.70345],"type":"Point"}
}