{
  "type": "Feature",
  "properties": {
    "addr:full":"4111 Little Creek Ln Richmond VA 23234",
    "addr:housenumber":"4111",
    "addr:postcode":"23234",
    "addr:street":"Little Creek Ln",
    "iso:country":"US",
    "sg:address":"4111 Little Creek Ln",
    "sg:city":"Richmond",
    "sg:classifiers":[
        {
            "category":"Home & Garden",
            "subcategory":"Building Materials",
            "type":"Retail Goods"
        },
        {
            "category":"Building & Trades",
            "subcategory":"Construction",
            "type":"Services"
        }
    ],
    "sg:phone":"+1 804 218 7665",
    "sg:postcode":"23234",
    "sg:province":"VA",
    "sg:tags":[
        "concrete",
        "staining",
        "contractor"
    ],
    "wof:name":"Concrete Builders",
    "wof:placetype":"venue"
},
  "geometry": {"coordinates":[-77.470049,37.434332],"type":"Point"}
}