{
  "type": "Feature",
  "properties": {
    "iso:country":"US",
    "sg:address":"12124 Washington Hwy",
    "sg:city":"Ashland",
    "sg:classifiers":[
        {
            "category":"Wholesale",
            "subcategory":"Construction Materials",
            "type":"Manufacturing & Wholesale Goods"
        },
        {
            "category":"Home & Garden",
            "subcategory":"Building Materials",
            "type":"Retail Goods"
        }
    ],
    "sg:phone":"+1 804 752 0060",
    "sg:postcode":"23005",
    "sg:province":"VA",
    "wof:name":"Wholesale Millwork Inc",
    "wof:placetype":"venue"
},
  "geometry": {"coordinates":[-77.471048,37.735801],"type":"Point"}
}