{
  "type": "Feature",
  "properties": {
    "addr:full":"16 Wade Ct Fredericksburg VA 22405",
    "addr:housenumber":"16",
    "addr:postcode":"22405",
    "addr:street":"Wade Ct",
    "iso:country":"US",
    "sg:address":"16 Wade Ct",
    "sg:city":"Fredericksburg",
    "sg:classifiers":[
        {
            "category":"Building & Trades",
            "subcategory":"Electrical",
            "type":"Services"
        }
    ],
    "sg:phone":"+1 540 374 1670",
    "sg:postcode":"22405",
    "sg:province":"VA",
    "sg:tags":[
        "electrical",
        "contractor"
    ],
    "wof:name":"G Long Electric",
    "wof:placetype":"venue"
},
  "geometry": {"coordinates":[-77.422116,38.312893],"type":"Point"}
}