{
  "type": "Feature",
  "properties": {
    "addr:full":"5628 Mineral Spring Rd Suffolk VA 23438",
    "addr:housenumber":"5628",
    "addr:postcode":"23438",
    "addr:street":"Mineral Spring Rd",
    "iso:country":"US",
    "sg:address":"5628 Mineral Spring Rd",
    "sg:city":"Suffolk",
    "sg:classifiers":[
        {
            "category":"Wholesale",
            "subcategory":"Seafood",
            "type":"Manufacturing & Wholesale Goods"
        }
    ],
    "sg:phone":"+1 757 986 3800",
    "sg:postcode":"23438",
    "sg:province":"VA",
    "sg:tags":[
        "construction",
        "material",
        "special",
        "commodity"
    ],
    "wof:name":"International Entp Unlimited",
    "wof:placetype":"venue"
},
  "geometry": {"coordinates":[-76.717721,36.612572],"type":"Point"}
}