{
  "type": "Feature",
  "properties": {
    "addr:full":"902 Wythe St Alexandria VA 22314",
    "addr:housenumber":"902",
    "addr:postcode":"22314",
    "addr:street":"Wythe St",
    "iso:country":"US",
    "sg:address":"902 Wythe St",
    "sg:city":"Alexandria",
    "sg:classifiers":[
        {
            "category":"Government",
            "subcategory":"Office",
            "type":"Public Place"
        },
        {
            "category":"Museum",
            "type":"Entertainment"
        }
    ],
    "sg:phone":"+1 703 838 4356",
    "sg:postcode":"22314",
    "sg:province":"VA",
    "sg:tags":[
        "township",
        "government-city",
        "village"
    ],
    "sg:website":"http://www.alexandriava.gov",
    "wof:name":"Alexandria Black Hstory Museum",
    "wof:placetype":"venue"
},
  "geometry": {"coordinates":[-77.047729,38.812163],"type":"Point"}
}