{
  "type": "Feature",
  "properties": {
    "addr:full":"13822 Braddock Rd Centreville VA 20121",
    "addr:housenumber":"13822",
    "addr:postcode":"20121",
    "addr:street":"Braddock Rd",
    "iso:country":"US",
    "sg:address":"13822 Braddock Rd",
    "sg:city":"Centreville",
    "sg:classifiers":[
        {
            "category":"Shopping",
            "subcategory":"Jewelry",
            "type":"Retail Goods"
        }
    ],
    "sg:phone":"+1 703 815 3470",
    "sg:postcode":"20121",
    "sg:province":"VA",
    "sg:tags":[
        "jeweler"
    ],
    "wof:name":"Youngs Jewelry & Boutique",
    "wof:placetype":"venue"
},
  "geometry": {"coordinates":[-77.425557,38.835502],"type":"Point"}
}