{
  "type": "Feature",
  "properties": {
    "addr:full":"380 S 4th St Wytheville VA 24382",
    "addr:housenumber":"380",
    "addr:postcode":"24382",
    "addr:street":"S 4Th St",
    "iso:country":"US",
    "sg:address":"380 S 4th St",
    "sg:city":"Wytheville",
    "sg:classifiers":[
        {
            "category":"Professional",
            "subcategory":"Lawyer & Legal Services",
            "type":"Services"
        }
    ],
    "sg:phone":"+1 276 625 0222",
    "sg:postcode":"24382",
    "sg:province":"VA",
    "sg:tags":[
        "attorney"
    ],
    "wof:name":"Scot S Farthing Atty At Law PC",
    "wof:placetype":"venue"
},
  "geometry": {"coordinates":[-81.082759,36.946536],"type":"Point"}
}