{
  "type": "Feature",
  "properties": {
    "addr:full":"7439 W Broad St Richmond VA 23294",
    "addr:housenumber":"7439",
    "addr:postcode":"23294",
    "addr:street":"W Broad St",
    "iso:country":"US",
    "sg:address":"7439 W Broad St",
    "sg:city":"Richmond",
    "sg:classifiers":[
        {
            "category":"Shopping",
            "subcategory":"Bicycles & Sporting Goods",
            "type":"Retail Goods"
        }
    ],
    "sg:phone":"+1 804 672 3441",
    "sg:postcode":"23294",
    "sg:province":"VA",
    "sg:tags":[
        "repair",
        "parts"
    ],
    "wof:name":"Agees Bicycle Company Inc",
    "wof:placetype":"venue"
},
  "geometry": {"coordinates":[-77.52285999999999,37.616674],"type":"Point"}
}