{
  "type": "Feature",
  "properties": {
    "addr:full":"1133 Emmet St N Charlottesville VA 22903",
    "addr:housenumber":"1133",
    "addr:postcode":"22903",
    "addr:street":"Emmet St N",
    "iso:country":"US",
    "sg:address":"1133 Emmet St N",
    "sg:city":"Charlottesville",
    "sg:classifiers":[
        {
            "category":"Restaurant",
            "type":"Food & Drink"
        }
    ],
    "sg:phone":"+1 434 245 4050",
    "sg:postcode":"22903",
    "sg:province":"VA",
    "sg:tags":[
        "pizza"
    ],
    "sg:website":"www.brixxpizza.com/charlottesvil...",
    "wof:name":"Brixx Wood Fired Pizza",
    "wof:placetype":"venue"
},
  "geometry": {"coordinates":[-78.500271,38.051915],"type":"Point"}
}