{
  "type": "Feature",
  "properties": {
    "iso:country":"US",
    "sg:address":"188 Crest Rd",
    "sg:city":"Ruckersville",
    "sg:classifiers":[
        {
            "category":"Building & Trades",
            "subcategory":"Construction",
            "type":"Services"
        }
    ],
    "sg:phone":"+1 434 985 4471",
    "sg:postcode":"22968",
    "sg:province":"VA",
    "sg:tags":[
        "house"
    ],
    "wof:name":"Amj Construction Ltd Inc",
    "wof:placetype":"venue"
},
  "geometry": {"coordinates":[-78.423754,38.26591],"type":"Point"}
}