{
  "type": "Feature",
  "properties": {
    "addr:full":"421 Butler Farm Rd Hampton VA 23666",
    "addr:housenumber":"421",
    "addr:postcode":"23666",
    "addr:street":"Butler Farm Rd",
    "iso:country":"US",
    "sg:address":"421 Butler Farm Rd",
    "sg:city":"Hampton",
    "sg:classifiers":[
        {
            "category":"Utilities",
            "subcategory":"Mobile Phone",
            "type":"Services"
        }
    ],
    "sg:phone":"+1 757 223 4000",
    "sg:postcode":"23666",
    "sg:province":"VA",
    "sg:tags":[
        "telephone",
        "cellular"
    ],
    "wof:name":"Nextel Communications Inc",
    "wof:placetype":"venue"
},
  "geometry": {"coordinates":[-76.406587,37.062553],"type":"Point"}
}