{
  "type": "Feature",
  "properties": {
    "iso:country":"US",
    "sg:address":"2031 Meadow Springs Dr",
    "sg:city":"Vienna",
    "sg:classifiers":[
        {
            "category":"Professional",
            "subcategory":"Computer Services",
            "type":"Services"
        }
    ],
    "sg:phone":"+1 703 995 0583",
    "sg:postcode":"22182",
    "sg:province":"VA",
    "sg:tags":[
        "consulting"
    ],
    "wof:name":"Epic Solutions Inc",
    "wof:placetype":"venue"
},
  "geometry": {"coordinates":[-77.225703,38.906968],"type":"Point"}
}