{
  "type": "Feature",
  "properties": {
    "addr:full":"4541 Glendale Rd Woodbridge VA 22193",
    "addr:housenumber":"4541",
    "addr:postcode":"22193",
    "addr:street":"Glendale Rd",
    "iso:country":"US",
    "sg:address":"4541 Glendale Rd",
    "sg:city":"Woodbridge",
    "sg:classifiers":[
        {
            "category":"Travel",
            "subcategory":"Travel Agent",
            "type":"Entertainment"
        }
    ],
    "sg:phone":"+1 703 730 1657",
    "sg:postcode":"22193",
    "sg:province":"VA",
    "wof:name":"Bostic Travel",
    "wof:placetype":"venue"
},
  "geometry": {"coordinates":[-77.34394,38.652142],"type":"Point"}
}