{
  "type": "Feature",
  "properties": {
    "addr:full":"232 Greenwich Cir Danville VA 24540",
    "addr:housenumber":"232",
    "addr:postcode":"24540",
    "addr:street":"Greenwich Cir",
    "iso:country":"US",
    "sg:address":"232 Greenwich Cir",
    "sg:city":"Danville",
    "sg:classifiers":[
        {
            "category":"Social Services",
            "subcategory":"Child Care",
            "type":"Services"
        }
    ],
    "sg:phone":"+1 434 792 5002",
    "sg:postcode":"24540",
    "sg:province":"VA",
    "wof:name":"Unbelievable Toddlers",
    "wof:placetype":"venue"
},
  "geometry": {"coordinates":[-79.376717,36.609981],"type":"Point"}
}