{
  "type": "Feature",
  "properties": {
    "addr:full":"4311 November Ave Richmond VA 23231",
    "addr:postcode":"4311;23231",
    "addr:street":"November Ave",
    "iso:country":"US",
    "sg:address":"4311 November Ave",
    "sg:city":"Richmond",
    "sg:classifiers":[
        {
            "category":"Wholesale",
            "subcategory":"Machinery & Supplies",
            "type":"Manufacturing & Wholesale Goods"
        }
    ],
    "sg:phone":"+1 804 232 6703",
    "sg:postcode":"23231",
    "sg:province":"VA",
    "sg:tags":[
        "detergent",
        "soap"
    ],
    "wof:name":"W P Ballard & Co",
    "wof:placetype":"venue"
},
  "geometry": {"coordinates":[-77.35454799999999,37.514255],"type":"Point"}
}