{
  "type": "Feature",
  "properties": {
    "addr:full":"25387 Patriot Ter Aldie VA 20105",
    "addr:postcode":"25387;20105",
    "addr:street":"Patriot Ter Aldie",
    "iso:country":"US",
    "sg:address":"25387 Patriot Ter",
    "sg:city":"Aldie",
    "sg:classifiers":[
        {
            "category":"Building & Trades",
            "subcategory":"Construction",
            "type":"Services"
        }
    ],
    "sg:phone":"+1 703 542 7947",
    "sg:postcode":"20105",
    "sg:province":"VA",
    "sg:tags":[
        "contractor"
    ],
    "sg:website":"www.ryanhomes.com",
    "wof:name":"Ryan Homes Inc",
    "wof:placetype":"venue"
},
  "geometry": {"coordinates":[-77.557929,38.916723],"type":"Point"}
}