{
  "type": "Feature",
  "properties": {
    "iso:country":"US",
    "sg:address":"109 Piney Forest Rd",
    "sg:city":"Danville",
    "sg:classifiers":[
        {
            "category":"Home & Garden",
            "subcategory":"Home Furnishings",
            "type":"Retail Goods"
        }
    ],
    "sg:phone":"+1 434 791 2623",
    "sg:postcode":"24540",
    "sg:province":"VA",
    "sg:tags":[
        "linen"
    ],
    "wof:name":"Plej's",
    "wof:placetype":"venue"
},
  "geometry": {"coordinates":[-79.414115,36.594844],"type":"Point"}
}