{
  "type": "Feature",
  "properties": {
    "addr:full":"111 Kempsville Rd Chesapeake VA 23320",
    "addr:housenumber":"111",
    "addr:postcode":"23320",
    "addr:street":"Kempsville Rd",
    "iso:country":"US",
    "sg:address":"111 Kempsville Rd",
    "sg:city":"Chesapeake",
    "sg:classifiers":[
        {
            "category":"Travel",
            "subcategory":"Travel Agent",
            "type":"Entertainment"
        }
    ],
    "sg:phone":"+1 757 547 9741",
    "sg:postcode":"23320",
    "sg:province":"VA",
    "sg:tags":[
        "agency"
    ],
    "wof:name":"AAA",
    "wof:placetype":"venue"
},
  "geometry": {"coordinates":[-76.239688,36.733943],"type":"Point"}
}