{
  "type": "Feature",
  "properties": {
    "iso:country":"US",
    "sg:address":"407 Coffman Rd",
    "sg:city":"Weyers Cave",
    "sg:classifiers":[
        {
            "category":"Retail",
            "subcategory":"Repair Shop",
            "type":"Services"
        }
    ],
    "sg:phone":"+1 540 434 2445",
    "sg:postcode":"24486",
    "sg:province":"VA",
    "sg:tags":[
        "appliance",
        "electrical",
        "contractor"
    ],
    "wof:name":"Blevins Appliance Svc",
    "wof:placetype":"venue"
},
  "geometry": {"coordinates":[-78.96878100000001,38.309676],"type":"Point"}
}