{
  "type": "Feature",
  "properties": {
    "addr:full":"402 S Summit Ave Woodstock VA 22664",
    "addr:housenumber":"402",
    "addr:postcode":"22664",
    "addr:street":"S Summit Ave",
    "iso:country":"US",
    "sg:address":"402 S Summit Ave",
    "sg:city":"Woodstock",
    "sg:classifiers":[
        {
            "category":"Building & Trades",
            "subcategory":"Landscaping Services",
            "type":"Services"
        }
    ],
    "sg:phone":"+1 540 459 7278",
    "sg:postcode":"22664",
    "sg:province":"VA",
    "wof:name":"Lonas Lawn & Landscaping",
    "wof:placetype":"venue"
},
  "geometry": {"coordinates":[-78.519021,38.880437],"type":"Point"}
}