{
  "type": "Feature",
  "properties": {
    "addr:full":"6011 Tower Ct Alexandria VA 22304",
    "addr:housenumber":"6011",
    "addr:postcode":"22304",
    "addr:street":"Tower Ct",
    "iso:country":"US",
    "sg:address":"6011 Tower Ct",
    "sg:city":"Alexandria",
    "sg:classifiers":[
        {
            "category":"Professional",
            "subcategory":"Computer Services",
            "type":"Services"
        }
    ],
    "sg:phone":"+1 703 370 6630",
    "sg:postcode":"22304",
    "sg:province":"VA",
    "sg:tags":[
        "home",
        "consulting",
        "page",
        "dev",
        "internet"
    ],
    "wof:name":"Stat Experts",
    "wof:placetype":"venue"
},
  "geometry": {"coordinates":[-77.137371,38.814603],"type":"Point"}
}