{
  "type": "Feature",
  "properties": {
    "addr:full":"3684 Centerview Dr Chantilly VA 20151",
    "addr:housenumber":"3684",
    "addr:postcode":"20151",
    "addr:street":"Centerview Dr",
    "iso:country":"US",
    "sg:address":"3684 Centerview Dr",
    "sg:city":"Chantilly",
    "sg:classifiers":[
        {
            "category":"Building & Trades",
            "subcategory":"Construction",
            "type":"Services"
        }
    ],
    "sg:phone":"+1 703 679 1600",
    "sg:postcode":"20151",
    "sg:province":"VA",
    "sg:tags":[
        "new",
        "home"
    ],
    "wof:name":"Centex Homes  Inc",
    "wof:placetype":"venue"
},
  "geometry": {"coordinates":[-77.42845800000001,38.902202],"type":"Point"}
}