{
  "type": "Feature",
  "properties": {
    "iso:country":"US",
    "sg:address":"2900 W Clay St",
    "sg:city":"Richmond",
    "sg:classifiers":[
        {
            "category":"Wholesale",
            "subcategory":"Painting Supplies",
            "type":"Manufacturing & Wholesale Goods"
        },
        {
            "category":"Home & Garden",
            "subcategory":"Building Materials",
            "type":"Retail Goods"
        },
        {
            "category":"Building & Trades",
            "subcategory":"Construction",
            "type":"Services"
        }
    ],
    "sg:phone":"+1 804 525 5374",
    "sg:postcode":"23230",
    "sg:province":"VA",
    "sg:tags":[
        "wallcoverings-installation",
        "wallpaper",
        "wallcoverings",
        "paint",
        "contractor"
    ],
    "wof:name":"Scotland Painting Company",
    "wof:placetype":"venue"
},
  "geometry": {"coordinates":[-77.46970399999999,37.564812],"type":"Point"}
}