{
  "type": "Feature",
  "properties": {
    "addr:full":"4222 Sarellen Rd Richmond VA 23231",
    "addr:housenumber":"4222",
    "addr:postcode":"23231",
    "addr:street":"Sarellen Rd",
    "iso:country":"US",
    "sg:address":"4222 Sarellen Rd",
    "sg:city":"Richmond",
    "sg:classifiers":[
        {
            "category":"Professional",
            "subcategory":"Business Services",
            "type":"Services"
        }
    ],
    "sg:phone":"+1 804 222 9226",
    "sg:postcode":"23231",
    "sg:province":"VA",
    "sg:tags":[
        "packaging"
    ],
    "sg:website":"www.midatlanticsupply.com",
    "wof:name":"Mid-Atlantic Ind Supply",
    "wof:placetype":"venue"
},
  "geometry": {"coordinates":[-77.359421,37.511758],"type":"Point"}
}