{
  "type": "Feature",
  "properties": {
    "addr:full":"6500 George Washington Memorial Hwy Grafton VA 23692",
    "addr:housenumber":"6500",
    "addr:postcode":"23692",
    "addr:street":"George Washington Memorial Hwy",
    "iso:country":"US",
    "sg:address":"6500 George Washington Memorial Hwy",
    "sg:city":"Grafton",
    "sg:classifiers":[
        {
            "category":"Shopping",
            "subcategory":"Pharmacy",
            "type":"Retail Goods"
        }
    ],
    "sg:phone":"+1 757 989 0734",
    "sg:postcode":"23692",
    "sg:province":"VA",
    "wof:name":"Eckerd Drugs",
    "wof:placetype":"venue"
},
  "geometry": {"coordinates":[-76.47315999999999,37.170978],"type":"Point"}
}