{
  "type": "Feature",
  "properties": {
    "addr:full":"3041 Scottsburg Rd Scottsburg VA 24589",
    "addr:postcode":"3041;24589",
    "addr:street":"Scottsburg Rd",
    "iso:country":"US",
    "sg:address":"3041 Scottsburg Rd",
    "sg:city":"Scottsburg",
    "sg:classifiers":[
        {
            "category":"Food & Beverages",
            "subcategory":"Meat & Fish",
            "type":"Retail Goods"
        }
    ],
    "sg:phone":"+1 434 454 7225",
    "sg:postcode":"24589",
    "sg:province":"VA",
    "wof:name":"Clark's Self Svc",
    "wof:placetype":"venue"
},
  "geometry": {"coordinates":[-78.79309600000001,36.757381],"type":"Point"}
}