{
  "type": "Feature",
  "properties": {
    "addr:full":"5346 Glebe Hall Rd Gloucester VA 23061",
    "addr:housenumber":"5346",
    "addr:postcode":"23061",
    "addr:street":"Glebe Hall Rd",
    "iso:country":"US",
    "sg:address":"5346 Glebe Hall Rd",
    "sg:city":"Gloucester",
    "sg:classifiers":[
        {
            "category":"Professional",
            "subcategory":"Advertising",
            "type":"Services"
        }
    ],
    "sg:phone":"+1 804 693 7082",
    "sg:postcode":"23061",
    "sg:province":"VA",
    "sg:tags":[
        "counselor",
        "agency"
    ],
    "wof:name":"Advertising Resources",
    "wof:placetype":"venue"
},
  "geometry": {"coordinates":[-76.54253199999999,37.360402],"type":"Point"}
}