{
  "type": "Feature",
  "properties": {
    "addr:full":"704 W Grayson St Hillsville VA 24343",
    "addr:housenumber":"704",
    "addr:postcode":"24343",
    "addr:street":"W Grayson St",
    "iso:country":"US",
    "sg:address":"704 W Grayson St",
    "sg:city":"Hillsville",
    "sg:classifiers":[
        {
            "category":"Building & Trades",
            "subcategory":"Construction",
            "type":"Services"
        }
    ],
    "sg:phone":"+1 276 728 5690",
    "sg:postcode":"24343",
    "sg:province":"VA",
    "sg:tags":[
        "repair",
        "contractor"
    ],
    "wof:name":"Edwards Antenna Service Co",
    "wof:placetype":"venue"
},
  "geometry": {"coordinates":[-80.744112,36.756397],"type":"Point"}
}