{
  "type": "Feature",
  "properties": {
    "addr:full":"4419 Vacation Ln Arlington VA 22207",
    "addr:housenumber":"4419",
    "addr:postcode":"22207",
    "addr:street":"Vacation Ln",
    "iso:country":"US",
    "sg:address":"4419 Vacation Ln",
    "sg:city":"Arlington",
    "sg:classifiers":[
        {
            "category":"Health Services",
            "subcategory":"Doctor",
            "type":"Services"
        }
    ],
    "sg:phone":"+1 703 524 8056",
    "sg:postcode":"22207",
    "sg:province":"VA",
    "wof:name":"Doyle Brian B MD",
    "wof:placetype":"venue"
},
  "geometry": {"coordinates":[-77.117401,38.904598],"type":"Point"}
}