{
  "type": "Feature",
  "properties": {
    "addr:full":"1525 Wilson Blvd Arlington VA 22209",
    "addr:housenumber":"1525",
    "addr:postcode":"22209",
    "addr:street":"Wilson Blvd",
    "iso:country":"US",
    "sg:address":"1525 Wilson Blvd",
    "sg:city":"Arlington",
    "sg:classifiers":[
        {
            "category":"Professional",
            "subcategory":"Research",
            "type":"Services"
        }
    ],
    "sg:phone":"+1 703 465 2700",
    "sg:postcode":"22209",
    "sg:province":"VA",
    "sg:tags":[
        "educational"
    ],
    "wof:name":"National Board for Professional Teaching Standards",
    "wof:placetype":"venue"
},
  "geometry": {"coordinates":[-77.074673,38.894701],"type":"Point"}
}