{
  "type": "Feature",
  "properties": {
    "addr:full":"2546 W Pembroke Ave Hampton VA 23661",
    "addr:housenumber":"2546",
    "addr:postcode":"23661",
    "addr:street":"W Pembroke Ave",
    "iso:country":"US",
    "sg:address":"2546 W Pembroke Ave",
    "sg:city":"Hampton",
    "sg:classifiers":[
        {
            "category":"Food & Beverages",
            "subcategory":"Meat & Fish",
            "type":"Retail Goods"
        }
    ],
    "sg:phone":"+1 757 244 1884",
    "sg:postcode":"23661",
    "sg:province":"VA",
    "sg:tags":[
        "seafood"
    ],
    "wof:name":"Pembroke Seafood",
    "wof:placetype":"venue"
},
  "geometry": {"coordinates":[-76.405602,36.999064],"type":"Point"}
}