{
  "type": "Feature",
  "properties": {
    "addr:full":"5600 Seminole Ave Lynchburg VA 24502",
    "addr:housenumber":"5600",
    "addr:postcode":"24502",
    "addr:street":"Seminole Ave",
    "iso:country":"US",
    "sg:address":"5600 Seminole Ave",
    "sg:city":"Lynchburg",
    "sg:classifiers":[
        {
            "category":"Travel",
            "subcategory":"Hotels & Motels",
            "type":"Entertainment"
        }
    ],
    "sg:phone":"+1 434 237 7771",
    "sg:postcode":"24502",
    "sg:province":"VA",
    "wof:name":"Holiday Inn Express Lynchburg",
    "wof:placetype":"venue"
},
  "geometry": {"coordinates":[-79.18151,37.367449],"type":"Point"}
}