{
  "type": "Feature",
  "properties": {
    "iso:country":"US",
    "sg:address":"8330 Fletchers Chapel Rd",
    "sg:city":"King George",
    "sg:classifiers":[
        {
            "category":"Organizations",
            "subcategory":"Religious Organization",
            "type":"Services"
        }
    ],
    "sg:phone":"+1 540 775 7247",
    "sg:postcode":"22485",
    "sg:province":"VA",
    "wof:name":"Fletchers Chapel Untd Methdst",
    "wof:placetype":"venue"
},
  "geometry": {"coordinates":[-77.31493,38.296949],"type":"Point"}
}