{
  "type": "Feature",
  "properties": {
    "addr:full":"2110 Gallows Rd Ste D Vienna VA 22182",
    "addr:housenumber":"2110",
    "addr:postcode":"22182",
    "addr:street":"Gallows Rd Ste D",
    "iso:country":"US",
    "sg:address":"2110 Gallows Rd Ste D",
    "sg:city":"Vienna",
    "sg:classifiers":[
        {
            "category":"Health Services",
            "subcategory":"Doctor",
            "type":"Services"
        }
    ],
    "sg:phone":"+1 703 883 2942",
    "sg:postcode":"22182",
    "sg:province":"VA",
    "sg:tags":[
        "physician",
        "surgeon",
        "surgeons",
        "psychiatry"
    ],
    "wof:name":"Gary Litovitz Md Pc",
    "wof:placetype":"venue"
},
  "geometry": {"coordinates":[-77.222931,38.903984],"type":"Point"}
}