{
  "type": "Feature",
  "properties": {
    "addr:full":"13909 Metrotech Dr Chantilly VA 20151",
    "addr:housenumber":"13909",
    "addr:postcode":"20151",
    "addr:street":"Metrotech Dr",
    "iso:country":"US",
    "sg:address":"13909 Metrotech Dr",
    "sg:city":"Chantilly",
    "sg:classifiers":[
        {
            "category":"Retail",
            "subcategory":"Auto Repair",
            "type":"Services"
        }
    ],
    "sg:phone":"+1 703 263 2222",
    "sg:postcode":"20151",
    "sg:province":"VA",
    "sg:tags":[
        "repairing",
        "automobile"
    ],
    "sg:website":"www.chantillygoodyear.com",
    "wof:name":"Chantilly Automotive",
    "wof:placetype":"venue"
},
  "geometry": {"coordinates":[-77.42571,38.893444],"type":"Point"}
}