{
  "type": "Feature",
  "properties": {
    "addr:full":"600 Broad St Altavista VA 24517",
    "addr:housenumber":"600",
    "addr:postcode":"24517",
    "addr:street":"Broad St",
    "iso:country":"US",
    "sg:address":"600 Broad St",
    "sg:city":"Altavista",
    "sg:classifiers":[
        {
            "category":"Professional",
            "subcategory":"Accounting & Tax Preparation",
            "type":"Services"
        }
    ],
    "sg:phone":"+1 434 369 4800",
    "sg:postcode":"24517",
    "sg:province":"VA",
    "sg:tags":[
        "return",
        "filing"
    ],
    "wof:name":"H & R Block Tax Svc",
    "wof:placetype":"venue"
},
  "geometry": {"coordinates":[-79.290713,37.109397],"type":"Point"}
}