{
  "type": "Feature",
  "properties": {
    "addr:full":"615 Church St Lynchburg VA 24504",
    "addr:housenumber":"615",
    "addr:postcode":"24504",
    "addr:street":"Church St",
    "iso:country":"US",
    "sg:address":"615 Church St",
    "sg:city":"Lynchburg",
    "sg:classifiers":[
        {
            "category":"Banks & Credit Unions",
            "subcategory":"Bank",
            "type":"Services"
        }
    ],
    "sg:phone":"+1 434 846 2000",
    "sg:postcode":"24504",
    "sg:province":"VA",
    "sg:website":"www.bankofthejames.com",
    "wof:name":"Bank Of The James",
    "wof:placetype":"venue"
},
  "geometry": {"coordinates":[-79.14480399999999,37.416064],"type":"Point"}
}