{
  "type": "Feature",
  "properties": {
    "iso:country":"US",
    "sg:address":"105 Clonce St",
    "sg:city":"Weber City",
    "sg:classifiers":[
        {
            "category":"Social Services",
            "subcategory":"Job Training",
            "type":"Services"
        }
    ],
    "sg:phone":"+1 276 386 9444",
    "sg:postcode":"24290",
    "sg:province":"VA",
    "sg:tags":[
        "rehabilitation"
    ],
    "wof:name":"Brian Center Health & Rtrmnt",
    "wof:placetype":"venue"
},
  "geometry": {"coordinates":[-82.565304,36.617305],"type":"Point"}
}