{
  "type": "Feature",
  "properties": {
    "iso:country":"US",
    "sg:address":"2601 Broad St",
    "sg:city":"Chesapeake",
    "sg:classifiers":[
        {
            "category":"Education",
            "subcategory":"School",
            "type":"Public Place"
        }
    ],
    "sg:phone":"+1 757 494 7505",
    "sg:postcode":"23324",
    "sg:province":"VA",
    "wof:name":"G W Carver Int School",
    "wof:placetype":"venue"
},
  "geometry": {"coordinates":[-76.25809,36.799217],"type":"Point"}
}