{
  "type": "Feature",
  "properties": {
    "addr:full":"21432 Main St Courtland VA 23837",
    "addr:housenumber":"21432",
    "addr:postcode":"23837",
    "addr:street":"Main St",
    "iso:country":"US",
    "sg:address":"21432 Main St",
    "sg:city":"Courtland",
    "sg:classifiers":[
        {
            "category":"Food & Beverages",
            "subcategory":"Groceries & Convenience Stores",
            "type":"Retail Goods"
        }
    ],
    "sg:phone":"+1 757 653 0800",
    "sg:postcode":"23837",
    "sg:province":"VA",
    "wof:name":"Sandy Run Market",
    "wof:placetype":"venue"
},
  "geometry": {"coordinates":[-77.071485,36.725535],"type":"Point"}
}