{
  "type": "Feature",
  "properties": {
    "iso:country":"US",
    "sg:address":"25 W Calhoun St",
    "sg:city":"Salem",
    "sg:classifiers":[
        {
            "category":"Shopping",
            "type":"Retail Goods"
        }
    ],
    "sg:phone":"+1 540 389 8700",
    "sg:postcode":"24153",
    "sg:province":"VA",
    "sg:tags":[
        "supply",
        "heating",
        "hearing",
        "equipment",
        "impaired",
        "aids"
    ],
    "wof:name":"Beltone Hearing Aid Center",
    "wof:placetype":"venue"
},
  "geometry": {"coordinates":[-80.058806,37.291832],"type":"Point"}
}