{
  "type": "Feature",
  "properties": {
    "addr:full":"926 Virginia Ave NW Norton VA 24273",
    "addr:housenumber":"926",
    "addr:postcode":"24273",
    "addr:street":"Virginia Ave Nw",
    "iso:country":"US",
    "sg:address":"926 Virginia Ave NW",
    "sg:city":"Norton",
    "sg:classifiers":[
        {
            "category":"Professional",
            "subcategory":"Lawyer & Legal Services",
            "type":"Services"
        }
    ],
    "sg:phone":"+1 276 679 7717",
    "sg:postcode":"24273",
    "sg:province":"VA",
    "wof:name":"Client Centered Services",
    "wof:placetype":"venue"
},
  "geometry": {"coordinates":[-82.63309,36.933712],"type":"Point"}
}