{
  "type": "Feature",
  "properties": {
    "iso:country":"US",
    "sg:address":"12815 Wrexham Rd",
    "sg:city":"Herndon",
    "sg:classifiers":[
        {
            "category":"Building & Trades",
            "subcategory":"Construction",
            "type":"Services"
        }
    ],
    "sg:phone":"+1 703 620 3841",
    "sg:postcode":"20171",
    "sg:province":"VA",
    "sg:tags":[
        "carpentry",
        "contractor"
    ],
    "wof:name":"Virginia Trim",
    "wof:placetype":"venue"
},
  "geometry": {"coordinates":[-77.391706,38.927507],"type":"Point"}
}