{
  "type": "Feature",
  "properties": {
    "iso:country":"US",
    "sg:address":"5110 Althea Dr",
    "sg:city":"Annandale",
    "sg:classifiers":[
        {
            "category":"Professional",
            "subcategory":"Employment Agencies",
            "type":"Services"
        }
    ],
    "sg:phone":"+1 703 323 6524",
    "sg:postcode":"22003",
    "sg:province":"VA",
    "wof:name":"McGee & Associates",
    "wof:placetype":"venue"
},
  "geometry": {"coordinates":[-77.246072,38.812643],"type":"Point"}
}