{
  "type": "Feature",
  "properties": {
    "addr:full":"1360 Northgate Sq Reston VA 20190",
    "addr:housenumber":"1360",
    "addr:postcode":"20190",
    "addr:street":"Northgate Sq",
    "iso:country":"US",
    "sg:address":"1360 Northgate Sq",
    "sg:city":"Reston",
    "sg:classifiers":[
        {
            "category":"Organizations",
            "subcategory":"Religious Organization",
            "type":"Services"
        }
    ],
    "sg:phone":"+1 703 435 4409",
    "sg:postcode":"20190",
    "sg:province":"VA",
    "wof:name":"Cacina Diocese of Virginia",
    "wof:placetype":"venue"
},
  "geometry": {"coordinates":[-77.33692000000001,38.971584],"type":"Point"}
}