{
  "type": "Feature",
  "properties": {
    "addr:full":"1452 English Tavern Rd Lynchburg VA 24501",
    "addr:housenumber":"1452",
    "addr:postcode":"24501",
    "addr:street":"English Tavern Rd",
    "iso:country":"US",
    "sg:address":"1452 English Tavern Rd",
    "sg:city":"Lynchburg",
    "sg:classifiers":[
        {
            "category":"Building & Trades",
            "subcategory":"Construction",
            "type":"Services"
        }
    ],
    "sg:phone":"+1 434 385 4464",
    "sg:postcode":"24501",
    "sg:province":"VA",
    "sg:tags":[
        "concrete",
        "contractor"
    ],
    "wof:name":"Wm Concrete Inc",
    "wof:placetype":"venue"
},
  "geometry": {"coordinates":[-79.164334,37.303838],"type":"Point"}
}