{
  "type": "Feature",
  "properties": {
    "addr:full":"2117 Troxel Gap Rd Craigsville VA 24430",
    "addr:housenumber":"2117",
    "addr:postcode":"24430",
    "addr:street":"Troxel Gap Rd",
    "iso:country":"US",
    "sg:address":"2117 Troxel Gap Rd",
    "sg:city":"Craigsville",
    "sg:classifiers":[
        {
            "category":"Organizations",
            "subcategory":"Religious Organization",
            "type":"Services"
        }
    ],
    "sg:phone":"+1 540 997 5526",
    "sg:postcode":"24430",
    "sg:province":"VA",
    "sg:tags":[
        "church"
    ],
    "wof:name":"Estaline Valley Chr-The Nzrn",
    "wof:placetype":"venue"
},
  "geometry": {"coordinates":[-79.35086699999999,38.049288],"type":"Point"}
}