{
  "type": "Feature",
  "properties": {
    "iso:country":"US",
    "sg:address":"44050 Woodridge Pkwy",
    "sg:city":"Lansdowne",
    "sg:classifiers":[
        {
            "category":"Restaurant",
            "type":"Food & Drink"
        }
    ],
    "sg:menulink":"http://www.allmenus.com/va/broad-run/269848-on-the-potomac/menu/",
    "sg:phone":"+1 703 729 8400",
    "sg:postcode":"20176",
    "sg:province":"VA",
    "sg:tags":[
        "american"
    ],
    "wof:name":"On the Potomac",
    "wof:placetype":"venue"
},
  "geometry": {"coordinates":[-77.47699900000001,39.080154],"type":"Point"}
}