{
  "type": "Feature",
  "properties": {
    "iso:country":"US",
    "sg:address":"130 Environs Rd",
    "sg:city":"Sterling",
    "sg:classifiers":[
        {
            "category":"Manufacturing",
            "subcategory":"Printing",
            "type":"Manufacturing & Wholesale Goods"
        }
    ],
    "sg:phone":"+1 703 450 7326",
    "sg:postcode":"20165",
    "sg:province":"VA",
    "sg:tags":[
        "book"
    ],
    "wof:name":"Global Information & Comm",
    "wof:placetype":"venue"
},
  "geometry": {"coordinates":[-77.41054,39.046236],"type":"Point"}
}