{
  "type": "Feature",
  "properties": {
    "addr:full":"510 Blue Ridge Ave Bedford VA 24523",
    "addr:housenumber":"510",
    "addr:postcode":"24523",
    "addr:street":"Blue Ridge Ave",
    "iso:country":"US",
    "sg:address":"510 Blue Ridge Ave",
    "sg:city":"Bedford",
    "sg:classifiers":[
        {
            "category":"Fast Food",
            "type":"Food & Drink"
        },
        {
            "category":"Restaurant",
            "type":"Food & Drink"
        }
    ],
    "sg:phone":"+1 540 586 2883",
    "sg:postcode":"24523",
    "sg:province":"VA",
    "sg:tags":[
        "pizza",
        "take",
        "italian"
    ],
    "wof:name":"Original Italian Pizza & Restaurant",
    "wof:placetype":"venue"
},
  "geometry": {"coordinates":[-79.54538700000001,37.336651],"type":"Point"}
}