{
  "type": "Feature",
  "properties": {
    "addr:full":"501 Dulany St Ste 1 Alexandria VA 22314",
    "addr:housenumber":"501",
    "addr:postcode":"22314",
    "addr:street":"Dulany St Ste 1",
    "iso:country":"US",
    "sg:address":"501 Dulany St Ste 1",
    "sg:city":"Alexandria",
    "sg:classifiers":[
        {
            "category":"Banks & Credit Unions",
            "subcategory":"Bank",
            "type":"Services"
        }
    ],
    "sg:phone":"+1 571 272 0350",
    "sg:postcode":"22314",
    "sg:province":"VA",
    "wof:name":"Pto Federal Credit Union",
    "wof:placetype":"venue"
},
  "geometry": {"coordinates":[-77.063484,38.80262],"type":"Point"}
}