{
  "type": "Feature",
  "properties": {
    "addr:full":"1101 Fort Evans Rd NE Leesburg VA 20176",
    "addr:housenumber":"1101",
    "addr:postcode":"20176",
    "addr:street":"Fort Evans Rd Ne",
    "iso:country":"US",
    "sg:address":"1101 Fort Evans Rd NE",
    "sg:city":"Leesburg",
    "sg:classifiers":[
        {
            "category":"Shopping",
            "subcategory":"Clothing, Apparel, & Fashions",
            "type":"Retail Goods"
        }
    ],
    "sg:phone":"+1 703 669 5930",
    "sg:postcode":"20176",
    "sg:province":"VA",
    "sg:website":"www.chicos.com",
    "wof:name":"Chico's",
    "wof:placetype":"venue"
},
  "geometry": {"coordinates":[-77.53815299999999,39.110345],"type":"Point"}
}