{
  "type": "Feature",
  "properties": {
    "iso:country":"US",
    "sg:address":"3029 Old Forest Rd",
    "sg:city":"Lynchburg",
    "sg:classifiers":[
        {
            "category":"Health Services",
            "subcategory":"Doctor",
            "type":"Services"
        }
    ],
    "sg:phone":"+1 434 385 7707",
    "sg:postcode":"24501",
    "sg:province":"VA",
    "sg:tags":[
        "dentist"
    ],
    "wof:name":"Riley & Riley LTD",
    "wof:placetype":"venue"
},
  "geometry": {"coordinates":[-79.20681399999999,37.414845],"type":"Point"}
}