{
  "type": "Feature",
  "properties": {
    "iso:country":"US",
    "sg:address":"17300 River Ridge Blvd",
    "sg:city":"Dumfries",
    "sg:classifiers":[
        {
            "category":"Real Estate",
            "subcategory":"Developer",
            "type":"Services"
        },
        {
            "category":"Professional",
            "subcategory":"Business Services",
            "type":"Services"
        }
    ],
    "sg:phone":"+1 703 221 7495",
    "sg:postcode":"22026",
    "sg:province":"VA",
    "wof:name":"Cherry Hill Commercial LLC",
    "wof:placetype":"venue"
},
  "geometry": {"coordinates":[-77.299493,38.57711],"type":"Point"}
}