{
  "type": "Feature",
  "properties": {
    "iso:country":"US",
    "sg:address":"1389 Harness Shop Rd",
    "sg:city":"Dayton",
    "sg:classifiers":[
        {
            "category":"Farming",
            "subcategory":"Livestock Farm",
            "type":"Manufacturing & Wholesale Goods"
        }
    ],
    "sg:phone":"+1 540 867 9418",
    "sg:postcode":"22821",
    "sg:province":"VA",
    "sg:tags":[
        "beef",
        "feedlot",
        "cattle"
    ],
    "wof:name":"Marion Coakley Farm",
    "wof:placetype":"venue"
},
  "geometry": {"coordinates":[-78.981658,38.448231],"type":"Point"}
}