{
  "type": "Feature",
  "properties": {
    "addr:full":"5615 Chamberlayne Ave Richmond VA 23227",
    "addr:housenumber":"5615",
    "addr:postcode":"23227",
    "addr:street":"Chamberlayne Ave",
    "iso:country":"US",
    "sg:address":"5615 Chamberlayne Ave",
    "sg:city":"Richmond",
    "sg:classifiers":[
        {
            "category":"Travel",
            "subcategory":"Hotels & Motels",
            "type":"Entertainment"
        }
    ],
    "sg:phone":"+1 804 262 8880",
    "sg:postcode":"23227",
    "sg:province":"VA",
    "sg:tags":[
        "operation"
    ],
    "wof:name":"Super 8 Motel",
    "wof:placetype":"venue"
},
  "geometry": {"coordinates":[-77.455012,37.621671],"type":"Point"}
}