{
  "type": "Feature",
  "properties": {
    "addr:full":"1525 Hollow Rd Gore VA 22637",
    "addr:housenumber":"1525",
    "addr:postcode":"22637",
    "addr:street":"Hollow Rd",
    "iso:country":"US",
    "sg:address":"1525 Hollow Rd",
    "sg:city":"Gore",
    "sg:classifiers":[
        {
            "category":"Building & Trades",
            "subcategory":"Construction",
            "type":"Services"
        }
    ],
    "sg:phone":"+1 540 858 3399",
    "sg:postcode":"22637",
    "sg:province":"VA",
    "sg:tags":[
        "carpentry",
        "contractor"
    ],
    "wof:name":"Schrock & Son Fine Carpentry",
    "wof:placetype":"venue"
},
  "geometry": {"coordinates":[-78.392415,39.268681],"type":"Point"}
}