{
  "type": "Feature",
  "properties": {
    "iso:country":"US",
    "sg:address":"707 S Jefferson St Ste 300",
    "sg:city":"Roanoke",
    "sg:classifiers":[
        {
            "category":"Professional",
            "subcategory":"Lawyer & Legal Services",
            "type":"Services"
        }
    ],
    "sg:phone":"+1 540 343 2451",
    "sg:postcode":"24016",
    "sg:province":"VA",
    "sg:tags":[
        "plan"
    ],
    "sg:website":"http://www.wootendhart.com",
    "wof:name":"Downs Charles L",
    "wof:placetype":"venue"
},
  "geometry": {"coordinates":[-79.940759,37.267839],"type":"Point"}
}