{
  "type": "Feature",
  "properties": {
    "addr:full":"115 Maryanne Ave SW Leesburg VA 20175",
    "addr:housenumber":"115",
    "addr:postcode":"20175",
    "addr:street":"Maryanne Ave Sw",
    "iso:country":"US",
    "sg:address":"115 Maryanne Ave SW",
    "sg:city":"Leesburg",
    "sg:classifiers":[
        {
            "category":"Home & Garden",
            "subcategory":"Home Furnishings",
            "type":"Retail Goods"
        }
    ],
    "sg:phone":"+1 703 777 9490",
    "sg:postcode":"20175",
    "sg:province":"VA",
    "sg:tags":[
        "lighting",
        "fixture"
    ],
    "wof:name":"Industrial Lighting",
    "wof:placetype":"venue"
},
  "geometry": {"coordinates":[-77.580404,39.10004],"type":"Point"}
}