{
  "type": "Feature",
  "properties": {
    "iso:country":"US",
    "sg:address":"21341 Old Dominion Rd",
    "sg:city":"Bristol",
    "sg:classifiers":[
        {
            "category":"Government",
            "subcategory":"Office",
            "type":"Public Place"
        }
    ],
    "sg:phone":"+1 276 669 9962",
    "sg:postcode":"24202",
    "sg:province":"VA",
    "wof:name":"Virginia Dept Motor Vehicles",
    "wof:placetype":"venue"
},
  "geometry": {"coordinates":[-82.098562,36.640872],"type":"Point"}
}