{
  "type": "Feature",
  "properties": {
    "addr:full":"401 N Old Church St Petersburg VA 23803",
    "addr:housenumber":"401",
    "addr:postcode":"23803",
    "addr:street":"N Old Church",
    "iso:country":"US",
    "sg:address":"401 N Old Church St",
    "sg:city":"Petersburg",
    "sg:classifiers":[
        {
            "category":"Taxi",
            "type":"Transportation"
        }
    ],
    "sg:phone":"+1 804 861 1183",
    "sg:postcode":"23803",
    "sg:province":"VA",
    "sg:tags":[
        "taxicab"
    ],
    "wof:name":"Yellow Cab Co",
    "wof:placetype":"venue"
},
  "geometry": {"coordinates":[-77.393726,37.235451],"type":"Point"}
}