{
  "type": "Feature",
  "properties": {
    "addr:full":"1320 Prince St Alexandria VA 22314",
    "addr:housenumber":"1320",
    "addr:postcode":"22314",
    "addr:street":"Prince St",
    "iso:country":"US",
    "sg:address":"1320 Prince St",
    "sg:city":"Alexandria",
    "sg:classifiers":[
        {
            "category":"Professional",
            "subcategory":"Business Services",
            "type":"Services"
        }
    ],
    "sg:phone":"+1 703 778 6440",
    "sg:postcode":"22314",
    "sg:province":"VA",
    "sg:tags":[
        "auctioneer"
    ],
    "wof:name":"EZ Auctioning",
    "wof:placetype":"venue"
},
  "geometry": {"coordinates":[-77.05400400000001,38.804798],"type":"Point"}
}