{
  "type": "Feature",
  "properties": {
    "iso:country":"US",
    "sg:address":"44055 Riverside Pkwy",
    "sg:city":"Leesburg",
    "sg:classifiers":[
        {
            "category":"Health Services",
            "subcategory":"Doctor",
            "type":"Services"
        }
    ],
    "sg:phone":"+1 703 858 5400",
    "sg:postcode":"20176",
    "sg:province":"VA",
    "sg:tags":[
        "medical"
    ],
    "wof:name":"Yasmin A Choudhry MD",
    "wof:placetype":"venue"
},
  "geometry": {"coordinates":[-77.47319899999999,39.072342],"type":"Point"}
}