{
  "type": "Feature",
  "properties": {
    "addr:full":"46740 Hollow Mountain Pl Sterling VA 20164",
    "addr:housenumber":"46740",
    "addr:postcode":"20164",
    "addr:street":"Hollow Mountain Pl",
    "iso:country":"US",
    "sg:address":"46740 Hollow Mountain Pl",
    "sg:city":"Sterling",
    "sg:classifiers":[
        {
            "category":"Professional",
            "subcategory":"Computer Services",
            "type":"Services"
        }
    ],
    "sg:phone":"+1 703 981 6096",
    "sg:postcode":"20164",
    "sg:province":"VA",
    "sg:tags":[
        "programming",
        "related"
    ],
    "wof:name":"Integralit Solutions LLC",
    "wof:placetype":"venue"
},
  "geometry": {"coordinates":[-77.380809,39.022877],"type":"Point"}
}