{
  "type": "Feature",
  "properties": {
    "addr:full":"620 W Park St Covington VA 24426",
    "addr:housenumber":"620",
    "addr:postcode":"24426",
    "addr:street":"W Park St",
    "iso:country":"US",
    "sg:address":"620 W Park St",
    "sg:city":"Covington",
    "sg:classifiers":[
        {
            "category":"Freight",
            "type":"Transportation"
        }
    ],
    "sg:phone":"+1 540 962 3215",
    "sg:postcode":"24426",
    "sg:province":"VA",
    "sg:tags":[
        "duct",
        "storage",
        "heating",
        "preparation",
        "also",
        "warehouse"
    ],
    "wof:name":"Phillips AC & Appl Sls & Svc",
    "wof:placetype":"venue"
},
  "geometry": {"coordinates":[-79.994573,37.759122],"type":"Point"}
}