{
  "type": "Feature",
  "properties": {
    "addr:full":"2003A Mt. Vernon Ave Alexandria VA 22301",
    "addr:housenumber":"2003a",
    "addr:postcode":"22301",
    "addr:street":"Mt. Vernon Ave",
    "iso:country":"US",
    "sg:address":"2003A Mt. Vernon Ave",
    "sg:city":"Alexandria",
    "sg:classifiers":[
        {
            "category":"Arts & Performance",
            "subcategory":"Art Gallery",
            "type":"Entertainment"
        },
        {
            "category":"Food & Beverages",
            "subcategory":"Chocolate",
            "type":"Retail Goods"
        }
    ],
    "sg:phone":"+1 703 635 7917",
    "sg:postcode":"22301",
    "sg:province":"VA",
    "sg:tags":[
        "shop",
        "cocoa",
        "chocolatiers"
    ],
    "sg:website":"www.thecocoagallery.com/",
    "wof:name":"Artfully Chocolate",
    "wof:placetype":"venue"
},
  "geometry": {"coordinates":[-77.05825299999999,38.824131],"type":"Point"}
}