{
  "type": "Feature",
  "properties": {
    "addr:full":"5131 S Scenic Hwy Bland VA 24315",
    "addr:housenumber":"5131",
    "addr:postcode":"24315",
    "addr:street":"S Scenic Hwy",
    "iso:country":"US",
    "sg:address":"5131 S Scenic Hwy",
    "sg:city":"Bland",
    "sg:classifiers":[
        {
            "category":"Building & Trades",
            "subcategory":"Plumbing",
            "type":"Services"
        }
    ],
    "sg:phone":"+1 276 688 4657",
    "sg:postcode":"24315",
    "sg:province":"VA",
    "sg:tags":[
        "heating",
        "contractor"
    ],
    "wof:name":"Quality Heating & A/C",
    "wof:placetype":"venue"
},
  "geometry": {"coordinates":[-81.171381,37.075209],"type":"Point"}
}