{
  "type": "Feature",
  "properties": {
    "addr:full":"1467 Joppa Mill Rd Bedford VA 24523",
    "addr:housenumber":"1467",
    "addr:postcode":"24523",
    "addr:street":"Joppa Mill Rd",
    "iso:country":"US",
    "sg:address":"1467 Joppa Mill Rd",
    "sg:city":"Bedford",
    "sg:classifiers":[
        {
            "category":"Professional",
            "subcategory":"Management & Consulting",
            "type":"Services"
        }
    ],
    "sg:phone":"+1 540 586 2946",
    "sg:postcode":"24523",
    "sg:province":"VA",
    "sg:tags":[
        "business"
    ],
    "wof:name":"Fe LLC",
    "wof:placetype":"venue"
},
  "geometry": {"coordinates":[-79.56038700000001,37.275464],"type":"Point"}
}