{
  "type": "Feature",
  "properties": {
    "addr:full":"4314 Chancery Park Dr Fairfax VA 22030",
    "addr:housenumber":"4314",
    "addr:postcode":"22030",
    "addr:street":"Chancery Park Dr",
    "iso:country":"US",
    "sg:address":"4314 Chancery Park Dr",
    "sg:city":"Fairfax",
    "sg:classifiers":[
        {
            "category":"Professional",
            "type":"Services"
        }
    ],
    "sg:phone":"+1 703 273 2824",
    "sg:postcode":"22030",
    "sg:province":"VA",
    "wof:name":"Dr Kanwar Habib Khan",
    "wof:placetype":"venue"
},
  "geometry": {"coordinates":[-77.31758000000001,38.838338],"type":"Point"}
}