{
  "type": "Feature",
  "properties": {
    "addr:full":"25331 Lafayette Dr Rhoadesville VA 22542",
    "addr:housenumber":"25331",
    "addr:postcode":"22542",
    "addr:street":"Lafayette Dr",
    "iso:country":"US",
    "sg:address":"25331 Lafayette Dr",
    "sg:city":"Rhoadesville",
    "sg:classifiers":[
        {
            "category":"Building & Trades",
            "subcategory":"Construction",
            "type":"Services"
        }
    ],
    "sg:phone":"+1 540 854 7753",
    "sg:postcode":"22542",
    "sg:province":"VA",
    "sg:tags":[
        "speculative",
        "builder",
        "contractor"
    ],
    "wof:name":"Wright Way Construction Co",
    "wof:placetype":"venue"
},
  "geometry": {"coordinates":[-77.928594,38.273535],"type":"Point"}
}