{
  "type": "Feature",
  "properties": {
    "addr:full":"3646 Delhart Rd Galax VA 24333",
    "addr:housenumber":"3646",
    "addr:postcode":"24333",
    "addr:street":"Delhart Rd",
    "iso:country":"US",
    "sg:address":"3646 Delhart Rd",
    "sg:city":"Galax",
    "sg:classifiers":[
        {
            "category":"Building & Trades",
            "subcategory":"Construction",
            "type":"Services"
        }
    ],
    "sg:phone":"+1 276 238 9888",
    "sg:postcode":"24333",
    "sg:province":"VA",
    "sg:tags":[
        "water",
        "well",
        "drilling"
    ],
    "wof:name":"Clearwater Drilling Company",
    "wof:placetype":"venue"
},
  "geometry": {"coordinates":[-80.974142,36.597901],"type":"Point"}
}