{
  "type": "Feature",
  "properties": {
    "addr:full":"2020 14th St N Ste 301 Arlington VA 22201",
    "addr:housenumber":"2020",
    "addr:postcode":"22201",
    "addr:street":"14Th St N Ste 301",
    "iso:country":"US",
    "sg:address":"2020 14th St N Ste 301",
    "sg:city":"Arlington",
    "sg:classifiers":[
        {
            "category":"Travel",
            "subcategory":"Travel Agent",
            "type":"Entertainment"
        }
    ],
    "sg:phone":"+1 800 591 7218",
    "sg:postcode":"22201",
    "sg:province":"VA",
    "sg:tags":[
        "agency",
        "services-commercial"
    ],
    "sg:website":"http://www.garber.com",
    "wof:name":"Garber's Travel Agency 60",
    "wof:placetype":"venue"
},
  "geometry": {"coordinates":[-77.08289600000001,38.889667],"type":"Point"}
}