{
  "type": "Feature",
  "properties": {
    "addr:full":"4500 N Old Dominion Dr Arlington VA 22207",
    "addr:housenumber":"4500",
    "addr:postcode":"22207",
    "addr:street":"N Old Dominion Dr",
    "iso:country":"US",
    "sg:address":"4500 N Old Dominion Dr",
    "sg:city":"Arlington",
    "sg:classifiers":[
        {
            "category":"Real Estate",
            "subcategory":"Real Estate Agent",
            "type":"Services"
        }
    ],
    "sg:phone":"+1 703 524 2100",
    "sg:postcode":"22207",
    "sg:province":"VA",
    "sg:website":"www.cbmove.com",
    "wof:name":"Coldwell Banker",
    "wof:placetype":"venue"
},
  "geometry": {"coordinates":[-77.118628,38.899043],"type":"Point"}
}