{
  "type": "Feature",
  "properties": {
    "iso:country":"US",
    "sg:address":"815 Arlington Ter",
    "sg:city":"Hampton",
    "sg:classifiers":[
        {
            "category":"Food & Beverages",
            "subcategory":"Groceries & Convenience Stores",
            "type":"Retail Goods"
        }
    ],
    "sg:phone":"+1 757 896 1074",
    "sg:postcode":"23666",
    "sg:province":"VA",
    "wof:name":"Sergeants Woodcrafts",
    "wof:placetype":"venue"
},
  "geometry": {"coordinates":[-76.42729799999999,37.041598],"type":"Point"}
}