{
  "type": "Feature",
  "properties": {
    "addr:full":"2811 12th St S Arlington VA 22204",
    "addr:housenumber":"2811",
    "addr:postcode":"22204",
    "addr:street":"12Th St S",
    "iso:country":"US",
    "sg:address":"2811 12th St S",
    "sg:city":"Arlington",
    "sg:classifiers":[
        {
            "category":"Building & Trades",
            "subcategory":"Construction",
            "type":"Services"
        }
    ],
    "sg:phone":"+1 703 920 3812",
    "sg:postcode":"22204",
    "sg:province":"VA",
    "sg:tags":[
        "equipment",
        "supply",
        "drywall",
        "contractor"
    ],
    "wof:name":"Pat Contractors Inc",
    "wof:placetype":"venue"
},
  "geometry": {"coordinates":[-77.0859,38.860953],"type":"Point"}
}