{
  "type": "Feature",
  "properties": {
    "addr:full":"510 S 18th Ave Hopewell VA 23860",
    "addr:housenumber":"510",
    "addr:postcode":"23860",
    "addr:street":"S 18Th Ave",
    "iso:country":"US",
    "sg:address":"510 S 18th Ave",
    "sg:city":"Hopewell",
    "sg:classifiers":[
        {
            "category":"Building & Trades",
            "subcategory":"Construction",
            "type":"Services"
        }
    ],
    "sg:phone":"+1 804 458 8540",
    "sg:postcode":"23860",
    "sg:province":"VA",
    "sg:tags":[
        "painter"
    ],
    "wof:name":"G T Painting & Construction Co",
    "wof:placetype":"venue"
},
  "geometry": {"coordinates":[-77.298973,37.291793],"type":"Point"}
}