{
  "type": "Feature",
  "properties": {
    "iso:country":"US",
    "sg:address":"113 Oxford Cir W",
    "sg:city":"Richmond",
    "sg:classifiers":[
        {
            "category":"Health Services",
            "subcategory":"Doctor",
            "type":"Services"
        }
    ],
    "sg:phone":"+1 804 359 4381",
    "sg:postcode":"23221",
    "sg:province":"VA",
    "sg:tags":[
        "medical"
    ],
    "wof:name":"Mauck H Page Jr Dr",
    "wof:placetype":"venue"
},
  "geometry": {"coordinates":[-77.501964,37.557525],"type":"Point"}
}