{
  "type": "Feature",
  "properties": {
    "iso:country":"US",
    "sg:address":"1010 N Glebe Rd",
    "sg:city":"Arlington",
    "sg:classifiers":[
        {
            "category":"Parking",
            "type":"Transportation"
        }
    ],
    "sg:phone":"+1 703 524 2516",
    "sg:postcode":"22201",
    "sg:province":"VA",
    "wof:name":"Carrpark",
    "wof:placetype":"venue"
},
  "geometry": {"coordinates":[-77.116302,38.8829],"type":"Point"}
}