{
  "type": "Feature",
  "properties": {
    "addr:full":"5104 Glenwood Way Virginia Beach VA 23456",
    "addr:housenumber":"5104",
    "addr:postcode":"23456",
    "addr:street":"Glenwood Way",
    "iso:country":"US",
    "sg:address":"5104 Glenwood Way",
    "sg:city":"Virginia Beach",
    "sg:classifiers":[
        {
            "category":"Building & Trades",
            "subcategory":"Construction",
            "type":"Services"
        }
    ],
    "sg:phone":"+1 757 339 9443",
    "sg:postcode":"23456",
    "sg:province":"VA",
    "sg:tags":[
        "hanging",
        "contractor"
    ],
    "wof:name":"Custom Pntg & Pressure Wshg",
    "wof:placetype":"venue"
},
  "geometry": {"coordinates":[-76.130381,36.778631],"type":"Point"}
}