{
  "type": "Feature",
  "properties": {
    "addr:full":"8403 Porter Ln Alexandria VA 22308",
    "addr:housenumber":"8403",
    "addr:postcode":"22308",
    "addr:street":"Porter Ln",
    "iso:country":"US",
    "sg:address":"8403 Porter Ln",
    "sg:city":"Alexandria",
    "sg:classifiers":[
        {
            "category":"Professional",
            "subcategory":"Computer Services",
            "type":"Services"
        }
    ],
    "sg:phone":"+1 703 684 1660",
    "sg:postcode":"22308",
    "sg:province":"VA",
    "sg:tags":[
        "co",
        "for",
        "financial",
        "modeling",
        "develop",
        "software"
    ],
    "sg:website":"www.ferox.com",
    "wof:name":"Ferox Microsystems Inc",
    "wof:placetype":"venue"
},
  "geometry": {"coordinates":[-77.076111,38.728492],"type":"Point"}
}