{
  "type": "Feature",
  "properties": {
    "iso:country":"US",
    "sg:address":"305 Grove Ave",
    "sg:city":"Petersburg",
    "sg:classifiers":[
        {
            "category":"Shopping",
            "subcategory":"Books",
            "type":"Retail Goods"
        }
    ],
    "sg:phone":"+1 804 732 2752",
    "sg:postcode":"23803",
    "sg:province":"VA",
    "wof:name":"Riverside Book Shoppe",
    "wof:placetype":"venue"
},
  "geometry": {"coordinates":[-77.41001199999999,37.232346],"type":"Point"}
}