{
  "type": "Feature",
  "properties": {
    "addr:full":"46490 Cedarhurst Dr Sterling VA 20165",
    "addr:housenumber":"46490",
    "addr:postcode":"20165",
    "addr:street":"Cedarhurst Dr",
    "iso:country":"US",
    "sg:address":"46490 Cedarhurst Dr",
    "sg:city":"Sterling",
    "sg:classifiers":[
        {
            "category":"Building & Trades",
            "subcategory":"Equipment Rental",
            "type":"Services"
        }
    ],
    "sg:phone":"+1 703 406 0006",
    "sg:postcode":"20165",
    "sg:province":"VA",
    "wof:name":"A V Comm",
    "wof:placetype":"venue"
},
  "geometry": {"coordinates":[-77.392364,39.047458],"type":"Point"}
}