{
  "type": "Feature",
  "properties": {
    "iso:country":"US",
    "sg:address":"1091 Rocky Run Rd",
    "sg:city":"Mc Lean",
    "sg:classifiers":[
        {
            "category":"Professional",
            "subcategory":"Research",
            "type":"Services"
        }
    ],
    "sg:phone":"+1 703 757 7395",
    "sg:postcode":"22102",
    "sg:province":"VA",
    "sg:tags":[
        "nonphysical",
        "consulting",
        "management",
        "commercial",
        "s"
    ],
    "sg:website":"www.dodiligence.com",
    "wof:name":"Do Diligence Partners Inc",
    "wof:placetype":"venue"
},
  "geometry": {"coordinates":[-77.25660000000001,38.96328],"type":"Point"}
}