{
  "type": "Feature",
  "properties": {
    "addr:full":"405 N 1st St Richmond VA 23219",
    "addr:housenumber":"405",
    "addr:postcode":"23219",
    "addr:street":"N 1St St",
    "iso:country":"US",
    "sg:address":"405 N 1st St",
    "sg:city":"Richmond",
    "sg:classifiers":[
        {
            "category":"Shopping",
            "subcategory":"Used Merchandise",
            "type":"Retail Goods"
        }
    ],
    "sg:phone":"+1 804 225 9663",
    "sg:postcode":"23219",
    "sg:province":"VA",
    "sg:tags":[
        "clothing"
    ],
    "wof:name":"All That Fashions",
    "wof:placetype":"venue"
},
  "geometry": {"coordinates":[-77.43938799999999,37.546741],"type":"Point"}
}