{
  "type": "Feature",
  "properties": {
    "addr:full":"500 Turner Rd Salem VA 24153",
    "addr:housenumber":"500",
    "addr:postcode":"24153",
    "addr:street":"Turner Rd",
    "iso:country":"US",
    "sg:address":"500 Turner Rd",
    "sg:city":"Salem",
    "sg:classifiers":[
        {
            "category":"Social Services",
            "subcategory":"Child Care",
            "type":"Services"
        }
    ],
    "sg:phone":"+1 540 389 7031",
    "sg:postcode":"24153",
    "sg:province":"VA",
    "wof:name":"West Salem Child Development",
    "wof:placetype":"venue"
},
  "geometry": {"coordinates":[-80.088246,37.293973],"type":"Point"}
}