{
  "type": "Feature",
  "properties": {
    "iso:country":"US",
    "sg:address":"11104 Light Guard Loop",
    "sg:city":"Manassas",
    "sg:classifiers":[
        {
            "category":"Building & Trades",
            "subcategory":"Plumbing",
            "type":"Services"
        }
    ],
    "sg:phone":"+1 703 393 1207",
    "sg:postcode":"20109",
    "sg:province":"VA",
    "sg:tags":[
        "contractor"
    ],
    "wof:name":"Quick Call Plumbing LLC",
    "wof:placetype":"venue"
},
  "geometry": {"coordinates":[-77.527957,38.787493],"type":"Point"}
}