{
  "type": "Feature",
  "properties": {
    "addr:full":"530 S Sycamore St Petersburg VA 23803",
    "addr:housenumber":"530",
    "addr:postcode":"23803",
    "addr:street":"S Sycamore",
    "iso:country":"US",
    "sg:address":"530 S Sycamore St",
    "sg:city":"Petersburg",
    "sg:classifiers":[
        {
            "category":"Health Services",
            "subcategory":"Doctor",
            "type":"Services"
        }
    ],
    "sg:phone":"+1 804 732 0301",
    "sg:postcode":"23803",
    "sg:province":"VA",
    "sg:tags":[
        "physician",
        "surgeon",
        "medical"
    ],
    "wof:name":"Arthristis & Musculoskeletal",
    "wof:placetype":"venue"
},
  "geometry": {"coordinates":[-77.400235,37.21946],"type":"Point"}
}