{
  "type": "Feature",
  "properties": {
    "iso:country":"US",
    "sg:address":"901 4th St",
    "sg:city":"Waynesboro",
    "sg:classifiers":[
        {
            "category":"Real Estate",
            "subcategory":"Real Estate Operator",
            "type":"Services"
        }
    ],
    "sg:phone":"+1 540 943 6372",
    "sg:postcode":"22980",
    "sg:province":"VA",
    "sg:tags":[
        "building",
        "apartment"
    ],
    "wof:name":"Quadrangle Apartments",
    "wof:placetype":"venue"
},
  "geometry": {"coordinates":[-78.870171,38.072401],"type":"Point"}
}