{
  "type": "Feature",
  "properties": {
    "addr:full":"1409 Rittenour Rd Edinburg VA 22824",
    "addr:housenumber":"1409",
    "addr:postcode":"22824",
    "addr:street":"Rittenour Rd",
    "iso:country":"US",
    "sg:address":"1409 Rittenour Rd",
    "sg:city":"Edinburg",
    "sg:classifiers":[
        {
            "category":"Shopping",
            "subcategory":"Hobbies, Toys, & Games",
            "type":"Retail Goods"
        }
    ],
    "sg:phone":"+1 540 984 4577",
    "sg:postcode":"22824",
    "sg:province":"VA",
    "sg:tags":[
        "equipment",
        "ceramic",
        "supply"
    ],
    "wof:name":"Dodson Ceramics & Crafts",
    "wof:placetype":"venue"
},
  "geometry": {"coordinates":[-78.59112399999999,38.85934],"type":"Point"}
}