{
  "type": "Feature",
  "properties": {
    "addr:full":"525 Clifton St Damascus VA 24236",
    "addr:housenumber":"525",
    "addr:postcode":"24236",
    "addr:street":"Clifton St",
    "iso:country":"US",
    "sg:address":"525 Clifton St",
    "sg:city":"Damascus",
    "sg:classifiers":[
        {
            "category":"Recreation",
            "type":"Entertainment"
        }
    ],
    "sg:phone":"+1 276 475 5765",
    "sg:postcode":"24236",
    "sg:province":"VA",
    "wof:name":"Flyaway Hot Air Balloons",
    "wof:placetype":"venue"
},
  "geometry": {"coordinates":[-81.793645,36.634968],"type":"Point"}
}