{
  "type": "Feature",
  "properties": {
    "addr:full":"2251 Eisenhower Ave Alexandria VA 22314",
    "addr:housenumber":"2251",
    "addr:postcode":"22314",
    "addr:street":"Eisenhower Ave",
    "iso:country":"US",
    "sg:address":"2251 Eisenhower Ave",
    "sg:city":"Alexandria",
    "sg:classifiers":[
        {
            "category":"Building & Trades",
            "subcategory":"Construction",
            "type":"Services"
        }
    ],
    "sg:phone":"+1 703 706 0076",
    "sg:postcode":"22314",
    "sg:province":"VA",
    "sg:tags":[
        "contractor"
    ],
    "wof:name":"Ronan Spelman",
    "wof:placetype":"venue"
},
  "geometry": {"coordinates":[-77.068443,38.800924],"type":"Point"}
}