{
  "type": "Feature",
  "properties": {
    "iso:country":"US",
    "sg:address":"8801 Forest Hill Ave",
    "sg:city":"Richmond",
    "sg:classifiers":[
        {
            "category":"Building & Trades",
            "subcategory":"Construction",
            "type":"Services"
        }
    ],
    "sg:phone":"+1 804 320 4678",
    "sg:postcode":"23235",
    "sg:province":"VA",
    "sg:tags":[
        "contractor",
        "mechanical"
    ],
    "wof:name":"Richmond Mech Serv",
    "wof:placetype":"venue"
},
  "geometry": {"coordinates":[-77.56012,37.53466],"type":"Point"}
}