{
  "type": "Feature",
  "properties": {
    "addr:full":"305 S Park St Marion VA 24354",
    "addr:housenumber":"305",
    "addr:postcode":"24354",
    "addr:street":"S Park St",
    "iso:country":"US",
    "sg:address":"305 S Park St",
    "sg:city":"Marion",
    "sg:classifiers":[
        {
            "category":"Government",
            "subcategory":"Police Station",
            "type":"Public Place"
        }
    ],
    "sg:phone":"+1 276 783 8145",
    "sg:postcode":"24354",
    "sg:province":"VA",
    "sg:tags":[
        "department",
        "protection"
    ],
    "wof:name":"Marion Police Department",
    "wof:placetype":"venue"
},
  "geometry": {"coordinates":[-81.51906700000001,36.830573],"type":"Point"}
}