{
  "type": "Feature",
  "properties": {
    "addr:full":"325 Elm Ave SE Roanoke VA 24013",
    "addr:housenumber":"325",
    "addr:postcode":"24013",
    "addr:street":"Elm Ave Se",
    "iso:country":"US",
    "sg:address":"325 Elm Ave SE",
    "sg:city":"Roanoke",
    "sg:classifiers":[
        {
            "category":"Restaurant",
            "type":"Food & Drink"
        }
    ],
    "sg:menulink":"http://www.allmenus.com/va/roanoke/80429-dominos-pizza/menu/",
    "sg:phone":"+1 540 345 3033",
    "sg:postcode":"24013",
    "sg:province":"VA",
    "sg:tags":[
        "american",
        "wing",
        "pizza"
    ],
    "wof:name":"Domino's Pizza",
    "wof:placetype":"venue"
},
  "geometry": {"coordinates":[-79.93612899999999,37.266762],"type":"Point"}
}