{
  "type": "Feature",
  "properties": {
    "addr:full":"2007 Sleepy Hollow Rd Stanley VA 22835",
    "addr:housenumber":"2007",
    "addr:postcode":"22835",
    "addr:street":"Sleepy Hollow Rd",
    "iso:country":"US",
    "sg:address":"2007 Sleepy Hollow Rd",
    "sg:city":"Stanley",
    "sg:classifiers":[
        {
            "category":"Professional",
            "type":"Services"
        }
    ],
    "sg:phone":"+1 540 778 1239",
    "sg:postcode":"22835",
    "sg:province":"VA",
    "wof:name":"Apollo World LLC",
    "wof:placetype":"venue"
},
  "geometry": {"coordinates":[-78.468283,38.600256],"type":"Point"}
}