{
  "type": "Feature",
  "properties": {
    "addr:full":"371 Circuit Ln Newport News VA 23608",
    "addr:housenumber":"371",
    "addr:postcode":"23608",
    "addr:street":"Circuit Ln",
    "iso:country":"US",
    "sg:address":"371 Circuit Ln",
    "sg:city":"Newport News",
    "sg:classifiers":[
        {
            "category":"Travel",
            "subcategory":"Travel Agent",
            "type":"Entertainment"
        }
    ],
    "sg:phone":"+1 757 874 1992",
    "sg:postcode":"23608",
    "sg:province":"VA",
    "sg:tags":[
        "agency",
        "bureau"
    ],
    "wof:name":"Victoria's Travels",
    "wof:placetype":"venue"
},
  "geometry": {"coordinates":[-76.534503,37.139049],"type":"Point"}
}