{
  "type": "Feature",
  "properties": {
    "addr:full":"661 University Ln Orange VA 22960",
    "addr:housenumber":"661",
    "addr:postcode":"22960",
    "addr:street":"University Ln",
    "iso:country":"US",
    "sg:address":"661 University Ln",
    "sg:city":"Orange",
    "sg:classifiers":[
        {
            "category":"Health Services",
            "subcategory":"Doctor",
            "type":"Services"
        }
    ],
    "sg:phone":"+1 540 672 0522",
    "sg:postcode":"22960",
    "sg:province":"VA",
    "sg:tags":[
        "physician",
        "surgeon"
    ],
    "wof:name":"Orange Medical Ctr",
    "wof:placetype":"venue"
},
  "geometry": {"coordinates":[-78.118909,38.258358],"type":"Point"}
}