{
  "type": "Feature",
  "properties": {
    "addr:full":"4029 Majestic Ln Fairfax VA 22033",
    "addr:housenumber":"4029",
    "addr:postcode":"22033",
    "addr:street":"Majestic Ln",
    "iso:country":"US",
    "sg:address":"4029 Majestic Ln",
    "sg:city":"Fairfax",
    "sg:classifiers":[
        {
            "category":"Professional",
            "type":"Services"
        }
    ],
    "sg:phone":"+1 703 378 0947",
    "sg:postcode":"22033",
    "sg:province":"VA",
    "wof:name":"Preslav Panev",
    "wof:placetype":"venue"
},
  "geometry": {"coordinates":[-77.395712,38.878446],"type":"Point"}
}