{
  "type": "Feature",
  "properties": {
    "iso:country":"US",
    "sg:address":"40 E Market St",
    "sg:city":"Harrisonburg",
    "sg:classifiers":[
        {
            "category":"Shopping",
            "subcategory":"Used Merchandise",
            "type":"Retail Goods"
        }
    ],
    "sg:phone":"+1 540 432 6677",
    "sg:postcode":"22801",
    "sg:province":"VA",
    "sg:tags":[
        "antique"
    ],
    "wof:name":"Hoot & Annie",
    "wof:placetype":"venue"
},
  "geometry": {"coordinates":[-78.868207,38.449396],"type":"Point"}
}