{
  "type": "Feature",
  "properties": {
    "addr:full":"3520 James Madison Hwy Haymarket VA 20169",
    "addr:housenumber":"3520",
    "addr:postcode":"20169",
    "addr:street":"James Madison Hwy",
    "iso:country":"US",
    "sg:address":"3520 James Madison Hwy",
    "sg:city":"Haymarket",
    "sg:classifiers":[
        {
            "category":"Sports & Exercise",
            "subcategory":"Golf",
            "type":"Entertainment"
        }
    ],
    "sg:phone":"+1 703 753 7777",
    "sg:postcode":"20169",
    "sg:province":"VA",
    "sg:website":"www.bullruncc.com",
    "wof:name":"Bull Run Golf Club",
    "wof:placetype":"venue"
},
  "geometry": {"coordinates":[-77.633797,38.8811],"type":"Point"}
}