{
  "type": "Feature",
  "properties": {
    "addr:full":"1319 Summit Ave Richmond VA 23230",
    "addr:housenumber":"1319",
    "addr:postcode":"23230",
    "addr:street":"Summit Ave",
    "iso:country":"US",
    "sg:address":"1319 Summit Ave",
    "sg:city":"Richmond",
    "sg:classifiers":[
        {
            "category":"Personal",
            "subcategory":"Beauty Salon",
            "type":"Services"
        }
    ],
    "sg:phone":"+1 804 353 2463",
    "sg:postcode":"23230",
    "sg:province":"VA",
    "sg:tags":[
        "shop"
    ],
    "wof:name":"Olga's Beauty Salon",
    "wof:placetype":"venue"
},
  "geometry": {"coordinates":[-77.471985,37.56644],"type":"Point"}
}