{
  "type": "Feature",
  "properties": {
    "addr:full":"13855 Langstone Dr Woodbridge VA 22193",
    "addr:postcode":"13855;22193",
    "addr:street":"Langstone Dr",
    "iso:country":"US",
    "sg:address":"13855 Langstone Dr",
    "sg:city":"Woodbridge",
    "sg:classifiers":[
        {
            "category":"Building & Trades",
            "subcategory":"Construction",
            "type":"Services"
        }
    ],
    "sg:phone":"+1 703 730 2154",
    "sg:postcode":"22193",
    "sg:province":"VA",
    "sg:tags":[
        "house"
    ],
    "wof:name":"Jaime Construction",
    "wof:placetype":"venue"
},
  "geometry": {"coordinates":[-77.359734,38.652913],"type":"Point"}
}