{
  "type": "Feature",
  "properties": {
    "iso:country":"US",
    "sg:address":"6305 Willowfield Way",
    "sg:city":"Springfield",
    "sg:classifiers":[
        {
            "category":"Shopping",
            "subcategory":"Computers & Home Electronics",
            "type":"Retail Goods"
        }
    ],
    "sg:phone":"+1 703 314 7055",
    "sg:postcode":"22150",
    "sg:province":"VA",
    "wof:name":"Blue Cow Audio LLC",
    "wof:placetype":"venue"
},
  "geometry": {"coordinates":[-77.158339,38.782147],"type":"Point"}
}