{
  "type": "Feature",
  "properties": {
    "addr:full":"4902 Frontage Rd NW Roanoke VA 24019",
    "addr:housenumber":"4902",
    "addr:postcode":"24019",
    "addr:street":"Frontage Rd Nw",
    "iso:country":"US",
    "sg:address":"4902 Frontage Rd NW",
    "sg:city":"Roanoke",
    "sg:classifiers":[
        {
            "category":"Health Services",
            "subcategory":"Hospital",
            "type":"Services"
        }
    ],
    "sg:phone":"+1 540 563 8575",
    "sg:postcode":"24019",
    "sg:province":"VA",
    "sg:tags":[
        "general"
    ],
    "wof:name":"Evsr",
    "wof:placetype":"venue"
},
  "geometry": {"coordinates":[-79.99305200000001,37.32465],"type":"Point"}
}