{
  "type": "Feature",
  "properties": {
    "addr:full":"3027 Peters Creek Rd NW Roanoke VA 24019",
    "addr:housenumber":"3027",
    "addr:postcode":"24019",
    "addr:street":"Peters Creek Rd Nw",
    "iso:country":"US",
    "sg:address":"3027 Peters Creek Rd NW",
    "sg:city":"Roanoke",
    "sg:classifiers":[
        {
            "category":"Health Services",
            "subcategory":"Medical Lab",
            "type":"Services"
        }
    ],
    "sg:phone":"+1 540 562 2180",
    "sg:postcode":"24019",
    "sg:province":"VA",
    "sg:tags":[
        "laboratory"
    ],
    "wof:name":"Quest Diagnostics",
    "wof:placetype":"venue"
},
  "geometry": {"coordinates":[-80.001384,37.318982],"type":"Point"}
}