{
  "type": "Feature",
  "properties": {
    "iso:country":"US",
    "sg:address":"7715 Bristol Square Ct",
    "sg:city":"Springfield",
    "sg:classifiers":[
        {
            "category":"Wholesale",
            "subcategory":"Hardware",
            "type":"Manufacturing & Wholesale Goods"
        }
    ],
    "sg:phone":"+1 703 866 5521",
    "sg:postcode":"22153",
    "sg:province":"VA",
    "sg:tags":[
        "plumbing",
        "equipment",
        "fixture",
        "supply"
    ],
    "wof:name":"Environmental Solutions",
    "wof:placetype":"venue"
},
  "geometry": {"coordinates":[-77.210441,38.735724],"type":"Point"}
}