{
  "type": "Feature",
  "properties": {
    "addr:full":"605 N Loudoun St Winchester VA 22601",
    "addr:housenumber":"605",
    "addr:postcode":"22601",
    "addr:street":"N Loudoun St",
    "iso:country":"US",
    "sg:address":"605 N Loudoun St",
    "sg:city":"Winchester",
    "sg:classifiers":[
        {
            "category":"Freight",
            "type":"Transportation"
        }
    ],
    "sg:phone":"+1 540 667 4014",
    "sg:postcode":"22601",
    "sg:province":"VA",
    "sg:tags":[
        "packaging",
        "fruit"
    ],
    "wof:name":"Shenandoah Fruit Company Inc",
    "wof:placetype":"venue"
},
  "geometry": {"coordinates":[-78.161912,39.19404],"type":"Point"}
}