{
  "type": "Feature",
  "properties": {
    "addr:full":"211 High View Dr Blacksburg VA 24060",
    "addr:housenumber":"211",
    "addr:postcode":"24060",
    "addr:street":"High View Dr",
    "iso:country":"US",
    "sg:address":"211 High View Dr",
    "sg:city":"Blacksburg",
    "sg:classifiers":[
        {
            "category":"Retail",
            "subcategory":"Repair Shop",
            "type":"Services"
        }
    ],
    "sg:phone":"+1 540 552 4726",
    "sg:postcode":"24060",
    "sg:province":"VA",
    "wof:name":"Jones Auto Supply",
    "wof:placetype":"venue"
},
  "geometry": {"coordinates":[-80.41009,37.246196],"type":"Point"}
}