{
  "type": "Feature",
  "properties": {
    "addr:full":"8580 Overhill Dr Manassas VA 20111",
    "addr:housenumber":"8580",
    "addr:postcode":"20111",
    "addr:street":"Overhill Dr",
    "iso:country":"US",
    "sg:address":"8580 Overhill Dr",
    "sg:city":"Manassas",
    "sg:classifiers":[
        {
            "category":"Utilities",
            "subcategory":"Telephone",
            "type":"Services"
        }
    ],
    "sg:phone":"+1 703 392 7040",
    "sg:postcode":"20111",
    "sg:province":"VA",
    "sg:tags":[
        "communications"
    ],
    "wof:name":"Needguide LLC",
    "wof:placetype":"venue"
},
  "geometry": {"coordinates":[-77.448168,38.770236],"type":"Point"}
}