{
  "type": "Feature",
  "properties": {
    "addr:full":"213 Wilderness Way Moneta VA 24121",
    "addr:housenumber":"213",
    "addr:postcode":"24121",
    "addr:street":"Wilderness Way",
    "iso:country":"US",
    "sg:address":"213 Wilderness Way",
    "sg:city":"Moneta",
    "sg:classifiers":[
        {
            "category":"Professional",
            "subcategory":"Accounting & Tax Preparation",
            "type":"Services"
        }
    ],
    "sg:phone":"+1 540 296 1544",
    "sg:postcode":"24121",
    "sg:province":"VA",
    "sg:tags":[
        "accountant"
    ],
    "wof:name":"Orndorff & Assoc",
    "wof:placetype":"venue"
},
  "geometry": {"coordinates":[-79.64471399999999,37.131516],"type":"Point"}
}