{
  "type": "Feature",
  "properties": {
    "iso:country":"US",
    "sg:address":"10300 Spotsylvania Ave",
    "sg:city":"Fredericksburg",
    "sg:classifiers":[
        {
            "category":"Professional",
            "subcategory":"Management & Consulting",
            "type":"Services"
        }
    ],
    "sg:phone":"+1 540 710 7707",
    "sg:postcode":"22408",
    "sg:province":"VA",
    "sg:tags":[
        "fuel"
    ],
    "wof:name":"Bernstein Management Corp",
    "wof:placetype":"venue"
},
  "geometry": {"coordinates":[-77.496461,38.239051],"type":"Point"}
}