{
  "type": "Feature",
  "properties": {
    "addr:full":"7434 Little River Tpke Annandale VA 22003",
    "addr:housenumber":"7434",
    "addr:postcode":"22003",
    "addr:street":"Little River Tpke",
    "iso:country":"US",
    "sg:address":"7434 Little River Tpke",
    "sg:city":"Annandale",
    "sg:classifiers":[
        {
            "category":"Shopping",
            "subcategory":"Pharmacy",
            "type":"Retail Goods"
        }
    ],
    "sg:phone":"+1 703 256 7487",
    "sg:postcode":"22003",
    "sg:province":"VA",
    "sg:tags":[
        "drug",
        "store"
    ],
    "wof:name":"Rite Aid",
    "wof:placetype":"venue"
},
  "geometry": {"coordinates":[-77.20241300000001,38.831619],"type":"Point"}
}