{
  "type": "Feature",
  "properties": {
    "addr:full":"2702 Sutton Rd Vienna VA 22181",
    "addr:housenumber":"2702",
    "addr:postcode":"22181",
    "addr:street":"Sutton Rd",
    "iso:country":"US",
    "sg:address":"2702 Sutton Rd",
    "sg:city":"Vienna",
    "sg:classifiers":[
        {
            "category":"Building & Trades",
            "subcategory":"Construction",
            "type":"Services"
        }
    ],
    "sg:phone":"+1 703 242 3599",
    "sg:postcode":"22181",
    "sg:province":"VA",
    "sg:tags":[
        "contractor"
    ],
    "wof:name":"Gutter Works Co",
    "wof:placetype":"venue"
},
  "geometry": {"coordinates":[-77.280959,38.885709],"type":"Point"}
}