{
  "type": "Feature",
  "properties": {
    "addr:full":"202 N Loudoun St Winchester VA 22601",
    "addr:housenumber":"202",
    "addr:postcode":"22601",
    "addr:street":"N Loudoun St",
    "iso:country":"US",
    "sg:address":"202 N Loudoun St",
    "sg:city":"Winchester",
    "sg:classifiers":[
        {
            "category":"Banks & Credit Unions",
            "subcategory":"Bank",
            "type":"Services"
        }
    ],
    "sg:phone":"+1 540 665 6614",
    "sg:postcode":"22601",
    "sg:province":"VA",
    "sg:tags":[
        "national",
        "commercial"
    ],
    "wof:name":"Wachovia Mortgage Fincl Svcs",
    "wof:placetype":"venue"
},
  "geometry": {"coordinates":[-78.16443599999999,39.187027],"type":"Point"}
}