{
  "type": "Feature",
  "properties": {
    "iso:country":"US",
    "sg:address":"120 Front Royal Pike",
    "sg:city":"Winchester",
    "sg:classifiers":[
        {
            "category":"Restaurant",
            "type":"Food & Drink"
        }
    ],
    "sg:menulink":"http://www.allmenus.com/va/shawnee/257656-texas-steakhouse-and-saloon/menu/",
    "sg:phone":"+1 540 665 4400",
    "sg:postcode":"22602",
    "sg:province":"VA",
    "sg:tags":[
        "american",
        "steakhouse"
    ],
    "wof:name":"Texas Steakhouse And Saloon",
    "wof:placetype":"venue"
},
  "geometry": {"coordinates":[-78.156144,39.160218],"type":"Point"}
}