{
  "type": "Feature",
  "properties": {
    "iso:country":"US",
    "sg:address":"10880 General Puller Hwy",
    "sg:city":"Hartfield",
    "sg:classifiers":[
        {
            "category":"Insurance",
            "subcategory":"Insurance Agent",
            "type":"Services"
        }
    ],
    "sg:phone":"+1 804 776 8774",
    "sg:postcode":"23071",
    "sg:province":"VA",
    "wof:name":"AFLAC",
    "wof:placetype":"venue"
},
  "geometry": {"coordinates":[-76.448567,37.552878],"type":"Point"}
}