{
  "type": "Feature",
  "properties": {
    "addr:full":"1105 Waters Rd Chesapeake VA 23322",
    "addr:housenumber":"1105",
    "addr:postcode":"23322",
    "addr:street":"Waters Rd",
    "iso:country":"US",
    "sg:address":"1105 Waters Rd",
    "sg:city":"Chesapeake",
    "sg:classifiers":[
        {
            "category":"Building & Trades",
            "subcategory":"Construction",
            "type":"Services"
        }
    ],
    "sg:phone":"+1 757 547 4320",
    "sg:postcode":"23322",
    "sg:province":"VA",
    "sg:tags":[
        "hanging",
        "contractor"
    ],
    "wof:name":"C A Thymides & Associates",
    "wof:placetype":"venue"
},
  "geometry": {"coordinates":[-76.255619,36.691703],"type":"Point"}
}