{
  "type": "Feature",
  "properties": {
    "iso:country":"US",
    "sg:address":"3829 Catawba Rd",
    "sg:city":"Blacksburg",
    "sg:classifiers":[
        {
            "category":"Manufacturing",
            "subcategory":"Wood Products",
            "type":"Manufacturing & Wholesale Goods"
        }
    ],
    "sg:phone":"+1 540 951 2323",
    "sg:postcode":"24060",
    "sg:province":"VA",
    "sg:tags":[
        "mfg"
    ],
    "wof:name":"Just Woodstuff",
    "wof:placetype":"venue"
},
  "geometry": {"coordinates":[-80.27527600000001,37.300161],"type":"Point"}
}