{
  "type": "Feature",
  "properties": {
    "addr:full":"908 S Fork Rd Marion VA 24354",
    "addr:housenumber":"908",
    "addr:postcode":"24354",
    "addr:street":"S Fork Rd",
    "iso:country":"US",
    "sg:address":"908 S Fork Rd",
    "sg:city":"Marion",
    "sg:classifiers":[
        {
            "category":"Autos & Motor Vehicles",
            "subcategory":"Automobile Sales",
            "type":"Retail Goods"
        }
    ],
    "sg:phone":"+1 276 783 4529",
    "sg:postcode":"24354",
    "sg:province":"VA",
    "sg:tags":[
        "car",
        "dealer"
    ],
    "wof:name":"River Auto Sales",
    "wof:placetype":"venue"
},
  "geometry": {"coordinates":[-81.56409499999999,36.767984],"type":"Point"}
}