{
  "type": "Feature",
  "properties": {
    "addr:full":"8505 Bucyrus Ct Manassas VA 20110",
    "addr:housenumber":"8505",
    "addr:postcode":"20110",
    "addr:street":"Bucyrus Ct",
    "iso:country":"US",
    "sg:address":"8505 Bucyrus Ct",
    "sg:city":"Manassas",
    "sg:classifiers":[
        {
            "category":"Building & Trades",
            "subcategory":"Construction",
            "type":"Services"
        }
    ],
    "sg:phone":"+1 703 335 9555",
    "sg:postcode":"20110",
    "sg:province":"VA",
    "sg:tags":[
        "painter"
    ],
    "wof:name":"East Coast Painters",
    "wof:placetype":"venue"
},
  "geometry": {"coordinates":[-77.454002,38.762645],"type":"Point"}
}