{
  "type": "Feature",
  "properties": {
    "addr:full":"9204 Birmingham Dr Manassas VA 20111",
    "addr:housenumber":"9204",
    "addr:postcode":"20111",
    "addr:street":"Birmingham Dr",
    "iso:country":"US",
    "sg:address":"9204 Birmingham Dr",
    "sg:city":"Manassas",
    "sg:classifiers":[
        {
            "category":"Professional",
            "type":"Services"
        }
    ],
    "sg:phone":"+1 703 365 0115",
    "sg:postcode":"20111",
    "sg:province":"VA",
    "sg:tags":[
        "establishment"
    ],
    "wof:name":"Birchwood Manassas Assoc",
    "wof:placetype":"venue"
},
  "geometry": {"coordinates":[-77.426388,38.754624],"type":"Point"}
}