{
  "type": "Feature",
  "properties": {
    "iso:country":"US",
    "sg:address":"725 Tanbark Dr",
    "sg:city":"Newport News",
    "sg:classifiers":[
        {
            "category":"Building & Trades",
            "subcategory":"Construction",
            "type":"Services"
        }
    ],
    "sg:phone":"+1 757 595 7319",
    "sg:postcode":"23601",
    "sg:province":"VA",
    "sg:tags":[
        "house"
    ],
    "wof:name":"Sheridan Custom Building Inc",
    "wof:placetype":"venue"
},
  "geometry": {"coordinates":[-76.455997,37.058561],"type":"Point"}
}