{
  "type": "Feature",
  "properties": {
    "addr:full":"2547 Princess Anne Rd Virginia Beach VA 23456",
    "addr:housenumber":"2547",
    "addr:postcode":"23456",
    "addr:street":"Princess Anne Rd",
    "iso:country":"US",
    "sg:address":"2547 Princess Anne Rd",
    "sg:city":"Virginia Beach",
    "sg:classifiers":[
        {
            "category":"Retail",
            "subcategory":"Laundry & Dry Cleaning",
            "type":"Services"
        }
    ],
    "sg:phone":"+1 757 430 4489",
    "sg:postcode":"23456",
    "sg:province":"VA",
    "sg:tags":[
        "cleaners",
        "rug",
        "carpet"
    ],
    "wof:name":"Hampton Roads Carpet Care",
    "wof:placetype":"venue"
},
  "geometry": {"coordinates":[-76.06320599999999,36.757502],"type":"Point"}
}