{
  "type": "Feature",
  "properties": {
    "addr:full":"14742 Moneta Rd Moneta VA 24121",
    "addr:postcode":"14742;24121",
    "addr:street":"Moneta Rd",
    "iso:country":"US",
    "sg:address":"14742 Moneta Rd",
    "sg:city":"Moneta",
    "sg:classifiers":[
        {
            "category":"Home & Garden",
            "subcategory":"Furniture",
            "type":"Retail Goods"
        }
    ],
    "sg:phone":"+1 540 297 2231",
    "sg:postcode":"24121",
    "sg:province":"VA",
    "wof:name":"Cozy Corner Mattress Shop",
    "wof:placetype":"venue"
},
  "geometry": {"coordinates":[-79.63694599999999,37.165182],"type":"Point"}
}