{
  "type": "Feature",
  "properties": {
    "iso:country":"US",
    "sg:address":"3300 W Cary St",
    "sg:city":"Richmond",
    "sg:classifiers":[
        {
            "category":"Professional",
            "subcategory":"Business Services",
            "type":"Services"
        },
        {
            "category":"Government",
            "subcategory":"Post Office",
            "type":"Public Place"
        }
    ],
    "sg:phone":"+1 804 358 2901",
    "sg:postcode":"23221",
    "sg:province":"VA",
    "sg:tags":[
        "delivery",
        "notary",
        "messenger",
        "courier"
    ],
    "wof:name":"Mail Services & Such",
    "wof:placetype":"venue"
},
  "geometry": {"coordinates":[-77.48384900000001,37.554298],"type":"Point"}
}