{
  "type": "Feature",
  "properties": {
    "addr:full":"913 Virginia Beach Blvd Virginia Beach VA 23451",
    "addr:housenumber":"913",
    "addr:postcode":"23451",
    "addr:street":"Virginia Beach Blvd",
    "iso:country":"US",
    "sg:address":"913 Virginia Beach Blvd",
    "sg:city":"Virginia Beach",
    "sg:classifiers":[
        {
            "category":"Travel",
            "subcategory":"Hotels & Motels",
            "type":"Entertainment"
        }
    ],
    "sg:phone":"+1 757 428 6302",
    "sg:postcode":"23451",
    "sg:province":"VA",
    "wof:name":"Colony Motel & Mobile Home Pk",
    "wof:placetype":"venue"
},
  "geometry": {"coordinates":[-75.98835099999999,36.842889],"type":"Point"}
}