{
  "type": "Feature",
  "properties": {
    "iso:country":"US",
    "sg:address":"2626 Shepherds Mill Rd",
    "sg:city":"Berryville",
    "sg:classifiers":[
        {
            "category":"Shopping",
            "type":"Retail Goods"
        }
    ],
    "sg:phone":"+1 540 955 9690",
    "sg:postcode":"22611",
    "sg:province":"VA",
    "sg:tags":[
        "merchandise",
        "animal"
    ],
    "wof:name":"Midas Touch Golden Retrievers",
    "wof:placetype":"venue"
},
  "geometry": {"coordinates":[-77.92071300000001,39.16008],"type":"Point"}
}