{
  "type": "Feature",
  "properties": {
    "iso:country":"US",
    "sg:address":"6102 Talavera Ct",
    "sg:city":"Alexandria",
    "sg:classifiers":[
        {
            "category":"Sports & Exercise",
            "subcategory":"Gym",
            "type":"Entertainment"
        }
    ],
    "sg:phone":"+1 703 971 0879",
    "sg:postcode":"22310",
    "sg:province":"VA",
    "sg:tags":[
        "fitness",
        "physical",
        "facility"
    ],
    "wof:name":"Gap Fitness Videos LLC",
    "wof:placetype":"venue"
},
  "geometry": {"coordinates":[-77.13333900000001,38.785434],"type":"Point"}
}