{
  "type": "Feature",
  "properties": {
    "iso:country":"US",
    "sg:address":"80 E Windsor Blvd",
    "sg:city":"Windsor",
    "sg:classifiers":[
        {
            "category":"Government",
            "subcategory":"Fire Station",
            "type":"Public Place"
        }
    ],
    "sg:phone":"+1 757 242 3191",
    "sg:postcode":"23487",
    "sg:province":"VA",
    "sg:tags":[
        "protection"
    ],
    "wof:name":"Windsor Volunteer Fire Dept",
    "wof:placetype":"venue"
},
  "geometry": {"coordinates":[-76.732038,36.805167],"type":"Point"}
}