{
  "type": "Feature",
  "properties": {
    "addr:full":"11306 Pendleton Pl Richmond VA 23236",
    "addr:housenumber":"11306",
    "addr:postcode":"23236",
    "addr:street":"Pendleton Pl",
    "iso:country":"US",
    "sg:address":"11306 Pendleton Pl",
    "sg:city":"Richmond",
    "sg:classifiers":[
        {
            "category":"Organizations",
            "subcategory":"Religious Organization",
            "type":"Services"
        }
    ],
    "sg:phone":"+1 804 794 4928",
    "sg:postcode":"23236",
    "sg:province":"VA",
    "wof:name":"C K Stratton",
    "wof:placetype":"venue"
},
  "geometry": {"coordinates":[-77.606471,37.478974],"type":"Point"}
}