{
  "type": "Feature",
  "properties": {
    "addr:full":"566 Butylo Rd Laneview VA 22504",
    "addr:housenumber":"566",
    "addr:postcode":"22504",
    "addr:street":"Butylo Rd",
    "iso:country":"US",
    "sg:address":"566 Butylo Rd",
    "sg:city":"Laneview",
    "sg:classifiers":[
        {
            "category":"Autos & Motor Vehicles",
            "subcategory":"Auto Supplies",
            "type":"Retail Goods"
        }
    ],
    "sg:phone":"+1 804 443 2455",
    "sg:postcode":"22504",
    "sg:province":"VA",
    "wof:name":"Jimmys Auto Parts",
    "wof:placetype":"venue"
},
  "geometry": {"coordinates":[-76.720547,37.759653],"type":"Point"}
}