{
  "type": "Feature",
  "properties": {
    "addr:full":"950 Edwards Ferry Rd NE Leesburg VA 20176",
    "addr:housenumber":"950",
    "addr:postcode":"20176",
    "addr:street":"Edwards Ferry Rd Ne",
    "iso:country":"US",
    "sg:address":"950 Edwards Ferry Rd NE",
    "sg:city":"Leesburg",
    "sg:classifiers":[
        {
            "category":"Shopping",
            "subcategory":"Optical Goods",
            "type":"Retail Goods"
        }
    ],
    "sg:phone":"+1 703 779 0186",
    "sg:postcode":"20176",
    "sg:province":"VA",
    "wof:name":"National Vision",
    "wof:placetype":"venue"
},
  "geometry": {"coordinates":[-77.540673,39.113725],"type":"Point"}
}