{
  "type": "Feature",
  "properties": {
    "addr:full":"2015 Reservoir St Harrisonburg VA 22801",
    "addr:housenumber":"2015",
    "addr:postcode":"22801",
    "addr:street":"Reservoir St",
    "iso:country":"US",
    "sg:address":"2015 Reservoir St",
    "sg:city":"Harrisonburg",
    "sg:classifiers":[
        {
            "category":"Health Services",
            "subcategory":"Doctor",
            "type":"Services"
        }
    ],
    "sg:phone":"+1 540 434 2102",
    "sg:postcode":"22801",
    "sg:province":"VA",
    "sg:tags":[
        "dentist"
    ],
    "wof:name":"Brown & Sutt Pllc",
    "wof:placetype":"venue"
},
  "geometry": {"coordinates":[-78.855329,38.424473],"type":"Point"}
}