{
  "type": "Feature",
  "properties": {
    "addr:full":"7038 Mechanicsville Tpke Mechanicsville VA 23111",
    "addr:housenumber":"7038",
    "addr:postcode":"23111",
    "addr:street":"Mechanicsville Tpke",
    "iso:country":"US",
    "sg:address":"7038 Mechanicsville Tpke",
    "sg:city":"Mechanicsville",
    "sg:classifiers":[
        {
            "category":"Personal",
            "subcategory":"Beauty Salon",
            "type":"Services"
        }
    ],
    "sg:phone":"+1 804 427 2887",
    "sg:postcode":"23111",
    "sg:province":"VA",
    "sg:tags":[
        "shop"
    ],
    "wof:name":"Adventure Cuts Inc",
    "wof:placetype":"venue"
},
  "geometry": {"coordinates":[-77.338072,37.61226],"type":"Point"}
}