{
  "type": "Feature",
  "properties": {
    "addr:full":"1333 Poindexter St Chesapeake VA 23324",
    "addr:housenumber":"1333",
    "addr:postcode":"23324",
    "addr:street":"Poindexter St",
    "iso:country":"US",
    "sg:address":"1333 Poindexter St",
    "sg:city":"Chesapeake",
    "sg:classifiers":[
        {
            "category":"Professional",
            "subcategory":"Accounting & Tax Preparation",
            "type":"Services"
        }
    ],
    "sg:phone":"+1 757 543 7555",
    "sg:postcode":"23324",
    "sg:province":"VA",
    "sg:tags":[
        "return",
        "filing"
    ],
    "wof:name":"Liberty Income Tax",
    "wof:placetype":"venue"
},
  "geometry": {"coordinates":[-76.272958,36.818758],"type":"Point"}
}