{
  "type": "Feature",
  "properties": {
    "addr:full":"2160 Salem Industrial Dr Salem VA 24153",
    "addr:housenumber":"2160",
    "addr:postcode":"24153",
    "addr:street":"Salem Industrial Dr",
    "iso:country":"US",
    "sg:address":"2160 Salem Industrial Dr",
    "sg:city":"Salem",
    "sg:classifiers":[
        {
            "category":"Manufacturing",
            "subcategory":"Buildings",
            "type":"Manufacturing & Wholesale Goods"
        },
        {
            "category":"Building & Trades",
            "subcategory":"Construction",
            "type":"Services"
        }
    ],
    "sg:phone":"+1 540 387 0129",
    "sg:postcode":"24153",
    "sg:province":"VA",
    "sg:tags":[
        "industrial",
        "builder",
        "contractor",
        "contractors-commercial",
        "home",
        "masonry",
        "mason"
    ],
    "wof:name":"Carroll Construction",
    "wof:placetype":"venue"
},
  "geometry": {"coordinates":[-80.09764699999999,37.282447],"type":"Point"}
}