{
  "type": "Feature",
  "properties": {
    "iso:country":"US",
    "sg:address":"2250 Cedar Cove Court",
    "sg:city":"Reston",
    "sg:classifiers":[
        {
            "category":"Professional",
            "subcategory":"Computer Services",
            "type":"Services"
        }
    ],
    "sg:phone":"+1 202 556 0737",
    "sg:postcode":"20191",
    "sg:province":"VA",
    "sg:tags":[
        "childrens-artwork",
        "parents",
        "art-sharing"
    ],
    "sg:website":"http://www.refrigeratorartist.com",
    "wof:name":"RefrigeratorArtist.com",
    "wof:placetype":"venue"
},
  "geometry": {"coordinates":[-77.335228,38.930155],"type":"Point"}
}