{
  "type": "Feature",
  "properties": {
    "addr:full":"8781 Mathis Ave Manassas VA 20110",
    "addr:housenumber":"8781",
    "addr:postcode":"20110",
    "addr:street":"Mathis Ave",
    "iso:country":"US",
    "sg:address":"8781 Mathis Ave",
    "sg:city":"Manassas",
    "sg:classifiers":[
        {
            "category":"Freight",
            "type":"Transportation"
        }
    ],
    "sg:phone":"+1 703 392 7007",
    "sg:postcode":"20110",
    "sg:province":"VA",
    "sg:tags":[
        "forwarder"
    ],
    "wof:name":"Superior Logistics MGT Svcs I",
    "wof:placetype":"venue"
},
  "geometry": {"coordinates":[-77.459402,38.764648],"type":"Point"}
}