{
  "type": "Feature",
  "properties": {
    "addr:full":"9103 Quarter Ct Vienna VA 22182",
    "addr:postcode":"9103;22182",
    "addr:street":"Quarter Ct",
    "iso:country":"US",
    "sg:address":"9103 Quarter Ct",
    "sg:city":"Vienna",
    "sg:classifiers":[
        {
            "category":"Food & Beverages",
            "subcategory":"Specialty",
            "type":"Retail Goods"
        }
    ],
    "sg:phone":"+1 703 242 8866",
    "sg:postcode":"22182",
    "sg:province":"VA",
    "wof:name":"Daily Grind Roasters LLC",
    "wof:placetype":"venue"
},
  "geometry": {"coordinates":[-77.261534,38.931439],"type":"Point"}
}