{
  "type": "Feature",
  "properties": {
    "addr:full":"917 S Colorado St Salem VA 24153",
    "addr:housenumber":"917",
    "addr:postcode":"24153",
    "addr:street":"S Colorado St",
    "iso:country":"US",
    "sg:address":"917 S Colorado St",
    "sg:city":"Salem",
    "sg:classifiers":[
        {
            "category":"Insurance",
            "subcategory":"Insurance Agent",
            "type":"Services"
        }
    ],
    "sg:phone":"+1 540 389 7255",
    "sg:postcode":"24153",
    "sg:province":"VA",
    "sg:tags":[
        "agency"
    ],
    "wof:name":"State Farm Insurance",
    "wof:placetype":"venue"
},
  "geometry": {"coordinates":[-80.05293,37.282],"type":"Point"}
}