{
  "type": "Feature",
  "properties": {
    "iso:country":"US",
    "sg:address":"6690 Mooretown Rd",
    "sg:city":"Williamsburg",
    "sg:classifiers":[
        {
            "category":"Restaurant",
            "type":"Food & Drink"
        }
    ],
    "sg:menulink":"http://www.allmenus.com/va/forest-hill-park/116397-quiznos-sub/menu/",
    "sg:phone":"+1 757 259 7849",
    "sg:postcode":"23188",
    "sg:province":"VA",
    "sg:tags":[
        "wrap",
        "american",
        "sandwich"
    ],
    "wof:name":"Quiznos Sub",
    "wof:placetype":"venue"
},
  "geometry": {"coordinates":[-76.73757999999999,37.337691],"type":"Point"}
}