{
  "type": "Feature",
  "properties": {
    "iso:country":"US",
    "sg:address":"8311 Stationhouse Ct",
    "sg:city":"Lorton",
    "sg:classifiers":[
        {
            "category":"Professional",
            "type":"Services"
        }
    ],
    "sg:phone":"+1 703 339 3208",
    "sg:postcode":"22079",
    "sg:province":"VA",
    "wof:name":"Michael Warchol",
    "wof:placetype":"venue"
},
  "geometry": {"coordinates":[-77.180325,38.731839],"type":"Point"}
}