{
  "type": "Feature",
  "properties": {
    "addr:full":"202 Meadowfield Rd Yorktown VA 23692",
    "addr:housenumber":"202",
    "addr:postcode":"23692",
    "addr:street":"Meadowfield Rd",
    "iso:country":"US",
    "sg:address":"202 Meadowfield Rd",
    "sg:city":"Yorktown",
    "sg:classifiers":[
        {
            "category":"Personal",
            "type":"Services"
        }
    ],
    "sg:phone":"+1 757 234 0929",
    "sg:postcode":"23692",
    "sg:province":"VA",
    "wof:name":"Motivational Hypnosis Center",
    "wof:placetype":"venue"
},
  "geometry": {"coordinates":[-76.496183,37.192948],"type":"Point"}
}