{
  "type": "Feature",
  "properties": {
    "iso:country":"US",
    "sg:address":"14620 Tranor Ave",
    "sg:city":"Chester",
    "sg:classifiers":[
        {
            "category":"Professional",
            "subcategory":"Research",
            "type":"Services"
        }
    ],
    "sg:phone":"+1 804 530 1490",
    "sg:postcode":"23836",
    "sg:province":"VA",
    "sg:tags":[
        "development",
        "marketing",
        "product"
    ],
    "wof:name":"H P Products Co",
    "wof:placetype":"venue"
},
  "geometry": {"coordinates":[-77.330495,37.325525],"type":"Point"}
}