{
  "type": "Feature",
  "properties": {
    "addr:full":"627 Independence Blvd Virginia Beach VA 23462",
    "addr:housenumber":"627",
    "addr:postcode":"23462",
    "addr:street":"Independence Blvd",
    "iso:country":"US",
    "sg:address":"627 Independence Blvd",
    "sg:city":"Virginia Beach",
    "sg:classifiers":[
        {
            "category":"Restaurant",
            "type":"Food & Drink"
        }
    ],
    "sg:menulink":"http://www.allmenus.com/va/virginia-beach/162985-rallys/menu/",
    "sg:phone":"+1 757 490 8601",
    "sg:postcode":"23462",
    "sg:province":"VA",
    "sg:tags":[
        "sandwich",
        "dog",
        "burger",
        "hot",
        "wrap",
        "american"
    ],
    "wof:name":"Rally's",
    "wof:placetype":"venue"
},
  "geometry": {"coordinates":[-76.13549500000001,36.855108],"type":"Point"}
}