{
  "type": "Feature",
  "properties": {
    "addr:full":"11600 Busy St Richmond VA 23236",
    "addr:postcode":"11600;23236",
    "addr:street":"Busy St",
    "iso:country":"US",
    "sg:address":"11600 Busy St",
    "sg:city":"Richmond",
    "sg:classifiers":[
        {
            "category":"Professional",
            "type":"Services"
        }
    ],
    "sg:phone":"+1 804 794 7831",
    "sg:postcode":"23236",
    "sg:province":"VA",
    "sg:tags":[
        "establishment"
    ],
    "wof:name":"Advanced Surface Technologies",
    "wof:placetype":"venue"
},
  "geometry": {"coordinates":[-77.613545,37.502145],"type":"Point"}
}