{
  "type": "Feature",
  "properties": {
    "iso:country":"US",
    "sg:address":"301 4th St",
    "sg:city":"Waynesboro",
    "sg:classifiers":[
        {
            "category":"Manufacturing",
            "subcategory":"Rubber & Plastics",
            "type":"Manufacturing & Wholesale Goods"
        }
    ],
    "sg:phone":"+1 540 949 8351",
    "sg:postcode":"22980",
    "sg:province":"VA",
    "sg:website":"www.klannorgan.com",
    "wof:name":"Klann Inc",
    "wof:placetype":"venue"
},
  "geometry": {"coordinates":[-78.87769,38.075379],"type":"Point"}
}