{
  "type": "Feature",
  "properties": {
    "addr:full":"1924 Plantation Rd NE Roanoke VA 24012",
    "addr:housenumber":"1924",
    "addr:postcode":"24012",
    "addr:street":"Plantation Rd Ne",
    "iso:country":"US",
    "sg:address":"1924 Plantation Rd NE",
    "sg:city":"Roanoke",
    "sg:classifiers":[
        {
            "category":"Freight",
            "type":"Transportation"
        }
    ],
    "sg:phone":"+1 540 345 1062",
    "sg:postcode":"24012",
    "sg:province":"VA",
    "sg:tags":[
        "trucking"
    ],
    "wof:name":"J & M Intermodal Inc",
    "wof:placetype":"venue"
},
  "geometry": {"coordinates":[-79.92886300000001,37.291418],"type":"Point"}
}