{
  "type": "Feature",
  "properties": {
    "addr:full":"117 Norfolk Ave SW Roanoke VA 24011",
    "addr:housenumber":"117",
    "addr:postcode":"24011",
    "addr:street":"Norfolk Ave Sw",
    "iso:country":"US",
    "sg:address":"117 Norfolk Ave SW",
    "sg:city":"Roanoke",
    "sg:classifiers":[
        {
            "category":"Professional",
            "subcategory":"Computer Services",
            "type":"Services"
        }
    ],
    "sg:phone":"+1 540 344 5211",
    "sg:postcode":"24011",
    "sg:province":"VA",
    "sg:tags":[
        "prepackaged",
        "software"
    ],
    "wof:name":"Rustys Best Corporation",
    "wof:placetype":"venue"
},
  "geometry": {"coordinates":[-79.944152,37.27304],"type":"Point"}
}