{
  "type": "Feature",
  "properties": {
    "iso:country":"US",
    "sg:address":"2524 Langhorne Rd",
    "sg:city":"Lynchburg",
    "sg:classifiers":[
        {
            "category":"Professional",
            "subcategory":"Engineering",
            "type":"Services"
        }
    ],
    "sg:phone":"+1 434 847 7796",
    "sg:postcode":"24501",
    "sg:province":"VA",
    "sg:tags":[
        "surveyor",
        "consulting",
        "land",
        "engineer"
    ],
    "sg:website":"www.handp.com",
    "wof:name":"Hurt & Proffitt Inc",
    "wof:placetype":"venue"
},
  "geometry": {"coordinates":[-79.16568599999999,37.409236],"type":"Point"}
}