{
  "type": "Feature",
  "properties": {
    "addr:full":"114 Three Cedars Ln Fredericksburg VA 22407",
    "addr:housenumber":"114",
    "addr:postcode":"22407",
    "addr:street":"Three Cedars Ln",
    "iso:country":"US",
    "sg:address":"114 Three Cedars Ln",
    "sg:city":"Fredericksburg",
    "sg:classifiers":[
        {
            "category":"Organizations",
            "subcategory":"Religious Organization",
            "type":"Services"
        }
    ],
    "sg:phone":"+1 540 898 0378",
    "sg:postcode":"22407",
    "sg:province":"VA",
    "wof:name":"Raymond L Silver Rev",
    "wof:placetype":"venue"
},
  "geometry": {"coordinates":[-77.53012200000001,38.229551],"type":"Point"}
}