{
  "type": "Feature",
  "properties": {
    "iso:country":"US",
    "sg:address":"8460 Circle Dr",
    "sg:city":"Hayes",
    "sg:classifiers":[
        {
            "category":"Building & Trades",
            "subcategory":"Cleaning & Sanitation",
            "type":"Services"
        }
    ],
    "sg:phone":"+1 804 642 0051",
    "sg:postcode":"23072",
    "sg:province":"VA",
    "sg:tags":[
        "construction"
    ],
    "wof:name":"Carpenter Construction & Svcs",
    "wof:placetype":"venue"
},
  "geometry": {"coordinates":[-76.473564,37.26481],"type":"Point"}
}