{
  "type": "Feature",
  "properties": {
    "iso:country":"US",
    "sg:address":"1149 Seminole Trl",
    "sg:city":"Charlottesville",
    "sg:classifiers":[
        {
            "category":"Health Services",
            "subcategory":"Doctor",
            "type":"Services"
        }
    ],
    "sg:phone":"+1 434 978 3998",
    "sg:postcode":"22901",
    "sg:province":"VA",
    "wof:name":"Munson Amie R MD",
    "wof:placetype":"venue"
},
  "geometry": {"coordinates":[-78.484703,38.069801],"type":"Point"}
}