{
  "type": "Feature",
  "properties": {
    "addr:full":"50 Maple Ave Newport News VA 23607",
    "addr:housenumber":"50",
    "addr:postcode":"23607",
    "addr:street":"Maple Ave",
    "iso:country":"US",
    "sg:address":"50 Maple Ave",
    "sg:city":"Newport News",
    "sg:classifiers":[
        {
            "category":"Social Services",
            "subcategory":"Child Care",
            "type":"Services"
        }
    ],
    "sg:phone":"+1 757 245 1781",
    "sg:postcode":"23607",
    "sg:province":"VA",
    "sg:tags":[
        "day"
    ],
    "wof:name":"Ivy Baptist Child Care Center",
    "wof:placetype":"venue"
},
  "geometry": {"coordinates":[-76.392636,36.989737],"type":"Point"}
}