{
  "type": "Feature",
  "properties": {
    "addr:full":"8086 Alban Rd Springfield VA 22150",
    "addr:housenumber":"8086",
    "addr:postcode":"22150",
    "addr:street":"Alban Rd",
    "iso:country":"US",
    "sg:address":"8086 Alban Rd",
    "sg:city":"Springfield",
    "sg:classifiers":[
        {
            "category":"Retail",
            "subcategory":"Repair Shop",
            "type":"Services"
        }
    ],
    "sg:phone":"+1 703 842 4985",
    "sg:postcode":"22150",
    "sg:province":"VA",
    "sg:tags":[
        "lock",
        "locksmith"
    ],
    "wof:name":"24 Hour Locksmith",
    "wof:placetype":"venue"
},
  "geometry": {"coordinates":[-77.19479800000001,38.73577],"type":"Point"}
}