{
  "type": "Feature",
  "properties": {
    "iso:country":"US",
    "sg:address":"476 James Madison Hwy",
    "sg:city":"Culpeper",
    "sg:classifiers":[
        {
            "category":"Professional",
            "subcategory":"Art Services",
            "type":"Services"
        }
    ],
    "sg:phone":"+1 540 727 9422",
    "sg:postcode":"22701",
    "sg:province":"VA",
    "sg:tags":[
        "commercial",
        "design"
    ],
    "wof:name":"Performance Press & Graphics",
    "wof:placetype":"venue"
},
  "geometry": {"coordinates":[-77.987511,38.481036],"type":"Point"}
}