{
  "type": "Feature",
  "properties": {
    "iso:country":"US",
    "sg:address":"11 W 2nd St",
    "sg:city":"Front Royal",
    "sg:classifiers":[
        {
            "category":"Health Services",
            "subcategory":"Nursing And Care Facility",
            "type":"Services"
        }
    ],
    "sg:phone":"+1 540 635 5024",
    "sg:postcode":"22630",
    "sg:province":"VA",
    "sg:tags":[
        "skilled"
    ],
    "wof:name":"Blue Ridge Hospice",
    "wof:placetype":"venue"
},
  "geometry": {"coordinates":[-78.19386799999999,38.921089],"type":"Point"}
}