{
  "type": "Feature",
  "properties": {
    "iso:country":"US",
    "sg:address":"9041 Backlick Rd",
    "sg:city":"Fort Belvoir",
    "sg:classifiers":[
        {
            "category":"Organizations",
            "subcategory":"Religious Organization",
            "type":"Services"
        }
    ],
    "sg:phone":"+1 703 922 7168",
    "sg:postcode":"22060",
    "sg:province":"VA",
    "wof:name":"Accotink United Methdst Church",
    "wof:placetype":"venue"
},
  "geometry": {"coordinates":[-77.163788,38.712679],"type":"Point"}
}