{
  "type": "Feature",
  "properties": {
    "addr:full":"43145 Broadlands Center Plz Ashburn VA 20148",
    "addr:postcode":"43145;20148",
    "addr:street":"Center Plz",
    "iso:country":"US",
    "sg:address":"43145 Broadlands Center Plz",
    "sg:city":"Ashburn",
    "sg:classifiers":[
        {
            "category":"Shopping",
            "subcategory":"Jewelry",
            "type":"Retail Goods"
        }
    ],
    "sg:phone":"+1 703 723 3623",
    "sg:postcode":"20148",
    "sg:province":"VA",
    "sg:tags":[
        "jeweler"
    ],
    "wof:name":"Opus Jewelry",
    "wof:placetype":"venue"
},
  "geometry": {"coordinates":[-77.508546,39.026396],"type":"Point"}
}