{
  "type": "Feature",
  "properties": {
    "iso:country":"US",
    "sg:address":"620 Montebello Cir",
    "sg:city":"Chesapeake",
    "sg:classifiers":[
        {
            "category":"Shopping",
            "subcategory":"Used Merchandise",
            "type":"Retail Goods"
        }
    ],
    "sg:phone":"+1 757 436 6815",
    "sg:postcode":"23322",
    "sg:province":"VA",
    "wof:name":"Antiques & Accents",
    "wof:placetype":"venue"
},
  "geometry": {"coordinates":[-76.263099,36.707163],"type":"Point"}
}