{
  "type": "Feature",
  "properties": {
    "addr:full":"217 W Main St Radford VA 24141",
    "addr:housenumber":"217",
    "addr:postcode":"24141",
    "addr:street":"W Main St",
    "iso:country":"US",
    "sg:address":"217 W Main St",
    "sg:city":"Radford",
    "sg:classifiers":[
        {
            "category":"Personal",
            "subcategory":"Beauty Salon",
            "type":"Services"
        }
    ],
    "sg:phone":"+1 540 639 4330",
    "sg:postcode":"24141",
    "sg:province":"VA",
    "sg:tags":[
        "shop"
    ],
    "wof:name":"Central Styling Barbr Buty Sp",
    "wof:placetype":"venue"
},
  "geometry": {"coordinates":[-80.573891,37.134912],"type":"Point"}
}