{
  "type": "Feature",
  "properties": {
    "iso:country":"US",
    "sg:address":"1408 Martha Custis Dr",
    "sg:city":"Alexandria",
    "sg:classifiers":[
        {
            "category":"Professional",
            "subcategory":"Management & Consulting",
            "type":"Services"
        },
        {
            "category":"Professional",
            "subcategory":"Business Services",
            "type":"Services"
        }
    ],
    "sg:phone":"+1 703 820 1270",
    "sg:postcode":"22302",
    "sg:province":"VA",
    "sg:tags":[
        "relation",
        "counselor",
        "publicity",
        "public"
    ],
    "sg:website":"http://www.rothenberg.com",
    "wof:name":"Rothenberg Communications",
    "wof:placetype":"venue"
},
  "geometry": {"coordinates":[-77.082778,38.841076],"type":"Point"}
}