{
  "type": "Feature",
  "properties": {
    "iso:country":"US",
    "sg:address":"681 Battlefield Blvd S",
    "sg:city":"Chesapeake",
    "sg:classifiers":[
        {
            "category":"Personal",
            "subcategory":"Beauty Salon",
            "type":"Services"
        }
    ],
    "sg:phone":"+1 757 472 0296",
    "sg:postcode":"23322",
    "sg:province":"VA",
    "sg:tags":[
        "shop"
    ],
    "wof:name":"Nails By Trang",
    "wof:placetype":"venue"
},
  "geometry": {"coordinates":[-76.23495,36.702917],"type":"Point"}
}