{
  "type": "Feature",
  "properties": {
    "addr:full":"2463 Chopping Rd Mineral VA 23117",
    "addr:housenumber":"2463",
    "addr:postcode":"23117",
    "addr:street":"Chopping Rd",
    "iso:country":"US",
    "sg:address":"2463 Chopping Rd",
    "sg:city":"Mineral",
    "sg:classifiers":[
        {
            "category":"Organizations",
            "subcategory":"Membership Organization",
            "type":"Services"
        }
    ],
    "sg:phone":"+1 540 894 4830",
    "sg:postcode":"23117",
    "sg:province":"VA",
    "wof:name":"Free & Accepted Masons In",
    "wof:placetype":"venue"
},
  "geometry": {"coordinates":[-77.909307,38.052163],"type":"Point"}
}