{
  "type": "Feature",
  "properties": {
    "addr:full":"4105 Fort Worth Pl Alexandria VA 22304",
    "addr:housenumber":"4105",
    "addr:postcode":"22304",
    "addr:street":"Fort;Pl",
    "iso:country":"US",
    "sg:address":"4105 Fort Worth Pl",
    "sg:city":"Alexandria",
    "sg:classifiers":[
        {
            "category":"Building & Trades",
            "subcategory":"Construction",
            "type":"Services"
        }
    ],
    "sg:phone":"+1 703 370 8738",
    "sg:postcode":"22304",
    "sg:province":"VA",
    "sg:tags":[
        "house"
    ],
    "wof:name":"Good News Home Improvements",
    "wof:placetype":"venue"
},
  "geometry": {"coordinates":[-77.096847,38.816415],"type":"Point"}
}