{
  "type": "Feature",
  "properties": {
    "iso:country":"US",
    "sg:address":"3108 W Marshall St",
    "sg:city":"Richmond",
    "sg:classifiers":[
        {
            "category":"Building & Trades",
            "subcategory":"Construction",
            "type":"Services"
        }
    ],
    "sg:phone":"+1 804 359 7477",
    "sg:postcode":"23230",
    "sg:province":"VA",
    "sg:tags":[
        "maker",
        "cabinet"
    ],
    "wof:name":"Trademark Woodworking",
    "wof:placetype":"venue"
},
  "geometry": {"coordinates":[-77.473705,37.566686],"type":"Point"}
}