{
  "type": "Feature",
  "properties": {
    "addr:full":"2002 Mercer Ave NW Roanoke VA 24017",
    "addr:housenumber":"2002",
    "addr:postcode":"24017",
    "addr:street":"Mercer Ave Nw",
    "iso:country":"US",
    "sg:address":"2002 Mercer Ave NW",
    "sg:city":"Roanoke",
    "sg:classifiers":[
        {
            "category":"Organizations",
            "subcategory":"Religious Organization",
            "type":"Services"
        }
    ],
    "sg:phone":"+1 540 345 6676",
    "sg:postcode":"24017",
    "sg:province":"VA",
    "sg:website":"www.klminternational.org",
    "wof:name":"Kingdom Life Ministries",
    "wof:placetype":"venue"
},
  "geometry": {"coordinates":[-79.969762,37.289012],"type":"Point"}
}