{
  "type": "Feature",
  "properties": {
    "addr:full":"256 Industrial Dr Roanoke VA 24019",
    "addr:housenumber":"256",
    "addr:postcode":"24019",
    "addr:street":"Industrial Dr",
    "iso:country":"US",
    "sg:address":"256 Industrial Dr",
    "sg:city":"Roanoke",
    "sg:classifiers":[
        {
            "category":"Retail",
            "subcategory":"Repair Shop",
            "type":"Services"
        }
    ],
    "sg:phone":"+1 540 992 2122",
    "sg:postcode":"24019",
    "sg:province":"VA",
    "sg:tags":[
        "equipment",
        "hydraulic"
    ],
    "wof:name":"Precision Hydraulics Co Inc",
    "wof:placetype":"venue"
},
  "geometry": {"coordinates":[-79.92259799999999,37.355111],"type":"Point"}
}