{
  "type": "Feature",
  "properties": {
    "addr:full":"2241 Tacketts Mill Dr Woodbridge VA 22192",
    "addr:housenumber":"2241",
    "addr:postcode":"22192",
    "addr:street":"Tacketts Mill Dr",
    "iso:country":"US",
    "sg:address":"2241 Tacketts Mill Dr",
    "sg:city":"Woodbridge",
    "sg:classifiers":[
        {
            "category":"Building & Trades",
            "subcategory":"Construction",
            "type":"Services"
        }
    ],
    "sg:phone":"+1 703 490 3393",
    "sg:postcode":"22192",
    "sg:province":"VA",
    "sg:tags":[
        "home",
        "improvement"
    ],
    "wof:name":"By Design Home Improvement Inc",
    "wof:placetype":"venue"
},
  "geometry": {"coordinates":[-77.27768,38.675577],"type":"Point"}
}