{
  "type": "Feature",
  "properties": {
    "addr:full":"10232 Orby Cantrell Hwy Pound VA 24279",
    "addr:housenumber":"10232",
    "addr:postcode":"24279",
    "addr:street":"Orby Cantrell Hwy",
    "iso:country":"US",
    "sg:address":"10232 Orby Cantrell Hwy",
    "sg:city":"Pound",
    "sg:classifiers":[
        {
            "category":"Travel",
            "subcategory":"Hotels & Motels",
            "type":"Entertainment"
        }
    ],
    "sg:phone":"+1 276 796 5428",
    "sg:postcode":"24279",
    "sg:province":"VA",
    "wof:name":"Travelers Motel",
    "wof:placetype":"venue"
},
  "geometry": {"coordinates":[-82.59983200000001,37.095249],"type":"Point"}
}