{
  "type": "Feature",
  "properties": {
    "addr:full":"7158 Deacon Rd Gloucester VA 23061",
    "addr:housenumber":"7158",
    "addr:postcode":"23061",
    "addr:street":"Deacon Rd",
    "iso:country":"US",
    "sg:address":"7158 Deacon Rd",
    "sg:city":"Gloucester",
    "sg:classifiers":[
        {
            "category":"Organizations",
            "subcategory":"Membership Organization",
            "type":"Services"
        }
    ],
    "sg:phone":"+1 804 694 4855",
    "sg:postcode":"23061",
    "sg:province":"VA",
    "wof:name":"Youth Crisis Netwrk Pickup Svc",
    "wof:placetype":"venue"
},
  "geometry": {"coordinates":[-76.505256,37.408536],"type":"Point"}
}