{
  "type": "Feature",
  "properties": {
    "addr:full":"8025 Mims St Lorton VA 22079",
    "addr:housenumber":"8025",
    "addr:postcode":"22079",
    "addr:street":"Mims St",
    "iso:country":"US",
    "sg:address":"8025 Mims St",
    "sg:city":"Lorton",
    "sg:classifiers":[
        {
            "category":"Local Transit",
            "type":"Transportation"
        }
    ],
    "sg:phone":"+1 703 339 0131",
    "sg:postcode":"22079",
    "sg:province":"VA",
    "sg:tags":[
        "bus",
        "line"
    ],
    "wof:name":"Atlantic Coach Inc",
    "wof:placetype":"venue"
},
  "geometry": {"coordinates":[-77.22063799999999,38.689427],"type":"Point"}
}