{
  "type": "Feature",
  "properties": {
    "addr:full":"12146 Jefferson Ave Newport News VA 23602",
    "addr:housenumber":"12146",
    "addr:postcode":"23602",
    "addr:street":"Jefferson Ave",
    "iso:country":"US",
    "sg:address":"12146 Jefferson Ave",
    "sg:city":"Newport News",
    "sg:classifiers":[
        {
            "category":"Shopping",
            "subcategory":"Clothing, Apparel, & Fashions",
            "type":"Retail Goods"
        }
    ],
    "sg:phone":"+1 757 269 0280",
    "sg:postcode":"23602",
    "sg:province":"VA",
    "sg:tags":[
        "furnishing"
    ],
    "wof:name":"Men's Wearhouse",
    "wof:placetype":"venue"
},
  "geometry": {"coordinates":[-76.49108699999999,37.100466],"type":"Point"}
}