{
  "type": "Feature",
  "properties": {
    "iso:country":"US",
    "sg:address":"2601 Princess Anne St",
    "sg:city":"Fredericksburg",
    "sg:classifiers":[
        {
            "category":"Government",
            "subcategory":"Office",
            "type":"Public Place"
        }
    ],
    "sg:phone":"+1 540 899 4463",
    "sg:postcode":"22401",
    "sg:province":"VA",
    "sg:tags":[
        "state"
    ],
    "wof:name":"Soil & Water Conservation",
    "wof:placetype":"venue"
},
  "geometry": {"coordinates":[-77.471328,38.316812],"type":"Point"}
}