{
  "type": "Feature",
  "properties": {
    "iso:country":"US",
    "sg:address":"18029 Hilliard Ln",
    "sg:city":"King George",
    "sg:classifiers":[
        {
            "category":"Real Estate",
            "subcategory":"Real Estate Agent",
            "type":"Services"
        }
    ],
    "sg:phone":"+1 540 663 0066",
    "sg:postcode":"22485",
    "sg:province":"VA",
    "wof:name":"Evolving Realty LLC",
    "wof:placetype":"venue"
},
  "geometry": {"coordinates":[-77.035042,38.393018],"type":"Point"}
}