{
  "type": "Feature",
  "properties": {
    "iso:country":"US",
    "sg:address":"209 N 3rd St",
    "sg:city":"Richmond",
    "sg:classifiers":[
        {
            "category":"Restaurant",
            "type":"Food & Drink"
        }
    ],
    "sg:phone":"+1 804 643 0540",
    "sg:postcode":"23219",
    "sg:province":"VA",
    "wof:name":"3rd Street Market & Deli",
    "wof:placetype":"venue"
},
  "geometry": {"coordinates":[-77.44001,37.543232],"type":"Point"}
}