{
  "type": "Feature",
  "properties": {
    "iso:country":"US",
    "sg:address":"178 Flat Ridge Rd",
    "sg:city":"Sugar Grove",
    "sg:classifiers":[
        {
            "category":"Government",
            "subcategory":"Fire Station",
            "type":"Public Place"
        }
    ],
    "sg:phone":"+1 276 677 3100",
    "sg:postcode":"24375",
    "sg:province":"VA",
    "sg:tags":[
        "department"
    ],
    "wof:name":"Sugar Grove Volunteer Fire Dep",
    "wof:placetype":"venue"
},
  "geometry": {"coordinates":[-81.410509,36.774042],"type":"Point"}
}