{
  "type": "Feature",
  "properties": {
    "addr:full":"810 Caroline St Fredericksburg VA 22401",
    "addr:housenumber":"810",
    "addr:postcode":"22401",
    "addr:street":"Caroline St",
    "iso:country":"US",
    "sg:address":"810 Caroline St",
    "sg:city":"Fredericksburg",
    "sg:classifiers":[
        {
            "category":"Shopping",
            "subcategory":"Clothing, Apparel, & Fashions",
            "type":"Retail Goods"
        }
    ],
    "sg:phone":"+1 540 373 3428",
    "sg:postcode":"22401",
    "sg:province":"VA",
    "sg:tags":[
        "item",
        "boutique"
    ],
    "wof:name":"Red Hatters' Boutique",
    "wof:placetype":"venue"
},
  "geometry": {"coordinates":[-77.458808,38.302257],"type":"Point"}
}