{
  "type": "Feature",
  "properties": {
    "addr:full":"8811 Sudley Rd Manassas VA 20110",
    "addr:housenumber":"8811",
    "addr:postcode":"20110",
    "addr:street":"Sudley Rd",
    "iso:country":"US",
    "sg:address":"8811 Sudley Rd",
    "sg:city":"Manassas",
    "sg:classifiers":[
        {
            "category":"Professional",
            "subcategory":"Business Services",
            "type":"Services"
        }
    ],
    "sg:phone":"+1 703 365 7575",
    "sg:postcode":"20110",
    "sg:province":"VA",
    "wof:name":"Paragon Business Solutions",
    "wof:placetype":"venue"
},
  "geometry": {"coordinates":[-77.48107,38.764958],"type":"Point"}
}