{
  "type": "Feature",
  "properties": {
    "addr:full":"3822 Farrcroft Dr Fairfax VA 22030",
    "addr:housenumber":"3822",
    "addr:postcode":"22030",
    "addr:street":"Farrcroft Dr",
    "iso:country":"US",
    "sg:address":"3822 Farrcroft Dr",
    "sg:city":"Fairfax",
    "sg:classifiers":[
        {
            "category":"Wholesale",
            "subcategory":"Construction Materials",
            "type":"Manufacturing & Wholesale Goods"
        }
    ],
    "sg:phone":"+1 703 383 4816",
    "sg:postcode":"22030",
    "sg:province":"VA",
    "sg:tags":[
        "rep",
        "mfg"
    ],
    "wof:name":"Associated Sales Engineer LLC",
    "wof:placetype":"venue"
},
  "geometry": {"coordinates":[-77.293547,38.848518],"type":"Point"}
}