{
  "type": "Feature",
  "properties": {
    "iso:country":"US",
    "sg:address":"546 E Mercury Blvd",
    "sg:city":"Hampton",
    "sg:classifiers":[
        {
            "category":"Wholesale",
            "subcategory":"Seafood",
            "type":"Manufacturing & Wholesale Goods"
        }
    ],
    "sg:phone":"+1 757 727 0532",
    "sg:postcode":"23663",
    "sg:province":"VA",
    "wof:name":"Roberts Creek Seafood",
    "wof:placetype":"venue"
},
  "geometry": {"coordinates":[-76.320938,37.023394],"type":"Point"}
}