{
  "type": "Feature",
  "properties": {
    "addr:full":"167 Kelley Dr Front Royal VA 22630",
    "addr:housenumber":"167",
    "addr:postcode":"22630",
    "addr:street":"Kelley Dr",
    "iso:country":"US",
    "sg:address":"167 Kelley Dr",
    "sg:city":"Front Royal",
    "sg:classifiers":[
        {
            "category":"Professional",
            "subcategory":"Computer Services",
            "type":"Services"
        }
    ],
    "sg:phone":"+1 540 631 3200",
    "sg:postcode":"22630",
    "sg:province":"VA",
    "sg:tags":[
        "home",
        "consulting",
        "page",
        "dev",
        "internet"
    ],
    "wof:name":"New Breed Corp",
    "wof:placetype":"venue"
},
  "geometry": {"coordinates":[-78.175558,38.976219],"type":"Point"}
}