{
  "type": "Feature",
  "properties": {
    "addr:full":"1015 E Clay St Richmond VA 23219",
    "addr:housenumber":"1015",
    "addr:postcode":"23219",
    "addr:street":"E Clay St",
    "iso:country":"US",
    "sg:address":"1015 E Clay St",
    "sg:city":"Richmond",
    "sg:classifiers":[
        {
            "category":"Education",
            "subcategory":"Library",
            "type":"Public Place"
        }
    ],
    "sg:phone":"+1 804 649 0711",
    "sg:postcode":"23219",
    "sg:province":"VA",
    "sg:tags":[
        "special",
        "interest"
    ],
    "wof:name":"Historic Richmond Tours",
    "wof:placetype":"venue"
},
  "geometry": {"coordinates":[-77.430615,37.541484],"type":"Point"}
}