{
  "type": "Feature",
  "properties": {
    "iso:country":"US",
    "sg:address":"11745 Jefferson Ave",
    "sg:city":"Newport News",
    "sg:classifiers":[
        {
            "category":"Sports & Exercise",
            "subcategory":"Gym",
            "type":"Entertainment"
        }
    ],
    "sg:phone":"+1 757 594 1380",
    "sg:postcode":"23606",
    "sg:province":"VA",
    "sg:tags":[
        "fitness",
        "physical",
        "facility"
    ],
    "wof:name":"Personal Touch Fitness",
    "wof:placetype":"venue"
},
  "geometry": {"coordinates":[-76.48072999999999,37.083185],"type":"Point"}
}