{
  "type": "Feature",
  "properties": {
    "iso:country":"US",
    "sg:address":"12007 Sunrise Valley Dr",
    "sg:city":"Reston",
    "sg:classifiers":[
        {
            "category":"Professional",
            "subcategory":"Computer Services",
            "type":"Services"
        }
    ],
    "sg:phone":"+1 703 262 9400",
    "sg:postcode":"20191",
    "sg:province":"VA",
    "sg:tags":[
        "related"
    ],
    "wof:name":"Interface Consulting Solutions",
    "wof:placetype":"venue"
},
  "geometry": {"coordinates":[-77.360528,38.946509],"type":"Point"}
}