{
  "type": "Feature",
  "properties": {
    "iso:country":"US",
    "sg:address":"1257 Fox Crest Way",
    "sg:city":"Charlottesville",
    "sg:classifiers":[
        {
            "category":"Professional",
            "subcategory":"Business Services",
            "type":"Services"
        }
    ],
    "sg:phone":"+1 434 245 9766",
    "sg:postcode":"22902",
    "sg:province":"VA",
    "wof:name":"Booker Music Productions LLC",
    "wof:placetype":"venue"
},
  "geometry": {"coordinates":[-78.504643,38.003794],"type":"Point"}
}