{
  "type": "Feature",
  "properties": {
    "addr:full":"13540 E Boundary Rd Midlothian VA 23112",
    "addr:housenumber":"13540",
    "addr:postcode":"23112",
    "addr:street":"E Boundary Rd",
    "iso:country":"US",
    "sg:address":"13540 E Boundary Rd",
    "sg:city":"Midlothian",
    "sg:classifiers":[
        {
            "category":"Wholesale",
            "subcategory":"Computers",
            "type":"Manufacturing & Wholesale Goods"
        }
    ],
    "sg:phone":"+1 804 744 1766",
    "sg:postcode":"23112",
    "sg:province":"VA",
    "wof:name":"Synnex Corporation",
    "wof:placetype":"venue"
},
  "geometry": {"coordinates":[-77.646444,37.448046],"type":"Point"}
}