{
  "type": "Feature",
  "properties": {
    "iso:country":"US",
    "sg:address":"1550 Shannon St SE",
    "sg:city":"Roanoke",
    "sg:classifiers":[
        {
            "category":"Wholesale",
            "subcategory":"Furniture",
            "type":"Manufacturing & Wholesale Goods"
        }
    ],
    "sg:phone":"+1 540 427 5093",
    "sg:postcode":"24014",
    "sg:province":"VA",
    "wof:name":"Installation Alternatives",
    "wof:placetype":"venue"
},
  "geometry": {"coordinates":[-79.910123,37.245689],"type":"Point"}
}