{
  "type": "Feature",
  "properties": {
    "addr:full":"5813 Baron Dr Chesterfield VA 23832",
    "addr:housenumber":"5813",
    "addr:postcode":"23832",
    "addr:street":"Baron Dr",
    "iso:country":"US",
    "sg:address":"5813 Baron Dr",
    "sg:city":"Chesterfield",
    "sg:classifiers":[
        {
            "category":"Social Services",
            "subcategory":"Child Care",
            "type":"Services"
        }
    ],
    "sg:phone":"+1 804 275 3847",
    "sg:postcode":"23832",
    "sg:province":"VA",
    "sg:tags":[
        "day"
    ],
    "wof:name":"Mary's Day Care",
    "wof:placetype":"venue"
},
  "geometry": {"coordinates":[-77.53067900000001,37.429294],"type":"Point"}
}