{
  "type": "Feature",
  "properties": {
    "addr:full":"709 Johnston Willis Dr Richmond VA 23236",
    "addr:housenumber":"709",
    "addr:postcode":"23236",
    "addr:street":"Johnston Willis Dr",
    "iso:country":"US",
    "sg:address":"709 Johnston Willis Dr",
    "sg:city":"Richmond",
    "sg:classifiers":[
        {
            "category":"Autos & Motor Vehicles",
            "subcategory":"Auto Supplies",
            "type":"Retail Goods"
        },
        {
            "category":"Retail",
            "subcategory":"Repair Shop",
            "type":"Services"
        },
        {
            "category":"Shopping",
            "subcategory":"Crafts & Fabrics",
            "type":"Retail Goods"
        },
        {
            "category":"Retail",
            "subcategory":"Auto Repair",
            "type":"Services"
        }
    ],
    "sg:phone":"+1 804 794 0795",
    "sg:postcode":"23236",
    "sg:province":"VA",
    "sg:tags":[
        "body",
        "repairing",
        "upholstery",
        "upholsterer",
        "automobile",
        "top",
        "covers",
        "seat",
        "parts",
        "accessories-wholesale",
        "painting",
        "manufacturer"
    ],
    "sg:website":"http://www.vaupholstery.com/",
    "wof:name":"Ray's Upholstery & Glass Shop",
    "wof:placetype":"venue"
},
  "geometry": {"coordinates":[-77.59119,37.501275],"type":"Point"}
}