{
  "type": "Feature",
  "properties": {
    "iso:country":"US",
    "sg:address":"1455 Kempsville Rd",
    "sg:city":"Norfolk",
    "sg:classifiers":[
        {
            "category":"Building & Trades",
            "subcategory":"Construction",
            "type":"Services"
        }
    ],
    "sg:phone":"+1 757 461 8361",
    "sg:postcode":"23502",
    "sg:province":"VA",
    "sg:tags":[
        "contractor"
    ],
    "wof:name":"Floorslayers Inc",
    "wof:placetype":"venue"
},
  "geometry": {"coordinates":[-76.207286,36.873056],"type":"Point"}
}