{
  "type": "Feature",
  "properties": {
    "iso:country":"US",
    "sg:address":"219 Patton St",
    "sg:city":"Danville",
    "sg:classifiers":[
        {
            "category":"Professional",
            "subcategory":"Lawyer & Legal Services",
            "type":"Services"
        }
    ],
    "sg:phone":"+1 434 792 8722",
    "sg:postcode":"24541",
    "sg:province":"VA",
    "sg:tags":[
        "attorney"
    ],
    "wof:name":"Randy W Sinclair",
    "wof:placetype":"venue"
},
  "geometry": {"coordinates":[-79.389871,36.587659],"type":"Point"}
}