{
  "type": "Feature",
  "properties": {
    "addr:full":"2229 Rosson Rd Powhatan VA 23139",
    "addr:housenumber":"2229",
    "addr:postcode":"23139",
    "addr:street":"Rosson Rd",
    "iso:country":"US",
    "sg:address":"2229 Rosson Rd",
    "sg:city":"Powhatan",
    "sg:classifiers":[
        {
            "category":"Building & Trades",
            "subcategory":"Cleaning & Sanitation",
            "type":"Services"
        }
    ],
    "sg:phone":"+1 804 598 7855",
    "sg:postcode":"23139",
    "sg:province":"VA",
    "sg:tags":[
        "maintenance"
    ],
    "wof:name":"Newtons Chimney Cleaning",
    "wof:placetype":"venue"
},
  "geometry": {"coordinates":[-77.92301999999999,37.544661],"type":"Point"}
}