{
  "type": "Feature",
  "properties": {
    "addr:full":"4804 Hood Dr Fredericksburg VA 22408",
    "addr:housenumber":"4804",
    "addr:postcode":"22408",
    "addr:street":"Hood Dr",
    "iso:country":"US",
    "sg:address":"4804 Hood Dr",
    "sg:city":"Fredericksburg",
    "sg:classifiers":[
        {
            "category":"Retail",
            "subcategory":"Veterinary Services",
            "type":"Services"
        }
    ],
    "sg:phone":"+1 540 898 7387",
    "sg:postcode":"22408",
    "sg:province":"VA",
    "wof:name":"Hood Drive Veterinary Clinic",
    "wof:placetype":"venue"
},
  "geometry": {"coordinates":[-77.50316599999999,38.249479],"type":"Point"}
}