{
  "type": "Feature",
  "properties": {
    "addr:full":"1601 Potomac Greens Dr Alexandria VA 22314",
    "addr:housenumber":"1601",
    "addr:postcode":"22314",
    "addr:street":"Potomac Greens Dr",
    "iso:country":"US",
    "sg:address":"1601 Potomac Greens Dr",
    "sg:city":"Alexandria",
    "sg:classifiers":[
        {
            "category":"Professional",
            "subcategory":"Management & Consulting",
            "type":"Services"
        }
    ],
    "sg:phone":"+1 703 256 3164",
    "sg:postcode":"22314",
    "sg:province":"VA",
    "sg:tags":[
        "acting",
        "writing",
        "promotional"
    ],
    "wof:name":"Emsquare",
    "wof:placetype":"venue"
},
  "geometry": {"coordinates":[-77.048625,38.821101],"type":"Point"}
}