{
  "type": "Feature",
  "properties": {
    "addr:full":"11216 Air Park Rd Ashland VA 23005",
    "addr:housenumber":"11216",
    "addr:postcode":"23005",
    "addr:street":"Air Park Rd",
    "iso:country":"US",
    "sg:address":"11216 Air Park Rd",
    "sg:city":"Ashland",
    "sg:classifiers":[
        {
            "category":"Building & Trades",
            "subcategory":"Cleaning & Sanitation",
            "type":"Services"
        }
    ],
    "sg:phone":"+1 888 296 2692",
    "sg:postcode":"23005",
    "sg:province":"VA",
    "sg:tags":[
        "furnaces-repairing"
    ],
    "sg:website":"http://local.ingenio.com/Listings/Details.aspx?NUM=a%3a10070950%3a13%3a4859924%3a14%3a0%3a7",
    "wof:name":"Howell's Heating & Air Conditioning",
    "wof:placetype":"venue"
},
  "geometry": {"coordinates":[-77.440912,37.708751],"type":"Point"}
}