{
  "type": "Feature",
  "properties": {
    "iso:country":"US",
    "sg:address":"8030 W Broad St",
    "sg:city":"Richmond",
    "sg:classifiers":[
        {
            "category":"Health Services",
            "subcategory":"Health Practitioner",
            "type":"Services"
        }
    ],
    "sg:phone":"+1 804 288 1010",
    "sg:postcode":"23294",
    "sg:province":"VA",
    "wof:name":"Diversions",
    "wof:placetype":"venue"
},
  "geometry": {"coordinates":[-77.529483,37.624734],"type":"Point"}
}