{
  "type": "Feature",
  "properties": {
    "addr:full":"7839 Whiterim Ter Potomac MD 20854",
    "addr:housenumber":"7839",
    "addr:postcode":"20854",
    "addr:street":"Whiterim Ter",
    "iso:country":"US",
    "sg:address":"7839 Whiterim Ter",
    "sg:city":"Potomac",
    "sg:classifiers":[
        {
            "category":"Professional",
            "subcategory":"Management & Consulting",
            "type":"Services"
        }
    ],
    "sg:phone":"+1 301 983 0785",
    "sg:postcode":"20854",
    "sg:province":"MD",
    "sg:tags":[
        "international",
        "marketing"
    ],
    "wof:name":"Kaminsky Associates",
    "wof:placetype":"venue"
},
  "geometry": {"coordinates":[-77.22289600000001,38.987078],"type":"Point"}
}