{
  "type": "Feature",
  "properties": {
    "addr:full":"7685 Sudley Road Manassas VA 20109",
    "addr:housenumber":"7685",
    "addr:postcode":"20109",
    "addr:street":"Sudley Road",
    "iso:country":"US",
    "sg:address":"7685 Sudley Road",
    "sg:city":"Manassas",
    "sg:classifiers":[
        {
            "category":"Shopping",
            "subcategory":"Department Store",
            "type":"Retail Goods"
        }
    ],
    "sg:phone":"+1 703 368 6355",
    "sg:postcode":"20109",
    "sg:province":"VA",
    "sg:website":"www.babydepot.com",
    "wof:name":"Baby Depot At Burlington Coat Factory",
    "wof:placetype":"venue"
},
  "geometry": {"coordinates":[-77.514726,38.789804],"type":"Point"}
}