{
  "type": "Feature",
  "properties": {
    "addr:full":"500 Muller Ln Newport News VA 23606",
    "addr:housenumber":"500",
    "addr:postcode":"23606",
    "addr:street":"Muller Ln",
    "iso:country":"US",
    "sg:address":"500 Muller Ln",
    "sg:city":"Newport News",
    "sg:classifiers":[
        {
            "category":"Wholesale",
            "subcategory":"Machinery & Supplies",
            "type":"Manufacturing & Wholesale Goods"
        },
        {
            "category":"Wholesale",
            "subcategory":"Stationery",
            "type":"Manufacturing & Wholesale Goods"
        }
    ],
    "sg:phone":"+1 757 249 3312",
    "sg:postcode":"23606",
    "sg:province":"VA",
    "sg:tags":[
        "industrial",
        "product",
        "paper",
        "janitor",
        "janitorial"
    ],
    "wof:name":"Riverside Paper Supply Co",
    "wof:placetype":"venue"
},
  "geometry": {"coordinates":[-76.491499,37.09222],"type":"Point"}
}