{
  "type": "Feature",
  "properties": {
    "iso:country":"US",
    "sg:address":"220 S Sheffey St",
    "sg:city":"Marion",
    "sg:classifiers":[
        {
            "category":"Organizations",
            "subcategory":"Religious Organization",
            "type":"Services"
        }
    ],
    "sg:phone":"+1 276 783 2033",
    "sg:postcode":"24354",
    "sg:province":"VA",
    "sg:tags":[
        "church"
    ],
    "wof:name":"First Assembly Of God",
    "wof:placetype":"venue"
},
  "geometry": {"coordinates":[-81.520431,36.830594],"type":"Point"}
}