{
  "type": "Feature",
  "properties": {
    "iso:country":"US",
    "sg:address":"4208 Feather Ridge Dr",
    "sg:city":"Virginia Beach",
    "sg:classifiers":[
        {
            "category":"Arts & Performance",
            "subcategory":"Theater",
            "type":"Entertainment"
        }
    ],
    "sg:phone":"+1 757 416 0110",
    "sg:postcode":"23456",
    "sg:province":"VA",
    "sg:tags":[
        "group"
    ],
    "wof:name":"Entertainment Concepts",
    "wof:placetype":"venue"
},
  "geometry": {"coordinates":[-76.131407,36.759916],"type":"Point"}
}