{
  "type": "Feature",
  "properties": {
    "iso:country":"US",
    "sg:address":"4107 Mallard Landing Cir",
    "sg:city":"Midlothian",
    "sg:classifiers":[
        {
            "category":"Professional",
            "subcategory":"Business Services",
            "type":"Services"
        }
    ],
    "sg:phone":"+1 804 674 8857",
    "sg:postcode":"23112",
    "sg:province":"VA",
    "wof:name":"Carrington Enterprises",
    "wof:placetype":"venue"
},
  "geometry": {"coordinates":[-77.589985,37.434215],"type":"Point"}
}