{
  "type": "Feature",
  "properties": {
    "addr:full":"303 River City Court Way # 101 Richmond VA 23221",
    "addr:housenumber":"303;101",
    "addr:postcode":"23221",
    "addr:street":"River City Court Way #",
    "iso:country":"US",
    "sg:address":"303 River City Court Way # 101",
    "sg:city":"Richmond",
    "sg:classifiers":[
        {
            "category":"Arts & Performance",
            "subcategory":"Dance",
            "type":"Entertainment"
        }
    ],
    "sg:phone":"+1 804 308 2285",
    "sg:postcode":"23221",
    "sg:province":"VA",
    "sg:tags":[
        "instruction",
        "dancing"
    ],
    "wof:name":"Broadway's Dance & Fitness Studio",
    "wof:placetype":"venue"
},
  "geometry": {"coordinates":[-77.485315,37.560203],"type":"Point"}
}