{
  "type": "Feature",
  "properties": {
    "addr:full":"9625 Belvoir Rd Fort Belvoir VA 22060",
    "addr:housenumber":"9625",
    "addr:postcode":"22060",
    "addr:street":"Belvoir Rd",
    "iso:country":"US",
    "sg:address":"9625 Belvoir Rd",
    "sg:city":"Fort Belvoir",
    "sg:classifiers":[
        {
            "category":"Education",
            "subcategory":"College",
            "type":"Public Place"
        }
    ],
    "sg:phone":"+1 703 781 0299",
    "sg:postcode":"22060",
    "sg:province":"VA",
    "wof:name":"Off Cmps Acdmc Prgrm Cllge",
    "wof:placetype":"venue"
},
  "geometry": {"coordinates":[-77.13880399999999,38.696355],"type":"Point"}
}