{
  "type": "Feature",
  "properties": {
    "addr:full":"734 Red Mill Rd Norfolk VA 23502",
    "addr:housenumber":"734",
    "addr:postcode":"23502",
    "addr:street":"Red Mill Rd",
    "iso:country":"US",
    "sg:address":"734 Red Mill Rd",
    "sg:city":"Norfolk",
    "sg:classifiers":[
        {
            "category":"Wholesale",
            "subcategory":"Construction Materials",
            "type":"Manufacturing & Wholesale Goods"
        }
    ],
    "sg:phone":"+1 757 714 6505",
    "sg:postcode":"23502",
    "sg:province":"VA",
    "sg:tags":[
        "repair",
        "installation",
        "fence"
    ],
    "wof:name":"Quality Fence Company",
    "wof:placetype":"venue"
},
  "geometry": {"coordinates":[-76.223457,36.85105],"type":"Point"}
}