{
  "type": "Feature",
  "properties": {
    "iso:country":"US",
    "sg:address":"249 Indian Creek Rd",
    "sg:city":"Chesapeake",
    "sg:classifiers":[
        {
            "category":"Building & Trades",
            "subcategory":"Construction",
            "type":"Services"
        }
    ],
    "sg:phone":"+1 757 421 9114",
    "sg:postcode":"23322",
    "sg:province":"VA",
    "sg:tags":[
        "hanging",
        "contractor"
    ],
    "wof:name":"H&H Plaster & Painting",
    "wof:placetype":"venue"
},
  "geometry": {"coordinates":[-76.200306,36.609281],"type":"Point"}
}