{
  "type": "Feature",
  "properties": {
    "addr:full":"2097 Langhorne Rd Lynchburg VA 24501",
    "addr:housenumber":"2097",
    "addr:postcode":"24501",
    "addr:street":"Langhorne Rd",
    "iso:country":"US",
    "sg:address":"2097 Langhorne Rd",
    "sg:city":"Lynchburg",
    "sg:classifiers":[
        {
            "category":"Health Services",
            "subcategory":"Doctor",
            "type":"Services"
        }
    ],
    "sg:phone":"+1 434 200 5200",
    "sg:postcode":"24501",
    "sg:province":"VA",
    "sg:tags":[
        "physician",
        "surgeon"
    ],
    "wof:name":"Thompson Terry J MD",
    "wof:placetype":"venue"
},
  "geometry": {"coordinates":[-79.180181,37.413711],"type":"Point"}
}