{
  "type": "Feature",
  "properties": {
    "addr:full":"20925 Professional Plz Ashburn VA 20147",
    "addr:housenumber":"20925",
    "addr:postcode":"20147",
    "addr:street":"Professional Plz",
    "iso:country":"US",
    "sg:address":"20925 Professional Plz",
    "sg:city":"Ashburn",
    "sg:classifiers":[
        {
            "category":"Organizations",
            "subcategory":"Religious Organization",
            "type":"Services"
        }
    ],
    "sg:phone":"+1 703 858 7800",
    "sg:postcode":"20147",
    "sg:province":"VA",
    "wof:name":"Grace Community Plaza",
    "wof:placetype":"venue"
},
  "geometry": {"coordinates":[-77.50421799999999,39.036793],"type":"Point"}
}