{
  "type": "Feature",
  "properties": {
    "iso:country":"US",
    "sg:address":"3265 Ives Rd",
    "sg:city":"Virginia Beach",
    "sg:classifiers":[
        {
            "category":"Retail",
            "subcategory":"Repair Shop",
            "type":"Services"
        }
    ],
    "sg:phone":"+1 757 340 5565",
    "sg:postcode":"23457",
    "sg:province":"VA",
    "sg:tags":[
        "cleaning"
    ],
    "wof:name":"Carpet Tech Of Tidewater",
    "wof:placetype":"venue"
},
  "geometry": {"coordinates":[-76.10630500000001,36.661291],"type":"Point"}
}