{
  "type": "Feature",
  "properties": {
    "addr:full":"440 South St Front Royal VA 22630",
    "addr:housenumber":"440",
    "addr:postcode":"22630",
    "addr:street":"South St",
    "iso:country":"US",
    "sg:address":"440 South St",
    "sg:city":"Front Royal",
    "sg:classifiers":[
        {
            "category":"Building & Trades",
            "subcategory":"Construction",
            "type":"Services"
        }
    ],
    "sg:phone":"+1 540 635 9379",
    "sg:postcode":"22630",
    "sg:province":"VA",
    "sg:tags":[
        "general",
        "contractor"
    ],
    "wof:name":"Acorn Construction LTD",
    "wof:placetype":"venue"
},
  "geometry": {"coordinates":[-78.186508,38.911135],"type":"Point"}
}