{
  "type": "Feature",
  "properties": {
    "addr:full":"14257 Blue Ridge Tpke Somerset VA 22972",
    "addr:housenumber":"14257",
    "addr:postcode":"22972",
    "addr:street":"Blue Ridge Tpke",
    "iso:country":"US",
    "sg:address":"14257 Blue Ridge Tpke",
    "sg:city":"Somerset",
    "sg:classifiers":[
        {
            "category":"Government",
            "subcategory":"Post Office",
            "type":"Public Place"
        }
    ],
    "sg:phone":"+1 540 672 2492",
    "sg:postcode":"22972",
    "sg:province":"VA",
    "sg:tags":[
        "postal",
        "us"
    ],
    "wof:name":"Somerset Main Office",
    "wof:placetype":"venue"
},
  "geometry": {"coordinates":[-78.218013,38.208712],"type":"Point"}
}