{
  "type": "Feature",
  "properties": {
    "addr:full":"204 Ridge Rd Callao VA 22435",
    "addr:housenumber":"204",
    "addr:postcode":"22435",
    "addr:street":"Ridge Rd",
    "iso:country":"US",
    "sg:address":"204 Ridge Rd",
    "sg:city":"Callao",
    "sg:classifiers":[
        {
            "category":"Shopping",
            "subcategory":"Computers & Home Electronics",
            "type":"Retail Goods"
        }
    ],
    "sg:phone":"+1 804 529 6568",
    "sg:postcode":"22435",
    "sg:province":"VA",
    "sg:tags":[
        "antenna"
    ],
    "wof:name":"Frank Comb's Satellite",
    "wof:placetype":"venue"
},
  "geometry": {"coordinates":[-76.58568,37.945469],"type":"Point"}
}