{
  "type": "Feature",
  "properties": {
    "addr:full":"4036 Electric Rd Roanoke VA 24018",
    "addr:housenumber":"4036",
    "addr:postcode":"24018",
    "addr:street":"Electric Rd",
    "iso:country":"US",
    "sg:address":"4036 Electric Rd",
    "sg:city":"Roanoke",
    "sg:classifiers":[
        {
            "category":"Retail",
            "subcategory":"Auto Repair",
            "type":"Services"
        }
    ],
    "sg:phone":"+1 540 772 0660",
    "sg:postcode":"24018",
    "sg:province":"VA",
    "sg:tags":[
        "automotive"
    ],
    "sg:website":"www.jiffylube.com",
    "wof:name":"Jiffy Lube",
    "wof:placetype":"venue"
},
  "geometry": {"coordinates":[-79.984544,37.223957],"type":"Point"}
}