{
  "type": "Feature",
  "properties": {
    "addr:full":"1005 Cup Leaf Holly Ct Great Falls VA 22066",
    "addr:housenumber":"1005",
    "addr:postcode":"22066",
    "addr:street":"Cup Leaf Holly Ct",
    "iso:country":"US",
    "sg:address":"1005 Cup Leaf Holly Ct",
    "sg:city":"Great Falls",
    "sg:classifiers":[
        {
            "category":"Professional",
            "subcategory":"Engineering",
            "type":"Services"
        }
    ],
    "sg:phone":"+1 703 450 6105",
    "sg:postcode":"22066",
    "sg:province":"VA",
    "wof:name":"Norman L Smith Consultant",
    "wof:placetype":"venue"
},
  "geometry": {"coordinates":[-77.36016100000001,39.011931],"type":"Point"}
}