{
  "type": "Feature",
  "properties": {
    "addr:full":"24203 River Rd Petersburg VA 23803",
    "addr:housenumber":"24203",
    "addr:postcode":"23803",
    "addr:street":"River Rd",
    "iso:country":"US",
    "sg:address":"24203 River Rd",
    "sg:city":"Petersburg",
    "sg:classifiers":[
        {
            "category":"Building & Trades",
            "subcategory":"Construction",
            "type":"Services"
        }
    ],
    "sg:phone":"+1 804 768 2418",
    "sg:postcode":"23803",
    "sg:province":"VA",
    "sg:tags":[
        "ceiling",
        "ins",
        "contractor",
        "exterior",
        "an",
        "drywall"
    ],
    "wof:name":"M & P Interiors Inc",
    "wof:placetype":"venue"
},
  "geometry": {"coordinates":[-77.48650000000001,37.217778],"type":"Point"}
}