{
  "type": "Feature",
  "properties": {
    "iso:country":"US",
    "sg:address":"2800 Electric Rd",
    "sg:city":"Roanoke",
    "sg:classifiers":[
        {
            "category":"Health Services",
            "subcategory":"Doctor",
            "type":"Services"
        }
    ],
    "sg:phone":"+1 540 772 0103",
    "sg:postcode":"24018",
    "sg:province":"VA",
    "sg:tags":[
        "physician",
        "surgeon"
    ],
    "wof:name":"Oncology & Hematology Assoc",
    "wof:placetype":"venue"
},
  "geometry": {"coordinates":[-80.019088,37.233588],"type":"Point"}
}