{
  "type": "Feature",
  "properties": {
    "iso:country":"US",
    "sg:address":"864 Forrest Dr",
    "sg:city":"Stanley",
    "sg:classifiers":[
        {
            "category":"Professional",
            "subcategory":"Business Services",
            "type":"Services"
        }
    ],
    "sg:phone":"+1 540 778 4284",
    "sg:postcode":"22851",
    "sg:province":"VA",
    "sg:tags":[
        "embroidery"
    ],
    "wof:name":"B & B Embroidery",
    "wof:placetype":"venue"
},
  "geometry": {"coordinates":[-78.51984400000001,38.580847],"type":"Point"}
}