{
  "type": "Feature",
  "properties": {
    "iso:country":"US",
    "sg:address":"1227 Central Park Blvd",
    "sg:city":"Fredericksburg",
    "sg:classifiers":[
        {
            "category":"Real Estate",
            "subcategory":"Architect",
            "type":"Services"
        },
        {
            "category":"Professional",
            "subcategory":"Engineering",
            "type":"Services"
        }
    ],
    "sg:phone":"+1 540 785 2528",
    "sg:postcode":"22401",
    "sg:province":"VA",
    "sg:tags":[
        "architectural",
        "engineer"
    ],
    "sg:website":"www.g-and-o.com",
    "wof:name":"Greenhorne & O'Mara Inc",
    "wof:placetype":"venue"
},
  "geometry": {"coordinates":[-77.515371,38.300618],"type":"Point"}
}