{
  "type": "Feature",
  "properties": {
    "addr:full":"119 Sylvia Rd Ashland VA 23005",
    "addr:housenumber":"119",
    "addr:postcode":"23005",
    "addr:street":"Sylvia Rd",
    "iso:country":"US",
    "sg:address":"119 Sylvia Rd",
    "sg:city":"Ashland",
    "sg:classifiers":[
        {
            "category":"Building & Trades",
            "subcategory":"Construction",
            "type":"Services"
        }
    ],
    "sg:phone":"+1 804 798 1385",
    "sg:postcode":"23005",
    "sg:province":"VA",
    "sg:tags":[
        "masonry",
        "contractor"
    ],
    "wof:name":"Boschen Masonry Inc",
    "wof:placetype":"venue"
},
  "geometry": {"coordinates":[-77.46900599999999,37.770879],"type":"Point"}
}