{
  "type": "Feature",
  "properties": {
    "iso:country":"US",
    "sg:address":"10562 Ramey Rd",
    "sg:city":"Marshall",
    "sg:classifiers":[
        {
            "category":"Professional",
            "subcategory":"Business Services",
            "type":"Services"
        }
    ],
    "sg:phone":"+1 540 364 3762",
    "sg:postcode":"20115",
    "sg:province":"VA",
    "wof:name":"Stonehurst Enterprise",
    "wof:placetype":"venue"
},
  "geometry": {"coordinates":[-77.939142,38.84184],"type":"Point"}
}