{
  "type": "Feature",
  "properties": {
    "addr:full":"4485 Lookout Rd Virginia Beach VA 23455",
    "addr:housenumber":"4485",
    "addr:postcode":"23455",
    "addr:street":"Lookout Rd",
    "iso:country":"US",
    "sg:address":"4485 Lookout Rd",
    "sg:city":"Virginia Beach",
    "sg:classifiers":[
        {
            "category":"Real Estate",
            "subcategory":"Real Estate Agent",
            "type":"Services"
        }
    ],
    "sg:phone":"+1 757 363 2705",
    "sg:postcode":"23455",
    "sg:province":"VA",
    "sg:tags":[
        "manager"
    ],
    "wof:name":"Jack Essayian",
    "wof:placetype":"venue"
},
  "geometry": {"coordinates":[-76.125462,36.914961],"type":"Point"}
}