{
  "type": "Feature",
  "properties": {
    "iso:country":"US",
    "sg:address":"3920 Virginia Beach Blvd",
    "sg:city":"Virginia Beach",
    "sg:classifiers":[
        {
            "category":"Shopping",
            "subcategory":"Clothing, Apparel, & Fashions",
            "type":"Retail Goods"
        }
    ],
    "sg:phone":"+1 757 631 1906",
    "sg:postcode":"23452",
    "sg:province":"VA",
    "wof:name":"C & R Alterations Inc",
    "wof:placetype":"venue"
},
  "geometry": {"coordinates":[-76.110726,36.840759],"type":"Point"}
}