{
  "type": "Feature",
  "properties": {
    "addr:full":"8900 Telegraph Rd Lorton VA 22079",
    "addr:housenumber":"8900",
    "addr:postcode":"22079",
    "addr:street":"Telegraph Rd",
    "iso:country":"US",
    "sg:address":"8900 Telegraph Rd",
    "sg:city":"Lorton",
    "sg:classifiers":[
        {
            "category":"Manufacturing",
            "subcategory":"Textiles",
            "type":"Manufacturing & Wholesale Goods"
        },
        {
            "category":"Manufacturing",
            "subcategory":"Glass & Minerals",
            "type":"Manufacturing & Wholesale Goods"
        },
        {
            "category":"Manufacturing",
            "subcategory":"Building Materials",
            "type":"Manufacturing & Wholesale Goods"
        },
        {
            "category":"Building & Trades",
            "subcategory":"Construction",
            "type":"Services"
        }
    ],
    "sg:phone":"+1 703 550 0980",
    "sg:postcode":"22079",
    "sg:province":"VA",
    "sg:tags":[
        "tile-contractors",
        "ceramic",
        "marble-cultured",
        "products-industrial",
        "tile-wholesale",
        "manufacturer"
    ],
    "sg:website":"http://www.bfceramics.com",
    "wof:name":"B & F Ceramics Design Showroom",
    "wof:placetype":"venue"
},
  "geometry": {"coordinates":[-77.19367200000001,38.71711],"type":"Point"}
}