{
  "type": "Feature",
  "properties": {
    "addr:full":"590 Radio Hill Rd Marion VA 24354",
    "addr:housenumber":"590",
    "addr:postcode":"24354",
    "addr:street":"Radio Hill Rd",
    "iso:country":"US",
    "sg:address":"590 Radio Hill Rd",
    "sg:city":"Marion",
    "sg:classifiers":[
        {
            "category":"Health Services",
            "subcategory":"Doctor",
            "type":"Services"
        }
    ],
    "sg:phone":"+1 276 783 8183",
    "sg:postcode":"24354",
    "sg:province":"VA",
    "sg:tags":[
        "physician",
        "surgeon",
        "medical"
    ],
    "wof:name":"Marion Pediatric Associates PC",
    "wof:placetype":"venue"
},
  "geometry": {"coordinates":[-81.508655,36.850432],"type":"Point"}
}