{
  "type": "Feature",
  "properties": {
    "iso:country":"US",
    "sg:address":"9502 Chamberlayne Rd",
    "sg:city":"Mechanicsville",
    "sg:classifiers":[
        {
            "category":"Restaurant",
            "type":"Food & Drink"
        }
    ],
    "sg:phone":"+1 804 730 5050",
    "sg:postcode":"23116",
    "sg:province":"VA",
    "sg:tags":[
        "shop",
        "coffee"
    ],
    "wof:name":"San Marco Coffee",
    "wof:placetype":"venue"
},
  "geometry": {"coordinates":[-77.38526299999999,37.659592],"type":"Point"}
}