{
  "type": "Feature",
  "properties": {
    "iso:country":"US",
    "sg:address":"9518 Lee Hwy",
    "sg:city":"Fairfax",
    "sg:classifiers":[
        {
            "category":"Professional",
            "subcategory":"Accounting & Tax Preparation",
            "type":"Services"
        }
    ],
    "sg:phone":"+1 703 934 7000",
    "sg:postcode":"22031",
    "sg:province":"VA",
    "sg:tags":[
        "accountant"
    ],
    "sg:website":"www.goldklangcavanaugh.com",
    "wof:name":"Goldklang Cavanaugh & Assoc PC",
    "wof:placetype":"venue"
},
  "geometry": {"coordinates":[-77.272687,38.867726],"type":"Point"}
}