{
  "type": "Feature",
  "properties": {
    "addr:full":"1900 Mechanicsville Tpke Richmond VA 23223",
    "addr:postcode":"1900;23223",
    "addr:street":"Tpke",
    "iso:country":"US",
    "sg:address":"1900 Mechanicsville Tpke",
    "sg:city":"Richmond",
    "sg:classifiers":[
        {
            "category":"Fast Food",
            "type":"Food & Drink"
        },
        {
            "category":"Restaurant",
            "type":"Food & Drink"
        }
    ],
    "sg:phone":"+1 804 783 9924",
    "sg:postcode":"23223",
    "sg:province":"VA",
    "sg:tags":[
        "chicken",
        "take"
    ],
    "sg:website":"http://www.churchschicken.com",
    "wof:name":"Church's Chicken",
    "wof:placetype":"venue"
},
  "geometry": {"coordinates":[-77.41211699999999,37.552769],"type":"Point"}
}