{
  "type": "Feature",
  "properties": {
    "addr:full":"5317 Balfor Dr Virginia Beach VA 23464",
    "addr:housenumber":"5317",
    "addr:postcode":"23464",
    "addr:street":"Balfor Dr",
    "iso:country":"US",
    "sg:address":"5317 Balfor Dr",
    "sg:city":"Virginia Beach",
    "sg:classifiers":[
        {
            "category":"Building & Trades",
            "subcategory":"Construction",
            "type":"Services"
        }
    ],
    "sg:phone":"+1 757 420 5528",
    "sg:postcode":"23464",
    "sg:province":"VA",
    "sg:tags":[
        "house"
    ],
    "wof:name":"Leos Home Improvement Svcs",
    "wof:placetype":"venue"
},
  "geometry": {"coordinates":[-76.172855,36.820072],"type":"Point"}
}