{
  "type": "Feature",
  "properties": {
    "iso:country":"US",
    "sg:address":"6429 Williamson Rd",
    "sg:city":"Roanoke",
    "sg:classifiers":[
        {
            "category":"Manufacturing",
            "subcategory":"Signs",
            "type":"Manufacturing & Wholesale Goods"
        }
    ],
    "sg:phone":"+1 540 362 2025",
    "sg:postcode":"24019",
    "sg:province":"VA",
    "sg:tags":[
        "specialty",
        "mfg"
    ],
    "wof:name":"Rapidsign Inc",
    "wof:placetype":"venue"
},
  "geometry": {"coordinates":[-79.955172,37.335512],"type":"Point"}
}