{
  "type": "Feature",
  "properties": {
    "addr:full":"11501 N Lakeridge Pkwy Ashland VA 23005",
    "addr:housenumber":"11501",
    "addr:postcode":"23005",
    "addr:street":"N Lakeridge Pkwy",
    "iso:country":"US",
    "sg:address":"11501 N Lakeridge Pkwy",
    "sg:city":"Ashland",
    "sg:phone":"+1 804 798 8500",
    "sg:postcode":"23005",
    "sg:province":"VA",
    "sg:tags":[
        "fab",
        "comp",
        "wire",
        "commercial",
        "mfg"
    ],
    "wof:name":"I F S",
    "wof:placetype":"venue"
},
  "geometry": {"coordinates":[-77.455045,37.721579],"type":"Point"}
}