{
  "type": "Feature",
  "properties": {
    "addr:full":"11010 Air Park Rd Ashland VA 23005",
    "addr:housenumber":"11010",
    "addr:postcode":"23005",
    "addr:street":"Air Park Rd",
    "iso:country":"US",
    "sg:address":"11010 Air Park Rd",
    "sg:city":"Ashland",
    "sg:classifiers":[
        {
            "category":"Building & Trades",
            "subcategory":"Cleaning & Sanitation",
            "type":"Services"
        }
    ],
    "sg:phone":"+1 804 752 7510",
    "sg:postcode":"23005",
    "sg:province":"VA",
    "sg:tags":[
        "janitor"
    ],
    "wof:name":"Ind Steam Cleaning",
    "wof:placetype":"venue"
},
  "geometry": {"coordinates":[-77.434483,37.70085],"type":"Point"}
}