{
  "type": "Feature",
  "properties": {
    "addr:full":"4011 Wythe Ave Richmond VA 23221",
    "addr:housenumber":"4011",
    "addr:postcode":"23221",
    "addr:street":"Wythe Ave",
    "iso:country":"US",
    "sg:address":"4011 Wythe Ave",
    "sg:city":"Richmond",
    "sg:classifiers":[
        {
            "category":"Insurance",
            "subcategory":"Insurance Agent",
            "type":"Services"
        }
    ],
    "sg:phone":"+1 804 359 4152",
    "sg:postcode":"23221",
    "sg:province":"VA",
    "wof:name":"Logan Mark P Agency",
    "wof:placetype":"venue"
},
  "geometry": {"coordinates":[-77.487168,37.568582],"type":"Point"}
}