{
  "type": "Feature",
  "properties": {
    "addr:full":"404 E 2nd Ave Franklin VA 23851",
    "addr:housenumber":"404",
    "addr:postcode":"23851",
    "addr:street":"E 2Nd Ave",
    "iso:country":"US",
    "sg:address":"404 E 2nd Ave",
    "sg:city":"Franklin",
    "sg:classifiers":[
        {
            "category":"Building & Trades",
            "subcategory":"Equipment Rental",
            "type":"Services"
        }
    ],
    "sg:phone":"+1 757 569 9323",
    "sg:postcode":"23851",
    "sg:province":"VA",
    "wof:name":"U-Haul",
    "wof:placetype":"venue"
},
  "geometry": {"coordinates":[-76.918454,36.680425],"type":"Point"}
}