{
  "type": "Feature",
  "properties": {
    "addr:full":"520 James Madison Hwy Culpeper VA 22701",
    "addr:housenumber":"520",
    "addr:postcode":"22701",
    "addr:street":"James Madison Hwy",
    "iso:country":"US",
    "sg:address":"520 James Madison Hwy",
    "sg:city":"Culpeper",
    "sg:classifiers":[
        {
            "category":"Food & Beverages",
            "subcategory":"Groceries & Convenience Stores",
            "type":"Retail Goods"
        }
    ],
    "sg:phone":"+1 540 825 1222",
    "sg:postcode":"22701",
    "sg:province":"VA",
    "wof:name":"7-Eleven",
    "wof:placetype":"venue"
},
  "geometry": {"coordinates":[-77.982702,38.4811],"type":"Point"}
}