{
  "type": "Feature",
  "properties": {
    "iso:country":"US",
    "sg:address":"715 Spottswood Rd",
    "sg:city":"Richmond",
    "sg:classifiers":[
        {
            "category":"Parking",
            "type":"Transportation"
        }
    ],
    "sg:phone":"+1 804 359 4541",
    "sg:postcode":"23220",
    "sg:province":"VA",
    "sg:tags":[
        "lot"
    ],
    "wof:name":"Urban Industries Richmond Inc",
    "wof:placetype":"venue"
},
  "geometry": {"coordinates":[-77.47794399999999,37.542846],"type":"Point"}
}