{
  "type": "Feature",
  "properties": {
    "addr:full":"900 N Hamilton St Richmond VA 23221",
    "addr:housenumber":"900",
    "addr:postcode":"23221",
    "addr:street":"N Hamilton St",
    "iso:country":"US",
    "sg:address":"900 N Hamilton St",
    "sg:city":"Richmond",
    "sg:classifiers":[
        {
            "category":"Health Services",
            "subcategory":"Doctor",
            "type":"Services"
        }
    ],
    "sg:phone":"+1 804 359 6442",
    "sg:postcode":"23221",
    "sg:province":"VA",
    "sg:tags":[
        "dentist"
    ],
    "wof:name":"Julie F Palmore DDS",
    "wof:placetype":"venue"
},
  "geometry": {"coordinates":[-77.48344299999999,37.566433],"type":"Point"}
}