{
  "type": "Feature",
  "properties": {
    "addr:full":"5904 Main St Mt Jackson VA 22842",
    "addr:housenumber":"5904",
    "addr:postcode":"22842",
    "addr:street":"Main St",
    "iso:country":"US",
    "sg:address":"5904 Main St",
    "sg:city":"Mt Jackson",
    "sg:classifiers":[
        {
            "category":"Sports & Exercise",
            "subcategory":"Bowling",
            "type":"Entertainment"
        }
    ],
    "sg:phone":"+1 540 477 2341",
    "sg:postcode":"22842",
    "sg:province":"VA",
    "sg:tags":[
        "center"
    ],
    "wof:name":"Shenandoah Bowling Lanes",
    "wof:placetype":"venue"
},
  "geometry": {"coordinates":[-78.642261,38.746753],"type":"Point"}
}