{
  "type": "Feature",
  "properties": {
    "addr:full":"359 W Main St Wytheville VA 24382",
    "addr:housenumber":"359",
    "addr:postcode":"24382",
    "addr:street":"W Main St",
    "iso:country":"US",
    "sg:address":"359 W Main St",
    "sg:city":"Wytheville",
    "sg:classifiers":[
        {
            "category":"Autos & Motor Vehicles",
            "subcategory":"Auto Supplies",
            "type":"Retail Goods"
        }
    ],
    "sg:phone":"+1 276 228 3655",
    "sg:postcode":"24382",
    "sg:province":"VA",
    "wof:name":"Bug Shop  The",
    "wof:placetype":"venue"
},
  "geometry": {"coordinates":[-81.08571000000001,36.948156],"type":"Point"}
}