{
  "type": "Feature",
  "properties": {
    "addr:full":"600 King St Portsmouth VA 23704",
    "addr:housenumber":"600",
    "addr:postcode":"23704",
    "addr:street":"King St",
    "iso:country":"US",
    "sg:address":"600 King St",
    "sg:city":"Portsmouth",
    "sg:classifiers":[
        {
            "category":"Organizations",
            "subcategory":"Religious Organization",
            "type":"Services"
        }
    ],
    "sg:phone":"+1 757 399 6556",
    "sg:postcode":"23704",
    "sg:province":"VA",
    "wof:name":"First Lutheran Church",
    "wof:placetype":"venue"
},
  "geometry": {"coordinates":[-76.305342,36.834436],"type":"Point"}
}