{
  "type": "Feature",
  "properties": {
    "addr:full":"4572 Airlie Way Annandale VA 22003",
    "addr:housenumber":"4572",
    "addr:postcode":"22003",
    "addr:street":"Airlie Way",
    "iso:country":"US",
    "sg:address":"4572 Airlie Way",
    "sg:city":"Annandale",
    "sg:classifiers":[
        {
            "category":"Professional",
            "type":"Services"
        }
    ],
    "sg:phone":"+1 703 750 7813",
    "sg:postcode":"22003",
    "sg:province":"VA",
    "wof:name":"Advantec",
    "wof:placetype":"venue"
},
  "geometry": {"coordinates":[-77.17557499999999,38.827105],"type":"Point"}
}