{
  "type": "Feature",
  "properties": {
    "addr:full":"619 N Coalter St Staunton VA 24401",
    "addr:housenumber":"619",
    "addr:postcode":"24401",
    "addr:street":"N Coalter St",
    "iso:country":"US",
    "sg:address":"619 N Coalter St",
    "sg:city":"Staunton",
    "sg:classifiers":[
        {
            "category":"Building & Trades",
            "subcategory":"Construction",
            "type":"Services"
        }
    ],
    "sg:phone":"+1 540 886 5110",
    "sg:postcode":"24401",
    "sg:province":"VA",
    "sg:tags":[
        "planning",
        "remodeling",
        "kitchen"
    ],
    "wof:name":"Panther Creek Kitchens",
    "wof:placetype":"venue"
},
  "geometry": {"coordinates":[-79.062011,38.159519],"type":"Point"}
}