{
  "type": "Feature",
  "properties": {
    "addr:full":"9517 Farmview Ct Fairfax VA 22032",
    "addr:housenumber":"9517",
    "addr:postcode":"22032",
    "addr:street":"Farmview Ct",
    "iso:country":"US",
    "sg:address":"9517 Farmview Ct",
    "sg:city":"Fairfax",
    "sg:classifiers":[
        {
            "category":"Professional",
            "subcategory":"Management & Consulting",
            "type":"Services"
        }
    ],
    "sg:phone":"+1 703 426 1535",
    "sg:postcode":"22032",
    "sg:province":"VA",
    "sg:tags":[
        "consultant",
        "business"
    ],
    "wof:name":"G E Access",
    "wof:placetype":"venue"
},
  "geometry": {"coordinates":[-77.27447100000001,38.832037],"type":"Point"}
}