{
  "type": "Feature",
  "properties": {
    "addr:full":"3457 Whiting Rd Marshall VA 20198",
    "addr:housenumber":"3457",
    "addr:postcode":"20198",
    "addr:street":"Whiting Rd",
    "iso:country":"US",
    "sg:address":"3457 Whiting Rd",
    "sg:city":"Marshall",
    "sg:classifiers":[
        {
            "category":"Professional",
            "type":"Services"
        }
    ],
    "sg:phone":"+1 540 364 1600",
    "sg:postcode":"20198",
    "sg:province":"VA",
    "sg:tags":[
        "establishment"
    ],
    "wof:name":"Team Technology Inc",
    "wof:placetype":"venue"
},
  "geometry": {"coordinates":[-77.84606100000001,38.892727],"type":"Point"}
}