{
  "type": "Feature",
  "properties": {
    "addr:full":"10664 Runnymeade Dr Glen Allen VA 23059",
    "addr:housenumber":"10664",
    "addr:postcode":"23059",
    "addr:street":"Runnymeade Dr",
    "iso:country":"US",
    "sg:address":"10664 Runnymeade Dr",
    "sg:city":"Glen Allen",
    "sg:classifiers":[
        {
            "category":"Wholesale",
            "subcategory":"Home Furnishings",
            "type":"Manufacturing & Wholesale Goods"
        }
    ],
    "sg:phone":"+1 804 515 8847",
    "sg:postcode":"23059",
    "sg:province":"VA",
    "sg:tags":[
        "product"
    ],
    "wof:name":"House Of Designs Inc",
    "wof:placetype":"venue"
},
  "geometry": {"coordinates":[-77.46853400000001,37.66995],"type":"Point"}
}