{
  "type": "Feature",
  "properties": {
    "iso:country":"US",
    "sg:address":"3501 2nd St S",
    "sg:city":"Arlington",
    "sg:classifiers":[
        {
            "category":"Building & Trades",
            "subcategory":"Locksmith",
            "type":"Services"
        }
    ],
    "sg:phone":"+1 202 621 2109",
    "sg:postcode":"22204",
    "sg:province":"VA",
    "sg:tags":[
        "key"
    ],
    "wof:name":"Hex Locksmith",
    "wof:placetype":"venue"
},
  "geometry": {"coordinates":[-77.096276,38.868992],"type":"Point"}
}