{
  "type": "Feature",
  "properties": {
    "addr:full":"1650 Diagonal Rd Alexandria VA 22314",
    "addr:housenumber":"1650",
    "addr:postcode":"22314",
    "addr:street":"Diagonal Rd",
    "iso:country":"US",
    "sg:address":"1650 Diagonal Rd",
    "sg:city":"Alexandria",
    "sg:classifiers":[
        {
            "category":"Recreation",
            "type":"Entertainment"
        }
    ],
    "sg:phone":"+1 703 838 8791",
    "sg:postcode":"22314",
    "sg:province":"VA",
    "sg:tags":[
        "carnival"
    ],
    "wof:name":"D C Festival With Luis Palau",
    "wof:placetype":"venue"
},
  "geometry": {"coordinates":[-77.059318,38.806194],"type":"Point"}
}