{
  "type": "Feature",
  "properties": {
    "iso:country":"US",
    "sg:address":"5741 S Laburnum Ave",
    "sg:city":"Richmond",
    "sg:classifiers":[
        {
            "category":"Utilities",
            "subcategory":"Refuse",
            "type":"Services"
        }
    ],
    "sg:phone":"+1 804 222 8360",
    "sg:postcode":"23231",
    "sg:province":"VA",
    "sg:tags":[
        "waste",
        "removal"
    ],
    "wof:name":"Stericycle Inc",
    "wof:placetype":"venue"
},
  "geometry": {"coordinates":[-77.34936399999999,37.507994],"type":"Point"}
}