{
  "type": "Feature",
  "properties": {
    "iso:country":"US",
    "sg:address":"4116 W Mercury Blvd",
    "sg:city":"Hampton",
    "sg:classifiers":[
        {
            "category":"Autos & Motor Vehicles",
            "subcategory":"Automobile Sales",
            "type":"Retail Goods"
        }
    ],
    "sg:phone":"+1 757 890 8861",
    "sg:postcode":"23666",
    "sg:province":"VA",
    "sg:tags":[
        "car",
        "dealer"
    ],
    "wof:name":"Pomoco Lincoln Mercury Newport",
    "wof:placetype":"venue"
},
  "geometry": {"coordinates":[-76.427313,37.028114],"type":"Point"}
}