{
  "type": "Feature",
  "properties": {
    "iso:country":"US",
    "sg:address":"1315 E Cary St",
    "sg:city":"Richmond",
    "sg:classifiers":[
        {
            "category":"Real Estate",
            "subcategory":"Real Estate Operator",
            "type":"Services"
        }
    ],
    "sg:phone":"+1 804 780 3140",
    "sg:postcode":"23219",
    "sg:province":"VA",
    "sg:tags":[
        "apartment"
    ],
    "sg:website":"www.shockoeproperties.com",
    "wof:name":"Shockoe Properties",
    "wof:placetype":"venue"
},
  "geometry": {"coordinates":[-77.433463,37.535096],"type":"Point"}
}