{
  "type": "Feature",
  "properties": {
    "iso:country":"US",
    "sg:address":"510 Roland Ave",
    "sg:city":"Elkton",
    "sg:classifiers":[
        {
            "category":"Farming",
            "subcategory":"Farm",
            "type":"Manufacturing & Wholesale Goods"
        }
    ],
    "sg:phone":"+1 540 298 9966",
    "sg:postcode":"22827",
    "sg:province":"VA",
    "sg:tags":[
        "crop",
        "general"
    ],
    "wof:name":"Old Mountain Farm LLC",
    "wof:placetype":"venue"
},
  "geometry": {"coordinates":[-78.628111,38.404352],"type":"Point"}
}