{
  "type": "Feature",
  "properties": {
    "iso:country":"US",
    "sg:address":"201 Loudoun St SW",
    "sg:city":"Leesburg",
    "sg:classifiers":[
        {
            "category":"Professional",
            "subcategory":"Lawyer & Legal Services",
            "type":"Services"
        }
    ],
    "sg:phone":"+1 703 777 4403",
    "sg:postcode":"20175",
    "sg:province":"VA",
    "wof:name":"Douglas H Westbrook",
    "wof:placetype":"venue"
},
  "geometry": {"coordinates":[-77.56795099999999,39.115021],"type":"Point"}
}