{
  "type": "Feature",
  "properties": {
    "addr:full":"341 Oyster Point Rd Newport News VA 23602",
    "addr:housenumber":"341",
    "addr:postcode":"23602",
    "addr:street":"Oyster Point Rd",
    "iso:country":"US",
    "sg:address":"341 Oyster Point Rd",
    "sg:city":"Newport News",
    "sg:classifiers":[
        {
            "category":"Autos & Motor Vehicles",
            "subcategory":"Fuel & Gas Station",
            "type":"Retail Goods"
        }
    ],
    "sg:phone":"+1 757 249 9692",
    "sg:postcode":"23602",
    "sg:province":"VA",
    "sg:tags":[
        "convenience",
        "station",
        "gasoline",
        "store"
    ],
    "wof:name":"Racetrac",
    "wof:placetype":"venue"
},
  "geometry": {"coordinates":[-76.50756199999999,37.105792],"type":"Point"}
}