{
  "type": "Feature",
  "properties": {
    "addr:full":"574 Blue Ridge Ave Bedford VA 24523",
    "addr:housenumber":"574",
    "addr:postcode":"24523",
    "addr:street":"Blue Ridge Ave",
    "iso:country":"US",
    "sg:address":"574 Blue Ridge Ave",
    "sg:city":"Bedford",
    "sg:classifiers":[
        {
            "category":"Shopping",
            "subcategory":"Clothing, Apparel, & Fashions",
            "type":"Retail Goods"
        }
    ],
    "sg:phone":"+1 540 586 3432",
    "sg:postcode":"24523",
    "sg:province":"VA",
    "sg:tags":[
        "athletic"
    ],
    "wof:name":"A & N Store",
    "wof:placetype":"venue"
},
  "geometry": {"coordinates":[-79.53307,37.335618],"type":"Point"}
}