{
  "type": "Feature",
  "properties": {
    "addr:full":"122 Forrest Rd Poquoson VA 23662",
    "addr:housenumber":"122",
    "addr:postcode":"23662",
    "addr:street":"Forrest Rd",
    "iso:country":"US",
    "sg:address":"122 Forrest Rd",
    "sg:city":"Poquoson",
    "sg:classifiers":[
        {
            "category":"Government",
            "subcategory":"Office",
            "type":"Public Place"
        }
    ],
    "sg:phone":"+1 757 868 3705",
    "sg:postcode":"23662",
    "sg:province":"VA",
    "sg:tags":[
        "national",
        "security"
    ],
    "wof:name":"Civil Air Patrol",
    "wof:placetype":"venue"
},
  "geometry": {"coordinates":[-76.368032,37.137442],"type":"Point"}
}