{
  "type": "Feature",
  "properties": {
    "addr:full":"305 Westover Dr Danville VA 24541",
    "addr:housenumber":"305",
    "addr:postcode":"24541",
    "addr:street":"Westover Dr",
    "iso:country":"US",
    "sg:address":"305 Westover Dr",
    "sg:city":"Danville",
    "sg:classifiers":[
        {
            "category":"Personal",
            "type":"Services"
        },
        {
            "category":"Personal",
            "subcategory":"Tattoo Parlor",
            "type":"Services"
        }
    ],
    "sg:phone":"+1 434 791 1073",
    "sg:postcode":"24541",
    "sg:province":"VA",
    "sg:tags":[
        "tattooing"
    ],
    "wof:name":"Harry's Tattoo Shop",
    "wof:placetype":"venue"
},
  "geometry": {"coordinates":[-79.430421,36.588023],"type":"Point"}
}