{
  "type": "Feature",
  "properties": {
    "addr:full":"501 Wolf St Narrows VA 24124",
    "addr:housenumber":"501",
    "addr:postcode":"24124",
    "addr:street":"Wolf St",
    "iso:country":"US",
    "sg:address":"501 Wolf St",
    "sg:city":"Narrows",
    "sg:classifiers":[
        {
            "category":"Education",
            "subcategory":"School",
            "type":"Public Place"
        }
    ],
    "sg:phone":"+1 540 726 2391",
    "sg:postcode":"24124",
    "sg:province":"VA",
    "wof:name":"Giles County School",
    "wof:placetype":"venue"
},
  "geometry": {"coordinates":[-80.81106699999999,37.327247],"type":"Point"}
}