{
  "type": "Feature",
  "properties": {
    "iso:country":"US",
    "sg:address":"1707 Belle View Blvd",
    "sg:city":"Alexandria",
    "sg:classifiers":[
        {
            "category":"Health Services",
            "subcategory":"Health Practitioner",
            "type":"Services"
        }
    ],
    "sg:phone":"+1 703 765 7595",
    "sg:postcode":"22307",
    "sg:province":"VA",
    "sg:tags":[
        "psychologist"
    ],
    "wof:name":"Mancusi Maria M PH D",
    "wof:placetype":"venue"
},
  "geometry": {"coordinates":[-77.062547,38.774981],"type":"Point"}
}