{
  "type": "Feature",
  "properties": {
    "addr:full":"101 S Independence Blvd Virginia Beach VA 23462",
    "addr:housenumber":"101",
    "addr:postcode":"23462",
    "addr:street":"S Independence Blvd",
    "iso:country":"US",
    "sg:address":"101 S Independence Blvd",
    "sg:city":"Virginia Beach",
    "sg:classifiers":[
        {
            "category":"Restaurant",
            "type":"Food & Drink"
        }
    ],
    "sg:menulink":"http://www.allmenus.com/va/virginia-beach/136197-tripps/menu/",
    "sg:phone":"+1 757 490 4517",
    "sg:postcode":"23462",
    "sg:province":"VA",
    "sg:tags":[
        "american"
    ],
    "wof:name":"Tripps",
    "wof:placetype":"venue"
},
  "geometry": {"coordinates":[-76.137535,36.839585],"type":"Point"}
}