{
  "type": "Feature",
  "properties": {
    "iso:country":"US",
    "sg:address":"218 N Boundary St",
    "sg:city":"Williamsburg",
    "sg:classifiers":[
        {
            "category":"Insurance",
            "subcategory":"Insurance Agent",
            "type":"Services"
        }
    ],
    "sg:phone":"+1 757 220 5431",
    "sg:postcode":"23185",
    "sg:province":"VA",
    "sg:tags":[
        "processing"
    ],
    "wof:name":"Intelligent Solutions Group",
    "wof:placetype":"venue"
},
  "geometry": {"coordinates":[-76.70765,37.272565],"type":"Point"}
}