{
  "type": "Feature",
  "properties": {
    "addr:full":"6603 Indian Trail Ct Alexandria VA 22310",
    "addr:housenumber":"6603",
    "addr:postcode":"22310",
    "addr:street":"Indian Trail Ct",
    "iso:country":"US",
    "sg:address":"6603 Indian Trail Ct",
    "sg:city":"Alexandria",
    "sg:classifiers":[
        {
            "category":"Building & Trades",
            "subcategory":"Cleaning & Sanitation",
            "type":"Services"
        }
    ],
    "sg:phone":"+1 703 838 9007",
    "sg:postcode":"22310",
    "sg:province":"VA",
    "sg:tags":[
        "butler",
        "maid"
    ],
    "wof:name":"Air Express",
    "wof:placetype":"venue"
},
  "geometry": {"coordinates":[-77.15376999999999,38.774176],"type":"Point"}
}