{
  "type": "Feature",
  "properties": {
    "iso:country":"US",
    "sg:address":"4768 Hermitage Rd",
    "sg:city":"Virginia Beach",
    "sg:classifiers":[
        {
            "category":"Wholesale",
            "subcategory":"Chemicals & Plastics",
            "type":"Manufacturing & Wholesale Goods"
        },
        {
            "category":"Manufacturing",
            "subcategory":"Chemicals & Compounds",
            "type":"Manufacturing & Wholesale Goods"
        }
    ],
    "sg:phone":"+1 757 460 3115",
    "sg:postcode":"23455",
    "sg:province":"VA",
    "sg:tags":[
        "agricultural",
        "mfg"
    ],
    "wof:name":"Livingston Group Inc",
    "wof:placetype":"venue"
},
  "geometry": {"coordinates":[-76.138486,36.895836],"type":"Point"}
}