{
  "type": "Feature",
  "properties": {
    "iso:country":"US",
    "sg:address":"13454 Sunrise Valley Drive Suite 210",
    "sg:city":"Herndon",
    "sg:classifiers":[
        {
            "category":"Professional",
            "subcategory":"Computer Services",
            "type":"Services"
        }
    ],
    "sg:phone":"+1 877 890 8910",
    "sg:postcode":"20176",
    "sg:province":"VA",
    "sg:website":"https://mapsindeed.com/",
    "wof:name":"Maps InDeed",
    "wof:placetype":"venue"
},
  "geometry": {"coordinates":[-77.51902699999999,39.101562],"type":"Point"}
}