{
  "type": "Feature",
  "properties": {
    "addr:full":"2756 Derry Dr Chesapeake VA 23323",
    "addr:housenumber":"2756",
    "addr:postcode":"23323",
    "addr:street":"Derry Dr",
    "iso:country":"US",
    "sg:address":"2756 Derry Dr",
    "sg:city":"Chesapeake",
    "sg:classifiers":[
        {
            "category":"Utilities",
            "subcategory":"Telephone",
            "type":"Services"
        }
    ],
    "sg:phone":"+1 757 676 4743",
    "sg:postcode":"23323",
    "sg:province":"VA",
    "sg:tags":[
        "communications"
    ],
    "wof:name":"Affordable Web Designs",
    "wof:placetype":"venue"
},
  "geometry": {"coordinates":[-76.33577,36.728558],"type":"Point"}
}