{
  "type": "Feature",
  "properties": {
    "addr:full":"36 Weems Ln Winchester VA 22601",
    "addr:housenumber":"36",
    "addr:postcode":"22601",
    "addr:street":"Weems Ln",
    "iso:country":"US",
    "sg:address":"36 Weems Ln",
    "sg:city":"Winchester",
    "sg:classifiers":[
        {
            "category":"Banks & Credit Unions",
            "subcategory":"Bank",
            "type":"Services"
        }
    ],
    "sg:phone":"+1 540 535 0955",
    "sg:postcode":"22601",
    "sg:province":"VA",
    "sg:tags":[
        "cashing",
        "check"
    ],
    "wof:name":"Check Cashed",
    "wof:placetype":"venue"
},
  "geometry": {"coordinates":[-78.176603,39.161458],"type":"Point"}
}