{
  "type": "Feature",
  "properties": {
    "iso:country":"US",
    "sg:address":"1201 Rivermont Ave",
    "sg:city":"Lynchburg",
    "sg:classifiers":[
        {
            "category":"Retail",
            "subcategory":"Car Wash",
            "type":"Services"
        }
    ],
    "sg:phone":"+1 434 948 9430",
    "sg:postcode":"24504",
    "sg:province":"VA",
    "sg:tags":[
        "polishing",
        "washing"
    ],
    "wof:name":"Touch Of Class Car Wash",
    "wof:placetype":"venue"
},
  "geometry": {"coordinates":[-79.15387,37.428661],"type":"Point"}
}