{
  "type": "Feature",
  "properties": {
    "iso:country":"US",
    "sg:address":"2908 Westcott St",
    "sg:city":"Falls Church",
    "sg:classifiers":[
        {
            "category":"Banks & Credit Unions",
            "subcategory":"Bank",
            "type":"Services"
        }
    ],
    "sg:phone":"+1 703 237 4184",
    "sg:postcode":"22042",
    "sg:province":"VA",
    "sg:tags":[
        "loan",
        "mortgage",
        "real estate"
    ],
    "wof:name":"Mortgage Concepts Inc",
    "wof:placetype":"venue"
},
  "geometry": {"coordinates":[-77.18505999999999,38.872747],"type":"Point"}
}