{
  "type": "Feature",
  "properties": {
    "addr:full":"631 Broad Street Rd Manakin Sabot VA 23103",
    "addr:housenumber":"631",
    "addr:postcode":"sabot;23103",
    "addr:street":"Broad Street Rd",
    "iso:country":"US",
    "sg:address":"631 Broad Street Rd",
    "sg:city":"Manakin Sabot",
    "sg:phone":"+1 804 784 6041",
    "sg:postcode":"23103",
    "sg:province":"VA",
    "sg:tags":[
        "gas"
    ],
    "wof:name":"Blue & White Propane",
    "wof:placetype":"venue"
},
  "geometry": {"coordinates":[-77.727808,37.681132],"type":"Point"}
}