{
  "type": "Feature",
  "properties": {
    "addr:full":"9534 Selby Pl Norfolk VA 23503",
    "addr:housenumber":"9534",
    "addr:postcode":"23503",
    "addr:street":"Selby Pl",
    "iso:country":"US",
    "sg:address":"9534 Selby Pl",
    "sg:city":"Norfolk",
    "sg:classifiers":[
        {
            "category":"Professional",
            "subcategory":"Computer Services",
            "type":"Services"
        }
    ],
    "sg:phone":"+1 757 587 0427",
    "sg:postcode":"23503",
    "sg:province":"VA",
    "sg:tags":[
        "related"
    ],
    "wof:name":"Product Data Service",
    "wof:placetype":"venue"
},
  "geometry": {"coordinates":[-76.252174,36.950348],"type":"Point"}
}