{
  "type": "Feature",
  "properties": {
    "iso:country":"US",
    "sg:address":"968 S Spigel Dr",
    "sg:city":"Virginia Beach",
    "sg:classifiers":[
        {
            "category":"Health Services",
            "subcategory":"Doctor",
            "type":"Services"
        }
    ],
    "sg:phone":"+1 757 499 4977",
    "sg:postcode":"23454",
    "sg:province":"VA",
    "sg:tags":[
        "medical"
    ],
    "wof:name":"Vianmar Pascual MD",
    "wof:placetype":"venue"
},
  "geometry": {"coordinates":[-76.063079,36.865449],"type":"Point"}
}