{
  "type": "Feature",
  "properties": {
    "iso:country":"US",
    "sg:address":"8130 Old Keene Mill Rd",
    "sg:city":"Springfield",
    "sg:classifiers":[
        {
            "category":"Home & Garden",
            "subcategory":"Building Materials",
            "type":"Retail Goods"
        }
    ],
    "sg:phone":"+1 703 912 9770",
    "sg:postcode":"22152",
    "sg:province":"VA",
    "wof:name":"Auto Glass America",
    "wof:placetype":"venue"
},
  "geometry": {"coordinates":[-77.226742,38.780535],"type":"Point"}
}