{
  "type": "Feature",
  "properties": {
    "addr:full":"607 Herndon Pkwy Herndon VA 20170",
    "addr:housenumber":"607",
    "addr:postcode":"20170",
    "addr:street":"Herndon Pkwy",
    "iso:country":"US",
    "sg:address":"607 Herndon Pkwy",
    "sg:city":"Herndon",
    "sg:classifiers":[
        {
            "category":"Professional",
            "subcategory":"Employment Agencies",
            "type":"Services"
        }
    ],
    "sg:phone":"+1 703 463 9011",
    "sg:postcode":"20170",
    "sg:province":"VA",
    "sg:tags":[
        "temporary"
    ],
    "sg:website":"http://washingtondc.citysearch.com/profile/external/34756000/herndon_va/manpower_professional.html?publisher=yellowpages&reference_id=1&placement=ypwebsitemip",
    "wof:name":"Manpower Professional",
    "wof:placetype":"venue"
},
  "geometry": {"coordinates":[-77.386217,38.95544],"type":"Point"}
}