{
  "type": "Feature",
  "properties": {
    "addr:full":"1567 Bumpass Rd Bumpass VA 23024",
    "addr:housenumber":"1567",
    "addr:postcode":"23024",
    "addr:street":"Bumpass Rd",
    "iso:country":"US",
    "sg:address":"1567 Bumpass Rd",
    "sg:city":"Bumpass",
    "sg:classifiers":[
        {
            "category":"Organizations",
            "subcategory":"Religious Organization",
            "type":"Services"
        }
    ],
    "sg:phone":"+1 540 872 7200",
    "sg:postcode":"23024",
    "sg:province":"VA",
    "sg:tags":[
        "church"
    ],
    "wof:name":"St Thomas Baptist Church",
    "wof:placetype":"venue"
},
  "geometry": {"coordinates":[-77.731414,37.964741],"type":"Point"}
}