{
  "type": "Feature",
  "properties": {
    "addr:full":"5801 Harbour View Blvd Suffolk VA 23435",
    "addr:housenumber":"5801",
    "addr:postcode":"23435",
    "addr:street":"Harbour View Blvd",
    "iso:country":"US",
    "sg:address":"5801 Harbour View Blvd",
    "sg:city":"Suffolk",
    "sg:classifiers":[
        {
            "category":"Real Estate",
            "subcategory":"Developer",
            "type":"Services"
        }
    ],
    "sg:phone":"+1 757 483 5888",
    "sg:postcode":"23435",
    "sg:province":"VA",
    "wof:name":"Tri City Development",
    "wof:placetype":"venue"
},
  "geometry": {"coordinates":[-76.44356999999999,36.86709],"type":"Point"}
}