{
  "type": "Feature",
  "properties": {
    "iso:country":"US",
    "sg:address":"2643 Landview Cir",
    "sg:city":"Virginia Beach",
    "sg:classifiers":[
        {
            "category":"Professional",
            "subcategory":"Detective & Security Services",
            "type":"Services"
        }
    ],
    "sg:phone":"+1 757 412 0574",
    "sg:postcode":"23454",
    "sg:province":"VA",
    "sg:tags":[
        "private",
        "investigator"
    ],
    "wof:name":"Henry Maurer",
    "wof:placetype":"venue"
},
  "geometry": {"coordinates":[-76.057782,36.892614],"type":"Point"}
}