{
  "type": "Feature",
  "properties": {
    "addr:full":"14950 Washington St Suite 100 Haymarket VA 20169",
    "addr:housenumber":"14950",
    "addr:postcode":"20169",
    "addr:street":"Washington St Suite 100",
    "iso:country":"US",
    "sg:address":"14950 Washington St Suite 100",
    "sg:city":"Haymarket",
    "sg:classifiers":[
        {
            "category":"Food & Beverages",
            "subcategory":"Candy",
            "type":"Retail Goods"
        },
        {
            "category":"Coffee & Tea",
            "type":"Food & Drink"
        }
    ],
    "sg:phone":"+1 703 754 6300",
    "sg:postcode":"20169",
    "sg:province":"VA",
    "sg:tags":[
        "dessert"
    ],
    "sg:website":"www.cupcakeheavenandcafe.com",
    "wof:name":"Cupcake Heaven And Cafe",
    "wof:placetype":"venue"
},
  "geometry": {"coordinates":[-77.635817,38.812244],"type":"Point"}
}