{
  "type": "Feature",
  "properties": {
    "iso:country":"US",
    "sg:address":"201 Campbell Ave SW",
    "sg:city":"Roanoke",
    "sg:classifiers":[
        {
            "category":"Education",
            "subcategory":"Library",
            "type":"Public Place"
        }
    ],
    "sg:phone":"+1 540 981 3279",
    "sg:postcode":"24011",
    "sg:province":"VA",
    "sg:tags":[
        "special",
        "interest"
    ],
    "sg:website":"www.roanoke.com",
    "wof:name":"Times World Corp Library",
    "wof:placetype":"venue"
},
  "geometry": {"coordinates":[-79.94561299999999,37.271538],"type":"Point"}
}