{
  "type": "Feature",
  "properties": {
    "iso:country":"US",
    "sg:address":"1110 Pinecrest Ave",
    "sg:city":"Bedford",
    "sg:classifiers":[
        {
            "category":"Building & Trades",
            "subcategory":"Construction",
            "type":"Services"
        }
    ],
    "sg:phone":"+1 540 586 0683",
    "sg:postcode":"24523",
    "sg:province":"VA",
    "sg:tags":[
        "house"
    ],
    "wof:name":"Billy T Hackworth",
    "wof:placetype":"venue"
},
  "geometry": {"coordinates":[-79.509511,37.327435],"type":"Point"}
}