{
  "type": "Feature",
  "properties": {
    "iso:country":"US",
    "sg:address":"8210 Crossbrook Ct",
    "sg:city":"Lorton",
    "sg:classifiers":[
        {
            "category":"Retail",
            "subcategory":"Car Wash",
            "type":"Services"
        }
    ],
    "sg:phone":"+1 703 690 6970",
    "sg:postcode":"22079",
    "sg:province":"VA",
    "sg:tags":[
        "carwash"
    ],
    "wof:name":"Derecks Detailing Inc",
    "wof:placetype":"venue"
},
  "geometry": {"coordinates":[-77.22910400000001,38.705793],"type":"Point"}
}