{
  "type": "Feature",
  "properties": {
    "addr:full":"3001 Silina Dr Virginia Beach VA 23452",
    "addr:housenumber":"3001",
    "addr:postcode":"23452",
    "addr:street":"Silina Dr",
    "iso:country":"US",
    "sg:address":"3001 Silina Dr",
    "sg:city":"Virginia Beach",
    "sg:classifiers":[
        {
            "category":"Retail",
            "subcategory":"Laundry & Dry Cleaning",
            "type":"Services"
        }
    ],
    "sg:phone":"+1 757 486 8488",
    "sg:postcode":"23452",
    "sg:province":"VA",
    "sg:tags":[
        "cleaners"
    ],
    "wof:name":"Bon Air Cleaners",
    "wof:placetype":"venue"
},
  "geometry": {"coordinates":[-76.07859500000001,36.827884],"type":"Point"}
}