{
  "type": "Feature",
  "properties": {
    "addr:full":"2821 N Valley Pike Harrisonburg VA 22802",
    "addr:housenumber":"2821",
    "addr:postcode":"22802",
    "addr:street":"N Valley Pike",
    "iso:country":"US",
    "sg:address":"2821 N Valley Pike",
    "sg:city":"Harrisonburg",
    "sg:classifiers":[
        {
            "category":"Autos & Motor Vehicles",
            "subcategory":"Automobile Sales",
            "type":"Retail Goods"
        }
    ],
    "sg:phone":"+1 540 434 3200",
    "sg:postcode":"22802",
    "sg:province":"VA",
    "sg:tags":[
        "used"
    ],
    "wof:name":"D & M Automotive Inc",
    "wof:placetype":"venue"
},
  "geometry": {"coordinates":[-78.815563,38.483552],"type":"Point"}
}