{
  "type": "Feature",
  "properties": {
    "iso:country":"US",
    "sg:address":"2708 Moons Rd",
    "sg:city":"Long Island",
    "sg:phone":"+1 434 324 4127",
    "sg:postcode":"24569",
    "sg:province":"VA",
    "sg:tags":[
        "farm",
        "tobacco"
    ],
    "wof:name":"Ray Moon",
    "wof:placetype":"venue"
},
  "geometry": {"coordinates":[-79.178527,37.043126],"type":"Point"}
}