{
  "type": "Feature",
  "properties": {
    "iso:country":"US",
    "sg:address":"1636 Vance Tank Rd",
    "sg:city":"Bristol",
    "sg:classifiers":[
        {
            "category":"Building & Trades",
            "subcategory":"Construction",
            "type":"Services"
        }
    ],
    "sg:phone":"+1 423 878 7067",
    "sg:postcode":"37620",
    "sg:province":"VA",
    "sg:tags":[
        "house"
    ],
    "wof:name":"Deb Builders",
    "wof:placetype":"venue"
},
  "geometry": {"coordinates":[-82.20818300000001,36.528388],"type":"Point"}
}