{
  "type": "Feature",
  "properties": {
    "iso:country":"US",
    "sg:address":"1794 Rocky Mountain Rd",
    "sg:city":"Forest",
    "sg:classifiers":[
        {
            "category":"Wholesale",
            "subcategory":"Office Equipment",
            "type":"Manufacturing & Wholesale Goods"
        }
    ],
    "sg:phone":"+1 434 384 7040",
    "sg:postcode":"24551",
    "sg:province":"VA",
    "sg:tags":[
        "credit"
    ],
    "wof:name":"ABA Merchant Svc",
    "wof:placetype":"venue"
},
  "geometry": {"coordinates":[-79.328884,37.442367],"type":"Point"}
}