{
  "type": "Feature",
  "properties": {
    "addr:full":"10296 Portsmouth Rd Manassas VA 20109",
    "addr:housenumber":"10296",
    "addr:postcode":"20109",
    "addr:street":"Portsmouth Rd",
    "iso:country":"US",
    "sg:address":"10296 Portsmouth Rd",
    "sg:city":"Manassas",
    "sg:classifiers":[
        {
            "category":"Social Services",
            "subcategory":"Child Care",
            "type":"Services"
        }
    ],
    "sg:phone":"+1 703 393 6677",
    "sg:postcode":"20109",
    "sg:province":"VA",
    "wof:name":"YMCA",
    "wof:placetype":"venue"
},
  "geometry": {"coordinates":[-77.502493,38.780333],"type":"Point"}
}