{
  "type": "Feature",
  "properties": {
    "iso:country":"US",
    "sg:address":"2420 14th St N",
    "sg:city":"Arlington",
    "sg:classifiers":[
        {
            "category":"Personal",
            "type":"Services"
        }
    ],
    "sg:phone":"+1 703 527 1033",
    "sg:postcode":"22201",
    "sg:province":"VA",
    "sg:tags":[
        "information",
        "consumer"
    ],
    "sg:website":"http://www.forsytheglobal.com",
    "wof:name":"Forsythe Global",
    "wof:placetype":"venue"
},
  "geometry": {"coordinates":[-77.08763999999999,38.889153],"type":"Point"}
}