{
  "type": "Feature",
  "properties": {
    "iso:country":"US",
    "sg:address":"8281 Centreville Rd",
    "sg:city":"Manassas",
    "sg:classifiers":[
        {
            "category":"Building & Trades",
            "subcategory":"Equipment Rental",
            "type":"Services"
        }
    ],
    "sg:phone":"+1 703 368 1151",
    "sg:postcode":"20111",
    "sg:province":"VA",
    "wof:name":"Prime Industrial",
    "wof:placetype":"venue"
},
  "geometry": {"coordinates":[-77.45156299999999,38.775485],"type":"Point"}
}