{
  "type": "Feature",
  "properties": {
    "iso:country":"US",
    "sg:address":"1013 E Bayview Blvd",
    "sg:city":"Norfolk",
    "sg:classifiers":[
        {
            "category":"Home & Garden",
            "subcategory":"Hardware",
            "type":"Retail Goods"
        }
    ],
    "sg:phone":"+1 757 583 1484",
    "sg:postcode":"23503",
    "sg:province":"VA",
    "wof:name":"Best Value Hardware",
    "wof:placetype":"venue"
},
  "geometry": {"coordinates":[-76.24414,36.933755],"type":"Point"}
}