{
  "type": "Feature",
  "properties": {
    "addr:full":"2401 Ivy Rd Charlottesville VA 22903",
    "addr:housenumber":"2401",
    "addr:postcode":"22903",
    "addr:street":"Ivy Rd",
    "iso:country":"US",
    "sg:address":"2401 Ivy Rd",
    "sg:city":"Charlottesville",
    "sg:classifiers":[
        {
            "category":"Coffee & Tea",
            "type":"Food & Drink"
        }
    ],
    "sg:phone":"+1 434 977 0222",
    "sg:postcode":"22903",
    "sg:province":"VA",
    "sg:website":"www.mudhouse.com",
    "wof:name":"Mudhouse Bellair",
    "wof:placetype":"venue"
},
  "geometry": {"coordinates":[-78.527241,38.050516],"type":"Point"}
}