{
  "type": "Feature",
  "properties": {
    "iso:country":"US",
    "sg:address":"13510 Westfield Rd",
    "sg:city":"Midlothian",
    "sg:classifiers":[
        {
            "category":"Organizations",
            "subcategory":"Community Association",
            "type":"Services"
        }
    ],
    "sg:phone":"+1 804 379 0735",
    "sg:postcode":"23113",
    "sg:province":"VA",
    "sg:tags":[
        "club"
    ],
    "wof:name":"Masonic Lodge",
    "wof:placetype":"venue"
},
  "geometry": {"coordinates":[-77.649218,37.5062],"type":"Point"}
}