{
  "type": "Feature",
  "properties": {
    "iso:country":"US",
    "sg:address":"111 S Main St",
    "sg:city":"Hopewell",
    "sg:classifiers":[
        {
            "category":"Manufacturing",
            "subcategory":"Signs",
            "type":"Manufacturing & Wholesale Goods"
        }
    ],
    "sg:phone":"+1 804 541 8545",
    "sg:postcode":"23860",
    "sg:province":"VA",
    "sg:tags":[
        "specialty",
        "mfg"
    ],
    "wof:name":"Imperial Sign Co",
    "wof:placetype":"venue"
},
  "geometry": {"coordinates":[-77.286962,37.301148],"type":"Point"}
}