{
  "type": "Feature",
  "properties": {
    "iso:country":"US",
    "sg:address":"5317 Lee Hwy",
    "sg:city":"Arlington",
    "sg:classifiers":[
        {
            "category":"Real Estate",
            "subcategory":"Real Estate Services",
            "type":"Services"
        }
    ],
    "sg:phone":"+1 703 538 1100",
    "sg:postcode":"22207",
    "sg:province":"VA",
    "wof:name":"Provincial Real Estate",
    "wof:placetype":"venue"
},
  "geometry": {"coordinates":[-77.135498,38.896301],"type":"Point"}
}