{
  "type": "Feature",
  "properties": {
    "iso:country":"US",
    "sg:address":"1115 Moneta Rd",
    "sg:city":"Bedford",
    "sg:classifiers":[
        {
            "category":"Retail",
            "subcategory":"Repair Shop",
            "type":"Services"
        }
    ],
    "sg:phone":"+1 540 587 6911",
    "sg:postcode":"24523",
    "sg:province":"VA",
    "sg:tags":[
        "related"
    ],
    "wof:name":"Autocraft & Repair",
    "wof:placetype":"venue"
},
  "geometry": {"coordinates":[-79.53810199999999,37.314912],"type":"Point"}
}