{
  "type": "Feature",
  "properties": {
    "addr:full":"339 Adwood Ct Hampton VA 23605",
    "addr:housenumber":"339",
    "addr:postcode":"23605",
    "addr:street":"Adwood Ct",
    "iso:country":"US",
    "sg:address":"339 Adwood Ct",
    "sg:city":"Hampton",
    "sg:classifiers":[
        {
            "category":"Building & Trades",
            "subcategory":"Construction",
            "type":"Services"
        }
    ],
    "sg:phone":"+1 757 825 6044",
    "sg:postcode":"23605",
    "sg:province":"VA",
    "sg:tags":[
        "painter"
    ],
    "wof:name":"Scope Painting Co Interior",
    "wof:placetype":"venue"
},
  "geometry": {"coordinates":[-76.436694,37.027968],"type":"Point"}
}