{
  "type": "Feature",
  "properties": {
    "iso:country":"US",
    "sg:address":"2639 N Rockingham St",
    "sg:city":"Arlington",
    "sg:classifiers":[
        {
            "category":"Freight",
            "type":"Transportation"
        }
    ],
    "sg:phone":"+1 703 241 1001",
    "sg:postcode":"22207",
    "sg:province":"VA",
    "sg:tags":[
        "mover"
    ],
    "wof:name":"Big Green Moving",
    "wof:placetype":"venue"
},
  "geometry": {"coordinates":[-77.15617399999999,38.89601],"type":"Point"}
}