{
  "type": "Feature",
  "properties": {
    "addr:full":"1706 Vaughn Summit Rd Luray VA 22835",
    "addr:housenumber":"1706",
    "addr:postcode":"22835",
    "addr:street":"Vaughn Summit Rd",
    "iso:country":"US",
    "sg:address":"1706 Vaughn Summit Rd",
    "sg:city":"Luray",
    "sg:classifiers":[
        {
            "category":"Retail",
            "subcategory":"Auto Repair",
            "type":"Services"
        }
    ],
    "sg:phone":"+1 540 743 3600",
    "sg:postcode":"22835",
    "sg:province":"VA",
    "sg:tags":[
        "general"
    ],
    "wof:name":"Steves Auto",
    "wof:placetype":"venue"
},
  "geometry": {"coordinates":[-78.406356,38.718061],"type":"Point"}
}