{
  "type": "Feature",
  "properties": {
    "iso:country":"US",
    "sg:address":"620 Shenandoah Ave NW",
    "sg:city":"Roanoke",
    "sg:classifiers":[
        {
            "category":"Social Services",
            "type":"Services"
        }
    ],
    "sg:phone":"+1 540 344 1787",
    "sg:postcode":"24016",
    "sg:province":"VA",
    "sg:tags":[
        "organization",
        "welfare"
    ],
    "wof:name":"Total Action Against Poverty",
    "wof:placetype":"venue"
},
  "geometry": {"coordinates":[-79.95195699999999,37.275269],"type":"Point"}
}