{
  "type": "Feature",
  "properties": {
    "addr:full":"4300 Ridgewood Center Dr Woodbridge VA 22192",
    "addr:housenumber":"4300",
    "addr:postcode":"22192",
    "addr:street":"Ridgewood Center Dr",
    "iso:country":"US",
    "sg:address":"4300 Ridgewood Center Dr",
    "sg:city":"Woodbridge",
    "sg:classifiers":[
        {
            "category":"Social Services",
            "type":"Services"
        }
    ],
    "sg:phone":"+1 703 580 7210",
    "sg:postcode":"22192",
    "sg:province":"VA",
    "sg:tags":[
        "counseling"
    ],
    "wof:name":"Family Teamwork Inc",
    "wof:placetype":"venue"
},
  "geometry": {"coordinates":[-77.34066799999999,38.674051],"type":"Point"}
}