{
  "type": "Feature",
  "properties": {
    "iso:country":"US",
    "sg:address":"6948 Forest Hill Ave",
    "sg:city":"Richmond",
    "sg:classifiers":[
        {
            "category":"Insurance",
            "subcategory":"Insurance Agent",
            "type":"Services"
        }
    ],
    "sg:phone":"+1 804 323 6767",
    "sg:postcode":"23225",
    "sg:province":"VA",
    "wof:name":"Graziano & Assoc",
    "wof:placetype":"venue"
},
  "geometry": {"coordinates":[-77.522943,37.538035],"type":"Point"}
}