{
  "type": "Feature",
  "properties": {
    "iso:country":"US",
    "sg:address":"103 S College Ave",
    "sg:city":"Salem",
    "sg:classifiers":[
        {
            "category":"Building & Trades",
            "subcategory":"Construction",
            "type":"Services"
        }
    ],
    "sg:phone":"+1 540 375 3833",
    "sg:postcode":"24153",
    "sg:province":"VA",
    "sg:tags":[
        "house"
    ],
    "wof:name":"Todd Lewis Construction Inc",
    "wof:placetype":"venue"
},
  "geometry": {"coordinates":[-80.05433600000001,37.29202],"type":"Point"}
}