{
  "type": "Feature",
  "properties": {
    "addr:full":"188 Bethany Church Rd Bumpass VA 23024",
    "addr:housenumber":"188",
    "addr:postcode":"23024",
    "addr:street":"Bethany Church Rd",
    "iso:country":"US",
    "sg:address":"188 Bethany Church Rd",
    "sg:city":"Bumpass",
    "sg:classifiers":[
        {
            "category":"Banks & Credit Unions",
            "subcategory":"Bank",
            "type":"Services"
        }
    ],
    "sg:phone":"+1 540 872 2446",
    "sg:postcode":"23024",
    "sg:province":"VA",
    "sg:tags":[
        "consultant",
        "financing",
        "short",
        "institution",
        "business"
    ],
    "wof:name":"Capitol City Capital Inc",
    "wof:placetype":"venue"
},
  "geometry": {"coordinates":[-77.78704399999999,37.869159],"type":"Point"}
}