{
  "type": "Feature",
  "properties": {
    "iso:country":"US",
    "sg:address":"4033 Woodland Dr",
    "sg:city":"Chesapeake",
    "sg:classifiers":[
        {
            "category":"Professional",
            "subcategory":"Secretarial Services",
            "type":"Services"
        }
    ],
    "sg:phone":"+1 757 488 5037",
    "sg:postcode":"23321",
    "sg:province":"VA",
    "sg:tags":[
        "processing",
        "word"
    ],
    "wof:name":"D P & M Desktop Svc",
    "wof:placetype":"venue"
},
  "geometry": {"coordinates":[-76.41008600000001,36.805122],"type":"Point"}
}