{
  "type": "Feature",
  "properties": {
    "addr:full":"5905 Pratt St Alexandria VA 22310",
    "addr:housenumber":"5905",
    "addr:postcode":"22310",
    "addr:street":"Pratt St",
    "iso:country":"US",
    "sg:address":"5905 Pratt St",
    "sg:city":"Alexandria",
    "sg:classifiers":[
        {
            "category":"Retail",
            "subcategory":"Repair Shop",
            "type":"Services"
        }
    ],
    "sg:phone":"+1 800 455 5505",
    "sg:postcode":"22310",
    "sg:province":"VA",
    "sg:tags":[
        "electrical"
    ],
    "wof:name":"Trust Appliance Repair Inc",
    "wof:placetype":"venue"
},
  "geometry": {"coordinates":[-77.133448,38.78913],"type":"Point"}
}