{
  "type": "Feature",
  "properties": {
    "iso:country":"US",
    "sg:address":"1248 Martha Custis Dr",
    "sg:city":"Alexandria",
    "sg:classifiers":[
        {
            "category":"Professional",
            "type":"Services"
        }
    ],
    "sg:phone":"+1 703 575 9051",
    "sg:postcode":"22302",
    "sg:province":"VA",
    "wof:name":"Denisin Kirill",
    "wof:placetype":"venue"
},
  "geometry": {"coordinates":[-77.082364,38.841358],"type":"Point"}
}