{
  "type": "Feature",
  "properties": {
    "addr:full":"3703 Moss Brooke Ct Fairfax VA 22031",
    "addr:postcode":"3703;22031",
    "addr:street":"Brooke Ct",
    "iso:country":"US",
    "sg:address":"3703 Moss Brooke Ct",
    "sg:city":"Fairfax",
    "sg:classifiers":[
        {
            "category":"Professional",
            "subcategory":"Management & Consulting",
            "type":"Services"
        }
    ],
    "sg:phone":"+1 703 426 4806",
    "sg:postcode":"22031",
    "sg:province":"VA",
    "wof:name":"David Breen",
    "wof:placetype":"venue"
},
  "geometry": {"coordinates":[-77.253866,38.844421],"type":"Point"}
}