{
  "type": "Feature",
  "properties": {
    "addr:full":"3030 Armistead Rd Nathalie VA 24577",
    "addr:housenumber":"3030",
    "addr:postcode":"24577",
    "addr:street":"Armistead Rd",
    "iso:country":"US",
    "sg:address":"3030 Armistead Rd",
    "sg:city":"Nathalie",
    "sg:classifiers":[
        {
            "category":"Manufacturing",
            "subcategory":"Lumber",
            "type":"Manufacturing & Wholesale Goods"
        }
    ],
    "sg:phone":"+1 434 349 1999",
    "sg:postcode":"24577",
    "sg:province":"VA",
    "sg:tags":[
        "company",
        "logging"
    ],
    "wof:name":"James David Crews Logging",
    "wof:placetype":"venue"
},
  "geometry": {"coordinates":[-78.90736099999999,36.936509],"type":"Point"}
}