{
  "type": "Feature",
  "properties": {
    "iso:country":"US",
    "sg:address":"400 N 1st St",
    "sg:city":"Richmond",
    "sg:classifiers":[
        {
            "category":"Personal",
            "subcategory":"Beauty Salon",
            "type":"Services"
        }
    ],
    "sg:phone":"+1 804 780 1134",
    "sg:postcode":"23219",
    "sg:province":"VA",
    "sg:website":"www.supremehair.com",
    "wof:name":"Supreme Hairstyling Lounge",
    "wof:placetype":"venue"
},
  "geometry": {"coordinates":[-77.43942199999999,37.546821],"type":"Point"}
}