{
  "type": "Feature",
  "properties": {
    "addr:full":"7398 Ward Park Ln Springfield VA 22153",
    "addr:housenumber":"7398",
    "addr:postcode":"22153",
    "addr:street":"Ward Park Ln",
    "iso:country":"US",
    "sg:address":"7398 Ward Park Ln",
    "sg:city":"Springfield",
    "sg:classifiers":[
        {
            "category":"Wholesale",
            "subcategory":"Stationery",
            "type":"Manufacturing & Wholesale Goods"
        }
    ],
    "sg:phone":"+1 703 644 5550",
    "sg:postcode":"22153",
    "sg:province":"VA",
    "sg:tags":[
        "box",
        "fiber"
    ],
    "wof:name":"Atlas Alexandria Packaging",
    "wof:placetype":"venue"
},
  "geometry": {"coordinates":[-77.20060599999999,38.744208],"type":"Point"}
}