{
  "type": "Feature",
  "properties": {
    "addr:full":"4291 Holland Rd Virginia Beach VA 23452",
    "addr:housenumber":"4291",
    "addr:postcode":"23452",
    "addr:street":"Holland Rd",
    "iso:country":"US",
    "sg:address":"4291 Holland Rd",
    "sg:city":"Virginia Beach",
    "sg:classifiers":[
        {
            "category":"Restaurant",
            "type":"Food & Drink"
        }
    ],
    "sg:phone":"+1 757 467 8225",
    "sg:postcode":"23452",
    "sg:province":"VA",
    "sg:tags":[
        "eating"
    ],
    "wof:name":"China Wong",
    "wof:placetype":"venue"
},
  "geometry": {"coordinates":[-76.12231199999999,36.820387],"type":"Point"}
}