{
  "type": "Feature",
  "properties": {
    "addr:full":"5208 Rock Harbour Rd Midlothian VA 23112",
    "addr:housenumber":"5208",
    "addr:postcode":"23112",
    "addr:street":"Rock Harbour Rd",
    "iso:country":"US",
    "sg:address":"5208 Rock Harbour Rd",
    "sg:city":"Midlothian",
    "sg:classifiers":[
        {
            "category":"Professional",
            "subcategory":"Management & Consulting",
            "type":"Services"
        }
    ],
    "sg:phone":"+1 804 739 0454",
    "sg:postcode":"23112",
    "sg:province":"VA",
    "wof:name":"Cost Management Inc",
    "wof:placetype":"venue"
},
  "geometry": {"coordinates":[-77.67931299999999,37.428141],"type":"Point"}
}