{
  "type": "Feature",
  "properties": {
    "addr:full":"201 Hemlock St Glade Spring VA 24340",
    "addr:housenumber":"201",
    "addr:postcode":"24340",
    "addr:street":"Hemlock St",
    "iso:country":"US",
    "sg:address":"201 Hemlock St",
    "sg:city":"Glade Spring",
    "sg:classifiers":[
        {
            "category":"Building & Trades",
            "subcategory":"Plumbing",
            "type":"Services"
        }
    ],
    "sg:phone":"+1 276 429 2391",
    "sg:postcode":"24340",
    "sg:province":"VA",
    "sg:tags":[
        "septic"
    ],
    "wof:name":"Shreeves Septic Tank Svc",
    "wof:placetype":"venue"
},
  "geometry": {"coordinates":[-81.773867,36.791651],"type":"Point"}
}