{
  "type": "Feature",
  "properties": {
    "addr:full":"129 Baker Farm Dr Hampton VA 23666",
    "addr:housenumber":"129",
    "addr:postcode":"23666",
    "addr:street":"Baker Farm Dr",
    "iso:country":"US",
    "sg:address":"129 Baker Farm Dr",
    "sg:city":"Hampton",
    "sg:classifiers":[
        {
            "category":"Personal",
            "subcategory":"Beauty Salon",
            "type":"Services"
        }
    ],
    "sg:phone":"+1 757 826 0111",
    "sg:postcode":"23666",
    "sg:province":"VA",
    "sg:tags":[
        "shop"
    ],
    "wof:name":"Starcuts Salon LLC",
    "wof:placetype":"venue"
},
  "geometry": {"coordinates":[-76.408343,37.089043],"type":"Point"}
}