{
  "type": "Feature",
  "properties": {
    "addr:full":"2150 Anderson Hwy Powhatan VA 23139",
    "addr:housenumber":"2150",
    "addr:postcode":"23139",
    "addr:street":"Anderson Hwy",
    "iso:country":"US",
    "sg:address":"2150 Anderson Hwy",
    "sg:city":"Powhatan",
    "sg:classifiers":[
        {
            "category":"Building & Trades",
            "subcategory":"Equipment Rental",
            "type":"Services"
        }
    ],
    "sg:phone":"+1 804 598 2798",
    "sg:postcode":"23139",
    "sg:province":"VA",
    "sg:tags":[
        "yard"
    ],
    "wof:name":"Powhatan Rental Ctr",
    "wof:placetype":"venue"
},
  "geometry": {"coordinates":[-77.792796,37.514824],"type":"Point"}
}