{
  "type": "Feature",
  "properties": {
    "addr:full":"15111 Farm Creek Dr Woodbridge VA 22191",
    "addr:housenumber":"15111",
    "addr:postcode":"22191",
    "addr:street":"Farm Creek Dr",
    "iso:country":"US",
    "sg:address":"15111 Farm Creek Dr",
    "sg:city":"Woodbridge",
    "sg:classifiers":[
        {
            "category":"Professional",
            "type":"Services"
        },
        {
            "category":"Personal",
            "type":"Services"
        }
    ],
    "sg:phone":"+1 866 761 6402",
    "sg:postcode":"22191",
    "sg:province":"VA",
    "sg:tags":[
        "industrial",
        "organ",
        "material",
        "storage",
        "movers-commercial",
        "full",
        "moving",
        "services-labor",
        "mover",
        "piano"
    ],
    "sg:website":"https://ecom-bekins-com.netsolads.com/householdmove/action/autoSelectAgent.do?leadSourceCode=35&_nsag=31476",
    "wof:name":"Bekins A-1 Movers, Inc.",
    "wof:placetype":"venue"
},
  "geometry": {"coordinates":[-77.25465,38.622909],"type":"Point"}
}