{
  "type": "Feature",
  "properties": {
    "addr:full":"6023 Fort Hunt Rd Alexandria VA 22307",
    "addr:housenumber":"6023",
    "addr:postcode":"22307",
    "addr:street":"Fort Hunt Rd",
    "iso:country":"US",
    "sg:address":"6023 Fort Hunt Rd",
    "sg:city":"Alexandria",
    "sg:classifiers":[
        {
            "category":"Shopping",
            "subcategory":"Bicycles & Sporting Goods",
            "type":"Retail Goods"
        }
    ],
    "sg:phone":"+1 703 329 1055",
    "sg:postcode":"22307",
    "sg:province":"VA",
    "sg:tags":[
        "equipment",
        "golf"
    ],
    "wof:name":"Belle Haven Golf Shop Inc",
    "wof:placetype":"venue"
},
  "geometry": {"coordinates":[-77.061092,38.785451],"type":"Point"}
}