{
  "type": "Feature",
  "properties": {
    "addr:full":"2500 Jefferson Ave Newport News VA 23607",
    "addr:housenumber":"2500",
    "addr:postcode":"23607",
    "addr:street":"Jefferson Ave",
    "iso:country":"US",
    "sg:address":"2500 Jefferson Ave",
    "sg:city":"Newport News",
    "sg:classifiers":[
        {
            "category":"Retail",
            "subcategory":"Laundry & Dry Cleaning",
            "type":"Services"
        }
    ],
    "sg:phone":"+1 757 247 0991",
    "sg:postcode":"23607",
    "sg:province":"VA",
    "wof:name":"Andrews Tailor Shop",
    "wof:placetype":"venue"
},
  "geometry": {"coordinates":[-76.421488,36.982079],"type":"Point"}
}