{
  "type": "Feature",
  "properties": {
    "iso:country":"US",
    "sg:address":"50 Green Valley Rd",
    "sg:city":"Bristol",
    "sg:classifiers":[
        {
            "category":"Retail",
            "subcategory":"Repair Shop",
            "type":"Services"
        }
    ],
    "sg:phone":"+1 276 466 8744",
    "sg:postcode":"24202",
    "sg:province":"VA",
    "wof:name":"Preferred Doors Inc",
    "wof:placetype":"venue"
},
  "geometry": {"coordinates":[-82.137044,36.626337],"type":"Point"}
}