{
  "type": "Feature",
  "properties": {
    "iso:country":"US",
    "sg:address":"8016 Kidd St",
    "sg:city":"Alexandria",
    "sg:classifiers":[
        {
            "category":"Building & Trades",
            "subcategory":"Construction",
            "type":"Services"
        }
    ],
    "sg:phone":"+1 703 303 9040",
    "sg:postcode":"22309",
    "sg:province":"VA",
    "sg:tags":[
        "house"
    ],
    "wof:name":"Dl Home Remodeling",
    "wof:placetype":"venue"
},
  "geometry": {"coordinates":[-77.11135400000001,38.738658],"type":"Point"}
}