{
  "type": "Feature",
  "properties": {
    "iso:country":"US",
    "sg:address":"2702 Rogers Ln",
    "sg:city":"Herndon",
    "sg:classifiers":[
        {
            "category":"Shopping",
            "subcategory":"Computers & Home Electronics",
            "type":"Retail Goods"
        }
    ],
    "sg:phone":"+1 703 904 9000",
    "sg:postcode":"20171",
    "sg:province":"VA",
    "sg:tags":[
        "equipment",
        "dealer"
    ],
    "wof:name":"Cyberdata Technologies Inc",
    "wof:placetype":"venue"
},
  "geometry": {"coordinates":[-77.410724,38.936328],"type":"Point"}
}