{
  "type": "Feature",
  "properties": {
    "addr:full":"2248 Brooksfield Rd Blacksburg VA 24060",
    "addr:housenumber":"2248",
    "addr:postcode":"24060",
    "addr:street":"Brooksfield Rd",
    "iso:country":"US",
    "sg:address":"2248 Brooksfield Rd",
    "sg:city":"Blacksburg",
    "sg:classifiers":[
        {
            "category":"Building & Trades",
            "subcategory":"Landscaping Services",
            "type":"Services"
        }
    ],
    "sg:phone":"+1 540 552 3134",
    "sg:postcode":"24060",
    "sg:province":"VA",
    "wof:name":"Vaughts Tree Service",
    "wof:placetype":"venue"
},
  "geometry": {"coordinates":[-80.497288,37.22534],"type":"Point"}
}