{
  "type": "Feature",
  "properties": {
    "addr:full":"980 Baker Ln Winchester VA 22603",
    "addr:housenumber":"980",
    "addr:postcode":"22603",
    "addr:street":"Baker Ln",
    "iso:country":"US",
    "sg:address":"980 Baker Ln",
    "sg:city":"Winchester",
    "sg:classifiers":[
        {
            "category":"Manufacturing",
            "subcategory":"Metals",
            "type":"Manufacturing & Wholesale Goods"
        },
        {
            "category":"Manufacturing",
            "subcategory":"Tools & Machinery",
            "type":"Manufacturing & Wholesale Goods"
        }
    ],
    "sg:phone":"+1 540 667 1141",
    "sg:postcode":"22603",
    "sg:province":"VA",
    "sg:tags":[
        "manufacture",
        "shop",
        "product",
        "machine",
        "fabrication"
    ],
    "wof:name":"Lawrence Fabrications Inc",
    "wof:placetype":"venue"
},
  "geometry": {"coordinates":[-78.139629,39.195816],"type":"Point"}
}