{
  "type": "Feature",
  "properties": {
    "addr:full":"3110 Sterling Point Dr Portsmouth VA 23703",
    "addr:housenumber":"3110",
    "addr:postcode":"23703",
    "addr:street":"Sterling Point Dr",
    "iso:country":"US",
    "sg:address":"3110 Sterling Point Dr",
    "sg:city":"Portsmouth",
    "sg:classifiers":[
        {
            "category":"Social Services",
            "subcategory":"Child Care",
            "type":"Services"
        }
    ],
    "sg:phone":"+1 757 686 2480",
    "sg:postcode":"23703",
    "sg:province":"VA",
    "sg:tags":[
        "kindergarten",
        "academic",
        "school"
    ],
    "wof:name":"Torah Day School",
    "wof:placetype":"venue"
},
  "geometry": {"coordinates":[-76.37947,36.849598],"type":"Point"}
}