{
  "type": "Feature",
  "properties": {
    "iso:country":"US",
    "sg:address":"224 Beavers Mill Rd",
    "sg:city":"Danville",
    "sg:classifiers":[
        {
            "category":"Real Estate",
            "subcategory":"Real Estate Operator",
            "type":"Services"
        }
    ],
    "sg:phone":"+1 434 836 1020",
    "sg:postcode":"24540",
    "sg:province":"VA",
    "sg:tags":[
        "building",
        "apartment"
    ],
    "wof:name":"Sterling Trace Apartments",
    "wof:placetype":"venue"
},
  "geometry": {"coordinates":[-79.413312,36.618619],"type":"Point"}
}