{
  "type": "Feature",
  "properties": {
    "iso:country":"US",
    "sg:address":"2717 Pleasant Run Dr",
    "sg:city":"Richmond",
    "sg:classifiers":[
        {
            "category":"Professional",
            "subcategory":"Computer Services",
            "type":"Services"
        }
    ],
    "sg:phone":"+1 804 741 4240",
    "sg:postcode":"23233",
    "sg:province":"VA",
    "sg:tags":[
        "prepackaged",
        "software"
    ],
    "wof:name":"Acumen Technologies Corp",
    "wof:placetype":"venue"
},
  "geometry": {"coordinates":[-77.64469800000001,37.628765],"type":"Point"}
}