{
  "type": "Feature",
  "properties": {
    "addr:full":"44964 Underwood Ln Sterling VA 20166",
    "addr:housenumber":"44964",
    "addr:postcode":"20166",
    "addr:street":"Underwood Ln",
    "iso:country":"US",
    "sg:address":"44964 Underwood Ln",
    "sg:city":"Sterling",
    "sg:classifiers":[
        {
            "category":"Wholesale",
            "subcategory":"Electrical",
            "type":"Manufacturing & Wholesale Goods"
        }
    ],
    "sg:phone":"+1 703 796 1116",
    "sg:postcode":"20166",
    "sg:province":"VA",
    "sg:tags":[
        "lighting",
        "fixture",
        "supply"
    ],
    "wof:name":"Laser Lighting Inc",
    "wof:placetype":"venue"
},
  "geometry": {"coordinates":[-77.44466,38.981967],"type":"Point"}
}