{
  "type": "Feature",
  "properties": {
    "addr:full":"300 Avon St Charlottesville VA 22902",
    "addr:housenumber":"300",
    "addr:postcode":"22902",
    "addr:street":"Avon St",
    "iso:country":"US",
    "sg:address":"300 Avon St",
    "sg:city":"Charlottesville",
    "sg:classifiers":[
        {
            "category":"Personal",
            "subcategory":"Beauty Salon",
            "type":"Services"
        }
    ],
    "sg:phone":"+1 434 295 4841",
    "sg:postcode":"22902",
    "sg:province":"VA",
    "sg:tags":[
        "shop"
    ],
    "wof:name":"Natural Beauty Salon",
    "wof:placetype":"venue"
},
  "geometry": {"coordinates":[-78.47771299999999,38.027037],"type":"Point"}
}