{
  "type": "Feature",
  "properties": {
    "addr:full":"97 Marina Dr Deltaville VA 23043",
    "addr:housenumber":"97",
    "addr:postcode":"23043",
    "addr:street":"Marina Dr",
    "iso:country":"US",
    "sg:address":"97 Marina Dr",
    "sg:city":"Deltaville",
    "sg:classifiers":[
        {
            "category":"Autos & Motor Vehicles",
            "subcategory":"Boat Sales",
            "type":"Retail Goods"
        }
    ],
    "sg:phone":"+1 804 776 9211",
    "sg:postcode":"23043",
    "sg:province":"VA",
    "sg:tags":[
        "yacht",
        "broker"
    ],
    "sg:website":"www.nortonyachts.com",
    "wof:name":"Norton's Yacht Sales",
    "wof:placetype":"venue"
},
  "geometry": {"coordinates":[-76.319334,37.559805],"type":"Point"}
}