{
  "type": "Feature",
  "properties": {
    "iso:country":"US",
    "sg:address":"629 King St",
    "sg:city":"Alexandria",
    "sg:classifiers":[
        {
            "category":"Wholesale",
            "subcategory":"Stationery",
            "type":"Manufacturing & Wholesale Goods"
        }
    ],
    "sg:phone":"+1 703 549 3200",
    "sg:postcode":"22314",
    "sg:province":"VA",
    "sg:tags":[
        "product",
        "paper"
    ],
    "wof:name":"Paper Store",
    "wof:placetype":"venue"
},
  "geometry": {"coordinates":[-77.046149,38.805021],"type":"Point"}
}