{
  "type": "Feature",
  "properties": {
    "addr:full":"906 S Lynnhaven Rd Virginia Beach VA 23452",
    "addr:housenumber":"906",
    "addr:postcode":"23452",
    "addr:street":"S Lynnhaven Rd",
    "iso:country":"US",
    "sg:address":"906 S Lynnhaven Rd",
    "sg:city":"Virginia Beach",
    "sg:classifiers":[
        {
            "category":"Shopping",
            "subcategory":"Used Merchandise",
            "type":"Retail Goods"
        }
    ],
    "sg:phone":"+1 757 368 9922",
    "sg:postcode":"23452",
    "sg:province":"VA",
    "sg:tags":[
        "shop",
        "thrift"
    ],
    "wof:name":"Love & Caring Ministries",
    "wof:placetype":"venue"
},
  "geometry": {"coordinates":[-76.073194,36.812005],"type":"Point"}
}