{
  "type": "Feature",
  "properties": {
    "addr:full":"226 E Broadway Ave Hopewell VA 23860",
    "addr:housenumber":"226",
    "addr:postcode":"23860",
    "addr:street":"E Broadway Ave",
    "iso:country":"US",
    "sg:address":"226 E Broadway Ave",
    "sg:city":"Hopewell",
    "sg:classifiers":[
        {
            "category":"Shopping",
            "subcategory":"Used Merchandise",
            "type":"Retail Goods"
        }
    ],
    "sg:phone":"+1 804 452 1148",
    "sg:postcode":"23860",
    "sg:province":"VA",
    "sg:tags":[
        "antique"
    ],
    "wof:name":"Hopewell Antiques",
    "wof:placetype":"venue"
},
  "geometry": {"coordinates":[-77.28481600000001,37.304798],"type":"Point"}
}