{
  "type": "Feature",
  "properties": {
    "iso:country":"US",
    "sg:address":"5445 Stewart Dr",
    "sg:city":"Virginia Beach",
    "sg:classifiers":[
        {
            "category":"Wholesale",
            "subcategory":"Machinery & Supplies",
            "type":"Manufacturing & Wholesale Goods"
        }
    ],
    "sg:phone":"+1 757 479 2999",
    "sg:postcode":"23464",
    "sg:province":"VA",
    "sg:tags":[
        "industrial",
        "representative",
        "manufacturer"
    ],
    "wof:name":"Flomerfelt Stephen E & Assoc",
    "wof:placetype":"venue"
},
  "geometry": {"coordinates":[-76.172607,36.784381],"type":"Point"}
}