{
  "type": "Feature",
  "properties": {
    "addr:full":"7236 New Market Ct Manassas VA 20109",
    "addr:housenumber":"7236",
    "addr:postcode":"20109",
    "addr:street":"New Market Ct",
    "iso:country":"US",
    "sg:address":"7236 New Market Ct",
    "sg:city":"Manassas",
    "sg:classifiers":[
        {
            "category":"Food & Beverages",
            "subcategory":"Groceries & Convenience Stores",
            "type":"Retail Goods"
        }
    ],
    "sg:phone":"+1 703 369 4816",
    "sg:postcode":"20109",
    "sg:province":"VA",
    "sg:tags":[
        "eating"
    ],
    "wof:name":"Hunan Deli",
    "wof:placetype":"venue"
},
  "geometry": {"coordinates":[-77.52155999999999,38.7997],"type":"Point"}
}