{
  "type": "Feature",
  "properties": {
    "addr:full":"23150 Simcox Dr Bristol VA 24202",
    "addr:postcode":"23150;24202",
    "addr:street":"Simcox Dr",
    "iso:country":"US",
    "sg:address":"23150 Simcox Dr",
    "sg:city":"Bristol",
    "sg:classifiers":[
        {
            "category":"Professional",
            "subcategory":"Business Services",
            "type":"Services"
        }
    ],
    "sg:phone":"+1 276 669 8562",
    "sg:postcode":"24202",
    "sg:province":"VA",
    "wof:name":"Classy Chassis Interiors",
    "wof:placetype":"venue"
},
  "geometry": {"coordinates":[-82.112647,36.616993],"type":"Point"}
}