{
  "type": "Feature",
  "properties": {
    "iso:country":"US",
    "sg:address":"8202 Beech Monarch Ct",
    "sg:city":"Springfield",
    "sg:classifiers":[
        {
            "category":"Shopping",
            "subcategory":"Catalog Store",
            "type":"Retail Goods"
        }
    ],
    "sg:phone":"+1 703 493 8585",
    "sg:postcode":"22153",
    "sg:province":"VA",
    "sg:tags":[
        "home",
        "base",
        "order",
        "mail"
    ],
    "wof:name":"Stone & Stone Inc",
    "wof:placetype":"venue"
},
  "geometry": {"coordinates":[-77.22683499999999,38.733525],"type":"Point"}
}