{
  "type": "Feature",
  "properties": {
    "addr:full":"1320 Wards Ferry Rd Lynchburg VA 24502",
    "addr:housenumber":"1320",
    "addr:postcode":"24502",
    "addr:street":"Wards Ferry Rd",
    "iso:country":"US",
    "sg:address":"1320 Wards Ferry Rd",
    "sg:city":"Lynchburg",
    "sg:classifiers":[
        {
            "category":"Wholesale",
            "subcategory":"Stationery",
            "type":"Manufacturing & Wholesale Goods"
        }
    ],
    "sg:phone":"+1 434 237 5700",
    "sg:postcode":"24502",
    "sg:province":"VA",
    "sg:tags":[
        "product",
        "paper"
    ],
    "wof:name":"Frank Parsons Paper Co",
    "wof:placetype":"venue"
},
  "geometry": {"coordinates":[-79.19152,37.351098],"type":"Point"}
}