{
  "type": "Feature",
  "properties": {
    "addr:full":"21286 Hibbs Bridge Rd Middleburg VA 20117",
    "addr:postcode":"21286;20117",
    "addr:street":"Hibbs Bridge Rd",
    "iso:country":"US",
    "sg:address":"21286 Hibbs Bridge Rd",
    "sg:city":"Middleburg",
    "sg:classifiers":[
        {
            "category":"Building & Trades",
            "subcategory":"Construction",
            "type":"Services"
        }
    ],
    "sg:phone":"+1 540 687 5404",
    "sg:postcode":"20117",
    "sg:province":"VA",
    "sg:tags":[
        "contractor"
    ],
    "wof:name":"Tyler & Co Homes",
    "wof:placetype":"venue"
},
  "geometry": {"coordinates":[-77.72740400000001,39.026871],"type":"Point"}
}