{
  "type": "Feature",
  "properties": {
    "addr:full":"482 Patti Rd Rocky Mount VA 24151",
    "addr:housenumber":"482",
    "addr:postcode":"24151",
    "addr:street":"Patti Rd",
    "iso:country":"US",
    "sg:address":"482 Patti Rd",
    "sg:city":"Rocky Mount",
    "sg:classifiers":[
        {
            "category":"Farming",
            "subcategory":"Farm",
            "type":"Manufacturing & Wholesale Goods"
        }
    ],
    "sg:phone":"+1 540 483 0404",
    "sg:postcode":"24151",
    "sg:province":"VA",
    "sg:tags":[
        "crop",
        "general"
    ],
    "wof:name":"Cora Reynolds",
    "wof:placetype":"venue"
},
  "geometry": {"coordinates":[-79.795805,36.945668],"type":"Point"}
}