{
  "type": "Feature",
  "properties": {
    "addr:full":"5607 Gordonsville Rd Keswick VA 22947",
    "addr:housenumber":"5607",
    "addr:postcode":"22947",
    "addr:street":"Gordonsville Rd",
    "iso:country":"US",
    "sg:address":"5607 Gordonsville Rd",
    "sg:city":"Keswick",
    "sg:classifiers":[
        {
            "category":"Organizations",
            "subcategory":"Religious Organization",
            "type":"Services"
        }
    ],
    "sg:phone":"+1 434 293 3549",
    "sg:postcode":"22947",
    "sg:province":"VA",
    "sg:tags":[
        "church"
    ],
    "sg:website":"www.gracekeswick.org",
    "wof:name":"Grace Episcopal Church-Keswick",
    "wof:placetype":"venue"
},
  "geometry": {"coordinates":[-78.309558,38.060551],"type":"Point"}
}