{
  "type": "Feature",
  "properties": {
    "iso:country":"US",
    "sg:address":"291 Slemp Creek Rd",
    "sg:city":"Sugar Grove",
    "sg:classifiers":[
        {
            "category":"Retail",
            "subcategory":"Laundry & Dry Cleaning",
            "type":"Services"
        }
    ],
    "sg:phone":"+1 276 677 3540",
    "sg:postcode":"24375",
    "sg:province":"VA",
    "sg:tags":[
        "equipment",
        "industrial"
    ],
    "wof:name":"Results Plus",
    "wof:placetype":"venue"
},
  "geometry": {"coordinates":[-81.401223,36.782463],"type":"Point"}
}