{
  "type": "Feature",
  "properties": {
    "iso:country":"US",
    "sg:address":"1131 Park St",
    "sg:city":"Bedford",
    "sg:classifiers":[
        {
            "category":"Government",
            "subcategory":"Office",
            "type":"Public Place"
        }
    ],
    "sg:phone":"+1 540 587 6068",
    "sg:postcode":"24523",
    "sg:province":"VA",
    "sg:tags":[
        "village"
    ],
    "wof:name":"Bedford City Cemeteries",
    "wof:placetype":"venue"
},
  "geometry": {"coordinates":[-79.51224499999999,37.340259],"type":"Point"}
}