{
  "type": "Feature",
  "properties": {
    "addr:full":"109 Gainsborough Sq E Chesapeake VA 23320",
    "addr:housenumber":"109",
    "addr:postcode":"23320",
    "addr:street":"Gainsborough Sq E",
    "iso:country":"US",
    "sg:address":"109 Gainsborough Sq E",
    "sg:city":"Chesapeake",
    "sg:classifiers":[
        {
            "category":"Restaurant",
            "type":"Food & Drink"
        }
    ],
    "sg:phone":"+1 757 548 8808",
    "sg:postcode":"23320",
    "sg:province":"VA",
    "sg:tags":[
        "eating"
    ],
    "wof:name":"Lucky Star",
    "wof:placetype":"venue"
},
  "geometry": {"coordinates":[-76.24258500000001,36.741916],"type":"Point"}
}