{
  "type": "Feature",
  "properties": {
    "addr:full":"6784 Springfield Blvd Springfield VA 22150",
    "addr:housenumber":"6784",
    "addr:postcode":"22150",
    "addr:street":"Springfield Blvd",
    "iso:country":"US",
    "sg:address":"6784 Springfield Blvd",
    "sg:city":"Springfield",
    "sg:classifiers":[
        {
            "category":"Restaurant",
            "type":"Food & Drink"
        }
    ],
    "sg:phone":"+1 703 971 9894",
    "sg:postcode":"22150",
    "sg:province":"VA",
    "sg:tags":[
        "eating"
    ],
    "wof:name":"Pizza Xpress",
    "wof:placetype":"venue"
},
  "geometry": {"coordinates":[-77.183423,38.778204],"type":"Point"}
}