{
  "type": "Feature",
  "properties": {
    "addr:full":"4060 Walney Rd Chantilly VA 20151",
    "addr:housenumber":"4060",
    "addr:postcode":"20151",
    "addr:street":"Walney Rd",
    "iso:country":"US",
    "sg:address":"4060 Walney Rd",
    "sg:city":"Chantilly",
    "sg:classifiers":[
        {
            "category":"Home & Garden",
            "subcategory":"Home Furnishings",
            "type":"Retail Goods"
        },
        {
            "category":"Home & Garden",
            "subcategory":"Furniture",
            "type":"Retail Goods"
        }
    ],
    "sg:phone":"+1 703 537 5559",
    "sg:postcode":"20151",
    "sg:province":"VA",
    "sg:tags":[
        "set",
        "store",
        "bed",
        "bedroom"
    ],
    "sg:website":"http://washingtondc.citysearch.com/profile/external/36270451/chantilly_va/hamilton_s_sofa_gallery.html?publisher=yellowpages&reference_id=15&placement=ypwebsitemip",
    "wof:name":"Hamiltons Sofa Gallery",
    "wof:placetype":"venue"
},
  "geometry": {"coordinates":[-77.43224499999999,38.891955],"type":"Point"}
}