{
  "type": "Feature",
  "properties": {
    "addr:full":"1505 Front Royal Dr Richmond VA 23228",
    "addr:housenumber":"1505",
    "addr:postcode":"23228",
    "addr:street":"Front Royal Dr",
    "iso:country":"US",
    "sg:address":"1505 Front Royal Dr",
    "sg:city":"Richmond",
    "sg:classifiers":[
        {
            "category":"Shopping",
            "subcategory":"Catalog Store",
            "type":"Retail Goods"
        }
    ],
    "sg:phone":"+1 804 303 8359",
    "sg:postcode":"23228",
    "sg:province":"VA",
    "sg:tags":[
        "mail",
        "house"
    ],
    "wof:name":"J and J Audia",
    "wof:placetype":"venue"
},
  "geometry": {"coordinates":[-77.465785,37.634615],"type":"Point"}
}