{
  "type": "Feature",
  "properties": {
    "addr:full":"205 Charles St Harrisonburg VA 22802",
    "addr:housenumber":"205",
    "addr:postcode":"22802",
    "addr:street":"Charles St",
    "iso:country":"US",
    "sg:address":"205 Charles St",
    "sg:city":"Harrisonburg",
    "sg:classifiers":[
        {
            "category":"Freight",
            "type":"Transportation"
        }
    ],
    "sg:phone":"+1 540 434 8766",
    "sg:postcode":"22802",
    "sg:province":"VA",
    "sg:tags":[
        "operator",
        "local",
        "trucking"
    ],
    "wof:name":"Loudoun Milk Transportation",
    "wof:placetype":"venue"
},
  "geometry": {"coordinates":[-78.86399,38.464698],"type":"Point"}
}