{
  "type": "Feature",
  "properties": {
    "addr:full":"3438 Caledonia Cir Woodbridge VA 22192",
    "addr:housenumber":"3438",
    "addr:postcode":"22192",
    "addr:street":"Caledonia Cir",
    "iso:country":"US",
    "sg:address":"3438 Caledonia Cir",
    "sg:city":"Woodbridge",
    "sg:classifiers":[
        {
            "category":"Professional",
            "type":"Services"
        }
    ],
    "sg:phone":"+1 703 491 3756",
    "sg:postcode":"22192",
    "sg:province":"VA",
    "wof:name":"Debrito Brothers Corporation",
    "wof:placetype":"venue"
},
  "geometry": {"coordinates":[-77.315612,38.689701],"type":"Point"}
}