{
  "type": "Feature",
  "properties": {
    "iso:country":"US",
    "sg:address":"859 Planters Rd",
    "sg:city":"Lawrenceville",
    "sg:classifiers":[
        {
            "category":"Manufacturing",
            "subcategory":"Wood Products",
            "type":"Manufacturing & Wholesale Goods"
        }
    ],
    "sg:phone":"+1 434 848 2407",
    "sg:postcode":"23868",
    "sg:province":"VA",
    "sg:tags":[
        "mfg"
    ],
    "wof:name":"Brunswick Academy Mill",
    "wof:placetype":"venue"
},
  "geometry": {"coordinates":[-77.82104,36.77261],"type":"Point"}
}