{
  "type": "Feature",
  "properties": {
    "addr:full":"4320 Commerce Rd Richmond VA 23234",
    "addr:housenumber":"4320",
    "addr:postcode":"23234",
    "addr:street":"Commerce Rd",
    "iso:country":"US",
    "sg:address":"4320 Commerce Rd",
    "sg:city":"Richmond",
    "sg:classifiers":[
        {
            "category":"Restaurant",
            "type":"Food & Drink"
        }
    ],
    "sg:phone":"+1 804 275 6871",
    "sg:postcode":"23234",
    "sg:province":"VA",
    "sg:tags":[
        "eating"
    ],
    "wof:name":"Hardees",
    "wof:placetype":"venue"
},
  "geometry": {"coordinates":[-77.42760199999999,37.464269],"type":"Point"}
}