{
  "type": "Feature",
  "properties": {
    "iso:country":"US",
    "sg:address":"906 Lauren Ln SE",
    "sg:city":"Vienna",
    "sg:classifiers":[
        {
            "category":"Banks & Credit Unions",
            "subcategory":"Investment Brokerage",
            "type":"Services"
        }
    ],
    "sg:phone":"+1 703 281 6442",
    "sg:postcode":"22180",
    "sg:province":"VA",
    "sg:tags":[
        "security"
    ],
    "wof:name":"Virginia Naturally",
    "wof:placetype":"venue"
},
  "geometry": {"coordinates":[-77.245807,38.897723],"type":"Point"}
}