{
  "type": "Feature",
  "properties": {
    "iso:country":"US",
    "sg:address":"46400 Benedict Dr",
    "sg:city":"Sterling",
    "sg:classifiers":[
        {
            "category":"Health Services",
            "subcategory":"Doctor",
            "type":"Services"
        }
    ],
    "sg:phone":"+1 703 444 3412",
    "sg:postcode":"20164",
    "sg:province":"VA",
    "sg:tags":[
        "dentist"
    ],
    "wof:name":"Zahra Kavianpour DDS",
    "wof:placetype":"venue"
},
  "geometry": {"coordinates":[-77.395522,39.0252],"type":"Point"}
}