{
  "type": "Feature",
  "properties": {
    "addr:full":"511 E Main St Richmond VA 23219",
    "addr:housenumber":"511",
    "addr:postcode":"23219",
    "addr:street":"E Main St",
    "iso:country":"US",
    "sg:address":"511 E Main St",
    "sg:city":"Richmond",
    "sg:classifiers":[
        {
            "category":"Professional",
            "subcategory":"Management & Consulting",
            "type":"Services"
        }
    ],
    "sg:phone":"+1 804 643 8500",
    "sg:postcode":"23219",
    "sg:province":"VA",
    "sg:tags":[
        "construction"
    ],
    "wof:name":"Goodstein Organizations",
    "wof:placetype":"venue"
},
  "geometry": {"coordinates":[-77.439117,37.539821],"type":"Point"}
}