{
  "type": "Feature",
  "properties": {
    "iso:country":"US",
    "sg:address":"4138 Melrose Ave NW",
    "sg:city":"Roanoke",
    "sg:classifiers":[
        {
            "category":"Home & Garden",
            "subcategory":"Household Appliances",
            "type":"Retail Goods"
        },
        {
            "category":"Wholesale",
            "subcategory":"Electrical",
            "type":"Manufacturing & Wholesale Goods"
        }
    ],
    "sg:phone":"+1 540 563 5522",
    "sg:postcode":"24017",
    "sg:province":"VA",
    "wof:name":"Tribles Inc",
    "wof:placetype":"venue"
},
  "geometry": {"coordinates":[-80.004041,37.296078],"type":"Point"}
}