{
  "type": "Feature",
  "properties": {
    "addr:full":"2284 London Bridge Rd Virginia Beach VA 23456",
    "addr:housenumber":"2284",
    "addr:postcode":"23456",
    "addr:street":"London Bridge Rd",
    "iso:country":"US",
    "sg:address":"2284 London Bridge Rd",
    "sg:city":"Virginia Beach",
    "sg:classifiers":[
        {
            "category":"Retail",
            "subcategory":"Animal Services",
            "type":"Services"
        }
    ],
    "sg:phone":"+1 757 630 2926",
    "sg:postcode":"23456",
    "sg:province":"VA",
    "sg:tags":[
        "pet",
        "crematory",
        "cemetery"
    ],
    "sg:website":"www.cherishpetcremation.com",
    "wof:name":"Cherish Pet Cremation Svc Inc",
    "wof:placetype":"venue"
},
  "geometry": {"coordinates":[-76.028583,36.774065],"type":"Point"}
}