{
  "type": "Feature",
  "properties": {
    "addr:full":"8477 Springfield Oaks Dr Springfield VA 22153",
    "addr:housenumber":"8477",
    "addr:postcode":"22153",
    "addr:street":"Springfield Oaks Dr",
    "iso:country":"US",
    "sg:address":"8477 Springfield Oaks Dr",
    "sg:city":"Springfield",
    "sg:classifiers":[
        {
            "category":"Health Services",
            "subcategory":"Chiropractor",
            "type":"Services"
        }
    ],
    "sg:phone":"+1 703 839 2373",
    "sg:postcode":"22153",
    "sg:province":"VA",
    "sg:tags":[
        "chiropractic"
    ],
    "wof:name":"Ozone Co Md/Dc",
    "wof:placetype":"venue"
},
  "geometry": {"coordinates":[-77.205338,38.726559],"type":"Point"}
}