{
  "type": "Feature",
  "properties": {
    "addr:full":"319 E Market St Leesburg VA 20176",
    "addr:housenumber":"319",
    "addr:postcode":"20176",
    "addr:street":"E Market St",
    "iso:country":"US",
    "sg:address":"319 E Market St",
    "sg:city":"Leesburg",
    "sg:classifiers":[
        {
            "category":"Professional",
            "subcategory":"Business Services",
            "type":"Services"
        }
    ],
    "sg:phone":"+1 703 669 4941",
    "sg:postcode":"20176",
    "sg:province":"VA",
    "wof:name":"A Accessbile Bail Bonding",
    "wof:placetype":"venue"
},
  "geometry": {"coordinates":[-77.558978,39.112257],"type":"Point"}
}