{
  "type": "Feature",
  "properties": {
    "addr:full":"256 W Ocean View Ave Norfolk VA 23503",
    "addr:housenumber":"256",
    "addr:postcode":"23503",
    "addr:street":"W Ocean View Ave",
    "iso:country":"US",
    "sg:address":"256 W Ocean View Ave",
    "sg:city":"Norfolk",
    "sg:classifiers":[
        {
            "category":"Banks & Credit Unions",
            "subcategory":"Investment Brokerage",
            "type":"Services"
        }
    ],
    "sg:phone":"+1 757 587 2618",
    "sg:postcode":"23503",
    "sg:province":"VA",
    "sg:tags":[
        "advisory"
    ],
    "wof:name":"Dream Investors",
    "wof:placetype":"venue"
},
  "geometry": {"coordinates":[-76.255608,36.957453],"type":"Point"}
}