{
  "type": "Feature",
  "properties": {
    "iso:country":"US",
    "sg:address":"114 E Jackson St",
    "sg:city":"Gate City",
    "sg:classifiers":[
        {
            "category":"Government",
            "subcategory":"Office",
            "type":"Public Place"
        }
    ],
    "sg:phone":"+1 276 386 2525",
    "sg:postcode":"24251",
    "sg:province":"VA",
    "sg:tags":[
        "county"
    ],
    "wof:name":"Scott County Economic Dev Auth",
    "wof:placetype":"venue"
},
  "geometry": {"coordinates":[-82.55673299999999,36.6475],"type":"Point"}
}