{
  "type": "Feature",
  "properties": {
    "addr:full":"3301 Hampton Hwy Yorktown VA 23693",
    "addr:housenumber":"3301",
    "addr:postcode":"23693",
    "addr:street":"Hampton Hwy",
    "iso:country":"US",
    "sg:address":"3301 Hampton Hwy",
    "sg:city":"Yorktown",
    "sg:classifiers":[
        {
            "category":"Health Services",
            "subcategory":"Doctor",
            "type":"Services"
        }
    ],
    "sg:phone":"+1 757 867 5003",
    "sg:postcode":"23693",
    "sg:province":"VA",
    "wof:name":"Jeffrey L Ezekiel DDS",
    "wof:placetype":"venue"
},
  "geometry": {"coordinates":[-76.412633,37.100466],"type":"Point"}
}