{
  "type": "Feature",
  "properties": {
    "iso:country":"US",
    "sg:address":"3228 Riverside Dr",
    "sg:city":"Danville",
    "sg:classifiers":[
        {
            "category":"Banks & Credit Unions",
            "subcategory":"Bank",
            "type":"Services"
        }
    ],
    "sg:phone":"+1 434 799 5444",
    "sg:postcode":"24541",
    "sg:province":"VA",
    "sg:tags":[
        "cashing",
        "money",
        "agency",
        "check",
        "notary",
        "order"
    ],
    "wof:name":"USA Check Cashiers Inc",
    "wof:placetype":"venue"
},
  "geometry": {"coordinates":[-79.426058,36.584908],"type":"Point"}
}