{
  "type": "Feature",
  "properties": {
    "addr:full":"7882 Main St Middletown VA 22645",
    "addr:housenumber":"7882",
    "addr:postcode":"22645",
    "addr:street":"Main St",
    "iso:country":"US",
    "sg:address":"7882 Main St",
    "sg:city":"Middletown",
    "sg:classifiers":[
        {
            "category":"Organizations",
            "subcategory":"Religious Organization",
            "type":"Services"
        }
    ],
    "sg:phone":"+1 540 869 1008",
    "sg:postcode":"22645",
    "sg:province":"VA",
    "sg:tags":[
        "church"
    ],
    "wof:name":"Grace United Methodist",
    "wof:placetype":"venue"
},
  "geometry": {"coordinates":[-78.27945699999999,39.028031],"type":"Point"}
}