{
  "type": "Feature",
  "properties": {
    "addr:full":"14221 Willard Rd Chantilly VA 20151",
    "addr:housenumber":"14221",
    "addr:postcode":"20151",
    "addr:street":"Willard Rd",
    "iso:country":"US",
    "sg:address":"14221 Willard Rd",
    "sg:city":"Chantilly",
    "sg:classifiers":[
        {
            "category":"Professional",
            "subcategory":"Engineering",
            "type":"Services"
        }
    ],
    "sg:phone":"+1 703 961 1960",
    "sg:postcode":"20151",
    "sg:province":"VA",
    "sg:tags":[
        "civil",
        "engineer"
    ],
    "wof:name":"Stevenson & Stewart Inc",
    "wof:placetype":"venue"
},
  "geometry": {"coordinates":[-77.440664,38.886214],"type":"Point"}
}