{
  "type": "Feature",
  "properties": {
    "addr:full":"707 Gittings St Suffolk VA 23434",
    "addr:housenumber":"707",
    "addr:postcode":"23434",
    "addr:street":"Gittings St",
    "iso:country":"US",
    "sg:address":"707 Gittings St",
    "sg:city":"Suffolk",
    "sg:classifiers":[
        {
            "category":"Professional",
            "subcategory":"Lawyer & Legal Services",
            "type":"Services"
        },
        {
            "category":"Government",
            "subcategory":"Court House",
            "type":"Public Place"
        }
    ],
    "sg:phone":"+1 757 925 2489",
    "sg:postcode":"23434",
    "sg:province":"VA",
    "sg:tags":[
        "state",
        "counsel"
    ],
    "wof:name":"Public Defender Ofc",
    "wof:placetype":"venue"
},
  "geometry": {"coordinates":[-76.596007,36.729455],"type":"Point"}
}