{
  "type": "Feature",
  "properties": {
    "iso:country":"US",
    "sg:address":"326 Vine St",
    "sg:city":"Harrisonburg",
    "sg:classifiers":[
        {
            "category":"Organizations",
            "subcategory":"Labor Organization",
            "type":"Services"
        }
    ],
    "sg:phone":"+1 540 432 1723",
    "sg:postcode":"22802",
    "sg:province":"VA",
    "wof:name":"Valley Speech Services Lc",
    "wof:placetype":"venue"
},
  "geometry": {"coordinates":[-78.847674,38.457385],"type":"Point"}
}