{
  "type": "Feature",
  "properties": {
    "addr:full":"4220 Ardmore Pl Fairfax VA 22030",
    "addr:housenumber":"4220",
    "addr:postcode":"22030",
    "addr:street":"Ardmore Pl",
    "iso:country":"US",
    "sg:address":"4220 Ardmore Pl",
    "sg:city":"Fairfax",
    "sg:classifiers":[
        {
            "category":"Manufacturing",
            "subcategory":"Tools & Machinery",
            "type":"Manufacturing & Wholesale Goods"
        }
    ],
    "sg:phone":"+1 703 960 2003",
    "sg:postcode":"22030",
    "sg:province":"VA",
    "sg:tags":[
        "electrical",
        "mfg"
    ],
    "wof:name":"Armtek Security Systems I",
    "wof:placetype":"venue"
},
  "geometry": {"coordinates":[-77.312949,38.841399],"type":"Point"}
}