{
  "type": "Feature",
  "properties": {
    "addr:full":"206 Tyler Von Way Fredericksburg VA 22405",
    "addr:housenumber":"206",
    "addr:postcode":"22405",
    "addr:street":"Tyler Von Way",
    "iso:country":"US",
    "sg:address":"206 Tyler Von Way",
    "sg:city":"Fredericksburg",
    "sg:classifiers":[
        {
            "category":"Professional",
            "subcategory":"Advertising",
            "type":"Services"
        }
    ],
    "sg:phone":"+1 540 657 0057",
    "sg:postcode":"22405",
    "sg:province":"VA",
    "sg:tags":[
        "mail",
        "direct"
    ],
    "sg:website":"www.advantagemagazine.com",
    "wof:name":"Advantage Magazine",
    "wof:placetype":"venue"
},
  "geometry": {"coordinates":[-77.44300699999999,38.384222],"type":"Point"}
}