{
  "type": "Feature",
  "properties": {
    "addr:full":"1538 Richmond Rd Charlottesville VA 22911",
    "addr:housenumber":"1538",
    "addr:postcode":"22911",
    "addr:street":"Richmond Rd",
    "iso:country":"US",
    "sg:address":"1538 Richmond Rd",
    "sg:city":"Charlottesville",
    "sg:classifiers":[
        {
            "category":"Education",
            "subcategory":"Preschool",
            "type":"Public Place"
        },
        {
            "category":"Education",
            "subcategory":"School",
            "type":"Public Place"
        }
    ],
    "sg:phone":"+1 434 979 8886",
    "sg:postcode":"22911",
    "sg:province":"VA",
    "sg:tags":[
        "high",
        "middle",
        "elementary"
    ],
    "wof:name":"Montessori Community School the",
    "wof:placetype":"venue"
},
  "geometry": {"coordinates":[-78.442398,38.0299],"type":"Point"}
}