{
  "type": "Feature",
  "properties": {
    "addr:full":"109 E Culpeper St Culpeper VA 22701",
    "addr:housenumber":"109",
    "addr:postcode":"22701",
    "addr:street":"E Culpeper St",
    "iso:country":"US",
    "sg:address":"109 E Culpeper St",
    "sg:city":"Culpeper",
    "sg:classifiers":[
        {
            "category":"Personal",
            "subcategory":"Beauty Salon",
            "type":"Services"
        }
    ],
    "sg:phone":"+1 540 825 1894",
    "sg:postcode":"22701",
    "sg:province":"VA",
    "wof:name":"Rane Hairstylists",
    "wof:placetype":"venue"
},
  "geometry": {"coordinates":[-77.996296,38.472553],"type":"Point"}
}