{
  "type": "Feature",
  "properties": {
    "iso:country":"US",
    "sg:address":"1821 Lafayette Blvd",
    "sg:city":"Norfolk",
    "sg:classifiers":[
        {
            "category":"Organizations",
            "subcategory":"Religious Organization",
            "type":"Services"
        }
    ],
    "sg:phone":"+1 757 627 8629",
    "sg:postcode":"23509",
    "sg:province":"VA",
    "wof:name":"Lafayette Presbyterian Church",
    "wof:placetype":"venue"
},
  "geometry": {"coordinates":[-76.263848,36.877626],"type":"Point"}
}