{
  "type": "Feature",
  "properties": {
    "addr:full":"2810 Old Lee Hwy Fairfax VA 22031",
    "addr:housenumber":"2810",
    "addr:postcode":"22031",
    "addr:street":"Old Lee Hwy",
    "iso:country":"US",
    "sg:address":"2810 Old Lee Hwy",
    "sg:city":"Fairfax",
    "sg:classifiers":[
        {
            "category":"Professional",
            "subcategory":"Engineering",
            "type":"Services"
        }
    ],
    "sg:phone":"+1 703 560 6855",
    "sg:postcode":"22031",
    "sg:province":"VA",
    "sg:tags":[
        "communication"
    ],
    "wof:name":"Ultimate System Enterprises",
    "wof:placetype":"venue"
},
  "geometry": {"coordinates":[-77.24046,38.87551],"type":"Point"}
}