{
  "type": "Feature",
  "properties": {
    "iso:country":"US",
    "sg:address":"3005 Glastonbury Dr",
    "sg:city":"Virginia Beach",
    "sg:classifiers":[
        {
            "category":"Manufacturing",
            "subcategory":"Glass & Minerals",
            "type":"Manufacturing & Wholesale Goods"
        }
    ],
    "sg:phone":"+1 757 368 5208",
    "sg:postcode":"23453",
    "sg:province":"VA",
    "sg:tags":[
        "concrete",
        "product",
        "mfg"
    ],
    "wof:name":"Fountains of Hope",
    "wof:placetype":"venue"
},
  "geometry": {"coordinates":[-76.075344,36.780055],"type":"Point"}
}