{
  "type": "Feature",
  "properties": {
    "addr:full":"8210 Lone Oak Ct Manassas VA 20111",
    "addr:housenumber":"8210",
    "addr:postcode":"20111",
    "addr:street":"Lone Oak Ct",
    "iso:country":"US",
    "sg:address":"8210 Lone Oak Ct",
    "sg:city":"Manassas",
    "sg:classifiers":[
        {
            "category":"Professional",
            "subcategory":"Management & Consulting",
            "type":"Services"
        }
    ],
    "sg:phone":"+1 703 330 7852",
    "sg:postcode":"20111",
    "sg:province":"VA",
    "wof:name":"Enterprses Mngmnet Systems LLC",
    "wof:placetype":"venue"
},
  "geometry": {"coordinates":[-77.445792,38.747665],"type":"Point"}
}