{
  "type": "Feature",
  "properties": {
    "iso:country":"US",
    "sg:address":"43045 Tavernsprings Ct",
    "sg:city":"Ashburn",
    "sg:classifiers":[
        {
            "category":"Professional",
            "subcategory":"Business Services",
            "type":"Services"
        },
        {
            "category":"Recreation",
            "type":"Entertainment"
        }
    ],
    "sg:phone":"+1 703 729 1110",
    "sg:postcode":"20147",
    "sg:province":"VA",
    "sg:tags":[
        "installation",
        "aquarium"
    ],
    "wof:name":"Crystal Clear Aquarium Svc",
    "wof:placetype":"venue"
},
  "geometry": {"coordinates":[-77.512837,39.04551],"type":"Point"}
}