{
  "type": "Feature",
  "properties": {
    "addr:full":"16600 Pouncey Tract Rd Rockville VA 23146",
    "addr:housenumber":"16600",
    "addr:postcode":"23146",
    "addr:street":"Pouncey Tract Rd",
    "iso:country":"US",
    "sg:address":"16600 Pouncey Tract Rd",
    "sg:city":"Rockville",
    "sg:classifiers":[
        {
            "category":"Education",
            "subcategory":"Library",
            "type":"Public Place"
        }
    ],
    "sg:phone":"+1 804 749 3146",
    "sg:postcode":"23146",
    "sg:province":"VA",
    "sg:website":"www.pamunkeylibrary.org",
    "wof:name":"Rockville Library",
    "wof:placetype":"venue"
},
  "geometry": {"coordinates":[-77.681168,37.725805],"type":"Point"}
}