{
  "type": "Feature",
  "properties": {
    "addr:full":"614 Leesville Rd Lynchburg VA 24502",
    "addr:housenumber":"614",
    "addr:postcode":"24502",
    "addr:street":"Leesville Rd",
    "iso:country":"US",
    "sg:address":"614 Leesville Rd",
    "sg:city":"Lynchburg",
    "sg:classifiers":[
        {
            "category":"Building & Trades",
            "subcategory":"Construction",
            "type":"Services"
        }
    ],
    "sg:phone":"+1 434 239 4934",
    "sg:postcode":"24502",
    "sg:province":"VA",
    "sg:tags":[
        "masonry",
        "contractor"
    ],
    "wof:name":"Halls Quality Masonry Inc",
    "wof:placetype":"venue"
},
  "geometry": {"coordinates":[-79.20582,37.349006],"type":"Point"}
}