{
  "type": "Feature",
  "properties": {
    "addr:full":"9836 Fairfax Sq Fairfax VA 22031",
    "addr:housenumber":"9836",
    "addr:postcode":"22031",
    "addr:street":"Fairfax Sq",
    "iso:country":"US",
    "sg:address":"9836 Fairfax Sq",
    "sg:city":"Fairfax",
    "sg:classifiers":[
        {
            "category":"Freight",
            "type":"Transportation"
        }
    ],
    "sg:phone":"+1 703 362 0279",
    "sg:postcode":"22031",
    "sg:province":"VA",
    "sg:tags":[
        "courier"
    ],
    "wof:name":"Galaxy Xpress",
    "wof:placetype":"venue"
},
  "geometry": {"coordinates":[-77.285098,38.843015],"type":"Point"}
}