{
  "type": "Feature",
  "properties": {
    "addr:full":"14275 Town Commons Way Gainesville VA 20155",
    "addr:housenumber":"14275",
    "addr:postcode":"20155",
    "addr:street":"Town Commons Way",
    "iso:country":"US",
    "sg:address":"14275 Town Commons Way",
    "sg:city":"Gainesville",
    "sg:classifiers":[
        {
            "category":"Professional",
            "subcategory":"Business Services",
            "type":"Services"
        }
    ],
    "sg:phone":"+1 703 753 3526",
    "sg:postcode":"20155",
    "sg:province":"VA",
    "wof:name":"Youl Enterprises Inc",
    "wof:placetype":"venue"
},
  "geometry": {"coordinates":[-77.612483,38.812242],"type":"Point"}
}