{
  "type": "Feature",
  "properties": {
    "addr:full":"2629 Valley Ave Winchester VA 22601",
    "addr:housenumber":"2629",
    "addr:postcode":"22601",
    "addr:street":"Valley Ave",
    "iso:country":"US",
    "sg:address":"2629 Valley Ave",
    "sg:city":"Winchester",
    "sg:classifiers":[
        {
            "category":"Retail",
            "subcategory":"Auto Rental",
            "type":"Services"
        }
    ],
    "sg:phone":"+1 540 665 3009",
    "sg:postcode":"22601",
    "sg:province":"VA",
    "sg:tags":[
        "passenger",
        "car"
    ],
    "wof:name":"Rent-A-Wreck",
    "wof:placetype":"venue"
},
  "geometry": {"coordinates":[-78.18662999999999,39.156069],"type":"Point"}
}