{
  "type": "Feature",
  "properties": {
    "iso:country":"US",
    "sg:address":"43462 Ridgeview Pl",
    "sg:city":"Ashburn",
    "sg:classifiers":[
        {
            "category":"Professional",
            "subcategory":"Business Services",
            "type":"Services"
        }
    ],
    "sg:phone":"+1 703 723 3132",
    "sg:postcode":"20147",
    "sg:province":"VA",
    "wof:name":"Inspiration",
    "wof:placetype":"venue"
},
  "geometry": {"coordinates":[-77.49795,39.028247],"type":"Point"}
}