{
  "type": "Feature",
  "properties": {
    "addr:full":"10730 Anita Dr Lorton VA 22079",
    "addr:housenumber":"10730",
    "addr:postcode":"22079",
    "addr:street":"Anita Dr",
    "iso:country":"US",
    "sg:address":"10730 Anita Dr",
    "sg:city":"Lorton",
    "sg:classifiers":[
        {
            "category":"Building & Trades",
            "subcategory":"Construction",
            "type":"Services"
        }
    ],
    "sg:phone":"+1 703 339 8025",
    "sg:postcode":"22079",
    "sg:province":"VA",
    "sg:tags":[
        "hanging",
        "contractor"
    ],
    "wof:name":"Collins Painting Co Inc",
    "wof:placetype":"venue"
},
  "geometry": {"coordinates":[-77.22559699999999,38.664981],"type":"Point"}
}