{
  "type": "Feature",
  "properties": {
    "iso:country":"US",
    "sg:address":"3423 W Cary St",
    "sg:city":"Richmond",
    "sg:classifiers":[
        {
            "category":"Shopping",
            "subcategory":"Gifts & Souvenirs",
            "type":"Retail Goods"
        }
    ],
    "sg:phone":"+1 804 358 0053",
    "sg:postcode":"23221",
    "sg:province":"VA",
    "wof:name":"Lane Sanson Home Eclectique",
    "wof:placetype":"venue"
},
  "geometry": {"coordinates":[-77.484781,37.554516],"type":"Point"}
}