{
  "type": "Feature",
  "properties": {
    "iso:country":"US",
    "sg:address":"11211 Waples Mill Rd",
    "sg:city":"Fairfax",
    "sg:classifiers":[
        {
            "category":"Health Services",
            "subcategory":"Dentist",
            "type":"Services"
        }
    ],
    "sg:phone":"+1 703 261 6960",
    "sg:postcode":"22030",
    "sg:province":"VA",
    "wof:name":"Ariani Mehran D.D.S, PC",
    "wof:placetype":"venue"
},
  "geometry": {"coordinates":[-77.335097,38.85908],"type":"Point"}
}