{
  "type": "Feature",
  "properties": {
    "iso:country":"US",
    "sg:address":"1151 Oliver Creek Rd",
    "sg:city":"Troy",
    "sg:classifiers":[
        {
            "category":"Building & Trades",
            "subcategory":"Construction",
            "type":"Services"
        }
    ],
    "sg:phone":"+1 434 591 0345",
    "sg:postcode":"22974",
    "sg:province":"VA",
    "sg:tags":[
        "concrete",
        "contractor"
    ],
    "wof:name":"Creasey Concrete",
    "wof:placetype":"venue"
},
  "geometry": {"coordinates":[-78.265046,37.963757],"type":"Point"}
}