{
  "type": "Feature",
  "properties": {
    "addr:full":"2645 Red Lane Rd Powhatan VA 23139",
    "addr:housenumber":"2645",
    "addr:postcode":"23139",
    "addr:street":"Red Lane Rd",
    "iso:country":"US",
    "sg:address":"2645 Red Lane Rd",
    "sg:city":"Powhatan",
    "sg:classifiers":[
        {
            "category":"Professional",
            "subcategory":"Business Services",
            "type":"Services"
        }
    ],
    "sg:phone":"+1 804 598 6567",
    "sg:postcode":"23139",
    "sg:province":"VA",
    "wof:name":"Dominion Interior Supply",
    "wof:placetype":"venue"
},
  "geometry": {"coordinates":[-77.83421800000001,37.567634],"type":"Point"}
}