{
  "type": "Feature",
  "properties": {
    "iso:country":"US",
    "sg:address":"340 S Pickett St",
    "sg:city":"Alexandria",
    "sg:classifiers":[
        {
            "category":"Government",
            "subcategory":"Post Office",
            "type":"Public Place"
        }
    ],
    "sg:phone":"+1 703 823 2170",
    "sg:postcode":"22304",
    "sg:province":"VA",
    "sg:tags":[
        "postal",
        "us"
    ],
    "wof:name":"US Post Office",
    "wof:placetype":"venue"
},
  "geometry": {"coordinates":[-77.123783,38.808921],"type":"Point"}
}