{
  "type": "Feature",
  "properties": {
    "addr:full":"1101 Cavalier Blvd Chesapeake VA 23323",
    "addr:housenumber":"1101",
    "addr:postcode":"23323",
    "addr:street":"Cavalier Blvd",
    "iso:country":"US",
    "sg:address":"1101 Cavalier Blvd",
    "sg:city":"Chesapeake",
    "sg:classifiers":[
        {
            "category":"Retail",
            "subcategory":"Repair Shop",
            "type":"Services"
        }
    ],
    "sg:phone":"+1 757 487 6000",
    "sg:postcode":"23323",
    "sg:province":"VA",
    "sg:tags":[
        "equipment",
        "mfg"
    ],
    "wof:name":"Dresser-Rand Company",
    "wof:placetype":"venue"
},
  "geometry": {"coordinates":[-76.36423000000001,36.780624],"type":"Point"}
}