{
  "type": "Feature",
  "properties": {
    "addr:full":"904 Kempsville Rd Virginia Beach VA 23464",
    "addr:housenumber":"904",
    "addr:postcode":"23464",
    "addr:street":"Kempsville Rd",
    "iso:country":"US",
    "sg:address":"904 Kempsville Rd",
    "sg:city":"Virginia Beach",
    "sg:classifiers":[
        {
            "category":"Health Services",
            "subcategory":"Chiropractor",
            "type":"Services"
        }
    ],
    "sg:phone":"+1 757 467 5258",
    "sg:postcode":"23464",
    "sg:province":"VA",
    "wof:name":"Kempsville Chiropractic",
    "wof:placetype":"venue"
},
  "geometry": {"coordinates":[-76.165368,36.813112],"type":"Point"}
}