{
  "type": "Feature",
  "properties": {
    "addr:full":"211 Edwards Ferry Rd NE Leesburg VA 20176",
    "addr:housenumber":"211",
    "addr:postcode":"20176",
    "addr:street":"Edwards Ferry Rd Ne",
    "iso:country":"US",
    "sg:address":"211 Edwards Ferry Rd NE",
    "sg:city":"Leesburg",
    "sg:classifiers":[
        {
            "category":"Professional",
            "type":"Services"
        }
    ],
    "sg:phone":"+1 703 443 8883",
    "sg:postcode":"20176",
    "sg:province":"VA",
    "sg:tags":[
        "establishment"
    ],
    "wof:name":"Exceptions",
    "wof:placetype":"venue"
},
  "geometry": {"coordinates":[-77.560986,39.11441],"type":"Point"}
}