{
  "type": "Feature",
  "properties": {
    "addr:full":"43998 Needmore Ct Ashburn VA 20147",
    "addr:postcode":"43998;20147",
    "addr:street":"Needmore Ct",
    "iso:country":"US",
    "sg:address":"43998 Needmore Ct",
    "sg:city":"Ashburn",
    "sg:classifiers":[
        {
            "category":"Professional",
            "subcategory":"Computer Services",
            "type":"Services"
        }
    ],
    "sg:phone":"+1 703 729 5409",
    "sg:postcode":"20147",
    "sg:province":"VA",
    "sg:tags":[
        "consulting"
    ],
    "wof:name":"Innovative Technology Services",
    "wof:placetype":"venue"
},
  "geometry": {"coordinates":[-77.47942,39.04987],"type":"Point"}
}