{
  "type": "Feature",
  "properties": {
    "addr:full":"201 Hall Ave Suffolk VA 23434",
    "addr:housenumber":"201",
    "addr:postcode":"23434",
    "addr:street":"Hall Ave",
    "iso:country":"US",
    "sg:address":"201 Hall Ave",
    "sg:city":"Suffolk",
    "sg:classifiers":[
        {
            "category":"Retail",
            "subcategory":"Repair Shop",
            "type":"Services"
        }
    ],
    "sg:phone":"+1 757 539 6702",
    "sg:postcode":"23434",
    "sg:province":"VA",
    "sg:tags":[
        "appliance"
    ],
    "wof:name":"Appliance Service Ctr",
    "wof:placetype":"venue"
},
  "geometry": {"coordinates":[-76.586872,36.725695],"type":"Point"}
}