{
  "type": "Feature",
  "properties": {
    "addr:full":"4505 Jefferson Davis Hwy Richmond VA 23234",
    "addr:housenumber":"4505",
    "addr:postcode":"23234",
    "addr:street":"Jefferson Davis Hwy",
    "iso:country":"US",
    "sg:address":"4505 Jefferson Davis Hwy",
    "sg:city":"Richmond",
    "sg:classifiers":[
        {
            "category":"Restaurant",
            "type":"Food & Drink"
        }
    ],
    "sg:menulink":"http://www.allmenus.com/va/richmond/181325-kfc---kentucky-fried-chicken/menu/",
    "sg:phone":"+1 804 275 8354",
    "sg:postcode":"23234",
    "sg:province":"VA",
    "sg:tags":[
        "american",
        "chicken"
    ],
    "wof:name":"KFC - Kentucky Fried Chicken",
    "wof:placetype":"venue"
},
  "geometry": {"coordinates":[-77.442809,37.465038],"type":"Point"}
}