{
  "type": "Feature",
  "properties": {
    "iso:country":"US",
    "sg:address":"7214 Arlington Blvd",
    "sg:city":"Falls Church",
    "sg:classifiers":[
        {
            "category":"Professional",
            "subcategory":"Accounting & Tax Preparation",
            "type":"Services"
        }
    ],
    "sg:phone":"+1 703 645 9855",
    "sg:postcode":"22042",
    "sg:province":"VA",
    "sg:tags":[
        "return"
    ],
    "wof:name":"Nova Financial Services LLC",
    "wof:placetype":"venue"
},
  "geometry": {"coordinates":[-77.194,38.866526],"type":"Point"}
}