{
  "type": "Feature",
  "properties": {
    "addr:full":"732 N Washington St Alexandria VA 22314",
    "addr:housenumber":"732",
    "addr:postcode":"22314",
    "addr:street":"N Washington St",
    "iso:country":"US",
    "sg:address":"732 N Washington St",
    "sg:city":"Alexandria",
    "sg:classifiers":[
        {
            "category":"Professional",
            "type":"Services"
        }
    ],
    "sg:phone":"+1 703 836 7890",
    "sg:postcode":"22314",
    "sg:province":"VA",
    "sg:tags":[
        "consulting",
        "aerospace"
    ],
    "wof:name":"Hurricane Bobs",
    "wof:placetype":"venue"
},
  "geometry": {"coordinates":[-77.04539800000001,38.812656],"type":"Point"}
}