{
  "type": "Feature",
  "properties": {
    "addr:full":"2102 W Washington St Petersburg VA 23803",
    "addr:housenumber":"2102",
    "addr:postcode":"23803",
    "addr:street":"W Washington",
    "iso:country":"US",
    "sg:address":"2102 W Washington St",
    "sg:city":"Petersburg",
    "sg:classifiers":[
        {
            "category":"Autos & Motor Vehicles",
            "subcategory":"Automobile Sales",
            "type":"Retail Goods"
        },
        {
            "category":"Autos & Motor Vehicles",
            "subcategory":"Auto Supplies",
            "type":"Retail Goods"
        }
    ],
    "sg:phone":"+1 804 732 0500",
    "sg:postcode":"23803",
    "sg:province":"VA",
    "sg:tags":[
        "truck"
    ],
    "wof:name":"Trucks & Equipment LLC",
    "wof:placetype":"venue"
},
  "geometry": {"coordinates":[-77.440297,37.217948],"type":"Point"}
}