{
  "type": "Feature",
  "properties": {
    "iso:country":"US",
    "sg:address":"13531 Persian Ct",
    "sg:city":"Woodbridge",
    "sg:classifiers":[
        {
            "category":"Building & Trades",
            "subcategory":"Cleaning & Sanitation",
            "type":"Services"
        }
    ],
    "sg:phone":"+1 703 580 8495",
    "sg:postcode":"22193",
    "sg:province":"VA",
    "sg:tags":[
        "janitor",
        "maintenance"
    ],
    "wof:name":"Ambassador Cleaning Service",
    "wof:placetype":"venue"
},
  "geometry": {"coordinates":[-77.38862899999999,38.659559],"type":"Point"}
}