{
  "type": "Feature",
  "properties": {
    "iso:country":"US",
    "sg:address":"373 Edwin Dr",
    "sg:city":"Virginia Beach",
    "sg:classifiers":[
        {
            "category":"Real Estate",
            "subcategory":"Real Estate Agent",
            "type":"Services"
        }
    ],
    "sg:phone":"+1 757 499 6161",
    "sg:postcode":"23462",
    "sg:province":"VA",
    "sg:tags":[
        "management"
    ],
    "sg:website":"www.lawsoncompanies.com",
    "wof:name":"Lawson Co",
    "wof:placetype":"venue"
},
  "geometry": {"coordinates":[-76.131145,36.826004],"type":"Point"}
}