{
  "type": "Feature",
  "properties": {
    "iso:country":"US",
    "sg:address":"1110 Herndon Pkwy",
    "sg:city":"Herndon",
    "sg:classifiers":[
        {
            "category":"Wholesale",
            "subcategory":"Electrical",
            "type":"Manufacturing & Wholesale Goods"
        }
    ],
    "sg:phone":"+1 703 318 5500",
    "sg:postcode":"20170",
    "sg:province":"VA",
    "sg:tags":[
        "telecommunication"
    ],
    "sg:website":"www.ctitele.com",
    "wof:name":"CTI Telecom",
    "wof:placetype":"venue"
},
  "geometry": {"coordinates":[-77.401445,38.965065],"type":"Point"}
}