{
  "type": "Feature",
  "properties": {
    "iso:country":"US",
    "sg:address":"1178 Big Bethel Rd",
    "sg:city":"Hampton",
    "sg:classifiers":[
        {
            "category":"Shopping",
            "subcategory":"Tobacco",
            "type":"Retail Goods"
        }
    ],
    "sg:phone":"+1 757 825 8787",
    "sg:postcode":"23666",
    "sg:province":"VA",
    "sg:tags":[
        "cigarette",
        "cigar",
        "dealer"
    ],
    "wof:name":"Dona Juana's Cigar Shop",
    "wof:placetype":"venue"
},
  "geometry": {"coordinates":[-76.427958,37.056107],"type":"Point"}
}