{
  "type": "Feature",
  "properties": {
    "addr:full":"8815 Jackson Ave Manassas VA 20110",
    "addr:housenumber":"8815",
    "addr:postcode":"20110",
    "addr:street":"Jackson Ave",
    "iso:country":"US",
    "sg:address":"8815 Jackson Ave",
    "sg:city":"Manassas",
    "sg:classifiers":[
        {
            "category":"Retail",
            "subcategory":"Repair Shop",
            "type":"Services"
        },
        {
            "category":"Building & Trades",
            "subcategory":"Plumbing",
            "type":"Services"
        }
    ],
    "sg:phone":"+1 703 365 7707",
    "sg:postcode":"20110",
    "sg:province":"VA",
    "sg:tags":[
        "plumbing",
        "drain",
        "cleaning",
        "sewer",
        "contractor"
    ],
    "wof:name":"Herb The Plumber",
    "wof:placetype":"venue"
},
  "geometry": {"coordinates":[-77.469398,38.765284],"type":"Point"}
}