{
  "type": "Feature",
  "properties": {
    "iso:country":"US",
    "sg:address":"213 64th St",
    "sg:city":"Virginia Beach",
    "sg:classifiers":[
        {
            "category":"Health Services",
            "subcategory":"Health Practitioner",
            "type":"Services"
        }
    ],
    "sg:phone":"+1 757 437 8777",
    "sg:postcode":"23451",
    "sg:province":"VA",
    "sg:tags":[
        "physician",
        "nurse",
        "extender",
        "pediatric"
    ],
    "wof:name":"Suzanne R Stillman",
    "wof:placetype":"venue"
},
  "geometry": {"coordinates":[-75.988394,36.889361],"type":"Point"}
}