{
  "type": "Feature",
  "properties": {
    "iso:country":"US",
    "sg:address":"8316 Abbey Rd",
    "sg:city":"Richmond",
    "sg:classifiers":[
        {
            "category":"Professional",
            "type":"Services"
        }
    ],
    "sg:phone":"+1 804 272 1608",
    "sg:postcode":"23235",
    "sg:province":"VA",
    "wof:name":"Fak Inc",
    "wof:placetype":"venue"
},
  "geometry": {"coordinates":[-77.552235,37.544815],"type":"Point"}
}