{
  "type": "Feature",
  "properties": {
    "addr:full":"913 Grove Rd Ste 12 Midlothian VA 23114",
    "addr:housenumber":"913;12",
    "addr:postcode":"23114",
    "addr:street":"Grove Rd Ste",
    "iso:country":"US",
    "sg:address":"913 Grove Rd Ste 12",
    "sg:city":"Midlothian",
    "sg:classifiers":[
        {
            "category":"Autos & Motor Vehicles",
            "subcategory":"Automobile Sales",
            "type":"Retail Goods"
        }
    ],
    "sg:phone":"+1 804 794 6000",
    "sg:postcode":"23114",
    "sg:province":"VA",
    "sg:tags":[
        "used",
        "car",
        "broker",
        "dealers-used",
        "truck",
        "cars-wholesale"
    ],
    "wof:name":"Tams Auto Brokers",
    "wof:placetype":"venue"
},
  "geometry": {"coordinates":[-77.615229,37.503462],"type":"Point"}
}