{
  "type": "Feature",
  "properties": {
    "iso:country":"US",
    "sg:address":"49 Clark Ln",
    "sg:city":"Kilmarnock",
    "sg:classifiers":[
        {
            "category":"Building & Trades",
            "subcategory":"Construction",
            "type":"Services"
        }
    ],
    "sg:phone":"+1 804 435 7793",
    "sg:postcode":"22482",
    "sg:province":"VA",
    "sg:tags":[
        "residential"
    ],
    "wof:name":"Southern Star Builders",
    "wof:placetype":"venue"
},
  "geometry": {"coordinates":[-76.37296499999999,37.710471],"type":"Point"}
}