{
  "type": "Feature",
  "properties": {
    "addr:full":"1111 N Stuart St Arlington VA 22201",
    "addr:housenumber":"1111",
    "addr:postcode":"22201",
    "addr:street":"N Stuart St",
    "iso:country":"US",
    "sg:address":"1111 N Stuart St",
    "sg:city":"Arlington",
    "sg:classifiers":[
        {
            "category":"Professional",
            "subcategory":"Management & Consulting",
            "type":"Services"
        }
    ],
    "sg:phone":"+1 703 312 0785",
    "sg:postcode":"22201",
    "sg:province":"VA",
    "sg:tags":[
        "business"
    ],
    "wof:name":"Williams Associates Intl",
    "wof:placetype":"venue"
},
  "geometry": {"coordinates":[-77.11212,38.885387],"type":"Point"}
}