{
  "type": "Feature",
  "properties": {
    "addr:full":"4501 Old Well Ter Midlothian VA 23112",
    "addr:housenumber":"4501",
    "addr:postcode":"23112",
    "addr:street":"Old Well Ter",
    "iso:country":"US",
    "sg:address":"4501 Old Well Ter",
    "sg:city":"Midlothian",
    "sg:classifiers":[
        {
            "category":"Professional",
            "subcategory":"Secretarial Services",
            "type":"Services"
        }
    ],
    "sg:phone":"+1 804 744 3812",
    "sg:postcode":"23112",
    "sg:province":"VA",
    "sg:tags":[
        "reporting"
    ],
    "wof:name":"Morrison When-Dee",
    "wof:placetype":"venue"
},
  "geometry": {"coordinates":[-77.640654,37.424937],"type":"Point"}
}