{
  "type": "Feature",
  "properties": {
    "addr:full":"620 Woodbrook Dr Charlottesville VA 22901",
    "addr:housenumber":"620",
    "addr:postcode":"22901",
    "addr:street":"Woodbrook Dr",
    "iso:country":"US",
    "sg:address":"620 Woodbrook Dr",
    "sg:city":"Charlottesville",
    "sg:classifiers":[
        {
            "category":"Banks & Credit Unions",
            "subcategory":"Bank",
            "type":"Services"
        }
    ],
    "sg:phone":"+1 434 975 4622",
    "sg:postcode":"22901",
    "sg:province":"VA",
    "sg:tags":[
        "loan"
    ],
    "wof:name":"GMAC Mortgage",
    "wof:placetype":"venue"
},
  "geometry": {"coordinates":[-78.475101,38.091097],"type":"Point"}
}