{
  "type": "Feature",
  "properties": {
    "iso:country":"US",
    "sg:address":"8500 Leesburg Pike Ste 7500",
    "sg:city":"Vienna",
    "sg:classifiers":[
        {
            "category":"Professional",
            "subcategory":"Lawyer & Legal Services",
            "type":"Services"
        }
    ],
    "sg:phone":"+1 703 288 5105",
    "sg:postcode":"22182",
    "sg:province":"VA",
    "wof:name":"H C Park & Associates Plc",
    "wof:placetype":"venue"
},
  "geometry": {"coordinates":[-77.23855,38.926453],"type":"Point"}
}