{
  "type": "Feature",
  "properties": {
    "iso:country":"US",
    "sg:address":"1834 E Nine Mile Rd",
    "sg:city":"Highland Springs",
    "sg:classifiers":[
        {
            "category":"Retail",
            "subcategory":"Repair Shop",
            "type":"Services"
        }
    ],
    "sg:phone":"+1 804 328 2300",
    "sg:postcode":"23075",
    "sg:province":"VA",
    "sg:tags":[
        "scooter",
        "motorcycle",
        "motor"
    ],
    "wof:name":"East End Custom Cycle",
    "wof:placetype":"venue"
},
  "geometry": {"coordinates":[-77.313508,37.530899],"type":"Point"}
}