{
  "type": "Feature",
  "properties": {
    "addr:full":"43704 Biddle Ln Chantilly VA 20152",
    "addr:housenumber":"43704",
    "addr:postcode":"20152",
    "addr:street":"Biddle Ln",
    "iso:country":"US",
    "sg:address":"43704 Biddle Ln",
    "sg:city":"Chantilly",
    "sg:classifiers":[
        {
            "category":"Building & Trades",
            "subcategory":"Construction",
            "type":"Services"
        }
    ],
    "sg:phone":"+1 703 327 5572",
    "sg:postcode":"20152",
    "sg:province":"VA",
    "sg:tags":[
        "home",
        "house",
        "improvement"
    ],
    "wof:name":"Phase II Renovations Inc",
    "wof:placetype":"venue"
},
  "geometry": {"coordinates":[-77.491595,38.89757],"type":"Point"}
}