{
  "type": "Feature",
  "properties": {
    "addr:full":"524 Buffalo Rd Clarksville VA 23927",
    "addr:housenumber":"524",
    "addr:postcode":"23927",
    "addr:street":"Buffalo Rd",
    "iso:country":"US",
    "sg:address":"524 Buffalo Rd",
    "sg:city":"Clarksville",
    "sg:classifiers":[
        {
            "category":"Freight",
            "type":"Transportation"
        }
    ],
    "sg:phone":"+1 434 374 9261",
    "sg:postcode":"23927",
    "sg:province":"VA",
    "sg:tags":[
        "commercial",
        "storage"
    ],
    "wof:name":"Clarksville Mini-Storage",
    "wof:placetype":"venue"
},
  "geometry": {"coordinates":[-78.58706100000001,36.614545],"type":"Point"}
}