{
  "type": "Feature",
  "properties": {
    "addr:full":"6622 Old Chesterbrook Rd Mc Lean VA 22101",
    "addr:housenumber":"6622",
    "addr:postcode":"22101",
    "addr:street":"Old Chesterbrook Rd",
    "iso:country":"US",
    "sg:address":"6622 Old Chesterbrook Rd",
    "sg:city":"Mc Lean",
    "sg:classifiers":[
        {
            "category":"Professional",
            "subcategory":"Computer Services",
            "type":"Services"
        }
    ],
    "sg:phone":"+1 703 797 1881",
    "sg:postcode":"22101",
    "sg:province":"VA",
    "sg:tags":[
        "develop",
        "software"
    ],
    "wof:name":"Corasworks Corporation",
    "wof:placetype":"venue"
},
  "geometry": {"coordinates":[-77.17102800000001,38.925744],"type":"Point"}
}