{
  "type": "Feature",
  "properties": {
    "addr:full":"8769 Cold Plain Ct Springfield VA 22153",
    "addr:housenumber":"8769",
    "addr:postcode":"22153",
    "addr:street":"Cold Plain Ct",
    "iso:country":"US",
    "sg:address":"8769 Cold Plain Ct",
    "sg:city":"Springfield",
    "sg:classifiers":[
        {
            "category":"Professional",
            "subcategory":"Management & Consulting",
            "type":"Services"
        }
    ],
    "sg:phone":"+1 703 455 3821",
    "sg:postcode":"22153",
    "sg:province":"VA",
    "sg:tags":[
        "development",
        "consultant",
        "training"
    ],
    "wof:name":"Bradley L Bennett",
    "wof:placetype":"venue"
},
  "geometry": {"coordinates":[-77.24675999999999,38.739157],"type":"Point"}
}