{
  "type": "Feature",
  "properties": {
    "iso:country":"US",
    "sg:address":"2929 Eskridge Rd Ste T",
    "sg:city":"Fairfax",
    "sg:classifiers":[
        {
            "category":"Professional",
            "subcategory":"Computer Services",
            "type":"Services"
        }
    ],
    "sg:phone":"+1 703 698 7332",
    "sg:postcode":"22031",
    "sg:province":"VA",
    "sg:tags":[
        "equipment",
        "rooms-installation"
    ],
    "wof:name":"Phil Muller",
    "wof:placetype":"venue"
},
  "geometry": {"coordinates":[-77.23188399999999,38.872359],"type":"Point"}
}