{
  "type": "Feature",
  "properties": {
    "addr:full":"4455 Flexon Dr Prince George VA 23875",
    "addr:housenumber":"4455",
    "addr:postcode":"23875",
    "addr:street":"Flexon Dr",
    "iso:country":"US",
    "sg:address":"4455 Flexon Dr",
    "sg:city":"Prince George",
    "sg:classifiers":[
        {
            "category":"Building & Trades",
            "subcategory":"Electrical",
            "type":"Services"
        }
    ],
    "sg:phone":"+1 804 526 7693",
    "sg:postcode":"23875",
    "sg:province":"VA",
    "sg:tags":[
        "electric",
        "contractor"
    ],
    "wof:name":"Industrial Control Specialties",
    "wof:placetype":"venue"
},
  "geometry": {"coordinates":[-77.367913,37.254388],"type":"Point"}
}