{
  "type": "Feature",
  "properties": {
    "iso:country":"US",
    "sg:address":"11649 Sandal Wood Ln",
    "sg:city":"Manassas",
    "sg:classifiers":[
        {
            "category":"Personal",
            "subcategory":"Hair Removal",
            "type":"Services"
        }
    ],
    "sg:phone":"+1 703 791 7882",
    "sg:postcode":"20112",
    "sg:province":"VA",
    "sg:tags":[
        "financial"
    ],
    "wof:name":"Hbw Insurance & Fincl Svcs Inc",
    "wof:placetype":"venue"
},
  "geometry": {"coordinates":[-77.41504500000001,38.708427],"type":"Point"}
}