{
  "type": "Feature",
  "properties": {
    "addr:full":"1000 Oakwood St Fredericksburg VA 22401",
    "addr:housenumber":"1000",
    "addr:postcode":"22401",
    "addr:street":"Oakwood St",
    "iso:country":"US",
    "sg:address":"1000 Oakwood St",
    "sg:city":"Fredericksburg",
    "sg:classifiers":[
        {
            "category":"Health Services",
            "subcategory":"Chiropractor",
            "type":"Services"
        }
    ],
    "sg:phone":"+1 540 373 1633",
    "sg:postcode":"22401",
    "sg:province":"VA",
    "wof:name":"Schulz Chiropractic Ctr",
    "wof:placetype":"venue"
},
  "geometry": {"coordinates":[-77.495676,38.29729],"type":"Point"}
}