{
  "type": "Feature",
  "properties": {
    "addr:full":"53 Pine Haven Dr Lynchburg VA 24502",
    "addr:housenumber":"53",
    "addr:postcode":"24502",
    "addr:street":"Pine Haven Dr",
    "iso:country":"US",
    "sg:address":"53 Pine Haven Dr",
    "sg:city":"Lynchburg",
    "sg:classifiers":[
        {
            "category":"Professional",
            "subcategory":"Detective & Security Services",
            "type":"Services"
        }
    ],
    "sg:phone":"+1 434 239 2609",
    "sg:postcode":"24502",
    "sg:province":"VA",
    "sg:tags":[
        "guard",
        "patrol"
    ],
    "wof:name":"Richmond Security Svc",
    "wof:placetype":"venue"
},
  "geometry": {"coordinates":[-79.247699,37.327754],"type":"Point"}
}