{
  "type": "Feature",
  "properties": {
    "addr:full":"223 Park Gate Dr SE Leesburg VA 20175",
    "addr:housenumber":"223",
    "addr:postcode":"20175",
    "addr:street":"Park Gate Dr Se",
    "iso:country":"US",
    "sg:address":"223 Park Gate Dr SE",
    "sg:city":"Leesburg",
    "sg:classifiers":[
        {
            "category":"Professional",
            "subcategory":"Computer Services",
            "type":"Services"
        }
    ],
    "sg:phone":"+1 703 669 0325",
    "sg:postcode":"20175",
    "sg:province":"VA",
    "sg:tags":[
        "it"
    ],
    "wof:name":"Quantifex Financial Group Inc",
    "wof:placetype":"venue"
},
  "geometry": {"coordinates":[-77.55648100000001,39.09581],"type":"Point"}
}