{
  "type": "Feature",
  "properties": {
    "addr:full":"391 Patowmack Ct Great Falls VA 22066",
    "addr:housenumber":"391",
    "addr:postcode":"22066",
    "addr:street":"Patowmack Ct",
    "iso:country":"US",
    "sg:address":"391 Patowmack Ct",
    "sg:city":"Great Falls",
    "sg:classifiers":[
        {
            "category":"Professional",
            "type":"Services"
        }
    ],
    "sg:phone":"+1 703 450 4622",
    "sg:postcode":"22066",
    "sg:province":"VA",
    "sg:tags":[
        "establishment"
    ],
    "wof:name":"Anez & Anez",
    "wof:placetype":"venue"
},
  "geometry": {"coordinates":[-77.320863,39.032509],"type":"Point"}
}