{
  "type": "Feature",
  "properties": {
    "addr:full":"14140 Washington Hwy Ashland VA 23047",
    "addr:housenumber":"14140",
    "addr:postcode":"23047",
    "addr:street":"Washington Hwy",
    "iso:country":"US",
    "sg:address":"14140 Washington Hwy",
    "sg:city":"Ashland",
    "sg:classifiers":[
        {
            "category":"Freight",
            "type":"Transportation"
        }
    ],
    "sg:phone":"+1 804 412 2500",
    "sg:postcode":"23047",
    "sg:province":"VA",
    "sg:tags":[
        "delivery"
    ],
    "wof:name":"Delivery & Svc",
    "wof:placetype":"venue"
},
  "geometry": {"coordinates":[-77.470901,37.794236],"type":"Point"}
}