{
  "type": "Feature",
  "properties": {
    "addr:full":"10800 Midlothian Tpke Ste 120 Richmond VA 23235",
    "addr:housenumber":"10800",
    "addr:postcode":"23235",
    "addr:street":"Midlothian Tpke Ste 120",
    "iso:country":"US",
    "sg:address":"10800 Midlothian Tpke Ste 120",
    "sg:city":"Richmond",
    "sg:classifiers":[
        {
            "category":"Social Services",
            "type":"Services"
        },
        {
            "category":"Health Services",
            "subcategory":"Nursing And Care Facility",
            "type":"Services"
        },
        {
            "category":"Health Services",
            "subcategory":"Health Practitioner",
            "type":"Services"
        },
        {
            "category":"Social Services",
            "subcategory":"Adult Care",
            "type":"Services"
        }
    ],
    "sg:phone":"+1 804 332 5359",
    "sg:postcode":"23235",
    "sg:province":"VA",
    "sg:tags":[
        "living",
        "consulting",
        "geriatric",
        "alzheimer's",
        "assisted",
        "elder",
        "home",
        "nurse",
        "eldercare-home"
    ],
    "sg:website":"http://www.brightstarcare.com/find-a-location/va/richmond/",
    "wof:name":"BrightStar - Richmond",
    "wof:placetype":"venue"
},
  "geometry": {"coordinates":[-77.596054,37.506891],"type":"Point"}
}