{
  "type": "Feature",
  "properties": {
    "addr:full":"919 Virginia Ave Harrisonburg VA 22802",
    "addr:housenumber":"919",
    "addr:postcode":"22802",
    "addr:street":"Virginia Ave",
    "iso:country":"US",
    "sg:address":"919 Virginia Ave",
    "sg:city":"Harrisonburg",
    "sg:classifiers":[
        {
            "category":"Retail",
            "subcategory":"Repair Shop",
            "type":"Services"
        }
    ],
    "sg:phone":"+1 540 434 6352",
    "sg:postcode":"22802",
    "sg:province":"VA",
    "sg:tags":[
        "related"
    ],
    "wof:name":"Appliance Repairing",
    "wof:placetype":"venue"
},
  "geometry": {"coordinates":[-78.869803,38.461038],"type":"Point"}
}