{
  "type": "Feature",
  "properties": {
    "iso:country":"US",
    "sg:address":"8540 Cinderbed Rd",
    "sg:city":"Lorton",
    "sg:classifiers":[
        {
            "category":"Professional",
            "subcategory":"Computer Services",
            "type":"Services"
        }
    ],
    "sg:phone":"+1 703 550 5397",
    "sg:postcode":"22079",
    "sg:province":"VA",
    "sg:tags":[
        "graphics"
    ],
    "sg:website":"www.titan.com",
    "wof:name":"Titan Corp",
    "wof:placetype":"venue"
},
  "geometry": {"coordinates":[-77.186046,38.72957],"type":"Point"}
}