{
  "type": "Feature",
  "properties": {
    "addr:full":"8521 Quarry Rd Manassas VA 20110",
    "addr:housenumber":"8521",
    "addr:postcode":"20110",
    "addr:street":"Quarry Rd",
    "iso:country":"US",
    "sg:address":"8521 Quarry Rd",
    "sg:city":"Manassas",
    "sg:classifiers":[
        {
            "category":"Home & Garden",
            "subcategory":"Hardware",
            "type":"Retail Goods"
        }
    ],
    "sg:phone":"+1 703 369 3969",
    "sg:postcode":"20110",
    "sg:province":"VA",
    "sg:tags":[
        "material"
    ],
    "wof:name":"Commonwealth Door & Hardware",
    "wof:placetype":"venue"
},
  "geometry": {"coordinates":[-77.454787,38.755616],"type":"Point"}
}