{
  "type": "Feature",
  "properties": {
    "addr:full":"1100 S Hayes St Arlington VA 22202",
    "addr:housenumber":"1100",
    "addr:postcode":"22202",
    "addr:street":"S Hayes St",
    "iso:country":"US",
    "sg:address":"1100 S Hayes St",
    "sg:city":"Arlington",
    "sg:classifiers":[
        {
            "category":"Restaurant",
            "type":"Food & Drink"
        }
    ],
    "sg:phone":"+1 703 412 5893",
    "sg:postcode":"22202",
    "sg:province":"VA",
    "sg:website":"http://www.tacobell.com",
    "wof:name":"Taco Bell",
    "wof:placetype":"venue"
},
  "geometry": {"coordinates":[-77.05902,38.864344],"type":"Point"}
}