{
  "type": "Feature",
  "properties": {
    "addr:full":"8518 Lewinsville Rd Mc Lean VA 22102",
    "addr:housenumber":"8518",
    "addr:postcode":"22102",
    "addr:street":"Lewinsville Rd",
    "iso:country":"US",
    "sg:address":"8518 Lewinsville Rd",
    "sg:city":"Mc Lean",
    "sg:classifiers":[
        {
            "category":"Professional",
            "subcategory":"Business Services",
            "type":"Services"
        }
    ],
    "sg:phone":"+1 703 748 1545",
    "sg:postcode":"22102",
    "sg:province":"VA",
    "wof:name":"Vector Solutions",
    "wof:placetype":"venue"
},
  "geometry": {"coordinates":[-77.243005,38.938967],"type":"Point"}
}