{
  "type": "Feature",
  "properties": {
    "addr:full":"7502 Justice Dr Zanoni VA 23061",
    "addr:housenumber":"7502",
    "addr:postcode":"23061",
    "addr:street":"Justice Dr Zanoni",
    "iso:country":"US",
    "sg:address":"7502 Justice Dr",
    "sg:city":"Zanoni",
    "sg:classifiers":[
        {
            "category":"Government",
            "subcategory":"Police Station",
            "type":"Public Place"
        }
    ],
    "sg:phone":"+1 804 693 3890",
    "sg:postcode":"23061",
    "sg:province":"VA",
    "sg:tags":[
        "sheriff"
    ],
    "wof:name":"Gloucester Sheriff's Office",
    "wof:placetype":"venue"
},
  "geometry": {"coordinates":[-76.53027400000001,37.415956],"type":"Point"}
}