{
  "type": "Feature",
  "properties": {
    "iso:country":"US",
    "sg:address":"751 Old Brandy Rd",
    "sg:city":"Culpeper",
    "sg:classifiers":[
        {
            "category":"Manufacturing",
            "subcategory":"Metals",
            "type":"Manufacturing & Wholesale Goods"
        }
    ],
    "sg:phone":"+1 540 825 2111",
    "sg:postcode":"22701",
    "sg:province":"VA",
    "sg:tags":[
        "product",
        "wire",
        "fabricated"
    ],
    "wof:name":"Rochester Corp",
    "wof:placetype":"venue"
},
  "geometry": {"coordinates":[-77.981623,38.479418],"type":"Point"}
}