{
  "type": "Feature",
  "properties": {
    "iso:country":"US",
    "sg:address":"430 Crawford St",
    "sg:city":"Portsmouth",
    "sg:classifiers":[
        {
            "category":"Professional",
            "subcategory":"Lawyer & Legal Services",
            "type":"Services"
        }
    ],
    "sg:phone":"+1 757 393 8581",
    "sg:postcode":"23704",
    "sg:province":"VA",
    "wof:name":"Common Wlth Attrney Portsmouth",
    "wof:placetype":"venue"
},
  "geometry": {"coordinates":[-76.29797000000001,36.836351],"type":"Point"}
}