{
  "type": "Feature",
  "properties": {
    "iso:country":"US",
    "sg:address":"12700 Old Stage Rd",
    "sg:city":"Chester",
    "sg:classifiers":[
        {
            "category":"Wholesale",
            "subcategory":"Sporting Goods",
            "type":"Manufacturing & Wholesale Goods"
        }
    ],
    "sg:phone":"+1 804 778 4191",
    "sg:postcode":"23836",
    "sg:province":"VA",
    "wof:name":"Rugged Marine Supplies",
    "wof:placetype":"venue"
},
  "geometry": {"coordinates":[-77.3967,37.35582],"type":"Point"}
}