{
  "type": "Feature",
  "properties": {
    "addr:full":"508 Centerville Tpke N Chesapeake VA 23320",
    "addr:housenumber":"508",
    "addr:postcode":"23320",
    "addr:street":"Centerville Tpke N",
    "iso:country":"US",
    "sg:address":"508 Centerville Tpke N",
    "sg:city":"Chesapeake",
    "sg:classifiers":[
        {
            "category":"Organizations",
            "subcategory":"Religious Organization",
            "type":"Services"
        }
    ],
    "sg:phone":"+1 757 436 7264",
    "sg:postcode":"23320",
    "sg:province":"VA",
    "sg:tags":[
        "church"
    ],
    "sg:website":"www.sgconline.org",
    "wof:name":"Sovereign Grace Church",
    "wof:placetype":"venue"
},
  "geometry": {"coordinates":[-76.185271,36.738876],"type":"Point"}
}