{
  "type": "Feature",
  "properties": {
    "iso:country":"US",
    "sg:address":"4 N 18th St",
    "sg:city":"Richmond",
    "sg:classifiers":[
        {
            "category":"Restaurant",
            "type":"Food & Drink"
        }
    ],
    "sg:phone":"+1 804 788 0713",
    "sg:postcode":"23223",
    "sg:province":"VA",
    "wof:name":"Little Ochi Hide Out",
    "wof:placetype":"venue"
},
  "geometry": {"coordinates":[-77.42747799999999,37.53318],"type":"Point"}
}