{
  "type": "Feature",
  "properties": {
    "iso:country":"US",
    "sg:address":"703 E Market St",
    "sg:city":"Leesburg",
    "sg:classifiers":[
        {
            "category":"Home & Garden",
            "subcategory":"Household Appliances",
            "type":"Retail Goods"
        }
    ],
    "sg:phone":"+1 703 771 7188",
    "sg:postcode":"20176",
    "sg:province":"VA",
    "sg:tags":[
        "cleaners",
        "vacuum"
    ],
    "wof:name":"Vacuum Store",
    "wof:placetype":"venue"
},
  "geometry": {"coordinates":[-77.54919,39.10709],"type":"Point"}
}