{
  "type": "Feature",
  "properties": {
    "addr:full":"10167 Mosby Wood Dr Fairfax VA 22030",
    "addr:postcode":"10167;22030",
    "addr:street":"Wood Dr",
    "iso:country":"US",
    "sg:address":"10167 Mosby Wood Dr",
    "sg:city":"Fairfax",
    "sg:classifiers":[
        {
            "category":"Building & Trades",
            "subcategory":"Construction",
            "type":"Services"
        }
    ],
    "sg:phone":"+1 703 691 1397",
    "sg:postcode":"22030",
    "sg:province":"VA",
    "sg:tags":[
        "general",
        "contractor"
    ],
    "wof:name":"Nile Construction",
    "wof:placetype":"venue"
},
  "geometry": {"coordinates":[-77.292829,38.865386],"type":"Point"}
}