{
  "type": "Feature",
  "properties": {
    "addr:full":"6516 Fairlawn Dr Mc Lean VA 22101",
    "addr:housenumber":"6516",
    "addr:postcode":"22101",
    "addr:street":"Fairlawn Dr",
    "iso:country":"US",
    "sg:address":"6516 Fairlawn Dr",
    "sg:city":"Mc Lean",
    "sg:classifiers":[
        {
            "category":"Social Services",
            "type":"Services"
        }
    ],
    "sg:phone":"+1 703 442 0585",
    "sg:postcode":"22101",
    "sg:province":"VA",
    "sg:tags":[
        "counselor",
        "marriage",
        "family"
    ],
    "wof:name":"Mc Lean Counsleing Ctr",
    "wof:placetype":"venue"
},
  "geometry": {"coordinates":[-77.16677199999999,38.919084],"type":"Point"}
}