{
  "type": "Feature",
  "properties": {
    "iso:country":"US",
    "sg:address":"1612 Laskin Rd",
    "sg:city":"Virginia Beach",
    "sg:classifiers":[
        {
            "category":"Shopping",
            "subcategory":"Clothing, Apparel, & Fashions",
            "type":"Retail Goods"
        }
    ],
    "sg:phone":"+1 757 425 0660",
    "sg:postcode":"23451",
    "sg:province":"VA",
    "sg:tags":[
        "furnishing"
    ],
    "wof:name":"Dan Ryan's For Men",
    "wof:placetype":"venue"
},
  "geometry": {"coordinates":[-76.018086,36.851154],"type":"Point"}
}