{
  "type": "Feature",
  "properties": {
    "iso:country":"US",
    "sg:address":"406 N Cleveland St",
    "sg:city":"Arlington",
    "sg:classifiers":[
        {
            "category":"Shopping",
            "subcategory":"Jewelry",
            "type":"Retail Goods"
        }
    ],
    "sg:phone":"+1 703 522 7234",
    "sg:postcode":"22201",
    "sg:province":"VA",
    "wof:name":"LArtesan Inc",
    "wof:placetype":"venue"
},
  "geometry": {"coordinates":[-77.08857999999999,38.880656],"type":"Point"}
}