{
  "type": "Feature",
  "properties": {
    "addr:full":"3702 Tollgate Ter Falls Church VA 22041",
    "addr:housenumber":"3702",
    "addr:postcode":"22041",
    "addr:street":"Tollgate Ter",
    "iso:country":"US",
    "sg:address":"3702 Tollgate Ter",
    "sg:city":"Falls Church",
    "sg:classifiers":[
        {
            "category":"Health Services",
            "subcategory":"Doctor",
            "type":"Services"
        }
    ],
    "sg:phone":"+1 703 256 5436",
    "sg:postcode":"22041",
    "sg:province":"VA",
    "sg:tags":[
        "medical"
    ],
    "wof:name":"J O Shibuya MD",
    "wof:placetype":"venue"
},
  "geometry": {"coordinates":[-77.14900299999999,38.842842],"type":"Point"}
}