{
  "type": "Feature",
  "properties": {
    "addr:full":"290 Stafford Glen Ct Stafford VA 22554",
    "addr:housenumber":"290",
    "addr:postcode":"22554",
    "addr:street":"Stafford Glen Ct",
    "iso:country":"US",
    "sg:address":"290 Stafford Glen Ct",
    "sg:city":"Stafford",
    "sg:classifiers":[
        {
            "category":"Organizations",
            "subcategory":"Community Association",
            "type":"Services"
        }
    ],
    "sg:phone":"+1 540 659 4461",
    "sg:postcode":"22554",
    "sg:province":"VA",
    "wof:name":"American Legion Post 290",
    "wof:placetype":"venue"
},
  "geometry": {"coordinates":[-77.411536,38.462029],"type":"Point"}
}