{
  "type": "Feature",
  "properties": {
    "addr:full":"151 Kristiansand Dr Williamsburg VA 23188",
    "addr:housenumber":"151",
    "addr:postcode":"23188",
    "addr:street":"Kristiansand Dr",
    "iso:country":"US",
    "sg:address":"151 Kristiansand Dr",
    "sg:city":"Williamsburg",
    "sg:classifiers":[
        {
            "category":"Insurance",
            "subcategory":"Insurance Agent",
            "type":"Services"
        }
    ],
    "sg:phone":"+1 757 564 3929",
    "sg:postcode":"23188",
    "sg:province":"VA",
    "wof:name":"Farm Bureau Insurance",
    "wof:placetype":"venue"
},
  "geometry": {"coordinates":[-76.76715900000001,37.362015],"type":"Point"}
}