{
  "type": "Feature",
  "properties": {
    "addr:full":"9291 Laurel Grove Rd Mechanicsville VA 23116",
    "addr:housenumber":"9291",
    "addr:postcode":"23116",
    "addr:street":"Laurel Grove Rd",
    "iso:country":"US",
    "sg:address":"9291 Laurel Grove Rd",
    "sg:city":"Mechanicsville",
    "sg:classifiers":[
        {
            "category":"Professional",
            "type":"Services"
        },
        {
            "category":"Professional",
            "subcategory":"Accounting & Tax Preparation",
            "type":"Services"
        }
    ],
    "sg:phone":"+1 804 569 1230",
    "sg:postcode":"23116",
    "sg:province":"VA",
    "sg:tags":[
        "return",
        "filing"
    ],
    "wof:name":"C Emily Mc Comsey Ea",
    "wof:placetype":"venue"
},
  "geometry": {"coordinates":[-77.386765,37.658747],"type":"Point"}
}