{
  "type": "Feature",
  "properties": {
    "addr:full":"2812 E Virginia Beach Blvd Norfolk VA 23504",
    "addr:housenumber":"2812",
    "addr:postcode":"23504",
    "addr:street":"E Virginia Beach Blvd",
    "iso:country":"US",
    "sg:address":"2812 E Virginia Beach Blvd",
    "sg:city":"Norfolk",
    "sg:classifiers":[
        {
            "category":"Personal",
            "subcategory":"Barber",
            "type":"Services"
        }
    ],
    "sg:phone":"+1 757 627 8850",
    "sg:postcode":"23504",
    "sg:province":"VA",
    "sg:tags":[
        "shop"
    ],
    "wof:name":"Furious Styles",
    "wof:placetype":"venue"
},
  "geometry": {"coordinates":[-76.253101,36.85242],"type":"Point"}
}