{
  "type": "Feature",
  "properties": {
    "addr:full":"3109 Providence Rd Suffolk VA 23434",
    "addr:housenumber":"3109",
    "addr:postcode":"23434",
    "addr:street":"Providence Rd",
    "iso:country":"US",
    "sg:address":"3109 Providence Rd",
    "sg:city":"Suffolk",
    "sg:classifiers":[
        {
            "category":"Organizations",
            "subcategory":"Religious Organization",
            "type":"Services"
        }
    ],
    "sg:phone":"+1 757 539 9582",
    "sg:postcode":"23434",
    "sg:province":"VA",
    "wof:name":"Providence Untd Methdst Church",
    "wof:placetype":"venue"
},
  "geometry": {"coordinates":[-76.633321,36.78328],"type":"Point"}
}