{
  "type": "Feature",
  "properties": {
    "iso:country":"US",
    "sg:address":"9335 Fletchers Chapel Rd",
    "sg:city":"King George",
    "sg:classifiers":[
        {
            "category":"Arts & Performance",
            "subcategory":"Theater",
            "type":"Entertainment"
        }
    ],
    "sg:phone":"+1 540 775 3438",
    "sg:postcode":"22485",
    "sg:province":"VA",
    "sg:tags":[
        "group"
    ],
    "wof:name":"Creative Entertainment",
    "wof:placetype":"venue"
},
  "geometry": {"coordinates":[-77.323176,38.285608],"type":"Point"}
}