{
  "type": "Feature",
  "properties": {
    "iso:country":"US",
    "sg:address":"901 N Columbus St",
    "sg:city":"Alexandria",
    "sg:classifiers":[
        {
            "category":"Freight",
            "type":"Transportation"
        }
    ],
    "sg:phone":"+1 703 519 9647",
    "sg:postcode":"22314",
    "sg:province":"VA",
    "sg:tags":[
        "delivery"
    ],
    "wof:name":"C J's",
    "wof:placetype":"venue"
},
  "geometry": {"coordinates":[-77.045935,38.81543],"type":"Point"}
}