{
  "type": "Feature",
  "properties": {
    "addr:full":"18292 Forest Rd Forest VA 24551",
    "addr:housenumber":"18292",
    "addr:postcode":"24551",
    "addr:street":"Forest Rd",
    "iso:country":"US",
    "sg:address":"18292 Forest Rd",
    "sg:city":"Forest",
    "sg:classifiers":[
        {
            "category":"Professional",
            "subcategory":"Research",
            "type":"Services"
        }
    ],
    "sg:phone":"+1 434 847 2852",
    "sg:postcode":"24551",
    "sg:province":"VA",
    "sg:tags":[
        "environmental",
        "ecological"
    ],
    "wof:name":"Central Virginia Laboratories",
    "wof:placetype":"venue"
},
  "geometry": {"coordinates":[-79.247602,37.379319],"type":"Point"}
}