{
  "type": "Feature",
  "properties": {
    "addr:full":"642 Arnett Blvd Danville VA 24540",
    "addr:housenumber":"642",
    "addr:postcode":"24540",
    "addr:street":"Arnett Blvd",
    "iso:country":"US",
    "sg:address":"642 Arnett Blvd",
    "sg:city":"Danville",
    "sg:classifiers":[
        {
            "category":"Real Estate",
            "subcategory":"Real Estate Operator",
            "type":"Services"
        }
    ],
    "sg:phone":"+1 434 792 7368",
    "sg:postcode":"24540",
    "sg:province":"VA",
    "sg:tags":[
        "apartment"
    ],
    "wof:name":"Colonial Heights Apartments",
    "wof:placetype":"venue"
},
  "geometry": {"coordinates":[-79.397936,36.615058],"type":"Point"}
}