{
  "type": "Feature",
  "properties": {
    "addr:full":"118 Maryland Ave Portsmouth VA 23707",
    "addr:housenumber":"118",
    "addr:postcode":"23707",
    "addr:street":"Maryland Ave",
    "iso:country":"US",
    "sg:address":"118 Maryland Ave",
    "sg:city":"Portsmouth",
    "sg:classifiers":[
        {
            "category":"Building & Trades",
            "subcategory":"Cleaning & Sanitation",
            "type":"Services"
        }
    ],
    "sg:phone":"+1 757 393 2613",
    "sg:postcode":"23707",
    "sg:province":"VA",
    "sg:tags":[
        "maintenance"
    ],
    "wof:name":"Nhp Cleaning Service",
    "wof:placetype":"venue"
},
  "geometry": {"coordinates":[-76.33463500000001,36.854104],"type":"Point"}
}