{
  "type": "Feature",
  "properties": {
    "addr:full":"750 Sundance Mountain Rd New Market VA 22844",
    "addr:housenumber":"750",
    "addr:postcode":"22844",
    "addr:street":"Sundance Mountain Rd",
    "iso:country":"US",
    "sg:address":"750 Sundance Mountain Rd",
    "sg:city":"New Market",
    "sg:classifiers":[
        {
            "category":"Shopping",
            "subcategory":"Florist",
            "type":"Retail Goods"
        }
    ],
    "sg:phone":"+1 703 892 3070",
    "sg:postcode":"22844",
    "sg:province":"VA",
    "wof:name":"Lucky Floral Design Inc Jack H",
    "wof:placetype":"venue"
},
  "geometry": {"coordinates":[-78.655728,38.616815],"type":"Point"}
}