{
  "type": "Feature",
  "properties": {
    "iso:country":"US",
    "sg:address":"5700 Cleveland St",
    "sg:city":"Virginia Beach",
    "sg:classifiers":[
        {
            "category":"Professional",
            "subcategory":"Business Services",
            "type":"Services"
        }
    ],
    "sg:phone":"+1 757 557 0006",
    "sg:postcode":"23462",
    "sg:province":"VA",
    "wof:name":"Sunbelt Business Advisors of H",
    "wof:placetype":"venue"
},
  "geometry": {"coordinates":[-76.17641399999999,36.847398],"type":"Point"}
}