{
  "type": "Feature",
  "properties": {
    "addr:full":"14000 Willard Rd Chantilly VA 20151",
    "addr:housenumber":"14000",
    "addr:postcode":"20151",
    "addr:street":"Willard Rd",
    "iso:country":"US",
    "sg:address":"14000 Willard Rd",
    "sg:city":"Chantilly",
    "sg:classifiers":[
        {
            "category":"Wholesale",
            "subcategory":"Construction Materials",
            "type":"Manufacturing & Wholesale Goods"
        },
        {
            "category":"Wholesale",
            "subcategory":"Hardware",
            "type":"Manufacturing & Wholesale Goods"
        }
    ],
    "sg:phone":"+1 703 222 2600",
    "sg:postcode":"20151",
    "sg:province":"VA",
    "sg:tags":[
        "commercial",
        "builder",
        "door"
    ],
    "wof:name":"Systems Architectural Doors",
    "wof:placetype":"venue"
},
  "geometry": {"coordinates":[-77.430246,38.886428],"type":"Point"}
}