{
  "type": "Feature",
  "properties": {
    "addr:full":"103 W Federal St Middleburg VA 20117",
    "addr:housenumber":"103",
    "addr:postcode":"20117",
    "addr:street":"W Federal St",
    "iso:country":"US",
    "sg:address":"103 W Federal St",
    "sg:city":"Middleburg",
    "sg:classifiers":[
        {
            "category":"Shopping",
            "subcategory":"Used Merchandise",
            "type":"Retail Goods"
        }
    ],
    "sg:phone":"+1 540 687 8800",
    "sg:postcode":"20117",
    "sg:province":"VA",
    "sg:tags":[
        "shop",
        "consignment"
    ],
    "sg:website":"www.whitelephant.com",
    "wof:name":"White Elephant",
    "wof:placetype":"venue"
},
  "geometry": {"coordinates":[-77.735917,38.967748],"type":"Point"}
}