{
  "type": "Feature",
  "properties": {
    "addr:full":"13 W Boscawen St Winchester VA 22601",
    "addr:housenumber":"13",
    "addr:postcode":"22601",
    "addr:street":"W Boscawen St",
    "iso:country":"US",
    "sg:address":"13 W Boscawen St",
    "sg:city":"Winchester",
    "sg:classifiers":[
        {
            "category":"Restaurant",
            "type":"Food & Drink"
        }
    ],
    "sg:phone":"+1 540 667 3473",
    "sg:postcode":"22601",
    "sg:province":"VA",
    "sg:tags":[
        "eating"
    ],
    "wof:name":"Brown Bag Sandwich Shop",
    "wof:placetype":"venue"
},
  "geometry": {"coordinates":[-78.16609099999999,39.184053],"type":"Point"}
}