{
  "type": "Feature",
  "properties": {
    "iso:country":"US",
    "sg:address":"10350 Portsmouth Rd",
    "sg:city":"Manassas",
    "sg:classifiers":[
        {
            "category":"Banks & Credit Unions",
            "subcategory":"Financial Services",
            "type":"Services"
        }
    ],
    "sg:phone":"+1 703 368 3181",
    "sg:postcode":"20109",
    "sg:province":"VA",
    "sg:tags":[
        "broker",
        "mortgage"
    ],
    "sg:website":"www.loansfast.com",
    "wof:name":"American General Financial Services",
    "wof:placetype":"venue"
},
  "geometry": {"coordinates":[-77.503162,38.780089],"type":"Point"}
}