{
  "type": "Feature",
  "properties": {
    "iso:country":"US",
    "sg:address":"133 Pioneers Rd",
    "sg:city":"Winchester",
    "sg:classifiers":[
        {
            "category":"Wholesale",
            "subcategory":"Durable Goods & Equipment",
            "type":"Manufacturing & Wholesale Goods"
        }
    ],
    "sg:phone":"+1 540 662 7346",
    "sg:postcode":"22602",
    "sg:province":"VA",
    "sg:tags":[
        "wholesaler"
    ],
    "wof:name":"Thomas Sales",
    "wof:placetype":"venue"
},
  "geometry": {"coordinates":[-78.114615,39.185688],"type":"Point"}
}