{
  "type": "Feature",
  "properties": {
    "iso:country":"US",
    "sg:address":"5804 Channing Rd",
    "sg:city":"Springfield",
    "sg:classifiers":[
        {
            "category":"Professional",
            "type":"Services"
        }
    ],
    "sg:phone":"+1 703 644 2225",
    "sg:postcode":"22150",
    "sg:province":"VA",
    "sg:tags":[
        "establishment"
    ],
    "wof:name":"Max Connections",
    "wof:placetype":"venue"
},
  "geometry": {"coordinates":[-77.183869,38.793051],"type":"Point"}
}