{
  "type": "Feature",
  "properties": {
    "addr:full":"3955 Bradwater St Fairfax VA 22031",
    "addr:housenumber":"3955",
    "addr:postcode":"22031",
    "addr:street":"Bradwater St",
    "iso:country":"US",
    "sg:address":"3955 Bradwater St",
    "sg:city":"Fairfax",
    "sg:classifiers":[
        {
            "category":"Organizations",
            "subcategory":"Professional Association",
            "type":"Services"
        }
    ],
    "sg:phone":"+1 703 323 9712",
    "sg:postcode":"22031",
    "sg:province":"VA",
    "wof:name":"Comstock Homeowners Assn",
    "wof:placetype":"venue"
},
  "geometry": {"coordinates":[-77.277835,38.843315],"type":"Point"}
}