{
  "type": "Feature",
  "properties": {
    "addr:full":"143 Red Roof Ln SW Willis VA 24380",
    "addr:housenumber":"143",
    "addr:postcode":"24380",
    "addr:street":"Red Roof Ln Sw",
    "iso:country":"US",
    "sg:address":"143 Red Roof Ln SW",
    "sg:city":"Willis",
    "sg:classifiers":[
        {
            "category":"Professional",
            "subcategory":"Management & Consulting",
            "type":"Services"
        }
    ],
    "sg:phone":"+1 540 593 2000",
    "sg:postcode":"24380",
    "sg:province":"VA",
    "sg:tags":[
        "consultant",
        "business"
    ],
    "wof:name":"Public Management Resources",
    "wof:placetype":"venue"
},
  "geometry": {"coordinates":[-80.426802,36.802507],"type":"Point"}
}