{
  "type": "Feature",
  "properties": {
    "addr:full":"1192 Occoneechee Park Rd Clarksville VA 23927",
    "addr:housenumber":"1192",
    "addr:postcode":"23927",
    "addr:street":"Occoneechee Park Rd",
    "iso:country":"US",
    "sg:address":"1192 Occoneechee Park Rd",
    "sg:city":"Clarksville",
    "sg:classifiers":[
        {
            "category":"Government",
            "subcategory":"Office",
            "type":"Public Place"
        }
    ],
    "sg:phone":"+1 434 374 2210",
    "sg:postcode":"23927",
    "sg:province":"VA",
    "sg:tags":[
        "conservation"
    ],
    "sg:website":"www.dcr.state.va.us",
    "wof:name":"Occoneechee State Park",
    "wof:placetype":"venue"
},
  "geometry": {"coordinates":[-78.52627200000001,36.62349],"type":"Point"}
}