{
  "type": "Feature",
  "properties": {
    "addr:full":"1017 Horsepen Rd Richmond VA 23229",
    "addr:housenumber":"1017",
    "addr:postcode":"23229",
    "addr:street":"Horsepen Rd",
    "iso:country":"US",
    "sg:address":"1017 Horsepen Rd",
    "sg:city":"Richmond",
    "sg:classifiers":[
        {
            "category":"Shopping",
            "subcategory":"Used Merchandise",
            "type":"Retail Goods"
        }
    ],
    "sg:phone":"+1 804 285 0231",
    "sg:postcode":"23229",
    "sg:province":"VA",
    "wof:name":"Dovetail Antiques",
    "wof:placetype":"venue"
},
  "geometry": {"coordinates":[-77.534671,37.592679],"type":"Point"}
}