{
  "type": "Feature",
  "properties": {
    "addr:full":"122 Timberidge Dr Fredericksburg VA 22406",
    "addr:housenumber":"122",
    "addr:postcode":"22406",
    "addr:street":"Timberidge Dr",
    "iso:country":"US",
    "sg:address":"122 Timberidge Dr",
    "sg:city":"Fredericksburg",
    "sg:classifiers":[
        {
            "category":"Retail",
            "subcategory":"Repair Shop",
            "type":"Services"
        }
    ],
    "sg:phone":"+1 540 752 4700",
    "sg:postcode":"22406",
    "sg:province":"VA",
    "sg:tags":[
        "refinishing",
        "furniture"
    ],
    "wof:name":"Furniture Medic Inc",
    "wof:placetype":"venue"
},
  "geometry": {"coordinates":[-77.62649,38.428641],"type":"Point"}
}