{
  "type": "Feature",
  "properties": {
    "addr:full":"221 White Dogwood Dr Chesapeake VA 23322",
    "addr:housenumber":"221",
    "addr:postcode":"23322",
    "addr:street":"White Dogwood Dr",
    "iso:country":"US",
    "sg:address":"221 White Dogwood Dr",
    "sg:city":"Chesapeake",
    "sg:classifiers":[
        {
            "category":"Real Estate",
            "subcategory":"Real Estate Agent",
            "type":"Services"
        }
    ],
    "sg:phone":"+1 757 482 2574",
    "sg:postcode":"23322",
    "sg:province":"VA",
    "wof:name":"David L Jones & Associates",
    "wof:placetype":"venue"
},
  "geometry": {"coordinates":[-76.231622,36.712644],"type":"Point"}
}