{
  "type": "Feature",
  "properties": {
    "addr:full":"2651 Osborne Rd Chester VA 23831",
    "addr:housenumber":"2651",
    "addr:postcode":"23831",
    "addr:street":"Osborne Rd",
    "iso:country":"US",
    "sg:address":"2651 Osborne Rd",
    "sg:city":"Chester",
    "sg:classifiers":[
        {
            "category":"Insurance",
            "subcategory":"Insurance Agent",
            "type":"Services"
        },
        {
            "category":"Insurance",
            "subcategory":"Hazard Insurance",
            "type":"Services"
        },
        {
            "category":"Insurance",
            "subcategory":"Title Insurance",
            "type":"Services"
        },
        {
            "category":"Insurance",
            "subcategory":"Life Insurance",
            "type":"Services"
        }
    ],
    "sg:phone":"+1 804 796 1507",
    "sg:postcode":"23831",
    "sg:province":"VA",
    "sg:tags":[
        "business",
        "auto",
        "commercial",
        "homeowner",
        "motorcycle",
        "renter"
    ],
    "wof:name":"Allstate Insurance Company - Pamela Landen",
    "wof:placetype":"venue"
},
  "geometry": {"coordinates":[-77.418324,37.36786],"type":"Point"}
}