{
  "type": "Feature",
  "properties": {
    "iso:country":"US",
    "sg:address":"9312 Convento Ter",
    "sg:city":"Fairfax",
    "sg:classifiers":[
        {
            "category":"Professional",
            "subcategory":"Management & Consulting",
            "type":"Services"
        }
    ],
    "sg:phone":"+1 703 385 2802",
    "sg:postcode":"22031",
    "sg:province":"VA",
    "wof:name":"Mis Inc",
    "wof:placetype":"venue"
},
  "geometry": {"coordinates":[-77.26761399999999,38.849635],"type":"Point"}
}