{
  "type": "Feature",
  "properties": {
    "addr:full":"4715 Wilson Blvd Arlington VA 22203",
    "addr:housenumber":"4715",
    "addr:postcode":"22203",
    "addr:street":"Wilson Blvd",
    "iso:country":"US",
    "sg:address":"4715 Wilson Blvd",
    "sg:city":"Arlington",
    "sg:classifiers":[
        {
            "category":"Building & Trades",
            "subcategory":"Construction",
            "type":"Services"
        }
    ],
    "sg:phone":"+1 703 675 8700",
    "sg:postcode":"22203",
    "sg:province":"VA",
    "sg:tags":[
        "industrial",
        "contractors-commercial",
        "contractor"
    ],
    "wof:name":"Discovery Contractors Inc",
    "wof:placetype":"venue"
},
  "geometry": {"coordinates":[-77.11851900000001,38.87885],"type":"Point"}
}