{
  "type": "Feature",
  "properties": {
    "addr:full":"11022 Naples Ct Fredericksburg VA 22407",
    "addr:housenumber":"11022",
    "addr:postcode":"22407",
    "addr:street":"Naples Ct",
    "iso:country":"US",
    "sg:address":"11022 Naples Ct",
    "sg:city":"Fredericksburg",
    "sg:classifiers":[
        {
            "category":"Professional",
            "subcategory":"Accounting & Tax Preparation",
            "type":"Services"
        }
    ],
    "sg:phone":"+1 540 220 1830",
    "sg:postcode":"22407",
    "sg:province":"VA",
    "wof:name":"Accounting Edge Inc",
    "wof:placetype":"venue"
},
  "geometry": {"coordinates":[-77.57050700000001,38.261651],"type":"Point"}
}