{
  "type": "Feature",
  "properties": {
    "addr:full":"3812 Concord Pl Roanoke VA 24018",
    "addr:housenumber":"3812",
    "addr:postcode":"24018",
    "addr:street":"Concord Pl",
    "iso:country":"US",
    "sg:address":"3812 Concord Pl",
    "sg:city":"Roanoke",
    "sg:classifiers":[
        {
            "category":"Building & Trades",
            "subcategory":"Construction",
            "type":"Services"
        }
    ],
    "sg:phone":"+1 540 772 8770",
    "sg:postcode":"24018",
    "sg:province":"VA",
    "sg:tags":[
        "contractor"
    ],
    "wof:name":"Roof System",
    "wof:placetype":"venue"
},
  "geometry": {"coordinates":[-80.005472,37.232686],"type":"Point"}
}