{
  "type": "Feature",
  "properties": {
    "addr:full":"10854 Warwick Blvd Newport News VA 23601",
    "addr:housenumber":"10854",
    "addr:postcode":"23601",
    "addr:street":"Warwick Blvd",
    "iso:country":"US",
    "sg:address":"10854 Warwick Blvd",
    "sg:city":"Newport News",
    "sg:classifiers":[
        {
            "category":"Shopping",
            "subcategory":"Shoes",
            "type":"Retail Goods"
        }
    ],
    "sg:phone":"+1 757 596 9252",
    "sg:postcode":"23601",
    "sg:province":"VA",
    "sg:tags":[
        "family"
    ],
    "wof:name":"Adams Shoe Stores Inc",
    "wof:placetype":"venue"
},
  "geometry": {"coordinates":[-76.467386,37.037827],"type":"Point"}
}