{
  "type": "Feature",
  "properties": {
    "iso:country":"US",
    "sg:address":"7871 Heritage Dr",
    "sg:city":"Annandale",
    "sg:classifiers":[
        {
            "category":"Personal",
            "subcategory":"Beauty Salon",
            "type":"Services"
        }
    ],
    "sg:phone":"+1 703 256 8181",
    "sg:postcode":"22003",
    "sg:province":"VA",
    "sg:tags":[
        "shop"
    ],
    "wof:name":"Hair Gossip",
    "wof:placetype":"venue"
},
  "geometry": {"coordinates":[-77.213093,38.825548],"type":"Point"}
}