{
  "type": "Feature",
  "properties": {
    "addr:full":"1333 Jamestown Rd Williamsburg VA 23185",
    "addr:housenumber":"1333",
    "addr:postcode":"23185",
    "addr:street":"Jamestown Rd",
    "iso:country":"US",
    "sg:address":"1333 Jamestown Rd",
    "sg:city":"Williamsburg",
    "sg:classifiers":[
        {
            "category":"Social Services",
            "type":"Services"
        }
    ],
    "sg:phone":"+1 757 229 3535",
    "sg:postcode":"23185",
    "sg:province":"VA",
    "wof:name":"ARC of Greater Williamsburg",
    "wof:placetype":"venue"
},
  "geometry": {"coordinates":[-76.735631,37.250077],"type":"Point"}
}