{
  "type": "Feature",
  "properties": {
    "iso:country":"US",
    "sg:address":"2755 January Ct",
    "sg:city":"Falls Church",
    "sg:classifiers":[
        {
            "category":"Communications",
            "subcategory":"Film & Video Production",
            "type":"Services"
        }
    ],
    "sg:phone":"+1 703 573 4096",
    "sg:postcode":"22043",
    "sg:province":"VA",
    "sg:tags":[
        "motion"
    ],
    "wof:name":"Robert Evans",
    "wof:placetype":"venue"
},
  "geometry": {"coordinates":[-77.212048,38.879975],"type":"Point"}
}