{
  "type": "Feature",
  "properties": {
    "addr:full":"205 E John Redd Blvd Collinsville VA 24078",
    "addr:housenumber":"205",
    "addr:postcode":"24078",
    "addr:street":"E John Redd Blvd",
    "iso:country":"US",
    "sg:address":"205 E John Redd Blvd",
    "sg:city":"Collinsville",
    "sg:classifiers":[
        {
            "category":"Government",
            "subcategory":"Fire Station",
            "type":"Public Place"
        }
    ],
    "sg:phone":"+1 276 647 3711",
    "sg:postcode":"24078",
    "sg:province":"VA",
    "sg:tags":[
        "department"
    ],
    "wof:name":"Collinsville Vol Fire Dept",
    "wof:placetype":"venue"
},
  "geometry": {"coordinates":[-79.91173999999999,36.727407],"type":"Point"}
}