{
  "type": "Feature",
  "properties": {
    "addr:full":"13653 Lee Jackson Memorial Hwy Chantilly VA 20151",
    "addr:housenumber":"13653",
    "addr:postcode":"20151",
    "addr:street":"Lee Jackson Memorial Hwy",
    "iso:country":"US",
    "sg:address":"13653 Lee Jackson Memorial Hwy",
    "sg:city":"Chantilly",
    "sg:classifiers":[
        {
            "category":"Autos & Motor Vehicles",
            "subcategory":"Auto Supplies",
            "type":"Retail Goods"
        }
    ],
    "sg:phone":"+1 703 968 7367",
    "sg:postcode":"20151",
    "sg:province":"VA",
    "sg:tags":[
        "automobile",
        "parts"
    ],
    "wof:name":"Advance Auto Parts Inc",
    "wof:placetype":"venue"
},
  "geometry": {"coordinates":[-77.421086,38.890112],"type":"Point"}
}