{
  "type": "Feature",
  "properties": {
    "iso:country":"US",
    "sg:address":"854 W Main St",
    "sg:city":"Charlottesville",
    "sg:classifiers":[
        {
            "category":"Wholesale",
            "subcategory":"Sporting Goods",
            "type":"Manufacturing & Wholesale Goods"
        }
    ],
    "sg:phone":"+1 434 977 7951",
    "sg:postcode":"22903",
    "sg:province":"VA",
    "wof:name":"Valence Usa LLC",
    "wof:placetype":"venue"
},
  "geometry": {"coordinates":[-78.494204,38.032375],"type":"Point"}
}