{
  "type": "Feature",
  "properties": {
    "addr:full":"923 Aberdeen Rd Hampton VA 23666",
    "addr:housenumber":"923",
    "addr:postcode":"23666",
    "addr:street":"Aberdeen Rd",
    "iso:country":"US",
    "sg:address":"923 Aberdeen Rd",
    "sg:city":"Hampton",
    "sg:classifiers":[
        {
            "category":"Social Services",
            "subcategory":"Child Care",
            "type":"Services"
        }
    ],
    "sg:phone":"+1 757 827 0794",
    "sg:postcode":"23666",
    "sg:province":"VA",
    "sg:tags":[
        "day"
    ],
    "wof:name":"Tots Landing Child Care Center",
    "wof:placetype":"venue"
},
  "geometry": {"coordinates":[-76.403988,37.019739],"type":"Point"}
}