{
  "type": "Feature",
  "properties": {
    "iso:country":"US",
    "sg:address":"4715 Marymead Dr",
    "sg:city":"Fairfax",
    "sg:classifiers":[
        {
            "category":"Manufacturing",
            "subcategory":"Retail Goods",
            "type":"Manufacturing & Wholesale Goods"
        }
    ],
    "sg:phone":"+1 703 631 2021",
    "sg:postcode":"22030",
    "sg:province":"VA",
    "sg:tags":[
        "product",
        "mfg"
    ],
    "wof:name":"Jeanne Leckert Puppet Party",
    "wof:placetype":"venue"
},
  "geometry": {"coordinates":[-77.36279500000001,38.846039],"type":"Point"}
}