{
  "type": "Feature",
  "properties": {
    "addr:full":"12701 Sterling Heights Ln Providence Forge VA 23140",
    "addr:housenumber":"12701",
    "addr:postcode":"23140",
    "addr:street":"Sterling Heights Ln;Forge",
    "iso:country":"US",
    "sg:address":"12701 Sterling Heights Ln",
    "sg:city":"Providence Forge",
    "sg:classifiers":[
        {
            "category":"Retail",
            "subcategory":"Auto Repair",
            "type":"Services"
        }
    ],
    "sg:phone":"+1 804 966 2625",
    "sg:postcode":"23140",
    "sg:province":"VA",
    "sg:tags":[
        "wrecker"
    ],
    "wof:name":"Russell's Towing",
    "wof:placetype":"venue"
},
  "geometry": {"coordinates":[-77.04795900000001,37.412811],"type":"Point"}
}