{
  "type": "Feature",
  "properties": {
    "iso:country":"US",
    "sg:address":"3815 White Post Ct",
    "sg:city":"Alexandria",
    "sg:classifiers":[
        {
            "category":"Professional",
            "subcategory":"Detective & Security Services",
            "type":"Services"
        }
    ],
    "sg:phone":"+1 703 370 1682",
    "sg:postcode":"22304",
    "sg:province":"VA",
    "sg:tags":[
        "equipment",
        "system",
        "consultant"
    ],
    "wof:name":"Wybenga, John",
    "wof:placetype":"venue"
},
  "geometry": {"coordinates":[-77.09613299999999,38.807887],"type":"Point"}
}