{
  "type": "Feature",
  "properties": {
    "addr:full":"1515 N Courthouse Rd Arlington VA 22201",
    "addr:housenumber":"1515",
    "addr:postcode":"22201",
    "addr:street":"N Courthouse Rd",
    "iso:country":"US",
    "sg:address":"1515 N Courthouse Rd",
    "sg:city":"Arlington",
    "sg:classifiers":[
        {
            "category":"Education",
            "subcategory":"School",
            "type":"Public Place"
        }
    ],
    "sg:phone":"+1 703 894 0481",
    "sg:postcode":"22201",
    "sg:province":"VA",
    "sg:website":"www.performanceweb.org",
    "wof:name":"Performance Institute",
    "wof:placetype":"venue"
},
  "geometry": {"coordinates":[-77.083737,38.891196],"type":"Point"}
}