{
  "type": "Feature",
  "properties": {
    "addr:full":"2204 Wood Ibis Way Virginia Beach VA 23455",
    "addr:housenumber":"2204",
    "addr:postcode":"23455",
    "addr:street":"Wood Ibis Way",
    "iso:country":"US",
    "sg:address":"2204 Wood Ibis Way",
    "sg:city":"Virginia Beach",
    "sg:classifiers":[
        {
            "category":"Professional",
            "subcategory":"Advertising",
            "type":"Services"
        }
    ],
    "sg:phone":"+1 757 567 8400",
    "sg:postcode":"23455",
    "sg:province":"VA",
    "sg:tags":[
        "counselor"
    ],
    "wof:name":"LPR Group",
    "wof:placetype":"venue"
},
  "geometry": {"coordinates":[-76.112483,36.909557],"type":"Point"}
}