{
  "type": "Feature",
  "properties": {
    "addr:full":"303 N Main St Chase City VA 23924",
    "addr:housenumber":"303",
    "addr:postcode":"23924",
    "addr:street":"N Main St",
    "iso:country":"US",
    "sg:address":"303 N Main St",
    "sg:city":"Chase City",
    "sg:classifiers":[
        {
            "category":"Organizations",
            "subcategory":"Religious Organization",
            "type":"Services"
        }
    ],
    "sg:phone":"+1 434 372 3447",
    "sg:postcode":"23924",
    "sg:province":"VA",
    "wof:name":"Awesome Faith Temple of P",
    "wof:placetype":"venue"
},
  "geometry": {"coordinates":[-78.45933100000001,36.801028],"type":"Point"}
}