{
  "type": "Feature",
  "properties": {
    "iso:country":"US",
    "sg:address":"2600 Memorial Ave",
    "sg:city":"Lynchburg",
    "sg:classifiers":[
        {
            "category":"Insurance",
            "subcategory":"Insurance Agent",
            "type":"Services"
        }
    ],
    "sg:phone":"+1 434 846 5208",
    "sg:postcode":"24501",
    "sg:province":"VA",
    "sg:website":"www.dewittfinancial.com",
    "wof:name":"De WITT Tarkington Insurance",
    "wof:placetype":"venue"
},
  "geometry": {"coordinates":[-79.16837099999999,37.4006],"type":"Point"}
}