{
  "type": "Feature",
  "properties": {
    "iso:country":"US",
    "sg:address":"410 Mt Jackson Rd",
    "sg:city":"Mt Jackson",
    "sg:classifiers":[
        {
            "category":"Building & Trades",
            "subcategory":"Construction",
            "type":"Services"
        }
    ],
    "sg:phone":"+1 540 856 8203",
    "sg:postcode":"22842",
    "sg:province":"VA",
    "sg:tags":[
        "general",
        "contractor"
    ],
    "wof:name":"Hansberger Construction",
    "wof:placetype":"venue"
},
  "geometry": {"coordinates":[-78.649356,38.76473],"type":"Point"}
}