{
  "type": "Feature",
  "properties": {
    "addr:full":"4008 Walney Rd Chantilly VA 20151",
    "addr:housenumber":"4008",
    "addr:postcode":"20151",
    "addr:street":"Walney Rd",
    "iso:country":"US",
    "sg:address":"4008 Walney Rd",
    "sg:city":"Chantilly",
    "sg:classifiers":[
        {
            "category":"Restaurant",
            "type":"Food & Drink"
        }
    ],
    "sg:phone":"+1 703 961 8989",
    "sg:postcode":"20151",
    "sg:province":"VA",
    "sg:tags":[
        "seafood"
    ],
    "wof:name":"Daves Seafood & Subs Chantilly",
    "wof:placetype":"venue"
},
  "geometry": {"coordinates":[-77.431303,38.893778],"type":"Point"}
}