{
  "type": "Feature",
  "properties": {
    "iso:country":"US",
    "sg:address":"118 Primrose Dr",
    "sg:city":"Blacksburg",
    "sg:classifiers":[
        {
            "category":"Building & Trades",
            "subcategory":"Landscaping Services",
            "type":"Services"
        }
    ],
    "sg:phone":"+1 540 961 1611",
    "sg:postcode":"24060",
    "sg:province":"VA",
    "sg:tags":[
        "pond",
        "product",
        "aquarium",
        "mfg"
    ],
    "wof:name":"Jonas Works Inc",
    "wof:placetype":"venue"
},
  "geometry": {"coordinates":[-80.411711,37.257912],"type":"Point"}
}