{
  "type": "Feature",
  "properties": {
    "addr:full":"1922 Thomson Dr Lynchburg VA 24501",
    "addr:housenumber":"1922",
    "addr:postcode":"24501",
    "addr:street":"Thomson Dr",
    "iso:country":"US",
    "sg:address":"1922 Thomson Dr",
    "sg:city":"Lynchburg",
    "sg:classifiers":[
        {
            "category":"Health Services",
            "subcategory":"Doctor",
            "type":"Services"
        }
    ],
    "sg:phone":"+1 434 846 5733",
    "sg:postcode":"24501",
    "sg:province":"VA",
    "sg:tags":[
        "physician",
        "surgeon"
    ],
    "wof:name":"Lynchburg Anesthesia Assoc",
    "wof:placetype":"venue"
},
  "geometry": {"coordinates":[-79.177662,37.419704],"type":"Point"}
}