{
  "type": "Feature",
  "properties": {
    "addr:full":"5630 Hopkins Rd Richmond VA 23234",
    "addr:housenumber":"5630",
    "addr:postcode":"23234",
    "addr:street":"Hopkins Rd",
    "iso:country":"US",
    "sg:address":"5630 Hopkins Rd",
    "sg:city":"Richmond",
    "sg:classifiers":[
        {
            "category":"Banks & Credit Unions",
            "subcategory":"Bank",
            "type":"Services"
        },
        {
            "category":"Banks & Credit Unions",
            "subcategory":"Financial Services",
            "type":"Services"
        }
    ],
    "sg:phone":"+1 804 743 0390",
    "sg:postcode":"23234",
    "sg:province":"VA",
    "sg:tags":[
        "commercial",
        "loan",
        "saving",
        "mortgage"
    ],
    "sg:website":"https://www.wachovia.com/?DCMP=KNL-CPS-DS-Directory-0703&HBX_PK=Banks&HBX_OU=71",
    "wof:name":"Wachovia Bank",
    "wof:placetype":"venue"
},
  "geometry": {"coordinates":[-77.473159,37.444065],"type":"Point"}
}