{
  "type": "Feature",
  "properties": {
    "iso:country":"US",
    "sg:address":"317 Highland Ave NW",
    "sg:city":"Norton",
    "sg:classifiers":[
        {
            "category":"Professional",
            "subcategory":"Art Services",
            "type":"Services"
        }
    ],
    "sg:phone":"+1 276 679 3555",
    "sg:postcode":"24273",
    "sg:province":"VA",
    "sg:tags":[
        "photography",
        "videography"
    ],
    "wof:name":"John Mccarroll Photography",
    "wof:placetype":"venue"
},
  "geometry": {"coordinates":[-82.630709,36.937314],"type":"Point"}
}