{
  "type": "Feature",
  "properties": {
    "addr:full":"12720 Cople Hwy Kinsale VA 22488",
    "addr:housenumber":"12720",
    "addr:postcode":"22488",
    "addr:street":"Cople Hwy",
    "iso:country":"US",
    "sg:address":"12720 Cople Hwy",
    "sg:city":"Kinsale",
    "sg:classifiers":[
        {
            "category":"Restaurant",
            "type":"Food & Drink"
        }
    ],
    "sg:phone":"+1 804 472 4385",
    "sg:postcode":"22488",
    "sg:province":"VA",
    "wof:name":"Good Eats Cafe",
    "wof:placetype":"venue"
},
  "geometry": {"coordinates":[-76.611834,38.023575],"type":"Point"}
}