{
  "type": "Feature",
  "properties": {
    "iso:country":"US",
    "sg:address":"4925 Boonsboro Rd",
    "sg:city":"Lynchburg",
    "sg:classifiers":[
        {
            "category":"Banks & Credit Unions",
            "subcategory":"Bank",
            "type":"Services"
        }
    ],
    "sg:phone":"+1 434 384 6100",
    "sg:postcode":"24503",
    "sg:province":"VA",
    "sg:tags":[
        "national",
        "commercial"
    ],
    "wof:name":"One Valley Bank",
    "wof:placetype":"venue"
},
  "geometry": {"coordinates":[-79.217207,37.447196],"type":"Point"}
}