{
  "type": "Feature",
  "properties": {
    "iso:country":"US",
    "sg:address":"4005 Williamsburg Ct",
    "sg:city":"Fairfax",
    "sg:classifiers":[
        {
            "category":"Insurance",
            "subcategory":"Hazard Insurance",
            "type":"Services"
        }
    ],
    "sg:phone":"+1 703 278 0010",
    "sg:postcode":"22032",
    "sg:province":"VA",
    "sg:tags":[
        "commercial",
        "business"
    ],
    "wof:name":"Insurance Plus",
    "wof:placetype":"venue"
},
  "geometry": {"coordinates":[-77.282087,38.842334],"type":"Point"}
}