{
  "type": "Feature",
  "properties": {
    "iso:country":"US",
    "sg:address":"6686 Fleet Dr",
    "sg:city":"Alexandria",
    "sg:classifiers":[
        {
            "category":"Shopping",
            "subcategory":"Clothing, Apparel, & Fashions",
            "type":"Retail Goods"
        }
    ],
    "sg:phone":"+1 703 924 6841",
    "sg:postcode":"22310",
    "sg:province":"VA",
    "sg:tags":[
        "furnishing"
    ],
    "wof:name":"Men's Wearhouse",
    "wof:placetype":"venue"
},
  "geometry": {"coordinates":[-77.154213,38.77312],"type":"Point"}
}