{
  "type": "Feature",
  "properties": {
    "addr:full":"4400 Jacobs Bend Dr Richmond VA 23236",
    "addr:housenumber":"4400",
    "addr:postcode":"23236",
    "addr:street":"Jacobs Bend Dr",
    "iso:country":"US",
    "sg:address":"4400 Jacobs Bend Dr",
    "sg:city":"Richmond",
    "sg:classifiers":[
        {
            "category":"Building & Trades",
            "subcategory":"Construction",
            "type":"Services"
        }
    ],
    "sg:phone":"+1 804 675 9259",
    "sg:postcode":"23236",
    "sg:province":"VA",
    "sg:tags":[
        "house"
    ],
    "wof:name":"Home Folks Home Repair",
    "wof:placetype":"venue"
},
  "geometry": {"coordinates":[-77.554051,37.439454],"type":"Point"}
}