{
  "type": "Feature",
  "properties": {
    "addr:full":"10 Starling Ct Richmond VA 23229",
    "addr:housenumber":"10",
    "addr:postcode":"23229",
    "addr:street":"Starling Ct",
    "iso:country":"US",
    "sg:address":"10 Starling Ct",
    "sg:city":"Richmond",
    "sg:classifiers":[
        {
            "category":"Professional",
            "subcategory":"Business Services",
            "type":"Services"
        }
    ],
    "sg:phone":"+1 804 273 6959",
    "sg:postcode":"23229",
    "sg:province":"VA",
    "wof:name":"Mighty Mouse Enterprizes",
    "wof:placetype":"venue"
},
  "geometry": {"coordinates":[-77.56794499999999,37.607015],"type":"Point"}
}