{
  "type": "Feature",
  "properties": {
    "addr:full":"8613 Mayland Dr Henrico VA 23294",
    "addr:housenumber":"8613",
    "addr:postcode":"23294",
    "addr:street":"Mayland Dr",
    "iso:country":"US",
    "sg:address":"8613 Mayland Dr",
    "sg:city":"Henrico",
    "sg:classifiers":[
        {
            "category":"Health Services",
            "subcategory":"Medical Lab",
            "type":"Services"
        }
    ],
    "sg:phone":"+1 434 263 6526",
    "sg:postcode":"23294",
    "sg:province":"VA",
    "sg:tags":[
        "detection",
        "laboratory",
        "testing",
        "drug",
        "equipment"
    ],
    "wof:name":"Workplace Services, Inc",
    "wof:placetype":"venue"
},
  "geometry": {"coordinates":[-77.55520799999999,37.630163],"type":"Point"}
}