{
  "type": "Feature",
  "properties": {
    "iso:country":"US",
    "sg:address":"3810 N Upland St",
    "sg:city":"Arlington",
    "sg:classifiers":[
        {
            "category":"Professional",
            "subcategory":"Management & Consulting",
            "type":"Services"
        }
    ],
    "sg:phone":"+1 703 533 9805",
    "sg:postcode":"22207",
    "sg:province":"VA",
    "sg:tags":[
        "relations",
        "public",
        "business"
    ],
    "sg:website":"www.buckleykaldenbach.com",
    "wof:name":"Buckley & Kaldenbach Inc",
    "wof:placetype":"venue"
},
  "geometry": {"coordinates":[-77.129751,38.920721],"type":"Point"}
}