{
  "type": "Feature",
  "properties": {
    "iso:country":"US",
    "sg:address":"6034 Richmond Hwy",
    "sg:city":"Alexandria",
    "sg:classifiers":[
        {
            "category":"Professional",
            "subcategory":"Business Services",
            "type":"Services"
        }
    ],
    "sg:phone":"+1 703 329 9645",
    "sg:postcode":"22303",
    "sg:province":"VA",
    "wof:name":"Small Business Technology Svcs",
    "wof:placetype":"venue"
},
  "geometry": {"coordinates":[-77.069695,38.785811],"type":"Point"}
}