{
  "type": "Feature",
  "properties": {
    "addr:full":"24 Center St Newport News VA 23606",
    "addr:housenumber":"24",
    "addr:postcode":"23606",
    "addr:street":"Center St",
    "iso:country":"US",
    "sg:address":"24 Center St",
    "sg:city":"Newport News",
    "sg:classifiers":[
        {
            "category":"Home & Garden",
            "subcategory":"Building Materials",
            "type":"Retail Goods"
        }
    ],
    "sg:phone":"+1 757 930 2234",
    "sg:postcode":"23606",
    "sg:province":"VA",
    "wof:name":"Clarke Contracting",
    "wof:placetype":"venue"
},
  "geometry": {"coordinates":[-76.492203,37.079966],"type":"Point"}
}