{
  "type": "Feature",
  "properties": {
    "iso:country":"US",
    "sg:address":"5602 Virginia Beach Blvd",
    "sg:city":"Virginia Beach",
    "sg:classifiers":[
        {
            "category":"Building & Trades",
            "subcategory":"Construction",
            "type":"Services"
        }
    ],
    "sg:phone":"+1 757 499 6130",
    "sg:postcode":"23462",
    "sg:province":"VA",
    "sg:tags":[
        "builder",
        "operative"
    ],
    "wof:name":"Executive Cove Center",
    "wof:placetype":"venue"
},
  "geometry": {"coordinates":[-76.175595,36.853575],"type":"Point"}
}