{
  "type": "Feature",
  "properties": {
    "addr:full":"334 Rose St NW Abingdon VA 24210",
    "addr:housenumber":"334",
    "addr:postcode":"24210",
    "addr:street":"Rose St Nw",
    "iso:country":"US",
    "sg:address":"334 Rose St NW",
    "sg:city":"Abingdon",
    "sg:classifiers":[
        {
            "category":"Organizations",
            "subcategory":"Religious Organization",
            "type":"Services"
        }
    ],
    "sg:phone":"+1 276 628 6396",
    "sg:postcode":"24210",
    "sg:province":"VA",
    "wof:name":"Valley Street Baptist Church",
    "wof:placetype":"venue"
},
  "geometry": {"coordinates":[-81.98053,36.71207],"type":"Point"}
}