{
  "type": "Feature",
  "properties": {
    "iso:country":"US",
    "sg:address":"3845 Bonney Rd",
    "sg:city":"Virginia Beach",
    "sg:classifiers":[
        {
            "category":"Shopping",
            "subcategory":"Clothing, Apparel, & Fashions",
            "type":"Retail Goods"
        }
    ],
    "sg:phone":"+1 757 498 6800",
    "sg:postcode":"23452",
    "sg:province":"VA",
    "wof:name":"All Dat & More",
    "wof:placetype":"venue"
},
  "geometry": {"coordinates":[-76.106663,36.839098],"type":"Point"}
}