{
  "type": "Feature",
  "properties": {
    "addr:full":"3395 Radford Rd Christiansburg VA 24073",
    "addr:housenumber":"3395",
    "addr:postcode":"24073",
    "addr:street":"Radford Rd",
    "iso:country":"US",
    "sg:address":"3395 Radford Rd",
    "sg:city":"Christiansburg",
    "sg:classifiers":[
        {
            "category":"Shopping",
            "subcategory":"Gifts & Souvenirs",
            "type":"Retail Goods"
        }
    ],
    "sg:phone":"+1 540 731 6900",
    "sg:postcode":"24073",
    "sg:province":"VA",
    "sg:tags":[
        "novelty"
    ],
    "wof:name":"Exotic Illusions Inc",
    "wof:placetype":"venue"
},
  "geometry": {"coordinates":[-80.50541699999999,37.128975],"type":"Point"}
}