{
  "type": "Feature",
  "properties": {
    "iso:country":"US",
    "sg:address":"309 Oak Ln",
    "sg:city":"Richmond",
    "sg:classifiers":[
        {
            "category":"Professional",
            "type":"Services"
        }
    ],
    "sg:phone":"+1 804 285 0946",
    "sg:postcode":"23226",
    "sg:province":"VA",
    "wof:name":"Scherer Foundation",
    "wof:placetype":"venue"
},
  "geometry": {"coordinates":[-77.506547,37.571661],"type":"Point"}
}