{
  "type": "Feature",
  "properties": {
    "addr:full":"339 Sumpter St Lynchburg VA 24503",
    "addr:housenumber":"339",
    "addr:postcode":"24503",
    "addr:street":"Sumpter St",
    "iso:country":"US",
    "sg:address":"339 Sumpter St",
    "sg:city":"Lynchburg",
    "sg:classifiers":[
        {
            "category":"Retail",
            "subcategory":"Veterinary Services",
            "type":"Services"
        }
    ],
    "sg:phone":"+1 434 845 8204",
    "sg:postcode":"24503",
    "sg:province":"VA",
    "wof:name":"C W Heath",
    "wof:placetype":"venue"
},
  "geometry": {"coordinates":[-79.169623,37.429273],"type":"Point"}
}