{
  "type": "Feature",
  "properties": {
    "addr:full":"8303 Arlington Blvd Fairfax VA 22031",
    "addr:housenumber":"8303",
    "addr:postcode":"22031",
    "addr:street":"Arlington Blvd",
    "iso:country":"US",
    "sg:address":"8303 Arlington Blvd",
    "sg:city":"Fairfax",
    "sg:classifiers":[
        {
            "category":"Organizations",
            "subcategory":"Professional Association",
            "type":"Services"
        }
    ],
    "sg:phone":"+1 703 698 9651",
    "sg:postcode":"22031",
    "sg:province":"VA",
    "wof:name":"Boulevard Profession Ctr Condo",
    "wof:placetype":"venue"
},
  "geometry": {"coordinates":[-77.229609,38.865432],"type":"Point"}
}