{
  "type": "Feature",
  "properties": {
    "addr:full":"2300 1st Ave Richmond VA 23222",
    "addr:housenumber":"2300",
    "addr:postcode":"23222",
    "addr:street":"1St Ave",
    "iso:country":"US",
    "sg:address":"2300 1st Ave",
    "sg:city":"Richmond",
    "sg:classifiers":[
        {
            "category":"Education",
            "subcategory":"School",
            "type":"Public Place"
        }
    ],
    "sg:phone":"+1 804 329 2515",
    "sg:postcode":"23222",
    "sg:province":"VA",
    "wof:name":"Overby Shppard Elementary Schl",
    "wof:placetype":"venue"
},
  "geometry": {"coordinates":[-77.424162,37.563773],"type":"Point"}
}