{
  "type": "Feature",
  "properties": {
    "iso:country":"US",
    "sg:address":"2424 Rivermont Ave",
    "sg:city":"Lynchburg",
    "sg:classifiers":[
        {
            "category":"Organizations",
            "subcategory":"Religious Organization",
            "type":"Services"
        }
    ],
    "sg:phone":"+1 434 846 3441",
    "sg:postcode":"24503",
    "sg:province":"VA",
    "sg:tags":[
        "church"
    ],
    "sg:website":"www.rivermont.org",
    "wof:name":"Rivermont Presbyterian Church",
    "wof:placetype":"venue"
},
  "geometry": {"coordinates":[-79.168577,37.435828],"type":"Point"}
}