{
  "type": "Feature",
  "properties": {
    "addr:full":"3924 N Landing Rd Virginia Beach VA 23456",
    "addr:housenumber":"3924",
    "addr:postcode":"23456",
    "addr:street":"N Landing Rd",
    "iso:country":"US",
    "sg:address":"3924 N Landing Rd",
    "sg:city":"Virginia Beach",
    "sg:classifiers":[
        {
            "category":"Freight",
            "type":"Transportation"
        }
    ],
    "sg:phone":"+1 757 427 1066",
    "sg:postcode":"23456",
    "sg:province":"VA",
    "sg:tags":[
        "storage",
        "facility"
    ],
    "wof:name":"St Services",
    "wof:placetype":"venue"
},
  "geometry": {"coordinates":[-76.09863,36.724975],"type":"Point"}
}