{
  "type": "Feature",
  "properties": {
    "addr:full":"27 Hobson St Portsmouth VA 23704",
    "addr:housenumber":"27",
    "addr:postcode":"23704",
    "addr:street":"Hobson St",
    "iso:country":"US",
    "sg:address":"27 Hobson St",
    "sg:city":"Portsmouth",
    "sg:classifiers":[
        {
            "category":"Social Services",
            "subcategory":"Child Care",
            "type":"Services"
        }
    ],
    "sg:phone":"+1 757 393 0342",
    "sg:postcode":"23704",
    "sg:province":"VA",
    "sg:tags":[
        "day"
    ],
    "wof:name":"Planning A Day To Remember",
    "wof:placetype":"venue"
},
  "geometry": {"coordinates":[-76.33025600000001,36.817089],"type":"Point"}
}