{
  "type": "Feature",
  "properties": {
    "iso:country":"US",
    "sg:address":"10685 Spotsylvania Ave",
    "sg:city":"Fredericksburg",
    "sg:classifiers":[
        {
            "category":"Real Estate",
            "subcategory":"Real Estate Agent",
            "type":"Services"
        }
    ],
    "sg:phone":"+1 540 834 4499",
    "sg:postcode":"22408",
    "sg:province":"VA",
    "wof:name":"Phillips Team Realty",
    "wof:placetype":"venue"
},
  "geometry": {"coordinates":[-77.49488100000001,38.247858],"type":"Point"}
}