{
  "type": "Feature",
  "properties": {
    "addr:full":"14400 Newton Patent Ct Centreville VA 20120",
    "addr:housenumber":"14400",
    "addr:postcode":"20120",
    "addr:street":"Newton Patent Ct",
    "iso:country":"US",
    "sg:address":"14400 Newton Patent Ct",
    "sg:city":"Centreville",
    "sg:classifiers":[
        {
            "category":"Health Services",
            "subcategory":"Nursing And Care Facility",
            "type":"Services"
        }
    ],
    "sg:phone":"+1 703 266 4504",
    "sg:postcode":"20120",
    "sg:province":"VA",
    "sg:tags":[
        "skilled"
    ],
    "wof:name":"Progressive Nursing",
    "wof:placetype":"venue"
},
  "geometry": {"coordinates":[-77.44640099999999,38.841172],"type":"Point"}
}