{
  "type": "Feature",
  "properties": {
    "addr:full":"2507 E Broad St Richmond VA 23223",
    "addr:housenumber":"2507",
    "addr:postcode":"23223",
    "addr:street":"E Broad St",
    "iso:country":"US",
    "sg:address":"2507 E Broad St",
    "sg:city":"Richmond",
    "sg:classifiers":[
        {
            "category":"Banks & Credit Unions",
            "subcategory":"Investment Brokerage",
            "type":"Services"
        }
    ],
    "sg:phone":"+1 804 648 4420",
    "sg:postcode":"23223",
    "sg:province":"VA",
    "sg:tags":[
        "advisory"
    ],
    "wof:name":"Common Wealth Capital Investments",
    "wof:placetype":"venue"
},
  "geometry": {"coordinates":[-77.418738,37.531616],"type":"Point"}
}