{
  "type": "Feature",
  "properties": {
    "addr:full":"137 N Washington St Falls Church VA 22046",
    "addr:housenumber":"137",
    "addr:postcode":"22046",
    "addr:street":"N Washington St",
    "iso:country":"US",
    "sg:address":"137 N Washington St",
    "sg:city":"Falls Church",
    "sg:classifiers":[
        {
            "category":"Manufacturing",
            "subcategory":"Printing",
            "type":"Manufacturing & Wholesale Goods"
        }
    ],
    "sg:phone":"+1 703 237 0203",
    "sg:postcode":"22046",
    "sg:province":"VA",
    "sg:tags":[
        "newspaper"
    ],
    "wof:name":"Military Living Publications",
    "wof:placetype":"venue"
},
  "geometry": {"coordinates":[-77.17053300000001,38.88278],"type":"Point"}
}