{
  "type": "Feature",
  "properties": {
    "addr:full":"21326 Plank Rd Courtland VA 23837",
    "addr:housenumber":"21326",
    "addr:postcode":"23837",
    "addr:street":"Plank Rd",
    "iso:country":"US",
    "sg:address":"21326 Plank Rd",
    "sg:city":"Courtland",
    "sg:classifiers":[
        {
            "category":"Building & Trades",
            "subcategory":"Construction",
            "type":"Services"
        }
    ],
    "sg:phone":"+1 757 653 2886",
    "sg:postcode":"23837",
    "sg:province":"VA",
    "sg:tags":[
        "grading",
        "contractor"
    ],
    "wof:name":"Southampton County Public Work",
    "wof:placetype":"venue"
},
  "geometry": {"coordinates":[-77.0728,36.728922],"type":"Point"}
}