{
  "type": "Feature",
  "properties": {
    "iso:country":"US",
    "sg:address":"34 Clark Ln",
    "sg:city":"Stafford",
    "sg:classifiers":[
        {
            "category":"Education",
            "subcategory":"Special Training",
            "type":"Public Place"
        }
    ],
    "sg:phone":"+1 540 898 6655",
    "sg:postcode":"22554",
    "sg:province":"VA",
    "wof:name":"Complete Cmbative Concepts LLC",
    "wof:placetype":"venue"
},
  "geometry": {"coordinates":[-77.36887900000001,38.492665],"type":"Point"}
}