{
  "type": "Feature",
  "properties": {
    "addr:full":"125 S Royal Ave Front Royal VA 22630",
    "addr:housenumber":"125",
    "addr:postcode":"22630",
    "addr:street":"S Royal Ave",
    "iso:country":"US",
    "sg:address":"125 S Royal Ave",
    "sg:city":"Front Royal",
    "sg:classifiers":[
        {
            "category":"Autos & Motor Vehicles",
            "subcategory":"Automobile Sales",
            "type":"Retail Goods"
        }
    ],
    "sg:phone":"+1 540 635 2153",
    "sg:postcode":"22630",
    "sg:province":"VA",
    "sg:tags":[
        "car",
        "dealer"
    ],
    "wof:name":"Jack Evans Chevrolet Cadillac",
    "wof:placetype":"venue"
},
  "geometry": {"coordinates":[-78.193618,38.916701],"type":"Point"}
}