{
  "type": "Feature",
  "properties": {
    "addr:full":"9408 Prince William St Manassas VA 20110",
    "addr:housenumber":"9408",
    "addr:postcode":"20110",
    "addr:street":"Prince William St",
    "iso:country":"US",
    "sg:address":"9408 Prince William St",
    "sg:city":"Manassas",
    "sg:classifiers":[
        {
            "category":"Government",
            "subcategory":"Office",
            "type":"Public Place"
        }
    ],
    "sg:phone":"+1 703 361 5606",
    "sg:postcode":"20110",
    "sg:province":"VA",
    "sg:tags":[
        "management"
    ],
    "wof:name":"Occoquan Wtr Shed Mntoring Lab",
    "wof:placetype":"venue"
},
  "geometry": {"coordinates":[-77.475353,38.749338],"type":"Point"}
}