{
  "type": "Feature",
  "properties": {
    "addr:full":"312 N Charlotte Ave Waynesboro VA 22980",
    "addr:housenumber":"312",
    "addr:postcode":"22980",
    "addr:street":"N Charlotte Ave",
    "iso:country":"US",
    "sg:address":"312 N Charlotte Ave",
    "sg:city":"Waynesboro",
    "sg:classifiers":[
        {
            "category":"Home & Garden",
            "subcategory":"Building Materials",
            "type":"Retail Goods"
        }
    ],
    "sg:phone":"+1 540 942 1866",
    "sg:postcode":"22980",
    "sg:province":"VA",
    "sg:tags":[
        "door"
    ],
    "wof:name":"Blue Ridge Doors Inc",
    "wof:placetype":"venue"
},
  "geometry": {"coordinates":[-78.87975,38.071955],"type":"Point"}
}