{
  "type": "Feature",
  "properties": {
    "iso:country":"US",
    "sg:address":"5760 Northampton Blvd",
    "sg:city":"Virginia Beach",
    "sg:classifiers":[
        {
            "category":"Education",
            "subcategory":"Special Training",
            "type":"Public Place"
        }
    ],
    "sg:phone":"+1 757 464 6008",
    "sg:postcode":"23455",
    "sg:province":"VA",
    "sg:tags":[
        "merchant",
        "marine"
    ],
    "wof:name":"Tidewater Schl of Navigations",
    "wof:placetype":"venue"
},
  "geometry": {"coordinates":[-76.183545,36.883545],"type":"Point"}
}