{
  "type": "Feature",
  "properties": {
    "addr:full":"4800 Brook Rd Richmond VA 23227",
    "addr:housenumber":"4800",
    "addr:postcode":"23227",
    "addr:street":"Brook Rd",
    "iso:country":"US",
    "sg:address":"4800 Brook Rd",
    "sg:city":"Richmond",
    "sg:classifiers":[
        {
            "category":"Home & Garden",
            "subcategory":"Garden Supply",
            "type":"Retail Goods"
        }
    ],
    "sg:phone":"+1 804 266 3119",
    "sg:postcode":"23227",
    "sg:province":"VA",
    "sg:tags":[
        "nurseryman"
    ],
    "wof:name":"Azalea Mall Garden Ctr",
    "wof:placetype":"venue"
},
  "geometry": {"coordinates":[-77.453975,37.599178],"type":"Point"}
}