{
  "type": "Feature",
  "properties": {
    "iso:country":"US",
    "sg:address":"6907 Graymoss Ct",
    "sg:city":"Richmond",
    "sg:classifiers":[
        {
            "category":"Home & Garden",
            "subcategory":"Building Materials",
            "type":"Retail Goods"
        }
    ],
    "sg:phone":"+1 804 275 5797",
    "sg:postcode":"23234",
    "sg:province":"VA",
    "wof:name":"Strictly Wallpaper",
    "wof:placetype":"venue"
},
  "geometry": {"coordinates":[-77.486414,37.424036],"type":"Point"}
}