{
  "type": "Feature",
  "properties": {
    "addr:full":"2941 Happy Hollow Rd Blacksburg VA 24060",
    "addr:housenumber":"2941",
    "addr:postcode":"24060",
    "addr:street":"Happy Hollow Rd",
    "iso:country":"US",
    "sg:address":"2941 Happy Hollow Rd",
    "sg:city":"Blacksburg",
    "sg:classifiers":[
        {
            "category":"Shopping",
            "subcategory":"Jewelry",
            "type":"Retail Goods"
        }
    ],
    "sg:phone":"+1 540 552 3243",
    "sg:postcode":"24060",
    "sg:province":"VA",
    "wof:name":"Susan M Sypolt",
    "wof:placetype":"venue"
},
  "geometry": {"coordinates":[-80.39804100000001,37.260589],"type":"Point"}
}