{
  "type": "Feature",
  "properties": {
    "iso:country":"US",
    "sg:address":"7483 Rose Bud Ln",
    "sg:city":"Eastville",
    "sg:classifiers":[
        {
            "category":"Farming",
            "subcategory":"Nursery",
            "type":"Manufacturing & Wholesale Goods"
        }
    ],
    "sg:phone":"+1 757 678 7235",
    "sg:postcode":"23310",
    "sg:province":"VA",
    "sg:tags":[
        "ornamental"
    ],
    "wof:name":"Zieger & Sons Inc",
    "wof:placetype":"venue"
},
  "geometry": {"coordinates":[-75.90297099999999,37.361223],"type":"Point"}
}