{
  "type": "Feature",
  "properties": {
    "iso:country":"US",
    "sg:address":"1301 Grumman Dr",
    "sg:city":"Richmond",
    "sg:classifiers":[
        {
            "category":"Professional",
            "subcategory":"Art Services",
            "type":"Services"
        }
    ],
    "sg:phone":"+1 804 740 5397",
    "sg:postcode":"23229",
    "sg:province":"VA",
    "sg:tags":[
        "graphic",
        "designer"
    ],
    "wof:name":"Redkat Graphics & Photography",
    "wof:placetype":"venue"
},
  "geometry": {"coordinates":[-77.575456,37.604675],"type":"Point"}
}