{
  "type": "Feature",
  "properties": {
    "addr:full":"216 Elizabeth Ct Sterling VA 20164",
    "addr:housenumber":"216",
    "addr:postcode":"20164",
    "addr:street":"Elizabeth Ct",
    "iso:country":"US",
    "sg:address":"216 Elizabeth Ct",
    "sg:city":"Sterling",
    "sg:classifiers":[
        {
            "category":"Professional",
            "subcategory":"Management & Consulting",
            "type":"Services"
        }
    ],
    "sg:phone":"+1 703 444 2655",
    "sg:postcode":"20164",
    "sg:province":"VA",
    "sg:tags":[
        "retail",
        "direct",
        "sales"
    ],
    "wof:name":"Pampered Chef",
    "wof:placetype":"venue"
},
  "geometry": {"coordinates":[-77.38679,38.999589],"type":"Point"}
}