{
  "type": "Feature",
  "properties": {
    "addr:full":"6805 Lois Dr Springfield VA 22150",
    "addr:housenumber":"6805",
    "addr:postcode":"22150",
    "addr:street":"Lois Dr",
    "iso:country":"US",
    "sg:address":"6805 Lois Dr",
    "sg:city":"Springfield",
    "sg:classifiers":[
        {
            "category":"Retail",
            "subcategory":"Auto Repair",
            "type":"Services"
        }
    ],
    "sg:phone":"+1 703 971 9262",
    "sg:postcode":"22150",
    "sg:province":"VA",
    "sg:tags":[
        "wrecker"
    ],
    "wof:name":"Springfield Towing",
    "wof:placetype":"venue"
},
  "geometry": {"coordinates":[-77.180046,38.758159],"type":"Point"}
}