{
  "type": "Feature",
  "properties": {
    "iso:country":"US",
    "sg:address":"9222 John Sevier Rd",
    "sg:city":"New Market",
    "sg:classifiers":[
        {
            "category":"Travel",
            "subcategory":"Hotels & Motels",
            "type":"Entertainment"
        }
    ],
    "sg:phone":"+1 540 740 4266",
    "sg:postcode":"22844",
    "sg:province":"VA",
    "sg:tags":[
        "breakfast",
        "accommodation",
        "bed"
    ],
    "sg:website":"www.crossroadsinnva.com",
    "wof:name":"Cross Roads Inn B & B",
    "wof:placetype":"venue"
},
  "geometry": {"coordinates":[-78.668594,38.651025],"type":"Point"}
}