{
  "type": "Feature",
  "properties": {
    "iso:country":"US",
    "sg:address":"11922 Carters Valley Turn",
    "sg:city":"Chesterfield",
    "sg:classifiers":[
        {
            "category":"Manufacturing",
            "subcategory":"Rubber & Plastics",
            "type":"Manufacturing & Wholesale Goods"
        }
    ],
    "sg:phone":"+1 804 739 3474",
    "sg:postcode":"23838",
    "sg:province":"VA",
    "sg:tags":[
        "plumbing",
        "fixture",
        "mfg"
    ],
    "wof:name":"Priority Services",
    "wof:placetype":"venue"
},
  "geometry": {"coordinates":[-77.64749399999999,37.342389],"type":"Point"}
}