{
  "type": "Feature",
  "properties": {
    "addr:full":"23057 Minerva Dr Ashburn VA 20148",
    "addr:housenumber":"23057",
    "addr:postcode":"20148",
    "addr:street":"Minerva Dr",
    "iso:country":"US",
    "sg:address":"23057 Minerva Dr",
    "sg:city":"Ashburn",
    "sg:classifiers":[
        {
            "category":"Shopping",
            "subcategory":"Pets & Pet Supplies",
            "type":"Retail Goods"
        }
    ],
    "sg:phone":"+1 703 327 0461",
    "sg:postcode":"20148",
    "sg:province":"VA",
    "sg:tags":[
        "furnishing",
        "dog",
        "store",
        "cat"
    ],
    "wof:name":"Atlas Pet Services",
    "wof:placetype":"venue"
},
  "geometry": {"coordinates":[-77.52372699999999,38.976429],"type":"Point"}
}