{
  "type": "Feature",
  "properties": {
    "addr:full":"1820 Memorial Ave SW Roanoke VA 24015",
    "addr:housenumber":"1820",
    "addr:postcode":"24015",
    "addr:street":"Memorial Ave Sw",
    "iso:country":"US",
    "sg:address":"1820 Memorial Ave SW",
    "sg:city":"Roanoke",
    "sg:classifiers":[
        {
            "category":"Retail",
            "subcategory":"Repair Shop",
            "type":"Services"
        }
    ],
    "sg:phone":"+1 540 344 1394",
    "sg:postcode":"24015",
    "sg:province":"VA",
    "wof:name":"Brandon Road TV Service",
    "wof:placetype":"venue"
},
  "geometry": {"coordinates":[-79.975599,37.265801],"type":"Point"}
}