{
  "type": "Feature",
  "properties": {
    "iso:country":"US",
    "sg:address":"2711 Buford Rd Apt 318",
    "sg:city":"Richmond",
    "sg:classifiers":[
        {
            "category":"Building & Trades",
            "subcategory":"Landscaping Services",
            "type":"Services"
        },
        {
            "category":"Professional",
            "subcategory":"Business Services",
            "type":"Services"
        }
    ],
    "sg:phone":"+1 804 502 2320",
    "sg:postcode":"23235",
    "sg:province":"VA",
    "sg:tags":[
        "development",
        "product",
        "designer",
        "designers-industrial",
        "consultant",
        "commercial",
        "design",
        "marketing",
        "landscape"
    ],
    "wof:name":"Inaray Design Group Incorporated",
    "wof:placetype":"venue"
},
  "geometry": {"coordinates":[-77.56141,37.534763],"type":"Point"}
}