{
  "type": "Feature",
  "properties": {
    "addr:full":"1686 Monacan Trail Rd Charlottesville VA 22903",
    "addr:housenumber":"1686",
    "addr:postcode":"22903",
    "addr:street":"Monacan Trail Rd",
    "iso:country":"US",
    "sg:address":"1686 Monacan Trail Rd",
    "sg:city":"Charlottesville",
    "sg:classifiers":[
        {
            "category":"Shopping",
            "subcategory":"Florist",
            "type":"Retail Goods"
        },
        {
            "category":"Farming",
            "subcategory":"Nursery",
            "type":"Manufacturing & Wholesale Goods"
        }
    ],
    "sg:phone":"+1 434 295 2488",
    "sg:postcode":"22903",
    "sg:province":"VA",
    "sg:tags":[
        "plant",
        "greenhouse"
    ],
    "wof:name":"Eltzroth & Thompson Greenhouse",
    "wof:placetype":"venue"
},
  "geometry": {"coordinates":[-78.582024,37.996085],"type":"Point"}
}