{
  "type": "Feature",
  "properties": {
    "iso:country":"US",
    "sg:address":"1212 Highland View Ave",
    "sg:city":"Richmond",
    "sg:classifiers":[
        {
            "category":"Organizations",
            "subcategory":"Membership Organization",
            "type":"Services"
        }
    ],
    "sg:phone":"+1 804 321 1381",
    "sg:postcode":"23222",
    "sg:province":"VA",
    "wof:name":"Northside Outreach Ctr",
    "wof:placetype":"venue"
},
  "geometry": {"coordinates":[-77.41903000000001,37.571071],"type":"Point"}
}