{
  "type": "Feature",
  "properties": {
    "addr:full":"2636 Dean Dr Virginia Beach VA 23452",
    "addr:housenumber":"2636",
    "addr:postcode":"23452",
    "addr:street":"Dean Dr",
    "iso:country":"US",
    "sg:address":"2636 Dean Dr",
    "sg:city":"Virginia Beach",
    "sg:classifiers":[
        {
            "category":"Retail",
            "subcategory":"Auto Repair",
            "type":"Services"
        }
    ],
    "sg:phone":"+1 757 340 0131",
    "sg:postcode":"23452",
    "sg:province":"VA",
    "sg:tags":[
        "repairing",
        "automobile"
    ],
    "wof:name":"Art Walker Auto Svc",
    "wof:placetype":"venue"
},
  "geometry": {"coordinates":[-76.064674,36.838107],"type":"Point"}
}