{
  "type": "Feature",
  "properties": {
    "addr:full":"224 S Creek Ct Collinsville VA 24078",
    "addr:housenumber":"224",
    "addr:postcode":"24078",
    "addr:street":"S Creek Ct",
    "iso:country":"US",
    "sg:address":"224 S Creek Ct",
    "sg:city":"Collinsville",
    "sg:classifiers":[
        {
            "category":"Shopping",
            "subcategory":"Discount & Variety Stores",
            "type":"Retail Goods"
        }
    ],
    "sg:phone":"+1 276 647 4688",
    "sg:postcode":"24078",
    "sg:province":"VA",
    "sg:tags":[
        "merchandise",
        "general"
    ],
    "wof:name":"Mash",
    "wof:placetype":"venue"
},
  "geometry": {"coordinates":[-79.91902,36.714813],"type":"Point"}
}