{
  "type": "Feature",
  "properties": {
    "addr:full":"3962 George Washington Memorial Hwy Yorktown VA 23692",
    "addr:housenumber":"3962",
    "addr:postcode":"23692",
    "addr:street":"George Washington Memorial Hwy",
    "iso:country":"US",
    "sg:address":"3962 George Washington Memorial Hwy",
    "sg:city":"Yorktown",
    "sg:classifiers":[
        {
            "category":"Autos & Motor Vehicles",
            "subcategory":"Fuel & Gas Station",
            "type":"Retail Goods"
        }
    ],
    "sg:phone":"+1 757 833 0601",
    "sg:postcode":"23692",
    "sg:province":"VA",
    "sg:tags":[
        "grocery",
        "station",
        "gasoline"
    ],
    "wof:name":"Racetrac",
    "wof:placetype":"venue"
},
  "geometry": {"coordinates":[-76.45642599999999,37.139449],"type":"Point"}
}