{
  "type": "Feature",
  "properties": {
    "iso:country":"US",
    "sg:address":"2838 Loop Rd",
    "sg:city":"Elkton",
    "sg:classifiers":[
        {
            "category":"Farming",
            "subcategory":"Livestock Farm",
            "type":"Manufacturing & Wholesale Goods"
        }
    ],
    "sg:phone":"+1 540 298 8857",
    "sg:postcode":"22827",
    "sg:province":"VA",
    "sg:tags":[
        "beef",
        "feedlot",
        "cattle"
    ],
    "wof:name":"Clearwater Farm",
    "wof:placetype":"venue"
},
  "geometry": {"coordinates":[-78.576634,38.46758],"type":"Point"}
}