{
  "type": "Feature",
  "properties": {
    "iso:country":"US",
    "sg:address":"1600 Prince St",
    "sg:city":"Alexandria",
    "sg:classifiers":[
        {
            "category":"Real Estate",
            "subcategory":"Real Estate Agent",
            "type":"Services"
        }
    ],
    "sg:phone":"+1 703 549 3370",
    "sg:postcode":"22314",
    "sg:province":"VA",
    "sg:tags":[
        "management"
    ],
    "wof:name":"Property Management Assoc Inc",
    "wof:placetype":"venue"
},
  "geometry": {"coordinates":[-77.05654199999999,38.805128],"type":"Point"}
}