{
  "type": "Feature",
  "properties": {
    "iso:country":"US",
    "sg:address":"4378 Montreux Rd",
    "sg:city":"Warrenton",
    "sg:classifiers":[
        {
            "category":"Banks & Credit Unions",
            "subcategory":"Financial Services",
            "type":"Services"
        }
    ],
    "sg:phone":"+1 540 349 1819",
    "sg:postcode":"20187",
    "sg:province":"VA",
    "sg:tags":[
        "trust",
        "nonprofit",
        "management"
    ],
    "wof:name":"Rice Family Foundation",
    "wof:placetype":"venue"
},
  "geometry": {"coordinates":[-77.69254599999999,38.790191],"type":"Point"}
}