{
  "type": "Feature",
  "properties": {
    "addr:full":"5401 Wingate Way Virginia Beach VA 23464",
    "addr:housenumber":"5401",
    "addr:postcode":"23464",
    "addr:street":"Wingate Way",
    "iso:country":"US",
    "sg:address":"5401 Wingate Way",
    "sg:city":"Virginia Beach",
    "sg:classifiers":[
        {
            "category":"Professional",
            "subcategory":"Research",
            "type":"Services"
        }
    ],
    "sg:phone":"+1 757 479 0557",
    "sg:postcode":"23464",
    "sg:province":"VA",
    "sg:tags":[
        "commercial",
        "physical"
    ],
    "wof:name":"Virginia Coatings Inspections",
    "wof:placetype":"venue"
},
  "geometry": {"coordinates":[-76.183494,36.778424],"type":"Point"}
}