{
  "type": "Feature",
  "properties": {
    "addr:full":"1917 Lafayette Blvd Norfolk VA 23509",
    "addr:housenumber":"1917",
    "addr:postcode":"23509",
    "addr:street":"Lafayette Blvd",
    "iso:country":"US",
    "sg:address":"1917 Lafayette Blvd",
    "sg:city":"Norfolk",
    "sg:classifiers":[
        {
            "category":"Shopping",
            "subcategory":"Clothing, Apparel, & Fashions",
            "type":"Retail Goods"
        }
    ],
    "sg:phone":"+1 757 623 0553",
    "sg:postcode":"23509",
    "sg:province":"VA",
    "sg:tags":[
        "sportswear"
    ],
    "wof:name":"Coston & Coston Ltd",
    "wof:placetype":"venue"
},
  "geometry": {"coordinates":[-76.26337599999999,36.877647],"type":"Point"}
}