{
  "type": "Feature",
  "properties": {
    "addr:full":"437 Twin Ford Loop Stuart VA 24171",
    "addr:housenumber":"437",
    "addr:postcode":"24171",
    "addr:street":"Twin Ford Loop",
    "iso:country":"US",
    "sg:address":"437 Twin Ford Loop",
    "sg:city":"Stuart",
    "sg:classifiers":[
        {
            "category":"Building & Trades",
            "subcategory":"Construction",
            "type":"Services"
        }
    ],
    "sg:phone":"+1 276 694 5324",
    "sg:postcode":"24171",
    "sg:province":"VA",
    "sg:tags":[
        "house"
    ],
    "wof:name":"Cogar Construction LLC",
    "wof:placetype":"venue"
},
  "geometry": {"coordinates":[-80.23029200000001,36.643055],"type":"Point"}
}