{
  "type": "Feature",
  "properties": {
    "addr:full":"860 Omni Blvd Newport News VA 23606",
    "addr:housenumber":"860",
    "addr:postcode":"23606",
    "addr:street":"Omni Blvd",
    "iso:country":"US",
    "sg:address":"860 Omni Blvd",
    "sg:city":"Newport News",
    "sg:classifiers":[
        {
            "category":"Professional",
            "subcategory":"Computer Services",
            "type":"Services"
        }
    ],
    "sg:phone":"+1 757 369 6522",
    "sg:postcode":"23606",
    "sg:province":"VA",
    "sg:tags":[
        "retail",
        "publishing",
        "internet"
    ],
    "wof:name":"Arcamax Inc",
    "wof:placetype":"venue"
},
  "geometry": {"coordinates":[-76.463455,37.089128],"type":"Point"}
}