{
  "type": "Feature",
  "properties": {
    "iso:country":"US",
    "sg:address":"9234 Cardinal Forest Ln",
    "sg:city":"Lorton",
    "sg:classifiers":[
        {
            "category":"Building & Trades",
            "subcategory":"Construction",
            "type":"Services"
        }
    ],
    "sg:phone":"+1 703 864 8069",
    "sg:postcode":"22079",
    "sg:province":"VA",
    "sg:tags":[
        "contractor"
    ],
    "wof:name":"Acoustical Concepts",
    "wof:placetype":"venue"
},
  "geometry": {"coordinates":[-77.229781,38.706196],"type":"Point"}
}