{
  "type": "Feature",
  "properties": {
    "addr:full":"2032 Electric Rd SW Roanoke VA 24018",
    "addr:housenumber":"2032",
    "addr:postcode":"24018",
    "addr:street":"Electric Rd Sw",
    "iso:country":"US",
    "sg:address":"2032 Electric Rd SW",
    "sg:city":"Roanoke",
    "sg:classifiers":[
        {
            "category":"Insurance",
            "subcategory":"Insurance Agent",
            "type":"Services"
        }
    ],
    "sg:phone":"+1 540 989 6969",
    "sg:postcode":"24018",
    "sg:province":"VA",
    "wof:name":"Frank L Schultz",
    "wof:placetype":"venue"
},
  "geometry": {"coordinates":[-80.032177,37.24682],"type":"Point"}
}