{
  "type": "Feature",
  "properties": {
    "iso:country":"US",
    "sg:address":"659 Mississippi Dr",
    "sg:city":"Herndon",
    "sg:classifiers":[
        {
            "category":"Manufacturing",
            "subcategory":"Apparel",
            "type":"Manufacturing & Wholesale Goods"
        }
    ],
    "sg:phone":"+1 703 471 7154",
    "sg:postcode":"20170",
    "sg:province":"VA",
    "sg:tags":[
        "household",
        "furnishing",
        "mfg"
    ],
    "wof:name":"Artistic Slipcovers Uphol",
    "wof:placetype":"venue"
},
  "geometry": {"coordinates":[-77.38983399999999,38.959051],"type":"Point"}
}