{
  "type": "Feature",
  "properties": {
    "iso:country":"US",
    "sg:address":"2110 W Main St",
    "sg:city":"Richmond",
    "sg:classifiers":[
        {
            "category":"Professional",
            "subcategory":"Management & Consulting",
            "type":"Services"
        }
    ],
    "sg:phone":"+1 804 355 5901",
    "sg:postcode":"23220",
    "sg:province":"VA",
    "sg:tags":[
        "medium",
        "marketing",
        "relations",
        "graphic",
        "design",
        "including"
    ],
    "wof:name":"The Public Affairs Office",
    "wof:placetype":"venue"
},
  "geometry": {"coordinates":[-77.468191,37.550116],"type":"Point"}
}