{
  "type": "Feature",
  "properties": {
    "addr:full":"751 Miller Dr SE Leesburg VA 20175",
    "addr:housenumber":"751",
    "addr:postcode":"20175",
    "addr:street":"Miller Dr Se",
    "iso:country":"US",
    "sg:address":"751 Miller Dr SE",
    "sg:city":"Leesburg",
    "sg:classifiers":[
        {
            "category":"Professional",
            "subcategory":"Lawyer & Legal Services",
            "type":"Services"
        }
    ],
    "sg:phone":"+1 703 443 2300",
    "sg:postcode":"20175",
    "sg:province":"VA",
    "sg:tags":[
        "attorney"
    ],
    "wof:name":"Grossman & Assoc",
    "wof:placetype":"venue"
},
  "geometry": {"coordinates":[-77.556074,39.0827],"type":"Point"}
}