{
  "type": "Feature",
  "properties": {
    "iso:country":"US",
    "sg:address":"1699 Oakland Rd",
    "sg:city":"Louisa",
    "sg:classifiers":[
        {
            "category":"Manufacturing",
            "subcategory":"Wood Products",
            "type":"Manufacturing & Wholesale Goods"
        }
    ],
    "sg:phone":"+1 540 967 4637",
    "sg:postcode":"23093",
    "sg:province":"VA",
    "sg:tags":[
        "mfg"
    ],
    "wof:name":"American Wood Fibers",
    "wof:placetype":"venue"
},
  "geometry": {"coordinates":[-78.055629,38.067811],"type":"Point"}
}