{
  "type": "Feature",
  "properties": {
    "addr:full":"2724 Robaleed Way Herndon VA 20171",
    "addr:housenumber":"2724",
    "addr:postcode":"20171",
    "addr:street":"Robaleed Way",
    "iso:country":"US",
    "sg:address":"2724 Robaleed Way",
    "sg:city":"Herndon",
    "sg:classifiers":[
        {
            "category":"Health Services",
            "subcategory":"Clinic",
            "type":"Services"
        }
    ],
    "sg:phone":"+1 703 758 0454",
    "sg:postcode":"20171",
    "sg:province":"VA",
    "wof:name":"Capital Home Health Care Inc",
    "wof:placetype":"venue"
},
  "geometry": {"coordinates":[-77.375353,38.921156],"type":"Point"}
}