{
  "type": "Feature",
  "properties": {
    "addr:full":"10231 Telegraph Rd Glen Allen VA 23059",
    "addr:housenumber":"10231",
    "addr:postcode":"23059",
    "addr:street":"Telegraph Rd",
    "iso:country":"US",
    "sg:address":"10231 Telegraph Rd",
    "sg:city":"Glen Allen",
    "sg:classifiers":[
        {
            "category":"Organizations",
            "subcategory":"Non-profit Organization",
            "type":"Services"
        }
    ],
    "sg:phone":"+1 804 264 5033",
    "sg:postcode":"23059",
    "sg:province":"VA",
    "sg:website":"www.varealtor.com",
    "wof:name":"Virginia Assn Of Realtors",
    "wof:placetype":"venue"
},
  "geometry": {"coordinates":[-77.45109100000001,37.664496],"type":"Point"}
}