{
  "type": "Feature",
  "properties": {
    "iso:country":"US",
    "sg:address":"3250 Broad Street Rd",
    "sg:city":"Gum Spring",
    "sg:classifiers":[
        {
            "category":"Government",
            "subcategory":"Post Office",
            "type":"Public Place"
        }
    ],
    "sg:phone":"+1 804 556 4347",
    "sg:postcode":"23065",
    "sg:province":"VA",
    "wof:name":"US Post Office",
    "wof:placetype":"venue"
},
  "geometry": {"coordinates":[-77.89774800000001,37.776157],"type":"Point"}
}