{
  "type": "Feature",
  "properties": {
    "addr:full":"2700 Virginia Beach Blvd Virginia Beach VA 23452",
    "addr:housenumber":"2700",
    "addr:postcode":"23452",
    "addr:street":"Virginia Beach Blvd",
    "iso:country":"US",
    "sg:address":"2700 Virginia Beach Blvd",
    "sg:city":"Virginia Beach",
    "sg:classifiers":[
        {
            "category":"Professional",
            "subcategory":"Employment Agencies",
            "type":"Services"
        }
    ],
    "sg:phone":"+1 757 499 4111",
    "sg:postcode":"23452",
    "sg:province":"VA",
    "sg:tags":[
        "help",
        "contractor"
    ],
    "wof:name":"Randstad",
    "wof:placetype":"venue"
},
  "geometry": {"coordinates":[-76.067046,36.843257],"type":"Point"}
}