{
  "type": "Feature",
  "properties": {
    "iso:country":"US",
    "sg:address":"128 Middle River Dr",
    "sg:city":"Verona",
    "sg:classifiers":[
        {
            "category":"Organizations",
            "subcategory":"Religious Organization",
            "type":"Services"
        }
    ],
    "sg:phone":"+1 540 248 1776",
    "sg:postcode":"24482",
    "sg:province":"VA",
    "sg:tags":[
        "church"
    ],
    "sg:website":"www.ebc-verona.net",
    "wof:name":"Emmanuel Baptist Church",
    "wof:placetype":"venue"
},
  "geometry": {"coordinates":[-79.014742,38.199309],"type":"Point"}
}