{
  "type": "Feature",
  "properties": {
    "iso:country":"US",
    "sg:address":"7506 Maritime Ln",
    "sg:city":"Springfield",
    "sg:classifiers":[
        {
            "category":"Health Services",
            "subcategory":"Doctor",
            "type":"Services"
        }
    ],
    "sg:phone":"+1 703 455 0125",
    "sg:postcode":"22153",
    "sg:province":"VA",
    "sg:tags":[
        "physician",
        "surgeon"
    ],
    "wof:name":"Continental Cnsltng Grp",
    "wof:placetype":"venue"
},
  "geometry": {"coordinates":[-77.255948,38.751965],"type":"Point"}
}