{
  "type": "Feature",
  "properties": {
    "addr:full":"4975 Columbia Pike Arlington VA 22204",
    "addr:housenumber":"4975",
    "addr:postcode":"22204",
    "addr:street":"Columbia Pike",
    "iso:country":"US",
    "sg:address":"4975 Columbia Pike",
    "sg:city":"Arlington",
    "sg:classifiers":[
        {
            "category":"Building & Trades",
            "subcategory":"Locksmith",
            "type":"Services"
        }
    ],
    "sg:phone":"+1 202 621 2089",
    "sg:postcode":"22204",
    "sg:province":"VA",
    "sg:tags":[
        "key"
    ],
    "wof:name":"Ark Locksmith",
    "wof:placetype":"venue"
},
  "geometry": {"coordinates":[-77.112218,38.856052],"type":"Point"}
}