{
  "type": "Feature",
  "properties": {
    "addr:full":"5704 Plank Rd Natural Bridge VA 24578",
    "addr:housenumber":"5704",
    "addr:postcode":"24578",
    "addr:street":"Plank Rd",
    "iso:country":"US",
    "sg:address":"5704 Plank Rd",
    "sg:city":"Natural Bridge",
    "sg:classifiers":[
        {
            "category":"Real Estate",
            "subcategory":"Real Estate Agent",
            "type":"Services"
        }
    ],
    "sg:phone":"+1 540 291 2816",
    "sg:postcode":"24578",
    "sg:province":"VA",
    "wof:name":"Town & Country Real Estate",
    "wof:placetype":"venue"
},
  "geometry": {"coordinates":[-79.546751,37.689265],"type":"Point"}
}