{
  "type": "Feature",
  "properties": {
    "iso:country":"US",
    "sg:address":"20 Overlook Cir",
    "sg:city":"Palmyra",
    "sg:classifiers":[
        {
            "category":"Professional",
            "type":"Services"
        }
    ],
    "sg:phone":"+1 434 589 1403",
    "sg:postcode":"22963",
    "sg:province":"VA",
    "sg:tags":[
        "pipe",
        "equipment",
        "line"
    ],
    "wof:name":"R & B Supply",
    "wof:placetype":"venue"
},
  "geometry": {"coordinates":[-78.302857,37.920795],"type":"Point"}
}