{
  "type": "Feature",
  "properties": {
    "addr:full":"2807 N Glebe Rd Arlington VA 22207",
    "addr:housenumber":"2807",
    "addr:postcode":"22207",
    "addr:street":"N Glebe Rd",
    "iso:country":"US",
    "sg:address":"2807 N Glebe Rd",
    "sg:city":"Arlington",
    "sg:classifiers":[
        {
            "category":"Education",
            "subcategory":"University",
            "type":"Public Place"
        }
    ],
    "sg:phone":"+1 703 522 5600",
    "sg:postcode":"22207",
    "sg:province":"VA",
    "sg:tags":[
        "college"
    ],
    "sg:website":"www.marymount.edu",
    "wof:name":"Marymount University",
    "wof:placetype":"venue"
},
  "geometry": {"coordinates":[-77.129898,38.905701],"type":"Point"}
}