{
  "type": "Feature",
  "properties": {
    "addr:full":"6532 Walnutdale Ln The Plains VA 20198",
    "addr:housenumber":"6532",
    "addr:postcode":"20198",
    "addr:street":"Walnutdale Ln",
    "iso:country":"US",
    "sg:address":"6532 Walnutdale Ln",
    "sg:city":"The Plains",
    "sg:classifiers":[
        {
            "category":"Building & Trades",
            "subcategory":"Construction",
            "type":"Services"
        }
    ],
    "sg:phone":"+1 540 687 5102",
    "sg:postcode":"20198",
    "sg:province":"VA",
    "sg:tags":[
        "general",
        "contractor"
    ],
    "wof:name":"Walnutdale Building Company",
    "wof:placetype":"venue"
},
  "geometry": {"coordinates":[-77.790843,38.92876],"type":"Point"}
}