{
  "type": "Feature",
  "properties": {
    "addr:full":"1226 Progressive Dr Chesapeake VA 23320",
    "addr:housenumber":"1226",
    "addr:postcode":"23320",
    "addr:street":"Progressive Dr",
    "iso:country":"US",
    "sg:address":"1226 Progressive Dr",
    "sg:city":"Chesapeake",
    "sg:classifiers":[
        {
            "category":"Professional",
            "subcategory":"Employment Agencies",
            "type":"Services"
        }
    ],
    "sg:phone":"+1 757 436 3560",
    "sg:postcode":"23320",
    "sg:province":"VA",
    "sg:tags":[
        "temporary"
    ],
    "wof:name":"Priority Staffing",
    "wof:placetype":"venue"
},
  "geometry": {"coordinates":[-76.230127,36.76594],"type":"Point"}
}