{
  "type": "Feature",
  "properties": {
    "addr:full":"1439 Mallory Ct Norfolk VA 23507",
    "addr:housenumber":"1439",
    "addr:postcode":"23507",
    "addr:street":"Mallory Ct",
    "iso:country":"US",
    "sg:address":"1439 Mallory Ct",
    "sg:city":"Norfolk",
    "sg:classifiers":[
        {
            "category":"Manufacturing",
            "subcategory":"Printing",
            "type":"Manufacturing & Wholesale Goods"
        }
    ],
    "sg:phone":"+1 757 627 2216",
    "sg:postcode":"23507",
    "sg:province":"VA",
    "sg:tags":[
        "newspaper",
        "publishing"
    ],
    "wof:name":"The Downtowner Newspaper",
    "wof:placetype":"venue"
},
  "geometry": {"coordinates":[-76.310316,36.871223],"type":"Point"}
}