{
  "type": "Feature",
  "properties": {
    "iso:country":"US",
    "sg:address":"7201 George Washington Memorial Hwy",
    "sg:city":"Yorktown",
    "sg:classifiers":[
        {
            "category":"Education",
            "subcategory":"Dance Studio",
            "type":"Public Place"
        }
    ],
    "sg:phone":"+1 757 898 1922",
    "sg:postcode":"23692",
    "sg:province":"VA",
    "sg:tags":[
        "instruction",
        "dancing"
    ],
    "wof:name":"Country Bootleggers Studio",
    "wof:placetype":"venue"
},
  "geometry": {"coordinates":[-76.480307,37.178643],"type":"Point"}
}