{
  "type": "Feature",
  "properties": {
    "addr:full":"10502 Dove Ln Stony Creek VA 23882",
    "addr:housenumber":"10502",
    "addr:postcode":"23882",
    "addr:street":"Dove Ln",
    "iso:country":"US",
    "sg:address":"10502 Dove Ln",
    "sg:city":"Stony Creek",
    "sg:classifiers":[
        {
            "category":"Real Estate",
            "subcategory":"Real Estate Operator",
            "type":"Services"
        }
    ],
    "sg:phone":"+1 434 246 5555",
    "sg:postcode":"23882",
    "sg:province":"VA",
    "sg:tags":[
        "property",
        "lessor"
    ],
    "wof:name":"Francis Lewis",
    "wof:placetype":"venue"
},
  "geometry": {"coordinates":[-77.44076,36.894488],"type":"Point"}
}