{
  "type": "Feature",
  "properties": {
    "addr:full":"2501 Salisbury Rd Midlothian VA 23113",
    "addr:housenumber":"2501",
    "addr:postcode":"23113",
    "addr:street":"Salisbury Rd",
    "iso:country":"US",
    "sg:address":"2501 Salisbury Rd",
    "sg:city":"Midlothian",
    "sg:classifiers":[
        {
            "category":"Building & Trades",
            "subcategory":"Construction",
            "type":"Services"
        }
    ],
    "sg:phone":"+1 804 794 1330",
    "sg:postcode":"23113",
    "sg:province":"VA",
    "sg:tags":[
        "contractor"
    ],
    "wof:name":"Richmond Fence LLC",
    "wof:placetype":"venue"
},
  "geometry": {"coordinates":[-77.64240599999999,37.52577],"type":"Point"}
}