{
  "type": "Feature",
  "properties": {
    "addr:full":"261 E Broadway Ave Hopewell VA 23860",
    "addr:housenumber":"261",
    "addr:postcode":"23860",
    "addr:street":"E Broadway Ave",
    "iso:country":"US",
    "sg:address":"261 E Broadway Ave",
    "sg:city":"Hopewell",
    "sg:classifiers":[
        {
            "category":"Real Estate",
            "subcategory":"Real Estate Operator",
            "type":"Services"
        }
    ],
    "sg:phone":"+1 804 458 6121",
    "sg:postcode":"23860",
    "sg:province":"VA",
    "sg:tags":[
        "building",
        "apartment"
    ],
    "wof:name":"Cornez Manor Apartments",
    "wof:placetype":"venue"
},
  "geometry": {"coordinates":[-77.285481,37.304534],"type":"Point"}
}