{
  "type": "Feature",
  "properties": {
    "addr:full":"229 Main St Smithfield VA 23430",
    "addr:housenumber":"229",
    "addr:postcode":"23430",
    "addr:street":"Main St",
    "iso:country":"US",
    "sg:address":"229 Main St",
    "sg:city":"Smithfield",
    "sg:classifiers":[
        {
            "category":"Professional",
            "subcategory":"Lawyer & Legal Services",
            "type":"Services"
        }
    ],
    "sg:phone":"+1 757 357 3050",
    "sg:postcode":"23430",
    "sg:province":"VA",
    "wof:name":"Crook H Woodrow",
    "wof:placetype":"venue"
},
  "geometry": {"coordinates":[-76.632497,36.981359],"type":"Point"}
}