{
  "type": "Feature",
  "properties": {
    "addr:full":"1275 Leaksville Rd Luray VA 22835",
    "addr:housenumber":"1275",
    "addr:postcode":"22835",
    "addr:street":"Leaksville Rd",
    "iso:country":"US",
    "sg:address":"1275 Leaksville Rd",
    "sg:city":"Luray",
    "sg:classifiers":[
        {
            "category":"Building & Trades",
            "subcategory":"Landscaping Services",
            "type":"Services"
        }
    ],
    "sg:phone":"+1 540 743 3717",
    "sg:postcode":"22835",
    "sg:province":"VA",
    "wof:name":"Lawn Core Inc",
    "wof:placetype":"venue"
},
  "geometry": {"coordinates":[-78.499622,38.642003],"type":"Point"}
}