{
  "type": "Feature",
  "properties": {
    "iso:country":"US",
    "sg:address":"7211 Layton Dr",
    "sg:city":"Springfield",
    "sg:classifiers":[
        {
            "category":"Shopping",
            "subcategory":"Hobbies, Toys, & Games",
            "type":"Retail Goods"
        }
    ],
    "sg:phone":"+1 703 971 3382",
    "sg:postcode":"22150",
    "sg:province":"VA",
    "wof:name":"Km Kreative Kraft",
    "wof:placetype":"venue"
},
  "geometry": {"coordinates":[-77.181601,38.758342],"type":"Point"}
}