{
  "type": "Feature",
  "properties": {
    "addr:full":"315 Shawnee Ave E Big Stone Gap VA 24219",
    "addr:housenumber":"315",
    "addr:postcode":"24219",
    "addr:street":"Shawnee Ave E",
    "iso:country":"US",
    "sg:address":"315 Shawnee Ave E",
    "sg:city":"Big Stone Gap",
    "sg:classifiers":[
        {
            "category":"Banks & Credit Unions",
            "subcategory":"Bank",
            "type":"Services"
        }
    ],
    "sg:phone":"+1 276 523 5723",
    "sg:postcode":"24219",
    "sg:province":"VA",
    "sg:tags":[
        "depository",
        "banking",
        "check",
        "cashing"
    ],
    "wof:name":"Southwest Check Advance Inc",
    "wof:placetype":"venue"
},
  "geometry": {"coordinates":[-82.775966,36.867705],"type":"Point"}
}