{
  "type": "Feature",
  "properties": {
    "addr:full":"24420 Batten Bay Ln Carrollton VA 23314",
    "addr:postcode":"24420;23314",
    "addr:street":"Bay Ln",
    "iso:country":"US",
    "sg:address":"24420 Batten Bay Ln",
    "sg:city":"Carrollton",
    "sg:classifiers":[
        {
            "category":"Manufacturing",
            "subcategory":"Tools & Machinery",
            "type":"Manufacturing & Wholesale Goods"
        }
    ],
    "sg:phone":"+1 757 238 3509",
    "sg:postcode":"23314",
    "sg:province":"VA",
    "sg:tags":[
        "mfg"
    ],
    "wof:name":"Virginia Tooling Inc",
    "wof:placetype":"venue"
},
  "geometry": {"coordinates":[-76.501902,36.928814],"type":"Point"}
}