{
  "type": "Feature",
  "properties": {
    "iso:country":"US",
    "sg:address":"3613 Chain Bridge Rd",
    "sg:city":"Fairfax",
    "sg:classifiers":[
        {
            "category":"Professional",
            "subcategory":"Computer Services",
            "type":"Services"
        },
        {
            "category":"Shopping",
            "subcategory":"Computers & Home Electronics",
            "type":"Retail Goods"
        }
    ],
    "sg:phone":"+1 703 273 0058",
    "sg:postcode":"22030",
    "sg:province":"VA",
    "sg:tags":[
        "prepackaged",
        "software"
    ],
    "wof:name":"Method Innovation Corporation",
    "wof:placetype":"venue"
},
  "geometry": {"coordinates":[-77.307349,38.857703],"type":"Point"}
}