{
  "type": "Feature",
  "properties": {
    "iso:country":"US",
    "sg:address":"360 E Main St",
    "sg:city":"Abingdon",
    "sg:classifiers":[
        {
            "category":"Professional",
            "subcategory":"Lawyer & Legal Services",
            "type":"Services"
        }
    ],
    "sg:phone":"+1 276 698 3338",
    "sg:postcode":"24210",
    "sg:province":"VA",
    "sg:tags":[
        "attorney",
        "practice"
    ],
    "wof:name":"Coleman - Pratt Law Office",
    "wof:placetype":"venue"
},
  "geometry": {"coordinates":[-81.96603899999999,36.713535],"type":"Point"}
}