{
  "type": "Feature",
  "properties": {
    "addr:full":"8201 Atlee Rd Mechanicsville VA 23116",
    "addr:housenumber":"8201",
    "addr:postcode":"23116",
    "addr:street":"Atlee Rd",
    "iso:country":"US",
    "sg:address":"8201 Atlee Rd",
    "sg:city":"Mechanicsville",
    "sg:classifiers":[
        {
            "category":"Health Services",
            "subcategory":"Doctor",
            "type":"Services"
        }
    ],
    "sg:phone":"+1 804 730 5222",
    "sg:postcode":"23116",
    "sg:province":"VA",
    "sg:tags":[
        "physician",
        "surgeon",
        "medical"
    ],
    "wof:name":"Arthritis Specialists Ltd",
    "wof:placetype":"venue"
},
  "geometry": {"coordinates":[-77.389275,37.625493],"type":"Point"}
}