{
  "type": "Feature",
  "properties": {
    "iso:country":"US",
    "sg:address":"4514 Old Columbia Pike",
    "sg:city":"Annandale",
    "sg:classifiers":[
        {
            "category":"Personal",
            "subcategory":"Beauty Salon",
            "type":"Services"
        }
    ],
    "sg:phone":"+1 703 354 3555",
    "sg:postcode":"22003",
    "sg:province":"VA",
    "sg:tags":[
        "shop"
    ],
    "wof:name":"Yoosooni Skin Care",
    "wof:placetype":"venue"
},
  "geometry": {"coordinates":[-77.168915,38.829208],"type":"Point"}
}