{
  "type": "Feature",
  "properties": {
    "iso:country":"US",
    "sg:address":"1995 S Main St",
    "sg:city":"Blacksburg",
    "sg:classifiers":[
        {
            "category":"Banks & Credit Unions",
            "subcategory":"Bank",
            "type":"Services"
        }
    ],
    "sg:phone":"+1 540 552 3900",
    "sg:postcode":"24060",
    "sg:province":"VA",
    "sg:tags":[
        "loan",
        "real estate"
    ],
    "wof:name":"Homesouth Mortgage Svc Inc",
    "wof:placetype":"venue"
},
  "geometry": {"coordinates":[-80.398737,37.205837],"type":"Point"}
}