{
  "type": "Feature",
  "properties": {
    "iso:country":"US",
    "sg:address":"601 Meadowbrook Shopping Center",
    "sg:city":"Culpeper",
    "sg:classifiers":[
        {
            "category":"Banks & Credit Unions",
            "subcategory":"Bank",
            "type":"Services"
        }
    ],
    "sg:phone":"+1 540 825 0761",
    "sg:postcode":"22701",
    "sg:province":"VA",
    "sg:tags":[
        "personal",
        "institution"
    ],
    "wof:name":"Citifinancial",
    "wof:placetype":"venue"
},
  "geometry": {"coordinates":[-78.01183899999999,38.458357],"type":"Point"}
}