{
  "type": "Feature",
  "properties": {
    "iso:country":"US",
    "sg:address":"205 S Main St",
    "sg:city":"Broadway",
    "sg:classifiers":[
        {
            "category":"Restaurant",
            "type":"Food & Drink"
        }
    ],
    "sg:phone":"+1 540 828 3598",
    "sg:postcode":"22815",
    "sg:province":"VA",
    "wof:name":"Red Apple Chinese Restaurant",
    "wof:placetype":"venue"
},
  "geometry": {"coordinates":[-78.800591,38.610076],"type":"Point"}
}