{
  "type": "Feature",
  "properties": {
    "addr:full":"2512 Congreve Ct Herndon VA 20171",
    "addr:housenumber":"2512",
    "addr:postcode":"20171",
    "addr:street":"Congreve Ct",
    "iso:country":"US",
    "sg:address":"2512 Congreve Ct",
    "sg:city":"Herndon",
    "sg:classifiers":[
        {
            "category":"Building & Trades",
            "subcategory":"Construction",
            "type":"Services"
        }
    ],
    "sg:phone":"+1 703 758 5811",
    "sg:postcode":"20171",
    "sg:province":"VA",
    "sg:tags":[
        "house"
    ],
    "wof:name":"Excel Construction Group Inc",
    "wof:placetype":"venue"
},
  "geometry": {"coordinates":[-77.38276399999999,38.933138],"type":"Point"}
}