{
  "type": "Feature",
  "properties": {
    "iso:country":"US",
    "sg:address":"12010 Sunrise Valley Dr",
    "sg:city":"Reston",
    "sg:classifiers":[
        {
            "category":"Restaurant",
            "type":"Food & Drink"
        }
    ],
    "sg:phone":"+1 703 243 7567",
    "sg:postcode":"20191",
    "sg:province":"VA",
    "sg:tags":[
        "contract"
    ],
    "wof:name":"Sodexho Inc",
    "wof:placetype":"venue"
},
  "geometry": {"coordinates":[-77.360106,38.946473],"type":"Point"}
}