{
  "type": "Feature",
  "properties": {
    "iso:country":"US",
    "sg:address":"900 Kecoughtan Rd",
    "sg:city":"Hampton",
    "sg:classifiers":[
        {
            "category":"Organizations",
            "subcategory":"Community Association",
            "type":"Services"
        }
    ],
    "sg:phone":"+1 757 245 5943",
    "sg:postcode":"23661",
    "sg:province":"VA",
    "sg:tags":[
        "military"
    ],
    "wof:name":"American Legion",
    "wof:placetype":"venue"
},
  "geometry": {"coordinates":[-76.391081,36.996317],"type":"Point"}
}