{
  "type": "Feature",
  "properties": {
    "addr:full":"3117 Downing Dr Lynchburg VA 24503",
    "addr:housenumber":"3117",
    "addr:postcode":"24503",
    "addr:street":"Downing Dr",
    "iso:country":"US",
    "sg:address":"3117 Downing Dr",
    "sg:city":"Lynchburg",
    "sg:classifiers":[
        {
            "category":"Building & Trades",
            "subcategory":"Plumbing",
            "type":"Services"
        }
    ],
    "sg:phone":"+1 434 384 2719",
    "sg:postcode":"24503",
    "sg:province":"VA",
    "sg:tags":[
        "plumbing",
        "contractor"
    ],
    "wof:name":"Middleton Plumbing Inc",
    "wof:placetype":"venue"
},
  "geometry": {"coordinates":[-79.18208799999999,37.427665],"type":"Point"}
}