{
  "type": "Feature",
  "properties": {
    "addr:full":"2850 King William Rd West Point VA 23181",
    "addr:housenumber":"2850",
    "addr:postcode":"23181",
    "addr:street":"King William Rd",
    "iso:country":"US",
    "sg:address":"2850 King William Rd",
    "sg:city":"West Point",
    "sg:classifiers":[
        {
            "category":"Personal",
            "subcategory":"Beauty Salon",
            "type":"Services"
        }
    ],
    "sg:phone":"+1 804 843 4551",
    "sg:postcode":"23181",
    "sg:province":"VA",
    "sg:tags":[
        "shop"
    ],
    "wof:name":"Hair Affair",
    "wof:placetype":"venue"
},
  "geometry": {"coordinates":[-76.809062,37.550282],"type":"Point"}
}