{
  "type": "Feature",
  "properties": {
    "addr:full":"15 S Berlin Pike Lovettsville VA 20180",
    "addr:housenumber":"15",
    "addr:postcode":"20180",
    "addr:street":"S Berlin Pike",
    "iso:country":"US",
    "sg:address":"15 S Berlin Pike",
    "sg:city":"Lovettsville",
    "sg:classifiers":[
        {
            "category":"Professional",
            "type":"Services"
        }
    ],
    "sg:phone":"+1 540 822 3020",
    "sg:postcode":"20180",
    "sg:province":"VA",
    "sg:tags":[
        "establishment"
    ],
    "wof:name":"Pearson & Pearson",
    "wof:placetype":"venue"
},
  "geometry": {"coordinates":[-77.642433,39.268205],"type":"Point"}
}