{
  "type": "Feature",
  "properties": {
    "iso:country":"US",
    "sg:address":"3132 N Nelson St",
    "sg:city":"Arlington",
    "sg:classifiers":[
        {
            "category":"Manufacturing",
            "subcategory":"Building Materials",
            "type":"Manufacturing & Wholesale Goods"
        }
    ],
    "sg:phone":"+1 703 525 2030",
    "sg:postcode":"22207",
    "sg:province":"VA",
    "sg:tags":[
        "mfg",
        "wood",
        "kitchen",
        "cabinet"
    ],
    "wof:name":"Woodys Woodworking Inc",
    "wof:placetype":"venue"
},
  "geometry": {"coordinates":[-77.114,38.919292],"type":"Point"}
}