{
  "type": "Feature",
  "properties": {
    "addr:full":"7802 Halyard Ter Chesterfield VA 23832",
    "addr:housenumber":"7802",
    "addr:postcode":"23832",
    "addr:street":"Halyard Ter",
    "iso:country":"US",
    "sg:address":"7802 Halyard Ter",
    "sg:city":"Chesterfield",
    "sg:classifiers":[
        {
            "category":"Wholesale",
            "subcategory":"Sporting Goods",
            "type":"Manufacturing & Wholesale Goods"
        }
    ],
    "sg:phone":"+1 804 230 4081",
    "sg:postcode":"23832",
    "sg:province":"VA",
    "sg:tags":[
        "equipment",
        "billiard",
        "supply"
    ],
    "wof:name":"Jak Co Billiard Svc",
    "wof:placetype":"venue"
},
  "geometry": {"coordinates":[-77.68364099999999,37.393087],"type":"Point"}
}