{
  "type": "Feature",
  "properties": {
    "addr:full":"159 Alex Ct Warrenton VA 20186",
    "addr:housenumber":"159",
    "addr:postcode":"20186",
    "addr:street":"Alex Ct",
    "iso:country":"US",
    "sg:address":"159 Alex Ct",
    "sg:city":"Warrenton",
    "sg:classifiers":[
        {
            "category":"Organizations",
            "subcategory":"Religious Organization",
            "type":"Services"
        }
    ],
    "sg:phone":"+1 540 349 1149",
    "sg:postcode":"20186",
    "sg:province":"VA",
    "sg:tags":[
        "clergy"
    ],
    "wof:name":"Shank & Shank",
    "wof:placetype":"venue"
},
  "geometry": {"coordinates":[-77.796077,38.718966],"type":"Point"}
}