{
  "type": "Feature",
  "properties": {
    "addr:full":"933 S Club House Rd Virginia Beach VA 23452",
    "addr:housenumber":"933",
    "addr:postcode":"23452",
    "addr:street":"S Club House Rd",
    "iso:country":"US",
    "sg:address":"933 S Club House Rd",
    "sg:city":"Virginia Beach",
    "sg:classifiers":[
        {
            "category":"Shopping",
            "type":"Retail Goods"
        }
    ],
    "sg:phone":"+1 757 468 9394",
    "sg:postcode":"23452",
    "sg:province":"VA",
    "sg:tags":[
        "resale",
        "product",
        "various"
    ],
    "wof:name":"XYZ Sales",
    "wof:placetype":"venue"
},
  "geometry": {"coordinates":[-76.08177999999999,36.807338],"type":"Point"}
}