{
  "type": "Feature",
  "properties": {
    "addr:full":"936 Professional Pl Chesapeake VA 23320",
    "addr:housenumber":"936",
    "addr:postcode":"23320",
    "addr:street":"Professional Pl",
    "iso:country":"US",
    "sg:address":"936 Professional Pl",
    "sg:city":"Chesapeake",
    "sg:classifiers":[
        {
            "category":"Building & Trades",
            "subcategory":"Construction",
            "type":"Services"
        }
    ],
    "sg:phone":"+1 757 410 5668",
    "sg:postcode":"23320",
    "sg:province":"VA",
    "sg:tags":[
        "general",
        "contractor"
    ],
    "wof:name":"Docs Property Service Inc",
    "wof:placetype":"venue"
},
  "geometry": {"coordinates":[-76.231033,36.763318],"type":"Point"}
}