{
  "type": "Feature",
  "properties": {
    "addr:full":"873 Jennings Ordinary Rd Crewe VA 23930",
    "addr:housenumber":"873",
    "addr:postcode":"23930",
    "addr:street":"Jennings Ordinary Rd",
    "iso:country":"US",
    "sg:address":"873 Jennings Ordinary Rd",
    "sg:city":"Crewe",
    "sg:classifiers":[
        {
            "category":"Restaurant",
            "type":"Food & Drink"
        }
    ],
    "sg:phone":"+1 434 645 9555",
    "sg:postcode":"23930",
    "sg:province":"VA",
    "sg:tags":[
        "parlor",
        "ice",
        "cream"
    ],
    "wof:name":"Billy's Drive In",
    "wof:placetype":"venue"
},
  "geometry": {"coordinates":[-78.165615,37.244141],"type":"Point"}
}