{
  "type": "Feature",
  "properties": {
    "addr:full":"2946 Partlow Rd Partlow VA 22534",
    "addr:housenumber":"2946",
    "addr:postcode":"22534",
    "addr:street":"Partlow Rd",
    "iso:country":"US",
    "sg:address":"2946 Partlow Rd",
    "sg:city":"Partlow",
    "sg:classifiers":[
        {
            "category":"Building & Trades",
            "subcategory":"Plumbing",
            "type":"Services"
        }
    ],
    "sg:phone":"+1 804 448 8698",
    "sg:postcode":"22534",
    "sg:province":"VA",
    "sg:tags":[
        "plumbing",
        "contractor"
    ],
    "wof:name":"Barton's Plumbing",
    "wof:placetype":"venue"
},
  "geometry": {"coordinates":[-77.644256,38.041017],"type":"Point"}
}