{
  "type": "Feature",
  "properties": {
    "addr:full":"114 Carroll Dr Stephens City VA 22655",
    "addr:housenumber":"114",
    "addr:postcode":"22655",
    "addr:street":"Carroll Dr Stephens",
    "iso:country":"US",
    "sg:address":"114 Carroll Dr",
    "sg:city":"Stephens City",
    "sg:classifiers":[
        {
            "category":"Professional",
            "subcategory":"Accounting & Tax Preparation",
            "type":"Services"
        }
    ],
    "sg:phone":"+1 540 869 6778",
    "sg:postcode":"22655",
    "sg:province":"VA",
    "sg:tags":[
        "payroll"
    ],
    "wof:name":"AAA Bookkeeping & Tax Services",
    "wof:placetype":"venue"
},
  "geometry": {"coordinates":[-78.20427599999999,39.087094],"type":"Point"}
}