{
  "type": "Feature",
  "properties": {
    "addr:full":"8300 Sudley Rd Manassas VA 20109",
    "addr:housenumber":"8300",
    "addr:postcode":"20109",
    "addr:street":"Sudley Rd",
    "iso:country":"US",
    "sg:address":"8300 Sudley Rd",
    "sg:city":"Manassas",
    "sg:classifiers":[
        {
            "category":"Personal",
            "type":"Services"
        }
    ],
    "sg:phone":"+1 703 361 4463",
    "sg:postcode":"20109",
    "sg:province":"VA",
    "sg:tags":[
        "specializing",
        "rent",
        "formal",
        "retail",
        "clothing",
        "wear"
    ],
    "wof:name":"After Hours Formalwear",
    "wof:placetype":"venue"
},
  "geometry": {"coordinates":[-77.501817,38.774311],"type":"Point"}
}