{
  "type": "Feature",
  "properties": {
    "addr:full":"8610 Lamont Ct Manassas VA 20110",
    "addr:housenumber":"8610",
    "addr:postcode":"20110",
    "addr:street":"Lamont Ct",
    "iso:country":"US",
    "sg:address":"8610 Lamont Ct",
    "sg:city":"Manassas",
    "sg:classifiers":[
        {
            "category":"Building & Trades",
            "subcategory":"Construction",
            "type":"Services"
        }
    ],
    "sg:phone":"+1 703 369 4893",
    "sg:postcode":"20110",
    "sg:province":"VA",
    "sg:tags":[
        "altering",
        "remodeling",
        "contractor"
    ],
    "wof:name":"B & P Home Improvements",
    "wof:placetype":"venue"
},
  "geometry": {"coordinates":[-77.46257,38.76593],"type":"Point"}
}