{
  "type": "Feature",
  "properties": {
    "iso:country":"US",
    "sg:address":"1 N King St",
    "sg:city":"Leesburg",
    "sg:classifiers":[
        {
            "category":"Professional",
            "subcategory":"Lawyer & Legal Services",
            "type":"Services"
        }
    ],
    "sg:phone":"+1 888 987 9991",
    "sg:postcode":"20176",
    "sg:province":"VA",
    "sg:tags":[
        "plan"
    ],
    "wof:name":"Webster Book Llp",
    "wof:placetype":"venue"
},
  "geometry": {"coordinates":[-77.564537,39.115459],"type":"Point"}
}