{
  "type": "Feature",
  "properties": {
    "addr:full":"701 Port Republic Rd Harrisonburg VA 22801",
    "addr:housenumber":"701",
    "addr:postcode":"22801",
    "addr:street":"Port Republic Rd",
    "iso:country":"US",
    "sg:address":"701 Port Republic Rd",
    "sg:city":"Harrisonburg",
    "sg:classifiers":[
        {
            "category":"Professional",
            "type":"Services"
        }
    ],
    "sg:phone":"+1 540 574 0930",
    "sg:postcode":"22801",
    "sg:province":"VA",
    "sg:tags":[
        "establishment"
    ],
    "wof:name":"Chambers Mart Inc",
    "wof:placetype":"venue"
},
  "geometry": {"coordinates":[-78.874501,38.427035],"type":"Point"}
}