{
  "type": "Feature",
  "properties": {
    "addr:full":"8104 Martha St Alexandria VA 22309",
    "addr:housenumber":"8104",
    "addr:postcode":"22309",
    "addr:street":"Martha St",
    "iso:country":"US",
    "sg:address":"8104 Martha St",
    "sg:city":"Alexandria",
    "sg:classifiers":[
        {
            "category":"Building & Trades",
            "subcategory":"Construction",
            "type":"Services"
        }
    ],
    "sg:phone":"+1 703 799 1678",
    "sg:postcode":"22309",
    "sg:province":"VA",
    "sg:tags":[
        "residential"
    ],
    "wof:name":"Rojo Enterprises Inc",
    "wof:placetype":"venue"
},
  "geometry": {"coordinates":[-77.100696,38.736437],"type":"Point"}
}