{
  "type": "Feature",
  "properties": {
    "addr:full":"10905 Appletree Ln Hopewell VA 23860",
    "addr:housenumber":"10905",
    "addr:postcode":"23860",
    "addr:street":"Appletree Ln",
    "iso:country":"US",
    "sg:address":"10905 Appletree Ln",
    "sg:city":"Hopewell",
    "sg:classifiers":[
        {
            "category":"Professional",
            "subcategory":"Management & Consulting",
            "type":"Services"
        }
    ],
    "sg:phone":"+1 804 541 8602",
    "sg:postcode":"23860",
    "sg:province":"VA",
    "wof:name":"Prince George Company",
    "wof:placetype":"venue"
},
  "geometry": {"coordinates":[-77.210531,37.291437],"type":"Point"}
}