{
  "type": "Feature",
  "properties": {
    "iso:country":"US",
    "sg:address":"309 Columbia St",
    "sg:city":"Portsmouth",
    "sg:classifiers":[
        {
            "category":"Manufacturing",
            "subcategory":"Printing",
            "type":"Manufacturing & Wholesale Goods"
        }
    ],
    "sg:phone":"+1 757 397 4693",
    "sg:postcode":"23704",
    "sg:province":"VA",
    "sg:tags":[
        "commercial"
    ],
    "wof:name":"Printcraft Press Inc",
    "wof:placetype":"venue"
},
  "geometry": {"coordinates":[-76.299886,36.832953],"type":"Point"}
}