{
  "type": "Feature",
  "properties": {
    "iso:country":"US",
    "sg:address":"49 Laguna Rd",
    "sg:city":"Palmyra",
    "sg:classifiers":[
        {
            "category":"Professional",
            "subcategory":"Secretarial Services",
            "type":"Services"
        }
    ],
    "sg:phone":"+1 434 591 0604",
    "sg:postcode":"22963",
    "sg:province":"VA",
    "sg:tags":[
        "reporting"
    ],
    "wof:name":"Doubleshot Legal Video",
    "wof:placetype":"venue"
},
  "geometry": {"coordinates":[-78.323876,37.913849],"type":"Point"}
}