{
  "type": "Feature",
  "properties": {
    "iso:country":"US",
    "sg:address":"2970 Freezeland Rd",
    "sg:city":"Linden",
    "sg:classifiers":[
        {
            "category":"Building & Trades",
            "subcategory":"Construction",
            "type":"Services"
        }
    ],
    "sg:phone":"+1 540 636 8400",
    "sg:postcode":"22642",
    "sg:province":"VA",
    "sg:tags":[
        "house"
    ],
    "wof:name":"Simply Cedar Log Homes",
    "wof:placetype":"venue"
},
  "geometry": {"coordinates":[-78.053026,38.935562],"type":"Point"}
}