{
  "type": "Feature",
  "properties": {
    "addr:full":"1226 Progressive Dr Chesapeake VA 23320",
    "addr:housenumber":"1226",
    "addr:postcode":"23320",
    "addr:street":"Progressive Dr",
    "iso:country":"US",
    "sg:address":"1226 Progressive Dr",
    "sg:city":"Chesapeake",
    "sg:classifiers":[
        {
            "category":"Retail",
            "subcategory":"Auto Rental",
            "type":"Services"
        }
    ],
    "sg:phone":"+1 757 547 8182",
    "sg:postcode":"23320",
    "sg:province":"VA",
    "sg:tags":[
        "renting",
        "truck",
        "leasing"
    ],
    "wof:name":"U-Haul Co",
    "wof:placetype":"venue"
},
  "geometry": {"coordinates":[-76.230127,36.76594],"type":"Point"}
}