{
  "type": "Feature",
  "properties": {
    "addr:full":"14610 Baugher Dr Centreville VA 20120",
    "addr:postcode":"14610;20120",
    "addr:street":"Baugher Dr",
    "iso:country":"US",
    "sg:address":"14610 Baugher Dr",
    "sg:city":"Centreville",
    "sg:classifiers":[
        {
            "category":"Education",
            "subcategory":"Special Training",
            "type":"Public Place"
        }
    ],
    "sg:phone":"+1 703 322 0912",
    "sg:postcode":"20120",
    "sg:province":"VA",
    "sg:tags":[
        "educational"
    ],
    "sg:website":"www.quechuanetwork.org",
    "wof:name":"Education Advocates",
    "wof:placetype":"venue"
},
  "geometry": {"coordinates":[-77.453261,38.864181],"type":"Point"}
}