{
  "type": "Feature",
  "properties": {
    "addr:full":"9756 Turnbuckle Dr Burke VA 22015",
    "addr:housenumber":"9756",
    "addr:postcode":"22015",
    "addr:street":"Turnbuckle Dr",
    "iso:country":"US",
    "sg:address":"9756 Turnbuckle Dr",
    "sg:city":"Burke",
    "sg:classifiers":[
        {
            "category":"Building & Trades",
            "subcategory":"Cleaning & Sanitation",
            "type":"Services"
        }
    ],
    "sg:phone":"+1 703 455 4705",
    "sg:postcode":"22015",
    "sg:province":"VA",
    "sg:tags":[
        "residential",
        "commercial"
    ],
    "wof:name":"Wil-Klean",
    "wof:placetype":"venue"
},
  "geometry": {"coordinates":[-77.27955900000001,38.765781],"type":"Point"}
}