{
  "type": "Feature",
  "properties": {
    "iso:country":"US",
    "sg:address":"8150 Leesburg Pike",
    "sg:city":"Vienna",
    "sg:classifiers":[
        {
            "category":"Professional",
            "subcategory":"Management & Consulting",
            "type":"Services"
        }
    ],
    "sg:phone":"+1 703 760 8866",
    "sg:postcode":"22182",
    "sg:province":"VA",
    "sg:tags":[
        "consultant",
        "law",
        "business",
        "enforcement"
    ],
    "sg:website":"www.lafayettegroup.com",
    "wof:name":"Lafayette Group Inc",
    "wof:placetype":"venue"
},
  "geometry": {"coordinates":[-77.22668299999999,38.915917],"type":"Point"}
}