{
  "type": "Feature",
  "properties": {
    "iso:country":"US",
    "sg:address":"1238 Bay St",
    "sg:city":"Portsmouth",
    "sg:classifiers":[
        {
            "category":"Ferry",
            "type":"Transportation"
        }
    ],
    "sg:phone":"+1 757 393 4735",
    "sg:postcode":"23704",
    "sg:province":"VA",
    "sg:tags":[
        "tours",
        "sightseeing"
    ],
    "wof:name":"Carrie B",
    "wof:placetype":"venue"
},
  "geometry": {"coordinates":[-76.314924,36.845211],"type":"Point"}
}