{
  "type": "Feature",
  "properties": {
    "iso:country":"US",
    "sg:address":"2332 N Main St",
    "sg:city":"Danville",
    "sg:classifiers":[
        {
            "category":"Autos & Motor Vehicles",
            "subcategory":"Automobile Sales",
            "type":"Retail Goods"
        }
    ],
    "sg:phone":"+1 434 836 7970",
    "sg:postcode":"24540",
    "sg:province":"VA",
    "sg:tags":[
        "car",
        "dealer"
    ],
    "wof:name":"Auto Max Of Va Inc",
    "wof:placetype":"venue"
},
  "geometry": {"coordinates":[-79.383312,36.618845],"type":"Point"}
}