{
  "type": "Feature",
  "properties": {
    "addr:full":"107 E Davis St Culpeper VA 22701",
    "addr:housenumber":"107",
    "addr:postcode":"22701",
    "addr:street":"E Davis St",
    "iso:country":"US",
    "sg:address":"107 E Davis St",
    "sg:city":"Culpeper",
    "sg:classifiers":[
        {
            "category":"Shopping",
            "subcategory":"Used Merchandise",
            "type":"Retail Goods"
        }
    ],
    "sg:phone":"+1 540 829 6814",
    "sg:postcode":"22701",
    "sg:province":"VA",
    "sg:tags":[
        "antique"
    ],
    "wof:name":"Barter Post At Davis Street",
    "wof:placetype":"venue"
},
  "geometry": {"coordinates":[-77.99607399999999,38.473232],"type":"Point"}
}