{
  "type": "Feature",
  "properties": {
    "addr:full":"22200 Benhams Rd Bristol VA 24202",
    "addr:postcode":"22200;24202",
    "addr:street":"Benhams Rd",
    "iso:country":"US",
    "sg:address":"22200 Benhams Rd",
    "sg:city":"Bristol",
    "sg:classifiers":[
        {
            "category":"Retail",
            "subcategory":"Auto Repair",
            "type":"Services"
        }
    ],
    "sg:phone":"+1 276 669 3935",
    "sg:postcode":"24202",
    "sg:province":"VA",
    "sg:tags":[
        "wrecker"
    ],
    "wof:name":"Booher Wrecker Svc",
    "wof:placetype":"venue"
},
  "geometry": {"coordinates":[-82.18461499999999,36.628719],"type":"Point"}
}