{
  "type": "Feature",
  "properties": {
    "addr:full":"708 Wilson Ave NW Coeburn VA 24230",
    "addr:housenumber":"708",
    "addr:postcode":"coeburn;24230",
    "addr:street":"Wilson Ave Nw",
    "iso:country":"US",
    "sg:address":"708 Wilson Ave NW",
    "sg:city":"Coeburn",
    "sg:classifiers":[
        {
            "category":"Social Services",
            "subcategory":"Child Care",
            "type":"Services"
        }
    ],
    "sg:phone":"+1 276 395 8140",
    "sg:postcode":"24230",
    "sg:province":"VA",
    "sg:tags":[
        "day"
    ],
    "wof:name":"Munchkin Manor Day Care",
    "wof:placetype":"venue"
},
  "geometry": {"coordinates":[-82.471575,36.950645],"type":"Point"}
}