{
  "type": "Feature",
  "properties": {
    "addr:full":"901 Stony Creek Rd Lynch Station VA 24571",
    "addr:housenumber":"901",
    "addr:postcode":"24571",
    "addr:street":"Stony Creek Rd",
    "iso:country":"US",
    "sg:address":"901 Stony Creek Rd",
    "sg:city":"Lynch Station",
    "sg:classifiers":[
        {
            "category":"Building & Trades",
            "subcategory":"Electrical",
            "type":"Services"
        }
    ],
    "sg:phone":"+1 434 369 7146",
    "sg:postcode":"24571",
    "sg:province":"VA",
    "sg:tags":[
        "electric",
        "contractor"
    ],
    "wof:name":"Roller Electric Co",
    "wof:placetype":"venue"
},
  "geometry": {"coordinates":[-79.43295999999999,37.072874],"type":"Point"}
}