{
  "type": "Feature",
  "properties": {
    "addr:full":"13640 Brandy Oaks Dr Chesterfield VA 23832",
    "addr:housenumber":"13640",
    "addr:postcode":"23832",
    "addr:street":"Brandy Oaks Dr",
    "iso:country":"US",
    "sg:address":"13640 Brandy Oaks Dr",
    "sg:city":"Chesterfield",
    "sg:classifiers":[
        {
            "category":"Banks & Credit Unions",
            "subcategory":"Financial Services",
            "type":"Services"
        }
    ],
    "sg:phone":"+1 804 739 4182",
    "sg:postcode":"23832",
    "sg:province":"VA",
    "sg:tags":[
        "trust",
        "management"
    ],
    "wof:name":"Mary E Krohn Trust",
    "wof:placetype":"venue"
},
  "geometry": {"coordinates":[-77.65734500000001,37.357733],"type":"Point"}
}