{
  "type": "Feature",
  "properties": {
    "iso:country":"US",
    "sg:address":"7168 Harry L Brown Rd",
    "sg:city":"Fairlawn",
    "sg:classifiers":[
        {
            "category":"Government",
            "subcategory":"Office",
            "type":"Public Place"
        }
    ],
    "sg:phone":"+1 540 639 9096",
    "sg:postcode":"24141",
    "sg:province":"VA",
    "wof:name":"New River Regional Police Acad",
    "wof:placetype":"venue"
},
  "geometry": {"coordinates":[-80.59179399999999,37.141218],"type":"Point"}
}