{
  "type": "Feature",
  "properties": {
    "iso:country":"US",
    "sg:address":"529 Cedar Rd",
    "sg:city":"Chesapeake",
    "sg:classifiers":[
        {
            "category":"Professional",
            "type":"Services"
        }
    ],
    "sg:phone":"+1 757 436 4187",
    "sg:postcode":"23322",
    "sg:province":"VA",
    "sg:tags":[
        "establishment"
    ],
    "wof:name":"VMH Inc",
    "wof:placetype":"venue"
},
  "geometry": {"coordinates":[-76.254955,36.713117],"type":"Point"}
}