{
  "type": "Feature",
  "properties": {
    "addr:full":"4121 Plank Rd Fredericksburg VA 22407",
    "addr:housenumber":"4121",
    "addr:postcode":"22407",
    "addr:street":"Plank Rd",
    "iso:country":"US",
    "sg:address":"4121 Plank Rd",
    "sg:city":"Fredericksburg",
    "sg:classifiers":[
        {
            "category":"Government",
            "subcategory":"Court House",
            "type":"Public Place"
        }
    ],
    "sg:phone":"+1 540 785 9799",
    "sg:postcode":"22407",
    "sg:province":"VA",
    "sg:tags":[
        "state"
    ],
    "wof:name":"Supreme Court-Regional Tech",
    "wof:placetype":"venue"
},
  "geometry": {"coordinates":[-77.531921,38.289465],"type":"Point"}
}