{
  "type": "Feature",
  "properties": {
    "addr:full":"671 N Glebe Rd Arlington VA 22203",
    "addr:housenumber":"671",
    "addr:postcode":"22203",
    "addr:street":"N Glebe Rd",
    "iso:country":"US",
    "sg:address":"671 N Glebe Rd",
    "sg:city":"Arlington",
    "sg:classifiers":[
        {
            "category":"Restaurant",
            "type":"Food & Drink"
        }
    ],
    "sg:phone":"+1 703 248 0000",
    "sg:postcode":"22203",
    "sg:province":"VA",
    "sg:tags":[
        "eating"
    ],
    "wof:name":"Romano's Macaroni Grill",
    "wof:placetype":"venue"
},
  "geometry": {"coordinates":[-77.112167,38.878937],"type":"Point"}
}