{
  "type": "Feature",
  "properties": {
    "addr:full":"231 Riverside Dr Portsmouth VA 23707",
    "addr:housenumber":"231",
    "addr:postcode":"23707",
    "addr:street":"Riverside Dr",
    "iso:country":"US",
    "sg:address":"231 Riverside Dr",
    "sg:city":"Portsmouth",
    "sg:classifiers":[
        {
            "category":"Health Services",
            "subcategory":"Doctor",
            "type":"Services"
        }
    ],
    "sg:phone":"+1 757 399 1716",
    "sg:postcode":"23707",
    "sg:province":"VA",
    "sg:tags":[
        "physician",
        "surgeon"
    ],
    "wof:name":"V K Heely MD",
    "wof:placetype":"venue"
},
  "geometry": {"coordinates":[-76.353819,36.841803],"type":"Point"}
}