{
  "type": "Feature",
  "properties": {
    "iso:country":"US",
    "sg:address":"40 Southgate Sq",
    "sg:city":"Colonial Heights",
    "sg:classifiers":[
        {
            "category":"Autos & Motor Vehicles",
            "subcategory":"Auto Supplies",
            "type":"Retail Goods"
        }
    ],
    "sg:phone":"+1 804 862 2822",
    "sg:postcode":"23834",
    "sg:province":"VA",
    "sg:tags":[
        "automobile",
        "stereo",
        "radio"
    ],
    "wof:name":"Dominion Radio Supply Inc",
    "wof:placetype":"venue"
},
  "geometry": {"coordinates":[-77.391842,37.24589],"type":"Point"}
}