{
  "type": "Feature",
  "properties": {
    "addr:full":"437 Clifton Rd Rawlings VA 23876",
    "addr:housenumber":"437",
    "addr:postcode":"23876",
    "addr:street":"Clifton Rd",
    "iso:country":"US",
    "sg:address":"437 Clifton Rd",
    "sg:city":"Rawlings",
    "sg:classifiers":[
        {
            "category":"Freight",
            "type":"Transportation"
        }
    ],
    "sg:phone":"+1 434 949 7018",
    "sg:postcode":"23876",
    "sg:province":"VA",
    "sg:tags":[
        "operator",
        "trucking"
    ],
    "wof:name":"Jones Trucking Inc",
    "wof:placetype":"venue"
},
  "geometry": {"coordinates":[-77.852001,36.946141],"type":"Point"}
}