{
  "type": "Feature",
  "properties": {
    "addr:full":"1929 Thomson Dr Lynchburg VA 24501",
    "addr:housenumber":"1929",
    "addr:postcode":"24501",
    "addr:street":"Thomson Dr",
    "iso:country":"US",
    "sg:address":"1929 Thomson Dr",
    "sg:city":"Lynchburg",
    "sg:classifiers":[
        {
            "category":"Health Services",
            "subcategory":"Doctor",
            "type":"Services"
        }
    ],
    "sg:phone":"+1 434 846 2202",
    "sg:postcode":"24501",
    "sg:province":"VA",
    "sg:tags":[
        "dentist"
    ],
    "wof:name":"Chalfant Family Dentistry",
    "wof:placetype":"venue"
},
  "geometry": {"coordinates":[-79.177555,37.419452],"type":"Point"}
}