{
  "type": "Feature",
  "properties": {
    "iso:country":"US",
    "sg:address":"6515 Medinah Ln",
    "sg:city":"Alexandria",
    "sg:classifiers":[
        {
            "category":"Shopping",
            "subcategory":"Used Merchandise",
            "type":"Retail Goods"
        }
    ],
    "sg:phone":"+1 703 941 9443",
    "sg:postcode":"22312",
    "sg:province":"VA",
    "wof:name":"Affordable Antiques",
    "wof:placetype":"venue"
},
  "geometry": {"coordinates":[-77.16992999999999,38.824496],"type":"Point"}
}