{
  "type": "Feature",
  "properties": {
    "addr:full":"177 Cedar Bluff Louisa VA 23093",
    "addr:housenumber":"177",
    "addr:postcode":"23093",
    "addr:street":"Cedar Bluff",
    "iso:country":"US",
    "sg:address":"177 Cedar Bluff",
    "sg:city":"Louisa",
    "sg:classifiers":[
        {
            "category":"Retail",
            "subcategory":"Repair Shop",
            "type":"Services"
        }
    ],
    "sg:phone":"+1 540 894 8983",
    "sg:postcode":"23093",
    "sg:province":"VA",
    "sg:tags":[
        "equipment",
        "telephone",
        "system"
    ],
    "wof:name":"Cornerstone Communication",
    "wof:placetype":"venue"
},
  "geometry": {"coordinates":[-77.97115100000001,37.866215],"type":"Point"}
}