{
  "type": "Feature",
  "properties": {
    "iso:country":"US",
    "sg:address":"7603 Forest Ave",
    "sg:city":"Richmond",
    "sg:classifiers":[
        {
            "category":"Health Services",
            "subcategory":"Doctor",
            "type":"Services"
        }
    ],
    "sg:phone":"+1 804 285 9700",
    "sg:postcode":"23229",
    "sg:province":"VA",
    "sg:tags":[
        "physician",
        "surgeon",
        "medical"
    ],
    "sg:website":"www.eggdoc.com",
    "wof:name":"Richmond Center For Fertility",
    "wof:placetype":"venue"
},
  "geometry": {"coordinates":[-77.544349,37.603515],"type":"Point"}
}