{
  "type": "Feature",
  "properties": {
    "addr:full":"8400 Hilltop Rd Ste F Fairfax VA 22031",
    "addr:housenumber":"8400",
    "addr:postcode":"22031",
    "addr:street":"Hilltop Rd Ste F",
    "iso:country":"US",
    "sg:address":"8400 Hilltop Rd Ste F",
    "sg:city":"Fairfax",
    "sg:classifiers":[
        {
            "category":"Building & Trades",
            "subcategory":"Cleaning & Sanitation",
            "type":"Services"
        },
        {
            "category":"Building & Trades",
            "subcategory":"Construction",
            "type":"Services"
        }
    ],
    "sg:phone":"+1 703 560 9444",
    "sg:postcode":"22031",
    "sg:province":"VA",
    "sg:tags":[
        "house",
        "system",
        "contractor",
        "air conditioning"
    ],
    "sg:website":"http://www.bbairconditioning.com",
    "wof:name":"B & B Air Conditioning & Heating Service Company Incorporated",
    "wof:placetype":"venue"
},
  "geometry": {"coordinates":[-77.236572,38.875301],"type":"Point"}
}