{
  "type": "Feature",
  "properties": {
    "iso:country":"US",
    "sg:address":"11923 Centre St Suite A3",
    "sg:city":"Chester",
    "sg:classifiers":[
        {
            "category":"Professional",
            "subcategory":"Accounting & Tax Preparation",
            "type":"Services"
        }
    ],
    "sg:phone":"+1 804 425 9856",
    "sg:postcode":"23831",
    "sg:province":"VA",
    "sg:tags":[
        "payroll",
        "bookkeeping",
        "return",
        "preparation-business"
    ],
    "sg:website":"http://www.tntaccounting.net",
    "wof:name":"TNT Accounting Services, LLC",
    "wof:placetype":"venue"
},
  "geometry": {"coordinates":[-77.44739199999999,37.357695],"type":"Point"}
}