{
  "type": "Feature",
  "properties": {
    "addr:full":"3 Center Dr Norfolk VA 23502",
    "addr:housenumber":"3",
    "addr:postcode":"23502",
    "addr:street":"Center Dr",
    "iso:country":"US",
    "sg:address":"3 Center Dr",
    "sg:city":"Norfolk",
    "sg:classifiers":[
        {
            "category":"Organizations",
            "subcategory":"Professional Association",
            "type":"Services"
        }
    ],
    "sg:phone":"+1 757 461 4505",
    "sg:postcode":"23502",
    "sg:province":"VA",
    "wof:name":"International Union-Oper Engrs",
    "wof:placetype":"venue"
},
  "geometry": {"coordinates":[-76.18970899999999,36.846488],"type":"Point"}
}