{
  "type": "Feature",
  "properties": {
    "iso:country":"US",
    "sg:address":"13515 Delaney Rd",
    "sg:city":"Woodbridge",
    "sg:classifiers":[
        {
            "category":"Building & Trades",
            "subcategory":"Cleaning & Sanitation",
            "type":"Services"
        }
    ],
    "sg:phone":"+1 703 583 5554",
    "sg:postcode":"22193",
    "sg:province":"VA",
    "sg:tags":[
        "house"
    ],
    "wof:name":"Lety's Cleaning Svc",
    "wof:placetype":"venue"
},
  "geometry": {"coordinates":[-77.352684,38.657658],"type":"Point"}
}