{
  "type": "Feature",
  "properties": {
    "addr:full":"1205 Long St Charlottesville VA 22901",
    "addr:housenumber":"1205",
    "addr:postcode":"22901",
    "addr:street":"Long St",
    "iso:country":"US",
    "sg:address":"1205 Long St",
    "sg:city":"Charlottesville",
    "sg:classifiers":[
        {
            "category":"Banks & Credit Unions",
            "subcategory":"Bank",
            "type":"Services"
        }
    ],
    "sg:phone":"+1 434 963 2921",
    "sg:postcode":"22901",
    "sg:province":"VA",
    "sg:tags":[
        "national",
        "commercial"
    ],
    "sg:website":"www.bankofamerica.com",
    "wof:name":"Bank of America",
    "wof:placetype":"venue"
},
  "geometry": {"coordinates":[-78.462692,38.036551],"type":"Point"}
}