{
  "type": "Feature",
  "properties": {
    "addr:full":"1705 Shipyard Rd Chesapeake VA 23323",
    "addr:housenumber":"1705",
    "addr:postcode":"23323",
    "addr:street":"Shipyard Rd",
    "iso:country":"US",
    "sg:address":"1705 Shipyard Rd",
    "sg:city":"Chesapeake",
    "sg:classifiers":[
        {
            "category":"Organizations",
            "subcategory":"Religious Organization",
            "type":"Services"
        }
    ],
    "sg:phone":"+1 757 487 8427",
    "sg:postcode":"23323",
    "sg:province":"VA",
    "wof:name":"Macedonia Baptist Church",
    "wof:placetype":"venue"
},
  "geometry": {"coordinates":[-76.30890100000001,36.750917],"type":"Point"}
}