{
  "type": "Feature",
  "properties": {
    "iso:country":"US",
    "sg:address":"305 Hotchkiss Rd",
    "sg:city":"Churchville",
    "sg:classifiers":[
        {
            "category":"Professional",
            "type":"Services"
        }
    ],
    "sg:phone":"+1 540 337 6028",
    "sg:postcode":"24421",
    "sg:province":"VA",
    "wof:name":"Scott A Morris",
    "wof:placetype":"venue"
},
  "geometry": {"coordinates":[-79.148366,38.240605],"type":"Point"}
}