{
  "type": "Feature",
  "properties": {
    "iso:country":"US",
    "sg:address":"299 Ridgecrest Dr",
    "sg:city":"Daleville",
    "sg:classifiers":[
        {
            "category":"Professional",
            "type":"Services"
        }
    ],
    "sg:phone":"+1 540 992 5282",
    "sg:postcode":"24083",
    "sg:province":"VA",
    "wof:name":"Moser Inc",
    "wof:placetype":"venue"
},
  "geometry": {"coordinates":[-79.919881,37.426105],"type":"Point"}
}