{
  "type": "Feature",
  "properties": {
    "addr:full":"917 Anderson St Bristol VA 37620",
    "addr:housenumber":"917",
    "addr:postcode":"37620",
    "addr:street":"Anderson St",
    "iso:country":"US",
    "sg:address":"917 Anderson St",
    "sg:city":"Bristol",
    "sg:classifiers":[
        {
            "category":"Professional",
            "subcategory":"Lawyer & Legal Services",
            "type":"Services"
        }
    ],
    "sg:phone":"+1 423 968 9170",
    "sg:postcode":"37620",
    "sg:province":"VA",
    "wof:name":"Zager & Zager",
    "wof:placetype":"venue"
},
  "geometry": {"coordinates":[-82.191625,36.592323],"type":"Point"}
}