{
  "type": "Feature",
  "properties": {
    "addr:full":"101 Granby St Norfolk VA 23510",
    "addr:housenumber":"101",
    "addr:postcode":"23510",
    "addr:street":"Granby St",
    "iso:country":"US",
    "sg:address":"101 Granby St",
    "sg:city":"Norfolk",
    "sg:classifiers":[
        {
            "category":"Organizations",
            "subcategory":"Community Association",
            "type":"Services"
        }
    ],
    "sg:phone":"+1 757 622 7218",
    "sg:postcode":"23510",
    "sg:province":"VA",
    "sg:tags":[
        "club"
    ],
    "wof:name":"Va Club",
    "wof:placetype":"venue"
},
  "geometry": {"coordinates":[-76.29185699999999,36.847291],"type":"Point"}
}