{
  "type": "Feature",
  "properties": {
    "addr:full":"1621 Williamsburg Rd Richmond VA 23231",
    "addr:housenumber":"1621",
    "addr:postcode":"23231",
    "addr:street":"Williamsburg Rd",
    "iso:country":"US",
    "sg:address":"1621 Williamsburg Rd",
    "sg:city":"Richmond",
    "sg:classifiers":[
        {
            "category":"Food & Beverages",
            "subcategory":"Groceries & Convenience Stores",
            "type":"Retail Goods"
        }
    ],
    "sg:phone":"+1 804 226 4512",
    "sg:postcode":"23231",
    "sg:province":"VA",
    "wof:name":"Quickmart 1",
    "wof:placetype":"venue"
},
  "geometry": {"coordinates":[-77.396171,37.51446],"type":"Point"}
}