{
  "type": "Feature",
  "properties": {
    "addr:full":"2515 Seminary Ave Richmond VA 23220",
    "addr:housenumber":"2515",
    "addr:postcode":"23220",
    "addr:street":"Seminary Ave",
    "iso:country":"US",
    "sg:address":"2515 Seminary Ave",
    "sg:city":"Richmond",
    "sg:classifiers":[
        {
            "category":"Freight",
            "type":"Transportation"
        }
    ],
    "sg:phone":"+1 804 228 0068",
    "sg:postcode":"23220",
    "sg:province":"VA",
    "sg:tags":[
        "trucking"
    ],
    "wof:name":"Trailblazer Trucking",
    "wof:placetype":"venue"
},
  "geometry": {"coordinates":[-77.446276,37.567665],"type":"Point"}
}