{
  "type": "Feature",
  "properties": {
    "addr:full":"20 Edmondson Ave Lexington VA 24450",
    "addr:housenumber":"20",
    "addr:postcode":"24450",
    "addr:street":"Edmondson Ave",
    "iso:country":"US",
    "sg:address":"20 Edmondson Ave",
    "sg:city":"Lexington",
    "sg:classifiers":[
        {
            "category":"Building & Trades",
            "subcategory":"Construction",
            "type":"Services"
        }
    ],
    "sg:phone":"+1 540 464 5760",
    "sg:postcode":"24450",
    "sg:province":"VA",
    "sg:tags":[
        "house"
    ],
    "wof:name":"Distinctive Home Builders Inc",
    "wof:placetype":"venue"
},
  "geometry": {"coordinates":[-79.451425,37.779683],"type":"Point"}
}