{
  "type": "Feature",
  "properties": {
    "addr:full":"3822 Peach Orchard Cir Portsmouth VA 23703",
    "addr:housenumber":"3822",
    "addr:postcode":"23703",
    "addr:street":"Peach Orchard Cir",
    "iso:country":"US",
    "sg:address":"3822 Peach Orchard Cir",
    "sg:city":"Portsmouth",
    "sg:classifiers":[
        {
            "category":"Travel",
            "subcategory":"Travel Agent",
            "type":"Entertainment"
        }
    ],
    "sg:phone":"+1 757 483 9858",
    "sg:postcode":"23703",
    "sg:province":"VA",
    "sg:tags":[
        "agency"
    ],
    "wof:name":"Empress Andersons Travel",
    "wof:placetype":"venue"
},
  "geometry": {"coordinates":[-76.40370299999999,36.877817],"type":"Point"}
}