{
  "type": "Feature",
  "properties": {
    "iso:country":"US",
    "sg:address":"8465 Holly Leaf Dr",
    "sg:city":"Mc Lean",
    "sg:classifiers":[
        {
            "category":"Professional",
            "subcategory":"Management & Consulting",
            "type":"Services"
        }
    ],
    "sg:phone":"+1 703 847 8450",
    "sg:postcode":"22102",
    "sg:province":"VA",
    "wof:name":"Walden Assoc",
    "wof:placetype":"venue"
},
  "geometry": {"coordinates":[-77.23542999999999,38.943417],"type":"Point"}
}