{
  "type": "Feature",
  "properties": {
    "addr:full":"1230 Perry St Chesapeake VA 23324",
    "addr:housenumber":"1230",
    "addr:postcode":"23324",
    "addr:street":"Perry St",
    "iso:country":"US",
    "sg:address":"1230 Perry St",
    "sg:city":"Chesapeake",
    "sg:classifiers":[
        {
            "category":"Manufacturing",
            "subcategory":"Food",
            "type":"Manufacturing & Wholesale Goods"
        },
        {
            "category":"Wholesale",
            "subcategory":"Groceries",
            "type":"Manufacturing & Wholesale Goods"
        }
    ],
    "sg:phone":"+1 757 545 9311",
    "sg:postcode":"23324",
    "sg:province":"VA",
    "sg:tags":[
        "manufacture",
        "confectionery",
        "hard",
        "candy"
    ],
    "wof:name":"Williams Candy Co",
    "wof:placetype":"venue"
},
  "geometry": {"coordinates":[-76.279343,36.813828],"type":"Point"}
}