{
  "type": "Feature",
  "properties": {
    "iso:country":"US",
    "sg:address":"4638 Star Flower Dr",
    "sg:city":"Chantilly",
    "sg:classifiers":[
        {
            "category":"Professional",
            "subcategory":"Accounting & Tax Preparation",
            "type":"Services"
        }
    ],
    "sg:phone":"+1 703 815 2774",
    "sg:postcode":"20151",
    "sg:province":"VA",
    "wof:name":"Bookkeeping Support System",
    "wof:placetype":"venue"
},
  "geometry": {"coordinates":[-77.417873,38.868388],"type":"Point"}
}