{
  "type": "Feature",
  "properties": {
    "addr:full":"901 E Byrd St Richmond VA 23219",
    "addr:housenumber":"901",
    "addr:postcode":"23219",
    "addr:street":"E Byrd St",
    "iso:country":"US",
    "sg:address":"901 E Byrd St",
    "sg:city":"Richmond",
    "sg:classifiers":[
        {
            "category":"Banks & Credit Unions",
            "subcategory":"Investment Brokerage",
            "type":"Services"
        }
    ],
    "sg:phone":"+1 804 782 3501",
    "sg:postcode":"23219",
    "sg:province":"VA",
    "sg:tags":[
        "advisory"
    ],
    "wof:name":"Colonnade Capital Ii",
    "wof:placetype":"venue"
},
  "geometry": {"coordinates":[-77.438911,37.535782],"type":"Point"}
}