{
  "type": "Feature",
  "properties": {
    "addr:full":"101 Dilworth Cir Sandston VA 23150",
    "addr:housenumber":"101",
    "addr:postcode":"23150",
    "addr:street":"Dilworth Cir",
    "iso:country":"US",
    "sg:address":"101 Dilworth Cir",
    "sg:city":"Sandston",
    "sg:classifiers":[
        {
            "category":"Building & Trades",
            "subcategory":"Construction",
            "type":"Services"
        }
    ],
    "sg:phone":"+1 804 737 7026",
    "sg:postcode":"23150",
    "sg:province":"VA",
    "sg:tags":[
        "concrete",
        "work",
        "specialist"
    ],
    "wof:name":"Prestress Concrete Specialist",
    "wof:placetype":"venue"
},
  "geometry": {"coordinates":[-77.23518799999999,37.517412],"type":"Point"}
}