{
  "type": "Feature",
  "properties": {
    "iso:country":"US",
    "sg:address":"5219 Singing Hills Rd",
    "sg:city":"Roanoke",
    "sg:classifiers":[
        {
            "category":"Organizations",
            "subcategory":"Religious Organization",
            "type":"Services"
        }
    ],
    "sg:phone":"+1 540 774 3839",
    "sg:postcode":"24014",
    "sg:province":"VA",
    "sg:tags":[
        "church"
    ],
    "wof:name":"Clearbrook Baptist Church",
    "wof:placetype":"venue"
},
  "geometry": {"coordinates":[-79.95305999999999,37.207305],"type":"Point"}
}