{
  "type": "Feature",
  "properties": {
    "addr:full":"5221 Hideway Cove Rd Exmore VA 23350",
    "addr:housenumber":"5221",
    "addr:postcode":"23350",
    "addr:street":"Hideway Cove Rd",
    "iso:country":"US",
    "sg:address":"5221 Hideway Cove Rd",
    "sg:city":"Exmore",
    "sg:classifiers":[
        {
            "category":"Building & Trades",
            "subcategory":"Construction",
            "type":"Services"
        }
    ],
    "sg:phone":"+1 757 442 6122",
    "sg:postcode":"23350",
    "sg:province":"VA",
    "sg:tags":[
        "roofing",
        "contractor"
    ],
    "wof:name":"Anthony The Roof Man",
    "wof:placetype":"venue"
},
  "geometry": {"coordinates":[-75.942792,37.488119],"type":"Point"}
}