{
  "type": "Feature",
  "properties": {
    "addr:full":"405 S Washington Hwy Ashland VA 23005",
    "addr:housenumber":"405",
    "addr:postcode":"23005",
    "addr:street":"S Washington Hwy",
    "iso:country":"US",
    "sg:address":"405 S Washington Hwy",
    "sg:city":"Ashland",
    "sg:classifiers":[
        {
            "category":"Autos & Motor Vehicles",
            "subcategory":"Automobile Sales",
            "type":"Retail Goods"
        }
    ],
    "sg:phone":"+1 804 798 4200",
    "sg:postcode":"23005",
    "sg:province":"VA",
    "sg:tags":[
        "new",
        "used"
    ],
    "wof:name":"Patrick Auto Group",
    "wof:placetype":"venue"
},
  "geometry": {"coordinates":[-77.47133599999999,37.752406],"type":"Point"}
}