{
  "type": "Feature",
  "properties": {
    "addr:full":"5676 Hickory Dr Salem VA 24153",
    "addr:housenumber":"5676",
    "addr:postcode":"24153",
    "addr:street":"Hickory Dr",
    "iso:country":"US",
    "sg:address":"5676 Hickory Dr",
    "sg:city":"Salem",
    "sg:classifiers":[
        {
            "category":"Shopping",
            "subcategory":"Hobbies, Toys, & Games",
            "type":"Retail Goods"
        }
    ],
    "sg:phone":"+1 540 375 3700",
    "sg:postcode":"24153",
    "sg:province":"VA",
    "wof:name":"Heidis Hope Chest",
    "wof:placetype":"venue"
},
  "geometry": {"coordinates":[-80.135637,37.242881],"type":"Point"}
}