{
  "type": "Feature",
  "properties": {
    "addr:full":"5700 Telegraph Rd Alexandria VA 22303",
    "addr:housenumber":"5700",
    "addr:postcode":"22303",
    "addr:street":"Telegraph Rd",
    "iso:country":"US",
    "sg:address":"5700 Telegraph Rd",
    "sg:city":"Alexandria",
    "sg:classifiers":[
        {
            "category":"Autos & Motor Vehicles",
            "subcategory":"Fuel & Gas Station",
            "type":"Retail Goods"
        }
    ],
    "sg:phone":"+1 703 960 2030",
    "sg:postcode":"22303",
    "sg:province":"VA",
    "sg:tags":[
        "station",
        "gasoline"
    ],
    "wof:name":"Amoco",
    "wof:placetype":"venue"
},
  "geometry": {"coordinates":[-77.080962,38.797518],"type":"Point"}
}