{
  "type": "Feature",
  "properties": {
    "iso:country":"US",
    "sg:address":"1 Yeocomico Ln",
    "sg:city":"Callao",
    "sg:classifiers":[
        {
            "category":"Building & Trades",
            "subcategory":"Landscaping Services",
            "type":"Services"
        }
    ],
    "sg:phone":"+1 804 529 5482",
    "sg:postcode":"22435",
    "sg:province":"VA",
    "sg:website":"www.bullockdevelopment.com",
    "wof:name":"BDC",
    "wof:placetype":"venue"
},
  "geometry": {"coordinates":[-76.560456,38.023251],"type":"Point"}
}