{
  "type": "Feature",
  "properties": {
    "addr:full":"13266 Fallen Leaf Ct Woodbridge VA 22192",
    "addr:housenumber":"13266",
    "addr:postcode":"22192",
    "addr:street":"Fallen Leaf Ct",
    "iso:country":"US",
    "sg:address":"13266 Fallen Leaf Ct",
    "sg:city":"Woodbridge",
    "sg:classifiers":[
        {
            "category":"Building & Trades",
            "subcategory":"Construction",
            "type":"Services"
        }
    ],
    "sg:phone":"+1 703 583 1840",
    "sg:postcode":"22192",
    "sg:province":"VA",
    "sg:tags":[
        "house"
    ],
    "wof:name":"Couch Construction Group Incor",
    "wof:placetype":"venue"
},
  "geometry": {"coordinates":[-77.327699,38.665757],"type":"Point"}
}