{
  "type": "Feature",
  "properties": {
    "addr:full":"645 Park Blvd Ste 250 Marion VA 24354",
    "addr:housenumber":"645",
    "addr:postcode":"24354",
    "addr:street":"Park Blvd Ste 250",
    "iso:country":"US",
    "sg:address":"645 Park Blvd Ste 250",
    "sg:city":"Marion",
    "sg:classifiers":[
        {
            "category":"Health Services",
            "subcategory":"Dentist",
            "type":"Services"
        }
    ],
    "sg:phone":"+1 276 783 8131",
    "sg:postcode":"24354",
    "sg:province":"VA",
    "sg:tags":[
        "dentists-oral",
        "surgery",
        "maxillofacial"
    ],
    "wof:name":"Sukle, Hollyfield & Abbott",
    "wof:placetype":"venue"
},
  "geometry": {"coordinates":[-81.508681,36.85013],"type":"Point"}
}