{
  "type": "Feature",
  "properties": {
    "iso:country":"US",
    "sg:address":"309 Tahoe Dr",
    "sg:city":"Newport News",
    "sg:classifiers":[
        {
            "category":"Real Estate",
            "subcategory":"Real Estate Agent",
            "type":"Services"
        }
    ],
    "sg:phone":"+1 757 833 8463",
    "sg:postcode":"23602",
    "sg:province":"VA",
    "sg:tags":[
        "legal"
    ],
    "wof:name":"Smith and Company",
    "wof:placetype":"venue"
},
  "geometry": {"coordinates":[-76.533261,37.096793],"type":"Point"}
}