{
  "type": "Feature",
  "properties": {
    "addr:full":"4082 Electric Rd Roanoke VA 24018",
    "addr:housenumber":"4082",
    "addr:postcode":"24018",
    "addr:street":"Electric Rd",
    "iso:country":"US",
    "sg:address":"4082 Electric Rd",
    "sg:city":"Roanoke",
    "sg:classifiers":[
        {
            "category":"Shopping",
            "subcategory":"Stationery & Office Supplies",
            "type":"Retail Goods"
        }
    ],
    "sg:phone":"+1 540 776 0866",
    "sg:postcode":"24018",
    "sg:province":"VA",
    "wof:name":"Staples",
    "wof:placetype":"venue"
},
  "geometry": {"coordinates":[-79.981657,37.225513],"type":"Point"}
}