{
  "type": "Feature",
  "properties": {
    "addr:full":"15034 Warwick Blvd Newport News VA 23608",
    "addr:housenumber":"15034",
    "addr:postcode":"23608",
    "addr:street":"Warwick Blvd",
    "iso:country":"US",
    "sg:address":"15034 Warwick Blvd",
    "sg:city":"Newport News",
    "sg:classifiers":[
        {
            "category":"Retail",
            "subcategory":"Auto Rental",
            "type":"Services"
        }
    ],
    "sg:phone":"+1 757 886 5832",
    "sg:postcode":"23608",
    "sg:province":"VA",
    "sg:tags":[
        "truck"
    ],
    "wof:name":"Ryder",
    "wof:placetype":"venue"
},
  "geometry": {"coordinates":[-76.546125,37.138739],"type":"Point"}
}