{
  "type": "Feature",
  "properties": {
    "addr:full":"7419 Kincheloe Rd Clifton VA 20124",
    "addr:housenumber":"7419",
    "addr:postcode":"20124",
    "addr:street":"Kincheloe Rd",
    "iso:country":"US",
    "sg:address":"7419 Kincheloe Rd",
    "sg:city":"Clifton",
    "sg:classifiers":[
        {
            "category":"Professional",
            "subcategory":"Computer Services",
            "type":"Services"
        }
    ],
    "sg:phone":"+1 703 815 0900",
    "sg:postcode":"20124",
    "sg:province":"VA",
    "sg:tags":[
        "consultant",
        "designer",
        "programing",
        "related",
        "custom"
    ],
    "wof:name":"J P Systems Inc",
    "wof:placetype":"venue"
},
  "geometry": {"coordinates":[-77.38327,38.771118],"type":"Point"}
}