{
  "type": "Feature",
  "properties": {
    "addr:full":"6842 Elm St Mc Lean VA 22101",
    "addr:housenumber":"6842",
    "addr:postcode":"22101",
    "addr:street":"Elm St Mc Lean",
    "iso:country":"US",
    "sg:address":"6842 Elm St",
    "sg:city":"Mc Lean",
    "sg:classifiers":[
        {
            "category":"Real Estate",
            "subcategory":"Real Estate Agent",
            "type":"Services"
        }
    ],
    "sg:phone":"+1 703 356 9002",
    "sg:postcode":"22101",
    "sg:province":"VA",
    "sg:tags":[
        "consulting",
        "management"
    ],
    "wof:name":"Warkentin Co Realtors",
    "wof:placetype":"venue"
},
  "geometry": {"coordinates":[-77.179205,38.935516],"type":"Point"}
}