{
  "type": "Feature",
  "properties": {
    "addr:full":"4746 Eldon Ct Virginia Beach VA 23462",
    "addr:housenumber":"4746",
    "addr:postcode":"23462",
    "addr:street":"Eldon Ct",
    "iso:country":"US",
    "sg:address":"4746 Eldon Ct",
    "sg:city":"Virginia Beach",
    "sg:classifiers":[
        {
            "category":"Building & Trades",
            "subcategory":"Construction",
            "type":"Services"
        }
    ],
    "sg:phone":"+1 757 961 5001",
    "sg:postcode":"23462",
    "sg:province":"VA",
    "sg:tags":[
        "carpenter"
    ],
    "wof:name":"Carpenter Jennifer",
    "wof:placetype":"venue"
},
  "geometry": {"coordinates":[-76.148526,36.82794],"type":"Point"}
}