{
  "type": "Feature",
  "properties": {
    "iso:country":"US",
    "sg:address":"10 W Queens Way",
    "sg:city":"Hampton",
    "sg:classifiers":[
        {
            "category":"Restaurant",
            "type":"Food & Drink"
        }
    ],
    "sg:phone":"+1 757 990 0677",
    "sg:postcode":"23669",
    "sg:province":"VA",
    "wof:name":"Hot Roscoes Restaurant",
    "wof:placetype":"venue"
},
  "geometry": {"coordinates":[-76.344897,37.025757],"type":"Point"}
}