{
  "type": "Feature",
  "properties": {
    "addr:full":"312 W 24th St Norfolk VA 23517",
    "addr:housenumber":"312",
    "addr:postcode":"23517",
    "addr:street":"W 24Th St",
    "iso:country":"US",
    "sg:address":"312 W 24th St",
    "sg:city":"Norfolk",
    "sg:classifiers":[
        {
            "category":"Professional",
            "subcategory":"Engineering",
            "type":"Services"
        }
    ],
    "sg:phone":"+1 757 622 6299",
    "sg:postcode":"23517",
    "sg:province":"VA",
    "sg:tags":[
        "consulting",
        "inspection"
    ],
    "wof:name":"Interspec LLC",
    "wof:placetype":"venue"
},
  "geometry": {"coordinates":[-76.288809,36.87103],"type":"Point"}
}