{
  "type": "Feature",
  "properties": {
    "addr:full":"428 N Loudoun St Winchester VA 22601",
    "addr:housenumber":"428",
    "addr:postcode":"22601",
    "addr:street":"N Loudoun St",
    "iso:country":"US",
    "sg:address":"428 N Loudoun St",
    "sg:city":"Winchester",
    "sg:classifiers":[
        {
            "category":"Organizations",
            "subcategory":"Religious Organization",
            "type":"Services"
        }
    ],
    "sg:phone":"+1 540 665 2955",
    "sg:postcode":"22601",
    "sg:province":"VA",
    "sg:tags":[
        "church"
    ],
    "wof:name":"St Paul AME Church",
    "wof:placetype":"venue"
},
  "geometry": {"coordinates":[-78.16325500000001,39.190173],"type":"Point"}
}