{
  "type": "Feature",
  "properties": {
    "iso:country":"US",
    "sg:address":"3077 Patrick Henry Dr",
    "sg:city":"Falls Church",
    "sg:classifiers":[
        {
            "category":"Real Estate",
            "subcategory":"Real Estate Agent",
            "type":"Services"
        }
    ],
    "sg:phone":"+1 703 533 2002",
    "sg:postcode":"22044",
    "sg:province":"VA",
    "sg:tags":[
        "management"
    ],
    "wof:name":"Greenwood Apartments",
    "wof:placetype":"venue"
},
  "geometry": {"coordinates":[-77.150667,38.865835],"type":"Point"}
}