{
  "type": "Feature",
  "properties": {
    "iso:country":"US",
    "sg:address":"711 London St",
    "sg:city":"Portsmouth",
    "sg:classifiers":[
        {
            "category":"Personal",
            "subcategory":"Barber",
            "type":"Services"
        }
    ],
    "sg:phone":"+1 757 393 9399",
    "sg:postcode":"23704",
    "sg:province":"VA",
    "wof:name":"Ronnie's Professional Cutz",
    "wof:placetype":"venue"
},
  "geometry": {"coordinates":[-76.304794,36.836883],"type":"Point"}
}