{
  "type": "Feature",
  "properties": {
    "iso:country":"US",
    "sg:address":"1901 N Fort Myer Dr",
    "sg:city":"Arlington",
    "sg:classifiers":[
        {
            "category":"Professional",
            "subcategory":"Computer Services",
            "type":"Services"
        }
    ],
    "sg:phone":"+1 703 807 0400",
    "sg:postcode":"22209",
    "sg:province":"VA",
    "sg:tags":[
        "development",
        "internet",
        "business",
        "software"
    ],
    "wof:name":"Bidev Inc",
    "wof:placetype":"venue"
},
  "geometry": {"coordinates":[-77.072517,38.897729],"type":"Point"}
}