{
  "type": "Feature",
  "properties": {
    "addr:full":"3732 Falstone Rd Richmond VA 23234",
    "addr:housenumber":"3732",
    "addr:postcode":"23234",
    "addr:street":"Falstone Rd",
    "iso:country":"US",
    "sg:address":"3732 Falstone Rd",
    "sg:city":"Richmond",
    "sg:classifiers":[
        {
            "category":"Wholesale",
            "subcategory":"Machinery & Supplies",
            "type":"Manufacturing & Wholesale Goods"
        }
    ],
    "sg:phone":"+1 804 271 6516",
    "sg:postcode":"23234",
    "sg:province":"VA",
    "wof:name":"S P D Inc",
    "wof:placetype":"venue"
},
  "geometry": {"coordinates":[-77.46682,37.45403],"type":"Point"}
}