{
  "type": "Feature",
  "properties": {
    "iso:country":"US",
    "sg:address":"852 Virginia Center Pkwy",
    "sg:city":"Glen Allen",
    "sg:classifiers":[
        {
            "category":"Health Services",
            "subcategory":"Optometrist",
            "type":"Services"
        }
    ],
    "sg:phone":"+1 804 266 9511",
    "sg:postcode":"23059",
    "sg:province":"VA",
    "wof:name":"Howlette Od Assoc PC E Michael",
    "wof:placetype":"venue"
},
  "geometry": {"coordinates":[-77.443541,37.662238],"type":"Point"}
}