{
  "type": "Feature",
  "properties": {
    "addr:full":"14069 Asher Vw Centreville VA 20121",
    "addr:housenumber":"14069",
    "addr:postcode":"20121",
    "addr:street":"Asher Vw",
    "iso:country":"US",
    "sg:address":"14069 Asher Vw",
    "sg:city":"Centreville",
    "sg:classifiers":[
        {
            "category":"Professional",
            "subcategory":"Business Services",
            "type":"Services"
        }
    ],
    "sg:phone":"+1 703 830 1939",
    "sg:postcode":"20121",
    "sg:province":"VA",
    "wof:name":"Garland & Associates Limited",
    "wof:placetype":"venue"
},
  "geometry": {"coordinates":[-77.434978,38.830813],"type":"Point"}
}