{
  "type": "Feature",
  "properties": {
    "addr:full":"223 E City Hall Ave Norfolk VA 23510",
    "addr:housenumber":"223",
    "addr:postcode":"23510",
    "addr:street":"E City;Ave",
    "iso:country":"US",
    "sg:address":"223 E City Hall Ave",
    "sg:city":"Norfolk",
    "sg:classifiers":[
        {
            "category":"Restaurant",
            "type":"Food & Drink"
        }
    ],
    "sg:phone":"+1 757 623 6490",
    "sg:postcode":"23510",
    "sg:province":"VA",
    "sg:tags":[
        "pizza"
    ],
    "wof:name":"Tycorp Pizza",
    "wof:placetype":"venue"
},
  "geometry": {"coordinates":[-76.29001100000001,36.847546],"type":"Point"}
}