{
  "type": "Feature",
  "properties": {
    "addr:full":"1104 McConville Rd Lynchburg VA 24502",
    "addr:housenumber":"1104",
    "addr:postcode":"24502",
    "addr:street":"Mcconville Rd",
    "iso:country":"US",
    "sg:address":"1104 McConville Rd",
    "sg:city":"Lynchburg",
    "sg:classifiers":[
        {
            "category":"Manufacturing",
            "subcategory":"Electronics",
            "type":"Manufacturing & Wholesale Goods"
        }
    ],
    "sg:phone":"+1 434 237 6391",
    "sg:postcode":"24502",
    "sg:province":"VA",
    "sg:tags":[
        "boards",
        "circuit"
    ],
    "sg:website":"www.waytec.com",
    "wof:name":"Waytec Electronics Corp",
    "wof:placetype":"venue"
},
  "geometry": {"coordinates":[-79.22029499999999,37.381378],"type":"Point"}
}