{
  "type": "Feature",
  "properties": {
    "addr:full":"3708 Harton Ct Virginia Beach VA 23452",
    "addr:housenumber":"3708",
    "addr:postcode":"23452",
    "addr:street":"Harton Ct",
    "iso:country":"US",
    "sg:address":"3708 Harton Ct",
    "sg:city":"Virginia Beach",
    "sg:classifiers":[
        {
            "category":"Building & Trades",
            "subcategory":"Electrical",
            "type":"Services"
        }
    ],
    "sg:phone":"+1 757 486 4391",
    "sg:postcode":"23452",
    "sg:province":"VA",
    "sg:tags":[
        "electrical",
        "contractor"
    ],
    "wof:name":"Csa Electric Co",
    "wof:placetype":"venue"
},
  "geometry": {"coordinates":[-76.099974,36.849677],"type":"Point"}
}