{
  "type": "Feature",
  "properties": {
    "iso:country":"US",
    "sg:address":"6715 Whittier Ave Ste 100",
    "sg:city":"Mc Lean",
    "sg:classifiers":[
        {
            "category":"Health Services",
            "subcategory":"Doctor",
            "type":"Services"
        }
    ],
    "sg:phone":"+1 703 356 5700",
    "sg:postcode":"22101",
    "sg:province":"VA",
    "sg:tags":[
        "practice",
        "family"
    ],
    "wof:name":"Old Dominion Medical Center",
    "wof:placetype":"venue"
},
  "geometry": {"coordinates":[-77.17600299999999,38.931599],"type":"Point"}
}