{
  "type": "Feature",
  "properties": {
    "addr:full":"6462 Liberty Hill Rd Fries VA 24330",
    "addr:housenumber":"6462",
    "addr:postcode":"24330",
    "addr:street":"Liberty Hill Rd",
    "iso:country":"US",
    "sg:address":"6462 Liberty Hill Rd",
    "sg:city":"Fries",
    "sg:classifiers":[
        {
            "category":"Retail",
            "subcategory":"Funeral Services",
            "type":"Services"
        }
    ],
    "sg:phone":"+1 276 744 2735",
    "sg:postcode":"24330",
    "sg:province":"VA",
    "sg:tags":[
        "cemetery"
    ],
    "wof:name":"Ebenezer Cemetery Fund",
    "wof:placetype":"venue"
},
  "geometry": {"coordinates":[-81.067165,36.737602],"type":"Point"}
}