{
  "type": "Feature",
  "properties": {
    "iso:country":"US",
    "sg:address":"1100 N Wilson Blvd",
    "sg:city":"Arlington",
    "sg:classifiers":[
        {
            "category":"Professional",
            "subcategory":"Management & Consulting",
            "type":"Services"
        }
    ],
    "sg:phone":"+1 703 524 8957",
    "sg:postcode":"22209",
    "sg:province":"VA",
    "sg:tags":[
        "corporate"
    ],
    "wof:name":"Corporate Consulting Intl",
    "wof:placetype":"venue"
},
  "geometry": {"coordinates":[-77.070802,38.895091],"type":"Point"}
}