{
  "type": "Feature",
  "properties": {
    "addr:full":"15690 Crestview Ln Haymarket VA 20169",
    "addr:housenumber":"15690",
    "addr:postcode":"20169",
    "addr:street":"Crestview Ln",
    "iso:country":"US",
    "sg:address":"15690 Crestview Ln",
    "sg:city":"Haymarket",
    "sg:classifiers":[
        {
            "category":"Professional",
            "subcategory":"Computer Services",
            "type":"Services"
        }
    ],
    "sg:phone":"+1 703 753 2511",
    "sg:postcode":"20169",
    "sg:province":"VA",
    "sg:tags":[
        "repair"
    ],
    "wof:name":"J & S Networks",
    "wof:placetype":"venue"
},
  "geometry": {"coordinates":[-77.660235,38.858884],"type":"Point"}
}