{
  "type": "Feature",
  "properties": {
    "addr:full":"6175 Cobbs Rd Alexandria VA 22310",
    "addr:housenumber":"6175",
    "addr:postcode":"22310",
    "addr:street":"Cobbs Rd",
    "iso:country":"US",
    "sg:address":"6175 Cobbs Rd",
    "sg:city":"Alexandria",
    "sg:classifiers":[
        {
            "category":"Professional",
            "subcategory":"Business Services",
            "type":"Services"
        }
    ],
    "sg:phone":"+1 703 971 6061",
    "sg:postcode":"22310",
    "sg:province":"VA",
    "sg:tags":[
        "information",
        "referral"
    ],
    "wof:name":"Advanced Information Mgmt",
    "wof:placetype":"venue"
},
  "geometry": {"coordinates":[-77.146376,38.792224],"type":"Point"}
}