{
  "type": "Feature",
  "properties": {
    "addr:full":"1400 Key Blvd Arlington VA 22209",
    "addr:housenumber":"1400",
    "addr:postcode":"22209",
    "addr:street":"Key Blvd",
    "iso:country":"US",
    "sg:address":"1400 Key Blvd",
    "sg:city":"Arlington",
    "sg:classifiers":[
        {
            "category":"Sports & Exercise",
            "subcategory":"Gym",
            "type":"Entertainment"
        }
    ],
    "sg:phone":"+1 703 528 5555",
    "sg:postcode":"22209",
    "sg:province":"VA",
    "wof:name":"Gold's Gym & Aerobics Center",
    "wof:placetype":"venue"
},
  "geometry": {"coordinates":[-77.073303,38.8964],"type":"Point"}
}