{
  "type": "Feature",
  "properties": {
    "iso:country":"US",
    "sg:address":"401 Brittain Ln",
    "sg:city":"Hampton",
    "sg:classifiers":[
        {
            "category":"Professional",
            "subcategory":"Management & Consulting",
            "type":"Services"
        }
    ],
    "sg:phone":"+1 757 851 6816",
    "sg:postcode":"23669",
    "sg:province":"VA",
    "sg:tags":[
        "business"
    ],
    "wof:name":"Anchor Applications Inc",
    "wof:placetype":"venue"
},
  "geometry": {"coordinates":[-76.31938599999999,37.082668],"type":"Point"}
}