{
  "type": "Feature",
  "properties": {
    "addr:full":"218 Sunset Cir Cross Junction VA 22625",
    "addr:housenumber":"218",
    "addr:postcode":"22625",
    "addr:street":"Sunset Cir",
    "iso:country":"US",
    "sg:address":"218 Sunset Cir",
    "sg:city":"Cross Junction",
    "sg:classifiers":[
        {
            "category":"Organizations",
            "subcategory":"Membership Organization",
            "type":"Services"
        },
        {
            "category":"Professional",
            "subcategory":"Management & Consulting",
            "type":"Services"
        }
    ],
    "sg:phone":"+1 540 888 3762",
    "sg:postcode":"22625",
    "sg:province":"VA",
    "wof:name":"Still Meadow Benchmark Assn",
    "wof:placetype":"venue"
},
  "geometry": {"coordinates":[-78.317832,39.313728],"type":"Point"}
}