{
  "type": "Feature",
  "properties": {
    "addr:full":"2326 Plank Rd Fredericksburg VA 22401",
    "addr:housenumber":"2326",
    "addr:postcode":"22401",
    "addr:street":"Plank Rd",
    "iso:country":"US",
    "sg:address":"2326 Plank Rd",
    "sg:city":"Fredericksburg",
    "sg:classifiers":[
        {
            "category":"Food & Beverages",
            "subcategory":"Bakery",
            "type":"Retail Goods"
        }
    ],
    "sg:phone":"+1 540 368 0003",
    "sg:postcode":"22401",
    "sg:province":"VA",
    "sg:tags":[
        "cake",
        "decorating"
    ],
    "wof:name":"Cakes Galore",
    "wof:placetype":"venue"
},
  "geometry": {"coordinates":[-77.499112,38.296291],"type":"Point"}
}