{
  "type": "Feature",
  "properties": {
    "addr:full":"13840 Braddock Rd Centreville VA 20121",
    "addr:housenumber":"13840",
    "addr:postcode":"20121",
    "addr:street":"Braddock Rd",
    "iso:country":"US",
    "sg:address":"13840 Braddock Rd",
    "sg:city":"Centreville",
    "sg:classifiers":[
        {
            "category":"Retail",
            "subcategory":"Laundry & Dry Cleaning",
            "type":"Services"
        }
    ],
    "sg:phone":"+1 703 263 1722",
    "sg:postcode":"20121",
    "sg:province":"VA",
    "sg:tags":[
        "cleaners"
    ],
    "wof:name":"Centreville Brite Cleaners",
    "wof:placetype":"venue"
},
  "geometry": {"coordinates":[-77.426517,38.835468],"type":"Point"}
}