{
  "type": "Feature",
  "properties": {
    "iso:country":"US",
    "sg:address":"13220 Chummy Ln",
    "sg:city":"King George",
    "sg:classifiers":[
        {
            "category":"Professional",
            "subcategory":"Employment Agencies",
            "type":"Services"
        }
    ],
    "sg:phone":"+1 540 775 5340",
    "sg:postcode":"22485",
    "sg:province":"VA",
    "sg:tags":[
        "help",
        "supply"
    ],
    "wof:name":"Sunrise Express",
    "wof:placetype":"venue"
},
  "geometry": {"coordinates":[-77.119747,38.230576],"type":"Point"}
}