{
  "type": "Feature",
  "properties": {
    "addr:full":"422 Wildwood Rd Lynchburg VA 24502",
    "addr:housenumber":"422",
    "addr:postcode":"24502",
    "addr:street":"Wildwood Rd",
    "iso:country":"US",
    "sg:address":"422 Wildwood Rd",
    "sg:city":"Lynchburg",
    "sg:classifiers":[
        {
            "category":"Freight",
            "type":"Transportation"
        }
    ],
    "sg:phone":"+1 434 525 1406",
    "sg:postcode":"24502",
    "sg:province":"VA",
    "sg:tags":[
        "trucking"
    ],
    "wof:name":"Neice's Trucking",
    "wof:placetype":"venue"
},
  "geometry": {"coordinates":[-79.263594,37.297191],"type":"Point"}
}