{
  "type": "Feature",
  "properties": {
    "addr:full":"205 N Main St Edinburg VA 22824",
    "addr:housenumber":"205",
    "addr:postcode":"22824",
    "addr:street":"N Main St",
    "iso:country":"US",
    "sg:address":"205 N Main St",
    "sg:city":"Edinburg",
    "sg:classifiers":[
        {
            "category":"Professional",
            "subcategory":"Business Services",
            "type":"Services"
        },
        {
            "category":"Government",
            "subcategory":"Post Office",
            "type":"Public Place"
        }
    ],
    "sg:phone":"+1 800 275 8777",
    "sg:postcode":"22824",
    "sg:province":"VA",
    "sg:tags":[
        "mail",
        "shipping"
    ],
    "sg:website":"http://www.usps.com",
    "wof:name":"United States Postal Service",
    "wof:placetype":"venue"
},
  "geometry": {"coordinates":[-78.56307099999999,38.82129],"type":"Point"}
}