{
  "type": "Feature",
  "properties": {
    "iso:country":"US",
    "sg:address":"7716 Iroquois Ct",
    "sg:city":"Falls Church",
    "sg:classifiers":[
        {
            "category":"Local Transit",
            "type":"Transportation"
        }
    ],
    "sg:phone":"+1 703 734 1777",
    "sg:postcode":"22043",
    "sg:province":"VA",
    "sg:tags":[
        "passenger"
    ],
    "wof:name":"Sedan Service Inc",
    "wof:placetype":"venue"
},
  "geometry": {"coordinates":[-77.21145199999999,38.903194],"type":"Point"}
}