{
  "type": "Feature",
  "properties": {
    "addr:full":"4434 John Tyler Hwy Williamsburg VA 23185",
    "addr:housenumber":"4434",
    "addr:postcode":"23185",
    "addr:street":"John Tyler Hwy",
    "iso:country":"US",
    "sg:address":"4434 John Tyler Hwy",
    "sg:city":"Williamsburg",
    "sg:classifiers":[
        {
            "category":"Travel",
            "subcategory":"Travel Agent",
            "type":"Entertainment"
        }
    ],
    "sg:phone":"+1 757 220 0402",
    "sg:postcode":"23185",
    "sg:province":"VA",
    "sg:tags":[
        "agency"
    ],
    "wof:name":"Discovery Travel",
    "wof:placetype":"venue"
},
  "geometry": {"coordinates":[-76.76724900000001,37.251183],"type":"Point"}
}