{
  "type": "Feature",
  "properties": {
    "addr:full":"71 Coal Landing Rd Stafford VA 22554",
    "addr:housenumber":"71",
    "addr:postcode":"22554",
    "addr:street":"Coal Landing Rd",
    "iso:country":"US",
    "sg:address":"71 Coal Landing Rd",
    "sg:city":"Stafford",
    "sg:classifiers":[
        {
            "category":"Building & Trades",
            "subcategory":"Construction",
            "type":"Services"
        }
    ],
    "sg:phone":"+1 540 288 3116",
    "sg:postcode":"22554",
    "sg:province":"VA",
    "sg:tags":[
        "heavy"
    ],
    "wof:name":"Ta Loving Company Inc",
    "wof:placetype":"venue"
},
  "geometry": {"coordinates":[-77.39798500000001,38.445829],"type":"Point"}
}