{
  "type": "Feature",
  "properties": {
    "addr:full":"2703 E Princess Anne Rd Norfolk VA 23504",
    "addr:housenumber":"2703",
    "addr:postcode":"23504",
    "addr:street":"E Princess Anne Rd",
    "iso:country":"US",
    "sg:address":"2703 E Princess Anne Rd",
    "sg:city":"Norfolk",
    "sg:classifiers":[
        {
            "category":"Personal",
            "subcategory":"Barber",
            "type":"Services"
        }
    ],
    "sg:phone":"+1 757 623 0666",
    "sg:postcode":"23504",
    "sg:province":"VA",
    "wof:name":"Kappatal Cuts Unisex",
    "wof:placetype":"venue"
},
  "geometry": {"coordinates":[-76.25660499999999,36.855583],"type":"Point"}
}