{
  "type": "Feature",
  "properties": {
    "iso:country":"US",
    "sg:address":"622 Colonial Ave",
    "sg:city":"Colonial Heights",
    "sg:classifiers":[
        {
            "category":"Personal",
            "subcategory":"Tattoo Parlor",
            "type":"Services"
        }
    ],
    "sg:phone":"+1 804 504 8000",
    "sg:postcode":"23834",
    "sg:province":"VA",
    "sg:tags":[
        "tattooing"
    ],
    "wof:name":"USA Tattoo Studio",
    "wof:placetype":"venue"
},
  "geometry": {"coordinates":[-77.40350599999999,37.247203],"type":"Point"}
}