{
  "type": "Feature",
  "properties": {
    "addr:full":"6275 Franconia Rd Alexandria VA 22310",
    "addr:housenumber":"6275",
    "addr:postcode":"22310",
    "addr:street":"Franconia Rd",
    "iso:country":"US",
    "sg:address":"6275 Franconia Rd",
    "sg:city":"Alexandria",
    "sg:classifiers":[
        {
            "category":"Health Services",
            "subcategory":"Doctor",
            "type":"Services"
        }
    ],
    "sg:phone":"+1 703 971 8686",
    "sg:postcode":"22310",
    "sg:province":"VA",
    "sg:tags":[
        "medical"
    ],
    "wof:name":"S Parvin MD",
    "wof:placetype":"venue"
},
  "geometry": {"coordinates":[-77.15343,38.780511],"type":"Point"}
}