{
  "type": "Feature",
  "properties": {
    "iso:country":"US",
    "sg:address":"1059 E Stuart Dr",
    "sg:city":"Galax",
    "sg:classifiers":[
        {
            "category":"Home & Garden",
            "subcategory":"Building Materials",
            "type":"Retail Goods"
        }
    ],
    "sg:phone":"+1 276 238 9141",
    "sg:postcode":"24333",
    "sg:province":"VA",
    "sg:tags":[
        "windows"
    ],
    "wof:name":"Window World Inc",
    "wof:placetype":"venue"
},
  "geometry": {"coordinates":[-80.892821,36.682078],"type":"Point"}
}