{
  "type": "Feature",
  "properties": {
    "iso:country":"US",
    "sg:address":"729 Loyal St",
    "sg:city":"Danville",
    "sg:classifiers":[
        {
            "category":"Home & Garden",
            "subcategory":"Building Materials",
            "type":"Retail Goods"
        },
        {
            "category":"Building & Trades",
            "subcategory":"Construction",
            "type":"Services"
        }
    ],
    "sg:phone":"+1 434 791 4222",
    "sg:postcode":"24541",
    "sg:province":"VA",
    "sg:tags":[
        "glass",
        "window",
        "contractor",
        "plate"
    ],
    "wof:name":"Economy Glass Inc",
    "wof:placetype":"venue"
},
  "geometry": {"coordinates":[-79.393626,36.582741],"type":"Point"}
}