{
  "type": "Feature",
  "properties": {
    "addr:full":"5653 Columbia Pike Falls Church VA 22041",
    "addr:housenumber":"5653",
    "addr:postcode":"22041",
    "addr:street":"Columbia Pike",
    "iso:country":"US",
    "sg:address":"5653 Columbia Pike",
    "sg:city":"Falls Church",
    "sg:classifiers":[
        {
            "category":"Health Services",
            "subcategory":"Optometrist",
            "type":"Services"
        }
    ],
    "sg:phone":"+1 703 578 3600",
    "sg:postcode":"22041",
    "sg:province":"VA",
    "wof:name":"Renner Christopher OD",
    "wof:placetype":"venue"
},
  "geometry": {"coordinates":[-77.12449599999999,38.852501],"type":"Point"}
}