{
  "type": "Feature",
  "properties": {
    "addr:full":"5241 Ashby St Norfolk VA 23502",
    "addr:housenumber":"5241",
    "addr:postcode":"23502",
    "addr:street":"Ashby St",
    "iso:country":"US",
    "sg:address":"5241 Ashby St",
    "sg:city":"Norfolk",
    "sg:classifiers":[
        {
            "category":"Organizations",
            "subcategory":"Religious Organization",
            "type":"Services"
        }
    ],
    "sg:phone":"+1 757 853 8865",
    "sg:postcode":"23502",
    "sg:province":"VA",
    "wof:name":"All Nations Ministries",
    "wof:placetype":"venue"
},
  "geometry": {"coordinates":[-76.221514,36.874124],"type":"Point"}
}