{
  "type": "Feature",
  "properties": {
    "addr:full":"8300 Old Courthouse Rd Vienna VA 22182",
    "addr:housenumber":"8300",
    "addr:postcode":"22182",
    "addr:street":"Old Courthouse Rd",
    "iso:country":"US",
    "sg:address":"8300 Old Courthouse Rd",
    "sg:city":"Vienna",
    "sg:classifiers":[
        {
            "category":"Utilities",
            "subcategory":"Mobile Phone",
            "type":"Services"
        }
    ],
    "sg:phone":"+1 703 506 1475",
    "sg:postcode":"22182",
    "sg:province":"VA",
    "sg:tags":[
        "telephone",
        "cellular"
    ],
    "wof:name":"AAA Wireless",
    "wof:placetype":"venue"
},
  "geometry": {"coordinates":[-77.23178,38.91405],"type":"Point"}
}