{
  "type": "Feature",
  "properties": {
    "iso:country":"US",
    "sg:address":"6050 Clear Springs Rd",
    "sg:city":"Virginia Beach",
    "sg:classifiers":[
        {
            "category":"Wholesale",
            "subcategory":"Durable Goods & Equipment",
            "type":"Manufacturing & Wholesale Goods"
        }
    ],
    "sg:phone":"+1 757 578 7254",
    "sg:postcode":"23464",
    "sg:province":"VA",
    "wof:name":"Royal Glovers Body Care",
    "wof:placetype":"venue"
},
  "geometry": {"coordinates":[-76.208583,36.801223],"type":"Point"}
}