{
  "type": "Feature",
  "properties": {
    "iso:country":"US",
    "sg:address":"1019 Main St",
    "sg:city":"Lynchburg",
    "sg:classifiers":[
        {
            "category":"Shopping",
            "subcategory":"Clothing, Apparel, & Fashions",
            "type":"Retail Goods"
        }
    ],
    "sg:phone":"+1 434 846 7515",
    "sg:postcode":"24504",
    "sg:province":"VA",
    "sg:tags":[
        "furnishing"
    ],
    "wof:name":"Famous Inc",
    "wof:placetype":"venue"
},
  "geometry": {"coordinates":[-79.140981,37.413302],"type":"Point"}
}