{
  "type": "Feature",
  "properties": {
    "iso:country":"US",
    "sg:address":"207 Wallace Ln",
    "sg:city":"Fredericksburg",
    "sg:classifiers":[
        {
            "category":"Manufacturing",
            "subcategory":"Signs",
            "type":"Manufacturing & Wholesale Goods"
        }
    ],
    "sg:phone":"+1 540 898 9068",
    "sg:postcode":"22408",
    "sg:province":"VA",
    "sg:tags":[
        "commercial",
        "specialty",
        "mfg"
    ],
    "wof:name":"G & M Custom Graphics",
    "wof:placetype":"venue"
},
  "geometry": {"coordinates":[-77.497812,38.264408],"type":"Point"}
}