{
  "type": "Feature",
  "properties": {
    "iso:country":"US",
    "sg:address":"4885 Old Dominion Dr",
    "sg:city":"Arlington",
    "sg:classifiers":[
        {
            "category":"Arts & Performance",
            "subcategory":"Dance",
            "type":"Entertainment"
        }
    ],
    "sg:phone":"+1 703 532 5479",
    "sg:postcode":"22207",
    "sg:province":"VA",
    "sg:tags":[
        "instruction",
        "dancing"
    ],
    "wof:name":"Indian Dance Educators",
    "wof:placetype":"venue"
},
  "geometry": {"coordinates":[-77.135226,38.909297],"type":"Point"}
}