{
  "type": "Feature",
  "properties": {
    "addr:full":"9243 Courthouse Rd Fredericksburg VA 22407",
    "addr:housenumber":"9243",
    "addr:postcode":"22407",
    "addr:street":"Courthouse Rd",
    "iso:country":"US",
    "sg:address":"9243 Courthouse Rd",
    "sg:city":"Fredericksburg",
    "sg:classifiers":[
        {
            "category":"Autos & Motor Vehicles",
            "subcategory":"Fuel & Gas Station",
            "type":"Retail Goods"
        }
    ],
    "sg:phone":"+1 540 582 5434",
    "sg:postcode":"22407",
    "sg:province":"VA",
    "sg:tags":[
        "convenience",
        "gasoline",
        "store"
    ],
    "wof:name":"Git N Go",
    "wof:placetype":"venue"
},
  "geometry": {"coordinates":[-77.58644200000001,38.194258],"type":"Point"}
}