{
  "type": "Feature",
  "properties": {
    "addr:full":"116 Chase St Bowling Green VA 22427",
    "addr:housenumber":"116",
    "addr:postcode":"22427",
    "addr:street":"Chase St",
    "iso:country":"US",
    "sg:address":"116 Chase St",
    "sg:city":"Bowling Green",
    "sg:classifiers":[
        {
            "category":"Autos & Motor Vehicles",
            "subcategory":"Auto Supplies",
            "type":"Retail Goods"
        }
    ],
    "sg:phone":"+1 804 633 9837",
    "sg:postcode":"22427",
    "sg:province":"VA",
    "sg:tags":[
        "automobile",
        "parts"
    ],
    "wof:name":"Bowling Green Auto Parts",
    "wof:placetype":"venue"
},
  "geometry": {"coordinates":[-77.34341999999999,38.050166],"type":"Point"}
}