{
  "type": "Feature",
  "properties": {
    "iso:country":"US",
    "sg:address":"110 Terminal Dr",
    "sg:city":"Sterling",
    "sg:classifiers":[
        {
            "category":"Freight",
            "type":"Transportation"
        }
    ],
    "sg:phone":"+1 703 435 4000",
    "sg:postcode":"20166",
    "sg:province":"VA",
    "sg:tags":[
        "mover"
    ],
    "sg:website":"www.victoryvan.com",
    "wof:name":"Victory Van Corp",
    "wof:placetype":"venue"
},
  "geometry": {"coordinates":[-77.423258,38.986437],"type":"Point"}
}