{
  "type": "Feature",
  "properties": {
    "iso:country":"US",
    "sg:address":"365 Barclay Rd",
    "sg:city":"Newport News",
    "sg:classifiers":[
        {
            "category":"Professional",
            "type":"Services"
        }
    ],
    "sg:phone":"+1 757 223 0131",
    "sg:postcode":"23606",
    "sg:province":"VA",
    "sg:tags":[
        "establishment"
    ],
    "wof:name":"Reese & Reese",
    "wof:placetype":"venue"
},
  "geometry": {"coordinates":[-76.515885,37.075924],"type":"Point"}
}