{
  "type": "Feature",
  "properties": {
    "addr:full":"2728 N Mall Dr Virginia Beach VA 23452",
    "addr:housenumber":"2728",
    "addr:postcode":"23452",
    "addr:street":"N Mall Dr",
    "iso:country":"US",
    "sg:address":"2728 N Mall Dr",
    "sg:city":"Virginia Beach",
    "sg:classifiers":[
        {
            "category":"Shopping",
            "subcategory":"Computers & Home Electronics",
            "type":"Retail Goods"
        }
    ],
    "sg:phone":"+1 757 631 8898",
    "sg:postcode":"23452",
    "sg:province":"VA",
    "wof:name":"Computer Renaissance",
    "wof:placetype":"venue"
},
  "geometry": {"coordinates":[-76.069073,36.820565],"type":"Point"}
}