{
  "type": "Feature",
  "properties": {
    "iso:country":"US",
    "sg:address":"613 Pilot House Dr",
    "sg:city":"Newport News",
    "sg:classifiers":[
        {
            "category":"Professional",
            "subcategory":"Employment Agencies",
            "type":"Services"
        }
    ],
    "sg:phone":"+1 757 591 0400",
    "sg:postcode":"23606",
    "sg:province":"VA",
    "sg:tags":[
        "help",
        "supply"
    ],
    "wof:name":"Apple One Employment Services",
    "wof:placetype":"venue"
},
  "geometry": {"coordinates":[-76.478746,37.080447],"type":"Point"}
}