{
  "type": "Feature",
  "properties": {
    "iso:country":"US",
    "sg:address":"146 Garber Ln",
    "sg:city":"Winchester",
    "sg:classifiers":[
        {
            "category":"Retail",
            "subcategory":"Veterinary Services",
            "type":"Services"
        }
    ],
    "sg:phone":"+1 540 662 7811",
    "sg:postcode":"22602",
    "sg:province":"VA",
    "sg:tags":[
        "hospital",
        "animal"
    ],
    "wof:name":"Valley Emergency Veterinary",
    "wof:placetype":"venue"
},
  "geometry": {"coordinates":[-78.15943900000001,39.158933],"type":"Point"}
}