{
  "type": "Feature",
  "properties": {
    "addr:full":"5146 Snead Rd Richmond VA 23224",
    "addr:housenumber":"5146",
    "addr:postcode":"23224",
    "addr:street":"Snead Rd",
    "iso:country":"US",
    "sg:address":"5146 Snead Rd",
    "sg:city":"Richmond",
    "sg:classifiers":[
        {
            "category":"Education",
            "subcategory":"School",
            "type":"Public Place"
        }
    ],
    "sg:phone":"+1 804 745 3702",
    "sg:postcode":"23224",
    "sg:province":"VA",
    "sg:website":"www.richmond.k12.va.us",
    "wof:name":"J L Francis Elementary School",
    "wof:placetype":"venue"
},
  "geometry": {"coordinates":[-77.48719699999999,37.47608],"type":"Point"}
}