{
  "type": "Feature",
  "properties": {
    "iso:country":"US",
    "sg:address":"57 S Airport Dr",
    "sg:city":"Highland Springs",
    "sg:classifiers":[
        {
            "category":"Personal",
            "subcategory":"Beauty Salon",
            "type":"Services"
        }
    ],
    "sg:phone":"+1 804 737 4951",
    "sg:postcode":"23075",
    "sg:province":"VA",
    "sg:tags":[
        "shop"
    ],
    "wof:name":"Hair Art",
    "wof:placetype":"venue"
},
  "geometry": {"coordinates":[-77.32086200000001,37.536616],"type":"Point"}
}