{
  "type": "Feature",
  "properties": {
    "iso:country":"US",
    "sg:address":"7005 Hickory Hill Rd",
    "sg:city":"Falls Church",
    "sg:classifiers":[
        {
            "category":"Building & Trades",
            "subcategory":"Construction",
            "type":"Services"
        }
    ],
    "sg:phone":"+1 703 533 7766",
    "sg:postcode":"22042",
    "sg:province":"VA",
    "sg:tags":[
        "contractor",
        "carpentry"
    ],
    "wof:name":"Thomas G Hamilton Home Imprvs",
    "wof:placetype":"venue"
},
  "geometry": {"coordinates":[-77.18593,38.853913],"type":"Point"}
}