{
  "type": "Feature",
  "properties": {
    "addr:full":"5201 Leesburg Pike Falls Church VA 22041",
    "addr:housenumber":"5201",
    "addr:postcode":"22041",
    "addr:street":"Leesburg Pike",
    "iso:country":"US",
    "sg:address":"5201 Leesburg Pike",
    "sg:city":"Falls Church",
    "sg:classifiers":[
        {
            "category":"Health Services",
            "subcategory":"Chiropractor",
            "type":"Services"
        }
    ],
    "sg:phone":"+1 703 671 7373",
    "sg:postcode":"22041",
    "sg:province":"VA",
    "wof:name":"Dr Joseph Espositopc",
    "wof:placetype":"venue"
},
  "geometry": {"coordinates":[-77.11769700000001,38.845717],"type":"Point"}
}