{
  "type": "Feature",
  "properties": {
    "addr:full":"920 Park Ave Falls Church VA 22046",
    "addr:housenumber":"920",
    "addr:postcode":"22046",
    "addr:street":"Park Ave",
    "iso:country":"US",
    "sg:address":"920 Park Ave",
    "sg:city":"Falls Church",
    "sg:classifiers":[
        {
            "category":"Utilities",
            "subcategory":"Telephone",
            "type":"Services"
        }
    ],
    "sg:phone":"+1 703 534 6953",
    "sg:postcode":"22046",
    "sg:province":"VA",
    "sg:tags":[
        "communications"
    ],
    "wof:name":"Sabo Specialties",
    "wof:placetype":"venue"
},
  "geometry": {"coordinates":[-77.182366,38.891129],"type":"Point"}
}