{
  "type": "Feature",
  "properties": {
    "iso:country":"US",
    "sg:address":"11108 Leavells Rd",
    "sg:city":"Fredericksburg",
    "sg:classifiers":[
        {
            "category":"Education",
            "subcategory":"School",
            "type":"Public Place"
        }
    ],
    "sg:phone":"+1 540 786 4532",
    "sg:postcode":"22407",
    "sg:province":"VA",
    "wof:name":"Battlefield Elementary School",
    "wof:placetype":"venue"
},
  "geometry": {"coordinates":[-77.539973,38.262454],"type":"Point"}
}