{
  "type": "Feature",
  "properties": {
    "addr:full":"11701 Gordon School Rd Richmond VA 23236",
    "addr:housenumber":"11701",
    "addr:postcode":"23236",
    "addr:street":"Gordon School Rd",
    "iso:country":"US",
    "sg:address":"11701 Gordon School Rd",
    "sg:city":"Richmond",
    "sg:classifiers":[
        {
            "category":"Education",
            "subcategory":"School",
            "type":"Public Place"
        }
    ],
    "sg:phone":"+1 804 378 2410",
    "sg:postcode":"23236",
    "sg:province":"VA",
    "sg:website":"www.chesterfield.k12.va.us",
    "wof:name":"W W Gordon Elementary School",
    "wof:placetype":"venue"
},
  "geometry": {"coordinates":[-77.616275,37.478933],"type":"Point"}
}