{
  "type": "Feature",
  "properties": {
    "addr:full":"111 S Stocker Ct 200 Williamsburg VA 23188",
    "addr:housenumber":"111;200",
    "addr:postcode":"23188",
    "addr:street":"S Stocker Ct",
    "iso:country":"US",
    "sg:address":"111 S Stocker Ct 200",
    "sg:city":"Williamsburg",
    "sg:classifiers":[
        {
            "category":"Banks & Credit Unions",
            "subcategory":"Financial Services",
            "type":"Services"
        }
    ],
    "sg:phone":"+1 757 761 8760",
    "sg:postcode":"23188",
    "sg:province":"VA",
    "sg:tags":[
        "consultant",
        "planning"
    ],
    "wof:name":"Investforcollege.Com",
    "wof:placetype":"venue"
},
  "geometry": {"coordinates":[-76.769251,37.30621],"type":"Point"}
}