{
  "type": "Feature",
  "properties": {
    "addr:full":"4401 19th St N Arlington VA 22207",
    "addr:housenumber":"4401",
    "addr:postcode":"22207",
    "addr:street":"19Th St N",
    "iso:country":"US",
    "sg:address":"4401 19th St N",
    "sg:city":"Arlington",
    "sg:classifiers":[
        {
            "category":"Professional",
            "subcategory":"Management & Consulting",
            "type":"Services"
        }
    ],
    "sg:phone":"+1 703 351 9779",
    "sg:postcode":"22207",
    "sg:province":"VA",
    "sg:tags":[
        "business"
    ],
    "wof:name":"Sjm Business Consulting LLC",
    "wof:placetype":"venue"
},
  "geometry": {"coordinates":[-77.116629,38.893509],"type":"Point"}
}