{
  "type": "Feature",
  "properties": {
    "iso:country":"US",
    "sg:address":"8176 Richmond Hwy",
    "sg:city":"Alexandria",
    "sg:classifiers":[
        {
            "category":"Retail",
            "subcategory":"Repair Shop",
            "type":"Services"
        }
    ],
    "sg:phone":"+1 703 780 0909",
    "sg:postcode":"22309",
    "sg:province":"VA",
    "sg:tags":[
        "upholsterer"
    ],
    "wof:name":"Ahn's Upholstery",
    "wof:placetype":"venue"
},
  "geometry": {"coordinates":[-77.094735,38.736029],"type":"Point"}
}