{
  "type": "Feature",
  "properties": {
    "addr:full":"9902 Fairfax Sq Fairfax VA 22031",
    "addr:housenumber":"9902",
    "addr:postcode":"22031",
    "addr:street":"Fairfax Sq",
    "iso:country":"US",
    "sg:address":"9902 Fairfax Sq",
    "sg:city":"Fairfax",
    "sg:classifiers":[
        {
            "category":"Education",
            "subcategory":"Special Training",
            "type":"Public Place"
        }
    ],
    "sg:phone":"+1 703 385 6776",
    "sg:postcode":"22031",
    "sg:province":"VA",
    "sg:tags":[
        "instructor",
        "language"
    ],
    "wof:name":"Gursen Riza",
    "wof:placetype":"venue"
},
  "geometry": {"coordinates":[-77.289635,38.843809],"type":"Point"}
}