{
  "type": "Feature",
  "properties": {
    "addr:full":"9024 Ellenwood Ln Fairfax VA 22032",
    "addr:housenumber":"9024",
    "addr:postcode":"22032",
    "addr:street":"Ellenwood Ln",
    "iso:country":"US",
    "sg:address":"9024 Ellenwood Ln",
    "sg:city":"Fairfax",
    "sg:classifiers":[
        {
            "category":"Travel",
            "subcategory":"Travel Agent",
            "type":"Entertainment"
        }
    ],
    "sg:phone":"+1 703 978 4926",
    "sg:postcode":"22032",
    "sg:province":"VA",
    "sg:tags":[
        "agency",
        "bureau"
    ],
    "wof:name":"Clipper Travel Intl",
    "wof:placetype":"venue"
},
  "geometry": {"coordinates":[-77.257193,38.833527],"type":"Point"}
}