{
  "type": "Feature",
  "properties": {
    "addr:full":"39088 Bolington Rd Lovettsville VA 20180",
    "addr:postcode":"39088;20180",
    "addr:street":"Bolington Rd",
    "iso:country":"US",
    "sg:address":"39088 Bolington Rd",
    "sg:city":"Lovettsville",
    "sg:classifiers":[
        {
            "category":"Professional",
            "subcategory":"Computer Services",
            "type":"Services"
        }
    ],
    "sg:phone":"+1 540 822 5500",
    "sg:postcode":"20180",
    "sg:province":"VA",
    "sg:tags":[
        "design",
        "system"
    ],
    "wof:name":"Information Resource Engrg",
    "wof:placetype":"venue"
},
  "geometry": {"coordinates":[-77.64967300000001,39.23062],"type":"Point"}
}