{
  "type": "Feature",
  "properties": {
    "addr:full":"12480 Warwick Blvd Newport News VA 23606",
    "addr:housenumber":"12480",
    "addr:postcode":"23606",
    "addr:street":"Warwick Blvd",
    "iso:country":"US",
    "sg:address":"12480 Warwick Blvd",
    "sg:city":"Newport News",
    "sg:classifiers":[
        {
            "category":"Banks & Credit Unions",
            "subcategory":"Bank",
            "type":"Services"
        }
    ],
    "sg:phone":"+1 757 594 9630",
    "sg:postcode":"23606",
    "sg:province":"VA",
    "sg:tags":[
        "institution",
        "business"
    ],
    "wof:name":"Express Check Advance",
    "wof:placetype":"venue"
},
  "geometry": {"coordinates":[-76.49368200000001,37.073623],"type":"Point"}
}