{
  "type": "Feature",
  "properties": {
    "iso:country":"US",
    "sg:address":"5 Graham St",
    "sg:city":"Fredericksburg",
    "sg:classifiers":[
        {
            "category":"Health Services",
            "subcategory":"Clinic",
            "type":"Services"
        }
    ],
    "sg:phone":"+1 540 370 1745",
    "sg:postcode":"22405",
    "sg:province":"VA",
    "sg:tags":[
        "home",
        "care"
    ],
    "wof:name":"T L C Registry",
    "wof:placetype":"venue"
},
  "geometry": {"coordinates":[-77.423011,38.2745],"type":"Point"}
}