{
  "type": "Feature",
  "properties": {
    "iso:country":"US",
    "sg:address":"7349 Wolf Run Shoals Rd",
    "sg:city":"Fairfax Station",
    "sg:classifiers":[
        {
            "category":"Real Estate",
            "subcategory":"Architect",
            "type":"Services"
        },
        {
            "category":"Professional",
            "subcategory":"Engineering",
            "type":"Services"
        }
    ],
    "sg:phone":"+1 703 249 0177",
    "sg:postcode":"22039",
    "sg:province":"VA",
    "sg:tags":[
        "architectural",
        "engineer"
    ],
    "wof:name":"Charles Engineering Co Inc",
    "wof:placetype":"venue"
},
  "geometry": {"coordinates":[-77.339984,38.757996],"type":"Point"}
}