{
  "type": "Feature",
  "properties": {
    "addr:full":"530 King St Alexandria VA 22314",
    "addr:housenumber":"530",
    "addr:postcode":"22314",
    "addr:street":"King St",
    "iso:country":"US",
    "sg:address":"530 King St",
    "sg:city":"Alexandria",
    "sg:classifiers":[
        {
            "category":"Shopping",
            "subcategory":"Optical Goods",
            "type":"Retail Goods"
        }
    ],
    "sg:phone":"+1 703 683 3822",
    "sg:postcode":"22314",
    "sg:province":"VA",
    "sg:website":"http://www.voorthuis.com",
    "wof:name":"Voorthuis Opticians Inc",
    "wof:placetype":"venue"
},
  "geometry": {"coordinates":[-77.045098,38.804822],"type":"Point"}
}