{
  "type": "Feature",
  "properties": {
    "addr:full":"164 Standiford Rd Union Hall VA 24176",
    "addr:housenumber":"164",
    "addr:postcode":"24176",
    "addr:street":"Standiford Rd",
    "iso:country":"US",
    "sg:address":"164 Standiford Rd",
    "sg:city":"Union Hall",
    "sg:classifiers":[
        {
            "category":"Manufacturing",
            "subcategory":"Lumber",
            "type":"Manufacturing & Wholesale Goods"
        }
    ],
    "sg:phone":"+1 540 576 2231",
    "sg:postcode":"24176",
    "sg:province":"VA",
    "sg:tags":[
        "hardwood",
        "mill"
    ],
    "wof:name":"Purdue Sawmill",
    "wof:placetype":"venue"
},
  "geometry": {"coordinates":[-79.684907,37.006265],"type":"Point"}
}