{
  "type": "Feature",
  "properties": {
    "iso:country":"US",
    "sg:address":"7300 Pineleaf Dr",
    "sg:city":"Richmond",
    "sg:classifiers":[
        {
            "category":"Professional",
            "subcategory":"Art Services",
            "type":"Services"
        }
    ],
    "sg:phone":"+1 804 275 5591",
    "sg:postcode":"23234",
    "sg:province":"VA",
    "sg:tags":[
        "photographer"
    ],
    "sg:website":"www.videodiver.com",
    "wof:name":"Moore's Diving & Underwater",
    "wof:placetype":"venue"
},
  "geometry": {"coordinates":[-77.495047,37.415359],"type":"Point"}
}