{
  "type": "Feature",
  "properties": {
    "addr:full":"18 E Rosemont Ave Alexandria VA 22301",
    "addr:housenumber":"18",
    "addr:postcode":"22301",
    "addr:street":"E Rosemont Ave",
    "iso:country":"US",
    "sg:address":"18 E Rosemont Ave",
    "sg:city":"Alexandria",
    "sg:classifiers":[
        {
            "category":"Manufacturing",
            "subcategory":"Printing",
            "type":"Manufacturing & Wholesale Goods"
        }
    ],
    "sg:phone":"+1 703 739 4090",
    "sg:postcode":"22301",
    "sg:province":"VA",
    "sg:tags":[
        "publisher"
    ],
    "wof:name":"Oreana Press",
    "wof:placetype":"venue"
},
  "geometry": {"coordinates":[-77.05872599999999,38.810207],"type":"Point"}
}