{
  "type": "Feature",
  "properties": {
    "addr:full":"4702 Forest Hill Ave Richmond VA 23225",
    "addr:housenumber":"4702",
    "addr:postcode":"23225",
    "addr:street":"Forest Hill Ave",
    "iso:country":"US",
    "sg:address":"4702 Forest Hill Ave",
    "sg:city":"Richmond",
    "sg:classifiers":[
        {
            "category":"Restaurant",
            "type":"Food & Drink"
        }
    ],
    "sg:phone":"+1 804 233 3022",
    "sg:postcode":"23225",
    "sg:province":"VA",
    "wof:name":"Cieligo Lindo Mexican Rstrnt",
    "wof:placetype":"venue"
},
  "geometry": {"coordinates":[-77.487206,37.520631],"type":"Point"}
}