{
  "type": "Feature",
  "properties": {
    "addr:full":"4327 Ravensworth Rd Annandale VA 22003",
    "addr:housenumber":"4327",
    "addr:postcode":"22003",
    "addr:street":"Ravensworth Rd",
    "iso:country":"US",
    "sg:address":"4327 Ravensworth Rd",
    "sg:city":"Annandale",
    "sg:classifiers":[
        {
            "category":"Farming",
            "subcategory":"Livestock Farm",
            "type":"Manufacturing & Wholesale Goods"
        }
    ],
    "sg:phone":"+1 703 354 8881",
    "sg:postcode":"22003",
    "sg:province":"VA",
    "sg:tags":[
        "specialty",
        "animal"
    ],
    "wof:name":"Reef Boutique Inc",
    "wof:placetype":"venue"
},
  "geometry": {"coordinates":[-77.198663,38.828],"type":"Point"}
}