{
  "type": "Feature",
  "properties": {
    "iso:country":"US",
    "sg:address":"7712 Thor Dr",
    "sg:city":"Annandale",
    "sg:classifiers":[
        {
            "category":"Professional",
            "subcategory":"Engineering",
            "type":"Services"
        }
    ],
    "sg:phone":"+1 703 573 6321",
    "sg:postcode":"22003",
    "sg:province":"VA",
    "wof:name":"Rv Construction Inc",
    "wof:placetype":"venue"
},
  "geometry": {"coordinates":[-77.21132799999999,38.847405],"type":"Point"}
}