{
  "type": "Feature",
  "properties": {
    "iso:country":"US",
    "sg:address":"900 N Main St",
    "sg:city":"Suffolk",
    "sg:classifiers":[
        {
            "category":"Home & Garden",
            "subcategory":"Furniture",
            "type":"Retail Goods"
        }
    ],
    "sg:phone":"+1 757 925 2196",
    "sg:postcode":"23434",
    "sg:province":"VA",
    "wof:name":"Schewels Furniture",
    "wof:placetype":"venue"
},
  "geometry": {"coordinates":[-76.583473,36.742864],"type":"Point"}
}