{
  "type": "Feature",
  "properties": {
    "addr:full":"5114 Greenwich Rd Virginia Beach VA 23462",
    "addr:housenumber":"5114",
    "addr:postcode":"23462",
    "addr:street":"Greenwich Rd",
    "iso:country":"US",
    "sg:address":"5114 Greenwich Rd",
    "sg:city":"Virginia Beach",
    "sg:classifiers":[
        {
            "category":"Freight",
            "type":"Transportation"
        }
    ],
    "sg:phone":"+1 757 271 1694",
    "sg:postcode":"23462",
    "sg:province":"VA",
    "wof:name":"United Shipping Solutions",
    "wof:placetype":"venue"
},
  "geometry": {"coordinates":[-76.160732,36.83669],"type":"Point"}
}