{
  "type": "Feature",
  "properties": {
    "iso:country":"US",
    "sg:address":"627 Glendale Rd",
    "sg:city":"Galax",
    "sg:classifiers":[
        {
            "category":"Autos & Motor Vehicles",
            "subcategory":"Automobile Sales",
            "type":"Retail Goods"
        }
    ],
    "sg:phone":"+1 276 236 5167",
    "sg:postcode":"24333",
    "sg:province":"VA",
    "sg:tags":[
        "car",
        "dealer"
    ],
    "wof:name":"Mink Pontiac-Buick-GMC Inc",
    "wof:placetype":"venue"
},
  "geometry": {"coordinates":[-80.91794400000001,36.672133],"type":"Point"}
}