{
  "type": "Feature",
  "properties": {
    "addr:full":"21559 Cascades Pkwy Sterling VA 20166",
    "addr:housenumber":"21559",
    "addr:postcode":"20166",
    "addr:street":"Cascades Pkwy",
    "iso:country":"US",
    "sg:address":"21559 Cascades Pkwy",
    "sg:city":"Sterling",
    "sg:classifiers":[
        {
            "category":"Organizations",
            "subcategory":"Non-profit Organization",
            "type":"Services"
        },
        {
            "category":"Health Services",
            "subcategory":"Clinic",
            "type":"Services"
        }
    ],
    "sg:phone":"+1 703 430 7047",
    "sg:postcode":"20166",
    "sg:province":"VA",
    "sg:tags":[
        "information",
        "treatment",
        "specialty",
        "alcoholism",
        "outpatient"
    ],
    "wof:name":"Stepping Stones Men's Group",
    "wof:placetype":"venue"
},
  "geometry": {"coordinates":[-77.41239400000001,39.016299],"type":"Point"}
}