{
  "type": "Feature",
  "properties": {
    "addr:full":"3260 Duke St Alexandria VA 22314",
    "addr:housenumber":"3260",
    "addr:postcode":"22314",
    "addr:street":"Duke St",
    "iso:country":"US",
    "sg:address":"3260 Duke St",
    "sg:city":"Alexandria",
    "sg:classifiers":[
        {
            "category":"Professional",
            "type":"Services"
        }
    ],
    "sg:phone":"+1 703 247 4212",
    "sg:postcode":"22314",
    "sg:province":"VA",
    "wof:name":"Oceanwatch",
    "wof:placetype":"venue"
},
  "geometry": {"coordinates":[-77.083956,38.80777],"type":"Point"}
}