{
  "type": "Feature",
  "properties": {
    "addr:full":"126 Garrett St Charlottesville VA 22902",
    "addr:housenumber":"126",
    "addr:postcode":"22902",
    "addr:street":"Garrett St",
    "iso:country":"US",
    "sg:address":"126 Garrett St",
    "sg:city":"Charlottesville",
    "sg:classifiers":[
        {
            "category":"Personal",
            "subcategory":"Beauty Salon",
            "type":"Services"
        },
        {
            "category":"Personal",
            "subcategory":"Day Spa",
            "type":"Services"
        }
    ],
    "sg:phone":"+1 434 979 5556",
    "sg:postcode":"22902",
    "sg:province":"VA",
    "sg:tags":[
        "hair"
    ],
    "sg:website":"www.moxiehairlounge.com",
    "wof:name":"Moxie Hair Lounge",
    "wof:placetype":"venue"
},
  "geometry": {"coordinates":[-78.48248700000001,38.028529],"type":"Point"}
}