{
  "type": "Feature",
  "properties": {
    "addr:full":"5411 Williamson Rd NE Roanoke VA 24012",
    "addr:housenumber":"5411",
    "addr:postcode":"24012",
    "addr:street":"Williamson Rd Ne",
    "iso:country":"US",
    "sg:address":"5411 Williamson Rd NE",
    "sg:city":"Roanoke",
    "sg:classifiers":[
        {
            "category":"Retail",
            "subcategory":"Auto Repair",
            "type":"Services"
        }
    ],
    "sg:phone":"+1 540 265 4443",
    "sg:postcode":"24012",
    "sg:province":"VA",
    "sg:tags":[
        "body",
        "special",
        "mfg"
    ],
    "wof:name":"Gabes Graphix",
    "wof:placetype":"venue"
},
  "geometry": {"coordinates":[-79.95367,37.323557],"type":"Point"}
}