{
  "type": "Feature",
  "properties": {
    "addr:full":"2164 Royal Oak Cir Lynchburg VA 24503",
    "addr:housenumber":"2164",
    "addr:postcode":"24503",
    "addr:street":"Royal Oak Cir",
    "iso:country":"US",
    "sg:address":"2164 Royal Oak Cir",
    "sg:city":"Lynchburg",
    "sg:classifiers":[
        {
            "category":"Real Estate",
            "subcategory":"Real Estate Agent",
            "type":"Services"
        }
    ],
    "sg:phone":"+1 434 384 9021",
    "sg:postcode":"24503",
    "sg:province":"VA",
    "wof:name":"Graves Mill Structures LLC",
    "wof:placetype":"venue"
},
  "geometry": {"coordinates":[-79.22518599999999,37.44711],"type":"Point"}
}