{
  "type": "Feature",
  "properties": {
    "addr:full":"114 N Hicks St Lawrenceville VA 23868",
    "addr:housenumber":"114",
    "addr:postcode":"23868",
    "addr:street":"N Hicks St",
    "iso:country":"US",
    "sg:address":"114 N Hicks St",
    "sg:city":"Lawrenceville",
    "sg:classifiers":[
        {
            "category":"Professional",
            "subcategory":"Computer Services",
            "type":"Services"
        }
    ],
    "sg:phone":"+1 434 848 3472",
    "sg:postcode":"23868",
    "sg:province":"VA",
    "sg:tags":[
        "repair"
    ],
    "sg:website":"www.syslinkinc.com",
    "wof:name":"Syslink Communications",
    "wof:placetype":"venue"
},
  "geometry": {"coordinates":[-77.848777,36.757049],"type":"Point"}
}