{
  "type": "Feature",
  "properties": {
    "addr:full":"2729 Cumberland Rd Farmville VA 23901",
    "addr:housenumber":"2729",
    "addr:postcode":"23901",
    "addr:street":"Cumberland Rd",
    "iso:country":"US",
    "sg:address":"2729 Cumberland Rd",
    "sg:city":"Farmville",
    "sg:classifiers":[
        {
            "category":"Shopping",
            "subcategory":"Gifts & Souvenirs",
            "type":"Retail Goods"
        },
        {
            "category":"Personal",
            "subcategory":"Beauty Salon",
            "type":"Services"
        }
    ],
    "sg:phone":"+1 804 492 9930",
    "sg:postcode":"23901",
    "sg:province":"VA",
    "sg:tags":[
        "shop"
    ],
    "wof:name":"Beauty For Ashes Gifts & More",
    "wof:placetype":"venue"
},
  "geometry": {"coordinates":[-78.356049,37.409558],"type":"Point"}
}