{
  "type": "Feature",
  "properties": {
    "iso:country":"US",
    "sg:address":"10369 Democracy Ln",
    "sg:city":"Fairfax",
    "sg:classifiers":[
        {
            "category":"Professional",
            "subcategory":"Advertising",
            "type":"Services"
        }
    ],
    "sg:phone":"+1 703 691 1232",
    "sg:postcode":"22030",
    "sg:province":"VA",
    "sg:tags":[
        "mail",
        "direct"
    ],
    "wof:name":"Home Town Magazines",
    "wof:placetype":"venue"
},
  "geometry": {"coordinates":[-77.300591,38.849725],"type":"Point"}
}