{
  "type": "Feature",
  "properties": {
    "addr:full":"1025 Pechin Ave SE Roanoke VA 24013",
    "addr:housenumber":"1025",
    "addr:postcode":"24013",
    "addr:street":"Pechin Ave Se",
    "iso:country":"US",
    "sg:address":"1025 Pechin Ave SE",
    "sg:city":"Roanoke",
    "sg:classifiers":[
        {
            "category":"Professional",
            "type":"Services"
        }
    ],
    "sg:phone":"+1 540 345 3291",
    "sg:postcode":"24013",
    "sg:province":"VA",
    "wof:name":"Norman P Bumgarner Jr",
    "wof:placetype":"venue"
},
  "geometry": {"coordinates":[-79.92420799999999,37.261425],"type":"Point"}
}