{
  "type": "Feature",
  "properties": {
    "iso:country":"US",
    "sg:address":"120 S Payne St",
    "sg:city":"Alexandria",
    "sg:classifiers":[
        {
            "category":"Professional",
            "subcategory":"Management & Consulting",
            "type":"Services"
        }
    ],
    "sg:phone":"+1 703 684 7300",
    "sg:postcode":"22314",
    "sg:province":"VA",
    "sg:tags":[
        "consultant",
        "business"
    ],
    "wof:name":"Bentley Adams Hargett Riley Co",
    "wof:placetype":"venue"
},
  "geometry": {"coordinates":[-77.053788,38.804767],"type":"Point"}
}