{
  "type": "Feature",
  "properties": {
    "iso:country":"US",
    "sg:address":"1414 Gort Ct",
    "sg:city":"Portsmouth",
    "sg:classifiers":[
        {
            "category":"Building & Trades",
            "subcategory":"Landscaping Services",
            "type":"Services"
        }
    ],
    "sg:phone":"+1 757 485 1633",
    "sg:postcode":"23701",
    "sg:province":"VA",
    "sg:tags":[
        "tree"
    ],
    "wof:name":"J Wright Tree Svc",
    "wof:placetype":"venue"
},
  "geometry": {"coordinates":[-76.375913,36.788483],"type":"Point"}
}