{
  "type": "Feature",
  "properties": {
    "addr:full":"46304 McClellan Way Sterling VA 20165",
    "addr:housenumber":"46304",
    "addr:postcode":"20165",
    "addr:street":"Mcclellan Way",
    "iso:country":"US",
    "sg:address":"46304 McClellan Way",
    "sg:city":"Sterling",
    "sg:classifiers":[
        {
            "category":"Health Services",
            "subcategory":"Chiropractor",
            "type":"Services"
        }
    ],
    "sg:phone":"+1 703 433 5031",
    "sg:postcode":"20165",
    "sg:province":"VA",
    "wof:name":"Joseph Mazzara DC",
    "wof:placetype":"venue"
},
  "geometry": {"coordinates":[-77.398572,39.032468],"type":"Point"}
}