{
  "type": "Feature",
  "properties": {
    "addr:full":"957 Edwin Dr Virginia Beach VA 23464",
    "addr:housenumber":"957",
    "addr:postcode":"23464",
    "addr:street":"Edwin Dr",
    "iso:country":"US",
    "sg:address":"957 Edwin Dr",
    "sg:city":"Virginia Beach",
    "sg:classifiers":[
        {
            "category":"Building & Trades",
            "subcategory":"Construction",
            "type":"Services"
        }
    ],
    "sg:phone":"+1 757 474 1281",
    "sg:postcode":"23464",
    "sg:province":"VA",
    "sg:tags":[
        "house",
        "nonresidential"
    ],
    "wof:name":"Ewing Construction",
    "wof:placetype":"venue"
},
  "geometry": {"coordinates":[-76.15061799999999,36.809191],"type":"Point"}
}