{
  "type": "Feature",
  "properties": {
    "addr:full":"4201 Creek Way Chester VA 23831",
    "addr:housenumber":"4201",
    "addr:postcode":"23831",
    "addr:street":"Creek Way",
    "iso:country":"US",
    "sg:address":"4201 Creek Way",
    "sg:city":"Chester",
    "sg:classifiers":[
        {
            "category":"Real Estate",
            "subcategory":"Real Estate Operator",
            "type":"Services"
        }
    ],
    "sg:phone":"+1 804 751 9292",
    "sg:postcode":"23831",
    "sg:province":"VA",
    "sg:tags":[
        "apartment",
        "complex"
    ],
    "sg:website":"www.lincolnapts.com",
    "wof:name":"Ashton Creek Apartments",
    "wof:placetype":"venue"
},
  "geometry": {"coordinates":[-77.441698,37.344095],"type":"Point"}
}