{
  "type": "Feature",
  "properties": {
    "addr:full":"3155 Duke St Alexandria VA 22314",
    "addr:housenumber":"3155",
    "addr:postcode":"22314",
    "addr:street":"Duke St",
    "iso:country":"US",
    "sg:address":"3155 Duke St",
    "sg:city":"Alexandria",
    "sg:classifiers":[
        {
            "category":"Professional",
            "subcategory":"Business Services",
            "type":"Services"
        }
    ],
    "sg:phone":"+1 703 212 8226",
    "sg:postcode":"22314",
    "sg:province":"VA",
    "sg:tags":[
        "interior",
        "consultant",
        "design",
        "decorator"
    ],
    "sg:website":"www.mastercraftinteriors.com",
    "wof:name":"Mastercraft Interiors LTD",
    "wof:placetype":"venue"
},
  "geometry": {"coordinates":[-77.08689,38.80827],"type":"Point"}
}