{
  "type": "Feature",
  "properties": {
    "addr:full":"7019 Backlick Ct Springfield VA 22151",
    "addr:housenumber":"7019",
    "addr:postcode":"22151",
    "addr:street":"Backlick Ct",
    "iso:country":"US",
    "sg:address":"7019 Backlick Ct",
    "sg:city":"Springfield",
    "sg:classifiers":[
        {
            "category":"Insurance",
            "subcategory":"Title Insurance",
            "type":"Services"
        }
    ],
    "sg:phone":"+1 703 256 8880",
    "sg:postcode":"22151",
    "sg:province":"VA",
    "sg:tags":[
        "carrier"
    ],
    "wof:name":"Southshore Title & Escrow Inc",
    "wof:placetype":"venue"
},
  "geometry": {"coordinates":[-77.18546600000001,38.801278],"type":"Point"}
}