{
  "type": "Feature",
  "properties": {
    "addr:full":"707 Johnston Willis Dr Richmond VA 23236",
    "addr:housenumber":"707",
    "addr:postcode":"23236",
    "addr:street":"Johnston Willis Dr",
    "iso:country":"US",
    "sg:address":"707 Johnston Willis Dr",
    "sg:city":"Richmond",
    "sg:classifiers":[
        {
            "category":"Real Estate",
            "subcategory":"Developer",
            "type":"Services"
        }
    ],
    "sg:phone":"+1 804 740 0600",
    "sg:postcode":"23236",
    "sg:province":"VA",
    "wof:name":"Southport Financial Svc Inc",
    "wof:placetype":"venue"
},
  "geometry": {"coordinates":[-77.59146800000001,37.502291],"type":"Point"}
}