{
  "type": "Feature",
  "properties": {
    "addr:full":"7315 Bishop Creek Rd Lynch Station VA 24571",
    "addr:housenumber":"7315",
    "addr:postcode":"24571",
    "addr:street":"Bishop Creek Rd",
    "iso:country":"US",
    "sg:address":"7315 Bishop Creek Rd",
    "sg:city":"Lynch Station",
    "sg:classifiers":[
        {
            "category":"Building & Trades",
            "subcategory":"Landscaping Services",
            "type":"Services"
        }
    ],
    "sg:phone":"+1 540 297 3454",
    "sg:postcode":"24571",
    "sg:province":"VA",
    "sg:tags":[
        "landscape",
        "contractor"
    ],
    "wof:name":"David's Tree Svc",
    "wof:placetype":"venue"
},
  "geometry": {"coordinates":[-79.412916,37.18258],"type":"Point"}
}