{
  "type": "Feature",
  "properties": {
    "addr:full":"615 S Jefferson St Roanoke VA 24011",
    "addr:housenumber":"615",
    "addr:postcode":"24011",
    "addr:street":"S Jefferson St",
    "iso:country":"US",
    "sg:address":"615 S Jefferson St",
    "sg:city":"Roanoke",
    "sg:classifiers":[
        {
            "category":"Personal",
            "subcategory":"Barber",
            "type":"Services"
        }
    ],
    "sg:phone":"+1 540 342 7005",
    "sg:postcode":"24011",
    "sg:province":"VA",
    "sg:tags":[
        "shop",
        "beauty"
    ],
    "wof:name":"Gary Hair Styling & Associates",
    "wof:placetype":"venue"
},
  "geometry": {"coordinates":[-79.94071700000001,37.268595],"type":"Point"}
}