{
  "type": "Feature",
  "properties": {
    "addr:full":"23258 Village Rd Unionville VA 22567",
    "addr:housenumber":"23258",
    "addr:postcode":"22567",
    "addr:street":"Village Rd",
    "iso:country":"US",
    "sg:address":"23258 Village Rd",
    "sg:city":"Unionville",
    "sg:classifiers":[
        {
            "category":"Organizations",
            "subcategory":"Religious Organization",
            "type":"Services"
        }
    ],
    "sg:phone":"+1 540 854 5319",
    "sg:postcode":"22567",
    "sg:province":"VA",
    "sg:tags":[
        "church"
    ],
    "wof:name":"Bethlehem United Methodist Chr",
    "wof:placetype":"venue"
},
  "geometry": {"coordinates":[-77.969105,38.259845],"type":"Point"}
}