{
  "type": "Feature",
  "properties": {
    "iso:country":"US",
    "sg:address":"734 Poquoson Ave",
    "sg:city":"Poquoson",
    "sg:classifiers":[
        {
            "category":"Retail",
            "subcategory":"Auto Repair",
            "type":"Services"
        }
    ],
    "sg:phone":"+1 757 868 6753",
    "sg:postcode":"23662",
    "sg:province":"VA",
    "sg:tags":[
        "repairing",
        "automobile"
    ],
    "wof:name":"Tidewater Z Auto Svc",
    "wof:placetype":"venue"
},
  "geometry": {"coordinates":[-76.383565,37.132224],"type":"Point"}
}