{
  "type": "Feature",
  "properties": {
    "addr:full":"401 3rd St SW Roanoke VA 24011",
    "addr:housenumber":"401",
    "addr:postcode":"24011",
    "addr:street":"3Rd St Sw",
    "iso:country":"US",
    "sg:address":"401 3rd St SW",
    "sg:city":"Roanoke",
    "sg:classifiers":[
        {
            "category":"Communications",
            "subcategory":"Television Station",
            "type":"Services"
        }
    ],
    "sg:phone":"+1 540 857 0038",
    "sg:postcode":"24011",
    "sg:province":"VA",
    "wof:name":"Wpxr TV 38",
    "wof:placetype":"venue"
},
  "geometry": {"coordinates":[-79.94533699999999,37.270086],"type":"Point"}
}