{
  "type": "Feature",
  "properties": {
    "addr:full":"1215 Russell Rd Alexandria VA 22301",
    "addr:housenumber":"1215",
    "addr:postcode":"22301",
    "addr:street":"Russell Rd",
    "iso:country":"US",
    "sg:address":"1215 Russell Rd",
    "sg:city":"Alexandria",
    "sg:classifiers":[
        {
            "category":"Professional",
            "subcategory":"Management & Consulting",
            "type":"Services"
        }
    ],
    "sg:phone":"+1 703 683 3909",
    "sg:postcode":"22301",
    "sg:province":"VA",
    "wof:name":"Nadine Hogan & Associates",
    "wof:placetype":"venue"
},
  "geometry": {"coordinates":[-77.065862,38.816823],"type":"Point"}
}