{
  "type": "Feature",
  "properties": {
    "iso:country":"US",
    "sg:address":"621 S Belvidere St",
    "sg:city":"Richmond",
    "sg:classifiers":[
        {
            "category":"Organizations",
            "subcategory":"Membership Organization",
            "type":"Services"
        }
    ],
    "sg:phone":"+1 804 786 2060",
    "sg:postcode":"23220",
    "sg:province":"VA",
    "sg:tags":[
        "profit"
    ],
    "wof:name":"Virginia War Mem Edctl Fndtion",
    "wof:placetype":"venue"
},
  "geometry": {"coordinates":[-77.449065,37.537014],"type":"Point"}
}