{
  "type": "Feature",
  "properties": {
    "addr:full":"14658 Church St Eagle Rock VA 24085",
    "addr:housenumber":"14658",
    "addr:postcode":"24085",
    "addr:street":"Church St",
    "iso:country":"US",
    "sg:address":"14658 Church St",
    "sg:city":"Eagle Rock",
    "sg:classifiers":[
        {
            "category":"Government",
            "subcategory":"Fire Station",
            "type":"Public Place"
        }
    ],
    "sg:phone":"+1 540 884 2190",
    "sg:postcode":"24085",
    "sg:province":"VA",
    "sg:tags":[
        "dept",
        "v"
    ],
    "wof:name":"Eagle Rock Volunteer Fire Dept",
    "wof:placetype":"venue"
},
  "geometry": {"coordinates":[-79.798637,37.639065],"type":"Point"}
}