{
  "type": "Feature",
  "properties": {
    "iso:country":"US",
    "sg:address":"44 Canal Center Plz",
    "sg:city":"Alexandria",
    "sg:classifiers":[
        {
            "category":"Communications",
            "type":"Services"
        }
    ],
    "sg:phone":"+1 703 549 8800",
    "sg:postcode":"22314",
    "sg:province":"VA",
    "sg:tags":[
        "communication",
        "agency",
        "employment"
    ],
    "wof:name":"GLS Associates Inc",
    "wof:placetype":"venue"
},
  "geometry": {"coordinates":[-77.040305,38.81463],"type":"Point"}
}