{
  "type": "Feature",
  "properties": {
    "addr:full":"2219 Beechland Rd Elberon VA 23846",
    "addr:housenumber":"2219",
    "addr:postcode":"23846",
    "addr:street":"Beechland Rd",
    "iso:country":"US",
    "sg:address":"2219 Beechland Rd",
    "sg:city":"Elberon",
    "sg:classifiers":[
        {
            "category":"Farming",
            "subcategory":"Farm",
            "type":"Manufacturing & Wholesale Goods"
        }
    ],
    "sg:phone":"+1 757 294 5119",
    "sg:postcode":"23846",
    "sg:province":"VA",
    "sg:tags":[
        "crop",
        "general"
    ],
    "wof:name":"William Moody",
    "wof:placetype":"venue"
},
  "geometry": {"coordinates":[-76.823492,37.100793],"type":"Point"}
}