{
  "type": "Feature",
  "properties": {
    "iso:country":"US",
    "sg:address":"1624 S Crystal Dr",
    "sg:city":"Arlington",
    "sg:classifiers":[
        {
            "category":"Shopping",
            "subcategory":"Clothing, Apparel, & Fashions",
            "type":"Retail Goods"
        }
    ],
    "sg:phone":"+1 703 413 0608",
    "sg:postcode":"22202",
    "sg:province":"VA",
    "sg:tags":[
        "hosiery"
    ],
    "wof:name":"Soxies",
    "wof:placetype":"venue"
},
  "geometry": {"coordinates":[-77.049137,38.858075],"type":"Point"}
}