{
  "type": "Feature",
  "properties": {
    "iso:country":"US",
    "sg:address":"801 Lakeside Dr",
    "sg:city":"Lynchburg",
    "sg:classifiers":[
        {
            "category":"Personal",
            "type":"Services"
        }
    ],
    "sg:phone":"+1 434 528 5222",
    "sg:postcode":"24501",
    "sg:province":"VA",
    "sg:tags":[
        "consultant",
        "program",
        "health",
        "fitness"
    ],
    "wof:name":"APX Sports Performance Ctr",
    "wof:placetype":"venue"
},
  "geometry": {"coordinates":[-79.168336,37.404908],"type":"Point"}
}