{
  "type": "Feature",
  "properties": {
    "iso:country":"US",
    "sg:address":"3401 E Virginia Beach Blvd",
    "sg:city":"Norfolk",
    "sg:classifiers":[
        {
            "category":"Professional",
            "subcategory":"Detective & Security Services",
            "type":"Services"
        }
    ],
    "sg:phone":"+1 757 466 3380",
    "sg:postcode":"23502",
    "sg:province":"VA",
    "sg:tags":[
        "car"
    ],
    "wof:name":"Dunbar Armored Inc",
    "wof:placetype":"venue"
},
  "geometry": {"coordinates":[-76.24212199999999,36.853987],"type":"Point"}
}