{
  "type": "Feature",
  "properties": {
    "addr:full":"6368 Carters Run Rd Marshall VA 20115",
    "addr:housenumber":"6368",
    "addr:postcode":"20115",
    "addr:street":"Carters Run Rd",
    "iso:country":"US",
    "sg:address":"6368 Carters Run Rd",
    "sg:city":"Marshall",
    "sg:classifiers":[
        {
            "category":"Building & Trades",
            "subcategory":"Electrical",
            "type":"Services"
        }
    ],
    "sg:phone":"+1 540 347 9445",
    "sg:postcode":"20115",
    "sg:province":"VA",
    "sg:tags":[
        "electrical",
        "contractor"
    ],
    "wof:name":"Graham Electric",
    "wof:placetype":"venue"
},
  "geometry": {"coordinates":[-77.865905,38.774163],"type":"Point"}
}