{
  "type": "Feature",
  "properties": {
    "iso:country":"US",
    "sg:address":"447 Denbigh Blvd",
    "sg:city":"Newport News",
    "sg:classifiers":[
        {
            "category":"Restaurant",
            "type":"Food & Drink"
        }
    ],
    "sg:phone":"+1 757 886 0078",
    "sg:postcode":"23608",
    "sg:province":"VA",
    "sg:tags":[
        "eating"
    ],
    "wof:name":"Egg Roll King Inc",
    "wof:placetype":"venue"
},
  "geometry": {"coordinates":[-76.532832,37.131313],"type":"Point"}
}