{
  "type": "Feature",
  "properties": {
    "addr:full":"9942 Community Center Rd Pound VA 24279",
    "addr:housenumber":"9942",
    "addr:postcode":"24279",
    "addr:street":"Community Center Rd",
    "iso:country":"US",
    "sg:address":"9942 Community Center Rd",
    "sg:city":"Pound",
    "sg:classifiers":[
        {
            "category":"Social Services",
            "type":"Services"
        }
    ],
    "sg:phone":"+1 276 796 4984",
    "sg:postcode":"24279",
    "sg:province":"VA",
    "wof:name":"Flat Gap Community Center",
    "wof:placetype":"venue"
},
  "geometry": {"coordinates":[-82.69423999999999,37.082191],"type":"Point"}
}