{
  "type": "Feature",
  "properties": {
    "iso:country":"US",
    "sg:address":"3706 Danbury Dr",
    "sg:city":"Hopewell",
    "sg:classifiers":[
        {
            "category":"Autos & Motor Vehicles",
            "subcategory":"Auto Supplies",
            "type":"Retail Goods"
        }
    ],
    "sg:phone":"+1 804 458 1257",
    "sg:postcode":"23860",
    "sg:province":"VA",
    "sg:tags":[
        "alternator",
        "generator"
    ],
    "wof:name":"Miller's Rebuilt Starters",
    "wof:placetype":"venue"
},
  "geometry": {"coordinates":[-77.20925,37.259822],"type":"Point"}
}