{
  "type": "Feature",
  "properties": {
    "addr:full":"205 Peppertree Ln Winchester VA 22601",
    "addr:housenumber":"205",
    "addr:postcode":"22601",
    "addr:street":"Peppertree Ln",
    "iso:country":"US",
    "sg:address":"205 Peppertree Ln",
    "sg:city":"Winchester",
    "sg:classifiers":[
        {
            "category":"Retail",
            "subcategory":"Repair Shop",
            "type":"Services"
        }
    ],
    "sg:phone":"+1 540 720 9217",
    "sg:postcode":"22601",
    "sg:province":"VA",
    "wof:name":"Double Trouble Racing",
    "wof:placetype":"venue"
},
  "geometry": {"coordinates":[-78.181882,39.154972],"type":"Point"}
}