{
  "type": "Feature",
  "properties": {
    "iso:country":"US",
    "sg:address":"2200 Colonial Ave",
    "sg:city":"Norfolk",
    "sg:classifiers":[
        {
            "category":"Health Services",
            "subcategory":"Clinic",
            "type":"Services"
        }
    ],
    "sg:phone":"+1 757 627 8867",
    "sg:postcode":"23517",
    "sg:province":"VA",
    "sg:tags":[
        "home"
    ],
    "wof:name":"Bullock Corp",
    "wof:placetype":"venue"
},
  "geometry": {"coordinates":[-76.29114800000001,36.870678],"type":"Point"}
}