{
  "type": "Feature",
  "properties": {
    "iso:country":"US",
    "sg:address":"3633 Radford Rd",
    "sg:city":"Christiansburg",
    "sg:classifiers":[
        {
            "category":"Restaurant",
            "type":"Food & Drink"
        }
    ],
    "sg:menulink":"http://www.allmenus.com/va/riner/17592-italiano-pizza--subs/menu/",
    "sg:phone":"+1 540 633 2107",
    "sg:postcode":"24073",
    "sg:province":"VA",
    "sg:tags":[
        "sandwich",
        "salad",
        "calzones",
        "american",
        "pasta",
        "pizza",
        "wing",
        "italian"
    ],
    "wof:name":"Italiano Pizza & Subs",
    "wof:placetype":"venue"
},
  "geometry": {"coordinates":[-80.462785,37.132825],"type":"Point"}
}