{
  "type": "Feature",
  "properties": {
    "iso:country":"US",
    "sg:address":"211 E Virginia Ave",
    "sg:city":"Vinton",
    "sg:classifiers":[
        {
            "category":"Building & Trades",
            "subcategory":"Electrical",
            "type":"Services"
        }
    ],
    "sg:phone":"+1 540 343 8320",
    "sg:postcode":"24179",
    "sg:province":"VA",
    "sg:tags":[
        "electrical",
        "electric",
        "contractor"
    ],
    "wof:name":"Emert's Electric Co",
    "wof:placetype":"venue"
},
  "geometry": {"coordinates":[-79.895067,37.274451],"type":"Point"}
}