{
  "type": "Feature",
  "properties": {
    "iso:country":"US",
    "sg:address":"304 Warrenton Rd",
    "sg:city":"Fredericksburg",
    "sg:classifiers":[
        {
            "category":"Autos & Motor Vehicles",
            "subcategory":"Automobile Sales",
            "type":"Retail Goods"
        }
    ],
    "sg:phone":"+1 540 370 0311",
    "sg:postcode":"22405",
    "sg:province":"VA",
    "sg:tags":[
        "car",
        "dealer"
    ],
    "wof:name":"Auto Land",
    "wof:placetype":"venue"
},
  "geometry": {"coordinates":[-77.484032,38.336613],"type":"Point"}
}