{
  "type": "Feature",
  "properties": {
    "addr:full":"1640 General Booth Blvd Virginia Beach VA 23454",
    "addr:housenumber":"1640",
    "addr:postcode":"23454",
    "addr:street":"General Booth Blvd",
    "iso:country":"US",
    "sg:address":"1640 General Booth Blvd",
    "sg:city":"Virginia Beach",
    "sg:classifiers":[
        {
            "category":"Restaurant",
            "type":"Food & Drink"
        }
    ],
    "sg:menulink":"http://www.allmenus.com/va/virginia-beach/71935-pizza-hut/menu/",
    "sg:phone":"+1 757 721 7859",
    "sg:postcode":"23454",
    "sg:province":"VA",
    "sg:tags":[
        "american",
        "pizza"
    ],
    "wof:name":"Pizza Hut",
    "wof:placetype":"venue"
},
  "geometry": {"coordinates":[-76.000129,36.783317],"type":"Point"}
}