{
  "type": "Feature",
  "properties": {
    "iso:country":"US",
    "sg:address":"11298 Patterson Ave",
    "sg:city":"Richmond",
    "sg:classifiers":[
        {
            "category":"Restaurant",
            "type":"Food & Drink"
        }
    ],
    "sg:phone":"+1 804 740 9480",
    "sg:postcode":"23238",
    "sg:province":"VA",
    "wof:name":"Arby's",
    "wof:placetype":"venue"
},
  "geometry": {"coordinates":[-77.621712,37.597733],"type":"Point"}
}