{
  "type": "Feature",
  "properties": {
    "iso:country":"US",
    "sg:address":"293 Cherrystone Creek Rd",
    "sg:city":"Chatham",
    "sg:classifiers":[
        {
            "category":"Freight",
            "type":"Transportation"
        }
    ],
    "sg:phone":"+1 434 432 8745",
    "sg:postcode":"24531",
    "sg:province":"VA",
    "sg:tags":[
        "operator",
        "local",
        "trucking"
    ],
    "wof:name":"B L Brumfield Trucking Inc",
    "wof:placetype":"venue"
},
  "geometry": {"coordinates":[-79.42755200000001,36.852793],"type":"Point"}
}