{
  "type": "Feature",
  "properties": {
    "addr:full":"17 W 4th St Chase City VA 23924",
    "addr:housenumber":"17",
    "addr:postcode":"23924",
    "addr:street":"W 4Th St",
    "iso:country":"US",
    "sg:address":"17 W 4th St",
    "sg:city":"Chase City",
    "sg:classifiers":[
        {
            "category":"Government",
            "subcategory":"Office",
            "type":"Public Place"
        }
    ],
    "sg:phone":"+1 434 372 3220",
    "sg:postcode":"23924",
    "sg:province":"VA",
    "sg:tags":[
        "village"
    ],
    "wof:name":"Chase City Town Shop",
    "wof:placetype":"venue"
},
  "geometry": {"coordinates":[-78.462096,36.800854],"type":"Point"}
}