{
  "type": "Feature",
  "properties": {
    "iso:country":"US",
    "sg:address":"6401 Lincolnia Rd",
    "sg:city":"Alexandria",
    "sg:classifiers":[
        {
            "category":"Organizations",
            "subcategory":"Religious Organization",
            "type":"Services"
        }
    ],
    "sg:phone":"+1 703 642 3267",
    "sg:postcode":"22312",
    "sg:province":"VA",
    "sg:tags":[
        "church"
    ],
    "sg:website":"www.fgfcw.org",
    "wof:name":"Full Gospel Church-Washington",
    "wof:placetype":"venue"
},
  "geometry": {"coordinates":[-77.154079,38.833035],"type":"Point"}
}