{
  "type": "Feature",
  "properties": {
    "addr:full":"14501 Lee Jackson Memorial Hwy Chantilly VA 20151",
    "addr:housenumber":"14501",
    "addr:postcode":"20151",
    "addr:street":"Lee Jackson Memorial Hwy",
    "iso:country":"US",
    "sg:address":"14501 Lee Jackson Memorial Hwy",
    "sg:city":"Chantilly",
    "sg:classifiers":[
        {
            "category":"Home & Garden",
            "subcategory":"Household Appliances",
            "type":"Retail Goods"
        }
    ],
    "sg:phone":"+1 703 968 8079",
    "sg:postcode":"20151",
    "sg:province":"VA",
    "sg:website":"www.foremostappliances.com",
    "wof:name":"Foremost Appliances",
    "wof:placetype":"venue"
},
  "geometry": {"coordinates":[-77.447537,38.900739],"type":"Point"}
}