{
  "type": "Feature",
  "properties": {
    "addr:full":"15715 Southern Cross Ln Round Hill VA 20132",
    "addr:housenumber":"15715",
    "addr:postcode":"20132",
    "addr:street":"Southern Cross Ln",
    "iso:country":"US",
    "sg:address":"15715 Southern Cross Ln",
    "sg:city":"Round Hill",
    "sg:classifiers":[
        {
            "category":"Retail",
            "subcategory":"Animal Services",
            "type":"Services"
        }
    ],
    "sg:phone":"+1 540 338 1917",
    "sg:postcode":"20132",
    "sg:province":"VA",
    "sg:tags":[
        "horse",
        "training"
    ],
    "wof:name":"Equissage",
    "wof:placetype":"venue"
},
  "geometry": {"coordinates":[-77.774744,39.182664],"type":"Point"}
}