{
  "type": "Feature",
  "properties": {
    "addr:full":"2255 Langhorne Rd Lynchburg VA 24501",
    "addr:housenumber":"2255",
    "addr:postcode":"24501",
    "addr:street":"Langhorne Rd",
    "iso:country":"US",
    "sg:address":"2255 Langhorne Rd",
    "sg:city":"Lynchburg",
    "sg:classifiers":[
        {
            "category":"Health Services",
            "subcategory":"Health Practitioner",
            "type":"Services"
        }
    ],
    "sg:phone":"+1 434 845 6355",
    "sg:postcode":"24501",
    "sg:province":"VA",
    "wof:name":"Lynchburg Speech Therapy Inc",
    "wof:placetype":"venue"
},
  "geometry": {"coordinates":[-79.172873,37.412436],"type":"Point"}
}