{
  "type": "Feature",
  "properties": {
    "addr:full":"1879 E Ocean View Ave Norfolk VA 23503",
    "addr:housenumber":"1879",
    "addr:postcode":"23503",
    "addr:street":"E Ocean View Ave",
    "iso:country":"US",
    "sg:address":"1879 E Ocean View Ave",
    "sg:city":"Norfolk",
    "sg:classifiers":[
        {
            "category":"Banks & Credit Unions",
            "subcategory":"Bank",
            "type":"Services"
        }
    ],
    "sg:phone":"+1 757 531 2800",
    "sg:postcode":"23503",
    "sg:province":"VA",
    "sg:tags":[
        "cashing",
        "check"
    ],
    "wof:name":"America Cash Express",
    "wof:placetype":"venue"
},
  "geometry": {"coordinates":[-76.222109,36.938234],"type":"Point"}
}