{
  "type": "Feature",
  "properties": {
    "iso:country":"US",
    "sg:address":"11930 Beechwood Forest Dr",
    "sg:city":"Chesterfield",
    "sg:classifiers":[
        {
            "category":"Building & Trades",
            "subcategory":"Construction",
            "type":"Services"
        }
    ],
    "sg:phone":"+1 804 639 1645",
    "sg:postcode":"23838",
    "sg:province":"VA",
    "sg:tags":[
        "property",
        "s",
        "management"
    ],
    "wof:name":"A G Ramos Irrigation",
    "wof:placetype":"venue"
},
  "geometry": {"coordinates":[-77.59656200000001,37.339511],"type":"Point"}
}