{
  "type": "Feature",
  "properties": {
    "iso:country":"US",
    "sg:address":"913 Jeremy Ct",
    "sg:city":"Virginia Beach",
    "sg:classifiers":[
        {
            "category":"Banks & Credit Unions",
            "subcategory":"Financial Services",
            "type":"Services"
        }
    ],
    "sg:phone":"+1 757 496 7514",
    "sg:postcode":"23454",
    "sg:province":"VA",
    "sg:tags":[
        "trust",
        "management"
    ],
    "wof:name":"William T Mercer Foundation",
    "wof:placetype":"venue"
},
  "geometry": {"coordinates":[-76.035927,36.858717],"type":"Point"}
}