{
  "type": "Feature",
  "properties": {
    "addr:full":"4189 Plank Rd Fredericksburg VA 22407",
    "addr:housenumber":"4189",
    "addr:postcode":"22407",
    "addr:street":"Plank Rd",
    "iso:country":"US",
    "sg:address":"4189 Plank Rd",
    "sg:city":"Fredericksburg",
    "sg:classifiers":[
        {
            "category":"Government",
            "subcategory":"Office",
            "type":"Public Place"
        }
    ],
    "sg:phone":"+1 540 786 0917",
    "sg:postcode":"22407",
    "sg:province":"VA",
    "sg:tags":[
        "liquor",
        "store"
    ],
    "wof:name":"ABC",
    "wof:placetype":"venue"
},
  "geometry": {"coordinates":[-77.53281,38.289277],"type":"Point"}
}