{
  "type": "Feature",
  "properties": {
    "iso:country":"US",
    "sg:address":"5401 Jefferson Davis Hwy",
    "sg:city":"Richmond",
    "sg:classifiers":[
        {
            "category":"Professional",
            "subcategory":"Research",
            "type":"Services"
        }
    ],
    "sg:phone":"+1 804 383 5840",
    "sg:postcode":"23234",
    "sg:province":"VA",
    "sg:tags":[
        "environmental",
        "ecological"
    ],
    "wof:name":"Evanco Environmental Svc",
    "wof:placetype":"venue"
},
  "geometry": {"coordinates":[-77.44131899999999,37.449401],"type":"Point"}
}