{
  "type": "Feature",
  "properties": {
    "addr:full":"9986 Blackberry Ln Great Falls VA 22066",
    "addr:housenumber":"9986",
    "addr:postcode":"22066",
    "addr:street":"Blackberry Ln",
    "iso:country":"US",
    "sg:address":"9986 Blackberry Ln",
    "sg:city":"Great Falls",
    "sg:classifiers":[
        {
            "category":"Retail",
            "subcategory":"Auto Repair",
            "type":"Services"
        }
    ],
    "sg:phone":"+1 703 759 3077",
    "sg:postcode":"22066",
    "sg:province":"VA",
    "sg:tags":[
        "automotive"
    ],
    "wof:name":"Performance Brake Corp",
    "wof:placetype":"venue"
},
  "geometry": {"coordinates":[-77.290668,39.032021],"type":"Point"}
}