{
  "type": "Feature",
  "properties": {
    "addr:full":"1080 First Colonial Rd Virginia Beach VA 23454",
    "addr:housenumber":"1080",
    "addr:postcode":"23454",
    "addr:street":"First Colonial Rd",
    "iso:country":"US",
    "sg:address":"1080 First Colonial Rd",
    "sg:city":"Virginia Beach",
    "sg:classifiers":[
        {
            "category":"Health Services",
            "subcategory":"Medical Lab",
            "type":"Services"
        }
    ],
    "sg:phone":"+1 757 395 6464",
    "sg:postcode":"23454",
    "sg:province":"VA",
    "sg:tags":[
        "laboratory"
    ],
    "wof:name":"First Colonial Diagnostic Ctr",
    "wof:placetype":"venue"
},
  "geometry": {"coordinates":[-76.028897,36.865533],"type":"Point"}
}