{
  "type": "Feature",
  "properties": {
    "addr:full":"205 Cavalry Dr Winchester VA 22602",
    "addr:housenumber":"205",
    "addr:postcode":"22602",
    "addr:street":"Cavalry Dr",
    "iso:country":"US",
    "sg:address":"205 Cavalry Dr",
    "sg:city":"Winchester",
    "sg:classifiers":[
        {
            "category":"Banks & Credit Unions",
            "subcategory":"Bank",
            "type":"Services"
        }
    ],
    "sg:phone":"+1 540 545 8840",
    "sg:postcode":"22602",
    "sg:province":"VA",
    "sg:tags":[
        "other",
        "plan",
        "card"
    ],
    "wof:name":"Cardservice Of Chesapeake Inc",
    "wof:placetype":"venue"
},
  "geometry": {"coordinates":[-78.101445,39.184307],"type":"Point"}
}