{
  "type": "Feature",
  "properties": {
    "iso:country":"US",
    "sg:address":"5433 Chatsworth Dr",
    "sg:city":"Roanoke",
    "sg:classifiers":[
        {
            "category":"Professional",
            "type":"Services"
        }
    ],
    "sg:phone":"+1 540 776 7725",
    "sg:postcode":"24018",
    "sg:province":"VA",
    "wof:name":"Roanoke Valley Fincl News LLC",
    "wof:placetype":"venue"
},
  "geometry": {"coordinates":[-80.02432399999999,37.21157],"type":"Point"}
}