{
  "type": "Feature",
  "properties": {
    "iso:country":"US",
    "sg:address":"8112 Holdsworth Rd",
    "sg:city":"Disputanta",
    "sg:classifiers":[
        {
            "category":"Retail",
            "subcategory":"Veterinary Services",
            "type":"Services"
        }
    ],
    "sg:phone":"+1 804 991 3909",
    "sg:postcode":"23842",
    "sg:province":"VA",
    "sg:tags":[
        "veterinarian"
    ],
    "wof:name":"Tri City House Call Veterinary",
    "wof:placetype":"venue"
},
  "geometry": {"coordinates":[-77.26050600000001,37.094428],"type":"Point"}
}