{
  "type": "Feature",
  "properties": {
    "addr:full":"14465 Potomac Mills Rd Woodbridge VA 22192",
    "addr:housenumber":"14465",
    "addr:postcode":"22192",
    "addr:street":"Potomac Mills Rd",
    "iso:country":"US",
    "sg:address":"14465 Potomac Mills Rd",
    "sg:city":"Woodbridge",
    "sg:classifiers":[
        {
            "category":"Health Services",
            "subcategory":"Optometrist",
            "type":"Services"
        }
    ],
    "sg:phone":"+1 703 494 6184",
    "sg:postcode":"22192",
    "sg:province":"VA",
    "sg:website":"www.myeyedr.com",
    "wof:name":"My Eye Doctor",
    "wof:placetype":"venue"
},
  "geometry": {"coordinates":[-77.29775100000001,38.635411],"type":"Point"}
}