{
  "type": "Feature",
  "properties": {
    "addr:full":"200 Westgate Pkwy Richmond VA 23233",
    "addr:housenumber":"200",
    "addr:postcode":"23233",
    "addr:street":"Westgate Pkwy",
    "iso:country":"US",
    "sg:address":"200 Westgate Pkwy",
    "sg:city":"Richmond",
    "sg:classifiers":[
        {
            "category":"Education",
            "subcategory":"Special Training",
            "type":"Public Place"
        }
    ],
    "sg:phone":"+1 804 750 1024",
    "sg:postcode":"23233",
    "sg:province":"VA",
    "sg:tags":[
        "tutoring"
    ],
    "sg:website":"www.educate.com",
    "wof:name":"Sylvan Learning Ctr",
    "wof:placetype":"venue"
},
  "geometry": {"coordinates":[-77.62028599999999,37.651917],"type":"Point"}
}