{
  "type": "Feature",
  "properties": {
    "iso:country":"US",
    "sg:address":"928 Drivers Ln",
    "sg:city":"Newport News",
    "sg:classifiers":[
        {
            "category":"Professional",
            "subcategory":"Engineering",
            "type":"Services"
        }
    ],
    "sg:phone":"+1 757 874 9056",
    "sg:postcode":"23602",
    "sg:province":"VA",
    "wof:name":"Cost Reduction Systems",
    "wof:placetype":"venue"
},
  "geometry": {"coordinates":[-76.478206,37.118181],"type":"Point"}
}