{
  "type": "Feature",
  "properties": {
    "iso:country":"US",
    "sg:address":"409 McDaniel Dr",
    "sg:city":"Purcellville",
    "sg:classifiers":[
        {
            "category":"Social Services",
            "subcategory":"Child Care",
            "type":"Services"
        }
    ],
    "sg:phone":"+1 540 338 4254",
    "sg:postcode":"20132",
    "sg:province":"VA",
    "sg:tags":[
        "day"
    ],
    "wof:name":"Kid Kreation",
    "wof:placetype":"venue"
},
  "geometry": {"coordinates":[-77.700166,39.134328],"type":"Point"}
}