{
  "type": "Feature",
  "properties": {
    "addr:full":"3101 Virginia Beach Blvd Virginia Beach VA 23452",
    "addr:housenumber":"3101",
    "addr:postcode":"23452",
    "addr:street":"Virginia Beach Blvd",
    "iso:country":"US",
    "sg:address":"3101 Virginia Beach Blvd",
    "sg:city":"Virginia Beach",
    "sg:classifiers":[
        {
            "category":"Insurance",
            "subcategory":"Insurance Agent",
            "type":"Services"
        }
    ],
    "sg:phone":"+1 757 498 1500",
    "sg:postcode":"23452",
    "sg:province":"VA",
    "sg:website":"www.allstate.com",
    "wof:name":"Allstate Insurance",
    "wof:placetype":"venue"
},
  "geometry": {"coordinates":[-76.078197,36.843171],"type":"Point"}
}