{
  "type": "Feature",
  "properties": {
    "iso:country":"US",
    "sg:address":"3200 Olds Dr",
    "sg:city":"Falls Church",
    "sg:classifiers":[
        {
            "category":"Professional",
            "subcategory":"Management & Consulting",
            "type":"Services"
        }
    ],
    "sg:phone":"+1 703 820 5210",
    "sg:postcode":"22041",
    "sg:province":"VA",
    "wof:name":"Leadership 21 Worldwide",
    "wof:placetype":"venue"
},
  "geometry": {"coordinates":[-77.13252799999999,38.860763],"type":"Point"}
}