{
  "type": "Feature",
  "properties": {
    "addr:full":"3521 Martin Johnson Rd Chesapeake VA 23323",
    "addr:housenumber":"3521",
    "addr:postcode":"23323",
    "addr:street":"Martin Johnson Rd",
    "iso:country":"US",
    "sg:address":"3521 Martin Johnson Rd",
    "sg:city":"Chesapeake",
    "sg:classifiers":[
        {
            "category":"Professional",
            "type":"Services"
        }
    ],
    "sg:phone":"+1 757 816 4293",
    "sg:postcode":"23323",
    "sg:province":"VA",
    "sg:tags":[
        "consultant"
    ],
    "wof:name":"Mark Cernak",
    "wof:placetype":"venue"
},
  "geometry": {"coordinates":[-76.381788,36.74949],"type":"Point"}
}