{
  "type": "Feature",
  "properties": {
    "addr:full":"4675 E Princess Anne Rd Norfolk VA 23502",
    "addr:housenumber":"4675",
    "addr:postcode":"23502",
    "addr:street":"E Princess Anne Rd",
    "iso:country":"US",
    "sg:address":"4675 E Princess Anne Rd",
    "sg:city":"Norfolk",
    "sg:classifiers":[
        {
            "category":"Wholesale",
            "subcategory":"Vending Machines",
            "type":"Manufacturing & Wholesale Goods"
        }
    ],
    "sg:phone":"+1 757 855 8083",
    "sg:postcode":"23502",
    "sg:province":"VA",
    "wof:name":"CRH Catering Co",
    "wof:placetype":"venue"
},
  "geometry": {"coordinates":[-76.230002,36.867463],"type":"Point"}
}