{
  "type": "Feature",
  "properties": {
    "addr:full":"2920 W Hundred Rd Chester VA 23831",
    "addr:housenumber":"2920",
    "addr:postcode":"23831",
    "addr:street":"W Hundred Rd",
    "iso:country":"US",
    "sg:address":"2920 W Hundred Rd",
    "sg:city":"Chester",
    "sg:classifiers":[
        {
            "category":"Government",
            "subcategory":"Police Station",
            "type":"Public Place"
        }
    ],
    "sg:phone":"+1 804 778 4550",
    "sg:postcode":"23831",
    "sg:province":"VA",
    "sg:tags":[
        "protection"
    ],
    "wof:name":"Chesterfield Cnty Chester Stn",
    "wof:placetype":"venue"
},
  "geometry": {"coordinates":[-77.42016700000001,37.356322],"type":"Point"}
}