{
  "type": "Feature",
  "properties": {
    "addr:full":"530 Southlake Blvd Richmond VA 23236",
    "addr:housenumber":"530",
    "addr:postcode":"23236",
    "addr:street":"Southlake Blvd",
    "iso:country":"US",
    "sg:address":"530 Southlake Blvd",
    "sg:city":"Richmond",
    "sg:classifiers":[
        {
            "category":"Professional",
            "subcategory":"Accounting & Tax Preparation",
            "type":"Services"
        }
    ],
    "sg:phone":"+1 804 379 6599",
    "sg:postcode":"23236",
    "sg:province":"VA",
    "sg:tags":[
        "bookkeeping",
        "general"
    ],
    "wof:name":"Nunnally Robertson Bus Svcs L",
    "wof:placetype":"venue"
},
  "geometry": {"coordinates":[-77.599523,37.499303],"type":"Point"}
}