{
  "type": "Feature",
  "properties": {
    "addr:full":"10109 Piper Ln Bristow VA 20136",
    "addr:housenumber":"10109",
    "addr:postcode":"20136",
    "addr:street":"Piper Ln",
    "iso:country":"US",
    "sg:address":"10109 Piper Ln",
    "sg:city":"Bristow",
    "sg:classifiers":[
        {
            "category":"Wholesale",
            "subcategory":"Motor Vehicles",
            "type":"Manufacturing & Wholesale Goods"
        }
    ],
    "sg:phone":"+1 703 330 2280",
    "sg:postcode":"20136",
    "sg:province":"VA",
    "sg:tags":[
        "sales",
        "emergency"
    ],
    "wof:name":"Performnce Spcial Vehicles LLC",
    "wof:placetype":"venue"
},
  "geometry": {"coordinates":[-77.531308,38.733255],"type":"Point"}
}