{
  "type": "Feature",
  "properties": {
    "iso:country":"US",
    "sg:address":"13607 Hull Street Rd",
    "sg:city":"Midlothian",
    "sg:classifiers":[
        {
            "category":"Restaurant",
            "type":"Food & Drink"
        }
    ],
    "sg:phone":"+1 804 639 9601",
    "sg:postcode":"23112",
    "sg:province":"VA",
    "wof:name":"Yamato Steakhouse & Sushi Rest",
    "wof:placetype":"venue"
},
  "geometry": {"coordinates":[-77.651984,37.409787],"type":"Point"}
}