{
  "type": "Feature",
  "properties": {
    "iso:country":"US",
    "sg:address":"430 Old Courthouse Rd NE",
    "sg:city":"Vienna",
    "sg:classifiers":[
        {
            "category":"Professional",
            "subcategory":"Management & Consulting",
            "type":"Services"
        }
    ],
    "sg:phone":"+1 703 281 2389",
    "sg:postcode":"22180",
    "sg:province":"VA",
    "sg:tags":[
        "case",
        "department",
        "manager",
        "navy"
    ],
    "wof:name":"Paganelli Virginia M",
    "wof:placetype":"venue"
},
  "geometry": {"coordinates":[-77.246932,38.919492],"type":"Point"}
}