{
  "type": "Feature",
  "properties": {
    "addr:full":"1245 S Boston Rd Danville VA 24540",
    "addr:housenumber":"1245",
    "addr:postcode":"24540",
    "addr:street":"S Boston Rd",
    "iso:country":"US",
    "sg:address":"1245 S Boston Rd",
    "sg:city":"Danville",
    "sg:classifiers":[
        {
            "category":"Wholesale",
            "subcategory":"Machinery & Supplies",
            "type":"Manufacturing & Wholesale Goods"
        }
    ],
    "sg:phone":"+1 434 792 0515",
    "sg:postcode":"24540",
    "sg:province":"VA",
    "sg:tags":[
        "repair"
    ],
    "wof:name":"Rudder Tractor Co Inc",
    "wof:placetype":"venue"
},
  "geometry": {"coordinates":[-79.35244299999999,36.582842],"type":"Point"}
}