{
  "type": "Feature",
  "properties": {
    "iso:country":"US",
    "sg:address":"9725 Aspen Hollow Way",
    "sg:city":"Fairfax",
    "sg:classifiers":[
        {
            "category":"Professional",
            "subcategory":"Research",
            "type":"Services"
        }
    ],
    "sg:phone":"+1 703 239 0638",
    "sg:postcode":"22032",
    "sg:province":"VA",
    "sg:tags":[
        "nonphysical",
        "commercial"
    ],
    "sg:website":"www.sigma-sys.com",
    "wof:name":"Sigma Systems Research Inc",
    "wof:placetype":"venue"
},
  "geometry": {"coordinates":[-77.287437,38.820921],"type":"Point"}
}