{
  "type": "Feature",
  "properties": {
    "iso:country":"US",
    "sg:address":"412 N Main St",
    "sg:city":"Suffolk",
    "sg:classifiers":[
        {
            "category":"Shopping",
            "type":"Retail Goods"
        }
    ],
    "sg:phone":"+1 757 934 6770",
    "sg:postcode":"23434",
    "sg:province":"VA",
    "sg:tags":[
        "trophy",
        "medal",
        "award"
    ],
    "wof:name":"Tony's Trophies & Agentry",
    "wof:placetype":"venue"
},
  "geometry": {"coordinates":[-76.582207,36.736148],"type":"Point"}
}