{
  "type": "Feature",
  "properties": {
    "addr:full":"1840 Jefferson Hwy Fishersville VA 22980",
    "addr:housenumber":"1840",
    "addr:postcode":"22980",
    "addr:street":"Jefferson Hwy Fishersville",
    "iso:country":"US",
    "sg:address":"1840 Jefferson Hwy",
    "sg:city":"Fishersville",
    "sg:classifiers":[
        {
            "category":"Wholesale",
            "subcategory":"Medical Equipment & Supplies",
            "type":"Manufacturing & Wholesale Goods"
        }
    ],
    "sg:phone":"+1 540 885 0944",
    "sg:postcode":"22980",
    "sg:province":"VA",
    "wof:name":"Rotech",
    "wof:placetype":"venue"
},
  "geometry": {"coordinates":[-78.945881,38.0891],"type":"Point"}
}