{
  "type": "Feature",
  "properties": {
    "iso:country":"US",
    "sg:address":"320 W Juniper Ave",
    "sg:city":"Sterling",
    "sg:classifiers":[
        {
            "category":"Professional",
            "subcategory":"Employment Agencies",
            "type":"Services"
        }
    ],
    "sg:phone":"+1 571 283 1463",
    "sg:postcode":"20164",
    "sg:province":"VA",
    "wof:name":"Samuel Alfredo Cerritos",
    "wof:placetype":"venue"
},
  "geometry": {"coordinates":[-77.39798399999999,39.015654],"type":"Point"}
}