{
  "type": "Feature",
  "properties": {
    "iso:country":"US",
    "sg:address":"1445 Monarch Reach",
    "sg:city":"Chesapeake",
    "sg:classifiers":[
        {
            "category":"Retail",
            "subcategory":"Photofinishing",
            "type":"Services"
        }
    ],
    "sg:phone":"+1 757 509 0890",
    "sg:postcode":"23320",
    "sg:province":"VA",
    "sg:tags":[
        "photography"
    ],
    "wof:name":"Ashe Dathan",
    "wof:placetype":"venue"
},
  "geometry": {"coordinates":[-76.279988,36.749733],"type":"Point"}
}