{
  "type": "Feature",
  "properties": {
    "addr:full":"8528 Oakview Dr Manassas VA 20110",
    "addr:housenumber":"8528",
    "addr:postcode":"20110",
    "addr:street":"Oakview Dr",
    "iso:country":"US",
    "sg:address":"8528 Oakview Dr",
    "sg:city":"Manassas",
    "sg:classifiers":[
        {
            "category":"Retail",
            "subcategory":"Auto Repair",
            "type":"Services"
        }
    ],
    "sg:phone":"+1 703 369 0431",
    "sg:postcode":"20110",
    "sg:province":"VA",
    "sg:tags":[
        "automotive",
        "welding",
        "supply"
    ],
    "wof:name":"Thompson Engineering",
    "wof:placetype":"venue"
},
  "geometry": {"coordinates":[-77.453354,38.734711],"type":"Point"}
}