{
  "type": "Feature",
  "properties": {
    "iso:country":"US",
    "sg:address":"721 Monroe St",
    "sg:city":"Herndon",
    "sg:classifiers":[
        {
            "category":"Shopping",
            "subcategory":"Clothing, Apparel, & Fashions",
            "type":"Retail Goods"
        }
    ],
    "sg:phone":"+1 703 464 0031",
    "sg:postcode":"20170",
    "sg:province":"VA",
    "sg:tags":[
        "item",
        "boutique"
    ],
    "wof:name":"Jessica's Boutique",
    "wof:placetype":"venue"
},
  "geometry": {"coordinates":[-77.383893,38.970115],"type":"Point"}
}