{
  "type": "Feature",
  "properties": {
    "iso:country":"US",
    "sg:address":"7401 Beaufont Spring Dr",
    "sg:city":"Richmond",
    "sg:classifiers":[
        {
            "category":"Health Services",
            "subcategory":"Doctor",
            "type":"Services"
        }
    ],
    "sg:phone":"+1 804 330 2013",
    "sg:postcode":"23225",
    "sg:province":"VA",
    "sg:tags":[
        "physician",
        "surgeon"
    ],
    "wof:name":"Chippenham Medical Ctr",
    "wof:placetype":"venue"
},
  "geometry": {"coordinates":[-77.52903999999999,37.508283],"type":"Point"}
}