{
  "type": "Feature",
  "properties": {
    "addr:full":"8119 Holland Rd Alexandria VA 22306",
    "addr:housenumber":"8119",
    "addr:postcode":"22306",
    "addr:street":"Holland Rd",
    "iso:country":"US",
    "sg:address":"8119 Holland Rd",
    "sg:city":"Alexandria",
    "sg:classifiers":[
        {
            "category":"Government",
            "subcategory":"Office",
            "type":"Public Place"
        }
    ],
    "sg:phone":"+1 703 360 7273",
    "sg:postcode":"22306",
    "sg:province":"VA",
    "wof:name":"Battered Wives",
    "wof:placetype":"venue"
},
  "geometry": {"coordinates":[-77.07993500000001,38.736424],"type":"Point"}
}