{
  "type": "Feature",
  "properties": {
    "iso:country":"US",
    "sg:address":"45945 Trefoil Ln",
    "sg:city":"Sterling",
    "sg:classifiers":[
        {
            "category":"Manufacturing",
            "subcategory":"Printing",
            "type":"Manufacturing & Wholesale Goods"
        }
    ],
    "sg:phone":"+1 703 318 0008",
    "sg:postcode":"20166",
    "sg:province":"VA",
    "sg:tags":[
        "commercial"
    ],
    "sg:website":"www.petreepress.com",
    "wof:name":"Petree Press Instant Printing",
    "wof:placetype":"venue"
},
  "geometry": {"coordinates":[-77.41040099999999,38.981343],"type":"Point"}
}