{
  "type": "Feature",
  "properties": {
    "iso:country":"US",
    "sg:address":"406 N Lee St",
    "sg:city":"Alexandria",
    "sg:classifiers":[
        {
            "category":"Social Services",
            "type":"Services"
        }
    ],
    "sg:phone":"+1 703 706 5277",
    "sg:postcode":"22314",
    "sg:province":"VA",
    "sg:tags":[
        "consulting"
    ],
    "wof:name":"Maura Brazill",
    "wof:placetype":"venue"
},
  "geometry": {"coordinates":[-77.040589,38.808859],"type":"Point"}
}