{
  "type": "Feature",
  "properties": {
    "addr:full":"6700 Old McLean Village Dr Mc Lean VA 22101",
    "addr:housenumber":"6700",
    "addr:postcode":"22101",
    "addr:street":"Old Mclean Village Dr",
    "iso:country":"US",
    "sg:address":"6700 Old McLean Village Dr",
    "sg:city":"Mc Lean",
    "sg:classifiers":[
        {
            "category":"Professional",
            "subcategory":"Engineering",
            "type":"Services"
        }
    ],
    "sg:phone":"+1 703 760 9076",
    "sg:postcode":"22101",
    "sg:province":"VA",
    "sg:tags":[
        "consultant",
        "electrical"
    ],
    "wof:name":"Lean Engineering Consultants",
    "wof:placetype":"venue"
},
  "geometry": {"coordinates":[-77.175787,38.936896],"type":"Point"}
}