{
  "type": "Feature",
  "properties": {
    "addr:full":"10000 Wilcox Neck Rd Charles City VA 23030",
    "addr:housenumber":"10000",
    "addr:postcode":"23030",
    "addr:street":"Wilcox Neck Rd",
    "iso:country":"US",
    "sg:address":"10000 Wilcox Neck Rd",
    "sg:city":"Charles City",
    "sg:classifiers":[
        {
            "category":"Health Services",
            "subcategory":"Doctor",
            "type":"Services"
        }
    ],
    "sg:phone":"+1 804 829 2118",
    "sg:postcode":"23030",
    "sg:province":"VA",
    "sg:tags":[
        "medical"
    ],
    "wof:name":"Richard F Bunting Dr",
    "wof:placetype":"venue"
},
  "geometry": {"coordinates":[-76.919202,37.348],"type":"Point"}
}