{
  "type": "Feature",
  "properties": {
    "addr:full":"9 Jackson Ave Round Hill VA 20141",
    "addr:housenumber":"9",
    "addr:postcode":"20141",
    "addr:street":"Jackson Ave",
    "iso:country":"US",
    "sg:address":"9 Jackson Ave",
    "sg:city":"Round Hill",
    "sg:classifiers":[
        {
            "category":"Professional",
            "subcategory":"Business Services",
            "type":"Services"
        }
    ],
    "sg:phone":"+1 540 338 4480",
    "sg:postcode":"20141",
    "sg:province":"VA",
    "wof:name":"Data Stream",
    "wof:placetype":"venue"
},
  "geometry": {"coordinates":[-77.774395,39.139302],"type":"Point"}
}