{
  "type": "Feature",
  "properties": {
    "addr:full":"311 Shawnee Ave E Big Stone Gap VA 24219",
    "addr:housenumber":"311",
    "addr:postcode":"24219",
    "addr:street":"Shawnee Ave E",
    "iso:country":"US",
    "sg:address":"311 Shawnee Ave E",
    "sg:city":"Big Stone Gap",
    "sg:classifiers":[
        {
            "category":"Professional",
            "type":"Services"
        }
    ],
    "sg:phone":"+1 276 523 7611",
    "sg:postcode":"24219",
    "sg:province":"VA",
    "wof:name":"A Touch Of Class Boutique",
    "wof:placetype":"venue"
},
  "geometry": {"coordinates":[-82.775936,36.867737],"type":"Point"}
}