{
  "type": "Feature",
  "properties": {
    "addr:full":"2610 E Parham Rd Richmond VA 23228",
    "addr:housenumber":"2610",
    "addr:postcode":"23228",
    "addr:street":"E Parham Rd",
    "iso:country":"US",
    "sg:address":"2610 E Parham Rd",
    "sg:city":"Richmond",
    "sg:classifiers":[
        {
            "category":"Building & Trades",
            "subcategory":"Pest Control",
            "type":"Services"
        }
    ],
    "sg:phone":"+1 804 737 7777",
    "sg:postcode":"23228",
    "sg:province":"VA",
    "sg:website":"www.loyalpest.com",
    "wof:name":"Loyal Termite & Pest Control",
    "wof:placetype":"venue"
},
  "geometry": {"coordinates":[-77.49652500000001,37.636592],"type":"Point"}
}