{
  "type": "Feature",
  "properties": {
    "addr:full":"11610 Gordon School Rd Richmond VA 23236",
    "addr:housenumber":"11610",
    "addr:postcode":"23236",
    "addr:street":"Gordon School Rd",
    "iso:country":"US",
    "sg:address":"11610 Gordon School Rd",
    "sg:city":"Richmond",
    "sg:classifiers":[
        {
            "category":"Freight",
            "type":"Transportation"
        }
    ],
    "sg:phone":"+1 804 400 3251",
    "sg:postcode":"23236",
    "sg:province":"VA",
    "sg:tags":[
        "mover"
    ],
    "wof:name":"Collegiate Movers",
    "wof:placetype":"venue"
},
  "geometry": {"coordinates":[-77.613964,37.480607],"type":"Point"}
}