{
  "type": "Feature",
  "properties": {
    "iso:country":"US",
    "sg:address":"125 Arrowhead Trl",
    "sg:city":"Christiansburg",
    "sg:classifiers":[
        {
            "category":"Building & Trades",
            "subcategory":"Construction",
            "type":"Services"
        }
    ],
    "sg:phone":"+1 540 381 9700",
    "sg:postcode":"24073",
    "sg:province":"VA",
    "sg:tags":[
        "home",
        "builder"
    ],
    "wof:name":"Housemart",
    "wof:placetype":"venue"
},
  "geometry": {"coordinates":[-80.388583,37.133689],"type":"Point"}
}