{
  "type": "Feature",
  "properties": {
    "addr:full":"5 S Drouin Dr Richmond VA 23238",
    "addr:housenumber":"5",
    "addr:postcode":"23238",
    "addr:street":"S Drouin Dr",
    "iso:country":"US",
    "sg:address":"5 S Drouin Dr",
    "sg:city":"Richmond",
    "sg:classifiers":[
        {
            "category":"Building & Trades",
            "subcategory":"Construction",
            "type":"Services"
        }
    ],
    "sg:phone":"+1 804 741 9254",
    "sg:postcode":"23238",
    "sg:province":"VA",
    "sg:tags":[
        "house"
    ],
    "wof:name":"Wilson Builder Inc",
    "wof:placetype":"venue"
},
  "geometry": {"coordinates":[-77.616083,37.587491],"type":"Point"}
}