{
  "type": "Feature",
  "properties": {
    "addr:full":"8785 Mathis Ave Manassas VA 20110",
    "addr:housenumber":"8785",
    "addr:postcode":"20110",
    "addr:street":"Mathis Ave",
    "iso:country":"US",
    "sg:address":"8785 Mathis Ave",
    "sg:city":"Manassas",
    "sg:classifiers":[
        {
            "category":"Personal",
            "subcategory":"Beauty Salon",
            "type":"Services"
        }
    ],
    "sg:phone":"+1 703 361 1894",
    "sg:postcode":"20110",
    "sg:province":"VA",
    "sg:tags":[
        "shop"
    ],
    "wof:name":"Clippers Hair Design",
    "wof:placetype":"venue"
},
  "geometry": {"coordinates":[-77.45949400000001,38.764521],"type":"Point"}
}