{
  "type": "Feature",
  "properties": {
    "iso:country":"US",
    "sg:address":"12 N New St",
    "sg:city":"Staunton",
    "sg:classifiers":[
        {
            "category":"Social Services",
            "subcategory":"Adult Care",
            "type":"Services"
        }
    ],
    "sg:phone":"+1 540 337 3377",
    "sg:postcode":"24401",
    "sg:province":"VA",
    "sg:tags":[
        "geriatric"
    ],
    "wof:name":"Christian Brenneman Homes LLC",
    "wof:placetype":"venue"
},
  "geometry": {"coordinates":[-79.07169500000001,38.14997],"type":"Point"}
}