{
  "type": "Feature",
  "properties": {
    "addr:full":"6619 Williamson Rd Roanoke VA 24019",
    "addr:housenumber":"6619",
    "addr:postcode":"24019",
    "addr:street":"Williamson Rd",
    "iso:country":"US",
    "sg:address":"6619 Williamson Rd",
    "sg:city":"Roanoke",
    "sg:classifiers":[
        {
            "category":"Banks & Credit Unions",
            "subcategory":"Bank",
            "type":"Services"
        }
    ],
    "sg:phone":"+1 540 982 8811",
    "sg:postcode":"24019",
    "sg:province":"VA",
    "sg:tags":[
        "federal"
    ],
    "wof:name":"Member One Federal Credit Un",
    "wof:placetype":"venue"
},
  "geometry": {"coordinates":[-79.955545,37.336641],"type":"Point"}
}