{
  "type": "Feature",
  "properties": {
    "iso:country":"US",
    "sg:address":"607 Aberdeen Rd",
    "sg:city":"Hampton",
    "sg:classifiers":[
        {
            "category":"Retail",
            "subcategory":"Veterinary Services",
            "type":"Services"
        }
    ],
    "sg:phone":"+1 757 826 5441",
    "sg:postcode":"23661",
    "sg:province":"VA",
    "sg:tags":[
        "veterinarian"
    ],
    "wof:name":"Hampton Veterinary Clinic",
    "wof:placetype":"venue"
},
  "geometry": {"coordinates":[-76.402975,37.012712],"type":"Point"}
}