{
  "type": "Feature",
  "properties": {
    "iso:country":"US",
    "sg:address":"413 Stuart Cir",
    "sg:city":"Richmond",
    "sg:classifiers":[
        {
            "category":"Travel",
            "subcategory":"Hotels & Motels",
            "type":"Entertainment"
        }
    ],
    "sg:phone":"+1 804 254 2082",
    "sg:postcode":"23220",
    "sg:province":"VA",
    "wof:name":"Richmond Executive Suites LLC",
    "wof:placetype":"venue"
},
  "geometry": {"coordinates":[-77.458162,37.551838],"type":"Point"}
}