{
  "type": "Feature",
  "properties": {
    "addr:full":"4808 11th St N Arlington VA 22205",
    "addr:housenumber":"4808",
    "addr:postcode":"22205",
    "addr:street":"11Th St N",
    "iso:country":"US",
    "sg:address":"4808 11th St N",
    "sg:city":"Arlington",
    "sg:classifiers":[
        {
            "category":"Professional",
            "subcategory":"Accounting & Tax Preparation",
            "type":"Services"
        }
    ],
    "sg:phone":"+1 703 979 0631",
    "sg:postcode":"22205",
    "sg:province":"VA",
    "sg:tags":[
        "bookkeeping",
        "general"
    ],
    "wof:name":"MMS Business Svc",
    "wof:placetype":"venue"
},
  "geometry": {"coordinates":[-77.121707,38.88378],"type":"Point"}
}