{
  "type": "Feature",
  "properties": {
    "addr:full":"250 S Wayne Ave Waynesboro VA 22980",
    "addr:housenumber":"250",
    "addr:postcode":"22980",
    "addr:street":"S Wayne Ave",
    "iso:country":"US",
    "sg:address":"250 S Wayne Ave",
    "sg:city":"Waynesboro",
    "sg:classifiers":[
        {
            "category":"Government",
            "subcategory":"Office",
            "type":"Public Place"
        }
    ],
    "sg:phone":"+1 540 942 6698",
    "sg:postcode":"22980",
    "sg:province":"VA",
    "sg:tags":[
        "village"
    ],
    "sg:website":"www.waynesboro.va.us",
    "wof:name":"Waynesboro EOC Director",
    "wof:placetype":"venue"
},
  "geometry": {"coordinates":[-78.889957,38.066947],"type":"Point"}
}