{
  "type": "Feature",
  "properties": {
    "iso:country":"US",
    "sg:address":"6917 Ridgeway Dr",
    "sg:city":"Springfield",
    "sg:classifiers":[
        {
            "category":"Professional",
            "subcategory":"Computer Services",
            "type":"Services"
        }
    ],
    "sg:phone":"+1 703 644 1188",
    "sg:postcode":"22150",
    "sg:province":"VA",
    "sg:tags":[
        "related"
    ],
    "wof:name":"Jon Radel",
    "wof:placetype":"venue"
},
  "geometry": {"coordinates":[-77.19380700000001,38.765191],"type":"Point"}
}