{
  "type": "Feature",
  "properties": {
    "addr:full":"411 Avory Ave Norfolk VA 23523",
    "addr:housenumber":"411",
    "addr:postcode":"23523",
    "addr:street":"Avory Ave",
    "iso:country":"US",
    "sg:address":"411 Avory Ave",
    "sg:city":"Norfolk",
    "sg:classifiers":[
        {
            "category":"Autos & Motor Vehicles",
            "subcategory":"Boat Sales",
            "type":"Retail Goods"
        }
    ],
    "sg:phone":"+1 757 543 1746",
    "sg:postcode":"23523",
    "sg:province":"VA",
    "sg:tags":[
        "equipment",
        "marine",
        "supply"
    ],
    "wof:name":"Brownco",
    "wof:placetype":"venue"
},
  "geometry": {"coordinates":[-76.26418200000001,36.835365],"type":"Point"}
}