{
  "type": "Feature",
  "properties": {
    "addr:full":"6636 E Virginia Beach Blvd Norfolk VA 23502",
    "addr:housenumber":"6636",
    "addr:postcode":"23502",
    "addr:street":"E Virginia Beach Blvd",
    "iso:country":"US",
    "sg:address":"6636 E Virginia Beach Blvd",
    "sg:city":"Norfolk",
    "sg:classifiers":[
        {
            "category":"Retail",
            "subcategory":"Veterinary Services",
            "type":"Services"
        }
    ],
    "sg:phone":"+1 757 461 4416",
    "sg:postcode":"23502",
    "sg:province":"VA",
    "sg:tags":[
        "hospital",
        "animal"
    ],
    "wof:name":"Boulevard Veterinary Hospital",
    "wof:placetype":"venue"
},
  "geometry": {"coordinates":[-76.17763600000001,36.854364],"type":"Point"}
}