{
  "type": "Feature",
  "properties": {
    "addr:full":"1910 Atlantic Ave Virginia Beach VA 23451",
    "addr:housenumber":"1910",
    "addr:postcode":"23451",
    "addr:street":"Atlantic Ave",
    "iso:country":"US",
    "sg:address":"1910 Atlantic Ave",
    "sg:city":"Virginia Beach",
    "sg:classifiers":[
        {
            "category":"Recreation",
            "type":"Entertainment"
        }
    ],
    "sg:phone":"+1 757 425 5233",
    "sg:postcode":"23451",
    "sg:province":"VA",
    "wof:name":"3d Fun House",
    "wof:placetype":"venue"
},
  "geometry": {"coordinates":[-75.975104,36.848153],"type":"Point"}
}