{
  "type": "Feature",
  "properties": {
    "iso:country":"US",
    "sg:address":"149 Saddle Rd",
    "sg:city":"Danville",
    "sg:classifiers":[
        {
            "category":"Professional",
            "type":"Services"
        }
    ],
    "sg:phone":"+1 434 685 2090",
    "sg:postcode":"24541",
    "sg:province":"VA",
    "wof:name":"Dennis Smith",
    "wof:placetype":"venue"
},
  "geometry": {"coordinates":[-79.58786000000001,36.602781],"type":"Point"}
}