{
  "type": "Feature",
  "properties": {
    "iso:country":"US",
    "sg:address":"943 Watertown Ct",
    "sg:city":"Virginia Beach",
    "sg:classifiers":[
        {
            "category":"Professional",
            "subcategory":"Management & Consulting",
            "type":"Services"
        }
    ],
    "sg:phone":"+1 757 200 7863",
    "sg:postcode":"23451",
    "sg:province":"VA",
    "wof:name":"Top Form Inc",
    "wof:placetype":"venue"
},
  "geometry": {"coordinates":[-75.98281799999999,36.807338],"type":"Point"}
}