{
  "type": "Feature",
  "properties": {
    "addr:full":"227 Pearson Dr Colonial Beach VA 22443",
    "addr:housenumber":"227",
    "addr:postcode":"22443",
    "addr:street":"Pearson Dr Colonial Beach",
    "iso:country":"US",
    "sg:address":"227 Pearson Dr",
    "sg:city":"Colonial Beach",
    "sg:classifiers":[
        {
            "category":"Building & Trades",
            "subcategory":"Plumbing",
            "type":"Services"
        }
    ],
    "sg:phone":"+1 804 224 8245",
    "sg:postcode":"22443",
    "sg:province":"VA",
    "sg:tags":[
        "conditioning",
        "air",
        "system",
        "contractor"
    ],
    "wof:name":"R K Payne Heating & Air",
    "wof:placetype":"venue"
},
  "geometry": {"coordinates":[-76.95574499999999,38.20644],"type":"Point"}
}