{
  "type": "Feature",
  "properties": {
    "addr:full":"8001 Algarve St Mc Lean VA 22102",
    "addr:postcode":"8001;22102",
    "addr:street":"Algarve St Mc Lean",
    "iso:country":"US",
    "sg:address":"8001 Algarve St",
    "sg:city":"Mc Lean",
    "sg:classifiers":[
        {
            "category":"Professional",
            "type":"Services"
        }
    ],
    "sg:phone":"+1 703 847 5844",
    "sg:postcode":"22102",
    "sg:province":"VA",
    "wof:name":"King of Northern Virginia",
    "wof:placetype":"venue"
},
  "geometry": {"coordinates":[-77.22220900000001,38.953247],"type":"Point"}
}