{
  "type": "Feature",
  "properties": {
    "addr:full":"601 Patrice Dr SE Leesburg VA 20175",
    "addr:housenumber":"601",
    "addr:postcode":"20175",
    "addr:street":"Patrice Dr Se",
    "iso:country":"US",
    "sg:address":"601 Patrice Dr SE",
    "sg:city":"Leesburg",
    "sg:classifiers":[
        {
            "category":"Professional",
            "subcategory":"Management & Consulting",
            "type":"Services"
        }
    ],
    "sg:phone":"+1 703 443 1013",
    "sg:postcode":"20175",
    "sg:province":"VA",
    "sg:tags":[
        "business"
    ],
    "wof:name":"Andersen Consulting",
    "wof:placetype":"venue"
},
  "geometry": {"coordinates":[-77.540189,39.090274],"type":"Point"}
}