{
  "type": "Feature",
  "properties": {
    "iso:country":"US",
    "sg:address":"10822 Warwick Blvd",
    "sg:city":"Newport News",
    "sg:classifiers":[
        {
            "category":"Personal",
            "subcategory":"Beauty Salon",
            "type":"Services"
        }
    ],
    "sg:phone":"+1 757 591 7619",
    "sg:postcode":"23601",
    "sg:province":"VA",
    "sg:tags":[
        "shop"
    ],
    "wof:name":"La Nails",
    "wof:placetype":"venue"
},
  "geometry": {"coordinates":[-76.46832999999999,37.039312],"type":"Point"}
}