{
  "type": "Feature",
  "properties": {
    "iso:country":"US",
    "sg:address":"2191 Fox Mill Rd",
    "sg:city":"Herndon",
    "sg:classifiers":[
        {
            "category":"Professional",
            "subcategory":"Lawyer & Legal Services",
            "type":"Services"
        }
    ],
    "sg:phone":"+1 703 234 4400",
    "sg:postcode":"20171",
    "sg:province":"VA",
    "sg:tags":[
        "attorney"
    ],
    "wof:name":"Rowan & Blewitt Inc",
    "wof:placetype":"venue"
},
  "geometry": {"coordinates":[-77.412249,38.956336],"type":"Point"}
}