{
  "type": "Feature",
  "properties": {
    "addr:full":"2020 Avon Ct Charlottesville VA 22902",
    "addr:housenumber":"2020",
    "addr:postcode":"22902",
    "addr:street":"Avon Ct",
    "iso:country":"US",
    "sg:address":"2020 Avon Ct",
    "sg:city":"Charlottesville",
    "sg:classifiers":[
        {
            "category":"Utilities",
            "type":"Services"
        }
    ],
    "sg:phone":"+1 434 984 0007",
    "sg:postcode":"22902",
    "sg:province":"VA",
    "sg:tags":[
        "provider",
        "internet"
    ],
    "wof:name":"Internet Payment Solutions",
    "wof:placetype":"venue"
},
  "geometry": {"coordinates":[-78.482201,38.001499],"type":"Point"}
}