{
  "type": "Feature",
  "properties": {
    "iso:country":"US",
    "sg:address":"3613 Meadowbridge Rd",
    "sg:city":"Richmond",
    "sg:classifiers":[
        {
            "category":"Retail",
            "subcategory":"Laundry & Dry Cleaning",
            "type":"Services"
        }
    ],
    "sg:phone":"+1 804 228 1961",
    "sg:postcode":"23222",
    "sg:province":"VA",
    "wof:name":"Meadowbridge Coin Laundry",
    "wof:placetype":"venue"
},
  "geometry": {"coordinates":[-77.423033,37.581659],"type":"Point"}
}