{
  "type": "Feature",
  "properties": {
    "addr:full":"110 Key Cir Yorktown VA 23692",
    "addr:housenumber":"110",
    "addr:postcode":"23692",
    "addr:street":"Key Cir",
    "iso:country":"US",
    "sg:address":"110 Key Cir",
    "sg:city":"Yorktown",
    "sg:classifiers":[
        {
            "category":"Building & Trades",
            "subcategory":"Electrical",
            "type":"Services"
        }
    ],
    "sg:phone":"+1 757 833 0550",
    "sg:postcode":"23692",
    "sg:province":"VA",
    "sg:tags":[
        "electric",
        "contractor"
    ],
    "wof:name":"Coastal Services & Techs",
    "wof:placetype":"venue"
},
  "geometry": {"coordinates":[-76.448542,37.136849],"type":"Point"}
}