{
  "type": "Feature",
  "properties": {
    "addr:full":"264 McLaws Cir Williamsburg VA 23185",
    "addr:housenumber":"264",
    "addr:postcode":"23185",
    "addr:street":"Mclaws Cir",
    "iso:country":"US",
    "sg:address":"264 McLaws Cir",
    "sg:city":"Williamsburg",
    "sg:classifiers":[
        {
            "category":"Shopping",
            "subcategory":"Clothing, Apparel, & Fashions",
            "type":"Retail Goods"
        }
    ],
    "sg:phone":"+1 757 220 8399",
    "sg:postcode":"23185",
    "sg:province":"VA",
    "sg:tags":[
        "lady",
        "accessory"
    ],
    "wof:name":"Swan Song",
    "wof:placetype":"venue"
},
  "geometry": {"coordinates":[-76.659154,37.245125],"type":"Point"}
}