{
  "type": "Feature",
  "properties": {
    "iso:country":"US",
    "sg:address":"9481 Windsor Blvd",
    "sg:city":"Windsor",
    "sg:classifiers":[
        {
            "category":"Retail",
            "subcategory":"Auto Repair",
            "type":"Services"
        }
    ],
    "sg:phone":"+1 757 242 6235",
    "sg:postcode":"23487",
    "sg:province":"VA",
    "sg:tags":[
        "repairing",
        "automobile",
        "radiator"
    ],
    "wof:name":"Roy's Radiator Repair",
    "wof:placetype":"venue"
},
  "geometry": {"coordinates":[-76.761937,36.820023],"type":"Point"}
}