{
  "type": "Feature",
  "properties": {
    "addr:full":"14705 Willard Rd Chantilly VA 20151",
    "addr:housenumber":"14705",
    "addr:postcode":"20151",
    "addr:street":"Willard Rd",
    "iso:country":"US",
    "sg:address":"14705 Willard Rd",
    "sg:city":"Chantilly",
    "sg:classifiers":[
        {
            "category":"Government",
            "subcategory":"Office",
            "type":"Public Place"
        }
    ],
    "sg:phone":"+1 703 735 3362",
    "sg:postcode":"20151",
    "sg:province":"VA",
    "sg:tags":[
        "department",
        "defense"
    ],
    "wof:name":"Tech Equipment Inspection",
    "wof:placetype":"venue"
},
  "geometry": {"coordinates":[-77.458733,38.8888],"type":"Point"}
}