{
  "type": "Feature",
  "properties": {
    "addr:full":"829 Santmyer Dr SE Leesburg VA 20175",
    "addr:housenumber":"829",
    "addr:postcode":"20175",
    "addr:street":"Santmyer Dr Se",
    "iso:country":"US",
    "sg:address":"829 Santmyer Dr SE",
    "sg:city":"Leesburg",
    "sg:classifiers":[
        {
            "category":"Wholesale",
            "subcategory":"Computers",
            "type":"Manufacturing & Wholesale Goods"
        }
    ],
    "sg:phone":"+1 703 443 6695",
    "sg:postcode":"20175",
    "sg:province":"VA",
    "wof:name":"Tech Data Government Sales",
    "wof:placetype":"venue"
},
  "geometry": {"coordinates":[-77.543094,39.082051],"type":"Point"}
}