{
  "type": "Feature",
  "properties": {
    "addr:full":"1909 Dressler Dr Covington VA 24426",
    "addr:housenumber":"1909",
    "addr:postcode":"24426",
    "addr:street":"Dressler Dr",
    "iso:country":"US",
    "sg:address":"1909 Dressler Dr",
    "sg:city":"Covington",
    "sg:classifiers":[
        {
            "category":"Social Services",
            "type":"Services"
        }
    ],
    "sg:phone":"+1 540 962 3045",
    "sg:postcode":"24426",
    "sg:province":"VA",
    "sg:tags":[
        "organization",
        "welfare"
    ],
    "wof:name":"Covington Woman's Club",
    "wof:placetype":"venue"
},
  "geometry": {"coordinates":[-79.987492,37.820403],"type":"Point"}
}