{
  "type": "Feature",
  "properties": {
    "iso:country":"US",
    "sg:address":"6444 Quarters Rd",
    "sg:city":"Woodford",
    "sg:classifiers":[
        {
            "category":"Freight",
            "type":"Transportation"
        }
    ],
    "sg:phone":"+1 804 448 3010",
    "sg:postcode":"22580",
    "sg:province":"VA",
    "sg:tags":[
        "operator",
        "local",
        "trucking"
    ],
    "wof:name":"Thomas Trucking Inc L A",
    "wof:placetype":"venue"
},
  "geometry": {"coordinates":[-77.534761,38.073271],"type":"Point"}
}