{
  "type": "Feature",
  "properties": {
    "addr:full":"407 Steeles Ln Tazewell VA 24651",
    "addr:housenumber":"407",
    "addr:postcode":"24651",
    "addr:street":"Steeles Ln",
    "iso:country":"US",
    "sg:address":"407 Steeles Ln",
    "sg:city":"Tazewell",
    "sg:classifiers":[
        {
            "category":"Local Transit",
            "type":"Transportation"
        }
    ],
    "sg:phone":"+1 276 988 9062",
    "sg:postcode":"24651",
    "sg:province":"VA",
    "sg:tags":[
        "squad",
        "rescue"
    ],
    "wof:name":"Jeffersonville Rescue Squad",
    "wof:placetype":"venue"
},
  "geometry": {"coordinates":[-81.499162,37.118765],"type":"Point"}
}