{
  "type": "Feature",
  "properties": {
    "addr:full":"639 Chelsea Pl Newport News VA 23603",
    "addr:housenumber":"639",
    "addr:postcode":"23603",
    "addr:street":"Chelsea Pl",
    "iso:country":"US",
    "sg:address":"639 Chelsea Pl",
    "sg:city":"Newport News",
    "sg:classifiers":[
        {
            "category":"Real Estate",
            "subcategory":"Real Estate Operator",
            "type":"Services"
        }
    ],
    "sg:phone":"+1 757 887 2316",
    "sg:postcode":"23603",
    "sg:province":"VA",
    "sg:tags":[
        "building",
        "apartment"
    ],
    "wof:name":"Chelsea Apts",
    "wof:placetype":"venue"
},
  "geometry": {"coordinates":[-76.574095,37.198367],"type":"Point"}
}