{
  "type": "Feature",
  "properties": {
    "iso:country":"US",
    "sg:address":"8394 Terminal Rd Ste K",
    "sg:city":"Lorton",
    "sg:classifiers":[
        {
            "category":"Home & Garden",
            "subcategory":"Home Furnishings",
            "type":"Retail Goods"
        },
        {
            "category":"Building & Trades",
            "subcategory":"Construction",
            "type":"Services"
        },
        {
            "category":"Manufacturing",
            "subcategory":"Building Materials",
            "type":"Manufacturing & Wholesale Goods"
        }
    ],
    "sg:phone":"+1 703 642 2828",
    "sg:postcode":"22079",
    "sg:province":"VA",
    "sg:tags":[
        "industrial",
        "cabinetmakers-commercial",
        "carpenter",
        "cabinet",
        "refacing",
        "resurfacing",
        "maker",
        "cabinets-refinishing",
        "kitchen"
    ],
    "wof:name":"Thanh Carpentry Inc",
    "wof:placetype":"venue"
},
  "geometry": {"coordinates":[-77.195543,38.728128],"type":"Point"}
}