{
  "type": "Feature",
  "properties": {
    "addr:full":"1200 Edwards Ferry Rd NE Leesburg VA 20176",
    "addr:housenumber":"1200",
    "addr:postcode":"20176",
    "addr:street":"Edwards Ferry Rd Ne",
    "iso:country":"US",
    "sg:address":"1200 Edwards Ferry Rd NE",
    "sg:city":"Leesburg",
    "sg:classifiers":[
        {
            "category":"Coffee & Tea",
            "type":"Food & Drink"
        }
    ],
    "sg:menulink":"http://www.allmenus.com/va/catoctin/112032-starbucks-coffee/menu/",
    "sg:phone":"+1 804 651 0388",
    "sg:postcode":"20176",
    "sg:province":"VA",
    "sg:tags":[
        "american"
    ],
    "wof:name":"Starbucks Coffee",
    "wof:placetype":"venue"
},
  "geometry": {"coordinates":[-77.534998,39.113805],"type":"Point"}
}