{
  "type": "Feature",
  "properties": {
    "addr:full":"220 Burlington Dr Fredericksburg VA 22407",
    "addr:housenumber":"220",
    "addr:postcode":"22407",
    "addr:street":"Burlington Dr",
    "iso:country":"US",
    "sg:address":"220 Burlington Dr",
    "sg:city":"Fredericksburg",
    "sg:classifiers":[
        {
            "category":"Personal",
            "subcategory":"Beauty Salon",
            "type":"Services"
        }
    ],
    "sg:phone":"+1 540 548 8775",
    "sg:postcode":"22407",
    "sg:province":"VA",
    "sg:tags":[
        "shop"
    ],
    "wof:name":"Creative Beauty Solutions",
    "wof:placetype":"venue"
},
  "geometry": {"coordinates":[-77.55931200000001,38.279787],"type":"Point"}
}