{
  "type": "Feature",
  "properties": {
    "iso:country":"US",
    "sg:address":"1833 Nansemond Pkwy",
    "sg:city":"Suffolk",
    "sg:classifiers":[
        {
            "category":"Building & Trades",
            "subcategory":"Construction",
            "type":"Services"
        }
    ],
    "sg:phone":"+1 757 538 2440",
    "sg:postcode":"23434",
    "sg:province":"VA",
    "sg:tags":[
        "mason",
        "masonry",
        "industrial",
        "contractors-commercial",
        "contractor"
    ],
    "wof:name":"Williams Masonry Inc, Milton",
    "wof:placetype":"venue"
},
  "geometry": {"coordinates":[-76.53003699999999,36.768153],"type":"Point"}
}