{
  "type": "Feature",
  "properties": {
    "iso:country":"US",
    "sg:address":"218 N Lee St",
    "sg:city":"Alexandria",
    "sg:classifiers":[
        {
            "category":"Professional",
            "subcategory":"Art Services",
            "type":"Services"
        }
    ],
    "sg:phone":"+1 703 548 0003",
    "sg:postcode":"22314",
    "sg:province":"VA",
    "sg:tags":[
        "commercial",
        "design"
    ],
    "wof:name":"Weber Design",
    "wof:placetype":"venue"
},
  "geometry": {"coordinates":[-77.041072,38.806646],"type":"Point"}
}