{
  "type": "Feature",
  "properties": {
    "addr:full":"1530 N Key Blvd Arlington VA 22209",
    "addr:housenumber":"1530",
    "addr:postcode":"22209",
    "addr:street":"N Key Blvd",
    "iso:country":"US",
    "sg:address":"1530 N Key Blvd",
    "sg:city":"Arlington",
    "sg:classifiers":[
        {
            "category":"Professional",
            "subcategory":"Business Services",
            "type":"Services"
        }
    ],
    "sg:phone":"+1 703 243 8608",
    "sg:postcode":"22209",
    "sg:province":"VA",
    "sg:tags":[
        "consulting",
        "management"
    ],
    "wof:name":"Benefield Limited",
    "wof:placetype":"venue"
},
  "geometry": {"coordinates":[-77.077337,38.896046],"type":"Point"}
}