{
  "type": "Feature",
  "properties": {
    "addr:full":"110 W Grace St Harrisonburg VA 22801",
    "addr:housenumber":"110",
    "addr:postcode":"22801",
    "addr:street":"W Grace St",
    "iso:country":"US",
    "sg:address":"110 W Grace St",
    "sg:city":"Harrisonburg",
    "sg:classifiers":[
        {
            "category":"Building & Trades",
            "subcategory":"Construction",
            "type":"Services"
        }
    ],
    "sg:phone":"+1 540 432 0415",
    "sg:postcode":"22801",
    "sg:province":"VA",
    "sg:tags":[
        "elevator"
    ],
    "wof:name":"JMU Studio Ctr Elevator",
    "wof:placetype":"venue"
},
  "geometry": {"coordinates":[-78.877813,38.443455],"type":"Point"}
}