{
  "type": "Feature",
  "properties": {
    "iso:country":"US",
    "sg:address":"985 Ballentine Blvd",
    "sg:city":"Norfolk",
    "sg:classifiers":[
        {
            "category":"Professional",
            "type":"Services"
        },
        {
            "category":"Retail",
            "subcategory":"Auto Repair",
            "type":"Services"
        }
    ],
    "sg:phone":"+1 757 627 8888",
    "sg:postcode":"23504",
    "sg:province":"VA",
    "sg:tags":[
        "body",
        "establishment"
    ],
    "wof:name":"Liberty Auto Werks Ltd",
    "wof:placetype":"venue"
},
  "geometry": {"coordinates":[-76.24834,36.853397],"type":"Point"}
}