{
  "type": "Feature",
  "properties": {
    "addr:full":"11205 Cedar Forest Pl Glen Allen VA 23060",
    "addr:housenumber":"11205",
    "addr:postcode":"23060",
    "addr:street":"Cedar Forest Pl",
    "iso:country":"US",
    "sg:address":"11205 Cedar Forest Pl",
    "sg:city":"Glen Allen",
    "sg:classifiers":[
        {
            "category":"Shopping",
            "subcategory":"Hobbies, Toys, & Games",
            "type":"Retail Goods"
        }
    ],
    "sg:phone":"+1 804 217 9422",
    "sg:postcode":"23060",
    "sg:province":"VA",
    "wof:name":"Zenblooms",
    "wof:placetype":"venue"
},
  "geometry": {"coordinates":[-77.58124599999999,37.662789],"type":"Point"}
}