{
  "type": "Feature",
  "properties": {
    "addr:full":"151 W Main St Abingdon VA 24210",
    "addr:housenumber":"151",
    "addr:postcode":"24210",
    "addr:street":"W Main St",
    "iso:country":"US",
    "sg:address":"151 W Main St",
    "sg:city":"Abingdon",
    "sg:classifiers":[
        {
            "category":"Professional",
            "subcategory":"Accounting & Tax Preparation",
            "type":"Services"
        }
    ],
    "sg:phone":"+1 276 676 3333",
    "sg:postcode":"24210",
    "sg:province":"VA",
    "sg:tags":[
        "accountant"
    ],
    "wof:name":"Henrietta S Skeens CPA",
    "wof:placetype":"venue"
},
  "geometry": {"coordinates":[-81.97588500000001,36.710319],"type":"Point"}
}