{
  "type": "Feature",
  "properties": {
    "addr:full":"2681 Arlington Dr Alexandria VA 22306",
    "addr:housenumber":"2681",
    "addr:postcode":"22306",
    "addr:street":"Arlington Dr",
    "iso:country":"US",
    "sg:address":"2681 Arlington Dr",
    "sg:city":"Alexandria",
    "sg:classifiers":[
        {
            "category":"Professional",
            "subcategory":"Computer Services",
            "type":"Services"
        }
    ],
    "sg:phone":"+1 703 765 8574",
    "sg:postcode":"22306",
    "sg:province":"VA",
    "sg:tags":[
        "consultant",
        "designer"
    ],
    "wof:name":"Technologix Inc",
    "wof:placetype":"venue"
},
  "geometry": {"coordinates":[-77.078317,38.758183],"type":"Point"}
}