{
  "type": "Feature",
  "properties": {
    "iso:country":"US",
    "sg:address":"520 E 4th St",
    "sg:city":"Salem",
    "sg:classifiers":[
        {
            "category":"Food & Beverages",
            "subcategory":"Groceries & Convenience Stores",
            "type":"Retail Goods"
        }
    ],
    "sg:phone":"+1 540 387 2197",
    "sg:postcode":"24153",
    "sg:province":"VA",
    "sg:website":"http://www.uni-mart.com",
    "wof:name":"Uni-Mart",
    "wof:placetype":"venue"
},
  "geometry": {"coordinates":[-80.050183,37.287446],"type":"Point"}
}