{
  "type": "Feature",
  "properties": {
    "addr:full":"601 Volunteer Pkwy Bristol VA 37620",
    "addr:housenumber":"601",
    "addr:postcode":"37620",
    "addr:street":"Volunteer Pkwy",
    "iso:country":"US",
    "sg:address":"601 Volunteer Pkwy",
    "sg:city":"Bristol",
    "sg:classifiers":[
        {
            "category":"Professional",
            "subcategory":"Accounting & Tax Preparation",
            "type":"Services"
        }
    ],
    "sg:phone":"+1 423 989 3369",
    "sg:postcode":"37620",
    "sg:province":"VA",
    "wof:name":"Blackley Steven CPA",
    "wof:placetype":"venue"
},
  "geometry": {"coordinates":[-82.185311,36.585838],"type":"Point"}
}