{
  "type": "Feature",
  "properties": {
    "iso:country":"US",
    "sg:address":"718 N Armistead St",
    "sg:city":"Alexandria",
    "sg:classifiers":[
        {
            "category":"Travel",
            "subcategory":"Travel Agent",
            "type":"Entertainment"
        }
    ],
    "sg:phone":"+1 703 642 9260",
    "sg:postcode":"22312",
    "sg:province":"VA",
    "sg:tags":[
        "operator",
        "tour"
    ],
    "wof:name":"Tours Program Inc",
    "wof:placetype":"venue"
},
  "geometry": {"coordinates":[-77.135062,38.823086],"type":"Point"}
}