{
  "type": "Feature",
  "properties": {
    "iso:country":"US",
    "sg:address":"901 N Washington St",
    "sg:city":"Alexandria",
    "sg:classifiers":[
        {
            "category":"Organizations",
            "subcategory":"Professional Association",
            "type":"Services"
        }
    ],
    "sg:phone":"+1 703 548 4540",
    "sg:postcode":"22314",
    "sg:province":"VA",
    "wof:name":"Association Of Intl Agri Rsrch",
    "wof:placetype":"venue"
},
  "geometry": {"coordinates":[-77.044766,38.815273],"type":"Point"}
}