{
  "type": "Feature",
  "properties": {
    "addr:full":"16117 Ira Hoffman Ln Culpeper VA 22701",
    "addr:housenumber":"16117",
    "addr:postcode":"22701",
    "addr:street":"Ira Hoffman Ln",
    "iso:country":"US",
    "sg:address":"16117 Ira Hoffman Ln",
    "sg:city":"Culpeper",
    "sg:classifiers":[
        {
            "category":"Retail",
            "subcategory":"Repair Shop",
            "type":"Services"
        }
    ],
    "sg:phone":"+1 540 825 1311",
    "sg:postcode":"22701",
    "sg:province":"VA",
    "sg:tags":[
        "lock",
        "locksmith"
    ],
    "wof:name":"Central Virginia Locksmith",
    "wof:placetype":"venue"
},
  "geometry": {"coordinates":[-77.974065,38.484235],"type":"Point"}
}