{
  "type": "Feature",
  "properties": {
    "addr:full":"205 James Thurber Ct Falls Church VA 22046",
    "addr:housenumber":"205",
    "addr:postcode":"22046",
    "addr:street":"James Thurber Ct",
    "iso:country":"US",
    "sg:address":"205 James Thurber Ct",
    "sg:city":"Falls Church",
    "sg:classifiers":[
        {
            "category":"Professional",
            "subcategory":"Management & Consulting",
            "type":"Services"
        }
    ],
    "sg:phone":"+1 703 532 1914",
    "sg:postcode":"22046",
    "sg:province":"VA",
    "sg:tags":[
        "business"
    ],
    "wof:name":"John Wilkinson Consulting",
    "wof:placetype":"venue"
},
  "geometry": {"coordinates":[-77.16856300000001,38.886467],"type":"Point"}
}