{
  "type": "Feature",
  "properties": {
    "iso:country":"US",
    "sg:address":"6704 Quander Rd",
    "sg:city":"Alexandria",
    "sg:classifiers":[
        {
            "category":"Travel",
            "subcategory":"Travel Agent",
            "type":"Entertainment"
        }
    ],
    "sg:phone":"+1 703 768 1272",
    "sg:postcode":"22307",
    "sg:province":"VA",
    "sg:tags":[
        "agency",
        "bureau"
    ],
    "wof:name":"XTC Unlimited",
    "wof:placetype":"venue"
},
  "geometry": {"coordinates":[-77.069068,38.771856],"type":"Point"}
}