{
  "type": "Feature",
  "properties": {
    "addr:full":"157 Melville Dr Newport News VA 23602",
    "addr:housenumber":"157",
    "addr:postcode":"23602",
    "addr:street":"Melville Dr",
    "iso:country":"US",
    "sg:address":"157 Melville Dr",
    "sg:city":"Newport News",
    "sg:classifiers":[
        {
            "category":"Home & Garden",
            "subcategory":"Home Furnishings",
            "type":"Retail Goods"
        }
    ],
    "sg:phone":"+1 757 594 0518",
    "sg:postcode":"23602",
    "sg:province":"VA",
    "sg:tags":[
        "pottery"
    ],
    "wof:name":"Polish Pottery Shop",
    "wof:placetype":"venue"
},
  "geometry": {"coordinates":[-76.526214,37.112482],"type":"Point"}
}