{
  "type": "Feature",
  "properties": {
    "addr:full":"704 Dillard Rd Madison Heights VA 24572",
    "addr:housenumber":"704",
    "addr:postcode":"24572",
    "addr:street":"Dillard Rd",
    "iso:country":"US",
    "sg:address":"704 Dillard Rd",
    "sg:city":"Madison Heights",
    "sg:classifiers":[
        {
            "category":"Professional",
            "subcategory":"Accounting & Tax Preparation",
            "type":"Services"
        }
    ],
    "sg:phone":"+1 434 845 2301",
    "sg:postcode":"24572",
    "sg:province":"VA",
    "sg:tags":[
        "return",
        "filing"
    ],
    "wof:name":"Douglas Eubank Jr",
    "wof:placetype":"venue"
},
  "geometry": {"coordinates":[-79.12411400000001,37.45235],"type":"Point"}
}