{
  "type": "Feature",
  "properties": {
    "addr:full":"5322 Oaklawn Blvd Prince George VA 23875",
    "addr:housenumber":"5322",
    "addr:postcode":"23875",
    "addr:street":"Oaklawn Blvd",
    "iso:country":"US",
    "sg:address":"5322 Oaklawn Blvd",
    "sg:city":"Prince George",
    "sg:classifiers":[
        {
            "category":"Restaurant",
            "type":"Food & Drink"
        }
    ],
    "sg:menulink":"http://www.allmenus.com/va/hopewell/205592-taco-bell/menu/",
    "sg:phone":"+1 804 452 0796",
    "sg:postcode":"23875",
    "sg:province":"VA",
    "sg:tags":[
        "mexican"
    ],
    "wof:name":"Taco Bell",
    "wof:placetype":"venue"
},
  "geometry": {"coordinates":[-77.328081,37.259607],"type":"Point"}
}