{
  "type": "Feature",
  "properties": {
    "iso:country":"US",
    "sg:address":"801 James Madison Hwy",
    "sg:city":"Culpeper",
    "sg:classifiers":[
        {
            "category":"Personal",
            "subcategory":"Beauty Salon",
            "type":"Services"
        }
    ],
    "sg:phone":"+1 540 825 7414",
    "sg:postcode":"22701",
    "sg:province":"VA",
    "sg:tags":[
        "shop"
    ],
    "wof:name":"Styles Smart",
    "wof:placetype":"venue"
},
  "geometry": {"coordinates":[-77.975638,38.481662],"type":"Point"}
}