{
  "type": "Feature",
  "properties": {
    "iso:country":"US",
    "sg:address":"983 Ingleside Rd",
    "sg:city":"Norfolk",
    "sg:classifiers":[
        {
            "category":"Personal",
            "subcategory":"Beauty Salon",
            "type":"Services"
        }
    ],
    "sg:phone":"+1 757 440 2839",
    "sg:postcode":"23502",
    "sg:province":"VA",
    "sg:tags":[
        "shop"
    ],
    "wof:name":"Divine Hair Designz",
    "wof:placetype":"venue"
},
  "geometry": {"coordinates":[-76.239209,36.853437],"type":"Point"}
}