{
  "type": "Feature",
  "properties": {
    "addr:full":"650 W 11th St Front Royal VA 22630",
    "addr:housenumber":"650",
    "addr:postcode":"22630",
    "addr:street":"W 11Th St",
    "iso:country":"US",
    "sg:address":"650 W 11th St",
    "sg:city":"Front Royal",
    "sg:classifiers":[
        {
            "category":"Personal",
            "subcategory":"Tattoo Parlor",
            "type":"Services"
        }
    ],
    "sg:phone":"+1 540 622 2465",
    "sg:postcode":"22630",
    "sg:province":"VA",
    "sg:tags":[
        "tattooing"
    ],
    "wof:name":"Cool & Selective Tattoos & Art",
    "wof:placetype":"venue"
},
  "geometry": {"coordinates":[-78.207004,38.933511],"type":"Point"}
}