{
  "type": "Feature",
  "properties": {
    "addr:full":"7636 Williamson Rd Roanoke VA 24019",
    "addr:housenumber":"7636",
    "addr:postcode":"24019",
    "addr:street":"Williamson Rd",
    "iso:country":"US",
    "sg:address":"7636 Williamson Rd",
    "sg:city":"Roanoke",
    "sg:classifiers":[
        {
            "category":"Professional",
            "subcategory":"Accounting & Tax Preparation",
            "type":"Services"
        }
    ],
    "sg:phone":"+1 540 777 1500",
    "sg:postcode":"24019",
    "sg:province":"VA",
    "sg:tags":[
        "accountant"
    ],
    "wof:name":"Moore & Campbell",
    "wof:placetype":"venue"
},
  "geometry": {"coordinates":[-79.946327,37.34975],"type":"Point"}
}