{
  "type": "Feature",
  "properties": {
    "addr:full":"3400 Ottobine Rd Dayton VA 22821",
    "addr:postcode":"3400;22821",
    "addr:street":"Ottobine Rd",
    "iso:country":"US",
    "sg:address":"3400 Ottobine Rd",
    "sg:city":"Dayton",
    "sg:classifiers":[
        {
            "category":"Farming",
            "subcategory":"Dairy Farm",
            "type":"Manufacturing & Wholesale Goods"
        }
    ],
    "sg:phone":"+1 540 879 2243",
    "sg:postcode":"22821",
    "sg:province":"VA",
    "wof:name":"Locust Hill Dairy",
    "wof:placetype":"venue"
},
  "geometry": {"coordinates":[-78.95956099999999,38.410481],"type":"Point"}
}