{
  "type": "Feature",
  "properties": {
    "addr:full":"1099 S Main St Farmville VA 23901",
    "addr:housenumber":"1099",
    "addr:postcode":"23901",
    "addr:street":"S Main St",
    "iso:country":"US",
    "sg:address":"1099 S Main St",
    "sg:city":"Farmville",
    "sg:classifiers":[
        {
            "category":"Restaurant",
            "type":"Food & Drink"
        }
    ],
    "sg:phone":"+1 434 392 8248",
    "sg:postcode":"23901",
    "sg:province":"VA",
    "wof:name":"Country Cookin Restaurant",
    "wof:placetype":"venue"
},
  "geometry": {"coordinates":[-78.397441,37.289133],"type":"Point"}
}