{
  "type": "Feature",
  "properties": {
    "addr:full":"5451 Wellington Rd Gainesville VA 20155",
    "addr:housenumber":"5451",
    "addr:postcode":"20155",
    "addr:street":"Wellington Rd",
    "iso:country":"US",
    "sg:address":"5451 Wellington Rd",
    "sg:city":"Gainesville",
    "sg:classifiers":[
        {
            "category":"Building & Trades",
            "subcategory":"Landscaping Services",
            "type":"Services"
        }
    ],
    "sg:phone":"+1 703 968 0668",
    "sg:postcode":"20155",
    "sg:province":"VA",
    "wof:name":"Tru Green-Chemlawn",
    "wof:placetype":"venue"
},
  "geometry": {"coordinates":[-77.59754700000001,38.794755],"type":"Point"}
}