{
  "type": "Feature",
  "properties": {
    "addr:full":"10580 Pineview Rd Manassas VA 20111",
    "addr:housenumber":"10580",
    "addr:postcode":"20111",
    "addr:street":"Pineview Rd",
    "iso:country":"US",
    "sg:address":"10580 Pineview Rd",
    "sg:city":"Manassas",
    "sg:classifiers":[
        {
            "category":"Organizations",
            "subcategory":"Religious Organization",
            "type":"Services"
        },
        {
            "category":"Education",
            "subcategory":"School",
            "type":"Public Place"
        }
    ],
    "sg:phone":"+1 703 368 5679",
    "sg:postcode":"20111",
    "sg:province":"VA",
    "sg:tags":[
        "sch",
        "church"
    ],
    "wof:name":"Holy Family Academy Inc",
    "wof:placetype":"venue"
},
  "geometry": {"coordinates":[-77.429749,38.721936],"type":"Point"}
}