{
  "type": "Feature",
  "properties": {
    "iso:country":"US",
    "sg:address":"19372 Brandy Rd",
    "sg:city":"Brandy Station",
    "sg:classifiers":[
        {
            "category":"Retail",
            "subcategory":"Auto Repair",
            "type":"Services"
        }
    ],
    "sg:phone":"+1 540 727 7545",
    "sg:postcode":"22714",
    "sg:province":"VA",
    "sg:tags":[
        "automobile",
        "inspection"
    ],
    "wof:name":"David Starkey Auto Repair",
    "wof:placetype":"venue"
},
  "geometry": {"coordinates":[-77.89449999999999,38.501346],"type":"Point"}
}