{
  "type": "Feature",
  "properties": {
    "addr:full":"2000 High St Portsmouth VA 23704",
    "addr:housenumber":"2000",
    "addr:postcode":"23704",
    "addr:street":"High St",
    "iso:country":"US",
    "sg:address":"2000 High St",
    "sg:city":"Portsmouth",
    "sg:classifiers":[
        {
            "category":"Health Services",
            "subcategory":"Clinic",
            "type":"Services"
        }
    ],
    "sg:phone":"+1 757 397 4300",
    "sg:postcode":"23704",
    "sg:province":"VA",
    "sg:tags":[
        "kidney",
        "dialysis",
        "center"
    ],
    "wof:name":"Davita Inc",
    "wof:placetype":"venue"
},
  "geometry": {"coordinates":[-76.324924,36.834851],"type":"Point"}
}