{
  "type": "Feature",
  "properties": {
    "iso:country":"US",
    "sg:address":"108 5th St SE",
    "sg:city":"Charlottesville",
    "sg:classifiers":[
        {
            "category":"Professional",
            "subcategory":"Management & Consulting",
            "type":"Services"
        }
    ],
    "sg:phone":"+1 434 817 8440",
    "sg:postcode":"22902",
    "sg:province":"VA",
    "sg:tags":[
        "counselor",
        "public",
        "relations"
    ],
    "wof:name":"Glickman Group",
    "wof:placetype":"venue"
},
  "geometry": {"coordinates":[-78.478769,38.029113],"type":"Point"}
}