{
  "type": "Feature",
  "properties": {
    "iso:country":"US",
    "sg:address":"12921 Wheatland Rd",
    "sg:city":"Fairfax",
    "sg:classifiers":[
        {
            "category":"Shopping",
            "type":"Retail Goods"
        }
    ],
    "sg:phone":"+1 703 860 8527",
    "sg:postcode":"22033",
    "sg:province":"VA",
    "sg:tags":[
        "merchandise"
    ],
    "wof:name":"Freehill Studio Inc",
    "wof:placetype":"venue"
},
  "geometry": {"coordinates":[-77.39259,38.886849],"type":"Point"}
}