{
  "type": "Feature",
  "properties": {
    "iso:country":"US",
    "sg:address":"537 Main St",
    "sg:city":"Clifton Forge",
    "sg:classifiers":[
        {
            "category":"Wholesale",
            "subcategory":"Medical Equipment & Supplies",
            "type":"Manufacturing & Wholesale Goods"
        }
    ],
    "sg:phone":"+1 540 862 8810",
    "sg:postcode":"24422",
    "sg:province":"VA",
    "sg:tags":[
        "hospital"
    ],
    "wof:name":"Regional Home Care",
    "wof:placetype":"venue"
},
  "geometry": {"coordinates":[-79.825772,37.816322],"type":"Point"}
}