{
  "type": "Feature",
  "properties": {
    "addr:full":"136 Pumpkin Ln Independence VA 24348",
    "addr:housenumber":"136",
    "addr:postcode":"24348",
    "addr:street":"Pumpkin Ln",
    "iso:country":"US",
    "sg:address":"136 Pumpkin Ln",
    "sg:city":"Independence",
    "sg:classifiers":[
        {
            "category":"Building & Trades",
            "subcategory":"Construction",
            "type":"Services"
        }
    ],
    "sg:phone":"+1 276 773 3344",
    "sg:postcode":"24348",
    "sg:province":"VA",
    "sg:tags":[
        "house"
    ],
    "wof:name":"Coe Building & Improvements",
    "wof:placetype":"venue"
},
  "geometry": {"coordinates":[-81.20551399999999,36.672409],"type":"Point"}
}