{
  "type": "Feature",
  "properties": {
    "iso:country":"US",
    "sg:address":"3059 Sleepy Hollow Rd",
    "sg:city":"Falls Church",
    "sg:classifiers":[
        {
            "category":"Building & Trades",
            "subcategory":"Construction",
            "type":"Services"
        }
    ],
    "sg:phone":"+1 703 534 7453",
    "sg:postcode":"22042",
    "sg:province":"VA",
    "sg:tags":[
        "house"
    ],
    "wof:name":"T & D General Home Improvement",
    "wof:placetype":"venue"
},
  "geometry": {"coordinates":[-77.162075,38.864547],"type":"Point"}
}