{
  "type": "Feature",
  "properties": {
    "addr:full":"829 2nd St Radford VA 24141",
    "addr:housenumber":"829",
    "addr:postcode":"24141",
    "addr:street":"2Nd St",
    "iso:country":"US",
    "sg:address":"829 2nd St",
    "sg:city":"Radford",
    "sg:classifiers":[
        {
            "category":"Retail",
            "subcategory":"Veterinary Services",
            "type":"Services"
        }
    ],
    "sg:phone":"+1 540 731 1111",
    "sg:postcode":"24141",
    "sg:province":"VA",
    "sg:tags":[
        "animal"
    ],
    "wof:name":"West End Animal Clinic",
    "wof:placetype":"venue"
},
  "geometry": {"coordinates":[-80.582025,37.128301],"type":"Point"}
}