{
  "type": "Feature",
  "properties": {
    "addr:full":"63 Potomac Ln Colonial Beach VA 22443",
    "addr:housenumber":"63",
    "addr:postcode":"22443",
    "addr:street":"Potomac Ln",
    "iso:country":"US",
    "sg:address":"63 Potomac Ln",
    "sg:city":"Colonial Beach",
    "sg:classifiers":[
        {
            "category":"Manufacturing",
            "subcategory":"Food",
            "type":"Manufacturing & Wholesale Goods"
        }
    ],
    "sg:phone":"+1 804 224 7123",
    "sg:postcode":"22443",
    "sg:province":"VA",
    "sg:tags":[
        "canned",
        "mfg"
    ],
    "wof:name":"Gails Jams & Preserves",
    "wof:placetype":"venue"
},
  "geometry": {"coordinates":[-76.972741,38.21858],"type":"Point"}
}