{
  "type": "Feature",
  "properties": {
    "iso:country":"US",
    "sg:address":"1548 N Cherry Grove Rd",
    "sg:city":"Suffolk",
    "sg:classifiers":[
        {
            "category":"Professional",
            "subcategory":"Business Services",
            "type":"Services"
        },
        {
            "category":"Home & Garden",
            "subcategory":"Home Furnishings",
            "type":"Retail Goods"
        }
    ],
    "sg:phone":"+1 757 255 2565",
    "sg:postcode":"23432",
    "sg:province":"VA",
    "sg:tags":[
        "curtain",
        "made",
        "drapery"
    ],
    "wof:name":"Birdsong Interior Design",
    "wof:placetype":"venue"
},
  "geometry": {"coordinates":[-76.542698,36.901068],"type":"Point"}
}