{
  "type": "Feature",
  "properties": {
    "iso:country":"US",
    "sg:address":"216 Forest Hills Dr",
    "sg:city":"Bristol",
    "sg:classifiers":[
        {
            "category":"Shopping",
            "subcategory":"Beauty & Cosmetics",
            "type":"Retail Goods"
        }
    ],
    "sg:phone":"+1 423 989 0042",
    "sg:postcode":"37620",
    "sg:province":"VA",
    "sg:tags":[
        "merchandise"
    ],
    "wof:name":"Mary Kay Cosmetics",
    "wof:placetype":"venue"
},
  "geometry": {"coordinates":[-82.14443,36.59056],"type":"Point"}
}