{
  "type": "Feature",
  "properties": {
    "addr:full":"3376 Pryor Rd Goochland VA 23063",
    "addr:housenumber":"3376",
    "addr:postcode":"23063",
    "addr:street":"Pryor Rd",
    "iso:country":"US",
    "sg:address":"3376 Pryor Rd",
    "sg:city":"Goochland",
    "sg:classifiers":[
        {
            "category":"Farming",
            "subcategory":"Dairy Farm",
            "type":"Manufacturing & Wholesale Goods"
        }
    ],
    "sg:phone":"+1 804 457 4177",
    "sg:postcode":"23063",
    "sg:province":"VA",
    "sg:tags":[
        "grain",
        "cash"
    ],
    "wof:name":"Hills-Dale Farm",
    "wof:placetype":"venue"
},
  "geometry": {"coordinates":[-78.026341,37.809329],"type":"Point"}
}