{
  "type": "Feature",
  "properties": {
    "addr:full":"81 Main St Stanardsville VA 22973",
    "addr:housenumber":"81",
    "addr:postcode":"22973",
    "addr:street":"Main St",
    "iso:country":"US",
    "sg:address":"81 Main St",
    "sg:city":"Stanardsville",
    "sg:classifiers":[
        {
            "category":"Building & Trades",
            "subcategory":"Pest Control",
            "type":"Services"
        }
    ],
    "sg:phone":"+1 434 985 8279",
    "sg:postcode":"22973",
    "sg:province":"VA",
    "wof:name":"Brown Exterminating",
    "wof:placetype":"venue"
},
  "geometry": {"coordinates":[-78.439532,38.29748],"type":"Point"}
}