{
  "type": "Feature",
  "properties": {
    "addr:full":"5701 Glamis Dr Alexandria VA 22315",
    "addr:housenumber":"5701",
    "addr:postcode":"22315",
    "addr:street":"Glamis Dr",
    "iso:country":"US",
    "sg:address":"5701 Glamis Dr",
    "sg:city":"Alexandria",
    "sg:classifiers":[
        {
            "category":"Professional",
            "subcategory":"Engineering",
            "type":"Services"
        }
    ],
    "sg:phone":"+1 703 971 7432",
    "sg:postcode":"22315",
    "sg:province":"VA",
    "sg:tags":[
        "consultant",
        "management",
        "facility"
    ],
    "wof:name":"Matthew J Jones Jr",
    "wof:placetype":"venue"
},
  "geometry": {"coordinates":[-77.134348,38.75071],"type":"Point"}
}