{
  "type": "Feature",
  "properties": {
    "addr:full":"4872 Cellar Creek Rd Blackstone VA 23824",
    "addr:housenumber":"4872",
    "addr:postcode":"23824",
    "addr:street":"Cellar Creek Rd",
    "iso:country":"US",
    "sg:address":"4872 Cellar Creek Rd",
    "sg:city":"Blackstone",
    "sg:classifiers":[
        {
            "category":"Building & Trades",
            "subcategory":"Construction",
            "type":"Services"
        }
    ],
    "sg:phone":"+1 434 292 6683",
    "sg:postcode":"23824",
    "sg:province":"VA",
    "sg:tags":[
        "hanging",
        "contractor"
    ],
    "wof:name":"Leonard Painting",
    "wof:placetype":"venue"
},
  "geometry": {"coordinates":[-77.98256499999999,37.195741],"type":"Point"}
}