{
  "type": "Feature",
  "properties": {
    "iso:country":"US",
    "sg:address":"10149 Squirrel Level Rd",
    "sg:city":"Petersburg",
    "sg:phone":"+1 804 733 0260",
    "sg:postcode":"23803",
    "sg:province":"VA",
    "sg:tags":[
        "farm",
        "field",
        "crop",
        "soybean",
        "cotton"
    ],
    "wof:name":"Alvin Blaha",
    "wof:placetype":"venue"
},
  "geometry": {"coordinates":[-77.464055,37.132335],"type":"Point"}
}