{
  "type": "Feature",
  "properties": {
    "addr:full":"7458 Lee Hwy Fairlawn VA 24141",
    "addr:housenumber":"7458",
    "addr:postcode":"24141",
    "addr:street":"Lee Hwy",
    "iso:country":"US",
    "sg:address":"7458 Lee Hwy",
    "sg:city":"Fairlawn",
    "sg:classifiers":[
        {
            "category":"Shopping",
            "subcategory":"Jewelry",
            "type":"Retail Goods"
        }
    ],
    "sg:phone":"+1 540 731 4277",
    "sg:postcode":"24141",
    "sg:province":"VA",
    "sg:tags":[
        "jeweler"
    ],
    "wof:name":"Lemons Jewelry",
    "wof:placetype":"venue"
},
  "geometry": {"coordinates":[-80.579943,37.142749],"type":"Point"}
}