{
  "type": "Feature",
  "properties": {
    "iso:country":"US",
    "sg:address":"153 Menlough Dr",
    "sg:city":"Warrenton",
    "sg:classifiers":[
        {
            "category":"Shopping",
            "subcategory":"Clothing, Apparel, & Fashions",
            "type":"Retail Goods"
        }
    ],
    "sg:phone":"+1 540 341 4358",
    "sg:postcode":"20186",
    "sg:province":"VA",
    "wof:name":"Xplosive T Shirts",
    "wof:placetype":"venue"
},
  "geometry": {"coordinates":[-77.80697499999999,38.707806],"type":"Point"}
}