{
  "type": "Feature",
  "properties": {
    "iso:country":"US",
    "sg:address":"221 E German School Rd",
    "sg:city":"Richmond",
    "sg:classifiers":[
        {
            "category":"Place Of Worship",
            "subcategory":"Church",
            "type":"Public Place"
        },
        {
            "category":"Place Of Worship",
            "type":"Public Place"
        }
    ],
    "sg:phone":"+1 804 232 1182",
    "sg:postcode":"23224",
    "sg:province":"VA",
    "sg:tags":[
        "churches-interdenominational",
        "churches-various",
        "denomination"
    ],
    "wof:name":"Message Of Hope Christian Center",
    "wof:placetype":"venue"
},
  "geometry": {"coordinates":[-77.504127,37.502528],"type":"Point"}
}