{
  "type": "Feature",
  "properties": {
    "iso:country":"US",
    "sg:address":"2407 W Main St",
    "sg:city":"Richmond",
    "sg:classifiers":[
        {
            "category":"Banks & Credit Unions",
            "subcategory":"Investment Brokerage",
            "type":"Services"
        }
    ],
    "sg:phone":"+1 804 359 3696",
    "sg:postcode":"23220",
    "sg:province":"VA",
    "sg:tags":[
        "i",
        "security",
        "management",
        "consulting"
    ],
    "wof:name":"Minor Financial Strategies",
    "wof:placetype":"venue"
},
  "geometry": {"coordinates":[-77.47199000000001,37.551312],"type":"Point"}
}