{
  "type": "Feature",
  "properties": {
    "addr:full":"21 University Cir Charlottesville VA 22903",
    "addr:housenumber":"21",
    "addr:postcode":"22903",
    "addr:street":"University Cir",
    "iso:country":"US",
    "sg:address":"21 University Cir",
    "sg:city":"Charlottesville",
    "sg:classifiers":[
        {
            "category":"Education",
            "subcategory":"University",
            "type":"Public Place"
        }
    ],
    "sg:phone":"+1 434 924 7983",
    "sg:postcode":"22903",
    "sg:province":"VA",
    "sg:tags":[
        "college"
    ],
    "wof:name":"University of Virginia",
    "wof:placetype":"venue"
},
  "geometry": {"coordinates":[-78.50378499999999,38.043456],"type":"Point"}
}