{
  "type": "Feature",
  "properties": {
    "addr:full":"1235 S Clark St Arlington VA 22202",
    "addr:housenumber":"1235",
    "addr:postcode":"22202",
    "addr:street":"S Clark St",
    "iso:country":"US",
    "sg:address":"1235 S Clark St",
    "sg:city":"Arlington",
    "sg:classifiers":[
        {
            "category":"Professional",
            "subcategory":"Engineering",
            "type":"Services"
        }
    ],
    "sg:phone":"+1 703 412 2500",
    "sg:postcode":"22202",
    "sg:province":"VA",
    "sg:tags":[
        "nuclear",
        "company",
        "holding"
    ],
    "wof:name":"Bnfl",
    "wof:placetype":"venue"
},
  "geometry": {"coordinates":[-77.051158,38.8626],"type":"Point"}
}