{
  "type": "Feature",
  "properties": {
    "addr:full":"1533 Virginia Ave Charlottesville VA 22903",
    "addr:housenumber":"1533",
    "addr:postcode":"22903",
    "addr:street":"Virginia Ave",
    "iso:country":"US",
    "sg:address":"1533 Virginia Ave",
    "sg:city":"Charlottesville",
    "sg:classifiers":[
        {
            "category":"Professional",
            "type":"Services"
        }
    ],
    "sg:phone":"+1 434 979 4386",
    "sg:postcode":"22903",
    "sg:province":"VA",
    "sg:tags":[
        "establishment"
    ],
    "wof:name":"Sigma Pi",
    "wof:placetype":"venue"
},
  "geometry": {"coordinates":[-78.50028500000001,38.038753],"type":"Point"}
}