{
  "type": "Feature",
  "properties": {
    "iso:country":"US",
    "sg:address":"105 W Washington St",
    "sg:city":"Middleburg",
    "sg:phone":"+1 540 687 8771",
    "sg:postcode":"20117",
    "sg:province":"VA",
    "wof:name":"Fish",
    "wof:placetype":"venue"
},
  "geometry": {"coordinates":[-77.73683,38.968501],"type":"Point"}
}