{
  "type": "Feature",
  "properties": {
    "addr:full":"3702 Pender Dr Fairfax VA 22030",
    "addr:housenumber":"3702",
    "addr:postcode":"22030",
    "addr:street":"Pender Dr",
    "iso:country":"US",
    "sg:address":"3702 Pender Dr",
    "sg:city":"Fairfax",
    "sg:classifiers":[
        {
            "category":"Professional",
            "subcategory":"Management & Consulting",
            "type":"Services"
        }
    ],
    "sg:phone":"+1 703 591 7272",
    "sg:postcode":"22030",
    "sg:province":"VA",
    "sg:tags":[
        "construction"
    ],
    "sg:website":"www.himesassociates.com",
    "wof:name":"Himes Associates Ltd",
    "wof:placetype":"venue"
},
  "geometry": {"coordinates":[-77.330724,38.862933],"type":"Point"}
}