{
  "type": "Feature",
  "properties": {
    "addr:full":"6395 Yates Ford Rd Manassas VA 20111",
    "addr:housenumber":"6395",
    "addr:postcode":"20111",
    "addr:street":"Yates Ford Rd",
    "iso:country":"US",
    "sg:address":"6395 Yates Ford Rd",
    "sg:city":"Manassas",
    "sg:classifiers":[
        {
            "category":"Professional",
            "subcategory":"Computer Services",
            "type":"Services"
        }
    ],
    "sg:phone":"+1 703 366 3300",
    "sg:postcode":"20111",
    "sg:province":"VA",
    "sg:tags":[
        "prepackaged",
        "software"
    ],
    "wof:name":"Eprence",
    "wof:placetype":"venue"
},
  "geometry": {"coordinates":[-77.393807,38.733989],"type":"Point"}
}