{
  "type": "Feature",
  "properties": {
    "addr:full":"5925 Shallow Way Richmond VA 23224",
    "addr:housenumber":"5925",
    "addr:postcode":"23224",
    "addr:street":"Shallow Way",
    "iso:country":"US",
    "sg:address":"5925 Shallow Way",
    "sg:city":"Richmond",
    "sg:classifiers":[
        {
            "category":"Building & Trades",
            "subcategory":"Construction",
            "type":"Services"
        }
    ],
    "sg:phone":"+1 804 230 6485",
    "sg:postcode":"23224",
    "sg:province":"VA",
    "sg:tags":[
        "handyman"
    ],
    "wof:name":"Fix Repair Daily",
    "wof:placetype":"venue"
},
  "geometry": {"coordinates":[-77.50546300000001,37.499329],"type":"Point"}
}