{
  "type": "Feature",
  "properties": {
    "iso:country":"US",
    "sg:address":"425 Winterham Dr",
    "sg:city":"Abingdon",
    "sg:classifiers":[
        {
            "category":"Professional",
            "subcategory":"Management & Consulting",
            "type":"Services"
        }
    ],
    "sg:phone":"+1 276 676 2093",
    "sg:postcode":"24211",
    "sg:province":"VA",
    "sg:tags":[
        "computer",
        "custom"
    ],
    "wof:name":"Mountain Systems Inc",
    "wof:placetype":"venue"
},
  "geometry": {"coordinates":[-81.958178,36.697294],"type":"Point"}
}