{
  "type": "Feature",
  "properties": {
    "addr:full":"1315 Euclid Ave Bristol VA 24201",
    "addr:housenumber":"1315",
    "addr:postcode":"24201",
    "addr:street":"Euclid Ave",
    "iso:country":"US",
    "sg:address":"1315 Euclid Ave",
    "sg:city":"Bristol",
    "sg:classifiers":[
        {
            "category":"Cinema",
            "subcategory":"Movie Rental",
            "type":"Entertainment"
        }
    ],
    "sg:phone":"+1 276 669 2126",
    "sg:postcode":"24201",
    "sg:province":"VA",
    "sg:tags":[
        "leasing",
        "video",
        "disc",
        "tape"
    ],
    "sg:website":"www.blockbuster.com",
    "wof:name":"Blockbuster Video",
    "wof:placetype":"venue"
},
  "geometry": {"coordinates":[-82.192279,36.602738],"type":"Point"}
}