{
  "type": "Feature",
  "properties": {
    "addr:full":"225 S Main St Galax VA 24333",
    "addr:housenumber":"225",
    "addr:postcode":"24333",
    "addr:street":"S Main St",
    "iso:country":"US",
    "sg:address":"225 S Main St",
    "sg:city":"Galax",
    "sg:classifiers":[
        {
            "category":"Organizations",
            "subcategory":"Religious Organization",
            "type":"Services"
        }
    ],
    "sg:phone":"+1 276 236 5757",
    "sg:postcode":"24333",
    "sg:province":"VA",
    "sg:tags":[
        "church"
    ],
    "wof:name":"Living Waters",
    "wof:placetype":"venue"
},
  "geometry": {"coordinates":[-80.924226,36.66079],"type":"Point"}
}