{
  "type": "Feature",
  "properties": {
    "iso:country":"US",
    "sg:address":"344 Seminole Ct",
    "sg:city":"Charlottesville",
    "sg:classifiers":[
        {
            "category":"Restaurant",
            "type":"Food & Drink"
        }
    ],
    "sg:menulink":"http://www.allmenus.com/va/charlottesville/256345-oriental-express/menu/",
    "sg:phone":"+1 434 974 9988",
    "sg:postcode":"22901",
    "sg:province":"VA",
    "sg:tags":[
        "sushi",
        "japanese",
        "chinese",
        "asian"
    ],
    "wof:name":"Oriental Express",
    "wof:placetype":"venue"
},
  "geometry": {"coordinates":[-78.484675,38.064832],"type":"Point"}
}