{
  "type": "Feature",
  "properties": {
    "addr:full":"6549 Main St Gloucester VA 23061",
    "addr:housenumber":"6549",
    "addr:postcode":"23061",
    "addr:street":"Main St",
    "iso:country":"US",
    "sg:address":"6549 Main St",
    "sg:city":"Gloucester",
    "sg:classifiers":[
        {
            "category":"Professional",
            "subcategory":"Research",
            "type":"Services"
        }
    ],
    "sg:phone":"+1 804 695 1234",
    "sg:postcode":"23061",
    "sg:province":"VA",
    "sg:tags":[
        "commercial",
        "physical"
    ],
    "wof:name":"William J Meagher",
    "wof:placetype":"venue"
},
  "geometry": {"coordinates":[-76.532633,37.41574],"type":"Point"}
}