{
  "type": "Feature",
  "properties": {
    "addr:full":"165 New Market Rd Timberville VA 22853",
    "addr:housenumber":"165",
    "addr:postcode":"22853",
    "addr:street":"New Market Rd",
    "iso:country":"US",
    "sg:address":"165 New Market Rd",
    "sg:city":"Timberville",
    "sg:classifiers":[
        {
            "category":"Health Services",
            "subcategory":"Doctor",
            "type":"Services"
        }
    ],
    "sg:phone":"+1 540 896 8964",
    "sg:postcode":"22853",
    "sg:province":"VA",
    "sg:tags":[
        "physician",
        "surgeon"
    ],
    "wof:name":"Carilion Family Medicine",
    "wof:placetype":"venue"
},
  "geometry": {"coordinates":[-78.776065,38.632116],"type":"Point"}
}