{
  "type": "Feature",
  "properties": {
    "addr:full":"713 Reese Dr Sandston VA 23150",
    "addr:housenumber":"713",
    "addr:postcode":"23150",
    "addr:street":"Reese Dr",
    "iso:country":"US",
    "sg:address":"713 Reese Dr",
    "sg:city":"Sandston",
    "sg:classifiers":[
        {
            "category":"Building & Trades",
            "subcategory":"Construction",
            "type":"Services"
        }
    ],
    "sg:phone":"+1 804 737 0094",
    "sg:postcode":"23150",
    "sg:province":"VA",
    "sg:tags":[
        "house",
        "nonresidential"
    ],
    "wof:name":"W J Childress Inc",
    "wof:placetype":"venue"
},
  "geometry": {"coordinates":[-77.212062,37.505877],"type":"Point"}
}