{
  "type": "Feature",
  "properties": {
    "addr:full":"1413 N Main St Marion VA 24354",
    "addr:housenumber":"1413",
    "addr:postcode":"24354",
    "addr:street":"N Main St",
    "iso:country":"US",
    "sg:address":"1413 N Main St",
    "sg:city":"Marion",
    "sg:classifiers":[
        {
            "category":"Banks & Credit Unions",
            "subcategory":"Bank",
            "type":"Services"
        }
    ],
    "sg:phone":"+1 276 782 9639",
    "sg:postcode":"24354",
    "sg:province":"VA",
    "sg:tags":[
        "federal"
    ],
    "wof:name":"Mountain Empire Federal CU",
    "wof:placetype":"venue"
},
  "geometry": {"coordinates":[-81.494659,36.845804],"type":"Point"}
}