{
  "type": "Feature",
  "properties": {
    "iso:country":"US",
    "sg:address":"13001 Midlothian Tpke",
    "sg:city":"Midlothian",
    "sg:classifiers":[
        {
            "category":"Education",
            "subcategory":"Special Training",
            "type":"Public Place"
        }
    ],
    "sg:phone":"+1 804 267 1400",
    "sg:postcode":"23113",
    "sg:province":"VA",
    "sg:tags":[
        "educational"
    ],
    "sg:website":"http://www.huntingtonlearning.com",
    "wof:name":"Huntington Learning Center",
    "wof:placetype":"venue"
},
  "geometry": {"coordinates":[-77.639168,37.502522],"type":"Point"}
}