{
  "type": "Feature",
  "properties": {
    "iso:country":"US",
    "sg:address":"1110 Tyler Ave",
    "sg:city":"Radford",
    "sg:classifiers":[
        {
            "category":"Organizations",
            "subcategory":"Religious Organization",
            "type":"Services"
        }
    ],
    "sg:phone":"+1 540 639 4714",
    "sg:postcode":"24141",
    "sg:province":"VA",
    "sg:tags":[
        "church"
    ],
    "wof:name":"Jehovah's Witnesses Hall",
    "wof:placetype":"venue"
},
  "geometry": {"coordinates":[-80.546778,37.12946],"type":"Point"}
}