{
  "type": "Feature",
  "properties": {
    "iso:country":"US",
    "sg:address":"370 Dogwood Dr",
    "sg:city":"Madison Heights",
    "sg:classifiers":[
        {
            "category":"Building & Trades",
            "subcategory":"Plumbing",
            "type":"Services"
        }
    ],
    "sg:phone":"+1 434 941 4893",
    "sg:postcode":"24572",
    "sg:province":"VA",
    "sg:tags":[
        "repair",
        "installation",
        "heating"
    ],
    "wof:name":"Tomlins Heating and Cooling",
    "wof:placetype":"venue"
},
  "geometry": {"coordinates":[-79.07915,37.472156],"type":"Point"}
}