{
  "type": "Feature",
  "properties": {
    "iso:country":"US",
    "sg:address":"2890 Virginia Beach Blvd",
    "sg:city":"Virginia Beach",
    "sg:classifiers":[
        {
            "category":"Restaurant",
            "type":"Food & Drink"
        }
    ],
    "sg:phone":"+1 757 486 4248",
    "sg:postcode":"23452",
    "sg:province":"VA",
    "sg:tags":[
        "eating"
    ],
    "wof:name":"Pizza Hut",
    "wof:placetype":"venue"
},
  "geometry": {"coordinates":[-76.069931,36.844193],"type":"Point"}
}