{
  "type": "Feature",
  "properties": {
    "addr:full":"28 Labelle Ln Stuarts Draft VA 24477",
    "addr:housenumber":"28",
    "addr:postcode":"24477",
    "addr:street":"Labelle Ln",
    "iso:country":"US",
    "sg:address":"28 Labelle Ln",
    "sg:city":"Stuarts Draft",
    "sg:classifiers":[
        {
            "category":"Travel",
            "subcategory":"Travel Agent",
            "type":"Entertainment"
        }
    ],
    "sg:phone":"+1 540 324 0202",
    "sg:postcode":"24477",
    "sg:province":"VA",
    "sg:tags":[
        "agency",
        "bureau"
    ],
    "wof:name":"European Travel Svc LLC",
    "wof:placetype":"venue"
},
  "geometry": {"coordinates":[-79.072045,38.033693],"type":"Point"}
}