{
  "type": "Feature",
  "properties": {
    "addr:full":"128 Rowe Rd Staunton VA 24401",
    "addr:housenumber":"128",
    "addr:postcode":"24401",
    "addr:street":"Rowe Rd",
    "iso:country":"US",
    "sg:address":"128 Rowe Rd",
    "sg:city":"Staunton",
    "sg:classifiers":[
        {
            "category":"Bars & Pubs",
            "type":"Food & Drink"
        }
    ],
    "sg:menulink":"http://www.allmenus.com/va/beverley-manor/222982-cracker-barrel-old-country-store/menu/",
    "sg:phone":"+1 540 885 7550",
    "sg:postcode":"24401",
    "sg:province":"VA",
    "sg:tags":[
        "american",
        "southern"
    ],
    "wof:name":"Cracker Barrel Old Country Store",
    "wof:placetype":"venue"
},
  "geometry": {"coordinates":[-79.03317800000001,38.125393],"type":"Point"}
}