{
  "type": "Feature",
  "properties": {
    "iso:country":"US",
    "sg:address":"11484 Washington Plz W Ste 100",
    "sg:city":"Reston",
    "sg:classifiers":[
        {
            "category":"Government",
            "subcategory":"Office",
            "type":"Public Place"
        }
    ],
    "sg:phone":"+1 703 787 4962",
    "sg:postcode":"20190",
    "sg:province":"VA",
    "sg:tags":[
        "government-united",
        "state"
    ],
    "wof:name":"System Mgt For Humn Svcs Dept",
    "wof:placetype":"venue"
},
  "geometry": {"coordinates":[-77.343222,38.968176],"type":"Point"}
}