{
  "type": "Feature",
  "properties": {
    "addr:full":"4000 Philpott Rd South Boston NC 24592",
    "addr:housenumber":"4000",
    "addr:postcode":"24592",
    "addr:street":"Philpott Rd",
    "iso:country":"US",
    "sg:address":"4000 Philpott Rd",
    "sg:city":"South Boston",
    "sg:classifiers":[
        {
            "category":"Building & Trades",
            "subcategory":"Electrical",
            "type":"Services"
        }
    ],
    "sg:phone":"+1 434 575 7407",
    "sg:postcode":"24592",
    "sg:province":"NC",
    "sg:tags":[
        "electrical",
        "contractor"
    ],
    "wof:name":"Stevens Electric",
    "wof:placetype":"venue"
},
  "geometry": {"coordinates":[-78.946702,36.675732],"type":"Point"}
}