{
  "type": "Feature",
  "properties": {
    "addr:full":"7210a Warwick Blvd Newport News VA 23607",
    "addr:housenumber":"7210a",
    "addr:postcode":"23607",
    "addr:street":"Warwick Blvd",
    "iso:country":"US",
    "sg:address":"7210a Warwick Blvd",
    "sg:city":"Newport News",
    "sg:classifiers":[
        {
            "category":"Restaurant",
            "type":"Food & Drink"
        }
    ],
    "sg:menulink":"http://www.allmenus.com/va/newport-news/42448-star-wok,-chinese-restaurant/menu/",
    "sg:phone":"+1 757 245 6788",
    "sg:postcode":"23607",
    "sg:province":"VA",
    "sg:tags":[
        "asian",
        "chinese"
    ],
    "wof:name":"Star Wok, Chinese Restaurant",
    "wof:placetype":"venue"
},
  "geometry": {"coordinates":[-76.446879,37.012123],"type":"Point"}
}