{
  "type": "Feature",
  "properties": {
    "addr:full":"409 Camp Nine Rd Rustburg VA 24588",
    "addr:housenumber":"409",
    "addr:postcode":"24588",
    "addr:street":"Camp Nine Rd",
    "iso:country":"US",
    "sg:address":"409 Camp Nine Rd",
    "sg:city":"Rustburg",
    "sg:classifiers":[
        {
            "category":"Freight",
            "type":"Transportation"
        }
    ],
    "sg:phone":"+1 434 332 6256",
    "sg:postcode":"24588",
    "sg:province":"VA",
    "wof:name":"Virginia Dept Transportation",
    "wof:placetype":"venue"
},
  "geometry": {"coordinates":[-79.07407499999999,37.26565],"type":"Point"}
}