{
  "type": "Feature",
  "properties": {
    "addr:full":"500 Oscar Loop Newport News VA 23606",
    "addr:housenumber":"500",
    "addr:postcode":"23606",
    "addr:street":"Oscar Loop",
    "iso:country":"US",
    "sg:address":"500 Oscar Loop",
    "sg:city":"Newport News",
    "sg:classifiers":[
        {
            "category":"Real Estate",
            "subcategory":"Real Estate Operator",
            "type":"Services"
        }
    ],
    "sg:phone":"+1 757 595 2141",
    "sg:postcode":"23606",
    "sg:province":"VA",
    "sg:tags":[
        "apartment"
    ],
    "wof:name":"Kingstowne Apartments",
    "wof:placetype":"venue"
},
  "geometry": {"coordinates":[-76.481281,37.079372],"type":"Point"}
}