{
  "type": "Feature",
  "properties": {
    "iso:country":"US",
    "sg:address":"43330 Junction Plz Unit 118",
    "sg:city":"Ashburn",
    "sg:classifiers":[
        {
            "category":"Fast Food",
            "type":"Food & Drink"
        },
        {
            "category":"Restaurant",
            "type":"Food & Drink"
        },
        {
            "category":"Professional",
            "type":"Services"
        }
    ],
    "sg:phone":"+1 703 729 6100",
    "sg:postcode":"20147",
    "sg:province":"VA",
    "sg:tags":[
        "delivery",
        "take",
        "pizza"
    ],
    "sg:website":"http://www.dominospizza.com",
    "wof:name":"Domino's Pizza",
    "wof:placetype":"venue"
},
  "geometry": {"coordinates":[-77.50281,39.036574],"type":"Point"}
}