{
  "type": "Feature",
  "properties": {
    "addr:full":"2496 Old Ivy Rd Charlottesville VA 22903",
    "addr:housenumber":"2496",
    "addr:postcode":"22903",
    "addr:street":"Old Ivy Rd",
    "iso:country":"US",
    "sg:address":"2496 Old Ivy Rd",
    "sg:city":"Charlottesville",
    "sg:classifiers":[
        {
            "category":"Health Services",
            "subcategory":"Health Practitioner",
            "type":"Services"
        }
    ],
    "sg:phone":"+1 434 984 0005",
    "sg:postcode":"22903",
    "sg:province":"VA",
    "wof:name":"Psychtric Alnce of Blue Rdge I",
    "wof:placetype":"venue"
},
  "geometry": {"coordinates":[-78.523538,38.049403],"type":"Point"}
}