{
  "type": "Feature",
  "properties": {
    "iso:country":"US",
    "sg:address":"333 W Cork St",
    "sg:city":"Winchester",
    "sg:classifiers":[
        {
            "category":"Health Services",
            "subcategory":"Clinic",
            "type":"Services"
        }
    ],
    "sg:phone":"+1 540 722 1111",
    "sg:postcode":"22601",
    "sg:province":"VA",
    "wof:name":"Shenandoah Ind Prctice Assciat",
    "wof:placetype":"venue"
},
  "geometry": {"coordinates":[-78.171638,39.183222],"type":"Point"}
}