{
  "type": "Feature",
  "properties": {
    "addr:full":"6508 Tower Dr Alexandria VA 22306",
    "addr:housenumber":"6508",
    "addr:postcode":"22306",
    "addr:street":"Tower Dr",
    "iso:country":"US",
    "sg:address":"6508 Tower Dr",
    "sg:city":"Alexandria",
    "sg:classifiers":[
        {
            "category":"Taxi",
            "type":"Transportation"
        }
    ],
    "sg:phone":"+1 703 768 6991",
    "sg:postcode":"22306",
    "sg:province":"VA",
    "sg:tags":[
        "delivery"
    ],
    "wof:name":"Felicity Delivery Service",
    "wof:placetype":"venue"
},
  "geometry": {"coordinates":[-77.085168,38.776842],"type":"Point"}
}