{
  "type": "Feature",
  "properties": {
    "addr:full":"31220 Camp Rd Hanover VA 23069",
    "addr:housenumber":"31220",
    "addr:postcode":"23069",
    "addr:street":"Camp Rd",
    "iso:country":"US",
    "sg:address":"31220 Camp Rd",
    "sg:city":"Hanover",
    "sg:classifiers":[
        {
            "category":"Government",
            "subcategory":"Office",
            "type":"Public Place"
        }
    ],
    "sg:phone":"+1 804 994 2435",
    "sg:postcode":"23069",
    "sg:province":"VA",
    "sg:tags":[
        "state",
        "program"
    ],
    "wof:name":"Transportation Dept",
    "wof:placetype":"venue"
},
  "geometry": {"coordinates":[-77.3312,37.834801],"type":"Point"}
}