{
  "type": "Feature",
  "properties": {
    "iso:country":"US",
    "sg:address":"2139 Francis Rd",
    "sg:city":"Glen Allen",
    "sg:classifiers":[
        {
            "category":"Building & Trades",
            "subcategory":"Construction",
            "type":"Services"
        }
    ],
    "sg:phone":"+1 804 266 4654",
    "sg:postcode":"23060",
    "sg:province":"VA",
    "sg:tags":[
        "house"
    ],
    "wof:name":"Ra Bracey 3 Constructio",
    "wof:placetype":"venue"
},
  "geometry": {"coordinates":[-77.47719499999999,37.660039],"type":"Point"}
}