{
  "type": "Feature",
  "properties": {
    "addr:full":"311 Captains Point Ln Heathsville VA 22473",
    "addr:housenumber":"311",
    "addr:postcode":"22473",
    "addr:street":"Captains Point Ln",
    "iso:country":"US",
    "sg:address":"311 Captains Point Ln",
    "sg:city":"Heathsville",
    "sg:classifiers":[
        {
            "category":"Organizations",
            "subcategory":"Non-profit Organization",
            "type":"Services"
        }
    ],
    "sg:phone":"+1 804 580 6043",
    "sg:postcode":"22473",
    "sg:province":"VA",
    "sg:tags":[
        "association",
        "social"
    ],
    "wof:name":"National Assoc Retired Fed Emp",
    "wof:placetype":"venue"
},
  "geometry": {"coordinates":[-76.42862700000001,37.879671],"type":"Point"}
}