{
  "type": "Feature",
  "properties": {
    "addr:full":"257 Sadlick Rd Strasburg VA 22657",
    "addr:housenumber":"257",
    "addr:postcode":"22657",
    "addr:street":"Sadlick Rd",
    "iso:country":"US",
    "sg:address":"257 Sadlick Rd",
    "sg:city":"Strasburg",
    "sg:classifiers":[
        {
            "category":"Home & Garden",
            "subcategory":"Garden Supply",
            "type":"Retail Goods"
        }
    ],
    "sg:phone":"+1 540 631 9411",
    "sg:postcode":"22657",
    "sg:province":"VA",
    "sg:tags":[
        "nurseryman"
    ],
    "wof:name":"Crownsville Nursery",
    "wof:placetype":"venue"
},
  "geometry": {"coordinates":[-78.298592,38.976717],"type":"Point"}
}