{
  "type": "Feature",
  "properties": {
    "addr:full":"1780 Big Spring Dr Elliston VA 24087",
    "addr:housenumber":"1780",
    "addr:postcode":"24087",
    "addr:street":"Big Spring Dr",
    "iso:country":"US",
    "sg:address":"1780 Big Spring Dr",
    "sg:city":"Elliston",
    "sg:classifiers":[
        {
            "category":"Travel",
            "subcategory":"Travel Agent",
            "type":"Entertainment"
        }
    ],
    "sg:phone":"+1 540 268 4300",
    "sg:postcode":"24087",
    "sg:province":"VA",
    "sg:tags":[
        "tours",
        "promoter"
    ],
    "wof:name":"Civil War Weekend",
    "wof:placetype":"venue"
},
  "geometry": {"coordinates":[-80.23110800000001,37.218962],"type":"Point"}
}