{
  "type": "Feature",
  "properties": {
    "addr:full":"100 W Jefferson St Falls Church VA 22046",
    "addr:housenumber":"100",
    "addr:postcode":"22046",
    "addr:street":"W Jefferson St",
    "iso:country":"US",
    "sg:address":"100 W Jefferson St",
    "sg:city":"Falls Church",
    "sg:classifiers":[
        {
            "category":"Real Estate",
            "subcategory":"Architect",
            "type":"Services"
        }
    ],
    "sg:phone":"+1 703 536 2488",
    "sg:postcode":"22046",
    "sg:province":"VA",
    "sg:tags":[
        "architectural"
    ],
    "wof:name":"Wieboldt Richard & Assoc Archt",
    "wof:placetype":"venue"
},
  "geometry": {"coordinates":[-77.16567499999999,38.88678],"type":"Point"}
}