{
  "type": "Feature",
  "properties": {
    "iso:country":"US",
    "sg:address":"4233 Sugar Hill Rd",
    "sg:city":"Kenbridge",
    "sg:classifiers":[
        {
            "category":"Freight",
            "type":"Transportation"
        }
    ],
    "sg:phone":"+1 434 676 8478",
    "sg:postcode":"23944",
    "sg:province":"VA",
    "sg:tags":[
        "operator",
        "local",
        "hauling",
        "trucking"
    ],
    "wof:name":"Parrish Trucking Co Inc",
    "wof:placetype":"venue"
},
  "geometry": {"coordinates":[-78.03680199999999,36.930681],"type":"Point"}
}