{
  "type": "Feature",
  "properties": {
    "iso:country":"US",
    "sg:address":"12023 Wakefield Rd",
    "sg:city":"Sedley",
    "sg:classifiers":[
        {
            "category":"Building & Trades",
            "subcategory":"Electrical",
            "type":"Services"
        }
    ],
    "sg:phone":"+1 757 899 7309",
    "sg:postcode":"23878",
    "sg:province":"VA",
    "sg:tags":[
        "electric",
        "contractor"
    ],
    "wof:name":"Robert L Beale Jr Mech Contr",
    "wof:placetype":"venue"
},
  "geometry": {"coordinates":[-77.047755,36.859193],"type":"Point"}
}