{
  "type": "Feature",
  "properties": {
    "addr:full":"5406 Green Glen Ln Alexandria VA 22315",
    "addr:housenumber":"5406",
    "addr:postcode":"22315",
    "addr:street":"Green Glen Ln",
    "iso:country":"US",
    "sg:address":"5406 Green Glen Ln",
    "sg:city":"Alexandria",
    "sg:classifiers":[
        {
            "category":"Retail",
            "subcategory":"Portrait Studio",
            "type":"Services"
        }
    ],
    "sg:phone":"+1 703 924 7288",
    "sg:postcode":"22315",
    "sg:province":"VA",
    "sg:tags":[
        "photo"
    ],
    "wof:name":"Williams Photography",
    "wof:placetype":"venue"
},
  "geometry": {"coordinates":[-77.12788500000001,38.775053],"type":"Point"}
}