{
  "type": "Feature",
  "properties": {
    "iso:country":"US",
    "sg:address":"1802 Augustine Ave",
    "sg:city":"Fredericksburg",
    "sg:classifiers":[
        {
            "category":"Health Services",
            "subcategory":"Clinic",
            "type":"Services"
        }
    ],
    "sg:phone":"+1 540 310 4072",
    "sg:postcode":"22401",
    "sg:province":"VA",
    "sg:tags":[
        "hypnotherapy"
    ],
    "wof:name":"Kilgore Hypnotherapy SOLUTIONS",
    "wof:placetype":"venue"
},
  "geometry": {"coordinates":[-77.480182,38.303649],"type":"Point"}
}