{
  "type": "Feature",
  "properties": {
    "iso:country":"US",
    "sg:address":"2883 Macao Dr",
    "sg:city":"Herndon",
    "sg:classifiers":[
        {
            "category":"Professional",
            "subcategory":"Lawyer & Legal Services",
            "type":"Services"
        }
    ],
    "sg:phone":"+1 703 391 1188",
    "sg:postcode":"20171",
    "sg:province":"VA",
    "wof:name":"Nelson Blitz Associates PLC",
    "wof:placetype":"venue"
},
  "geometry": {"coordinates":[-77.37484600000001,38.913613],"type":"Point"}
}