{
  "type": "Feature",
  "properties": {
    "addr:full":"7732 Donegan Dr Manassas VA 20109",
    "addr:postcode":"7732;20109",
    "addr:street":"Donegan Dr",
    "iso:country":"US",
    "sg:address":"7732 Donegan Dr",
    "sg:city":"Manassas",
    "sg:classifiers":[
        {
            "category":"Real Estate",
            "subcategory":"Real Estate Agent",
            "type":"Services"
        }
    ],
    "sg:phone":"+1 703 365 8444",
    "sg:postcode":"20109",
    "sg:province":"VA",
    "wof:name":"Realty America",
    "wof:placetype":"venue"
},
  "geometry": {"coordinates":[-77.516769,38.789532],"type":"Point"}
}