{
  "type": "Feature",
  "properties": {
    "addr:full":"9401 Peabody St Manassas VA 20110",
    "addr:housenumber":"9401",
    "addr:postcode":"20110",
    "addr:street":"Peabody St",
    "iso:country":"US",
    "sg:address":"9401 Peabody St",
    "sg:city":"Manassas",
    "sg:classifiers":[
        {
            "category":"Manufacturing",
            "subcategory":"Printing",
            "type":"Manufacturing & Wholesale Goods"
        }
    ],
    "sg:phone":"+1 703 335 9093",
    "sg:postcode":"20110",
    "sg:province":"VA",
    "sg:tags":[
        "screen"
    ],
    "wof:name":"Leading Edge",
    "wof:placetype":"venue"
},
  "geometry": {"coordinates":[-77.477183,38.751158],"type":"Point"}
}