{
  "type": "Feature",
  "properties": {
    "iso:country":"US",
    "sg:address":"6101 Straightstone Rd",
    "sg:city":"Long Island",
    "sg:classifiers":[
        {
            "category":"Organizations",
            "subcategory":"Religious Organization",
            "type":"Services"
        }
    ],
    "sg:phone":"+1 434 335 5700",
    "sg:postcode":"24569",
    "sg:province":"VA",
    "wof:name":"Staunton Baptist Church",
    "wof:placetype":"venue"
},
  "geometry": {"coordinates":[-79.134919,37.030607],"type":"Point"}
}