{
  "type": "Feature",
  "properties": {
    "addr:full":"1699 Carl D Silver Pkwy Fredericksburg VA 22401",
    "addr:housenumber":"1699",
    "addr:postcode":"22401",
    "addr:street":"Carl D Silver Pkwy",
    "iso:country":"US",
    "sg:address":"1699 Carl D Silver Pkwy",
    "sg:city":"Fredericksburg",
    "sg:classifiers":[
        {
            "category":"Restaurant",
            "type":"Food & Drink"
        }
    ],
    "sg:phone":"+1 540 371 4536",
    "sg:postcode":"22401",
    "sg:province":"VA",
    "wof:name":"Long John Silver's",
    "wof:placetype":"venue"
},
  "geometry": {"coordinates":[-77.509306,38.305282],"type":"Point"}
}