{
  "type": "Feature",
  "properties": {
    "addr:full":"1400 Independence Way Charlottesville VA 22902",
    "addr:housenumber":"1400",
    "addr:postcode":"22902",
    "addr:street":"Independence Way",
    "iso:country":"US",
    "sg:address":"1400 Independence Way",
    "sg:city":"Charlottesville",
    "sg:classifiers":[
        {
            "category":"Education",
            "subcategory":"School",
            "type":"Public Place"
        }
    ],
    "sg:phone":"+1 434 244 3100",
    "sg:postcode":"22902",
    "sg:province":"VA",
    "wof:name":"Monticello High School",
    "wof:placetype":"venue"
},
  "geometry": {"coordinates":[-78.489475,37.998632],"type":"Point"}
}