{
  "type": "Feature",
  "properties": {
    "addr:full":"506 Tina Dr Henrico VA 23075",
    "addr:housenumber":"506",
    "addr:postcode":"23075",
    "addr:street":"Tina Dr",
    "iso:country":"US",
    "sg:address":"506 Tina Dr",
    "sg:city":"Henrico",
    "sg:classifiers":[
        {
            "category":"Shopping",
            "subcategory":"Beauty & Cosmetics",
            "type":"Retail Goods"
        }
    ],
    "sg:phone":"+1 804 737 2066",
    "sg:postcode":"23075",
    "sg:province":"VA",
    "sg:tags":[
        "salons-equipment",
        "supply"
    ],
    "wof:name":"All About You Beauty Supply Ll",
    "wof:placetype":"venue"
},
  "geometry": {"coordinates":[-77.34046499999999,37.540858],"type":"Point"}
}