{
  "type": "Feature",
  "properties": {
    "addr:full":"605 Austin Ln Herndon VA 20170",
    "addr:housenumber":"605",
    "addr:postcode":"20170",
    "addr:street":"Austin Ln",
    "iso:country":"US",
    "sg:address":"605 Austin Ln",
    "sg:city":"Herndon",
    "sg:classifiers":[
        {
            "category":"Professional",
            "subcategory":"Art Services",
            "type":"Services"
        }
    ],
    "sg:phone":"+1 703 464 0550",
    "sg:postcode":"20170",
    "sg:province":"VA",
    "sg:tags":[
        "commercial",
        "design"
    ],
    "wof:name":"Designer For A Day",
    "wof:placetype":"venue"
},
  "geometry": {"coordinates":[-77.385183,38.963607],"type":"Point"}
}