{
  "type": "Feature",
  "properties": {
    "addr:full":"1235 Featherstone Rd Woodbridge VA 22191",
    "addr:housenumber":"1235",
    "addr:postcode":"22191",
    "addr:street":"Featherstone Rd",
    "iso:country":"US",
    "sg:address":"1235 Featherstone Rd",
    "sg:city":"Woodbridge",
    "sg:classifiers":[
        {
            "category":"Home & Garden",
            "subcategory":"Building Materials",
            "type":"Retail Goods"
        },
        {
            "category":"Building & Trades",
            "subcategory":"Construction",
            "type":"Services"
        }
    ],
    "sg:phone":"+1 703 496 4024",
    "sg:postcode":"22191",
    "sg:province":"VA",
    "sg:tags":[
        "tile-contractors"
    ],
    "sg:website":"http://www.pmgranite.com",
    "wof:name":"Potomac Marble&Granite",
    "wof:placetype":"venue"
},
  "geometry": {"coordinates":[-77.254453,38.630696],"type":"Point"}
}