{
  "type": "Feature",
  "properties": {
    "addr:full":"5547 E Virginia Beach Blvd Norfolk VA 23502",
    "addr:housenumber":"5547",
    "addr:postcode":"23502",
    "addr:street":"E Virginia Beach Blvd",
    "iso:country":"US",
    "sg:address":"5547 E Virginia Beach Blvd",
    "sg:city":"Norfolk",
    "sg:classifiers":[
        {
            "category":"Professional",
            "subcategory":"Advertising",
            "type":"Services"
        }
    ],
    "sg:phone":"+1 757 461 1355",
    "sg:postcode":"23502",
    "sg:province":"VA",
    "sg:website":"www.adamsoutdoor.com",
    "wof:name":"Adams Outdoor Advertising",
    "wof:placetype":"venue"
},
  "geometry": {"coordinates":[-76.21641200000001,36.855928],"type":"Point"}
}