{
  "type": "Feature",
  "properties": {
    "iso:country":"US",
    "sg:address":"1711 Montafia Ln",
    "sg:city":"Vienna",
    "sg:classifiers":[
        {
            "category":"Wholesale",
            "subcategory":"Apparel",
            "type":"Manufacturing & Wholesale Goods"
        }
    ],
    "sg:phone":"+1 703 281 3330",
    "sg:postcode":"22182",
    "sg:province":"VA",
    "sg:tags":[
        "distributor",
        "t",
        "for"
    ],
    "wof:name":"Arbre Group LLC",
    "wof:placetype":"venue"
},
  "geometry": {"coordinates":[-77.293082,38.938227],"type":"Point"}
}