{
  "type": "Feature",
  "properties": {
    "addr:full":"2742 Mary Linda Ave NE Roanoke VA 24012",
    "addr:housenumber":"2742",
    "addr:postcode":"24012",
    "addr:street":"Mary Linda Ave Ne",
    "iso:country":"US",
    "sg:address":"2742 Mary Linda Ave NE",
    "sg:city":"Roanoke",
    "sg:classifiers":[
        {
            "category":"Building & Trades",
            "subcategory":"Construction",
            "type":"Services"
        }
    ],
    "sg:phone":"+1 540 982 1403",
    "sg:postcode":"24012",
    "sg:province":"VA",
    "wof:name":"Irby Construction Company",
    "wof:placetype":"venue"
},
  "geometry": {"coordinates":[-79.90780700000001,37.299887],"type":"Point"}
}