{
  "type": "Feature",
  "properties": {
    "iso:country":"US",
    "sg:address":"4415 Carrico Dr",
    "sg:city":"Annandale",
    "sg:classifiers":[
        {
            "category":"Building & Trades",
            "subcategory":"Construction",
            "type":"Services"
        }
    ],
    "sg:phone":"+1 703 354 7727",
    "sg:postcode":"22003",
    "sg:province":"VA",
    "sg:tags":[
        "painter"
    ],
    "wof:name":"United Painting Contractors",
    "wof:placetype":"venue"
},
  "geometry": {"coordinates":[-77.187894,38.827161],"type":"Point"}
}