{
  "type": "Feature",
  "properties": {
    "iso:country":"US",
    "sg:address":"606 7th St",
    "sg:city":"Altavista",
    "sg:classifiers":[
        {
            "category":"Retail",
            "subcategory":"Auto Rental",
            "type":"Services"
        }
    ],
    "sg:phone":"+1 434 369 1238",
    "sg:postcode":"24517",
    "sg:province":"VA",
    "sg:tags":[
        "hardware",
        "truck"
    ],
    "wof:name":"U-Haul",
    "wof:placetype":"venue"
},
  "geometry": {"coordinates":[-79.289039,37.110611],"type":"Point"}
}