{
  "type": "Feature",
  "properties": {
    "iso:country":"US",
    "sg:address":"5542 Valley Dr",
    "sg:city":"Roanoke",
    "sg:classifiers":[
        {
            "category":"Real Estate",
            "subcategory":"Architect",
            "type":"Services"
        }
    ],
    "sg:phone":"+1 540 989 9555",
    "sg:postcode":"24018",
    "sg:province":"VA",
    "sg:tags":[
        "architectural"
    ],
    "wof:name":"Arcitchtural Design Consulting",
    "wof:placetype":"venue"
},
  "geometry": {"coordinates":[-80.037088,37.257929],"type":"Point"}
}