{
  "type": "Feature",
  "properties": {
    "iso:country":"US",
    "sg:address":"1900 Opitz Blvd Ste C",
    "sg:city":"Woodbridge",
    "sg:classifiers":[
        {
            "category":"Health Services",
            "subcategory":"Doctor",
            "type":"Services"
        },
        {
            "category":"Health Services",
            "subcategory":"Dentist",
            "type":"Services"
        }
    ],
    "sg:phone":"+1 703 494 0820",
    "sg:postcode":"22191",
    "sg:province":"VA",
    "sg:tags":[
        "dentists-oral",
        "physician",
        "maxillofacial",
        "surgeons",
        "surgery",
        "oral"
    ],
    "wof:name":"Wayne G Rasmussen Dds Pc",
    "wof:placetype":"venue"
},
  "geometry": {"coordinates":[-77.273403,38.634719],"type":"Point"}
}