{
  "type": "Feature",
  "properties": {
    "iso:country":"US",
    "sg:address":"5858 Linden Creek Ct",
    "sg:city":"Centreville",
    "sg:classifiers":[
        {
            "category":"Professional",
            "type":"Services"
        }
    ],
    "sg:phone":"+1 703 818 1740",
    "sg:postcode":"20120",
    "sg:province":"VA",
    "wof:name":"Swanson Soundworks",
    "wof:placetype":"venue"
},
  "geometry": {"coordinates":[-77.46001800000001,38.849223],"type":"Point"}
}