{
  "type": "Feature",
  "properties": {
    "addr:full":"1408 Pissarro Cir Virginia Beach VA 23456",
    "addr:housenumber":"1408",
    "addr:postcode":"23456",
    "addr:street":"Pissarro Cir",
    "iso:country":"US",
    "sg:address":"1408 Pissarro Cir",
    "sg:city":"Virginia Beach",
    "sg:classifiers":[
        {
            "category":"Real Estate",
            "subcategory":"Real Estate Agent",
            "type":"Services"
        }
    ],
    "sg:phone":"+1 757 467 4732",
    "sg:postcode":"23456",
    "sg:province":"VA",
    "wof:name":"Benner Enterprises Inc",
    "wof:placetype":"venue"
},
  "geometry": {"coordinates":[-76.128725,36.789717],"type":"Point"}
}