{
  "type": "Feature",
  "properties": {
    "addr:full":"3910 Desoto Ct Woodbridge VA 22193",
    "addr:housenumber":"3910",
    "addr:postcode":"22193",
    "addr:street":"Desoto Ct",
    "iso:country":"US",
    "sg:address":"3910 Desoto Ct",
    "sg:city":"Woodbridge",
    "sg:classifiers":[
        {
            "category":"Building & Trades",
            "subcategory":"Construction",
            "type":"Services"
        }
    ],
    "sg:phone":"+1 703 670 5969",
    "sg:postcode":"22193",
    "sg:province":"VA",
    "sg:tags":[
        "home",
        "improvement"
    ],
    "wof:name":"Farria's Home Improvement",
    "wof:placetype":"venue"
},
  "geometry": {"coordinates":[-77.32759799999999,38.63708],"type":"Point"}
}