{
  "type": "Feature",
  "properties": {
    "iso:country":"US",
    "sg:address":"3 Page Pl",
    "sg:city":"Poquoson",
    "sg:classifiers":[
        {
            "category":"Organizations",
            "subcategory":"Community Association",
            "type":"Services"
        }
    ],
    "sg:phone":"+1 757 868 8792",
    "sg:postcode":"23662",
    "sg:province":"VA",
    "wof:name":"Page Place Homeowners Assn",
    "wof:placetype":"venue"
},
  "geometry": {"coordinates":[-76.381694,37.126939],"type":"Point"}
}