{
  "type": "Feature",
  "properties": {
    "addr:full":"123 S Muhlenburg St Woodstock VA 22664",
    "addr:housenumber":"123",
    "addr:postcode":"22664",
    "addr:street":"S Muhlenburg St",
    "iso:country":"US",
    "sg:address":"123 S Muhlenburg St",
    "sg:city":"Woodstock",
    "sg:classifiers":[
        {
            "category":"Insurance",
            "subcategory":"Insurance Agent",
            "type":"Services"
        }
    ],
    "sg:phone":"+1 540 459 2032",
    "sg:postcode":"22664",
    "sg:province":"VA",
    "sg:tags":[
        "carrier",
        "title"
    ],
    "wof:name":"Woodstock Title Corp",
    "wof:placetype":"venue"
},
  "geometry": {"coordinates":[-78.507171,38.881854],"type":"Point"}
}