{
  "type": "Feature",
  "properties": {
    "addr:full":"515 York River Ln Newport News VA 23602",
    "addr:housenumber":"515",
    "addr:postcode":"23602",
    "addr:street":"York River Ln",
    "iso:country":"US",
    "sg:address":"515 York River Ln",
    "sg:city":"Newport News",
    "sg:classifiers":[
        {
            "category":"Building & Trades",
            "subcategory":"Plumbing",
            "type":"Services"
        }
    ],
    "sg:phone":"+1 757 249 0869",
    "sg:postcode":"23602",
    "sg:province":"VA",
    "sg:tags":[
        "contractor"
    ],
    "wof:name":"Princess Heating & AC",
    "wof:placetype":"venue"
},
  "geometry": {"coordinates":[-76.50955,37.117302],"type":"Point"}
}