{
  "type": "Feature",
  "properties": {
    "addr:full":"8600 Glen Myrtle Ave Norfolk VA 23505",
    "addr:housenumber":"8600",
    "addr:postcode":"23505",
    "addr:street":"Glen Myrtle Ave",
    "iso:country":"US",
    "sg:address":"8600 Glen Myrtle Ave",
    "sg:city":"Norfolk",
    "sg:classifiers":[
        {
            "category":"Professional",
            "subcategory":"Business Services",
            "type":"Services"
        }
    ],
    "sg:phone":"+1 757 575 2922",
    "sg:postcode":"23505",
    "sg:province":"VA",
    "sg:tags":[
        "engraver"
    ],
    "wof:name":"Francis Childs",
    "wof:placetype":"venue"
},
  "geometry": {"coordinates":[-76.312743,36.930314],"type":"Point"}
}