{
  "type": "Feature",
  "properties": {
    "iso:country":"US",
    "sg:address":"139 Victory Ln",
    "sg:city":"Max Meadows",
    "sg:classifiers":[
        {
            "category":"Autos & Motor Vehicles",
            "subcategory":"Fuel & Gas Station",
            "type":"Retail Goods"
        }
    ],
    "sg:phone":"+1 276 637 4115",
    "sg:postcode":"24326",
    "sg:province":"VA",
    "sg:tags":[
        "plaza",
        "truck",
        "stops"
    ],
    "wof:name":"Truck Fuel Island",
    "wof:placetype":"venue"
},
  "geometry": {"coordinates":[-81.17027,36.732227],"type":"Point"}
}