{
  "type": "Feature",
  "properties": {
    "addr:full":"1401 Greenbrier Pkwy Chesapeake VA 23320",
    "addr:housenumber":"1401",
    "addr:postcode":"23320",
    "addr:street":"Greenbrier Pkwy",
    "iso:country":"US",
    "sg:address":"1401 Greenbrier Pkwy",
    "sg:city":"Chesapeake",
    "sg:classifiers":[
        {
            "category":"Shopping",
            "subcategory":"Clothing, Apparel, & Fashions",
            "type":"Retail Goods"
        }
    ],
    "sg:phone":"+1 757 424 1131",
    "sg:postcode":"23320",
    "sg:province":"VA",
    "sg:tags":[
        "apparel",
        "women's"
    ],
    "sg:website":"http://www.christopherandbanks.com",
    "wof:name":"Christopher & Banks",
    "wof:placetype":"venue"
},
  "geometry": {"coordinates":[-76.23018399999999,36.776457],"type":"Point"}
}