{
  "type": "Feature",
  "properties": {
    "iso:country":"US",
    "sg:address":"8134 Wellington Rd",
    "sg:city":"Alexandria",
    "sg:classifiers":[
        {
            "category":"Professional",
            "type":"Services"
        }
    ],
    "sg:phone":"+1 703 765 7664",
    "sg:postcode":"22308",
    "sg:province":"VA",
    "wof:name":"Power Concepts Inc Maryland",
    "wof:placetype":"venue"
},
  "geometry": {"coordinates":[-77.050404,38.739031],"type":"Point"}
}