{
  "type": "Feature",
  "properties": {
    "addr:full":"5491 Lighthouse Ln Burke VA 22015",
    "addr:housenumber":"5491",
    "addr:postcode":"22015",
    "addr:street":"Lighthouse Ln",
    "iso:country":"US",
    "sg:address":"5491 Lighthouse Ln",
    "sg:city":"Burke",
    "sg:classifiers":[
        {
            "category":"Organizations",
            "subcategory":"Membership Organization",
            "type":"Services"
        }
    ],
    "sg:phone":"+1 703 425 0776",
    "sg:postcode":"22015",
    "sg:province":"VA",
    "wof:name":"National Assn Retired Federal",
    "wof:placetype":"venue"
},
  "geometry": {"coordinates":[-77.273324,38.801916],"type":"Point"}
}