{
  "type": "Feature",
  "properties": {
    "iso:country":"US",
    "sg:address":"4660 Pouncey Tract Rd",
    "sg:city":"Glen Allen",
    "sg:classifiers":[
        {
            "category":"Retail",
            "subcategory":"Animal Services",
            "type":"Services"
        }
    ],
    "sg:phone":"+1 804 364 1944",
    "sg:postcode":"23059",
    "sg:province":"VA",
    "sg:tags":[
        "shelter"
    ],
    "wof:name":"Friends United With-Richmond",
    "wof:placetype":"venue"
},
  "geometry": {"coordinates":[-77.612917,37.661938],"type":"Point"}
}