{
  "type": "Feature",
  "properties": {
    "addr:full":"2661 Governor Harrison Pkwy Brodnax VA 23920",
    "addr:housenumber":"2661",
    "addr:postcode":"23920",
    "addr:street":"Governor Harrison Pkwy",
    "iso:country":"US",
    "sg:address":"2661 Governor Harrison Pkwy",
    "sg:city":"Brodnax",
    "sg:classifiers":[
        {
            "category":"Manufacturing",
            "subcategory":"Lumber",
            "type":"Manufacturing & Wholesale Goods"
        }
    ],
    "sg:phone":"+1 434 729 2852",
    "sg:postcode":"23920",
    "sg:province":"VA",
    "sg:tags":[
        "planing",
        "mills",
        "sawmill"
    ],
    "wof:name":"Brodnax Lumber Co",
    "wof:placetype":"venue"
},
  "geometry": {"coordinates":[-77.99011400000001,36.711754],"type":"Point"}
}