{
  "type": "Feature",
  "properties": {
    "iso:country":"US",
    "sg:address":"6210 Seven Corners Center",
    "sg:city":"Falls Church",
    "sg:classifiers":[
        {
            "category":"Home & Garden",
            "subcategory":"Building Materials",
            "type":"Retail Goods"
        }
    ],
    "sg:phone":"+1 703 534 9580",
    "sg:postcode":"22044",
    "sg:province":"VA",
    "wof:name":"Home Depot",
    "wof:placetype":"venue"
},
  "geometry": {"coordinates":[-77.149597,38.868764],"type":"Point"}
}