{
  "type": "Feature",
  "properties": {
    "addr:full":"5005 Columbia Pike Arlington VA 22204",
    "addr:housenumber":"5005",
    "addr:postcode":"22204",
    "addr:street":"Columbia Pike",
    "iso:country":"US",
    "sg:address":"5005 Columbia Pike",
    "sg:city":"Arlington",
    "sg:classifiers":[
        {
            "category":"Restaurant",
            "type":"Food & Drink"
        }
    ],
    "sg:menulink":"http://www.allmenus.com/va/arlington/188072-mcdonalds/menu/",
    "sg:phone":"+1 703 820 9042",
    "sg:postcode":"22204",
    "sg:province":"VA",
    "sg:tags":[
        "burger",
        "american"
    ],
    "wof:name":"McDonald's",
    "wof:placetype":"venue"
},
  "geometry": {"coordinates":[-77.112256,38.855904],"type":"Point"}
}