{
  "type": "Feature",
  "properties": {
    "iso:country":"US",
    "sg:address":"759 J Clyde Morris Blvd",
    "sg:city":"Newport News",
    "sg:classifiers":[
        {
            "category":"Shopping",
            "subcategory":"Computers & Home Electronics",
            "type":"Retail Goods"
        }
    ],
    "sg:phone":"+1 757 599 7900",
    "sg:postcode":"23601",
    "sg:province":"VA",
    "sg:tags":[
        "high",
        "equipment",
        "fidelity",
        "electronic",
        "supply"
    ],
    "sg:website":"www.soundapproach.com",
    "wof:name":"Sound Approach",
    "wof:placetype":"venue"
},
  "geometry": {"coordinates":[-76.46167,37.079893],"type":"Point"}
}