{
  "type": "Feature",
  "properties": {
    "iso:country":"US",
    "sg:address":"7011 Manchester Blvd",
    "sg:city":"Alexandria",
    "sg:classifiers":[
        {
            "category":"Personal",
            "type":"Services"
        }
    ],
    "sg:phone":"+1 703 922 7174",
    "sg:postcode":"22301",
    "sg:province":"VA",
    "sg:tags":[
        "mover"
    ],
    "sg:website":"www.pakmail.com",
    "wof:name":"Pak Mail",
    "wof:placetype":"venue"
},
  "geometry": {"coordinates":[-77.059601,38.820301],"type":"Point"}
}