{
  "type": "Feature",
  "properties": {
    "addr:full":"317 Bank St Franklin VA 23890",
    "addr:housenumber":"317",
    "addr:postcode":"23890",
    "addr:street":"Bank St",
    "iso:country":"US",
    "sg:address":"317 Bank St",
    "sg:city":"Franklin",
    "sg:classifiers":[
        {
            "category":"Personal",
            "subcategory":"Beauty Salon",
            "type":"Services"
        }
    ],
    "sg:phone":"+1 757 516 2990",
    "sg:postcode":"23890",
    "sg:province":"VA",
    "wof:name":"Laura's Nail & Hair Salon",
    "wof:placetype":"venue"
},
  "geometry": {"coordinates":[-77.08935,37.025885],"type":"Point"}
}