{
  "type": "Feature",
  "properties": {
    "addr:full":"6490 Vinson Ln Dublin VA 24084",
    "addr:housenumber":"6490",
    "addr:postcode":"24084",
    "addr:street":"Vinson Ln",
    "iso:country":"US",
    "sg:address":"6490 Vinson Ln",
    "sg:city":"Dublin",
    "sg:phone":"+1 540 980 4913",
    "sg:postcode":"24084",
    "sg:province":"VA",
    "sg:tags":[
        "farm",
        "field",
        "crop"
    ],
    "wof:name":"Joe Worrell Farm",
    "wof:placetype":"venue"
},
  "geometry": {"coordinates":[-80.766479,37.132319],"type":"Point"}
}