{
  "type": "Feature",
  "properties": {
    "iso:country":"US",
    "sg:address":"6310 Dunman Way",
    "sg:city":"Alexandria",
    "sg:classifiers":[
        {
            "category":"Professional",
            "subcategory":"Management & Consulting",
            "type":"Services"
        }
    ],
    "sg:phone":"+1 703 924 9040",
    "sg:postcode":"22315",
    "sg:province":"VA",
    "sg:tags":[
        "marketing",
        "consultant"
    ],
    "wof:name":"M & C Group",
    "wof:placetype":"venue"
},
  "geometry": {"coordinates":[-77.127404,38.779339],"type":"Point"}
}