{
  "type": "Feature",
  "properties": {
    "iso:country":"US",
    "sg:address":"701 12th St S",
    "sg:city":"Arlington",
    "sg:classifiers":[
        {
            "category":"Professional",
            "subcategory":"Business Services",
            "type":"Services"
        }
    ],
    "sg:phone":"+1 703 418 2450",
    "sg:postcode":"22202",
    "sg:province":"VA",
    "wof:name":"Business Opportunities",
    "wof:placetype":"venue"
},
  "geometry": {"coordinates":[-77.058088,38.862913],"type":"Point"}
}