{
  "type": "Feature",
  "properties": {
    "addr:full":"145 Broadview Ln Woodstock VA 22664",
    "addr:housenumber":"145",
    "addr:postcode":"22664",
    "addr:street":"Broadview Ln",
    "iso:country":"US",
    "sg:address":"145 Broadview Ln",
    "sg:city":"Woodstock",
    "sg:classifiers":[
        {
            "category":"Professional",
            "type":"Services"
        }
    ],
    "sg:phone":"+1 540 459 5513",
    "sg:postcode":"22664",
    "sg:province":"VA",
    "sg:tags":[
        "water",
        "analysis"
    ],
    "wof:name":"Woodstock Water Treatment Plnt",
    "wof:placetype":"venue"
},
  "geometry": {"coordinates":[-78.51067399999999,38.864704],"type":"Point"}
}