{
  "type": "Feature",
  "properties": {
    "iso:country":"US",
    "sg:address":"21264 Battle Hill Dr",
    "sg:city":"Bristol",
    "sg:classifiers":[
        {
            "category":"Education",
            "subcategory":"School",
            "type":"Public Place"
        }
    ],
    "sg:phone":"+1 276 676 2017",
    "sg:postcode":"24202",
    "sg:province":"VA",
    "wof:name":"John S Battle High School",
    "wof:placetype":"venue"
},
  "geometry": {"coordinates":[-82.102957,36.643231],"type":"Point"}
}