{
  "type": "Feature",
  "properties": {
    "addr:full":"201 Henry St Ashland VA 23005",
    "addr:housenumber":"201",
    "addr:postcode":"23005",
    "addr:street":"Henry St",
    "iso:country":"US",
    "sg:address":"201 Henry St",
    "sg:city":"Ashland",
    "sg:classifiers":[
        {
            "category":"Organizations",
            "subcategory":"Religious Organization",
            "type":"Services"
        }
    ],
    "sg:phone":"+1 804 798 7224",
    "sg:postcode":"23005",
    "sg:province":"VA",
    "sg:tags":[
        "church"
    ],
    "wof:name":"Duncan Memorial United Mthdst",
    "wof:placetype":"venue"
},
  "geometry": {"coordinates":[-77.477856,37.760577],"type":"Point"}
}