{
  "type": "Feature",
  "properties": {
    "iso:country":"US",
    "sg:address":"7 Elliewood Ave",
    "sg:city":"Charlottesville",
    "sg:classifiers":[
        {
            "category":"Professional",
            "subcategory":"Management & Consulting",
            "type":"Services"
        }
    ],
    "sg:phone":"+1 434 244 9700",
    "sg:postcode":"22903",
    "sg:province":"VA",
    "sg:tags":[
        "consultant"
    ],
    "wof:name":"Equalnox Consulting",
    "wof:placetype":"venue"
},
  "geometry": {"coordinates":[-78.500309,38.03682],"type":"Point"}
}