{
  "type": "Feature",
  "properties": {
    "addr:full":"261 Bethany Hill Dr Winchester VA 22603",
    "addr:housenumber":"261",
    "addr:postcode":"22603",
    "addr:street":"Bethany Hill Dr",
    "iso:country":"US",
    "sg:address":"261 Bethany Hill Dr",
    "sg:city":"Winchester",
    "sg:classifiers":[
        {
            "category":"Social Services",
            "type":"Services"
        }
    ],
    "sg:phone":"+1 540 665 6418",
    "sg:postcode":"22603",
    "sg:province":"VA",
    "sg:tags":[
        "mission"
    ],
    "wof:name":"Outreach To Asian Nationals",
    "wof:placetype":"venue"
},
  "geometry": {"coordinates":[-78.23419800000001,39.259359],"type":"Point"}
}