{
  "type": "Feature",
  "properties": {
    "iso:country":"US",
    "sg:address":"5545 Limerick Ln",
    "sg:city":"Virginia Beach",
    "sg:classifiers":[
        {
            "category":"Health Services",
            "subcategory":"Chiropractor",
            "type":"Services"
        }
    ],
    "sg:phone":"+1 757 233 0949",
    "sg:postcode":"23455",
    "sg:province":"VA",
    "wof:name":"Eccher Family Chiropractic",
    "wof:placetype":"venue"
},
  "geometry": {"coordinates":[-76.17474900000001,36.904226],"type":"Point"}
}