{
  "type": "Feature",
  "properties": {
    "iso:country":"US",
    "sg:address":"308 Washington Ave",
    "sg:city":"Colonial Beach",
    "sg:classifiers":[
        {
            "category":"Shopping",
            "subcategory":"Gifts & Souvenirs",
            "type":"Retail Goods"
        }
    ],
    "sg:phone":"+1 804 224 2089",
    "sg:postcode":"22443",
    "sg:province":"VA",
    "sg:tags":[
        "book"
    ],
    "wof:name":"Potomac Accents",
    "wof:placetype":"venue"
},
  "geometry": {"coordinates":[-76.96357999999999,38.253083],"type":"Point"}
}