{
  "type": "Feature",
  "properties": {
    "addr:full":"2847 N Clarendon Blvd Arlington VA 22201",
    "addr:housenumber":"2847",
    "addr:postcode":"22201",
    "addr:street":"N Clarendon Blvd",
    "iso:country":"US",
    "sg:address":"2847 N Clarendon Blvd",
    "sg:city":"Arlington",
    "sg:classifiers":[
        {
            "category":"Shopping",
            "subcategory":"Used Merchandise",
            "type":"Retail Goods"
        }
    ],
    "sg:phone":"+1 703 816 0245",
    "sg:postcode":"22201",
    "sg:province":"VA",
    "sg:tags":[
        "consulting",
        "business"
    ],
    "wof:name":"Bowhe & Peare LLC",
    "wof:placetype":"venue"
},
  "geometry": {"coordinates":[-77.092521,38.888205],"type":"Point"}
}