{
  "type": "Feature",
  "properties": {
    "addr:full":"2 Pidgeon Hill Dr Sterling VA 20165",
    "addr:housenumber":"2",
    "addr:postcode":"20165",
    "addr:street":"Pidgeon Hill Dr",
    "iso:country":"US",
    "sg:address":"2 Pidgeon Hill Dr",
    "sg:city":"Sterling",
    "sg:classifiers":[
        {
            "category":"Health Services",
            "subcategory":"Doctor",
            "type":"Services"
        }
    ],
    "sg:phone":"+1 703 450 8700",
    "sg:postcode":"20165",
    "sg:province":"VA",
    "sg:tags":[
        "clinic",
        "medical"
    ],
    "wof:name":"Jeffrey M Schulman MD",
    "wof:placetype":"venue"
},
  "geometry": {"coordinates":[-77.41407,39.038517],"type":"Point"}
}