{
  "type": "Feature",
  "properties": {
    "addr:full":"11901 Longstreet Dr Spotsylvania VA 22551",
    "addr:housenumber":"11901",
    "addr:postcode":"22551",
    "addr:street":"Longstreet Dr",
    "iso:country":"US",
    "sg:address":"11901 Longstreet Dr",
    "sg:city":"Spotsylvania",
    "sg:classifiers":[
        {
            "category":"Real Estate",
            "subcategory":"Real Estate Operator",
            "type":"Services"
        }
    ],
    "sg:phone":"+1 540 972 0400",
    "sg:postcode":"22551",
    "sg:province":"VA",
    "sg:tags":[
        "building",
        "nonresidential"
    ],
    "wof:name":"Fawn Lake Real Estate",
    "wof:placetype":"venue"
},
  "geometry": {"coordinates":[-77.71271900000001,38.281846],"type":"Point"}
}