{
  "type": "Feature",
  "properties": {
    "addr:full":"1916 Centerville Tpke Virginia Beach VA 23464",
    "addr:housenumber":"1916",
    "addr:postcode":"23464",
    "addr:street":"Centerville Tpke",
    "iso:country":"US",
    "sg:address":"1916 Centerville Tpke",
    "sg:city":"Virginia Beach",
    "sg:classifiers":[
        {
            "category":"Restaurant",
            "type":"Food & Drink"
        }
    ],
    "sg:phone":"+1 757 479 1900",
    "sg:postcode":"23464",
    "sg:province":"VA",
    "wof:name":"Sonic Drive-In",
    "wof:placetype":"venue"
},
  "geometry": {"coordinates":[-76.19210099999999,36.780359],"type":"Point"}
}