{
  "type": "Feature",
  "properties": {
    "addr:full":"2793 Virginia Ave Narrows VA 24124",
    "addr:housenumber":"2793",
    "addr:postcode":"24124",
    "addr:street":"Virginia Ave",
    "iso:country":"US",
    "sg:address":"2793 Virginia Ave",
    "sg:city":"Narrows",
    "sg:classifiers":[
        {
            "category":"Autos & Motor Vehicles",
            "subcategory":"Automobile Sales",
            "type":"Retail Goods"
        }
    ],
    "sg:phone":"+1 540 726 8333",
    "sg:postcode":"24124",
    "sg:province":"VA",
    "sg:tags":[
        "car",
        "dealer"
    ],
    "wof:name":"Lee Hy Motors",
    "wof:placetype":"venue"
},
  "geometry": {"coordinates":[-80.799145,37.336081],"type":"Point"}
}