{
  "type": "Feature",
  "properties": {
    "iso:country":"US",
    "sg:address":"3449 S Utah St",
    "sg:city":"Arlington",
    "sg:classifiers":[
        {
            "category":"Professional",
            "subcategory":"Business Services",
            "type":"Services"
        }
    ],
    "sg:phone":"+1 703 998 2308",
    "sg:postcode":"22206",
    "sg:province":"VA",
    "wof:name":"Social Technologies",
    "wof:placetype":"venue"
},
  "geometry": {"coordinates":[-77.088925,38.832627],"type":"Point"}
}