{
  "type": "Feature",
  "properties": {
    "addr:full":"1069 Gershwin Ct Virginia Beach VA 23454",
    "addr:housenumber":"1069",
    "addr:postcode":"23454",
    "addr:street":"Gershwin Ct",
    "iso:country":"US",
    "sg:address":"1069 Gershwin Ct",
    "sg:city":"Virginia Beach",
    "sg:classifiers":[
        {
            "category":"Professional",
            "subcategory":"Management & Consulting",
            "type":"Services"
        }
    ],
    "sg:phone":"+1 757 427 6054",
    "sg:postcode":"23454",
    "sg:province":"VA",
    "sg:tags":[
        "business"
    ],
    "wof:name":"Kenneth Mestad",
    "wof:placetype":"venue"
},
  "geometry": {"coordinates":[-75.99368800000001,36.773474],"type":"Point"}
}