{
  "type": "Feature",
  "properties": {
    "addr:full":"5400 Midlothian Tpke Richmond VA 23225",
    "addr:housenumber":"5400",
    "addr:postcode":"23225",
    "addr:street":"Midlothian Tpke",
    "iso:country":"US",
    "sg:address":"5400 Midlothian Tpke",
    "sg:city":"Richmond",
    "sg:classifiers":[
        {
            "category":"Wholesale",
            "subcategory":"Groceries",
            "type":"Manufacturing & Wholesale Goods"
        }
    ],
    "sg:phone":"+1 804 422 8908",
    "sg:postcode":"23225",
    "sg:province":"VA",
    "sg:tags":[
        "general"
    ],
    "wof:name":"Jl & Sons",
    "wof:placetype":"venue"
},
  "geometry": {"coordinates":[-77.496528,37.506685],"type":"Point"}
}