{
  "type": "Feature",
  "properties": {
    "addr:full":"405 W 6th St Richmond VA 23224",
    "addr:housenumber":"405",
    "addr:postcode":"23224",
    "addr:street":"W 6Th St",
    "iso:country":"US",
    "sg:address":"405 W 6th St",
    "sg:city":"Richmond",
    "sg:classifiers":[
        {
            "category":"Railroad",
            "type":"Transportation"
        }
    ],
    "sg:phone":"+1 804 843 2744",
    "sg:postcode":"23224",
    "sg:province":"VA",
    "sg:tags":[
        "operator",
        "line"
    ],
    "wof:name":"Norfolk Southern Corporation",
    "wof:placetype":"venue"
},
  "geometry": {"coordinates":[-77.44363199999999,37.528272],"type":"Point"}
}