{
  "type": "Feature",
  "properties": {
    "addr:full":"259 Moseby Dr Manassas VA 20111",
    "addr:housenumber":"259",
    "addr:postcode":"20111",
    "addr:street":"Moseby Dr",
    "iso:country":"US",
    "sg:address":"259 Moseby Dr",
    "sg:city":"Manassas",
    "sg:classifiers":[
        {
            "category":"Building & Trades",
            "subcategory":"Construction",
            "type":"Services"
        }
    ],
    "sg:phone":"+1 703 392 8164",
    "sg:postcode":"20111",
    "sg:province":"VA",
    "sg:tags":[
        "concrete",
        "contractor"
    ],
    "wof:name":"Navarro Concrete LLC",
    "wof:placetype":"venue"
},
  "geometry": {"coordinates":[-77.46905,38.780857],"type":"Point"}
}