{
  "type": "Feature",
  "properties": {
    "addr:full":"11976 Falling Creek Dr Manassas VA 20112",
    "addr:housenumber":"11976",
    "addr:postcode":"20112",
    "addr:street":"Falling Creek Dr",
    "iso:country":"US",
    "sg:address":"11976 Falling Creek Dr",
    "sg:city":"Manassas",
    "sg:classifiers":[
        {
            "category":"Home & Garden",
            "subcategory":"Building Materials",
            "type":"Retail Goods"
        }
    ],
    "sg:phone":"+1 703 753 9113",
    "sg:postcode":"20112",
    "sg:province":"VA",
    "sg:tags":[
        "door"
    ],
    "wof:name":"Jackson Construction",
    "wof:placetype":"venue"
},
  "geometry": {"coordinates":[-77.43658499999999,38.696098],"type":"Point"}
}