{
  "type": "Feature",
  "properties": {
    "addr:full":"14315 Candlewick Ct Midlothian VA 23112",
    "addr:housenumber":"14315",
    "addr:postcode":"23112",
    "addr:street":"Candlewick Ct",
    "iso:country":"US",
    "sg:address":"14315 Candlewick Ct",
    "sg:city":"Midlothian",
    "sg:classifiers":[
        {
            "category":"Professional",
            "subcategory":"Management & Consulting",
            "type":"Services"
        }
    ],
    "sg:phone":"+1 804 739 7939",
    "sg:postcode":"23112",
    "sg:province":"VA",
    "sg:tags":[
        "business"
    ],
    "wof:name":"Contemporary Consulting LLC",
    "wof:placetype":"venue"
},
  "geometry": {"coordinates":[-77.67184899999999,37.425887],"type":"Point"}
}