{
  "type": "Feature",
  "properties": {
    "addr:full":"9106 Woodlake Dr Richmond VA 23294",
    "addr:housenumber":"9106",
    "addr:postcode":"23294",
    "addr:street":"Woodlake Dr",
    "iso:country":"US",
    "sg:address":"9106 Woodlake Dr",
    "sg:city":"Richmond",
    "sg:classifiers":[
        {
            "category":"Professional",
            "type":"Services"
        }
    ],
    "sg:phone":"+1 804 747 7841",
    "sg:postcode":"23294",
    "sg:province":"VA",
    "wof:name":"Co Bui Thi Bass",
    "wof:placetype":"venue"
},
  "geometry": {"coordinates":[-77.54467,37.645622],"type":"Point"}
}