{
  "type": "Feature",
  "properties": {
    "addr:full":"7933 Jefferson Davis Hwy Richmond VA 23237",
    "addr:housenumber":"7933",
    "addr:postcode":"23237",
    "addr:street":"Jefferson Davis Hwy",
    "iso:country":"US",
    "sg:address":"7933 Jefferson Davis Hwy",
    "sg:city":"Richmond",
    "sg:classifiers":[
        {
            "category":"Autos & Motor Vehicles",
            "subcategory":"Fuel & Gas Station",
            "type":"Retail Goods"
        }
    ],
    "sg:phone":"+1 804 271 5619",
    "sg:postcode":"23237",
    "sg:province":"VA",
    "sg:tags":[
        "convenience",
        "station",
        "store"
    ],
    "wof:name":"Market Place",
    "wof:placetype":"venue"
},
  "geometry": {"coordinates":[-77.436229,37.416893],"type":"Point"}
}