{
  "type": "Feature",
  "properties": {
    "iso:country":"US",
    "sg:address":"6 North St",
    "sg:city":"Onancock",
    "sg:classifiers":[
        {
            "category":"Shopping",
            "subcategory":"Books",
            "type":"Retail Goods"
        }
    ],
    "sg:phone":"+1 757 302 0322",
    "sg:postcode":"23417",
    "sg:province":"VA",
    "wof:name":"Vineyard Bookstore",
    "wof:placetype":"venue"
},
  "geometry": {"coordinates":[-75.748739,37.712572],"type":"Point"}
}