{
  "type": "Feature",
  "properties": {
    "iso:country":"US",
    "sg:address":"409 S Hicks St",
    "sg:city":"Lawrenceville",
    "sg:classifiers":[
        {
            "category":"Government",
            "subcategory":"Post Office",
            "type":"Public Place"
        }
    ],
    "sg:phone":"+1 434 848 2956",
    "sg:postcode":"23868",
    "sg:province":"VA",
    "sg:website":"www.usps.gov",
    "wof:name":"US Post Office",
    "wof:placetype":"venue"
},
  "geometry": {"coordinates":[-77.850617,36.754572],"type":"Point"}
}