{
  "type": "Feature",
  "properties": {
    "addr:full":"46030 Manekin Plz Sterling VA 20166",
    "addr:postcode":"46030;20166",
    "addr:street":"Manekin Plz",
    "iso:country":"US",
    "sg:address":"46030 Manekin Plz",
    "sg:city":"Sterling",
    "sg:classifiers":[
        {
            "category":"Banks & Credit Unions",
            "subcategory":"Investment Brokerage",
            "type":"Services"
        }
    ],
    "sg:phone":"+1 571 434 5800",
    "sg:postcode":"20166",
    "sg:province":"VA",
    "wof:name":"Investment Co Institute",
    "wof:placetype":"venue"
},
  "geometry": {"coordinates":[-77.407076,39.023472],"type":"Point"}
}