{
  "type": "Feature",
  "properties": {
    "iso:country":"US",
    "sg:address":"9301 Quioccasin Rd",
    "sg:city":"Richmond",
    "sg:classifiers":[
        {
            "category":"Food & Beverages",
            "subcategory":"Groceries & Convenience Stores",
            "type":"Retail Goods"
        }
    ],
    "sg:phone":"+1 804 740 7185",
    "sg:postcode":"23229",
    "sg:province":"VA",
    "wof:name":"Qk Pk",
    "wof:placetype":"venue"
},
  "geometry": {"coordinates":[-77.580135,37.607368],"type":"Point"}
}