{
  "type": "Feature",
  "properties": {
    "addr:full":"6310 Gravel Ave Alexandria VA 22310",
    "addr:housenumber":"6310",
    "addr:postcode":"22310",
    "addr:street":"Gravel Ave",
    "iso:country":"US",
    "sg:address":"6310 Gravel Ave",
    "sg:city":"Alexandria",
    "sg:classifiers":[
        {
            "category":"Freight",
            "type":"Transportation"
        }
    ],
    "sg:phone":"+1 703 971 0700",
    "sg:postcode":"22310",
    "sg:province":"VA",
    "sg:tags":[
        "trucking"
    ],
    "sg:website":"www.direct-services.com",
    "wof:name":"Direct Services",
    "wof:placetype":"venue"
},
  "geometry": {"coordinates":[-77.157758,38.770719],"type":"Point"}
}