{
  "type": "Feature",
  "properties": {
    "addr:full":"12510 Lake Ridge Dr Woodbridge VA 22192",
    "addr:housenumber":"12510",
    "addr:postcode":"22192",
    "addr:street":"Lake Ridge Dr",
    "iso:country":"US",
    "sg:address":"12510 Lake Ridge Dr",
    "sg:city":"Woodbridge",
    "sg:classifiers":[
        {
            "category":"Health Services",
            "subcategory":"Medical Lab",
            "type":"Services"
        }
    ],
    "sg:phone":"+1 703 499 9930",
    "sg:postcode":"22192",
    "sg:province":"VA",
    "sg:tags":[
        "detection",
        "equipment",
        "drug"
    ],
    "wof:name":"Alcohol & Drug Testing Svc",
    "wof:placetype":"venue"
},
  "geometry": {"coordinates":[-77.27650800000001,38.679395],"type":"Point"}
}