{
  "type": "Feature",
  "properties": {
    "addr:full":"20 S Cameron St Winchester VA 22601",
    "addr:housenumber":"20",
    "addr:postcode":"22601",
    "addr:street":"S Cameron St",
    "iso:country":"US",
    "sg:address":"20 S Cameron St",
    "sg:city":"Winchester",
    "sg:classifiers":[
        {
            "category":"Banks & Credit Unions",
            "subcategory":"Investment Brokerage",
            "type":"Services"
        }
    ],
    "sg:phone":"+1 540 665 1888",
    "sg:postcode":"22601",
    "sg:province":"VA",
    "sg:tags":[
        "consultant",
        "planning",
        "financial"
    ],
    "wof:name":"Merrill Lynch Pierce Fenner",
    "wof:placetype":"venue"
},
  "geometry": {"coordinates":[-78.16413900000001,39.18351],"type":"Point"}
}