{
  "type": "Feature",
  "properties": {
    "addr:full":"948 Franklin Pike SE Floyd VA 24091",
    "addr:housenumber":"948",
    "addr:postcode":"24091",
    "addr:street":"Franklin Pike Se",
    "iso:country":"US",
    "sg:address":"948 Franklin Pike SE",
    "sg:city":"Floyd",
    "sg:classifiers":[
        {
            "category":"Organizations",
            "subcategory":"Religious Organization",
            "type":"Services"
        }
    ],
    "sg:phone":"+1 540 745 6922",
    "sg:postcode":"24091",
    "sg:province":"VA",
    "sg:tags":[
        "church"
    ],
    "wof:name":"New Beginning Christian Church",
    "wof:placetype":"venue"
},
  "geometry": {"coordinates":[-80.278327,36.911364],"type":"Point"}
}