{
  "type": "Feature",
  "properties": {
    "addr:full":"12917 Alton Sq Herndon VA 20170",
    "addr:housenumber":"12917",
    "addr:postcode":"20170",
    "addr:street":"Alton Sq",
    "iso:country":"US",
    "sg:address":"12917 Alton Sq",
    "sg:city":"Herndon",
    "sg:classifiers":[
        {
            "category":"Real Estate",
            "subcategory":"Real Estate Agent",
            "type":"Services"
        },
        {
            "category":"Real Estate",
            "subcategory":"Real Estate Operator",
            "type":"Services"
        }
    ],
    "sg:phone":"+1 703 904 7671",
    "sg:postcode":"20170",
    "sg:province":"VA",
    "sg:tags":[
        "management",
        "condominium"
    ],
    "wof:name":"Worldgate Condominiums",
    "wof:placetype":"venue"
},
  "geometry": {"coordinates":[-77.39487200000001,38.956346],"type":"Point"}
}