{
  "type": "Feature",
  "properties": {
    "iso:country":"US",
    "sg:address":"2722 W Broad St",
    "sg:city":"Richmond",
    "sg:classifiers":[
        {
            "category":"Freight",
            "type":"Transportation"
        }
    ],
    "sg:phone":"+1 804 355 7388",
    "sg:postcode":"23220",
    "sg:province":"VA",
    "sg:tags":[
        "courier"
    ],
    "wof:name":"Red Rider Express",
    "wof:placetype":"venue"
},
  "geometry": {"coordinates":[-77.469784,37.562269],"type":"Point"}
}