{
  "type": "Feature",
  "properties": {
    "addr:full":"4250 County Line Rd Cullen VA 23934",
    "addr:housenumber":"4250",
    "addr:postcode":"23934",
    "addr:street":"County Line Rd",
    "iso:country":"US",
    "sg:address":"4250 County Line Rd",
    "sg:city":"Cullen",
    "sg:classifiers":[
        {
            "category":"Farming",
            "subcategory":"Dairy Farm",
            "type":"Manufacturing & Wholesale Goods"
        }
    ],
    "sg:phone":"+1 434 542 5462",
    "sg:postcode":"23934",
    "sg:province":"VA",
    "wof:name":"Samuel Geesaman",
    "wof:placetype":"venue"
},
  "geometry": {"coordinates":[-78.636084,37.175009],"type":"Point"}
}