{
  "type": "Feature",
  "properties": {
    "iso:country":"US",
    "sg:address":"10049 Midlothian Tpke A",
    "sg:city":"Richmond",
    "sg:classifiers":[
        {
            "category":"Professional",
            "subcategory":"Accounting & Tax Preparation",
            "type":"Services"
        },
        {
            "category":"Insurance",
            "subcategory":"Hazard Insurance",
            "type":"Services"
        }
    ],
    "sg:phone":"+1 804 323 5900",
    "sg:postcode":"23235",
    "sg:province":"VA",
    "sg:tags":[
        "bookkeeping",
        "billing"
    ],
    "sg:website":"http://www.ibsaccounts.com",
    "wof:name":"Insurance Billing Services Inc",
    "wof:placetype":"venue"
},
  "geometry": {"coordinates":[-77.58162400000001,37.505975],"type":"Point"}
}