{
  "type": "Feature",
  "properties": {
    "iso:country":"US",
    "sg:address":"2912 Pleasant Glen Dr",
    "sg:city":"Herndon",
    "sg:classifiers":[
        {
            "category":"Banks & Credit Unions",
            "subcategory":"Investment Brokerage",
            "type":"Services"
        }
    ],
    "sg:phone":"+1 703 376 8244",
    "sg:postcode":"20171",
    "sg:province":"VA",
    "sg:tags":[
        "advisory"
    ],
    "wof:name":"Christian And Jacob Invest",
    "wof:placetype":"venue"
},
  "geometry": {"coordinates":[-77.40316900000001,38.921116],"type":"Point"}
}