{
  "type": "Feature",
  "properties": {
    "iso:country":"US",
    "sg:address":"12902 Tarragon Ct",
    "sg:city":"Herndon",
    "sg:classifiers":[
        {
            "category":"Professional",
            "subcategory":"Computer Services",
            "type":"Services"
        }
    ],
    "sg:phone":"+1 703 860 9127",
    "sg:postcode":"20171",
    "sg:province":"VA",
    "sg:tags":[
        "design",
        "system",
        "related"
    ],
    "wof:name":"Aimtech",
    "wof:placetype":"venue"
},
  "geometry": {"coordinates":[-77.39254200000001,38.916773],"type":"Point"}
}