{
  "type": "Feature",
  "properties": {
    "addr:full":"10317 Amberleigh Ct Manassas VA 20110",
    "addr:housenumber":"10317",
    "addr:postcode":"20110",
    "addr:street":"Amberleigh Ct",
    "iso:country":"US",
    "sg:address":"10317 Amberleigh Ct",
    "sg:city":"Manassas",
    "sg:classifiers":[
        {
            "category":"Shopping",
            "type":"Retail Goods"
        }
    ],
    "sg:phone":"+1 703 330 9028",
    "sg:postcode":"20110",
    "sg:province":"VA",
    "sg:tags":[
        "communications",
        "satellite",
        "equipment"
    ],
    "wof:name":"Psn",
    "wof:placetype":"venue"
},
  "geometry": {"coordinates":[-77.48626,38.733136],"type":"Point"}
}