{
  "type": "Feature",
  "properties": {
    "addr:full":"1752 Anderson Rd Falls Church VA 22043",
    "addr:housenumber":"1752",
    "addr:postcode":"22043",
    "addr:street":"Anderson Rd",
    "iso:country":"US",
    "sg:address":"1752 Anderson Rd",
    "sg:city":"Falls Church",
    "sg:classifiers":[
        {
            "category":"Building & Trades",
            "subcategory":"Plumbing",
            "type":"Services"
        }
    ],
    "sg:phone":"+1 703 534 9585",
    "sg:postcode":"22043",
    "sg:province":"VA",
    "sg:tags":[
        "contractor"
    ],
    "wof:name":"Vernco Plumbing Company",
    "wof:placetype":"venue"
},
  "geometry": {"coordinates":[-77.19944099999999,38.91997],"type":"Point"}
}