{
  "type": "Feature",
  "properties": {
    "addr:full":"4345 W Creek Rd Crewe VA 23930",
    "addr:housenumber":"4345",
    "addr:postcode":"23930",
    "addr:street":"W Creek Rd",
    "iso:country":"US",
    "sg:address":"4345 W Creek Rd",
    "sg:city":"Crewe",
    "sg:classifiers":[
        {
            "category":"Retail",
            "subcategory":"Auto Repair",
            "type":"Services"
        }
    ],
    "sg:phone":"+1 434 645 8952",
    "sg:postcode":"23930",
    "sg:province":"VA",
    "sg:tags":[
        "body"
    ],
    "wof:name":"Genes Auto Body Shop",
    "wof:placetype":"venue"
},
  "geometry": {"coordinates":[-78.068602,37.229704],"type":"Point"}
}