{
  "type": "Feature",
  "properties": {
    "addr:full":"7030 Harrison Rd Fredericksburg VA 22407",
    "addr:housenumber":"7030",
    "addr:postcode":"22407",
    "addr:street":"Harrison Rd",
    "iso:country":"US",
    "sg:address":"7030 Harrison Rd",
    "sg:city":"Fredericksburg",
    "sg:classifiers":[
        {
            "category":"Local Transit",
            "type":"Transportation"
        }
    ],
    "sg:phone":"+1 540 786 1128",
    "sg:postcode":"22407",
    "sg:province":"VA",
    "sg:tags":[
        "passenger",
        "executive"
    ],
    "wof:name":"Station 5",
    "wof:placetype":"venue"
},
  "geometry": {"coordinates":[-77.566945,38.288798],"type":"Point"}
}