{
  "type": "Feature",
  "properties": {
    "iso:country":"US",
    "sg:address":"7851 Sudley Rd",
    "sg:city":"Manassas",
    "sg:classifiers":[
        {
            "category":"Shopping",
            "subcategory":"Clothing, Apparel, & Fashions",
            "type":"Retail Goods"
        }
    ],
    "sg:phone":"+1 703 361 0690",
    "sg:postcode":"20109",
    "sg:province":"VA",
    "sg:tags":[
        "men's",
        "clothing",
        "women's"
    ],
    "sg:website":"www.ruggedwearhouse.com",
    "wof:name":"Rugged Wearhouse",
    "wof:placetype":"venue"
},
  "geometry": {"coordinates":[-77.513201,38.786114],"type":"Point"}
}