{
  "type": "Feature",
  "properties": {
    "iso:country":"US",
    "sg:address":"5307 W Hundred Rd",
    "sg:city":"Chester",
    "sg:classifiers":[
        {
            "category":"Professional",
            "subcategory":"Management & Consulting",
            "type":"Services"
        }
    ],
    "sg:phone":"+1 804 425 5104",
    "sg:postcode":"23831",
    "sg:province":"VA",
    "sg:tags":[
        "business"
    ],
    "wof:name":"Fire Analysis Consulting Group",
    "wof:placetype":"venue"
},
  "geometry": {"coordinates":[-77.458322,37.350809],"type":"Point"}
}