{
  "type": "Feature",
  "properties": {
    "addr:full":"21080 Dulles Town Cir Sterling VA 20166",
    "addr:housenumber":"21080",
    "addr:postcode":"20166",
    "addr:street":"Dulles Town Cir",
    "iso:country":"US",
    "sg:address":"21080 Dulles Town Cir",
    "sg:city":"Sterling",
    "sg:classifiers":[
        {
            "category":"Shopping",
            "subcategory":"Shoes",
            "type":"Retail Goods"
        }
    ],
    "sg:phone":"+1 703 406 7573",
    "sg:postcode":"20166",
    "sg:province":"VA",
    "wof:name":"Walking Store The 177",
    "wof:placetype":"venue"
},
  "geometry": {"coordinates":[-77.420789,39.029033],"type":"Point"}
}