{
  "type": "Feature",
  "properties": {
    "addr:full":"211 E Sycamore St Chase City VA 23924",
    "addr:housenumber":"211",
    "addr:postcode":"23924",
    "addr:street":"E Sycamore St",
    "iso:country":"US",
    "sg:address":"211 E Sycamore St",
    "sg:city":"Chase City",
    "sg:classifiers":[
        {
            "category":"Home & Garden",
            "subcategory":"Household Appliances",
            "type":"Retail Goods"
        }
    ],
    "sg:phone":"+1 434 372 3151",
    "sg:postcode":"23924",
    "sg:province":"VA",
    "sg:tags":[
        "furniture"
    ],
    "wof:name":"COLGATE FINANCIAL SERVICE",
    "wof:placetype":"venue"
},
  "geometry": {"coordinates":[-78.458513,36.796633],"type":"Point"}
}