{
  "type": "Feature",
  "properties": {
    "addr:full":"1300 17th St N Ste 750 Arlington VA 22209",
    "addr:housenumber":"1300",
    "addr:postcode":"22209",
    "addr:street":"17Th St N Ste 750",
    "iso:country":"US",
    "sg:address":"1300 17th St N Ste 750",
    "sg:city":"Arlington",
    "sg:classifiers":[
        {
            "category":"Banks & Credit Unions",
            "subcategory":"Investment Brokerage",
            "type":"Services"
        },
        {
            "category":"Banks & Credit Unions",
            "subcategory":"Financial Services",
            "type":"Services"
        }
    ],
    "sg:phone":"+1 703 812 3020",
    "sg:postcode":"22209",
    "sg:province":"VA",
    "sg:tags":[
        "advisory",
        "planner"
    ],
    "wof:name":"Relativity Capital",
    "wof:placetype":"venue"
},
  "geometry": {"coordinates":[-77.072739,38.894058],"type":"Point"}
}