{
  "type": "Feature",
  "properties": {
    "iso:country":"US",
    "sg:address":"2007 Woodlyn Dr Apt 1",
    "sg:city":"Fredericksburg",
    "sg:classifiers":[
        {
            "category":"Structure",
            "subcategory":"Office Building",
            "type":"Public Place"
        }
    ],
    "sg:phone":"+1 540 847 3730",
    "sg:postcode":"22401",
    "sg:province":"VA",
    "sg:tags":[
        "park"
    ],
    "wof:name":"Northwest Properties",
    "wof:placetype":"venue"
},
  "geometry": {"coordinates":[-77.49208400000001,38.29807],"type":"Point"}
}