{
  "type": "Feature",
  "properties": {
    "addr:full":"2331 Vicker Ave Chesapeake VA 23324",
    "addr:housenumber":"2331",
    "addr:postcode":"23324",
    "addr:street":"Vicker Ave",
    "iso:country":"US",
    "sg:address":"2331 Vicker Ave",
    "sg:city":"Chesapeake",
    "sg:classifiers":[
        {
            "category":"Building & Trades",
            "subcategory":"Plumbing",
            "type":"Services"
        }
    ],
    "sg:phone":"+1 757 494 3747",
    "sg:postcode":"23324",
    "sg:province":"VA",
    "sg:tags":[
        "contractor"
    ],
    "wof:name":"M J Lamy Marine AC & Refri",
    "wof:placetype":"venue"
},
  "geometry": {"coordinates":[-76.256541,36.803326],"type":"Point"}
}