{
  "type": "Feature",
  "properties": {
    "addr:full":"1861 Regent Rd Topping VA 23169",
    "addr:housenumber":"1861",
    "addr:postcode":"23169",
    "addr:street":"Regent Rd",
    "iso:country":"US",
    "sg:address":"1861 Regent Rd",
    "sg:city":"Topping",
    "sg:classifiers":[
        {
            "category":"Retail",
            "subcategory":"Repair Shop",
            "type":"Services"
        }
    ],
    "sg:phone":"+1 804 758 1177",
    "sg:postcode":"23169",
    "sg:province":"VA",
    "wof:name":"C & S Upholstery Co",
    "wof:placetype":"venue"
},
  "geometry": {"coordinates":[-76.45638599999999,37.581613],"type":"Point"}
}