{
  "type": "Feature",
  "properties": {
    "addr:full":"13431 Wood Lilly Ln Centreville VA 20120",
    "addr:housenumber":"13431",
    "addr:postcode":"20120",
    "addr:street":"Wood Lilly Ln",
    "iso:country":"US",
    "sg:address":"13431 Wood Lilly Ln",
    "sg:city":"Centreville",
    "sg:classifiers":[
        {
            "category":"Building & Trades",
            "subcategory":"Construction",
            "type":"Services"
        }
    ],
    "sg:phone":"+1 703 830 4857",
    "sg:postcode":"20120",
    "sg:province":"VA",
    "sg:tags":[
        "home",
        "builder"
    ],
    "wof:name":"Winchester Homes",
    "wof:placetype":"venue"
},
  "geometry": {"coordinates":[-77.411012,38.844529],"type":"Point"}
}