{
  "type": "Feature",
  "properties": {
    "iso:country":"US",
    "sg:address":"5742 Backlick Rd",
    "sg:city":"Springfield",
    "sg:classifiers":[
        {
            "category":"Personal",
            "type":"Services"
        }
    ],
    "sg:phone":"+1 703 644 4223",
    "sg:postcode":"22150",
    "sg:province":"VA",
    "wof:name":"Diggs Services LLC",
    "wof:placetype":"venue"
},
  "geometry": {"coordinates":[-77.186168,38.794892],"type":"Point"}
}