{
  "type": "Feature",
  "properties": {
    "iso:country":"US",
    "sg:address":"10340 Lewis Ln",
    "sg:city":"King George",
    "sg:classifiers":[
        {
            "category":"Manufacturing",
            "subcategory":"Signs",
            "type":"Manufacturing & Wholesale Goods"
        }
    ],
    "sg:phone":"+1 540 775 2636",
    "sg:postcode":"22485",
    "sg:province":"VA",
    "sg:tags":[
        "specialty",
        "mfg"
    ],
    "wof:name":"Just In Tyme Promotions",
    "wof:placetype":"venue"
},
  "geometry": {"coordinates":[-77.328929,38.269895],"type":"Point"}
}