{
  "type": "Feature",
  "properties": {
    "iso:country":"US",
    "sg:address":"8600 Old Brompton Rd",
    "sg:city":"Chesterfield",
    "sg:classifiers":[
        {
            "category":"Real Estate",
            "subcategory":"Real Estate Agent",
            "type":"Services"
        }
    ],
    "sg:phone":"+1 804 639 1102",
    "sg:postcode":"23832",
    "sg:province":"VA",
    "wof:name":"J & B Holdings LLC",
    "wof:placetype":"venue"
},
  "geometry": {"coordinates":[-77.673326,37.38765],"type":"Point"}
}