{
  "type": "Feature",
  "properties": {
    "addr:full":"22712 Commerce Center Ct Sterling VA 20166",
    "addr:housenumber":"22712",
    "addr:postcode":"20166",
    "addr:street":"Commerce Center Ct",
    "iso:country":"US",
    "sg:address":"22712 Commerce Center Ct",
    "sg:city":"Sterling",
    "sg:classifiers":[
        {
            "category":"Building & Trades",
            "subcategory":"Construction",
            "type":"Services"
        }
    ],
    "sg:phone":"+1 703 661 0300",
    "sg:postcode":"20166",
    "sg:province":"VA",
    "wof:name":"Project Developers Inc",
    "wof:placetype":"venue"
},
  "geometry": {"coordinates":[-77.471024,38.989374],"type":"Point"}
}