{
  "type": "Feature",
  "properties": {
    "addr:full":"14241 Newgate Rd Midlothian VA 23113",
    "addr:housenumber":"14241",
    "addr:postcode":"23113",
    "addr:street":"Newgate Rd",
    "iso:country":"US",
    "sg:address":"14241 Newgate Rd",
    "sg:city":"Midlothian",
    "sg:classifiers":[
        {
            "category":"Insurance",
            "subcategory":"Insurance Agent",
            "type":"Services"
        }
    ],
    "sg:phone":"+1 804 379 1358",
    "sg:postcode":"23113",
    "sg:province":"VA",
    "wof:name":"Insurance Concepts",
    "wof:placetype":"venue"
},
  "geometry": {"coordinates":[-77.662881,37.515799],"type":"Point"}
}