{
  "type": "Feature",
  "properties": {
    "addr:full":"415 N Military Hwy Norfolk VA 23502",
    "addr:housenumber":"415",
    "addr:postcode":"23502",
    "addr:street":"N Military Hwy",
    "iso:country":"US",
    "sg:address":"415 N Military Hwy",
    "sg:city":"Norfolk",
    "sg:classifiers":[
        {
            "category":"Home & Garden",
            "subcategory":"Hardware",
            "type":"Retail Goods"
        }
    ],
    "sg:phone":"+1 757 893 1302",
    "sg:postcode":"23502",
    "sg:province":"VA",
    "sg:tags":[
        "tool",
        "used"
    ],
    "sg:website":"www.harborfreight.com",
    "wof:name":"Harbor Freight Tools USA Inc",
    "wof:placetype":"venue"
},
  "geometry": {"coordinates":[-76.2103,36.847511],"type":"Point"}
}