{
  "type": "Feature",
  "properties": {
    "addr:full":"107 E Cary St Richmond VA 23219",
    "addr:housenumber":"107",
    "addr:postcode":"23219",
    "addr:street":"E Cary St",
    "iso:country":"US",
    "sg:address":"107 E Cary St",
    "sg:city":"Richmond",
    "sg:classifiers":[
        {
            "category":"Home & Garden",
            "subcategory":"Carpets & Floor Coverings",
            "type":"Retail Goods"
        }
    ],
    "sg:phone":"+1 804 648 7877",
    "sg:postcode":"23219",
    "sg:province":"VA",
    "sg:tags":[
        "rug"
    ],
    "wof:name":"Sarah Gayle Carter Studio Cllc",
    "wof:placetype":"venue"
},
  "geometry": {"coordinates":[-77.4435,37.541087],"type":"Point"}
}