{
  "type": "Feature",
  "properties": {
    "addr:full":"104 Highland Ave Bluefield VA 24605",
    "addr:housenumber":"104",
    "addr:postcode":"24605",
    "addr:street":"Highland Ave",
    "iso:country":"US",
    "sg:address":"104 Highland Ave",
    "sg:city":"Bluefield",
    "sg:classifiers":[
        {
            "category":"Organizations",
            "subcategory":"Religious Organization",
            "type":"Services"
        }
    ],
    "sg:phone":"+1 276 326 1356",
    "sg:postcode":"24605",
    "sg:province":"VA",
    "sg:tags":[
        "church"
    ],
    "wof:name":"Church Of God",
    "wof:placetype":"venue"
},
  "geometry": {"coordinates":[-81.280788,37.253717],"type":"Point"}
}