{
  "type": "Feature",
  "properties": {
    "addr:full":"1600 Wilson Blvd Ste 102 Arlington VA 22209",
    "addr:housenumber":"1600",
    "addr:postcode":"22209",
    "addr:street":"Wilson Blvd Ste 102",
    "iso:country":"US",
    "sg:address":"1600 Wilson Blvd Ste 102",
    "sg:city":"Arlington",
    "sg:classifiers":[
        {
            "category":"Professional",
            "subcategory":"Printing & Photocopies",
            "type":"Services"
        }
    ],
    "sg:phone":"+1 703 525 5218",
    "sg:postcode":"22209",
    "sg:province":"VA",
    "sg:website":"www.sirspeedy.com/centers/arling...",
    "wof:name":"SIR Speedy Printing",
    "wof:placetype":"venue"
},
  "geometry": {"coordinates":[-77.07705300000001,38.894189],"type":"Point"}
}