{
  "type": "Feature",
  "properties": {
    "addr:full":"791 Palmer Point Rd Boydton VA 23917",
    "addr:housenumber":"791",
    "addr:postcode":"23917",
    "addr:street":"Palmer Point Rd",
    "iso:country":"US",
    "sg:address":"791 Palmer Point Rd",
    "sg:city":"Boydton",
    "sg:classifiers":[
        {
            "category":"Professional",
            "type":"Services"
        }
    ],
    "sg:phone":"+1 434 689 3330",
    "sg:postcode":"23917",
    "sg:province":"VA",
    "sg:tags":[
        "establishment"
    ],
    "wof:name":"Mobile Environment",
    "wof:placetype":"venue"
},
  "geometry": {"coordinates":[-78.28263099999999,36.566231],"type":"Point"}
}