{
  "type": "Feature",
  "properties": {
    "iso:country":"US",
    "sg:address":"5124 Southpoint Pkwy",
    "sg:city":"Fredericksburg",
    "sg:classifiers":[
        {
            "category":"Personal",
            "subcategory":"Beauty Salon",
            "type":"Services"
        }
    ],
    "sg:phone":"+1 540 710 6333",
    "sg:postcode":"22407",
    "sg:province":"VA",
    "sg:tags":[
        "shop"
    ],
    "wof:name":"Salon 2000 Inc",
    "wof:placetype":"venue"
},
  "geometry": {"coordinates":[-77.49964199999999,38.232639],"type":"Point"}
}