{
  "type": "Feature",
  "properties": {
    "addr:full":"20702 Ashburn Rd Ashburn VA 20147",
    "addr:housenumber":"20702",
    "addr:postcode":"20147",
    "addr:street":"Ashburn Rd",
    "iso:country":"US",
    "sg:address":"20702 Ashburn Rd",
    "sg:city":"Ashburn",
    "sg:classifiers":[
        {
            "category":"Restaurant",
            "type":"Food & Drink"
        }
    ],
    "sg:phone":"+1 703 729 0333",
    "sg:postcode":"20147",
    "sg:province":"VA",
    "sg:tags":[
        "eating"
    ],
    "wof:name":"Docs B B Q & Catering Co",
    "wof:placetype":"venue"
},
  "geometry": {"coordinates":[-77.487188,39.042418],"type":"Point"}
}