{
  "type": "Feature",
  "properties": {
    "iso:country":"US",
    "sg:address":"7200 Sanford Ct",
    "sg:city":"Annandale",
    "sg:classifiers":[
        {
            "category":"Manufacturing",
            "subcategory":"Buildings",
            "type":"Manufacturing & Wholesale Goods"
        },
        {
            "category":"Home & Garden",
            "subcategory":"Building Materials",
            "type":"Retail Goods"
        },
        {
            "category":"Building & Trades",
            "subcategory":"Construction",
            "type":"Services"
        }
    ],
    "sg:phone":"+1 703 204 0733",
    "sg:postcode":"22003",
    "sg:province":"VA",
    "sg:tags":[
        "concrete",
        "builder",
        "staining",
        "contractor"
    ],
    "wof:name":"Alba Construction Co Inc",
    "wof:placetype":"venue"
},
  "geometry": {"coordinates":[-77.192993,38.844269],"type":"Point"}
}