{
  "type": "Feature",
  "properties": {
    "addr:full":"207 W 2nd Ave Franklin VA 23851",
    "addr:housenumber":"207",
    "addr:postcode":"23851",
    "addr:street":"W 2Nd Ave",
    "iso:country":"US",
    "sg:address":"207 W 2nd Ave",
    "sg:city":"Franklin",
    "sg:classifiers":[
        {
            "category":"Education",
            "subcategory":"School",
            "type":"Public Place"
        }
    ],
    "sg:phone":"+1 757 562 5348",
    "sg:postcode":"23851",
    "sg:province":"VA",
    "wof:name":"Franklin City Public Schools",
    "wof:placetype":"venue"
},
  "geometry": {"coordinates":[-76.923658,36.677166],"type":"Point"}
}