{
  "type": "Feature",
  "properties": {
    "addr:full":"1666 Balls Neck Rd Kilmarnock VA 22482",
    "addr:housenumber":"1666",
    "addr:postcode":"22482",
    "addr:street":"Balls Neck Rd",
    "iso:country":"US",
    "sg:address":"1666 Balls Neck Rd",
    "sg:city":"Kilmarnock",
    "sg:classifiers":[
        {
            "category":"Professional",
            "subcategory":"Business Services",
            "type":"Services"
        }
    ],
    "sg:phone":"+1 804 435 7065",
    "sg:postcode":"22482",
    "sg:province":"VA",
    "sg:tags":[
        "teaching"
    ],
    "wof:name":"Chesapeake Writing Consultants",
    "wof:placetype":"venue"
},
  "geometry": {"coordinates":[-76.34729299999999,37.787688],"type":"Point"}
}