{
  "type": "Feature",
  "properties": {
    "iso:country":"US",
    "sg:address":"4872 George Washington Memorial Hwy",
    "sg:city":"Yorktown",
    "sg:classifiers":[
        {
            "category":"Wholesale",
            "subcategory":"Groceries",
            "type":"Manufacturing & Wholesale Goods"
        }
    ],
    "sg:phone":"+1 804 693 7777",
    "sg:postcode":"23692",
    "sg:province":"VA",
    "sg:tags":[
        "baker"
    ],
    "wof:name":"Flowers Baking Co",
    "wof:placetype":"venue"
},
  "geometry": {"coordinates":[-76.460177,37.15112],"type":"Point"}
}