{
  "type": "Feature",
  "properties": {
    "iso:country":"US",
    "sg:address":"249 Robinson Dr",
    "sg:city":"Newport News",
    "sg:classifiers":[
        {
            "category":"Shopping",
            "subcategory":"Catalog Store",
            "type":"Retail Goods"
        }
    ],
    "sg:phone":"+1 757 599 1834",
    "sg:postcode":"23601",
    "sg:province":"VA",
    "sg:tags":[
        "mail",
        "house"
    ],
    "wof:name":"Choice Collections",
    "wof:placetype":"venue"
},
  "geometry": {"coordinates":[-76.453323,37.074026],"type":"Point"}
}