{
  "type": "Feature",
  "properties": {
    "addr:full":"2202 Garfield Ave Lynchburg VA 24501",
    "addr:housenumber":"2202",
    "addr:postcode":"24501",
    "addr:street":"Garfield Ave",
    "iso:country":"US",
    "sg:address":"2202 Garfield Ave",
    "sg:city":"Lynchburg",
    "sg:classifiers":[
        {
            "category":"Shopping",
            "subcategory":"Florist",
            "type":"Retail Goods"
        }
    ],
    "sg:phone":"+1 434 847 5809",
    "sg:postcode":"24501",
    "sg:province":"VA",
    "wof:name":"Julia's Flower Boutique",
    "wof:placetype":"venue"
},
  "geometry": {"coordinates":[-79.150812,37.394081],"type":"Point"}
}