{
  "type": "Feature",
  "properties": {
    "addr:full":"800 Chicago Ave Harrisonburg VA 22802",
    "addr:housenumber":"800",
    "addr:postcode":"22802",
    "addr:street":"Chicago Ave",
    "iso:country":"US",
    "sg:address":"800 Chicago Ave",
    "sg:city":"Harrisonburg",
    "sg:classifiers":[
        {
            "category":"Retail",
            "subcategory":"Repair Shop",
            "type":"Services"
        }
    ],
    "sg:phone":"+1 540 434 4681",
    "sg:postcode":"22802",
    "sg:province":"VA",
    "sg:tags":[
        "commercial",
        "refrigeration"
    ],
    "wof:name":"Harrisonburg Refrigeration Svc",
    "wof:placetype":"venue"
},
  "geometry": {"coordinates":[-78.874911,38.460499],"type":"Point"}
}