{
  "type": "Feature",
  "properties": {
    "addr:full":"1450 Roanoke Rd Daleville VA 24083",
    "addr:housenumber":"1450",
    "addr:postcode":"24083",
    "addr:street":"Roanoke Rd",
    "iso:country":"US",
    "sg:address":"1450 Roanoke Rd",
    "sg:city":"Daleville",
    "sg:classifiers":[
        {
            "category":"Personal",
            "subcategory":"Beauty Salon",
            "type":"Services"
        }
    ],
    "sg:phone":"+1 540 992 6512",
    "sg:postcode":"24083",
    "sg:province":"VA",
    "sg:tags":[
        "shop"
    ],
    "wof:name":"Nails By Joann Limage",
    "wof:placetype":"venue"
},
  "geometry": {"coordinates":[-79.913501,37.405588],"type":"Point"}
}