{
  "type": "Feature",
  "properties": {
    "addr:full":"13487 Dahlgren Rd King George VA 22485",
    "addr:housenumber":"13487",
    "addr:postcode":"22485",
    "addr:street":"Dahlgren Rd",
    "iso:country":"US",
    "sg:address":"13487 Dahlgren Rd",
    "sg:city":"King George",
    "sg:classifiers":[
        {
            "category":"Retail",
            "subcategory":"Auto Repair",
            "type":"Services"
        }
    ],
    "sg:phone":"+1 540 663 6255",
    "sg:postcode":"22485",
    "sg:province":"VA",
    "sg:tags":[
        "wrecker"
    ],
    "wof:name":"Sheltons Towing",
    "wof:placetype":"venue"
},
  "geometry": {"coordinates":[-77.10655800000001,38.337142],"type":"Point"}
}