{
  "type": "Feature",
  "properties": {
    "addr:full":"207 Granby St Norfolk VA 23510",
    "addr:housenumber":"207",
    "addr:postcode":"23510",
    "addr:street":"Granby St",
    "iso:country":"US",
    "sg:address":"207 Granby St",
    "sg:city":"Norfolk",
    "sg:classifiers":[
        {
            "category":"Real Estate",
            "subcategory":"Real Estate Operator",
            "type":"Services"
        }
    ],
    "sg:phone":"+1 757 626 3510",
    "sg:postcode":"23510",
    "sg:province":"VA",
    "sg:tags":[
        "building",
        "nonresidential"
    ],
    "wof:name":"Shopping Center Group",
    "wof:placetype":"venue"
},
  "geometry": {"coordinates":[-76.291336,36.848379],"type":"Point"}
}