{
  "type": "Feature",
  "properties": {
    "addr:full":"9704 Beach Mill Rd Great Falls VA 22066",
    "addr:housenumber":"9704",
    "addr:postcode":"22066",
    "addr:street":"Beach Mill Rd",
    "iso:country":"US",
    "sg:address":"9704 Beach Mill Rd",
    "sg:city":"Great Falls",
    "sg:classifiers":[
        {
            "category":"Professional",
            "subcategory":"Management & Consulting",
            "type":"Services"
        }
    ],
    "sg:phone":"+1 703 757 9477",
    "sg:postcode":"22066",
    "sg:province":"VA",
    "sg:tags":[
        "business"
    ],
    "wof:name":"Telework Management Training",
    "wof:placetype":"venue"
},
  "geometry": {"coordinates":[-77.28173700000001,39.023927],"type":"Point"}
}