{
  "type": "Feature",
  "properties": {
    "iso:country":"US",
    "sg:address":"300 Army Navy Dr",
    "sg:city":"Arlington",
    "sg:classifiers":[
        {
            "category":"Retail",
            "subcategory":"Auto Rental",
            "type":"Services"
        }
    ],
    "sg:phone":"+1 703 416 3805",
    "sg:postcode":"22202",
    "sg:province":"VA",
    "sg:tags":[
        "truck"
    ],
    "wof:name":"Virginia Htl Vef 4",
    "wof:placetype":"venue"
},
  "geometry": {"coordinates":[-77.052003,38.864159],"type":"Point"}
}