{
  "type": "Feature",
  "properties": {
    "addr:full":"5990 Richmond Hwy Alexandria VA 22303",
    "addr:housenumber":"5990",
    "addr:postcode":"22303",
    "addr:street":"Richmond Hwy",
    "iso:country":"US",
    "sg:address":"5990 Richmond Hwy",
    "sg:city":"Alexandria",
    "sg:classifiers":[
        {
            "category":"Organizations",
            "subcategory":"Religious Organization",
            "type":"Services"
        }
    ],
    "sg:phone":"+1 703 960 0935",
    "sg:postcode":"22303",
    "sg:province":"VA",
    "wof:name":"Sent Ones Ministry",
    "wof:placetype":"venue"
},
  "geometry": {"coordinates":[-77.065861,38.788677],"type":"Point"}
}