{
  "type": "Feature",
  "properties": {
    "addr:full":"1525 2nd St Waynesboro VA 22980",
    "addr:housenumber":"1525",
    "addr:postcode":"22980",
    "addr:street":"2Nd St",
    "iso:country":"US",
    "sg:address":"1525 2nd St",
    "sg:city":"Waynesboro",
    "sg:classifiers":[
        {
            "category":"Building & Trades",
            "subcategory":"Construction",
            "type":"Services"
        }
    ],
    "sg:phone":"+1 540 943 4006",
    "sg:postcode":"22980",
    "sg:province":"VA",
    "sg:tags":[
        "h",
        "siding",
        "contractor",
        "new"
    ],
    "wof:name":"Valley Siding & Home Imprvs",
    "wof:placetype":"venue"
},
  "geometry": {"coordinates":[-78.86273799999999,38.073526],"type":"Point"}
}