{
  "type": "Feature",
  "properties": {
    "addr:full":"1002 Amherst St Winchester VA 22601",
    "addr:housenumber":"1002",
    "addr:postcode":"22601",
    "addr:street":"Amherst St",
    "iso:country":"US",
    "sg:address":"1002 Amherst St",
    "sg:city":"Winchester",
    "sg:classifiers":[
        {
            "category":"Health Services",
            "subcategory":"Doctor",
            "type":"Services"
        }
    ],
    "sg:phone":"+1 540 662 3853",
    "sg:postcode":"22601",
    "sg:province":"VA",
    "sg:tags":[
        "physician",
        "surgeon"
    ],
    "wof:name":"Pediatric Associates",
    "wof:placetype":"venue"
},
  "geometry": {"coordinates":[-78.181145,39.189315],"type":"Point"}
}