{
  "type": "Feature",
  "properties": {
    "iso:country":"US",
    "sg:address":"14 River Downs Dr",
    "sg:city":"Fredericksburg",
    "sg:classifiers":[
        {
            "category":"Building & Trades",
            "subcategory":"Construction",
            "type":"Services"
        }
    ],
    "sg:phone":"+1 540 785 6792",
    "sg:postcode":"22407",
    "sg:province":"VA",
    "sg:tags":[
        "management",
        "general",
        "contractor"
    ],
    "wof:name":"Virginia Properties Inc",
    "wof:placetype":"venue"
},
  "geometry": {"coordinates":[-77.54946,38.323495],"type":"Point"}
}