{
  "type": "Feature",
  "properties": {
    "addr:full":"428 Lee Ave Harrisonburg VA 22802",
    "addr:housenumber":"428",
    "addr:postcode":"22802",
    "addr:street":"Lee Ave",
    "iso:country":"US",
    "sg:address":"428 Lee Ave",
    "sg:city":"Harrisonburg",
    "sg:classifiers":[
        {
            "category":"Professional",
            "type":"Services"
        }
    ],
    "sg:phone":"+1 540 433 5199",
    "sg:postcode":"22802",
    "sg:province":"VA",
    "wof:name":"Hayden Music of Roahoke I",
    "wof:placetype":"venue"
},
  "geometry": {"coordinates":[-78.87255,38.455036],"type":"Point"}
}