{
  "type": "Feature",
  "properties": {
    "addr:full":"4400 W Braddock Rd Alexandria VA 22304",
    "addr:housenumber":"4400",
    "addr:postcode":"22304",
    "addr:street":"W Braddock Rd",
    "iso:country":"US",
    "sg:address":"4400 W Braddock Rd",
    "sg:city":"Alexandria",
    "sg:classifiers":[
        {
            "category":"Place Of Worship",
            "subcategory":"Church",
            "type":"Public Place"
        },
        {
            "category":"Place Of Worship",
            "type":"Public Place"
        },
        {
            "category":"Organizations",
            "subcategory":"Religious Organization",
            "type":"Services"
        }
    ],
    "sg:phone":"+1 703 379 6000",
    "sg:postcode":"22304",
    "sg:province":"VA",
    "sg:tags":[
        "science",
        "churches-christian",
        "churches-religious"
    ],
    "wof:name":"Lynn House",
    "wof:placetype":"venue"
},
  "geometry": {"coordinates":[-77.103821,38.82933],"type":"Point"}
}