{
  "type": "Feature",
  "properties": {
    "iso:country":"US",
    "sg:address":"510 King St",
    "sg:city":"Alexandria",
    "sg:classifiers":[
        {
            "category":"Professional",
            "subcategory":"Lawyer & Legal Services",
            "type":"Services"
        }
    ],
    "sg:phone":"+1 703 836 8557",
    "sg:postcode":"22314",
    "sg:province":"VA",
    "sg:tags":[
        "attorney"
    ],
    "wof:name":"Kathleen Murphy Ring",
    "wof:placetype":"venue"
},
  "geometry": {"coordinates":[-77.04575199999999,38.804826],"type":"Point"}
}