{
  "type": "Feature",
  "properties": {
    "addr:full":"779 Center St Herndon VA 20170",
    "addr:housenumber":"779",
    "addr:postcode":"20170",
    "addr:street":"Center St",
    "iso:country":"US",
    "sg:address":"779 Center St",
    "sg:city":"Herndon",
    "sg:classifiers":[
        {
            "category":"Organizations",
            "subcategory":"Community Association",
            "type":"Services"
        }
    ],
    "sg:phone":"+1 703 437 8075",
    "sg:postcode":"20170",
    "sg:province":"VA",
    "wof:name":"Lodge 2274 - Herndon",
    "wof:placetype":"venue"
},
  "geometry": {"coordinates":[-77.385656,38.971989],"type":"Point"}
}