{
  "type": "Feature",
  "properties": {
    "iso:country":"US",
    "sg:address":"6505 Markwood Rd",
    "sg:city":"Earlysville",
    "sg:classifiers":[
        {
            "category":"Building & Trades",
            "subcategory":"Plumbing",
            "type":"Services"
        }
    ],
    "sg:phone":"+1 434 973 1957",
    "sg:postcode":"22936",
    "sg:province":"VA",
    "sg:tags":[
        "conditioning",
        "air",
        "system",
        "contractor"
    ],
    "wof:name":"Yowell Heating & Air Cond Inc",
    "wof:placetype":"venue"
},
  "geometry": {"coordinates":[-78.54327600000001,38.209621],"type":"Point"}
}