{
  "type": "Feature",
  "properties": {
    "iso:country":"US",
    "sg:address":"8791 Commerce Ct",
    "sg:city":"Manassas",
    "sg:classifiers":[
        {
            "category":"Building & Trades",
            "subcategory":"Pest Control",
            "type":"Services"
        }
    ],
    "sg:phone":"+1 703 335 6556",
    "sg:postcode":"20110",
    "sg:province":"VA",
    "wof:name":"Pest Management Services Inc",
    "wof:placetype":"venue"
},
  "geometry": {"coordinates":[-77.45957300000001,38.759743],"type":"Point"}
}