{
  "type": "Feature",
  "properties": {
    "addr:full":"16492 Mlc Ln Rockville VA 23146",
    "addr:housenumber":"16492",
    "addr:postcode":"23146",
    "addr:street":"Mlc Ln",
    "iso:country":"US",
    "sg:address":"16492 Mlc Ln",
    "sg:city":"Rockville",
    "sg:classifiers":[
        {
            "category":"Communications",
            "subcategory":"News Services",
            "type":"Services"
        }
    ],
    "sg:phone":"+1 804 749 3774",
    "sg:postcode":"23146",
    "sg:province":"VA",
    "wof:name":"Commodity News Brief",
    "wof:placetype":"venue"
},
  "geometry": {"coordinates":[-77.665256,37.743683],"type":"Point"}
}