{
  "type": "Feature",
  "properties": {
    "addr:full":"5222 Fairfield Blvd Virginia Beach VA 23464",
    "addr:housenumber":"5222",
    "addr:postcode":"23464",
    "addr:street":"Fairfield Blvd",
    "iso:country":"US",
    "sg:address":"5222 Fairfield Blvd",
    "sg:city":"Virginia Beach",
    "sg:classifiers":[
        {
            "category":"Shopping",
            "subcategory":"Shoes",
            "type":"Retail Goods"
        }
    ],
    "sg:phone":"+1 757 467 6029",
    "sg:postcode":"23464",
    "sg:province":"VA",
    "sg:tags":[
        "shoe",
        "store"
    ],
    "wof:name":"Payless Shoesource Mdsg",
    "wof:placetype":"venue"
},
  "geometry": {"coordinates":[-76.16420599999999,36.82265],"type":"Point"}
}