{
  "type": "Feature",
  "properties": {
    "iso:country":"US",
    "sg:address":"991 Mica Rd",
    "sg:city":"Ridgeway",
    "sg:classifiers":[
        {
            "category":"Manufacturing",
            "subcategory":"Furniture",
            "type":"Manufacturing & Wholesale Goods"
        }
    ],
    "sg:phone":"+1 276 956 2322",
    "sg:postcode":"24148",
    "sg:province":"VA",
    "sg:tags":[
        "household",
        "wood",
        "mfg"
    ],
    "wof:name":"Sheppard Furniture Co",
    "wof:placetype":"venue"
},
  "geometry": {"coordinates":[-79.860246,36.591033],"type":"Point"}
}