{
  "type": "Feature",
  "properties": {
    "iso:country":"US",
    "sg:address":"3709 Cannon Point Dr",
    "sg:city":"Chesapeake",
    "sg:classifiers":[
        {
            "category":"Building & Trades",
            "subcategory":"Plumbing",
            "type":"Services"
        }
    ],
    "sg:phone":"+1 757 484 7420",
    "sg:postcode":"23321",
    "sg:province":"VA",
    "sg:tags":[
        "contractor"
    ],
    "wof:name":"Haskells Heating & Cooling",
    "wof:placetype":"venue"
},
  "geometry": {"coordinates":[-76.389926,36.839592],"type":"Point"}
}