{
  "type": "Feature",
  "properties": {
    "addr:full":"190 James River Rd Scottsville VA 24590",
    "addr:housenumber":"190",
    "addr:postcode":"24590",
    "addr:street":"James River Rd",
    "iso:country":"US",
    "sg:address":"190 James River Rd",
    "sg:city":"Scottsville",
    "sg:classifiers":[
        {
            "category":"Health Services",
            "subcategory":"Health Practitioner",
            "type":"Services"
        }
    ],
    "sg:phone":"+1 434 286 4491",
    "sg:postcode":"24590",
    "sg:province":"VA",
    "sg:tags":[
        "therapist",
        "physical"
    ],
    "wof:name":"Progressive Therapy Inc",
    "wof:placetype":"venue"
},
  "geometry": {"coordinates":[-78.502636,37.80744],"type":"Point"}
}