{
  "type": "Feature",
  "properties": {
    "addr:full":"2915 Elmsmeade Ct Oakton VA 22124",
    "addr:housenumber":"2915",
    "addr:postcode":"22124",
    "addr:street":"Elmsmeade Ct",
    "iso:country":"US",
    "sg:address":"2915 Elmsmeade Ct",
    "sg:city":"Oakton",
    "sg:classifiers":[
        {
            "category":"Professional",
            "type":"Services"
        }
    ],
    "sg:phone":"+1 703 938 5362",
    "sg:postcode":"22124",
    "sg:province":"VA",
    "wof:name":"Focal Point Radio",
    "wof:placetype":"venue"
},
  "geometry": {"coordinates":[-77.31136100000001,38.878422],"type":"Point"}
}