{
  "type": "Feature",
  "properties": {
    "iso:country":"US",
    "sg:address":"8215 Hull Street Rd",
    "sg:city":"Richmond",
    "sg:classifiers":[
        {
            "category":"Social Services",
            "type":"Services"
        }
    ],
    "sg:phone":"+1 804 276 4006",
    "sg:postcode":"23235",
    "sg:province":"VA",
    "sg:tags":[
        "care",
        "centers-adult",
        "center",
        "day"
    ],
    "wof:name":"Chesterfield Adult Day Service",
    "wof:placetype":"venue"
},
  "geometry": {"coordinates":[-77.545182,37.460574],"type":"Point"}
}