{
  "type": "Feature",
  "properties": {
    "addr:full":"12500 Warwick Blvd Newport News VA 23606",
    "addr:housenumber":"12500",
    "addr:postcode":"23606",
    "addr:street":"Warwick Blvd",
    "iso:country":"US",
    "sg:address":"12500 Warwick Blvd",
    "sg:city":"Newport News",
    "sg:classifiers":[
        {
            "category":"Shopping",
            "subcategory":"Pharmacy",
            "type":"Retail Goods"
        }
    ],
    "sg:phone":"+1 757 595 1151",
    "sg:postcode":"23606",
    "sg:province":"VA",
    "wof:name":"Hidenwood Pharmacy",
    "wof:placetype":"venue"
},
  "geometry": {"coordinates":[-76.495181,37.077304],"type":"Point"}
}