{
  "type": "Feature",
  "properties": {
    "addr:full":"1951 Kidwell Dr Vienna VA 22182",
    "addr:housenumber":"1951",
    "addr:postcode":"22182",
    "addr:street":"Kidwell Dr",
    "iso:country":"US",
    "sg:address":"1951 Kidwell Dr",
    "sg:city":"Vienna",
    "sg:classifiers":[
        {
            "category":"Real Estate",
            "subcategory":"Real Estate Agent",
            "type":"Services"
        }
    ],
    "sg:phone":"+1 703 564 2900",
    "sg:postcode":"22182",
    "sg:province":"VA",
    "wof:name":"Capitol Realty Services LLC",
    "wof:placetype":"venue"
},
  "geometry": {"coordinates":[-77.220831,38.910944],"type":"Point"}
}