{
  "type": "Feature",
  "properties": {
    "addr:full":"12528 Warwick Blvd Newport News VA 23606",
    "addr:housenumber":"12528",
    "addr:postcode":"23606",
    "addr:street":"Warwick Blvd",
    "iso:country":"US",
    "sg:address":"12528 Warwick Blvd",
    "sg:city":"Newport News",
    "sg:classifiers":[
        {
            "category":"Health Services",
            "subcategory":"Doctor",
            "type":"Services"
        }
    ],
    "sg:phone":"+1 757 596 4221",
    "sg:postcode":"23606",
    "sg:province":"VA",
    "sg:tags":[
        "dentist"
    ],
    "wof:name":"Wild & Koun",
    "wof:placetype":"venue"
},
  "geometry": {"coordinates":[-76.49640599999999,37.079177],"type":"Point"}
}