{
  "type": "Feature",
  "properties": {
    "addr:full":"2852 Jefferson Davis Hwy Stafford VA 22554",
    "addr:housenumber":"2852",
    "addr:postcode":"22554",
    "addr:street":"Jefferson Davis Hwy",
    "iso:country":"US",
    "sg:address":"2852 Jefferson Davis Hwy",
    "sg:city":"Stafford",
    "sg:classifiers":[
        {
            "category":"Health Services",
            "subcategory":"Optometrist",
            "type":"Services"
        }
    ],
    "sg:phone":"+1 540 720 2020",
    "sg:postcode":"22554",
    "sg:province":"VA",
    "sg:tags":[
        "optical",
        "good"
    ],
    "wof:name":"Mancini Jenise Koziol Od",
    "wof:placetype":"venue"
},
  "geometry": {"coordinates":[-77.405541,38.463488],"type":"Point"}
}