{
  "type": "Feature",
  "properties": {
    "iso:country":"US",
    "sg:address":"8995 Meadowview Dr",
    "sg:city":"Manassas",
    "sg:classifiers":[
        {
            "category":"Building & Trades",
            "subcategory":"Construction",
            "type":"Services"
        }
    ],
    "sg:phone":"+1 703 361 2879",
    "sg:postcode":"20110",
    "sg:province":"VA",
    "sg:tags":[
        "home",
        "remodeling",
        "contractor"
    ],
    "wof:name":"Reids Home Improvement Inc",
    "wof:placetype":"venue"
},
  "geometry": {"coordinates":[-77.466455,38.739132],"type":"Point"}
}