{
  "type": "Feature",
  "properties": {
    "addr:full":"144 Smith Hollow Rd Blacksburg VA 24084",
    "addr:housenumber":"144",
    "addr:postcode":"24084",
    "addr:street":"Smith Hollow Rd",
    "iso:country":"US",
    "sg:address":"144 Smith Hollow Rd",
    "sg:city":"Blacksburg",
    "sg:classifiers":[
        {
            "category":"Recreation",
            "type":"Entertainment"
        }
    ],
    "sg:phone":"+1 540 231 6480",
    "sg:postcode":"24084",
    "sg:province":"VA",
    "wof:name":"Teaching & Learning",
    "wof:placetype":"venue"
},
  "geometry": {"coordinates":[-81.093296,37.03814],"type":"Point"}
}