{
  "type": "Feature",
  "properties": {
    "addr:full":"182 Ikenberry Rd Boones Mill VA 24065",
    "addr:housenumber":"182",
    "addr:postcode":"24065",
    "addr:street":"Ikenberry Rd Boones",
    "iso:country":"US",
    "sg:address":"182 Ikenberry Rd",
    "sg:city":"Boones Mill",
    "sg:classifiers":[
        {
            "category":"Shopping",
            "type":"Retail Goods"
        }
    ],
    "sg:phone":"+1 540 353 5141",
    "sg:postcode":"24065",
    "sg:province":"VA",
    "sg:tags":[
        "merchandise"
    ],
    "wof:name":"Pinkley Designs",
    "wof:placetype":"venue"
},
  "geometry": {"coordinates":[-79.943736,37.068579],"type":"Point"}
}