{
  "type": "Feature",
  "properties": {
    "addr:full":"11620 Jefferson Davis Hwy Chester VA 23831",
    "addr:housenumber":"11620",
    "addr:postcode":"23831",
    "addr:street":"Jefferson Davis Hwy",
    "iso:country":"US",
    "sg:address":"11620 Jefferson Davis Hwy",
    "sg:city":"Chester",
    "sg:classifiers":[
        {
            "category":"Autos & Motor Vehicles",
            "subcategory":"Auto Supplies",
            "type":"Retail Goods"
        }
    ],
    "sg:phone":"+1 804 768 0130",
    "sg:postcode":"23831",
    "sg:province":"VA",
    "sg:tags":[
        "automobile",
        "parts"
    ],
    "sg:website":"www.advancedautoparts.com",
    "wof:name":"Advance Auto Parts Inc",
    "wof:placetype":"venue"
},
  "geometry": {"coordinates":[-77.417789,37.369462],"type":"Point"}
}