{
  "type": "Feature",
  "properties": {
    "addr:full":"8013 Langley Dr Glen Allen VA 23060",
    "addr:housenumber":"8013",
    "addr:postcode":"23060",
    "addr:street":"Langley Dr",
    "iso:country":"US",
    "sg:address":"8013 Langley Dr",
    "sg:city":"Glen Allen",
    "sg:classifiers":[
        {
            "category":"Retail",
            "subcategory":"Repair Shop",
            "type":"Services"
        }
    ],
    "sg:phone":"+1 804 266 1700",
    "sg:postcode":"23060",
    "sg:province":"VA",
    "wof:name":"Jims Medical",
    "wof:placetype":"venue"
},
  "geometry": {"coordinates":[-77.477806,37.65037],"type":"Point"}
}