{
  "type": "Feature",
  "properties": {
    "iso:country":"US",
    "sg:address":"4256 Callaghan Cir",
    "sg:city":"Covington",
    "sg:classifiers":[
        {
            "category":"Manufacturing",
            "subcategory":"Tools & Machinery",
            "type":"Manufacturing & Wholesale Goods"
        }
    ],
    "sg:phone":"+1 540 962 4779",
    "sg:postcode":"24426",
    "sg:province":"VA",
    "sg:tags":[
        "industrial",
        "mfg"
    ],
    "wof:name":"Callaghan Machine Shop",
    "wof:placetype":"venue"
},
  "geometry": {"coordinates":[-80.07747500000001,37.812436],"type":"Point"}
}