{
  "type": "Feature",
  "properties": {
    "addr:full":"7614 Tiffany Ct Clifton VA 20124",
    "addr:housenumber":"7614",
    "addr:postcode":"20124",
    "addr:street":"Tiffany Ct",
    "iso:country":"US",
    "sg:address":"7614 Tiffany Ct",
    "sg:city":"Clifton",
    "sg:classifiers":[
        {
            "category":"Professional",
            "subcategory":"Management & Consulting",
            "type":"Services"
        }
    ],
    "sg:phone":"+1 703 830 1355",
    "sg:postcode":"20124",
    "sg:province":"VA",
    "wof:name":"Benefit Management Corporation",
    "wof:placetype":"venue"
},
  "geometry": {"coordinates":[-77.403379,38.769859],"type":"Point"}
}