{
  "type": "Feature",
  "properties": {
    "addr:full":"129 E Main St Luray VA 22835",
    "addr:housenumber":"129",
    "addr:postcode":"22835",
    "addr:street":"E Main St",
    "iso:country":"US",
    "sg:address":"129 E Main St",
    "sg:city":"Luray",
    "sg:classifiers":[
        {
            "category":"Professional",
            "subcategory":"Lawyer & Legal Services",
            "type":"Services"
        }
    ],
    "sg:phone":"+1 540 743 5179",
    "sg:postcode":"22835",
    "sg:province":"VA",
    "sg:tags":[
        "attorney"
    ],
    "wof:name":"Smith Rdger L Counselor At Law",
    "wof:placetype":"venue"
},
  "geometry": {"coordinates":[-78.45692,38.665553],"type":"Point"}
}