{
  "type": "Feature",
  "properties": {
    "addr:full":"856 Turner Ashby Rd Martinsville VA 24112",
    "addr:housenumber":"856",
    "addr:postcode":"24112",
    "addr:street":"Turner Ashby Rd",
    "iso:country":"US",
    "sg:address":"856 Turner Ashby Rd",
    "sg:city":"Martinsville",
    "sg:classifiers":[
        {
            "category":"Professional",
            "subcategory":"Management & Consulting",
            "type":"Services"
        }
    ],
    "sg:phone":"+1 276 638 1134",
    "sg:postcode":"24112",
    "sg:province":"VA",
    "sg:tags":[
        "consultant",
        "resource",
        "human"
    ],
    "wof:name":"Tax Retrieval Systems",
    "wof:placetype":"venue"
},
  "geometry": {"coordinates":[-79.80547799999999,36.676428],"type":"Point"}
}