{
  "type": "Feature",
  "properties": {
    "iso:country":"US",
    "sg:address":"418 Garrisonville Rd",
    "sg:city":"Stafford",
    "sg:classifiers":[
        {
            "category":"Shopping",
            "type":"Retail Goods"
        },
        {
            "category":"Shopping",
            "subcategory":"Computers & Home Electronics",
            "type":"Retail Goods"
        }
    ],
    "sg:phone":"+1 540 659 4520",
    "sg:postcode":"22554",
    "sg:province":"VA",
    "sg:tags":[
        "equipment",
        "electronic",
        "merchandise",
        "supply"
    ],
    "wof:name":"Radio Shack",
    "wof:placetype":"venue"
},
  "geometry": {"coordinates":[-77.42984,38.474585],"type":"Point"}
}