{
  "type": "Feature",
  "properties": {
    "addr:full":"334 Catalpa Rd Lynchburg VA 24502",
    "addr:housenumber":"334",
    "addr:postcode":"24502",
    "addr:street":"Catalpa Rd",
    "iso:country":"US",
    "sg:address":"334 Catalpa Rd",
    "sg:city":"Lynchburg",
    "sg:classifiers":[
        {
            "category":"Retail",
            "subcategory":"Car Wash",
            "type":"Services"
        }
    ],
    "sg:phone":"+1 434 525 7282",
    "sg:postcode":"24502",
    "sg:province":"VA",
    "sg:tags":[
        "carwash"
    ],
    "wof:name":"Sparkle Wash",
    "wof:placetype":"venue"
},
  "geometry": {"coordinates":[-79.272988,37.291999],"type":"Point"}
}