{
  "type": "Feature",
  "properties": {
    "addr:full":"763 Piney Forest Rd Danville VA 24540",
    "addr:housenumber":"763",
    "addr:postcode":"24540",
    "addr:street":"Piney Forest Rd",
    "iso:country":"US",
    "sg:address":"763 Piney Forest Rd",
    "sg:city":"Danville",
    "sg:classifiers":[
        {
            "category":"Wholesale",
            "subcategory":"Electrical",
            "type":"Manufacturing & Wholesale Goods"
        }
    ],
    "sg:phone":"+1 434 575 6222",
    "sg:postcode":"24540",
    "sg:province":"VA",
    "sg:tags":[
        "alarm",
        "burglar",
        "system"
    ],
    "wof:name":"Security Alliance",
    "wof:placetype":"venue"
},
  "geometry": {"coordinates":[-79.40577500000001,36.615003],"type":"Point"}
}