{
  "type": "Feature",
  "properties": {
    "addr:full":"19844 James Monroe Hwy Leesburg VA 20175",
    "addr:housenumber":"19844",
    "addr:postcode":"20175",
    "addr:street":"James Monroe Hwy",
    "iso:country":"US",
    "sg:address":"19844 James Monroe Hwy",
    "sg:city":"Leesburg",
    "sg:classifiers":[
        {
            "category":"Shopping",
            "subcategory":"Bicycles & Sporting Goods",
            "type":"Retail Goods"
        }
    ],
    "sg:phone":"+1 703 779 2689",
    "sg:postcode":"20175",
    "sg:province":"VA",
    "sg:tags":[
        "training",
        "horse",
        "sales"
    ],
    "wof:name":"European Sport Horses of Amer",
    "wof:placetype":"venue"
},
  "geometry": {"coordinates":[-77.61118399999999,39.067989],"type":"Point"}
}