{
  "type": "Feature",
  "properties": {
    "addr:full":"233 N Union St Danville VA 24541",
    "addr:housenumber":"233",
    "addr:postcode":"24541",
    "addr:street":"N Union St",
    "iso:country":"US",
    "sg:address":"233 N Union St",
    "sg:city":"Danville",
    "sg:classifiers":[
        {
            "category":"Personal",
            "subcategory":"Barber",
            "type":"Services"
        }
    ],
    "sg:phone":"+1 434 792 9860",
    "sg:postcode":"24541",
    "sg:province":"VA",
    "wof:name":"Headhunters Barber Salon",
    "wof:placetype":"venue"
},
  "geometry": {"coordinates":[-79.393908,36.589306],"type":"Point"}
}