{
  "type": "Feature",
  "properties": {
    "addr:full":"217 Franklin St Harrisonburg VA 22801",
    "addr:housenumber":"217",
    "addr:postcode":"22801",
    "addr:street":"Franklin St",
    "iso:country":"US",
    "sg:address":"217 Franklin St",
    "sg:city":"Harrisonburg",
    "sg:classifiers":[
        {
            "category":"Professional",
            "subcategory":"Lawyer & Legal Services",
            "type":"Services"
        }
    ],
    "sg:phone":"+1 540 433 6661",
    "sg:postcode":"22801",
    "sg:province":"VA",
    "wof:name":"Exchangers Ltd",
    "wof:placetype":"venue"
},
  "geometry": {"coordinates":[-78.867034,38.446283],"type":"Point"}
}