{
  "type": "Feature",
  "properties": {
    "iso:country":"US",
    "sg:address":"2212 Mt. Vernon Ave 2nd Fl",
    "sg:city":"Alexandria",
    "sg:classifiers":[
        {
            "category":"Personal",
            "subcategory":"Massage",
            "type":"Services"
        },
        {
            "category":"Personal",
            "subcategory":"Day Spa",
            "type":"Services"
        },
        {
            "category":"Personal",
            "subcategory":"Skin Care",
            "type":"Services"
        },
        {
            "category":"Health Services",
            "subcategory":"Chiropractor",
            "type":"Services"
        }
    ],
    "sg:phone":"+1 703 664 0184",
    "sg:postcode":"22301",
    "sg:province":"VA",
    "sg:tags":[
        "information",
        "referral",
        "chiropractic"
    ],
    "sg:website":"www.PureAesthetica.com",
    "wof:name":"Pure Aesthetica",
    "wof:placetype":"venue"
},
  "geometry": {"coordinates":[-77.05872100000001,38.825771],"type":"Point"}
}