{
  "type": "Feature",
  "properties": {
    "addr:full":"2121 Colonial Ave SW Roanoke VA 24015",
    "addr:housenumber":"2121",
    "addr:postcode":"24015",
    "addr:street":"Colonial Ave Sw",
    "iso:country":"US",
    "sg:address":"2121 Colonial Ave SW",
    "sg:city":"Roanoke",
    "sg:classifiers":[
        {
            "category":"Restaurant",
            "type":"Food & Drink"
        }
    ],
    "sg:phone":"+1 540 343 9708",
    "sg:postcode":"24015",
    "sg:province":"VA",
    "sg:tags":[
        "asian",
        "chinese",
        "pan"
    ],
    "wof:name":"Great Wall",
    "wof:placetype":"venue"
},
  "geometry": {"coordinates":[-79.955181,37.255266],"type":"Point"}
}