{
  "type": "Feature",
  "properties": {
    "addr:full":"901 N Pitt St Ste 325 Alexandria VA 22314",
    "addr:housenumber":"901",
    "addr:postcode":"22314",
    "addr:street":"N Pitt St Ste 325",
    "iso:country":"US",
    "sg:address":"901 N Pitt St Ste 325",
    "sg:city":"Alexandria",
    "sg:classifiers":[
        {
            "category":"Professional",
            "subcategory":"Computer Services",
            "type":"Services"
        },
        {
            "category":"Wholesale",
            "subcategory":"Computers",
            "type":"Manufacturing & Wholesale Goods"
        }
    ],
    "sg:phone":"+1 703 739 3210",
    "sg:postcode":"22314",
    "sg:province":"VA",
    "sg:tags":[
        "equipment",
        "cd-rom",
        "software"
    ],
    "wof:name":"Advanced Solutions International",
    "wof:placetype":"venue"
},
  "geometry": {"coordinates":[-77.042778,38.81385],"type":"Point"}
}