{
  "type": "Feature",
  "properties": {
    "addr:full":"307 Lansing Ave Lynchburg VA 24503",
    "addr:housenumber":"307",
    "addr:postcode":"24503",
    "addr:street":"Lansing Ave",
    "iso:country":"US",
    "sg:address":"307 Lansing Ave",
    "sg:city":"Lynchburg",
    "sg:classifiers":[
        {
            "category":"Community Center",
            "subcategory":"Youth",
            "type":"Public Place"
        }
    ],
    "sg:phone":"+1 434 846 7108",
    "sg:postcode":"24503",
    "sg:province":"VA",
    "wof:name":"Artzone",
    "wof:placetype":"venue"
},
  "geometry": {"coordinates":[-79.171199,37.432369],"type":"Point"}
}