{
  "type": "Feature",
  "properties": {
    "iso:country":"US",
    "sg:address":"2841 Denbigh Blvd",
    "sg:city":"Yorktown",
    "sg:classifiers":[
        {
            "category":"Personal",
            "subcategory":"Beauty Salon",
            "type":"Services"
        }
    ],
    "sg:phone":"+1 757 898 4412",
    "sg:postcode":"23692",
    "sg:province":"VA",
    "wof:name":"A J's Beauty Salon",
    "wof:placetype":"venue"
},
  "geometry": {"coordinates":[-76.476337,37.172132],"type":"Point"}
}