{
  "type": "Feature",
  "properties": {
    "addr:full":"2301 Taylor Rd Chesapeake VA 23321",
    "addr:housenumber":"2301",
    "addr:postcode":"23321",
    "addr:street":"Taylor Rd",
    "iso:country":"US",
    "sg:address":"2301 Taylor Rd",
    "sg:city":"Chesapeake",
    "sg:classifiers":[
        {
            "category":"Shopping",
            "subcategory":"Discount & Variety Stores",
            "type":"Retail Goods"
        },
        {
            "category":"Shopping",
            "subcategory":"Department Store",
            "type":"Retail Goods"
        }
    ],
    "sg:phone":"+1 757 465 2700",
    "sg:postcode":"23321",
    "sg:province":"VA",
    "sg:tags":[
        "warehouse",
        "club"
    ],
    "wof:name":"Bj's Wholesale Club",
    "wof:placetype":"venue"
},
  "geometry": {"coordinates":[-76.408751,36.821374],"type":"Point"}
}