{
  "type": "Feature",
  "properties": {
    "addr:full":"4505 Oak Hollow Rd Chester VA 23831",
    "addr:housenumber":"4505",
    "addr:postcode":"23831",
    "addr:street":"Oak Hollow Rd",
    "iso:country":"US",
    "sg:address":"4505 Oak Hollow Rd",
    "sg:city":"Chester",
    "sg:classifiers":[
        {
            "category":"Professional",
            "subcategory":"Computer Services",
            "type":"Services"
        }
    ],
    "sg:phone":"+1 804 943 1046",
    "sg:postcode":"23831",
    "sg:province":"VA",
    "wof:name":"Network Business Technologies",
    "wof:placetype":"venue"
},
  "geometry": {"coordinates":[-77.440358,37.323637],"type":"Point"}
}