{
  "type": "Feature",
  "properties": {
    "iso:country":"US",
    "sg:address":"154 Chessington Rd",
    "sg:city":"Richmond",
    "sg:classifiers":[
        {
            "category":"Shopping",
            "subcategory":"Catalog Store",
            "type":"Retail Goods"
        },
        {
            "category":"Professional",
            "subcategory":"Accounting & Tax Preparation",
            "type":"Services"
        }
    ],
    "sg:phone":"+1 804 320 4630",
    "sg:postcode":"23236",
    "sg:province":"VA",
    "sg:tags":[
        "mail",
        "billing",
        "house"
    ],
    "wof:name":"Metro Politan Health System",
    "wof:placetype":"venue"
},
  "geometry": {"coordinates":[-77.573176,37.494585],"type":"Point"}
}