{
  "type": "Feature",
  "properties": {
    "addr:full":"744 Berryville Ave Winchester VA 22601",
    "addr:housenumber":"744",
    "addr:postcode":"22601",
    "addr:street":"Berryville Ave",
    "iso:country":"US",
    "sg:address":"744 Berryville Ave",
    "sg:city":"Winchester",
    "sg:classifiers":[
        {
            "category":"Cinema",
            "subcategory":"Movie Rental",
            "type":"Entertainment"
        }
    ],
    "sg:phone":"+1 540 678 8070",
    "sg:postcode":"22601",
    "sg:province":"VA",
    "sg:tags":[
        "video",
        "tape"
    ],
    "wof:name":"Hit List Video",
    "wof:placetype":"venue"
},
  "geometry": {"coordinates":[-78.148982,39.186175],"type":"Point"}
}