{
  "type": "Feature",
  "properties": {
    "addr:full":"14011 Broadview Ln Culpeper VA 22701",
    "addr:housenumber":"14011",
    "addr:postcode":"22701",
    "addr:street":"Broadview Ln",
    "iso:country":"US",
    "sg:address":"14011 Broadview Ln",
    "sg:city":"Culpeper",
    "sg:classifiers":[
        {
            "category":"Wholesale",
            "subcategory":"Non-durable Goods",
            "type":"Manufacturing & Wholesale Goods"
        }
    ],
    "sg:phone":"+1 540 829 9374",
    "sg:postcode":"22701",
    "sg:province":"VA",
    "wof:name":"Whk Distributors",
    "wof:placetype":"venue"
},
  "geometry": {"coordinates":[-77.96762200000001,38.509189],"type":"Point"}
}