{
  "type": "Feature",
  "properties": {
    "iso:country":"US",
    "sg:address":"624 Pine Grove Rd",
    "sg:city":"Stanley",
    "sg:classifiers":[
        {
            "category":"Retail",
            "subcategory":"Repair Shop",
            "type":"Services"
        }
    ],
    "sg:phone":"+1 540 778 4078",
    "sg:postcode":"22851",
    "sg:province":"VA",
    "wof:name":"Painter Taxidermy",
    "wof:placetype":"venue"
},
  "geometry": {"coordinates":[-78.48441,38.560399],"type":"Point"}
}