{
  "type": "Feature",
  "properties": {
    "iso:country":"US",
    "sg:address":"9002 Lupine Den Dr",
    "sg:city":"Vienna",
    "sg:classifiers":[
        {
            "category":"Real Estate",
            "subcategory":"Real Estate Agent",
            "type":"Services"
        }
    ],
    "sg:phone":"+1 703 281 0667",
    "sg:postcode":"22182",
    "sg:province":"VA",
    "wof:name":"Greendale Estates Inc",
    "wof:placetype":"venue"
},
  "geometry": {"coordinates":[-77.256495,38.925125],"type":"Point"}
}