{
  "type": "Feature",
  "properties": {
    "iso:country":"US",
    "sg:address":"1000 Dartmouth Rd",
    "sg:city":"Alexandria",
    "sg:classifiers":[
        {
            "category":"Manufacturing",
            "subcategory":"Buildings",
            "type":"Manufacturing & Wholesale Goods"
        }
    ],
    "sg:phone":"+1 703 505 4001",
    "sg:postcode":"22314",
    "sg:province":"VA",
    "sg:tags":[
        "prefabricated",
        "wood",
        "mfg"
    ],
    "wof:name":"Colonial Structures",
    "wof:placetype":"venue"
},
  "geometry": {"coordinates":[-77.08283900000001,38.811377],"type":"Point"}
}