{
  "type": "Feature",
  "properties": {
    "addr:full":"13663 Lee Jackson Memorial Hwy Chantilly VA 20151",
    "addr:housenumber":"13663",
    "addr:postcode":"20151",
    "addr:street":"Lee Jackson Memorial Hwy",
    "iso:country":"US",
    "sg:address":"13663 Lee Jackson Memorial Hwy",
    "sg:city":"Chantilly",
    "sg:classifiers":[
        {
            "category":"Retail",
            "subcategory":"Car Wash",
            "type":"Services"
        }
    ],
    "sg:phone":"+1 703 961 9774",
    "sg:postcode":"20151",
    "sg:province":"VA",
    "sg:tags":[
        "full",
        "automobile",
        "express",
        "detailing",
        "detail",
        "clean"
    ],
    "wof:name":"Dr Wash",
    "wof:placetype":"venue"
},
  "geometry": {"coordinates":[-77.420939,38.89004],"type":"Point"}
}