{
  "type": "Feature",
  "properties": {
    "addr:full":"9601 4th View St Norfolk VA 23503",
    "addr:housenumber":"9601",
    "addr:postcode":"23503",
    "addr:street":"4Th View St",
    "iso:country":"US",
    "sg:address":"9601 4th View St",
    "sg:city":"Norfolk",
    "sg:classifiers":[
        {
            "category":"Travel",
            "subcategory":"Hotels & Motels",
            "type":"Entertainment"
        }
    ],
    "sg:phone":"+1 757 480 9611",
    "sg:postcode":"23503",
    "sg:province":"VA",
    "wof:name":"Econo Lodge",
    "wof:placetype":"venue"
},
  "geometry": {"coordinates":[-76.26118700000001,36.959847],"type":"Point"}
}