{
  "type": "Feature",
  "properties": {
    "addr:full":"14718 Lee Hwy Centreville VA 20120",
    "addr:housenumber":"14718",
    "addr:postcode":"20120",
    "addr:street":"Lee Hwy",
    "iso:country":"US",
    "sg:address":"14718 Lee Hwy",
    "sg:city":"Centreville",
    "sg:classifiers":[
        {
            "category":"Social Services",
            "subcategory":"Child Care",
            "type":"Services"
        }
    ],
    "sg:phone":"+1 703 830 6336",
    "sg:postcode":"20120",
    "sg:province":"VA",
    "wof:name":"Kinder Care Learning Ctr",
    "wof:placetype":"venue"
},
  "geometry": {"coordinates":[-77.453001,38.835654],"type":"Point"}
}