{
  "type": "Feature",
  "properties": {
    "addr:full":"21300 Ridgetop Cir Sterling VA 20166",
    "addr:housenumber":"21300",
    "addr:postcode":"20166",
    "addr:street":"Ridgetop Cir",
    "iso:country":"US",
    "sg:address":"21300 Ridgetop Cir",
    "sg:city":"Sterling",
    "sg:classifiers":[
        {
            "category":"Manufacturing",
            "subcategory":"Tools & Machinery",
            "type":"Manufacturing & Wholesale Goods"
        }
    ],
    "sg:phone":"+1 703 406 2800",
    "sg:postcode":"20166",
    "sg:province":"VA",
    "sg:tags":[
        "manufacture",
        "environmental",
        "c",
        "monitoring",
        "design"
    ],
    "wof:name":"Sutron Corporation",
    "wof:placetype":"venue"
},
  "geometry": {"coordinates":[-77.412605,39.029619],"type":"Point"}
}