{
  "type": "Feature",
  "properties": {
    "addr:full":"3480 Old Franklin Tpke Glade Hill VA 24151",
    "addr:housenumber":"3480",
    "addr:postcode":"24151",
    "addr:street":"Old Franklin Tpke Glade Hill",
    "iso:country":"US",
    "sg:address":"3480 Old Franklin Tpke",
    "sg:city":"Glade Hill",
    "sg:classifiers":[
        {
            "category":"Food & Beverages",
            "subcategory":"Groceries & Convenience Stores",
            "type":"Retail Goods"
        }
    ],
    "sg:phone":"+1 540 483 3491",
    "sg:postcode":"24151",
    "sg:province":"VA",
    "sg:tags":[
        "grocer"
    ],
    "wof:name":"Redwood Minute Market",
    "wof:placetype":"venue"
},
  "geometry": {"coordinates":[-79.804823,37.01659],"type":"Point"}
}