{
  "type": "Feature",
  "properties": {
    "iso:country":"US",
    "sg:address":"1414 Cottage St SW",
    "sg:city":"Vienna",
    "sg:classifiers":[
        {
            "category":"Recreation",
            "type":"Entertainment"
        }
    ],
    "sg:phone":"+1 703 205 2440",
    "sg:postcode":"22180",
    "sg:province":"VA",
    "wof:name":"C & S Marketing",
    "wof:placetype":"venue"
},
  "geometry": {"coordinates":[-77.247832,38.883146],"type":"Point"}
}