{
  "type": "Feature",
  "properties": {
    "addr:full":"12934 Percival St Chester VA 23831",
    "addr:housenumber":"12934",
    "addr:postcode":"23831",
    "addr:street":"Percival St",
    "iso:country":"US",
    "sg:address":"12934 Percival St",
    "sg:city":"Chester",
    "sg:classifiers":[
        {
            "category":"Professional",
            "subcategory":"Business Services",
            "type":"Services"
        }
    ],
    "sg:phone":"+1 804 748 0770",
    "sg:postcode":"23831",
    "sg:province":"VA",
    "wof:name":"Qualified Telecom Svcs",
    "wof:placetype":"venue"
},
  "geometry": {"coordinates":[-77.43013500000001,37.343567],"type":"Point"}
}