{
  "type": "Feature",
  "properties": {
    "addr:full":"43 Town and Country Dr Fredericksburg VA 22405",
    "addr:housenumber":"43",
    "addr:postcode":"22405",
    "addr:street":"Town And Country Dr",
    "iso:country":"US",
    "sg:address":"43 Town and Country Dr",
    "sg:city":"Fredericksburg",
    "sg:classifiers":[
        {
            "category":"Sports & Exercise",
            "subcategory":"Gym",
            "type":"Entertainment"
        }
    ],
    "sg:phone":"+1 540 368 5533",
    "sg:postcode":"22405",
    "sg:province":"VA",
    "sg:tags":[
        "club",
        "health",
        "studio",
        "gymnasium"
    ],
    "wof:name":"Ladies Workout Express",
    "wof:placetype":"venue"
},
  "geometry": {"coordinates":[-77.428853,38.309582],"type":"Point"}
}