{
  "type": "Feature",
  "properties": {
    "addr:full":"1008 Valley Dr Alexandria VA 22302",
    "addr:housenumber":"1008",
    "addr:postcode":"22302",
    "addr:street":"Valley Dr",
    "iso:country":"US",
    "sg:address":"1008 Valley Dr",
    "sg:city":"Alexandria",
    "sg:classifiers":[
        {
            "category":"Retail",
            "subcategory":"Repair Shop",
            "type":"Services"
        }
    ],
    "sg:phone":"+1 571 274 1047",
    "sg:postcode":"22302",
    "sg:province":"VA",
    "sg:tags":[
        "instrument",
        "musical"
    ],
    "wof:name":"Alberto Grossi Woodwinds",
    "wof:placetype":"venue"
},
  "geometry": {"coordinates":[-77.078863,38.840953],"type":"Point"}
}