{
  "type": "Feature",
  "properties": {
    "iso:country":"US",
    "sg:address":"239 South St",
    "sg:city":"Front Royal",
    "sg:classifiers":[
        {
            "category":"Food & Beverages",
            "subcategory":"Meat & Fish",
            "type":"Retail Goods"
        }
    ],
    "sg:phone":"+1 540 636 6688",
    "sg:postcode":"22630",
    "sg:province":"VA",
    "sg:tags":[
        "seafood"
    ],
    "wof:name":"Coastal Seafood",
    "wof:placetype":"venue"
},
  "geometry": {"coordinates":[-78.191247,38.911717],"type":"Point"}
}