{
  "type": "Feature",
  "properties": {
    "iso:country":"US",
    "sg:address":"664 Red Valley Rd",
    "sg:city":"Boones Mill",
    "sg:classifiers":[
        {
            "category":"Building & Trades",
            "subcategory":"Electrical",
            "type":"Services"
        },
        {
            "category":"Building & Trades",
            "subcategory":"Plumbing",
            "type":"Services"
        }
    ],
    "sg:phone":"+1 540 721 2046",
    "sg:postcode":"24065",
    "sg:province":"VA",
    "sg:tags":[
        "electric",
        "contractor"
    ],
    "wof:name":"Layman Electric & Plumbing Inc",
    "wof:placetype":"venue"
},
  "geometry": {"coordinates":[-79.871064,37.132496],"type":"Point"}
}