{
  "type": "Feature",
  "properties": {
    "addr:full":"2800 Robys Way Midlothian VA 23113",
    "addr:housenumber":"2800",
    "addr:postcode":"23113",
    "addr:street":"Robys Way",
    "iso:country":"US",
    "sg:address":"2800 Robys Way",
    "sg:city":"Midlothian",
    "sg:classifiers":[
        {
            "category":"Building & Trades",
            "subcategory":"Construction",
            "type":"Services"
        }
    ],
    "sg:phone":"+1 804 272 3129",
    "sg:postcode":"23113",
    "sg:province":"VA",
    "sg:tags":[
        "contractor"
    ],
    "wof:name":"M & E Contractors",
    "wof:placetype":"venue"
},
  "geometry": {"coordinates":[-77.60432,37.5345],"type":"Point"}
}