{
  "type": "Feature",
  "properties": {
    "addr:full":"12948 Old Richmond Rd Keeling VA 24566",
    "addr:housenumber":"12948",
    "addr:postcode":"24566",
    "addr:street":"Old Richmond Rd",
    "iso:country":"US",
    "sg:address":"12948 Old Richmond Rd",
    "sg:city":"Keeling",
    "sg:classifiers":[
        {
            "category":"Professional",
            "subcategory":"Business Services",
            "type":"Services"
        }
    ],
    "sg:phone":"+1 434 797 1163",
    "sg:postcode":"24566",
    "sg:province":"VA",
    "wof:name":"Precious Prints & Nik Naks",
    "wof:placetype":"venue"
},
  "geometry": {"coordinates":[-79.286841,36.721002],"type":"Point"}
}