{
  "type": "Feature",
  "properties": {
    "iso:country":"US",
    "sg:address":"1803 Hursley Ct",
    "sg:city":"Vienna",
    "sg:classifiers":[
        {
            "category":"Professional",
            "type":"Services"
        }
    ],
    "sg:phone":"+1 703 938 7713",
    "sg:postcode":"22182",
    "sg:province":"VA",
    "wof:name":"Fenwick Co Inc Vj",
    "wof:placetype":"venue"
},
  "geometry": {"coordinates":[-77.25413,38.922129],"type":"Point"}
}