{
  "type": "Feature",
  "properties": {
    "addr:full":"5000 E Richmond Rd Richmond VA 23223",
    "addr:housenumber":"5000",
    "addr:postcode":"23223",
    "addr:street":"E Richmond Rd",
    "iso:country":"US",
    "sg:address":"5000 E Richmond Rd",
    "sg:city":"Richmond",
    "sg:classifiers":[
        {
            "category":"Building & Trades",
            "subcategory":"Construction",
            "type":"Services"
        }
    ],
    "sg:phone":"+1 804 226 9504",
    "sg:postcode":"23223",
    "sg:province":"VA",
    "sg:tags":[
        "contractor",
        "hanging"
    ],
    "wof:name":"Reese Machine & Sndblst Svc",
    "wof:placetype":"venue"
},
  "geometry": {"coordinates":[-77.38463900000001,37.529098],"type":"Point"}
}