{
  "type": "Feature",
  "properties": {
    "addr:full":"902 N Main St Suffolk VA 23434",
    "addr:housenumber":"902",
    "addr:postcode":"23434",
    "addr:street":"N Main St",
    "iso:country":"US",
    "sg:address":"902 N Main St",
    "sg:city":"Suffolk",
    "sg:classifiers":[
        {
            "category":"Banks & Credit Unions",
            "subcategory":"Bank",
            "type":"Services"
        }
    ],
    "sg:phone":"+1 757 539 6530",
    "sg:postcode":"23434",
    "sg:province":"VA",
    "sg:tags":[
        "personal",
        "financing",
        "institution"
    ],
    "wof:name":"Lendmark Financial Services",
    "wof:placetype":"venue"
},
  "geometry": {"coordinates":[-76.583476,36.74282],"type":"Point"}
}