{
  "type": "Feature",
  "properties": {
    "addr:full":"8717 Parliament Dr Springfield VA 22151",
    "addr:housenumber":"8717",
    "addr:postcode":"22151",
    "addr:street":"Parliament Dr",
    "iso:country":"US",
    "sg:address":"8717 Parliament Dr",
    "sg:city":"Springfield",
    "sg:classifiers":[
        {
            "category":"Retail",
            "subcategory":"Repair Shop",
            "type":"Services"
        }
    ],
    "sg:phone":"+1 703 764 0022",
    "sg:postcode":"22151",
    "sg:province":"VA",
    "sg:tags":[
        "refrigeration"
    ],
    "wof:name":"Hongs Refrigeration Co",
    "wof:placetype":"venue"
},
  "geometry": {"coordinates":[-77.245976,38.806165],"type":"Point"}
}