{
  "type": "Feature",
  "properties": {
    "iso:country":"US",
    "sg:address":"3116 Western Branch Blvd",
    "sg:city":"Chesapeake",
    "sg:classifiers":[
        {
            "category":"Shopping",
            "subcategory":"Clothing, Apparel, & Fashions",
            "type":"Retail Goods"
        }
    ],
    "sg:phone":"+1 757 484 0527",
    "sg:postcode":"23321",
    "sg:province":"VA",
    "sg:tags":[
        "accessory"
    ],
    "wof:name":"Motion",
    "wof:placetype":"venue"
},
  "geometry": {"coordinates":[-76.404188,36.863368],"type":"Point"}
}