{
  "type": "Feature",
  "properties": {
    "iso:country":"US",
    "sg:address":"11747 Jefferson Ave",
    "sg:city":"Newport News",
    "sg:classifiers":[
        {
            "category":"Wholesale",
            "subcategory":"Electrical",
            "type":"Manufacturing & Wholesale Goods"
        }
    ],
    "sg:phone":"+1 757 597 7033",
    "sg:postcode":"23606",
    "sg:province":"VA",
    "sg:tags":[
        "control",
        "security",
        "system"
    ],
    "wof:name":"Broadcast Imagineering",
    "wof:placetype":"venue"
},
  "geometry": {"coordinates":[-76.480687,37.083098],"type":"Point"}
}