{
  "type": "Feature",
  "properties": {
    "iso:country":"US",
    "sg:address":"3407 Silver Maple Pl",
    "sg:city":"Falls Church",
    "sg:classifiers":[
        {
            "category":"Wholesale",
            "subcategory":"Durable Goods & Equipment",
            "type":"Manufacturing & Wholesale Goods"
        }
    ],
    "sg:phone":"+1 703 849 8350",
    "sg:postcode":"22042",
    "sg:province":"VA",
    "sg:tags":[
        "exporter"
    ],
    "wof:name":"Eastern American Trading",
    "wof:placetype":"venue"
},
  "geometry": {"coordinates":[-77.20253099999999,38.851303],"type":"Point"}
}