{
  "type": "Feature",
  "properties": {
    "addr:full":"4240 Harborwood Rd Salem VA 24153",
    "addr:housenumber":"4240",
    "addr:postcode":"24153",
    "addr:street":"Harborwood Rd",
    "iso:country":"US",
    "sg:address":"4240 Harborwood Rd",
    "sg:city":"Salem",
    "sg:classifiers":[
        {
            "category":"Professional",
            "subcategory":"Accounting & Tax Preparation",
            "type":"Services"
        }
    ],
    "sg:phone":"+1 540 380 3027",
    "sg:postcode":"24153",
    "sg:province":"VA",
    "sg:tags":[
        "return",
        "filing"
    ],
    "wof:name":"Gayle Pillow Taxes & Bkpng",
    "wof:placetype":"venue"
},
  "geometry": {"coordinates":[-80.12378699999999,37.240359],"type":"Point"}
}