{
  "type": "Feature",
  "properties": {
    "addr:full":"5109 8th Rd N Arlington VA 22205",
    "addr:housenumber":"5109",
    "addr:postcode":"22205",
    "addr:street":"8Th Rd N",
    "iso:country":"US",
    "sg:address":"5109 8th Rd N",
    "sg:city":"Arlington",
    "sg:classifiers":[
        {
            "category":"Building & Trades",
            "subcategory":"Electrical",
            "type":"Services"
        }
    ],
    "sg:phone":"+1 703 527 1878",
    "sg:postcode":"22205",
    "sg:province":"VA",
    "sg:tags":[
        "electric",
        "contractor"
    ],
    "wof:name":"Bob Electric Co",
    "wof:placetype":"venue"
},
  "geometry": {"coordinates":[-77.12447400000001,38.878741],"type":"Point"}
}