{
  "type": "Feature",
  "properties": {
    "addr:full":"216 Heron Dr Newport News VA 23608",
    "addr:housenumber":"216",
    "addr:postcode":"23608",
    "addr:street":"Heron Dr",
    "iso:country":"US",
    "sg:address":"216 Heron Dr",
    "sg:city":"Newport News",
    "sg:classifiers":[
        {
            "category":"Professional",
            "type":"Services"
        }
    ],
    "sg:phone":"+1 757 887 9327",
    "sg:postcode":"23608",
    "sg:province":"VA",
    "wof:name":"Gwendolyn B Funcheon",
    "wof:placetype":"venue"
},
  "geometry": {"coordinates":[-76.560211,37.158451],"type":"Point"}
}