{
  "type": "Feature",
  "properties": {
    "iso:country":"US",
    "sg:address":"5941 Rockfish Gap Tpke",
    "sg:city":"Crozet",
    "sg:classifiers":[
        {
            "category":"Education",
            "subcategory":"School",
            "type":"Public Place"
        }
    ],
    "sg:phone":"+1 434 823 8700",
    "sg:postcode":"22932",
    "sg:province":"VA",
    "sg:tags":[
        "high"
    ],
    "wof:name":"Western Albemarle High School",
    "wof:placetype":"venue"
},
  "geometry": {"coordinates":[-78.707763,38.050557],"type":"Point"}
}