{
  "type": "Feature",
  "properties": {
    "addr:full":"9701 Brook Rd Glen Allen VA 23059",
    "addr:housenumber":"9701",
    "addr:postcode":"23059",
    "addr:street":"Brook Rd",
    "iso:country":"US",
    "sg:address":"9701 Brook Rd",
    "sg:city":"Glen Allen",
    "sg:classifiers":[
        {
            "category":"Travel",
            "subcategory":"Hotels & Motels",
            "type":"Entertainment"
        }
    ],
    "sg:phone":"+1 804 266 9403",
    "sg:postcode":"23059",
    "sg:province":"VA",
    "wof:name":"Springhill Suites By Marriott",
    "wof:placetype":"venue"
},
  "geometry": {"coordinates":[-77.460024,37.661872],"type":"Point"}
}