{
  "type": "Feature",
  "properties": {
    "addr:full":"136 Franklin Ct Danville VA 24540",
    "addr:housenumber":"136",
    "addr:postcode":"24540",
    "addr:street":"Franklin Ct",
    "iso:country":"US",
    "sg:address":"136 Franklin Ct",
    "sg:city":"Danville",
    "sg:classifiers":[
        {
            "category":"Recreation",
            "type":"Entertainment"
        }
    ],
    "sg:phone":"+1 434 836 2403",
    "sg:postcode":"24540",
    "sg:province":"VA",
    "sg:tags":[
        "martial",
        "arts",
        "instruction"
    ],
    "wof:name":"Divine Fitness & Judo School",
    "wof:placetype":"venue"
},
  "geometry": {"coordinates":[-79.389622,36.629332],"type":"Point"}
}