{
  "type": "Feature",
  "properties": {
    "addr:full":"2615 Anderson Hwy Powhatan VA 23139",
    "addr:housenumber":"2615",
    "addr:postcode":"23139",
    "addr:street":"Anderson Hwy",
    "iso:country":"US",
    "sg:address":"2615 Anderson Hwy",
    "sg:city":"Powhatan",
    "sg:classifiers":[
        {
            "category":"Health Services",
            "subcategory":"Doctor",
            "type":"Services"
        }
    ],
    "sg:phone":"+1 804 598 3000",
    "sg:postcode":"23139",
    "sg:province":"VA",
    "sg:tags":[
        "dentist"
    ],
    "sg:website":"www.wbperkinson.com",
    "wof:name":"Baxter Perkinson & Assoc",
    "wof:placetype":"venue"
},
  "geometry": {"coordinates":[-77.823752,37.522493],"type":"Point"}
}