{
  "type": "Feature",
  "properties": {
    "addr:full":"43330 Junction Plz Ste 172 Ashburn VA 20147",
    "addr:housenumber":"43330",
    "addr:postcode":"20147",
    "addr:street":"Junction Plz Ste 172",
    "iso:country":"US",
    "sg:address":"43330 Junction Plz Ste 172",
    "sg:city":"Ashburn",
    "sg:classifiers":[
        {
            "category":"Retail",
            "subcategory":"Veterinary Services",
            "type":"Services"
        }
    ],
    "sg:phone":"+1 703 726 8784",
    "sg:postcode":"20147",
    "sg:province":"VA",
    "sg:tags":[
        "clinic",
        "hospital",
        "veterinarian",
        "specialty"
    ],
    "sg:website":"http://www.loudounvet.com",
    "wof:name":"Ashburn Farm Animal Hospital",
    "wof:placetype":"venue"
},
  "geometry": {"coordinates":[-77.50281,39.036574],"type":"Point"}
}