{
  "type": "Feature",
  "properties": {
    "addr:full":"9988 Main St Fairfax VA 22031",
    "addr:housenumber":"9988",
    "addr:postcode":"22031",
    "addr:street":"Main St",
    "iso:country":"US",
    "sg:address":"9988 Main St",
    "sg:city":"Fairfax",
    "sg:classifiers":[
        {
            "category":"Home & Garden",
            "subcategory":"Carpets & Floor Coverings",
            "type":"Retail Goods"
        }
    ],
    "sg:phone":"+1 703 273 6784",
    "sg:postcode":"22031",
    "sg:province":"VA",
    "wof:name":"Floor Galaxy & Rugs Inc",
    "wof:placetype":"venue"
},
  "geometry": {"coordinates":[-77.290864,38.843685],"type":"Point"}
}