{
  "type": "Feature",
  "properties": {
    "iso:country":"US",
    "sg:address":"3917 8th St S",
    "sg:city":"Arlington",
    "sg:classifiers":[
        {
            "category":"Organizations",
            "subcategory":"Religious Organization",
            "type":"Services"
        }
    ],
    "sg:phone":"+1 703 979 3917",
    "sg:postcode":"22204",
    "sg:province":"VA",
    "wof:name":"Lynn Billingsley",
    "wof:placetype":"venue"
},
  "geometry": {"coordinates":[-77.098399,38.863117],"type":"Point"}
}