{
  "type": "Feature",
  "properties": {
    "addr:full":"225 Rawlings Rd Rawlings VA 23876",
    "addr:housenumber":"225",
    "addr:postcode":"23876",
    "addr:street":"Rawlings Rd",
    "iso:country":"US",
    "sg:address":"225 Rawlings Rd",
    "sg:city":"Rawlings",
    "sg:classifiers":[
        {
            "category":"Organizations",
            "subcategory":"Religious Organization",
            "type":"Services"
        }
    ],
    "sg:phone":"+1 434 949 0407",
    "sg:postcode":"23876",
    "sg:province":"VA",
    "wof:name":"Hickory Run Baptist Church",
    "wof:placetype":"venue"
},
  "geometry": {"coordinates":[-77.849645,36.965442],"type":"Point"}
}