{
  "type": "Feature",
  "properties": {
    "addr:full":"789 W Main St Abingdon VA 24210",
    "addr:housenumber":"789",
    "addr:postcode":"24210",
    "addr:street":"W Main St",
    "iso:country":"US",
    "sg:address":"789 W Main St",
    "sg:city":"Abingdon",
    "sg:classifiers":[
        {
            "category":"Freight",
            "type":"Transportation"
        }
    ],
    "sg:phone":"+1 276 628 4667",
    "sg:postcode":"24210",
    "sg:province":"VA",
    "sg:tags":[
        "trucking"
    ],
    "wof:name":"Melton Trucking",
    "wof:placetype":"venue"
},
  "geometry": {"coordinates":[-81.997666,36.70493],"type":"Point"}
}