{
  "type": "Feature",
  "properties": {
    "addr:full":"212 South St Farmville VA 23901",
    "addr:housenumber":"212",
    "addr:postcode":"23901",
    "addr:street":"South St",
    "iso:country":"US",
    "sg:address":"212 South St",
    "sg:city":"Farmville",
    "sg:classifiers":[
        {
            "category":"Shopping",
            "subcategory":"Used Merchandise",
            "type":"Retail Goods"
        }
    ],
    "sg:phone":"+1 434 392 8788",
    "sg:postcode":"23901",
    "sg:province":"VA",
    "sg:tags":[
        "shop",
        "consignment"
    ],
    "wof:name":"Broom Tree Ministries",
    "wof:placetype":"venue"
},
  "geometry": {"coordinates":[-78.390406,37.30316],"type":"Point"}
}