{
  "type": "Feature",
  "properties": {
    "iso:country":"US",
    "sg:address":"8370 Tidewater Dr",
    "sg:city":"Norfolk",
    "sg:classifiers":[
        {
            "category":"Restaurant",
            "type":"Food & Drink"
        }
    ],
    "sg:phone":"+1 757 587 8185",
    "sg:postcode":"23518",
    "sg:province":"VA",
    "wof:name":"Pollard's Chicken",
    "wof:placetype":"venue"
},
  "geometry": {"coordinates":[-76.252334,36.92472],"type":"Point"}
}