{
  "type": "Feature",
  "properties": {
    "iso:country":"US",
    "sg:address":"2801 Glade Vale Way",
    "sg:city":"Vienna",
    "sg:classifiers":[
        {
            "category":"Professional",
            "type":"Services"
        }
    ],
    "sg:phone":"+1 703 938 7350",
    "sg:postcode":"22181",
    "sg:province":"VA",
    "wof:name":"Personality By Aggie",
    "wof:placetype":"venue"
},
  "geometry": {"coordinates":[-77.29419300000001,38.886376],"type":"Point"}
}