{
  "type": "Feature",
  "properties": {
    "iso:country":"US",
    "sg:address":"20605 Gordon Park Sq",
    "sg:city":"Ashburn",
    "sg:classifiers":[
        {
            "category":"Insurance",
            "subcategory":"Insurance Agent",
            "type":"Services"
        },
        {
            "category":"Insurance",
            "subcategory":"Hazard Insurance",
            "type":"Services"
        },
        {
            "category":"Insurance",
            "subcategory":"Title Insurance",
            "type":"Services"
        },
        {
            "category":"Insurance",
            "subcategory":"Life Insurance",
            "type":"Services"
        }
    ],
    "sg:phone":"+1 703 724 1981",
    "sg:postcode":"20147",
    "sg:province":"VA",
    "sg:tags":[
        "business",
        "auto",
        "commercial",
        "homeowner",
        "motorcycle",
        "renter"
    ],
    "wof:name":"Allstate Insurance Company - Malan Chakravarthi",
    "wof:placetype":"venue"
},
  "geometry": {"coordinates":[-77.487092,39.046346],"type":"Point"}
}