{
  "type": "Feature",
  "properties": {
    "addr:full":"8130 Porter Rd Falls Church VA 22042",
    "addr:housenumber":"8130",
    "addr:postcode":"22042",
    "addr:street":"Porter Rd",
    "iso:country":"US",
    "sg:address":"8130 Porter Rd",
    "sg:city":"Falls Church",
    "sg:classifiers":[
        {
            "category":"Cinema",
            "subcategory":"Movie Theater",
            "type":"Entertainment"
        }
    ],
    "sg:phone":"+1 703 204 1475",
    "sg:postcode":"22042",
    "sg:province":"VA",
    "wof:name":"Sattelite Movie Co",
    "wof:placetype":"venue"
},
  "geometry": {"coordinates":[-77.226574,38.872683],"type":"Point"}
}