{
  "type": "Feature",
  "properties": {
    "addr:full":"2660 Radford Rd Christiansburg VA 24073",
    "addr:housenumber":"2660",
    "addr:postcode":"24073",
    "addr:street":"Radford Rd",
    "iso:country":"US",
    "sg:address":"2660 Radford Rd",
    "sg:city":"Christiansburg",
    "sg:classifiers":[
        {
            "category":"Restaurant",
            "type":"Food & Drink"
        }
    ],
    "sg:phone":"+1 540 731 1154",
    "sg:postcode":"24073",
    "sg:province":"VA",
    "sg:tags":[
        "eating"
    ],
    "wof:name":"Plum Creek Restaurant",
    "wof:placetype":"venue"
},
  "geometry": {"coordinates":[-80.486181,37.130837],"type":"Point"}
}