{
  "type": "Feature",
  "properties": {
    "iso:country":"US",
    "sg:address":"11921 Freedom Dr",
    "sg:city":"Reston",
    "sg:classifiers":[
        {
            "category":"Professional",
            "subcategory":"Management & Consulting",
            "type":"Services"
        }
    ],
    "sg:phone":"+1 703 925 5907",
    "sg:postcode":"20190",
    "sg:province":"VA",
    "sg:tags":[
        "consultant",
        "business"
    ],
    "wof:name":"MJI",
    "wof:placetype":"venue"
},
  "geometry": {"coordinates":[-77.35851599999999,38.959335],"type":"Point"}
}