{
  "type": "Feature",
  "properties": {
    "iso:country":"US",
    "sg:address":"2302 Hunters Way",
    "sg:city":"Charlottesville",
    "sg:classifiers":[
        {
            "category":"Wholesale",
            "subcategory":"Non-durable Goods",
            "type":"Manufacturing & Wholesale Goods"
        }
    ],
    "sg:phone":"+1 434 245 8400",
    "sg:postcode":"22911",
    "sg:province":"VA",
    "sg:tags":[
        "advertising"
    ],
    "sg:website":"www.gobrightideas.com",
    "wof:name":"Bright Ideas LLC",
    "wof:placetype":"venue"
},
  "geometry": {"coordinates":[-78.418057,38.017988],"type":"Point"}
}