{
  "type": "Feature",
  "properties": {
    "addr:full":"15439 Warwick Blvd Newport News VA 23608",
    "addr:housenumber":"15439",
    "addr:postcode":"23608",
    "addr:street":"Warwick Blvd",
    "iso:country":"US",
    "sg:address":"15439 Warwick Blvd",
    "sg:city":"Newport News",
    "sg:classifiers":[
        {
            "category":"Professional",
            "subcategory":"Accounting & Tax Preparation",
            "type":"Services"
        }
    ],
    "sg:phone":"+1 757 890 1279",
    "sg:postcode":"23608",
    "sg:province":"VA",
    "sg:tags":[
        "return"
    ],
    "wof:name":"H & R Block Newport News",
    "wof:placetype":"venue"
},
  "geometry": {"coordinates":[-76.55441,37.152315],"type":"Point"}
}