{
  "type": "Feature",
  "properties": {
    "addr:full":"Barracks Rd Shp Ctr Charlottesville VA 22901",
    "addr:postcode":"22901",
    "addr:street":"Barracks Rd",
    "iso:country":"US",
    "sg:address":"Barracks Rd Shp Ctr",
    "sg:city":"Charlottesville",
    "sg:classifiers":[
        {
            "category":"Restaurant",
            "type":"Food & Drink"
        }
    ],
    "sg:phone":"+1 434 979 7011",
    "sg:postcode":"22901",
    "sg:province":"VA",
    "sg:tags":[
        "pizza",
        "italian"
    ],
    "wof:name":"Casella's Italian Restaurant",
    "wof:placetype":"venue"
},
  "geometry": {"coordinates":[-78.50039700000001,38.072701],"type":"Point"}
}