{
  "type": "Feature",
  "properties": {
    "addr:full":"11948l Fair Oaks Mall Fairfax VA 22033",
    "addr:housenumber":"11948l",
    "addr:postcode":"22033",
    "addr:street":"Fair Oaks Mall",
    "iso:country":"US",
    "sg:address":"11948l Fair Oaks Mall",
    "sg:city":"Fairfax",
    "sg:classifiers":[
        {
            "category":"Restaurant",
            "type":"Food & Drink"
        }
    ],
    "sg:menulink":"http://www.allmenus.com/va/sully/68327-uno-chicago-grill/menu/",
    "sg:phone":"+1 703 273 8667",
    "sg:postcode":"22033",
    "sg:province":"VA",
    "sg:tags":[
        "american",
        "italian",
        "pizza"
    ],
    "wof:name":"Uno Chicago Grill",
    "wof:placetype":"venue"
},
  "geometry": {"coordinates":[-77.36237,38.864909],"type":"Point"}
}