{
  "type": "Feature",
  "properties": {
    "addr:full":"2411 Virgil H Goode Hwy Rocky Mount VA 24151",
    "addr:housenumber":"2411;h",
    "addr:postcode":"24151",
    "addr:street":"Virgil;Goode Hwy",
    "iso:country":"US",
    "sg:address":"2411 Virgil H Goode Hwy",
    "sg:city":"Rocky Mount",
    "sg:classifiers":[
        {
            "category":"Autos & Motor Vehicles",
            "subcategory":"Automobile Sales",
            "type":"Retail Goods"
        }
    ],
    "sg:phone":"+1 540 483 1900",
    "sg:postcode":"24151",
    "sg:province":"VA",
    "sg:tags":[
        "used"
    ],
    "wof:name":"Tri County Sales",
    "wof:placetype":"venue"
},
  "geometry": {"coordinates":[-79.908226,36.843122],"type":"Point"}
}