{
  "type": "Feature",
  "properties": {
    "iso:country":"US",
    "sg:address":"195 Old Mill Rd",
    "sg:city":"Staunton",
    "sg:classifiers":[
        {
            "category":"Professional",
            "type":"Services"
        }
    ],
    "sg:phone":"+1 540 363 5051",
    "sg:postcode":"24401",
    "sg:province":"VA",
    "wof:name":"Oak Leaf Services",
    "wof:placetype":"venue"
},
  "geometry": {"coordinates":[-78.933466,38.183475],"type":"Point"}
}