{
  "type": "Feature",
  "properties": {
    "iso:country":"US",
    "sg:address":"102 Hill St NE",
    "sg:city":"Christiansburg",
    "sg:classifiers":[
        {
            "category":"Shopping",
            "subcategory":"Musical Instruments",
            "type":"Retail Goods"
        }
    ],
    "sg:phone":"+1 540 381 6406",
    "sg:postcode":"24073",
    "sg:province":"VA",
    "sg:tags":[
        "piano"
    ],
    "wof:name":"Allen Piano Tuning",
    "wof:placetype":"venue"
},
  "geometry": {"coordinates":[-80.40848200000001,37.132078],"type":"Point"}
}