{
  "type": "Feature",
  "properties": {
    "addr:full":"7777 Leesburg Pike Falls Church VA 22043",
    "addr:housenumber":"7777",
    "addr:postcode":"22043",
    "addr:street":"Leesburg Pike",
    "iso:country":"US",
    "sg:address":"7777 Leesburg Pike",
    "sg:city":"Falls Church",
    "sg:classifiers":[
        {
            "category":"Manufacturing",
            "subcategory":"Printing",
            "type":"Manufacturing & Wholesale Goods"
        }
    ],
    "sg:phone":"+1 703 734 8618",
    "sg:postcode":"22043",
    "sg:province":"VA",
    "sg:tags":[
        "company",
        "holding"
    ],
    "wof:name":"UCI",
    "wof:placetype":"venue"
},
  "geometry": {"coordinates":[-77.214259,38.908365],"type":"Point"}
}