{
  "type": "Feature",
  "properties": {
    "addr:full":"9940 Tunstall Rd New Kent VA 23124",
    "addr:housenumber":"9940",
    "addr:postcode":"23124",
    "addr:street":"Tunstall Rd",
    "iso:country":"US",
    "sg:address":"9940 Tunstall Rd",
    "sg:city":"New Kent",
    "sg:classifiers":[
        {
            "category":"Professional",
            "subcategory":"Business Services",
            "type":"Services"
        }
    ],
    "sg:phone":"+1 804 932 4662",
    "sg:postcode":"23124",
    "sg:province":"VA",
    "wof:name":"Pearson Enterprises LLC",
    "wof:placetype":"venue"
},
  "geometry": {"coordinates":[-77.11502900000001,37.534307],"type":"Point"}
}