{
  "type": "Feature",
  "properties": {
    "iso:country":"US",
    "sg:address":"3100 Edison Ln",
    "sg:city":"Blacksburg",
    "sg:classifiers":[
        {
            "category":"Building & Trades",
            "subcategory":"Construction",
            "type":"Services"
        }
    ],
    "sg:phone":"+1 540 552 8035",
    "sg:postcode":"24060",
    "sg:province":"VA",
    "sg:tags":[
        "house"
    ],
    "wof:name":"Cumberland Design Construction",
    "wof:placetype":"venue"
},
  "geometry": {"coordinates":[-80.45312199999999,37.259373],"type":"Point"}
}