{
  "type": "Feature",
  "properties": {
    "iso:country":"US",
    "sg:address":"1511 Starling Dr",
    "sg:city":"Richmond",
    "sg:classifiers":[
        {
            "category":"Health Services",
            "subcategory":"Clinic",
            "type":"Services"
        },
        {
            "category":"Health Services",
            "subcategory":"Doctor",
            "type":"Services"
        }
    ],
    "sg:phone":"+1 804 754 1928",
    "sg:postcode":"23229",
    "sg:province":"VA",
    "sg:tags":[
        "abortion"
    ],
    "wof:name":"A Capital Womens Health Clinic",
    "wof:placetype":"venue"
},
  "geometry": {"coordinates":[-77.568473,37.605564],"type":"Point"}
}