{
  "type": "Feature",
  "properties": {
    "addr:full":"1004 74th St Newport News VA 23605",
    "addr:housenumber":"1004",
    "addr:postcode":"23605",
    "addr:street":"74Th St",
    "iso:country":"US",
    "sg:address":"1004 74th St",
    "sg:city":"Newport News",
    "sg:classifiers":[
        {
            "category":"Building & Trades",
            "subcategory":"Plumbing",
            "type":"Services"
        }
    ],
    "sg:phone":"+1 757 596 6912",
    "sg:postcode":"23605",
    "sg:province":"VA",
    "sg:tags":[
        "plumbing",
        "contractor"
    ],
    "wof:name":"Barrow Plumbing & Heating Co",
    "wof:placetype":"venue"
},
  "geometry": {"coordinates":[-76.42887500000001,37.017869],"type":"Point"}
}