{
  "type": "Feature",
  "properties": {
    "addr:full":"11841 Midlothian Tpke Midlothian VA 23113",
    "addr:housenumber":"11841",
    "addr:postcode":"23113",
    "addr:street":"Midlothian Tpke",
    "iso:country":"US",
    "sg:address":"11841 Midlothian Tpke",
    "sg:city":"Midlothian",
    "sg:phone":"+1 804 378 3000",
    "sg:postcode":"23113",
    "sg:province":"VA",
    "sg:website":"http://www.paylessatpencenissan.com/",
    "wof:name":"Pence Nissan",
    "wof:placetype":"venue"
},
  "geometry": {"coordinates":[-77.618672,37.504452],"type":"Point"}
}