{
  "type": "Feature",
  "properties": {
    "iso:country":"US",
    "sg:address":"1904 Miracle Ln",
    "sg:city":"Falls Church",
    "sg:classifiers":[
        {
            "category":"Organizations",
            "subcategory":"Community Association",
            "type":"Services"
        }
    ],
    "sg:phone":"+1 703 847 9106",
    "sg:postcode":"22043",
    "sg:province":"VA",
    "wof:name":"Lemon Road Civic Assoc In",
    "wof:placetype":"venue"
},
  "geometry": {"coordinates":[-77.19053599999999,38.911995],"type":"Point"}
}