{
  "type": "Feature",
  "properties": {
    "iso:country":"US",
    "sg:address":"10954 Adare Dr",
    "sg:city":"Fairfax",
    "sg:classifiers":[
        {
            "category":"Professional",
            "subcategory":"Engineering",
            "type":"Services"
        }
    ],
    "sg:phone":"+1 703 250 9559",
    "sg:postcode":"22032",
    "sg:province":"VA",
    "sg:tags":[
        "consulting"
    ],
    "wof:name":"Kevin OBrien",
    "wof:placetype":"venue"
},
  "geometry": {"coordinates":[-77.324119,38.803786],"type":"Point"}
}