{
  "type": "Feature",
  "properties": {
    "iso:country":"US",
    "sg:address":"327 South St SE",
    "sg:city":"Leesburg",
    "sg:classifiers":[
        {
            "category":"Retail",
            "subcategory":"Auto Repair",
            "type":"Services"
        }
    ],
    "sg:phone":"+1 703 777 5643",
    "sg:postcode":"20175",
    "sg:province":"VA",
    "sg:tags":[
        "repairing",
        "exhaust",
        "general",
        "automobile"
    ],
    "wof:name":"Dick's Mufflers & Automotive",
    "wof:placetype":"venue"
},
  "geometry": {"coordinates":[-77.557322,39.108342],"type":"Point"}
}