{
  "type": "Feature",
  "properties": {
    "iso:country":"US",
    "sg:address":"2110 S Washington Blvd",
    "sg:city":"Arlington",
    "sg:classifiers":[
        {
            "category":"Wholesale",
            "subcategory":"Office Equipment",
            "type":"Manufacturing & Wholesale Goods"
        }
    ],
    "sg:phone":"+1 703 807 3200",
    "sg:postcode":"22204",
    "sg:province":"VA",
    "sg:tags":[
        "machine",
        "computer",
        "duplicating",
        "copying"
    ],
    "wof:name":"Canon Business Solutions East",
    "wof:placetype":"venue"
},
  "geometry": {"coordinates":[-77.082622,38.872828],"type":"Point"}
}