{
  "type": "Feature",
  "properties": {
    "addr:full":"12695 Valley Oaks Ct Fairfax VA 22033",
    "addr:housenumber":"12695",
    "addr:postcode":"22033",
    "addr:street":"Valley Oaks Ct",
    "iso:country":"US",
    "sg:address":"12695 Valley Oaks Ct",
    "sg:city":"Fairfax",
    "sg:classifiers":[
        {
            "category":"Personal",
            "subcategory":"Beauty Salon",
            "type":"Services"
        }
    ],
    "sg:phone":"+1 703 968 9112",
    "sg:postcode":"22033",
    "sg:province":"VA",
    "sg:tags":[
        "manicuring"
    ],
    "wof:name":"Fancy Nails",
    "wof:placetype":"venue"
},
  "geometry": {"coordinates":[-77.38506700000001,38.884722],"type":"Point"}
}