{
  "type": "Feature",
  "properties": {
    "iso:country":"US",
    "sg:address":"11 Jolama Dr",
    "sg:city":"Newport News",
    "sg:classifiers":[
        {
            "category":"Recreation",
            "type":"Entertainment"
        }
    ],
    "sg:phone":"+1 757 877 2536",
    "sg:postcode":"23602",
    "sg:province":"VA",
    "sg:tags":[
        "pool",
        "swimming"
    ],
    "wof:name":"Quail Run Pool",
    "wof:placetype":"venue"
},
  "geometry": {"coordinates":[-76.556392,37.120449],"type":"Point"}
}