{
  "type": "Feature",
  "properties": {
    "iso:country":"US",
    "sg:address":"11416 Canterbury Rd",
    "sg:city":"Chester",
    "sg:classifiers":[
        {
            "category":"Shopping",
            "subcategory":"Pets & Pet Supplies",
            "type":"Retail Goods"
        }
    ],
    "sg:phone":"+1 804 748 7626",
    "sg:postcode":"23831",
    "sg:province":"VA",
    "sg:tags":[
        "furnishing",
        "dog",
        "store",
        "cat"
    ],
    "wof:name":"Purely Pets",
    "wof:placetype":"venue"
},
  "geometry": {"coordinates":[-77.42325700000001,37.370605],"type":"Point"}
}