{
  "type": "Feature",
  "properties": {
    "iso:country":"US",
    "sg:address":"222 Apple Blossom Ct",
    "sg:city":"Vienna",
    "sg:classifiers":[
        {
            "category":"Education",
            "subcategory":"Special Training",
            "type":"Public Place"
        }
    ],
    "sg:phone":"+1 703 281 6452",
    "sg:postcode":"22181",
    "sg:province":"VA",
    "sg:tags":[
        "instructor"
    ],
    "wof:name":"Araujo Thilys",
    "wof:placetype":"venue"
},
  "geometry": {"coordinates":[-77.273787,38.889425],"type":"Point"}
}