{
  "type": "Feature",
  "properties": {
    "iso:country":"US",
    "sg:address":"6619 Custer St",
    "sg:city":"Springfield",
    "sg:classifiers":[
        {
            "category":"Organizations",
            "subcategory":"Community Association",
            "type":"Services"
        }
    ],
    "sg:phone":"+1 703 719 5580",
    "sg:postcode":"22150",
    "sg:province":"VA",
    "sg:tags":[
        "military"
    ],
    "wof:name":"Society Of The First Infantry",
    "wof:placetype":"venue"
},
  "geometry": {"coordinates":[-77.174802,38.783306],"type":"Point"}
}