{
  "type": "Feature",
  "properties": {
    "addr:full":"1902 Cellar Creek Rd Blackstone VA 23824",
    "addr:housenumber":"1902",
    "addr:postcode":"23824",
    "addr:street":"Cellar Creek Rd",
    "iso:country":"US",
    "sg:address":"1902 Cellar Creek Rd",
    "sg:city":"Blackstone",
    "sg:classifiers":[
        {
            "category":"Building & Trades",
            "subcategory":"Construction",
            "type":"Services"
        }
    ],
    "sg:phone":"+1 434 292 5128",
    "sg:postcode":"23824",
    "sg:province":"VA",
    "sg:tags":[
        "house"
    ],
    "wof:name":"Hardy Builders Inc",
    "wof:placetype":"venue"
},
  "geometry": {"coordinates":[-78.011741,37.145215],"type":"Point"}
}