{
  "type": "Feature",
  "properties": {
    "addr:full":"3711 S Columbia Pike Arlington VA 22204",
    "addr:housenumber":"3711",
    "addr:postcode":"22204",
    "addr:street":"S Columbia Pike",
    "iso:country":"US",
    "sg:address":"3711 S Columbia Pike",
    "sg:city":"Arlington",
    "sg:classifiers":[
        {
            "category":"Manufacturing",
            "subcategory":"Printing",
            "type":"Manufacturing & Wholesale Goods"
        }
    ],
    "sg:phone":"+1 703 521 2569",
    "sg:postcode":"22204",
    "sg:province":"VA",
    "sg:tags":[
        "newspaper"
    ],
    "wof:name":"Pakistan Post Inc",
    "wof:placetype":"venue"
},
  "geometry": {"coordinates":[-77.094774,38.860636],"type":"Point"}
}