{
  "type": "Feature",
  "properties": {
    "iso:country":"US",
    "sg:address":"3652 King St",
    "sg:city":"Alexandria",
    "sg:classifiers":[
        {
            "category":"Shopping",
            "subcategory":"Jewelry",
            "type":"Retail Goods"
        }
    ],
    "sg:phone":"+1 703 379 6010",
    "sg:postcode":"22302",
    "sg:province":"VA",
    "wof:name":"B & C Jewelers",
    "wof:placetype":"venue"
},
  "geometry": {"coordinates":[-77.092394,38.830533],"type":"Point"}
}