{
  "type": "Feature",
  "properties": {
    "addr:full":"4126 Hillcrest Rd Richmond VA 23225",
    "addr:housenumber":"4126",
    "addr:postcode":"23225",
    "addr:street":"Hillcrest Rd",
    "iso:country":"US",
    "sg:address":"4126 Hillcrest Rd",
    "sg:city":"Richmond",
    "sg:classifiers":[
        {
            "category":"Banks & Credit Unions",
            "subcategory":"Investment Brokerage",
            "type":"Services"
        }
    ],
    "sg:phone":"+1 804 232 2008",
    "sg:postcode":"23225",
    "sg:province":"VA",
    "sg:tags":[
        "consultant",
        "planning",
        "financial"
    ],
    "wof:name":"Kent S Greenway Assoc",
    "wof:placetype":"venue"
},
  "geometry": {"coordinates":[-77.475172,37.522769],"type":"Point"}
}