{
  "type": "Feature",
  "properties": {
    "iso:country":"US",
    "sg:address":"2034 Great Falls St",
    "sg:city":"Falls Church",
    "sg:classifiers":[
        {
            "category":"Organizations",
            "subcategory":"Religious Organization",
            "type":"Services"
        }
    ],
    "sg:phone":"+1 703 538 4175",
    "sg:postcode":"22043",
    "sg:province":"VA",
    "sg:tags":[
        "church"
    ],
    "wof:name":"Church Of Jesus Christ Of Lds",
    "wof:placetype":"venue"
},
  "geometry": {"coordinates":[-77.182215,38.906654],"type":"Point"}
}