{
  "type": "Feature",
  "properties": {
    "addr:full":"425 Crosman Ct Purcellville VA 20132",
    "addr:housenumber":"425",
    "addr:postcode":"20132",
    "addr:street":"Crosman Ct",
    "iso:country":"US",
    "sg:address":"425 Crosman Ct",
    "sg:city":"Purcellville",
    "sg:classifiers":[
        {
            "category":"Building & Trades",
            "subcategory":"Construction",
            "type":"Services"
        }
    ],
    "sg:phone":"+1 540 338 2048",
    "sg:postcode":"20132",
    "sg:province":"VA",
    "sg:tags":[
        "contractor"
    ],
    "wof:name":"Loudoun Deck & Fence Co",
    "wof:placetype":"venue"
},
  "geometry": {"coordinates":[-77.708434,39.125504],"type":"Point"}
}