{
  "type": "Feature",
  "properties": {
    "addr:full":"318 The Maine W Williamsburg VA 23185",
    "addr:housenumber":"318",
    "addr:postcode":"23185",
    "addr:street":"The Maine W",
    "iso:country":"US",
    "sg:address":"318 The Maine W",
    "sg:city":"Williamsburg",
    "sg:classifiers":[
        {
            "category":"Building & Trades",
            "subcategory":"Construction",
            "type":"Services"
        }
    ],
    "sg:phone":"+1 757 229 8771",
    "sg:postcode":"23185",
    "sg:province":"VA",
    "sg:tags":[
        "house",
        "contractor"
    ],
    "wof:name":"T M Jolliffe Builder Inc",
    "wof:placetype":"venue"
},
  "geometry": {"coordinates":[-76.814851,37.244355],"type":"Point"}
}