{
  "type": "Feature",
  "properties": {
    "addr:full":"116 Featherbed Ln Winchester VA 22601",
    "addr:housenumber":"116",
    "addr:postcode":"22601",
    "addr:street":"Featherbed Ln",
    "iso:country":"US",
    "sg:address":"116 Featherbed Ln",
    "sg:city":"Winchester",
    "sg:classifiers":[
        {
            "category":"Home & Garden",
            "subcategory":"Carpets & Floor Coverings",
            "type":"Retail Goods"
        }
    ],
    "sg:phone":"+1 540 667 9507",
    "sg:postcode":"22601",
    "sg:province":"VA",
    "sg:tags":[
        "dealer",
        "rug"
    ],
    "sg:website":"www.rugs-direct.com",
    "wof:name":"RUGS-Direct.Com",
    "wof:placetype":"venue"
},
  "geometry": {"coordinates":[-78.169471,39.165001],"type":"Point"}
}