{
  "type": "Feature",
  "properties": {
    "addr:full":"201 Overlook Ct Fredericksburg VA 22405",
    "addr:housenumber":"201",
    "addr:postcode":"22405",
    "addr:street":"Overlook Ct",
    "iso:country":"US",
    "sg:address":"201 Overlook Ct",
    "sg:city":"Fredericksburg",
    "sg:classifiers":[
        {
            "category":"Professional",
            "type":"Services"
        }
    ],
    "sg:phone":"+1 540 371 4445",
    "sg:postcode":"22405",
    "sg:province":"VA",
    "sg:tags":[
        "consultant",
        "geological"
    ],
    "wof:name":"Ground Water & Environmental",
    "wof:placetype":"venue"
},
  "geometry": {"coordinates":[-77.461083,38.329589],"type":"Point"}
}