{
  "type": "Feature",
  "properties": {
    "iso:country":"US",
    "sg:address":"312 Montgomery St",
    "sg:city":"Alexandria",
    "sg:classifiers":[
        {
            "category":"Professional",
            "subcategory":"Management & Consulting",
            "type":"Services"
        }
    ],
    "sg:phone":"+1 703 683 5625",
    "sg:postcode":"22314",
    "sg:province":"VA",
    "wof:name":"Dewees Dev Assoc Ltd Partnr",
    "wof:placetype":"venue"
},
  "geometry": {"coordinates":[-77.04159,38.813633],"type":"Point"}
}