{
  "type": "Feature",
  "properties": {
    "addr:full":"200 Front St Galax VA 24333",
    "addr:housenumber":"200",
    "addr:postcode":"24333",
    "addr:street":"Front St",
    "iso:country":"US",
    "sg:address":"200 Front St",
    "sg:city":"Galax",
    "sg:classifiers":[
        {
            "category":"Professional",
            "subcategory":"Business Services",
            "type":"Services"
        }
    ],
    "sg:phone":"+1 276 236 3681",
    "sg:postcode":"24333",
    "sg:province":"VA",
    "wof:name":"Thomas L Jennings",
    "wof:placetype":"venue"
},
  "geometry": {"coordinates":[-80.92500099999999,36.656411],"type":"Point"}
}