{
  "type": "Feature",
  "properties": {
    "addr:full":"166 Basalt Dr Fredericksburg VA 22406",
    "addr:housenumber":"166",
    "addr:postcode":"22406",
    "addr:street":"Basalt Dr",
    "iso:country":"US",
    "sg:address":"166 Basalt Dr",
    "sg:city":"Fredericksburg",
    "sg:classifiers":[
        {
            "category":"Social Services",
            "type":"Services"
        }
    ],
    "sg:phone":"+1 540 286 2277",
    "sg:postcode":"22406",
    "sg:province":"VA",
    "wof:name":"Counseling Answers",
    "wof:placetype":"venue"
},
  "geometry": {"coordinates":[-77.531628,38.36376],"type":"Point"}
}