{
  "type": "Feature",
  "properties": {
    "addr:full":"5834 Upton St Mc Lean VA 22101",
    "addr:housenumber":"5834",
    "addr:postcode":"22101",
    "addr:street":"Upton St Mc Lean",
    "iso:country":"US",
    "sg:address":"5834 Upton St",
    "sg:city":"Mc Lean",
    "sg:classifiers":[
        {
            "category":"Professional",
            "subcategory":"Management & Consulting",
            "type":"Services"
        }
    ],
    "sg:phone":"+1 703 241 8117",
    "sg:postcode":"22101",
    "sg:province":"VA",
    "sg:tags":[
        "consultant",
        "business"
    ],
    "wof:name":"Executive Consulting Service",
    "wof:placetype":"venue"
},
  "geometry": {"coordinates":[-77.131123,38.928008],"type":"Point"}
}