{
  "type": "Feature",
  "properties": {
    "iso:country":"US",
    "sg:address":"510 S Van Dorn St Ste F",
    "sg:city":"Alexandria",
    "sg:classifiers":[
        {
            "category":"Retail",
            "subcategory":"Repair Shop",
            "type":"Services"
        },
        {
            "category":"Shopping",
            "subcategory":"Crafts & Fabrics",
            "type":"Retail Goods"
        }
    ],
    "sg:phone":"+1 703 370 1520",
    "sg:postcode":"22304",
    "sg:province":"VA",
    "sg:tags":[
        "curtain",
        "upholstery",
        "drapery",
        "upholsterer"
    ],
    "wof:name":"Van Dorn Upholstery",
    "wof:placetype":"venue"
},
  "geometry": {"coordinates":[-77.13319199999999,38.807226],"type":"Point"}
}