{
  "type": "Feature",
  "properties": {
    "addr:full":"821 W Stuart Dr Hillsville VA 24343",
    "addr:housenumber":"821",
    "addr:postcode":"24343",
    "addr:street":"W Stuart Dr",
    "iso:country":"US",
    "sg:address":"821 W Stuart Dr",
    "sg:city":"Hillsville",
    "sg:classifiers":[
        {
            "category":"Professional",
            "type":"Services"
        }
    ],
    "sg:phone":"+1 276 728 9082",
    "sg:postcode":"24343",
    "sg:province":"VA",
    "wof:name":"Brass Exchange",
    "wof:placetype":"venue"
},
  "geometry": {"coordinates":[-80.741477,36.756618],"type":"Point"}
}