{
  "type": "Feature",
  "properties": {
    "addr:full":"1540 Sea Farer Ln Virginia Beach VA 23454",
    "addr:housenumber":"1540",
    "addr:postcode":"23454",
    "addr:street":"Sea Farer Ln",
    "iso:country":"US",
    "sg:address":"1540 Sea Farer Ln",
    "sg:city":"Virginia Beach",
    "sg:classifiers":[
        {
            "category":"Utilities",
            "subcategory":"Telephone",
            "type":"Services"
        }
    ],
    "sg:phone":"+1 757 496 6511",
    "sg:postcode":"23454",
    "sg:province":"VA",
    "sg:tags":[
        "communications"
    ],
    "wof:name":"Jastan Inc",
    "wof:placetype":"venue"
},
  "geometry": {"coordinates":[-76.033676,36.886593],"type":"Point"}
}