{
  "type": "Feature",
  "properties": {
    "addr:full":"7009 Dalemar Dr Clifton VA 20124",
    "addr:housenumber":"7009",
    "addr:postcode":"20124",
    "addr:street":"Dalemar Dr",
    "iso:country":"US",
    "sg:address":"7009 Dalemar Dr",
    "sg:city":"Clifton",
    "sg:classifiers":[
        {
            "category":"Building & Trades",
            "subcategory":"Construction",
            "type":"Services"
        }
    ],
    "sg:phone":"+1 703 263 9634",
    "sg:postcode":"20124",
    "sg:province":"VA",
    "sg:tags":[
        "contractor"
    ],
    "wof:name":"Shriner Contracting",
    "wof:placetype":"venue"
},
  "geometry": {"coordinates":[-77.43406299999999,38.804934],"type":"Point"}
}