{
  "type": "Feature",
  "properties": {
    "iso:country":"US",
    "sg:address":"1043 Glebe Rd",
    "sg:city":"Daleville",
    "sg:classifiers":[
        {
            "category":"Health Services",
            "subcategory":"Doctor",
            "type":"Services"
        }
    ],
    "sg:phone":"+1 540 992 1128",
    "sg:postcode":"24083",
    "sg:province":"VA",
    "sg:tags":[
        "physician",
        "surgeon"
    ],
    "wof:name":"Paul J Woods MD",
    "wof:placetype":"venue"
},
  "geometry": {"coordinates":[-79.927587,37.418068],"type":"Point"}
}