{
  "type": "Feature",
  "properties": {
    "iso:country":"US",
    "sg:address":"8101 Robert E Lee Dr",
    "sg:city":"Spotsylvania",
    "sg:classifiers":[
        {
            "category":"Professional",
            "subcategory":"Business Services",
            "type":"Services"
        }
    ],
    "sg:phone":"+1 540 582 5991",
    "sg:postcode":"22553",
    "sg:province":"VA",
    "wof:name":"Finishing Touch",
    "wof:placetype":"venue"
},
  "geometry": {"coordinates":[-77.618201,38.198128],"type":"Point"}
}