{
  "type": "Feature",
  "properties": {
    "iso:country":"US",
    "sg:address":"900 Elm Ave",
    "sg:city":"Portsmouth",
    "sg:classifiers":[
        {
            "category":"Government",
            "subcategory":"Office",
            "type":"Public Place"
        }
    ],
    "sg:phone":"+1 757 393 8755",
    "sg:postcode":"23704",
    "sg:province":"VA",
    "sg:tags":[
        "village"
    ],
    "wof:name":"Portsmouth Public Utlts Supl",
    "wof:placetype":"venue"
},
  "geometry": {"coordinates":[-76.312826,36.831695],"type":"Point"}
}