{
  "type": "Feature",
  "properties": {
    "addr:full":"10301 Hull Street Rd Midlothian VA 23112",
    "addr:housenumber":"10301",
    "addr:postcode":"23112",
    "addr:street":"Hull Street Rd",
    "iso:country":"US",
    "sg:address":"10301 Hull Street Rd",
    "sg:city":"Midlothian",
    "sg:classifiers":[
        {
            "category":"Home & Garden",
            "subcategory":"Building Materials",
            "type":"Retail Goods"
        }
    ],
    "sg:phone":"+1 804 276 1819",
    "sg:postcode":"23112",
    "sg:province":"VA",
    "sg:tags":[
        "door",
        "commercial",
        "equipment"
    ],
    "wof:name":"Modern Door & Equipment Sales",
    "wof:placetype":"venue"
},
  "geometry": {"coordinates":[-77.58538799999999,37.442161],"type":"Point"}
}