{
  "type": "Feature",
  "properties": {
    "addr:full":"815 Main St Altavista VA 24517",
    "addr:housenumber":"815",
    "addr:postcode":"24517",
    "addr:street":"Main St",
    "iso:country":"US",
    "sg:address":"815 Main St",
    "sg:city":"Altavista",
    "sg:classifiers":[
        {
            "category":"Wholesale",
            "subcategory":"Medical Equipment & Supplies",
            "type":"Manufacturing & Wholesale Goods"
        }
    ],
    "sg:phone":"+1 434 369 1868",
    "sg:postcode":"24517",
    "sg:province":"VA",
    "sg:tags":[
        "hospital"
    ],
    "wof:name":"Home Medical Svc",
    "wof:placetype":"venue"
},
  "geometry": {"coordinates":[-79.285376,37.111905],"type":"Point"}
}