{
  "type": "Feature",
  "properties": {
    "addr:full":"6052 Providence Rd Virginia Beach VA 23464",
    "addr:housenumber":"6052",
    "addr:postcode":"23464",
    "addr:street":"Providence Rd",
    "iso:country":"US",
    "sg:address":"6052 Providence Rd",
    "sg:city":"Virginia Beach",
    "sg:classifiers":[
        {
            "category":"Professional",
            "subcategory":"Accounting & Tax Preparation",
            "type":"Services"
        }
    ],
    "sg:phone":"+1 757 420 6379",
    "sg:postcode":"23464",
    "sg:province":"VA",
    "wof:name":"Larossa & Co",
    "wof:placetype":"venue"
},
  "geometry": {"coordinates":[-76.202905,36.812924],"type":"Point"}
}