{
  "type": "Feature",
  "properties": {
    "addr:full":"13125 Arto St Bristow VA 20136",
    "addr:postcode":"13125;20136",
    "addr:street":"Arto St",
    "iso:country":"US",
    "sg:address":"13125 Arto St",
    "sg:city":"Bristow",
    "sg:classifiers":[
        {
            "category":"Building & Trades",
            "subcategory":"Locksmith",
            "type":"Services"
        }
    ],
    "sg:phone":"+1 571 261 0548",
    "sg:postcode":"20136",
    "sg:province":"VA",
    "sg:tags":[
        "key"
    ],
    "wof:name":"Emergency Locksmith Available 24 7",
    "wof:placetype":"venue"
},
  "geometry": {"coordinates":[-77.584035,38.784601],"type":"Point"}
}