{
  "type": "Feature",
  "properties": {
    "addr:full":"3701 Gay Ave Richmond VA 23231",
    "addr:housenumber":"3701",
    "addr:postcode":"23231",
    "addr:street":"Gay Ave",
    "iso:country":"US",
    "sg:address":"3701 Gay Ave",
    "sg:city":"Richmond",
    "sg:classifiers":[
        {
            "category":"Real Estate",
            "subcategory":"Real Estate Operator",
            "type":"Services"
        }
    ],
    "sg:phone":"+1 804 497 4343",
    "sg:postcode":"23231",
    "sg:province":"VA",
    "sg:tags":[
        "apartment"
    ],
    "wof:name":"Reflections",
    "wof:placetype":"venue"
},
  "geometry": {"coordinates":[-77.36490999999999,37.525068],"type":"Point"}
}