{
  "type": "Feature",
  "properties": {
    "iso:country":"US",
    "sg:address":"7521 Jaguar Trl",
    "sg:city":"Falls Church",
    "sg:classifiers":[
        {
            "category":"Education",
            "subcategory":"School",
            "type":"Public Place"
        }
    ],
    "sg:phone":"+1 703 207 4000",
    "sg:postcode":"22042",
    "sg:province":"VA",
    "wof:name":"Falls Church High School",
    "wof:placetype":"venue"
},
  "geometry": {"coordinates":[-77.20789000000001,38.862742],"type":"Point"}
}