{
  "type": "Feature",
  "properties": {
    "iso:country":"US",
    "sg:address":"87 Lincoln St",
    "sg:city":"Hampton",
    "sg:classifiers":[
        {
            "category":"Restaurant",
            "type":"Food & Drink"
        }
    ],
    "sg:phone":"+1 757 728 9050",
    "sg:postcode":"23669",
    "sg:province":"VA",
    "wof:name":"Mary Helen's",
    "wof:placetype":"venue"
},
  "geometry": {"coordinates":[-76.347601,37.027569],"type":"Point"}
}