{
  "type": "Feature",
  "properties": {
    "iso:country":"US",
    "sg:address":"2811 Fall Hill Ave",
    "sg:city":"Fredericksburg",
    "sg:classifiers":[
        {
            "category":"Banks & Credit Unions",
            "subcategory":"Financial Services",
            "type":"Services"
        }
    ],
    "sg:phone":"+1 540 371 1000",
    "sg:postcode":"22401",
    "sg:province":"VA",
    "sg:tags":[
        "security",
        "investment",
        "closed"
    ],
    "wof:name":"Raymond James",
    "wof:placetype":"venue"
},
  "geometry": {"coordinates":[-77.47623299999999,38.31491],"type":"Point"}
}