{
  "type": "Feature",
  "properties": {
    "iso:country":"US",
    "sg:address":"5430 Cabot Ridge Ct",
    "sg:city":"Fairfax",
    "sg:classifiers":[
        {
            "category":"Restaurant",
            "type":"Food & Drink"
        }
    ],
    "sg:phone":"+1 703 239 1597",
    "sg:postcode":"22032",
    "sg:province":"VA",
    "sg:tags":[
        "eating"
    ],
    "wof:name":"So & Kim Inc",
    "wof:placetype":"venue"
},
  "geometry": {"coordinates":[-77.303854,38.804811],"type":"Point"}
}