{
  "type": "Feature",
  "properties": {
    "iso:country":"US",
    "sg:address":"10417 Buffapple Dr",
    "sg:city":"Richmond",
    "sg:classifiers":[
        {
            "category":"Professional",
            "type":"Services"
        }
    ],
    "sg:phone":"+1 804 741 5707",
    "sg:postcode":"23233",
    "sg:province":"VA",
    "wof:name":"Malvern LLC",
    "wof:placetype":"venue"
},
  "geometry": {"coordinates":[-77.60392299999999,37.625169],"type":"Point"}
}