{
  "type": "Feature",
  "properties": {
    "addr:full":"447 George Bateman Rd Ridgeway VA 24148",
    "addr:housenumber":"447",
    "addr:postcode":"24148",
    "addr:street":"George Bateman Rd",
    "iso:country":"US",
    "sg:address":"447 George Bateman Rd",
    "sg:city":"Ridgeway",
    "sg:classifiers":[
        {
            "category":"Building & Trades",
            "subcategory":"Construction",
            "type":"Services"
        }
    ],
    "sg:phone":"+1 276 956 1233",
    "sg:postcode":"24148",
    "sg:province":"VA",
    "sg:tags":[
        "hanging",
        "contractor"
    ],
    "wof:name":"Powell Painting & Construction",
    "wof:placetype":"venue"
},
  "geometry": {"coordinates":[-79.821172,36.599018],"type":"Point"}
}