{
  "type": "Feature",
  "properties": {
    "addr:full":"2601 Wilson Blvd Arlington VA 22201",
    "addr:housenumber":"2601",
    "addr:postcode":"22201",
    "addr:street":"Wilson Blvd",
    "iso:country":"US",
    "sg:address":"2601 Wilson Blvd",
    "sg:city":"Arlington",
    "sg:classifiers":[
        {
            "category":"Communications",
            "type":"Services"
        }
    ],
    "sg:phone":"+1 703 525 1575",
    "sg:postcode":"22201",
    "sg:province":"VA",
    "sg:tags":[
        "recording",
        "rehearsal",
        "studio"
    ],
    "wof:name":"Ritters Film Company",
    "wof:placetype":"venue"
},
  "geometry": {"coordinates":[-77.08998800000001,38.89029],"type":"Point"}
}