{
  "type": "Feature",
  "properties": {
    "addr:full":"4860 Randolph Dr Annandale VA 22003",
    "addr:housenumber":"4860",
    "addr:postcode":"22003",
    "addr:street":"Randolph Dr",
    "iso:country":"US",
    "sg:address":"4860 Randolph Dr",
    "sg:city":"Annandale",
    "sg:classifiers":[
        {
            "category":"Building & Trades",
            "subcategory":"Construction",
            "type":"Services"
        }
    ],
    "sg:phone":"+1 703 750 3885",
    "sg:postcode":"22003",
    "sg:province":"VA",
    "sg:tags":[
        "house"
    ],
    "wof:name":"Home Spirit Remodeling Service",
    "wof:placetype":"venue"
},
  "geometry": {"coordinates":[-77.169094,38.816266],"type":"Point"}
}