{
  "type": "Feature",
  "properties": {
    "addr:full":"3519 High St Portsmouth VA 23707",
    "addr:housenumber":"3519",
    "addr:postcode":"23707",
    "addr:street":"High St",
    "iso:country":"US",
    "sg:address":"3519 High St",
    "sg:city":"Portsmouth",
    "sg:classifiers":[
        {
            "category":"Autos & Motor Vehicles",
            "subcategory":"Automobile Sales",
            "type":"Retail Goods"
        }
    ],
    "sg:phone":"+1 757 399 8300",
    "sg:postcode":"23707",
    "sg:province":"VA",
    "sg:tags":[
        "used"
    ],
    "wof:name":"Auto U S A Sales & Leasing",
    "wof:placetype":"venue"
},
  "geometry": {"coordinates":[-76.34526099999999,36.834349],"type":"Point"}
}