{
  "type": "Feature",
  "properties": {
    "addr:full":"471 N Military Hwy Norfolk VA 23502",
    "addr:housenumber":"471",
    "addr:postcode":"23502",
    "addr:street":"N Military Hwy",
    "iso:country":"US",
    "sg:address":"471 N Military Hwy",
    "sg:city":"Norfolk",
    "sg:classifiers":[
        {
            "category":"Restaurant",
            "type":"Food & Drink"
        }
    ],
    "sg:phone":"+1 757 455 5509",
    "sg:postcode":"23502",
    "sg:province":"VA",
    "wof:name":"Mi Hogar Mexican Restaurant",
    "wof:placetype":"venue"
},
  "geometry": {"coordinates":[-76.210278,36.848309],"type":"Point"}
}