{
  "type": "Feature",
  "properties": {
    "iso:country":"US",
    "sg:address":"2220 Fairfax Dr",
    "sg:city":"Arlington",
    "sg:classifiers":[
        {
            "category":"Government",
            "subcategory":"Court House",
            "type":"Public Place"
        }
    ],
    "sg:phone":"+1 703 248 8855",
    "sg:postcode":"22201",
    "sg:province":"VA",
    "sg:tags":[
        "justice"
    ],
    "wof:name":"The Park At Courthouse",
    "wof:placetype":"venue"
},
  "geometry": {"coordinates":[-77.084548,38.886319],"type":"Point"}
}