{
  "type": "Feature",
  "properties": {
    "iso:country":"US",
    "sg:address":"5213 Lancelot Ln NW",
    "sg:city":"Roanoke",
    "sg:classifiers":[
        {
            "category":"Real Estate",
            "subcategory":"Real Estate Operator",
            "type":"Services"
        }
    ],
    "sg:phone":"+1 540 562 0300",
    "sg:postcode":"24019",
    "sg:province":"VA",
    "sg:tags":[
        "building",
        "apartment"
    ],
    "wof:name":"North Ridge Apartments",
    "wof:placetype":"venue"
},
  "geometry": {"coordinates":[-80.01118099999999,37.315818],"type":"Point"}
}