{
  "type": "Feature",
  "properties": {
    "iso:country":"US",
    "sg:address":"1807 Jefferson Ave",
    "sg:city":"Newport News",
    "sg:classifiers":[
        {
            "category":"Personal",
            "subcategory":"Beauty Salon",
            "type":"Services"
        }
    ],
    "sg:phone":"+1 757 244 1890",
    "sg:postcode":"23607",
    "sg:province":"VA",
    "sg:tags":[
        "shop"
    ],
    "wof:name":"Adells House of Style",
    "wof:placetype":"venue"
},
  "geometry": {"coordinates":[-76.418344,36.976827],"type":"Point"}
}