{
  "type": "Feature",
  "properties": {
    "addr:full":"1417 Battlefield Blvd N Chesapeake VA 23320",
    "addr:housenumber":"1417",
    "addr:postcode":"23320",
    "addr:street":"Battlefield Blvd N",
    "iso:country":"US",
    "sg:address":"1417 Battlefield Blvd N",
    "sg:city":"Chesapeake",
    "sg:classifiers":[
        {
            "category":"Professional",
            "subcategory":"Employment Agencies",
            "type":"Services"
        }
    ],
    "sg:phone":"+1 757 548 1187",
    "sg:postcode":"23320",
    "sg:province":"VA",
    "sg:tags":[
        "help",
        "contractor"
    ],
    "wof:name":"Snelling Personnel Svc",
    "wof:placetype":"venue"
},
  "geometry": {"coordinates":[-76.251813,36.766637],"type":"Point"}
}