{
  "type": "Feature",
  "properties": {
    "addr:full":"251 Robinson Dr Newport News VA 23601",
    "addr:housenumber":"251",
    "addr:postcode":"23601",
    "addr:street":"Robinson Dr",
    "iso:country":"US",
    "sg:address":"251 Robinson Dr",
    "sg:city":"Newport News",
    "sg:classifiers":[
        {
            "category":"Shopping",
            "subcategory":"Hobbies, Toys, & Games",
            "type":"Retail Goods"
        }
    ],
    "sg:phone":"+1 757 596 4521",
    "sg:postcode":"23601",
    "sg:province":"VA",
    "wof:name":"Joan Dolls",
    "wof:placetype":"venue"
},
  "geometry": {"coordinates":[-76.453638,37.074052],"type":"Point"}
}