{
  "type": "Feature",
  "properties": {
    "addr:full":"8420 Sedgemoor Dr Richmond VA 23228",
    "addr:housenumber":"8420",
    "addr:postcode":"23228",
    "addr:street":"Sedgemoor Dr",
    "iso:country":"US",
    "sg:address":"8420 Sedgemoor Dr",
    "sg:city":"Richmond",
    "sg:classifiers":[
        {
            "category":"Professional",
            "subcategory":"Management & Consulting",
            "type":"Services"
        }
    ],
    "sg:phone":"+1 804 266 2990",
    "sg:postcode":"23228",
    "sg:province":"VA",
    "wof:name":"Chem Shield of VA",
    "wof:placetype":"venue"
},
  "geometry": {"coordinates":[-77.49520200000001,37.629621],"type":"Point"}
}