{
  "type": "Feature",
  "properties": {
    "iso:country":"US",
    "sg:address":"13613 Bethel Rd",
    "sg:city":"Manassas",
    "sg:classifiers":[
        {
            "category":"Building & Trades",
            "subcategory":"Plumbing",
            "type":"Services"
        }
    ],
    "sg:phone":"+1 703 791 6063",
    "sg:postcode":"20112",
    "sg:province":"VA",
    "sg:tags":[
        "conditioning",
        "air",
        "system",
        "contractor"
    ],
    "wof:name":"All County Heating & Air Cond",
    "wof:placetype":"venue"
},
  "geometry": {"coordinates":[-77.413347,38.656417],"type":"Point"}
}