{
  "type": "Feature",
  "properties": {
    "addr:full":"940 S George Mason Dr Arlington VA 22204",
    "addr:housenumber":"940",
    "addr:postcode":"22204",
    "addr:street":"S George Mason Dr",
    "iso:country":"US",
    "sg:address":"940 S George Mason Dr",
    "sg:city":"Arlington",
    "sg:classifiers":[
        {
            "category":"Shopping",
            "subcategory":"Pharmacy",
            "type":"Retail Goods"
        }
    ],
    "sg:phone":"+1 703 920 3400",
    "sg:postcode":"22204",
    "sg:province":"VA",
    "wof:name":"Rite Aid",
    "wof:placetype":"venue"
},
  "geometry": {"coordinates":[-77.10224100000001,38.860079],"type":"Point"}
}