{
  "type": "Feature",
  "properties": {
    "addr:full":"6105 Howard Rd Richmond VA 23226",
    "addr:housenumber":"6105",
    "addr:postcode":"23226",
    "addr:street":"Howard Rd",
    "iso:country":"US",
    "sg:address":"6105 Howard Rd",
    "sg:city":"Richmond",
    "sg:classifiers":[
        {
            "category":"Professional",
            "subcategory":"Management & Consulting",
            "type":"Services"
        }
    ],
    "sg:phone":"+1 804 314 2490",
    "sg:postcode":"23226",
    "sg:province":"VA",
    "sg:tags":[
        "marketing",
        "medium",
        "consultant"
    ],
    "wof:name":"Susan Mitchell",
    "wof:placetype":"venue"
},
  "geometry": {"coordinates":[-77.524537,37.576797],"type":"Point"}
}