{
  "type": "Feature",
  "properties": {
    "iso:country":"US",
    "sg:address":"5 Staton Dr",
    "sg:city":"Hampton",
    "sg:classifiers":[
        {
            "category":"Professional",
            "subcategory":"Management & Consulting",
            "type":"Services"
        }
    ],
    "sg:phone":"+1 757 816 4496",
    "sg:postcode":"23666",
    "sg:province":"VA",
    "sg:tags":[
        "related",
        "real estate"
    ],
    "wof:name":"YH Real Estate Solutions",
    "wof:placetype":"venue"
},
  "geometry": {"coordinates":[-76.43500400000001,37.031697],"type":"Point"}
}