{
  "type": "Feature",
  "properties": {
    "addr:full":"3909 Litchfield Dr Chesterfield VA 23832",
    "addr:housenumber":"3909",
    "addr:postcode":"23832",
    "addr:street":"Litchfield Dr",
    "iso:country":"US",
    "sg:address":"3909 Litchfield Dr",
    "sg:city":"Chesterfield",
    "sg:classifiers":[
        {
            "category":"Manufacturing",
            "subcategory":"Printing",
            "type":"Manufacturing & Wholesale Goods"
        }
    ],
    "sg:phone":"+1 804 276 6464",
    "sg:postcode":"23832",
    "sg:province":"VA",
    "sg:tags":[
        "commercial"
    ],
    "wof:name":"Wedding Invitations & More",
    "wof:placetype":"venue"
},
  "geometry": {"coordinates":[-77.53588999999999,37.453339],"type":"Point"}
}