{
  "type": "Feature",
  "properties": {
    "addr:full":"178 Tiger Valley Rd Washington VA 22747",
    "addr:housenumber":"178",
    "addr:postcode":"22747",
    "addr:street":"Tiger Valley Rd",
    "iso:country":"US",
    "sg:address":"178 Tiger Valley Rd",
    "sg:city":"Washington",
    "sg:classifiers":[
        {
            "category":"Building & Trades",
            "subcategory":"Construction",
            "type":"Services"
        }
    ],
    "sg:phone":"+1 540 675 2395",
    "sg:postcode":"22747",
    "sg:province":"VA",
    "sg:tags":[
        "contractor"
    ],
    "wof:name":"Joseph F Keyser Construction",
    "wof:placetype":"venue"
},
  "geometry": {"coordinates":[-78.146021,38.702083],"type":"Point"}
}