{
  "type": "Feature",
  "properties": {
    "addr:full":"8957 Colesbury Pl Fairfax VA 22031",
    "addr:housenumber":"8957",
    "addr:postcode":"22031",
    "addr:street":"Colesbury Pl",
    "iso:country":"US",
    "sg:address":"8957 Colesbury Pl",
    "sg:city":"Fairfax",
    "sg:classifiers":[
        {
            "category":"Retail",
            "subcategory":"Veterinary Services",
            "type":"Services"
        }
    ],
    "sg:phone":"+1 703 280 9598",
    "sg:postcode":"22031",
    "sg:province":"VA",
    "sg:tags":[
        "veterinarian"
    ],
    "wof:name":"M C Bassett DVM",
    "wof:placetype":"venue"
},
  "geometry": {"coordinates":[-77.2495,38.847788],"type":"Point"}
}