{
  "type": "Feature",
  "properties": {
    "iso:country":"US",
    "sg:address":"6900 Woodpecker Rd",
    "sg:city":"Chesterfield",
    "sg:classifiers":[
        {
            "category":"Manufacturing",
            "subcategory":"Printing",
            "type":"Manufacturing & Wholesale Goods"
        }
    ],
    "sg:phone":"+1 804 590 1234",
    "sg:postcode":"23838",
    "sg:province":"VA",
    "sg:tags":[
        "screen"
    ],
    "wof:name":"Sketch'z",
    "wof:placetype":"venue"
},
  "geometry": {"coordinates":[-77.48731600000001,37.289373],"type":"Point"}
}