{
  "type": "Feature",
  "properties": {
    "iso:country":"US",
    "sg:address":"256 Long Point Rd",
    "sg:city":"Hague",
    "sg:classifiers":[
        {
            "category":"Recreation",
            "subcategory":"Marina",
            "type":"Entertainment"
        }
    ],
    "sg:phone":"+1 804 472 2164",
    "sg:postcode":"22469",
    "sg:province":"VA",
    "wof:name":"North Point Marine",
    "wof:placetype":"venue"
},
  "geometry": {"coordinates":[-76.62384400000001,38.126929],"type":"Point"}
}