{
  "type": "Feature",
  "properties": {
    "addr:full":"1308 Sage Ct Chesapeake VA 23320",
    "addr:housenumber":"1308",
    "addr:postcode":"23320",
    "addr:street":"Sage Ct",
    "iso:country":"US",
    "sg:address":"1308 Sage Ct",
    "sg:city":"Chesapeake",
    "sg:classifiers":[
        {
            "category":"Professional",
            "type":"Services"
        }
    ],
    "sg:phone":"+1 757 523 2030",
    "sg:postcode":"23320",
    "sg:province":"VA",
    "wof:name":"TW Inc",
    "wof:placetype":"venue"
},
  "geometry": {"coordinates":[-76.21777299999999,36.775581],"type":"Point"}
}