{
  "type": "Feature",
  "properties": {
    "addr:full":"8907 Michaux Ln Richmond VA 23229",
    "addr:postcode":"8907;23229",
    "addr:street":"Michaux Ln",
    "iso:country":"US",
    "sg:address":"8907 Michaux Ln",
    "sg:city":"Richmond",
    "sg:classifiers":[
        {
            "category":"Travel",
            "subcategory":"Hotels & Motels",
            "type":"Entertainment"
        }
    ],
    "sg:phone":"+1 804 405 5818",
    "sg:postcode":"23229",
    "sg:province":"VA",
    "sg:tags":[
        "membership",
        "lodging"
    ],
    "wof:name":"Virginia State Bemolay",
    "wof:placetype":"venue"
},
  "geometry": {"coordinates":[-77.575911,37.591645],"type":"Point"}
}