{
  "type": "Feature",
  "properties": {
    "iso:country":"US",
    "sg:address":"513 Henri Rd",
    "sg:city":"Richmond",
    "sg:classifiers":[
        {
            "category":"Building & Trades",
            "subcategory":"Construction",
            "type":"Services"
        }
    ],
    "sg:phone":"+1 804 285 5923",
    "sg:postcode":"23226",
    "sg:province":"VA",
    "sg:tags":[
        "specializing",
        "home",
        "family",
        "contractor"
    ],
    "wof:name":"Hasker Homes Inc",
    "wof:placetype":"venue"
},
  "geometry": {"coordinates":[-77.522437,37.576661],"type":"Point"}
}