{
  "type": "Feature",
  "properties": {
    "iso:country":"US",
    "sg:address":"500 Fairfield Dr",
    "sg:city":"Chesapeake",
    "sg:classifiers":[
        {
            "category":"Building & Trades",
            "subcategory":"Construction",
            "type":"Services"
        }
    ],
    "sg:phone":"+1 757 546 1711",
    "sg:postcode":"23322",
    "sg:province":"VA",
    "sg:tags":[
        "contractor"
    ],
    "wof:name":"South Atlantic Cleaning",
    "wof:placetype":"venue"
},
  "geometry": {"coordinates":[-76.19020999999999,36.70901],"type":"Point"}
}