{
  "type": "Feature",
  "properties": {
    "addr:full":"2736 Maidens Rd Goochland VA 23063",
    "addr:housenumber":"2736",
    "addr:postcode":"23063",
    "addr:street":"Maidens Rd",
    "iso:country":"US",
    "sg:address":"2736 Maidens Rd",
    "sg:city":"Goochland",
    "sg:classifiers":[
        {
            "category":"Retail",
            "subcategory":"Auto Repair",
            "type":"Services"
        }
    ],
    "sg:phone":"+1 804 556 5980",
    "sg:postcode":"23063",
    "sg:province":"VA",
    "sg:tags":[
        "glass",
        "replacement"
    ],
    "wof:name":"West End Auto Glass",
    "wof:placetype":"venue"
},
  "geometry": {"coordinates":[-77.85737899999999,37.74602],"type":"Point"}
}