{
  "type": "Feature",
  "properties": {
    "addr:full":"3605 Shenandoah Ave NW Roanoke VA 24017",
    "addr:housenumber":"3605",
    "addr:postcode":"24017",
    "addr:street":"Shenandoah Ave Nw",
    "iso:country":"US",
    "sg:address":"3605 Shenandoah Ave NW",
    "sg:city":"Roanoke",
    "sg:classifiers":[
        {
            "category":"Food & Beverages",
            "subcategory":"Groceries & Convenience Stores",
            "type":"Retail Goods"
        }
    ],
    "sg:phone":"+1 540 985 0855",
    "sg:postcode":"24017",
    "sg:province":"VA",
    "sg:tags":[
        "grocer"
    ],
    "wof:name":"Wilmont Market",
    "wof:placetype":"venue"
},
  "geometry": {"coordinates":[-79.997647,37.281403],"type":"Point"}
}