{
  "type": "Feature",
  "properties": {
    "addr:full":"3901 A Ave Fort Lee VA 23801",
    "addr:housenumber":"3901 a",
    "addr:postcode":"23801",
    "addr:street":"Ave",
    "iso:country":"US",
    "sg:address":"3901 A Ave",
    "sg:city":"Fort Lee",
    "sg:classifiers":[
        {
            "category":"Government",
            "subcategory":"Office",
            "type":"Public Place"
        }
    ],
    "sg:phone":"+1 804 734 1542",
    "sg:postcode":"23801",
    "sg:province":"VA",
    "sg:tags":[
        "military",
        "installation",
        "army"
    ],
    "wof:name":"US Army Combined Arms Support",
    "wof:placetype":"venue"
},
  "geometry": {"coordinates":[-77.33299100000001,37.224255],"type":"Point"}
}