{
  "type": "Feature",
  "properties": {
    "iso:country":"US",
    "sg:address":"2715 Swineford Rd",
    "sg:city":"Richmond",
    "sg:classifiers":[
        {
            "category":"Organizations",
            "subcategory":"Religious Organization",
            "type":"Services"
        }
    ],
    "sg:phone":"+1 804 275 1656",
    "sg:postcode":"23237",
    "sg:province":"VA",
    "sg:tags":[
        "presbyterian",
        "church"
    ],
    "wof:name":"Korean Central Presbt Church",
    "wof:placetype":"venue"
},
  "geometry": {"coordinates":[-77.442744,37.431114],"type":"Point"}
}