{
  "type": "Feature",
  "properties": {
    "addr:full":"1718 Epps Fork Rd Clarksville VA 23927",
    "addr:housenumber":"1718",
    "addr:postcode":"23927",
    "addr:street":"Epps Fork Rd",
    "iso:country":"US",
    "sg:address":"1718 Epps Fork Rd",
    "sg:city":"Clarksville",
    "sg:classifiers":[
        {
            "category":"Building & Trades",
            "subcategory":"Landscaping Services",
            "type":"Services"
        }
    ],
    "sg:phone":"+1 434 252 0066",
    "sg:postcode":"23927",
    "sg:province":"VA",
    "wof:name":"Private Gardens",
    "wof:placetype":"venue"
},
  "geometry": {"coordinates":[-78.34706199999999,36.5556],"type":"Point"}
}