{
  "type": "Feature",
  "properties": {
    "addr:full":"2625 Rocky Hill Rd Blackstone VA 23824",
    "addr:housenumber":"2625",
    "addr:postcode":"23824",
    "addr:street":"Rocky Hill Rd",
    "iso:country":"US",
    "sg:address":"2625 Rocky Hill Rd",
    "sg:city":"Blackstone",
    "sg:classifiers":[
        {
            "category":"Personal",
            "subcategory":"Beauty Salon",
            "type":"Services"
        }
    ],
    "sg:phone":"+1 434 292 7200",
    "sg:postcode":"23824",
    "sg:province":"VA",
    "sg:tags":[
        "shop"
    ],
    "wof:name":"Juliettes Beauty Salon",
    "wof:placetype":"venue"
},
  "geometry": {"coordinates":[-77.91509600000001,37.190895],"type":"Point"}
}