{
  "type": "Feature",
  "properties": {
    "addr:full":"230 Lost Mountain Rd Wirtz VA 24184",
    "addr:housenumber":"230",
    "addr:postcode":"24184",
    "addr:street":"Lost Mountain Rd",
    "iso:country":"US",
    "sg:address":"230 Lost Mountain Rd",
    "sg:city":"Wirtz",
    "sg:classifiers":[
        {
            "category":"Building & Trades",
            "subcategory":"Construction",
            "type":"Services"
        }
    ],
    "sg:phone":"+1 540 721 4626",
    "sg:postcode":"24184",
    "sg:province":"VA",
    "sg:tags":[
        "concrete",
        "contractor"
    ],
    "wof:name":"Buddy's Concrete Foundations",
    "wof:placetype":"venue"
},
  "geometry": {"coordinates":[-79.75580100000001,37.094022],"type":"Point"}
}