{
  "type": "Feature",
  "properties": {
    "addr:full":"1919 Andrews Rd NW Roanoke VA 24017",
    "addr:housenumber":"1919",
    "addr:postcode":"24017",
    "addr:street":"Andrews Rd Nw",
    "iso:country":"US",
    "sg:address":"1919 Andrews Rd NW",
    "sg:city":"Roanoke",
    "sg:classifiers":[
        {
            "category":"Building & Trades",
            "subcategory":"Construction",
            "type":"Services"
        }
    ],
    "sg:phone":"+1 540 345 3489",
    "sg:postcode":"24017",
    "sg:province":"VA",
    "sg:tags":[
        "contractor"
    ],
    "wof:name":"Virginia Pools & Gunite",
    "wof:placetype":"venue"
},
  "geometry": {"coordinates":[-79.965774,37.294308],"type":"Point"}
}