{
  "type": "Feature",
  "properties": {
    "iso:country":"US",
    "sg:address":"6026 Georgetown Rd",
    "sg:city":"Broad Run",
    "sg:classifiers":[
        {
            "category":"Personal",
            "subcategory":"Beauty Salon",
            "type":"Services"
        }
    ],
    "sg:phone":"+1 540 349 3335",
    "sg:postcode":"20137",
    "sg:province":"VA",
    "sg:tags":[
        "shop"
    ],
    "wof:name":"Fresh Cut",
    "wof:placetype":"venue"
},
  "geometry": {"coordinates":[-77.735023,38.788897],"type":"Point"}
}