{
  "type": "Feature",
  "properties": {
    "iso:country":"US",
    "sg:address":"2266 S Boston Rd",
    "sg:city":"Danville",
    "sg:classifiers":[
        {
            "category":"Shopping",
            "subcategory":"Music",
            "type":"Retail Goods"
        }
    ],
    "sg:phone":"+1 434 792 7100",
    "sg:postcode":"24540",
    "sg:province":"VA",
    "sg:tags":[
        "video",
        "disc",
        "tape",
        "cassette"
    ],
    "wof:name":"Popcorn Video",
    "wof:placetype":"venue"
},
  "geometry": {"coordinates":[-79.309387,36.580788],"type":"Point"}
}