{
  "type": "Feature",
  "properties": {
    "addr:full":"12240 Five Mile Rd Fredericksburg VA 22407",
    "addr:housenumber":"12240",
    "addr:postcode":"22407",
    "addr:street":"Five Mile Rd",
    "iso:country":"US",
    "sg:address":"12240 Five Mile Rd",
    "sg:city":"Fredericksburg",
    "sg:classifiers":[
        {
            "category":"Organizations",
            "subcategory":"Religious Organization",
            "type":"Services"
        }
    ],
    "sg:phone":"+1 540 898 1918",
    "sg:postcode":"22407",
    "sg:province":"VA",
    "sg:website":"www.spotsychurchofgod.com",
    "wof:name":"Splatsylvania Church of God",
    "wof:placetype":"venue"
},
  "geometry": {"coordinates":[-77.55594000000001,38.29201],"type":"Point"}
}