{
  "type": "Feature",
  "properties": {
    "addr:full":"2511 Memorial Ave Lynchburg VA 24501",
    "addr:housenumber":"2511",
    "addr:postcode":"24501",
    "addr:street":"Memorial Ave",
    "iso:country":"US",
    "sg:address":"2511 Memorial Ave",
    "sg:city":"Lynchburg",
    "sg:classifiers":[
        {
            "category":"Sports & Exercise",
            "subcategory":"Gym",
            "type":"Entertainment"
        }
    ],
    "sg:phone":"+1 434 845 2467",
    "sg:postcode":"24501",
    "sg:province":"VA",
    "sg:tags":[
        "fitness",
        "physical",
        "gymnasium",
        "facility"
    ],
    "sg:website":"www.superkickskarate.com",
    "wof:name":"Super Kicks",
    "wof:placetype":"venue"
},
  "geometry": {"coordinates":[-79.168278,37.401076],"type":"Point"}
}