{
  "type": "Feature",
  "properties": {
    "addr:full":"41 Berea Church Rd Fredericksburg VA 22406",
    "addr:housenumber":"41",
    "addr:postcode":"22406",
    "addr:street":"Berea Church Rd",
    "iso:country":"US",
    "sg:address":"41 Berea Church Rd",
    "sg:city":"Fredericksburg",
    "sg:classifiers":[
        {
            "category":"Retail",
            "subcategory":"Repair Shop",
            "type":"Services"
        }
    ],
    "sg:phone":"+1 540 659 3874",
    "sg:postcode":"22406",
    "sg:province":"VA",
    "sg:tags":[
        "upholsterer"
    ],
    "wof:name":"Coachcraft Upholstery",
    "wof:placetype":"venue"
},
  "geometry": {"coordinates":[-77.515747,38.363819],"type":"Point"}
}