{
  "type": "Feature",
  "properties": {
    "addr:full":"9127 W Broad St Henrico VA 23294",
    "addr:housenumber":"9127",
    "addr:postcode":"23294",
    "addr:street":"W Broad St",
    "iso:country":"US",
    "sg:address":"9127 W Broad St",
    "sg:city":"Henrico",
    "sg:classifiers":[
        {
            "category":"Shopping",
            "subcategory":"Clothing, Apparel, & Fashions",
            "type":"Retail Goods"
        }
    ],
    "sg:phone":"+1 804 967 9196",
    "sg:postcode":"23294",
    "sg:province":"VA",
    "sg:tags":[
        "sale",
        "rental",
        "wear",
        "formal"
    ],
    "wof:name":"Savvi Formalwear",
    "wof:placetype":"venue"
},
  "geometry": {"coordinates":[-77.550349,37.636619],"type":"Point"}
}