{
  "type": "Feature",
  "properties": {
    "iso:country":"US",
    "sg:address":"9197 Merrybelle Ct",
    "sg:city":"Manassas",
    "sg:classifiers":[
        {
            "category":"Wholesale",
            "subcategory":"Electrical",
            "type":"Manufacturing & Wholesale Goods"
        }
    ],
    "sg:phone":"+1 703 257 0277",
    "sg:postcode":"20110",
    "sg:province":"VA",
    "sg:tags":[
        "equipment"
    ],
    "wof:name":"Child Watch Inc",
    "wof:placetype":"venue"
},
  "geometry": {"coordinates":[-77.47961599999999,38.741544],"type":"Point"}
}