{
  "type": "Feature",
  "properties": {
    "addr:full":"12894 Hunterbrook Dr Woodbridge VA 22192",
    "addr:housenumber":"12894",
    "addr:postcode":"22192",
    "addr:street":"Hunterbrook Dr",
    "iso:country":"US",
    "sg:address":"12894 Hunterbrook Dr",
    "sg:city":"Woodbridge",
    "sg:classifiers":[
        {
            "category":"Government",
            "subcategory":"Office",
            "type":"Public Place"
        }
    ],
    "sg:phone":"+1 703 220 7209",
    "sg:postcode":"22192",
    "sg:province":"VA",
    "sg:tags":[
        "national",
        "security"
    ],
    "wof:name":"Precision Analyitics",
    "wof:placetype":"venue"
},
  "geometry": {"coordinates":[-77.274591,38.675305],"type":"Point"}
}