{
  "type": "Feature",
  "properties": {
    "addr:full":"2920 S Glebe Rd Arlington VA 22206",
    "addr:housenumber":"2920",
    "addr:postcode":"22206",
    "addr:street":"S Glebe Rd",
    "iso:country":"US",
    "sg:address":"2920 S Glebe Rd",
    "sg:city":"Arlington",
    "sg:classifiers":[
        {
            "category":"Professional",
            "subcategory":"Engineering",
            "type":"Services"
        }
    ],
    "sg:phone":"+1 703 299 1600",
    "sg:postcode":"22206",
    "sg:province":"VA",
    "wof:name":"Defense Tech Inc",
    "wof:placetype":"venue"
},
  "geometry": {"coordinates":[-77.06719699999999,38.844803],"type":"Point"}
}