{
  "type": "Feature",
  "properties": {
    "addr:full":"9185 Michael Dr King George VA 22485",
    "addr:housenumber":"9185",
    "addr:postcode":"22485",
    "addr:street":"Michael Dr",
    "iso:country":"US",
    "sg:address":"9185 Michael Dr",
    "sg:city":"King George",
    "sg:classifiers":[
        {
            "category":"Building & Trades",
            "subcategory":"Plumbing",
            "type":"Services"
        }
    ],
    "sg:phone":"+1 540 775 5800",
    "sg:postcode":"22485",
    "sg:province":"VA",
    "sg:tags":[
        "conditioning",
        "air",
        "system",
        "contractor"
    ],
    "wof:name":"Puller Heating & Cooling Inc",
    "wof:placetype":"venue"
},
  "geometry": {"coordinates":[-77.182762,38.298457],"type":"Point"}
}