{
  "type": "Feature",
  "properties": {
    "addr:full":"45 Pine St Chatham VA 24531",
    "addr:housenumber":"45",
    "addr:postcode":"24531",
    "addr:street":"Pine St",
    "iso:country":"US",
    "sg:address":"45 Pine St",
    "sg:city":"Chatham",
    "sg:classifiers":[
        {
            "category":"Real Estate",
            "subcategory":"Real Estate Operator",
            "type":"Services"
        }
    ],
    "sg:phone":"+1 434 432 8857",
    "sg:postcode":"24531",
    "sg:province":"VA",
    "sg:tags":[
        "apartment"
    ],
    "wof:name":"Guildfield Heights",
    "wof:placetype":"venue"
},
  "geometry": {"coordinates":[-79.39274500000001,36.836973],"type":"Point"}
}