{
  "type": "Feature",
  "properties": {
    "iso:country":"US",
    "sg:address":"101 E Grayson St",
    "sg:city":"Galax",
    "sg:classifiers":[
        {
            "category":"Shopping",
            "subcategory":"Used Merchandise",
            "type":"Retail Goods"
        }
    ],
    "sg:phone":"+1 276 236 3338",
    "sg:postcode":"24333",
    "sg:province":"VA",
    "sg:tags":[
        "shop",
        "consignment"
    ],
    "wof:name":"Doubletakes Resale",
    "wof:placetype":"venue"
},
  "geometry": {"coordinates":[-80.924233,36.66202],"type":"Point"}
}