{
  "type": "Feature",
  "properties": {
    "iso:country":"US",
    "sg:address":"1024 Cameron St",
    "sg:city":"Alexandria",
    "sg:classifiers":[
        {
            "category":"Professional",
            "subcategory":"Employment Agencies",
            "type":"Services"
        },
        {
            "category":"Wholesale",
            "subcategory":"Vending Machines",
            "type":"Manufacturing & Wholesale Goods"
        }
    ],
    "sg:phone":"+1 703 739 8850",
    "sg:postcode":"22314",
    "sg:province":"VA",
    "sg:tags":[
        "patent",
        "agent",
        "searcher"
    ],
    "wof:name":"Metropatent",
    "wof:placetype":"venue"
},
  "geometry": {"coordinates":[-77.050316,38.806661],"type":"Point"}
}