{
  "type": "Feature",
  "properties": {
    "iso:country":"US",
    "sg:address":"125 Gray Fox Ln",
    "sg:city":"Lexington",
    "sg:classifiers":[
        {
            "category":"Professional",
            "subcategory":"Accounting & Tax Preparation",
            "type":"Services"
        }
    ],
    "sg:phone":"+1 540 463 9465",
    "sg:postcode":"24450",
    "sg:province":"VA",
    "sg:tags":[
        "accountant",
        "public",
        "certified"
    ],
    "wof:name":"PC Accounting Inc",
    "wof:placetype":"venue"
},
  "geometry": {"coordinates":[-79.37678,37.814401],"type":"Point"}
}