{
  "type": "Feature",
  "properties": {
    "addr:full":"47426 Riverbank Forest Pl Sterling VA 20165",
    "addr:postcode":"47426;20165",
    "addr:street":"Riverbank Forest Pl",
    "iso:country":"US",
    "sg:address":"47426 Riverbank Forest Pl",
    "sg:city":"Sterling",
    "sg:classifiers":[
        {
            "category":"Professional",
            "subcategory":"Computer Services",
            "type":"Services"
        }
    ],
    "sg:phone":"+1 571 213 5706",
    "sg:postcode":"20165",
    "sg:province":"VA",
    "sg:tags":[
        "information",
        "technology"
    ],
    "wof:name":"Federal Solutions Inc",
    "wof:placetype":"venue"
},
  "geometry": {"coordinates":[-77.35669300000001,39.043595],"type":"Point"}
}