{
  "type": "Feature",
  "properties": {
    "addr:full":"8400 Meadowbridge Rd Mechanicsville VA 23116",
    "addr:postcode":"8400;23116",
    "addr:street":"Meadowbridge Rd",
    "iso:country":"US",
    "sg:address":"8400 Meadowbridge Rd",
    "sg:city":"Mechanicsville",
    "sg:classifiers":[
        {
            "category":"Building & Trades",
            "subcategory":"Construction",
            "type":"Services"
        }
    ],
    "sg:phone":"+1 804 569 6185",
    "sg:postcode":"23116",
    "sg:province":"VA",
    "sg:tags":[
        "general",
        "contractor"
    ],
    "wof:name":"Graybeale Construction Inc",
    "wof:placetype":"venue"
},
  "geometry": {"coordinates":[-77.394097,37.620167],"type":"Point"}
}