{
  "type": "Feature",
  "properties": {
    "iso:country":"US",
    "sg:address":"511 Falmouth St",
    "sg:city":"Warrenton",
    "sg:classifiers":[
        {
            "category":"Shopping",
            "type":"Retail Goods"
        }
    ],
    "sg:phone":"+1 540 341 7766",
    "sg:postcode":"20186",
    "sg:province":"VA",
    "sg:tags":[
        "wedding",
        "supply"
    ],
    "wof:name":"Alwyngton Manor",
    "wof:placetype":"venue"
},
  "geometry": {"coordinates":[-77.786995,38.702789],"type":"Point"}
}