{
  "type": "Feature",
  "properties": {
    "addr:full":"8921 Three Chopt Rd Richmond VA 23229",
    "addr:housenumber":"8921",
    "addr:postcode":"23229",
    "addr:street":"Three Chopt Rd",
    "iso:country":"US",
    "sg:address":"8921 Three Chopt Rd",
    "sg:city":"Richmond",
    "sg:classifiers":[
        {
            "category":"Health Services",
            "subcategory":"Health Practitioner",
            "type":"Services"
        }
    ],
    "sg:phone":"+1 804 285 2758",
    "sg:postcode":"23229",
    "sg:province":"VA",
    "sg:tags":[
        "therapist",
        "physical"
    ],
    "sg:website":"www.healthsouth.com",
    "wof:name":"Healthsouth Sports Medicine",
    "wof:placetype":"venue"
},
  "geometry": {"coordinates":[-77.560678,37.606055],"type":"Point"}
}