{
  "type": "Feature",
  "properties": {
    "iso:country":"US",
    "sg:address":"6829 Elm St",
    "sg:city":"Mc Lean",
    "sg:classifiers":[
        {
            "category":"Personal",
            "subcategory":"Beauty Salon",
            "type":"Services"
        }
    ],
    "sg:phone":"+1 703 821 3166",
    "sg:postcode":"22101",
    "sg:province":"VA",
    "sg:tags":[
        "shop"
    ],
    "wof:name":"Caprisse",
    "wof:placetype":"venue"
},
  "geometry": {"coordinates":[-77.180796,38.936636],"type":"Point"}
}