{
  "type": "Feature",
  "properties": {
    "addr:full":"7127 Braeburn Pl Bethesda MD 20817",
    "addr:housenumber":"7127",
    "addr:postcode":"20817",
    "addr:street":"Braeburn Pl",
    "iso:country":"US",
    "sg:address":"7127 Braeburn Pl",
    "sg:city":"Bethesda",
    "sg:classifiers":[
        {
            "category":"Organizations",
            "subcategory":"Professional Association",
            "type":"Services"
        }
    ],
    "sg:phone":"+1 301 229 4081",
    "sg:postcode":"20817",
    "sg:province":"MD",
    "sg:tags":[
        "trade"
    ],
    "wof:name":"Itpa",
    "wof:placetype":"venue"
},
  "geometry": {"coordinates":[-77.14524900000001,38.973643],"type":"Point"}
}