{
  "type": "Feature",
  "properties": {
    "iso:country":"US",
    "sg:address":"1005 E Main St",
    "sg:city":"Richmond",
    "sg:classifiers":[
        {
            "category":"Restaurant",
            "type":"Food & Drink"
        }
    ],
    "sg:menulink":"http://www.allmenus.com/va/richmond/27310-bank/menu/",
    "sg:phone":"+1 804 638 3070",
    "sg:postcode":"23219",
    "sg:province":"VA",
    "sg:tags":[
        "new",
        "american"
    ],
    "wof:name":"Bank",
    "wof:placetype":"venue"
},
  "geometry": {"coordinates":[-77.435294,37.537573],"type":"Point"}
}