{
  "type": "Feature",
  "properties": {
    "addr:full":"296 Missouri Ave Herndon VA 20170",
    "addr:housenumber":"296",
    "addr:postcode":"20170",
    "addr:street":"Missouri Ave",
    "iso:country":"US",
    "sg:address":"296 Missouri Ave",
    "sg:city":"Herndon",
    "sg:classifiers":[
        {
            "category":"Organizations",
            "subcategory":"Membership Organization",
            "type":"Services"
        }
    ],
    "sg:phone":"+1 703 437 8677",
    "sg:postcode":"20170",
    "sg:province":"VA",
    "wof:name":"Colegium Cantorum",
    "wof:placetype":"venue"
},
  "geometry": {"coordinates":[-77.389709,38.95747],"type":"Point"}
}