{
  "type": "Feature",
  "properties": {
    "addr:full":"133 Woodview Ave Norfolk VA 23505",
    "addr:housenumber":"133",
    "addr:postcode":"23505",
    "addr:street":"Woodview Ave",
    "iso:country":"US",
    "sg:address":"133 Woodview Ave",
    "sg:city":"Norfolk",
    "sg:classifiers":[
        {
            "category":"Organizations",
            "subcategory":"Religious Organization",
            "type":"Services"
        }
    ],
    "sg:phone":"+1 757 489 1987",
    "sg:postcode":"23505",
    "sg:province":"VA",
    "wof:name":"Christ First Cmnty Fellowship",
    "wof:placetype":"venue"
},
  "geometry": {"coordinates":[-76.315223,36.926803],"type":"Point"}
}