{
  "type": "Feature",
  "properties": {
    "addr:full":"11239 Jefferson Ave Newport News VA 23601",
    "addr:housenumber":"11239",
    "addr:postcode":"23601",
    "addr:street":"Jefferson Ave",
    "iso:country":"US",
    "sg:address":"11239 Jefferson Ave",
    "sg:city":"Newport News",
    "sg:classifiers":[
        {
            "category":"Retail",
            "subcategory":"Auto Repair",
            "type":"Services"
        }
    ],
    "sg:phone":"+1 757 595 7722",
    "sg:postcode":"23601",
    "sg:province":"VA",
    "sg:tags":[
        "repairing",
        "automobile"
    ],
    "wof:name":"A 2z Auto Repair & Accessories",
    "wof:placetype":"venue"
},
  "geometry": {"coordinates":[-76.467437,37.061524],"type":"Point"}
}