{
  "type": "Feature",
  "properties": {
    "iso:country":"US",
    "sg:address":"14334 Ferndale Rd",
    "sg:city":"Woodbridge",
    "sg:classifiers":[
        {
            "category":"Building & Trades",
            "subcategory":"Construction",
            "type":"Services"
        }
    ],
    "sg:phone":"+1 703 590 3900",
    "sg:postcode":"22193",
    "sg:province":"VA",
    "sg:tags":[
        "contractor"
    ],
    "wof:name":"Off The Glass",
    "wof:placetype":"venue"
},
  "geometry": {"coordinates":[-77.324155,38.640866],"type":"Point"}
}