{
  "type": "Feature",
  "properties": {
    "iso:country":"US",
    "sg:address":"14703 Warwick Blvd",
    "sg:city":"Newport News",
    "sg:classifiers":[
        {
            "category":"Health Services",
            "subcategory":"Doctor",
            "type":"Services"
        }
    ],
    "sg:phone":"+1 757 886 6012",
    "sg:postcode":"23608",
    "sg:province":"VA",
    "sg:tags":[
        "medical"
    ],
    "wof:name":"Matry Maduclat Med Care",
    "wof:placetype":"venue"
},
  "geometry": {"coordinates":[-76.54290399999999,37.132808],"type":"Point"}
}