{
  "type": "Feature",
  "properties": {
    "addr:full":"5004 Talbois Pl Alexandria VA 22310",
    "addr:housenumber":"5004",
    "addr:postcode":"22310",
    "addr:street":"Talbois Pl",
    "iso:country":"US",
    "sg:address":"5004 Talbois Pl",
    "sg:city":"Alexandria",
    "sg:classifiers":[
        {
            "category":"Professional",
            "subcategory":"Business Services",
            "type":"Services"
        }
    ],
    "sg:phone":"+1 703 922 0354",
    "sg:postcode":"22310",
    "sg:province":"VA",
    "sg:tags":[
        "interior",
        "consultant",
        "design",
        "decorator"
    ],
    "wof:name":"Kashmir Decor",
    "wof:placetype":"venue"
},
  "geometry": {"coordinates":[-77.121011,38.790716],"type":"Point"}
}