{
  "type": "Feature",
  "properties": {
    "iso:country":"US",
    "sg:address":"1961 Chain Bridge Rd",
    "sg:city":"Mc Lean",
    "sg:classifiers":[
        {
            "category":"Home & Garden",
            "subcategory":"Furniture",
            "type":"Retail Goods"
        }
    ],
    "sg:phone":"+1 703 442 8861",
    "sg:postcode":"22102",
    "sg:province":"VA",
    "sg:tags":[
        "furnishing"
    ],
    "wof:name":"Domain 8",
    "wof:placetype":"venue"
},
  "geometry": {"coordinates":[-77.226226,38.919716],"type":"Point"}
}