{
  "type": "Feature",
  "properties": {
    "addr:full":"10134 Colvin Run Rd Great Falls VA 22066",
    "addr:housenumber":"10134",
    "addr:postcode":"22066",
    "addr:street":"Colvin Run Rd",
    "iso:country":"US",
    "sg:address":"10134 Colvin Run Rd",
    "sg:city":"Great Falls",
    "sg:classifiers":[
        {
            "category":"Health Services",
            "subcategory":"Doctor",
            "type":"Services"
        }
    ],
    "sg:phone":"+1 703 757 7950",
    "sg:postcode":"22066",
    "sg:province":"VA",
    "sg:tags":[
        "clinic",
        "medical"
    ],
    "wof:name":"Depaola Francesco",
    "wof:placetype":"venue"
},
  "geometry": {"coordinates":[-77.296762,38.973839],"type":"Point"}
}