{
  "type": "Feature",
  "properties": {
    "iso:country":"US",
    "sg:address":"5673 Columbia Pike",
    "sg:city":"Falls Church",
    "sg:classifiers":[
        {
            "category":"Health Services",
            "subcategory":"Doctor",
            "type":"Services"
        }
    ],
    "sg:phone":"+1 703 933 0222",
    "sg:postcode":"22041",
    "sg:province":"VA",
    "sg:tags":[
        "medical"
    ],
    "wof:name":"Masri Asad MD Fapa Diplomatic",
    "wof:placetype":"venue"
},
  "geometry": {"coordinates":[-77.124448,38.852606],"type":"Point"}
}