{
  "type": "Feature",
  "properties": {
    "iso:country":"US",
    "sg:address":"571 Madrid Rd",
    "sg:city":"Waynesboro",
    "sg:classifiers":[
        {
            "category":"Farming",
            "subcategory":"Livestock Farm",
            "type":"Manufacturing & Wholesale Goods"
        }
    ],
    "sg:phone":"+1 540 363 5347",
    "sg:postcode":"22980",
    "sg:province":"VA",
    "sg:tags":[
        "equine"
    ],
    "wof:name":"Cricket Hill Stables",
    "wof:placetype":"venue"
},
  "geometry": {"coordinates":[-78.89449,38.15464],"type":"Point"}
}