{
  "type": "Feature",
  "properties": {
    "addr:full":"30 Angel Ridge Ln Boones Mill VA 24065",
    "addr:housenumber":"30",
    "addr:postcode":"24065",
    "addr:street":"Angel Ridge Ln",
    "iso:country":"US",
    "sg:address":"30 Angel Ridge Ln",
    "sg:city":"Boones Mill",
    "sg:classifiers":[
        {
            "category":"Home & Garden",
            "subcategory":"Furniture",
            "type":"Retail Goods"
        }
    ],
    "sg:phone":"+1 540 334 5936",
    "sg:postcode":"24065",
    "sg:province":"VA",
    "sg:tags":[
        "interior",
        "reupholstery"
    ],
    "wof:name":"Heart and Home Interiors",
    "wof:placetype":"venue"
},
  "geometry": {"coordinates":[-80.045721,37.035427],"type":"Point"}
}