{
  "type": "Feature",
  "properties": {
    "iso:country":"US",
    "sg:address":"306 Oakridge Blvd",
    "sg:city":"Lynchburg",
    "sg:classifiers":[
        {
            "category":"Building & Trades",
            "subcategory":"Construction",
            "type":"Services"
        }
    ],
    "sg:phone":"+1 434 528 9138",
    "sg:postcode":"24502",
    "sg:province":"VA",
    "sg:tags":[
        "contractor"
    ],
    "wof:name":"Jerome Enos Contractor",
    "wof:placetype":"venue"
},
  "geometry": {"coordinates":[-79.177395,37.391433],"type":"Point"}
}