{
  "type": "Feature",
  "properties": {
    "addr:full":"188 Tattle Branch Rd Chilhowie VA 24319",
    "addr:housenumber":"188",
    "addr:postcode":"24319",
    "addr:street":"Tattle Branch Rd",
    "iso:country":"US",
    "sg:address":"188 Tattle Branch Rd",
    "sg:city":"Chilhowie",
    "sg:classifiers":[
        {
            "category":"Organizations",
            "subcategory":"Religious Organization",
            "type":"Services"
        }
    ],
    "sg:phone":"+1 276 646 8222",
    "sg:postcode":"24319",
    "sg:province":"VA",
    "sg:tags":[
        "church"
    ],
    "wof:name":"Middle Fork Baptist",
    "wof:placetype":"venue"
},
  "geometry": {"coordinates":[-81.663903,36.809997],"type":"Point"}
}