{
  "type": "Feature",
  "properties": {
    "addr:full":"1001 Dewolfe Dr Alexandria VA 22308",
    "addr:housenumber":"1001",
    "addr:postcode":"22308",
    "addr:street":"Dewolfe Dr",
    "iso:country":"US",
    "sg:address":"1001 Dewolfe Dr",
    "sg:city":"Alexandria",
    "sg:classifiers":[
        {
            "category":"Professional",
            "subcategory":"Advertising",
            "type":"Services"
        }
    ],
    "sg:phone":"+1 703 799 0024",
    "sg:postcode":"22308",
    "sg:province":"VA",
    "sg:tags":[
        "counselor",
        "agency"
    ],
    "sg:website":"www.theandrewsagency.com",
    "wof:name":"Andrews Agency The",
    "wof:placetype":"venue"
},
  "geometry": {"coordinates":[-77.047481,38.722383],"type":"Point"}
}