{
  "type": "Feature",
  "properties": {
    "addr:full":"9102 Dove Creek Pl Mechanicsville VA 23116",
    "addr:housenumber":"9102",
    "addr:postcode":"23116",
    "addr:street":"Dove Creek Pl",
    "iso:country":"US",
    "sg:address":"9102 Dove Creek Pl",
    "sg:city":"Mechanicsville",
    "sg:classifiers":[
        {
            "category":"Home & Garden",
            "subcategory":"Building Materials",
            "type":"Retail Goods"
        }
    ],
    "sg:phone":"+1 804 746 7830",
    "sg:postcode":"23116",
    "sg:province":"VA",
    "wof:name":"National Distributing Inc",
    "wof:placetype":"venue"
},
  "geometry": {"coordinates":[-77.38447499999999,37.650022],"type":"Point"}
}