{
  "type": "Feature",
  "properties": {
    "addr:full":"7794 Progress Ct Gainesville VA 20155",
    "addr:housenumber":"7794",
    "addr:postcode":"20155",
    "addr:street":"Progress Ct",
    "iso:country":"US",
    "sg:address":"7794 Progress Ct",
    "sg:city":"Gainesville",
    "sg:classifiers":[
        {
            "category":"Autos & Motor Vehicles",
            "subcategory":"Automobile Sales",
            "type":"Retail Goods"
        }
    ],
    "sg:phone":"+1 703 753 0720",
    "sg:postcode":"20155",
    "sg:province":"VA",
    "sg:tags":[
        "automotive"
    ],
    "sg:website":"www.jk-auto.com",
    "wof:name":"JK Auto Parts",
    "wof:placetype":"venue"
},
  "geometry": {"coordinates":[-77.593762,38.790306],"type":"Point"}
}