{
  "type": "Feature",
  "properties": {
    "iso:country":"US",
    "sg:address":"9557 Saluda Ct",
    "sg:city":"Lorton",
    "sg:classifiers":[
        {
            "category":"Freight",
            "type":"Transportation"
        }
    ],
    "sg:phone":"+1 703 283 2857",
    "sg:postcode":"22079",
    "sg:province":"VA",
    "sg:tags":[
        "operator",
        "local",
        "trucking"
    ],
    "wof:name":"Lab Delivery",
    "wof:placetype":"venue"
},
  "geometry": {"coordinates":[-77.21150900000001,38.700786],"type":"Point"}
}