{
  "type": "Feature",
  "properties": {
    "addr:full":"1508 Bumpass Rd Bumpass VA 23024",
    "addr:housenumber":"1508",
    "addr:postcode":"23024",
    "addr:street":"Bumpass Rd",
    "iso:country":"US",
    "sg:address":"1508 Bumpass Rd",
    "sg:city":"Bumpass",
    "sg:classifiers":[
        {
            "category":"Professional",
            "subcategory":"Lawyer & Legal Services",
            "type":"Services"
        }
    ],
    "sg:phone":"+1 540 872 3515",
    "sg:postcode":"23024",
    "sg:province":"VA",
    "sg:tags":[
        "attorney"
    ],
    "wof:name":"David Wayne Gramling",
    "wof:placetype":"venue"
},
  "geometry": {"coordinates":[-77.732511,37.964459],"type":"Point"}
}