{
  "type": "Feature",
  "properties": {
    "addr:full":"1300 Branchlands Dr Charlottesville VA 22901",
    "addr:housenumber":"1300",
    "addr:postcode":"22901",
    "addr:street":"Branchlands Dr",
    "iso:country":"US",
    "sg:address":"1300 Branchlands Dr",
    "sg:city":"Charlottesville",
    "sg:classifiers":[
        {
            "category":"Professional",
            "type":"Services"
        }
    ],
    "sg:phone":"+1 434 978 1997",
    "sg:postcode":"22901",
    "sg:province":"VA",
    "sg:tags":[
        "establishment"
    ],
    "wof:name":"MHC Of Charlottesville Va",
    "wof:placetype":"venue"
},
  "geometry": {"coordinates":[-78.477729,38.07152],"type":"Point"}
}