{
  "type": "Feature",
  "properties": {
    "iso:country":"US",
    "sg:address":"412 Dunmore St",
    "sg:city":"Fredericksburg",
    "sg:classifiers":[
        {
            "category":"Retail",
            "subcategory":"Auto Rental",
            "type":"Services"
        }
    ],
    "sg:phone":"+1 540 370 0033",
    "sg:postcode":"22401",
    "sg:province":"VA",
    "sg:tags":[
        "renting",
        "automobile"
    ],
    "wof:name":"Berryman's Car Rental Svc",
    "wof:placetype":"venue"
},
  "geometry": {"coordinates":[-77.45714,38.295004],"type":"Point"}
}