{
  "type": "Feature",
  "properties": {
    "addr:full":"1940 Blue Ridge Rd Charlottesville VA 22903",
    "addr:housenumber":"1940",
    "addr:postcode":"22903",
    "addr:street":"Blue Ridge Rd",
    "iso:country":"US",
    "sg:address":"1940 Blue Ridge Rd",
    "sg:city":"Charlottesville",
    "sg:classifiers":[
        {
            "category":"Real Estate",
            "subcategory":"Real Estate Operator",
            "type":"Services"
        }
    ],
    "sg:phone":"+1 434 295 6553",
    "sg:postcode":"22903",
    "sg:province":"VA",
    "sg:tags":[
        "apartment"
    ],
    "wof:name":"Charlottesville Apartments",
    "wof:placetype":"venue"
},
  "geometry": {"coordinates":[-78.492203,38.0495],"type":"Point"}
}