{
  "type": "Feature",
  "properties": {
    "addr:full":"1120 Old New Castle Rd Manquin VA 23106",
    "addr:housenumber":"1120",
    "addr:postcode":"23106",
    "addr:street":"Old New Castle Rd",
    "iso:country":"US",
    "sg:address":"1120 Old New Castle Rd",
    "sg:city":"Manquin",
    "sg:classifiers":[
        {
            "category":"Building & Trades",
            "subcategory":"Plumbing",
            "type":"Services"
        }
    ],
    "sg:phone":"+1 804 769 0475",
    "sg:postcode":"23106",
    "sg:province":"VA",
    "sg:tags":[
        "mechanical",
        "contractor"
    ],
    "wof:name":"R W Mechanical",
    "wof:placetype":"venue"
},
  "geometry": {"coordinates":[-77.15650599999999,37.687728],"type":"Point"}
}