{
  "type": "Feature",
  "properties": {
    "addr:full":"2975 Ivy Rd Charlottesvle VA 22903",
    "addr:housenumber":"2975",
    "addr:postcode":"22903",
    "addr:street":"Ivy Rd",
    "iso:country":"US",
    "sg:address":"2975 Ivy Rd",
    "sg:city":"Charlottesvle",
    "sg:classifiers":[
        {
            "category":"Home & Garden",
            "subcategory":"Home Furnishings",
            "type":"Retail Goods"
        }
    ],
    "sg:phone":"+1 434 295 0849",
    "sg:postcode":"22903",
    "sg:province":"VA",
    "sg:tags":[
        "decor"
    ],
    "wof:name":"Asd Luck Stone",
    "wof:placetype":"venue"
},
  "geometry": {"coordinates":[-78.54830200000001,38.050598],"type":"Point"}
}