{
  "type": "Feature",
  "properties": {
    "addr:full":"4825 S Laburnum Ave Richmond VA 23231",
    "addr:housenumber":"4825",
    "addr:postcode":"23231",
    "addr:street":"S Laburnum Ave",
    "iso:country":"US",
    "sg:address":"4825 S Laburnum Ave",
    "sg:city":"Richmond",
    "sg:classifiers":[
        {
            "category":"Professional",
            "type":"Services"
        }
    ],
    "sg:phone":"+1 804 222 2607",
    "sg:postcode":"23231",
    "sg:province":"VA",
    "wof:name":"Henrico Co Client Services",
    "wof:placetype":"venue"
},
  "geometry": {"coordinates":[-77.350792,37.519543],"type":"Point"}
}