{
  "type": "Feature",
  "properties": {
    "addr:full":"7201 Midlothian Tpke Richmond VA 23225",
    "addr:housenumber":"7201",
    "addr:postcode":"23225",
    "addr:street":"Midlothian Tpke",
    "iso:country":"US",
    "sg:address":"7201 Midlothian Tpke",
    "sg:city":"Richmond",
    "sg:classifiers":[
        {
            "category":"Building & Trades",
            "subcategory":"Cleaning & Sanitation",
            "type":"Services"
        }
    ],
    "sg:phone":"+1 804 276 5966",
    "sg:postcode":"23225",
    "sg:province":"VA",
    "sg:tags":[
        "janitorial"
    ],
    "sg:website":"http://www.defenderservices.com",
    "wof:name":"Defender Services, Inc.",
    "wof:placetype":"venue"
},
  "geometry": {"coordinates":[-77.529363,37.500582],"type":"Point"}
}