{
  "type": "Feature",
  "properties": {
    "iso:country":"US",
    "sg:address":"2801 Jefferson Davis Hwy",
    "sg:city":"Alexandria",
    "sg:classifiers":[
        {
            "category":"Building & Trades",
            "subcategory":"Construction",
            "type":"Services"
        }
    ],
    "sg:phone":"+1 703 299 6724",
    "sg:postcode":"22301",
    "sg:province":"VA",
    "sg:tags":[
        "contractor"
    ],
    "wof:name":"Truland Systems Corp",
    "wof:placetype":"venue"
},
  "geometry": {"coordinates":[-77.05079600000001,38.830981],"type":"Point"}
}