{
  "type": "Feature",
  "properties": {
    "addr:full":"9200 Stony Point Pkwy Richmond VA 23235",
    "addr:housenumber":"9200",
    "addr:postcode":"23235",
    "addr:street":"Stony Point Pkwy",
    "iso:country":"US",
    "sg:address":"9200 Stony Point Pkwy",
    "sg:city":"Richmond",
    "sg:classifiers":[
        {
            "category":"Shopping",
            "type":"Retail Goods"
        }
    ],
    "sg:phone":"+1 804 330 5920",
    "sg:postcode":"23235",
    "sg:province":"VA",
    "sg:tags":[
        "item",
        "boutique"
    ],
    "wof:name":"Movado Boutique",
    "wof:placetype":"venue"
},
  "geometry": {"coordinates":[-77.57308999999999,37.547409],"type":"Point"}
}