{
  "type": "Feature",
  "properties": {
    "addr:full":"94 Ridgecrest Rd Bristol VA 37620",
    "addr:housenumber":"94",
    "addr:postcode":"37620",
    "addr:street":"Ridgecrest Rd",
    "iso:country":"US",
    "sg:address":"94 Ridgecrest Rd",
    "sg:city":"Bristol",
    "sg:classifiers":[
        {
            "category":"Organizations",
            "subcategory":"Religious Organization",
            "type":"Services"
        }
    ],
    "sg:phone":"+1 423 968 3006",
    "sg:postcode":"37620",
    "sg:province":"VA",
    "sg:tags":[
        "church"
    ],
    "wof:name":"Full Gopsel Fellowship Assmbly",
    "wof:placetype":"venue"
},
  "geometry": {"coordinates":[-82.169636,36.573117],"type":"Point"}
}