{
  "type": "Feature",
  "properties": {
    "iso:country":"US",
    "sg:address":"316 Commerce St",
    "sg:city":"Alexandria",
    "sg:classifiers":[
        {
            "category":"Personal",
            "type":"Services"
        }
    ],
    "sg:phone":"+1 703 914 4545",
    "sg:postcode":"22314",
    "sg:province":"VA",
    "sg:tags":[
        "therapist",
        "massage"
    ],
    "wof:name":"Janet De Holl",
    "wof:placetype":"venue"
},
  "geometry": {"coordinates":[-77.05670000000001,38.804284],"type":"Point"}
}