{
  "type": "Feature",
  "properties": {
    "addr:full":"5 Oakleigh Ave Appomattox VA 24522",
    "addr:housenumber":"5",
    "addr:postcode":"24522",
    "addr:street":"Oakleigh Ave",
    "iso:country":"US",
    "sg:address":"5 Oakleigh Ave",
    "sg:city":"Appomattox",
    "sg:classifiers":[
        {
            "category":"Professional",
            "subcategory":"Lawyer & Legal Services",
            "type":"Services"
        }
    ],
    "sg:phone":"+1 434 352 0699",
    "sg:postcode":"24522",
    "sg:province":"VA",
    "sg:tags":[
        "attorney"
    ],
    "wof:name":"Micheal J Brickhill PC",
    "wof:placetype":"venue"
},
  "geometry": {"coordinates":[-78.823033,37.355342],"type":"Point"}
}