{
  "type": "Feature",
  "properties": {
    "addr:full":"8000 Towers Crescent Drive Suite 800 Vienna VA 22182",
    "addr:housenumber":"8000",
    "addr:postcode":"22182",
    "addr:street":"Towers Crescent Drive Suite 800",
    "iso:country":"US",
    "sg:address":"8000 Towers Crescent Drive Suite 800",
    "sg:city":"Vienna",
    "sg:classifiers":[
        {
            "category":"Professional",
            "subcategory":"Computer Services",
            "type":"Services"
        }
    ],
    "sg:phone":"+1 703 564 7758",
    "sg:postcode":"22182",
    "sg:province":"VA",
    "sg:tags":[
        "customer-support",
        "customer-service",
        "help-desk-software",
        "customer-service-software",
        "customer-support-software",
        "member-support",
        "player-support",
        "social-networking-support"
    ],
    "sg:website":"http://www.parature.com",
    "wof:name":"Parature",
    "wof:placetype":"venue"
},
  "geometry": {"coordinates":[-77.21982199999999,38.913664],"type":"Point"}
}