{
  "type": "Feature",
  "properties": {
    "addr:full":"2322 E Little Creek Rd Norfolk VA 23518",
    "addr:housenumber":"2322",
    "addr:postcode":"23518",
    "addr:street":"E Little Creek Rd",
    "iso:country":"US",
    "sg:address":"2322 E Little Creek Rd",
    "sg:city":"Norfolk",
    "sg:classifiers":[
        {
            "category":"Shopping",
            "subcategory":"Pharmacy",
            "type":"Retail Goods"
        }
    ],
    "sg:phone":"+1 757 480 6402",
    "sg:postcode":"23518",
    "sg:province":"VA",
    "sg:tags":[
        "equipment",
        "home",
        "medical",
        "supply"
    ],
    "wof:name":"American Drug Center Inc",
    "wof:placetype":"venue"
},
  "geometry": {"coordinates":[-76.219311,36.915263],"type":"Point"}
}