{
  "type": "Feature",
  "properties": {
    "iso:country":"US",
    "sg:address":"14367 Newbern Loop",
    "sg:city":"Gainesville",
    "sg:classifiers":[
        {
            "category":"Restaurant",
            "type":"Food & Drink"
        }
    ],
    "sg:phone":"+1 703 753 7300",
    "sg:postcode":"20155",
    "sg:province":"VA",
    "sg:tags":[
        "eating"
    ],
    "sg:website":"www.digitalmediakitchen.com",
    "wof:name":"Digital Media Kitchen",
    "wof:placetype":"venue"
},
  "geometry": {"coordinates":[-77.61801,38.810719],"type":"Point"}
}