{
  "type": "Feature",
  "properties": {
    "addr:full":"502 Tanbark Dr Afton VA 22920",
    "addr:housenumber":"502",
    "addr:postcode":"22920",
    "addr:street":"Tanbark Dr",
    "iso:country":"US",
    "sg:address":"502 Tanbark Dr",
    "sg:city":"Afton",
    "sg:classifiers":[
        {
            "category":"Wholesale",
            "subcategory":"Machinery & Supplies",
            "type":"Manufacturing & Wholesale Goods"
        }
    ],
    "sg:phone":"+1 540 456 8171",
    "sg:postcode":"22920",
    "sg:province":"VA",
    "sg:tags":[
        "industrial",
        "miscellaneous"
    ],
    "wof:name":"Afton Equipment Exchange",
    "wof:placetype":"venue"
},
  "geometry": {"coordinates":[-78.83895099999999,37.993595],"type":"Point"}
}