{
  "type": "Feature",
  "properties": {
    "iso:country":"US",
    "sg:address":"2 Stafford Ct",
    "sg:city":"Sterling",
    "sg:classifiers":[
        {
            "category":"Professional",
            "subcategory":"Business Services",
            "type":"Services"
        }
    ],
    "sg:phone":"+1 703 406 4483",
    "sg:postcode":"20165",
    "sg:province":"VA",
    "wof:name":"J & W Enteprises",
    "wof:placetype":"venue"
},
  "geometry": {"coordinates":[-77.406565,39.048172],"type":"Point"}
}