{
  "type": "Feature",
  "properties": {
    "iso:country":"US",
    "sg:address":"4004 Novar Dr",
    "sg:city":"Chantilly",
    "sg:classifiers":[
        {
            "category":"Building & Trades",
            "subcategory":"Construction",
            "type":"Services"
        }
    ],
    "sg:phone":"+1 703 263 1991",
    "sg:postcode":"20151",
    "sg:province":"VA",
    "sg:tags":[
        "carpentry",
        "contractor"
    ],
    "wof:name":"Samuel Carpentry Inc",
    "wof:placetype":"venue"
},
  "geometry": {"coordinates":[-77.417883,38.885334],"type":"Point"}
}