{
  "type": "Feature",
  "properties": {
    "addr:full":"206 Manassas Dr Manassas Park VA 20111",
    "addr:housenumber":"206",
    "addr:postcode":"20111",
    "addr:street":"Manassas Dr",
    "iso:country":"US",
    "sg:address":"206 Manassas Dr",
    "sg:city":"Manassas Park",
    "sg:classifiers":[
        {
            "category":"Organizations",
            "subcategory":"Religious Organization",
            "type":"Services"
        }
    ],
    "sg:phone":"+1 703 361 3385",
    "sg:postcode":"20111",
    "sg:province":"VA",
    "sg:tags":[
        "church"
    ],
    "wof:name":"First Bible Baptist Church",
    "wof:placetype":"venue"
},
  "geometry": {"coordinates":[-77.465447,38.781666],"type":"Point"}
}