{
  "type": "Feature",
  "properties": {
    "iso:country":"US",
    "sg:address":"1120 Lakeview Dr",
    "sg:city":"Portsmouth",
    "sg:classifiers":[
        {
            "category":"Social Services",
            "type":"Services"
        }
    ],
    "sg:phone":"+1 757 487 3870",
    "sg:postcode":"23701",
    "sg:province":"VA",
    "sg:tags":[
        "care",
        "center",
        "day"
    ],
    "wof:name":"Lucas Lodge Lakeview 1120",
    "wof:placetype":"venue"
},
  "geometry": {"coordinates":[-76.375933,36.790607],"type":"Point"}
}