{
  "type": "Feature",
  "properties": {
    "iso:country":"US",
    "sg:address":"1248 Green Garden Cir",
    "sg:city":"Virginia Beach",
    "sg:classifiers":[
        {
            "category":"Organizations",
            "subcategory":"Professional Association",
            "type":"Services"
        },
        {
            "category":"Organizations",
            "subcategory":"Community Association",
            "type":"Services"
        }
    ],
    "sg:phone":"+1 757 427 2600",
    "sg:postcode":"23453",
    "sg:province":"VA",
    "sg:tags":[
        "home"
    ],
    "wof:name":"Green Run Homes Association",
    "wof:placetype":"venue"
},
  "geometry": {"coordinates":[-76.089747,36.800354],"type":"Point"}
}