{
  "type": "Feature",
  "properties": {
    "iso:country":"US",
    "sg:address":"6796 Sugar Hollow Rd",
    "sg:city":"Crozet",
    "sg:classifiers":[
        {
            "category":"Government",
            "subcategory":"Office",
            "type":"Public Place"
        }
    ],
    "sg:phone":"+1 434 823 4738",
    "sg:postcode":"22932",
    "sg:province":"VA",
    "sg:tags":[
        "govt",
        "city"
    ],
    "wof:name":"Rivanna Water & Sewer Auth",
    "wof:placetype":"venue"
},
  "geometry": {"coordinates":[-78.736452,38.135149],"type":"Point"}
}