{
  "type": "Feature",
  "properties": {
    "iso:country":"US",
    "sg:address":"11 Bethel Rd",
    "sg:city":"Newport News",
    "sg:classifiers":[
        {
            "category":"Building & Trades",
            "subcategory":"Construction",
            "type":"Services"
        }
    ],
    "sg:phone":"+1 757 887 2890",
    "sg:postcode":"23608",
    "sg:province":"VA",
    "sg:tags":[
        "house"
    ],
    "wof:name":"Steves Odd Jobs",
    "wof:placetype":"venue"
},
  "geometry": {"coordinates":[-76.560186,37.164665],"type":"Point"}
}