{
  "type": "Feature",
  "properties": {
    "iso:country":"US",
    "sg:address":"1 College Cir",
    "sg:city":"Weyers Cave",
    "sg:classifiers":[
        {
            "category":"Shopping",
            "subcategory":"Books",
            "type":"Retail Goods"
        }
    ],
    "sg:phone":"+1 540 234 8606",
    "sg:postcode":"24401",
    "sg:province":"VA",
    "sg:tags":[
        "dealer"
    ],
    "wof:name":"BRCC Book Store",
    "wof:placetype":"venue"
},
  "geometry": {"coordinates":[-79.057839,38.169312],"type":"Point"}
}