{
  "type": "Feature",
  "properties": {
    "addr:full":"2561 Campostella Rd Chesapeake VA 23324",
    "addr:housenumber":"2561",
    "addr:postcode":"23324",
    "addr:street":"Campostella Rd",
    "iso:country":"US",
    "sg:address":"2561 Campostella Rd",
    "sg:city":"Chesapeake",
    "sg:classifiers":[
        {
            "category":"Food & Beverages",
            "subcategory":"Groceries & Convenience Stores",
            "type":"Retail Goods"
        }
    ],
    "sg:phone":"+1 757 545 5820",
    "sg:postcode":"23324",
    "sg:province":"VA",
    "wof:name":"Camp Ostella LLC",
    "wof:placetype":"venue"
},
  "geometry": {"coordinates":[-76.25574400000001,36.805409],"type":"Point"}
}