{
  "type": "Feature",
  "properties": {
    "iso:country":"US",
    "sg:address":"5850 14th St N",
    "sg:city":"Arlington",
    "sg:classifiers":[
        {
            "category":"Professional",
            "type":"Services"
        }
    ],
    "sg:phone":"+1 703 300 9033",
    "sg:postcode":"22205",
    "sg:province":"VA",
    "sg:tags":[
        "motion",
        "technician",
        "picture"
    ],
    "wof:name":"Dolce Studio Films",
    "wof:placetype":"venue"
},
  "geometry": {"coordinates":[-77.14321099999999,38.88253],"type":"Point"}
}