{
  "type": "Feature",
  "properties": {
    "addr:full":"1020 Champions Way Suffolk VA 23435",
    "addr:housenumber":"1020",
    "addr:postcode":"23435",
    "addr:street":"Champions Way",
    "iso:country":"US",
    "sg:address":"1020 Champions Way",
    "sg:city":"Suffolk",
    "sg:classifiers":[
        {
            "category":"Social Services",
            "subcategory":"Child Care",
            "type":"Services"
        }
    ],
    "sg:phone":"+1 757 483 2693",
    "sg:postcode":"23435",
    "sg:province":"VA",
    "wof:name":"Children's Harbor - Suffolk",
    "wof:placetype":"venue"
},
  "geometry": {"coordinates":[-76.441762,36.872452],"type":"Point"}
}