{
  "type": "Feature",
  "properties": {
    "iso:country":"US",
    "sg:address":"433 E Monroe Ave",
    "sg:city":"Alexandria",
    "sg:classifiers":[
        {
            "category":"Organizations",
            "subcategory":"Professional Association",
            "type":"Services"
        }
    ],
    "sg:phone":"+1 703 836 6232",
    "sg:postcode":"22301",
    "sg:province":"VA",
    "sg:website":"www.dmia.org",
    "wof:name":"Document Mgmt Industries Assn",
    "wof:placetype":"venue"
},
  "geometry": {"coordinates":[-77.055487,38.820694],"type":"Point"}
}