{
  "type": "Feature",
  "properties": {
    "addr:full":"1624 Boles Pl Virginia Beach VA 23454",
    "addr:housenumber":"1624",
    "addr:postcode":"23454",
    "addr:street":"Boles Pl",
    "iso:country":"US",
    "sg:address":"1624 Boles Pl",
    "sg:city":"Virginia Beach",
    "sg:classifiers":[
        {
            "category":"Home & Garden",
            "subcategory":"Garden Supply",
            "type":"Retail Goods"
        }
    ],
    "sg:phone":"+1 757 426 1338",
    "sg:postcode":"23454",
    "sg:province":"VA",
    "sg:tags":[
        "nurseryman"
    ],
    "wof:name":"Deer Ridge Nursery & Tree Farm",
    "wof:placetype":"venue"
},
  "geometry": {"coordinates":[-76.002808,36.78201],"type":"Point"}
}