{
  "type": "Feature",
  "properties": {
    "addr:full":"1409 Valley St Harrisonburg VA 22801",
    "addr:housenumber":"1409",
    "addr:postcode":"22801",
    "addr:street":"Valley St",
    "iso:country":"US",
    "sg:address":"1409 Valley St",
    "sg:city":"Harrisonburg",
    "sg:classifiers":[
        {
            "category":"Professional",
            "type":"Services"
        }
    ],
    "sg:phone":"+1 540 434 7431",
    "sg:postcode":"22801",
    "sg:province":"VA",
    "wof:name":"Polly H Taylor",
    "wof:placetype":"venue"
},
  "geometry": {"coordinates":[-78.878984,38.431948],"type":"Point"}
}