{
  "type": "Feature",
  "properties": {
    "iso:country":"US",
    "sg:address":"328 Cedar Green Rd",
    "sg:city":"Staunton",
    "sg:classifiers":[
        {
            "category":"Building & Trades",
            "subcategory":"Construction",
            "type":"Services"
        }
    ],
    "sg:phone":"+1 540 885 2189",
    "sg:postcode":"24401",
    "sg:province":"VA",
    "sg:tags":[
        "general",
        "light",
        "contractor",
        "commercial",
        "custom"
    ],
    "wof:name":"Lovegrove Construction Inc",
    "wof:placetype":"venue"
},
  "geometry": {"coordinates":[-79.122742,38.149908],"type":"Point"}
}