{
  "type": "Feature",
  "properties": {
    "addr:full":"5321 Dorchester Rd Norton VA 24273",
    "addr:housenumber":"5321",
    "addr:postcode":"24273",
    "addr:street":"Dorchester Rd",
    "iso:country":"US",
    "sg:address":"5321 Dorchester Rd",
    "sg:city":"Norton",
    "sg:classifiers":[
        {
            "category":"Organizations",
            "subcategory":"Religious Organization",
            "type":"Services"
        }
    ],
    "sg:phone":"+1 276 679 7419",
    "sg:postcode":"24273",
    "sg:province":"VA",
    "sg:tags":[
        "church"
    ],
    "wof:name":"Wilson's Chapel",
    "wof:placetype":"venue"
},
  "geometry": {"coordinates":[-82.633017,36.955113],"type":"Point"}
}