{
  "type": "Feature",
  "properties": {
    "addr:full":"1320 Carl D Silver Pkwy Fredericksburg VA 22401",
    "addr:housenumber":"1320",
    "addr:postcode":"22401",
    "addr:street":"Carl D Silver Pkwy",
    "iso:country":"US",
    "sg:address":"1320 Carl D Silver Pkwy",
    "sg:city":"Fredericksburg",
    "sg:classifiers":[
        {
            "category":"Banks & Credit Unions",
            "subcategory":"Bank",
            "type":"Services"
        }
    ],
    "sg:phone":"+1 540 548 3395",
    "sg:postcode":"22401",
    "sg:province":"VA",
    "sg:tags":[
        "personal",
        "state",
        "commercial",
        "institution"
    ],
    "wof:name":"Provident Bank",
    "wof:placetype":"venue"
},
  "geometry": {"coordinates":[-77.507949,38.301418],"type":"Point"}
}