{
  "type": "Feature",
  "properties": {
    "addr:full":"167 Old Oak Ln Winchester VA 22630",
    "addr:housenumber":"167",
    "addr:postcode":"22630",
    "addr:street":"Old Oak Ln",
    "iso:country":"US",
    "sg:address":"167 Old Oak Ln",
    "sg:city":"Winchester",
    "sg:classifiers":[
        {
            "category":"Farming",
            "subcategory":"Livestock Farm",
            "type":"Manufacturing & Wholesale Goods"
        }
    ],
    "sg:phone":"+1 540 667 7220",
    "sg:postcode":"22630",
    "sg:province":"VA",
    "sg:tags":[
        "beef",
        "orchard",
        "tree",
        "fruit",
        "cattle",
        "feedlot"
    ],
    "wof:name":"West Oaks Farm Inc",
    "wof:placetype":"venue"
},
  "geometry": {"coordinates":[-78.049041,38.987598],"type":"Point"}
}