{
  "type": "Feature",
  "properties": {
    "iso:country":"US",
    "sg:address":"5820 2nd St S",
    "sg:city":"Arlington",
    "sg:classifiers":[
        {
            "category":"Building & Trades",
            "subcategory":"Landscaping Services",
            "type":"Services"
        }
    ],
    "sg:phone":"+1 703 379 4688",
    "sg:postcode":"22204",
    "sg:province":"VA",
    "sg:tags":[
        "lawn",
        "landscape"
    ],
    "wof:name":"Arturo S Landscaping",
    "wof:placetype":"venue"
},
  "geometry": {"coordinates":[-77.127753,38.864494],"type":"Point"}
}