{
  "type": "Feature",
  "properties": {
    "addr:full":"6920 Bradlick Shopping Ctr Annandale VA 22003",
    "addr:housenumber":"6920",
    "addr:postcode":"22003",
    "addr:street":"Bradlick Shopping Ctr",
    "iso:country":"US",
    "sg:address":"6920 Bradlick Shopping Ctr",
    "sg:city":"Annandale",
    "sg:classifiers":[
        {
            "category":"Restaurant",
            "type":"Food & Drink"
        }
    ],
    "sg:phone":"+1 703 658 2252",
    "sg:postcode":"22003",
    "sg:province":"VA",
    "sg:tags":[
        "mexican"
    ],
    "wof:name":"Delmars Baja Mexican",
    "wof:placetype":"venue"
},
  "geometry": {"coordinates":[-77.184189,38.812611],"type":"Point"}
}