{
  "type": "Feature",
  "properties": {
    "iso:country":"US",
    "sg:address":"6400 Old Westham Dr N",
    "sg:city":"Suffolk",
    "sg:classifiers":[
        {
            "category":"Professional",
            "subcategory":"Management & Consulting",
            "type":"Services"
        }
    ],
    "sg:phone":"+1 757 483 5814",
    "sg:postcode":"23435",
    "sg:province":"VA",
    "sg:tags":[
        "educational"
    ],
    "wof:name":"Jbroks-Buck Eductl Consulting",
    "wof:placetype":"venue"
},
  "geometry": {"coordinates":[-76.41279,36.885484],"type":"Point"}
}