{
  "type": "Feature",
  "properties": {
    "addr:full":"4925 W Broad St Richmond VA 23230",
    "addr:housenumber":"4925",
    "addr:postcode":"23230",
    "addr:street":"W Broad St",
    "iso:country":"US",
    "sg:address":"4925 W Broad St",
    "sg:city":"Richmond",
    "sg:classifiers":[
        {
            "category":"Shopping",
            "subcategory":"Department Store",
            "type":"Retail Goods"
        }
    ],
    "sg:phone":"+1 804 355 4900",
    "sg:postcode":"23230",
    "sg:province":"VA",
    "sg:tags":[
        "shop"
    ],
    "wof:name":"Ben Franklin",
    "wof:placetype":"venue"
},
  "geometry": {"coordinates":[-77.496764,37.584219],"type":"Point"}
}