{
  "type": "Feature",
  "properties": {
    "addr:full":"3407 Alabama Ave Alexandria VA 22305",
    "addr:housenumber":"3407",
    "addr:postcode":"22305",
    "addr:street":"Alabama Ave",
    "iso:country":"US",
    "sg:address":"3407 Alabama Ave",
    "sg:city":"Alexandria",
    "sg:classifiers":[
        {
            "category":"Wholesale",
            "subcategory":"Durable Goods & Equipment",
            "type":"Manufacturing & Wholesale Goods"
        }
    ],
    "sg:phone":"+1 703 549 9898",
    "sg:postcode":"22305",
    "sg:province":"VA",
    "wof:name":"Supplement Co",
    "wof:placetype":"venue"
},
  "geometry": {"coordinates":[-77.068889,38.835328],"type":"Point"}
}