{
  "type": "Feature",
  "properties": {
    "addr:full":"801 Alta Cir Salem VA 24153",
    "addr:housenumber":"801",
    "addr:postcode":"24153",
    "addr:street":"Alta Cir",
    "iso:country":"US",
    "sg:address":"801 Alta Cir",
    "sg:city":"Salem",
    "sg:classifiers":[
        {
            "category":"Freight",
            "type":"Transportation"
        }
    ],
    "sg:phone":"+1 540 986 0167",
    "sg:postcode":"24153",
    "sg:province":"VA",
    "sg:tags":[
        "operator",
        "local",
        "trucking"
    ],
    "wof:name":"Franklin Spa Delivery Inc",
    "wof:placetype":"venue"
},
  "geometry": {"coordinates":[-80.02855599999999,37.311334],"type":"Point"}
}