{
  "type": "Feature",
  "properties": {
    "iso:country":"US",
    "sg:address":"1423 Powhatan St",
    "sg:city":"Alexandria",
    "sg:classifiers":[
        {
            "category":"Communications",
            "type":"Services"
        }
    ],
    "sg:phone":"+1 703 548 8900",
    "sg:postcode":"22314",
    "sg:province":"VA",
    "sg:tags":[
        "web",
        "design"
    ],
    "sg:website":"www.trinetinternetsolutions.com",
    "wof:name":"Trinet Internet Solutions",
    "wof:placetype":"venue"
},
  "geometry": {"coordinates":[-77.048101,38.820062],"type":"Point"}
}