{
  "type": "Feature",
  "properties": {
    "addr:full":"101 Mill Rd Yorktown VA 23693",
    "addr:housenumber":"101",
    "addr:postcode":"23693",
    "addr:street":"Mill Rd",
    "iso:country":"US",
    "sg:address":"101 Mill Rd",
    "sg:city":"Yorktown",
    "sg:classifiers":[
        {
            "category":"Professional",
            "subcategory":"Management & Consulting",
            "type":"Services"
        }
    ],
    "sg:phone":"+1 757 867 6162",
    "sg:postcode":"23693",
    "sg:province":"VA",
    "wof:name":"Matthews John E & Assoc Inc",
    "wof:placetype":"venue"
},
  "geometry": {"coordinates":[-76.457593,37.134668],"type":"Point"}
}