{
  "type": "Feature",
  "properties": {
    "addr:full":"910 Mecklenburg Ave Victoria VA 23974",
    "addr:housenumber":"910",
    "addr:postcode":"23974",
    "addr:street":"Mecklenburg Ave",
    "iso:country":"US",
    "sg:address":"910 Mecklenburg Ave",
    "sg:city":"Victoria",
    "sg:classifiers":[
        {
            "category":"Food & Beverages",
            "subcategory":"Groceries & Convenience Stores",
            "type":"Retail Goods"
        }
    ],
    "sg:phone":"+1 434 696 3650",
    "sg:postcode":"23974",
    "sg:province":"VA",
    "sg:tags":[
        "grocer"
    ],
    "wof:name":"Pennington Grocery Store",
    "wof:placetype":"venue"
},
  "geometry": {"coordinates":[-78.224417,36.985077],"type":"Point"}
}