{
  "type": "Feature",
  "properties": {
    "iso:country":"US",
    "sg:address":"5241 Westhaven Cres",
    "sg:city":"Virginia Beach",
    "sg:classifiers":[
        {
            "category":"Wholesale",
            "subcategory":"Vending Machines",
            "type":"Manufacturing & Wholesale Goods"
        }
    ],
    "sg:phone":"+1 757 467 6083",
    "sg:postcode":"23464",
    "sg:province":"VA",
    "sg:tags":[
        "operator"
    ],
    "wof:name":"Griffin Vending",
    "wof:placetype":"venue"
},
  "geometry": {"coordinates":[-76.16189,36.788455],"type":"Point"}
}