{
  "type": "Feature",
  "properties": {
    "addr:full":"154 Hampshire Sq SW Leesburg VA 20175",
    "addr:housenumber":"154",
    "addr:postcode":"20175",
    "addr:street":"Hampshire Sq Sw",
    "iso:country":"US",
    "sg:address":"154 Hampshire Sq SW",
    "sg:city":"Leesburg",
    "sg:classifiers":[
        {
            "category":"Banks & Credit Unions",
            "subcategory":"Bank",
            "type":"Services"
        }
    ],
    "sg:phone":"+1 703 779 5680",
    "sg:postcode":"20175",
    "sg:province":"VA",
    "sg:tags":[
        "mortgage"
    ],
    "wof:name":"East West Mortgage Company",
    "wof:placetype":"venue"
},
  "geometry": {"coordinates":[-77.58716,39.093953],"type":"Point"}
}