{
  "type": "Feature",
  "properties": {
    "iso:country":"US",
    "sg:address":"630 W Franklin St",
    "sg:city":"Wytheville",
    "sg:classifiers":[
        {
            "category":"Organizations",
            "subcategory":"Religious Organization",
            "type":"Services"
        }
    ],
    "sg:phone":"+1 276 228 7599",
    "sg:postcode":"24382",
    "sg:province":"VA",
    "sg:tags":[
        "church"
    ],
    "wof:name":"Sunny Hills Community Church",
    "wof:placetype":"venue"
},
  "geometry": {"coordinates":[-81.086614,36.944584],"type":"Point"}
}