{
  "type": "Feature",
  "properties": {
    "addr:full":"6847 Washington Blvd Arlington VA 22213",
    "addr:housenumber":"6847",
    "addr:postcode":"22213",
    "addr:street":"Washington Blvd",
    "iso:country":"US",
    "sg:address":"6847 Washington Blvd",
    "sg:city":"Arlington",
    "sg:classifiers":[
        {
            "category":"Building & Trades",
            "subcategory":"Construction",
            "type":"Services"
        },
        {
            "category":"Sports & Exercise",
            "subcategory":"Swimming Pool",
            "type":"Entertainment"
        }
    ],
    "sg:phone":"+1 703 538 2199",
    "sg:postcode":"22213",
    "sg:province":"VA",
    "wof:name":"High Sierra Pools",
    "wof:placetype":"venue"
},
  "geometry": {"coordinates":[-77.163033,38.889931],"type":"Point"}
}