{
  "type": "Feature",
  "properties": {
    "iso:country":"US",
    "sg:address":"2998 Lanier Ln",
    "sg:city":"Mc Gaheysville",
    "sg:classifiers":[
        {
            "category":"Building & Trades",
            "subcategory":"Construction",
            "type":"Services"
        }
    ],
    "sg:phone":"+1 540 289 5090",
    "sg:postcode":"22840",
    "sg:province":"VA",
    "sg:tags":[
        "house"
    ],
    "wof:name":"Jnl Remodeling LLC",
    "wof:placetype":"venue"
},
  "geometry": {"coordinates":[-78.715001,38.398573],"type":"Point"}
}