{
  "type": "Feature",
  "properties": {
    "addr:full":"10504 Beaver Pond Ct Fairfax Station VA 22039",
    "addr:housenumber":"10504",
    "addr:postcode":"22039",
    "addr:street":"Beaver Pond Ct",
    "iso:country":"US",
    "sg:address":"10504 Beaver Pond Ct",
    "sg:city":"Fairfax Station",
    "sg:classifiers":[
        {
            "category":"Professional",
            "type":"Services"
        }
    ],
    "sg:phone":"+1 703 250 0139",
    "sg:postcode":"22039",
    "sg:province":"VA",
    "wof:name":"Carbill Inc",
    "wof:placetype":"venue"
},
  "geometry": {"coordinates":[-77.308977,38.722226],"type":"Point"}
}