{
  "type": "Feature",
  "properties": {
    "addr:full":"1000 Salem Church Rd Stephens City VA 22655",
    "addr:housenumber":"1000",
    "addr:postcode":"22655",
    "addr:street":"Salem Church Rd",
    "iso:country":"US",
    "sg:address":"1000 Salem Church Rd",
    "sg:city":"Stephens City",
    "sg:classifiers":[
        {
            "category":"Building & Trades",
            "subcategory":"Construction",
            "type":"Services"
        }
    ],
    "sg:phone":"+1 540 869 2484",
    "sg:postcode":"22655",
    "sg:province":"VA",
    "sg:tags":[
        "contractor"
    ],
    "wof:name":"Reed Roofing",
    "wof:placetype":"venue"
},
  "geometry": {"coordinates":[-78.224897,39.042509],"type":"Point"}
}