{
  "type": "Feature",
  "properties": {
    "addr:full":"1310 Robinson Pl Falls Church VA 22046",
    "addr:housenumber":"1310",
    "addr:postcode":"22046",
    "addr:street":"Robinson Pl",
    "iso:country":"US",
    "sg:address":"1310 Robinson Pl",
    "sg:city":"Falls Church",
    "sg:classifiers":[
        {
            "category":"Retail",
            "subcategory":"Portrait Studio",
            "type":"Services"
        }
    ],
    "sg:phone":"+1 703 237 5623",
    "sg:postcode":"22046",
    "sg:province":"VA",
    "sg:tags":[
        "photo"
    ],
    "wof:name":"Mike Olliver Photography",
    "wof:placetype":"venue"
},
  "geometry": {"coordinates":[-77.18999700000001,38.881319],"type":"Point"}
}