{
  "type": "Feature",
  "properties": {
    "addr:full":"1861 Wiehle Ave Ste 125 Reston VA 20190",
    "addr:housenumber":"1861",
    "addr:postcode":"20190",
    "addr:street":"Wiehle Ave Ste 125",
    "iso:country":"US",
    "sg:address":"1861 Wiehle Ave Ste 125",
    "sg:city":"Reston",
    "sg:classifiers":[
        {
            "category":"Banks & Credit Unions",
            "subcategory":"Financial Services",
            "type":"Services"
        }
    ],
    "sg:phone":"+1 703 689 3553",
    "sg:postcode":"20190",
    "sg:province":"VA",
    "sg:tags":[
        "consultant",
        "planning"
    ],
    "wof:name":"John C Ferguson",
    "wof:placetype":"venue"
},
  "geometry": {"coordinates":[-77.336538,38.948783],"type":"Point"}
}