{
  "type": "Feature",
  "properties": {
    "addr:full":"7635 Hull Street Rd Richmond VA 23235",
    "addr:housenumber":"7635",
    "addr:postcode":"23235",
    "addr:street":"Hull Street Rd",
    "iso:country":"US",
    "sg:address":"7635 Hull Street Rd",
    "sg:city":"Richmond",
    "sg:classifiers":[
        {
            "category":"Organizations",
            "subcategory":"Non-profit Organization",
            "type":"Services"
        },
        {
            "category":"Professional",
            "subcategory":"Business Services",
            "type":"Services"
        }
    ],
    "sg:phone":"+1 804 276 9512",
    "sg:postcode":"23235",
    "sg:province":"VA",
    "sg:tags":[
        "fund",
        "counselor",
        "raising"
    ],
    "wof:name":"Mutual Funding Inc",
    "wof:placetype":"venue"
},
  "geometry": {"coordinates":[-77.533096,37.467843],"type":"Point"}
}