{
  "type": "Feature",
  "properties": {
    "addr:full":"16375 Doswell Park Rd Doswell VA 23047",
    "addr:postcode":"16375;23047",
    "addr:street":"Doswell Park Rd",
    "iso:country":"US",
    "sg:address":"16375 Doswell Park Rd",
    "sg:city":"Doswell",
    "sg:classifiers":[
        {
            "category":"Manufacturing",
            "subcategory":"Pet Food",
            "type":"Manufacturing & Wholesale Goods"
        }
    ],
    "sg:phone":"+1 804 876 3415",
    "sg:postcode":"23047",
    "sg:province":"VA",
    "sg:tags":[
        "feed"
    ],
    "sg:website":"www.griffinind.com",
    "wof:name":"Bakery Feeds",
    "wof:placetype":"venue"
},
  "geometry": {"coordinates":[-77.458552,37.859107],"type":"Point"}
}