{
  "type": "Feature",
  "properties": {
    "addr:full":"401 12th St S Arlington VA 22202",
    "addr:housenumber":"401",
    "addr:postcode":"22202",
    "addr:street":"12Th St S",
    "iso:country":"US",
    "sg:address":"401 12th St S",
    "sg:city":"Arlington",
    "sg:classifiers":[
        {
            "category":"Professional",
            "subcategory":"Management & Consulting",
            "type":"Services"
        }
    ],
    "sg:phone":"+1 602 743 0426",
    "sg:postcode":"22202",
    "sg:province":"VA",
    "sg:tags":[
        "business"
    ],
    "wof:name":"Carrie Brooks-Brown",
    "wof:placetype":"venue"
},
  "geometry": {"coordinates":[-77.051919,38.862922],"type":"Point"}
}