{
  "type": "Feature",
  "properties": {
    "addr:full":"11700 Sudley Manor Dr Manassas VA 20109",
    "addr:housenumber":"11700",
    "addr:postcode":"20109",
    "addr:street":"Sudley Manor Dr",
    "iso:country":"US",
    "sg:address":"11700 Sudley Manor Dr",
    "sg:city":"Manassas",
    "sg:classifiers":[
        {
            "category":"Organizations",
            "subcategory":"Religious Organization",
            "type":"Services"
        }
    ],
    "sg:phone":"+1 703 368 6286",
    "sg:postcode":"20109",
    "sg:province":"VA",
    "wof:name":"Christ In Action Ministries",
    "wof:placetype":"venue"
},
  "geometry": {"coordinates":[-77.528397,38.775101],"type":"Point"}
}