{
  "type": "Feature",
  "properties": {
    "addr:full":"921 Philpotts Rd Norfolk VA 23513",
    "addr:housenumber":"921",
    "addr:postcode":"23513",
    "addr:street":"Philpotts Rd",
    "iso:country":"US",
    "sg:address":"921 Philpotts Rd",
    "sg:city":"Norfolk",
    "sg:classifiers":[
        {
            "category":"Building & Trades",
            "subcategory":"Construction",
            "type":"Services"
        }
    ],
    "sg:phone":"+1 757 549 0656",
    "sg:postcode":"23513",
    "sg:province":"VA",
    "sg:tags":[
        "sandblasting",
        "painting"
    ],
    "wof:name":"North Marine Inc",
    "wof:placetype":"venue"
},
  "geometry": {"coordinates":[-76.250658,36.898394],"type":"Point"}
}