{
  "type": "Feature",
  "properties": {
    "addr:full":"4683 Mount Airy Rd Louisa VA 23093",
    "addr:housenumber":"4683",
    "addr:postcode":"23093",
    "addr:street":"Mount Airy Rd",
    "iso:country":"US",
    "sg:address":"4683 Mount Airy Rd",
    "sg:city":"Louisa",
    "sg:classifiers":[
        {
            "category":"Organizations",
            "subcategory":"Religious Organization",
            "type":"Services"
        }
    ],
    "sg:phone":"+1 540 967 9528",
    "sg:postcode":"23093",
    "sg:province":"VA",
    "wof:name":"Eagle Baptist Church",
    "wof:placetype":"venue"
},
  "geometry": {"coordinates":[-77.967478,37.999715],"type":"Point"}
}