{
  "type": "Feature",
  "properties": {
    "addr:full":"22883 Quicksilver Dr Sterling VA 20166",
    "addr:housenumber":"22883",
    "addr:postcode":"20166",
    "addr:street":"Quicksilver Dr",
    "iso:country":"US",
    "sg:address":"22883 Quicksilver Dr",
    "sg:city":"Sterling",
    "sg:classifiers":[
        {
            "category":"Manufacturing",
            "subcategory":"Printing",
            "type":"Manufacturing & Wholesale Goods"
        }
    ],
    "sg:phone":"+1 703 794 2148",
    "sg:postcode":"20166",
    "sg:province":"VA",
    "sg:tags":[
        "book"
    ],
    "wof:name":"Tab Professional Reference Bks",
    "wof:placetype":"venue"
},
  "geometry": {"coordinates":[-77.47703199999999,38.983182],"type":"Point"}
}