{
  "type": "Feature",
  "properties": {
    "iso:country":"US",
    "sg:address":"9433 Main St",
    "sg:city":"Manassas",
    "sg:classifiers":[
        {
            "category":"Wholesale",
            "subcategory":"Computers",
            "type":"Manufacturing & Wholesale Goods"
        }
    ],
    "sg:phone":"+1 703 393 0039",
    "sg:postcode":"20110",
    "sg:province":"VA",
    "sg:tags":[
        "distributor",
        "product",
        "production"
    ],
    "wof:name":"Falcon Graphic Solutions  Inc",
    "wof:placetype":"venue"
},
  "geometry": {"coordinates":[-77.471232,38.749864],"type":"Point"}
}