{
  "type": "Feature",
  "properties": {
    "addr:full":"10275 Racquet Cir Manassas VA 20110",
    "addr:housenumber":"10275",
    "addr:postcode":"20110",
    "addr:street":"Racquet Cir",
    "iso:country":"US",
    "sg:address":"10275 Racquet Cir",
    "sg:city":"Manassas",
    "sg:classifiers":[
        {
            "category":"Professional",
            "type":"Services"
        }
    ],
    "sg:phone":"+1 703 368 4454",
    "sg:postcode":"20110",
    "sg:province":"VA",
    "wof:name":"Lwd Inc",
    "wof:placetype":"venue"
},
  "geometry": {"coordinates":[-77.45884100000001,38.73724],"type":"Point"}
}