{
  "type": "Feature",
  "properties": {
    "addr:full":"9614 Coeburn Mountain Rd Wise VA 24293",
    "addr:housenumber":"9614",
    "addr:postcode":"24293",
    "addr:street":"Coeburn Mountain Rd",
    "iso:country":"US",
    "sg:address":"9614 Coeburn Mountain Rd",
    "sg:city":"Wise",
    "sg:classifiers":[
        {
            "category":"Organizations",
            "subcategory":"Religious Organization",
            "type":"Services"
        }
    ],
    "sg:phone":"+1 276 328 2076",
    "sg:postcode":"24293",
    "sg:province":"VA",
    "wof:name":"Mount Olive Freewill Baptist C",
    "wof:placetype":"venue"
},
  "geometry": {"coordinates":[-82.551416,36.966879],"type":"Point"}
}