{
  "type": "Feature",
  "properties": {
    "addr:full":"6853 Blackwells Hollow Rd Crozet VA 22932",
    "addr:postcode":"6853;22932",
    "addr:street":"Blackwells Hollow Rd",
    "iso:country":"US",
    "sg:address":"6853 Blackwells Hollow Rd",
    "sg:city":"Crozet",
    "sg:classifiers":[
        {
            "category":"Building & Trades",
            "subcategory":"Construction",
            "type":"Services"
        }
    ],
    "sg:phone":"+1 434 964 2181",
    "sg:postcode":"22932",
    "sg:province":"VA",
    "sg:tags":[
        "general",
        "contractor"
    ],
    "wof:name":"Brubeck Construction",
    "wof:placetype":"venue"
},
  "geometry": {"coordinates":[-78.636011,38.222883],"type":"Point"}
}