{
  "type": "Feature",
  "properties": {
    "iso:country":"US",
    "sg:address":"420 3rd St NE",
    "sg:city":"Charlottesville",
    "sg:classifiers":[
        {
            "category":"Social Services",
            "type":"Services"
        }
    ],
    "sg:phone":"+1 434 971 9287",
    "sg:postcode":"22902",
    "sg:province":"VA",
    "sg:tags":[
        "worker"
    ],
    "wof:name":"Jane W Ransom",
    "wof:placetype":"venue"
},
  "geometry": {"coordinates":[-78.478295,38.033687],"type":"Point"}
}