{
  "type": "Feature",
  "properties": {
    "addr:full":"Hilton Arlington 950 N Stafford St Arlington VA 22203",
    "addr:housenumber":"950",
    "addr:postcode":"22203",
    "addr:street":"N Stafford St",
    "iso:country":"US",
    "sg:address":"Hilton Arlington 950 N Stafford St",
    "sg:city":"Arlington",
    "sg:classifiers":[
        {
            "category":"Restaurant",
            "type":"Food & Drink"
        }
    ],
    "sg:phone":"+1 703 812 5114",
    "sg:postcode":"22203",
    "sg:province":"VA",
    "sg:tags":[
        "house",
        "american",
        "steak",
        "new"
    ],
    "wof:name":"Dan & Brad's",
    "wof:placetype":"venue"
},
  "geometry": {"coordinates":[-77.11067,38.881818],"type":"Point"}
}