{
  "type": "Feature",
  "properties": {
    "addr:full":"181 Oak Rd Bumpass VA 23024",
    "addr:housenumber":"181",
    "addr:postcode":"23024",
    "addr:street":"Oak Rd",
    "iso:country":"US",
    "sg:address":"181 Oak Rd",
    "sg:city":"Bumpass",
    "sg:classifiers":[
        {
            "category":"Farming",
            "subcategory":"Livestock Farm",
            "type":"Manufacturing & Wholesale Goods"
        }
    ],
    "sg:phone":"+1 540 872 3327",
    "sg:postcode":"23024",
    "sg:province":"VA",
    "sg:tags":[
        "beef",
        "feedlot",
        "cattle"
    ],
    "wof:name":"Charles Taylor Farm",
    "wof:placetype":"venue"
},
  "geometry": {"coordinates":[-77.729113,37.994177],"type":"Point"}
}