{
  "type": "Feature",
  "properties": {
    "iso:country":"US",
    "sg:address":"4426 Plantation Rd NE",
    "sg:city":"Roanoke",
    "sg:classifiers":[
        {
            "category":"Real Estate",
            "subcategory":"Real Estate Operator",
            "type":"Services"
        }
    ],
    "sg:phone":"+1 540 366 4316",
    "sg:postcode":"24012",
    "sg:province":"VA",
    "sg:tags":[
        "building",
        "apartment"
    ],
    "wof:name":"Frontier Apartments",
    "wof:placetype":"venue"
},
  "geometry": {"coordinates":[-79.933303,37.317248],"type":"Point"}
}