{
  "type": "Feature",
  "properties": {
    "addr:full":"1354 Pearl Ln Blacksburg VA 24060",
    "addr:housenumber":"1354",
    "addr:postcode":"24060",
    "addr:street":"Pearl Ln",
    "iso:country":"US",
    "sg:address":"1354 Pearl Ln",
    "sg:city":"Blacksburg",
    "sg:classifiers":[
        {
            "category":"Retail",
            "subcategory":"Repair Shop",
            "type":"Services"
        }
    ],
    "sg:phone":"+1 540 951 0398",
    "sg:postcode":"24060",
    "sg:province":"VA",
    "sg:tags":[
        "repairing",
        "piano",
        "refinishing"
    ],
    "wof:name":"Doss Piano Svc",
    "wof:placetype":"venue"
},
  "geometry": {"coordinates":[-80.433295,37.192229],"type":"Point"}
}