{
  "type": "Feature",
  "properties": {
    "addr:full":"4600 Monticello Ave Williamsburg VA 23188",
    "addr:housenumber":"4600",
    "addr:postcode":"23188",
    "addr:street":"Monticello Ave",
    "iso:country":"US",
    "sg:address":"4600 Monticello Ave",
    "sg:city":"Williamsburg",
    "sg:classifiers":[
        {
            "category":"Restaurant",
            "type":"Food & Drink"
        }
    ],
    "sg:menulink":"http://www.allmenus.com/va/berkeley/218490-burger-king/menu/",
    "sg:postcode":"23188",
    "sg:province":"VA",
    "sg:tags":[
        "american"
    ],
    "wof:name":"Burger King",
    "wof:placetype":"venue"
},
  "geometry": {"coordinates":[-76.75953800000001,37.270387],"type":"Point"}
}