{
  "type": "Feature",
  "properties": {
    "iso:country":"US",
    "sg:address":"10750 Ambassador Dr",
    "sg:city":"Manassas",
    "sg:classifiers":[
        {
            "category":"Personal",
            "subcategory":"Beauty Salon",
            "type":"Services"
        }
    ],
    "sg:phone":"+1 703 369 3699",
    "sg:postcode":"20109",
    "sg:province":"VA",
    "sg:tags":[
        "shop"
    ],
    "wof:name":"Design Studio",
    "wof:placetype":"venue"
},
  "geometry": {"coordinates":[-77.51708000000001,38.793838],"type":"Point"}
}