{
  "type": "Feature",
  "properties": {
    "addr:full":"1501 N Wilson Blvd Arlington VA 22209",
    "addr:housenumber":"1501",
    "addr:postcode":"22209",
    "addr:street":"N Wilson Blvd",
    "iso:country":"US",
    "sg:address":"1501 N Wilson Blvd",
    "sg:city":"Arlington",
    "sg:classifiers":[
        {
            "category":"Wholesale",
            "subcategory":"Electrical",
            "type":"Manufacturing & Wholesale Goods"
        }
    ],
    "sg:phone":"+1 703 528 8800",
    "sg:postcode":"22209",
    "sg:province":"VA",
    "sg:tags":[
        "control",
        "security",
        "system"
    ],
    "wof:name":"Kastle Systems",
    "wof:placetype":"venue"
},
  "geometry": {"coordinates":[-77.076731,38.894387],"type":"Point"}
}