{
  "type": "Feature",
  "properties": {
    "addr:full":"1707 26th St S Arlington VA 22206",
    "addr:housenumber":"1707",
    "addr:postcode":"22206",
    "addr:street":"26Th St S",
    "iso:country":"US",
    "sg:address":"1707 26th St S",
    "sg:city":"Arlington",
    "sg:classifiers":[
        {
            "category":"Professional",
            "type":"Services"
        }
    ],
    "sg:phone":"+1 703 836 0745",
    "sg:postcode":"22206",
    "sg:province":"VA",
    "sg:tags":[
        "establishment"
    ],
    "wof:name":"Park At Arlington",
    "wof:placetype":"venue"
},
  "geometry": {"coordinates":[-77.075124,38.848548],"type":"Point"}
}