{
  "type": "Feature",
  "properties": {
    "addr:full":"1515 Summerset Pl Herndon VA 20170",
    "addr:housenumber":"1515",
    "addr:postcode":"20170",
    "addr:street":"Summerset Pl",
    "iso:country":"US",
    "sg:address":"1515 Summerset Pl",
    "sg:city":"Herndon",
    "sg:classifiers":[
        {
            "category":"Retail",
            "subcategory":"Repair Shop",
            "type":"Services"
        },
        {
            "category":"Building & Trades",
            "subcategory":"Plumbing",
            "type":"Services"
        }
    ],
    "sg:phone":"+1 703 478 3993",
    "sg:postcode":"20170",
    "sg:province":"VA",
    "sg:tags":[
        "equipment",
        "conditioning",
        "air",
        "heating",
        "contractor"
    ],
    "wof:name":"T & T Associates Inc",
    "wof:placetype":"venue"
},
  "geometry": {"coordinates":[-77.409256,38.974132],"type":"Point"}
}