{
  "type": "Feature",
  "properties": {
    "addr:full":"5210 Anthony Rd Sandston VA 23150",
    "addr:housenumber":"5210",
    "addr:postcode":"23150",
    "addr:street":"Anthony Rd",
    "iso:country":"US",
    "sg:address":"5210 Anthony Rd",
    "sg:city":"Sandston",
    "sg:classifiers":[
        {
            "category":"Manufacturing",
            "subcategory":"Printing",
            "type":"Manufacturing & Wholesale Goods"
        },
        {
            "category":"Professional",
            "subcategory":"Printing & Photocopies",
            "type":"Services"
        }
    ],
    "sg:phone":"+1 800 463 3339",
    "sg:postcode":"23150",
    "sg:province":"VA",
    "sg:tags":[
        "document",
        "digital",
        "duplicating",
        "copying",
        "imaging"
    ],
    "sg:website":"http://www.fedex.com",
    "wof:name":"FedEx Express Airport Facility",
    "wof:placetype":"venue"
},
  "geometry": {"coordinates":[-77.337431,37.513608],"type":"Point"}
}