{
  "type": "Feature",
  "properties": {
    "iso:country":"US",
    "sg:address":"5312 Commons Ct",
    "sg:city":"Virginia Beach",
    "sg:classifiers":[
        {
            "category":"Education",
            "subcategory":"Special Training",
            "type":"Public Place"
        }
    ],
    "sg:phone":"+1 757 456 0936",
    "sg:postcode":"23462",
    "sg:province":"VA",
    "wof:name":"Go E Squared",
    "wof:placetype":"venue"
},
  "geometry": {"coordinates":[-76.168566,36.836002],"type":"Point"}
}