{
  "type": "Feature",
  "properties": {
    "iso:country":"US",
    "sg:address":"9057 Marmont Ln",
    "sg:city":"Williamsburg",
    "sg:classifiers":[
        {
            "category":"Professional",
            "subcategory":"Computer Services",
            "type":"Services"
        }
    ],
    "sg:phone":"+1 757 566 3774",
    "sg:postcode":"23188",
    "sg:province":"VA",
    "wof:name":"Basic PC Functions",
    "wof:placetype":"venue"
},
  "geometry": {"coordinates":[-76.73699999999999,37.411165],"type":"Point"}
}