{
  "type": "Feature",
  "properties": {
    "addr:full":"116 Creeden Dr Moneta VA 24121",
    "addr:housenumber":"116",
    "addr:postcode":"24121",
    "addr:street":"Creeden Dr",
    "iso:country":"US",
    "sg:address":"116 Creeden Dr",
    "sg:city":"Moneta",
    "sg:classifiers":[
        {
            "category":"Retail",
            "subcategory":"Self-service Laundry",
            "type":"Services"
        }
    ],
    "sg:phone":"+1 540 297 5030",
    "sg:postcode":"24121",
    "sg:province":"VA",
    "sg:tags":[
        "coin"
    ],
    "wof:name":"Village Laundromat",
    "wof:placetype":"venue"
},
  "geometry": {"coordinates":[-79.619711,37.112038],"type":"Point"}
}