{
  "type": "Feature",
  "properties": {
    "iso:country":"US",
    "sg:address":"2203 W Mercury Blvd",
    "sg:city":"Hampton",
    "sg:classifiers":[
        {
            "category":"Restaurant",
            "type":"Food & Drink"
        }
    ],
    "sg:phone":"+1 757 262 1109",
    "sg:postcode":"23666",
    "sg:province":"VA",
    "wof:name":"Texas Steakhouse & Saloon",
    "wof:placetype":"venue"
},
  "geometry": {"coordinates":[-76.40441300000001,37.038112],"type":"Point"}
}