{
  "type": "Feature",
  "properties": {
    "addr:full":"4300 Penick Rd Henrico VA 23228",
    "addr:postcode":"4300;23228",
    "addr:street":"Penick Rd",
    "iso:country":"US",
    "sg:address":"4300 Penick Rd",
    "sg:city":"Henrico",
    "sg:classifiers":[
        {
            "category":"Autos & Motor Vehicles",
            "subcategory":"Auto Supplies",
            "type":"Retail Goods"
        },
        {
            "category":"Manufacturing",
            "subcategory":"Glass & Minerals",
            "type":"Manufacturing & Wholesale Goods"
        },
        {
            "category":"Retail",
            "subcategory":"Auto Repair",
            "type":"Services"
        }
    ],
    "sg:phone":"+1 804 288 3008",
    "sg:postcode":"23228",
    "sg:province":"VA",
    "sg:tags":[
        "plate",
        "automobile",
        "shape",
        "accessory",
        "window",
        "part",
        "special",
        "circle",
        "windshield",
        "glass-auto"
    ],
    "wof:name":"AA Auto Glass",
    "wof:placetype":"venue"
},
  "geometry": {"coordinates":[-77.500242,37.61043],"type":"Point"}
}