{
  "type": "Feature",
  "properties": {
    "iso:country":"US",
    "sg:address":"2401 Smith Creek Rd",
    "sg:city":"New Market",
    "sg:classifiers":[
        {
            "category":"Farming",
            "subcategory":"Farm",
            "type":"Manufacturing & Wholesale Goods"
        }
    ],
    "sg:phone":"+1 540 740 3686",
    "sg:postcode":"22844",
    "sg:province":"VA",
    "sg:tags":[
        "crop",
        "general"
    ],
    "wof:name":"John J Patricia L Brumback Frm",
    "wof:placetype":"venue"
},
  "geometry": {"coordinates":[-78.64452199999999,38.643316],"type":"Point"}
}