{
  "type": "Feature",
  "properties": {
    "iso:country":"US",
    "sg:address":"2616 Volunteer Pkwy",
    "sg:city":"Bristol",
    "sg:classifiers":[
        {
            "category":"Retail",
            "subcategory":"Veterinary Services",
            "type":"Services"
        }
    ],
    "sg:phone":"+1 423 968 7241",
    "sg:postcode":"37620",
    "sg:province":"VA",
    "wof:name":"Parkway Animal Clinic",
    "wof:placetype":"venue"
},
  "geometry": {"coordinates":[-82.254865,36.525897],"type":"Point"}
}