{
  "type": "Feature",
  "properties": {
    "iso:country":"US",
    "sg:address":"8810 Gayton Rd",
    "sg:city":"Richmond",
    "sg:classifiers":[
        {
            "category":"Building & Trades",
            "subcategory":"Construction",
            "type":"Services"
        }
    ],
    "sg:phone":"+1 804 740 8113",
    "sg:postcode":"23229",
    "sg:province":"VA",
    "sg:tags":[
        "contractor"
    ],
    "wof:name":"Hobbs Masonry",
    "wof:placetype":"venue"
},
  "geometry": {"coordinates":[-77.572157,37.594751],"type":"Point"}
}