{
  "type": "Feature",
  "properties": {
    "addr:full":"1343 Flanagan Dr Christiansburg VA 24073",
    "addr:housenumber":"1343",
    "addr:postcode":"24073",
    "addr:street":"Flanagan Dr",
    "iso:country":"US",
    "sg:address":"1343 Flanagan Dr",
    "sg:city":"Christiansburg",
    "sg:classifiers":[
        {
            "category":"Building & Trades",
            "subcategory":"Cleaning & Sanitation",
            "type":"Services"
        },
        {
            "category":"Building & Trades",
            "subcategory":"Construction",
            "type":"Services"
        }
    ],
    "sg:phone":"+1 540 382 8712",
    "sg:postcode":"24073",
    "sg:province":"VA",
    "sg:tags":[
        "excavating",
        "contractor",
        "snow",
        "removal"
    ],
    "wof:name":"Woods Pipeline Excavating Inc",
    "wof:placetype":"venue"
},
  "geometry": {"coordinates":[-80.445131,37.110227],"type":"Point"}
}