{
  "type": "Feature",
  "properties": {
    "iso:country":"US",
    "sg:address":"6150 Finchingfield Rd",
    "sg:city":"Warrenton",
    "sg:classifiers":[
        {
            "category":"Professional",
            "subcategory":"Business Services",
            "type":"Services"
        }
    ],
    "sg:phone":"+1 540 428 2311",
    "sg:postcode":"20187",
    "sg:province":"VA",
    "sg:tags":[
        "international",
        "consultant",
        "trade"
    ],
    "wof:name":"Ezra International",
    "wof:placetype":"venue"
},
  "geometry": {"coordinates":[-77.696562,38.786409],"type":"Point"}
}