{
  "type": "Feature",
  "properties": {
    "addr:full":"1211 Slemp St Salem VA 24153",
    "addr:housenumber":"1211",
    "addr:postcode":"24153",
    "addr:street":"Slemp St",
    "iso:country":"US",
    "sg:address":"1211 Slemp St",
    "sg:city":"Salem",
    "sg:classifiers":[
        {
            "category":"Insurance",
            "subcategory":"Insurance Agent",
            "type":"Services"
        }
    ],
    "sg:phone":"+1 540 389 0823",
    "sg:postcode":"24153",
    "sg:province":"VA",
    "wof:name":"Trout Insurance Services",
    "wof:placetype":"venue"
},
  "geometry": {"coordinates":[-80.03267700000001,37.284776],"type":"Point"}
}