{
  "type": "Feature",
  "properties": {
    "addr:full":"2478 Minebank Rd Strasburg VA 22657",
    "addr:housenumber":"2478",
    "addr:postcode":"22657",
    "addr:street":"Minebank Rd",
    "iso:country":"US",
    "sg:address":"2478 Minebank Rd",
    "sg:city":"Strasburg",
    "sg:classifiers":[
        {
            "category":"Organizations",
            "subcategory":"Religious Organization",
            "type":"Services"
        }
    ],
    "sg:phone":"+1 540 635 6355",
    "sg:postcode":"22657",
    "sg:province":"VA",
    "wof:name":"Church At Waterlick",
    "wof:placetype":"venue"
},
  "geometry": {"coordinates":[-78.332847,39.037669],"type":"Point"}
}