{
  "type": "Feature",
  "properties": {
    "addr:full":"231 Roanoke Blvd Salem VA 24153",
    "addr:housenumber":"231",
    "addr:postcode":"24153",
    "addr:street":"Roanoke Blvd",
    "iso:country":"US",
    "sg:address":"231 Roanoke Blvd",
    "sg:city":"Salem",
    "sg:classifiers":[
        {
            "category":"Professional",
            "subcategory":"Lawyer & Legal Services",
            "type":"Services"
        }
    ],
    "sg:phone":"+1 540 375 7275",
    "sg:postcode":"24153",
    "sg:province":"VA",
    "wof:name":"Clemens & Clemens PC",
    "wof:placetype":"venue"
},
  "geometry": {"coordinates":[-80.053805,37.290243],"type":"Point"}
}