{
  "type": "Feature",
  "properties": {
    "addr:full":"Crossroad Ctr Alexandria VA 22301",
    "addr:postcode":"22301",
    "addr:street":"Crossroad Ctr",
    "iso:country":"US",
    "sg:address":"Crossroad Ctr",
    "sg:city":"Alexandria",
    "sg:classifiers":[
        {
            "category":"Shopping",
            "subcategory":"Shoes",
            "type":"Retail Goods"
        }
    ],
    "sg:phone":"+1 703 931 4047",
    "sg:postcode":"22301",
    "sg:province":"VA",
    "sg:tags":[
        "store"
    ],
    "sg:website":"www.payless.com",
    "wof:name":"Payless Shoesource",
    "wof:placetype":"venue"
},
  "geometry": {"coordinates":[-77.059601,38.820301],"type":"Point"}
}