{
  "type": "Feature",
  "properties": {
    "addr:full":"9008 Church St Manassas VA 20110",
    "addr:housenumber":"9008",
    "addr:postcode":"20110",
    "addr:street":"Church St",
    "iso:country":"US",
    "sg:address":"9008 Church St",
    "sg:city":"Manassas",
    "sg:classifiers":[
        {
            "category":"Arts & Performance",
            "subcategory":"Theater",
            "type":"Entertainment"
        }
    ],
    "sg:phone":"+1 703 365 0240",
    "sg:postcode":"20110",
    "sg:province":"VA",
    "wof:name":"Vpstart Crow Productions",
    "wof:placetype":"venue"
},
  "geometry": {"coordinates":[-77.469945,38.75203],"type":"Point"}
}