{
  "type": "Feature",
  "properties": {
    "addr:full":"6700 E Tanners Creek Dr Norfolk VA 23513",
    "addr:housenumber":"6700",
    "addr:postcode":"23513",
    "addr:street":"E Tanners Creek Dr",
    "iso:country":"US",
    "sg:address":"6700 E Tanners Creek Dr",
    "sg:city":"Norfolk",
    "sg:classifiers":[
        {
            "category":"Education",
            "subcategory":"Library",
            "type":"Public Place"
        }
    ],
    "sg:phone":"+1 757 441 5806",
    "sg:postcode":"23513",
    "sg:province":"VA",
    "sg:tags":[
        "executive"
    ],
    "wof:name":"Barron F Black Branch Library",
    "wof:placetype":"venue"
},
  "geometry": {"coordinates":[-76.229851,36.901845],"type":"Point"}
}