{
  "type": "Feature",
  "properties": {
    "iso:country":"US",
    "sg:address":"913 Haledon Rd",
    "sg:city":"Chesapeake",
    "sg:classifiers":[
        {
            "category":"Building & Trades",
            "subcategory":"Plumbing",
            "type":"Services"
        }
    ],
    "sg:phone":"+1 757 543 8045",
    "sg:postcode":"23320",
    "sg:province":"VA",
    "sg:tags":[
        "contractor"
    ],
    "wof:name":"Scotts Heating & Cooling",
    "wof:placetype":"venue"
},
  "geometry": {"coordinates":[-76.267021,36.770063],"type":"Point"}
}