{
  "type": "Feature",
  "properties": {
    "addr:full":"1634 Prospect Dr Chesapeake VA 23322",
    "addr:housenumber":"1634",
    "addr:postcode":"23322",
    "addr:street":"Prospect Dr",
    "iso:country":"US",
    "sg:address":"1634 Prospect Dr",
    "sg:city":"Chesapeake",
    "sg:classifiers":[
        {
            "category":"Professional",
            "subcategory":"Advertising",
            "type":"Services"
        }
    ],
    "sg:phone":"+1 757 546 8355",
    "sg:postcode":"23322",
    "sg:province":"VA",
    "sg:website":"www.quiltscape.com",
    "wof:name":"Rooftile Marketing",
    "wof:placetype":"venue"
},
  "geometry": {"coordinates":[-76.174087,36.710791],"type":"Point"}
}