{
  "type": "Feature",
  "properties": {
    "iso:country":"US",
    "sg:address":"6744 Gravel Ave",
    "sg:city":"Alexandria",
    "sg:classifiers":[
        {
            "category":"Manufacturing",
            "subcategory":"Building Materials",
            "type":"Manufacturing & Wholesale Goods"
        }
    ],
    "sg:phone":"+1 703 313 8101",
    "sg:postcode":"22310",
    "sg:province":"VA",
    "sg:tags":[
        "installs",
        "mfg",
        "custom"
    ],
    "wof:name":"Rainbow Custom Woodworking",
    "wof:placetype":"venue"
},
  "geometry": {"coordinates":[-77.15419300000001,38.771675],"type":"Point"}
}