{
  "type": "Feature",
  "properties": {
    "addr:full":"801 Davis St Ste 1 Blacksburg VA 24060",
    "addr:housenumber":"801",
    "addr:postcode":"24060",
    "addr:street":"Davis St Ste 1",
    "iso:country":"US",
    "sg:address":"801 Davis St Ste 1",
    "sg:city":"Blacksburg",
    "sg:classifiers":[
        {
            "category":"Health Services",
            "subcategory":"Doctor",
            "type":"Services"
        }
    ],
    "sg:phone":"+1 540 961 0218",
    "sg:postcode":"24060",
    "sg:province":"VA",
    "sg:tags":[
        "physician",
        "surgeon"
    ],
    "wof:name":"Dr Daniel Osimani",
    "wof:placetype":"venue"
},
  "geometry": {"coordinates":[-80.413737,37.187],"type":"Point"}
}