{
  "type": "Feature",
  "properties": {
    "addr:full":"6919 Lakeside Ave Richmond VA 23228",
    "addr:housenumber":"6919",
    "addr:postcode":"23228",
    "addr:street":"Lakeside Ave",
    "iso:country":"US",
    "sg:address":"6919 Lakeside Ave",
    "sg:city":"Richmond",
    "sg:classifiers":[
        {
            "category":"Shopping",
            "type":"Retail Goods"
        }
    ],
    "sg:phone":"+1 804 261 9335",
    "sg:postcode":"23228",
    "sg:province":"VA",
    "sg:tags":[
        "trophy",
        "medal",
        "award"
    ],
    "wof:name":"Champion Awards",
    "wof:placetype":"venue"
},
  "geometry": {"coordinates":[-77.470437,37.615771],"type":"Point"}
}