{
  "type": "Feature",
  "properties": {
    "addr:full":"5203 Franconia Rd Alexandria VA 22310",
    "addr:housenumber":"5203",
    "addr:postcode":"22310",
    "addr:street":"Franconia Rd",
    "iso:country":"US",
    "sg:address":"5203 Franconia Rd",
    "sg:city":"Alexandria",
    "sg:classifiers":[
        {
            "category":"Banks & Credit Unions",
            "subcategory":"Bank",
            "type":"Services"
        }
    ],
    "sg:phone":"+1 703 241 3465",
    "sg:postcode":"22310",
    "sg:province":"VA",
    "sg:tags":[
        "state"
    ],
    "wof:name":"Branch Banking and Trust Corp",
    "wof:placetype":"venue"
},
  "geometry": {"coordinates":[-77.126026,38.784199],"type":"Point"}
}