{
  "type": "Feature",
  "properties": {
    "iso:country":"US",
    "sg:address":"10608 Kitty Pozer Dr",
    "sg:city":"Fairfax",
    "sg:classifiers":[
        {
            "category":"Real Estate",
            "subcategory":"Real Estate Agent",
            "type":"Services"
        }
    ],
    "sg:phone":"+1 703 691 1097",
    "sg:postcode":"22030",
    "sg:province":"VA",
    "wof:name":"Avalon At Providence Park",
    "wof:placetype":"venue"
},
  "geometry": {"coordinates":[-77.314458,38.838677],"type":"Point"}
}