{
  "type": "Feature",
  "properties": {
    "iso:country":"US",
    "sg:address":"45665 Willow Pond Plaza",
    "sg:city":"Sterling",
    "sg:classifiers":[
        {
            "category":"Professional",
            "subcategory":"Computer Services",
            "type":"Services"
        }
    ],
    "sg:phone":"+1 703 435 6375",
    "sg:postcode":"20164",
    "sg:province":"VA",
    "sg:website":"http://www.paxfire.com",
    "wof:name":"Paxfire",
    "wof:placetype":"venue"
},
  "geometry": {"coordinates":[-77.422613,38.988775],"type":"Point"}
}