{
  "type": "Feature",
  "properties": {
    "iso:country":"US",
    "sg:address":"4316 George Washington Memorial Hwy",
    "sg:city":"Grafton",
    "sg:classifiers":[
        {
            "category":"Social Services",
            "subcategory":"Child Care",
            "type":"Services"
        }
    ],
    "sg:phone":"+1 757 898 8610",
    "sg:postcode":"23692",
    "sg:province":"VA",
    "sg:website":"www.lapetite.com",
    "wof:name":"LA Petite Academy",
    "wof:placetype":"venue"
},
  "geometry": {"coordinates":[-76.45740000000001,37.143429],"type":"Point"}
}