{
  "type": "Feature",
  "properties": {
    "iso:country":"US",
    "sg:address":"415 Duke St",
    "sg:city":"Tappahannock",
    "sg:classifiers":[
        {
            "category":"Health Services",
            "subcategory":"Clinic",
            "type":"Services"
        }
    ],
    "sg:phone":"+1 804 443 4073",
    "sg:postcode":"22560",
    "sg:province":"VA",
    "sg:tags":[
        "home"
    ],
    "wof:name":"Horizon Home Health Care LLC",
    "wof:placetype":"venue"
},
  "geometry": {"coordinates":[-76.860433,37.927003],"type":"Point"}
}