{
  "type": "Feature",
  "properties": {
    "addr:full":"9856 Lori Rd Chesterfield VA 23832",
    "addr:housenumber":"9856",
    "addr:postcode":"23832",
    "addr:street":"Lori Rd",
    "iso:country":"US",
    "sg:address":"9856 Lori Rd",
    "sg:city":"Chesterfield",
    "sg:classifiers":[
        {
            "category":"Health Services",
            "subcategory":"Doctor",
            "type":"Services"
        }
    ],
    "sg:phone":"+1 804 717 1100",
    "sg:postcode":"23832",
    "sg:province":"VA",
    "sg:tags":[
        "dentist"
    ],
    "wof:name":"Albert T Sasala Family Dentist",
    "wof:placetype":"venue"
},
  "geometry": {"coordinates":[-77.50998199999999,37.378878],"type":"Point"}
}