{
  "type": "Feature",
  "properties": {
    "addr:full":"10850 Main St Fairfax VA 22030",
    "addr:housenumber":"10850",
    "addr:postcode":"22030",
    "addr:street":"Main St",
    "iso:country":"US",
    "sg:address":"10850 Main St",
    "sg:city":"Fairfax",
    "sg:classifiers":[
        {
            "category":"Shopping",
            "subcategory":"Optical Goods",
            "type":"Retail Goods"
        }
    ],
    "sg:phone":"+1 703 273 8274",
    "sg:postcode":"22030",
    "sg:province":"VA",
    "wof:name":"Nuvision Optical International",
    "wof:placetype":"venue"
},
  "geometry": {"coordinates":[-77.31974599999999,38.851051],"type":"Point"}
}