{
  "type": "Feature",
  "properties": {
    "iso:country":"US",
    "sg:address":"2821 Shore Dr",
    "sg:city":"Virginia Beach",
    "sg:classifiers":[
        {
            "category":"Banks & Credit Unions",
            "subcategory":"Bank",
            "type":"Services"
        }
    ],
    "sg:phone":"+1 757 448 6400",
    "sg:postcode":"23451",
    "sg:province":"VA",
    "sg:tags":[
        "state",
        "commercial"
    ],
    "sg:website":"www.southtrust.com",
    "wof:name":"South Trust Bank",
    "wof:placetype":"venue"
},
  "geometry": {"coordinates":[-76.067001,36.912501],"type":"Point"}
}