{
  "type": "Feature",
  "properties": {
    "addr:full":"1001 N Fillmore St Arlington VA 22201",
    "addr:housenumber":"1001",
    "addr:postcode":"22201",
    "addr:street":"N Fillmore St",
    "iso:country":"US",
    "sg:address":"1001 N Fillmore St",
    "sg:city":"Arlington",
    "sg:classifiers":[
        {
            "category":"Government",
            "subcategory":"Office",
            "type":"Public Place"
        }
    ],
    "sg:phone":"+1 703 875 0135",
    "sg:postcode":"22201",
    "sg:province":"VA",
    "sg:tags":[
        "govt",
        "state",
        "utility"
    ],
    "wof:name":"Mines Minerals & Energy Dept",
    "wof:placetype":"venue"
},
  "geometry": {"coordinates":[-77.09293099999999,38.886278],"type":"Point"}
}