{
  "type": "Feature",
  "properties": {
    "addr:full":"60 Willow Branch Pl Fredericksburg VA 22405",
    "addr:housenumber":"60",
    "addr:postcode":"22405",
    "addr:street":"Willow Branch Pl",
    "iso:country":"US",
    "sg:address":"60 Willow Branch Pl",
    "sg:city":"Fredericksburg",
    "sg:classifiers":[
        {
            "category":"Building & Trades",
            "subcategory":"Construction",
            "type":"Services"
        }
    ],
    "sg:phone":"+1 540 373 2600",
    "sg:postcode":"22405",
    "sg:province":"VA",
    "sg:tags":[
        "cleaning",
        "exterior"
    ],
    "wof:name":"Magic Wand Pwerwashing Pntg Lc",
    "wof:placetype":"venue"
},
  "geometry": {"coordinates":[-77.441745,38.35546],"type":"Point"}
}