{
  "type": "Feature",
  "properties": {
    "iso:country":"US",
    "sg:address":"4055 Oak Moss Ct",
    "sg:city":"Chesapeake",
    "sg:classifiers":[
        {
            "category":"Building & Trades",
            "subcategory":"Landscaping Services",
            "type":"Services"
        }
    ],
    "sg:phone":"+1 757 488 6532",
    "sg:postcode":"23321",
    "sg:province":"VA",
    "wof:name":"Paxton Contractors Corp",
    "wof:placetype":"venue"
},
  "geometry": {"coordinates":[-76.406594,36.82995],"type":"Point"}
}