{
  "type": "Feature",
  "properties": {
    "addr:full":"409 S Pine St Richmond VA 23220",
    "addr:housenumber":"409",
    "addr:postcode":"23220",
    "addr:street":"S Pine St",
    "iso:country":"US",
    "sg:address":"409 S Pine St",
    "sg:city":"Richmond",
    "sg:classifiers":[
        {
            "category":"Professional",
            "subcategory":"Detective & Security Services",
            "type":"Services"
        }
    ],
    "sg:phone":"+1 804 780 0493",
    "sg:postcode":"23220",
    "sg:province":"VA",
    "sg:tags":[
        "system"
    ],
    "wof:name":"Investigative Consultants Inc",
    "wof:placetype":"venue"
},
  "geometry": {"coordinates":[-77.45038700000001,37.539253],"type":"Point"}
}