{
  "type": "Feature",
  "properties": {
    "addr:full":"11776 Stratford House Pl Ofc Reston VA 20190",
    "addr:housenumber":"11776",
    "addr:postcode":"20190",
    "addr:street":"Stratford House Pl",
    "iso:country":"US",
    "sg:address":"11776 Stratford House Pl Ofc",
    "sg:city":"Reston",
    "sg:classifiers":[
        {
            "category":"Shopping",
            "subcategory":"Catalog Store",
            "type":"Retail Goods"
        }
    ],
    "sg:phone":"+1 571 203 0099",
    "sg:postcode":"20190",
    "sg:province":"VA",
    "sg:tags":[
        "mail",
        "order",
        "online"
    ],
    "wof:name":"Stanley G Miller Enterprises Inc",
    "wof:placetype":"venue"
},
  "geometry": {"coordinates":[-77.354101,38.958381],"type":"Point"}
}