{
  "type": "Feature",
  "properties": {
    "addr:full":"54 Buena Rd Martinsville VA 24112",
    "addr:housenumber":"54",
    "addr:postcode":"24112",
    "addr:street":"Buena Rd",
    "iso:country":"US",
    "sg:address":"54 Buena Rd",
    "sg:city":"Martinsville",
    "sg:classifiers":[
        {
            "category":"Retail",
            "subcategory":"Repair Shop",
            "type":"Services"
        }
    ],
    "sg:phone":"+1 276 632 4592",
    "sg:postcode":"24112",
    "sg:province":"VA",
    "wof:name":"Automotive Upholstery",
    "wof:placetype":"venue"
},
  "geometry": {"coordinates":[-79.886464,36.643592],"type":"Point"}
}