{
  "type": "Feature",
  "properties": {
    "addr:full":"546 Park Ave NE Norton VA 24273",
    "addr:housenumber":"546",
    "addr:postcode":"24273",
    "addr:street":"Park Ave Ne",
    "iso:country":"US",
    "sg:address":"546 Park Ave NE",
    "sg:city":"Norton",
    "sg:classifiers":[
        {
            "category":"Shopping",
            "subcategory":"Department Store",
            "type":"Retail Goods"
        }
    ],
    "sg:phone":"+1 276 679 6110",
    "sg:postcode":"24273",
    "sg:province":"VA",
    "sg:tags":[
        "shop"
    ],
    "wof:name":"Debz",
    "wof:placetype":"venue"
},
  "geometry": {"coordinates":[-82.61767399999999,36.946939],"type":"Point"}
}