{
  "type": "Feature",
  "properties": {
    "addr:full":"5418 Heredity Ln Gainesville VA 20155",
    "addr:housenumber":"5418",
    "addr:postcode":"20155",
    "addr:street":"Heredity Ln",
    "iso:country":"US",
    "sg:address":"5418 Heredity Ln",
    "sg:city":"Gainesville",
    "sg:classifiers":[
        {
            "category":"Real Estate",
            "subcategory":"Real Estate Agent",
            "type":"Services"
        }
    ],
    "sg:phone":"+1 703 753 3023",
    "sg:postcode":"20155",
    "sg:province":"VA",
    "wof:name":"Devon Enterprises",
    "wof:placetype":"venue"
},
  "geometry": {"coordinates":[-77.597956,38.83966],"type":"Point"}
}