{
  "type": "Feature",
  "properties": {
    "iso:country":"US",
    "sg:address":"5375 Duke St",
    "sg:city":"Alexandria",
    "sg:classifiers":[
        {
            "category":"Professional",
            "subcategory":"Computer Services",
            "type":"Services"
        }
    ],
    "sg:phone":"+1 703 751 5933",
    "sg:postcode":"22304",
    "sg:province":"VA",
    "sg:tags":[
        "datum"
    ],
    "wof:name":"Robert Firsching",
    "wof:placetype":"venue"
},
  "geometry": {"coordinates":[-77.124798,38.812899],"type":"Point"}
}