{
  "type": "Feature",
  "properties": {
    "addr:full":"7402 Kettle Ridge Dr Nokesville VA 20181",
    "addr:housenumber":"7402",
    "addr:postcode":"20181",
    "addr:street":"Kettle Ridge Dr",
    "iso:country":"US",
    "sg:address":"7402 Kettle Ridge Dr",
    "sg:city":"Nokesville",
    "sg:classifiers":[
        {
            "category":"Wholesale",
            "subcategory":"Metals & Minerals",
            "type":"Manufacturing & Wholesale Goods"
        }
    ],
    "sg:phone":"+1 703 550 8303",
    "sg:postcode":"20181",
    "sg:province":"VA",
    "sg:tags":[
        "specialty"
    ],
    "wof:name":"Lambert Metal Svc",
    "wof:placetype":"venue"
},
  "geometry": {"coordinates":[-77.66809000000001,38.72808],"type":"Point"}
}