{
  "type": "Feature",
  "properties": {
    "addr:full":"220 Westside Blvd NW Roanoke VA 24017",
    "addr:housenumber":"220",
    "addr:postcode":"24017",
    "addr:street":"Westside Blvd Nw",
    "iso:country":"US",
    "sg:address":"220 Westside Blvd NW",
    "sg:city":"Roanoke",
    "sg:classifiers":[
        {
            "category":"Real Estate",
            "subcategory":"Real Estate Operator",
            "type":"Services"
        }
    ],
    "sg:phone":"+1 540 344 3800",
    "sg:postcode":"24017",
    "sg:province":"VA",
    "sg:tags":[
        "apartment"
    ],
    "wof:name":"West Creek Manor Apartments",
    "wof:placetype":"venue"
},
  "geometry": {"coordinates":[-80.00254200000001,37.276076],"type":"Point"}
}