{
  "type": "Feature",
  "properties": {
    "addr:full":"1099 Kempsville Rd Norfolk VA 23502",
    "addr:housenumber":"1099",
    "addr:postcode":"23502",
    "addr:street":"Kempsville Rd",
    "iso:country":"US",
    "sg:address":"1099 Kempsville Rd",
    "sg:city":"Norfolk",
    "sg:classifiers":[
        {
            "category":"Organizations",
            "subcategory":"Religious Organization",
            "type":"Services"
        }
    ],
    "sg:phone":"+1 757 461 6049",
    "sg:postcode":"23502",
    "sg:province":"VA",
    "wof:name":"Norfolk Seventh Day Advent Chu",
    "wof:placetype":"venue"
},
  "geometry": {"coordinates":[-76.199354,36.860417],"type":"Point"}
}