{
  "type": "Feature",
  "properties": {
    "iso:country":"US",
    "sg:address":"9201 Patterson Ave",
    "sg:city":"Richmond",
    "sg:classifiers":[
        {
            "category":"Manufacturing",
            "subcategory":"Food",
            "type":"Manufacturing & Wholesale Goods"
        }
    ],
    "sg:phone":"+1 804 377 2454",
    "sg:postcode":"23229",
    "sg:province":"VA",
    "sg:tags":[
        "making",
        "custom",
        "chocolate"
    ],
    "wof:name":"Joseph & Amy Dejongh",
    "wof:placetype":"venue"
},
  "geometry": {"coordinates":[-77.577805,37.595239],"type":"Point"}
}