{
  "type": "Feature",
  "properties": {
    "addr:full":"4219 Campbell Ave Lynchburg VA 24501",
    "addr:housenumber":"4219",
    "addr:postcode":"24501",
    "addr:street":"Campbell Ave",
    "iso:country":"US",
    "sg:address":"4219 Campbell Ave",
    "sg:city":"Lynchburg",
    "sg:classifiers":[
        {
            "category":"Government",
            "subcategory":"Office",
            "type":"Public Place"
        }
    ],
    "sg:phone":"+1 434 947 6559",
    "sg:postcode":"24501",
    "sg:province":"VA",
    "sg:tags":[
        "state",
        "program"
    ],
    "wof:name":"Transportation Dept",
    "wof:placetype":"venue"
},
  "geometry": {"coordinates":[-79.12795699999999,37.37654],"type":"Point"}
}