{
  "type": "Feature",
  "properties": {
    "iso:country":"US",
    "sg:address":"10129 Deepwood Cir",
    "sg:city":"Richmond",
    "sg:classifiers":[
        {
            "category":"Professional",
            "type":"Services"
        }
    ],
    "sg:phone":"+1 804 354 8806",
    "sg:postcode":"23238",
    "sg:province":"VA",
    "sg:tags":[
        "establishment"
    ],
    "wof:name":"Communications Unlimited",
    "wof:placetype":"venue"
},
  "geometry": {"coordinates":[-77.59469900000001,37.608449],"type":"Point"}
}