{
  "type": "Feature",
  "properties": {
    "addr:full":"432 Washington St Boydton VA 23917",
    "addr:housenumber":"432",
    "addr:postcode":"23917",
    "addr:street":"Washington St",
    "iso:country":"US",
    "sg:address":"432 Washington St",
    "sg:city":"Boydton",
    "sg:classifiers":[
        {
            "category":"Shopping",
            "subcategory":"Pharmacy",
            "type":"Retail Goods"
        }
    ],
    "sg:phone":"+1 434 738 6676",
    "sg:postcode":"23917",
    "sg:province":"VA",
    "wof:name":"Boydton Pharmacy",
    "wof:placetype":"venue"
},
  "geometry": {"coordinates":[-78.38791000000001,36.667808],"type":"Point"}
}