{
  "type": "Feature",
  "properties": {
    "addr:full":"5317 Challedon Dr Virginia Beach VA 23462",
    "addr:housenumber":"5317",
    "addr:postcode":"23462",
    "addr:street":"Challedon Dr",
    "iso:country":"US",
    "sg:address":"5317 Challedon Dr",
    "sg:city":"Virginia Beach",
    "sg:classifiers":[
        {
            "category":"Professional",
            "subcategory":"Business Services",
            "type":"Services"
        }
    ],
    "sg:phone":"+1 757 490 2914",
    "sg:postcode":"23462",
    "sg:province":"VA",
    "sg:tags":[
        "handwriting",
        "analysis"
    ],
    "wof:name":"Farmer Inc Lawrence M",
    "wof:placetype":"venue"
},
  "geometry": {"coordinates":[-76.169894,36.827259],"type":"Point"}
}