{
  "type": "Feature",
  "properties": {
    "addr:full":"8390 Seminole Trl Ruckersville VA 22968",
    "addr:housenumber":"8390",
    "addr:postcode":"22968",
    "addr:street":"Seminole Trl",
    "iso:country":"US",
    "sg:address":"8390 Seminole Trl",
    "sg:city":"Ruckersville",
    "sg:classifiers":[
        {
            "category":"Insurance",
            "subcategory":"Insurance Agent",
            "type":"Services"
        }
    ],
    "sg:phone":"+1 434 985 6700",
    "sg:postcode":"22968",
    "sg:province":"VA",
    "wof:name":"Save-Rite Insurance Agency",
    "wof:placetype":"venue"
},
  "geometry": {"coordinates":[-78.37160299999999,38.229546],"type":"Point"}
}