{
  "type": "Feature",
  "properties": {
    "addr:full":"105 Chesterfield Pl SW Leesburg VA 20175",
    "addr:housenumber":"105",
    "addr:postcode":"20175",
    "addr:street":"Chesterfield Pl Sw",
    "iso:country":"US",
    "sg:address":"105 Chesterfield Pl SW",
    "sg:city":"Leesburg",
    "sg:classifiers":[
        {
            "category":"Food & Beverages",
            "subcategory":"Candy",
            "type":"Retail Goods"
        }
    ],
    "sg:phone":"+1 703 777 9297",
    "sg:postcode":"20175",
    "sg:province":"VA",
    "wof:name":"Designline",
    "wof:placetype":"venue"
},
  "geometry": {"coordinates":[-77.568318,39.114436],"type":"Point"}
}