{
  "type": "Feature",
  "properties": {
    "addr:full":"3100 Valley Dr Alexandria VA 22302",
    "addr:housenumber":"3100",
    "addr:postcode":"22302",
    "addr:street":"Valley Dr",
    "iso:country":"US",
    "sg:address":"3100 Valley Dr",
    "sg:city":"Alexandria",
    "sg:classifiers":[
        {
            "category":"Professional",
            "subcategory":"Business Services",
            "type":"Services"
        }
    ],
    "sg:phone":"+1 703 578 1400",
    "sg:postcode":"22302",
    "sg:province":"VA",
    "wof:name":"Ebsco Subscription Services",
    "wof:placetype":"venue"
},
  "geometry": {"coordinates":[-77.07953500000001,38.833447],"type":"Point"}
}