{
  "type": "Feature",
  "properties": {
    "iso:country":"US",
    "sg:address":"100 E Beverley St",
    "sg:city":"Staunton",
    "sg:classifiers":[
        {
            "category":"Shopping",
            "subcategory":"Gifts & Souvenirs",
            "type":"Retail Goods"
        }
    ],
    "sg:phone":"+1 540 885 8261",
    "sg:postcode":"24401",
    "sg:province":"VA",
    "wof:name":"Honeysuckle Hill",
    "wof:placetype":"venue"
},
  "geometry": {"coordinates":[-79.070486,38.149673],"type":"Point"}
}