{
  "type": "Feature",
  "properties": {
    "addr:full":"169 Spruce Ln Luray VA 22812",
    "addr:housenumber":"169",
    "addr:postcode":"22812",
    "addr:street":"Spruce Ln",
    "iso:country":"US",
    "sg:address":"169 Spruce Ln",
    "sg:city":"Luray",
    "sg:classifiers":[
        {
            "category":"Travel",
            "subcategory":"Hotels & Motels",
            "type":"Entertainment"
        }
    ],
    "sg:phone":"+1 540 743 1329",
    "sg:postcode":"22812",
    "sg:province":"VA",
    "wof:name":"Spiro Inn",
    "wof:placetype":"venue"
},
  "geometry": {"coordinates":[-78.972416,38.387903],"type":"Point"}
}