{
  "type": "Feature",
  "properties": {
    "addr:full":"4000 Legato Rd Fairfax VA 22033",
    "addr:postcode":"4000;22033",
    "addr:street":"Legato Rd",
    "iso:country":"US",
    "sg:address":"4000 Legato Rd",
    "sg:city":"Fairfax",
    "sg:classifiers":[
        {
            "category":"Insurance",
            "subcategory":"Insurance Agent",
            "type":"Services"
        }
    ],
    "sg:phone":"+1 703 385 4444",
    "sg:postcode":"22033",
    "sg:province":"VA",
    "wof:name":"Liberty Mutual Insurance",
    "wof:placetype":"venue"
},
  "geometry": {"coordinates":[-77.365782,38.865238],"type":"Point"}
}