{
  "type": "Feature",
  "properties": {
    "addr:full":"7004 Vantage Dr Alexandria VA 22306",
    "addr:housenumber":"7004",
    "addr:postcode":"22306",
    "addr:street":"Vantage Dr",
    "iso:country":"US",
    "sg:address":"7004 Vantage Dr",
    "sg:city":"Alexandria",
    "sg:classifiers":[
        {
            "category":"Building & Trades",
            "subcategory":"Construction",
            "type":"Services"
        }
    ],
    "sg:phone":"+1 703 765 3508",
    "sg:postcode":"22306",
    "sg:province":"VA",
    "sg:tags":[
        "house"
    ],
    "wof:name":"Continental Maintenance Svcs",
    "wof:placetype":"venue"
},
  "geometry": {"coordinates":[-77.108862,38.764927],"type":"Point"}
}