{
  "type": "Feature",
  "properties": {
    "iso:country":"US",
    "sg:address":"201 Pintail Trl",
    "sg:city":"Wake",
    "sg:classifiers":[
        {
            "category":"Professional",
            "subcategory":"Employment Agencies",
            "type":"Services"
        }
    ],
    "sg:phone":"+1 804 776 0712",
    "sg:postcode":"23176",
    "sg:province":"VA",
    "sg:tags":[
        "trucking"
    ],
    "wof:name":"R & K Trucking Inc",
    "wof:placetype":"venue"
},
  "geometry": {"coordinates":[-76.40606,37.577607],"type":"Point"}
}