{
  "type": "Feature",
  "properties": {
    "iso:country":"US",
    "sg:address":"2955 Ivy Rd Ste 104",
    "sg:city":"Charlottesville",
    "sg:classifiers":[
        {
            "category":"Health Services",
            "subcategory":"Doctor",
            "type":"Services"
        }
    ],
    "sg:phone":"+1 434 243 4720",
    "sg:postcode":"22903",
    "sg:province":"VA",
    "wof:name":"Mandell Elizabeth B MD",
    "wof:placetype":"venue"
},
  "geometry": {"coordinates":[-78.546843,38.050786],"type":"Point"}
}