{
  "type": "Feature",
  "properties": {
    "addr:full":"105 Cherwell Ct Williamsburg VA 23188",
    "addr:housenumber":"105",
    "addr:postcode":"23188",
    "addr:street":"Cherwell Ct",
    "iso:country":"US",
    "sg:address":"105 Cherwell Ct",
    "sg:city":"Williamsburg",
    "sg:classifiers":[
        {
            "category":"Real Estate",
            "subcategory":"Real Estate Agent",
            "type":"Services"
        }
    ],
    "sg:phone":"+1 757 565 0419",
    "sg:postcode":"23188",
    "sg:province":"VA",
    "sg:tags":[
        "counseling",
        "appraisal"
    ],
    "wof:name":"Dana Jo Inc",
    "wof:placetype":"venue"
},
  "geometry": {"coordinates":[-76.71973800000001,37.359062],"type":"Point"}
}