{
  "type": "Feature",
  "properties": {
    "iso:country":"US",
    "sg:address":"6207 Huntingcreek Dr",
    "sg:city":"Richmond",
    "sg:classifiers":[
        {
            "category":"Manufacturing",
            "subcategory":"Signs",
            "type":"Manufacturing & Wholesale Goods"
        }
    ],
    "sg:phone":"+1 804 354 3282",
    "sg:postcode":"23237",
    "sg:province":"VA",
    "sg:tags":[
        "specialty",
        "mfg"
    ],
    "wof:name":"Bydesign-Online",
    "wof:placetype":"venue"
},
  "geometry": {"coordinates":[-77.49790900000001,37.395772],"type":"Point"}
}