{
  "type": "Feature",
  "properties": {
    "addr:full":"240 Clayhill Dr Winchester VA 22602",
    "addr:housenumber":"240",
    "addr:postcode":"22602",
    "addr:street":"Clayhill Dr",
    "iso:country":"US",
    "sg:address":"240 Clayhill Dr",
    "sg:city":"Winchester",
    "sg:classifiers":[
        {
            "category":"Real Estate",
            "subcategory":"Real Estate Agent",
            "type":"Services"
        }
    ],
    "sg:phone":"+1 540 662 6565",
    "sg:postcode":"22602",
    "sg:province":"VA",
    "sg:tags":[
        "appraiser"
    ],
    "wof:name":"A Brokers Associated",
    "wof:placetype":"venue"
},
  "geometry": {"coordinates":[-78.202292,39.156472],"type":"Point"}
}