{
  "type": "Feature",
  "properties": {
    "addr:full":"56 Pidgeon Hill Dr Sterling VA 20165",
    "addr:housenumber":"56",
    "addr:postcode":"20165",
    "addr:street":"Pidgeon Hill Dr",
    "iso:country":"US",
    "sg:address":"56 Pidgeon Hill Dr",
    "sg:city":"Sterling",
    "sg:classifiers":[
        {
            "category":"Shopping",
            "subcategory":"Pets & Pet Supplies",
            "type":"Retail Goods"
        }
    ],
    "sg:phone":"+1 703 404 9518",
    "sg:postcode":"20165",
    "sg:province":"VA",
    "sg:tags":[
        "furnishing",
        "dog",
        "store",
        "cat"
    ],
    "wof:name":"Puppies Guppies & More Inc",
    "wof:placetype":"venue"
},
  "geometry": {"coordinates":[-77.41280399999999,39.038993],"type":"Point"}
}