{
  "type": "Feature",
  "properties": {
    "iso:country":"US",
    "sg:address":"1251 Virginia Ave",
    "sg:city":"Harrisonburg",
    "sg:classifiers":[
        {
            "category":"Professional",
            "subcategory":"Computer Services",
            "type":"Services"
        }
    ],
    "sg:phone":"+1 540 432 1900",
    "sg:postcode":"22802",
    "sg:province":"VA",
    "sg:tags":[
        "developer"
    ],
    "wof:name":"Vistashare",
    "wof:placetype":"venue"
},
  "geometry": {"coordinates":[-78.87182199999999,38.469846],"type":"Point"}
}