{
  "type": "Feature",
  "properties": {
    "addr:full":"26016 Rachel Hill Dr Chantilly VA 20152",
    "addr:postcode":"26016;20152",
    "addr:street":"Rachel Hill Dr",
    "iso:country":"US",
    "sg:address":"26016 Rachel Hill Dr",
    "sg:city":"Chantilly",
    "sg:classifiers":[
        {
            "category":"Professional",
            "subcategory":"Computer Services",
            "type":"Services"
        }
    ],
    "sg:phone":"+1 703 327 1338",
    "sg:postcode":"20152",
    "sg:province":"VA",
    "sg:tags":[
        "related"
    ],
    "wof:name":"H&R Computers",
    "wof:placetype":"venue"
},
  "geometry": {"coordinates":[-77.500494,38.895562],"type":"Point"}
}