{
  "type": "Feature",
  "properties": {
    "addr:full":"13040 A L Philpott Hwy Martinsville VA 24112",
    "addr:housenumber":"13040 a",
    "addr:postcode":"24112",
    "addr:street":"L Philpott Hwy",
    "iso:country":"US",
    "sg:address":"13040 A L Philpott Hwy",
    "sg:city":"Martinsville",
    "sg:classifiers":[
        {
            "category":"Freight",
            "type":"Transportation"
        }
    ],
    "sg:phone":"+1 276 638 5240",
    "sg:postcode":"24112",
    "sg:province":"VA",
    "sg:tags":[
        "commercial",
        "storage"
    ],
    "wof:name":"Handy Space",
    "wof:placetype":"venue"
},
  "geometry": {"coordinates":[-79.88695300000001,36.662027],"type":"Point"}
}