{
  "type": "Feature",
  "properties": {
    "addr:full":"234 Springfield Est Dr Rileyville VA 22835",
    "addr:housenumber":"234",
    "addr:postcode":"22835",
    "addr:street":"Springfield Est Dr",
    "iso:country":"US",
    "sg:address":"234 Springfield Est Dr",
    "sg:city":"Rileyville",
    "sg:classifiers":[
        {
            "category":"Real Estate",
            "subcategory":"Surveying",
            "type":"Services"
        }
    ],
    "sg:phone":"+1 540 843 0608",
    "sg:postcode":"22835",
    "sg:province":"VA",
    "sg:tags":[
        "surveyor"
    ],
    "wof:name":"Dodson Surveying",
    "wof:placetype":"venue"
},
  "geometry": {"coordinates":[-78.414852,38.726618],"type":"Point"}
}