{
  "type": "Feature",
  "properties": {
    "addr:full":"1957 Virginia Ave Bluefield VA 24605",
    "addr:housenumber":"1957",
    "addr:postcode":"24605",
    "addr:street":"Virginia Ave",
    "iso:country":"US",
    "sg:address":"1957 Virginia Ave",
    "sg:city":"Bluefield",
    "sg:classifiers":[
        {
            "category":"Organizations",
            "subcategory":"Religious Organization",
            "type":"Services"
        }
    ],
    "sg:phone":"+1 276 322 3815",
    "sg:postcode":"24605",
    "sg:province":"VA",
    "sg:tags":[
        "church"
    ],
    "wof:name":"Bluefield Church Of Christ",
    "wof:placetype":"venue"
},
  "geometry": {"coordinates":[-81.298896,37.248185],"type":"Point"}
}