{
  "type": "Feature",
  "properties": {
    "addr:full":"29072 Foxhare Rd Rhoadesville VA 22542",
    "addr:postcode":"29072;22542",
    "addr:street":"Foxhare Rd",
    "iso:country":"US",
    "sg:address":"29072 Foxhare Rd",
    "sg:city":"Rhoadesville",
    "sg:classifiers":[
        {
            "category":"Shopping",
            "subcategory":"Gifts & Souvenirs",
            "type":"Retail Goods"
        }
    ],
    "sg:phone":"+1 540 854 7400",
    "sg:postcode":"22542",
    "sg:province":"VA",
    "wof:name":"Burr Hill Gifts & Ceramics",
    "wof:placetype":"venue"
},
  "geometry": {"coordinates":[-77.871752,38.321191],"type":"Point"}
}