{
  "type": "Feature",
  "properties": {
    "iso:country":"US",
    "sg:address":"1316 Jefferson St",
    "sg:city":"Lynchburg",
    "sg:classifiers":[
        {
            "category":"Professional",
            "subcategory":"Advertising",
            "type":"Services"
        }
    ],
    "sg:phone":"+1 434 847 7240",
    "sg:postcode":"24504",
    "sg:province":"VA",
    "sg:tags":[
        "counselor"
    ],
    "wof:name":"Sisson Creative",
    "wof:placetype":"venue"
},
  "geometry": {"coordinates":[-79.136802,37.411904],"type":"Point"}
}