{
  "type": "Feature",
  "properties": {
    "addr:full":"4930B Eisenhower Ave Alexandria VA 22304",
    "addr:housenumber":"4930b",
    "addr:postcode":"22304",
    "addr:street":"Eisenhower Ave",
    "iso:country":"US",
    "sg:address":"4930B Eisenhower Ave",
    "sg:city":"Alexandria",
    "sg:classifiers":[
        {
            "category":"Retail",
            "subcategory":"Laundry & Dry Cleaning",
            "type":"Services"
        }
    ],
    "sg:phone":"+1 703 751 4816",
    "sg:postcode":"22304",
    "sg:province":"VA",
    "sg:tags":[
        "cleaner",
        "rug",
        "carpet"
    ],
    "wof:name":"B & B Carpet Services",
    "wof:placetype":"venue"
},
  "geometry": {"coordinates":[-77.120418,38.803022],"type":"Point"}
}