{
  "type": "Feature",
  "properties": {
    "addr:full":"2220 Woodford Rd Vienna VA 22182",
    "addr:housenumber":"2220",
    "addr:postcode":"22182",
    "addr:street":"Woodford Rd",
    "iso:country":"US",
    "sg:address":"2220 Woodford Rd",
    "sg:city":"Vienna",
    "sg:classifiers":[
        {
            "category":"Communications",
            "type":"Services"
        }
    ],
    "sg:phone":"+1 703 208 2220",
    "sg:postcode":"22182",
    "sg:province":"VA",
    "sg:tags":[
        "communication"
    ],
    "wof:name":"Elite Communications LLC",
    "wof:placetype":"venue"
},
  "geometry": {"coordinates":[-77.239362,38.901399],"type":"Point"}
}