{
  "type": "Feature",
  "properties": {
    "addr:full":"603 Waterlick Rd Lynchburg VA 24501",
    "addr:housenumber":"603",
    "addr:postcode":"24501",
    "addr:street":"Waterlick Rd",
    "iso:country":"US",
    "sg:address":"603 Waterlick Rd",
    "sg:city":"Lynchburg",
    "sg:classifiers":[
        {
            "category":"Utilities",
            "subcategory":"Refuse",
            "type":"Services"
        }
    ],
    "sg:phone":"+1 434 237 8538",
    "sg:postcode":"24501",
    "sg:province":"VA",
    "sg:tags":[
        "garbage",
        "collection"
    ],
    "wof:name":"BSW",
    "wof:placetype":"venue"
},
  "geometry": {"coordinates":[-79.21387199999999,37.302723],"type":"Point"}
}