{
  "type": "Feature",
  "properties": {
    "addr:full":"5320 S Laburnum Ave Richmond VA 23231",
    "addr:housenumber":"5320",
    "addr:postcode":"23231",
    "addr:street":"S Laburnum Ave",
    "iso:country":"US",
    "sg:address":"5320 S Laburnum Ave",
    "sg:city":"Richmond",
    "sg:classifiers":[
        {
            "category":"Wholesale",
            "subcategory":"Machinery & Supplies",
            "type":"Manufacturing & Wholesale Goods"
        },
        {
            "category":"Wholesale",
            "subcategory":"Non-durable Goods",
            "type":"Manufacturing & Wholesale Goods"
        }
    ],
    "sg:phone":"+1 804 222 2110",
    "sg:postcode":"23231",
    "sg:province":"VA",
    "sg:tags":[
        "equipment",
        "industrial",
        "cartridge",
        "printer"
    ],
    "sg:website":"www.gerichards.com",
    "wof:name":"GE Richards Graphic Supplies",
    "wof:placetype":"venue"
},
  "geometry": {"coordinates":[-77.349782,37.513578],"type":"Point"}
}