{
  "type": "Feature",
  "properties": {
    "addr:full":"11730 Saddle Crescent Cir Oakton VA 22124",
    "addr:housenumber":"11730",
    "addr:postcode":"22124",
    "addr:street":"Saddle Crescent Cir",
    "iso:country":"US",
    "sg:address":"11730 Saddle Crescent Cir",
    "sg:city":"Oakton",
    "sg:classifiers":[
        {
            "category":"Home & Garden",
            "subcategory":"Home Furnishings",
            "type":"Retail Goods"
        }
    ],
    "sg:phone":"+1 703 716 0430",
    "sg:postcode":"22124",
    "sg:province":"VA",
    "sg:tags":[
        "curtain",
        "made",
        "drapery"
    ],
    "wof:name":"Carol Regan Designs",
    "wof:placetype":"venue"
},
  "geometry": {"coordinates":[-77.357389,38.895649],"type":"Point"}
}