{
  "type": "Feature",
  "properties": {
    "addr:full":"4730 Larkspur Ct Virginia Beach VA 23462",
    "addr:housenumber":"4730",
    "addr:postcode":"23462",
    "addr:street":"Larkspur Ct",
    "iso:country":"US",
    "sg:address":"4730 Larkspur Ct",
    "sg:city":"Virginia Beach",
    "sg:classifiers":[
        {
            "category":"Retail",
            "subcategory":"Auto Repair",
            "type":"Services"
        }
    ],
    "sg:phone":"+1 757 497 1553",
    "sg:postcode":"23462",
    "sg:province":"VA",
    "sg:tags":[
        "repairing",
        "automobile",
        "radiator"
    ],
    "wof:name":"Wholesale Auto Radiator",
    "wof:placetype":"venue"
},
  "geometry": {"coordinates":[-76.14264799999999,36.819219],"type":"Point"}
}