{
  "type": "Feature",
  "properties": {
    "iso:country":"US",
    "sg:address":"3355 Breckenridge Ct",
    "sg:city":"Annandale",
    "sg:classifiers":[
        {
            "category":"Building & Trades",
            "subcategory":"Construction",
            "type":"Services"
        }
    ],
    "sg:phone":"+1 703 849 0855",
    "sg:postcode":"22003",
    "sg:province":"VA",
    "sg:tags":[
        "house"
    ],
    "wof:name":"Affordable Home Remodeling",
    "wof:placetype":"venue"
},
  "geometry": {"coordinates":[-77.236572,38.854864],"type":"Point"}
}