{
  "type": "Feature",
  "properties": {
    "addr:full":"2211 N 28th St Richmond VA 23223",
    "addr:housenumber":"2211",
    "addr:postcode":"23223",
    "addr:street":"N 28Th St",
    "iso:country":"US",
    "sg:address":"2211 N 28th St",
    "sg:city":"Richmond",
    "sg:classifiers":[
        {
            "category":"Retail",
            "subcategory":"Laundry & Dry Cleaning",
            "type":"Services"
        }
    ],
    "sg:phone":"+1 804 648 6799",
    "sg:postcode":"23223",
    "sg:province":"VA",
    "sg:tags":[
        "cleaners",
        "rug",
        "carpet"
    ],
    "wof:name":"Hopkins Carpet Cleaning Svc",
    "wof:placetype":"venue"
},
  "geometry": {"coordinates":[-77.39849100000001,37.547654],"type":"Point"}
}