{
  "type": "Feature",
  "properties": {
    "iso:country":"US",
    "sg:address":"204 S Jefferson St",
    "sg:city":"Roanoke",
    "sg:classifiers":[
        {
            "category":"Social Services",
            "subcategory":"Job Training",
            "type":"Services"
        }
    ],
    "sg:phone":"+1 540 929 4800",
    "sg:postcode":"24011",
    "sg:province":"VA",
    "sg:tags":[
        "career",
        "counseling",
        "vocational"
    ],
    "wof:name":"Vocational Rehabilitation",
    "wof:placetype":"venue"
},
  "geometry": {"coordinates":[-79.940494,37.271192],"type":"Point"}
}