{
  "type": "Feature",
  "properties": {
    "addr:full":"3316 Highland Ln Fairfax VA 22031",
    "addr:housenumber":"3316",
    "addr:postcode":"22031",
    "addr:street":"Highland Ln",
    "iso:country":"US",
    "sg:address":"3316 Highland Ln",
    "sg:city":"Fairfax",
    "sg:classifiers":[
        {
            "category":"Communications",
            "subcategory":"Film & Video Production",
            "type":"Services"
        },
        {
            "category":"Professional",
            "type":"Services"
        }
    ],
    "sg:phone":"+1 703 573 5091",
    "sg:postcode":"22031",
    "sg:province":"VA",
    "sg:tags":[
        "motion",
        "establishment"
    ],
    "wof:name":"Side Stream Productions Inc",
    "wof:placetype":"venue"
},
  "geometry": {"coordinates":[-77.242802,38.856023],"type":"Point"}
}