{
  "type": "Feature",
  "properties": {
    "addr:full":"2408 Brook Rd Charlottesville VA 22901",
    "addr:housenumber":"2408",
    "addr:postcode":"22901",
    "addr:street":"Brook Rd",
    "iso:country":"US",
    "sg:address":"2408 Brook Rd",
    "sg:city":"Charlottesville",
    "sg:classifiers":[
        {
            "category":"Professional",
            "type":"Services"
        }
    ],
    "sg:phone":"+1 434 964 1238",
    "sg:postcode":"22901",
    "sg:province":"VA",
    "sg:tags":[
        "consulting",
        "management",
        "commercial"
    ],
    "wof:name":"Grantland Enterprises",
    "wof:placetype":"venue"
},
  "geometry": {"coordinates":[-78.470939,38.066044],"type":"Point"}
}