{
  "type": "Feature",
  "properties": {
    "iso:country":"US",
    "sg:address":"702 E Main St",
    "sg:city":"Saltville",
    "sg:classifiers":[
        {
            "category":"Organizations",
            "subcategory":"Religious Organization",
            "type":"Services"
        }
    ],
    "sg:phone":"+1 276 496 4713",
    "sg:postcode":"24370",
    "sg:province":"VA",
    "sg:tags":[
        "church"
    ],
    "wof:name":"Main Street Christian Church",
    "wof:placetype":"venue"
},
  "geometry": {"coordinates":[-81.7591,36.883162],"type":"Point"}
}