{
  "type": "Feature",
  "properties": {
    "iso:country":"US",
    "sg:address":"2003 Huguenot Rd",
    "sg:city":"Richmond",
    "sg:classifiers":[
        {
            "category":"Shopping",
            "subcategory":"Crafts & Fabrics",
            "type":"Retail Goods"
        }
    ],
    "sg:phone":"+1 804 320 1730",
    "sg:postcode":"23113",
    "sg:province":"VA",
    "sg:tags":[
        "shop"
    ],
    "wof:name":"Williams & Sherrill",
    "wof:placetype":"venue"
},
  "geometry": {"coordinates":[-77.61327,37.521424],"type":"Point"}
}