{
  "type": "Feature",
  "properties": {
    "iso:country":"US",
    "sg:address":"2 Main St",
    "sg:city":"Appomattox",
    "sg:classifiers":[
        {
            "category":"Manufacturing",
            "subcategory":"Printing",
            "type":"Manufacturing & Wholesale Goods"
        }
    ],
    "sg:phone":"+1 434 352 7191",
    "sg:postcode":"24592",
    "sg:province":"NC",
    "sg:tags":[
        "printer"
    ],
    "wof:name":"Village Printshop Inc",
    "wof:placetype":"venue"
},
  "geometry": {"coordinates":[-78.90079299999999,36.695074],"type":"Point"}
}