{
  "type": "Feature",
  "properties": {
    "iso:country":"US",
    "sg:address":"960 Jamestown Cres",
    "sg:city":"Norfolk",
    "sg:classifiers":[
        {
            "category":"Health Services",
            "subcategory":"Doctor",
            "type":"Services"
        }
    ],
    "sg:phone":"+1 757 489 8569",
    "sg:postcode":"23508",
    "sg:province":"VA",
    "sg:tags":[
        "physician",
        "surgeon"
    ],
    "wof:name":"Fred T Given Jr MD",
    "wof:placetype":"venue"
},
  "geometry": {"coordinates":[-76.296409,36.895152],"type":"Point"}
}