{
  "type": "Feature",
  "properties": {
    "addr:full":"10719 Catharpin Rd Spotsylvania VA 22553",
    "addr:housenumber":"10719",
    "addr:postcode":"22553",
    "addr:street":"Catharpin Rd",
    "iso:country":"US",
    "sg:address":"10719 Catharpin Rd",
    "sg:city":"Spotsylvania",
    "sg:classifiers":[
        {
            "category":"Professional",
            "type":"Services"
        }
    ],
    "sg:phone":"+1 540 972 8446",
    "sg:postcode":"22553",
    "sg:province":"VA",
    "wof:name":"ASI Svc Corp",
    "wof:placetype":"venue"
},
  "geometry": {"coordinates":[-77.667202,38.248666],"type":"Point"}
}