{
  "type": "Feature",
  "properties": {
    "iso:country":"US",
    "sg:address":"6182 Treywood Ln",
    "sg:city":"Manassas",
    "sg:classifiers":[
        {
            "category":"Building & Trades",
            "subcategory":"Construction",
            "type":"Services"
        }
    ],
    "sg:phone":"+1 703 794 0320",
    "sg:postcode":"20112",
    "sg:province":"VA",
    "sg:tags":[
        "residential",
        "commercial"
    ],
    "wof:name":"Tricorn Construction LLC",
    "wof:placetype":"venue"
},
  "geometry": {"coordinates":[-77.39290200000001,38.685613],"type":"Point"}
}