{
  "type": "Feature",
  "properties": {
    "iso:country":"US",
    "sg:address":"2852 Ontario Rd",
    "sg:city":"Keysville",
    "sg:classifiers":[
        {
            "category":"Organizations",
            "subcategory":"Religious Organization",
            "type":"Services"
        }
    ],
    "sg:phone":"+1 434 736 0703",
    "sg:postcode":"23947",
    "sg:province":"VA",
    "sg:tags":[
        "church"
    ],
    "wof:name":"Cool Spring Christian Church",
    "wof:placetype":"venue"
},
  "geometry": {"coordinates":[-78.41435199999999,36.961132],"type":"Point"}
}