{
  "type": "Feature",
  "properties": {
    "addr:full":"4700 Feldspar Quay Chesapeake VA 23321",
    "addr:postcode":"4700;23321",
    "addr:street":"Feldspar Quay",
    "iso:country":"US",
    "sg:address":"4700 Feldspar Quay",
    "sg:city":"Chesapeake",
    "sg:classifiers":[
        {
            "category":"Shopping",
            "subcategory":"Pharmacy",
            "type":"Retail Goods"
        }
    ],
    "sg:phone":"+1 757 405 5565",
    "sg:postcode":"23321",
    "sg:province":"VA",
    "wof:name":"First Vend",
    "wof:placetype":"venue"
},
  "geometry": {"coordinates":[-76.427356,36.815675],"type":"Point"}
}