{
  "type": "Feature",
  "properties": {
    "addr:full":"700 Dawn St Richmond VA 23222",
    "addr:housenumber":"700",
    "addr:postcode":"23222",
    "addr:street":"Dawn St",
    "iso:country":"US",
    "sg:address":"700 Dawn St",
    "sg:city":"Richmond",
    "sg:classifiers":[
        {
            "category":"Autos & Motor Vehicles",
            "subcategory":"Automobile Sales",
            "type":"Retail Goods"
        }
    ],
    "sg:phone":"+1 804 321 0013",
    "sg:postcode":"23222",
    "sg:province":"VA",
    "sg:tags":[
        "used"
    ],
    "wof:name":"Classic Car Sales",
    "wof:placetype":"venue"
},
  "geometry": {"coordinates":[-77.44235500000001,37.562073],"type":"Point"}
}