{
  "type": "Feature",
  "properties": {
    "addr:full":"4530 Drakes Main St Drakes Branch VA 23937",
    "addr:housenumber":"4530",
    "addr:postcode":"23937",
    "addr:street":"Drakes Main St",
    "iso:country":"US",
    "sg:address":"4530 Drakes Main St",
    "sg:city":"Drakes Branch",
    "sg:classifiers":[
        {
            "category":"Restaurant",
            "type":"Food & Drink"
        }
    ],
    "sg:phone":"+1 434 568 4415",
    "sg:postcode":"23937",
    "sg:province":"VA",
    "sg:tags":[
        "eating"
    ],
    "wof:name":"Duck In Cafe",
    "wof:placetype":"venue"
},
  "geometry": {"coordinates":[-78.601669,36.99324],"type":"Point"}
}