{
  "type": "Feature",
  "properties": {
    "addr:full":"2600 Ridge Rd Charlottesville VA 22901",
    "addr:housenumber":"2600",
    "addr:postcode":"22901",
    "addr:street":"Ridge Rd",
    "iso:country":"US",
    "sg:address":"2600 Ridge Rd",
    "sg:city":"Charlottesville",
    "sg:classifiers":[
        {
            "category":"Shopping",
            "subcategory":"Used Merchandise",
            "type":"Retail Goods"
        }
    ],
    "sg:phone":"+1 434 296 1960",
    "sg:postcode":"22901",
    "sg:province":"VA",
    "wof:name":"Muscogee Antq & Intr Designs",
    "wof:placetype":"venue"
},
  "geometry": {"coordinates":[-78.596997,38.11028],"type":"Point"}
}