{
  "type": "Feature",
  "properties": {
    "iso:country":"US",
    "sg:address":"1700 Tysons Blvd",
    "sg:city":"Mc Lean",
    "sg:classifiers":[
        {
            "category":"Retail",
            "subcategory":"Repair Shop",
            "type":"Services"
        }
    ],
    "sg:phone":"+1 703 893 6387",
    "sg:postcode":"22102",
    "sg:province":"VA",
    "wof:name":"Wtvr TV Station",
    "wof:placetype":"venue"
},
  "geometry": {"coordinates":[-77.221862,38.921963],"type":"Point"}
}