{
  "type": "Feature",
  "properties": {
    "addr:full":"1905 Huguenot Rd Richmond VA 23113",
    "addr:housenumber":"1905",
    "addr:postcode":"23113",
    "addr:street":"Huguenot Rd",
    "iso:country":"US",
    "sg:address":"1905 Huguenot Rd",
    "sg:city":"Richmond",
    "sg:classifiers":[
        {
            "category":"Health Services",
            "subcategory":"Doctor",
            "type":"Services"
        }
    ],
    "sg:phone":"+1 804 794 4469",
    "sg:postcode":"23113",
    "sg:province":"VA",
    "sg:tags":[
        "dentist"
    ],
    "wof:name":"Raymond E Weddle DDS",
    "wof:placetype":"venue"
},
  "geometry": {"coordinates":[-77.61438099999999,37.520982],"type":"Point"}
}