{
  "type": "Feature",
  "properties": {
    "iso:country":"US",
    "sg:address":"245 S Pickett St",
    "sg:city":"Alexandria",
    "sg:classifiers":[
        {
            "category":"Education",
            "subcategory":"Special Training",
            "type":"Public Place"
        }
    ],
    "sg:phone":"+1 703 751 2679",
    "sg:postcode":"22304",
    "sg:province":"VA",
    "wof:name":"Squiglycom LLC",
    "wof:placetype":"venue"
},
  "geometry": {"coordinates":[-77.12402400000001,38.808999],"type":"Point"}
}