{
  "type": "Feature",
  "properties": {
    "iso:country":"US",
    "sg:address":"700 Harris St",
    "sg:city":"Charlottesville",
    "sg:classifiers":[
        {
            "category":"Professional",
            "subcategory":"Engineering",
            "type":"Services"
        }
    ],
    "sg:phone":"+1 434 295 0700",
    "sg:postcode":"22903",
    "sg:province":"VA",
    "wof:name":"Draper Aden & Associates Inc",
    "wof:placetype":"venue"
},
  "geometry": {"coordinates":[-78.48439399999999,38.036214],"type":"Point"}
}