{
  "type": "Feature",
  "properties": {
    "iso:country":"US",
    "sg:address":"3850 Gaskins Rd",
    "sg:city":"Richmond",
    "sg:classifiers":[
        {
            "category":"Health Services",
            "subcategory":"Chiropractor",
            "type":"Services"
        }
    ],
    "sg:phone":"+1 804 290 8080",
    "sg:postcode":"23233",
    "sg:province":"VA",
    "wof:name":"Blumberg Family Chiropractic",
    "wof:placetype":"venue"
},
  "geometry": {"coordinates":[-77.569357,37.643371],"type":"Point"}
}