{
  "type": "Feature",
  "properties": {
    "addr:full":"13187 Warwick Blvd Newport News VA 23602",
    "addr:housenumber":"13187",
    "addr:postcode":"23602",
    "addr:street":"Warwick Blvd",
    "iso:country":"US",
    "sg:address":"13187 Warwick Blvd",
    "sg:city":"Newport News",
    "sg:classifiers":[
        {
            "category":"Retail",
            "subcategory":"Veterinary Services",
            "type":"Services"
        }
    ],
    "sg:phone":"+1 757 877 6464",
    "sg:postcode":"23602",
    "sg:province":"VA",
    "wof:name":"Piske Gregory A",
    "wof:placetype":"venue"
},
  "geometry": {"coordinates":[-76.518163,37.112207],"type":"Point"}
}