{
  "type": "Feature",
  "properties": {
    "iso:country":"US",
    "sg:address":"1811 Huguenot Rd",
    "sg:city":"Midlothian",
    "sg:classifiers":[
        {
            "category":"Retail",
            "subcategory":"Portrait Studio",
            "type":"Services"
        }
    ],
    "sg:phone":"+1 804 379 6768",
    "sg:postcode":"23113",
    "sg:province":"VA",
    "sg:tags":[
        "photographer"
    ],
    "wof:name":"Shot By Dellinger",
    "wof:placetype":"venue"
},
  "geometry": {"coordinates":[-77.616033,37.517939],"type":"Point"}
}