{
  "type": "Feature",
  "properties": {
    "iso:country":"US",
    "sg:address":"21800 Towncenter Plz Suite 266A-650",
    "sg:city":"Sterling",
    "sg:phone":"+1 703 579 8912",
    "sg:postcode":"20164",
    "sg:province":"VA",
    "sg:website":"http://www.puro-restore.com",
    "wof:name":"PuroClean Emergency Restoration Services",
    "wof:placetype":"venue"
},
  "geometry": {"coordinates":[-77.372101,39.014519],"type":"Point"}
}