{
  "type": "Feature",
  "properties": {
    "addr:full":"3514 Bart St Portsmouth VA 23707",
    "addr:housenumber":"3514",
    "addr:postcode":"23707",
    "addr:street":"Bart St",
    "iso:country":"US",
    "sg:address":"3514 Bart St",
    "sg:city":"Portsmouth",
    "sg:classifiers":[
        {
            "category":"Organizations",
            "subcategory":"Religious Organization",
            "type":"Services"
        }
    ],
    "sg:phone":"+1 757 393 4385",
    "sg:postcode":"23707",
    "sg:province":"VA",
    "sg:tags":[
        "clergy"
    ],
    "wof:name":"J W Banks",
    "wof:placetype":"venue"
},
  "geometry": {"coordinates":[-76.34585199999999,36.830575],"type":"Point"}
}