{
  "type": "Feature",
  "properties": {
    "iso:country":"US",
    "sg:address":"868 Carolina Rd",
    "sg:city":"Suffolk",
    "sg:classifiers":[
        {
            "category":"Bars & Pubs",
            "type":"Food & Drink"
        }
    ],
    "sg:menulink":"http://www.allmenus.com/va/suffolk/36758-herbs-barbecue/menu/",
    "sg:phone":"+1 757 539 6678",
    "sg:postcode":"23434",
    "sg:province":"VA",
    "sg:tags":[
        "barbecue",
        "american"
    ],
    "wof:name":"Herb's Barbecue",
    "wof:placetype":"venue"
},
  "geometry": {"coordinates":[-76.602486,36.698029],"type":"Point"}
}