{
  "type": "Feature",
  "properties": {
    "addr:full":"200 N Columbus St Alexandria VA 22314",
    "addr:housenumber":"200",
    "addr:postcode":"22314",
    "addr:street":"N Columbus St",
    "iso:country":"US",
    "sg:address":"200 N Columbus St",
    "sg:city":"Alexandria",
    "sg:classifiers":[
        {
            "category":"Professional",
            "type":"Services"
        }
    ],
    "sg:phone":"+1 703 299 1700",
    "sg:postcode":"22314",
    "sg:province":"VA",
    "sg:tags":[
        "consultant",
        "professor",
        "author"
    ],
    "wof:name":"Sindell Kathleen Phd",
    "wof:placetype":"venue"
},
  "geometry": {"coordinates":[-77.047708,38.8071],"type":"Point"}
}