{
  "type": "Feature",
  "properties": {
    "iso:country":"US",
    "sg:address":"1430 Villaverde Ln",
    "sg:city":"Charlottesville",
    "sg:classifiers":[
        {
            "category":"Building & Trades",
            "subcategory":"Construction",
            "type":"Services"
        }
    ],
    "sg:phone":"+1 434 971 8938",
    "sg:postcode":"22902",
    "sg:province":"VA",
    "sg:tags":[
        "house"
    ],
    "wof:name":"Henry Rexrode",
    "wof:placetype":"venue"
},
  "geometry": {"coordinates":[-78.414374,37.995751],"type":"Point"}
}