{
  "type": "Feature",
  "properties": {
    "addr:full":"2442 Jasper Ct Norfolk VA 23518",
    "addr:housenumber":"2442",
    "addr:postcode":"23518",
    "addr:street":"Jasper Ct",
    "iso:country":"US",
    "sg:address":"2442 Jasper Ct",
    "sg:city":"Norfolk",
    "sg:classifiers":[
        {
            "category":"Wholesale",
            "subcategory":"Auto Parts",
            "type":"Manufacturing & Wholesale Goods"
        }
    ],
    "sg:phone":"+1 757 587 8184",
    "sg:postcode":"23518",
    "sg:province":"VA",
    "sg:tags":[
        "supply"
    ],
    "wof:name":"Mel Auto Supply Inc",
    "wof:placetype":"venue"
},
  "geometry": {"coordinates":[-76.2124,36.913055],"type":"Point"}
}