{
  "type": "Feature",
  "properties": {
    "iso:country":"US",
    "sg:address":"1285 Progress Rd",
    "sg:city":"Front Royal",
    "sg:classifiers":[
        {
            "category":"Wholesale",
            "subcategory":"Farm Supplies",
            "type":"Manufacturing & Wholesale Goods"
        }
    ],
    "sg:phone":"+1 540 622 6901",
    "sg:postcode":"22630",
    "sg:province":"VA",
    "sg:tags":[
        "product",
        "distributes",
        "equestrian",
        "english"
    ],
    "wof:name":"Equibrand Products Group LP",
    "wof:placetype":"venue"
},
  "geometry": {"coordinates":[-78.155407,38.937674],"type":"Point"}
}