{
  "type": "Feature",
  "properties": {
    "addr:full":"5400 Southpoint Centre Blvd Fredericksburg VA 22407",
    "addr:postcode":"5400;22407",
    "addr:street":"Southpoint Centre Blvd",
    "iso:country":"US",
    "sg:address":"5400 Southpoint Centre Blvd",
    "sg:city":"Fredericksburg",
    "sg:classifiers":[
        {
            "category":"Travel",
            "subcategory":"Hotels & Motels",
            "type":"Entertainment"
        }
    ],
    "sg:phone":"+1 540 710 5500",
    "sg:postcode":"22407",
    "sg:province":"VA",
    "wof:name":"Sleep Inn Southpoint",
    "wof:placetype":"venue"
},
  "geometry": {"coordinates":[-77.501589,38.229782],"type":"Point"}
}