{
  "type": "Feature",
  "properties": {
    "iso:country":"US",
    "sg:address":"74 W Main St",
    "sg:city":"Pulaski",
    "sg:classifiers":[
        {
            "category":"Professional",
            "subcategory":"Business Services",
            "type":"Services"
        }
    ],
    "sg:phone":"+1 540 994 9313",
    "sg:postcode":"24301",
    "sg:province":"VA",
    "sg:tags":[
        "process",
        "server"
    ],
    "wof:name":"S W Virginia Court Svc",
    "wof:placetype":"venue"
},
  "geometry": {"coordinates":[-80.780248,37.047848],"type":"Point"}
}