{
  "type": "Feature",
  "properties": {
    "iso:country":"US",
    "sg:address":"1573 Bay Point Dr",
    "sg:city":"Virginia Beach",
    "sg:classifiers":[
        {
            "category":"Wholesale",
            "subcategory":"Sporting Goods",
            "type":"Manufacturing & Wholesale Goods"
        }
    ],
    "sg:phone":"+1 757 496 9152",
    "sg:postcode":"23454",
    "sg:province":"VA",
    "sg:tags":[
        "field",
        "distribution",
        "court",
        "equipment"
    ],
    "wof:name":"Sport Partners Inc",
    "wof:placetype":"venue"
},
  "geometry": {"coordinates":[-76.03493400000001,36.892585],"type":"Point"}
}