{
  "type": "Feature",
  "properties": {
    "iso:country":"US",
    "sg:address":"700 S Sycamore St",
    "sg:city":"Petersburg",
    "sg:classifiers":[
        {
            "category":"Health Services",
            "subcategory":"Doctor",
            "type":"Services"
        }
    ],
    "sg:phone":"+1 804 863 4370",
    "sg:postcode":"23803",
    "sg:province":"VA",
    "sg:tags":[
        "physician",
        "surgeon",
        "medical"
    ],
    "wof:name":"Sakuntla Kondragunta MD",
    "wof:placetype":"venue"
},
  "geometry": {"coordinates":[-77.39905,37.216508],"type":"Point"}
}