{
  "type": "Feature",
  "properties": {
    "addr:full":"3100 Popular Bend Virginia Beach VA 23452",
    "addr:postcode":"3100;23452",
    "addr:street":"Popular Bend",
    "iso:country":"US",
    "sg:address":"3100 Popular Bend",
    "sg:city":"Virginia Beach",
    "sg:classifiers":[
        {
            "category":"Professional",
            "subcategory":"Management & Consulting",
            "type":"Services"
        }
    ],
    "sg:phone":"+1 757 340 1860",
    "sg:postcode":"23452",
    "sg:province":"VA",
    "sg:tags":[
        "marketing",
        "program"
    ],
    "wof:name":"M2W Inc",
    "wof:placetype":"venue"
},
  "geometry": {"coordinates":[-76.08552899999999,36.863526],"type":"Point"}
}