{
  "type": "Feature",
  "properties": {
    "iso:country":"US",
    "sg:address":"2780 Middlecoff Pl",
    "sg:city":"Falls Church",
    "sg:classifiers":[
        {
            "category":"Professional",
            "subcategory":"Computer Services",
            "type":"Services"
        }
    ],
    "sg:phone":"+1 703 280 1647",
    "sg:postcode":"22043",
    "sg:province":"VA",
    "sg:tags":[
        "accounting",
        "consulting",
        "it"
    ],
    "wof:name":"Dka & Associates",
    "wof:placetype":"venue"
},
  "geometry": {"coordinates":[-77.212144,38.87907],"type":"Point"}
}