{
  "type": "Feature",
  "properties": {
    "iso:country":"US",
    "sg:address":"172 S Main St",
    "sg:city":"Hillsville",
    "sg:classifiers":[
        {
            "category":"Organizations",
            "subcategory":"Religious Organization",
            "type":"Services"
        }
    ],
    "sg:phone":"+1 276 728 2722",
    "sg:postcode":"24343",
    "sg:province":"VA",
    "sg:tags":[
        "church"
    ],
    "wof:name":"Hillsville's Presbyterian Chr",
    "wof:placetype":"venue"
},
  "geometry": {"coordinates":[-80.73410199999999,36.760796],"type":"Point"}
}