{
  "type": "Feature",
  "properties": {
    "addr:full":"1796 King William Rd Mangohick VA 23069",
    "addr:housenumber":"1796",
    "addr:postcode":"23069",
    "addr:street":"King William Rd",
    "iso:country":"US",
    "sg:address":"1796 King William Rd",
    "sg:city":"Mangohick",
    "sg:classifiers":[
        {
            "category":"Retail",
            "subcategory":"Auto Repair",
            "type":"Services"
        }
    ],
    "sg:phone":"+1 804 994 2424",
    "sg:postcode":"23069",
    "sg:province":"VA",
    "sg:tags":[
        "wrecker"
    ],
    "wof:name":"Woody's Garage",
    "wof:placetype":"venue"
},
  "geometry": {"coordinates":[-77.29621299999999,37.812452],"type":"Point"}
}