{
  "type": "Feature",
  "properties": {
    "addr:full":"5359 E Virginia Beach Blvd Norfolk VA 23502",
    "addr:housenumber":"5359",
    "addr:postcode":"23502",
    "addr:street":"E Virginia Beach Blvd",
    "iso:country":"US",
    "sg:address":"5359 E Virginia Beach Blvd",
    "sg:city":"Norfolk",
    "sg:classifiers":[
        {
            "category":"Home & Garden",
            "subcategory":"Furniture",
            "type":"Retail Goods"
        }
    ],
    "sg:phone":"+1 757 216 3085",
    "sg:postcode":"23502",
    "sg:province":"VA",
    "wof:name":"66 Mattress USA",
    "wof:placetype":"venue"
},
  "geometry": {"coordinates":[-76.219256,36.856029],"type":"Point"}
}