{
  "type": "Feature",
  "properties": {
    "addr:full":"5306 Affinity Ct Centreville VA 20120",
    "addr:housenumber":"5306",
    "addr:postcode":"20120",
    "addr:street":"Affinity Ct",
    "iso:country":"US",
    "sg:address":"5306 Affinity Ct",
    "sg:city":"Centreville",
    "sg:classifiers":[
        {
            "category":"Professional",
            "subcategory":"Business Services",
            "type":"Services"
        }
    ],
    "sg:phone":"+1 703 803 2810",
    "sg:postcode":"20120",
    "sg:province":"VA",
    "wof:name":"Campus Talent Partners",
    "wof:placetype":"venue"
},
  "geometry": {"coordinates":[-77.447866,38.86196],"type":"Point"}
}