{
  "type": "Feature",
  "properties": {
    "addr:full":"2233 Casemont Dr Falls Church VA 22046",
    "addr:housenumber":"2233",
    "addr:postcode":"22046",
    "addr:street":"Casemont Dr",
    "iso:country":"US",
    "sg:address":"2233 Casemont Dr",
    "sg:city":"Falls Church",
    "sg:classifiers":[
        {
            "category":"Health Services",
            "subcategory":"Doctor",
            "type":"Services"
        }
    ],
    "sg:phone":"+1 703 536 8321",
    "sg:postcode":"22046",
    "sg:province":"VA",
    "wof:name":"Perman Gerald P MD",
    "wof:placetype":"venue"
},
  "geometry": {"coordinates":[-77.176598,38.900799],"type":"Point"}
}