{
  "type": "Feature",
  "properties": {
    "addr:full":"3208 Oaklawn Blvd Hopewell VA 23860",
    "addr:housenumber":"3208",
    "addr:postcode":"23860",
    "addr:street":"Oaklawn Blvd",
    "iso:country":"US",
    "sg:address":"3208 Oaklawn Blvd",
    "sg:city":"Hopewell",
    "sg:classifiers":[
        {
            "category":"Autos & Motor Vehicles",
            "subcategory":"Automobile Sales",
            "type":"Retail Goods"
        }
    ],
    "sg:phone":"+1 804 458 7552",
    "sg:postcode":"23860",
    "sg:province":"VA",
    "wof:name":"Quality Lincoln Mercury Inc",
    "wof:placetype":"venue"
},
  "geometry": {"coordinates":[-77.30780300000001,37.279067],"type":"Point"}
}