{
  "type": "Feature",
  "properties": {
    "iso:country":"US",
    "sg:address":"1460 Anderson Hwy",
    "sg:city":"Powhatan",
    "sg:classifiers":[
        {
            "category":"Retail",
            "subcategory":"Auto Repair",
            "type":"Services"
        }
    ],
    "sg:phone":"+1 804 794 4604",
    "sg:postcode":"23139",
    "sg:province":"VA",
    "sg:tags":[
        "automotive",
        "towing",
        "general"
    ],
    "wof:name":"Llewellyns Towing and Repair",
    "wof:placetype":"venue"
},
  "geometry": {"coordinates":[-77.743679,37.507711],"type":"Point"}
}