{
  "type": "Feature",
  "properties": {
    "addr:full":"193 Wilderness Trl Luray VA 22835",
    "addr:housenumber":"193",
    "addr:postcode":"22835",
    "addr:street":"Wilderness Trl",
    "iso:country":"US",
    "sg:address":"193 Wilderness Trl",
    "sg:city":"Luray",
    "sg:classifiers":[
        {
            "category":"Freight",
            "type":"Transportation"
        }
    ],
    "sg:phone":"+1 540 743 4428",
    "sg:postcode":"22835",
    "sg:province":"VA",
    "wof:name":"Page Valley Transport",
    "wof:placetype":"venue"
},
  "geometry": {"coordinates":[-78.397828,38.66657],"type":"Point"}
}