{
  "type": "Feature",
  "properties": {
    "iso:country":"US",
    "sg:address":"812 Leftwich St",
    "sg:city":"Gretna",
    "sg:classifiers":[
        {
            "category":"Government",
            "subcategory":"Office",
            "type":"Public Place"
        }
    ],
    "sg:phone":"+1 434 656 2330",
    "sg:postcode":"24557",
    "sg:province":"VA",
    "sg:tags":[
        "transportation"
    ],
    "wof:name":"Department of Transportation",
    "wof:placetype":"venue"
},
  "geometry": {"coordinates":[-79.374493,36.954121],"type":"Point"}
}