{
  "type": "Feature",
  "properties": {
    "iso:country":"US",
    "sg:address":"324 William St",
    "sg:city":"Fredericksburg",
    "sg:classifiers":[
        {
            "category":"Restaurant",
            "type":"Food & Drink"
        }
    ],
    "sg:phone":"+1 540 373 6650",
    "sg:postcode":"22401",
    "sg:province":"VA",
    "sg:tags":[
        "eating"
    ],
    "wof:name":"Castiglia's Italian Restaurant",
    "wof:placetype":"venue"
},
  "geometry": {"coordinates":[-77.460824,38.303132],"type":"Point"}
}