{
  "type": "Feature",
  "properties": {
    "addr:full":"13032 Wards Rd Lynchburg VA 24501",
    "addr:housenumber":"13032",
    "addr:postcode":"24501",
    "addr:street":"Wards Rd",
    "iso:country":"US",
    "sg:address":"13032 Wards Rd",
    "sg:city":"Lynchburg",
    "sg:classifiers":[
        {
            "category":"Shopping",
            "subcategory":"Computers & Home Electronics",
            "type":"Retail Goods"
        }
    ],
    "sg:phone":"+1 434 821 4608",
    "sg:postcode":"24501",
    "sg:province":"VA",
    "sg:tags":[
        "repair",
        "electrical"
    ],
    "wof:name":"Satellite Place & Video Store",
    "wof:placetype":"venue"
},
  "geometry": {"coordinates":[-79.179558,37.306429],"type":"Point"}
}