{
  "type": "Feature",
  "properties": {
    "iso:country":"US",
    "sg:address":"6786 Forest Hill Ave",
    "sg:city":"Richmond",
    "sg:classifiers":[
        {
            "category":"Wholesale",
            "subcategory":"Machinery & Supplies",
            "type":"Manufacturing & Wholesale Goods"
        }
    ],
    "sg:phone":"+1 804 320 8688",
    "sg:postcode":"23225",
    "sg:province":"VA",
    "sg:tags":[
        "equipment",
        "barber"
    ],
    "wof:name":"Davidson Beauty Systems",
    "wof:placetype":"venue"
},
  "geometry": {"coordinates":[-77.519487,37.538099],"type":"Point"}
}