{
  "type": "Feature",
  "properties": {
    "addr:full":"4484 Hurston Rd Pulaski VA 24301",
    "addr:housenumber":"4484",
    "addr:postcode":"24301",
    "addr:street":"Hurston Rd",
    "iso:country":"US",
    "sg:address":"4484 Hurston Rd",
    "sg:city":"Pulaski",
    "sg:classifiers":[
        {
            "category":"Retail",
            "subcategory":"Repair Shop",
            "type":"Services"
        }
    ],
    "sg:phone":"+1 540 674 4753",
    "sg:postcode":"24301",
    "sg:province":"VA",
    "sg:tags":[
        "refinishing",
        "furniture"
    ],
    "wof:name":"Dale's Upholstery",
    "wof:placetype":"venue"
},
  "geometry": {"coordinates":[-80.704088,37.058226],"type":"Point"}
}