{
  "type": "Feature",
  "properties": {
    "iso:country":"US",
    "sg:address":"818 Norview Ave",
    "sg:city":"Norfolk",
    "sg:classifiers":[
        {
            "category":"Retail",
            "subcategory":"Funeral Services",
            "type":"Services"
        }
    ],
    "sg:phone":"+1 757 855 5558",
    "sg:postcode":"23509",
    "sg:province":"VA",
    "sg:tags":[
        "home",
        "crematory"
    ],
    "wof:name":"Smith & Williams Funeral Home",
    "wof:placetype":"venue"
},
  "geometry": {"coordinates":[-76.255017,36.890573],"type":"Point"}
}