{
  "type": "Feature",
  "properties": {
    "addr:full":"4890 Fort Ave Lynchburg VA 24502",
    "addr:housenumber":"4890",
    "addr:postcode":"24502",
    "addr:street":"Fort Ave",
    "iso:country":"US",
    "sg:address":"4890 Fort Ave",
    "sg:city":"Lynchburg",
    "sg:classifiers":[
        {
            "category":"Organizations",
            "subcategory":"Religious Organization",
            "type":"Services"
        }
    ],
    "sg:phone":"+1 434 239 4339",
    "sg:postcode":"24502",
    "sg:province":"VA",
    "wof:name":"Let Go Of The Pain Ministries",
    "wof:placetype":"venue"
},
  "geometry": {"coordinates":[-79.18208199999999,37.38065],"type":"Point"}
}