{
  "type": "Feature",
  "properties": {
    "iso:country":"US",
    "sg:address":"204 James Landing Cir",
    "sg:city":"Smithfield",
    "sg:classifiers":[
        {
            "category":"Banks & Credit Unions",
            "subcategory":"Bank",
            "type":"Services"
        }
    ],
    "sg:phone":"+1 757 356 1115",
    "sg:postcode":"23430",
    "sg:province":"VA",
    "sg:tags":[
        "financing"
    ],
    "sg:website":"www.firstveterans.com",
    "wof:name":"Veteran's First Financial Svc",
    "wof:placetype":"venue"
},
  "geometry": {"coordinates":[-76.58169100000001,36.993674],"type":"Point"}
}