{
  "type": "Feature",
  "properties": {
    "iso:country":"US",
    "sg:address":"8 Herbert St",
    "sg:city":"Alexandria",
    "sg:classifiers":[
        {
            "category":"Professional",
            "subcategory":"Employment Agencies",
            "type":"Services"
        }
    ],
    "sg:phone":"+1 703 683 9027",
    "sg:postcode":"22305",
    "sg:province":"VA",
    "sg:tags":[
        "employer"
    ],
    "wof:name":"National Association of Postmasters",
    "wof:placetype":"venue"
},
  "geometry": {"coordinates":[-77.058494,38.834087],"type":"Point"}
}