{
  "type": "Feature",
  "properties": {
    "addr:full":"18 Walnut St Martinsville VA 24112",
    "addr:housenumber":"18",
    "addr:postcode":"24112",
    "addr:street":"Walnut St",
    "iso:country":"US",
    "sg:address":"18 Walnut St",
    "sg:city":"Martinsville",
    "sg:classifiers":[
        {
            "category":"Real Estate",
            "subcategory":"Real Estate Agent",
            "type":"Services"
        }
    ],
    "sg:phone":"+1 276 666 0279",
    "sg:postcode":"24112",
    "sg:province":"VA",
    "wof:name":"Trent Realty Co Inc",
    "wof:placetype":"venue"
},
  "geometry": {"coordinates":[-79.872478,36.691517],"type":"Point"}
}