{
  "type": "Feature",
  "properties": {
    "iso:country":"US",
    "sg:address":"105 Brittania Dr",
    "sg:city":"Williamsburg",
    "sg:classifiers":[
        {
            "category":"Shopping",
            "type":"Retail Goods"
        }
    ],
    "sg:phone":"+1 757 564 0477",
    "sg:postcode":"23185",
    "sg:province":"VA",
    "sg:tags":[
        "rubber",
        "stamp"
    ],
    "wof:name":"Stampn Memories",
    "wof:placetype":"venue"
},
  "geometry": {"coordinates":[-76.663725,37.267368],"type":"Point"}
}