{
  "type": "Feature",
  "properties": {
    "iso:country":"US",
    "sg:address":"9772 Routts Hill Rd",
    "sg:city":"Warrenton",
    "sg:classifiers":[
        {
            "category":"Building & Trades",
            "subcategory":"Construction",
            "type":"Services"
        }
    ],
    "sg:phone":"+1 540 439 8899",
    "sg:postcode":"20186",
    "sg:province":"VA",
    "sg:tags":[
        "excavation",
        "contractor"
    ],
    "wof:name":"Vw Bridges Excavating",
    "wof:placetype":"venue"
},
  "geometry": {"coordinates":[-77.83362099999999,38.62827],"type":"Point"}
}