{
  "type": "Feature",
  "properties": {
    "addr:full":"10832 Split Rail Dr Manassas VA 20112",
    "addr:postcode":"20112",
    "addr:street":"Split Rail Dr",
    "iso:country":"US",
    "sg:address":"10832 Split Rail Dr",
    "sg:city":"Manassas",
    "sg:classifiers":[
        {
            "category":"Personal",
            "type":"Services"
        }
    ],
    "sg:phone":"+1 703 675 9214",
    "sg:postcode":"20112",
    "sg:province":"VA",
    "sg:tags":[
        "repair",
        "handyman"
    ],
    "wof:name":"Gorham Property Management LLC",
    "wof:placetype":"venue"
},
  "geometry": {"coordinates":[-77.387998,38.724192],"type":"Point"}
}