{
  "type": "Feature",
  "properties": {
    "iso:country":"US",
    "sg:address":"9256 Old Keene Mill Rd",
    "sg:city":"Burke",
    "sg:classifiers":[
        {
            "category":"Shopping",
            "subcategory":"Shoes",
            "type":"Retail Goods"
        }
    ],
    "sg:phone":"+1 703 912 6944",
    "sg:postcode":"22015",
    "sg:province":"VA",
    "wof:name":"Parade of Shoes 154",
    "wof:placetype":"venue"
},
  "geometry": {"coordinates":[-77.264016,38.775368],"type":"Point"}
}