{
  "type": "Feature",
  "properties": {
    "iso:country":"US",
    "sg:address":"201 S Lexington Ave",
    "sg:city":"Covington",
    "sg:classifiers":[
        {
            "category":"Retail",
            "subcategory":"Auto Repair",
            "type":"Services"
        }
    ],
    "sg:phone":"+1 540 962 6366",
    "sg:postcode":"24426",
    "sg:province":"VA",
    "sg:tags":[
        "repairing",
        "automobile"
    ],
    "wof:name":"Covington Auto Repair",
    "wof:placetype":"venue"
},
  "geometry": {"coordinates":[-79.99531399999999,37.787935],"type":"Point"}
}