{
  "type": "Feature",
  "properties": {
    "iso:country":"US",
    "sg:address":"105 Clermont Ave",
    "sg:city":"Alexandria",
    "sg:classifiers":[
        {
            "category":"Taxi",
            "type":"Transportation"
        },
        {
            "category":"Retail",
            "subcategory":"Auto Rental",
            "type":"Services"
        },
        {
            "category":"Local Transit",
            "type":"Transportation"
        }
    ],
    "sg:phone":"+1 703 836 2601",
    "sg:postcode":"22304",
    "sg:province":"VA",
    "sg:tags":[
        "shuttle",
        "limousine"
    ],
    "wof:name":"Boston Coach",
    "wof:placetype":"venue"
},
  "geometry": {"coordinates":[-77.113253,38.805344],"type":"Point"}
}