{
  "type": "Feature",
  "properties": {
    "iso:country":"US",
    "sg:address":"5927 Colfax Ave",
    "sg:city":"Alexandria",
    "sg:classifiers":[
        {
            "category":"Manufacturing",
            "subcategory":"Printing",
            "type":"Manufacturing & Wholesale Goods"
        }
    ],
    "sg:phone":"+1 703 845 0900",
    "sg:postcode":"22311",
    "sg:province":"VA",
    "sg:tags":[
        "publisher"
    ],
    "wof:name":"Mc Graw-Hill Co",
    "wof:placetype":"venue"
},
  "geometry": {"coordinates":[-77.137044,38.839104],"type":"Point"}
}