{
  "type": "Feature",
  "properties": {
    "iso:country":"US",
    "sg:address":"5249 Providence Rd",
    "sg:city":"Virginia Beach",
    "sg:classifiers":[
        {
            "category":"Health Services",
            "subcategory":"Doctor",
            "type":"Services"
        }
    ],
    "sg:phone":"+1 757 467 3900",
    "sg:postcode":"23464",
    "sg:province":"VA",
    "sg:tags":[
        "physician",
        "surgeon"
    ],
    "wof:name":"Tidewater Skin Care",
    "wof:placetype":"venue"
},
  "geometry": {"coordinates":[-76.16899600000001,36.813885],"type":"Point"}
}