{
  "type": "Feature",
  "properties": {
    "addr:full":"8225 Gunston Corner Ln Lorton VA 22079",
    "addr:housenumber":"8225",
    "addr:postcode":"22079",
    "addr:street":"Gunston Corner Ln",
    "iso:country":"US",
    "sg:address":"8225 Gunston Corner Ln",
    "sg:city":"Lorton",
    "sg:classifiers":[
        {
            "category":"Autos & Motor Vehicles",
            "subcategory":"Fuel & Gas Station",
            "type":"Retail Goods"
        }
    ],
    "sg:phone":"+1 703 643 1146",
    "sg:postcode":"22079",
    "sg:province":"VA",
    "sg:tags":[
        "oil"
    ],
    "wof:name":"Shell",
    "wof:placetype":"venue"
},
  "geometry": {"coordinates":[-77.228557,38.704806],"type":"Point"}
}