{
  "type": "Feature",
  "properties": {
    "iso:country":"US",
    "sg:address":"2001 Jefferson Davis Hwy Ste 405",
    "sg:city":"Arlington",
    "sg:classifiers":[
        {
            "category":"Building & Trades",
            "subcategory":"Construction",
            "type":"Services"
        }
    ],
    "sg:phone":"+1 703 415 3000",
    "sg:postcode":"22202",
    "sg:province":"VA",
    "sg:tags":[
        "contractor"
    ],
    "wof:name":"Hi-Tech Systems",
    "wof:placetype":"venue"
},
  "geometry": {"coordinates":[-77.05172399999999,38.856051],"type":"Point"}
}