{
  "type": "Feature",
  "properties": {
    "addr:full":"2109C N Hamilton St Richmond VA 23230",
    "addr:housenumber":"2109c",
    "addr:postcode":"23230",
    "addr:street":"N Hamilton St",
    "iso:country":"US",
    "sg:address":"2109C N Hamilton St",
    "sg:city":"Richmond",
    "sg:classifiers":[
        {
            "category":"Home & Garden",
            "subcategory":"Household Appliances",
            "type":"Retail Goods"
        },
        {
            "category":"Building & Trades",
            "subcategory":"Cleaning & Sanitation",
            "type":"Services"
        },
        {
            "category":"Building & Trades",
            "subcategory":"Construction",
            "type":"Services"
        }
    ],
    "sg:phone":"+1 804 285 8882",
    "sg:postcode":"23230",
    "sg:province":"VA",
    "sg:tags":[
        "site-clean-up",
        "floor",
        "waxing",
        "contractor",
        "window",
        "cleaning-industrial",
        "vacuum",
        "polishing",
        "janitorial"
    ],
    "sg:website":"https://smclean.custhelp.com/cgi-bin/smclean.cfg/php/enduser/doc_serve.php?2=BSYellowPages09",
    "wof:name":"ServiceMaster Clean",
    "wof:placetype":"venue"
},
  "geometry": {"coordinates":[-77.47452,37.575069],"type":"Point"}
}