{
  "type": "Feature",
  "properties": {
    "addr:full":"45575 Dulles Eastern Plz Sterling VA 20166",
    "addr:housenumber":"45575",
    "addr:postcode":"20166",
    "addr:street":"Dulles Eastern Plz",
    "iso:country":"US",
    "sg:address":"45575 Dulles Eastern Plz",
    "sg:city":"Sterling",
    "sg:classifiers":[
        {
            "category":"Shopping",
            "subcategory":"Shoes",
            "type":"Retail Goods"
        }
    ],
    "sg:phone":"+1 703 421 3411",
    "sg:postcode":"20166",
    "sg:province":"VA",
    "wof:name":"Rack Room Shoes",
    "wof:placetype":"venue"
},
  "geometry": {"coordinates":[-77.42432599999999,39.024481],"type":"Point"}
}