{
  "type": "Feature",
  "properties": {
    "iso:country":"US",
    "sg:address":"6047 Greenway Ct",
    "sg:city":"Manassas",
    "sg:classifiers":[
        {
            "category":"Social Services",
            "subcategory":"Child Care",
            "type":"Services"
        }
    ],
    "sg:phone":"+1 703 590 4739",
    "sg:postcode":"20112",
    "sg:province":"VA",
    "wof:name":"Lhr Infant Toddler Day Care",
    "wof:placetype":"venue"
},
  "geometry": {"coordinates":[-77.395495,38.708805],"type":"Point"}
}