{
  "type": "Feature",
  "properties": {
    "addr:full":"10921 Rockfish Valley Hwy Afton VA 22920",
    "addr:housenumber":"10921",
    "addr:postcode":"22920",
    "addr:street":"Rockfish Valley Hwy",
    "iso:country":"US",
    "sg:address":"10921 Rockfish Valley Hwy",
    "sg:city":"Afton",
    "sg:classifiers":[
        {
            "category":"Banks & Credit Unions",
            "subcategory":"Bank",
            "type":"Services"
        }
    ],
    "sg:phone":"+1 540 456 6042",
    "sg:postcode":"22920",
    "sg:province":"VA",
    "wof:name":"B B & T",
    "wof:placetype":"venue"
},
  "geometry": {"coordinates":[-78.83586200000001,37.992525],"type":"Point"}
}