{
  "type": "Feature",
  "properties": {
    "iso:country":"US",
    "sg:address":"11732 Timber Mill Ln",
    "sg:city":"Richmond",
    "sg:classifiers":[
        {
            "category":"Building & Trades",
            "subcategory":"Construction",
            "type":"Services"
        }
    ],
    "sg:phone":"+1 804 360 1614",
    "sg:postcode":"23233",
    "sg:province":"VA",
    "sg:tags":[
        "painter"
    ],
    "wof:name":"Brush Strokes",
    "wof:placetype":"venue"
},
  "geometry": {"coordinates":[-77.615542,37.63404],"type":"Point"}
}