{
  "type": "Feature",
  "properties": {
    "iso:country":"US",
    "sg:address":"1801 Anderson Rd",
    "sg:city":"Falls Church",
    "sg:classifiers":[
        {
            "category":"Retail",
            "subcategory":"Auto Repair",
            "type":"Services"
        }
    ],
    "sg:phone":"+1 703 847 6096",
    "sg:postcode":"22043",
    "sg:province":"VA",
    "sg:tags":[
        "shop",
        "automotive",
        "general"
    ],
    "wof:name":"Mechanicson Wheels",
    "wof:placetype":"venue"
},
  "geometry": {"coordinates":[-77.19734099999999,38.915828],"type":"Point"}
}