{
  "type": "Feature",
  "properties": {
    "addr:full":"3903 Larchwood Rd Falls Church VA 22041",
    "addr:housenumber":"3903",
    "addr:postcode":"22041",
    "addr:street":"Larchwood Rd",
    "iso:country":"US",
    "sg:address":"3903 Larchwood Rd",
    "sg:city":"Falls Church",
    "sg:classifiers":[
        {
            "category":"Retail",
            "subcategory":"Portrait Studio",
            "type":"Services"
        }
    ],
    "sg:phone":"+1 703 941 5452",
    "sg:postcode":"22041",
    "sg:province":"VA",
    "sg:tags":[
        "photo"
    ],
    "wof:name":"Rsvp Portait Studio LLC",
    "wof:placetype":"venue"
},
  "geometry": {"coordinates":[-77.164061,38.839355],"type":"Point"}
}