{
  "type": "Feature",
  "properties": {
    "addr:full":"20722 Ashburn Rd Ashburn VA 20147",
    "addr:housenumber":"20722",
    "addr:postcode":"20147",
    "addr:street":"Ashburn Rd",
    "iso:country":"US",
    "sg:address":"20722 Ashburn Rd",
    "sg:city":"Ashburn",
    "sg:classifiers":[
        {
            "category":"Building & Trades",
            "subcategory":"Landscaping Services",
            "type":"Services"
        }
    ],
    "sg:phone":"+1 703 214 1644",
    "sg:postcode":"20147",
    "sg:province":"VA",
    "sg:tags":[
        "landscape",
        "contractor"
    ],
    "wof:name":"Metro Landscaping Contracting",
    "wof:placetype":"venue"
},
  "geometry": {"coordinates":[-77.487284,39.042967],"type":"Point"}
}