{
  "type": "Feature",
  "properties": {
    "addr:full":"7438 Tack Room Dr Mechanicsville VA 23111",
    "addr:housenumber":"7438",
    "addr:postcode":"23111",
    "addr:street":"Tack Room Dr",
    "iso:country":"US",
    "sg:address":"7438 Tack Room Dr",
    "sg:city":"Mechanicsville",
    "sg:classifiers":[
        {
            "category":"Real Estate",
            "subcategory":"Real Estate Operator",
            "type":"Services"
        }
    ],
    "sg:phone":"+1 804 746 9469",
    "sg:postcode":"23111",
    "sg:province":"VA",
    "sg:tags":[
        "building",
        "apartment"
    ],
    "wof:name":"Windsor At Hunters Woods",
    "wof:placetype":"venue"
},
  "geometry": {"coordinates":[-77.36618,37.598417],"type":"Point"}
}