{
  "type": "Feature",
  "properties": {
    "iso:country":"US",
    "sg:address":"2359 York Crossing Dr",
    "sg:city":"Hayes",
    "sg:classifiers":[
        {
            "category":"Personal",
            "subcategory":"Beauty Salon",
            "type":"Services"
        }
    ],
    "sg:phone":"+1 804 642 5593",
    "sg:postcode":"23072",
    "sg:province":"VA",
    "sg:tags":[
        "shop"
    ],
    "wof:name":"Creative Hairdressers",
    "wof:placetype":"venue"
},
  "geometry": {"coordinates":[-76.497185,37.275487],"type":"Point"}
}