{
  "type": "Feature",
  "properties": {
    "iso:country":"US",
    "sg:address":"526 Orange Ave NE",
    "sg:city":"Roanoke",
    "sg:classifiers":[
        {
            "category":"Restaurant",
            "type":"Food & Drink"
        }
    ],
    "sg:phone":"+1 540 777 1029",
    "sg:postcode":"24016",
    "sg:province":"VA",
    "wof:name":"Beverly's Restaurant",
    "wof:placetype":"venue"
},
  "geometry": {"coordinates":[-79.930369,37.282554],"type":"Point"}
}