{
  "type": "Feature",
  "properties": {
    "iso:country":"US",
    "sg:address":"11235 Spotswood Trl",
    "sg:city":"Stanardsville",
    "sg:classifiers":[
        {
            "category":"Utilities",
            "subcategory":"Water",
            "type":"Services"
        }
    ],
    "sg:phone":"+1 434 985 7811",
    "sg:postcode":"22973",
    "sg:province":"VA",
    "sg:tags":[
        "company",
        "sewage"
    ],
    "wof:name":"Rapidan Service Authority",
    "wof:placetype":"venue"
},
  "geometry": {"coordinates":[-78.409801,38.270992],"type":"Point"}
}