{
  "type": "Feature",
  "properties": {
    "addr:full":"515 E Liberty St Wytheville VA 24382",
    "addr:housenumber":"515",
    "addr:postcode":"24382",
    "addr:street":"E Liberty St",
    "iso:country":"US",
    "sg:address":"515 E Liberty St",
    "sg:city":"Wytheville",
    "sg:classifiers":[
        {
            "category":"Professional",
            "subcategory":"Engineering",
            "type":"Services"
        }
    ],
    "sg:phone":"+1 276 228 4592",
    "sg:postcode":"24382",
    "sg:province":"VA",
    "sg:tags":[
        "engineer"
    ],
    "wof:name":"Us Army Corps Of Engineers",
    "wof:placetype":"venue"
},
  "geometry": {"coordinates":[-81.07346200000001,36.94823],"type":"Point"}
}