{
  "type": "Feature",
  "properties": {
    "addr:full":"1592 Penniman Rd Williamsburg VA 23185",
    "addr:housenumber":"1592",
    "addr:postcode":"23185",
    "addr:street":"Penniman Rd",
    "iso:country":"US",
    "sg:address":"1592 Penniman Rd",
    "sg:city":"Williamsburg",
    "sg:classifiers":[
        {
            "category":"Manufacturing",
            "subcategory":"Signs",
            "type":"Manufacturing & Wholesale Goods"
        }
    ],
    "sg:phone":"+1 757 258 2520",
    "sg:postcode":"23185",
    "sg:province":"VA",
    "wof:name":"Sign Vision",
    "wof:placetype":"venue"
},
  "geometry": {"coordinates":[-76.64525399999999,37.262817],"type":"Point"}
}