{
  "type": "Feature",
  "properties": {
    "addr:full":"5350 Darbytown Rd Richmond VA 23231",
    "addr:postcode":"5350;23231",
    "addr:street":"Darbytown Rd",
    "iso:country":"US",
    "sg:address":"5350 Darbytown Rd",
    "sg:city":"Richmond",
    "sg:classifiers":[
        {
            "category":"Organizations",
            "subcategory":"Religious Organization",
            "type":"Services"
        }
    ],
    "sg:phone":"+1 804 795 2710",
    "sg:postcode":"23231",
    "sg:province":"VA",
    "sg:tags":[
        "church"
    ],
    "wof:name":"Varina Church Of The Nazarene",
    "wof:placetype":"venue"
},
  "geometry": {"coordinates":[-77.27210700000001,37.449217],"type":"Point"}
}