{
  "type": "Feature",
  "properties": {
    "addr:full":"2310 Whitetail Ct Reston VA 20191",
    "addr:housenumber":"2310",
    "addr:postcode":"20191",
    "addr:street":"Whitetail Ct",
    "iso:country":"US",
    "sg:address":"2310 Whitetail Ct",
    "sg:city":"Reston",
    "sg:classifiers":[
        {
            "category":"Communications",
            "subcategory":"Film & Video Production",
            "type":"Services"
        }
    ],
    "sg:phone":"+1 703 860 1236",
    "sg:postcode":"20191",
    "sg:province":"VA",
    "sg:tags":[
        "motion",
        "picture",
        "taping"
    ],
    "wof:name":"Capture Video Inc",
    "wof:placetype":"venue"
},
  "geometry": {"coordinates":[-77.346932,38.927653],"type":"Point"}
}