{
  "type": "Feature",
  "properties": {
    "iso:country":"US",
    "sg:address":"4113 Lee Hwy",
    "sg:city":"Arlington",
    "sg:classifiers":[
        {
            "category":"Autos & Motor Vehicles",
            "subcategory":"Automobile Sales",
            "type":"Retail Goods"
        },
        {
            "category":"Airline",
            "type":"Transportation"
        }
    ],
    "sg:phone":"+1 703 465 8700",
    "sg:postcode":"22207",
    "sg:province":"VA",
    "sg:tags":[
        "shuttle",
        "airport",
        "limo"
    ],
    "sg:website":"www.jupiterlimo.com",
    "wof:name":"Jupiter Sedan & Limousine",
    "wof:placetype":"venue"
},
  "geometry": {"coordinates":[-77.11129800000001,38.897099],"type":"Point"}
}