{
  "type": "Feature",
  "properties": {
    "addr:full":"8679 Telegraph Rd Glen Allen VA 23060",
    "addr:housenumber":"8679",
    "addr:postcode":"23060",
    "addr:street":"Telegraph Rd",
    "iso:country":"US",
    "sg:address":"8679 Telegraph Rd",
    "sg:city":"Glen Allen",
    "sg:classifiers":[
        {
            "category":"Wholesale",
            "subcategory":"Machinery & Supplies",
            "type":"Manufacturing & Wholesale Goods"
        },
        {
            "category":"Autos & Motor Vehicles",
            "subcategory":"Auto Supplies",
            "type":"Retail Goods"
        }
    ],
    "sg:phone":"+1 804 262 0004",
    "sg:postcode":"23060",
    "sg:province":"VA",
    "sg:tags":[
        "automobile",
        "industrial",
        "parts"
    ],
    "wof:name":"Sentinel Automotive Distr Inc",
    "wof:placetype":"venue"
},
  "geometry": {"coordinates":[-77.45971900000001,37.640062],"type":"Point"}
}