{
  "type": "Feature",
  "properties": {
    "iso:country":"US",
    "sg:address":"1100 Jefferson Davis Hwy",
    "sg:city":"Richmond",
    "sg:classifiers":[
        {
            "category":"Manufacturing",
            "subcategory":"Retail Goods",
            "type":"Manufacturing & Wholesale Goods"
        }
    ],
    "sg:phone":"+1 804 233 8400",
    "sg:postcode":"23224",
    "sg:province":"VA",
    "sg:tags":[
        "manufacturer"
    ],
    "wof:name":"Im Manufacturing Imc",
    "wof:placetype":"venue"
},
  "geometry": {"coordinates":[-77.446923,37.504373],"type":"Point"}
}