{
  "type": "Feature",
  "properties": {
    "iso:country":"US",
    "sg:address":"13208 Hull Street Rd",
    "sg:city":"Midlothian",
    "sg:classifiers":[
        {
            "category":"Banks & Credit Unions",
            "subcategory":"Bank",
            "type":"Services"
        }
    ],
    "sg:phone":"+1 804 763 6414",
    "sg:postcode":"23112",
    "sg:province":"VA",
    "sg:tags":[
        "loan",
        "real estate"
    ],
    "wof:name":"Tower Mortgage LLC",
    "wof:placetype":"venue"
},
  "geometry": {"coordinates":[-77.641166,37.417157],"type":"Point"}
}