{
  "type": "Feature",
  "properties": {
    "addr:full":"6297 Laurel Grove Rd Norton VA 24273",
    "addr:housenumber":"6297",
    "addr:postcode":"24273",
    "addr:street":"Laurel Grove Rd",
    "iso:country":"US",
    "sg:address":"6297 Laurel Grove Rd",
    "sg:city":"Norton",
    "sg:classifiers":[
        {
            "category":"Building & Trades",
            "subcategory":"Construction",
            "type":"Services"
        }
    ],
    "sg:phone":"+1 276 679 5910",
    "sg:postcode":"24273",
    "sg:province":"VA",
    "sg:tags":[
        "excavating",
        "contractor"
    ],
    "wof:name":"Steve Caudill",
    "wof:placetype":"venue"
},
  "geometry": {"coordinates":[-82.659854,36.979358],"type":"Point"}
}