{
  "type": "Feature",
  "properties": {
    "addr:full":"7 Bunker Blvd Palmyra VA 22963",
    "addr:housenumber":"7",
    "addr:postcode":"22963",
    "addr:street":"Bunker Blvd",
    "iso:country":"US",
    "sg:address":"7 Bunker Blvd",
    "sg:city":"Palmyra",
    "sg:classifiers":[
        {
            "category":"Professional",
            "subcategory":"Computer Services",
            "type":"Services"
        }
    ],
    "sg:phone":"+1 434 589 2952",
    "sg:postcode":"22963",
    "sg:province":"VA",
    "sg:tags":[
        "related"
    ],
    "wof:name":"Gvsystems Inc Co",
    "wof:placetype":"venue"
},
  "geometry": {"coordinates":[-78.316553,37.899606],"type":"Point"}
}