{
  "type": "Feature",
  "properties": {
    "addr:full":"3922 Egan Dr Fairfax VA 22030",
    "addr:housenumber":"3922",
    "addr:postcode":"22030",
    "addr:street":"Egan Dr",
    "iso:country":"US",
    "sg:address":"3922 Egan Dr",
    "sg:city":"Fairfax",
    "sg:classifiers":[
        {
            "category":"Building & Trades",
            "subcategory":"Plumbing",
            "type":"Services"
        }
    ],
    "sg:phone":"+1 703 273 1089",
    "sg:postcode":"22030",
    "sg:province":"VA",
    "sg:tags":[
        "contractor"
    ],
    "wof:name":"Paragon Waterworks",
    "wof:placetype":"venue"
},
  "geometry": {"coordinates":[-77.324479,38.854492],"type":"Point"}
}