{
  "type": "Feature",
  "properties": {
    "iso:country":"US",
    "sg:address":"1504 Santa Rosa Rd",
    "sg:city":"Richmond",
    "sg:classifiers":[
        {
            "category":"Professional",
            "subcategory":"Management & Consulting",
            "type":"Services"
        }
    ],
    "sg:phone":"+1 804 285 4780",
    "sg:postcode":"23229",
    "sg:province":"VA",
    "wof:name":"Alexander Financial Services",
    "wof:placetype":"venue"
},
  "geometry": {"coordinates":[-77.54863,37.602226],"type":"Point"}
}