{
  "type": "Feature",
  "properties": {
    "addr:full":"1900 George Washington Memorial Hwy Yorktown VA 23693",
    "addr:housenumber":"1900",
    "addr:postcode":"23693",
    "addr:street":"George Washington Memorial Hwy",
    "iso:country":"US",
    "sg:address":"1900 George Washington Memorial Hwy",
    "sg:city":"Yorktown",
    "sg:classifiers":[
        {
            "category":"Professional",
            "subcategory":"Management & Consulting",
            "type":"Services"
        }
    ],
    "sg:phone":"+1 757 596 4508",
    "sg:postcode":"23693",
    "sg:province":"VA",
    "sg:tags":[
        "consultant",
        "training"
    ],
    "sg:website":"www.aoce.com",
    "wof:name":"Alpha Omega Change Engineering",
    "wof:placetype":"venue"
},
  "geometry": {"coordinates":[-76.45616699999999,37.112693],"type":"Point"}
}