{
  "type": "Feature",
  "properties": {
    "addr:full":"5509 Yates Ln Richmond VA 23223",
    "addr:housenumber":"5509",
    "addr:postcode":"23223",
    "addr:street":"Yates Ln",
    "iso:country":"US",
    "sg:address":"5509 Yates Ln",
    "sg:city":"Richmond",
    "sg:classifiers":[
        {
            "category":"Organizations",
            "subcategory":"Religious Organization",
            "type":"Services"
        }
    ],
    "sg:phone":"+1 804 737 5560",
    "sg:postcode":"23223",
    "sg:province":"VA",
    "wof:name":"Great Commission Outreach Mini",
    "wof:placetype":"venue"
},
  "geometry": {"coordinates":[-77.352949,37.545259],"type":"Point"}
}