{
  "type": "Feature",
  "properties": {
    "iso:country":"US",
    "sg:address":"3247 Electric Rd",
    "sg:city":"Roanoke",
    "sg:classifiers":[
        {
            "category":"Education",
            "subcategory":"Special Training",
            "type":"Public Place"
        }
    ],
    "sg:phone":"+1 540 774 9326",
    "sg:postcode":"24018",
    "sg:province":"VA",
    "sg:tags":[
        "instruction",
        "music"
    ],
    "wof:name":"Tim Martin",
    "wof:placetype":"venue"
},
  "geometry": {"coordinates":[-80.00729,37.229363],"type":"Point"}
}