{
  "type": "Feature",
  "properties": {
    "iso:country":"US",
    "sg:address":"6813 Tennyson Dr",
    "sg:city":"Mc Lean",
    "sg:classifiers":[
        {
            "category":"Professional",
            "subcategory":"Management & Consulting",
            "type":"Services"
        }
    ],
    "sg:phone":"+1 703 864 9247",
    "sg:postcode":"22101",
    "sg:province":"VA",
    "wof:name":"Focus Management & Consulting",
    "wof:placetype":"venue"
},
  "geometry": {"coordinates":[-77.180498,38.931385],"type":"Point"}
}