{
  "type": "Feature",
  "properties": {
    "addr:full":"4523 Franconia Rd Alexandria VA 22310",
    "addr:housenumber":"4523",
    "addr:postcode":"22310",
    "addr:street":"Franconia Rd",
    "iso:country":"US",
    "sg:address":"4523 Franconia Rd",
    "sg:city":"Alexandria",
    "sg:classifiers":[
        {
            "category":"Organizations",
            "subcategory":"Community Association",
            "type":"Services"
        }
    ],
    "sg:phone":"+1 703 971 6831",
    "sg:postcode":"22310",
    "sg:province":"VA",
    "wof:name":"Ancient Order of Hibernia",
    "wof:placetype":"venue"
},
  "geometry": {"coordinates":[-77.113034,38.788698],"type":"Point"}
}