{
  "type": "Feature",
  "properties": {
    "addr:full":"11240 Waples Mill Rd Fairfax VA 22030",
    "addr:housenumber":"11240",
    "addr:postcode":"22030",
    "addr:street":"Waples Mill Rd",
    "iso:country":"US",
    "sg:address":"11240 Waples Mill Rd",
    "sg:city":"Fairfax",
    "sg:classifiers":[
        {
            "category":"Manufacturing",
            "subcategory":"Printing",
            "type":"Manufacturing & Wholesale Goods"
        }
    ],
    "sg:phone":"+1 703 383 6740",
    "sg:postcode":"22030",
    "sg:province":"VA",
    "sg:tags":[
        "cards",
        "greeting",
        "mfg"
    ],
    "wof:name":"American Greetings",
    "wof:placetype":"venue"
},
  "geometry": {"coordinates":[-77.33632799999999,38.862278],"type":"Point"}
}