{
  "type": "Feature",
  "properties": {
    "addr:full":"7640 Provincial Dr Mc Lean VA 22102",
    "addr:housenumber":"7640",
    "addr:postcode":"22102",
    "addr:street":"Provincial Dr",
    "iso:country":"US",
    "sg:address":"7640 Provincial Dr",
    "sg:city":"Mc Lean",
    "sg:classifiers":[
        {
            "category":"Professional",
            "subcategory":"Management & Consulting",
            "type":"Services"
        }
    ],
    "sg:phone":"+1 703 893 7618",
    "sg:postcode":"22102",
    "sg:province":"VA",
    "sg:tags":[
        "consultant",
        "engineer"
    ],
    "wof:name":"Semprex International Inc",
    "wof:placetype":"venue"
},
  "geometry": {"coordinates":[-77.20954,38.917903],"type":"Point"}
}