{
  "type": "Feature",
  "properties": {
    "addr:full":"1223 Front St Richlands VA 24641",
    "addr:housenumber":"1223",
    "addr:postcode":"24641",
    "addr:street":"Front St",
    "iso:country":"US",
    "sg:address":"1223 Front St",
    "sg:city":"Richlands",
    "sg:classifiers":[
        {
            "category":"Personal",
            "subcategory":"Beauty Salon",
            "type":"Services"
        }
    ],
    "sg:phone":"+1 276 963 7830",
    "sg:postcode":"24641",
    "sg:province":"VA",
    "wof:name":"Hair Unlimited",
    "wof:placetype":"venue"
},
  "geometry": {"coordinates":[-81.79673699999999,37.093073],"type":"Point"}
}