{
  "type": "Feature",
  "properties": {
    "addr:full":"10 Independence St Portsmouth VA 23701",
    "addr:housenumber":"10",
    "addr:postcode":"23701",
    "addr:street":"Independence St",
    "iso:country":"US",
    "sg:address":"10 Independence St",
    "sg:city":"Portsmouth",
    "sg:classifiers":[
        {
            "category":"Education",
            "subcategory":"School",
            "type":"Public Place"
        }
    ],
    "sg:phone":"+1 757 393 8728",
    "sg:postcode":"23701",
    "sg:province":"VA",
    "sg:website":"www.pps.k12.va.us",
    "wof:name":"New Directions Ctr School",
    "wof:placetype":"venue"
},
  "geometry": {"coordinates":[-76.33563599999999,36.807497],"type":"Point"}
}