{
  "type": "Feature",
  "properties": {
    "addr:full":"175 E Jackson St Gate City VA 24251",
    "addr:housenumber":"175",
    "addr:postcode":"24251",
    "addr:street":"E Jackson St Gate",
    "iso:country":"US",
    "sg:address":"175 E Jackson St",
    "sg:city":"Gate City",
    "sg:classifiers":[
        {
            "category":"Shopping",
            "subcategory":"Discount & Variety Stores",
            "type":"Retail Goods"
        }
    ],
    "sg:phone":"+1 276 386 9960",
    "sg:postcode":"24251",
    "sg:province":"VA",
    "wof:name":"Dollar General",
    "wof:placetype":"venue"
},
  "geometry": {"coordinates":[-82.57915,36.639213],"type":"Point"}
}