{
  "type": "Feature",
  "properties": {
    "addr:full":"4601 Fairfax Dr Arlington VA 22203",
    "addr:housenumber":"4601",
    "addr:postcode":"22203",
    "addr:street":"Fairfax Dr",
    "iso:country":"US",
    "sg:address":"4601 Fairfax Dr",
    "sg:city":"Arlington",
    "sg:classifiers":[
        {
            "category":"Shopping",
            "subcategory":"Computers & Home Electronics",
            "type":"Retail Goods"
        }
    ],
    "sg:phone":"+1 703 908 7000",
    "sg:postcode":"22203",
    "sg:province":"VA",
    "sg:tags":[
        "equipment",
        "dealer"
    ],
    "wof:name":"Computer Sciences Corp",
    "wof:placetype":"venue"
},
  "geometry": {"coordinates":[-77.117344,38.882044],"type":"Point"}
}