{
  "type": "Feature",
  "properties": {
    "addr:full":"9300 Old Keene Mill Rd Burke VA 22015",
    "addr:housenumber":"9300",
    "addr:postcode":"22015",
    "addr:street":"Old Keene Mill Rd",
    "iso:country":"US",
    "sg:address":"9300 Old Keene Mill Rd",
    "sg:city":"Burke",
    "sg:classifiers":[
        {
            "category":"Education",
            "subcategory":"Vocational School",
            "type":"Public Place"
        }
    ],
    "sg:phone":"+1 703 923 0041",
    "sg:postcode":"22015",
    "sg:province":"VA",
    "sg:tags":[
        "training",
        "computer"
    ],
    "wof:name":"Global Certification",
    "wof:placetype":"venue"
},
  "geometry": {"coordinates":[-77.26833499999999,38.776071],"type":"Point"}
}