{
  "type": "Feature",
  "properties": {
    "iso:country":"US",
    "sg:address":"11806 Spectrum Center",
    "sg:city":"Reston",
    "sg:classifiers":[
        {
            "category":"Organizations",
            "subcategory":"Professional Association",
            "type":"Services"
        }
    ],
    "sg:phone":"+1 703 435 5800",
    "sg:postcode":"20190",
    "sg:province":"VA",
    "wof:name":"Harris Teeter",
    "wof:placetype":"venue"
},
  "geometry": {"coordinates":[-77.35533,38.96415],"type":"Point"}
}