{
  "type": "Feature",
  "properties": {
    "addr:full":"1001 Hioaks Rd Richmond VA 23225",
    "addr:housenumber":"1001",
    "addr:postcode":"23225",
    "addr:street":"Hioaks Rd",
    "iso:country":"US",
    "sg:address":"1001 Hioaks Rd",
    "sg:city":"Richmond",
    "sg:classifiers":[
        {
            "category":"Health Services",
            "subcategory":"Doctor",
            "type":"Services"
        }
    ],
    "sg:phone":"+1 804 320 7139",
    "sg:postcode":"23225",
    "sg:province":"VA",
    "sg:tags":[
        "physician",
        "surgeon"
    ],
    "wof:name":"Pediatrics Associates",
    "wof:placetype":"venue"
},
  "geometry": {"coordinates":[-77.52473500000001,37.512235],"type":"Point"}
}