{
  "type": "Feature",
  "properties": {
    "addr:full":"6088 Crown Royal Cir Alexandria VA 22310",
    "addr:housenumber":"6088",
    "addr:postcode":"22310",
    "addr:street":"Crown Royal Cir",
    "iso:country":"US",
    "sg:address":"6088 Crown Royal Cir",
    "sg:city":"Alexandria",
    "sg:classifiers":[
        {
            "category":"Professional",
            "subcategory":"Lawyer & Legal Services",
            "type":"Services"
        }
    ],
    "sg:phone":"+1 703 971 6558",
    "sg:postcode":"22310",
    "sg:province":"VA",
    "wof:name":"Dennis Pryba",
    "wof:placetype":"venue"
},
  "geometry": {"coordinates":[-77.137885,38.787504],"type":"Point"}
}