{
  "type": "Feature",
  "properties": {
    "iso:country":"US",
    "sg:address":"2707 Dellrose Ave",
    "sg:city":"Richmond",
    "sg:classifiers":[
        {
            "category":"Building & Trades",
            "subcategory":"Construction",
            "type":"Services"
        }
    ],
    "sg:phone":"+1 804 264 8948",
    "sg:postcode":"23228",
    "sg:province":"VA",
    "sg:tags":[
        "house"
    ],
    "wof:name":"Garrett Home Improvement",
    "wof:placetype":"venue"
},
  "geometry": {"coordinates":[-77.48136599999999,37.607726],"type":"Point"}
}