{
  "type": "Feature",
  "properties": {
    "addr:full":"12309 Duncannon Ct Glen Allen VA 23059",
    "addr:housenumber":"12309",
    "addr:postcode":"23059",
    "addr:street":"Duncannon Ct",
    "iso:country":"US",
    "sg:address":"12309 Duncannon Ct",
    "sg:city":"Glen Allen",
    "sg:classifiers":[
        {
            "category":"Professional",
            "type":"Services"
        }
    ],
    "sg:phone":"+1 804 360 9496",
    "sg:postcode":"23059",
    "sg:province":"VA",
    "wof:name":"Itsearchresearch LLC",
    "wof:placetype":"venue"
},
  "geometry": {"coordinates":[-77.62594199999999,37.700514],"type":"Point"}
}