{
  "type": "Feature",
  "properties": {
    "addr:full":"250 Mt Jackson Rd Mt Jackson VA 22842",
    "addr:housenumber":"250",
    "addr:postcode":"22842",
    "addr:street":"Mt Jackson Rd",
    "iso:country":"US",
    "sg:address":"250 Mt Jackson Rd",
    "sg:city":"Mt Jackson",
    "sg:classifiers":[
        {
            "category":"Professional",
            "subcategory":"Advertising",
            "type":"Services"
        }
    ],
    "sg:phone":"+1 540 477 2735",
    "sg:postcode":"22842",
    "sg:province":"VA",
    "sg:tags":[
        "distributing",
        "sample"
    ],
    "wof:name":"Mailcon",
    "wof:placetype":"venue"
},
  "geometry": {"coordinates":[-78.64955399999999,38.764876],"type":"Point"}
}