{
  "type": "Feature",
  "properties": {
    "addr:full":"9193 Barhamsville Rd Toano VA 23168",
    "addr:housenumber":"9193",
    "addr:postcode":"23168",
    "addr:street":"Barhamsville Rd",
    "iso:country":"US",
    "sg:address":"9193 Barhamsville Rd",
    "sg:city":"Toano",
    "sg:classifiers":[
        {
            "category":"Restaurant",
            "type":"Food & Drink"
        }
    ],
    "sg:menulink":"http://www.allmenus.com/va/stonehouse/188166-mcdonalds/menu/",
    "sg:phone":"+1 757 566 3042",
    "sg:postcode":"23168",
    "sg:province":"VA",
    "sg:tags":[
        "burger",
        "american"
    ],
    "wof:name":"McDonald's",
    "wof:placetype":"venue"
},
  "geometry": {"coordinates":[-76.82086200000001,37.41628],"type":"Point"}
}