{
  "type": "Feature",
  "properties": {
    "iso:country":"US",
    "sg:address":"7901 Jones Branch Dr",
    "sg:city":"Mc Lean",
    "sg:classifiers":[
        {
            "category":"Health Services",
            "subcategory":"Doctor",
            "type":"Services"
        }
    ],
    "sg:phone":"+1 703 448 0004",
    "sg:postcode":"22102",
    "sg:province":"VA",
    "sg:tags":[
        "physician",
        "surgeon"
    ],
    "wof:name":"Care Rehab Orthopaedic Prod",
    "wof:placetype":"venue"
},
  "geometry": {"coordinates":[-77.218971,38.931472],"type":"Point"}
}