{
  "type": "Feature",
  "properties": {
    "addr:full":"7027 Manahoac Pl Gainesville VA 20155",
    "addr:housenumber":"7027",
    "addr:postcode":"20155",
    "addr:street":"Manahoac Pl",
    "iso:country":"US",
    "sg:address":"7027 Manahoac Pl",
    "sg:city":"Gainesville",
    "sg:classifiers":[
        {
            "category":"Banks & Credit Unions",
            "subcategory":"Bank",
            "type":"Services"
        }
    ],
    "sg:phone":"+1 703 753 8911",
    "sg:postcode":"20155",
    "sg:province":"VA",
    "sg:tags":[
        "loan",
        "real estate"
    ],
    "wof:name":"Catoctin Mortgage LLC",
    "wof:placetype":"venue"
},
  "geometry": {"coordinates":[-77.63083399999999,38.806928],"type":"Point"}
}