{
  "type": "Feature",
  "properties": {
    "addr:full":"1401 Sanderson Dr Sterling VA 20164",
    "addr:housenumber":"1401",
    "addr:postcode":"20164",
    "addr:street":"Sanderson Dr",
    "iso:country":"US",
    "sg:address":"1401 Sanderson Dr",
    "sg:city":"Sterling",
    "sg:classifiers":[
        {
            "category":"Building & Trades",
            "subcategory":"Construction",
            "type":"Services"
        }
    ],
    "sg:phone":"+1 703 444 0886",
    "sg:postcode":"20164",
    "sg:province":"VA",
    "sg:tags":[
        "dry wall",
        "contractor"
    ],
    "wof:name":"Tucker Drywall",
    "wof:placetype":"venue"
},
  "geometry": {"coordinates":[-77.38499899999999,39.035517],"type":"Point"}
}