{
  "type": "Feature",
  "properties": {
    "iso:country":"US",
    "sg:address":"549 Newtown Rd",
    "sg:city":"Virginia Beach",
    "sg:classifiers":[
        {
            "category":"Shopping",
            "subcategory":"Clothing, Apparel, & Fashions",
            "type":"Retail Goods"
        }
    ],
    "sg:phone":"+1 757 456 5066",
    "sg:postcode":"23462",
    "sg:province":"VA",
    "sg:tags":[
        "item",
        "boutique"
    ],
    "wof:name":"Spoiled Rotten",
    "wof:placetype":"venue"
},
  "geometry": {"coordinates":[-76.176422,36.858366],"type":"Point"}
}