{
  "type": "Feature",
  "properties": {
    "addr:full":"6244 Old Dominion Dr Mc Lean VA 22101",
    "addr:housenumber":"6244",
    "addr:postcode":"22101",
    "addr:street":"Old Dominion Dr",
    "iso:country":"US",
    "sg:address":"6244 Old Dominion Dr",
    "sg:city":"Mc Lean",
    "sg:classifiers":[
        {
            "category":"Shopping",
            "subcategory":"Pharmacy",
            "type":"Retail Goods"
        }
    ],
    "sg:phone":"+1 703 533 7315",
    "sg:postcode":"22101",
    "sg:province":"VA",
    "sg:tags":[
        "drugstore"
    ],
    "wof:name":"Safeway Pharmacy",
    "wof:placetype":"venue"
},
  "geometry": {"coordinates":[-77.152,38.920799],"type":"Point"}
}