{
  "type": "Feature",
  "properties": {
    "iso:country":"US",
    "sg:address":"1395 Volunteer Pkwy",
    "sg:city":"Bristol",
    "sg:classifiers":[
        {
            "category":"Personal",
            "subcategory":"Tanning Parlor",
            "type":"Services"
        },
        {
            "category":"Personal",
            "subcategory":"Beauty Salon",
            "type":"Services"
        }
    ],
    "sg:phone":"+1 423 764 8180",
    "sg:postcode":"37620",
    "sg:province":"VA",
    "sg:tags":[
        "shop"
    ],
    "wof:name":"Changing Image",
    "wof:placetype":"venue"
},
  "geometry": {"coordinates":[-82.211922,36.559099],"type":"Point"}
}