{
  "type": "Feature",
  "properties": {
    "addr:full":"1577 Wilroy Rd Suffolk VA 23434",
    "addr:housenumber":"1577",
    "addr:postcode":"23434",
    "addr:street":"Wilroy Rd",
    "iso:country":"US",
    "sg:address":"1577 Wilroy Rd",
    "sg:city":"Suffolk",
    "sg:classifiers":[
        {
            "category":"Professional",
            "subcategory":"Employment Agencies",
            "type":"Services"
        }
    ],
    "sg:phone":"+1 757 538 1519",
    "sg:postcode":"23434",
    "sg:province":"VA",
    "sg:tags":[
        "personnel",
        "placement"
    ],
    "wof:name":"Management Recruiters Intl",
    "wof:placetype":"venue"
},
  "geometry": {"coordinates":[-76.55725700000001,36.760689],"type":"Point"}
}