{
  "type": "Feature",
  "properties": {
    "addr:full":"5377 Colt Dr Broad Run VA 20137",
    "addr:housenumber":"5377",
    "addr:postcode":"20137",
    "addr:street":"Colt Dr Broad Run",
    "iso:country":"US",
    "sg:address":"5377 Colt Dr",
    "sg:city":"Broad Run",
    "sg:classifiers":[
        {
            "category":"Professional",
            "subcategory":"Engineering",
            "type":"Services"
        }
    ],
    "sg:phone":"+1 540 347 0439",
    "sg:postcode":"20137",
    "sg:province":"VA",
    "wof:name":"Enviro Construction Service",
    "wof:placetype":"venue"
},
  "geometry": {"coordinates":[-77.73345999999999,38.788515],"type":"Point"}
}