{
  "type": "Feature",
  "properties": {
    "iso:country":"US",
    "sg:address":"2283 Cocquina Dr",
    "sg:city":"Reston",
    "sg:classifiers":[
        {
            "category":"Freight",
            "type":"Transportation"
        }
    ],
    "sg:phone":"+1 703 860 5400",
    "sg:postcode":"20191",
    "sg:province":"VA",
    "sg:tags":[
        "hauling",
        "trucking"
    ],
    "wof:name":"Debbie's Trucking",
    "wof:placetype":"venue"
},
  "geometry": {"coordinates":[-77.37490699999999,38.946951],"type":"Point"}
}