{
  "type": "Feature",
  "properties": {
    "addr:full":"23131 Rock Hill Rd Sterling VA 20166",
    "addr:housenumber":"23131",
    "addr:postcode":"20166",
    "addr:street":"Rock Hill Rd",
    "iso:country":"US",
    "sg:address":"23131 Rock Hill Rd",
    "sg:city":"Sterling",
    "sg:classifiers":[
        {
            "category":"Food & Beverages",
            "subcategory":"Groceries & Convenience Stores",
            "type":"Retail Goods"
        }
    ],
    "sg:phone":"+1 703 437 0104",
    "sg:postcode":"20166",
    "sg:province":"VA",
    "wof:name":"7-Eleven",
    "wof:placetype":"venue"
},
  "geometry": {"coordinates":[-77.411857,38.97356],"type":"Point"}
}