{
  "type": "Feature",
  "properties": {
    "iso:country":"US",
    "sg:address":"9766 Center St",
    "sg:city":"Manassas",
    "sg:classifiers":[
        {
            "category":"Retail",
            "subcategory":"Repair Shop",
            "type":"Services"
        }
    ],
    "sg:phone":"+1 703 361 9100",
    "sg:postcode":"20110",
    "sg:province":"VA",
    "wof:name":"One Dollar Movie Video",
    "wof:placetype":"venue"
},
  "geometry": {"coordinates":[-77.489102,38.753456],"type":"Point"}
}