{
  "type": "Feature",
  "properties": {
    "addr:full":"4593 Picasso Dr Virginia Beach VA 23456",
    "addr:housenumber":"4593",
    "addr:postcode":"23456",
    "addr:street":"Picasso Dr",
    "iso:country":"US",
    "sg:address":"4593 Picasso Dr",
    "sg:city":"Virginia Beach",
    "sg:classifiers":[
        {
            "category":"Professional",
            "type":"Services"
        }
    ],
    "sg:phone":"+1 757 474 4408",
    "sg:postcode":"23456",
    "sg:province":"VA",
    "wof:name":"Domingo L Bayonla",
    "wof:placetype":"venue"
},
  "geometry": {"coordinates":[-76.140384,36.789819],"type":"Point"}
}