{
  "type": "Feature",
  "properties": {
    "iso:country":"US",
    "sg:address":"433 Park St",
    "sg:city":"Charlottesville",
    "sg:classifiers":[
        {
            "category":"Manufacturing",
            "subcategory":"Glass & Minerals",
            "type":"Manufacturing & Wholesale Goods"
        }
    ],
    "sg:phone":"+1 434 293 2825",
    "sg:postcode":"22902",
    "sg:province":"VA",
    "sg:tags":[
        "concrete",
        "product",
        "mfg"
    ],
    "wof:name":"Gate Concrete Products Co",
    "wof:placetype":"venue"
},
  "geometry": {"coordinates":[-78.47672300000001,38.032436],"type":"Point"}
}