{
  "type": "Feature",
  "properties": {
    "addr:full":"96 Seafood Ln Irvington VA 22480",
    "addr:postcode":"22480",
    "addr:street":"Seafood Ln",
    "iso:country":"US",
    "sg:address":"96 Seafood Ln",
    "sg:city":"Irvington",
    "sg:classifiers":[
        {
            "category":"Recreation",
            "subcategory":"Marina",
            "type":"Entertainment"
        }
    ],
    "sg:phone":"+1 804 438 5563",
    "sg:postcode":"22480",
    "sg:province":"VA",
    "sg:tags":[
        "repairing",
        "boat"
    ],
    "wof:name":"Custom Yacht Svc Inc",
    "wof:placetype":"venue"
},
  "geometry": {"coordinates":[-76.42062799999999,37.656216],"type":"Point"}
}