{
  "type": "Feature",
  "properties": {
    "addr:full":"1806 N Calvert St Arlington VA 22201",
    "addr:housenumber":"1806",
    "addr:postcode":"22201",
    "addr:street":"N Calvert St",
    "iso:country":"US",
    "sg:address":"1806 N Calvert St",
    "sg:city":"Arlington",
    "sg:classifiers":[
        {
            "category":"Professional",
            "subcategory":"Management & Consulting",
            "type":"Services"
        }
    ],
    "sg:phone":"+1 703 527 3048",
    "sg:postcode":"22201",
    "sg:province":"VA",
    "wof:name":"Rdb Group Inc",
    "wof:placetype":"venue"
},
  "geometry": {"coordinates":[-77.09218199999999,38.894616],"type":"Point"}
}