{
  "type": "Feature",
  "properties": {
    "addr:full":"4192 Innslake Dr Glen Allen VA 23060",
    "addr:housenumber":"4192",
    "addr:postcode":"23060",
    "addr:street":"Innslake Dr",
    "iso:country":"US",
    "sg:address":"4192 Innslake Dr",
    "sg:city":"Glen Allen",
    "sg:classifiers":[
        {
            "category":"Professional",
            "subcategory":"Computer Services",
            "type":"Services"
        }
    ],
    "sg:phone":"+1 804 965 9800",
    "sg:postcode":"23060",
    "sg:province":"VA",
    "sg:tags":[
        "repair"
    ],
    "wof:name":"Hyper Formance Inc",
    "wof:placetype":"venue"
},
  "geometry": {"coordinates":[-77.579474,37.651291],"type":"Point"}
}