{
  "type": "Feature",
  "properties": {
    "addr:full":"119 W York St Norfolk VA 23510",
    "addr:housenumber":"119",
    "addr:postcode":"23510",
    "addr:street":"W York St",
    "iso:country":"US",
    "sg:address":"119 W York St",
    "sg:city":"Norfolk",
    "sg:classifiers":[
        {
            "category":"Professional",
            "subcategory":"Accounting & Tax Preparation",
            "type":"Services"
        }
    ],
    "sg:phone":"+1 757 625 1010",
    "sg:postcode":"23510",
    "sg:province":"VA",
    "wof:name":"Eileen K Shannon CPA",
    "wof:placetype":"venue"
},
  "geometry": {"coordinates":[-76.292153,36.853573],"type":"Point"}
}