{
  "type": "Feature",
  "properties": {
    "iso:country":"US",
    "sg:address":"12919 Clifton Creek Dr",
    "sg:city":"Clifton",
    "sg:classifiers":[
        {
            "category":"Building & Trades",
            "subcategory":"Electrical",
            "type":"Services"
        }
    ],
    "sg:phone":"+1 703 631 0077",
    "sg:postcode":"20124",
    "sg:province":"VA",
    "sg:tags":[
        "electrical",
        "contractor"
    ],
    "wof:name":"Maxine C Thompson",
    "wof:placetype":"venue"
},
  "geometry": {"coordinates":[-77.39884600000001,38.784877],"type":"Point"}
}