{
  "type": "Feature",
  "properties": {
    "iso:country":"US",
    "sg:address":"2146 W Mercury Blvd",
    "sg:city":"Hampton",
    "sg:classifiers":[
        {
            "category":"Utilities",
            "subcategory":"Mobile Phone",
            "type":"Services"
        }
    ],
    "sg:phone":"+1 757 262 0575",
    "sg:postcode":"23666",
    "sg:province":"VA",
    "sg:tags":[
        "telephone",
        "cellular"
    ],
    "wof:name":"Sprint",
    "wof:placetype":"venue"
},
  "geometry": {"coordinates":[-76.40054000000001,37.039293],"type":"Point"}
}