{
  "type": "Feature",
  "properties": {
    "addr:full":"3976 Seminary Rd Alexandria VA 22304",
    "addr:housenumber":"3976",
    "addr:postcode":"22304",
    "addr:street":"Seminary Rd",
    "iso:country":"US",
    "sg:address":"3976 Seminary Rd",
    "sg:city":"Alexandria",
    "sg:classifiers":[
        {
            "category":"Shopping",
            "subcategory":"Pets & Pet Supplies",
            "type":"Retail Goods"
        }
    ],
    "sg:phone":"+1 703 915 3635",
    "sg:postcode":"22304",
    "sg:province":"VA",
    "sg:tags":[
        "training"
    ],
    "wof:name":"Merit Puppy Training, L.C.",
    "wof:placetype":"venue"
},
  "geometry": {"coordinates":[-77.09682599999999,38.821532],"type":"Point"}
}