{
  "type": "Feature",
  "properties": {
    "addr:full":"115 Wolfe St Winchester VA 22601",
    "addr:housenumber":"115",
    "addr:postcode":"22601",
    "addr:street":"Wolfe St",
    "iso:country":"US",
    "sg:address":"115 Wolfe St",
    "sg:city":"Winchester",
    "sg:classifiers":[
        {
            "category":"Place Of Worship",
            "subcategory":"Church",
            "type":"Public Place"
        }
    ],
    "sg:phone":"+1 540 667 3366",
    "sg:postcode":"22601",
    "sg:province":"VA",
    "sg:tags":[
        "churches-methodist"
    ],
    "sg:website":"http://www.braddockstreetumc.org",
    "wof:name":"Braddock Street Methodist",
    "wof:placetype":"venue"
},
  "geometry": {"coordinates":[-78.16825900000001,39.183601],"type":"Point"}
}