{
  "type": "Feature",
  "properties": {
    "addr:full":"13804 Rock Ter Centreville VA 20120",
    "addr:housenumber":"13804",
    "addr:postcode":"20120",
    "addr:street":"Rock Ter",
    "iso:country":"US",
    "sg:address":"13804 Rock Ter",
    "sg:city":"Centreville",
    "sg:classifiers":[
        {
            "category":"Insurance",
            "subcategory":"Insurance Agent",
            "type":"Services"
        }
    ],
    "sg:phone":"+1 703 449 0047",
    "sg:postcode":"20120",
    "sg:province":"VA",
    "wof:name":"Nase",
    "wof:placetype":"venue"
},
  "geometry": {"coordinates":[-77.424138,38.846769],"type":"Point"}
}