{
  "type": "Feature",
  "properties": {
    "addr:full":"536 Heather Rd Danville VA 24541",
    "addr:housenumber":"536",
    "addr:postcode":"24541",
    "addr:street":"Heather Rd",
    "iso:country":"US",
    "sg:address":"536 Heather Rd",
    "sg:city":"Danville",
    "sg:classifiers":[
        {
            "category":"Building & Trades",
            "subcategory":"Landscaping Services",
            "type":"Services"
        }
    ],
    "sg:phone":"+1 434 797 9933",
    "sg:postcode":"24541",
    "sg:province":"VA",
    "wof:name":"Hoskins Jeffrey",
    "wof:placetype":"venue"
},
  "geometry": {"coordinates":[-79.441918,36.548841],"type":"Point"}
}