{
  "type": "Feature",
  "properties": {
    "addr:full":"4742 Robin Hood Rd Norfolk VA 23513",
    "addr:housenumber":"4742",
    "addr:postcode":"23513",
    "addr:street":"Robin Hood Rd",
    "iso:country":"US",
    "sg:address":"4742 Robin Hood Rd",
    "sg:city":"Norfolk",
    "sg:classifiers":[
        {
            "category":"Building & Trades",
            "subcategory":"Plumbing",
            "type":"Services"
        }
    ],
    "sg:phone":"+1 757 853 2025",
    "sg:postcode":"23513",
    "sg:province":"VA",
    "sg:tags":[
        "contractor"
    ],
    "wof:name":"Moose Mechanical Maint Svc",
    "wof:placetype":"venue"
},
  "geometry": {"coordinates":[-76.23370300000001,36.878105],"type":"Point"}
}