{
  "type": "Feature",
  "properties": {
    "addr:full":"1529 E Parham Rd Richmond VA 23228",
    "addr:housenumber":"1529",
    "addr:postcode":"23228",
    "addr:street":"E Parham Rd",
    "iso:country":"US",
    "sg:address":"1529 E Parham Rd",
    "sg:city":"Richmond",
    "sg:classifiers":[
        {
            "category":"Restaurant",
            "type":"Food & Drink"
        }
    ],
    "sg:phone":"+1 804 285 3294",
    "sg:postcode":"23228",
    "sg:province":"VA",
    "wof:name":"Hardee's",
    "wof:placetype":"venue"
},
  "geometry": {"coordinates":[-77.474341,37.638605],"type":"Point"}
}