{
  "type": "Feature",
  "properties": {
    "addr:full":"2519 Doverhill Ct Woodbridge VA 22192",
    "addr:housenumber":"2519",
    "addr:postcode":"22192",
    "addr:street":"Doverhill Ct",
    "iso:country":"US",
    "sg:address":"2519 Doverhill Ct",
    "sg:city":"Woodbridge",
    "sg:classifiers":[
        {
            "category":"Professional",
            "type":"Services"
        }
    ],
    "sg:phone":"+1 703 497 8880",
    "sg:postcode":"22192",
    "sg:province":"VA",
    "wof:name":"Hatim Suliman",
    "wof:placetype":"venue"
},
  "geometry": {"coordinates":[-77.287795,38.683088],"type":"Point"}
}