{
  "type": "Feature",
  "properties": {
    "addr:full":"1005 48th St Newport News VA 23607",
    "addr:housenumber":"1005",
    "addr:postcode":"23607",
    "addr:street":"48Th St",
    "iso:country":"US",
    "sg:address":"1005 48th St",
    "sg:city":"Newport News",
    "sg:classifiers":[
        {
            "category":"Freight",
            "type":"Transportation"
        }
    ],
    "sg:phone":"+1 757 380 6034",
    "sg:postcode":"23607",
    "sg:province":"VA",
    "sg:tags":[
        "arrangement"
    ],
    "wof:name":"Veridyne Inc",
    "wof:placetype":"venue"
},
  "geometry": {"coordinates":[-76.418447,37.000872],"type":"Point"}
}