{
  "type": "Feature",
  "properties": {
    "iso:country":"US",
    "sg:address":"105 Ship Point Rd",
    "sg:city":"Yorktown",
    "sg:classifiers":[
        {
            "category":"Building & Trades",
            "subcategory":"Construction",
            "type":"Services"
        }
    ],
    "sg:phone":"+1 757 898 9392",
    "sg:postcode":"23692",
    "sg:province":"VA",
    "sg:tags":[
        "contractor"
    ],
    "wof:name":"Upright Homes",
    "wof:placetype":"venue"
},
  "geometry": {"coordinates":[-76.422507,37.171114],"type":"Point"}
}