{
  "type": "Feature",
  "properties": {
    "addr:full":"500 Commerce Rd Richmond VA 23224",
    "addr:housenumber":"500",
    "addr:postcode":"23224",
    "addr:street":"Commerce Rd",
    "iso:country":"US",
    "sg:address":"500 Commerce Rd",
    "sg:city":"Richmond",
    "sg:classifiers":[
        {
            "category":"Wholesale",
            "subcategory":"Auto Parts",
            "type":"Manufacturing & Wholesale Goods"
        }
    ],
    "sg:phone":"+1 804 233 8321",
    "sg:postcode":"23224",
    "sg:province":"VA",
    "sg:tags":[
        "equipment",
        "truck"
    ],
    "wof:name":"Standard Parts Corp",
    "wof:placetype":"venue"
},
  "geometry": {"coordinates":[-77.43694000000001,37.517345],"type":"Point"}
}