{
  "type": "Feature",
  "properties": {
    "iso:country":"US",
    "sg:address":"4634 Old Princess Anne Rd",
    "sg:city":"Virginia Beach",
    "sg:classifiers":[
        {
            "category":"Professional",
            "subcategory":"Business Services",
            "type":"Services"
        }
    ],
    "sg:phone":"+1 757 467 4391",
    "sg:postcode":"23462",
    "sg:province":"VA",
    "sg:tags":[
        "transportation"
    ],
    "wof:name":"Akorn Automotive Appraisals",
    "wof:placetype":"venue"
},
  "geometry": {"coordinates":[-76.138848,36.809819],"type":"Point"}
}