{
  "type": "Feature",
  "properties": {
    "addr:full":"4551 Cox Rd Glen Allen VA 23060",
    "addr:housenumber":"4551",
    "addr:postcode":"23060",
    "addr:street":"Cox Rd",
    "iso:country":"US",
    "sg:address":"4551 Cox Rd",
    "sg:city":"Glen Allen",
    "sg:classifiers":[
        {
            "category":"Restaurant",
            "type":"Food & Drink"
        }
    ],
    "sg:phone":"+1 804 273 1993",
    "sg:postcode":"23060",
    "sg:province":"VA",
    "wof:name":"Innsbrook Cafe",
    "wof:placetype":"venue"
},
  "geometry": {"coordinates":[-77.57469399999999,37.660531],"type":"Point"}
}