{
  "type": "Feature",
  "properties": {
    "iso:country":"US",
    "sg:address":"300 2nd St NE",
    "sg:city":"Charlottesville",
    "sg:classifiers":[
        {
            "category":"Professional",
            "type":"Services"
        }
    ],
    "sg:phone":"+1 434 293 7335",
    "sg:postcode":"22902",
    "sg:province":"VA",
    "wof:name":"Accident Recovery PC",
    "wof:placetype":"venue"
},
  "geometry": {"coordinates":[-78.479731,38.032769],"type":"Point"}
}