{
  "type": "Feature",
  "properties": {
    "addr:full":"46463 Saffron Ct Sterling VA 20165",
    "addr:housenumber":"46463",
    "addr:postcode":"20165",
    "addr:street":"Saffron Ct",
    "iso:country":"US",
    "sg:address":"46463 Saffron Ct",
    "sg:city":"Sterling",
    "sg:classifiers":[
        {
            "category":"Building & Trades",
            "subcategory":"Construction",
            "type":"Services"
        }
    ],
    "sg:phone":"+1 703 430 7949",
    "sg:postcode":"20165",
    "sg:province":"VA",
    "sg:tags":[
        "installation",
        "furniture"
    ],
    "wof:name":"Rab Installations",
    "wof:placetype":"venue"
},
  "geometry": {"coordinates":[-77.392516,39.038852],"type":"Point"}
}