{
  "type": "Feature",
  "properties": {
    "addr:full":"10111 Oxford Ct Nokesville VA 20181",
    "addr:housenumber":"10111",
    "addr:postcode":"20181",
    "addr:street":"Oxford Ct",
    "iso:country":"US",
    "sg:address":"10111 Oxford Ct",
    "sg:city":"Nokesville",
    "sg:classifiers":[
        {
            "category":"Professional",
            "subcategory":"Computer Services",
            "type":"Services"
        }
    ],
    "sg:phone":"+1 703 335 9827",
    "sg:postcode":"20181",
    "sg:province":"VA",
    "sg:tags":[
        "datum"
    ],
    "wof:name":"Databasics",
    "wof:placetype":"venue"
},
  "geometry": {"coordinates":[-77.507124,38.683505],"type":"Point"}
}