{
  "type": "Feature",
  "properties": {
    "addr:full":"326 Glenpark Ln Midlothian VA 23114",
    "addr:housenumber":"326",
    "addr:postcode":"23114",
    "addr:street":"Glenpark Ln",
    "iso:country":"US",
    "sg:address":"326 Glenpark Ln",
    "sg:city":"Midlothian",
    "sg:classifiers":[
        {
            "category":"Real Estate",
            "subcategory":"Real Estate Agent",
            "type":"Services"
        }
    ],
    "sg:phone":"+1 804 276 0000",
    "sg:postcode":"23114",
    "sg:province":"VA",
    "wof:name":"First Real Estate Store Inc",
    "wof:placetype":"venue"
},
  "geometry": {"coordinates":[-77.64071199999999,37.49498],"type":"Point"}
}