{
  "type": "Feature",
  "properties": {
    "addr:full":"930 E Little Creek Rd Norfolk VA 23518",
    "addr:housenumber":"930",
    "addr:postcode":"23518",
    "addr:street":"E Little Creek Rd",
    "iso:country":"US",
    "sg:address":"930 E Little Creek Rd",
    "sg:city":"Norfolk",
    "sg:classifiers":[
        {
            "category":"Autos & Motor Vehicles",
            "subcategory":"Automobile Sales",
            "type":"Retail Goods"
        }
    ],
    "sg:phone":"+1 757 588 0420",
    "sg:postcode":"23518",
    "sg:province":"VA",
    "sg:tags":[
        "used"
    ],
    "wof:name":"G & H Sales",
    "wof:placetype":"venue"
},
  "geometry": {"coordinates":[-76.243633,36.914778],"type":"Point"}
}