{
  "type": "Feature",
  "properties": {
    "addr:full":"47310 Rock Falls Ter Sterling VA 20165",
    "addr:housenumber":"47310",
    "addr:postcode":"20165",
    "addr:street":"Rock Falls Ter",
    "iso:country":"US",
    "sg:address":"47310 Rock Falls Ter",
    "sg:city":"Sterling",
    "sg:classifiers":[
        {
            "category":"Professional",
            "subcategory":"Business Services",
            "type":"Services"
        }
    ],
    "sg:phone":"+1 703 444 4351",
    "sg:postcode":"20165",
    "sg:province":"VA",
    "sg:tags":[
        "fund",
        "promotion",
        "raising"
    ],
    "wof:name":"Navarro Productions",
    "wof:placetype":"venue"
},
  "geometry": {"coordinates":[-77.361981,39.043369],"type":"Point"}
}