{
  "type": "Feature",
  "properties": {
    "addr:full":"6522 Richmond Rd Williamsburg VA 23188",
    "addr:housenumber":"6522",
    "addr:postcode":"23188",
    "addr:street":"Richmond Rd",
    "iso:country":"US",
    "sg:address":"6522 Richmond Rd",
    "sg:city":"Williamsburg",
    "sg:classifiers":[
        {
            "category":"Utilities",
            "subcategory":"Mobile Phone",
            "type":"Services"
        }
    ],
    "sg:phone":"+1 757 565 2275",
    "sg:postcode":"23188",
    "sg:province":"VA",
    "sg:tags":[
        "communication",
        "cellular",
        "telephone",
        "merchandise",
        "radiotelephone"
    ],
    "wof:name":"Alltel",
    "wof:placetype":"venue"
},
  "geometry": {"coordinates":[-76.755736,37.342135],"type":"Point"}
}