{
  "type": "Feature",
  "properties": {
    "addr:full":"7373 Miramar Dr Manassas VA 20109",
    "addr:housenumber":"7373",
    "addr:postcode":"20109",
    "addr:street":"Miramar Dr",
    "iso:country":"US",
    "sg:address":"7373 Miramar Dr",
    "sg:city":"Manassas",
    "sg:classifiers":[
        {
            "category":"Building & Trades",
            "subcategory":"Construction",
            "type":"Services"
        },
        {
            "category":"Home & Garden",
            "subcategory":"Carpets & Floor Coverings",
            "type":"Retail Goods"
        }
    ],
    "sg:phone":"+1 703 257 0800",
    "sg:postcode":"20109",
    "sg:province":"VA",
    "sg:tags":[
        "installs",
        "furniture",
        "dealer",
        "rug"
    ],
    "wof:name":"Floors & Home Design Inc",
    "wof:placetype":"venue"
},
  "geometry": {"coordinates":[-77.519662,38.795303],"type":"Point"}
}