{
  "type": "Feature",
  "properties": {
    "addr:full":"100 Quail Ridge Dr Altavista VA 24517",
    "addr:housenumber":"100",
    "addr:postcode":"24517",
    "addr:street":"Quail Ridge Dr",
    "iso:country":"US",
    "sg:address":"100 Quail Ridge Dr",
    "sg:city":"Altavista",
    "sg:classifiers":[
        {
            "category":"Banks & Credit Unions",
            "subcategory":"Investment Brokerage",
            "type":"Services"
        }
    ],
    "sg:phone":"+1 434 369 1954",
    "sg:postcode":"24517",
    "sg:province":"VA",
    "wof:name":"G/M Investments Inc",
    "wof:placetype":"venue"
},
  "geometry": {"coordinates":[-79.31408999999999,37.128],"type":"Point"}
}