{
  "type": "Feature",
  "properties": {
    "addr:full":"1101 Potomac Ave Fredericksburg VA 22405",
    "addr:housenumber":"1101",
    "addr:postcode":"22405",
    "addr:street":"Potomac Ave",
    "iso:country":"US",
    "sg:address":"1101 Potomac Ave",
    "sg:city":"Fredericksburg",
    "sg:classifiers":[
        {
            "category":"Autos & Motor Vehicles",
            "subcategory":"Auto Supplies",
            "type":"Retail Goods"
        }
    ],
    "sg:phone":"+1 540 372 1442",
    "sg:postcode":"22405",
    "sg:province":"VA",
    "sg:tags":[
        "tire"
    ],
    "wof:name":"Pro-Trucks",
    "wof:placetype":"venue"
},
  "geometry": {"coordinates":[-77.434527,38.311465],"type":"Point"}
}