{
  "type": "Feature",
  "properties": {
    "addr:full":"8128 Mechanicsville Tpke Mechanicsville VA 23111",
    "addr:housenumber":"8128",
    "addr:postcode":"23111",
    "addr:street":"Mechanicsville Tpke",
    "iso:country":"US",
    "sg:address":"8128 Mechanicsville Tpke",
    "sg:city":"Mechanicsville",
    "sg:classifiers":[
        {
            "category":"Manufacturing",
            "subcategory":"Building Materials",
            "type":"Manufacturing & Wholesale Goods"
        },
        {
            "category":"Home & Garden",
            "subcategory":"Carpets & Floor Coverings",
            "type":"Retail Goods"
        }
    ],
    "sg:phone":"+1 804 730 3500",
    "sg:postcode":"23111",
    "sg:province":"VA",
    "sg:tags":[
        "materials-wholesale",
        "installation",
        "rug",
        "manufacturer"
    ],
    "wof:name":"Hanover Carpet & Vinyl Shop",
    "wof:placetype":"venue"
},
  "geometry": {"coordinates":[-77.377968,37.599239],"type":"Point"}
}