{
  "type": "Feature",
  "properties": {
    "addr:full":"617 Warren Ave Chesapeake VA 23322",
    "addr:housenumber":"617",
    "addr:postcode":"23322",
    "addr:street":"Warren Ave",
    "iso:country":"US",
    "sg:address":"617 Warren Ave",
    "sg:city":"Chesapeake",
    "sg:classifiers":[
        {
            "category":"Shopping",
            "subcategory":"Antiques",
            "type":"Retail Goods"
        }
    ],
    "sg:phone":"+1 757 482 9414",
    "sg:postcode":"23322",
    "sg:province":"VA",
    "wof:name":"Kos Classics",
    "wof:placetype":"venue"
},
  "geometry": {"coordinates":[-76.224216,36.703506],"type":"Point"}
}