{
  "type": "Feature",
  "properties": {
    "iso:country":"US",
    "sg:address":"410 N 1st St",
    "sg:city":"Richmond",
    "sg:classifiers":[
        {
            "category":"Retail",
            "subcategory":"Laundry & Dry Cleaning",
            "type":"Services"
        }
    ],
    "sg:phone":"+1 804 643 0331",
    "sg:postcode":"23219",
    "sg:province":"VA",
    "sg:tags":[
        "cleaners"
    ],
    "wof:name":"Moizelles Cleaners & Launderer",
    "wof:placetype":"venue"
},
  "geometry": {"coordinates":[-77.439547,37.546778],"type":"Point"}
}