{
  "type": "Feature",
  "properties": {
    "iso:country":"US",
    "sg:address":"3232 Academy Ave",
    "sg:city":"Portsmouth",
    "sg:classifiers":[
        {
            "category":"Education",
            "subcategory":"Dance Studio",
            "type":"Public Place"
        }
    ],
    "sg:phone":"+1 757 686 2900",
    "sg:postcode":"23703",
    "sg:province":"VA",
    "wof:name":"Jazzin With Vicky",
    "wof:placetype":"venue"
},
  "geometry": {"coordinates":[-76.397222,36.863145],"type":"Point"}
}