{
  "type": "Feature",
  "properties": {
    "addr:full":"100 N 8th St Richmond VA 23219",
    "addr:housenumber":"100",
    "addr:postcode":"23219",
    "addr:street":"N 8Th St",
    "iso:country":"US",
    "sg:address":"100 N 8th St",
    "sg:city":"Richmond",
    "sg:classifiers":[
        {
            "category":"Food & Beverages",
            "subcategory":"Groceries & Convenience Stores",
            "type":"Retail Goods"
        },
        {
            "category":"Restaurant",
            "type":"Food & Drink"
        }
    ],
    "sg:phone":"+1 804 643 3354",
    "sg:postcode":"23219",
    "sg:province":"VA",
    "sg:tags":[
        "delicatessen"
    ],
    "wof:name":"Wall Street Deli The",
    "wof:placetype":"venue"
},
  "geometry": {"coordinates":[-77.43556599999999,37.540466],"type":"Point"}
}