{
  "type": "Feature",
  "properties": {
    "addr:full":"1748 W Clara Dr Petersburg VA 23803",
    "addr:housenumber":"1748",
    "addr:postcode":"23803",
    "addr:street":"W Clara Dr",
    "iso:country":"US",
    "sg:address":"1748 W Clara Dr",
    "sg:city":"Petersburg",
    "sg:classifiers":[
        {
            "category":"Building & Trades",
            "subcategory":"Electrical",
            "type":"Services"
        }
    ],
    "sg:phone":"+1 804 733 0063",
    "sg:postcode":"23803",
    "sg:province":"VA",
    "sg:tags":[
        "electrical",
        "contractor"
    ],
    "wof:name":"Dance Electric",
    "wof:placetype":"venue"
},
  "geometry": {"coordinates":[-77.41544500000001,37.202543],"type":"Point"}
}