{
  "type": "Feature",
  "properties": {
    "iso:country":"US",
    "sg:address":"12801 Clementown Rd",
    "sg:city":"Amelia Court House",
    "sg:classifiers":[
        {
            "category":"Building & Trades",
            "subcategory":"Construction",
            "type":"Services"
        }
    ],
    "sg:phone":"+1 804 561 6329",
    "sg:postcode":"23002",
    "sg:province":"VA",
    "sg:tags":[
        "house"
    ],
    "wof:name":"In Sweeneys Construction",
    "wof:placetype":"venue"
},
  "geometry": {"coordinates":[-78.06596399999999,37.402474],"type":"Point"}
}