{
  "type": "Feature",
  "properties": {
    "addr:full":"300 W Freemason St Norfolk VA 23510",
    "addr:housenumber":"300",
    "addr:postcode":"23510",
    "addr:street":"W Freemason St",
    "iso:country":"US",
    "sg:address":"300 W Freemason St",
    "sg:city":"Norfolk",
    "sg:classifiers":[
        {
            "category":"Wholesale",
            "subcategory":"Furniture",
            "type":"Manufacturing & Wholesale Goods"
        }
    ],
    "sg:phone":"+1 757 627 6391",
    "sg:postcode":"23510",
    "sg:province":"VA",
    "wof:name":"Open Plan Systems",
    "wof:placetype":"venue"
},
  "geometry": {"coordinates":[-76.29382,36.852137],"type":"Point"}
}