{
  "type": "Feature",
  "properties": {
    "iso:country":"US",
    "sg:address":"1005 May Ave",
    "sg:city":"Norfolk",
    "sg:classifiers":[
        {
            "category":"Health Services",
            "subcategory":"Doctor",
            "type":"Services"
        }
    ],
    "sg:phone":"+1 757 623 2123",
    "sg:postcode":"23504",
    "sg:province":"VA",
    "sg:tags":[
        "ophthalmologist"
    ],
    "wof:name":"Cauthen Cherly G",
    "wof:placetype":"venue"
},
  "geometry": {"coordinates":[-76.270641,36.855588],"type":"Point"}
}