{
  "type": "Feature",
  "properties": {
    "iso:country":"US",
    "sg:address":"133 S Washington St",
    "sg:city":"Falls Church",
    "sg:classifiers":[
        {
            "category":"Banks & Credit Unions",
            "subcategory":"Bank",
            "type":"Services"
        }
    ],
    "sg:phone":"+1 703 536 2644",
    "sg:postcode":"22046",
    "sg:province":"VA",
    "wof:name":"First Horizon Financial Ctr",
    "wof:placetype":"venue"
},
  "geometry": {"coordinates":[-77.17174199999999,38.881506],"type":"Point"}
}