{
  "type": "Feature",
  "properties": {
    "addr:full":"1421 Prince St Ste 410 Alexandria VA 22314",
    "addr:housenumber":"1421",
    "addr:postcode":"22314",
    "addr:street":"Prince St Ste 410",
    "iso:country":"US",
    "sg:address":"1421 Prince St Ste 410",
    "sg:city":"Alexandria",
    "sg:classifiers":[
        {
            "category":"Bus Charters",
            "type":"Transportation"
        }
    ],
    "sg:phone":"+1 703 836 8884",
    "sg:postcode":"22314",
    "sg:province":"VA",
    "sg:tags":[
        "buses-charter",
        "rental"
    ],
    "wof:name":"Common Ground Alliance",
    "wof:placetype":"venue"
},
  "geometry": {"coordinates":[-77.05552299999999,38.805005],"type":"Point"}
}