{
  "type": "Feature",
  "properties": {
    "iso:country":"US",
    "sg:address":"1230 Alverser Dr",
    "sg:city":"Midlothian",
    "sg:classifiers":[
        {
            "category":"Health Services",
            "subcategory":"Doctor",
            "type":"Services"
        }
    ],
    "sg:phone":"+1 804 897 9800",
    "sg:postcode":"23113",
    "sg:province":"VA",
    "wof:name":"Stephen F Tuttle DDS",
    "wof:placetype":"venue"
},
  "geometry": {"coordinates":[-77.616906,37.508223],"type":"Point"}
}