{
  "type": "Feature",
  "properties": {
    "addr:full":"4730 Business Dr Fredericksburg VA 22408",
    "addr:housenumber":"4730",
    "addr:postcode":"22408",
    "addr:street":"Business Dr",
    "iso:country":"US",
    "sg:address":"4730 Business Dr",
    "sg:city":"Fredericksburg",
    "sg:classifiers":[
        {
            "category":"Wholesale",
            "subcategory":"Electrical",
            "type":"Manufacturing & Wholesale Goods"
        }
    ],
    "sg:phone":"+1 540 898 9100",
    "sg:postcode":"22408",
    "sg:province":"VA",
    "sg:tags":[
        "equipment"
    ],
    "wof:name":"Rexel Inc",
    "wof:placetype":"venue"
},
  "geometry": {"coordinates":[-77.495389,38.247723],"type":"Point"}
}