{
  "type": "Feature",
  "properties": {
    "addr:full":"301 Concourse Blvd Glen Allen VA 23059",
    "addr:housenumber":"301",
    "addr:postcode":"23059",
    "addr:street":"Concourse Blvd",
    "iso:country":"US",
    "sg:address":"301 Concourse Blvd",
    "sg:city":"Glen Allen",
    "sg:classifiers":[
        {
            "category":"Professional",
            "subcategory":"Business Services",
            "type":"Services"
        }
    ],
    "sg:phone":"+1 804 273 0700",
    "sg:postcode":"23059",
    "sg:province":"VA",
    "wof:name":"Energy Systems Group",
    "wof:placetype":"venue"
},
  "geometry": {"coordinates":[-77.590597,37.687902],"type":"Point"}
}