{
  "type": "Feature",
  "properties": {
    "iso:country":"US",
    "sg:address":"4560 South Blvd",
    "sg:city":"Virginia Beach",
    "sg:classifiers":[
        {
            "category":"Professional",
            "type":"Services"
        }
    ],
    "sg:phone":"+1 757 490 2465",
    "sg:postcode":"23452",
    "sg:province":"VA",
    "sg:website":"www.swissport.com",
    "wof:name":"Swissport Cfe Inc",
    "wof:placetype":"venue"
},
  "geometry": {"coordinates":[-76.133135,36.832915],"type":"Point"}
}