{
  "type": "Feature",
  "properties": {
    "iso:country":"US",
    "sg:address":"5462 Germanna Hwy",
    "sg:city":"Locust Grove",
    "sg:classifiers":[
        {
            "category":"Government",
            "subcategory":"Post Office",
            "type":"Public Place"
        }
    ],
    "sg:phone":"+1 540 000 1111",
    "sg:postcode":"22508",
    "sg:province":"VA",
    "wof:name":"US Post Office",
    "wof:placetype":"venue"
},
  "geometry": {"coordinates":[-77.728374,38.326016],"type":"Point"}
}