{
  "type": "Feature",
  "properties": {
    "addr:full":"820 Yorkshire Trl Chesapeake VA 23322",
    "addr:housenumber":"820",
    "addr:postcode":"23322",
    "addr:street":"Yorkshire Trl",
    "iso:country":"US",
    "sg:address":"820 Yorkshire Trl",
    "sg:city":"Chesapeake",
    "sg:classifiers":[
        {
            "category":"Professional",
            "type":"Services"
        }
    ],
    "sg:phone":"+1 757 546 0993",
    "sg:postcode":"23322",
    "sg:province":"VA",
    "wof:name":"Words & Ideas Unlimited",
    "wof:placetype":"venue"
},
  "geometry": {"coordinates":[-76.257717,36.690897],"type":"Point"}
}