{
  "type": "Feature",
  "properties": {
    "iso:country":"US",
    "sg:address":"1003 N 20th St",
    "sg:city":"Richmond",
    "sg:classifiers":[
        {
            "category":"Shopping",
            "subcategory":"Clothing, Apparel, & Fashions",
            "type":"Retail Goods"
        }
    ],
    "sg:phone":"+1 804 726 5770",
    "sg:postcode":"23223",
    "sg:province":"VA",
    "sg:tags":[
        "family"
    ],
    "wof:name":"L & S Clothing",
    "wof:placetype":"venue"
},
  "geometry": {"coordinates":[-77.416663,37.541288],"type":"Point"}
}