{
  "type": "Feature",
  "properties": {
    "addr:full":"11215 Lee Hwy Fairfax VA 22030",
    "addr:housenumber":"11215",
    "addr:postcode":"22030",
    "addr:street":"Lee Hwy",
    "iso:country":"US",
    "sg:address":"11215 Lee Hwy",
    "sg:city":"Fairfax",
    "sg:classifiers":[
        {
            "category":"Manufacturing",
            "subcategory":"Signs",
            "type":"Manufacturing & Wholesale Goods"
        }
    ],
    "sg:phone":"+1 703 591 1211",
    "sg:postcode":"22030",
    "sg:province":"VA",
    "sg:tags":[
        "computerized",
        "making"
    ],
    "wof:name":"Custom Signs Today",
    "wof:placetype":"venue"
},
  "geometry": {"coordinates":[-77.335227,38.851275],"type":"Point"}
}