{
  "type": "Feature",
  "properties": {
    "addr:full":"5804 Brandon Hill Loop Haymarket VA 20169",
    "addr:housenumber":"5804",
    "addr:postcode":"20169",
    "addr:street":"Brandon Hill Loop",
    "iso:country":"US",
    "sg:address":"5804 Brandon Hill Loop",
    "sg:city":"Haymarket",
    "sg:classifiers":[
        {
            "category":"Professional",
            "subcategory":"Management & Consulting",
            "type":"Services"
        }
    ],
    "sg:phone":"+1 703 754 1958",
    "sg:postcode":"20169",
    "sg:province":"VA",
    "sg:tags":[
        "business"
    ],
    "wof:name":"Snyder Enterprises",
    "wof:placetype":"venue"
},
  "geometry": {"coordinates":[-77.61407699999999,38.820919],"type":"Point"}
}