{
  "type": "Feature",
  "properties": {
    "addr:full":"1014 Mount Olive Rd Toms Brook VA 22660",
    "addr:housenumber":"1014",
    "addr:postcode":"22660",
    "addr:street":"Mount Olive Rd",
    "iso:country":"US",
    "sg:address":"1014 Mount Olive Rd",
    "sg:city":"Toms Brook",
    "sg:classifiers":[
        {
            "category":"Autos & Motor Vehicles",
            "subcategory":"Fuel & Gas Station",
            "type":"Retail Goods"
        }
    ],
    "sg:phone":"+1 540 436 3277",
    "sg:postcode":"22660",
    "sg:province":"VA",
    "sg:tags":[
        "grocery",
        "gasoline",
        "petroleum",
        "bulk",
        "s",
        "station"
    ],
    "sg:website":"www.wilcohess.com",
    "wof:name":"Dairy Queen",
    "wof:placetype":"venue"
},
  "geometry": {"coordinates":[-78.440574,38.967404],"type":"Point"}
}