{
  "type": "Feature",
  "properties": {
    "addr:full":"598 Goode Mountain Ln Rocky Mount VA 24151",
    "addr:housenumber":"598",
    "addr:postcode":"24151",
    "addr:street":"Goode Mountain Ln",
    "iso:country":"US",
    "sg:address":"598 Goode Mountain Ln",
    "sg:city":"Rocky Mount",
    "sg:classifiers":[
        {
            "category":"Food & Beverages",
            "subcategory":"Groceries & Convenience Stores",
            "type":"Retail Goods"
        }
    ],
    "sg:phone":"+1 540 489 5436",
    "sg:postcode":"24151",
    "sg:province":"VA",
    "wof:name":"Crystal Arant",
    "wof:placetype":"venue"
},
  "geometry": {"coordinates":[-79.786845,36.875234],"type":"Point"}
}