{
  "type": "Feature",
  "properties": {
    "addr:full":"543 Jefferson Davis Hwy Fredericksburg VA 22401",
    "addr:housenumber":"543",
    "addr:postcode":"22401",
    "addr:street":"Jefferson Davis Hwy",
    "iso:country":"US",
    "sg:address":"543 Jefferson Davis Hwy",
    "sg:city":"Fredericksburg",
    "sg:classifiers":[
        {
            "category":"Restaurant",
            "type":"Food & Drink"
        }
    ],
    "sg:phone":"+1 540 368 1937",
    "sg:postcode":"22401",
    "sg:province":"VA",
    "wof:name":"Burger Busters",
    "wof:placetype":"venue"
},
  "geometry": {"coordinates":[-77.475621,38.313084],"type":"Point"}
}