{
  "type": "Feature",
  "properties": {
    "addr:full":"2906 Meadow Ln Falls Church VA 22042",
    "addr:housenumber":"2906",
    "addr:postcode":"22042",
    "addr:street":"Meadow Ln",
    "iso:country":"US",
    "sg:address":"2906 Meadow Ln",
    "sg:city":"Falls Church",
    "sg:classifiers":[
        {
            "category":"Building & Trades",
            "subcategory":"Construction",
            "type":"Services"
        }
    ],
    "sg:phone":"+1 703 241 0198",
    "sg:postcode":"22042",
    "sg:province":"VA",
    "sg:tags":[
        "contractor"
    ],
    "wof:name":"D & R Drywall",
    "wof:placetype":"venue"
},
  "geometry": {"coordinates":[-77.167698,38.873916],"type":"Point"}
}