{
  "type": "Feature",
  "properties": {
    "addr:full":"1706 Woodgrove St Chesapeake VA 23320",
    "addr:housenumber":"1706",
    "addr:postcode":"23320",
    "addr:street":"Woodgrove St",
    "iso:country":"US",
    "sg:address":"1706 Woodgrove St",
    "sg:city":"Chesapeake",
    "sg:classifiers":[
        {
            "category":"Arts & Performance",
            "subcategory":"Theater",
            "type":"Entertainment"
        }
    ],
    "sg:phone":"+1 757 382 7865",
    "sg:postcode":"23320",
    "sg:province":"VA",
    "sg:tags":[
        "musician"
    ],
    "wof:name":"Swing That Music",
    "wof:placetype":"venue"
},
  "geometry": {"coordinates":[-76.200497,36.760485],"type":"Point"}
}