{
  "type": "Feature",
  "properties": {
    "addr:full":"1401 Chain Bridge Rd Mc Lean VA 22101",
    "addr:housenumber":"1401",
    "addr:postcode":"22101",
    "addr:street":"Chain Bridge Rd Mc Lean",
    "iso:country":"US",
    "sg:address":"1401 Chain Bridge Rd",
    "sg:city":"Mc Lean",
    "sg:classifiers":[
        {
            "category":"Home & Garden",
            "subcategory":"Carpets & Floor Coverings",
            "type":"Retail Goods"
        }
    ],
    "sg:phone":"+1 703 749 0700",
    "sg:postcode":"22101",
    "sg:province":"VA",
    "sg:website":"www.bestbuycarpet.com",
    "wof:name":"Best Buy Carpet",
    "wof:placetype":"venue"
},
  "geometry": {"coordinates":[-77.175771,38.936155],"type":"Point"}
}