{
  "type": "Feature",
  "properties": {
    "iso:country":"US",
    "sg:address":"1265 Sandbridge Rd",
    "sg:city":"Virginia Beach",
    "sg:classifiers":[
        {
            "category":"Organizations",
            "subcategory":"Religious Organization",
            "type":"Services"
        }
    ],
    "sg:phone":"+1 757 426 2396",
    "sg:postcode":"23456",
    "sg:province":"VA",
    "wof:name":"Tabernacle Untd Methdst Church",
    "wof:placetype":"venue"
},
  "geometry": {"coordinates":[-75.983126,36.730962],"type":"Point"}
}