{
  "type": "Feature",
  "properties": {
    "iso:country":"US",
    "sg:address":"339 High St",
    "sg:city":"Portsmouth",
    "sg:classifiers":[
        {
            "category":"Health Services",
            "subcategory":"Hospital",
            "type":"Services"
        }
    ],
    "sg:phone":"+1 757 000 1111",
    "sg:postcode":"23704",
    "sg:province":"VA",
    "sg:tags":[
        "mental"
    ],
    "wof:name":"Mental Health Services-Prtsmth",
    "wof:placetype":"venue"
},
  "geometry": {"coordinates":[-76.3004,36.835247],"type":"Point"}
}