{
  "type": "Feature",
  "properties": {
    "addr:full":"273 Gundry Dr Falls Church VA 22046",
    "addr:housenumber":"273",
    "addr:postcode":"22046",
    "addr:street":"Gundry Dr",
    "iso:country":"US",
    "sg:address":"273 Gundry Dr",
    "sg:city":"Falls Church",
    "sg:classifiers":[
        {
            "category":"Professional",
            "subcategory":"Management & Consulting",
            "type":"Services"
        }
    ],
    "sg:phone":"+1 703 534 2919",
    "sg:postcode":"22046",
    "sg:province":"VA",
    "sg:tags":[
        "consultant",
        "cost",
        "financial"
    ],
    "wof:name":"O & M Consulting",
    "wof:placetype":"venue"
},
  "geometry": {"coordinates":[-77.17575600000001,38.882728],"type":"Point"}
}