{
  "type": "Feature",
  "properties": {
    "iso:country":"US",
    "sg:address":"2641 Dean Dr",
    "sg:city":"Virginia Beach",
    "sg:classifiers":[
        {
            "category":"Shopping",
            "subcategory":"Used Merchandise",
            "type":"Retail Goods"
        }
    ],
    "sg:phone":"+1 757 463 1911",
    "sg:postcode":"23452",
    "sg:province":"VA",
    "sg:tags":[
        "antique"
    ],
    "wof:name":"Barrett Street Auctions",
    "wof:placetype":"venue"
},
  "geometry": {"coordinates":[-76.06453399999999,36.837955],"type":"Point"}
}