{
  "type": "Feature",
  "properties": {
    "iso:country":"US",
    "sg:address":"513 Freeman Ave",
    "sg:city":"Chesapeake",
    "sg:classifiers":[
        {
            "category":"Manufacturing",
            "subcategory":"Watercraft",
            "type":"Manufacturing & Wholesale Goods"
        }
    ],
    "sg:phone":"+1 757 494 1199",
    "sg:postcode":"23324",
    "sg:province":"VA",
    "sg:tags":[
        "repair",
        "ship"
    ],
    "wof:name":"Specialty Marine Inc",
    "wof:placetype":"venue"
},
  "geometry": {"coordinates":[-76.287836,36.786574],"type":"Point"}
}