{
  "type": "Feature",
  "properties": {
    "addr:full":"12943 Grays Pointe Rd Fairfax VA 22033",
    "addr:housenumber":"12943",
    "addr:postcode":"22033",
    "addr:street":"Grays Pointe Rd",
    "iso:country":"US",
    "sg:address":"12943 Grays Pointe Rd",
    "sg:city":"Fairfax",
    "sg:classifiers":[
        {
            "category":"Professional",
            "subcategory":"Business Services",
            "type":"Services"
        }
    ],
    "sg:phone":"+1 703 263 1152",
    "sg:postcode":"22033",
    "sg:province":"VA",
    "sg:tags":[
        "information",
        "consulting",
        "technology"
    ],
    "wof:name":"Gold Line Network Services",
    "wof:placetype":"venue"
},
  "geometry": {"coordinates":[-77.393837,38.876903],"type":"Point"}
}