{
  "type": "Feature",
  "properties": {
    "iso:country":"US",
    "sg:address":"1511 Oronoco St",
    "sg:city":"Alexandria",
    "sg:classifiers":[
        {
            "category":"Building & Trades",
            "subcategory":"Construction",
            "type":"Services"
        }
    ],
    "sg:phone":"+1 703 684 6634",
    "sg:postcode":"22314",
    "sg:province":"VA",
    "sg:tags":[
        "house"
    ],
    "wof:name":"Dpo Developers LLC",
    "wof:placetype":"venue"
},
  "geometry": {"coordinates":[-77.055267,38.810878],"type":"Point"}
}