{
  "type": "Feature",
  "properties": {
    "iso:country":"US",
    "sg:address":"7401 Pocahontas Trl",
    "sg:city":"Williamsburg",
    "sg:classifiers":[
        {
            "category":"Travel",
            "subcategory":"Campground",
            "type":"Entertainment"
        }
    ],
    "sg:phone":"+1 757 229 3300",
    "sg:postcode":"23185",
    "sg:province":"VA",
    "wof:name":"Jametown Beach Campground",
    "wof:placetype":"venue"
},
  "geometry": {"coordinates":[-76.664068,37.252551],"type":"Point"}
}