{
  "type": "Feature",
  "properties": {
    "addr:full":"3006 Impala Pl Henrico VA 23228",
    "addr:housenumber":"3006",
    "addr:postcode":"23228",
    "addr:street":"Impala Pl",
    "iso:country":"US",
    "sg:address":"3006 Impala Pl",
    "sg:city":"Henrico",
    "sg:classifiers":[
        {
            "category":"Building & Trades",
            "subcategory":"Construction",
            "type":"Services"
        }
    ],
    "sg:phone":"+1 804 266 9656",
    "sg:postcode":"23228",
    "sg:province":"VA",
    "sg:tags":[
        "equipment",
        "supply",
        "drywall",
        "contractor"
    ],
    "wof:name":"Bertozzi, Incorporated, A.",
    "wof:placetype":"venue"
},
  "geometry": {"coordinates":[-77.49200399999999,37.616928],"type":"Point"}
}