{
  "type": "Feature",
  "properties": {
    "addr:full":"1830 Town Center Pkwy Reston VA 20190",
    "addr:housenumber":"1830",
    "addr:postcode":"20190",
    "addr:street":"Town Center Pkwy",
    "iso:country":"US",
    "sg:address":"1830 Town Center Pkwy",
    "sg:city":"Reston",
    "sg:classifiers":[
        {
            "category":"Health Services",
            "subcategory":"Doctor",
            "type":"Services"
        }
    ],
    "sg:phone":"+1 703 437 0800",
    "sg:postcode":"20190",
    "sg:province":"VA",
    "sg:tags":[
        "medical"
    ],
    "wof:name":"Elizabeth Atkinson MD",
    "wof:placetype":"venue"
},
  "geometry": {"coordinates":[-77.36221999999999,38.962346],"type":"Point"}
}