{
  "type": "Feature",
  "properties": {
    "addr:full":"2600 Soapstone Dr Reston VA 20191",
    "addr:housenumber":"2600",
    "addr:postcode":"20191",
    "addr:street":"Soapstone Dr",
    "iso:country":"US",
    "sg:address":"2600 Soapstone Dr",
    "sg:city":"Reston",
    "sg:classifiers":[
        {
            "category":"Professional",
            "type":"Services"
        }
    ],
    "sg:phone":"+1 703 620 6136",
    "sg:postcode":"20191",
    "sg:province":"VA",
    "wof:name":"Walton E III Bell",
    "wof:placetype":"venue"
},
  "geometry": {"coordinates":[-77.350105,38.914851],"type":"Point"}
}