{
  "type": "Feature",
  "properties": {
    "addr:full":"11408 Old Stage Rd Prince George VA 23875",
    "addr:housenumber":"11408",
    "addr:postcode":"23875",
    "addr:street":"Old Stage Rd",
    "iso:country":"US",
    "sg:address":"11408 Old Stage Rd",
    "sg:city":"Prince George",
    "sg:classifiers":[
        {
            "category":"Building & Trades",
            "subcategory":"Construction",
            "type":"Services"
        }
    ],
    "sg:phone":"+1 804 541 3895",
    "sg:postcode":"23875",
    "sg:province":"VA",
    "sg:tags":[
        "hanging",
        "contractor"
    ],
    "wof:name":"Person Painting",
    "wof:placetype":"venue"
},
  "geometry": {"coordinates":[-77.199091,37.230828],"type":"Point"}
}