{
  "type": "Feature",
  "properties": {
    "iso:country":"US",
    "sg:address":"9186 Williamsville Rd",
    "sg:city":"Mechanicsville",
    "sg:classifiers":[
        {
            "category":"Manufacturing",
            "subcategory":"Food",
            "type":"Manufacturing & Wholesale Goods"
        },
        {
            "category":"Farming",
            "subcategory":"Farm",
            "type":"Manufacturing & Wholesale Goods"
        }
    ],
    "sg:phone":"+1 804 779 2506",
    "sg:postcode":"23116",
    "sg:province":"VA",
    "sg:tags":[
        "corn",
        "product"
    ],
    "wof:name":"Talley's Farm",
    "wof:placetype":"venue"
},
  "geometry": {"coordinates":[-77.2895,37.652054],"type":"Point"}
}