{
  "type": "Feature",
  "properties": {
    "iso:country":"US",
    "sg:address":"716 Claiborne St",
    "sg:city":"Danville",
    "sg:classifiers":[
        {
            "category":"Organizations",
            "subcategory":"Religious Organization",
            "type":"Services"
        }
    ],
    "sg:phone":"+1 434 799 3671",
    "sg:postcode":"24540",
    "sg:province":"VA",
    "sg:tags":[
        "church"
    ],
    "wof:name":"Christians United Baptist Chr",
    "wof:placetype":"venue"
},
  "geometry": {"coordinates":[-79.38795,36.597874],"type":"Point"}
}