{
  "type": "Feature",
  "properties": {
    "addr:full":"23800 Thompson Ln Jetersville VA 23083",
    "addr:housenumber":"23800",
    "addr:postcode":"23083",
    "addr:street":"Thompson Ln",
    "iso:country":"US",
    "sg:address":"23800 Thompson Ln",
    "sg:city":"Jetersville",
    "sg:classifiers":[
        {
            "category":"Farming",
            "subcategory":"Dairy Farm",
            "type":"Manufacturing & Wholesale Goods"
        }
    ],
    "sg:phone":"+1 804 561 6127",
    "sg:postcode":"23083",
    "sg:province":"VA",
    "wof:name":"Mountain View Dairy",
    "wof:placetype":"venue"
},
  "geometry": {"coordinates":[-78.13247,37.275102],"type":"Point"}
}