{
  "type": "Feature",
  "properties": {
    "iso:country":"US",
    "sg:address":"7330 Mallory Ln",
    "sg:city":"Alexandria",
    "sg:classifiers":[
        {
            "category":"Professional",
            "subcategory":"Management & Consulting",
            "type":"Services"
        }
    ],
    "sg:phone":"+1 703 719 0667",
    "sg:postcode":"22315",
    "sg:province":"VA",
    "sg:tags":[
        "consultant",
        "publishing"
    ],
    "wof:name":"Congress Nita",
    "wof:placetype":"venue"
},
  "geometry": {"coordinates":[-77.14422999999999,38.759173],"type":"Point"}
}