{
  "type": "Feature",
  "properties": {
    "iso:country":"US",
    "sg:address":"116 Muirfield",
    "sg:city":"Williamsburg",
    "sg:classifiers":[
        {
            "category":"Building & Trades",
            "subcategory":"Construction",
            "type":"Services"
        }
    ],
    "sg:phone":"+1 757 258 8510",
    "sg:postcode":"23188",
    "sg:province":"VA",
    "sg:tags":[
        "contractor"
    ],
    "wof:name":"Lawrence W Kitchens Contractor",
    "wof:placetype":"venue"
},
  "geometry": {"coordinates":[-76.778944,37.294714],"type":"Point"}
}