{
  "type": "Feature",
  "properties": {
    "iso:country":"US",
    "sg:address":"150 Monroe Farm Rd",
    "sg:city":"Fredericksburg",
    "sg:classifiers":[
        {
            "category":"Retail",
            "subcategory":"Repair Shop",
            "type":"Services"
        }
    ],
    "sg:phone":"+1 540 752 2726",
    "sg:postcode":"22406",
    "sg:province":"VA",
    "sg:tags":[
        "taxidermist"
    ],
    "wof:name":"Del's Taxidermy Studio",
    "wof:placetype":"venue"
},
  "geometry": {"coordinates":[-77.563272,38.371911],"type":"Point"}
}