{
  "type": "Feature",
  "properties": {
    "iso:country":"US",
    "sg:address":"15247 Tomahawk Creek Rd",
    "sg:city":"Orange",
    "sg:classifiers":[
        {
            "category":"Social Services",
            "subcategory":"Child Care",
            "type":"Services"
        }
    ],
    "sg:phone":"+1 540 661 3330",
    "sg:postcode":"22960",
    "sg:province":"VA",
    "wof:name":"Shining Star Christian Prschl",
    "wof:placetype":"venue"
},
  "geometry": {"coordinates":[-78.109139,38.214618],"type":"Point"}
}