{
  "type": "Feature",
  "properties": {
    "addr:full":"4594 Eisenhower Ave Alexandria VA 22304",
    "addr:housenumber":"4594",
    "addr:postcode":"22304",
    "addr:street":"Eisenhower Ave",
    "iso:country":"US",
    "sg:address":"4594 Eisenhower Ave",
    "sg:city":"Alexandria",
    "sg:classifiers":[
        {
            "category":"Building & Trades",
            "subcategory":"Construction",
            "type":"Services"
        }
    ],
    "sg:phone":"+1 703 550 0165",
    "sg:postcode":"22304",
    "sg:province":"VA",
    "sg:tags":[
        "roofing",
        "general",
        "commercial",
        "contractor"
    ],
    "sg:website":"www.northeastcontracting.net",
    "wof:name":"Northeast Contracting Corp",
    "wof:placetype":"venue"
},
  "geometry": {"coordinates":[-77.112865,38.804187],"type":"Point"}
}