{
  "type": "Feature",
  "properties": {
    "iso:country":"US",
    "sg:address":"1445 Old Bridge Rd",
    "sg:city":"Woodbridge",
    "sg:classifiers":[
        {
            "category":"Food & Beverages",
            "subcategory":"Groceries & Convenience Stores",
            "type":"Retail Goods"
        }
    ],
    "sg:phone":"+1 703 494 5775",
    "sg:postcode":"22192",
    "sg:province":"VA",
    "wof:name":"7-Eleven",
    "wof:placetype":"venue"
},
  "geometry": {"coordinates":[-77.258556,38.673297],"type":"Point"}
}