{
  "type": "Feature",
  "properties": {
    "iso:country":"US",
    "sg:address":"4502 Starkey Rd",
    "sg:city":"Roanoke",
    "sg:classifiers":[
        {
            "category":"Real Estate",
            "subcategory":"Real Estate Services",
            "type":"Services"
        }
    ],
    "sg:phone":"+1 540 989 4988",
    "sg:postcode":"24018",
    "sg:province":"VA",
    "sg:tags":[
        "company",
        "title"
    ],
    "wof:name":"Southwest Title Agency LLC",
    "wof:placetype":"venue"
},
  "geometry": {"coordinates":[-79.984443,37.223803],"type":"Point"}
}