{
  "type": "Feature",
  "properties": {
    "iso:country":"US",
    "sg:address":"2050 Langhorne Rd",
    "sg:city":"Lynchburg",
    "sg:classifiers":[
        {
            "category":"Shopping",
            "type":"Retail Goods"
        }
    ],
    "sg:phone":"+1 434 528 1030",
    "sg:postcode":"24501",
    "sg:province":"VA",
    "sg:tags":[
        "orthopedic",
        "appliance"
    ],
    "wof:name":"Old Dominion Prosthetics Inc",
    "wof:placetype":"venue"
},
  "geometry": {"coordinates":[-79.18366399999999,37.413599],"type":"Point"}
}