{
  "type": "Feature",
  "properties": {
    "addr:full":"2600 Galena Ave Richmond VA 23237",
    "addr:housenumber":"2600",
    "addr:postcode":"23237",
    "addr:street":"Galena Ave",
    "iso:country":"US",
    "sg:address":"2600 Galena Ave",
    "sg:city":"Richmond",
    "sg:classifiers":[
        {
            "category":"Retail",
            "subcategory":"Auto Repair",
            "type":"Services"
        }
    ],
    "sg:phone":"+1 804 275 0002",
    "sg:postcode":"23237",
    "sg:province":"VA",
    "sg:tags":[
        "body",
        "automobile",
        "painting"
    ],
    "wof:name":"Quintanilla Auto Body Shop",
    "wof:placetype":"venue"
},
  "geometry": {"coordinates":[-77.43362399999999,37.392796],"type":"Point"}
}