{
  "type": "Feature",
  "properties": {
    "addr:full":"3556 S Jefferson St Falls Church VA 22041",
    "addr:housenumber":"3556",
    "addr:postcode":"22041",
    "addr:street":"S Jefferson St",
    "iso:country":"US",
    "sg:address":"3556 S Jefferson St",
    "sg:city":"Falls Church",
    "sg:classifiers":[
        {
            "category":"Bagels",
            "type":"Food & Drink"
        }
    ],
    "sg:menulink":"http://www.allmenus.com/va/mason/149774-einstein-bros/menu/",
    "sg:phone":"+1 703 998 5022",
    "sg:postcode":"22041",
    "sg:province":"VA",
    "sg:tags":[
        "wrap",
        "soup",
        "american",
        "sandwich",
        "salad"
    ],
    "wof:name":"Einstein Bros",
    "wof:placetype":"venue"
},
  "geometry": {"coordinates":[-77.118348,38.847775],"type":"Point"}
}