{
  "type": "Feature",
  "properties": {
    "addr:full":"44880 Falcon Pl Sterling VA 20166",
    "addr:housenumber":"44880",
    "addr:postcode":"20166",
    "addr:street":"Falcon Pl",
    "iso:country":"US",
    "sg:address":"44880 Falcon Pl",
    "sg:city":"Sterling",
    "sg:classifiers":[
        {
            "category":"Manufacturing",
            "subcategory":"Printing",
            "type":"Manufacturing & Wholesale Goods"
        }
    ],
    "sg:phone":"+1 703 793 3500",
    "sg:postcode":"20166",
    "sg:province":"VA",
    "sg:tags":[
        "multimedia"
    ],
    "wof:name":"Cross Media Networks Corp",
    "wof:placetype":"venue"
},
  "geometry": {"coordinates":[-77.448198,38.979224],"type":"Point"}
}