{
  "type": "Feature",
  "properties": {
    "addr:full":"2036 Victoria Dr Stafford VA 22554",
    "addr:housenumber":"2036",
    "addr:postcode":"22554",
    "addr:street":"Victoria Dr",
    "iso:country":"US",
    "sg:address":"2036 Victoria Dr",
    "sg:city":"Stafford",
    "sg:classifiers":[
        {
            "category":"Manufacturing",
            "subcategory":"Wood Products",
            "type":"Manufacturing & Wholesale Goods"
        }
    ],
    "sg:phone":"+1 540 659 3972",
    "sg:postcode":"22554",
    "sg:province":"VA",
    "sg:tags":[
        "mfg"
    ],
    "wof:name":"D & S Woodworking",
    "wof:placetype":"venue"
},
  "geometry": {"coordinates":[-77.38208299999999,38.47643],"type":"Point"}
}