{
  "type": "Feature",
  "properties": {
    "addr:full":"19763 Popes Station Rd Capron VA 23829",
    "addr:housenumber":"19763",
    "addr:postcode":"23829",
    "addr:street":"Popes Station Rd",
    "iso:country":"US",
    "sg:address":"19763 Popes Station Rd",
    "sg:city":"Capron",
    "sg:classifiers":[
        {
            "category":"Recreation",
            "type":"Entertainment"
        }
    ],
    "sg:phone":"+1 434 658 4205",
    "sg:postcode":"23829",
    "sg:province":"VA",
    "sg:tags":[
        "club",
        "membership"
    ],
    "wof:name":"Bucks Branch Hunt Club",
    "wof:placetype":"venue"
},
  "geometry": {"coordinates":[-77.22136999999999,36.783915],"type":"Point"}
}