{
  "type": "Feature",
  "properties": {
    "iso:country":"US",
    "sg:address":"5928 Fox Glove Trl",
    "sg:city":"Lorton",
    "sg:classifiers":[
        {
            "category":"Arts & Performance",
            "subcategory":"Theater",
            "type":"Entertainment"
        }
    ],
    "sg:phone":"+1 703 541 1131",
    "sg:postcode":"22079",
    "sg:province":"VA",
    "sg:tags":[
        "group"
    ],
    "wof:name":"Karaoke Showtime & Dj Service",
    "wof:placetype":"venue"
},
  "geometry": {"coordinates":[-77.138124,38.649465],"type":"Point"}
}