{
  "type": "Feature",
  "properties": {
    "addr:full":"14150 Willard Rd Chantilly VA 20151",
    "addr:housenumber":"14150",
    "addr:postcode":"20151",
    "addr:street":"Willard Rd",
    "iso:country":"US",
    "sg:address":"14150 Willard Rd",
    "sg:city":"Chantilly",
    "sg:classifiers":[
        {
            "category":"Banks & Credit Unions",
            "subcategory":"Bank",
            "type":"Services"
        }
    ],
    "sg:phone":"+1 703 272 0400",
    "sg:postcode":"20151",
    "sg:province":"VA",
    "sg:tags":[
        "financing"
    ],
    "wof:name":"Mid Atlantic Funding",
    "wof:placetype":"venue"
},
  "geometry": {"coordinates":[-77.434027,38.886674],"type":"Point"}
}