{
  "type": "Feature",
  "properties": {
    "iso:country":"US",
    "sg:address":"5841 Deep Forest Rd",
    "sg:city":"Richmond",
    "sg:classifiers":[
        {
            "category":"Health Services",
            "subcategory":"Doctor",
            "type":"Services"
        }
    ],
    "sg:phone":"+1 804 796 1051",
    "sg:postcode":"23237",
    "sg:province":"VA",
    "sg:tags":[
        "medical"
    ],
    "wof:name":"Hopewell Ob-Gyn Ltd",
    "wof:placetype":"venue"
},
  "geometry": {"coordinates":[-77.47993200000001,37.367081],"type":"Point"}
}