{
  "type": "Feature",
  "properties": {
    "addr:full":"4001 Murray Pl Lynchburg VA 24501",
    "addr:housenumber":"4001",
    "addr:postcode":"24501",
    "addr:street":"Murray Pl",
    "iso:country":"US",
    "sg:address":"4001 Murray Pl",
    "sg:city":"Lynchburg",
    "sg:classifiers":[
        {
            "category":"Restaurant",
            "type":"Food & Drink"
        }
    ],
    "sg:phone":"+1 434 528 1134",
    "sg:postcode":"24501",
    "sg:province":"VA",
    "sg:tags":[
        "drinking",
        "eating"
    ],
    "wof:name":"Texas Stakhouses Saloons L L C",
    "wof:placetype":"venue"
},
  "geometry": {"coordinates":[-79.167126,37.379736],"type":"Point"}
}