{
  "type": "Feature",
  "properties": {
    "addr:full":"2107 Electric Rd Roanoke VA 24018",
    "addr:housenumber":"2107",
    "addr:postcode":"24018",
    "addr:street":"Electric Rd",
    "iso:country":"US",
    "sg:address":"2107 Electric Rd",
    "sg:city":"Roanoke",
    "sg:classifiers":[
        {
            "category":"Banks & Credit Unions",
            "subcategory":"Investment Brokerage",
            "type":"Services"
        }
    ],
    "sg:phone":"+1 540 774 8479",
    "sg:postcode":"24018",
    "sg:province":"VA",
    "sg:tags":[
        "security"
    ],
    "wof:name":"Edward Jones 05038",
    "wof:placetype":"venue"
},
  "geometry": {"coordinates":[-80.030591,37.245224],"type":"Point"}
}