{
  "type": "Feature",
  "properties": {
    "addr:full":"3805 Cook Blvd Chesapeake VA 23323",
    "addr:housenumber":"3805",
    "addr:postcode":"23323",
    "addr:street":"Cook Blvd",
    "iso:country":"US",
    "sg:address":"3805 Cook Blvd",
    "sg:city":"Chesapeake",
    "sg:classifiers":[
        {
            "category":"Wholesale",
            "subcategory":"Construction Materials",
            "type":"Manufacturing & Wholesale Goods"
        }
    ],
    "sg:phone":"+1 757 487 2100",
    "sg:postcode":"23323",
    "sg:province":"VA",
    "sg:tags":[
        "pallet",
        "skid"
    ],
    "wof:name":"Mc Bride Lumber",
    "wof:placetype":"venue"
},
  "geometry": {"coordinates":[-76.373722,36.783474],"type":"Point"}
}