{
  "type": "Feature",
  "properties": {
    "iso:country":"US",
    "sg:address":"196 Van Buren St",
    "sg:city":"Herndon",
    "sg:classifiers":[
        {
            "category":"Real Estate",
            "subcategory":"Real Estate Agent",
            "type":"Services"
        }
    ],
    "sg:phone":"+1 703 742 6692",
    "sg:postcode":"20170",
    "sg:province":"VA",
    "wof:name":"Lasalle Jones Lang",
    "wof:placetype":"venue"
},
  "geometry": {"coordinates":[-77.388375,38.956373],"type":"Point"}
}