{
  "type": "Feature",
  "properties": {
    "iso:country":"US",
    "sg:address":"811 Commerce Rd",
    "sg:city":"Staunton",
    "sg:classifiers":[
        {
            "category":"Professional",
            "subcategory":"Management & Consulting",
            "type":"Services"
        }
    ],
    "sg:phone":"+1 540 213 1951",
    "sg:postcode":"24401",
    "sg:province":"VA",
    "sg:tags":[
        "consultant",
        "business"
    ],
    "wof:name":"Management Consulting Inc",
    "wof:placetype":"venue"
},
  "geometry": {"coordinates":[-79.05032199999999,38.157565],"type":"Point"}
}