{
  "type": "Feature",
  "properties": {
    "addr:full":"1204 Tampa Dr Chesapeake VA 23323",
    "addr:housenumber":"1204",
    "addr:postcode":"23323",
    "addr:street":"Tampa Dr",
    "iso:country":"US",
    "sg:address":"1204 Tampa Dr",
    "sg:city":"Chesapeake",
    "sg:classifiers":[
        {
            "category":"Building & Trades",
            "subcategory":"Construction",
            "type":"Services"
        }
    ],
    "sg:phone":"+1 757 488 6999",
    "sg:postcode":"23323",
    "sg:province":"VA",
    "sg:tags":[
        "general",
        "contractor"
    ],
    "wof:name":"Jcs Enterprises Inc",
    "wof:placetype":"venue"
},
  "geometry": {"coordinates":[-76.38320899999999,36.785819],"type":"Point"}
}