{
  "type": "Feature",
  "properties": {
    "addr:full":"1999 S Main St Blacksburg VA 24060",
    "addr:housenumber":"1999",
    "addr:postcode":"24060",
    "addr:street":"S Main St",
    "iso:country":"US",
    "sg:address":"1999 S Main St",
    "sg:city":"Blacksburg",
    "sg:classifiers":[
        {
            "category":"Insurance",
            "subcategory":"Insurance Agent",
            "type":"Services"
        }
    ],
    "sg:phone":"+1 540 951 0375",
    "sg:postcode":"24060",
    "sg:province":"VA",
    "wof:name":"New York Life Insurance Co",
    "wof:placetype":"venue"
},
  "geometry": {"coordinates":[-80.398737,37.20581],"type":"Point"}
}