{
  "type": "Feature",
  "properties": {
    "iso:country":"US",
    "sg:address":"1425 Laburnum St",
    "sg:city":"Mc Lean",
    "sg:classifiers":[
        {
            "category":"Professional",
            "subcategory":"Business Services",
            "type":"Services"
        }
    ],
    "sg:phone":"+1 703 237 3833",
    "sg:postcode":"22101",
    "sg:province":"VA",
    "wof:name":"Nse Enterprises LLC",
    "wof:placetype":"venue"
},
  "geometry": {"coordinates":[-77.13908499999999,38.934112],"type":"Point"}
}