{
  "type": "Feature",
  "properties": {
    "iso:country":"US",
    "sg:address":"2012 Venter Rd",
    "sg:city":"Aylett",
    "sg:classifiers":[
        {
            "category":"Manufacturing",
            "subcategory":"Lumber",
            "type":"Manufacturing & Wholesale Goods"
        }
    ],
    "sg:phone":"+1 804 769 2831",
    "sg:postcode":"23009",
    "sg:province":"VA",
    "sg:tags":[
        "logging"
    ],
    "wof:name":"J W Abrams Logging",
    "wof:placetype":"venue"
},
  "geometry": {"coordinates":[-77.15697900000001,37.756634],"type":"Point"}
}