{
  "type": "Feature",
  "properties": {
    "iso:country":"US",
    "sg:address":"325 Maple Ave E",
    "sg:city":"Vienna",
    "sg:classifiers":[
        {
            "category":"Fast Food",
            "type":"Food & Drink"
        },
        {
            "category":"Restaurant",
            "type":"Food & Drink"
        }
    ],
    "sg:phone":"+1 703 319 0700",
    "sg:postcode":"22180",
    "sg:province":"VA",
    "sg:tags":[
        "southern"
    ],
    "sg:website":"www.popeyes.com/",
    "wof:name":"Popeye's",
    "wof:placetype":"venue"
},
  "geometry": {"coordinates":[-77.259486,38.906113],"type":"Point"}
}