{
  "type": "Feature",
  "properties": {
    "iso:country":"US",
    "sg:address":"1614 New London Rd",
    "sg:city":"Forest",
    "sg:classifiers":[
        {
            "category":"Sports & Exercise",
            "subcategory":"Golf",
            "type":"Entertainment"
        }
    ],
    "sg:phone":"+1 434 525 4653",
    "sg:postcode":"24551",
    "sg:province":"VA",
    "sg:tags":[
        "course"
    ],
    "sg:website":"www.londondownsgolf.com",
    "wof:name":"London Downs Golf Club",
    "wof:placetype":"venue"
},
  "geometry": {"coordinates":[-79.3105,37.29678],"type":"Point"}
}