{
  "type": "Feature",
  "properties": {
    "addr:full":"818 Florida Ave Lynchburg VA 24504",
    "addr:housenumber":"818",
    "addr:postcode":"24504",
    "addr:street":"Florida Ave",
    "iso:country":"US",
    "sg:address":"818 Florida Ave",
    "sg:city":"Lynchburg",
    "sg:classifiers":[
        {
            "category":"Food & Beverages",
            "subcategory":"Groceries & Convenience Stores",
            "type":"Retail Goods"
        }
    ],
    "sg:phone":"+1 434 846 4457",
    "sg:postcode":"24504",
    "sg:province":"VA",
    "wof:name":"White Rock Food Market",
    "wof:placetype":"venue"
},
  "geometry": {"coordinates":[-79.136996,37.401504],"type":"Point"}
}