{
  "type": "Feature",
  "properties": {
    "addr:full":"6573 Springfield Blvd Springfield VA 22150",
    "addr:housenumber":"6573",
    "addr:postcode":"22150",
    "addr:street":"Springfield Blvd",
    "iso:country":"US",
    "sg:address":"6573 Springfield Blvd",
    "sg:city":"Springfield",
    "sg:classifiers":[
        {
            "category":"Utilities",
            "subcategory":"Mobile Phone",
            "type":"Services"
        }
    ],
    "sg:phone":"+1 703 921 2045",
    "sg:postcode":"22150",
    "sg:province":"VA",
    "sg:tags":[
        "telephone",
        "cellular"
    ],
    "wof:name":"T-Mobile",
    "wof:placetype":"venue"
},
  "geometry": {"coordinates":[-77.185451,38.777751],"type":"Point"}
}