{
  "type": "Feature",
  "properties": {
    "iso:country":"US",
    "sg:address":"210 Professional Park Dr SE",
    "sg:city":"Blacksburg",
    "sg:classifiers":[
        {
            "category":"Health Services",
            "subcategory":"Doctor",
            "type":"Services"
        },
        {
            "category":"Health Services",
            "subcategory":"Clinic",
            "type":"Services"
        }
    ],
    "sg:phone":"+1 540 961 0410",
    "sg:postcode":"24060",
    "sg:province":"VA",
    "sg:tags":[
        "physician",
        "surgeon",
        "neurology",
        "surgeons",
        "osteopathic"
    ],
    "wof:name":"Steven D Nack Dr",
    "wof:placetype":"venue"
},
  "geometry": {"coordinates":[-80.400578,37.197499],"type":"Point"}
}