{
  "type": "Feature",
  "properties": {
    "addr:full":"8316 Arlington Blvd # 222 Fairfax VA 22031",
    "addr:housenumber":"8316",
    "addr:postcode":"22031",
    "addr:street":"Arlington Blvd # 222",
    "iso:country":"US",
    "sg:address":"8316 Arlington Blvd # 222",
    "sg:city":"Fairfax",
    "sg:classifiers":[
        {
            "category":"Health Services",
            "subcategory":"Clinic",
            "type":"Services"
        },
        {
            "category":"Community Center",
            "type":"Public Place"
        }
    ],
    "sg:phone":"+1 703 573 0130",
    "sg:postcode":"22031",
    "sg:province":"VA",
    "sg:tags":[
        "medical"
    ],
    "wof:name":"Northern Va Center For Arthritis, P.C.",
    "wof:placetype":"venue"
},
  "geometry": {"coordinates":[-77.232811,38.865768],"type":"Point"}
}