{
  "type": "Feature",
  "properties": {
    "iso:country":"US",
    "sg:address":"1313 Belleview Ave",
    "sg:city":"Charlottesville",
    "sg:classifiers":[
        {
            "category":"Building & Trades",
            "subcategory":"Construction",
            "type":"Services"
        }
    ],
    "sg:phone":"+1 434 979 1490",
    "sg:postcode":"22901",
    "sg:province":"VA",
    "sg:tags":[
        "contractor"
    ],
    "wof:name":"Creative Construction",
    "wof:placetype":"venue"
},
  "geometry": {"coordinates":[-78.459396,38.037601],"type":"Point"}
}