{
  "type": "Feature",
  "properties": {
    "addr:full":"14326 Boondock Ln Montpelier VA 23192",
    "addr:housenumber":"14326",
    "addr:postcode":"23192",
    "addr:street":"Boondock Ln",
    "iso:country":"US",
    "sg:address":"14326 Boondock Ln",
    "sg:city":"Montpelier",
    "sg:classifiers":[
        {
            "category":"Recreation",
            "type":"Entertainment"
        }
    ],
    "sg:phone":"+1 804 883 3003",
    "sg:postcode":"23192",
    "sg:province":"VA",
    "wof:name":"Galloping Acres LLC",
    "wof:placetype":"venue"
},
  "geometry": {"coordinates":[-77.765979,37.799584],"type":"Point"}
}