{
  "type": "Feature",
  "properties": {
    "iso:country":"US",
    "sg:address":"7071 Falling Branch Rd",
    "sg:city":"Radford",
    "sg:classifiers":[
        {
            "category":"Retail",
            "subcategory":"Auto Repair",
            "type":"Services"
        }
    ],
    "sg:phone":"+1 540 731 4609",
    "sg:postcode":"24141",
    "sg:province":"VA",
    "sg:tags":[
        "general"
    ],
    "wof:name":"Als Auto Repair",
    "wof:placetype":"venue"
},
  "geometry": {"coordinates":[-80.59677499999999,37.130293],"type":"Point"}
}