{
  "type": "Feature",
  "properties": {
    "addr:full":"13137 Fair Oaks Ln Ashland VA 23005",
    "addr:housenumber":"13137",
    "addr:postcode":"23005",
    "addr:street":"Fair Oaks Ln",
    "iso:country":"US",
    "sg:address":"13137 Fair Oaks Ln",
    "sg:city":"Ashland",
    "sg:classifiers":[
        {
            "category":"Wholesale",
            "subcategory":"Stationery",
            "type":"Manufacturing & Wholesale Goods"
        }
    ],
    "sg:phone":"+1 804 798 7200",
    "sg:postcode":"23005",
    "sg:province":"VA",
    "sg:tags":[
        "business",
        "system",
        "form",
        "supply"
    ],
    "wof:name":"Data Graphics Inc",
    "wof:placetype":"venue"
},
  "geometry": {"coordinates":[-77.555958,37.762422],"type":"Point"}
}