{
  "type": "Feature",
  "properties": {
    "addr:full":"7097 Pocahontas Trl Williamsburg VA 23185",
    "addr:housenumber":"7097",
    "addr:postcode":"23185",
    "addr:street":"Pocahontas Trl",
    "iso:country":"US",
    "sg:address":"7097 Pocahontas Trl",
    "sg:city":"Williamsburg",
    "sg:classifiers":[
        {
            "category":"Restaurant",
            "type":"Food & Drink"
        },
        {
            "category":"Ice Cream",
            "type":"Food & Drink"
        }
    ],
    "sg:menulink":"http://www.allmenus.com/va/roberts/217450-ben--jerrys/menu/",
    "sg:postcode":"23185",
    "sg:province":"VA",
    "sg:tags":[
        "american",
        "ice",
        "cream"
    ],
    "wof:name":"Ben & Jerry's",
    "wof:placetype":"venue"
},
  "geometry": {"coordinates":[-76.67528799999999,37.261051],"type":"Point"}
}