{
  "type": "Feature",
  "properties": {
    "iso:country":"US",
    "sg:address":"121 S Hill Ave",
    "sg:city":"South Hill",
    "sg:classifiers":[
        {
            "category":"Personal",
            "subcategory":"Barber",
            "type":"Services"
        }
    ],
    "sg:phone":"+1 434 447 3900",
    "sg:postcode":"23970",
    "sg:province":"VA",
    "wof:name":"Cutting Edge",
    "wof:placetype":"venue"
},
  "geometry": {"coordinates":[-78.130742,36.724527],"type":"Point"}
}