{
  "type": "Feature",
  "properties": {
    "addr:full":"976 Marcus Dr Newport News VA 23602",
    "addr:housenumber":"976",
    "addr:postcode":"23602",
    "addr:street":"Marcus Dr",
    "iso:country":"US",
    "sg:address":"976 Marcus Dr",
    "sg:city":"Newport News",
    "sg:classifiers":[
        {
            "category":"Social Services",
            "type":"Services"
        }
    ],
    "sg:phone":"+1 757 599 5818",
    "sg:postcode":"23602",
    "sg:province":"VA",
    "sg:tags":[
        "personal",
        "problem",
        "referral",
        "for"
    ],
    "wof:name":"Kingdom Bound Ministries Inc",
    "wof:placetype":"venue"
},
  "geometry": {"coordinates":[-76.464303,37.09622],"type":"Point"}
}