{
  "type": "Feature",
  "properties": {
    "addr:full":"609 N Pinetta Dr Richmond VA 23235",
    "addr:housenumber":"609",
    "addr:postcode":"23235",
    "addr:street":"N Pinetta Dr",
    "iso:country":"US",
    "sg:address":"609 N Pinetta Dr",
    "sg:city":"Richmond",
    "sg:classifiers":[
        {
            "category":"Recreation",
            "type":"Entertainment"
        }
    ],
    "sg:phone":"+1 804 272 9946",
    "sg:postcode":"23235",
    "sg:province":"VA",
    "sg:tags":[
        "center"
    ],
    "wof:name":"Brighton Green Community Assn",
    "wof:placetype":"venue"
},
  "geometry": {"coordinates":[-77.559782,37.505108],"type":"Point"}
}