{
  "type": "Feature",
  "properties": {
    "addr:full":"1708 Potters Rd Virginia Beach VA 23454",
    "addr:housenumber":"1708",
    "addr:postcode":"23454",
    "addr:street":"Potters Rd",
    "iso:country":"US",
    "sg:address":"1708 Potters Rd",
    "sg:city":"Virginia Beach",
    "sg:classifiers":[
        {
            "category":"Manufacturing",
            "subcategory":"Building Materials",
            "type":"Manufacturing & Wholesale Goods"
        }
    ],
    "sg:phone":"+1 757 425 6681",
    "sg:postcode":"23454",
    "sg:province":"VA",
    "sg:tags":[
        "stairs"
    ],
    "wof:name":"Virginia Stairs Inc",
    "wof:placetype":"venue"
},
  "geometry": {"coordinates":[-76.024046,36.836866],"type":"Point"}
}