{
  "type": "Feature",
  "properties": {
    "addr:full":"223 Harpers Ferry Dr Locust Grove VA 22508",
    "addr:housenumber":"223",
    "addr:postcode":"22508",
    "addr:street":"Harpers Ferry Dr",
    "iso:country":"US",
    "sg:address":"223 Harpers Ferry Dr",
    "sg:city":"Locust Grove",
    "sg:classifiers":[
        {
            "category":"Professional",
            "subcategory":"Lawyer & Legal Services",
            "type":"Services"
        }
    ],
    "sg:phone":"+1 540 972 3545",
    "sg:postcode":"22508",
    "sg:province":"VA",
    "wof:name":"Lawrence D Huntsman",
    "wof:placetype":"venue"
},
  "geometry": {"coordinates":[-77.762293,38.345146],"type":"Point"}
}