{
  "type": "Feature",
  "properties": {
    "iso:country":"US",
    "sg:address":"3418 Richmond St",
    "sg:city":"Lynchburg",
    "sg:classifiers":[
        {
            "category":"Building & Trades",
            "subcategory":"Construction",
            "type":"Services"
        }
    ],
    "sg:phone":"+1 434 847 5232",
    "sg:postcode":"24501",
    "sg:province":"VA",
    "sg:tags":[
        "residential",
        "masonry",
        "contractor"
    ],
    "wof:name":"John D Kinsley Contractor",
    "wof:placetype":"venue"
},
  "geometry": {"coordinates":[-79.176585,37.397845],"type":"Point"}
}