{
  "type": "Feature",
  "properties": {
    "addr:full":"9114 Delaware Rd Fort Belvoir VA 22060",
    "addr:housenumber":"9114",
    "addr:postcode":"22060",
    "addr:street":"Delaware Rd",
    "iso:country":"US",
    "sg:address":"9114 Delaware Rd",
    "sg:city":"Fort Belvoir",
    "sg:classifiers":[
        {
            "category":"Professional",
            "type":"Services"
        }
    ],
    "sg:phone":"+1 571 594 0300",
    "sg:postcode":"22060",
    "sg:province":"VA",
    "sg:tags":[
        "sound",
        "lighting",
        "reinforcement"
    ],
    "wof:name":"Alescio Pro Sound",
    "wof:placetype":"venue"
},
  "geometry": {"coordinates":[-77.130414,38.70965],"type":"Point"}
}