{
  "type": "Feature",
  "properties": {
    "iso:country":"US",
    "sg:address":"851 Statler Blvd",
    "sg:city":"Staunton",
    "sg:classifiers":[
        {
            "category":"Sports & Exercise",
            "subcategory":"Gym",
            "type":"Entertainment"
        }
    ],
    "sg:phone":"+1 540 886 0262",
    "sg:postcode":"24401",
    "sg:province":"VA",
    "sg:tags":[
        "club",
        "health",
        "studio",
        "gymnasium"
    ],
    "wof:name":"Curves For Women",
    "wof:placetype":"venue"
},
  "geometry": {"coordinates":[-79.062068,38.142617],"type":"Point"}
}