{
  "type": "Feature",
  "properties": {
    "addr:full":"427 Cattle Scales Rd Waynesboro VA 22980",
    "addr:housenumber":"427",
    "addr:postcode":"22980",
    "addr:street":"Cattle Scales Rd",
    "iso:country":"US",
    "sg:address":"427 Cattle Scales Rd",
    "sg:city":"Waynesboro",
    "sg:classifiers":[
        {
            "category":"Organizations",
            "subcategory":"Religious Organization",
            "type":"Services"
        }
    ],
    "sg:phone":"+1 540 942 9194",
    "sg:postcode":"22980",
    "sg:province":"VA",
    "sg:tags":[
        "church"
    ],
    "wof:name":"Kingdom Hall-Jehovah's Witness",
    "wof:placetype":"venue"
},
  "geometry": {"coordinates":[-78.883444,38.120076],"type":"Point"}
}