{
  "type": "Feature",
  "properties": {
    "addr:full":"18896 Longhouse Pl Leesburg VA 20176",
    "addr:housenumber":"18896",
    "addr:postcode":"20176",
    "addr:street":"Longhouse Pl",
    "iso:country":"US",
    "sg:address":"18896 Longhouse Pl",
    "sg:city":"Leesburg",
    "sg:classifiers":[
        {
            "category":"Real Estate",
            "subcategory":"Real Estate Agent",
            "type":"Services"
        }
    ],
    "sg:phone":"+1 703 779 8585",
    "sg:postcode":"20176",
    "sg:province":"VA",
    "wof:name":"Engle Homes At Potomac Station",
    "wof:placetype":"venue"
},
  "geometry": {"coordinates":[-77.512508,39.091949],"type":"Point"}
}