{
  "type": "Feature",
  "properties": {
    "addr:full":"6525 Hampton Blvd Norfolk VA 23508",
    "addr:housenumber":"6525",
    "addr:postcode":"23508",
    "addr:street":"Hampton Blvd",
    "iso:country":"US",
    "sg:address":"6525 Hampton Blvd",
    "sg:city":"Norfolk",
    "sg:classifiers":[
        {
            "category":"Education",
            "subcategory":"Library",
            "type":"Public Place"
        }
    ],
    "sg:phone":"+1 757 441 5335",
    "sg:postcode":"23508",
    "sg:province":"VA",
    "sg:tags":[
        "executive"
    ],
    "wof:name":"Larchmont Branch Library",
    "wof:placetype":"venue"
},
  "geometry": {"coordinates":[-76.30400899999999,36.902003],"type":"Point"}
}