{
  "type": "Feature",
  "properties": {
    "addr:full":"6411 Iron Bridge Rd Richmond VA 23234",
    "addr:housenumber":"6411",
    "addr:postcode":"23234",
    "addr:street":"Iron Bridge Rd",
    "iso:country":"US",
    "sg:address":"6411 Iron Bridge Rd",
    "sg:city":"Richmond",
    "sg:classifiers":[
        {
            "category":"Personal",
            "subcategory":"Beauty Salon",
            "type":"Services"
        }
    ],
    "sg:phone":"+1 804 714 1003",
    "sg:postcode":"23234",
    "sg:province":"VA",
    "sg:tags":[
        "shop",
        "manicuring"
    ],
    "wof:name":"Club Nail",
    "wof:placetype":"venue"
},
  "geometry": {"coordinates":[-77.492999,37.428514],"type":"Point"}
}