{
  "type": "Feature",
  "properties": {
    "addr:full":"228 Oxford Dr Martinsville VA 24112",
    "addr:housenumber":"228",
    "addr:postcode":"24112",
    "addr:street":"Oxford Dr",
    "iso:country":"US",
    "sg:address":"228 Oxford Dr",
    "sg:city":"Martinsville",
    "sg:classifiers":[
        {
            "category":"Manufacturing",
            "subcategory":"Printing",
            "type":"Manufacturing & Wholesale Goods"
        }
    ],
    "sg:phone":"+1 276 956 5900",
    "sg:postcode":"24112",
    "sg:province":"VA",
    "sg:tags":[
        "publisher"
    ],
    "wof:name":"Virginia Real Estate Review",
    "wof:placetype":"venue"
},
  "geometry": {"coordinates":[-79.87054500000001,36.629289],"type":"Point"}
}