{
  "type": "Feature",
  "properties": {
    "iso:country":"US",
    "sg:address":"508 Rorer Ave SW",
    "sg:city":"Roanoke",
    "sg:classifiers":[
        {
            "category":"Manufacturing",
            "subcategory":"Tools & Machinery",
            "type":"Manufacturing & Wholesale Goods"
        }
    ],
    "sg:phone":"+1 540 345 1617",
    "sg:postcode":"24016",
    "sg:province":"VA",
    "sg:tags":[
        "machine",
        "shop"
    ],
    "wof:name":"Price Filler Machine & Mfg Co",
    "wof:placetype":"venue"
},
  "geometry": {"coordinates":[-79.952117,37.271895],"type":"Point"}
}