{
  "type": "Feature",
  "properties": {
    "addr:full":"240 Ridge Dr Amherst VA 24521",
    "addr:housenumber":"240",
    "addr:postcode":"24521",
    "addr:street":"Ridge Dr",
    "iso:country":"US",
    "sg:address":"240 Ridge Dr",
    "sg:city":"Amherst",
    "sg:classifiers":[
        {
            "category":"Professional",
            "subcategory":"Business Services",
            "type":"Services"
        }
    ],
    "sg:phone":"+1 434 946 0087",
    "sg:postcode":"24521",
    "sg:province":"VA",
    "wof:name":"Kennys Lawn Care & Landscape",
    "wof:placetype":"venue"
},
  "geometry": {"coordinates":[-79.042663,37.594647],"type":"Point"}
}