{
  "type": "Feature",
  "properties": {
    "iso:country":"US",
    "sg:address":"105 High St",
    "sg:city":"Charlottesville",
    "sg:classifiers":[
        {
            "category":"Professional",
            "subcategory":"Engineering",
            "type":"Services"
        }
    ],
    "sg:phone":"+1 434 296 3644",
    "sg:postcode":"22902",
    "sg:province":"VA",
    "sg:tags":[
        "architectural"
    ],
    "wof:name":"Brian P Smith Pe Civil Engrg",
    "wof:placetype":"venue"
},
  "geometry": {"coordinates":[-78.481208,38.033301],"type":"Point"}
}