{
  "type": "Feature",
  "properties": {
    "addr:full":"3800 Thalia Dr Virginia Beach VA 23452",
    "addr:housenumber":"3800",
    "addr:postcode":"23452",
    "addr:street":"Thalia Dr",
    "iso:country":"US",
    "sg:address":"3800 Thalia Dr",
    "sg:city":"Virginia Beach",
    "sg:classifiers":[
        {
            "category":"Real Estate",
            "subcategory":"Real Estate Agent",
            "type":"Services"
        }
    ],
    "sg:phone":"+1 757 965 3505",
    "sg:postcode":"23452",
    "sg:province":"VA",
    "wof:name":"Setnik & Setnik",
    "wof:placetype":"venue"
},
  "geometry": {"coordinates":[-76.104911,36.854994],"type":"Point"}
}