{
  "type": "Feature",
  "properties": {
    "addr:full":"512 Whitehaven Ct Chesapeake VA 23325",
    "addr:housenumber":"512",
    "addr:postcode":"23325",
    "addr:street":"Whitehaven Ct",
    "iso:country":"US",
    "sg:address":"512 Whitehaven Ct",
    "sg:city":"Chesapeake",
    "sg:classifiers":[
        {
            "category":"Restaurant",
            "type":"Food & Drink"
        }
    ],
    "sg:phone":"+1 757 523 9298",
    "sg:postcode":"23325",
    "sg:province":"VA",
    "sg:tags":[
        "eating"
    ],
    "wof:name":"Ecolias Elite Affairs",
    "wof:placetype":"venue"
},
  "geometry": {"coordinates":[-76.24027700000001,36.806653],"type":"Point"}
}