{
  "type": "Feature",
  "properties": {
    "addr:full":"4350 George Washington Memorial Hwy Grafton VA 23692",
    "addr:housenumber":"4350",
    "addr:postcode":"23692",
    "addr:street":"George Washington Memorial Hwy",
    "iso:country":"US",
    "sg:address":"4350 George Washington Memorial Hwy",
    "sg:city":"Grafton",
    "sg:classifiers":[
        {
            "category":"Restaurant",
            "type":"Food & Drink"
        }
    ],
    "sg:phone":"+1 757 898 1728",
    "sg:postcode":"23692",
    "sg:province":"VA",
    "sg:tags":[
        "eating"
    ],
    "wof:name":"KFC",
    "wof:placetype":"venue"
},
  "geometry": {"coordinates":[-76.458789,37.147469],"type":"Point"}
}