{
  "type": "Feature",
  "properties": {
    "addr:full":"67 Market St Onancock VA 23417",
    "addr:housenumber":"67",
    "addr:postcode":"23417",
    "addr:street":"Market St",
    "iso:country":"US",
    "sg:address":"67 Market St",
    "sg:city":"Onancock",
    "sg:classifiers":[
        {
            "category":"Shopping",
            "subcategory":"Computers & Home Electronics",
            "type":"Retail Goods"
        }
    ],
    "sg:phone":"+1 757 787 7777",
    "sg:postcode":"23417",
    "sg:province":"VA",
    "sg:tags":[
        "communications",
        "marine",
        "radio"
    ],
    "wof:name":"Shore Electronics Inc",
    "wof:placetype":"venue"
},
  "geometry": {"coordinates":[-75.74743100000001,37.711839],"type":"Point"}
}