{
  "type": "Feature",
  "properties": {
    "addr:full":"81 Breakwater St Hampton VA 23669",
    "addr:housenumber":"81",
    "addr:postcode":"23669",
    "addr:street":"Breakwater St",
    "iso:country":"US",
    "sg:address":"81 Breakwater St",
    "sg:city":"Hampton",
    "sg:classifiers":[
        {
            "category":"Professional",
            "subcategory":"Lawyer & Legal Services",
            "type":"Services"
        }
    ],
    "sg:phone":"+1 757 722 0379",
    "sg:postcode":"23669",
    "sg:province":"VA",
    "wof:name":"John W Bane",
    "wof:placetype":"venue"
},
  "geometry": {"coordinates":[-76.347065,37.018128],"type":"Point"}
}