{
  "type": "Feature",
  "properties": {
    "addr:full":"13615 S Springs Dr Clifton VA 20124",
    "addr:housenumber":"13615",
    "addr:postcode":"20124",
    "addr:street":"S Springs Dr",
    "iso:country":"US",
    "sg:address":"13615 S Springs Dr",
    "sg:city":"Clifton",
    "sg:classifiers":[
        {
            "category":"Home & Garden",
            "subcategory":"Hardware",
            "type":"Retail Goods"
        }
    ],
    "sg:phone":"+1 703 598 6075",
    "sg:postcode":"20124",
    "sg:province":"VA",
    "wof:name":"Sasser Enterprise Inc",
    "wof:placetype":"venue"
},
  "geometry": {"coordinates":[-77.41856199999999,38.817952],"type":"Point"}
}