{
  "type": "Feature",
  "properties": {
    "addr:full":"523 W Franklin St Richmond VA 23220",
    "addr:housenumber":"523",
    "addr:postcode":"23220",
    "addr:street":"W Franklin St",
    "iso:country":"US",
    "sg:address":"523 W Franklin St",
    "sg:city":"Richmond",
    "sg:classifiers":[
        {
            "category":"Professional",
            "subcategory":"Business Services",
            "type":"Services"
        }
    ],
    "sg:phone":"+1 804 644 6038",
    "sg:postcode":"23220",
    "sg:province":"VA",
    "wof:name":"Transland Inc",
    "wof:placetype":"venue"
},
  "geometry": {"coordinates":[-77.448549,37.546813],"type":"Point"}
}