{
  "type": "Feature",
  "properties": {
    "addr:full":"1906 Westmoreland St Mc Lean VA 22101",
    "addr:housenumber":"1906",
    "addr:postcode":"22101",
    "addr:street":"Westmoreland St Mc Lean",
    "iso:country":"US",
    "sg:address":"1906 Westmoreland St",
    "sg:city":"Mc Lean",
    "sg:classifiers":[
        {
            "category":"Recreation",
            "type":"Entertainment"
        }
    ],
    "sg:phone":"+1 703 893 7573",
    "sg:postcode":"22101",
    "sg:province":"VA",
    "sg:tags":[
        "pool",
        "swimming"
    ],
    "wof:name":"Kent Gardens Recreation Club",
    "wof:placetype":"venue"
},
  "geometry": {"coordinates":[-77.17676,38.914637],"type":"Point"}
}