{
  "type": "Feature",
  "properties": {
    "addr:full":"4090 Lankford Hwy Exmore VA 23350",
    "addr:housenumber":"4090",
    "addr:postcode":"23350",
    "addr:street":"Lankford Hwy Exmore",
    "iso:country":"US",
    "sg:address":"4090 Lankford Hwy",
    "sg:city":"Exmore",
    "sg:classifiers":[
        {
            "category":"Restaurant",
            "type":"Food & Drink"
        }
    ],
    "sg:menulink":"http://www.allmenus.com/va/hare-valley/147629-subway/menu/",
    "sg:phone":"+1 757 442 0090",
    "sg:postcode":"23350",
    "sg:province":"VA",
    "sg:tags":[
        "american",
        "sandwich"
    ],
    "wof:name":"Subway",
    "wof:placetype":"venue"
},
  "geometry": {"coordinates":[-75.832041,37.522183],"type":"Point"}
}