{
  "type": "Feature",
  "properties": {
    "addr:full":"965 Pleasant Valley Rd Harrisonburg VA 22801",
    "addr:housenumber":"965",
    "addr:postcode":"22801",
    "addr:street":"Pleasant Valley Rd",
    "iso:country":"US",
    "sg:address":"965 Pleasant Valley Rd",
    "sg:city":"Harrisonburg",
    "sg:classifiers":[
        {
            "category":"Government",
            "subcategory":"Office",
            "type":"Public Place"
        }
    ],
    "sg:phone":"+1 540 564 3080",
    "sg:postcode":"22801",
    "sg:province":"VA",
    "sg:website":"www.ext.vt.edu",
    "wof:name":"Virginia Cooperative Extension",
    "wof:placetype":"venue"
},
  "geometry": {"coordinates":[-78.899539,38.393221],"type":"Point"}
}