{
  "type": "Feature",
  "properties": {
    "iso:country":"US",
    "sg:address":"7715 Island Creek Ct",
    "sg:city":"Alexandria",
    "sg:classifiers":[
        {
            "category":"Home & Garden",
            "subcategory":"Carpets & Floor Coverings",
            "type":"Retail Goods"
        }
    ],
    "sg:phone":"+1 703 550 0158",
    "sg:postcode":"22315",
    "sg:province":"VA",
    "wof:name":"Josef Oriental Rugs Inc",
    "wof:placetype":"venue"
},
  "geometry": {"coordinates":[-77.17107300000001,38.749954],"type":"Point"}
}