{
  "type": "Feature",
  "properties": {
    "iso:country":"US",
    "sg:address":"3705 Marshall Ave",
    "sg:city":"Newport News",
    "sg:classifiers":[
        {
            "category":"Retail",
            "subcategory":"Laundry & Dry Cleaning",
            "type":"Services"
        }
    ],
    "sg:phone":"+1 757 245 9679",
    "sg:postcode":"23607",
    "sg:province":"VA",
    "sg:tags":[
        "drycleaning",
        "plant"
    ],
    "wof:name":"Blowes Cleaners",
    "wof:placetype":"venue"
},
  "geometry": {"coordinates":[-76.42112899999999,36.992171],"type":"Point"}
}