{
  "type": "Feature",
  "properties": {
    "iso:country":"US",
    "sg:address":"7759 Donnybrook Ct",
    "sg:city":"Annandale",
    "sg:classifiers":[
        {
            "category":"Building & Trades",
            "subcategory":"Construction",
            "type":"Services"
        }
    ],
    "sg:phone":"+1 703 256 5486",
    "sg:postcode":"22003",
    "sg:province":"VA",
    "sg:tags":[
        "home",
        "improvement"
    ],
    "wof:name":"Home Deco Plus Inc",
    "wof:placetype":"venue"
},
  "geometry": {"coordinates":[-77.213639,38.831514],"type":"Point"}
}