{
  "type": "Feature",
  "properties": {
    "addr:full":"457 Court St Portsmouth VA 23704",
    "addr:housenumber":"457",
    "addr:postcode":"23704",
    "addr:street":"Court St",
    "iso:country":"US",
    "sg:address":"457 Court St",
    "sg:city":"Portsmouth",
    "sg:classifiers":[
        {
            "category":"Insurance",
            "subcategory":"Insurance Agent",
            "type":"Services"
        }
    ],
    "sg:phone":"+1 757 397 2311",
    "sg:postcode":"23704",
    "sg:province":"VA",
    "sg:website":"www.bankersinsurance.net",
    "wof:name":"Bankers Insurance",
    "wof:placetype":"venue"
},
  "geometry": {"coordinates":[-76.300794,36.835388],"type":"Point"}
}