{
  "type": "Feature",
  "properties": {
    "addr:full":"3171 Little Creek Rd Dublin VA 24084",
    "addr:housenumber":"3171",
    "addr:postcode":"24084",
    "addr:street":"Little Creek Rd",
    "iso:country":"US",
    "sg:address":"3171 Little Creek Rd",
    "sg:city":"Dublin",
    "sg:classifiers":[
        {
            "category":"Retail",
            "subcategory":"Repair Shop",
            "type":"Services"
        }
    ],
    "sg:phone":"+1 540 674 1906",
    "sg:postcode":"24084",
    "sg:province":"VA",
    "wof:name":"V Twin Accessories Inc",
    "wof:placetype":"venue"
},
  "geometry": {"coordinates":[-80.79242499999999,37.162838],"type":"Point"}
}