{
  "type": "Feature",
  "properties": {
    "addr:full":"201 E Main St Stanley VA 22851",
    "addr:housenumber":"201",
    "addr:postcode":"22851",
    "addr:street":"E Main St",
    "iso:country":"US",
    "sg:address":"201 E Main St",
    "sg:city":"Stanley",
    "sg:classifiers":[
        {
            "category":"Manufacturing",
            "subcategory":"Rubber & Plastics",
            "type":"Manufacturing & Wholesale Goods"
        },
        {
            "category":"Autos & Motor Vehicles",
            "subcategory":"Auto Supplies",
            "type":"Retail Goods"
        },
        {
            "category":"Retail",
            "subcategory":"Auto Repair",
            "type":"Services"
        }
    ],
    "sg:phone":"+1 540 778 2563",
    "sg:postcode":"22851",
    "sg:province":"VA",
    "sg:tags":[
        "recap",
        "retread",
        "tires-wholesale",
        "tire",
        "manufacturer"
    ],
    "sg:website":"http://www.coopertire.com/html/",
    "wof:name":"Reed's Tire",
    "wof:placetype":"venue"
},
  "geometry": {"coordinates":[-78.500772,38.574939],"type":"Point"}
}