{
  "type": "Feature",
  "properties": {
    "addr:full":"3012 Island Ln Virginia Beach VA 23454",
    "addr:housenumber":"3012",
    "addr:postcode":"23454",
    "addr:street":"Island Ln",
    "iso:country":"US",
    "sg:address":"3012 Island Ln",
    "sg:city":"Virginia Beach",
    "sg:classifiers":[
        {
            "category":"Professional",
            "subcategory":"Management & Consulting",
            "type":"Services"
        }
    ],
    "sg:phone":"+1 757 481 5525",
    "sg:postcode":"23454",
    "sg:province":"VA",
    "sg:tags":[
        "business"
    ],
    "wof:name":"Kemp Enterprises",
    "wof:placetype":"venue"
},
  "geometry": {"coordinates":[-76.077409,36.903156],"type":"Point"}
}