{
  "type": "Feature",
  "properties": {
    "addr:full":"55 Black Feather Trl Ridgeway VA 24148",
    "addr:housenumber":"55",
    "addr:postcode":"24148",
    "addr:street":"Black Feather Trl",
    "iso:country":"US",
    "sg:address":"55 Black Feather Trl",
    "sg:city":"Ridgeway",
    "sg:classifiers":[
        {
            "category":"Professional",
            "subcategory":"Accounting & Tax Preparation",
            "type":"Services"
        }
    ],
    "sg:phone":"+1 276 956 3636",
    "sg:postcode":"24148",
    "sg:province":"VA",
    "sg:tags":[
        "return",
        "filing"
    ],
    "wof:name":"Rieson Tax Svc",
    "wof:placetype":"venue"
},
  "geometry": {"coordinates":[-79.873249,36.572561],"type":"Point"}
}