{
  "type": "Feature",
  "properties": {
    "addr:full":"20798 Amberview Ct Ashburn VA 20147",
    "addr:housenumber":"20798",
    "addr:postcode":"20147",
    "addr:street":"Amberview Ct",
    "iso:country":"US",
    "sg:address":"20798 Amberview Ct",
    "sg:city":"Ashburn",
    "sg:classifiers":[
        {
            "category":"Professional",
            "subcategory":"Management & Consulting",
            "type":"Services"
        }
    ],
    "sg:phone":"+1 703 723 0462",
    "sg:postcode":"20147",
    "sg:province":"VA",
    "sg:tags":[
        "consultant",
        "business"
    ],
    "wof:name":"Dan Brooks",
    "wof:placetype":"venue"
},
  "geometry": {"coordinates":[-77.514841,39.041019],"type":"Point"}
}