{
  "type": "Feature",
  "properties": {
    "iso:country":"US",
    "sg:address":"6324 September Dr",
    "sg:city":"Mineral",
    "sg:classifiers":[
        {
            "category":"Building & Trades",
            "subcategory":"Plumbing",
            "type":"Services"
        }
    ],
    "sg:phone":"+1 540 854 7000",
    "sg:postcode":"23117",
    "sg:province":"VA",
    "sg:tags":[
        "contractor"
    ],
    "wof:name":"In Evergreen Sprinkler Co",
    "wof:placetype":"venue"
},
  "geometry": {"coordinates":[-77.86065499999999,38.131609],"type":"Point"}
}