{
  "type": "Feature",
  "properties": {
    "iso:country":"US",
    "sg:address":"501 Prince George St",
    "sg:city":"Williamsburg",
    "sg:classifiers":[
        {
            "category":"Food & Beverages",
            "subcategory":"Specialty",
            "type":"Retail Goods"
        },
        {
            "category":"Restaurant",
            "type":"Food & Drink"
        }
    ],
    "sg:menulink":"http://www.allmenus.com/va/williamsburg/270668-a-chefs-kitchen/menu/",
    "sg:phone":"+1 757 564 8500",
    "sg:postcode":"23185",
    "sg:province":"VA",
    "sg:tags":[
        "american"
    ],
    "wof:name":"A Chef's Kitchen",
    "wof:placetype":"venue"
},
  "geometry": {"coordinates":[-76.707649,37.272429],"type":"Point"}
}