{
  "type": "Feature",
  "properties": {
    "iso:country":"US",
    "sg:address":"829 Corn Tassel Rd",
    "sg:city":"Danville",
    "sg:classifiers":[
        {
            "category":"Health Services",
            "subcategory":"Clinic",
            "type":"Services"
        }
    ],
    "sg:phone":"+1 434 836 1222",
    "sg:postcode":"24540",
    "sg:province":"VA",
    "sg:tags":[
        "organization",
        "medical",
        "surgical"
    ],
    "wof:name":"Qualitech",
    "wof:placetype":"venue"
},
  "geometry": {"coordinates":[-79.411631,36.679505],"type":"Point"}
}