{
  "type": "Feature",
  "properties": {
    "addr:full":"12638 Jefferson Ave Newport News VA 23602",
    "addr:housenumber":"12638",
    "addr:postcode":"23602",
    "addr:street":"Jefferson Ave",
    "iso:country":"US",
    "sg:address":"12638 Jefferson Ave",
    "sg:city":"Newport News",
    "sg:classifiers":[
        {
            "category":"Manufacturing",
            "subcategory":"Printing",
            "type":"Manufacturing & Wholesale Goods"
        }
    ],
    "sg:phone":"+1 757 872 7150",
    "sg:postcode":"23602",
    "sg:province":"VA",
    "sg:tags":[
        "offset"
    ],
    "wof:name":"Printing Plus",
    "wof:placetype":"venue"
},
  "geometry": {"coordinates":[-76.514141,37.131118],"type":"Point"}
}