{
  "type": "Feature",
  "properties": {
    "iso:country":"US",
    "sg:address":"6003 Leewood Dr",
    "sg:city":"Alexandria",
    "sg:classifiers":[
        {
            "category":"Building & Trades",
            "subcategory":"Construction",
            "type":"Services"
        }
    ],
    "sg:phone":"+1 703 924 2900",
    "sg:postcode":"22310",
    "sg:province":"VA",
    "sg:tags":[
        "painter"
    ],
    "wof:name":"Mendez Painting",
    "wof:placetype":"venue"
},
  "geometry": {"coordinates":[-77.11918900000001,38.786192],"type":"Point"}
}