{
  "type": "Feature",
  "properties": {
    "addr:full":"5062 26th Rd N Arlington VA 22207",
    "addr:housenumber":"5062",
    "addr:postcode":"22207",
    "addr:street":"26Th Rd N",
    "iso:country":"US",
    "sg:address":"5062 26th Rd N",
    "sg:city":"Arlington",
    "sg:classifiers":[
        {
            "category":"Professional",
            "subcategory":"Lawyer & Legal Services",
            "type":"Services"
        }
    ],
    "sg:phone":"+1 703 534 6716",
    "sg:postcode":"22207",
    "sg:province":"VA",
    "wof:name":"Matthews Stephen P Atty",
    "wof:placetype":"venue"
},
  "geometry": {"coordinates":[-77.135454,38.900604],"type":"Point"}
}