{
  "type": "Feature",
  "properties": {
    "addr:full":"4026 George Washington Memorial Hwy Yorktown VA 23692",
    "addr:housenumber":"4026",
    "addr:postcode":"23692",
    "addr:street":"George Washington Memorial Hwy",
    "iso:country":"US",
    "sg:address":"4026 George Washington Memorial Hwy",
    "sg:city":"Yorktown",
    "sg:classifiers":[
        {
            "category":"Personal",
            "subcategory":"Beauty Salon",
            "type":"Services"
        }
    ],
    "sg:phone":"+1 757 833 8876",
    "sg:postcode":"23692",
    "sg:province":"VA",
    "wof:name":"Turning Heads",
    "wof:placetype":"venue"
},
  "geometry": {"coordinates":[-76.456868,37.142166],"type":"Point"}
}