{
  "type": "Feature",
  "properties": {
    "addr:full":"8900 Portner Ave Manassas VA 20110",
    "addr:postcode":"8900;20110",
    "addr:street":"Portner Ave",
    "iso:country":"US",
    "sg:address":"8900 Portner Ave",
    "sg:city":"Manassas",
    "sg:classifiers":[
        {
            "category":"Organizations",
            "subcategory":"Religious Organization",
            "type":"Services"
        }
    ],
    "sg:phone":"+1 703 369 1222",
    "sg:postcode":"20110",
    "sg:province":"VA",
    "sg:tags":[
        "church"
    ],
    "wof:name":"Church Of God-Souls Harbor",
    "wof:placetype":"venue"
},
  "geometry": {"coordinates":[-77.464574,38.763014],"type":"Point"}
}