{
  "type": "Feature",
  "properties": {
    "addr:full":"15358 Brandy Rd Culpeper VA 22701",
    "addr:housenumber":"15358",
    "addr:postcode":"22701",
    "addr:street":"Brandy Rd",
    "iso:country":"US",
    "sg:address":"15358 Brandy Rd",
    "sg:city":"Culpeper",
    "sg:classifiers":[
        {
            "category":"Wholesale",
            "subcategory":"Hardware",
            "type":"Manufacturing & Wholesale Goods"
        }
    ],
    "sg:phone":"+1 540 825 4646",
    "sg:postcode":"22701",
    "sg:province":"VA",
    "sg:tags":[
        "plumbing",
        "fixture",
        "supply"
    ],
    "wof:name":"Noland Co",
    "wof:placetype":"venue"
},
  "geometry": {"coordinates":[-77.96445900000001,38.485978],"type":"Point"}
}