{
  "type": "Feature",
  "properties": {
    "iso:country":"US",
    "sg:address":"8623 Burling Wood Dr",
    "sg:city":"Springfield",
    "sg:classifiers":[
        {
            "category":"Retail",
            "subcategory":"Repair Shop",
            "type":"Services"
        }
    ],
    "sg:phone":"+1 703 451 1005",
    "sg:postcode":"22152",
    "sg:province":"VA",
    "sg:tags":[
        "electrical"
    ],
    "wof:name":"Appliance Service Depot",
    "wof:placetype":"venue"
},
  "geometry": {"coordinates":[-77.24086200000001,38.779177],"type":"Point"}
}