{
  "type": "Feature",
  "properties": {
    "iso:country":"US",
    "sg:address":"334 Cedar Meadow Dr",
    "sg:city":"Nellysford",
    "sg:classifiers":[
        {
            "category":"Professional",
            "subcategory":"Engineering",
            "type":"Services"
        }
    ],
    "sg:phone":"+1 434 361 9023",
    "sg:postcode":"22958",
    "sg:province":"VA",
    "sg:tags":[
        "technical"
    ],
    "wof:name":"Ultra Mac",
    "wof:placetype":"venue"
},
  "geometry": {"coordinates":[-78.884557,37.893122],"type":"Point"}
}