{
  "type": "Feature",
  "properties": {
    "iso:country":"US",
    "sg:address":"1086 Elden St",
    "sg:city":"Herndon",
    "sg:classifiers":[
        {
            "category":"Professional",
            "subcategory":"Management & Consulting",
            "type":"Services"
        }
    ],
    "sg:phone":"+1 703 435 6830",
    "sg:postcode":"20170",
    "sg:province":"VA",
    "sg:tags":[
        "consultant",
        "energy",
        "conservation"
    ],
    "wof:name":"Herndon Neighborhood Resources",
    "wof:placetype":"venue"
},
  "geometry": {"coordinates":[-77.39549700000001,38.968036],"type":"Point"}
}