{
  "type": "Feature",
  "properties": {
    "addr:full":"225 Beachside Cove Locust Grove VA 22508",
    "addr:housenumber":"225",
    "addr:postcode":"22508",
    "addr:street":"Beachside Cove",
    "iso:country":"US",
    "sg:address":"225 Beachside Cove",
    "sg:city":"Locust Grove",
    "sg:classifiers":[
        {
            "category":"Professional",
            "type":"Services"
        }
    ],
    "sg:phone":"+1 540 972 9444",
    "sg:postcode":"22508",
    "sg:province":"VA",
    "sg:tags":[
        "establishment"
    ],
    "wof:name":"Lakescapes",
    "wof:placetype":"venue"
},
  "geometry": {"coordinates":[-77.752859,38.341025],"type":"Point"}
}