{
  "type": "Feature",
  "properties": {
    "iso:country":"US",
    "sg:address":"101 S Whiting St",
    "sg:city":"Alexandria",
    "sg:classifiers":[
        {
            "category":"Social Services",
            "type":"Services"
        }
    ],
    "sg:phone":"+1 703 370 7140",
    "sg:postcode":"22304",
    "sg:province":"VA",
    "sg:tags":[
        "agency",
        "adoption"
    ],
    "wof:name":"A Loving Family",
    "wof:placetype":"venue"
},
  "geometry": {"coordinates":[-77.137207,38.813406],"type":"Point"}
}