{
  "type": "Feature",
  "properties": {
    "iso:country":"US",
    "sg:address":"10753 Jefferson Ave",
    "sg:city":"Newport News",
    "sg:classifiers":[
        {
            "category":"Restaurant",
            "type":"Food & Drink"
        }
    ],
    "sg:menulink":"http://www.allmenus.com/va/newport-news/42379-sam--steves-house-of-beef/menu/",
    "sg:phone":"+1 757 595 3441",
    "sg:postcode":"23601",
    "sg:province":"VA",
    "sg:tags":[
        "american",
        "steakhouse"
    ],
    "wof:name":"Sam & Steve's House of Beef",
    "wof:placetype":"venue"
},
  "geometry": {"coordinates":[-76.46207,37.053142],"type":"Point"}
}