{
  "type": "Feature",
  "properties": {
    "addr:full":"900 Asbury Ave Norfolk VA 23513",
    "addr:housenumber":"900",
    "addr:postcode":"23513",
    "addr:street":"Asbury Ave",
    "iso:country":"US",
    "sg:address":"900 Asbury Ave",
    "sg:city":"Norfolk",
    "sg:classifiers":[
        {
            "category":"Education",
            "subcategory":"School",
            "type":"Public Place"
        }
    ],
    "sg:phone":"+1 757 852 4570",
    "sg:postcode":"23513",
    "sg:province":"VA",
    "sg:tags":[
        "elementary"
    ],
    "wof:name":"Oakwood Elementary School",
    "wof:placetype":"venue"
},
  "geometry": {"coordinates":[-76.250128,36.911904],"type":"Point"}
}