{
  "type": "Feature",
  "properties": {
    "iso:country":"US",
    "sg:address":"4400 Williamsburg Ave",
    "sg:city":"Richmond",
    "sg:classifiers":[
        {
            "category":"Wholesale",
            "subcategory":"Groceries",
            "type":"Manufacturing & Wholesale Goods"
        }
    ],
    "sg:phone":"+1 804 222 1600",
    "sg:postcode":"23231",
    "sg:province":"VA",
    "sg:tags":[
        "extract",
        "flavoring"
    ],
    "wof:name":"Mafco Natural Products",
    "wof:placetype":"venue"
},
  "geometry": {"coordinates":[-77.410563,37.519135],"type":"Point"}
}