{
  "type": "Feature",
  "properties": {
    "iso:country":"US",
    "sg:address":"1201 1st St",
    "sg:city":"Radford",
    "sg:classifiers":[
        {
            "category":"Retail",
            "subcategory":"Auto Repair",
            "type":"Services"
        }
    ],
    "sg:phone":"+1 540 633 3000",
    "sg:postcode":"24141",
    "sg:province":"VA",
    "sg:tags":[
        "general"
    ],
    "wof:name":"Bb Auto Repair",
    "wof:placetype":"venue"
},
  "geometry": {"coordinates":[-80.587063,37.125909],"type":"Point"}
}