{
  "type": "Feature",
  "properties": {
    "addr:full":"603 Vicar Rd Danville VA 24540",
    "addr:housenumber":"603",
    "addr:postcode":"24540",
    "addr:street":"Vicar Rd",
    "iso:country":"US",
    "sg:address":"603 Vicar Rd",
    "sg:city":"Danville",
    "sg:classifiers":[
        {
            "category":"Professional",
            "subcategory":"Business Services",
            "type":"Services"
        }
    ],
    "sg:phone":"+1 434 836 6051",
    "sg:postcode":"24540",
    "sg:province":"VA",
    "wof:name":"T&B Diversified Inc",
    "wof:placetype":"venue"
},
  "geometry": {"coordinates":[-79.400471,36.640861],"type":"Point"}
}