{
  "type": "Feature",
  "properties": {
    "iso:country":"US",
    "sg:address":"3812 Main St",
    "sg:city":"Chincoteague",
    "sg:classifiers":[
        {
            "category":"Building & Trades",
            "subcategory":"Construction",
            "type":"Services"
        }
    ],
    "sg:phone":"+1 757 787 8833",
    "sg:postcode":"23336",
    "sg:province":"VA",
    "sg:tags":[
        "general",
        "contractor"
    ],
    "wof:name":"Spangler Construction Inc",
    "wof:placetype":"venue"
},
  "geometry": {"coordinates":[-75.381788,37.930469],"type":"Point"}
}