{
  "type": "Feature",
  "properties": {
    "addr:full":"24 Zion Park Rd Troy VA 22974",
    "addr:housenumber":"24",
    "addr:postcode":"22974",
    "addr:street":"Zion Park Rd",
    "iso:country":"US",
    "sg:address":"24 Zion Park Rd",
    "sg:city":"Troy",
    "sg:classifiers":[
        {
            "category":"Building & Trades",
            "subcategory":"Construction",
            "type":"Services"
        }
    ],
    "sg:phone":"+1 434 591 1222",
    "sg:postcode":"22974",
    "sg:province":"VA",
    "wof:name":"Ashlawn Woodworks Ltd",
    "wof:placetype":"venue"
},
  "geometry": {"coordinates":[-78.21440699999999,37.967804],"type":"Point"}
}