{
  "type": "Feature",
  "properties": {
    "addr:full":"2601 Brookforest Ter Midlothian VA 23112",
    "addr:housenumber":"2601",
    "addr:postcode":"23112",
    "addr:street":"Brookforest Ter",
    "iso:country":"US",
    "sg:address":"2601 Brookforest Ter",
    "sg:city":"Midlothian",
    "sg:classifiers":[
        {
            "category":"Manufacturing",
            "subcategory":"Watercraft",
            "type":"Manufacturing & Wholesale Goods"
        }
    ],
    "sg:phone":"+1 804 763 1569",
    "sg:postcode":"23112",
    "sg:province":"VA",
    "wof:name":"Browders Mobile Boat Repair",
    "wof:placetype":"venue"
},
  "geometry": {"coordinates":[-77.610573,37.454492],"type":"Point"}
}