{
  "type": "Feature",
  "properties": {
    "addr:full":"1989 Jake Sears Rd Virginia Beach VA 23464",
    "addr:housenumber":"1989",
    "addr:postcode":"23464",
    "addr:street":"Jake Sears Rd",
    "iso:country":"US",
    "sg:address":"1989 Jake Sears Rd",
    "sg:city":"Virginia Beach",
    "sg:classifiers":[
        {
            "category":"Utilities",
            "subcategory":"Refuse",
            "type":"Services"
        }
    ],
    "sg:phone":"+1 757 366 4560",
    "sg:postcode":"23464",
    "sg:province":"VA",
    "sg:tags":[
        "executive",
        "system"
    ],
    "wof:name":"Public Works Dept",
    "wof:placetype":"venue"
},
  "geometry": {"coordinates":[-76.201273,36.790389],"type":"Point"}
}