{
  "type": "Feature",
  "properties": {
    "iso:country":"US",
    "sg:address":"3830 Mt. Vernon Ave.",
    "sg:city":"Alexandria",
    "sg:classifiers":[
        {
            "category":"Restaurant",
            "type":"Food & Drink"
        }
    ],
    "sg:phone":"+1 703 535 8080",
    "sg:postcode":"22305",
    "sg:province":"VA",
    "sg:tags":[
        "chinese"
    ],
    "wof:name":"Jerry's Chan's Restaurant",
    "wof:placetype":"venue"
},
  "geometry": {"coordinates":[-77.0628,38.839703],"type":"Point"}
}