{
  "type": "Feature",
  "properties": {
    "iso:country":"US",
    "sg:address":"4412 Chantilly Pl",
    "sg:city":"Chantilly",
    "sg:classifiers":[
        {
            "category":"Restaurant",
            "type":"Food & Drink"
        }
    ],
    "sg:menulink":"http://www.allmenus.com/va/sully/179440-chick-fil-a/menu/",
    "sg:phone":"+1 703 631 2253",
    "sg:postcode":"20151",
    "sg:province":"VA",
    "sg:tags":[
        "wrap",
        "soup",
        "american",
        "sandwich",
        "salad"
    ],
    "wof:name":"Chick-fil-A",
    "wof:placetype":"venue"
},
  "geometry": {"coordinates":[-77.44462300000001,38.887485],"type":"Point"}
}