{
  "type": "Feature",
  "properties": {
    "addr:full":"688 Highland Ave Waynesboro VA 22980",
    "addr:housenumber":"688",
    "addr:postcode":"22980",
    "addr:street":"Highland Ave",
    "iso:country":"US",
    "sg:address":"688 Highland Ave",
    "sg:city":"Waynesboro",
    "sg:classifiers":[
        {
            "category":"Organizations",
            "subcategory":"Religious Organization",
            "type":"Services"
        }
    ],
    "sg:phone":"+1 540 943 3071",
    "sg:postcode":"22980",
    "sg:province":"VA",
    "sg:tags":[
        "church"
    ],
    "wof:name":"Glovier Memorial Methodist Chr",
    "wof:placetype":"venue"
},
  "geometry": {"coordinates":[-78.882842,38.077368],"type":"Point"}
}