{
  "type": "Feature",
  "properties": {
    "addr:full":"1252 Concord Ave Richmond VA 23228",
    "addr:housenumber":"1252",
    "addr:postcode":"23228",
    "addr:street":"Concord Ave",
    "iso:country":"US",
    "sg:address":"1252 Concord Ave",
    "sg:city":"Richmond",
    "sg:classifiers":[
        {
            "category":"Shopping",
            "subcategory":"Computers & Home Electronics",
            "type":"Retail Goods"
        }
    ],
    "sg:phone":"+1 804 262 9026",
    "sg:postcode":"23228",
    "sg:province":"VA",
    "sg:tags":[
        "personal",
        "hardware"
    ],
    "wof:name":"Ntk Computer Corp",
    "wof:placetype":"venue"
},
  "geometry": {"coordinates":[-77.460904,37.636241],"type":"Point"}
}