{
  "type": "Feature",
  "properties": {
    "addr:full":"941 Canal Dr Chesapeake VA 23323",
    "addr:housenumber":"941",
    "addr:postcode":"23323",
    "addr:street":"Canal Dr",
    "iso:country":"US",
    "sg:address":"941 Canal Dr",
    "sg:city":"Chesapeake",
    "sg:classifiers":[
        {
            "category":"Sports & Exercise",
            "subcategory":"Gym",
            "type":"Entertainment"
        }
    ],
    "sg:phone":"+1 757 487 4211",
    "sg:postcode":"23323",
    "sg:province":"VA",
    "sg:tags":[
        "facility",
        "club",
        "gymnasium",
        "health",
        "fitness",
        "studio",
        "physical"
    ],
    "wof:name":"Power Shack Gym",
    "wof:placetype":"venue"
},
  "geometry": {"coordinates":[-76.325182,36.775758],"type":"Point"}
}