{
  "type": "Feature",
  "properties": {
    "addr:full":"512 Powell Ave E Big Stone Gap VA 24219",
    "addr:housenumber":"512",
    "addr:postcode":"24219",
    "addr:street":"Powell Ave E",
    "iso:country":"US",
    "sg:address":"512 Powell Ave E",
    "sg:city":"Big Stone Gap",
    "sg:classifiers":[
        {
            "category":"Shopping",
            "subcategory":"Optical Goods",
            "type":"Retail Goods"
        }
    ],
    "sg:phone":"+1 276 523 3524",
    "sg:postcode":"24219",
    "sg:province":"VA",
    "sg:tags":[
        "optician"
    ],
    "wof:name":"Tri City Opticians",
    "wof:placetype":"venue"
},
  "geometry": {"coordinates":[-82.77615400000001,36.86994],"type":"Point"}
}