{
  "type": "Feature",
  "properties": {
    "addr:full":"200 E Fudge St Covington VA 24426",
    "addr:housenumber":"200",
    "addr:postcode":"24426",
    "addr:street":"E Fudge St",
    "iso:country":"US",
    "sg:address":"200 E Fudge St",
    "sg:city":"Covington",
    "sg:classifiers":[
        {
            "category":"Organizations",
            "subcategory":"Religious Organization",
            "type":"Services"
        }
    ],
    "sg:phone":"+1 540 965 3641",
    "sg:postcode":"24426",
    "sg:province":"VA",
    "wof:name":"Christ United Methodist Church",
    "wof:placetype":"venue"
},
  "geometry": {"coordinates":[-79.99017000000001,37.789453],"type":"Point"}
}