{
  "type": "Feature",
  "properties": {
    "addr:full":"537 Brentwood Dr Covington VA 24426",
    "addr:housenumber":"537",
    "addr:postcode":"24426",
    "addr:street":"Brentwood Dr",
    "iso:country":"US",
    "sg:address":"537 Brentwood Dr",
    "sg:city":"Covington",
    "sg:classifiers":[
        {
            "category":"Organizations",
            "subcategory":"Religious Organization",
            "type":"Services"
        }
    ],
    "sg:phone":"+1 540 962 6334",
    "sg:postcode":"24426",
    "sg:province":"VA",
    "sg:tags":[
        "clergy"
    ],
    "wof:name":"Billy Price",
    "wof:placetype":"venue"
},
  "geometry": {"coordinates":[-79.971952,37.766029],"type":"Point"}
}