{
  "type": "Feature",
  "properties": {
    "addr:full":"111 Willow Oaks Rd Richmond VA 23238",
    "addr:housenumber":"111",
    "addr:postcode":"23238",
    "addr:street":"Willow Oaks Rd",
    "iso:country":"US",
    "sg:address":"111 Willow Oaks Rd",
    "sg:city":"Richmond",
    "sg:classifiers":[
        {
            "category":"Shopping",
            "subcategory":"Computers & Home Electronics",
            "type":"Retail Goods"
        }
    ],
    "sg:phone":"+1 804 784 0225",
    "sg:postcode":"23238",
    "sg:province":"VA",
    "wof:name":"Trinity Computers",
    "wof:placetype":"venue"
},
  "geometry": {"coordinates":[-77.684398,37.59653],"type":"Point"}
}