{
  "type": "Feature",
  "properties": {
    "addr:full":"100 Pratt St Chesapeake VA 23324",
    "addr:housenumber":"100",
    "addr:postcode":"23324",
    "addr:street":"Pratt St",
    "iso:country":"US",
    "sg:address":"100 Pratt St",
    "sg:city":"Chesapeake",
    "sg:classifiers":[
        {
            "category":"Manufacturing",
            "subcategory":"Glass & Minerals",
            "type":"Manufacturing & Wholesale Goods"
        }
    ],
    "sg:phone":"+1 757 545 2481",
    "sg:postcode":"23324",
    "sg:province":"VA",
    "sg:tags":[
        "hydraulic",
        "cement",
        "mfg"
    ],
    "wof:name":"Blue Circle Cement",
    "wof:placetype":"venue"
},
  "geometry": {"coordinates":[-76.302778,36.780589],"type":"Point"}
}