{
  "type": "Feature",
  "properties": {
    "addr:full":"8696 Trenton Chapel Way Manassas VA 20109",
    "addr:housenumber":"8696",
    "addr:postcode":"20109",
    "addr:street":"Trenton Chapel Way",
    "iso:country":"US",
    "sg:address":"8696 Trenton Chapel Way",
    "sg:city":"Manassas",
    "sg:classifiers":[
        {
            "category":"Building & Trades",
            "subcategory":"Construction",
            "type":"Services"
        }
    ],
    "sg:phone":"+1 703 530 0222",
    "sg:postcode":"20109",
    "sg:province":"VA",
    "sg:tags":[
        "concrete",
        "contractor"
    ],
    "wof:name":"A J Concrete",
    "wof:placetype":"venue"
},
  "geometry": {"coordinates":[-77.551146,38.768082],"type":"Point"}
}