{
  "type": "Feature",
  "properties": {
    "iso:country":"US",
    "sg:address":"740 Shields Rd",
    "sg:city":"Newport News",
    "sg:classifiers":[
        {
            "category":"Retail",
            "subcategory":"Auto Repair",
            "type":"Services"
        }
    ],
    "sg:phone":"+1 757 877 4791",
    "sg:postcode":"23608",
    "sg:province":"VA",
    "sg:tags":[
        "repairing",
        "automobile",
        "general"
    ],
    "wof:name":"Castillo's Garage",
    "wof:placetype":"venue"
},
  "geometry": {"coordinates":[-76.533325,37.164448],"type":"Point"}
}