{
  "type": "Feature",
  "properties": {
    "iso:country":"US",
    "sg:address":"501 James Madison St",
    "sg:city":"Remington",
    "sg:classifiers":[
        {
            "category":"Government",
            "subcategory":"Post Office",
            "type":"Public Place"
        }
    ],
    "sg:phone":"+1 540 439 3900",
    "sg:postcode":"22734",
    "sg:province":"VA",
    "wof:name":"US Post Office",
    "wof:placetype":"venue"
},
  "geometry": {"coordinates":[-77.806444,38.537337],"type":"Point"}
}