{
  "type": "Feature",
  "properties": {
    "addr:full":"275 Piney Forest Rd Danville VA 24540",
    "addr:housenumber":"275",
    "addr:postcode":"24540",
    "addr:street":"Piney Forest Rd",
    "iso:country":"US",
    "sg:address":"275 Piney Forest Rd",
    "sg:city":"Danville",
    "sg:classifiers":[
        {
            "category":"Shopping",
            "subcategory":"Bicycles & Sporting Goods",
            "type":"Retail Goods"
        }
    ],
    "sg:phone":"+1 434 793 1832",
    "sg:postcode":"24540",
    "sg:province":"VA",
    "sg:tags":[
        "repair",
        "nursery"
    ],
    "wof:name":"of Newman & Son Inc",
    "wof:placetype":"venue"
},
  "geometry": {"coordinates":[-79.413282,36.599333],"type":"Point"}
}