{
  "type": "Feature",
  "properties": {
    "addr:full":"7801 W Broad St Richmond VA 23294",
    "addr:housenumber":"7801",
    "addr:postcode":"23294",
    "addr:street":"W Broad St",
    "iso:country":"US",
    "sg:address":"7801 W Broad St",
    "sg:city":"Richmond",
    "sg:classifiers":[
        {
            "category":"Banks & Credit Unions",
            "subcategory":"Bank",
            "type":"Services"
        }
    ],
    "sg:phone":"+1 804 282 7938",
    "sg:postcode":"23294",
    "sg:province":"VA",
    "sg:tags":[
        "personal",
        "institution"
    ],
    "wof:name":"Citifinancial",
    "wof:placetype":"venue"
},
  "geometry": {"coordinates":[-77.52670999999999,37.622102],"type":"Point"}
}