{
  "type": "Feature",
  "properties": {
    "iso:country":"US",
    "sg:address":"3121 Lockheed Blvd",
    "sg:city":"Alexandria",
    "sg:classifiers":[
        {
            "category":"Retail",
            "subcategory":"Laundry & Dry Cleaning",
            "type":"Services"
        }
    ],
    "sg:phone":"+1 703 768 3351",
    "sg:postcode":"22306",
    "sg:province":"VA",
    "sg:tags":[
        "drycleaning",
        "plant"
    ],
    "wof:name":"Madison Cleaners",
    "wof:placetype":"venue"
},
  "geometry": {"coordinates":[-77.085204,38.759083],"type":"Point"}
}