{
  "type": "Feature",
  "properties": {
    "addr:full":"6300 Summerday Ct Burke VA 22015",
    "addr:postcode":"6300;22015",
    "addr:street":"Summerday Ct",
    "iso:country":"US",
    "sg:address":"6300 Summerday Ct",
    "sg:city":"Burke",
    "sg:classifiers":[
        {
            "category":"Professional",
            "subcategory":"Management & Consulting",
            "type":"Services"
        }
    ],
    "sg:phone":"+1 703 425 4659",
    "sg:postcode":"22015",
    "sg:province":"VA",
    "wof:name":"Trinity Consultants",
    "wof:placetype":"venue"
},
  "geometry": {"coordinates":[-77.287267,38.779077],"type":"Point"}
}