{
  "type": "Feature",
  "properties": {
    "iso:country":"US",
    "sg:address":"6331 S Kings Hwy",
    "sg:city":"Alexandria",
    "sg:classifiers":[
        {
            "category":"Restaurant",
            "type":"Food & Drink"
        }
    ],
    "sg:phone":"+1 703 768 2338",
    "sg:postcode":"22306",
    "sg:province":"VA",
    "sg:tags":[
        "chinese"
    ],
    "wof:name":"Bamboo Garden Restaurant",
    "wof:placetype":"venue"
},
  "geometry": {"coordinates":[-77.081731,38.779569],"type":"Point"}
}