{
  "type": "Feature",
  "properties": {
    "addr:full":"12532 Cubs Ln Ashland VA 23005",
    "addr:housenumber":"12532",
    "addr:postcode":"23005",
    "addr:street":"Cubs Ln",
    "iso:country":"US",
    "sg:address":"12532 Cubs Ln",
    "sg:city":"Ashland",
    "sg:classifiers":[
        {
            "category":"Health Services",
            "subcategory":"Nursing And Care Facility",
            "type":"Services"
        }
    ],
    "sg:phone":"+1 804 752 2205",
    "sg:postcode":"23005",
    "sg:province":"VA",
    "sg:tags":[
        "personal",
        "home"
    ],
    "wof:name":"Companion Extraordinary Nurse",
    "wof:placetype":"venue"
},
  "geometry": {"coordinates":[-77.493824,37.752599],"type":"Point"}
}