{
  "type": "Feature",
  "properties": {
    "iso:country":"US",
    "sg:address":"3103 Valley Ave",
    "sg:city":"Winchester",
    "sg:classifiers":[
        {
            "category":"Home & Garden",
            "subcategory":"Furniture",
            "type":"Retail Goods"
        }
    ],
    "sg:phone":"+1 540 545 8933",
    "sg:postcode":"22601",
    "sg:province":"VA",
    "wof:name":"Perfectly Comfortable",
    "wof:placetype":"venue"
},
  "geometry": {"coordinates":[-78.18966899999999,39.144135],"type":"Point"}
}