{
  "type": "Feature",
  "properties": {
    "addr:full":"6707 Williamson Rd Roanoke VA 24019",
    "addr:housenumber":"6707",
    "addr:postcode":"24019",
    "addr:street":"Williamson Rd",
    "iso:country":"US",
    "sg:address":"6707 Williamson Rd",
    "sg:city":"Roanoke",
    "sg:classifiers":[
        {
            "category":"Home & Garden",
            "subcategory":"Building Materials",
            "type":"Retail Goods"
        }
    ],
    "sg:phone":"+1 540 265 1217",
    "sg:postcode":"24019",
    "sg:province":"VA",
    "sg:tags":[
        "paint"
    ],
    "wof:name":"Duron Paints & Wallcoverings",
    "wof:placetype":"venue"
},
  "geometry": {"coordinates":[-79.95577299999999,37.33725],"type":"Point"}
}