{
  "type": "Feature",
  "properties": {
    "iso:country":"US",
    "sg:address":"1363 Chain Bridge Rd",
    "sg:city":"Mc Lean",
    "sg:classifiers":[
        {
            "category":"Home & Garden",
            "subcategory":"Carpets & Floor Coverings",
            "type":"Retail Goods"
        }
    ],
    "sg:phone":"+1 703 821 9022",
    "sg:postcode":"22101",
    "sg:province":"VA",
    "wof:name":"JFK Floor & Remodeling Inc",
    "wof:placetype":"venue"
},
  "geometry": {"coordinates":[-77.175735,38.936569],"type":"Point"}
}