{
  "type": "Feature",
  "properties": {
    "iso:country":"US",
    "sg:address":"1740 Euclid Ave",
    "sg:city":"Bristol",
    "sg:classifiers":[
        {
            "category":"Health Services",
            "subcategory":"Doctor",
            "type":"Services"
        }
    ],
    "sg:phone":"+1 276 466 2028",
    "sg:postcode":"24201",
    "sg:province":"VA",
    "wof:name":"James M Seaver DDS",
    "wof:placetype":"venue"
},
  "geometry": {"coordinates":[-82.201756,36.599064],"type":"Point"}
}