{
  "type": "Feature",
  "properties": {
    "addr:full":"711 E Liberty St Norfolk VA 23523",
    "addr:housenumber":"711",
    "addr:postcode":"23523",
    "addr:street":"E Liberty St",
    "iso:country":"US",
    "sg:address":"711 E Liberty St",
    "sg:city":"Norfolk",
    "sg:classifiers":[
        {
            "category":"Government",
            "subcategory":"Post Office",
            "type":"Public Place"
        }
    ],
    "sg:phone":"+1 757 543 3952",
    "sg:postcode":"23523",
    "sg:province":"VA",
    "sg:tags":[
        "postal",
        "us"
    ],
    "wof:name":"Berkley Station",
    "wof:placetype":"venue"
},
  "geometry": {"coordinates":[-76.27946,36.827755],"type":"Point"}
}