{
  "type": "Feature",
  "properties": {
    "iso:country":"US",
    "sg:address":"4812 Market Dr",
    "sg:city":"Newport News",
    "sg:classifiers":[
        {
            "category":"Professional",
            "subcategory":"Business Services",
            "type":"Services"
        }
    ],
    "sg:phone":"+1 757 244 6146",
    "sg:postcode":"23607",
    "sg:province":"VA",
    "sg:tags":[
        "trade",
        "exposition",
        "fair",
        "show"
    ],
    "wof:name":"Dunmar Exhibit Svc",
    "wof:placetype":"venue"
},
  "geometry": {"coordinates":[-76.422022,37.000405],"type":"Point"}
}