{
  "type": "Feature",
  "properties": {
    "iso:country":"US",
    "sg:address":"4403 20th St N",
    "sg:city":"Arlington",
    "sg:classifiers":[
        {
            "category":"Shopping",
            "type":"Retail Goods"
        }
    ],
    "sg:phone":"+1 703 312 9199",
    "sg:postcode":"22207",
    "sg:province":"VA",
    "sg:tags":[
        "merchandise"
    ],
    "sg:website":"http://www.yellowdoor.com",
    "wof:name":"Yellow Door Floral Design",
    "wof:placetype":"venue"
},
  "geometry": {"coordinates":[-77.114293,38.894969],"type":"Point"}
}