{
  "type": "Feature",
  "properties": {
    "addr:full":"2301 Plank Rd Fredericksburg VA 22401",
    "addr:housenumber":"2301",
    "addr:postcode":"22401",
    "addr:street":"Plank Rd",
    "iso:country":"US",
    "sg:address":"2301 Plank Rd",
    "sg:city":"Fredericksburg",
    "sg:classifiers":[
        {
            "category":"Autos & Motor Vehicles",
            "subcategory":"Fuel & Gas Station",
            "type":"Retail Goods"
        }
    ],
    "sg:phone":"+1 540 371 1660",
    "sg:postcode":"22401",
    "sg:province":"VA",
    "sg:tags":[
        "station",
        "gasoline"
    ],
    "wof:name":"Quick Stop 3",
    "wof:placetype":"venue"
},
  "geometry": {"coordinates":[-77.498036,38.29629],"type":"Point"}
}