{
  "type": "Feature",
  "properties": {
    "iso:country":"US",
    "sg:address":"2352 Virginia Beach Blvd",
    "sg:city":"Virginia Beach",
    "sg:classifiers":[
        {
            "category":"Food & Beverages",
            "subcategory":"Groceries & Convenience Stores",
            "type":"Retail Goods"
        }
    ],
    "sg:phone":"+1 757 463 5741",
    "sg:postcode":"23454",
    "sg:province":"VA",
    "sg:tags":[
        "grocer"
    ],
    "sg:website":"www.foodlion.com",
    "wof:name":"Food Lion",
    "wof:placetype":"venue"
},
  "geometry": {"coordinates":[-76.048327,36.841736],"type":"Point"}
}