{
  "type": "Feature",
  "properties": {
    "addr:full":"4613 Kellywood Dr Glen Allen VA 23060",
    "addr:housenumber":"4613",
    "addr:postcode":"23060",
    "addr:street":"Kellywood Dr",
    "iso:country":"US",
    "sg:address":"4613 Kellywood Dr",
    "sg:city":"Glen Allen",
    "sg:classifiers":[
        {
            "category":"Professional",
            "subcategory":"Management & Consulting",
            "type":"Services"
        }
    ],
    "sg:phone":"+1 804 968 5225",
    "sg:postcode":"23060",
    "sg:province":"VA",
    "sg:tags":[
        "business"
    ],
    "wof:name":"JP Doolittle Enterprises P C",
    "wof:placetype":"venue"
},
  "geometry": {"coordinates":[-77.54548699999999,37.652409],"type":"Point"}
}