{
  "type": "Feature",
  "properties": {
    "addr:full":"104 Lee Cir Locust Grove VA 22508",
    "addr:housenumber":"104",
    "addr:postcode":"22508",
    "addr:street":"Lee Cir",
    "iso:country":"US",
    "sg:address":"104 Lee Cir",
    "sg:city":"Locust Grove",
    "sg:classifiers":[
        {
            "category":"Professional",
            "subcategory":"Research",
            "type":"Services"
        }
    ],
    "sg:phone":"+1 540 972 3353",
    "sg:postcode":"22508",
    "sg:province":"VA",
    "sg:tags":[
        "development"
    ],
    "wof:name":"Jet Technologies Inc",
    "wof:placetype":"venue"
},
  "geometry": {"coordinates":[-77.768565,38.327593],"type":"Point"}
}