{
  "type": "Feature",
  "properties": {
    "addr:full":"2645 Peters Creek Rd NW Roanoke VA 24017",
    "addr:housenumber":"2645",
    "addr:postcode":"24017",
    "addr:street":"Peters Creek Rd Nw",
    "iso:country":"US",
    "sg:address":"2645 Peters Creek Rd NW",
    "sg:city":"Roanoke",
    "sg:classifiers":[
        {
            "category":"Shopping",
            "subcategory":"Clothing, Apparel, & Fashions",
            "type":"Retail Goods"
        }
    ],
    "sg:phone":"+1 540 562 4800",
    "sg:postcode":"24017",
    "sg:province":"VA",
    "sg:tags":[
        "family"
    ],
    "wof:name":"Cashwel Fashions",
    "wof:placetype":"venue"
},
  "geometry": {"coordinates":[-80.00528300000001,37.314382],"type":"Point"}
}