{
  "type": "Feature",
  "properties": {
    "addr:full":"11720 Sunset Hills Rd Reston VA 20190",
    "addr:housenumber":"11720",
    "addr:postcode":"20190",
    "addr:street":"Sunset Hills Rd",
    "iso:country":"US",
    "sg:address":"11720 Sunset Hills Rd",
    "sg:city":"Reston",
    "sg:classifiers":[
        {
            "category":"Retail",
            "subcategory":"Auto Repair",
            "type":"Services"
        }
    ],
    "sg:phone":"+1 703 689 9700",
    "sg:postcode":"20190",
    "sg:province":"VA",
    "sg:tags":[
        "muffler",
        "exhaust",
        "system"
    ],
    "wof:name":"Midas Auto Svc Experts",
    "wof:placetype":"venue"
},
  "geometry": {"coordinates":[-77.352065,38.955135],"type":"Point"}
}