{
  "type": "Feature",
  "properties": {
    "iso:country":"US",
    "sg:address":"109 University Blvd",
    "sg:city":"Harrisonburg",
    "sg:classifiers":[
        {
            "category":"Restaurant",
            "type":"Food & Drink"
        }
    ],
    "sg:menulink":"http://www.allmenus.com/va/harrisonburg/95319-ihop/menu/",
    "sg:phone":"+1 540 438 9251",
    "sg:postcode":"22801",
    "sg:province":"VA",
    "sg:tags":[
        "sandwich",
        "salad",
        "burger",
        "soup",
        "american",
        "steakhouse",
        "wrap"
    ],
    "wof:name":"IHOP",
    "wof:placetype":"venue"
},
  "geometry": {"coordinates":[-78.847934,38.429825],"type":"Point"}
}