{
  "type": "Feature",
  "properties": {
    "iso:country":"US",
    "sg:address":"12315 Leith Ct",
    "sg:city":"Woodbridge",
    "sg:classifiers":[
        {
            "category":"Professional",
            "subcategory":"Management & Consulting",
            "type":"Services"
        }
    ],
    "sg:phone":"+1 703 670 3863",
    "sg:postcode":"22192",
    "sg:province":"VA",
    "sg:tags":[
        "business"
    ],
    "wof:name":"La Guardai International",
    "wof:placetype":"venue"
},
  "geometry": {"coordinates":[-77.33797800000001,38.69116],"type":"Point"}
}