{
  "type": "Feature",
  "properties": {
    "addr:full":"4092 Foxwood Dr Virginia Beach VA 23462",
    "addr:housenumber":"4092",
    "addr:postcode":"23462",
    "addr:street":"Foxwood Dr",
    "iso:country":"US",
    "sg:address":"4092 Foxwood Dr",
    "sg:city":"Virginia Beach",
    "sg:classifiers":[
        {
            "category":"Professional",
            "subcategory":"Engineering",
            "type":"Services"
        }
    ],
    "sg:phone":"+1 757 467 3087",
    "sg:postcode":"23462",
    "sg:province":"VA",
    "sg:tags":[
        "engineer"
    ],
    "wof:name":"Mary Ann Mijares PE",
    "wof:placetype":"venue"
},
  "geometry": {"coordinates":[-76.115486,36.803943],"type":"Point"}
}