{
  "type": "Feature",
  "properties": {
    "addr:full":"645 Royal Palm Dr Virginia Beach VA 23452",
    "addr:housenumber":"645",
    "addr:postcode":"23452",
    "addr:street":"Royal Palm Dr",
    "iso:country":"US",
    "sg:address":"645 Royal Palm Dr",
    "sg:city":"Virginia Beach",
    "sg:classifiers":[
        {
            "category":"Building & Trades",
            "subcategory":"Cleaning & Sanitation",
            "type":"Services"
        }
    ],
    "sg:phone":"+1 757 464 4888",
    "sg:postcode":"23452",
    "sg:province":"VA",
    "sg:tags":[
        "interior",
        "paint",
        "clean",
        "exterior"
    ],
    "wof:name":"Aqua Force Inc",
    "wof:placetype":"venue"
},
  "geometry": {"coordinates":[-76.099962,36.854385],"type":"Point"}
}