{
  "type": "Feature",
  "properties": {
    "addr:full":"804 N Main St Hillsville VA 24343",
    "addr:housenumber":"804",
    "addr:postcode":"24343",
    "addr:street":"N Main St",
    "iso:country":"US",
    "sg:address":"804 N Main St",
    "sg:city":"Hillsville",
    "sg:classifiers":[
        {
            "category":"Communications",
            "type":"Services"
        }
    ],
    "sg:phone":"+1 276 728 4819",
    "sg:postcode":"24343",
    "sg:province":"VA",
    "sg:tags":[
        "communication"
    ],
    "wof:name":"Mountain View Communication",
    "wof:placetype":"venue"
},
  "geometry": {"coordinates":[-80.737801,36.767607],"type":"Point"}
}