{
  "type": "Feature",
  "properties": {
    "addr:full":"4443 Brookfield Corporate Dr Chantilly VA 20151",
    "addr:housenumber":"4443",
    "addr:postcode":"20151",
    "addr:street":"Brookfield Corporate Dr",
    "iso:country":"US",
    "sg:address":"4443 Brookfield Corporate Dr",
    "sg:city":"Chantilly",
    "sg:classifiers":[
        {
            "category":"Real Estate",
            "subcategory":"Real Estate Services",
            "type":"Services"
        }
    ],
    "sg:phone":"+1 703 263 1455",
    "sg:postcode":"20151",
    "sg:province":"VA",
    "sg:tags":[
        "company",
        "title"
    ],
    "wof:name":"Hazelwood Title & Escrow Corp",
    "wof:placetype":"venue"
},
  "geometry": {"coordinates":[-77.438641,38.886075],"type":"Point"}
}