{
  "type": "Feature",
  "properties": {
    "addr:full":"2500 Fairhaven Ave Alexandria VA 22303",
    "addr:housenumber":"2500",
    "addr:postcode":"22303",
    "addr:street":"Fairhaven Ave",
    "iso:country":"US",
    "sg:address":"2500 Fairhaven Ave",
    "sg:city":"Alexandria",
    "sg:classifiers":[
        {
            "category":"Wholesale",
            "subcategory":"Machinery & Supplies",
            "type":"Manufacturing & Wholesale Goods"
        }
    ],
    "sg:phone":"+1 703 898 4012",
    "sg:postcode":"22303",
    "sg:province":"VA",
    "sg:tags":[
        "equipment",
        "irrigation",
        "system"
    ],
    "wof:name":"Tony's Irrigation Inc",
    "wof:placetype":"venue"
},
  "geometry": {"coordinates":[-77.075068,38.785259],"type":"Point"}
}