{
  "type": "Feature",
  "properties": {
    "addr:full":"1741 Driftwood Ln SW Roanoke VA 24018",
    "addr:housenumber":"1741",
    "addr:postcode":"24018",
    "addr:street":"Driftwood Ln Sw",
    "iso:country":"US",
    "sg:address":"1741 Driftwood Ln SW",
    "sg:city":"Roanoke",
    "sg:classifiers":[
        {
            "category":"Professional",
            "subcategory":"Accounting & Tax Preparation",
            "type":"Services"
        }
    ],
    "sg:phone":"+1 540 774 3607",
    "sg:postcode":"24018",
    "sg:province":"VA",
    "sg:tags":[
        "return"
    ],
    "wof:name":"S&S Tax Service",
    "wof:placetype":"venue"
},
  "geometry": {"coordinates":[-80.030658,37.250237],"type":"Point"}
}