{
  "type": "Feature",
  "properties": {
    "addr:full":"810 Juniper Cres Chesapeake VA 23320",
    "addr:housenumber":"810",
    "addr:postcode":"23320",
    "addr:street":"Juniper Cres",
    "iso:country":"US",
    "sg:address":"810 Juniper Cres",
    "sg:city":"Chesapeake",
    "sg:classifiers":[
        {
            "category":"Building & Trades",
            "subcategory":"Plumbing",
            "type":"Services"
        }
    ],
    "sg:phone":"+1 757 487 7865",
    "sg:postcode":"23320",
    "sg:province":"VA",
    "sg:tags":[
        "air",
        "heating",
        "conditioning",
        "contractor"
    ],
    "wof:name":"Ricks Heating and AC",
    "wof:placetype":"venue"
},
  "geometry": {"coordinates":[-76.231922,36.794481],"type":"Point"}
}