{
  "type": "Feature",
  "properties": {
    "addr:full":"1663 Blue Ridge Blvd Troutville VA 24175",
    "addr:housenumber":"1663",
    "addr:postcode":"24175",
    "addr:street":"Blue Ridge Blvd",
    "iso:country":"US",
    "sg:address":"1663 Blue Ridge Blvd",
    "sg:city":"Troutville",
    "sg:classifiers":[
        {
            "category":"Shopping",
            "subcategory":"Pharmacy",
            "type":"Retail Goods"
        }
    ],
    "sg:phone":"+1 540 977 4224",
    "sg:postcode":"24175",
    "sg:province":"VA",
    "wof:name":"Blue Ridge Pharmacy Cundiff",
    "wof:placetype":"venue"
},
  "geometry": {"coordinates":[-79.845118,37.345902],"type":"Point"}
}