{
  "type": "Feature",
  "properties": {
    "iso:country":"US",
    "sg:address":"12018 Canter Ln",
    "sg:city":"Reston",
    "sg:classifiers":[
        {
            "category":"Professional",
            "subcategory":"Engineering",
            "type":"Services"
        }
    ],
    "sg:phone":"+1 703 620 6499",
    "sg:postcode":"20191",
    "sg:province":"VA",
    "wof:name":"Wein & Associates",
    "wof:placetype":"venue"
},
  "geometry": {"coordinates":[-77.36674499999999,38.923589],"type":"Point"}
}