{
  "type": "Feature",
  "properties": {
    "iso:country":"US",
    "sg:address":"1000 Westover Hills Blvd",
    "sg:city":"Richmond",
    "sg:classifiers":[
        {
            "category":"Education",
            "subcategory":"School",
            "type":"Public Place"
        }
    ],
    "sg:phone":"+1 804 377 8024",
    "sg:postcode":"23225",
    "sg:province":"VA",
    "sg:website":"www.richmondwaldorf.com",
    "wof:name":"Richmond Waldorf School",
    "wof:placetype":"venue"
},
  "geometry": {"coordinates":[-77.488388,37.517899],"type":"Point"}
}