{
  "type": "Feature",
  "properties": {
    "iso:country":"US",
    "sg:address":"2503 S Columbia Pike",
    "sg:city":"Arlington",
    "sg:classifiers":[
        {
            "category":"Shopping",
            "subcategory":"Music",
            "type":"Retail Goods"
        }
    ],
    "sg:phone":"+1 703 553 8516",
    "sg:postcode":"22204",
    "sg:province":"VA",
    "wof:name":"Flying Saucer Discs Inc",
    "wof:placetype":"venue"
},
  "geometry": {"coordinates":[-77.08509100000001,38.863124],"type":"Point"}
}