{
  "type": "Feature",
  "properties": {
    "addr:full":"1766 Scottsville Rd Charlottesville VA 22902",
    "addr:housenumber":"1766",
    "addr:postcode":"22902",
    "addr:street":"Scottsville Rd",
    "iso:country":"US",
    "sg:address":"1766 Scottsville Rd",
    "sg:city":"Charlottesville",
    "sg:classifiers":[
        {
            "category":"Autos & Motor Vehicles",
            "subcategory":"Auto Supplies",
            "type":"Retail Goods"
        }
    ],
    "sg:phone":"+1 434 295 4770",
    "sg:postcode":"22902",
    "sg:province":"VA",
    "sg:tags":[
        "tire"
    ],
    "wof:name":"J & J Tire Service",
    "wof:placetype":"venue"
},
  "geometry": {"coordinates":[-78.5009,37.9884],"type":"Point"}
}