{
  "type": "Feature",
  "properties": {
    "iso:country":"US",
    "sg:address":"6917 Quander Rd",
    "sg:city":"Alexandria",
    "sg:classifiers":[
        {
            "category":"Building & Trades",
            "subcategory":"Construction",
            "type":"Services"
        }
    ],
    "sg:phone":"+1 703 765 8472",
    "sg:postcode":"22307",
    "sg:province":"VA",
    "wof:name":"Mw Knight General Contr",
    "wof:placetype":"venue"
},
  "geometry": {"coordinates":[-77.065271,38.768232],"type":"Point"}
}