{
  "type": "Feature",
  "properties": {
    "addr:full":"1710 Springfield Ave Norfolk VA 23523",
    "addr:housenumber":"1710",
    "addr:postcode":"23523",
    "addr:street":"Springfield Ave",
    "iso:country":"US",
    "sg:address":"1710 Springfield Ave",
    "sg:city":"Norfolk",
    "sg:classifiers":[
        {
            "category":"Organizations",
            "subcategory":"Religious Organization",
            "type":"Services"
        }
    ],
    "sg:phone":"+1 757 543 3886",
    "sg:postcode":"23523",
    "sg:province":"VA",
    "sg:tags":[
        "place",
        "worship",
        "church"
    ],
    "wof:name":"Metropolitan A M E Zion",
    "wof:placetype":"venue"
},
  "geometry": {"coordinates":[-76.262252,36.833952],"type":"Point"}
}