{
  "type": "Feature",
  "properties": {
    "addr:full":"4707 Main St Drakes Branch VA 23937",
    "addr:housenumber":"4707",
    "addr:postcode":"23937",
    "addr:street":"Main St",
    "iso:country":"US",
    "sg:address":"4707 Main St",
    "sg:city":"Drakes Branch",
    "sg:classifiers":[
        {
            "category":"Food & Beverages",
            "subcategory":"Groceries & Convenience Stores",
            "type":"Retail Goods"
        }
    ],
    "sg:phone":"+1 434 568 5401",
    "sg:postcode":"23937",
    "sg:province":"VA",
    "wof:name":"Joy Foods",
    "wof:placetype":"venue"
},
  "geometry": {"coordinates":[-78.60139100000001,36.993074],"type":"Point"}
}