{
  "type": "Feature",
  "properties": {
    "iso:country":"US",
    "sg:address":"1126 Larchmont Cres",
    "sg:city":"Norfolk",
    "sg:classifiers":[
        {
            "category":"Health Services",
            "subcategory":"Health Practitioner",
            "type":"Services"
        }
    ],
    "sg:phone":"+1 757 287 5100",
    "sg:postcode":"23508",
    "sg:province":"VA",
    "wof:name":"Norfolk Speech & Language",
    "wof:placetype":"venue"
},
  "geometry": {"coordinates":[-76.302102,36.896011],"type":"Point"}
}