{
  "type": "Feature",
  "properties": {
    "addr:full":"6900 Susquehanna Rd Gainesville VA 20155",
    "addr:housenumber":"6900",
    "addr:postcode":"20155",
    "addr:street":"Susquehanna Rd",
    "iso:country":"US",
    "sg:address":"6900 Susquehanna Rd",
    "sg:city":"Gainesville",
    "sg:classifiers":[
        {
            "category":"Professional",
            "subcategory":"Management & Consulting",
            "type":"Services"
        }
    ],
    "sg:phone":"+1 703 753 3288",
    "sg:postcode":"20155",
    "sg:province":"VA",
    "wof:name":"Netstar Marketing",
    "wof:placetype":"venue"
},
  "geometry": {"coordinates":[-77.62785599999999,38.808139],"type":"Point"}
}