{
  "type": "Feature",
  "properties": {
    "addr:full":"389 S Main St Kilmarnock VA 22482",
    "addr:housenumber":"389",
    "addr:postcode":"22482",
    "addr:street":"S Main St",
    "iso:country":"US",
    "sg:address":"389 S Main St",
    "sg:city":"Kilmarnock",
    "sg:classifiers":[
        {
            "category":"Personal",
            "subcategory":"Beauty Salon",
            "type":"Services"
        }
    ],
    "sg:phone":"+1 804 435 8785",
    "sg:postcode":"22482",
    "sg:province":"VA",
    "sg:tags":[
        "shop"
    ],
    "wof:name":"Nail Expo",
    "wof:placetype":"venue"
},
  "geometry": {"coordinates":[-76.376716,37.702083],"type":"Point"}
}