{
  "type": "Feature",
  "properties": {
    "addr:full":"3826 Virginia Beach Blvd Virginia Beach VA 23452",
    "addr:housenumber":"3826",
    "addr:postcode":"23452",
    "addr:street":"Virginia Beach Blvd",
    "iso:country":"US",
    "sg:address":"3826 Virginia Beach Blvd",
    "sg:city":"Virginia Beach",
    "sg:classifiers":[
        {
            "category":"Arts & Performance",
            "subcategory":"Theater",
            "type":"Entertainment"
        }
    ],
    "sg:phone":"+1 757 498 9866",
    "sg:postcode":"23452",
    "sg:province":"VA",
    "sg:tags":[
        "group"
    ],
    "wof:name":"American Males",
    "wof:placetype":"venue"
},
  "geometry": {"coordinates":[-76.108412,36.840188],"type":"Point"}
}