{
  "type": "Feature",
  "properties": {
    "iso:country":"US",
    "sg:address":"5001 Seminary Rd Ste 116",
    "sg:city":"Alexandria",
    "sg:classifiers":[
        {
            "category":"Health Services",
            "subcategory":"Doctor",
            "type":"Services"
        }
    ],
    "sg:phone":"+1 703 931 2164",
    "sg:postcode":"22311",
    "sg:province":"VA",
    "wof:name":"Daneshvar Hafez MD",
    "wof:placetype":"venue"
},
  "geometry": {"coordinates":[-77.11599699999999,38.833199],"type":"Point"}
}