{
  "type": "Feature",
  "properties": {
    "addr:full":"6901 Southridge Dr Mc Lean VA 22101",
    "addr:housenumber":"6901",
    "addr:postcode":"22101",
    "addr:street":"Southridge Dr",
    "iso:country":"US",
    "sg:address":"6901 Southridge Dr",
    "sg:city":"Mc Lean",
    "sg:classifiers":[
        {
            "category":"Professional",
            "subcategory":"Business Services",
            "type":"Services"
        }
    ],
    "sg:phone":"+1 703 821 3814",
    "sg:postcode":"22101",
    "sg:province":"VA",
    "wof:name":"Bubel Technologies",
    "wof:placetype":"venue"
},
  "geometry": {"coordinates":[-77.182571,38.920058],"type":"Point"}
}