{
  "type": "Feature",
  "properties": {
    "addr:full":"311 Jackson Dr Covington VA 24426",
    "addr:housenumber":"311",
    "addr:postcode":"24426",
    "addr:street":"Jackson Dr",
    "iso:country":"US",
    "sg:address":"311 Jackson Dr",
    "sg:city":"Covington",
    "sg:classifiers":[
        {
            "category":"Organizations",
            "subcategory":"Religious Organization",
            "type":"Services"
        }
    ],
    "sg:phone":"+1 540 962 6335",
    "sg:postcode":"24426",
    "sg:province":"VA",
    "wof:name":"Faith Baptist Church",
    "wof:placetype":"venue"
},
  "geometry": {"coordinates":[-79.967702,37.766447],"type":"Point"}
}