{
  "type": "Feature",
  "properties": {
    "iso:country":"US",
    "sg:address":"2772 S Randolph St 2798",
    "sg:city":"Arlington",
    "sg:classifiers":[
        {
            "category":"Cinema",
            "subcategory":"Movie Theater",
            "type":"Entertainment"
        }
    ],
    "sg:phone":"+1 703 671 0310",
    "sg:postcode":"22206",
    "sg:province":"VA",
    "wof:name":"Circle Shirlington Cinema 7",
    "wof:placetype":"venue"
},
  "geometry": {"coordinates":[-77.088689,38.841185],"type":"Point"}
}