{
  "type": "Feature",
  "properties": {
    "addr:full":"12012 Starboard Dr Reston VA 20194",
    "addr:housenumber":"12012",
    "addr:postcode":"20194",
    "addr:street":"Starboard Dr",
    "iso:country":"US",
    "sg:address":"12012 Starboard Dr",
    "sg:city":"Reston",
    "sg:classifiers":[
        {
            "category":"Shopping",
            "subcategory":"Bicycles & Sporting Goods",
            "type":"Retail Goods"
        }
    ],
    "sg:phone":"+1 703 438 8491",
    "sg:postcode":"20194",
    "sg:province":"VA",
    "wof:name":"All Sport Screenprinting",
    "wof:placetype":"venue"
},
  "geometry": {"coordinates":[-77.361116,38.966568],"type":"Point"}
}