{
  "type": "Feature",
  "properties": {
    "iso:country":"US",
    "sg:address":"7236 Beverly Park Dr",
    "sg:city":"Springfield",
    "sg:classifiers":[
        {
            "category":"Retail",
            "subcategory":"Repair Shop",
            "type":"Services"
        }
    ],
    "sg:phone":"+1 703 587 8284",
    "sg:postcode":"22150",
    "sg:province":"VA",
    "sg:tags":[
        "cleaning",
        "business"
    ],
    "wof:name":"New Horzion Cleaning Service",
    "wof:placetype":"venue"
},
  "geometry": {"coordinates":[-77.190302,38.76197],"type":"Point"}
}