{
  "type": "Feature",
  "properties": {
    "addr:full":"600 E Main St Richmond VA 23219",
    "addr:housenumber":"600",
    "addr:postcode":"23219",
    "addr:street":"E Main St",
    "iso:country":"US",
    "sg:address":"600 E Main St",
    "sg:city":"Richmond",
    "sg:classifiers":[
        {
            "category":"Professional",
            "subcategory":"Printing & Photocopies",
            "type":"Services"
        }
    ],
    "sg:phone":"+1 804 648 5300",
    "sg:postcode":"23219",
    "sg:province":"VA",
    "sg:tags":[
        "duplicating",
        "copying"
    ],
    "wof:name":"Document Technologies Inc",
    "wof:placetype":"venue"
},
  "geometry": {"coordinates":[-77.438104,37.539289],"type":"Point"}
}