{
  "type": "Feature",
  "properties": {
    "addr:full":"1101 Seminole Trl Charlottesville VA 22901",
    "addr:housenumber":"1101",
    "addr:postcode":"22901",
    "addr:street":"Seminole Trl",
    "iso:country":"US",
    "sg:address":"1101 Seminole Trl",
    "sg:city":"Charlottesville",
    "sg:classifiers":[
        {
            "category":"Restaurant",
            "type":"Food & Drink"
        }
    ],
    "sg:phone":"+1 434 973 3003",
    "sg:postcode":"22901",
    "sg:province":"VA",
    "sg:tags":[
        "eating"
    ],
    "wof:name":"CHI-Chis",
    "wof:placetype":"venue"
},
  "geometry": {"coordinates":[-78.48786699999999,38.06605],"type":"Point"}
}