{
  "type": "Feature",
  "properties": {
    "iso:country":"US",
    "sg:address":"3513 Beverly Dr",
    "sg:city":"Annandale",
    "sg:classifiers":[
        {
            "category":"Professional",
            "subcategory":"Management & Consulting",
            "type":"Services"
        }
    ],
    "sg:phone":"+1 703 573 6473",
    "sg:postcode":"22003",
    "sg:province":"VA",
    "sg:tags":[
        "consultant"
    ],
    "wof:name":"Cornick & Cornick Inc",
    "wof:placetype":"venue"
},
  "geometry": {"coordinates":[-77.23456400000001,38.84997],"type":"Point"}
}