{
  "type": "Feature",
  "properties": {
    "addr:full":"2535 Turkey Creek Rd Oilville VA 23146",
    "addr:housenumber":"2535",
    "addr:postcode":"23146",
    "addr:street":"Turkey Creek Rd",
    "iso:country":"US",
    "sg:address":"2535 Turkey Creek Rd",
    "sg:city":"Oilville",
    "sg:classifiers":[
        {
            "category":"Organizations",
            "subcategory":"Professional Association",
            "type":"Services"
        }
    ],
    "sg:phone":"+1 804 749 8191",
    "sg:postcode":"23146",
    "sg:province":"VA",
    "wof:name":"Va Assn-Volunteer Rescue Squad",
    "wof:placetype":"venue"
},
  "geometry": {"coordinates":[-77.773871,37.718318],"type":"Point"}
}