{
  "type": "Feature",
  "properties": {
    "addr:full":"2707 Williamsburg Rd Richmond VA 23231",
    "addr:housenumber":"2707",
    "addr:postcode":"23231",
    "addr:street":"Williamsburg Rd",
    "iso:country":"US",
    "sg:address":"2707 Williamsburg Rd",
    "sg:city":"Richmond",
    "sg:classifiers":[
        {
            "category":"Food & Beverages",
            "subcategory":"Groceries & Convenience Stores",
            "type":"Retail Goods"
        },
        {
            "category":"Autos & Motor Vehicles",
            "subcategory":"Fuel & Gas Station",
            "type":"Retail Goods"
        }
    ],
    "sg:phone":"+1 804 222 4486",
    "sg:postcode":"23231",
    "sg:province":"VA",
    "sg:tags":[
        "station",
        "gasoline"
    ],
    "wof:name":"Crown Central Petroleum",
    "wof:placetype":"venue"
},
  "geometry": {"coordinates":[-77.378551,37.518289],"type":"Point"}
}