{
  "type": "Feature",
  "properties": {
    "iso:country":"US",
    "sg:address":"13604 Old Dairy Rd",
    "sg:city":"Herndon",
    "sg:classifiers":[
        {
            "category":"Professional",
            "subcategory":"Art Services",
            "type":"Services"
        }
    ],
    "sg:phone":"+1 703 787 9320",
    "sg:postcode":"20171",
    "sg:province":"VA",
    "sg:tags":[
        "photographer"
    ],
    "wof:name":"Yee Yuen-GI",
    "wof:placetype":"venue"
},
  "geometry": {"coordinates":[-77.416257,38.906703],"type":"Point"}
}