{
  "type": "Feature",
  "properties": {
    "iso:country":"US",
    "sg:address":"7631 Fullerton Rd",
    "sg:city":"Springfield",
    "sg:classifiers":[
        {
            "category":"Manufacturing",
            "subcategory":"Printing",
            "type":"Manufacturing & Wholesale Goods"
        }
    ],
    "sg:phone":"+1 703 455 1119",
    "sg:postcode":"22153",
    "sg:province":"VA",
    "sg:tags":[
        "lithographic",
        "printer",
        "commercial"
    ],
    "wof:name":"Work Center Printing Inc",
    "wof:placetype":"venue"
},
  "geometry": {"coordinates":[-77.20413499999999,38.742607],"type":"Point"}
}