{
  "type": "Feature",
  "properties": {
    "addr:full":"4216 Benvenue Rd Haymarket VA 20169",
    "addr:housenumber":"4216",
    "addr:postcode":"20169",
    "addr:street":"Benvenue Rd",
    "iso:country":"US",
    "sg:address":"4216 Benvenue Rd",
    "sg:city":"Haymarket",
    "sg:classifiers":[
        {
            "category":"Building & Trades",
            "subcategory":"Construction",
            "type":"Services"
        }
    ],
    "sg:phone":"+1 703 753 0138",
    "sg:postcode":"20169",
    "sg:province":"VA",
    "sg:tags":[
        "contractor"
    ],
    "wof:name":"Vance Building Company",
    "wof:placetype":"venue"
},
  "geometry": {"coordinates":[-77.610001,38.873901],"type":"Point"}
}