{
  "type": "Feature",
  "properties": {
    "iso:country":"US",
    "sg:address":"140 Queen Mothers Ct",
    "sg:city":"Wirtz",
    "sg:classifiers":[
        {
            "category":"Real Estate",
            "subcategory":"Real Estate Agent",
            "type":"Services"
        }
    ],
    "sg:phone":"+1 540 721 2247",
    "sg:postcode":"24184",
    "sg:province":"VA",
    "wof:name":"Owens & Co Realtors",
    "wof:placetype":"venue"
},
  "geometry": {"coordinates":[-79.706649,37.05035],"type":"Point"}
}