{
  "type": "Feature",
  "properties": {
    "addr:full":"209 Plains View Rd Williamsburg VA 23188",
    "addr:housenumber":"209",
    "addr:postcode":"23188",
    "addr:street":"Plains View Rd",
    "iso:country":"US",
    "sg:address":"209 Plains View Rd",
    "sg:city":"Williamsburg",
    "sg:classifiers":[
        {
            "category":"Professional",
            "type":"Services"
        }
    ],
    "sg:phone":"+1 757 566 8236",
    "sg:postcode":"23188",
    "sg:province":"VA",
    "wof:name":"Richard F Wilke Jr",
    "wof:placetype":"venue"
},
  "geometry": {"coordinates":[-76.78001500000001,37.381737],"type":"Point"}
}