{
  "type": "Feature",
  "properties": {
    "addr:full":"6127 Harrison Rd Fredericksburg VA 22407",
    "addr:housenumber":"6127",
    "addr:postcode":"22407",
    "addr:street":"Harrison Rd",
    "iso:country":"US",
    "sg:address":"6127 Harrison Rd",
    "sg:city":"Fredericksburg",
    "sg:classifiers":[
        {
            "category":"Recreation",
            "type":"Entertainment"
        }
    ],
    "sg:phone":"+1 540 786 3600",
    "sg:postcode":"22407",
    "sg:province":"VA",
    "wof:name":"Quad J Farm",
    "wof:placetype":"venue"
},
  "geometry": {"coordinates":[-77.547194,38.273222],"type":"Point"}
}