{
  "type": "Feature",
  "properties": {
    "iso:country":"US",
    "sg:address":"623 Carlisle Dr",
    "sg:city":"Herndon",
    "sg:classifiers":[
        {
            "category":"Manufacturing",
            "subcategory":"Textiles",
            "type":"Manufacturing & Wholesale Goods"
        }
    ],
    "sg:phone":"+1 703 435 3174",
    "sg:postcode":"20170",
    "sg:province":"VA",
    "sg:tags":[
        "screen",
        "printing",
        "commercial"
    ],
    "sg:website":"www.fairfaxscreenprinting.com",
    "wof:name":"Fairfax Screen Printing",
    "wof:placetype":"venue"
},
  "geometry": {"coordinates":[-77.36921100000001,38.9649],"type":"Point"}
}