{
  "type": "Feature",
  "properties": {
    "iso:country":"US",
    "sg:address":"6250 Dumfries Rd",
    "sg:city":"Warrenton",
    "sg:classifiers":[
        {
            "category":"Social Services",
            "subcategory":"Child Care",
            "type":"Services"
        }
    ],
    "sg:phone":"+1 540 341 7785",
    "sg:postcode":"20187",
    "sg:province":"VA",
    "sg:tags":[
        "day"
    ],
    "wof:name":"Fauquier Community Child Care",
    "wof:placetype":"venue"
},
  "geometry": {"coordinates":[-77.764099,38.736698],"type":"Point"}
}