{
  "type": "Feature",
  "properties": {
    "addr:full":"241 Dominion Blvd S Chesapeake VA 23322",
    "addr:housenumber":"241",
    "addr:postcode":"23322",
    "addr:street":"Dominion Blvd",
    "iso:country":"US",
    "sg:address":"241 Dominion Blvd S",
    "sg:city":"Chesapeake",
    "sg:classifiers":[
        {
            "category":"Freight",
            "type":"Transportation"
        }
    ],
    "sg:phone":"+1 757 436 0444",
    "sg:postcode":"23322",
    "sg:province":"VA",
    "sg:tags":[
        "special"
    ],
    "wof:name":"Dominion Self Storage",
    "wof:placetype":"venue"
},
  "geometry": {"coordinates":[-76.299042,36.73169],"type":"Point"}
}