{
  "type": "Feature",
  "properties": {
    "addr:full":"820 Tight Squeeze Rd Chatham VA 24531",
    "addr:housenumber":"820",
    "addr:postcode":"24531",
    "addr:street":"Tight Squeeze Rd",
    "iso:country":"US",
    "sg:address":"820 Tight Squeeze Rd",
    "sg:city":"Chatham",
    "sg:classifiers":[
        {
            "category":"Manufacturing",
            "subcategory":"Paper Products",
            "type":"Manufacturing & Wholesale Goods"
        }
    ],
    "sg:phone":"+1 434 432 2310",
    "sg:postcode":"24531",
    "sg:province":"VA",
    "sg:tags":[
        "packaging",
        "container"
    ],
    "wof:name":"Sonoco Products Co",
    "wof:placetype":"venue"
},
  "geometry": {"coordinates":[-79.401225,36.78827],"type":"Point"}
}