{
  "type": "Feature",
  "properties": {
    "addr:full":"703 Swan View Drive Urbanna VA 23175",
    "addr:housenumber":"703",
    "addr:postcode":"23175",
    "addr:street":"Swan View Drive",
    "iso:country":"US",
    "sg:address":"703 Swan View Drive",
    "sg:city":"Urbanna",
    "sg:classifiers":[
        {
            "category":"Professional",
            "subcategory":"Computer Services",
            "type":"Services"
        }
    ],
    "sg:phone":"+1 415 335 4468",
    "sg:postcode":"23175",
    "sg:province":"VA",
    "sg:tags":[
        "digital-artist",
        "collaboration",
        "online-tools",
        "remote-media-groups"
    ],
    "sg:website":"http://www.gloomshade.com/",
    "wof:name":"Gloomshade",
    "wof:placetype":"venue"
},
  "geometry": {"coordinates":[-76.626115,37.677344],"type":"Point"}
}