{
  "type": "Feature",
  "properties": {
    "addr:full":"12740 Jefferson Ave Newport News VA 23602",
    "addr:housenumber":"12740",
    "addr:postcode":"23602",
    "addr:street":"Jefferson Ave",
    "iso:country":"US",
    "sg:address":"12740 Jefferson Ave",
    "sg:city":"Newport News",
    "sg:classifiers":[
        {
            "category":"Restaurant",
            "type":"Food & Drink"
        }
    ],
    "sg:menulink":"http://www.allmenus.com/va/newport-news/42314-sonic,-americas-drive-in/menu/",
    "sg:phone":"+1 757 988 8600",
    "sg:postcode":"23602",
    "sg:province":"VA",
    "sg:tags":[
        "american"
    ],
    "wof:name":"Sonic, America's Drive-In",
    "wof:placetype":"venue"
},
  "geometry": {"coordinates":[-76.518185,37.136408],"type":"Point"}
}