{
  "type": "Feature",
  "properties": {
    "iso:country":"US",
    "sg:address":"1590 Corporate Landing Pkwy",
    "sg:city":"Virginia Beach",
    "sg:classifiers":[
        {
            "category":"Education",
            "subcategory":"School",
            "type":"Public Place"
        }
    ],
    "sg:phone":"+1 757 437 4783",
    "sg:postcode":"23454",
    "sg:province":"VA",
    "sg:tags":[
        "elementary"
    ],
    "wof:name":"Corporate Lnding Elmntary Schl",
    "wof:placetype":"venue"
},
  "geometry": {"coordinates":[-76.00879399999999,36.787706],"type":"Point"}
}