{
  "type": "Feature",
  "properties": {
    "addr:full":"5200 Braywood Dr Centreville VA 20120",
    "addr:housenumber":"5200",
    "addr:postcode":"20120",
    "addr:street":"Braywood Dr",
    "iso:country":"US",
    "sg:address":"5200 Braywood Dr",
    "sg:city":"Centreville",
    "sg:classifiers":[
        {
            "category":"Local Transit",
            "type":"Transportation"
        }
    ],
    "sg:phone":"+1 703 266 0662",
    "sg:postcode":"20120",
    "sg:province":"VA",
    "sg:tags":[
        "airport"
    ],
    "wof:name":"A Dulles Taxi Sedan & Limo Co",
    "wof:placetype":"venue"
},
  "geometry": {"coordinates":[-77.445973,38.864922],"type":"Point"}
}