{
  "type": "Feature",
  "properties": {
    "addr:full":"1370 S Military Hwy Chesapeake VA 23320",
    "addr:housenumber":"1370",
    "addr:postcode":"23320",
    "addr:street":"S Military Hwy",
    "iso:country":"US",
    "sg:address":"1370 S Military Hwy",
    "sg:city":"Chesapeake",
    "sg:classifiers":[
        {
            "category":"Restaurant",
            "type":"Food & Drink"
        }
    ],
    "sg:menulink":"http://www.allmenus.com/va/chesapeake/71919-pizza-hut/menu/",
    "sg:phone":"+1 757 420 9105",
    "sg:postcode":"23320",
    "sg:province":"VA",
    "sg:tags":[
        "american",
        "pizza"
    ],
    "wof:name":"Pizza Hut",
    "wof:placetype":"venue"
},
  "geometry": {"coordinates":[-76.229784,36.800133],"type":"Point"}
}