{
  "type": "Feature",
  "properties": {
    "iso:country":"US",
    "sg:address":"401 N Main St",
    "sg:city":"Danville",
    "sg:classifiers":[
        {
            "category":"Shopping",
            "subcategory":"Hobbies, Toys, & Games",
            "type":"Retail Goods"
        }
    ],
    "sg:phone":"+1 434 799 8536",
    "sg:postcode":"24540",
    "sg:province":"VA",
    "wof:name":"R T Hobbies",
    "wof:placetype":"venue"
},
  "geometry": {"coordinates":[-79.38556199999999,36.594864],"type":"Point"}
}