{
  "type": "Feature",
  "properties": {
    "addr:full":"1372 Towne Sq Blvd NW Roanoke VA 24012",
    "addr:housenumber":"1372",
    "addr:postcode":"24012",
    "addr:street":"Towne Sq Blvd Nw",
    "iso:country":"US",
    "sg:address":"1372 Towne Sq Blvd NW",
    "sg:city":"Roanoke",
    "sg:classifiers":[
        {
            "category":"Shopping",
            "subcategory":"Stationery & Office Supplies",
            "type":"Retail Goods"
        }
    ],
    "sg:phone":"+1 540 265 0644",
    "sg:postcode":"24012",
    "sg:province":"VA",
    "wof:name":"Office Max",
    "wof:placetype":"venue"
},
  "geometry": {"coordinates":[-79.962076,37.318665],"type":"Point"}
}