{
  "type": "Feature",
  "properties": {
    "addr:full":"302 Shadow Woods Ln Rocky Mount VA 24151",
    "addr:housenumber":"302",
    "addr:postcode":"24151",
    "addr:street":"Shadow Woods Ln",
    "iso:country":"US",
    "sg:address":"302 Shadow Woods Ln",
    "sg:city":"Rocky Mount",
    "sg:classifiers":[
        {
            "category":"Building & Trades",
            "subcategory":"Landscaping Services",
            "type":"Services"
        }
    ],
    "sg:phone":"+1 540 483 9798",
    "sg:postcode":"24151",
    "sg:province":"VA",
    "sg:tags":[
        "landscape"
    ],
    "wof:name":"H&J Landscaping Inc",
    "wof:placetype":"venue"
},
  "geometry": {"coordinates":[-79.915995,36.960179],"type":"Point"}
}