{
  "type": "Feature",
  "properties": {
    "addr:full":"2017 Victory Blvd Yorktown VA 23693",
    "addr:housenumber":"2017",
    "addr:postcode":"23693",
    "addr:street":"Victory Blvd",
    "iso:country":"US",
    "sg:address":"2017 Victory Blvd",
    "sg:city":"Yorktown",
    "sg:classifiers":[
        {
            "category":"Organizations",
            "subcategory":"Religious Organization",
            "type":"Services"
        }
    ],
    "sg:phone":"+1 757 867 9625",
    "sg:postcode":"23693",
    "sg:province":"VA",
    "sg:tags":[
        "church"
    ],
    "wof:name":"Our Redeemer Lutheran Church",
    "wof:placetype":"venue"
},
  "geometry": {"coordinates":[-76.42497299999999,37.122793],"type":"Point"}
}