{
  "type": "Feature",
  "properties": {
    "iso:country":"US",
    "sg:address":"386 Maple Ave E",
    "sg:city":"Vienna",
    "sg:classifiers":[
        {
            "category":"Building & Trades",
            "subcategory":"Construction",
            "type":"Services"
        }
    ],
    "sg:phone":"+1 703 938 8303",
    "sg:postcode":"22180",
    "sg:province":"VA",
    "sg:tags":[
        "home",
        "contractor",
        "improvement",
        "remodeling",
        "residential"
    ],
    "wof:name":"C & D Home Improvements Inc",
    "wof:placetype":"venue"
},
  "geometry": {"coordinates":[-77.258349,38.90707],"type":"Point"}
}