{
  "type": "Feature",
  "properties": {
    "addr:full":"16064 Robert Terrell Rd Montpelier VA 23192",
    "addr:housenumber":"16064",
    "addr:postcode":"23192",
    "addr:street":"Robert Terrell Rd",
    "iso:country":"US",
    "sg:address":"16064 Robert Terrell Rd",
    "sg:city":"Montpelier",
    "sg:classifiers":[
        {
            "category":"Building & Trades",
            "subcategory":"Landscaping Services",
            "type":"Services"
        }
    ],
    "sg:phone":"+1 804 730 6563",
    "sg:postcode":"23192",
    "sg:province":"VA",
    "sg:tags":[
        "tree"
    ],
    "wof:name":"Ernie's Tree Svc",
    "wof:placetype":"venue"
},
  "geometry": {"coordinates":[-77.659542,37.841714],"type":"Point"}
}