{
  "type": "Feature",
  "properties": {
    "iso:country":"US",
    "sg:address":"206 3rd St",
    "sg:city":"Virginia Beach",
    "sg:classifiers":[
        {
            "category":"Professional",
            "subcategory":"Computer Services",
            "type":"Services"
        }
    ],
    "sg:phone":"+1 757 437 0035",
    "sg:postcode":"23451",
    "sg:province":"VA",
    "sg:tags":[
        "consultant",
        "designer"
    ],
    "wof:name":"Software Sciences Corp",
    "wof:placetype":"venue"
},
  "geometry": {"coordinates":[-75.97107200000001,36.832176],"type":"Point"}
}