{
  "type": "Feature",
  "properties": {
    "iso:country":"US",
    "sg:address":"212 70th St",
    "sg:city":"Virginia Beach",
    "sg:classifiers":[
        {
            "category":"Mining & Drilling",
            "type":"Manufacturing & Wholesale Goods"
        }
    ],
    "sg:phone":"+1 757 437 3097",
    "sg:postcode":"23451",
    "sg:province":"VA",
    "sg:tags":[
        "crude",
        "production",
        "gas"
    ],
    "wof:name":"Amerada Hess Corporation",
    "wof:placetype":"venue"
},
  "geometry": {"coordinates":[-75.990121,36.895461],"type":"Point"}
}