{
  "type": "Feature",
  "properties": {
    "iso:country":"US",
    "sg:address":"4818 Texas Ave",
    "sg:city":"Norfolk",
    "sg:classifiers":[
        {
            "category":"Organizations",
            "subcategory":"Religious Organization",
            "type":"Services"
        }
    ],
    "sg:phone":"+1 757 853 6560",
    "sg:postcode":"23513",
    "sg:province":"VA",
    "wof:name":"Little Creek Baptist Church",
    "wof:placetype":"venue"
},
  "geometry": {"coordinates":[-76.23428,36.886077],"type":"Point"}
}