{
  "type": "Feature",
  "properties": {
    "iso:country":"US",
    "sg:address":"1628 Ownby Ln",
    "sg:city":"Richmond",
    "sg:classifiers":[
        {
            "category":"Home & Garden",
            "subcategory":"Building Materials",
            "type":"Retail Goods"
        },
        {
            "category":"Retail",
            "subcategory":"Auto Repair",
            "type":"Services"
        }
    ],
    "sg:phone":"+1 804 288 2774",
    "sg:postcode":"23220",
    "sg:province":"VA",
    "sg:tags":[
        "glass",
        "window",
        "plate",
        "replacement"
    ],
    "wof:name":"Guardian Auto Glass",
    "wof:placetype":"venue"
},
  "geometry": {"coordinates":[-77.457026,37.565286],"type":"Point"}
}