{
  "type": "Feature",
  "properties": {
    "iso:country":"US",
    "sg:address":"106 E Luray Ave",
    "sg:city":"Alexandria",
    "sg:classifiers":[
        {
            "category":"Professional",
            "subcategory":"Management & Consulting",
            "type":"Services"
        }
    ],
    "sg:phone":"+1 703 548 2608",
    "sg:postcode":"22301",
    "sg:province":"VA",
    "wof:name":"Damond Osterhus",
    "wof:placetype":"venue"
},
  "geometry": {"coordinates":[-77.060109,38.817717],"type":"Point"}
}