{
  "type": "Feature",
  "properties": {
    "addr:full":"21 E Mellen St Hampton VA 23663",
    "addr:housenumber":"21",
    "addr:postcode":"23663",
    "addr:street":"E Mellen St",
    "iso:country":"US",
    "sg:address":"21 E Mellen St",
    "sg:city":"Hampton",
    "sg:classifiers":[
        {
            "category":"Social Services",
            "type":"Services"
        }
    ],
    "sg:phone":"+1 757 727 0808",
    "sg:postcode":"23663",
    "sg:province":"VA",
    "sg:tags":[
        "organization",
        "welfare"
    ],
    "wof:name":"Phoebus Improvement League",
    "wof:placetype":"venue"
},
  "geometry": {"coordinates":[-76.321794,37.018327],"type":"Point"}
}