{
  "type": "Feature",
  "properties": {
    "addr:full":"3923 16th St S Arlington VA 22204",
    "addr:housenumber":"3923",
    "addr:postcode":"22204",
    "addr:street":"16Th St S",
    "iso:country":"US",
    "sg:address":"3923 16th St S",
    "sg:city":"Arlington",
    "sg:classifiers":[
        {
            "category":"Professional",
            "subcategory":"Management & Consulting",
            "type":"Services"
        }
    ],
    "sg:phone":"+1 703 920 4002",
    "sg:postcode":"22204",
    "sg:province":"VA",
    "sg:tags":[
        "datum"
    ],
    "wof:name":"Clms",
    "wof:placetype":"venue"
},
  "geometry": {"coordinates":[-77.096333,38.854405],"type":"Point"}
}