{
  "type": "Feature",
  "properties": {
    "addr:full":"202 Huron Ave Lynchburg VA 24503",
    "addr:housenumber":"202",
    "addr:postcode":"24503",
    "addr:street":"Huron Ave",
    "iso:country":"US",
    "sg:address":"202 Huron Ave",
    "sg:city":"Lynchburg",
    "sg:classifiers":[
        {
            "category":"Manufacturing",
            "subcategory":"Wood Products",
            "type":"Manufacturing & Wholesale Goods"
        }
    ],
    "sg:phone":"+1 434 847 5388",
    "sg:postcode":"24503",
    "sg:province":"VA",
    "sg:tags":[
        "mfg"
    ],
    "wof:name":"Robert C Luse",
    "wof:placetype":"venue"
},
  "geometry": {"coordinates":[-79.159566,37.435042],"type":"Point"}
}