{
  "type": "Feature",
  "properties": {
    "addr:full":"21675 Cascades Pkwy Sterling VA 20166",
    "addr:housenumber":"21675",
    "addr:postcode":"20166",
    "addr:street":"Cascades Pkwy",
    "iso:country":"US",
    "sg:address":"21675 Cascades Pkwy",
    "sg:city":"Sterling",
    "sg:classifiers":[
        {
            "category":"Building & Trades",
            "subcategory":"Construction",
            "type":"Services"
        }
    ],
    "sg:phone":"+1 703 421 7722",
    "sg:postcode":"20166",
    "sg:province":"VA",
    "sg:tags":[
        "general",
        "contractor"
    ],
    "wof:name":"T & E Underground Construction",
    "wof:placetype":"venue"
},
  "geometry": {"coordinates":[-77.41212400000001,39.016752],"type":"Point"}
}