{
  "type": "Feature",
  "properties": {
    "addr:full":"6534 Amelia Springs Rd Jetersville VA 23002",
    "addr:housenumber":"6534",
    "addr:postcode":"23002",
    "addr:street":"Amelia Springs Rd",
    "iso:country":"US",
    "sg:address":"6534 Amelia Springs Rd",
    "sg:city":"Jetersville",
    "sg:classifiers":[
        {
            "category":"Freight",
            "type":"Transportation"
        }
    ],
    "sg:phone":"+1 804 561 6563",
    "sg:postcode":"23002",
    "sg:province":"VA",
    "sg:tags":[
        "hauling",
        "trucking"
    ],
    "wof:name":"Tatum's Hauling",
    "wof:placetype":"venue"
},
  "geometry": {"coordinates":[-78.11539,37.365663],"type":"Point"}
}