{
  "type": "Feature",
  "properties": {
    "addr:full":"22270 Guilford Dr Abingdon VA 24210",
    "addr:housenumber":"22270",
    "addr:postcode":"24210",
    "addr:street":"Guilford Dr",
    "iso:country":"US",
    "sg:address":"22270 Guilford Dr",
    "sg:city":"Abingdon",
    "sg:classifiers":[
        {
            "category":"Insurance",
            "subcategory":"Insurance Agent",
            "type":"Services"
        }
    ],
    "sg:phone":"+1 276 466 3361",
    "sg:postcode":"24210",
    "sg:province":"VA",
    "wof:name":"Ole Commonwealth Insurance",
    "wof:placetype":"venue"
},
  "geometry": {"coordinates":[-81.972444,36.731887],"type":"Point"}
}