{
  "type": "Feature",
  "properties": {
    "iso:country":"US",
    "sg:address":"1600 Prince St",
    "sg:city":"Alexandria",
    "sg:classifiers":[
        {
            "category":"Social Services",
            "subcategory":"Adult Care",
            "type":"Services"
        }
    ],
    "sg:phone":"+1 703 706 9595",
    "sg:postcode":"22314",
    "sg:province":"VA",
    "sg:tags":[
        "organization",
        "senior",
        "citizen"
    ],
    "wof:name":"Advanced Care Management Inc",
    "wof:placetype":"venue"
},
  "geometry": {"coordinates":[-77.05654199999999,38.805128],"type":"Point"}
}