{
  "type": "Feature",
  "properties": {
    "iso:country":"US",
    "sg:address":"17519 Beverly Run Rd",
    "sg:city":"Bowling Green",
    "sg:classifiers":[
        {
            "category":"Building & Trades",
            "subcategory":"Construction",
            "type":"Services"
        }
    ],
    "sg:phone":"+1 804 633 1496",
    "sg:postcode":"22427",
    "sg:province":"VA",
    "sg:tags":[
        "contractor"
    ],
    "wof:name":"Pier Pressure Construction",
    "wof:placetype":"venue"
},
  "geometry": {"coordinates":[-77.188368,38.008134],"type":"Point"}
}