{
  "type": "Feature",
  "properties": {
    "iso:country":"US",
    "sg:address":"5 Frye Ct",
    "sg:city":"Lovettsville",
    "sg:classifiers":[
        {
            "category":"Professional",
            "subcategory":"Management & Consulting",
            "type":"Services"
        }
    ],
    "sg:phone":"+1 540 822 5168",
    "sg:postcode":"20180",
    "sg:province":"VA",
    "sg:tags":[
        "business"
    ],
    "wof:name":"Laraine N Mansfield",
    "wof:placetype":"venue"
},
  "geometry": {"coordinates":[-77.636473,39.269967],"type":"Point"}
}