{
  "type": "Feature",
  "properties": {
    "iso:country":"US",
    "sg:address":"115 Environs Rd",
    "sg:city":"Sterling",
    "sg:classifiers":[
        {
            "category":"Freight",
            "type":"Transportation"
        }
    ],
    "sg:phone":"+1 703 430 1025",
    "sg:postcode":"20165",
    "sg:province":"VA",
    "sg:tags":[
        "special"
    ],
    "wof:name":"State Filings Inc",
    "wof:placetype":"venue"
},
  "geometry": {"coordinates":[-77.40942,39.046704],"type":"Point"}
}