{
  "type": "Feature",
  "properties": {
    "addr:full":"1671 Cool Spring Rd Charlottesville VA 22901",
    "addr:housenumber":"1671",
    "addr:postcode":"22901",
    "addr:street":"Cool Spring Rd",
    "iso:country":"US",
    "sg:address":"1671 Cool Spring Rd",
    "sg:city":"Charlottesville",
    "sg:classifiers":[
        {
            "category":"Taxi",
            "type":"Transportation"
        }
    ],
    "sg:phone":"+1 434 975 8294",
    "sg:postcode":"22901",
    "sg:province":"VA",
    "sg:tags":[
        "taxicab"
    ],
    "wof:name":"A & J Taxicab Svc",
    "wof:placetype":"venue"
},
  "geometry": {"coordinates":[-78.489873,38.078262],"type":"Point"}
}