{
  "type": "Feature",
  "properties": {
    "addr:full":"1075 Jefferson Ave Newport News VA 23607",
    "addr:housenumber":"1075",
    "addr:postcode":"23607",
    "addr:street":"Jefferson Ave",
    "iso:country":"US",
    "sg:address":"1075 Jefferson Ave",
    "sg:city":"Newport News",
    "sg:classifiers":[
        {
            "category":"Social Services",
            "subcategory":"Child Care",
            "type":"Services"
        }
    ],
    "sg:phone":"+1 757 287 9009",
    "sg:postcode":"23607",
    "sg:province":"VA",
    "wof:name":"Child's First Years Christian",
    "wof:placetype":"venue"
},
  "geometry": {"coordinates":[-76.41425599999999,36.970194],"type":"Point"}
}