{
  "type": "Feature",
  "properties": {
    "addr:full":"405 Dabbs House Rd Richmond VA 23223",
    "addr:housenumber":"405",
    "addr:postcode":"23223",
    "addr:street":"Dabbs House Rd",
    "iso:country":"US",
    "sg:address":"405 Dabbs House Rd",
    "sg:city":"Richmond",
    "sg:classifiers":[
        {
            "category":"Manufacturing",
            "subcategory":"Tools & Machinery",
            "type":"Manufacturing & Wholesale Goods"
        }
    ],
    "sg:phone":"+1 804 222 5017",
    "sg:postcode":"23223",
    "sg:province":"VA",
    "sg:tags":[
        "machine",
        "shop"
    ],
    "wof:name":"Henrico Tool & Die Co Inc",
    "wof:placetype":"venue"
},
  "geometry": {"coordinates":[-77.381553,37.542516],"type":"Point"}
}