{
  "type": "Feature",
  "properties": {
    "addr:full":"1575 Lone Jack Rd Glasgow VA 24555",
    "addr:housenumber":"1575",
    "addr:postcode":"24555",
    "addr:street":"Lone Jack Rd",
    "iso:country":"US",
    "sg:address":"1575 Lone Jack Rd",
    "sg:city":"Glasgow",
    "sg:classifiers":[
        {
            "category":"Organizations",
            "subcategory":"Non-profit Organization",
            "type":"Services"
        }
    ],
    "sg:phone":"+1 540 258 1774",
    "sg:postcode":"24555",
    "sg:province":"VA",
    "wof:name":"Literacy & Educational",
    "wof:placetype":"venue"
},
  "geometry": {"coordinates":[-79.44538900000001,37.660202],"type":"Point"}
}