{
  "type": "Feature",
  "properties": {
    "iso:country":"US",
    "sg:address":"2006 S Main St",
    "sg:city":"Farmville",
    "sg:classifiers":[
        {
            "category":"Sports & Exercise",
            "subcategory":"Bowling",
            "type":"Entertainment"
        }
    ],
    "sg:phone":"+1 434 392 9916",
    "sg:postcode":"23901",
    "sg:province":"VA",
    "sg:tags":[
        "center"
    ],
    "wof:name":"Main Street Lanes",
    "wof:placetype":"venue"
},
  "geometry": {"coordinates":[-78.40109200000001,37.274257],"type":"Point"}
}