{
  "type": "Feature",
  "properties": {
    "addr:full":"6700 N Lee Hwy Arlington VA 22205",
    "addr:housenumber":"6700",
    "addr:postcode":"22205",
    "addr:street":"N Lee Hwy",
    "iso:country":"US",
    "sg:address":"6700 N Lee Hwy",
    "sg:city":"Arlington",
    "sg:classifiers":[
        {
            "category":"Personal",
            "type":"Services"
        }
    ],
    "sg:phone":"+1 703 237 6737",
    "sg:postcode":"22205",
    "sg:province":"VA",
    "sg:tags":[
        "credit",
        "debt",
        "counseling"
    ],
    "wof:name":"Consumer Credit Counseling Svc",
    "wof:placetype":"venue"
},
  "geometry": {"coordinates":[-77.159981,38.888784],"type":"Point"}
}