{
  "type": "Feature",
  "properties": {
    "addr:full":"2020 14th St N Arlington VA 22201",
    "addr:housenumber":"2020",
    "addr:postcode":"22201",
    "addr:street":"14Th St N",
    "iso:country":"US",
    "sg:address":"2020 14th St N",
    "sg:city":"Arlington",
    "sg:classifiers":[
        {
            "category":"Real Estate",
            "subcategory":"Real Estate Services",
            "type":"Services"
        }
    ],
    "sg:phone":"+1 703 812 8989",
    "sg:postcode":"22201",
    "sg:province":"VA",
    "sg:tags":[
        "management",
        "property"
    ],
    "sg:website":"www.americanpressworks.com",
    "wof:name":"American Press Works",
    "wof:placetype":"venue"
},
  "geometry": {"coordinates":[-77.08288,38.889513],"type":"Point"}
}