{
  "type": "Feature",
  "properties": {
    "iso:country":"US",
    "sg:address":"3305 S Stafford St",
    "sg:city":"Arlington",
    "sg:classifiers":[
        {
            "category":"Professional",
            "subcategory":"Management & Consulting",
            "type":"Services"
        }
    ],
    "sg:phone":"+1 703 578 3078",
    "sg:postcode":"22206",
    "sg:province":"VA",
    "sg:tags":[
        "consultant",
        "business"
    ],
    "wof:name":"Dave Laufer & Assoc",
    "wof:placetype":"venue"
},
  "geometry": {"coordinates":[-77.087037,38.834019],"type":"Point"}
}