{
  "type": "Feature",
  "properties": {
    "addr:full":"5625 S Laburnum Ave Richmond VA 23231",
    "addr:housenumber":"5625",
    "addr:postcode":"23231",
    "addr:street":"S Laburnum Ave",
    "iso:country":"US",
    "sg:address":"5625 S Laburnum Ave",
    "sg:city":"Richmond",
    "sg:classifiers":[
        {
            "category":"Professional",
            "subcategory":"Engineering",
            "type":"Services"
        }
    ],
    "sg:phone":"+1 804 236 0190",
    "sg:postcode":"23231",
    "sg:province":"VA",
    "sg:tags":[
        "engineer"
    ],
    "wof:name":"Engineering Design Assoc",
    "wof:placetype":"venue"
},
  "geometry": {"coordinates":[-77.34932499999999,37.50626],"type":"Point"}
}