{
  "type": "Feature",
  "properties": {
    "addr:full":"6031 N Wilson Blvd Arlington VA 22205",
    "addr:housenumber":"6031",
    "addr:postcode":"22205",
    "addr:street":"N Wilson Blvd",
    "iso:country":"US",
    "sg:address":"6031 N Wilson Blvd",
    "sg:city":"Arlington",
    "sg:classifiers":[
        {
            "category":"Personal",
            "subcategory":"Barber",
            "type":"Services"
        }
    ],
    "sg:phone":"+1 703 241 1335",
    "sg:postcode":"22205",
    "sg:province":"VA",
    "sg:tags":[
        "shop"
    ],
    "wof:name":"Tom's Real Barber Shop",
    "wof:placetype":"venue"
},
  "geometry": {"coordinates":[-77.13946199999999,38.873872],"type":"Point"}
}