{
  "type": "Feature",
  "properties": {
    "addr:full":"407 Hounds Chase Yorktown VA 23693",
    "addr:housenumber":"407",
    "addr:postcode":"23693",
    "addr:street":"Hounds Chase",
    "iso:country":"US",
    "sg:address":"407 Hounds Chase",
    "sg:city":"Yorktown",
    "sg:classifiers":[
        {
            "category":"Food & Beverages",
            "subcategory":"Groceries & Convenience Stores",
            "type":"Retail Goods"
        }
    ],
    "sg:phone":"+1 757 223 9539",
    "sg:postcode":"23693",
    "sg:province":"VA",
    "sg:tags":[
        "station",
        "gasoline"
    ],
    "wof:name":"Coram Inc",
    "wof:placetype":"venue"
},
  "geometry": {"coordinates":[-76.46651,37.124914],"type":"Point"}
}