{
  "type": "Feature",
  "properties": {
    "addr:full":"4216 Whitacre Rd Fairfax VA 22032",
    "addr:housenumber":"4216",
    "addr:postcode":"22032",
    "addr:street":"Whitacre Rd",
    "iso:country":"US",
    "sg:address":"4216 Whitacre Rd",
    "sg:city":"Fairfax",
    "sg:classifiers":[
        {
            "category":"Professional",
            "subcategory":"Computer Services",
            "type":"Services"
        }
    ],
    "sg:phone":"+1 703 978 3439",
    "sg:postcode":"22032",
    "sg:province":"VA",
    "sg:tags":[
        "bureau",
        "management",
        "programming"
    ],
    "wof:name":"Encore Computer Services Inc",
    "wof:placetype":"venue"
},
  "geometry": {"coordinates":[-77.277309,38.833758],"type":"Point"}
}