{
  "type": "Feature",
  "properties": {
    "addr:full":"1645 Trap Rd Vienna VA 22182",
    "addr:housenumber":"1645",
    "addr:postcode":"22182",
    "addr:street":"Trap Rd",
    "iso:country":"US",
    "sg:address":"1645 Trap Rd",
    "sg:city":"Vienna",
    "sg:classifiers":[
        {
            "category":"Real Estate",
            "subcategory":"Real Estate Operator",
            "type":"Services"
        }
    ],
    "sg:phone":"+1 703 255 1900",
    "sg:postcode":"22182",
    "sg:province":"VA",
    "sg:tags":[
        "building",
        "nonresidential"
    ],
    "wof:name":"Wolf Trap Foundation",
    "wof:placetype":"venue"
},
  "geometry": {"coordinates":[-77.266419,38.932612],"type":"Point"}
}