{
  "type": "Feature",
  "properties": {
    "addr:full":"7707 Comanche Dr Richmond VA 23225",
    "addr:housenumber":"7707",
    "addr:postcode":"23225",
    "addr:street":"Comanche Dr",
    "iso:country":"US",
    "sg:address":"7707 Comanche Dr",
    "sg:city":"Richmond",
    "sg:classifiers":[
        {
            "category":"Building & Trades",
            "subcategory":"Electrical",
            "type":"Services"
        }
    ],
    "sg:phone":"+1 804 285 7233",
    "sg:postcode":"23225",
    "sg:province":"VA",
    "sg:tags":[
        "electrical",
        "contractor"
    ],
    "wof:name":"Alarm Security Inc",
    "wof:placetype":"venue"
},
  "geometry": {"coordinates":[-77.531626,37.551662],"type":"Point"}
}