{
  "type": "Feature",
  "properties": {
    "addr:full":"224 Brandylion Dr Stephens City VA 22655",
    "addr:housenumber":"224",
    "addr:postcode":"22655",
    "addr:street":"Brandylion Dr Stephens",
    "iso:country":"US",
    "sg:address":"224 Brandylion Dr",
    "sg:city":"Stephens City",
    "sg:classifiers":[
        {
            "category":"Wholesale",
            "subcategory":"Electrical",
            "type":"Manufacturing & Wholesale Goods"
        }
    ],
    "sg:phone":"+1 540 869 4941",
    "sg:postcode":"22655",
    "sg:province":"VA",
    "sg:tags":[
        "electronic"
    ],
    "wof:name":"Robert N Streets",
    "wof:placetype":"venue"
},
  "geometry": {"coordinates":[-78.176686,39.100454],"type":"Point"}
}