{
  "type": "Feature",
  "properties": {
    "addr:full":"4923 Americana Dr Annandale VA 22003",
    "addr:housenumber":"4923",
    "addr:postcode":"22003",
    "addr:street":"Americana Dr",
    "iso:country":"US",
    "sg:address":"4923 Americana Dr",
    "sg:city":"Annandale",
    "sg:classifiers":[
        {
            "category":"Professional",
            "subcategory":"Art Services",
            "type":"Services"
        }
    ],
    "sg:phone":"+1 703 256 7903",
    "sg:postcode":"22003",
    "sg:province":"VA",
    "sg:tags":[
        "commercial",
        "design"
    ],
    "wof:name":"Tc Productions Inc",
    "wof:placetype":"venue"
},
  "geometry": {"coordinates":[-77.221378,38.820037],"type":"Point"}
}