{
  "type": "Feature",
  "properties": {
    "addr:full":"282 Mt Jackson Rd Mt Jackson VA 22842",
    "addr:housenumber":"282",
    "addr:postcode":"22842",
    "addr:street":"Mt Jackson Rd",
    "iso:country":"US",
    "sg:address":"282 Mt Jackson Rd",
    "sg:city":"Mt Jackson",
    "sg:classifiers":[
        {
            "category":"Organizations",
            "subcategory":"Religious Organization",
            "type":"Services"
        }
    ],
    "sg:phone":"+1 540 856 3279",
    "sg:postcode":"22842",
    "sg:province":"VA",
    "sg:tags":[
        "church"
    ],
    "wof:name":"Morning Star Lutheran Church",
    "wof:placetype":"venue"
},
  "geometry": {"coordinates":[-78.64951499999999,38.764847],"type":"Point"}
}