{
  "type": "Feature",
  "properties": {
    "addr:full":"132 E Olney Rd Norfolk VA 23510",
    "addr:housenumber":"132",
    "addr:postcode":"23510",
    "addr:street":"E Olney Rd",
    "iso:country":"US",
    "sg:address":"132 E Olney Rd",
    "sg:city":"Norfolk",
    "sg:classifiers":[
        {
            "category":"Professional",
            "subcategory":"Detective & Security Services",
            "type":"Services"
        }
    ],
    "sg:phone":"+1 757 622 0888",
    "sg:postcode":"23510",
    "sg:province":"VA",
    "sg:tags":[
        "car",
        "investigator"
    ],
    "wof:name":"Kennedies Investigative Svc",
    "wof:placetype":"venue"
},
  "geometry": {"coordinates":[-76.28709000000001,36.856249],"type":"Point"}
}