{
  "type": "Feature",
  "properties": {
    "iso:country":"US",
    "sg:address":"5321 Hull Street Rd",
    "sg:city":"Richmond",
    "sg:classifiers":[
        {
            "category":"Food & Beverages",
            "subcategory":"Groceries & Convenience Stores",
            "type":"Retail Goods"
        }
    ],
    "sg:phone":"+1 804 291 1384",
    "sg:postcode":"23224",
    "sg:province":"VA",
    "wof:name":"MI Pais Mart",
    "wof:placetype":"venue"
},
  "geometry": {"coordinates":[-77.488512,37.492421],"type":"Point"}
}