{
  "type": "Feature",
  "properties": {
    "iso:country":"US",
    "sg:address":"4716 N Southside Plaza St",
    "sg:city":"Richmond",
    "sg:classifiers":[
        {
            "category":"Shopping",
            "subcategory":"Beauty & Cosmetics",
            "type":"Retail Goods"
        },
        {
            "category":"Personal",
            "subcategory":"Barber",
            "type":"Services"
        }
    ],
    "sg:phone":"+1 804 231 9903",
    "sg:postcode":"23224",
    "sg:province":"VA",
    "sg:tags":[
        "equipment",
        "perfume",
        "salons-equipment",
        "supply"
    ],
    "wof:name":"S & D Kim Enterprises",
    "wof:placetype":"venue"
},
  "geometry": {"coordinates":[-77.478008,37.502243],"type":"Point"}
}