{
  "type": "Feature",
  "properties": {
    "iso:country":"US",
    "sg:address":"2416 Carolina Rd",
    "sg:city":"Suffolk",
    "sg:classifiers":[
        {
            "category":"Retail",
            "subcategory":"Repair Shop",
            "type":"Services"
        }
    ],
    "sg:phone":"+1 757 925 2067",
    "sg:postcode":"23434",
    "sg:province":"VA",
    "sg:tags":[
        "welding"
    ],
    "wof:name":"Salters Welding & Fabrication",
    "wof:placetype":"venue"
},
  "geometry": {"coordinates":[-76.61428600000001,36.654983],"type":"Point"}
}