{
  "type": "Feature",
  "properties": {
    "iso:country":"US",
    "sg:address":"3309 Oaklawn Blvd",
    "sg:city":"Hopewell",
    "sg:classifiers":[
        {
            "category":"Restaurant",
            "type":"Food & Drink"
        }
    ],
    "sg:menulink":"http://www.allmenus.com/va/hopewell/188028-mcdonalds/menu/",
    "sg:phone":"+1 804 458 0783",
    "sg:postcode":"23860",
    "sg:province":"VA",
    "sg:tags":[
        "burger",
        "american"
    ],
    "wof:name":"McDonald's",
    "wof:placetype":"venue"
},
  "geometry": {"coordinates":[-77.30849600000001,37.278561],"type":"Point"}
}