{
  "type": "Feature",
  "properties": {
    "addr:full":"3273 Longhorn Dr Colonial Heights VA 23834",
    "addr:housenumber":"3273",
    "addr:postcode":"23834",
    "addr:street":"Longhorn Dr",
    "iso:country":"US",
    "sg:address":"3273 Longhorn Dr",
    "sg:city":"Colonial Heights",
    "sg:classifiers":[
        {
            "category":"Health Services",
            "subcategory":"Doctor",
            "type":"Services"
        }
    ],
    "sg:phone":"+1 804 526 5253",
    "sg:postcode":"23834",
    "sg:province":"VA",
    "sg:tags":[
        "clinic",
        "medical"
    ],
    "wof:name":"Jay S Goldberg Dr",
    "wof:placetype":"venue"
},
  "geometry": {"coordinates":[-77.40281,37.270452],"type":"Point"}
}