{
  "type": "Feature",
  "properties": {
    "addr:full":"4808 King St Alexandria VA 22311",
    "addr:housenumber":"4808",
    "addr:postcode":"22311",
    "addr:street":"King St",
    "iso:country":"US",
    "sg:address":"4808 King St",
    "sg:city":"Alexandria",
    "sg:classifiers":[
        {
            "category":"Autos & Motor Vehicles",
            "subcategory":"Fuel & Gas Station",
            "type":"Retail Goods"
        }
    ],
    "sg:postcode":"22311",
    "sg:province":"VA",
    "wof:name":"Hess",
    "wof:placetype":"venue"
},
  "geometry": {"coordinates":[-77.111056,38.84328],"type":"Point"}
}