{
  "type": "Feature",
  "properties": {
    "addr:full":"425 Burnett Rd SW Meadows Of Dan VA 24120",
    "addr:housenumber":"425",
    "addr:postcode":"24120",
    "addr:street":"Burnett Rd Sw",
    "iso:country":"US",
    "sg:address":"425 Burnett Rd SW",
    "sg:city":"Meadows Of Dan",
    "sg:classifiers":[
        {
            "category":"Real Estate",
            "subcategory":"Surveying",
            "type":"Services"
        }
    ],
    "sg:phone":"+1 276 952 1303",
    "sg:postcode":"24120",
    "sg:province":"VA",
    "sg:tags":[
        "surveyor"
    ],
    "wof:name":"Ed Register Licensed Land",
    "wof:placetype":"venue"
},
  "geometry": {"coordinates":[-80.430729,36.746025],"type":"Point"}
}