{
  "type": "Feature",
  "properties": {
    "addr:full":"302 Park St Charlottesville VA 22902",
    "addr:housenumber":"302",
    "addr:postcode":"22902",
    "addr:street":"Park St",
    "iso:country":"US",
    "sg:address":"302 Park St",
    "sg:city":"Charlottesville",
    "sg:classifiers":[
        {
            "category":"Professional",
            "type":"Services"
        }
    ],
    "sg:phone":"+1 434 295 8574",
    "sg:postcode":"22902",
    "sg:province":"VA",
    "wof:name":"Bechtel Stefan",
    "wof:placetype":"venue"
},
  "geometry": {"coordinates":[-78.47713400000001,38.031408],"type":"Point"}
}