{
  "type": "Feature",
  "properties": {
    "addr:full":"43763 Partlow Rd Ashburn VA 20147",
    "addr:housenumber":"43763",
    "addr:postcode":"20147",
    "addr:street":"Partlow Rd",
    "iso:country":"US",
    "sg:address":"43763 Partlow Rd",
    "sg:city":"Ashburn",
    "sg:classifiers":[
        {
            "category":"Real Estate",
            "subcategory":"Real Estate Agent",
            "type":"Services"
        }
    ],
    "sg:phone":"+1 703 729 7700",
    "sg:postcode":"20147",
    "sg:province":"VA",
    "wof:name":"Andrews Community Investment",
    "wof:placetype":"venue"
},
  "geometry": {"coordinates":[-77.488466,39.039985],"type":"Point"}
}