{
  "type": "Feature",
  "properties": {
    "iso:country":"US",
    "sg:address":"4121 Glendale Rd",
    "sg:city":"Woodbridge",
    "sg:classifiers":[
        {
            "category":"Building & Trades",
            "subcategory":"Construction",
            "type":"Services"
        }
    ],
    "sg:phone":"+1 703 505 0763",
    "sg:postcode":"22193",
    "sg:province":"VA",
    "sg:tags":[
        "wallcoverings-installation",
        "wallpaper",
        "painting",
        "contractor"
    ],
    "wof:name":"Amador Painting",
    "wof:placetype":"venue"
},
  "geometry": {"coordinates":[-77.335213,38.653881],"type":"Point"}
}