{
  "type": "Feature",
  "properties": {
    "addr:full":"2245 Euclid Ave Bristol VA 24201",
    "addr:housenumber":"2245",
    "addr:postcode":"24201",
    "addr:street":"Euclid Ave",
    "iso:country":"US",
    "sg:address":"2245 Euclid Ave",
    "sg:city":"Bristol",
    "sg:classifiers":[
        {
            "category":"Autos & Motor Vehicles",
            "subcategory":"Automobile Sales",
            "type":"Retail Goods"
        }
    ],
    "sg:phone":"+1 276 669 3321",
    "sg:postcode":"24201",
    "sg:province":"VA",
    "sg:tags":[
        "used"
    ],
    "wof:name":"G & S Auto Sales",
    "wof:placetype":"venue"
},
  "geometry": {"coordinates":[-82.210061,36.596097],"type":"Point"}
}