{
  "type": "Feature",
  "properties": {
    "addr:full":"511 Washington St Portsmouth VA 23704",
    "addr:housenumber":"511",
    "addr:postcode":"23704",
    "addr:street":"Washington St",
    "iso:country":"US",
    "sg:address":"511 Washington St",
    "sg:city":"Portsmouth",
    "sg:classifiers":[
        {
            "category":"Shopping",
            "subcategory":"Clothing, Apparel, & Fashions",
            "type":"Retail Goods"
        }
    ],
    "sg:phone":"+1 757 393 6668",
    "sg:postcode":"23704",
    "sg:province":"VA",
    "sg:tags":[
        "item",
        "boutique"
    ],
    "wof:name":"Finer Things Boutique",
    "wof:placetype":"venue"
},
  "geometry": {"coordinates":[-76.30376,36.834558],"type":"Point"}
}