{
  "type": "Feature",
  "properties": {
    "addr:full":"3000 Bells Rd Richmond VA 23234",
    "addr:housenumber":"3000",
    "addr:postcode":"23234",
    "addr:street":"Bells Rd",
    "iso:country":"US",
    "sg:address":"3000 Bells Rd",
    "sg:city":"Richmond",
    "sg:classifiers":[
        {
            "category":"Wholesale",
            "subcategory":"Scrap",
            "type":"Manufacturing & Wholesale Goods"
        }
    ],
    "sg:phone":"+1 804 271 1253",
    "sg:postcode":"23234",
    "sg:province":"VA",
    "sg:tags":[
        "metal",
        "iron"
    ],
    "wof:name":"Smith Iron & Metal Co Inc",
    "wof:placetype":"venue"
},
  "geometry": {"coordinates":[-77.45477700000001,37.472301],"type":"Point"}
}