{
  "type": "Feature",
  "properties": {
    "addr:full":"201 Loudoun St SW Leesburg VA 20175",
    "addr:housenumber":"201",
    "addr:postcode":"20175",
    "addr:street":"Loudoun St Sw",
    "iso:country":"US",
    "sg:address":"201 Loudoun St SW",
    "sg:city":"Leesburg",
    "sg:classifiers":[
        {
            "category":"Wholesale",
            "subcategory":"Construction Materials",
            "type":"Manufacturing & Wholesale Goods"
        }
    ],
    "sg:phone":"+1 703 771 1991",
    "sg:postcode":"20175",
    "sg:province":"VA",
    "sg:tags":[
        "stone",
        "wall",
        "product",
        "system",
        "retaining",
        "precast",
        "timber"
    ],
    "wof:name":"Metroplex Retaining Walls of",
    "wof:placetype":"venue"
},
  "geometry": {"coordinates":[-77.56795099999999,39.115021],"type":"Point"}
}