{
  "type": "Feature",
  "properties": {
    "iso:country":"US",
    "sg:address":"6318 Peters Creek Rd NW",
    "sg:city":"Roanoke",
    "sg:classifiers":[
        {
            "category":"Personal",
            "subcategory":"Beauty Salon",
            "type":"Services"
        }
    ],
    "sg:phone":"+1 540 563 1515",
    "sg:postcode":"24019",
    "sg:province":"VA",
    "wof:name":"Just For Looks",
    "wof:placetype":"venue"
},
  "geometry": {"coordinates":[-79.967162,37.34314],"type":"Point"}
}