{
  "type": "Feature",
  "properties": {
    "addr:full":"1403 Greenbrier Pkwy Chesapeake VA 23320",
    "addr:housenumber":"1403",
    "addr:postcode":"23320",
    "addr:street":"Greenbrier Pkwy",
    "iso:country":"US",
    "sg:address":"1403 Greenbrier Pkwy",
    "sg:city":"Chesapeake",
    "sg:classifiers":[
        {
            "category":"Professional",
            "subcategory":"Research",
            "type":"Services"
        },
        {
            "category":"Professional",
            "subcategory":"Management & Consulting",
            "type":"Services"
        }
    ],
    "sg:phone":"+1 757 436 3933",
    "sg:postcode":"23320",
    "sg:province":"VA",
    "sg:tags":[
        "environmental",
        "ecological",
        "consultant"
    ],
    "wof:name":"ESA Environmental Specialists",
    "wof:placetype":"venue"
},
  "geometry": {"coordinates":[-76.230333,36.776802],"type":"Point"}
}