{
  "type": "Feature",
  "properties": {
    "iso:country":"US",
    "sg:address":"4660 Kenmore Ave Ste 902",
    "sg:city":"Alexandria",
    "sg:classifiers":[
        {
            "category":"Health Services",
            "subcategory":"Doctor",
            "type":"Services"
        },
        {
            "category":"Personal",
            "subcategory":"Adult",
            "type":"Services"
        }
    ],
    "sg:phone":"+1 703 370 4300",
    "sg:postcode":"22304",
    "sg:province":"VA",
    "sg:tags":[
        "obstetrician",
        "midwife",
        "gynecologist"
    ],
    "wof:name":"Kisthardt Anne MD",
    "wof:placetype":"venue"
},
  "geometry": {"coordinates":[-77.11039700000001,38.829498],"type":"Point"}
}