{
  "type": "Feature",
  "properties": {
    "iso:country":"US",
    "sg:address":"136 Woodside Rd",
    "sg:city":"Danville",
    "sg:classifiers":[
        {
            "category":"Real Estate",
            "subcategory":"Real Estate Agent",
            "type":"Services"
        },
        {
            "category":"Professional",
            "subcategory":"Business Services",
            "type":"Services"
        }
    ],
    "sg:phone":"+1 434 791 1984",
    "sg:postcode":"24540",
    "sg:province":"VA",
    "sg:tags":[
        "appraiser"
    ],
    "wof:name":"Southside Appraisal Services",
    "wof:placetype":"venue"
},
  "geometry": {"coordinates":[-79.348615,36.580027],"type":"Point"}
}