{
  "type": "Feature",
  "properties": {
    "addr:full":"8610 Perrymont Rd Richmond VA 23237",
    "addr:housenumber":"8610",
    "addr:postcode":"23237",
    "addr:street":"Perrymont Rd",
    "iso:country":"US",
    "sg:address":"8610 Perrymont Rd",
    "sg:city":"Richmond",
    "sg:classifiers":[
        {
            "category":"Education",
            "subcategory":"School",
            "type":"Public Place"
        }
    ],
    "sg:phone":"+1 804 743 3701",
    "sg:postcode":"23237",
    "sg:province":"VA",
    "wof:name":"Perrymont Middle School",
    "wof:placetype":"venue"
},
  "geometry": {"coordinates":[-77.43563,37.407188],"type":"Point"}
}