{
  "type": "Feature",
  "properties": {
    "addr:full":"13956 Farmer Dr Woodford VA 22580",
    "addr:housenumber":"13956",
    "addr:postcode":"22580",
    "addr:street":"Farmer Dr",
    "iso:country":"US",
    "sg:address":"13956 Farmer Dr",
    "sg:city":"Woodford",
    "sg:classifiers":[
        {
            "category":"Retail",
            "subcategory":"Repair Shop",
            "type":"Services"
        }
    ],
    "sg:phone":"+1 804 633 9049",
    "sg:postcode":"22580",
    "sg:province":"VA",
    "wof:name":"Thompson Wood Inc",
    "wof:placetype":"venue"
},
  "geometry": {"coordinates":[-77.36669000000001,38.078752],"type":"Point"}
}