{
  "type": "Feature",
  "properties": {
    "addr:full":"3328 Catlett Rd Catlett VA 20119",
    "addr:housenumber":"3328",
    "addr:postcode":"20119",
    "addr:street":"Catlett Rd",
    "iso:country":"US",
    "sg:address":"3328 Catlett Rd",
    "sg:city":"Catlett",
    "sg:classifiers":[
        {
            "category":"Freight",
            "type":"Transportation"
        }
    ],
    "sg:phone":"+1 540 788 9859",
    "sg:postcode":"20119",
    "sg:province":"VA",
    "sg:tags":[
        "operator",
        "trucking"
    ],
    "wof:name":"M D Mullins Heavy Haulin",
    "wof:placetype":"venue"
},
  "geometry": {"coordinates":[-77.63368699999999,38.665875],"type":"Point"}
}