{
  "type": "Feature",
  "properties": {
    "addr:full":"1802 Jefferson Davis Hwy Richmond VA 23224",
    "addr:housenumber":"1802",
    "addr:postcode":"23224",
    "addr:street":"Jefferson Davis Hwy",
    "iso:country":"US",
    "sg:address":"1802 Jefferson Davis Hwy",
    "sg:city":"Richmond",
    "sg:classifiers":[
        {
            "category":"Retail",
            "subcategory":"Auto Repair",
            "type":"Services"
        }
    ],
    "sg:phone":"+1 804 232 4136",
    "sg:postcode":"23224",
    "sg:province":"VA",
    "sg:tags":[
        "repairing",
        "automotive",
        "general",
        "automobile"
    ],
    "wof:name":"Mark's Automotive & Tire",
    "wof:placetype":"venue"
},
  "geometry": {"coordinates":[-77.445959,37.49508],"type":"Point"}
}