{
  "type": "Feature",
  "properties": {
    "addr:full":"1032 George Washington Hwy N Chesapeake VA 23323",
    "addr:housenumber":"1032",
    "addr:postcode":"23323",
    "addr:street":"George Washington Hwy N",
    "iso:country":"US",
    "sg:address":"1032 George Washington Hwy N",
    "sg:city":"Chesapeake",
    "sg:classifiers":[
        {
            "category":"Shopping",
            "subcategory":"Florist",
            "type":"Retail Goods"
        }
    ],
    "sg:phone":"+1 757 485 2330",
    "sg:postcode":"23323",
    "sg:province":"VA",
    "wof:name":"L&J Floral Wholesale",
    "wof:placetype":"venue"
},
  "geometry": {"coordinates":[-76.33721,36.779616],"type":"Point"}
}