{
  "type": "Feature",
  "properties": {
    "addr:full":"250 Memorial Dr Ste B Luray VA 22835",
    "addr:housenumber":"250",
    "addr:postcode":"22835",
    "addr:street":"Memorial Dr Ste B",
    "iso:country":"US",
    "sg:address":"250 Memorial Dr Ste B",
    "sg:city":"Luray",
    "sg:classifiers":[
        {
            "category":"Health Services",
            "subcategory":"Doctor",
            "type":"Services"
        }
    ],
    "sg:phone":"+1 540 743 9087",
    "sg:postcode":"22835",
    "sg:province":"VA",
    "sg:tags":[
        "medicine",
        "physician",
        "practice",
        "surgeons",
        "family"
    ],
    "wof:name":"Page Primary Care",
    "wof:placetype":"venue"
},
  "geometry": {"coordinates":[-78.46902,38.662273],"type":"Point"}
}