{
  "type": "Feature",
  "properties": {
    "addr:full":"14500 Lee Rd Ste G Chantilly VA 20151",
    "addr:housenumber":"14500",
    "addr:postcode":"20151",
    "addr:street":"Lee Rd Ste G",
    "iso:country":"US",
    "sg:address":"14500 Lee Rd Ste G",
    "sg:city":"Chantilly",
    "sg:classifiers":[
        {
            "category":"Home & Garden",
            "subcategory":"Household Appliances",
            "type":"Retail Goods"
        }
    ],
    "sg:phone":"+1 703 961 1740",
    "sg:postcode":"20151",
    "sg:province":"VA",
    "sg:tags":[
        "equipment",
        "system",
        "cleaners-household-dealers",
        "vacuum"
    ],
    "wof:name":"Vacuums Unlimited",
    "wof:placetype":"venue"
},
  "geometry": {"coordinates":[-77.446167,38.90015],"type":"Point"}
}