{
  "type": "Feature",
  "properties": {
    "addr:full":"1806 Main St Victoria VA 23974",
    "addr:housenumber":"1806",
    "addr:postcode":"23974",
    "addr:street":"Main St",
    "iso:country":"US",
    "sg:address":"1806 Main St",
    "sg:city":"Victoria",
    "sg:classifiers":[
        {
            "category":"Home & Garden",
            "subcategory":"Hardware",
            "type":"Retail Goods"
        }
    ],
    "sg:phone":"+1 434 696 2237",
    "sg:postcode":"23974",
    "sg:province":"VA",
    "wof:name":"J W 's Store",
    "wof:placetype":"venue"
},
  "geometry": {"coordinates":[-78.227092,36.994626],"type":"Point"}
}