{
  "type": "Feature",
  "properties": {
    "iso:country":"US",
    "sg:address":"220 N 6th St",
    "sg:city":"Suffolk",
    "sg:classifiers":[
        {
            "category":"Organizations",
            "subcategory":"Religious Organization",
            "type":"Services"
        }
    ],
    "sg:phone":"+1 757 538 1932",
    "sg:postcode":"23434",
    "sg:province":"VA",
    "wof:name":"New Calvary Baptist Church",
    "wof:placetype":"venue"
},
  "geometry": {"coordinates":[-76.565502,36.728129],"type":"Point"}
}