{
  "type": "Feature",
  "properties": {
    "addr:full":"121 Maple Ave W Vienna VA 22180",
    "addr:housenumber":"121",
    "addr:postcode":"22180",
    "addr:street":"Maple Ave W",
    "iso:country":"US",
    "sg:address":"121 Maple Ave W",
    "sg:city":"Vienna",
    "sg:classifiers":[
        {
            "category":"Retail",
            "subcategory":"Repair Shop",
            "type":"Services"
        }
    ],
    "sg:phone":"+1 703 255 3913",
    "sg:postcode":"22180",
    "sg:province":"VA",
    "wof:name":"Super Dry Cleaner Inc",
    "wof:placetype":"venue"
},
  "geometry": {"coordinates":[-77.267151,38.900197],"type":"Point"}
}