{
  "type": "Feature",
  "properties": {
    "addr:full":"46163 Westridge Dr Sterling VA 20165",
    "addr:housenumber":"46163",
    "addr:postcode":"20165",
    "addr:street":"Westridge Dr",
    "iso:country":"US",
    "sg:address":"46163 Westridge Dr",
    "sg:city":"Sterling",
    "sg:classifiers":[
        {
            "category":"Professional",
            "subcategory":"Computer Services",
            "type":"Services"
        }
    ],
    "sg:phone":"+1 703 587 7688",
    "sg:postcode":"20165",
    "sg:province":"VA",
    "sg:tags":[
        "programming",
        "software"
    ],
    "wof:name":"Halo E-Solutions",
    "wof:placetype":"venue"
},
  "geometry": {"coordinates":[-77.4019,39.039313],"type":"Point"}
}