{
  "type": "Feature",
  "properties": {
    "iso:country":"US",
    "sg:address":"7900 Sudley Rd Ste 420",
    "sg:city":"Manassas",
    "sg:classifiers":[
        {
            "category":"Professional",
            "subcategory":"Lawyer & Legal Services",
            "type":"Services"
        }
    ],
    "sg:phone":"+1 703 369 7727",
    "sg:postcode":"20109",
    "sg:province":"VA",
    "wof:name":"Scriven Wayne Marcus & Associates",
    "wof:placetype":"venue"
},
  "geometry": {"coordinates":[-77.51309999999999,38.785],"type":"Point"}
}