{
  "type": "Feature",
  "properties": {
    "iso:country":"US",
    "sg:address":"100 Beeline Ln",
    "sg:city":"Berryville",
    "sg:classifiers":[
        {
            "category":"Wholesale",
            "subcategory":"Groceries",
            "type":"Manufacturing & Wholesale Goods"
        }
    ],
    "sg:phone":"+1 540 955 1734",
    "sg:postcode":"22611",
    "sg:province":"VA",
    "sg:tags":[
        "honey"
    ],
    "wof:name":"Gunter's Honey",
    "wof:placetype":"venue"
},
  "geometry": {"coordinates":[-78.01064100000001,39.172712],"type":"Point"}
}