{
  "type": "Feature",
  "properties": {
    "addr:full":"9524 Kennesaw Rd Richmond VA 23236",
    "addr:housenumber":"9524",
    "addr:postcode":"23236",
    "addr:street":"Kennesaw Rd",
    "iso:country":"US",
    "sg:address":"9524 Kennesaw Rd",
    "sg:city":"Richmond",
    "sg:classifiers":[
        {
            "category":"Building & Trades",
            "subcategory":"Construction",
            "type":"Services"
        }
    ],
    "sg:phone":"+1 804 421 8364",
    "sg:postcode":"23236",
    "sg:province":"VA",
    "sg:tags":[
        "contractor"
    ],
    "wof:name":"Partnership For Better Ho",
    "wof:placetype":"venue"
},
  "geometry": {"coordinates":[-77.57958000000001,37.481756],"type":"Point"}
}