{
  "type": "Feature",
  "properties": {
    "addr:full":"1040 West Ave Richmond VA 23220",
    "addr:housenumber":"1040",
    "addr:postcode":"23220",
    "addr:street":"West Ave",
    "iso:country":"US",
    "sg:address":"1040 West Ave",
    "sg:city":"Richmond",
    "sg:classifiers":[
        {
            "category":"Building & Trades",
            "subcategory":"Construction",
            "type":"Services"
        }
    ],
    "sg:phone":"+1 804 674 4100",
    "sg:postcode":"23220",
    "sg:province":"VA",
    "sg:tags":[
        "contractor"
    ],
    "sg:website":"www.basements.com",
    "wof:name":"Mid-Atlantic Waterproofing Incorporated",
    "wof:placetype":"venue"
},
  "geometry": {"coordinates":[-77.45493,37.549566],"type":"Point"}
}