{
  "type": "Feature",
  "properties": {
    "addr:full":"108 E Glebe Rd Alexandria VA 22305",
    "addr:housenumber":"108",
    "addr:postcode":"22305",
    "addr:street":"E Glebe Rd",
    "iso:country":"US",
    "sg:address":"108 E Glebe Rd",
    "sg:city":"Alexandria",
    "sg:classifiers":[
        {
            "category":"Building & Trades",
            "subcategory":"Construction",
            "type":"Services"
        }
    ],
    "sg:phone":"+1 703 684 6588",
    "sg:postcode":"22305",
    "sg:province":"VA",
    "sg:tags":[
        "painter"
    ],
    "wof:name":"Las Mesas Remodeling",
    "wof:placetype":"venue"
},
  "geometry": {"coordinates":[-77.05389599999999,38.833739],"type":"Point"}
}