{
  "type": "Feature",
  "properties": {
    "addr:full":"4900 Leesburg Pike Alexandria VA 22302",
    "addr:housenumber":"4900",
    "addr:postcode":"22302",
    "addr:street":"Leesburg Pike",
    "iso:country":"US",
    "sg:address":"4900 Leesburg Pike",
    "sg:city":"Alexandria",
    "sg:classifiers":[
        {
            "category":"Professional",
            "subcategory":"Lawyer & Legal Services",
            "type":"Services"
        }
    ],
    "sg:phone":"+1 703 998 8995",
    "sg:postcode":"22302",
    "sg:province":"VA",
    "sg:tags":[
        "naturalization",
        "immigration"
    ],
    "wof:name":"Lafeota",
    "wof:placetype":"venue"
},
  "geometry": {"coordinates":[-77.114901,38.844926],"type":"Point"}
}