{
  "type": "Feature",
  "properties": {
    "iso:country":"US",
    "sg:address":"3980 Oldtown Rd",
    "sg:city":"Shawsville",
    "sg:classifiers":[
        {
            "category":"Professional",
            "subcategory":"Lawyer & Legal Services",
            "type":"Services"
        }
    ],
    "sg:phone":"+1 540 268 2002",
    "sg:postcode":"24162",
    "sg:province":"VA",
    "sg:tags":[
        "attorney"
    ],
    "wof:name":"B K Cruey Law Offices",
    "wof:placetype":"venue"
},
  "geometry": {"coordinates":[-80.254295,37.169218],"type":"Point"}
}