{
  "type": "Feature",
  "properties": {
    "addr:full":"3980 Oldtown Rd Shawsville VA 24162",
    "addr:housenumber":"3980",
    "addr:postcode":"24162",
    "addr:street":"Oldtown Rd",
    "iso:country":"US",
    "sg:address":"3980 Oldtown Rd",
    "sg:city":"Shawsville",
    "sg:classifiers":[
        {
            "category":"Professional",
            "subcategory":"Lawyer & Legal Services",
            "type":"Services"
        }
    ],
    "sg:phone":"+1 540 268 2002",
    "sg:postcode":"24162",
    "sg:province":"VA",
    "sg:tags":[
        "attorney"
    ],
    "wof:name":"B K Cruey Law Offices",
    "wof:placetype":"venue"
},
  "geometry": {"coordinates":[-80.254295,37.169218],"type":"Point"}
}