{
  "type": "Feature",
  "properties": {
    "iso:country":"US",
    "sg:address":"1678 W Commonwealth Dr",
    "sg:city":"Front Royal",
    "sg:classifiers":[
        {
            "category":"Professional",
            "type":"Services"
        }
    ],
    "sg:phone":"+1 540 622 2600",
    "sg:postcode":"22630",
    "sg:province":"VA",
    "wof:name":"Forensic Is Inc",
    "wof:placetype":"venue"
},
  "geometry": {"coordinates":[-78.158012,38.907801],"type":"Point"}
}