{
  "type": "Feature",
  "properties": {
    "addr:full":"1930 Orange Ave NE Roanoke VA 24012",
    "addr:housenumber":"1930",
    "addr:postcode":"24012",
    "addr:street":"Orange Ave Ne",
    "iso:country":"US",
    "sg:address":"1930 Orange Ave NE",
    "sg:city":"Roanoke",
    "sg:classifiers":[
        {
            "category":"Professional",
            "subcategory":"Business Services",
            "type":"Services"
        }
    ],
    "sg:phone":"+1 540 567 6133",
    "sg:postcode":"24012",
    "sg:province":"VA",
    "sg:tags":[
        "water",
        "treatment"
    ],
    "wof:name":"Rainsoft",
    "wof:placetype":"venue"
},
  "geometry": {"coordinates":[-79.91137999999999,37.289559],"type":"Point"}
}