{
  "type": "Feature",
  "properties": {
    "iso:country":"US",
    "sg:address":"1340 Braddock Pl",
    "sg:city":"Alexandria",
    "sg:classifiers":[
        {
            "category":"Manufacturing",
            "subcategory":"Printing",
            "type":"Manufacturing & Wholesale Goods"
        }
    ],
    "sg:phone":"+1 703 706 8260",
    "sg:postcode":"22314",
    "sg:province":"VA",
    "sg:tags":[
        "publisher"
    ],
    "wof:name":"Research Institute Of America",
    "wof:placetype":"venue"
},
  "geometry": {"coordinates":[-77.051057,38.814849],"type":"Point"}
}