{
  "type": "Feature",
  "properties": {
    "iso:country":"US",
    "sg:address":"6836 Fort Valley Rd",
    "sg:city":"Fort Valley",
    "sg:classifiers":[
        {
            "category":"Building & Trades",
            "subcategory":"Construction",
            "type":"Services"
        }
    ],
    "sg:phone":"+1 540 933 6200",
    "sg:postcode":"22652",
    "sg:province":"VA",
    "sg:tags":[
        "excavation",
        "excavating",
        "contractor"
    ],
    "wof:name":"Elmo V Mantz Excavating",
    "wof:placetype":"venue"
},
  "geometry": {"coordinates":[-78.418553,38.841979],"type":"Point"}
}