{
  "type": "Feature",
  "properties": {
    "addr:full":"519 2nd St Radford VA 24141",
    "addr:housenumber":"519",
    "addr:postcode":"24141",
    "addr:street":"2Nd St",
    "iso:country":"US",
    "sg:address":"519 2nd St",
    "sg:city":"Radford",
    "sg:classifiers":[
        {
            "category":"Professional",
            "subcategory":"Lawyer & Legal Services",
            "type":"Services"
        }
    ],
    "sg:phone":"+1 540 639 9081",
    "sg:postcode":"24141",
    "sg:province":"VA",
    "sg:tags":[
        "attorney"
    ],
    "wof:name":"Davis Davis & Davis",
    "wof:placetype":"venue"
},
  "geometry": {"coordinates":[-80.57691199999999,37.131762],"type":"Point"}
}