{
  "type": "Feature",
  "properties": {
    "iso:country":"US",
    "sg:address":"1360 Beverly Rd Ste 300",
    "sg:city":"Mc Lean",
    "sg:classifiers":[
        {
            "category":"Professional",
            "subcategory":"Accounting & Tax Preparation",
            "type":"Services"
        }
    ],
    "sg:phone":"+1 703 821 0702",
    "sg:postcode":"22101",
    "sg:province":"VA",
    "sg:tags":[
        "accountant"
    ],
    "wof:name":"Miller Sue",
    "wof:placetype":"venue"
},
  "geometry": {"coordinates":[-77.177299,38.9384],"type":"Point"}
}