{
  "type": "Feature",
  "properties": {
    "iso:country":"US",
    "sg:address":"2788 Deer Run Dr",
    "sg:city":"Petersburg",
    "sg:classifiers":[
        {
            "category":"Organizations",
            "subcategory":"Community Association",
            "type":"Services"
        }
    ],
    "sg:phone":"+1 804 862 3204",
    "sg:postcode":"23805",
    "sg:province":"VA",
    "wof:name":"Ancient Free & Accepted Masons",
    "wof:placetype":"venue"
},
  "geometry": {"coordinates":[-77.347562,37.125826],"type":"Point"}
}