{
  "type": "Feature",
  "properties": {
    "iso:country":"US",
    "sg:address":"11500 Midlothian Tpke",
    "sg:city":"Richmond",
    "sg:classifiers":[
        {
            "category":"Shopping",
            "subcategory":"Clothing, Apparel, & Fashions",
            "type":"Retail Goods"
        }
    ],
    "sg:phone":"+1 804 378 5949",
    "sg:postcode":"23235",
    "sg:province":"VA",
    "wof:name":"Semina",
    "wof:placetype":"venue"
},
  "geometry": {"coordinates":[-77.60893299999999,37.505533],"type":"Point"}
}