{
  "type": "Feature",
  "properties": {
    "iso:country":"US",
    "sg:address":"4636 Little John Dr",
    "sg:city":"Norfolk",
    "sg:classifiers":[
        {
            "category":"Personal",
            "subcategory":"Barber",
            "type":"Services"
        }
    ],
    "sg:phone":"+1 757 857 0373",
    "sg:postcode":"23513",
    "sg:province":"VA",
    "sg:tags":[
        "shop"
    ],
    "wof:name":"Cartwright Barber Shop",
    "wof:placetype":"venue"
},
  "geometry": {"coordinates":[-76.235747,36.878576],"type":"Point"}
}