{
  "type": "Feature",
  "properties": {
    "iso:country":"US",
    "sg:address":"321 S Alleghany Ave",
    "sg:city":"Covington",
    "sg:classifiers":[
        {
            "category":"Professional",
            "subcategory":"Management & Consulting",
            "type":"Services"
        }
    ],
    "sg:phone":"+1 540 965 9583",
    "sg:postcode":"24426",
    "sg:province":"VA",
    "wof:name":"Metro-Thebe Inc",
    "wof:placetype":"venue"
},
  "geometry": {"coordinates":[-79.98741699999999,37.790258],"type":"Point"}
}