{
  "type": "Feature",
  "properties": {
    "addr:full":"9200 W Broad St Richmond VA 23294",
    "addr:housenumber":"9200",
    "addr:postcode":"23294",
    "addr:street":"W Broad St",
    "iso:country":"US",
    "sg:address":"9200 W Broad St",
    "sg:city":"Richmond",
    "sg:classifiers":[
        {
            "category":"Retail",
            "subcategory":"Car Wash",
            "type":"Services"
        }
    ],
    "sg:phone":"+1 804 273 9400",
    "sg:postcode":"23294",
    "sg:province":"VA",
    "sg:tags":[
        "polishing",
        "washing"
    ],
    "sg:website":"www.carpoolinc.com",
    "wof:name":"Car Pool Auto Wash Quick Lube",
    "wof:placetype":"venue"
},
  "geometry": {"coordinates":[-77.552733,37.637703],"type":"Point"}
}