{
  "type": "Feature",
  "properties": {
    "addr:full":"2451 Centreville Rd Herndon VA 20171",
    "addr:housenumber":"2451",
    "addr:postcode":"20171",
    "addr:street":"Centreville Rd",
    "iso:country":"US",
    "sg:address":"2451 Centreville Rd",
    "sg:city":"Herndon",
    "sg:classifiers":[
        {
            "category":"Food & Beverages",
            "subcategory":"Bakery",
            "type":"Retail Goods"
        }
    ],
    "sg:phone":"+1 703 793 2787",
    "sg:postcode":"20171",
    "sg:province":"VA",
    "sg:tags":[
        "baker"
    ],
    "sg:website":"www.4lille.com",
    "wof:name":"Patisserie Lille French Bakery",
    "wof:placetype":"venue"
},
  "geometry": {"coordinates":[-77.414064,38.948163],"type":"Point"}
}