{
  "type": "Feature",
  "properties": {
    "addr:full":"413 Cooper St Spotsylvania VA 22551",
    "addr:housenumber":"413",
    "addr:postcode":"22551",
    "addr:street":"Cooper St",
    "iso:country":"US",
    "sg:address":"413 Cooper St",
    "sg:city":"Spotsylvania",
    "sg:classifiers":[
        {
            "category":"Building & Trades",
            "subcategory":"Construction",
            "type":"Services"
        }
    ],
    "sg:phone":"+1 540 582 7711",
    "sg:postcode":"22551",
    "sg:province":"VA",
    "sg:tags":[
        "contractor"
    ],
    "wof:name":"First Class Roofing",
    "wof:placetype":"venue"
},
  "geometry": {"coordinates":[-77.59374200000001,38.198171],"type":"Point"}
}