{
  "type": "Feature",
  "properties": {
    "addr:full":"5911 York Haven Ln Zanoni VA 23061",
    "addr:housenumber":"5911",
    "addr:postcode":"23061",
    "addr:street":"York Haven Ln Zanoni",
    "iso:country":"US",
    "sg:address":"5911 York Haven Ln",
    "sg:city":"Zanoni",
    "sg:classifiers":[
        {
            "category":"Professional",
            "subcategory":"Business Services",
            "type":"Services"
        }
    ],
    "sg:phone":"+1 804 694 4312",
    "sg:postcode":"23061",
    "sg:province":"VA",
    "sg:tags":[
        "auctioneer"
    ],
    "wof:name":"Action Auction",
    "wof:placetype":"venue"
},
  "geometry": {"coordinates":[-76.62853200000001,37.380598],"type":"Point"}
}