{
  "type": "Feature",
  "properties": {
    "iso:country":"US",
    "sg:address":"1960 Chain Bridge Rd",
    "sg:city":"Mc Lean",
    "sg:classifiers":[
        {
            "category":"Professional",
            "type":"Services"
        },
        {
            "category":"Travel",
            "subcategory":"Hotels & Motels",
            "type":"Entertainment"
        }
    ],
    "sg:phone":"+1 703 348 2141",
    "sg:postcode":"22102",
    "sg:province":"VA",
    "sg:tags":[
        "caterer"
    ],
    "wof:name":"Wickers",
    "wof:placetype":"venue"
},
  "geometry": {"coordinates":[-77.227898,38.919899],"type":"Point"}
}