{
  "type": "Feature",
  "properties": {
    "iso:country":"US",
    "sg:address":"5840 New England Woods Dr",
    "sg:city":"Burke",
    "sg:classifiers":[
        {
            "category":"Travel",
            "subcategory":"Travel Agent",
            "type":"Entertainment"
        }
    ],
    "sg:phone":"+1 703 764 0355",
    "sg:postcode":"22015",
    "sg:province":"VA",
    "sg:tags":[
        "operator",
        "tour",
        "tours",
        "promoter"
    ],
    "sg:website":"www.designatour.com",
    "wof:name":"Design A Tour Inc",
    "wof:placetype":"venue"
},
  "geometry": {"coordinates":[-77.286096,38.791343],"type":"Point"}
}