{
  "type": "Feature",
  "properties": {
    "addr:full":"104 Winifred Ter Huddleston VA 24104",
    "addr:housenumber":"104",
    "addr:postcode":"24104",
    "addr:street":"Winifred Ter Huddleston",
    "iso:country":"US",
    "sg:address":"104 Winifred Ter",
    "sg:city":"Huddleston",
    "sg:classifiers":[
        {
            "category":"Professional",
            "subcategory":"Management & Consulting",
            "type":"Services"
        }
    ],
    "sg:phone":"+1 540 297 1784",
    "sg:postcode":"24104",
    "sg:province":"VA",
    "sg:tags":[
        "business"
    ],
    "wof:name":"Lipscomb & Associates Inc",
    "wof:placetype":"venue"
},
  "geometry": {"coordinates":[-79.589073,37.048464],"type":"Point"}
}