{
  "type": "Feature",
  "properties": {
    "iso:country":"US",
    "sg:address":"2705 Green Holly Springs Ct",
    "sg:city":"Oakton",
    "sg:classifiers":[
        {
            "category":"Manufacturing",
            "subcategory":"Printing",
            "type":"Manufacturing & Wholesale Goods"
        }
    ],
    "sg:phone":"+1 703 716 0900",
    "sg:postcode":"22124",
    "sg:province":"VA",
    "sg:tags":[
        "publisher",
        "periodical"
    ],
    "sg:website":"www.amren.com",
    "wof:name":"American Renaissance",
    "wof:placetype":"venue"
},
  "geometry": {"coordinates":[-77.33215800000001,38.899592],"type":"Point"}
}