{
  "type": "Feature",
  "properties": {
    "iso:country":"US",
    "sg:address":"6820 Fairfax Dr",
    "sg:city":"Arlington",
    "sg:classifiers":[
        {
            "category":"Retail",
            "subcategory":"Auto Repair",
            "type":"Services"
        }
    ],
    "sg:phone":"+1 703 412 1111",
    "sg:postcode":"22213",
    "sg:province":"VA",
    "sg:tags":[
        "automotive"
    ],
    "wof:name":"Franks Towing & Recovery",
    "wof:placetype":"venue"
},
  "geometry": {"coordinates":[-77.162002,38.887037],"type":"Point"}
}