{
  "type": "Feature",
  "properties": {
    "iso:country":"US",
    "sg:address":"1157 Azalea Ave",
    "sg:city":"Richmond",
    "sg:classifiers":[
        {
            "category":"Restaurant",
            "type":"Food & Drink"
        }
    ],
    "sg:phone":"+1 804 264 9105",
    "sg:postcode":"23227",
    "sg:province":"VA",
    "sg:tags":[
        "eating"
    ],
    "wof:name":"Checkers Drive-In Restaurants",
    "wof:placetype":"venue"
},
  "geometry": {"coordinates":[-77.45240200000001,37.601459],"type":"Point"}
}