{
  "type": "Feature",
  "properties": {
    "addr:full":"705 E Market St Leesburg VA 20176",
    "addr:housenumber":"705",
    "addr:postcode":"20176",
    "addr:street":"E Market St",
    "iso:country":"US",
    "sg:address":"705 E Market St",
    "sg:city":"Leesburg",
    "sg:classifiers":[
        {
            "category":"Autos & Motor Vehicles",
            "subcategory":"Auto Supplies",
            "type":"Retail Goods"
        }
    ],
    "sg:phone":"+1 703 589 1600",
    "sg:postcode":"20176",
    "sg:province":"VA",
    "sg:tags":[
        "battery"
    ],
    "wof:name":"NAPA Auto Parts",
    "wof:placetype":"venue"
},
  "geometry": {"coordinates":[-77.54917500000001,39.107069],"type":"Point"}
}