{
  "type": "Feature",
  "properties": {
    "addr:full":"609 Church St Blackstone VA 23824",
    "addr:housenumber":"609",
    "addr:postcode":"23824",
    "addr:street":"Church St",
    "iso:country":"US",
    "sg:address":"609 Church St",
    "sg:city":"Blackstone",
    "sg:classifiers":[
        {
            "category":"Professional",
            "subcategory":"Detective & Security Services",
            "type":"Services"
        },
        {
            "category":"Professional",
            "subcategory":"Lawyer & Legal Services",
            "type":"Services"
        }
    ],
    "sg:phone":"+1 434 294 3332",
    "sg:postcode":"23824",
    "sg:province":"VA",
    "sg:tags":[
        "process",
        "server",
        "private",
        "investigator"
    ],
    "wof:name":"Commonwealth Security & Investigation Llc",
    "wof:placetype":"venue"
},
  "geometry": {"coordinates":[-78.007795,37.077572],"type":"Point"}
}