{
  "type": "Feature",
  "properties": {
    "iso:country":"US",
    "sg:address":"184 Midway Ln",
    "sg:city":"Aylett",
    "sg:classifiers":[
        {
            "category":"Professional",
            "subcategory":"Accounting & Tax Preparation",
            "type":"Services"
        }
    ],
    "sg:phone":"+1 804 769 2883",
    "sg:postcode":"23009",
    "sg:province":"VA",
    "sg:tags":[
        "accountant"
    ],
    "wof:name":"Schools & Barnette Plc",
    "wof:placetype":"venue"
},
  "geometry": {"coordinates":[-77.14201799999999,37.7637],"type":"Point"}
}