{
  "type": "Feature",
  "properties": {
    "addr:full":"6713 Mechanicsville Tpke Mechanicsville VA 23111",
    "addr:housenumber":"6713",
    "addr:postcode":"23111",
    "addr:street":"Mechanicsville Tpke",
    "iso:country":"US",
    "sg:address":"6713 Mechanicsville Tpke",
    "sg:city":"Mechanicsville",
    "sg:classifiers":[
        {
            "category":"Building & Trades",
            "subcategory":"Plumbing",
            "type":"Services"
        }
    ],
    "sg:phone":"+1 804 730 5080",
    "sg:postcode":"23111",
    "sg:province":"VA",
    "sg:tags":[
        "refrigeration",
        "contractor"
    ],
    "wof:name":"Whitman Refrigeration",
    "wof:placetype":"venue"
},
  "geometry": {"coordinates":[-77.334604,37.612691],"type":"Point"}
}