{
  "type": "Feature",
  "properties": {
    "addr:full":"10320 Layton Hall Dr Fairfax VA 22030",
    "addr:housenumber":"10320",
    "addr:postcode":"22030",
    "addr:street":"Layton Hall Dr",
    "iso:country":"US",
    "sg:address":"10320 Layton Hall Dr",
    "sg:city":"Fairfax",
    "sg:classifiers":[
        {
            "category":"Real Estate",
            "subcategory":"Real Estate Operator",
            "type":"Services"
        }
    ],
    "sg:phone":"+1 703 273 1013",
    "sg:postcode":"22030",
    "sg:province":"VA",
    "sg:tags":[
        "building",
        "apartment"
    ],
    "wof:name":"Layton Hall Apartments",
    "wof:placetype":"venue"
},
  "geometry": {"coordinates":[-77.299769,38.850186],"type":"Point"}
}