{
  "type": "Feature",
  "properties": {
    "addr:full":"370 Colonial Ave Colonial Beach VA 22443",
    "addr:housenumber":"370",
    "addr:postcode":"beach;22443",
    "addr:street":"Colonial Ave",
    "iso:country":"US",
    "sg:address":"370 Colonial Ave",
    "sg:city":"Colonial Beach",
    "sg:classifiers":[
        {
            "category":"Shopping",
            "type":"Retail Goods"
        }
    ],
    "sg:phone":"+1 804 224 9140",
    "sg:postcode":"22443",
    "sg:province":"VA",
    "sg:tags":[
        "picture",
        "frame"
    ],
    "wof:name":"Olga's Art & Framing",
    "wof:placetype":"venue"
},
  "geometry": {"coordinates":[-76.966605,38.254503],"type":"Point"}
}