{
  "type": "Feature",
  "properties": {
    "iso:country":"US",
    "sg:address":"300 Grande Ct",
    "sg:city":"Richmond",
    "sg:classifiers":[
        {
            "category":"Professional",
            "subcategory":"Management & Consulting",
            "type":"Services"
        }
    ],
    "sg:phone":"+1 804 750 1065",
    "sg:postcode":"23229",
    "sg:province":"VA",
    "sg:tags":[
        "business"
    ],
    "wof:name":"Gil Gonzales Assoc Inc",
    "wof:placetype":"venue"
},
  "geometry": {"coordinates":[-77.587811,37.584219],"type":"Point"}
}