{
  "type": "Feature",
  "properties": {
    "addr:full":"8784 Centreville Rd Manassas VA 20110",
    "addr:housenumber":"8784",
    "addr:postcode":"20110",
    "addr:street":"Centreville Rd",
    "iso:country":"US",
    "sg:address":"8784 Centreville Rd",
    "sg:city":"Manassas",
    "sg:classifiers":[
        {
            "category":"Retail",
            "subcategory":"Car Wash",
            "type":"Services"
        }
    ],
    "sg:phone":"+1 703 330 4910",
    "sg:postcode":"20110",
    "sg:province":"VA",
    "sg:tags":[
        "automobile",
        "material",
        "coating",
        "detail",
        "tinting",
        "glass",
        "clean"
    ],
    "sg:website":"http://www.latint.com",
    "wof:name":"LA Tint",
    "wof:placetype":"venue"
},
  "geometry": {"coordinates":[-77.45875599999999,38.763479],"type":"Point"}
}