{
  "type": "Feature",
  "properties": {
    "addr:full":"354 Morgan Ford Rd Front Royal VA 22630",
    "addr:housenumber":"354",
    "addr:postcode":"22630",
    "addr:street":"Morgan Ford Rd",
    "iso:country":"US",
    "sg:address":"354 Morgan Ford Rd",
    "sg:city":"Front Royal",
    "sg:classifiers":[
        {
            "category":"Building & Trades",
            "subcategory":"Construction",
            "type":"Services"
        }
    ],
    "sg:phone":"+1 540 636 9694",
    "sg:postcode":"22630",
    "sg:province":"VA",
    "sg:tags":[
        "house"
    ],
    "wof:name":"Dollys Home Improvement",
    "wof:placetype":"venue"
},
  "geometry": {"coordinates":[-78.126328,38.94367],"type":"Point"}
}