{
  "type": "Feature",
  "properties": {
    "addr:full":"7200 Telegraph Square Dr Lorton VA 22079",
    "addr:housenumber":"7200",
    "addr:postcode":"22079",
    "addr:street":"Telegraph Square Dr",
    "iso:country":"US",
    "sg:address":"7200 Telegraph Square Dr",
    "sg:city":"Lorton",
    "sg:classifiers":[
        {
            "category":"Restaurant",
            "type":"Food & Drink"
        }
    ],
    "sg:phone":"+1 703 550 1235",
    "sg:postcode":"22079",
    "sg:province":"VA",
    "sg:tags":[
        "out"
    ],
    "wof:name":"Sun Deli Express",
    "wof:placetype":"venue"
},
  "geometry": {"coordinates":[-77.193658,38.71704],"type":"Point"}
}