{
  "type": "Feature",
  "properties": {
    "iso:country":"US",
    "sg:address":"207 E Main St",
    "sg:city":"Remington",
    "sg:classifiers":[
        {
            "category":"Shopping",
            "subcategory":"Pharmacy",
            "type":"Retail Goods"
        }
    ],
    "sg:phone":"+1 540 439 3247",
    "sg:postcode":"22734",
    "sg:province":"VA",
    "wof:name":"Remington Drug Co",
    "wof:placetype":"venue"
},
  "geometry": {"coordinates":[-77.806558,38.53293],"type":"Point"}
}