{
  "type": "Feature",
  "properties": {
    "addr:full":"5809 W Norfolk Rd Portsmouth VA 23703",
    "addr:housenumber":"5809",
    "addr:postcode":"23703",
    "addr:street":"W Norfolk Rd",
    "iso:country":"US",
    "sg:address":"5809 W Norfolk Rd",
    "sg:city":"Portsmouth",
    "sg:classifiers":[
        {
            "category":"Shopping",
            "subcategory":"Used Merchandise",
            "type":"Retail Goods"
        }
    ],
    "sg:phone":"+1 757 686 5404",
    "sg:postcode":"23703",
    "sg:province":"VA",
    "sg:tags":[
        "antique"
    ],
    "wof:name":"Art Artifacts Antq & Auctions",
    "wof:placetype":"venue"
},
  "geometry": {"coordinates":[-76.394777,36.864509],"type":"Point"}
}