{
  "type": "Feature",
  "properties": {
    "addr:full":"1477 Carl D Silver Pkwy Fredericksburg VA 22401",
    "addr:housenumber":"1477",
    "addr:postcode":"22401",
    "addr:street":"Carl D Silver Pkwy",
    "iso:country":"US",
    "sg:address":"1477 Carl D Silver Pkwy",
    "sg:city":"Fredericksburg",
    "sg:classifiers":[
        {
            "category":"Personal",
            "subcategory":"Beauty Salon",
            "type":"Services"
        }
    ],
    "sg:phone":"+1 540 785 2522",
    "sg:postcode":"22401",
    "sg:province":"VA",
    "sg:tags":[
        "shop"
    ],
    "wof:name":"Great Clips",
    "wof:placetype":"venue"
},
  "geometry": {"coordinates":[-77.507874,38.303751],"type":"Point"}
}