{
  "type": "Feature",
  "properties": {
    "addr:full":"202 Susan Newton Ln Yorktown VA 23693",
    "addr:housenumber":"202",
    "addr:postcode":"23693",
    "addr:street":"Susan Newton Ln",
    "iso:country":"US",
    "sg:address":"202 Susan Newton Ln",
    "sg:city":"Yorktown",
    "sg:classifiers":[
        {
            "category":"Professional",
            "subcategory":"Management & Consulting",
            "type":"Services"
        }
    ],
    "sg:phone":"+1 757 867 6565",
    "sg:postcode":"23693",
    "sg:province":"VA",
    "sg:tags":[
        "contracting"
    ],
    "wof:name":"Adrian Incorporated",
    "wof:placetype":"venue"
},
  "geometry": {"coordinates":[-76.438211,37.119155],"type":"Point"}
}