{
  "type": "Feature",
  "properties": {
    "addr:full":"305 Bartell Dr Chesapeake VA 23322",
    "addr:housenumber":"305",
    "addr:postcode":"23322",
    "addr:street":"Bartell Dr",
    "iso:country":"US",
    "sg:address":"305 Bartell Dr",
    "sg:city":"Chesapeake",
    "sg:classifiers":[
        {
            "category":"Mining & Drilling",
            "type":"Manufacturing & Wholesale Goods"
        }
    ],
    "sg:phone":"+1 757 548 2947",
    "sg:postcode":"23322",
    "sg:province":"VA",
    "sg:tags":[
        "field"
    ],
    "wof:name":"Leslie Beliles",
    "wof:placetype":"venue"
},
  "geometry": {"coordinates":[-76.25306999999999,36.712669],"type":"Point"}
}