{
  "type": "Feature",
  "properties": {
    "addr:full":"92 Le-Way Ln Fredericksburg VA 22406",
    "addr:housenumber":"92",
    "addr:postcode":"22406",
    "addr:street":"Le-Way Ln",
    "iso:country":"US",
    "sg:address":"92 Le-Way Ln",
    "sg:city":"Fredericksburg",
    "sg:classifiers":[
        {
            "category":"Building & Trades",
            "subcategory":"Construction",
            "type":"Services"
        }
    ],
    "sg:phone":"+1 540 752 7535",
    "sg:postcode":"22406",
    "sg:province":"VA",
    "sg:tags":[
        "concrete",
        "contractor"
    ],
    "wof:name":"Aarons Concrete Pumping Inc",
    "wof:placetype":"venue"
},
  "geometry": {"coordinates":[-77.516081,38.355131],"type":"Point"}
}