{
  "type": "Feature",
  "properties": {
    "addr:full":"5512 Sunbeam Rd Richmond VA 23234",
    "addr:housenumber":"5512",
    "addr:postcode":"23234",
    "addr:street":"Sunbeam Rd",
    "iso:country":"US",
    "sg:address":"5512 Sunbeam Rd",
    "sg:city":"Richmond",
    "sg:classifiers":[
        {
            "category":"Professional",
            "subcategory":"Business Services",
            "type":"Services"
        }
    ],
    "sg:phone":"+1 804 714 3400",
    "sg:postcode":"23234",
    "sg:province":"VA",
    "sg:tags":[
        "liquidator"
    ],
    "wof:name":"Global Travel Intl",
    "wof:placetype":"venue"
},
  "geometry": {"coordinates":[-77.47616600000001,37.445878],"type":"Point"}
}