{
  "type": "Feature",
  "properties": {
    "addr:full":"1080 S Antioch Rd Luray VA 22835",
    "addr:housenumber":"1080",
    "addr:postcode":"22835",
    "addr:street":"S Antioch Rd",
    "iso:country":"US",
    "sg:address":"1080 S Antioch Rd",
    "sg:city":"Luray",
    "sg:classifiers":[
        {
            "category":"Farming",
            "subcategory":"Livestock Farm",
            "type":"Manufacturing & Wholesale Goods"
        }
    ],
    "sg:phone":"+1 540 743 5637",
    "sg:postcode":"22835",
    "sg:province":"VA",
    "sg:tags":[
        "egg",
        "beef",
        "feedlot",
        "cattle"
    ],
    "wof:name":"Charles Spitler",
    "wof:placetype":"venue"
},
  "geometry": {"coordinates":[-78.430145,38.653826],"type":"Point"}
}