{
  "type": "Feature",
  "properties": {
    "addr:full":"619 Chimborazo Blvd Richmond VA 23223",
    "addr:housenumber":"619",
    "addr:postcode":"23223",
    "addr:street":"Chimborazo Blvd",
    "iso:country":"US",
    "sg:address":"619 Chimborazo Blvd",
    "sg:city":"Richmond",
    "sg:classifiers":[
        {
            "category":"Restaurant",
            "type":"Food & Drink"
        }
    ],
    "sg:phone":"+1 804 236 3982",
    "sg:postcode":"23223",
    "sg:province":"VA",
    "sg:tags":[
        "eating"
    ],
    "wof:name":"Richbrau Brewery",
    "wof:placetype":"venue"
},
  "geometry": {"coordinates":[-77.407394,37.529942],"type":"Point"}
}