{
  "type": "Feature",
  "properties": {
    "iso:country":"US",
    "sg:address":"1000 Cherry Ave",
    "sg:city":"Charlottesville",
    "sg:classifiers":[
        {
            "category":"Recreation",
            "type":"Entertainment"
        }
    ],
    "sg:phone":"+1 434 977 1960",
    "sg:postcode":"22903",
    "sg:province":"VA",
    "sg:tags":[
        "pool",
        "swimming"
    ],
    "sg:website":"www.charlottesville.org/recreation",
    "wof:name":"Smith Pool",
    "wof:placetype":"venue"
},
  "geometry": {"coordinates":[-78.495876,38.028649],"type":"Point"}
}