{
  "type": "Feature",
  "properties": {
    "addr:full":"19011 Industrial Rd Culpeper VA 22701",
    "addr:housenumber":"19011",
    "addr:postcode":"22701",
    "addr:street":"Industrial Rd",
    "iso:country":"US",
    "sg:address":"19011 Industrial Rd",
    "sg:city":"Culpeper",
    "sg:classifiers":[
        {
            "category":"Utilities",
            "subcategory":"Mobile Phone",
            "type":"Services"
        }
    ],
    "sg:phone":"+1 540 825 9924",
    "sg:postcode":"22701",
    "sg:province":"VA",
    "sg:tags":[
        "telephone",
        "cellular"
    ],
    "wof:name":"Verizon",
    "wof:placetype":"venue"
},
  "geometry": {"coordinates":[-78.002342,38.442313],"type":"Point"}
}