{
  "type": "Feature",
  "properties": {
    "iso:country":"US",
    "sg:address":"9233 Okla Dr",
    "sg:city":"Fairfax",
    "sg:classifiers":[
        {
            "category":"Retail",
            "subcategory":"Car Wash",
            "type":"Services"
        }
    ],
    "sg:phone":"+1 703 323 1239",
    "sg:postcode":"22031",
    "sg:province":"VA",
    "sg:tags":[
        "carwash"
    ],
    "wof:name":"Mobile Auto Detailing",
    "wof:placetype":"venue"
},
  "geometry": {"coordinates":[-77.265609,38.841736],"type":"Point"}
}