{
  "type": "Feature",
  "properties": {
    "addr:full":"2548 Virginia Beach Blvd Virginia Beach VA 23452",
    "addr:housenumber":"2548",
    "addr:postcode":"23452",
    "addr:street":"Virginia Beach Blvd",
    "iso:country":"US",
    "sg:address":"2548 Virginia Beach Blvd",
    "sg:city":"Virginia Beach",
    "sg:classifiers":[
        {
            "category":"Shopping",
            "subcategory":"Computers & Home Electronics",
            "type":"Retail Goods"
        }
    ],
    "sg:phone":"+1 757 200 3900",
    "sg:postcode":"23452",
    "sg:province":"VA",
    "sg:tags":[
        "equipment",
        "dealer"
    ],
    "wof:name":"Tomorrow's Treasures",
    "wof:placetype":"venue"
},
  "geometry": {"coordinates":[-76.058266,36.841256],"type":"Point"}
}