{
  "type": "Feature",
  "properties": {
    "addr:full":"343 Sawyers Mill Xing Chesapeake VA 23323",
    "addr:housenumber":"343",
    "addr:postcode":"23323",
    "addr:street":"Sawyers Mill Xing",
    "iso:country":"US",
    "sg:address":"343 Sawyers Mill Xing",
    "sg:city":"Chesapeake",
    "sg:classifiers":[
        {
            "category":"Professional",
            "type":"Services"
        }
    ],
    "sg:phone":"+1 757 487 9814",
    "sg:postcode":"23323",
    "sg:province":"VA",
    "sg:tags":[
        "establishment"
    ],
    "wof:name":"Sawyers Mill Clubhouse",
    "wof:placetype":"venue"
},
  "geometry": {"coordinates":[-76.332753,36.723486],"type":"Point"}
}