{
  "type": "Feature",
  "properties": {
    "iso:country":"US",
    "sg:address":"1189 Steep Hill Ln",
    "sg:city":"Vinton",
    "sg:classifiers":[
        {
            "category":"Professional",
            "subcategory":"Secretarial Services",
            "type":"Services"
        }
    ],
    "sg:phone":"+1 540 890 0316",
    "sg:postcode":"24179",
    "sg:province":"VA",
    "sg:tags":[
        "reporting",
        "court"
    ],
    "wof:name":"Carole Ayers",
    "wof:placetype":"venue"
},
  "geometry": {"coordinates":[-79.82119400000001,37.290966],"type":"Point"}
}