{
  "type": "Feature",
  "properties": {
    "addr:full":"74 Rowe St Staunton VA 24401",
    "addr:housenumber":"74",
    "addr:postcode":"24401",
    "addr:street":"Rowe St",
    "iso:country":"US",
    "sg:address":"74 Rowe St",
    "sg:city":"Staunton",
    "sg:classifiers":[
        {
            "category":"Restaurant",
            "type":"Food & Drink"
        }
    ],
    "sg:phone":"+1 540 886 1833",
    "sg:postcode":"24401",
    "sg:province":"VA",
    "sg:tags":[
        "country",
        "style",
        "family"
    ],
    "wof:name":"Mrs Rowe Family Rest & Bky",
    "wof:placetype":"venue"
},
  "geometry": {"coordinates":[-79.102594,38.154245],"type":"Point"}
}