{
  "type": "Feature",
  "properties": {
    "addr:full":"4415 Pheasant Ridge Rd Roanoke VA 24014",
    "addr:housenumber":"4415",
    "addr:postcode":"24014",
    "addr:street":"Pheasant Ridge Rd",
    "iso:country":"US",
    "sg:address":"4415 Pheasant Ridge Rd",
    "sg:city":"Roanoke",
    "sg:classifiers":[
        {
            "category":"Home & Garden",
            "subcategory":"Garden Supply",
            "type":"Retail Goods"
        }
    ],
    "sg:phone":"+1 540 774 6855",
    "sg:postcode":"24014",
    "sg:province":"VA",
    "wof:name":"Harmony Holdings Inc",
    "wof:placetype":"venue"
},
  "geometry": {"coordinates":[-79.963994,37.223354],"type":"Point"}
}