{
  "type": "Feature",
  "properties": {
    "iso:country":"US",
    "sg:address":"5517 N Wilson Blvd",
    "sg:city":"Arlington",
    "sg:classifiers":[
        {
            "category":"Retail",
            "subcategory":"Repair Shop",
            "type":"Services"
        }
    ],
    "sg:phone":"+1 703 842 5294",
    "sg:postcode":"22205",
    "sg:province":"VA",
    "sg:tags":[
        "lock",
        "locksmith"
    ],
    "wof:name":"1 All Day Emergency",
    "wof:placetype":"venue"
},
  "geometry": {"coordinates":[-77.12808699999999,38.87654],"type":"Point"}
}