{
  "type": "Feature",
  "properties": {
    "addr:full":"9087 Liberia Ave Manassas VA 20110",
    "addr:housenumber":"9087",
    "addr:postcode":"20110",
    "addr:street":"Liberia Ave",
    "iso:country":"US",
    "sg:address":"9087 Liberia Ave",
    "sg:city":"Manassas",
    "sg:classifiers":[
        {
            "category":"Shopping",
            "subcategory":"Computers & Home Electronics",
            "type":"Retail Goods"
        }
    ],
    "sg:phone":"+1 703 361 9649",
    "sg:postcode":"20110",
    "sg:province":"VA",
    "wof:name":"IMPACT Ltd",
    "wof:placetype":"venue"
},
  "geometry": {"coordinates":[-77.456611,38.760408],"type":"Point"}
}