{
  "type": "Feature",
  "properties": {
    "addr:full":"211 Lester St Martinsville VA 24112",
    "addr:housenumber":"211",
    "addr:postcode":"24112",
    "addr:street":"Lester St",
    "iso:country":"US",
    "sg:address":"211 Lester St",
    "sg:city":"Martinsville",
    "sg:classifiers":[
        {
            "category":"Wholesale",
            "subcategory":"Construction Materials",
            "type":"Manufacturing & Wholesale Goods"
        }
    ],
    "sg:phone":"+1 276 632 3968",
    "sg:postcode":"24112",
    "sg:province":"VA",
    "sg:tags":[
        "sand",
        "gravel"
    ],
    "wof:name":"H B Martin Limestone & Frtlzr",
    "wof:placetype":"venue"
},
  "geometry": {"coordinates":[-79.869539,36.694634],"type":"Point"}
}