{
  "type": "Feature",
  "properties": {
    "addr:full":"2787 Melchester Dr Herndon VA 20171",
    "addr:housenumber":"2787",
    "addr:postcode":"20171",
    "addr:street":"Melchester Dr",
    "iso:country":"US",
    "sg:address":"2787 Melchester Dr",
    "sg:city":"Herndon",
    "sg:classifiers":[
        {
            "category":"Retail",
            "subcategory":"Repair Shop",
            "type":"Services"
        },
        {
            "category":"Home & Garden",
            "subcategory":"Furniture",
            "type":"Retail Goods"
        }
    ],
    "sg:phone":"+1 703 478 0080",
    "sg:postcode":"20171",
    "sg:province":"VA",
    "sg:tags":[
        "refinishing"
    ],
    "wof:name":"Furniture Medic Inc",
    "wof:placetype":"venue"
},
  "geometry": {"coordinates":[-77.39858700000001,38.928858],"type":"Point"}
}