{
  "type": "Feature",
  "properties": {
    "addr:full":"10507 Braddock Rd Fairfax VA 22032",
    "addr:housenumber":"10507",
    "addr:postcode":"22032",
    "addr:street":"Braddock Rd",
    "iso:country":"US",
    "sg:address":"10507 Braddock Rd",
    "sg:city":"Fairfax",
    "sg:classifiers":[
        {
            "category":"Building & Trades",
            "subcategory":"Cleaning & Sanitation",
            "type":"Services"
        }
    ],
    "sg:phone":"+1 703 426 2038",
    "sg:postcode":"22032",
    "sg:province":"VA",
    "sg:tags":[
        "maintenance"
    ],
    "wof:name":"Cavalier Telephone",
    "wof:placetype":"venue"
},
  "geometry": {"coordinates":[-77.308318,38.823998],"type":"Point"}
}