{
  "type": "Feature",
  "properties": {
    "iso:country":"US",
    "sg:address":"4600 King St",
    "sg:city":"Alexandria",
    "sg:classifiers":[
        {
            "category":"Health Services",
            "subcategory":"Doctor",
            "type":"Services"
        },
        {
            "category":"Health Services",
            "subcategory":"Hospital",
            "type":"Services"
        }
    ],
    "sg:phone":"+1 703 354 6665",
    "sg:postcode":"22302",
    "sg:province":"VA",
    "sg:tags":[
        "throat",
        "ear",
        "nose"
    ],
    "wof:name":"A A A Urgent Care",
    "wof:placetype":"venue"
},
  "geometry": {"coordinates":[-77.10700199999999,38.841099],"type":"Point"}
}