{
  "type": "Feature",
  "properties": {
    "addr:full":"6800 Grayson Tpke Speedwell VA 24374",
    "addr:housenumber":"6800",
    "addr:postcode":"24374",
    "addr:street":"Grayson Tpke",
    "iso:country":"US",
    "sg:address":"6800 Grayson Tpke",
    "sg:city":"Speedwell",
    "sg:classifiers":[
        {
            "category":"Freight",
            "type":"Transportation"
        }
    ],
    "sg:phone":"+1 276 621 5232",
    "sg:postcode":"24374",
    "sg:province":"VA",
    "sg:tags":[
        "operator",
        "trucking"
    ],
    "wof:name":"McCowan Mobile Home Movers",
    "wof:placetype":"venue"
},
  "geometry": {"coordinates":[-81.17477599999999,36.815279],"type":"Point"}
}