{
  "type": "Feature",
  "properties": {
    "iso:country":"US",
    "sg:address":"707 Main Dr",
    "sg:city":"Herndon",
    "sg:classifiers":[
        {
            "category":"Building & Trades",
            "subcategory":"Landscaping Services",
            "type":"Services"
        }
    ],
    "sg:phone":"+1 703 437 5489",
    "sg:postcode":"20170",
    "sg:province":"VA",
    "sg:tags":[
        "landscape"
    ],
    "wof:name":"Rw Updike & Co Inc",
    "wof:placetype":"venue"
},
  "geometry": {"coordinates":[-77.393287,38.969558],"type":"Point"}
}