{
  "type": "Feature",
  "properties": {
    "addr:full":"1071 Jacob Burner Dr Mc Gaheysville VA 22840",
    "addr:housenumber":"1071",
    "addr:postcode":"22840",
    "addr:street":"Jacob Burner Dr",
    "iso:country":"US",
    "sg:address":"1071 Jacob Burner Dr",
    "sg:city":"Mc Gaheysville",
    "sg:classifiers":[
        {
            "category":"Farming",
            "subcategory":"Dairy Farm",
            "type":"Manufacturing & Wholesale Goods"
        }
    ],
    "sg:phone":"+1 540 289 9728",
    "sg:postcode":"22840",
    "sg:province":"VA",
    "wof:name":"W Indrose Holsteins",
    "wof:placetype":"venue"
},
  "geometry": {"coordinates":[-78.718411,38.361027],"type":"Point"}
}