{
  "type": "Feature",
  "properties": {
    "addr:full":"8010 Whitebark Ter Richmond VA 23237",
    "addr:postcode":"8010;23237",
    "addr:street":"Whitebark Ter",
    "iso:country":"US",
    "sg:address":"8010 Whitebark Ter",
    "sg:city":"Richmond",
    "sg:classifiers":[
        {
            "category":"Professional",
            "subcategory":"Research",
            "type":"Services"
        }
    ],
    "sg:phone":"+1 804 271 8069",
    "sg:postcode":"23237",
    "sg:province":"VA",
    "sg:tags":[
        "environmental",
        "ecological"
    ],
    "sg:website":"www.cfe.com",
    "wof:name":"Growth Environmental Svc Inc",
    "wof:placetype":"venue"
},
  "geometry": {"coordinates":[-77.52775800000001,37.400894],"type":"Point"}
}