{
  "type": "Feature",
  "properties": {
    "addr:full":"4921 Whitman Ln Virginia Beach VA 23455",
    "addr:housenumber":"4921",
    "addr:postcode":"23455",
    "addr:street":"Whitman Ln",
    "iso:country":"US",
    "sg:address":"4921 Whitman Ln",
    "sg:city":"Virginia Beach",
    "sg:classifiers":[
        {
            "category":"Freight",
            "type":"Transportation"
        }
    ],
    "sg:phone":"+1 757 416 0008",
    "sg:postcode":"23455",
    "sg:province":"VA",
    "wof:name":"Direct Express Freight Service",
    "wof:placetype":"venue"
},
  "geometry": {"coordinates":[-76.148599,36.865677],"type":"Point"}
}