{
  "type": "Feature",
  "properties": {
    "iso:country":"US",
    "sg:address":"21376 Potomac View Rd",
    "sg:city":"Sterling",
    "sg:classifiers":[
        {
            "category":"Organizations",
            "subcategory":"Professional Association",
            "type":"Services"
        }
    ],
    "sg:phone":"+1 703 404 2971",
    "sg:postcode":"20164",
    "sg:province":"VA",
    "wof:name":"Christopher Dulin",
    "wof:placetype":"venue"
},
  "geometry": {"coordinates":[-77.391997,39.024768],"type":"Point"}
}