{
  "type": "Feature",
  "properties": {
    "iso:country":"US",
    "sg:address":"108 Molesey Hurst",
    "sg:city":"Williamsburg",
    "sg:classifiers":[
        {
            "category":"Building & Trades",
            "subcategory":"Equipment Rental",
            "type":"Services"
        }
    ],
    "sg:phone":"+1 757 258 8947",
    "sg:postcode":"23188",
    "sg:province":"VA",
    "wof:name":"Premier Rental Purchase",
    "wof:placetype":"venue"
},
  "geometry": {"coordinates":[-76.792903,37.297479],"type":"Point"}
}