{
  "type": "Feature",
  "properties": {
    "iso:country":"US",
    "sg:address":"100 Deidre Ln",
    "sg:city":"Newport News",
    "sg:classifiers":[
        {
            "category":"Home & Garden",
            "subcategory":"Building Materials",
            "type":"Retail Goods"
        }
    ],
    "sg:phone":"+1 757 880 3438",
    "sg:postcode":"23602",
    "sg:province":"VA",
    "sg:tags":[
        "windows"
    ],
    "wof:name":"Mr Window Express",
    "wof:placetype":"venue"
},
  "geometry": {"coordinates":[-76.542991,37.123408],"type":"Point"}
}