{
  "type": "Feature",
  "properties": {
    "iso:country":"US",
    "sg:address":"2508 Seaview Ave",
    "sg:city":"Virginia Beach",
    "sg:classifiers":[
        {
            "category":"Building & Trades",
            "subcategory":"Construction",
            "type":"Services"
        }
    ],
    "sg:phone":"+1 757 464 2621",
    "sg:postcode":"23455",
    "sg:province":"VA",
    "sg:tags":[
        "house"
    ],
    "wof:name":"Surf & Sand Construction Co",
    "wof:placetype":"venue"
},
  "geometry": {"coordinates":[-76.125489,36.915504],"type":"Point"}
}