{
  "type": "Feature",
  "properties": {
    "addr:full":"9680 Eaton Woods Pl Lorton VA 22079",
    "addr:housenumber":"9680",
    "addr:postcode":"22079",
    "addr:street":"Eaton Woods Pl",
    "iso:country":"US",
    "sg:address":"9680 Eaton Woods Pl",
    "sg:city":"Lorton",
    "sg:classifiers":[
        {
            "category":"Social Services",
            "subcategory":"Child Care",
            "type":"Services"
        }
    ],
    "sg:phone":"+1 703 339 1886",
    "sg:postcode":"22079",
    "sg:province":"VA",
    "sg:tags":[
        "day"
    ],
    "wof:name":"Maria A Aponte",
    "wof:placetype":"venue"
},
  "geometry": {"coordinates":[-77.220107,38.694325],"type":"Point"}
}