{
  "type": "Feature",
  "properties": {
    "addr:full":"161 Jefferson St Williamsburg VA 23185",
    "addr:housenumber":"161",
    "addr:postcode":"23185",
    "addr:street":"Jefferson St",
    "iso:country":"US",
    "sg:address":"161 Jefferson St",
    "sg:city":"Williamsburg",
    "sg:classifiers":[
        {
            "category":"Wholesale",
            "subcategory":"Farm Supplies",
            "type":"Manufacturing & Wholesale Goods"
        }
    ],
    "sg:phone":"+1 757 564 5913",
    "sg:postcode":"23185",
    "sg:province":"VA",
    "sg:tags":[
        "feed"
    ],
    "wof:name":"Commodity Specialists Company",
    "wof:placetype":"venue"
},
  "geometry": {"coordinates":[-76.690887,37.277787],"type":"Point"}
}