{
  "type": "Feature",
  "properties": {
    "addr:full":"6412 Shady Ln Falls Church VA 22042",
    "addr:housenumber":"6412",
    "addr:postcode":"22042",
    "addr:street":"Shady Ln",
    "iso:country":"US",
    "sg:address":"6412 Shady Ln",
    "sg:city":"Falls Church",
    "sg:classifiers":[
        {
            "category":"Travel",
            "subcategory":"Travel Agent",
            "type":"Entertainment"
        }
    ],
    "sg:phone":"+1 703 237 0100",
    "sg:postcode":"22042",
    "sg:province":"VA",
    "sg:tags":[
        "agency",
        "bureau"
    ],
    "wof:name":"Cross Cultural Adventures",
    "wof:placetype":"venue"
},
  "geometry": {"coordinates":[-77.162606,38.873951],"type":"Point"}
}