{
  "type": "Feature",
  "properties": {
    "addr:full":"2823 Mustang Dr Herndon VA 20171",
    "addr:housenumber":"2823",
    "addr:postcode":"20171",
    "addr:street":"Mustang Dr",
    "iso:country":"US",
    "sg:address":"2823 Mustang Dr",
    "sg:city":"Herndon",
    "sg:classifiers":[
        {
            "category":"Shopping",
            "subcategory":"Gifts & Souvenirs",
            "type":"Retail Goods"
        }
    ],
    "sg:phone":"+1 703 793 0149",
    "sg:postcode":"20171",
    "sg:province":"VA",
    "sg:tags":[
        "personal"
    ],
    "wof:name":"Party Troupers",
    "wof:placetype":"venue"
},
  "geometry": {"coordinates":[-77.41672800000001,38.931829],"type":"Point"}
}