{
  "type": "Feature",
  "properties": {
    "addr:full":"392 Garrisonville Rd Stafford VA 22554",
    "addr:housenumber":"392",
    "addr:postcode":"22554",
    "addr:street":"Garrisonville Rd",
    "iso:country":"US",
    "sg:address":"392 Garrisonville Rd",
    "sg:city":"Stafford",
    "sg:classifiers":[
        {
            "category":"Health Services",
            "subcategory":"Doctor",
            "type":"Services"
        }
    ],
    "sg:phone":"+1 540 659 4885",
    "sg:postcode":"22554",
    "sg:province":"VA",
    "sg:tags":[
        "physician",
        "surgeon"
    ],
    "wof:name":"Physician Inforamtion & Referr",
    "wof:placetype":"venue"
},
  "geometry": {"coordinates":[-77.428612,38.474897],"type":"Point"}
}