{
  "type": "Feature",
  "properties": {
    "iso:country":"US",
    "sg:address":"10015 Jefferson Ave",
    "sg:city":"Newport News",
    "sg:classifiers":[
        {
            "category":"Shopping",
            "subcategory":"Hobbies, Toys, & Games",
            "type":"Retail Goods"
        }
    ],
    "sg:phone":"+1 757 591 0720",
    "sg:postcode":"23605",
    "sg:province":"VA",
    "sg:website":"www.streamhobbyshop.com",
    "wof:name":"Stream Hobby Shop",
    "wof:placetype":"venue"
},
  "geometry": {"coordinates":[-76.456897,37.038931],"type":"Point"}
}