{
  "type": "Feature",
  "properties": {
    "addr:full":"44901 Falcon Pl Sterling VA 20166",
    "addr:housenumber":"44901",
    "addr:postcode":"20166",
    "addr:street":"Falcon Pl",
    "iso:country":"US",
    "sg:address":"44901 Falcon Pl",
    "sg:city":"Sterling",
    "sg:classifiers":[
        {
            "category":"Wholesale",
            "subcategory":"Machinery & Supplies",
            "type":"Manufacturing & Wholesale Goods"
        }
    ],
    "sg:phone":"+1 571 323 2497",
    "sg:postcode":"20166",
    "sg:province":"VA",
    "wof:name":"Granite Transformations",
    "wof:placetype":"venue"
},
  "geometry": {"coordinates":[-77.448154,38.978911],"type":"Point"}
}