{
  "type": "Feature",
  "properties": {
    "addr:full":"2623 Grand Glen Rd Richmond VA 23223",
    "addr:housenumber":"2623",
    "addr:postcode":"23223",
    "addr:street":"Grand Glen Rd",
    "iso:country":"US",
    "sg:address":"2623 Grand Glen Rd",
    "sg:city":"Richmond",
    "sg:classifiers":[
        {
            "category":"Social Services",
            "type":"Services"
        }
    ],
    "sg:phone":"+1 804 447 5793",
    "sg:postcode":"23223",
    "sg:province":"VA",
    "wof:name":"From Within Counseling",
    "wof:placetype":"venue"
},
  "geometry": {"coordinates":[-77.38858500000001,37.560731],"type":"Point"}
}