{
  "type": "Feature",
  "properties": {
    "iso:country":"US",
    "sg:address":"815 Branch Dr",
    "sg:city":"Herndon",
    "sg:classifiers":[
        {
            "category":"Health Services",
            "subcategory":"Doctor",
            "type":"Services"
        }
    ],
    "sg:phone":"+1 703 787 8124",
    "sg:postcode":"20170",
    "sg:province":"VA",
    "sg:tags":[
        "physician",
        "surgeon"
    ],
    "wof:name":"Healthcare Dist",
    "wof:placetype":"venue"
},
  "geometry": {"coordinates":[-77.38708200000001,38.973282],"type":"Point"}
}