{
  "type": "Feature",
  "properties": {
    "addr:full":"3195 N Wilson Blvd Arlington VA 22201",
    "addr:housenumber":"3195",
    "addr:postcode":"22201",
    "addr:street":"N Wilson Blvd",
    "iso:country":"US",
    "sg:address":"3195 N Wilson Blvd",
    "sg:city":"Arlington",
    "sg:classifiers":[
        {
            "category":"Organizations",
            "subcategory":"Non-profit Organization",
            "type":"Services"
        }
    ],
    "sg:phone":"+1 703 276 0228",
    "sg:postcode":"22201",
    "sg:province":"VA",
    "sg:tags":[
        "social"
    ],
    "wof:name":"Clarendon Alliance Inc",
    "wof:placetype":"venue"
},
  "geometry": {"coordinates":[-77.09625800000001,38.886629],"type":"Point"}
}