{
  "type": "Feature",
  "properties": {
    "addr:full":"5171 Kennebeck Ave Norfolk VA 23513",
    "addr:housenumber":"5171",
    "addr:postcode":"23513",
    "addr:street":"Kennebeck Ave",
    "iso:country":"US",
    "sg:address":"5171 Kennebeck Ave",
    "sg:city":"Norfolk",
    "sg:classifiers":[
        {
            "category":"Retail",
            "subcategory":"Auto Repair",
            "type":"Services"
        }
    ],
    "sg:phone":"+1 757 853 5743",
    "sg:postcode":"23513",
    "sg:province":"VA",
    "sg:tags":[
        "general"
    ],
    "wof:name":"Kap Services",
    "wof:placetype":"venue"
},
  "geometry": {"coordinates":[-76.229416,36.882557],"type":"Point"}
}