{
  "type": "Feature",
  "properties": {
    "addr:full":"1204 Drake St SW Vienna VA 22180",
    "addr:housenumber":"1204",
    "addr:postcode":"22180",
    "addr:street":"Drake St Sw",
    "iso:country":"US",
    "sg:address":"1204 Drake St SW",
    "sg:city":"Vienna",
    "sg:classifiers":[
        {
            "category":"Organizations",
            "subcategory":"Religious Organization",
            "type":"Services"
        }
    ],
    "sg:phone":"+1 703 281 3467",
    "sg:postcode":"22180",
    "sg:province":"VA",
    "sg:tags":[
        "clergy"
    ],
    "wof:name":"William C Poston",
    "wof:placetype":"venue"
},
  "geometry": {"coordinates":[-77.25559800000001,38.882007],"type":"Point"}
}