{
  "type": "Feature",
  "properties": {
    "addr:full":"100 Alleghany St Clifton Forge VA 24422",
    "addr:housenumber":"100",
    "addr:postcode":"24422",
    "addr:street":"Alleghany St",
    "iso:country":"US",
    "sg:address":"100 Alleghany St",
    "sg:city":"Clifton Forge",
    "sg:classifiers":[
        {
            "category":"Professional",
            "type":"Services"
        }
    ],
    "sg:phone":"+1 540 862 1257",
    "sg:postcode":"24422",
    "sg:province":"VA",
    "sg:tags":[
        "establishment"
    ],
    "wof:name":"Pure & Simple",
    "wof:placetype":"venue"
},
  "geometry": {"coordinates":[-79.83235999999999,37.814411],"type":"Point"}
}