{
  "type": "Feature",
  "properties": {
    "iso:country":"US",
    "sg:address":"23109 Tidewater Trl",
    "sg:city":"Port Royal",
    "sg:classifiers":[
        {
            "category":"Personal",
            "subcategory":"Beauty Salon",
            "type":"Services"
        }
    ],
    "sg:phone":"+1 804 742 5671",
    "sg:postcode":"22538",
    "sg:province":"VA",
    "sg:tags":[
        "shop"
    ],
    "wof:name":"Family Affair Event Planning C",
    "wof:placetype":"venue"
},
  "geometry": {"coordinates":[-77.23573399999999,38.175885],"type":"Point"}
}