{
  "type": "Feature",
  "properties": {
    "addr:full":"2353 52nd St Hampton VA 23661",
    "addr:housenumber":"2353",
    "addr:postcode":"23661",
    "addr:street":"52Nd St",
    "iso:country":"US",
    "sg:address":"2353 52nd St",
    "sg:city":"Hampton",
    "sg:classifiers":[
        {
            "category":"Wholesale",
            "subcategory":"Machinery & Supplies",
            "type":"Manufacturing & Wholesale Goods"
        }
    ],
    "sg:phone":"+1 757 825 0594",
    "sg:postcode":"23661",
    "sg:province":"VA",
    "sg:tags":[
        "truck"
    ],
    "wof:name":"Joseph E Sullivan Inc",
    "wof:placetype":"venue"
},
  "geometry": {"coordinates":[-76.401712,37.00793],"type":"Point"}
}