{
  "type": "Feature",
  "properties": {
    "iso:country":"US",
    "sg:address":"1835 S 9th St",
    "sg:city":"Arlington",
    "sg:classifiers":[
        {
            "category":"Organizations",
            "subcategory":"Community Association",
            "type":"Services"
        }
    ],
    "sg:phone":"+1 703 528 3139",
    "sg:postcode":"22204",
    "sg:province":"VA",
    "sg:tags":[
        "military"
    ],
    "wof:name":"Mt Vernon Chapter-Military",
    "wof:placetype":"venue"
},
  "geometry": {"coordinates":[-77.07703600000001,38.866495],"type":"Point"}
}