{
  "type": "Feature",
  "properties": {
    "iso:country":"US",
    "sg:address":"21279 Lake Rd",
    "sg:city":"Abingdon",
    "sg:classifiers":[
        {
            "category":"Communications",
            "type":"Services"
        }
    ],
    "sg:phone":"+1 276 676 4566",
    "sg:postcode":"24211",
    "sg:province":"VA",
    "wof:name":"Holston Valley Communications",
    "wof:placetype":"venue"
},
  "geometry": {"coordinates":[-81.98633599999999,36.621466],"type":"Point"}
}