{
  "type": "Feature",
  "properties": {
    "iso:country":"US",
    "sg:address":"803 N Highland St",
    "sg:city":"Arlington",
    "sg:classifiers":[
        {
            "category":"Professional",
            "subcategory":"Computer Services",
            "type":"Services"
        }
    ],
    "sg:phone":"+1 703 243 3981",
    "sg:postcode":"22201",
    "sg:province":"VA",
    "sg:tags":[
        "prepackaged",
        "software"
    ],
    "wof:name":"Gale Force Software Inc",
    "wof:placetype":"venue"
},
  "geometry": {"coordinates":[-77.094471,38.882818],"type":"Point"}
}