{
  "type": "Feature",
  "properties": {
    "addr:full":"2031 Huskie Dr Hampton VA 23665",
    "addr:housenumber":"2031",
    "addr:postcode":"23665",
    "addr:street":"Huskie Dr",
    "iso:country":"US",
    "sg:address":"2031 Huskie Dr",
    "sg:city":"Hampton",
    "sg:classifiers":[
        {
            "category":"Professional",
            "subcategory":"Lawyer & Legal Services",
            "type":"Services"
        }
    ],
    "sg:phone":"+1 757 766 7422",
    "sg:postcode":"23665",
    "sg:province":"VA",
    "wof:name":"Prepaid Legal Services Inc",
    "wof:placetype":"venue"
},
  "geometry": {"coordinates":[-76.428557,37.10003],"type":"Point"}
}