{
  "type": "Feature",
  "properties": {
    "addr:full":"5003 Gilritchie Ct Petersburg VA 23803",
    "addr:housenumber":"5003",
    "addr:postcode":"23803",
    "addr:street":"Gilritchie Ct",
    "iso:country":"US",
    "sg:address":"5003 Gilritchie Ct",
    "sg:city":"Petersburg",
    "sg:classifiers":[
        {
            "category":"Building & Trades",
            "subcategory":"Landscaping Services",
            "type":"Services"
        }
    ],
    "sg:phone":"+1 804 526 8214",
    "sg:postcode":"23803",
    "sg:province":"VA",
    "wof:name":"J&D Lawn Svc",
    "wof:placetype":"venue"
},
  "geometry": {"coordinates":[-77.45754599999999,37.23075],"type":"Point"}
}