{
  "type": "Feature",
  "properties": {
    "iso:country":"US",
    "sg:address":"8301 Frosty Ct",
    "sg:city":"Lorton",
    "sg:classifiers":[
        {
            "category":"Building & Trades",
            "subcategory":"Construction",
            "type":"Services"
        }
    ],
    "sg:phone":"+1 703 550 2558",
    "sg:postcode":"22079",
    "sg:province":"VA",
    "sg:tags":[
        "house"
    ],
    "wof:name":"Canyon Construction Corp",
    "wof:placetype":"venue"
},
  "geometry": {"coordinates":[-77.18023100000001,38.729113],"type":"Point"}
}