{
  "type": "Feature",
  "properties": {
    "addr:full":"933 Queen St Portsmouth VA 23704",
    "addr:housenumber":"933",
    "addr:postcode":"23704",
    "addr:street":"Queen St",
    "iso:country":"US",
    "sg:address":"933 Queen St",
    "sg:city":"Portsmouth",
    "sg:classifiers":[
        {
            "category":"Shopping",
            "subcategory":"Used Merchandise",
            "type":"Retail Goods"
        }
    ],
    "sg:phone":"+1 757 397 7070",
    "sg:postcode":"23704",
    "sg:province":"VA",
    "sg:tags":[
        "junk"
    ],
    "wof:name":"East Coast Auto Recovery",
    "wof:placetype":"venue"
},
  "geometry": {"coordinates":[-76.310017,36.835844],"type":"Point"}
}