{
  "type": "Feature",
  "properties": {
    "addr:full":"5043 Parrish Branch Rd Midlothian VA 23112",
    "addr:housenumber":"5043",
    "addr:postcode":"23112",
    "addr:street":"Parrish Branch Rd",
    "iso:country":"US",
    "sg:address":"5043 Parrish Branch Rd",
    "sg:city":"Midlothian",
    "sg:classifiers":[
        {
            "category":"Restaurant",
            "type":"Food & Drink"
        }
    ],
    "sg:phone":"+1 804 744 0699",
    "sg:postcode":"23112",
    "sg:province":"VA",
    "sg:tags":[
        "eating"
    ],
    "wof:name":"Village Grill",
    "wof:placetype":"venue"
},
  "geometry": {"coordinates":[-77.608437,37.420678],"type":"Point"}
}