{
  "type": "Feature",
  "properties": {
    "iso:country":"US",
    "sg:address":"6100 Warwick Blvd",
    "sg:city":"Newport News",
    "sg:classifiers":[
        {
            "category":"Building & Trades",
            "subcategory":"Construction",
            "type":"Services"
        }
    ],
    "sg:phone":"+1 757 247 8416",
    "sg:postcode":"23607",
    "sg:province":"VA",
    "sg:tags":[
        "executive"
    ],
    "wof:name":"Newport News Water Works",
    "wof:placetype":"venue"
},
  "geometry": {"coordinates":[-76.441137,37.002966],"type":"Point"}
}