{
  "type": "Feature",
  "properties": {
    "iso:country":"US",
    "sg:address":"7556 Telegraph Rd",
    "sg:city":"Alexandria",
    "sg:classifiers":[
        {
            "category":"Shopping",
            "subcategory":"Florist",
            "type":"Retail Goods"
        }
    ],
    "sg:phone":"+1 703 922 5557",
    "sg:postcode":"22315",
    "sg:province":"VA",
    "wof:name":"Christopher's Flowers",
    "wof:placetype":"venue"
},
  "geometry": {"coordinates":[-77.13820200000001,38.753938],"type":"Point"}
}