{
  "type": "Feature",
  "properties": {
    "addr:full":"1905 Front St Richlands VA 24641",
    "addr:housenumber":"1905",
    "addr:postcode":"24641",
    "addr:street":"Front St",
    "iso:country":"US",
    "sg:address":"1905 Front St",
    "sg:city":"Richlands",
    "sg:classifiers":[
        {
            "category":"Banks & Credit Unions",
            "subcategory":"Bank",
            "type":"Services"
        }
    ],
    "sg:phone":"+1 276 963 8311",
    "sg:postcode":"24641",
    "sg:province":"VA",
    "sg:tags":[
        "state",
        "commercial"
    ],
    "wof:name":"Bank Of Tazewell County",
    "wof:placetype":"venue"
},
  "geometry": {"coordinates":[-81.802437,37.094364],"type":"Point"}
}