{
  "type": "Feature",
  "properties": {
    "addr:full":"1325 Progress Rd Front Royal VA 22630",
    "addr:housenumber":"1325",
    "addr:postcode":"22630",
    "addr:street":"Progress Rd",
    "iso:country":"US",
    "sg:address":"1325 Progress Rd",
    "sg:city":"Front Royal",
    "sg:classifiers":[
        {
            "category":"Shopping",
            "subcategory":"Optical Goods",
            "type":"Retail Goods"
        }
    ],
    "sg:phone":"+1 540 636 7976",
    "sg:postcode":"22630",
    "sg:province":"VA",
    "wof:name":"Correctech Inc",
    "wof:placetype":"venue"
},
  "geometry": {"coordinates":[-78.154065,38.93751],"type":"Point"}
}