{
  "type": "Feature",
  "properties": {
    "addr:full":"1136 Garcia Dr Moneta VA 24121",
    "addr:housenumber":"1136",
    "addr:postcode":"24121",
    "addr:street":"Garcia Dr",
    "iso:country":"US",
    "sg:address":"1136 Garcia Dr",
    "sg:city":"Moneta",
    "sg:classifiers":[
        {
            "category":"Organizations",
            "subcategory":"Religious Organization",
            "type":"Services"
        }
    ],
    "sg:phone":"+1 540 721 5764",
    "sg:postcode":"24121",
    "sg:province":"VA",
    "sg:tags":[
        "church"
    ],
    "wof:name":"Trinity Lutheran Church",
    "wof:placetype":"venue"
},
  "geometry": {"coordinates":[-79.605018,37.167342],"type":"Point"}
}