{
  "type": "Feature",
  "properties": {
    "addr:full":"3800 Colley Ave Norfolk VA 23508",
    "addr:housenumber":"3800",
    "addr:postcode":"23508",
    "addr:street":"Colley Ave",
    "iso:country":"US",
    "sg:address":"3800 Colley Ave",
    "sg:city":"Norfolk",
    "sg:classifiers":[
        {
            "category":"Government",
            "subcategory":"Post Office",
            "type":"Public Place"
        }
    ],
    "sg:phone":"+1 757 624 9472",
    "sg:postcode":"23508",
    "sg:province":"VA",
    "sg:tags":[
        "postal",
        "us"
    ],
    "wof:name":"US Post Office",
    "wof:placetype":"venue"
},
  "geometry": {"coordinates":[-76.294738,36.880786],"type":"Point"}
}