{
  "type": "Feature",
  "properties": {
    "iso:country":"US",
    "sg:address":"7314 Charlotte St",
    "sg:city":"Springfield",
    "sg:classifiers":[
        {
            "category":"Professional",
            "subcategory":"Accounting & Tax Preparation",
            "type":"Services"
        }
    ],
    "sg:phone":"+1 703 644 2590",
    "sg:postcode":"22150",
    "sg:province":"VA",
    "wof:name":"Arden Accunting Tax Fincl Svcs",
    "wof:placetype":"venue"
},
  "geometry": {"coordinates":[-77.19498299999999,38.78343],"type":"Point"}
}