{
  "type": "Feature",
  "properties": {
    "addr:full":"118 Long Bridge Rd Hampton VA 23669",
    "addr:housenumber":"118",
    "addr:postcode":"23669",
    "addr:street":"Long Bridge Rd",
    "iso:country":"US",
    "sg:address":"118 Long Bridge Rd",
    "sg:city":"Hampton",
    "sg:classifiers":[
        {
            "category":"Building & Trades",
            "subcategory":"Plumbing",
            "type":"Services"
        }
    ],
    "sg:phone":"+1 757 675 5282",
    "sg:postcode":"23669",
    "sg:province":"VA",
    "sg:tags":[
        "plumbing",
        "contractor"
    ],
    "wof:name":"E Z Way Plumbing Maintenance",
    "wof:placetype":"venue"
},
  "geometry": {"coordinates":[-76.33906,37.056173],"type":"Point"}
}