{
  "type": "Feature",
  "properties": {
    "iso:country":"US",
    "sg:address":"11026 Rixeyville Rd",
    "sg:city":"Culpeper",
    "sg:classifiers":[
        {
            "category":"Freight",
            "type":"Transportation"
        }
    ],
    "sg:phone":"+1 540 937 6054",
    "sg:postcode":"22701",
    "sg:province":"VA",
    "sg:tags":[
        "hauling",
        "trucking"
    ],
    "wof:name":"J & E Transport Inc",
    "wof:placetype":"venue"
},
  "geometry": {"coordinates":[-77.979298,38.553022],"type":"Point"}
}