{
  "type": "Feature",
  "properties": {
    "iso:country":"US",
    "sg:address":"3634 S Plaza Trl",
    "sg:city":"Virginia Beach",
    "sg:classifiers":[
        {
            "category":"Personal",
            "subcategory":"Beauty Salon",
            "type":"Services"
        }
    ],
    "sg:phone":"+1 757 486 7199",
    "sg:postcode":"23452",
    "sg:province":"VA",
    "wof:name":"Affinity Hair Studio",
    "wof:placetype":"venue"
},
  "geometry": {"coordinates":[-76.097886,36.829878],"type":"Point"}
}