{
  "type": "Feature",
  "properties": {
    "iso:country":"US",
    "sg:address":"1696 Cottenham Ln",
    "sg:city":"Virginia Beach",
    "sg:classifiers":[
        {
            "category":"Professional",
            "subcategory":"Business Services",
            "type":"Services"
        }
    ],
    "sg:phone":"+1 757 426 1500",
    "sg:postcode":"23454",
    "sg:province":"VA",
    "wof:name":"Java Business Solutions",
    "wof:placetype":"venue"
},
  "geometry": {"coordinates":[-75.993636,36.784985],"type":"Point"}
}