{
  "type": "Feature",
  "properties": {
    "addr:full":"4023 25th Rd N Arlington VA 22207",
    "addr:housenumber":"4023",
    "addr:postcode":"22207",
    "addr:street":"25Th Rd N",
    "iso:country":"US",
    "sg:address":"4023 25th Rd N",
    "sg:city":"Arlington",
    "sg:classifiers":[
        {
            "category":"Organizations",
            "subcategory":"Professional Association",
            "type":"Services"
        }
    ],
    "sg:phone":"+1 703 527 4565",
    "sg:postcode":"22207",
    "sg:province":"VA",
    "wof:name":"National Assn-Military Widows",
    "wof:placetype":"venue"
},
  "geometry": {"coordinates":[-77.109832,38.903924],"type":"Point"}
}