{
  "type": "Feature",
  "properties": {
    "iso:country":"US",
    "sg:address":"855 S Pickett St",
    "sg:city":"Alexandria",
    "sg:classifiers":[
        {
            "category":"Wholesale",
            "subcategory":"Machinery & Supplies",
            "type":"Manufacturing & Wholesale Goods"
        }
    ],
    "sg:phone":"+1 703 751 5777",
    "sg:postcode":"22304",
    "sg:province":"VA",
    "sg:tags":[
        "janitor"
    ],
    "wof:name":"Spectrowax Corp",
    "wof:placetype":"venue"
},
  "geometry": {"coordinates":[-77.14084099999999,38.803181],"type":"Point"}
}