{
  "type": "Feature",
  "properties": {
    "addr:full":"12819 Spotswood Trl Quinque VA 22968",
    "addr:housenumber":"12819",
    "addr:postcode":"22968",
    "addr:street":"Spotswood Trl",
    "iso:country":"US",
    "sg:address":"12819 Spotswood Trl",
    "sg:city":"Quinque",
    "sg:classifiers":[
        {
            "category":"Retail",
            "subcategory":"Funeral Services",
            "type":"Services"
        }
    ],
    "sg:phone":"+1 434 985 2620",
    "sg:postcode":"22968",
    "sg:province":"VA",
    "sg:tags":[
        "crematory"
    ],
    "wof:name":"Ryan Funeral Home",
    "wof:placetype":"venue"
},
  "geometry": {"coordinates":[-78.39821999999999,38.250589],"type":"Point"}
}