{
  "type": "Feature",
  "properties": {
    "addr:full":"8915 Footstep Ct Annandale VA 22003",
    "addr:housenumber":"8915",
    "addr:postcode":"22003",
    "addr:street":"Footstep Ct",
    "iso:country":"US",
    "sg:address":"8915 Footstep Ct",
    "sg:city":"Annandale",
    "sg:classifiers":[
        {
            "category":"Building & Trades",
            "subcategory":"Construction",
            "type":"Services"
        }
    ],
    "sg:phone":"+1 703 503 8495",
    "sg:postcode":"22003",
    "sg:province":"VA",
    "sg:tags":[
        "house"
    ],
    "wof:name":"Singletary Builders Inc",
    "wof:placetype":"venue"
},
  "geometry": {"coordinates":[-77.251985,38.83331],"type":"Point"}
}