{
  "type": "Feature",
  "properties": {
    "iso:country":"US",
    "sg:address":"1603 Liberty Lake Rd",
    "sg:city":"Red House",
    "sg:classifiers":[
        {
            "category":"Restaurant",
            "type":"Food & Drink"
        }
    ],
    "sg:phone":"+1 434 376 9900",
    "sg:postcode":"23963",
    "sg:province":"VA",
    "sg:tags":[
        "caterer"
    ],
    "wof:name":"Briery Creek Catering Steak",
    "wof:placetype":"venue"
},
  "geometry": {"coordinates":[-78.84979,37.203297],"type":"Point"}
}