{
  "type": "Feature",
  "properties": {
    "addr:full":"201 Concourse Blvd Glen Allen VA 23059",
    "addr:housenumber":"201",
    "addr:postcode":"23059",
    "addr:street":"Concourse Blvd",
    "iso:country":"US",
    "sg:address":"201 Concourse Blvd",
    "sg:city":"Glen Allen",
    "sg:classifiers":[
        {
            "category":"Banks & Credit Unions",
            "subcategory":"Bank",
            "type":"Services"
        }
    ],
    "sg:phone":"+1 804 217 8055",
    "sg:postcode":"23059",
    "sg:province":"VA",
    "sg:tags":[
        "loan",
        "real estate"
    ],
    "wof:name":"First Choice Mortgage",
    "wof:placetype":"venue"
},
  "geometry": {"coordinates":[-77.590597,37.687902],"type":"Point"}
}