{
  "type": "Feature",
  "properties": {
    "addr:full":"1421 Dolley Madison Blvd Mc Lean VA 22101",
    "addr:housenumber":"1421",
    "addr:postcode":"22101",
    "addr:street":"Dolley Madison Blvd Mc Lean",
    "iso:country":"US",
    "sg:address":"1421 Dolley Madison Blvd",
    "sg:city":"Mc Lean",
    "sg:classifiers":[
        {
            "category":"Professional",
            "subcategory":"Management & Consulting",
            "type":"Services"
        }
    ],
    "sg:phone":"+1 703 506 8026",
    "sg:postcode":"22101",
    "sg:province":"VA",
    "sg:tags":[
        "consultant",
        "business"
    ],
    "wof:name":"JBW Assoc Inc",
    "wof:placetype":"venue"
},
  "geometry": {"coordinates":[-77.18218299999999,38.93833],"type":"Point"}
}