{
  "type": "Feature",
  "properties": {
    "addr:full":"11800 Midlothian Tpke Midlothian VA 23113",
    "addr:housenumber":"11800",
    "addr:postcode":"23113",
    "addr:street":"Midlothian Tpke",
    "iso:country":"US",
    "sg:address":"11800 Midlothian Tpke",
    "sg:city":"Midlothian",
    "sg:classifiers":[
        {
            "category":"Wholesale",
            "subcategory":"Electrical",
            "type":"Manufacturing & Wholesale Goods"
        }
    ],
    "sg:phone":"+1 804 379 8296",
    "sg:postcode":"23113",
    "sg:province":"VA",
    "sg:tags":[
        "telecommunication"
    ],
    "wof:name":"Teleco",
    "wof:placetype":"venue"
},
  "geometry": {"coordinates":[-77.616467,37.504916],"type":"Point"}
}