{
  "type": "Feature",
  "properties": {
    "addr:full":"510 W Oldtown St Galax VA 24333",
    "addr:housenumber":"510",
    "addr:postcode":"24333",
    "addr:street":"W Oldtown St",
    "iso:country":"US",
    "sg:address":"510 W Oldtown St",
    "sg:city":"Galax",
    "sg:classifiers":[
        {
            "category":"Retail",
            "subcategory":"Auto Repair",
            "type":"Services"
        }
    ],
    "sg:phone":"+1 276 236 2741",
    "sg:postcode":"24333",
    "sg:province":"VA",
    "sg:tags":[
        "repairing",
        "automobile"
    ],
    "wof:name":"Stuart Drive Auto Svc",
    "wof:placetype":"venue"
},
  "geometry": {"coordinates":[-80.928848,36.659781],"type":"Point"}
}