{
  "type": "Feature",
  "properties": {
    "iso:country":"US",
    "sg:address":"109 Cherry St",
    "sg:city":"Suffolk",
    "sg:classifiers":[
        {
            "category":"Shopping",
            "subcategory":"Used Merchandise",
            "type":"Retail Goods"
        }
    ],
    "sg:phone":"+1 757 934 1423",
    "sg:postcode":"23434",
    "sg:province":"VA",
    "wof:name":"Southern Gun Works",
    "wof:placetype":"venue"
},
  "geometry": {"coordinates":[-76.58477600000001,36.726885],"type":"Point"}
}