{
  "type": "Feature",
  "properties": {
    "iso:country":"US",
    "sg:address":"13411 Green Orchard Ct",
    "sg:city":"Chester",
    "sg:classifiers":[
        {
            "category":"Wholesale",
            "subcategory":"Machinery & Supplies",
            "type":"Manufacturing & Wholesale Goods"
        }
    ],
    "sg:phone":"+1 804 530 0082",
    "sg:postcode":"23836",
    "sg:province":"VA",
    "sg:tags":[
        "brush"
    ],
    "wof:name":"Fuller Brush Co",
    "wof:placetype":"venue"
},
  "geometry": {"coordinates":[-77.350397,37.340378],"type":"Point"}
}