{
  "type": "Feature",
  "properties": {
    "addr:full":"3241 Douglas Rd Chesapeake VA 23322",
    "addr:housenumber":"3241",
    "addr:postcode":"23322",
    "addr:street":"Douglas Rd",
    "iso:country":"US",
    "sg:address":"3241 Douglas Rd",
    "sg:city":"Chesapeake",
    "sg:classifiers":[
        {
            "category":"Shopping",
            "type":"Retail Goods"
        }
    ],
    "sg:phone":"+1 757 421 4605",
    "sg:postcode":"23322",
    "sg:province":"VA",
    "wof:name":"T & J Cole Frame & Art",
    "wof:placetype":"venue"
},
  "geometry": {"coordinates":[-76.34088800000001,36.62956],"type":"Point"}
}