{
  "type": "Feature",
  "properties": {
    "iso:country":"US",
    "sg:address":"3701 Turnpike Rd",
    "sg:city":"Portsmouth",
    "sg:classifiers":[
        {
            "category":"Food & Beverages",
            "subcategory":"Groceries & Convenience Stores",
            "type":"Retail Goods"
        }
    ],
    "sg:phone":"+1 757 398 9369",
    "sg:postcode":"23701",
    "sg:province":"VA",
    "wof:name":"One Stop Food Store",
    "wof:placetype":"venue"
},
  "geometry": {"coordinates":[-76.347234,36.820033],"type":"Point"}
}