{
  "type": "Feature",
  "properties": {
    "addr:full":"13360 Minnieville Rd Woodbridge VA 22192",
    "addr:housenumber":"13360",
    "addr:postcode":"22192",
    "addr:street":"Minnieville Rd",
    "iso:country":"US",
    "sg:address":"13360 Minnieville Rd",
    "sg:city":"Woodbridge",
    "sg:classifiers":[
        {
            "category":"Food & Beverages",
            "subcategory":"Groceries & Convenience Stores",
            "type":"Retail Goods"
        }
    ],
    "sg:phone":"+1 703 897 7417",
    "sg:postcode":"22192",
    "sg:province":"VA",
    "wof:name":"Southland Corp",
    "wof:placetype":"venue"
},
  "geometry": {"coordinates":[-77.300962,38.6591],"type":"Point"}
}