{
  "type": "Feature",
  "properties": {
    "iso:country":"US",
    "sg:address":"660 Spring St",
    "sg:city":"Herndon",
    "sg:classifiers":[
        {
            "category":"Organizations",
            "subcategory":"Religious Organization",
            "type":"Services"
        }
    ],
    "sg:phone":"+1 703 736 0592",
    "sg:postcode":"20170",
    "sg:province":"VA",
    "wof:name":"Herndon Friends Meeting",
    "wof:placetype":"venue"
},
  "geometry": {"coordinates":[-77.386055,38.968641],"type":"Point"}
}