{
  "type": "Feature",
  "properties": {
    "addr:full":"126 Bent Tree Dr Blairs VA 24527",
    "addr:housenumber":"126",
    "addr:postcode":"blairs;24527",
    "addr:street":"Bent Tree Dr",
    "iso:country":"US",
    "sg:address":"126 Bent Tree Dr",
    "sg:city":"Blairs",
    "sg:classifiers":[
        {
            "category":"Shopping",
            "subcategory":"Catalog Store",
            "type":"Retail Goods"
        }
    ],
    "sg:phone":"+1 434 836 0749",
    "sg:postcode":"24527",
    "sg:province":"VA",
    "sg:tags":[
        "sales"
    ],
    "wof:name":"Brothersmith-Knivescom",
    "wof:placetype":"venue"
},
  "geometry": {"coordinates":[-79.38296200000001,36.712141],"type":"Point"}
}