{
  "type": "Feature",
  "properties": {
    "addr:full":"1940 Laskin Rd Virginia Beach VA 23454",
    "addr:housenumber":"1940",
    "addr:postcode":"23454",
    "addr:street":"Laskin Rd",
    "iso:country":"US",
    "sg:address":"1940 Laskin Rd",
    "sg:city":"Virginia Beach",
    "sg:classifiers":[
        {
            "category":"Shopping",
            "subcategory":"Discount & Variety Stores",
            "type":"Retail Goods"
        },
        {
            "category":"Shopping",
            "subcategory":"Department Store",
            "type":"Retail Goods"
        }
    ],
    "sg:phone":"+1 757 543 6650",
    "sg:postcode":"23454",
    "sg:province":"VA",
    "sg:tags":[
        "shop"
    ],
    "wof:name":"Dollar Tree",
    "wof:placetype":"venue"
},
  "geometry": {"coordinates":[-76.034087,36.848255],"type":"Point"}
}