{
  "type": "Feature",
  "properties": {
    "addr:full":"620 College Ter Williamsburg VA 23185",
    "addr:housenumber":"620",
    "addr:postcode":"23185",
    "addr:street":"College Ter",
    "iso:country":"US",
    "sg:address":"620 College Ter",
    "sg:city":"Williamsburg",
    "sg:classifiers":[
        {
            "category":"Shopping",
            "subcategory":"Clothing, Apparel, & Fashions",
            "type":"Retail Goods"
        }
    ],
    "sg:phone":"+1 757 229 8883",
    "sg:postcode":"23185",
    "sg:province":"VA",
    "sg:tags":[
        "tailor"
    ],
    "wof:name":"Saigon Tailors LLC",
    "wof:placetype":"venue"
},
  "geometry": {"coordinates":[-76.715937,37.27498],"type":"Point"}
}