{
  "type": "Feature",
  "properties": {
    "iso:country":"US",
    "sg:address":"5500 Carolina Rd",
    "sg:city":"Suffolk",
    "sg:classifiers":[
        {
            "category":"Organizations",
            "subcategory":"Religious Organization",
            "type":"Services"
        }
    ],
    "sg:phone":"+1 757 986 2548",
    "sg:postcode":"23434",
    "sg:province":"VA",
    "wof:name":"Virginia Crolina Temple Church",
    "wof:placetype":"venue"
},
  "geometry": {"coordinates":[-76.575344,36.552429],"type":"Point"}
}