{
  "type": "Feature",
  "properties": {
    "addr:full":"8310 Lilac Ln Alexandria VA 22308",
    "addr:housenumber":"8310",
    "addr:postcode":"22308",
    "addr:street":"Lilac Ln",
    "iso:country":"US",
    "sg:address":"8310 Lilac Ln",
    "sg:city":"Alexandria",
    "sg:classifiers":[
        {
            "category":"Professional",
            "type":"Services"
        }
    ],
    "sg:phone":"+1 703 360 7805",
    "sg:postcode":"22308",
    "sg:province":"VA",
    "sg:tags":[
        "establishment"
    ],
    "sg:website":"www.jmg-associates-ltd.com",
    "wof:name":"JMG Assoc LTD",
    "wof:placetype":"venue"
},
  "geometry": {"coordinates":[-77.04919,38.731612],"type":"Point"}
}