{
  "type": "Feature",
  "properties": {
    "addr:full":"5204 Port Royal Rd Springfield VA 22151",
    "addr:housenumber":"5204",
    "addr:postcode":"22151",
    "addr:street":"Port Royal Rd",
    "iso:country":"US",
    "sg:address":"5204 Port Royal Rd",
    "sg:city":"Springfield",
    "sg:classifiers":[
        {
            "category":"Food & Beverages",
            "subcategory":"Groceries & Convenience Stores",
            "type":"Retail Goods"
        }
    ],
    "sg:phone":"+1 703 321 8695",
    "sg:postcode":"22151",
    "sg:province":"VA",
    "wof:name":"Safeway",
    "wof:placetype":"venue"
},
  "geometry": {"coordinates":[-77.219582,38.809118],"type":"Point"}
}