{
  "type": "Feature",
  "properties": {
    "addr:full":"1804 Vista Cir Bedford VA 24523",
    "addr:housenumber":"1804",
    "addr:postcode":"24523",
    "addr:street":"Vista Cir",
    "iso:country":"US",
    "sg:address":"1804 Vista Cir",
    "sg:city":"Bedford",
    "sg:classifiers":[
        {
            "category":"Retail",
            "subcategory":"Portrait Studio",
            "type":"Services"
        }
    ],
    "sg:phone":"+1 540 587 8765",
    "sg:postcode":"24523",
    "sg:province":"VA",
    "sg:tags":[
        "photo"
    ],
    "wof:name":"Creative Images Photography",
    "wof:placetype":"venue"
},
  "geometry": {"coordinates":[-79.512044,37.358813],"type":"Point"}
}