{
  "type": "Feature",
  "properties": {
    "addr:full":"7753 Sudley Rd Manassas VA 20109",
    "addr:housenumber":"7753",
    "addr:postcode":"20109",
    "addr:street":"Sudley Rd",
    "iso:country":"US",
    "sg:address":"7753 Sudley Rd",
    "sg:city":"Manassas",
    "sg:classifiers":[
        {
            "category":"Bars & Pubs",
            "subcategory":"Sports Bar",
            "type":"Food & Drink"
        },
        {
            "category":"Restaurant",
            "type":"Food & Drink"
        }
    ],
    "sg:phone":"+1 703 365 8400",
    "sg:postcode":"20109",
    "sg:province":"VA",
    "sg:tags":[
        "traditional",
        "american"
    ],
    "sg:website":"www.hardtimes.com",
    "wof:name":"Hard Times Cafe & Cue",
    "wof:placetype":"venue"
},
  "geometry": {"coordinates":[-77.51400700000001,38.788103],"type":"Point"}
}