{
  "type": "Feature",
  "properties": {
    "addr:full":"131 Conway Dr Danville VA 24540",
    "addr:housenumber":"131",
    "addr:postcode":"24540",
    "addr:street":"Conway Dr",
    "iso:country":"US",
    "sg:address":"131 Conway Dr",
    "sg:city":"Danville",
    "sg:classifiers":[
        {
            "category":"Wholesale",
            "subcategory":"Construction Materials",
            "type":"Manufacturing & Wholesale Goods"
        }
    ],
    "sg:phone":"+1 434 836 6066",
    "sg:postcode":"24540",
    "sg:province":"VA",
    "wof:name":"Timber Products Co",
    "wof:placetype":"venue"
},
  "geometry": {"coordinates":[-79.396191,36.633913],"type":"Point"}
}