{
  "type": "Feature",
  "properties": {
    "addr:full":"259 Granby St Norfolk VA 23510",
    "addr:housenumber":"259",
    "addr:postcode":"23510",
    "addr:street":"Granby St",
    "iso:country":"US",
    "sg:address":"259 Granby St",
    "sg:city":"Norfolk",
    "sg:classifiers":[
        {
            "category":"Shopping",
            "type":"Retail Goods"
        }
    ],
    "sg:phone":"+1 757 962 7700",
    "sg:postcode":"23510",
    "sg:province":"VA",
    "sg:tags":[
        "merchandise"
    ],
    "wof:name":"Wonder Gallery",
    "wof:placetype":"venue"
},
  "geometry": {"coordinates":[-76.29056199999999,36.849907],"type":"Point"}
}