{
  "type": "Feature",
  "properties": {
    "addr:full":"4589 Ottobine Rd Dayton VA 22821",
    "addr:housenumber":"4589",
    "addr:postcode":"22821",
    "addr:street":"Ottobine Rd",
    "iso:country":"US",
    "sg:address":"4589 Ottobine Rd",
    "sg:city":"Dayton",
    "sg:classifiers":[
        {
            "category":"Home & Garden",
            "subcategory":"Building Materials",
            "type":"Retail Goods"
        }
    ],
    "sg:phone":"+1 540 879 9743",
    "sg:postcode":"22821",
    "sg:province":"VA",
    "sg:tags":[
        "sell",
        "roofing",
        "supply"
    ],
    "wof:name":"Showalter Brothers",
    "wof:placetype":"venue"
},
  "geometry": {"coordinates":[-78.983463,38.407966],"type":"Point"}
}