{
  "type": "Feature",
  "properties": {
    "addr:full":"302 S Cameron St Winchester VA 22601",
    "addr:housenumber":"302",
    "addr:postcode":"22601",
    "addr:street":"S Cameron St",
    "iso:country":"US",
    "sg:address":"302 S Cameron St",
    "sg:city":"Winchester",
    "sg:classifiers":[
        {
            "category":"Health Services",
            "subcategory":"Doctor",
            "type":"Services"
        }
    ],
    "sg:phone":"+1 540 667 7463",
    "sg:postcode":"22601",
    "sg:province":"VA",
    "sg:tags":[
        "physician",
        "surgeon"
    ],
    "wof:name":"Ophthalmology Eye Care",
    "wof:placetype":"venue"
},
  "geometry": {"coordinates":[-78.16515800000001,39.180931],"type":"Point"}
}