{
  "type": "Feature",
  "properties": {
    "iso:country":"US",
    "sg:address":"945 Canal Dr",
    "sg:city":"Chesapeake",
    "sg:classifiers":[
        {
            "category":"Personal",
            "subcategory":"Beauty Salon",
            "type":"Services"
        }
    ],
    "sg:phone":"+1 757 485 4247",
    "sg:postcode":"23323",
    "sg:province":"VA",
    "sg:tags":[
        "shop"
    ],
    "wof:name":"Hair Styles",
    "wof:placetype":"venue"
},
  "geometry": {"coordinates":[-76.325048,36.775631],"type":"Point"}
}