{
  "type": "Feature",
  "properties": {
    "addr:full":"11900 Livingston Rd Ste 126 Manassas VA 20109",
    "addr:housenumber":"11900",
    "addr:postcode":"20109",
    "addr:street":"Livingston Rd Ste 126",
    "iso:country":"US",
    "sg:address":"11900 Livingston Rd Ste 126",
    "sg:city":"Manassas",
    "sg:classifiers":[
        {
            "category":"Building & Trades",
            "subcategory":"Plumbing",
            "type":"Services"
        }
    ],
    "sg:phone":"+1 703 530 8001",
    "sg:postcode":"20109",
    "sg:province":"VA",
    "sg:website":"www.cameronplumbingva.com",
    "wof:name":"Cameron Plumbing",
    "wof:placetype":"venue"
},
  "geometry": {"coordinates":[-77.551014,38.783615],"type":"Point"}
}