{
  "type": "Feature",
  "properties": {
    "iso:country":"US",
    "sg:address":"3909 Redstone Dr",
    "sg:city":"Richmond",
    "sg:classifiers":[
        {
            "category":"Wholesale",
            "subcategory":"Plants",
            "type":"Manufacturing & Wholesale Goods"
        }
    ],
    "sg:phone":"+1 804 270 7408",
    "sg:postcode":"23294",
    "sg:province":"VA",
    "sg:tags":[
        "supply"
    ],
    "wof:name":"Seasonal Sales",
    "wof:placetype":"venue"
},
  "geometry": {"coordinates":[-77.53498999999999,37.641227],"type":"Point"}
}