{
  "type": "Feature",
  "properties": {
    "addr:full":"8309 Richmond Hwy Alexandria VA 22309",
    "addr:housenumber":"8309",
    "addr:postcode":"22309",
    "addr:street":"Richmond Hwy",
    "iso:country":"US",
    "sg:address":"8309 Richmond Hwy",
    "sg:city":"Alexandria",
    "sg:classifiers":[
        {
            "category":"Professional",
            "subcategory":"Computer Services",
            "type":"Services"
        }
    ],
    "sg:phone":"+1 703 360 5552",
    "sg:postcode":"22309",
    "sg:province":"VA",
    "sg:tags":[
        "system",
        "integration"
    ],
    "wof:name":"Computer Tchnical Support Svcs",
    "wof:placetype":"venue"
},
  "geometry": {"coordinates":[-77.101015,38.732723],"type":"Point"}
}