{
  "type": "Feature",
  "properties": {
    "iso:country":"US",
    "sg:address":"8907 Peoria Ct",
    "sg:city":"Springfield",
    "sg:classifiers":[
        {
            "category":"Professional",
            "type":"Services"
        }
    ],
    "sg:phone":"+1 703 913 0882",
    "sg:postcode":"22153",
    "sg:province":"VA",
    "wof:name":"Zeppieri",
    "wof:placetype":"venue"
},
  "geometry": {"coordinates":[-77.25188799999999,38.747916],"type":"Point"}
}