{
  "type": "Feature",
  "properties": {
    "addr:full":"1900 Wilson Blvd Arlington VA 22201",
    "addr:housenumber":"1900",
    "addr:postcode":"22201",
    "addr:street":"Wilson Blvd",
    "iso:country":"US",
    "sg:address":"1900 Wilson Blvd",
    "sg:city":"Arlington",
    "sg:classifiers":[
        {
            "category":"Shopping",
            "subcategory":"Hobbies, Toys, & Games",
            "type":"Retail Goods"
        }
    ],
    "sg:phone":"+1 703 527 5146",
    "sg:postcode":"22201",
    "sg:province":"VA",
    "sg:tags":[
        "video",
        "supply"
    ],
    "sg:website":"http://www.gamecrazy.com",
    "wof:name":"Game Crazy",
    "wof:placetype":"venue"
},
  "geometry": {"coordinates":[-77.080938,38.892972],"type":"Point"}
}