{
  "type": "Feature",
  "properties": {
    "iso:country":"US",
    "sg:address":"2138 S Military Hwy",
    "sg:city":"Chesapeake",
    "sg:classifiers":[
        {
            "category":"Restaurant",
            "type":"Food & Drink"
        }
    ],
    "sg:phone":"+1 757 545 9073",
    "sg:postcode":"23320",
    "sg:province":"VA",
    "sg:tags":[
        "eating"
    ],
    "wof:name":"Kellys Pub",
    "wof:placetype":"venue"
},
  "geometry": {"coordinates":[-76.266308,36.778749],"type":"Point"}
}