{
  "type": "Feature",
  "properties": {
    "addr:full":"4711 24th St N Arlington VA 22207",
    "addr:housenumber":"4711",
    "addr:postcode":"22207",
    "addr:street":"24Th St N",
    "iso:country":"US",
    "sg:address":"4711 24th St N",
    "sg:city":"Arlington",
    "sg:classifiers":[
        {
            "category":"Professional",
            "subcategory":"Business Services",
            "type":"Services"
        }
    ],
    "sg:phone":"+1 703 528 8525",
    "sg:postcode":"22207",
    "sg:province":"VA",
    "wof:name":"Runaway Development Group SA",
    "wof:placetype":"venue"
},
  "geometry": {"coordinates":[-77.123356,38.901264],"type":"Point"}
}