{
  "type": "Feature",
  "properties": {
    "iso:country":"US",
    "sg:address":"4191 Innslake Dr",
    "sg:city":"Glen Allen",
    "sg:classifiers":[
        {
            "category":"Real Estate",
            "subcategory":"Real Estate Agent",
            "type":"Services"
        }
    ],
    "sg:phone":"+1 757 640 1818",
    "sg:postcode":"23060",
    "sg:province":"VA",
    "sg:tags":[
        "manager"
    ],
    "wof:name":"Koll Property Resources",
    "wof:placetype":"venue"
},
  "geometry": {"coordinates":[-77.57971499999999,37.651205],"type":"Point"}
}