{
  "type": "Feature",
  "properties": {
    "iso:country":"US",
    "sg:address":"5251 Mitchell St",
    "sg:city":"Alexandria",
    "sg:classifiers":[
        {
            "category":"Communications",
            "type":"Services"
        },
        {
            "category":"Building & Trades",
            "subcategory":"Electrical",
            "type":"Services"
        },
        {
            "category":"Utilities",
            "type":"Services"
        }
    ],
    "sg:phone":"+1 703 354 4528",
    "sg:postcode":"22312",
    "sg:province":"VA",
    "sg:tags":[
        "contractors-commercial",
        "industrial",
        "electric",
        "contractor"
    ],
    "wof:name":"Hughes Communications",
    "wof:placetype":"venue"
},
  "geometry": {"coordinates":[-77.167924,38.807815],"type":"Point"}
}