{
  "type": "Feature",
  "properties": {
    "addr:full":"4724 Ellisville Dr Louisa VA 23093",
    "addr:postcode":"4724;23093",
    "addr:street":"Ellisville Dr",
    "iso:country":"US",
    "sg:address":"4724 Ellisville Dr",
    "sg:city":"Louisa",
    "sg:phone":"+1 540 967 2637",
    "sg:postcode":"23093",
    "sg:province":"VA",
    "sg:tags":[
        "farm",
        "soybean"
    ],
    "wof:name":"Fred Massie",
    "wof:placetype":"venue"
},
  "geometry": {"coordinates":[-77.996604,38.095571],"type":"Point"}
}