{
  "type": "Feature",
  "properties": {
    "addr:full":"998 Memorial Dr Pulaski VA 24301",
    "addr:housenumber":"998",
    "addr:postcode":"24301",
    "addr:street":"Memorial Dr",
    "iso:country":"US",
    "sg:address":"998 Memorial Dr",
    "sg:city":"Pulaski",
    "sg:classifiers":[
        {
            "category":"Banks & Credit Unions",
            "subcategory":"Bank",
            "type":"Services"
        }
    ],
    "sg:phone":"+1 540 994 9617",
    "sg:postcode":"24301",
    "sg:province":"VA",
    "sg:tags":[
        "state",
        "commercial"
    ],
    "wof:name":"Blue Ridge Bank NA",
    "wof:placetype":"venue"
},
  "geometry": {"coordinates":[-80.76081600000001,37.063065],"type":"Point"}
}