{
  "type": "Feature",
  "properties": {
    "iso:country":"US",
    "sg:address":"8265 Anderson Dr",
    "sg:city":"Fairfax",
    "sg:classifiers":[
        {
            "category":"Restaurant",
            "type":"Food & Drink"
        }
    ],
    "sg:phone":"+1 703 208 1055",
    "sg:postcode":"22031",
    "sg:province":"VA",
    "wof:name":"Archstone-Smith Cmm",
    "wof:placetype":"venue"
},
  "geometry": {"coordinates":[-77.230464,38.861562],"type":"Point"}
}