{
  "type": "Feature",
  "properties": {
    "addr:full":"7102 Rebecca Dr Alexandria VA 22307",
    "addr:housenumber":"7102",
    "addr:postcode":"22307",
    "addr:street":"Rebecca Dr",
    "iso:country":"US",
    "sg:address":"7102 Rebecca Dr",
    "sg:city":"Alexandria",
    "sg:classifiers":[
        {
            "category":"Professional",
            "subcategory":"Lawyer & Legal Services",
            "type":"Services"
        }
    ],
    "sg:phone":"+1 703 768 3665",
    "sg:postcode":"22307",
    "sg:province":"VA",
    "sg:tags":[
        "attorney"
    ],
    "wof:name":"Michael J Mc Manus",
    "wof:placetype":"venue"
},
  "geometry": {"coordinates":[-77.06939800000001,38.762027],"type":"Point"}
}