{
  "type": "Feature",
  "properties": {
    "iso:country":"US",
    "sg:address":"313 Church St NE",
    "sg:city":"Wise",
    "sg:classifiers":[
        {
            "category":"Restaurant",
            "type":"Food & Drink"
        }
    ],
    "sg:phone":"+1 276 328 3714",
    "sg:postcode":"24293",
    "sg:province":"VA",
    "wof:name":"Roma's Pizzeria II",
    "wof:placetype":"venue"
},
  "geometry": {"coordinates":[-82.57761499999999,36.977499],"type":"Point"}
}