{
  "type": "Feature",
  "properties": {
    "addr:full":"11109 Saint Just Rd Unionville VA 22567",
    "addr:housenumber":"11109",
    "addr:postcode":"22567",
    "addr:street":"Saint Just Rd",
    "iso:country":"US",
    "sg:address":"11109 Saint Just Rd",
    "sg:city":"Unionville",
    "sg:phone":"+1 540 854 4815",
    "sg:postcode":"22567",
    "sg:province":"VA",
    "sg:tags":[
        "farm",
        "field",
        "crop"
    ],
    "wof:name":"Mayo Brothers",
    "wof:placetype":"venue"
},
  "geometry": {"coordinates":[-77.870069,38.252884],"type":"Point"}
}