{
  "type": "Feature",
  "properties": {
    "addr:full":"6510 W Norton Rd Norton VA 24273",
    "addr:housenumber":"6510",
    "addr:postcode":"24273",
    "addr:street":"W Norton Rd",
    "iso:country":"US",
    "sg:address":"6510 W Norton Rd",
    "sg:city":"Norton",
    "sg:classifiers":[
        {
            "category":"Retail",
            "subcategory":"Auto Repair",
            "type":"Services"
        }
    ],
    "sg:phone":"+1 276 679 5335",
    "sg:postcode":"24273",
    "sg:province":"VA",
    "sg:tags":[
        "repairing",
        "automobile"
    ],
    "wof:name":"Tri Me Automotives",
    "wof:placetype":"venue"
},
  "geometry": {"coordinates":[-82.656397,36.927118],"type":"Point"}
}