{
  "type": "Feature",
  "properties": {
    "addr:full":"7067 Mechanicsville Tpke Mechanicsville VA 23111",
    "addr:housenumber":"7067",
    "addr:postcode":"23111",
    "addr:street":"Mechanicsville Tpke",
    "iso:country":"US",
    "sg:address":"7067 Mechanicsville Tpke",
    "sg:city":"Mechanicsville",
    "sg:classifiers":[
        {
            "category":"Shopping",
            "subcategory":"Clothing, Apparel, & Fashions",
            "type":"Retail Goods"
        }
    ],
    "sg:phone":"+1 804 730 1712",
    "sg:postcode":"23111",
    "sg:province":"VA",
    "sg:website":"www.amoreva.com",
    "wof:name":"Amore",
    "wof:placetype":"venue"
},
  "geometry": {"coordinates":[-77.34008300000001,37.611635],"type":"Point"}
}