{
  "type": "Feature",
  "properties": {
    "iso:country":"US",
    "sg:address":"613 E Charlotte St",
    "sg:city":"Sterling",
    "sg:classifiers":[
        {
            "category":"Taxi",
            "type":"Transportation"
        },
        {
            "category":"Retail",
            "subcategory":"Auto Rental",
            "type":"Services"
        }
    ],
    "sg:phone":"+1 703 433 1100",
    "sg:postcode":"20164",
    "sg:province":"VA",
    "sg:tags":[
        "limousine"
    ],
    "sg:website":"http://www.sterling-yellow.com",
    "wof:name":"Sterling Yellow Cab",
    "wof:placetype":"venue"
},
  "geometry": {"coordinates":[-77.381827,39.016891],"type":"Point"}
}