{
  "type": "Feature",
  "properties": {
    "addr:full":"6527 Bay Tree Ct Falls Church VA 22041",
    "addr:housenumber":"6527",
    "addr:postcode":"22041",
    "addr:street":"Bay Tree Ct",
    "iso:country":"US",
    "sg:address":"6527 Bay Tree Ct",
    "sg:city":"Falls Church",
    "sg:classifiers":[
        {
            "category":"Professional",
            "subcategory":"Lawyer & Legal Services",
            "type":"Services"
        }
    ],
    "sg:phone":"+1 703 642 2344",
    "sg:postcode":"22041",
    "sg:province":"VA",
    "wof:name":"Donald E Martin PC",
    "wof:placetype":"venue"
},
  "geometry": {"coordinates":[-77.171035,38.844252],"type":"Point"}
}