{
  "type": "Feature",
  "properties": {
    "addr:full":"16590 Pouncey Tract Rd Rockville VA 23146",
    "addr:housenumber":"16590",
    "addr:postcode":"23146",
    "addr:street":"Pouncey Tract Rd",
    "iso:country":"US",
    "sg:address":"16590 Pouncey Tract Rd",
    "sg:city":"Rockville",
    "sg:classifiers":[
        {
            "category":"Government",
            "subcategory":"Post Office",
            "type":"Public Place"
        }
    ],
    "sg:phone":"+1 804 749 3572",
    "sg:postcode":"23146",
    "sg:province":"VA",
    "sg:tags":[
        "postal",
        "us"
    ],
    "wof:name":"US Post Office",
    "wof:placetype":"venue"
},
  "geometry": {"coordinates":[-77.681476,37.725851],"type":"Point"}
}