{
  "type": "Feature",
  "properties": {
    "iso:country":"US",
    "sg:address":"1613 13th St NE",
    "sg:city":"Roanoke",
    "sg:classifiers":[
        {
            "category":"Autos & Motor Vehicles",
            "subcategory":"Automobile Sales",
            "type":"Retail Goods"
        }
    ],
    "sg:phone":"+1 540 345 2331",
    "sg:postcode":"24012",
    "sg:province":"VA",
    "sg:tags":[
        "truck"
    ],
    "wof:name":"A D Weddle Co",
    "wof:placetype":"venue"
},
  "geometry": {"coordinates":[-79.920559,37.288894],"type":"Point"}
}