{
  "type": "Feature",
  "properties": {
    "addr:full":"825 18th St Virginia Beach VA 23451",
    "addr:housenumber":"825",
    "addr:postcode":"23451",
    "addr:street":"18Th St",
    "iso:country":"US",
    "sg:address":"825 18th St",
    "sg:city":"Virginia Beach",
    "sg:classifiers":[
        {
            "category":"Government",
            "subcategory":"Office",
            "type":"Public Place"
        }
    ],
    "sg:phone":"+1 757 437 4911",
    "sg:postcode":"23451",
    "sg:province":"VA",
    "sg:tags":[
        "village"
    ],
    "wof:name":"Lighthouse Center",
    "wof:placetype":"venue"
},
  "geometry": {"coordinates":[-75.986637,36.844297],"type":"Point"}
}