{
  "type": "Feature",
  "properties": {
    "addr:full":"5311 Patterson Ave Richmond VA 23226",
    "addr:housenumber":"5311",
    "addr:postcode":"23226",
    "addr:street":"Patterson Ave",
    "iso:country":"US",
    "sg:address":"5311 Patterson Ave",
    "sg:city":"Richmond",
    "sg:classifiers":[
        {
            "category":"Insurance",
            "subcategory":"Hazard Insurance",
            "type":"Services"
        },
        {
            "category":"Insurance",
            "subcategory":"Life Insurance",
            "type":"Services"
        },
        {
            "category":"Banks & Credit Unions",
            "subcategory":"Financial Services",
            "type":"Services"
        },
        {
            "category":"Insurance",
            "subcategory":"Health Insurance",
            "type":"Services"
        }
    ],
    "sg:phone":"+1 804 288 6263",
    "sg:postcode":"23226",
    "sg:province":"VA",
    "sg:tags":[
        "term",
        "retirement",
        "group",
        "annuity",
        "long",
        "plan",
        "care"
    ],
    "sg:website":"http://www.fnbc.cc",
    "wof:name":"First National Brokerage Corporation",
    "wof:placetype":"venue"
},
  "geometry": {"coordinates":[-77.508616,37.575913],"type":"Point"}
}