{
  "type": "Feature",
  "properties": {
    "iso:country":"US",
    "sg:address":"3100 Shore Dr",
    "sg:city":"Virginia Beach",
    "sg:classifiers":[
        {
            "category":"Banks & Credit Unions",
            "subcategory":"Bank",
            "type":"Services"
        }
    ],
    "sg:phone":"+1 757 496 6100",
    "sg:postcode":"23451",
    "sg:province":"VA",
    "wof:name":"Wachovia Bank",
    "wof:placetype":"venue"
},
  "geometry": {"coordinates":[-76.069822,36.912077],"type":"Point"}
}