{
  "type": "Feature",
  "properties": {
    "addr:full":"2219 Chamberlayne Ave Richmond VA 23222",
    "addr:housenumber":"2219",
    "addr:postcode":"23222",
    "addr:street":"Chamberlayne Ave",
    "iso:country":"US",
    "sg:address":"2219 Chamberlayne Ave",
    "sg:city":"Richmond",
    "sg:classifiers":[
        {
            "category":"Retail",
            "subcategory":"Auto Rental",
            "type":"Services"
        }
    ],
    "sg:phone":"+1 804 329 7440",
    "sg:postcode":"23222",
    "sg:province":"VA",
    "sg:tags":[
        "passenger",
        "truck",
        "car"
    ],
    "wof:name":"Hertz",
    "wof:placetype":"venue"
},
  "geometry": {"coordinates":[-77.44246800000001,37.561001],"type":"Point"}
}