{
  "type": "Feature",
  "properties": {
    "addr:full":"2965 Colonnade Dr Roanoke VA 24018",
    "addr:housenumber":"2965",
    "addr:postcode":"24018",
    "addr:street":"Colonnade Dr",
    "iso:country":"US",
    "sg:address":"2965 Colonnade Dr",
    "sg:city":"Roanoke",
    "sg:classifiers":[
        {
            "category":"Professional",
            "subcategory":"Management & Consulting",
            "type":"Services"
        }
    ],
    "sg:phone":"+1 540 989 1709",
    "sg:postcode":"24018",
    "sg:province":"VA",
    "sg:tags":[
        "marketing",
        "consultant"
    ],
    "wof:name":"Mkg Enterprises",
    "wof:placetype":"venue"
},
  "geometry": {"coordinates":[-80.01671899999999,37.233839],"type":"Point"}
}