{
  "type": "Feature",
  "properties": {
    "addr:full":"8271 Centreville Rd Manassas VA 20111",
    "addr:housenumber":"8271",
    "addr:postcode":"20111",
    "addr:street":"Centreville Rd",
    "iso:country":"US",
    "sg:address":"8271 Centreville Rd",
    "sg:city":"Manassas",
    "sg:classifiers":[
        {
            "category":"Home & Garden",
            "subcategory":"Carpets & Floor Coverings",
            "type":"Retail Goods"
        },
        {
            "category":"Building & Trades",
            "subcategory":"Construction",
            "type":"Services"
        }
    ],
    "sg:phone":"+1 703 330 6013",
    "sg:postcode":"20111",
    "sg:province":"VA",
    "sg:tags":[
        "dealer",
        "laying",
        "rug",
        "contractor"
    ],
    "wof:name":"G & B Rug N Carpet City",
    "wof:placetype":"venue"
},
  "geometry": {"coordinates":[-77.451594,38.775304],"type":"Point"}
}