{
  "type": "Feature",
  "properties": {
    "addr:full":"2128 Barracks Rd Charlottesville VA 22903",
    "addr:housenumber":"2128",
    "addr:postcode":"22903",
    "addr:street":"Barracks Rd",
    "iso:country":"US",
    "sg:address":"2128 Barracks Rd",
    "sg:city":"Charlottesville",
    "sg:classifiers":[
        {
            "category":"Home & Garden",
            "subcategory":"Home Furnishings",
            "type":"Retail Goods"
        }
    ],
    "sg:phone":"+1 434 979 4543",
    "sg:postcode":"22903",
    "sg:province":"VA",
    "sg:tags":[
        "blanket"
    ],
    "wof:name":"Quilts Unlimited/J Fenton",
    "wof:placetype":"venue"
},
  "geometry": {"coordinates":[-78.50002000000001,38.054017],"type":"Point"}
}