{
  "type": "Feature",
  "properties": {
    "addr:full":"3923 Old Lee Hwy Fairfax VA 22030",
    "addr:housenumber":"3923",
    "addr:postcode":"22030",
    "addr:street":"Old Lee Hwy",
    "iso:country":"US",
    "sg:address":"3923 Old Lee Hwy",
    "sg:city":"Fairfax",
    "sg:classifiers":[
        {
            "category":"Professional",
            "subcategory":"Business Services",
            "type":"Services"
        },
        {
            "category":"Health Services",
            "subcategory":"Hospital",
            "type":"Services"
        }
    ],
    "sg:phone":"+1 703 385 2083",
    "sg:postcode":"22030",
    "sg:province":"VA",
    "sg:tags":[
        "consulting",
        "sales",
        "mental"
    ],
    "wof:name":"Sonya Stagnoli",
    "wof:placetype":"venue"
},
  "geometry": {"coordinates":[-77.30224,38.847421],"type":"Point"}
}