{
  "type": "Feature",
  "properties": {
    "addr:full":"879 Lynnhaven Pkwy Virginia Beach VA 23452",
    "addr:housenumber":"879",
    "addr:postcode":"23452",
    "addr:street":"Lynnhaven Pkwy",
    "iso:country":"US",
    "sg:address":"879 Lynnhaven Pkwy",
    "sg:city":"Virginia Beach",
    "sg:classifiers":[
        {
            "category":"Restaurant",
            "type":"Food & Drink"
        }
    ],
    "sg:phone":"+1 757 368 8682",
    "sg:postcode":"23452",
    "sg:province":"VA",
    "wof:name":"Happy Buffet Restaurant",
    "wof:placetype":"venue"
},
  "geometry": {"coordinates":[-76.072035,36.810964],"type":"Point"}
}