{
  "type": "Feature",
  "properties": {
    "addr:full":"8784 Centreville Rd Manassas VA 20110",
    "addr:housenumber":"8784",
    "addr:postcode":"20110",
    "addr:street":"Centreville Rd",
    "iso:country":"US",
    "sg:address":"8784 Centreville Rd",
    "sg:city":"Manassas",
    "sg:classifiers":[
        {
            "category":"Retail",
            "subcategory":"Auto Repair",
            "type":"Services"
        }
    ],
    "sg:phone":"+1 703 369 2223",
    "sg:postcode":"20110",
    "sg:province":"VA",
    "sg:tags":[
        "carwash",
        "automotive",
        "body"
    ],
    "wof:name":"Ziebart",
    "wof:placetype":"venue"
},
  "geometry": {"coordinates":[-77.45878500000001,38.763647],"type":"Point"}
}