{
  "type": "Feature",
  "properties": {
    "addr:full":"408 W Main St Abingdon VA 24210",
    "addr:housenumber":"408",
    "addr:postcode":"24210",
    "addr:street":"W Main St",
    "iso:country":"US",
    "sg:address":"408 W Main St",
    "sg:city":"Abingdon",
    "sg:classifiers":[
        {
            "category":"Autos & Motor Vehicles",
            "subcategory":"Auto Supplies",
            "type":"Retail Goods"
        },
        {
            "category":"Wholesale",
            "subcategory":"Electrical",
            "type":"Manufacturing & Wholesale Goods"
        }
    ],
    "sg:phone":"+1 276 628 2124",
    "sg:postcode":"24210",
    "sg:province":"VA",
    "sg:tags":[
        "battery",
        "automobile",
        "part",
        "accessory"
    ],
    "sg:website":"http://www.napaonline.com/",
    "wof:name":"NAPA AUTO PARTS",
    "wof:placetype":"venue"
},
  "geometry": {"coordinates":[-81.98411,36.707481],"type":"Point"}
}