{
  "type": "Feature",
  "properties": {
    "addr:full":"15120 Washington St Haymarket VA 20169",
    "addr:housenumber":"15120",
    "addr:postcode":"20169",
    "addr:street":"Washington St",
    "iso:country":"US",
    "sg:address":"15120 Washington St",
    "sg:city":"Haymarket",
    "sg:classifiers":[
        {
            "category":"Restaurant",
            "type":"Food & Drink"
        }
    ],
    "sg:phone":"+1 703 753 1004",
    "sg:postcode":"20169",
    "sg:province":"VA",
    "sg:tags":[
        "italian"
    ],
    "sg:website":"www.giuseppesri.com",
    "wof:name":"Giuseppe's Italian Restaurant",
    "wof:placetype":"venue"
},
  "geometry": {"coordinates":[-77.63788099999999,38.812888],"type":"Point"}
}