{
  "type": "Feature",
  "properties": {
    "iso:country":"US",
    "sg:address":"7231 Galveston Blvd",
    "sg:city":"Norfolk",
    "sg:classifiers":[
        {
            "category":"Communications",
            "type":"Services"
        }
    ],
    "sg:phone":"+1 757 583 0679",
    "sg:postcode":"23505",
    "sg:province":"VA",
    "sg:tags":[
        "communication"
    ],
    "wof:name":"Maritime Comminication",
    "wof:placetype":"venue"
},
  "geometry": {"coordinates":[-76.267079,36.90718],"type":"Point"}
}