{
  "type": "Feature",
  "properties": {
    "addr:full":"4150 Campbell Ave Ste 104 Arlington VA 22206",
    "addr:housenumber":"4150",
    "addr:postcode":"22206",
    "addr:street":"Campbell Ave Ste 104",
    "iso:country":"US",
    "sg:address":"4150 Campbell Ave Ste 104",
    "sg:city":"Arlington",
    "sg:classifiers":[
        {
            "category":"Shopping",
            "subcategory":"Clothing, Apparel, & Fashions",
            "type":"Retail Goods"
        }
    ],
    "sg:phone":"+1 703 379 5242",
    "sg:postcode":"22206",
    "sg:province":"VA",
    "sg:tags":[
        "clothing",
        "women's"
    ],
    "sg:website":"www.periwinkleshop.com/",
    "wof:name":"Periwinkle",
    "wof:placetype":"venue"
},
  "geometry": {"coordinates":[-77.089822,38.8409],"type":"Point"}
}