{
  "type": "Feature",
  "properties": {
    "iso:country":"US",
    "sg:address":"512 S Van Dorn St",
    "sg:city":"Alexandria",
    "sg:classifiers":[
        {
            "category":"Retail",
            "subcategory":"Laundry & Dry Cleaning",
            "type":"Services"
        }
    ],
    "sg:phone":"+1 703 370 5631",
    "sg:postcode":"22304",
    "sg:province":"VA",
    "wof:name":"Economy Laundromat",
    "wof:placetype":"venue"
},
  "geometry": {"coordinates":[-77.13336700000001,38.806823],"type":"Point"}
}