{
  "type": "Feature",
  "properties": {
    "iso:country":"US",
    "sg:address":"157 Delmar Ln",
    "sg:city":"Newport News",
    "sg:classifiers":[
        {
            "category":"Health Services",
            "subcategory":"Medical Lab",
            "type":"Services"
        }
    ],
    "sg:phone":"+1 757 886 2055",
    "sg:postcode":"23602",
    "sg:province":"VA",
    "sg:tags":[
        "technician"
    ],
    "wof:name":"Innocent Nialija",
    "wof:placetype":"venue"
},
  "geometry": {"coordinates":[-76.522935,37.127314],"type":"Point"}
}