{
  "type": "Feature",
  "properties": {
    "iso:country":"US",
    "sg:address":"1237 Marion's Trl",
    "sg:city":"Halifax",
    "sg:phone":"+1 434 476 6357",
    "sg:postcode":"24558",
    "sg:province":"VA",
    "sg:tags":[
        "farm",
        "tobacco"
    ],
    "wof:name":"Betty H Coleman",
    "wof:placetype":"venue"
},
  "geometry": {"coordinates":[-78.89418999999999,36.790312],"type":"Point"}
}