{
  "type": "Feature",
  "properties": {
    "addr:full":"11661 Eggleston Ln Amelia Court House VA 23002",
    "addr:housenumber":"11661",
    "addr:postcode":"23002",
    "addr:street":"Eggleston Ln",
    "iso:country":"US",
    "sg:address":"11661 Eggleston Ln",
    "sg:city":"Amelia Court House",
    "sg:classifiers":[
        {
            "category":"Shopping",
            "subcategory":"Bicycles & Sporting Goods",
            "type":"Retail Goods"
        }
    ],
    "sg:phone":"+1 804 561 5090",
    "sg:postcode":"23002",
    "sg:province":"VA",
    "sg:tags":[
        "hardwood",
        "mi"
    ],
    "wof:name":"Daves Sport Shop",
    "wof:placetype":"venue"
},
  "geometry": {"coordinates":[-78.022181,37.38877],"type":"Point"}
}