{
  "type": "Feature",
  "properties": {
    "iso:country":"US",
    "sg:address":"1128 Evelyn St",
    "sg:city":"Norfolk",
    "sg:classifiers":[
        {
            "category":"Professional",
            "subcategory":"Business Services",
            "type":"Services"
        }
    ],
    "sg:phone":"+1 757 636 3307",
    "sg:postcode":"23518",
    "sg:province":"VA",
    "wof:name":"Dlr Business Services",
    "wof:placetype":"venue"
},
  "geometry": {"coordinates":[-76.24190400000001,36.928619],"type":"Point"}
}