{
  "type": "Feature",
  "properties": {
    "addr:full":"3200 Dam Neck Rd Virginia Beach VA 23453",
    "addr:housenumber":"3200",
    "addr:postcode":"23453",
    "addr:street":"Dam Neck Rd",
    "iso:country":"US",
    "sg:address":"3200 Dam Neck Rd",
    "sg:city":"Virginia Beach",
    "sg:classifiers":[
        {
            "category":"Arena",
            "subcategory":"Sports Club",
            "type":"Entertainment"
        }
    ],
    "sg:phone":"+1 757 456 0165",
    "sg:postcode":"23453",
    "sg:province":"VA",
    "sg:tags":[
        "soccer"
    ],
    "wof:name":"Virginia Beach Travel Soccer",
    "wof:placetype":"venue"
},
  "geometry": {"coordinates":[-76.08259700000001,36.782802],"type":"Point"}
}