{
  "type": "Feature",
  "properties": {
    "iso:country":"US",
    "sg:address":"101 River Birch Ct",
    "sg:city":"Newport News",
    "sg:classifiers":[
        {
            "category":"Retail",
            "subcategory":"Repair Shop",
            "type":"Services"
        }
    ],
    "sg:phone":"+1 757 877 3994",
    "sg:postcode":"23602",
    "sg:province":"VA",
    "wof:name":"Custom Maid LLC",
    "wof:placetype":"venue"
},
  "geometry": {"coordinates":[-76.538213,37.094424],"type":"Point"}
}