{
  "type": "Feature",
  "properties": {
    "addr:full":"7400 Little River Tpke Annandale VA 22003",
    "addr:housenumber":"7400",
    "addr:postcode":"22003",
    "addr:street":"Little River Tpke",
    "iso:country":"US",
    "sg:address":"7400 Little River Tpke",
    "sg:city":"Annandale",
    "sg:classifiers":[
        {
            "category":"Manufacturing",
            "subcategory":"Glass & Minerals",
            "type":"Manufacturing & Wholesale Goods"
        },
        {
            "category":"Retail",
            "subcategory":"Auto Repair",
            "type":"Services"
        }
    ],
    "sg:phone":"+1 703 494 0414",
    "sg:postcode":"22003",
    "sg:province":"VA",
    "sg:tags":[
        "plate",
        "shape",
        "glass-wholesale",
        "window",
        "special",
        "circle",
        "windshield",
        "glass-auto",
        "manufacturer"
    ],
    "sg:website":"http://kavoos.tripod.com",
    "wof:name":"A AutoGlass SERVICE",
    "wof:placetype":"venue"
},
  "geometry": {"coordinates":[-77.199738,38.831261],"type":"Point"}
}