{
  "type": "Feature",
  "properties": {
    "iso:country":"US",
    "sg:address":"1022 W 47th St",
    "sg:city":"Richmond",
    "sg:classifiers":[
        {
            "category":"Shopping",
            "subcategory":"Used Merchandise",
            "type":"Retail Goods"
        }
    ],
    "sg:phone":"+1 804 231 1048",
    "sg:postcode":"23225",
    "sg:province":"VA",
    "sg:tags":[
        "flea",
        "market"
    ],
    "wof:name":"P-J's To Hang & To Hold",
    "wof:placetype":"venue"
},
  "geometry": {"coordinates":[-77.486672,37.51814],"type":"Point"}
}