{
  "type": "Feature",
  "properties": {
    "addr:full":"226 Meadow Ln Collinsville VA 24078",
    "addr:housenumber":"226",
    "addr:postcode":"24078",
    "addr:street":"Meadow Ln",
    "iso:country":"US",
    "sg:address":"226 Meadow Ln",
    "sg:city":"Collinsville",
    "sg:classifiers":[
        {
            "category":"Personal",
            "subcategory":"Beauty Salon",
            "type":"Services"
        }
    ],
    "sg:phone":"+1 276 647 1842",
    "sg:postcode":"24078",
    "sg:province":"VA",
    "sg:tags":[
        "shop"
    ],
    "wof:name":"Kay & Bckys Per Tuch Hair Slon",
    "wof:placetype":"venue"
},
  "geometry": {"coordinates":[-79.91099699999999,36.722913],"type":"Point"}
}