{
  "type": "Feature",
  "properties": {
    "addr:full":"6040 Wilson Blvd Arlington VA 22205",
    "addr:housenumber":"6040",
    "addr:postcode":"22205",
    "addr:street":"Wilson Blvd",
    "iso:country":"US",
    "sg:address":"6040 Wilson Blvd",
    "sg:city":"Arlington",
    "sg:classifiers":[
        {
            "category":"Place Of Worship",
            "subcategory":"Church",
            "type":"Public Place"
        },
        {
            "category":"Place Of Worship",
            "type":"Public Place"
        }
    ],
    "sg:phone":"+1 703 533 9874",
    "sg:postcode":"22205",
    "sg:province":"VA",
    "sg:tags":[
        "churches-community"
    ],
    "sg:website":"http://www.accweb.org",
    "wof:name":"Arlington Community Church",
    "wof:placetype":"venue"
},
  "geometry": {"coordinates":[-77.140762,38.87352],"type":"Point"}
}