{
  "type": "Feature",
  "properties": {
    "iso:country":"US",
    "sg:address":"2087 Camp Hydaway Rd",
    "sg:city":"Lynchburg",
    "sg:classifiers":[
        {
            "category":"Professional",
            "type":"Services"
        }
    ],
    "sg:phone":"+1 434 847 8900",
    "sg:postcode":"24501",
    "sg:province":"VA",
    "wof:name":"Chris Pallotti",
    "wof:placetype":"venue"
},
  "geometry": {"coordinates":[-79.137624,37.351261],"type":"Point"}
}