{
  "type": "Feature",
  "properties": {
    "addr:full":"9093 Colonial Ln Mechanicsville VA 23111",
    "addr:housenumber":"9093",
    "addr:postcode":"23111",
    "addr:street":"Colonial Ln",
    "iso:country":"US",
    "sg:address":"9093 Colonial Ln",
    "sg:city":"Mechanicsville",
    "sg:classifiers":[
        {
            "category":"Professional",
            "type":"Services"
        }
    ],
    "sg:phone":"+1 804 779 3651",
    "sg:postcode":"23111",
    "sg:province":"VA",
    "wof:name":"Charles F Bailey",
    "wof:placetype":"venue"
},
  "geometry": {"coordinates":[-77.228858,37.645609],"type":"Point"}
}