{
  "type": "Feature",
  "properties": {
    "addr:full":"204 Lakewood Park Dr Newport News VA 23602",
    "addr:housenumber":"204",
    "addr:postcode":"23602",
    "addr:street":"Lakewood Park Dr",
    "iso:country":"US",
    "sg:address":"204 Lakewood Park Dr",
    "sg:city":"Newport News",
    "sg:classifiers":[
        {
            "category":"Personal",
            "subcategory":"Beauty Salon",
            "type":"Services"
        }
    ],
    "sg:phone":"+1 757 874 5145",
    "sg:postcode":"23602",
    "sg:province":"VA",
    "sg:tags":[
        "shop"
    ],
    "wof:name":"Lakewood Park Dr",
    "wof:placetype":"venue"
},
  "geometry": {"coordinates":[-76.543436,37.102776],"type":"Point"}
}