{
  "type": "Feature",
  "properties": {
    "addr:full":"2705 Roanoke St Christiansburg VA 24073",
    "addr:housenumber":"2705",
    "addr:postcode":"24073",
    "addr:street":"Roanoke St",
    "iso:country":"US",
    "sg:address":"2705 Roanoke St",
    "sg:city":"Christiansburg",
    "sg:classifiers":[
        {
            "category":"Travel",
            "subcategory":"Campground",
            "type":"Entertainment"
        }
    ],
    "sg:phone":"+1 540 382 1554",
    "sg:postcode":"24073",
    "sg:province":"VA",
    "sg:tags":[
        "trailer"
    ],
    "wof:name":"Interstate Overnight Park",
    "wof:placetype":"venue"
},
  "geometry": {"coordinates":[-80.351564,37.138039],"type":"Point"}
}