{
  "type": "Feature",
  "properties": {
    "iso:country":"US",
    "sg:address":"308 Cedar Lakes Dr",
    "sg:city":"Chesapeake",
    "sg:classifiers":[
        {
            "category":"Government",
            "subcategory":"Office",
            "type":"Public Place"
        }
    ],
    "sg:phone":"+1 757 547 3422",
    "sg:postcode":"23322",
    "sg:province":"VA",
    "wof:name":"Delegate John Cosgrove",
    "wof:placetype":"venue"
},
  "geometry": {"coordinates":[-76.257211,36.711315],"type":"Point"}
}