{
  "type": "Feature",
  "properties": {
    "addr:full":"922 Lakeview Dr Woodstock VA 22664",
    "addr:housenumber":"922",
    "addr:postcode":"22664",
    "addr:street":"Lakeview Dr",
    "iso:country":"US",
    "sg:address":"922 Lakeview Dr",
    "sg:city":"Woodstock",
    "sg:classifiers":[
        {
            "category":"Freight",
            "type":"Transportation"
        }
    ],
    "sg:phone":"+1 540 335 9462",
    "sg:postcode":"22664",
    "sg:province":"VA",
    "sg:tags":[
        "trucking"
    ],
    "wof:name":"R L Crews Jr & Son Trucking",
    "wof:placetype":"venue"
},
  "geometry": {"coordinates":[-78.51130000000001,38.854262],"type":"Point"}
}