{
  "type": "Feature",
  "properties": {
    "addr:full":"1011 Arlington Blvd Arlington VA 22209",
    "addr:housenumber":"1011",
    "addr:postcode":"22209",
    "addr:street":"Arlington Blvd",
    "iso:country":"US",
    "sg:address":"1011 Arlington Blvd",
    "sg:city":"Arlington",
    "sg:classifiers":[
        {
            "category":"Bars & Pubs",
            "type":"Food & Drink"
        }
    ],
    "sg:phone":"+1 703 351 5152",
    "sg:postcode":"22209",
    "sg:province":"VA",
    "wof:name":"D C Life",
    "wof:placetype":"venue"
},
  "geometry": {"coordinates":[-77.06784500000001,38.890772],"type":"Point"}
}