{
  "type": "Feature",
  "properties": {
    "addr:full":"2446 Old Church Rd Mechanicsville VA 23111",
    "addr:housenumber":"2446",
    "addr:postcode":"23111",
    "addr:street":"Old Church Rd",
    "iso:country":"US",
    "sg:address":"2446 Old Church Rd",
    "sg:city":"Mechanicsville",
    "sg:classifiers":[
        {
            "category":"Organizations",
            "subcategory":"Religious Organization",
            "type":"Services"
        }
    ],
    "sg:phone":"+1 804 779 3775",
    "sg:postcode":"23111",
    "sg:province":"VA",
    "wof:name":"Bethlehem Presbyterian Church",
    "wof:placetype":"venue"
},
  "geometry": {"coordinates":[-77.1895,37.636322],"type":"Point"}
}