{
  "type": "Feature",
  "properties": {
    "addr:full":"9255 Glen Meadow Ln Bristow VA 20136",
    "addr:housenumber":"9255",
    "addr:postcode":"20136",
    "addr:street":"Glen Meadow Ln",
    "iso:country":"US",
    "sg:address":"9255 Glen Meadow Ln",
    "sg:city":"Bristow",
    "sg:classifiers":[
        {
            "category":"Banks & Credit Unions",
            "subcategory":"Bank",
            "type":"Services"
        }
    ],
    "sg:phone":"+1 703 551 4061",
    "sg:postcode":"20136",
    "sg:province":"VA",
    "sg:tags":[
        "mortgage"
    ],
    "wof:name":"C S V I",
    "wof:placetype":"venue"
},
  "geometry": {"coordinates":[-77.57806600000001,38.755131],"type":"Point"}
}