{
  "type": "Feature",
  "properties": {
    "addr:full":"3263 Proffit Rd Charlottesville VA 22911",
    "addr:housenumber":"3263",
    "addr:postcode":"22911",
    "addr:street":"Proffit Rd",
    "iso:country":"US",
    "sg:address":"3263 Proffit Rd",
    "sg:city":"Charlottesville",
    "sg:classifiers":[
        {
            "category":"Health Services",
            "subcategory":"Doctor",
            "type":"Services"
        }
    ],
    "sg:phone":"+1 434 923 4651",
    "sg:postcode":"22911",
    "sg:province":"VA",
    "sg:tags":[
        "medical"
    ],
    "wof:name":"Albemerle Assco",
    "wof:placetype":"venue"
},
  "geometry": {"coordinates":[-78.433803,38.131786],"type":"Point"}
}