{
  "type": "Feature",
  "properties": {
    "addr:full":"442 N Mason St Harrisonburg VA 22802",
    "addr:housenumber":"442",
    "addr:postcode":"22802",
    "addr:street":"N Mason St",
    "iso:country":"US",
    "sg:address":"442 N Mason St",
    "sg:city":"Harrisonburg",
    "sg:classifiers":[
        {
            "category":"Personal",
            "subcategory":"Beauty Salon",
            "type":"Services"
        }
    ],
    "sg:phone":"+1 540 433 1810",
    "sg:postcode":"22802",
    "sg:province":"VA",
    "sg:tags":[
        "shop"
    ],
    "wof:name":"Styles With A Touch Of Class",
    "wof:placetype":"venue"
},
  "geometry": {"coordinates":[-78.865467,38.455041],"type":"Point"}
}