{
  "type": "Feature",
  "properties": {
    "addr:full":"2100 Hutchison Grove Ct Falls Church VA 22043",
    "addr:housenumber":"2100",
    "addr:postcode":"22043",
    "addr:street":"Hutchison Grove Ct",
    "iso:country":"US",
    "sg:address":"2100 Hutchison Grove Ct",
    "sg:city":"Falls Church",
    "sg:classifiers":[
        {
            "category":"Professional",
            "subcategory":"Business Services",
            "type":"Services"
        }
    ],
    "sg:phone":"+1 703 534 9615",
    "sg:postcode":"22043",
    "sg:province":"VA",
    "sg:tags":[
        "interior",
        "consultant",
        "design",
        "decorator"
    ],
    "wof:name":"Magic Interior",
    "wof:placetype":"venue"
},
  "geometry": {"coordinates":[-77.20793999999999,38.906386],"type":"Point"}
}