{
  "type": "Feature",
  "properties": {
    "iso:country":"US",
    "sg:address":"4237 Cheswick Ln",
    "sg:city":"Virginia Beach",
    "sg:classifiers":[
        {
            "category":"Organizations",
            "subcategory":"Community Association",
            "type":"Services"
        }
    ],
    "sg:phone":"+1 757 490 3038",
    "sg:postcode":"23455",
    "sg:province":"VA",
    "wof:name":"Chesbay Condo Owners Assn I",
    "wof:placetype":"venue"
},
  "geometry": {"coordinates":[-76.12193000000001,36.858449],"type":"Point"}
}