{
  "type": "Feature",
  "properties": {
    "addr:full":"1160 Crystal Hill Rd Crystal Hill VA 24539",
    "addr:housenumber":"1160",
    "addr:postcode":"24539",
    "addr:street":"Crystal Hill Rd",
    "iso:country":"US",
    "sg:address":"1160 Crystal Hill Rd",
    "sg:city":"Crystal Hill",
    "sg:classifiers":[
        {
            "category":"Building & Trades",
            "subcategory":"Construction",
            "type":"Services"
        }
    ],
    "sg:phone":"+1 434 575 1254",
    "sg:postcode":"24539",
    "sg:province":"VA",
    "sg:tags":[
        "house"
    ],
    "wof:name":"Briton Construction",
    "wof:placetype":"venue"
},
  "geometry": {"coordinates":[-78.920777,36.855741],"type":"Point"}
}