{
  "type": "Feature",
  "properties": {
    "addr:full":"504 Lincoln Ave Franklin VA 23851",
    "addr:housenumber":"504",
    "addr:postcode":"23851",
    "addr:street":"Lincoln Ave",
    "iso:country":"US",
    "sg:address":"504 Lincoln Ave",
    "sg:city":"Franklin",
    "sg:classifiers":[
        {
            "category":"Retail",
            "subcategory":"Car Wash",
            "type":"Services"
        }
    ],
    "sg:phone":"+1 757 562 7642",
    "sg:postcode":"23851",
    "sg:province":"VA",
    "sg:tags":[
        "carwash"
    ],
    "wof:name":"Sumblin Pressure Wash",
    "wof:placetype":"venue"
},
  "geometry": {"coordinates":[-76.907371,36.680534],"type":"Point"}
}