{
  "type": "Feature",
  "properties": {
    "iso:country":"US",
    "sg:address":"2223 Maple St",
    "sg:city":"Virginia Beach",
    "sg:classifiers":[
        {
            "category":"Professional",
            "subcategory":"Computer Services",
            "type":"Services"
        }
    ],
    "sg:phone":"+1 757 496 4805",
    "sg:postcode":"23451",
    "sg:province":"VA",
    "sg:tags":[
        "datum"
    ],
    "wof:name":"Homespun",
    "wof:placetype":"venue"
},
  "geometry": {"coordinates":[-76.06361,36.911627],"type":"Point"}
}