{
  "type": "Feature",
  "properties": {
    "addr:full":"1100 Vinyard Rd Vinton VA 24179",
    "addr:housenumber":"1100",
    "addr:postcode":"24179",
    "addr:street":"Vinyard Rd",
    "iso:country":"US",
    "sg:address":"1100 Vinyard Rd",
    "sg:city":"Vinton",
    "sg:classifiers":[
        {
            "category":"Recreation",
            "type":"Entertainment"
        }
    ],
    "sg:phone":"+1 540 345 3557",
    "sg:postcode":"24179",
    "sg:province":"VA",
    "sg:tags":[
        "club",
        "hockey"
    ],
    "wof:name":"Virginia Lancers Hockey Club",
    "wof:placetype":"venue"
},
  "geometry": {"coordinates":[-79.888599,37.272124],"type":"Point"}
}