{
  "type": "Feature",
  "properties": {
    "addr:full":"19227 Gleedsville Rd Leesburg VA 20175",
    "addr:housenumber":"19227",
    "addr:postcode":"20175",
    "addr:street":"Gleedsville Rd",
    "iso:country":"US",
    "sg:address":"19227 Gleedsville Rd",
    "sg:city":"Leesburg",
    "sg:classifiers":[
        {
            "category":"Organizations",
            "subcategory":"Religious Organization",
            "type":"Services"
        }
    ],
    "sg:phone":"+1 703 777 5662",
    "sg:postcode":"20175",
    "sg:province":"VA",
    "wof:name":"Worship Center",
    "wof:placetype":"venue"
},
  "geometry": {"coordinates":[-77.588183,39.086332],"type":"Point"}
}