{
  "type": "Feature",
  "properties": {
    "iso:country":"US",
    "sg:address":"2140 Winston Ave SW",
    "sg:city":"Roanoke",
    "sg:classifiers":[
        {
            "category":"Shopping",
            "subcategory":"Clothing, Apparel, & Fashions",
            "type":"Retail Goods"
        }
    ],
    "sg:phone":"+1 540 345 7008",
    "sg:postcode":"24014",
    "sg:province":"VA",
    "wof:name":"Gantner Factory Outlet",
    "wof:placetype":"venue"
},
  "geometry": {"coordinates":[-79.95289200000001,37.253539],"type":"Point"}
}