{
  "type": "Feature",
  "properties": {
    "iso:country":"US",
    "sg:address":"1309 W Main St",
    "sg:city":"Charlottesville",
    "sg:classifiers":[
        {
            "category":"Travel",
            "subcategory":"Hotels & Motels",
            "type":"Entertainment"
        }
    ],
    "sg:phone":"+1 434 295 4333",
    "sg:postcode":"22903",
    "sg:province":"VA",
    "sg:website":"redroof.com/reservations/propert...",
    "wof:name":"Red Roof Inn",
    "wof:placetype":"venue"
},
  "geometry": {"coordinates":[-78.49870300000001,38.033501],"type":"Point"}
}