{
  "type": "Feature",
  "properties": {
    "addr:full":"1615 Jefferson Hwy Fishersville VA 22939",
    "addr:housenumber":"1615",
    "addr:postcode":"22939",
    "addr:street":"Jefferson Hwy Fishersville",
    "iso:country":"US",
    "sg:address":"1615 Jefferson Hwy",
    "sg:city":"Fishersville",
    "sg:classifiers":[
        {
            "category":"Health Services",
            "subcategory":"Hospital",
            "type":"Services"
        }
    ],
    "sg:phone":"+1 540 942 7811",
    "sg:postcode":"22939",
    "sg:province":"VA",
    "sg:tags":[
        "mental"
    ],
    "wof:name":"Valley Community Svc Board",
    "wof:placetype":"venue"
},
  "geometry": {"coordinates":[-78.984281,38.106765],"type":"Point"}
}