{
  "type": "Feature",
  "properties": {
    "iso:country":"US",
    "sg:address":"10380 Democracy Ln",
    "sg:city":"Fairfax",
    "sg:classifiers":[
        {
            "category":"Professional",
            "type":"Services"
        }
    ],
    "sg:phone":"+1 703 359 9008",
    "sg:postcode":"22030",
    "sg:province":"VA",
    "sg:tags":[
        "establishment"
    ],
    "wof:name":"Greenhoot Inc",
    "wof:placetype":"venue"
},
  "geometry": {"coordinates":[-77.30124000000001,38.849419],"type":"Point"}
}