{
  "type": "Feature",
  "properties": {
    "addr:full":"23411 Autopilot Dr Sterling VA 20166",
    "addr:housenumber":"23411",
    "addr:postcode":"20166",
    "addr:street":"Autopilot Dr",
    "iso:country":"US",
    "sg:address":"23411 Autopilot Dr",
    "sg:city":"Sterling",
    "sg:phone":"+1 703 661 0150",
    "sg:postcode":"20166",
    "sg:province":"VA",
    "sg:tags":[
        "fuel",
        "aircraft",
        "corporate",
        "private"
    ],
    "wof:name":"Piedmont Hawthorne Aviations",
    "wof:placetype":"venue"
},
  "geometry": {"coordinates":[-77.44961000000001,38.971289],"type":"Point"}
}