{
  "type": "Feature",
  "properties": {
    "addr:full":"684 Berkmar Cir Charlottesville VA 22901",
    "addr:housenumber":"684",
    "addr:postcode":"22901",
    "addr:street":"Berkmar Cir",
    "iso:country":"US",
    "sg:address":"684 Berkmar Cir",
    "sg:city":"Charlottesville",
    "sg:classifiers":[
        {
            "category":"Real Estate",
            "subcategory":"Real Estate Agent",
            "type":"Services"
        }
    ],
    "sg:phone":"+1 434 973 1977",
    "sg:postcode":"22901",
    "sg:province":"VA",
    "sg:tags":[
        "commercial",
        "broker"
    ],
    "wof:name":"Lebo Commercial Properties",
    "wof:placetype":"venue"
},
  "geometry": {"coordinates":[-78.478424,38.084853],"type":"Point"}
}