{
  "type": "Feature",
  "properties": {
    "addr:full":"216 Hatton St Portsmouth VA 23704",
    "addr:housenumber":"216",
    "addr:postcode":"23704",
    "addr:street":"Hatton St",
    "iso:country":"US",
    "sg:address":"216 Hatton St",
    "sg:city":"Portsmouth",
    "sg:classifiers":[
        {
            "category":"Health Services",
            "subcategory":"Doctor",
            "type":"Services"
        }
    ],
    "sg:phone":"+1 757 397 7842",
    "sg:postcode":"23704",
    "sg:province":"VA",
    "sg:tags":[
        "physician",
        "surgeon"
    ],
    "wof:name":"Robert V Forehand MD",
    "wof:placetype":"venue"
},
  "geometry": {"coordinates":[-76.310104,36.842109],"type":"Point"}
}