{
  "type": "Feature",
  "properties": {
    "addr:full":"12916 Kidwell Dr Woodbridge VA 22193",
    "addr:housenumber":"12916",
    "addr:postcode":"22193",
    "addr:street":"Kidwell Dr",
    "iso:country":"US",
    "sg:address":"12916 Kidwell Dr",
    "sg:city":"Woodbridge",
    "sg:classifiers":[
        {
            "category":"Banks & Credit Unions",
            "subcategory":"Financial Services",
            "type":"Services"
        }
    ],
    "sg:phone":"+1 703 730 2076",
    "sg:postcode":"22193",
    "sg:province":"VA",
    "sg:tags":[
        "trust",
        "investment",
        "real estate"
    ],
    "wof:name":"Advantages Property Investment",
    "wof:placetype":"venue"
},
  "geometry": {"coordinates":[-77.34240800000001,38.671165],"type":"Point"}
}