{
  "type": "Feature",
  "properties": {
    "addr:full":"16109 Burnley Rd Barboursville VA 22923",
    "addr:housenumber":"16109",
    "addr:postcode":"22923",
    "addr:street":"Burnley Rd",
    "iso:country":"US",
    "sg:address":"16109 Burnley Rd",
    "sg:city":"Barboursville",
    "sg:classifiers":[
        {
            "category":"Building & Trades",
            "subcategory":"Construction",
            "type":"Services"
        }
    ],
    "sg:phone":"+1 540 832 3895",
    "sg:postcode":"22923",
    "sg:province":"VA",
    "sg:tags":[
        "house"
    ],
    "wof:name":"Allison Construction",
    "wof:placetype":"venue"
},
  "geometry": {"coordinates":[-78.33801200000001,38.185131],"type":"Point"}
}