{
  "type": "Feature",
  "properties": {
    "addr:full":"9716 Lafayette Ave Manassas VA 20109",
    "addr:housenumber":"9716",
    "addr:postcode":"20109",
    "addr:street":"Lafayette Ave",
    "iso:country":"US",
    "sg:address":"9716 Lafayette Ave",
    "sg:city":"Manassas",
    "sg:classifiers":[
        {
            "category":"Building & Trades",
            "subcategory":"Construction",
            "type":"Services"
        }
    ],
    "sg:phone":"+1 703 330 1311",
    "sg:postcode":"20109",
    "sg:province":"VA",
    "sg:tags":[
        "roofing",
        "contractor"
    ],
    "wof:name":"Reyes Roofing Contractors  LLC",
    "wof:placetype":"venue"
},
  "geometry": {"coordinates":[-77.49203900000001,38.786463],"type":"Point"}
}