{
  "type": "Feature",
  "properties": {
    "addr:full":"6027 Cathedral Rd Fredericksburg VA 22407",
    "addr:housenumber":"6027",
    "addr:postcode":"22407",
    "addr:street":"Cathedral Rd",
    "iso:country":"US",
    "sg:address":"6027 Cathedral Rd",
    "sg:city":"Fredericksburg",
    "sg:classifiers":[
        {
            "category":"Professional",
            "subcategory":"Computer Services",
            "type":"Services"
        }
    ],
    "sg:phone":"+1 540 220 6104",
    "sg:postcode":"22407",
    "sg:province":"VA",
    "sg:tags":[
        "design",
        "system"
    ],
    "wof:name":"Codepoetscom",
    "wof:placetype":"venue"
},
  "geometry": {"coordinates":[-77.54175499999999,38.261073],"type":"Point"}
}