{
  "type": "Feature",
  "properties": {
    "iso:country":"US",
    "sg:address":"1727 Peters Creek Rd NW",
    "sg:city":"Roanoke",
    "sg:classifiers":[
        {
            "category":"Real Estate",
            "subcategory":"Real Estate Agent",
            "type":"Services"
        }
    ],
    "sg:phone":"+1 540 562 3200",
    "sg:postcode":"24017",
    "sg:province":"VA",
    "wof:name":"Buyers Broker Realty Inc",
    "wof:placetype":"venue"
},
  "geometry": {"coordinates":[-80.007041,37.304726],"type":"Point"}
}