{
  "type": "Feature",
  "properties": {
    "addr:full":"21509 Welby Ter Ashburn VA 20148",
    "addr:postcode":"21509;20148",
    "addr:street":"Welby Ter",
    "iso:country":"US",
    "sg:address":"21509 Welby Ter",
    "sg:city":"Ashburn",
    "sg:classifiers":[
        {
            "category":"Health Services",
            "subcategory":"Health Practitioner",
            "type":"Services"
        }
    ],
    "sg:phone":"+1 703 734 1119",
    "sg:postcode":"20148",
    "sg:province":"VA",
    "wof:name":"Point of Change Inc",
    "wof:placetype":"venue"
},
  "geometry": {"coordinates":[-77.510171,39.02082],"type":"Point"}
}