{
  "type": "Feature",
  "properties": {
    "addr:full":"3016 Quail Walk Dr Glen Allen VA 23059",
    "addr:housenumber":"3016",
    "addr:postcode":"23059",
    "addr:street":"Quail Walk Dr",
    "iso:country":"US",
    "sg:address":"3016 Quail Walk Dr",
    "sg:city":"Glen Allen",
    "sg:classifiers":[
        {
            "category":"Utilities",
            "subcategory":"Telephone",
            "type":"Services"
        }
    ],
    "sg:phone":"+1 804 262 0898",
    "sg:postcode":"23059",
    "sg:province":"VA",
    "sg:tags":[
        "communications"
    ],
    "wof:name":"Devol Childrens Telephone",
    "wof:placetype":"venue"
},
  "geometry": {"coordinates":[-77.494978,37.676262],"type":"Point"}
}