{
  "type": "Feature",
  "properties": {
    "iso:country":"US",
    "sg:address":"12149 Jefferson Davis Hwy",
    "sg:city":"Chester",
    "sg:classifiers":[
        {
            "category":"Home & Garden",
            "subcategory":"Mobile Homes",
            "type":"Retail Goods"
        }
    ],
    "sg:phone":"+1 804 748 2281",
    "sg:postcode":"23831",
    "sg:province":"VA",
    "wof:name":"Oakwood Mobile Homes",
    "wof:placetype":"venue"
},
  "geometry": {"coordinates":[-77.415162,37.360214],"type":"Point"}
}