{
  "type": "Feature",
  "properties": {
    "addr:full":"4525 40th St N Arlington VA 22207",
    "addr:housenumber":"4525",
    "addr:postcode":"22207",
    "addr:street":"40Th St N",
    "iso:country":"US",
    "sg:address":"4525 40th St N",
    "sg:city":"Arlington",
    "sg:classifiers":[
        {
            "category":"Building & Trades",
            "subcategory":"Electrical",
            "type":"Services"
        }
    ],
    "sg:phone":"+1 703 241 0126",
    "sg:postcode":"22207",
    "sg:province":"VA",
    "sg:tags":[
        "electrical",
        "contractor"
    ],
    "wof:name":"Electric Boat Manufacturers A",
    "wof:placetype":"venue"
},
  "geometry": {"coordinates":[-77.135487,38.920343],"type":"Point"}
}