{
  "type": "Feature",
  "properties": {
    "iso:country":"US",
    "sg:address":"2458 Piping Tree Ferry Rd",
    "sg:city":"Mechanicsville",
    "sg:phone":"+1 804 779 2240",
    "sg:postcode":"23111",
    "sg:province":"VA",
    "sg:tags":[
        "farm",
        "wheat"
    ],
    "wof:name":"Krexnus John",
    "wof:placetype":"venue"
},
  "geometry": {"coordinates":[-77.193738,37.642423],"type":"Point"}
}