{
  "type": "Feature",
  "properties": {
    "iso:country":"US",
    "sg:address":"355 Warrenton Rd",
    "sg:city":"Fredericksburg",
    "sg:classifiers":[
        {
            "category":"Autos & Motor Vehicles",
            "subcategory":"Automobile Sales",
            "type":"Retail Goods"
        }
    ],
    "sg:phone":"+1 540 654 5400",
    "sg:postcode":"22405",
    "sg:province":"VA",
    "sg:tags":[
        "car",
        "dealer"
    ],
    "wof:name":"Autobility Incautobility Inc",
    "wof:placetype":"venue"
},
  "geometry": {"coordinates":[-77.48821100000001,38.338315],"type":"Point"}
}