{
  "type": "Feature",
  "properties": {
    "addr:full":"4310 Jefferson Davis Hwy Richmond VA 23234",
    "addr:housenumber":"4310",
    "addr:postcode":"23234",
    "addr:street":"Jefferson Davis Hwy",
    "iso:country":"US",
    "sg:address":"4310 Jefferson Davis Hwy",
    "sg:city":"Richmond",
    "sg:classifiers":[
        {
            "category":"Travel",
            "subcategory":"Hotels & Motels",
            "type":"Entertainment"
        }
    ],
    "sg:phone":"+1 804 275 9100",
    "sg:postcode":"23234",
    "sg:province":"VA",
    "sg:tags":[
        "operation"
    ],
    "wof:name":"Southside Motel",
    "wof:placetype":"venue"
},
  "geometry": {"coordinates":[-77.443028,37.466402],"type":"Point"}
}