{
  "type": "Feature",
  "properties": {
    "addr:full":"360 Greenbrier Dr Charlottesville VA 22901",
    "addr:housenumber":"360",
    "addr:postcode":"22901",
    "addr:street":"Greenbrier Dr",
    "iso:country":"US",
    "sg:address":"360 Greenbrier Dr",
    "sg:city":"Charlottesville",
    "sg:classifiers":[
        {
            "category":"Wholesale",
            "subcategory":"Groceries",
            "type":"Manufacturing & Wholesale Goods"
        }
    ],
    "sg:phone":"+1 434 978 4105",
    "sg:postcode":"22901",
    "sg:province":"VA",
    "sg:tags":[
        "baker"
    ],
    "wof:name":"Flowers Baking Co",
    "wof:placetype":"venue"
},
  "geometry": {"coordinates":[-78.48900399999999,38.073091],"type":"Point"}
}