{
  "type": "Feature",
  "properties": {
    "iso:country":"US",
    "sg:address":"5134 Krick St",
    "sg:city":"Norfolk",
    "sg:classifiers":[
        {
            "category":"Shopping",
            "subcategory":"Gifts & Souvenirs",
            "type":"Retail Goods"
        }
    ],
    "sg:phone":"+1 757 853 2327",
    "sg:postcode":"23513",
    "sg:province":"VA",
    "sg:tags":[
        "basket",
        "parcel"
    ],
    "wof:name":"Beary Much",
    "wof:placetype":"venue"
},
  "geometry": {"coordinates":[-76.227673,36.878571],"type":"Point"}
}