{
  "type": "Feature",
  "properties": {
    "iso:country":"US",
    "sg:address":"43695 John Mosby Hwy",
    "sg:city":"Chantilly",
    "sg:classifiers":[
        {
            "category":"Building & Trades",
            "subcategory":"Landscaping Services",
            "type":"Services"
        }
    ],
    "sg:phone":"+1 703 327 6400",
    "sg:postcode":"20152",
    "sg:province":"VA",
    "sg:tags":[
        "landscape",
        "contractor"
    ],
    "wof:name":"C Dod Loanscape",
    "wof:placetype":"venue"
},
  "geometry": {"coordinates":[-77.491663,38.918432],"type":"Point"}
}