{
  "type": "Feature",
  "properties": {
    "addr:full":"106 E Court St Amherst VA 24521",
    "addr:housenumber":"106",
    "addr:postcode":"24521",
    "addr:street":"E Court St",
    "iso:country":"US",
    "sg:address":"106 E Court St",
    "sg:city":"Amherst",
    "sg:classifiers":[
        {
            "category":"Professional",
            "subcategory":"Accounting & Tax Preparation",
            "type":"Services"
        }
    ],
    "sg:phone":"+1 434 946 0332",
    "sg:postcode":"24521",
    "sg:province":"VA",
    "wof:name":"Doug L Thompson CPA",
    "wof:placetype":"venue"
},
  "geometry": {"coordinates":[-79.05194299999999,37.585425],"type":"Point"}
}