{
  "type": "Feature",
  "properties": {
    "addr:full":"3250 N Franklin St Christiansburg VA 24073",
    "addr:housenumber":"3250",
    "addr:postcode":"24073",
    "addr:street":"N Franklin St",
    "iso:country":"US",
    "sg:address":"3250 N Franklin St",
    "sg:city":"Christiansburg",
    "sg:classifiers":[
        {
            "category":"Restaurant",
            "type":"Food & Drink"
        }
    ],
    "sg:phone":"+1 540 381 9351",
    "sg:postcode":"24073",
    "sg:province":"VA",
    "wof:name":"Valentino's",
    "wof:placetype":"venue"
},
  "geometry": {"coordinates":[-80.420108,37.173926],"type":"Point"}
}