{
  "type": "Feature",
  "properties": {
    "iso:country":"US",
    "sg:address":"8728 Lukens Ln",
    "sg:city":"Alexandria",
    "sg:classifiers":[
        {
            "category":"Manufacturing",
            "subcategory":"Buildings",
            "type":"Manufacturing & Wholesale Goods"
        },
        {
            "category":"Building & Trades",
            "subcategory":"Construction",
            "type":"Services"
        }
    ],
    "sg:phone":"+1 703 780 0792",
    "sg:postcode":"22309",
    "sg:province":"VA",
    "sg:tags":[
        "home",
        "builder",
        "contractor"
    ],
    "wof:name":"Shelkin Homes",
    "wof:placetype":"venue"
},
  "geometry": {"coordinates":[-77.11891199999999,38.720053],"type":"Point"}
}