{
  "type": "Feature",
  "properties": {
    "addr:full":"245 Old Farm Rd Amherst VA 24521",
    "addr:housenumber":"245",
    "addr:postcode":"24521",
    "addr:street":"Old Farm Rd",
    "iso:country":"US",
    "sg:address":"245 Old Farm Rd",
    "sg:city":"Amherst",
    "sg:classifiers":[
        {
            "category":"Building & Trades",
            "subcategory":"Construction",
            "type":"Services"
        }
    ],
    "sg:phone":"+1 434 277 8338",
    "sg:postcode":"24521",
    "sg:province":"VA",
    "sg:tags":[
        "tile",
        "ceramic",
        "installation"
    ],
    "wof:name":"Steven M Stonelake",
    "wof:placetype":"venue"
},
  "geometry": {"coordinates":[-78.96529200000001,37.658235],"type":"Point"}
}