{
  "type": "Feature",
  "properties": {
    "iso:country":"US",
    "sg:address":"1463 Kirby Rd",
    "sg:city":"Mc Lean",
    "sg:classifiers":[
        {
            "category":"Professional",
            "subcategory":"Business Services",
            "type":"Services"
        }
    ],
    "sg:phone":"+1 703 442 0355",
    "sg:postcode":"22101",
    "sg:province":"VA",
    "wof:name":"North Star Group Inc",
    "wof:placetype":"venue"
},
  "geometry": {"coordinates":[-77.142737,38.932121],"type":"Point"}
}