{
  "type": "Feature",
  "properties": {
    "iso:country":"US",
    "sg:address":"100 W Nelson Ave",
    "sg:city":"Alexandria",
    "sg:classifiers":[
        {
            "category":"Shopping",
            "type":"Retail Goods"
        }
    ],
    "sg:phone":"+1 703 836 3348",
    "sg:postcode":"22301",
    "sg:province":"VA",
    "sg:tags":[
        "merchandise"
    ],
    "wof:name":"Dicks Trophies",
    "wof:placetype":"venue"
},
  "geometry": {"coordinates":[-77.066238,38.818912],"type":"Point"}
}