{
  "type": "Feature",
  "properties": {
    "addr:full":"32 Hampton Hall Rd Callao VA 22469",
    "addr:housenumber":"32",
    "addr:postcode":"22469",
    "addr:street":"Hampton Hall Rd",
    "iso:country":"US",
    "sg:address":"32 Hampton Hall Rd",
    "sg:city":"Callao",
    "sg:classifiers":[
        {
            "category":"Real Estate",
            "subcategory":"Real Estate Agent",
            "type":"Services"
        }
    ],
    "sg:phone":"+1 804 529 9390",
    "sg:postcode":"22469",
    "sg:province":"VA",
    "wof:name":"Frank Moss",
    "wof:placetype":"venue"
},
  "geometry": {"coordinates":[-76.56089799999999,37.970425],"type":"Point"}
}