{
  "type": "Feature",
  "properties": {
    "addr:full":"105 E Grayson St Galax VA 24333",
    "addr:housenumber":"105",
    "addr:postcode":"24333",
    "addr:street":"E Grayson St",
    "iso:country":"US",
    "sg:address":"105 E Grayson St",
    "sg:city":"Galax",
    "sg:classifiers":[
        {
            "category":"Personal",
            "subcategory":"Beauty Salon",
            "type":"Services"
        }
    ],
    "sg:phone":"+1 276 236 6811",
    "sg:postcode":"24333",
    "sg:province":"VA",
    "sg:tags":[
        "shop"
    ],
    "wof:name":"Hair Classics Inc",
    "wof:placetype":"venue"
},
  "geometry": {"coordinates":[-80.92475899999999,36.661871],"type":"Point"}
}