{
  "type": "Feature",
  "properties": {
    "iso:country":"US",
    "sg:address":"13466 John Marshall Hwy",
    "sg:city":"Linden",
    "sg:classifiers":[
        {
            "category":"Organizations",
            "subcategory":"Religious Organization",
            "type":"Services"
        }
    ],
    "sg:phone":"+1 540 636 9497",
    "sg:postcode":"22642",
    "sg:province":"VA",
    "sg:tags":[
        "church"
    ],
    "wof:name":"Linden/Markham United Meth Chr",
    "wof:placetype":"venue"
},
  "geometry": {"coordinates":[-78.07511,38.909514],"type":"Point"}
}