{
  "type": "Feature",
  "properties": {
    "addr:full":"14005 Wards Rd Lynchburg VA 24501",
    "addr:housenumber":"14005",
    "addr:postcode":"24501",
    "addr:street":"Wards Rd",
    "iso:country":"US",
    "sg:address":"14005 Wards Rd",
    "sg:city":"Lynchburg",
    "sg:classifiers":[
        {
            "category":"Professional",
            "subcategory":"Accounting & Tax Preparation",
            "type":"Services"
        },
        {
            "category":"Banks & Credit Unions",
            "subcategory":"Financial Services",
            "type":"Services"
        }
    ],
    "sg:phone":"+1 434 237 2386",
    "sg:postcode":"24501",
    "sg:province":"VA",
    "sg:tags":[
        "return",
        "preparation-business",
        "taxes-consultants",
        "loan",
        "reporting",
        "representative",
        "alternative",
        "bookkeeping"
    ],
    "sg:website":"http://www.hrblock.com",
    "wof:name":"H&R Block",
    "wof:placetype":"venue"
},
  "geometry": {"coordinates":[-79.187363,37.315907],"type":"Point"}
}