{
  "type": "Feature",
  "properties": {
    "iso:country":"US",
    "sg:address":"8422 Terminal Rd",
    "sg:city":"Lorton",
    "sg:classifiers":[
        {
            "category":"Manufacturing",
            "subcategory":"Textiles",
            "type":"Manufacturing & Wholesale Goods"
        },
        {
            "category":"Manufacturing",
            "subcategory":"Building Materials",
            "type":"Manufacturing & Wholesale Goods"
        }
    ],
    "sg:phone":"+1 571 291 0492",
    "sg:postcode":"22079",
    "sg:province":"VA",
    "sg:tags":[
        "solid",
        "surface"
    ],
    "wof:name":"Luroc Enterprises,llc",
    "wof:placetype":"venue"
},
  "geometry": {"coordinates":[-77.195683,38.727955],"type":"Point"}
}