{
  "type": "Feature",
  "properties": {
    "iso:country":"US",
    "sg:address":"4525 Pruden Blvd",
    "sg:city":"Suffolk",
    "sg:classifiers":[
        {
            "category":"Building & Trades",
            "subcategory":"Landscaping Services",
            "type":"Services"
        }
    ],
    "sg:phone":"+1 757 539 0579",
    "sg:postcode":"23434",
    "sg:province":"VA",
    "wof:name":"Greene Lawn Services",
    "wof:placetype":"venue"
},
  "geometry": {"coordinates":[-76.652069,36.787686],"type":"Point"}
}