{
  "type": "Feature",
  "properties": {
    "addr:full":"3318 Brest Ave Norfolk VA 23509",
    "addr:housenumber":"3318",
    "addr:postcode":"23509",
    "addr:street":"Brest Ave",
    "iso:country":"US",
    "sg:address":"3318 Brest Ave",
    "sg:city":"Norfolk",
    "sg:classifiers":[
        {
            "category":"Building & Trades",
            "subcategory":"Cleaning & Sanitation",
            "type":"Services"
        }
    ],
    "sg:phone":"+1 757 536 2637",
    "sg:postcode":"23509",
    "sg:province":"VA",
    "wof:name":"Normans Cleaning Service",
    "wof:placetype":"venue"
},
  "geometry": {"coordinates":[-76.25706700000001,36.879574],"type":"Point"}
}