{
  "type": "Feature",
  "properties": {
    "addr:full":"7022 Commerce St Springfield VA 22150",
    "addr:housenumber":"7022",
    "addr:postcode":"22150",
    "addr:street":"Commerce St",
    "iso:country":"US",
    "sg:address":"7022 Commerce St",
    "sg:city":"Springfield",
    "sg:classifiers":[
        {
            "category":"Banks & Credit Unions",
            "subcategory":"Bank",
            "type":"Services"
        }
    ],
    "sg:phone":"+1 703 644 2274",
    "sg:postcode":"22150",
    "sg:province":"VA",
    "sg:tags":[
        "depository",
        "banking",
        "check",
        "cashing"
    ],
    "wof:name":"Checks Cash & Cellular Service",
    "wof:placetype":"venue"
},
  "geometry": {"coordinates":[-77.187259,38.782604],"type":"Point"}
}