{
  "type": "Feature",
  "properties": {
    "iso:country":"US",
    "sg:address":"12388 Warwick Blvd",
    "sg:city":"Newport News",
    "sg:classifiers":[
        {
            "category":"Real Estate",
            "subcategory":"Real Estate Agent",
            "type":"Services"
        }
    ],
    "sg:phone":"+1 757 596 8890",
    "sg:postcode":"23606",
    "sg:province":"VA",
    "wof:name":"Lively Realty",
    "wof:placetype":"venue"
},
  "geometry": {"coordinates":[-76.49224,37.06724],"type":"Point"}
}