{
  "type": "Feature",
  "properties": {
    "addr:full":"434 Hickok Rd Lynchburg VA 24502",
    "addr:housenumber":"434",
    "addr:postcode":"24502",
    "addr:street":"Hickok Rd",
    "iso:country":"US",
    "sg:address":"434 Hickok Rd",
    "sg:city":"Lynchburg",
    "sg:classifiers":[
        {
            "category":"Health Services",
            "subcategory":"Doctor",
            "type":"Services"
        }
    ],
    "sg:phone":"+1 434 237 5344",
    "sg:postcode":"24502",
    "sg:province":"VA",
    "sg:tags":[
        "medical"
    ],
    "wof:name":"John D Morrison Dr",
    "wof:placetype":"venue"
},
  "geometry": {"coordinates":[-79.241496,37.320083],"type":"Point"}
}