{
  "type": "Feature",
  "properties": {
    "iso:country":"US",
    "sg:address":"224 Prince St NE",
    "sg:city":"Leesburg",
    "sg:classifiers":[
        {
            "category":"Building & Trades",
            "subcategory":"Construction",
            "type":"Services"
        }
    ],
    "sg:phone":"+1 703 779 2324",
    "sg:postcode":"20176",
    "sg:province":"VA",
    "sg:tags":[
        "house"
    ],
    "wof:name":"Premier Home Services Inc",
    "wof:placetype":"venue"
},
  "geometry": {"coordinates":[-77.553611,39.115115],"type":"Point"}
}