{
  "type": "Feature",
  "properties": {
    "addr:full":"11898 Falling Creek Dr Manassas VA 20112",
    "addr:housenumber":"11898",
    "addr:postcode":"20112",
    "addr:street":"Falling Creek Dr",
    "iso:country":"US",
    "sg:address":"11898 Falling Creek Dr",
    "sg:city":"Manassas",
    "sg:classifiers":[
        {
            "category":"Retail",
            "subcategory":"Repair Shop",
            "type":"Services"
        }
    ],
    "sg:phone":"+1 703 551 0535",
    "sg:postcode":"20112",
    "sg:province":"VA",
    "sg:tags":[
        "refinishing",
        "furniture"
    ],
    "wof:name":"Furniture Medic Inc",
    "wof:placetype":"venue"
},
  "geometry": {"coordinates":[-77.429863,38.698572],"type":"Point"}
}