{
  "type": "Feature",
  "properties": {
    "iso:country":"US",
    "sg:address":"3700 Candlers Mountain Rd",
    "sg:city":"Lynchburg",
    "sg:classifiers":[
        {
            "category":"Shopping",
            "subcategory":"Shoes",
            "type":"Retail Goods"
        }
    ],
    "sg:phone":"+1 434 846 4768",
    "sg:postcode":"24502",
    "sg:province":"VA",
    "wof:name":"Super Shoe Stores",
    "wof:placetype":"venue"
},
  "geometry": {"coordinates":[-79.17189500000001,37.35918],"type":"Point"}
}