{
  "type": "Feature",
  "properties": {
    "addr:full":"710 Houston St Chase City VA 23924",
    "addr:housenumber":"710",
    "addr:postcode":"23924",
    "addr:street":"Houston St",
    "iso:country":"US",
    "sg:address":"710 Houston St",
    "sg:city":"Chase City",
    "sg:phone":"+1 434 372 4373",
    "sg:postcode":"23924",
    "sg:province":"VA",
    "sg:tags":[
        "farm",
        "tobacco"
    ],
    "wof:name":"Edna Edgerton",
    "wof:placetype":"venue"
},
  "geometry": {"coordinates":[-78.449815,36.802171],"type":"Point"}
}