{
  "type": "Feature",
  "properties": {
    "addr:full":"1282 Smithfield Shopping Plz Smithfield VA 23430",
    "addr:housenumber":"1282",
    "addr:postcode":"23430",
    "addr:street":"Smithfield Shopping Plz",
    "iso:country":"US",
    "sg:address":"1282 Smithfield Shopping Plz",
    "sg:city":"Smithfield",
    "sg:classifiers":[
        {
            "category":"Shopping",
            "subcategory":"Florist",
            "type":"Retail Goods"
        }
    ],
    "sg:phone":"+1 757 357 5396",
    "sg:postcode":"23430",
    "sg:province":"VA",
    "wof:name":"Farm Fresh House of Flowers",
    "wof:placetype":"venue"
},
  "geometry": {"coordinates":[-76.603084,36.955267],"type":"Point"}
}