{
  "type": "Feature",
  "properties": {
    "addr:full":"7400 Granby St Norfolk VA 23505",
    "addr:housenumber":"7400",
    "addr:postcode":"23505",
    "addr:street":"Granby St",
    "iso:country":"US",
    "sg:address":"7400 Granby St",
    "sg:city":"Norfolk",
    "sg:classifiers":[
        {
            "category":"Health Services",
            "subcategory":"Doctor",
            "type":"Services"
        }
    ],
    "sg:phone":"+1 757 587 1243",
    "sg:postcode":"23505",
    "sg:province":"VA",
    "sg:tags":[
        "dentist"
    ],
    "wof:name":"Konikoff Periodontics",
    "wof:placetype":"venue"
},
  "geometry": {"coordinates":[-76.273096,36.913427],"type":"Point"}
}