{
  "type": "Feature",
  "properties": {
    "iso:country":"US",
    "sg:address":"3100 17th St S",
    "sg:city":"Arlington",
    "sg:classifiers":[
        {
            "category":"Shopping",
            "subcategory":"Music",
            "type":"Retail Goods"
        }
    ],
    "sg:phone":"+1 703 302 3930",
    "sg:postcode":"22204",
    "sg:province":"VA",
    "sg:tags":[
        "dvd's"
    ],
    "sg:website":"www.emcrhythm.com",
    "wof:name":"Emc Rhythm",
    "wof:placetype":"venue"
},
  "geometry": {"coordinates":[-77.087368,38.855567],"type":"Point"}
}