{
  "type": "Feature",
  "properties": {
    "addr:full":"7225 Chestnut Church Rd Mechanicsville VA 23116",
    "addr:housenumber":"7225",
    "addr:postcode":"23116",
    "addr:street":"Chestnut Church Rd",
    "iso:country":"US",
    "sg:address":"7225 Chestnut Church Rd",
    "sg:city":"Mechanicsville",
    "sg:classifiers":[
        {
            "category":"Building & Trades",
            "subcategory":"Construction",
            "type":"Services"
        }
    ],
    "sg:phone":"+1 804 641 6270",
    "sg:postcode":"23116",
    "sg:province":"VA",
    "sg:tags":[
        "house"
    ],
    "wof:name":"Grayt Homes & Improvements",
    "wof:placetype":"venue"
},
  "geometry": {"coordinates":[-77.34824500000001,37.70952],"type":"Point"}
}