{
  "type": "Feature",
  "properties": {
    "addr:full":"14225 River Rd Chesterfield VA 23838",
    "addr:housenumber":"14225",
    "addr:postcode":"23838",
    "addr:street":"River Rd",
    "iso:country":"US",
    "sg:address":"14225 River Rd",
    "sg:city":"Chesterfield",
    "sg:classifiers":[
        {
            "category":"Professional",
            "subcategory":"Business Services",
            "type":"Services"
        }
    ],
    "sg:phone":"+1 804 639 3488",
    "sg:postcode":"23838",
    "sg:province":"VA",
    "wof:name":"Interiors From Horses Mouth",
    "wof:placetype":"venue"
},
  "geometry": {"coordinates":[-77.673153,37.326563],"type":"Point"}
}