{
  "type": "Feature",
  "properties": {
    "addr:full":"3030 Stony Point Rd Richmond VA 23235",
    "addr:housenumber":"3030",
    "addr:postcode":"23235",
    "addr:street":"Stony Point Rd",
    "iso:country":"US",
    "sg:address":"3030 Stony Point Rd",
    "sg:city":"Richmond",
    "sg:classifiers":[
        {
            "category":"Shopping",
            "subcategory":"Crafts & Fabrics",
            "type":"Retail Goods"
        }
    ],
    "sg:phone":"+1 804 323 5777",
    "sg:postcode":"23235",
    "sg:province":"VA",
    "sg:tags":[
        "yarn"
    ],
    "wof:name":"Lettuce Knit",
    "wof:placetype":"venue"
},
  "geometry": {"coordinates":[-77.56267,37.537964],"type":"Point"}
}