{
  "type": "Feature",
  "properties": {
    "iso:country":"US",
    "sg:address":"10580 Main St",
    "sg:city":"Fairfax",
    "sg:classifiers":[
        {
            "category":"Shopping",
            "subcategory":"Optical Goods",
            "type":"Retail Goods"
        }
    ],
    "sg:phone":"+1 703 273 8274",
    "sg:postcode":"22030",
    "sg:province":"VA",
    "wof:name":"Nuvision Optical",
    "wof:placetype":"venue"
},
  "geometry": {"coordinates":[-77.30923300000001,38.847004],"type":"Point"}
}