{
  "type": "Feature",
  "properties": {
    "addr:full":"1127 N 29th St Richmond VA 23223",
    "addr:housenumber":"1127",
    "addr:postcode":"23223",
    "addr:street":"N 29Th St",
    "iso:country":"US",
    "sg:address":"1127 N 29th St",
    "sg:city":"Richmond",
    "sg:classifiers":[
        {
            "category":"Health Services",
            "subcategory":"Doctor",
            "type":"Services"
        }
    ],
    "sg:phone":"+1 804 648 6153",
    "sg:postcode":"23223",
    "sg:province":"VA",
    "sg:tags":[
        "physician",
        "surgeon"
    ],
    "wof:name":"Campbell & Whitaker LTD",
    "wof:placetype":"venue"
},
  "geometry": {"coordinates":[-77.40797600000001,37.536836],"type":"Point"}
}