{
  "type": "Feature",
  "properties": {
    "iso:country":"US",
    "sg:address":"89 Sager Hollow",
    "sg:city":"Strasburg",
    "sg:classifiers":[
        {
            "category":"Building & Trades",
            "subcategory":"Construction",
            "type":"Services"
        }
    ],
    "sg:phone":"+1 540 465 8312",
    "sg:postcode":"22657",
    "sg:province":"VA",
    "sg:tags":[
        "concrete",
        "contractor"
    ],
    "wof:name":"R & R Concrete",
    "wof:placetype":"venue"
},
  "geometry": {"coordinates":[-78.4515,38.990565],"type":"Point"}
}