{
  "type": "Feature",
  "properties": {
    "iso:country":"US",
    "sg:address":"220 Rosegate Pl",
    "sg:city":"Virginia Beach",
    "sg:classifiers":[
        {
            "category":"Real Estate",
            "subcategory":"Real Estate Operator",
            "type":"Services"
        }
    ],
    "sg:phone":"+1 757 486 7317",
    "sg:postcode":"23452",
    "sg:province":"VA",
    "sg:tags":[
        "building",
        "apartment"
    ],
    "wof:name":"Rose Gate Apartments",
    "wof:placetype":"venue"
},
  "geometry": {"coordinates":[-76.084672,36.839735],"type":"Point"}
}