{
  "type": "Feature",
  "properties": {
    "iso:country":"US",
    "sg:address":"2609 Oakledge Ct",
    "sg:city":"Vienna",
    "sg:classifiers":[
        {
            "category":"Real Estate",
            "subcategory":"Real Estate Operator",
            "type":"Services"
        }
    ],
    "sg:phone":"+1 703 281 3818",
    "sg:postcode":"22181",
    "sg:province":"VA",
    "sg:tags":[
        "building",
        "nonresidential"
    ],
    "wof:name":"Ftv Properties LLC",
    "wof:placetype":"venue"
},
  "geometry": {"coordinates":[-77.294214,38.892242],"type":"Point"}
}