{
  "type": "Feature",
  "properties": {
    "addr:full":"5099 Jefferson Davis Hwy Fredericksburg VA 22408",
    "addr:housenumber":"5099",
    "addr:postcode":"22408",
    "addr:street":"Jefferson Davis Hwy",
    "iso:country":"US",
    "sg:address":"5099 Jefferson Davis Hwy",
    "sg:city":"Fredericksburg",
    "sg:classifiers":[
        {
            "category":"Retail",
            "subcategory":"Repair Shop",
            "type":"Services"
        }
    ],
    "sg:phone":"+1 540 891 7536",
    "sg:postcode":"22408",
    "sg:province":"VA",
    "wof:name":"Vcr Doctor",
    "wof:placetype":"venue"
},
  "geometry": {"coordinates":[-77.49749,38.256866],"type":"Point"}
}