{
  "type": "Feature",
  "properties": {
    "addr:full":"9506 Hospital Ave Nassawadox VA 23413",
    "addr:housenumber":"9506",
    "addr:postcode":"23413",
    "addr:street":"Hospital Ave",
    "iso:country":"US",
    "sg:address":"9506 Hospital Ave",
    "sg:city":"Nassawadox",
    "sg:classifiers":[
        {
            "category":"Health Services",
            "subcategory":"Doctor",
            "type":"Services"
        }
    ],
    "sg:phone":"+1 757 442 6242",
    "sg:postcode":"23413",
    "sg:province":"VA",
    "sg:tags":[
        "physician",
        "surgeon"
    ],
    "wof:name":"Family Practice Assoc",
    "wof:placetype":"venue"
},
  "geometry": {"coordinates":[-75.862647,37.47505],"type":"Point"}
}