{
  "type": "Feature",
  "properties": {
    "iso:country":"US",
    "sg:address":"5916 River Dr",
    "sg:city":"Lorton",
    "sg:classifiers":[
        {
            "category":"Building & Trades",
            "subcategory":"Construction",
            "type":"Services"
        }
    ],
    "sg:phone":"+1 703 550 2141",
    "sg:postcode":"22079",
    "sg:province":"VA",
    "sg:tags":[
        "general",
        "contractor"
    ],
    "wof:name":"PBS Contracting Inc",
    "wof:placetype":"venue"
},
  "geometry": {"coordinates":[-77.14017699999999,38.636206],"type":"Point"}
}