{
  "type": "Feature",
  "properties": {
    "addr:full":"16414 Southampton Pkwy Capron VA 23829",
    "addr:housenumber":"16414",
    "addr:postcode":"23829",
    "addr:street":"Southampton Pkwy",
    "iso:country":"US",
    "sg:address":"16414 Southampton Pkwy",
    "sg:city":"Capron",
    "sg:classifiers":[
        {
            "category":"Building & Trades",
            "subcategory":"Landscaping Services",
            "type":"Services"
        }
    ],
    "sg:phone":"+1 434 658 3154",
    "sg:postcode":"23829",
    "sg:province":"VA",
    "sg:tags":[
        "tree",
        "work",
        "stump",
        "storm",
        "hurricane"
    ],
    "wof:name":"Stump Chasers",
    "wof:placetype":"venue"
},
  "geometry": {"coordinates":[-77.224002,36.703375],"type":"Point"}
}