{
  "type": "Feature",
  "properties": {
    "addr:full":"397 Azalea Ave Richmond VA 23227",
    "addr:housenumber":"397",
    "addr:postcode":"23227",
    "addr:street":"Azalea Ave",
    "iso:country":"US",
    "sg:address":"397 Azalea Ave",
    "sg:city":"Richmond",
    "sg:classifiers":[
        {
            "category":"Government",
            "subcategory":"Office",
            "type":"Public Place"
        }
    ],
    "sg:phone":"+1 804 371 3353",
    "sg:postcode":"23227",
    "sg:province":"VA",
    "sg:tags":[
        "state",
        "program"
    ],
    "wof:name":"Visually Handicapped Dept",
    "wof:placetype":"venue"
},
  "geometry": {"coordinates":[-77.43615200000001,37.602449],"type":"Point"}
}