{
  "type": "Feature",
  "properties": {
    "addr:full":"8275 Hampton Blvd Norfolk VA 23505",
    "addr:housenumber":"8275",
    "addr:postcode":"23505",
    "addr:street":"Hampton Blvd",
    "iso:country":"US",
    "sg:address":"8275 Hampton Blvd",
    "sg:city":"Norfolk",
    "sg:classifiers":[
        {
            "category":"Restaurant",
            "type":"Food & Drink"
        }
    ],
    "sg:menulink":"http://www.allmenus.com/va/norfolk/192313-wendys/menu/",
    "sg:phone":"+1 757 423 1971",
    "sg:postcode":"23505",
    "sg:province":"VA",
    "sg:tags":[
        "burger",
        "american",
        "soup"
    ],
    "wof:name":"Wendy's",
    "wof:placetype":"venue"
},
  "geometry": {"coordinates":[-76.317785,36.928134],"type":"Point"}
}