{
  "type": "Feature",
  "properties": {
    "addr:full":"122 Draft Ave Stuarts Draft VA 24477",
    "addr:housenumber":"122",
    "addr:postcode":"24477",
    "addr:street":"Draft Ave",
    "iso:country":"US",
    "sg:address":"122 Draft Ave",
    "sg:city":"Stuarts Draft",
    "sg:classifiers":[
        {
            "category":"Manufacturing",
            "subcategory":"Metals",
            "type":"Manufacturing & Wholesale Goods"
        }
    ],
    "sg:phone":"+1 540 337 2586",
    "sg:postcode":"24477",
    "sg:province":"VA",
    "sg:tags":[
        "mobile",
        "access"
    ],
    "wof:name":"Gary Campbell Inc",
    "wof:placetype":"venue"
},
  "geometry": {"coordinates":[-79.033287,38.024722],"type":"Point"}
}