{
  "type": "Feature",
  "properties": {
    "addr:full":"901 W Hundred Rd Chester VA 23836",
    "addr:housenumber":"901",
    "addr:postcode":"23836",
    "addr:street":"W Hundred Rd",
    "iso:country":"US",
    "sg:address":"901 W Hundred Rd",
    "sg:city":"Chester",
    "sg:classifiers":[
        {
            "category":"Autos & Motor Vehicles",
            "subcategory":"Automobile Sales",
            "type":"Retail Goods"
        }
    ],
    "sg:phone":"+1 804 768 4600",
    "sg:postcode":"23836",
    "sg:province":"VA",
    "sg:tags":[
        "truck"
    ],
    "wof:name":"Virginia Trucking Ctr-Richmond",
    "wof:placetype":"venue"
},
  "geometry": {"coordinates":[-77.37797999999999,37.34959],"type":"Point"}
}