{
  "type": "Feature",
  "properties": {
    "iso:country":"US",
    "sg:address":"225 Reinekers Ln",
    "sg:city":"Alexandria",
    "sg:classifiers":[
        {
            "category":"Professional",
            "subcategory":"Management & Consulting",
            "type":"Services"
        }
    ],
    "sg:phone":"+1 703 823 8765",
    "sg:postcode":"22314",
    "sg:province":"VA",
    "wof:name":"Martin Branding World Wide",
    "wof:placetype":"venue"
},
  "geometry": {"coordinates":[-77.060017,38.804679],"type":"Point"}
}