{
  "type": "Feature",
  "properties": {
    "addr:full":"109 Willow Wood Ave Smithfield VA 23430",
    "addr:housenumber":"109",
    "addr:postcode":"23430",
    "addr:street":"Willow Wood Ave",
    "iso:country":"US",
    "sg:address":"109 Willow Wood Ave",
    "sg:city":"Smithfield",
    "sg:classifiers":[
        {
            "category":"Wholesale",
            "subcategory":"Machinery & Supplies",
            "type":"Manufacturing & Wholesale Goods"
        }
    ],
    "sg:phone":"+1 757 371 3003",
    "sg:postcode":"23430",
    "sg:province":"VA",
    "sg:tags":[
        "equipment",
        "establishment"
    ],
    "wof:name":"Irrigators Inc",
    "wof:placetype":"venue"
},
  "geometry": {"coordinates":[-76.602558,36.968109],"type":"Point"}
}