{
  "type": "Feature",
  "properties": {
    "addr:full":"2405 Grand Summit Ct Richmond VA 23235",
    "addr:housenumber":"2405",
    "addr:postcode":"23235",
    "addr:street":"Grand Summit Ct",
    "iso:country":"US",
    "sg:address":"2405 Grand Summit Ct",
    "sg:city":"Richmond",
    "sg:classifiers":[
        {
            "category":"Health Services",
            "subcategory":"Doctor",
            "type":"Services"
        }
    ],
    "sg:phone":"+1 804 320 8803",
    "sg:postcode":"23235",
    "sg:province":"VA",
    "wof:name":"VA Academy Genl Dentistry",
    "wof:placetype":"venue"
},
  "geometry": {"coordinates":[-77.558088,37.531706],"type":"Point"}
}