{
  "type": "Feature",
  "properties": {
    "addr:full":"6751 Peach Tree Cir Roanoke VA 24018",
    "addr:housenumber":"6751",
    "addr:postcode":"24018",
    "addr:street":"Peach Tree Cir",
    "iso:country":"US",
    "sg:address":"6751 Peach Tree Cir",
    "sg:city":"Roanoke",
    "sg:classifiers":[
        {
            "category":"Shopping",
            "type":"Retail Goods"
        }
    ],
    "sg:phone":"+1 540 989 5424",
    "sg:postcode":"24018",
    "sg:province":"VA",
    "sg:tags":[
        "merchandise"
    ],
    "wof:name":"TBM Enterprises LLC",
    "wof:placetype":"venue"
},
  "geometry": {"coordinates":[-80.047601,37.224092],"type":"Point"}
}