{
  "type": "Feature",
  "properties": {
    "iso:country":"US",
    "sg:address":"3305 Stone Heather Ct",
    "sg:city":"Herndon",
    "sg:classifiers":[
        {
            "category":"Professional",
            "type":"Services"
        }
    ],
    "sg:phone":"+1 703 318 7218",
    "sg:postcode":"20171",
    "sg:province":"VA",
    "wof:name":"Richard McLaughlin",
    "wof:placetype":"venue"
},
  "geometry": {"coordinates":[-77.406009,38.911311],"type":"Point"}
}