{
  "type": "Feature",
  "properties": {
    "iso:country":"US",
    "sg:address":"8200 Greensboro Dr",
    "sg:city":"Mc Lean",
    "sg:classifiers":[
        {
            "category":"Real Estate",
            "subcategory":"Real Estate Agent",
            "type":"Services"
        },
        {
            "category":"Professional",
            "subcategory":"Management & Consulting",
            "type":"Services"
        }
    ],
    "sg:phone":"+1 703 761 3840",
    "sg:postcode":"22102",
    "sg:province":"VA",
    "sg:tags":[
        "consultant"
    ],
    "wof:name":"Clover Real Estate Corp",
    "wof:placetype":"venue"
},
  "geometry": {"coordinates":[-77.23132099999999,38.923633],"type":"Point"}
}