{
  "type": "Feature",
  "properties": {
    "iso:country":"US",
    "sg:address":"1203 Haig Cir",
    "sg:city":"Virginia Beach",
    "sg:classifiers":[
        {
            "category":"Retail",
            "subcategory":"Auto Repair",
            "type":"Services"
        }
    ],
    "sg:phone":"+1 757 471 6650",
    "sg:postcode":"23456",
    "sg:province":"VA",
    "sg:tags":[
        "automotive"
    ],
    "wof:name":"A1 Holloway Road Service",
    "wof:placetype":"venue"
},
  "geometry": {"coordinates":[-76.12214299999999,36.796067],"type":"Point"}
}