{
  "type": "Feature",
  "properties": {
    "addr:full":"1714 Kingsway Rd Norfolk VA 23518",
    "addr:housenumber":"1714",
    "addr:postcode":"23518",
    "addr:street":"Kingsway Rd",
    "iso:country":"US",
    "sg:address":"1714 Kingsway Rd",
    "sg:city":"Norfolk",
    "sg:classifiers":[
        {
            "category":"Manufacturing",
            "subcategory":"Apparel",
            "type":"Manufacturing & Wholesale Goods"
        }
    ],
    "sg:phone":"+1 757 587 6293",
    "sg:postcode":"23518",
    "sg:province":"VA",
    "sg:tags":[
        "outerwear",
        "mfg"
    ],
    "wof:name":"Celys Fine Accessories",
    "wof:placetype":"venue"
},
  "geometry": {"coordinates":[-76.22624399999999,36.913973],"type":"Point"}
}