{
  "type": "Feature",
  "properties": {
    "addr:full":"3747 Tonbridge Pl Woodbridge VA 22192",
    "addr:housenumber":"3747",
    "addr:postcode":"22192",
    "addr:street":"Tonbridge Pl",
    "iso:country":"US",
    "sg:address":"3747 Tonbridge Pl",
    "sg:city":"Woodbridge",
    "sg:classifiers":[
        {
            "category":"Professional",
            "subcategory":"Management & Consulting",
            "type":"Services"
        }
    ],
    "sg:phone":"+1 703 670 8321",
    "sg:postcode":"22192",
    "sg:province":"VA",
    "sg:tags":[
        "teacher"
    ],
    "wof:name":"Hocaoglu Khadega",
    "wof:placetype":"venue"
},
  "geometry": {"coordinates":[-77.322743,38.698543],"type":"Point"}
}