{
  "type": "Feature",
  "properties": {
    "addr:full":"32 Catoctin Cir SE Leesburg VA 20175",
    "addr:housenumber":"32",
    "addr:postcode":"20175",
    "addr:street":"Catoctin Cir Se",
    "iso:country":"US",
    "sg:address":"32 Catoctin Cir SE",
    "sg:city":"Leesburg",
    "sg:classifiers":[
        {
            "category":"Shopping",
            "subcategory":"Hobbies, Toys, & Games",
            "type":"Retail Goods"
        }
    ],
    "sg:phone":"+1 703 777 4133",
    "sg:postcode":"20175",
    "sg:province":"VA",
    "sg:tags":[
        "arts",
        "craft",
        "framing",
        "supply"
    ],
    "wof:name":"Ben Franklin Store 3214",
    "wof:placetype":"venue"
},
  "geometry": {"coordinates":[-77.564696,39.106799],"type":"Point"}
}