{
  "type": "Feature",
  "properties": {
    "addr:full":"3340 Holland Rd Virginia Beach VA 23452",
    "addr:housenumber":"3340",
    "addr:postcode":"23452",
    "addr:street":"Holland Rd",
    "iso:country":"US",
    "sg:address":"3340 Holland Rd",
    "sg:city":"Virginia Beach",
    "sg:classifiers":[
        {
            "category":"Social Services",
            "type":"Services"
        }
    ],
    "sg:phone":"+1 757 368 0888",
    "sg:postcode":"23452",
    "sg:province":"VA",
    "sg:tags":[
        "organization",
        "welfare"
    ],
    "wof:name":"Ymca Early Discoveries",
    "wof:placetype":"venue"
},
  "geometry": {"coordinates":[-76.087412,36.801983],"type":"Point"}
}