{
  "type": "Feature",
  "properties": {
    "iso:country":"US",
    "sg:address":"3460 Londonderry Ct",
    "sg:city":"Roanoke",
    "sg:classifiers":[
        {
            "category":"Retail",
            "subcategory":"Auto Repair",
            "type":"Services"
        }
    ],
    "sg:phone":"+1 540 345 1290",
    "sg:postcode":"24018",
    "sg:province":"VA",
    "sg:tags":[
        "automotive"
    ],
    "wof:name":"Magic Lube",
    "wof:placetype":"venue"
},
  "geometry": {"coordinates":[-79.989581,37.219052],"type":"Point"}
}