{
  "type": "Feature",
  "properties": {
    "addr:full":"418 Mowbray Arch Norfolk VA 23507",
    "addr:housenumber":"418",
    "addr:postcode":"23507",
    "addr:street":"Mowbray Arch",
    "iso:country":"US",
    "sg:address":"418 Mowbray Arch",
    "sg:city":"Norfolk",
    "sg:classifiers":[
        {
            "category":"Personal",
            "type":"Services"
        }
    ],
    "sg:phone":"+1 757 623 0400",
    "sg:postcode":"23507",
    "sg:province":"VA",
    "sg:tags":[
        "control",
        "weight"
    ],
    "wof:name":"Herbalife",
    "wof:placetype":"venue"
},
  "geometry": {"coordinates":[-76.296622,36.855486],"type":"Point"}
}