{
  "type": "Feature",
  "properties": {
    "addr:full":"2100 Ardmore Ave Chesapeake VA 23324",
    "addr:housenumber":"2100",
    "addr:postcode":"23324",
    "addr:street":"Ardmore Ave",
    "iso:country":"US",
    "sg:address":"2100 Ardmore Ave",
    "sg:city":"Chesapeake",
    "sg:classifiers":[
        {
            "category":"Professional",
            "type":"Services"
        }
    ],
    "sg:phone":"+1 757 545 1656",
    "sg:postcode":"23324",
    "sg:province":"VA",
    "wof:name":"Luther F Lewis",
    "wof:placetype":"venue"
},
  "geometry": {"coordinates":[-76.26853199999999,36.803086],"type":"Point"}
}