{
  "type": "Feature",
  "properties": {
    "addr:full":"800 Professional Pl W Chesapeake VA 23320",
    "addr:housenumber":"800",
    "addr:postcode":"23320",
    "addr:street":"Professional Pl W",
    "iso:country":"US",
    "sg:address":"800 Professional Pl W",
    "sg:city":"Chesapeake",
    "sg:classifiers":[
        {
            "category":"Retail",
            "subcategory":"Auto Rental",
            "type":"Services"
        },
        {
            "category":"Building & Trades",
            "subcategory":"Construction",
            "type":"Services"
        },
        {
            "category":"Professional",
            "subcategory":"Business Services",
            "type":"Services"
        },
        {
            "category":"Retail",
            "subcategory":"Storage",
            "type":"Services"
        },
        {
            "category":"Manufacturing",
            "subcategory":"Buildings",
            "type":"Manufacturing & Wholesale Goods"
        },
        {
            "category":"Building & Trades",
            "subcategory":"Equipment Rental",
            "type":"Services"
        }
    ],
    "sg:phone":"+1 757 548 3125",
    "sg:postcode":"23320",
    "sg:province":"VA",
    "sg:tags":[
        "renting",
        "leasing",
        "modular",
        "mobile",
        "household",
        "commercial",
        "prefabricated",
        "buildings-pre-cut",
        "buildings-portable",
        "trailer",
        "unit",
        "contractors'"
    ],
    "sg:website":"http://www.willscot.com",
    "wof:name":"Williams Scotsman Norfolk",
    "wof:placetype":"venue"
},
  "geometry": {"coordinates":[-76.23458100000001,36.759892],"type":"Point"}
}