{
  "type": "Feature",
  "properties": {
    "iso:country":"US",
    "sg:address":"334 Commerce St",
    "sg:city":"Alexandria",
    "sg:classifiers":[
        {
            "category":"Professional",
            "subcategory":"Management & Consulting",
            "type":"Services"
        }
    ],
    "sg:phone":"+1 703 535 3179",
    "sg:postcode":"22314",
    "sg:province":"VA",
    "sg:tags":[
        "consultant"
    ],
    "sg:website":"http://www.nuchemco.com",
    "wof:name":"Nuchemco Inc",
    "wof:placetype":"venue"
},
  "geometry": {"coordinates":[-77.055403,38.804812],"type":"Point"}
}