{
  "type": "Feature",
  "properties": {
    "addr:full":"6737 Arlington Blvd Falls Church VA 22042",
    "addr:housenumber":"6737",
    "addr:postcode":"22042",
    "addr:street":"Arlington Blvd",
    "iso:country":"US",
    "sg:address":"6737 Arlington Blvd",
    "sg:city":"Falls Church",
    "sg:classifiers":[
        {
            "category":"Professional",
            "subcategory":"Accounting & Tax Preparation",
            "type":"Services"
        }
    ],
    "sg:phone":"+1 703 536 2158",
    "sg:postcode":"22042",
    "sg:province":"VA",
    "wof:name":"CPA Ann LLC Tran",
    "wof:placetype":"venue"
},
  "geometry": {"coordinates":[-77.177279,38.869186],"type":"Point"}
}