{
  "type": "Feature",
  "properties": {
    "iso:country":"US",
    "sg:address":"711 Belair Ave",
    "sg:city":"Front Royal",
    "sg:classifiers":[
        {
            "category":"Building & Trades",
            "subcategory":"Equipment Rental",
            "type":"Services"
        }
    ],
    "sg:phone":"+1 540 635 3789",
    "sg:postcode":"22630",
    "sg:province":"VA",
    "sg:tags":[
        "light",
        "construction",
        "sale"
    ],
    "wof:name":"D & P Rental",
    "wof:placetype":"venue"
},
  "geometry": {"coordinates":[-78.18653500000001,38.929212],"type":"Point"}
}