{
  "type": "Feature",
  "properties": {
    "addr:full":"628 Oriole St Bluefield VA 24605",
    "addr:housenumber":"628",
    "addr:postcode":"24605",
    "addr:street":"Oriole St",
    "iso:country":"US",
    "sg:address":"628 Oriole St",
    "sg:city":"Bluefield",
    "sg:classifiers":[
        {
            "category":"Professional",
            "subcategory":"Printing & Photocopies",
            "type":"Services"
        }
    ],
    "sg:phone":"+1 276 322 3556",
    "sg:postcode":"24605",
    "sg:province":"VA",
    "sg:tags":[
        "duplicating",
        "copying"
    ],
    "wof:name":"Imagine That LLC",
    "wof:placetype":"venue"
},
  "geometry": {"coordinates":[-81.286512,37.225387],"type":"Point"}
}