{
  "type": "Feature",
  "properties": {
    "addr:full":"7758 Wolford Way Lorton VA 22079",
    "addr:housenumber":"7758",
    "addr:postcode":"22079",
    "addr:street":"Wolford Way",
    "iso:country":"US",
    "sg:address":"7758 Wolford Way",
    "sg:city":"Lorton",
    "sg:classifiers":[
        {
            "category":"Personal",
            "subcategory":"Beauty Salon",
            "type":"Services"
        }
    ],
    "sg:phone":"+1 703 550 9329",
    "sg:postcode":"22079",
    "sg:province":"VA",
    "sg:tags":[
        "shop"
    ],
    "wof:name":"Beauty Mark",
    "wof:placetype":"venue"
},
  "geometry": {"coordinates":[-77.207375,38.71368],"type":"Point"}
}