{
  "type": "Feature",
  "properties": {
    "addr:full":"16 Lee Ave Lexington VA 24450",
    "addr:housenumber":"16",
    "addr:postcode":"24450",
    "addr:street":"Lee Ave",
    "iso:country":"US",
    "sg:address":"16 Lee Ave",
    "sg:city":"Lexington",
    "sg:classifiers":[
        {
            "category":"Food & Beverages",
            "subcategory":"Bakery",
            "type":"Retail Goods"
        }
    ],
    "sg:phone":"+1 540 463 6546",
    "sg:postcode":"24450",
    "sg:province":"VA",
    "sg:tags":[
        "baker"
    ],
    "wof:name":"Blue Sky Bakery",
    "wof:placetype":"venue"
},
  "geometry": {"coordinates":[-79.443561,37.785973],"type":"Point"}
}