{
  "type": "Feature",
  "properties": {
    "addr:full":"7700 Richmond Hwy Alexandria VA 22306",
    "addr:housenumber":"7700",
    "addr:postcode":"22306",
    "addr:street":"Richmond Hwy",
    "iso:country":"US",
    "sg:address":"7700 Richmond Hwy",
    "sg:city":"Alexandria",
    "sg:classifiers":[
        {
            "category":"Shopping",
            "subcategory":"Computers & Home Electronics",
            "type":"Retail Goods"
        }
    ],
    "sg:phone":"+1 703 780 0402",
    "sg:postcode":"22306",
    "sg:province":"VA",
    "sg:tags":[
        "equipment",
        "consumer",
        "electronic",
        "supply"
    ],
    "wof:name":"Radio Shack",
    "wof:placetype":"venue"
},
  "geometry": {"coordinates":[-77.08318,38.747767],"type":"Point"}
}