{
  "type": "Feature",
  "properties": {
    "iso:country":"US",
    "sg:address":"605 Glendale Rd",
    "sg:city":"Galax",
    "sg:classifiers":[
        {
            "category":"Health Services",
            "subcategory":"Podiatrist",
            "type":"Services"
        }
    ],
    "sg:phone":"+1 276 236 9591",
    "sg:postcode":"24333",
    "sg:province":"VA",
    "wof:name":"Roderick A Cox DPM",
    "wof:placetype":"venue"
},
  "geometry": {"coordinates":[-80.917768,36.672378],"type":"Point"}
}