{
  "type": "Feature",
  "properties": {
    "addr:full":"820 Caroline St Fredericksburg VA 22401",
    "addr:housenumber":"820",
    "addr:postcode":"22401",
    "addr:street":"Caroline St",
    "iso:country":"US",
    "sg:address":"820 Caroline St",
    "sg:city":"Fredericksburg",
    "sg:classifiers":[
        {
            "category":"Shopping",
            "subcategory":"Shoes",
            "type":"Retail Goods"
        }
    ],
    "sg:phone":"+1 540 899 6040",
    "sg:postcode":"22401",
    "sg:province":"VA",
    "wof:name":"Comfort One Shoes",
    "wof:placetype":"venue"
},
  "geometry": {"coordinates":[-77.458758,38.302156],"type":"Point"}
}