{
  "type": "Feature",
  "properties": {
    "iso:country":"US",
    "sg:address":"6907 Marble Hill Dr",
    "sg:city":"Spotsylvania",
    "sg:classifiers":[
        {
            "category":"Building & Trades",
            "subcategory":"Construction",
            "type":"Services"
        }
    ],
    "sg:phone":"+1 540 582 3972",
    "sg:postcode":"22553",
    "sg:province":"VA",
    "sg:tags":[
        "waterproofing",
        "contractor"
    ],
    "wof:name":"Spotsylvania Caulking",
    "wof:placetype":"venue"
},
  "geometry": {"coordinates":[-77.568806,38.147795],"type":"Point"}
}