{
  "type": "Feature",
  "properties": {
    "iso:country":"US",
    "sg:address":"29 Wildwood Rd",
    "sg:city":"Salem",
    "sg:classifiers":[
        {
            "category":"Retail",
            "subcategory":"Veterinary Services",
            "type":"Services"
        }
    ],
    "sg:phone":"+1 540 375 0350",
    "sg:postcode":"24153",
    "sg:province":"VA",
    "sg:tags":[
        "hospital",
        "animal"
    ],
    "wof:name":"Companion Pet Care Clinic LLC",
    "wof:placetype":"venue"
},
  "geometry": {"coordinates":[-80.09520500000001,37.288585],"type":"Point"}
}