{
  "type": "Feature",
  "properties": {
    "addr:full":"6913 Rannoch Rd Bethesda MD 20817",
    "addr:housenumber":"6913",
    "addr:postcode":"20817",
    "addr:street":"Rannoch Rd",
    "iso:country":"US",
    "sg:address":"6913 Rannoch Rd",
    "sg:city":"Bethesda",
    "sg:classifiers":[
        {
            "category":"Professional",
            "subcategory":"Lawyer & Legal Services",
            "type":"Services"
        }
    ],
    "sg:phone":"+1 301 229 4439",
    "sg:postcode":"20817",
    "sg:province":"MD",
    "wof:name":"Gregg John P & Tredway Lo",
    "wof:placetype":"venue"
},
  "geometry": {"coordinates":[-77.135839,38.972925],"type":"Point"}
}