{
  "type": "Feature",
  "properties": {
    "iso:country":"US",
    "sg:address":"21115 Blue Bill Ct",
    "sg:city":"Ashburn",
    "sg:classifiers":[
        {
            "category":"Building & Trades",
            "subcategory":"Construction",
            "type":"Services"
        }
    ],
    "sg:phone":"+1 703 729 2832",
    "sg:postcode":"20147",
    "sg:province":"VA",
    "sg:tags":[
        "hanging",
        "contractor"
    ],
    "wof:name":"That Finishing Touch",
    "wof:placetype":"venue"
},
  "geometry": {"coordinates":[-77.488367,39.03223],"type":"Point"}
}