{
  "type": "Feature",
  "properties": {
    "addr:full":"14821 Lee Hwy Centreville VA 20121",
    "addr:housenumber":"14821",
    "addr:postcode":"20121",
    "addr:street":"Lee Hwy",
    "iso:country":"US",
    "sg:address":"14821 Lee Hwy",
    "sg:city":"Centreville",
    "sg:classifiers":[
        {
            "category":"Organizations",
            "subcategory":"Religious Organization",
            "type":"Services"
        }
    ],
    "sg:phone":"+1 703 830 1841",
    "sg:postcode":"20121",
    "sg:province":"VA",
    "sg:tags":[
        "church"
    ],
    "wof:name":"Centreville Assembly Of God",
    "wof:placetype":"venue"
},
  "geometry": {"coordinates":[-77.45891,38.834236],"type":"Point"}
}