{
  "type": "Feature",
  "properties": {
    "iso:country":"US",
    "sg:address":"1130 Cambria St NW",
    "sg:city":"Christiansburg",
    "sg:classifiers":[
        {
            "category":"Food & Beverages",
            "subcategory":"Groceries & Convenience Stores",
            "type":"Retail Goods"
        }
    ],
    "sg:phone":"+1 540 382 2691",
    "sg:postcode":"24073",
    "sg:province":"VA",
    "wof:name":"Deli Mart 65",
    "wof:placetype":"venue"
},
  "geometry": {"coordinates":[-80.43339,37.151286],"type":"Point"}
}