{
  "type": "Feature",
  "properties": {
    "addr:full":"3914 Kecoughtan Rd Hampton VA 23669",
    "addr:housenumber":"3914",
    "addr:postcode":"23669",
    "addr:street":"Kecoughtan Rd",
    "iso:country":"US",
    "sg:address":"3914 Kecoughtan Rd",
    "sg:city":"Hampton",
    "sg:classifiers":[
        {
            "category":"Building & Trades",
            "subcategory":"Construction",
            "type":"Services"
        }
    ],
    "sg:phone":"+1 757 722 5666",
    "sg:postcode":"23669",
    "sg:province":"VA",
    "sg:tags":[
        "contracting",
        "general"
    ],
    "wof:name":"Hunt Construction Company",
    "wof:placetype":"venue"
},
  "geometry": {"coordinates":[-76.352954,37.011331],"type":"Point"}
}