{
  "type": "Feature",
  "properties": {
    "iso:country":"US",
    "sg:address":"208 Hodges Manor Rd",
    "sg:city":"Portsmouth",
    "sg:classifiers":[
        {
            "category":"Building & Trades",
            "subcategory":"Landscaping Services",
            "type":"Services"
        }
    ],
    "sg:phone":"+1 757 488 1956",
    "sg:postcode":"23701",
    "sg:province":"VA",
    "sg:tags":[
        "landscape",
        "contractor"
    ],
    "wof:name":"Green Grows Irrgtn & Landscpg",
    "wof:placetype":"venue"
},
  "geometry": {"coordinates":[-76.38832600000001,36.818377],"type":"Point"}
}