{
  "type": "Feature",
  "properties": {
    "addr:full":"1603 S Meadow St Richmond VA 23220",
    "addr:housenumber":"1603",
    "addr:postcode":"23220",
    "addr:street":"S Meadow St",
    "iso:country":"US",
    "sg:address":"1603 S Meadow St",
    "sg:city":"Richmond",
    "sg:classifiers":[
        {
            "category":"Professional",
            "subcategory":"Business Services",
            "type":"Services"
        }
    ],
    "sg:phone":"+1 804 355 1271",
    "sg:postcode":"23220",
    "sg:province":"VA",
    "sg:tags":[
        "design",
        "bicycle",
        "assembly",
        "custom"
    ],
    "wof:name":"Gee-Dub Custom Bikes",
    "wof:placetype":"venue"
},
  "geometry": {"coordinates":[-77.47314299999999,37.534106],"type":"Point"}
}