{
  "type": "Feature",
  "properties": {
    "addr:full":"5326 Chamberlayne Ave Richmond VA 23227",
    "addr:housenumber":"5326",
    "addr:postcode":"23227",
    "addr:street":"Chamberlayne Ave",
    "iso:country":"US",
    "sg:address":"5326 Chamberlayne Ave",
    "sg:city":"Richmond",
    "sg:classifiers":[
        {
            "category":"Shopping",
            "subcategory":"Used Merchandise",
            "type":"Retail Goods"
        }
    ],
    "sg:phone":"+1 804 261 0091",
    "sg:postcode":"23227",
    "sg:province":"VA",
    "wof:name":"Goodwill Stores",
    "wof:placetype":"venue"
},
  "geometry": {"coordinates":[-77.454397,37.615634],"type":"Point"}
}