{
  "type": "Feature",
  "properties": {
    "addr:full":"3244 Pineland Rd SW Roanoke VA 24018",
    "addr:housenumber":"3244",
    "addr:postcode":"24018",
    "addr:street":"Pineland Rd Sw",
    "iso:country":"US",
    "sg:address":"3244 Pineland Rd SW",
    "sg:city":"Roanoke",
    "sg:classifiers":[
        {
            "category":"Professional",
            "type":"Services"
        }
    ],
    "sg:phone":"+1 540 774 3871",
    "sg:postcode":"24018",
    "sg:province":"VA",
    "wof:name":"Homeqwners Assoc of Summ",
    "wof:placetype":"venue"
},
  "geometry": {"coordinates":[-80.00631300000001,37.25402],"type":"Point"}
}