{
  "type": "Feature",
  "properties": {
    "addr:full":"205 N Main St Bridgewater VA 22812",
    "addr:housenumber":"205",
    "addr:postcode":"22812",
    "addr:street":"N Main St",
    "iso:country":"US",
    "sg:address":"205 N Main St",
    "sg:city":"Bridgewater",
    "sg:classifiers":[
        {
            "category":"Personal",
            "subcategory":"Beauty Salon",
            "type":"Services"
        }
    ],
    "sg:phone":"+1 540 828 2222",
    "sg:postcode":"22812",
    "sg:province":"VA",
    "sg:tags":[
        "shop",
        "merchandise"
    ],
    "wof:name":"Nan's New Look Beauty Salon",
    "wof:placetype":"venue"
},
  "geometry": {"coordinates":[-78.974988,38.38376],"type":"Point"}
}