{
  "type": "Feature",
  "properties": {
    "addr:full":"1495 Chain Bridge Rd Mc Lean VA 22101",
    "addr:housenumber":"1495",
    "addr:postcode":"22101",
    "addr:street":"Chain Bridge Rd Mc Lean",
    "iso:country":"US",
    "sg:address":"1495 Chain Bridge Rd",
    "sg:city":"Mc Lean",
    "sg:classifiers":[
        {
            "category":"Professional",
            "type":"Services"
        }
    ],
    "sg:phone":"+1 571 633 9798",
    "sg:postcode":"22101",
    "sg:province":"VA",
    "wof:name":"Phillip L Rosenblum Lcsw",
    "wof:placetype":"venue"
},
  "geometry": {"coordinates":[-77.18055099999999,38.93154],"type":"Point"}
}