{
  "type": "Feature",
  "properties": {
    "addr:full":"13873 Park Center Rd Suite 137 Herndon VA 20171",
    "addr:housenumber":"13873",
    "addr:postcode":"20171",
    "addr:street":"Park Center Rd Suite 137",
    "iso:country":"US",
    "sg:address":"13873 Park Center Rd Suite 137",
    "sg:city":"Herndon",
    "sg:classifiers":[
        {
            "category":"Health Services",
            "subcategory":"Dentist",
            "type":"Services"
        }
    ],
    "sg:phone":"+1 877 267 3921",
    "sg:postcode":"20171",
    "sg:province":"VA",
    "sg:tags":[
        "dentists-orthodontists",
        "dental",
        "clinic",
        "dentists-pediatric",
        "dentistry"
    ],
    "sg:website":"http://www-brightnow-com.netsolads.com/?_nsag=32924",
    "wof:name":"Mazin Alayssami, DMD & Associates",
    "wof:placetype":"venue"
},
  "geometry": {"coordinates":[-77.42597499999999,38.932833],"type":"Point"}
}