{
  "type": "Feature",
  "properties": {
    "addr:full":"706 Duke St Alexandria VA 22314",
    "addr:housenumber":"706",
    "addr:postcode":"22314",
    "addr:street":"Duke St",
    "iso:country":"US",
    "sg:address":"706 Duke St",
    "sg:city":"Alexandria",
    "sg:classifiers":[
        {
            "category":"Social Services",
            "type":"Services"
        }
    ],
    "sg:phone":"+1 703 518 8883",
    "sg:postcode":"22314",
    "sg:province":"VA",
    "sg:tags":[
        "counselor",
        "marriage",
        "family"
    ],
    "sg:website":"www.robynbrickel.com",
    "wof:name":"Robyn E Brickel",
    "wof:placetype":"venue"
},
  "geometry": {"coordinates":[-77.048557,38.802844],"type":"Point"}
}