{
  "type": "Feature",
  "properties": {
    "addr:full":"12068 Linda Pl Manassas VA 20112",
    "addr:housenumber":"12068",
    "addr:postcode":"20112",
    "addr:street":"Linda Pl",
    "iso:country":"US",
    "sg:address":"12068 Linda Pl",
    "sg:city":"Manassas",
    "sg:classifiers":[
        {
            "category":"Communications",
            "subcategory":"Film & Video Production",
            "type":"Services"
        }
    ],
    "sg:phone":"+1 703 794 1000",
    "sg:postcode":"20112",
    "sg:province":"VA",
    "wof:name":"Wag The Dog Productions Inc",
    "wof:placetype":"venue"
},
  "geometry": {"coordinates":[-77.456766,38.693096],"type":"Point"}
}