{
  "type": "Feature",
  "properties": {
    "iso:country":"US",
    "sg:address":"1201 S Barton St Unit 155",
    "sg:city":"Arlington",
    "sg:classifiers":[
        {
            "category":"Cinema",
            "subcategory":"Movie Rental",
            "type":"Entertainment"
        }
    ],
    "sg:phone":"+1 703 271 7150",
    "sg:postcode":"22204",
    "sg:province":"VA",
    "sg:tags":[
        "picture",
        "exchange",
        "motion",
        "distributor",
        "film"
    ],
    "wof:name":"W&H Productions",
    "wof:placetype":"venue"
},
  "geometry": {"coordinates":[-77.08301899999999,38.860547],"type":"Point"}
}