{
  "type": "Feature",
  "properties": {
    "addr:full":"5519 Lakeside Ave Richmond VA 23228",
    "addr:housenumber":"5519",
    "addr:postcode":"23228",
    "addr:street":"Lakeside Ave",
    "iso:country":"US",
    "sg:address":"5519 Lakeside Ave",
    "sg:city":"Richmond",
    "sg:classifiers":[
        {
            "category":"Retail",
            "subcategory":"Auto Repair",
            "type":"Services"
        }
    ],
    "sg:phone":"+1 804 266 4204",
    "sg:postcode":"23228",
    "sg:province":"VA",
    "sg:tags":[
        "general"
    ],
    "wof:name":"DMS Parts",
    "wof:placetype":"venue"
},
  "geometry": {"coordinates":[-77.467445,37.605498],"type":"Point"}
}