{
  "type": "Feature",
  "properties": {
    "iso:country":"US",
    "sg:address":"6164 A L Philpott Hwy",
    "sg:city":"Martinsville",
    "sg:classifiers":[
        {
            "category":"Banks & Credit Unions",
            "subcategory":"Bank",
            "type":"Services"
        }
    ],
    "sg:phone":"+1 276 632 1753",
    "sg:postcode":"24112",
    "sg:province":"VA",
    "wof:name":"Patrick Henry National Bank",
    "wof:placetype":"venue"
},
  "geometry": {"coordinates":[-79.79194200000001,36.681471],"type":"Point"}
}