{
  "type": "Feature",
  "properties": {
    "iso:country":"US",
    "sg:address":"1110 E Stuart Dr",
    "sg:city":"Galax",
    "sg:classifiers":[
        {
            "category":"Real Estate",
            "subcategory":"Real Estate Agent",
            "type":"Services"
        }
    ],
    "sg:phone":"+1 276 236 5171",
    "sg:postcode":"24333",
    "sg:province":"VA",
    "sg:website":"www.coxrealty-auction.com",
    "wof:name":"Cox Realty & Auction",
    "wof:placetype":"venue"
},
  "geometry": {"coordinates":[-80.878337,36.692464],"type":"Point"}
}