{
  "type": "Feature",
  "properties": {
    "addr:full":"23020 Eaglewood Ct Sterling VA 20166",
    "addr:postcode":"23020;20166",
    "addr:street":"Eaglewood Ct",
    "iso:country":"US",
    "sg:address":"23020 Eaglewood Ct",
    "sg:city":"Sterling",
    "sg:classifiers":[
        {
            "category":"Building & Trades",
            "subcategory":"Equipment Rental",
            "type":"Services"
        }
    ],
    "sg:phone":"+1 703 742 4000",
    "sg:postcode":"20166",
    "sg:province":"VA",
    "sg:tags":[
        "leasing"
    ],
    "sg:website":"www.ltidata.com",
    "wof:name":"Leasing Technolgies Inc",
    "wof:placetype":"venue"
},
  "geometry": {"coordinates":[-77.447836,38.978933],"type":"Point"}
}