{
  "type": "Feature",
  "properties": {
    "iso:country":"US",
    "sg:address":"10690 Crestwood Dr Ste A",
    "sg:city":"Manassas",
    "sg:classifiers":[
        {
            "category":"Building & Trades",
            "subcategory":"Cleaning & Sanitation",
            "type":"Services"
        }
    ],
    "sg:phone":"+1 703 369 5555",
    "sg:postcode":"20109",
    "sg:province":"VA",
    "sg:tags":[
        "home"
    ],
    "wof:name":"Merry Maids",
    "wof:placetype":"venue"
},
  "geometry": {"coordinates":[-77.512901,38.779099],"type":"Point"}
}