{
  "type": "Feature",
  "properties": {
    "iso:country":"US",
    "sg:address":"6609 Cottonwood Dr",
    "sg:city":"Alexandria",
    "sg:classifiers":[
        {
            "category":"Building & Trades",
            "subcategory":"Cleaning & Sanitation",
            "type":"Services"
        }
    ],
    "sg:phone":"+1 703 971 7160",
    "sg:postcode":"22310",
    "sg:province":"VA",
    "sg:tags":[
        "house"
    ],
    "sg:website":"http://www.evercleanmaids.com",
    "wof:name":"Everclean Maid Service",
    "wof:placetype":"venue"
},
  "geometry": {"coordinates":[-77.113974,38.773777],"type":"Point"}
}