{
  "type": "Feature",
  "properties": {
    "addr:full":"3014 Memorial Ave Lynchburg VA 24501",
    "addr:housenumber":"3014",
    "addr:postcode":"24501",
    "addr:street":"Memorial Ave",
    "iso:country":"US",
    "sg:address":"3014 Memorial Ave",
    "sg:city":"Lynchburg",
    "sg:classifiers":[
        {
            "category":"Shopping",
            "subcategory":"Bicycles & Sporting Goods",
            "type":"Retail Goods"
        }
    ],
    "sg:phone":"+1 434 845 6107",
    "sg:postcode":"24501",
    "sg:province":"VA",
    "wof:name":"American Fitness & Tanning Ctr",
    "wof:placetype":"venue"
},
  "geometry": {"coordinates":[-79.170191,37.397574],"type":"Point"}
}