{
  "type": "Feature",
  "properties": {
    "iso:country":"US",
    "sg:address":"241 Fort Evans Rd NE",
    "sg:city":"Leesburg",
    "sg:classifiers":[
        {
            "category":"Shopping",
            "subcategory":"Shoes",
            "type":"Retail Goods"
        }
    ],
    "sg:phone":"+1 703 669 9590",
    "sg:postcode":"20176",
    "sg:province":"VA",
    "sg:website":"www.donaldjpliner.com",
    "wof:name":"Donald J Pliner Outlet",
    "wof:placetype":"venue"
},
  "geometry": {"coordinates":[-77.538246,39.110385],"type":"Point"}
}