{
  "type": "Feature",
  "properties": {
    "addr:full":"4198 Cox Rd Glen Allen VA 23060",
    "addr:housenumber":"4198",
    "addr:postcode":"23060",
    "addr:street":"Cox Rd",
    "iso:country":"US",
    "sg:address":"4198 Cox Rd",
    "sg:city":"Glen Allen",
    "sg:classifiers":[
        {
            "category":"Professional",
            "subcategory":"Employment Agencies",
            "type":"Services"
        }
    ],
    "sg:phone":"+1 804 290 0799",
    "sg:postcode":"23060",
    "sg:province":"VA",
    "sg:tags":[
        "opportunity"
    ],
    "wof:name":"Sedona Staffing Svc",
    "wof:placetype":"venue"
},
  "geometry": {"coordinates":[-77.582264,37.648931],"type":"Point"}
}