{
  "type": "Feature",
  "properties": {
    "addr:full":"10208 Staples Mill Rd Glen Allen VA 23060",
    "addr:housenumber":"10208",
    "addr:postcode":"23060",
    "addr:street":"Staples Mill Rd",
    "iso:country":"US",
    "sg:address":"10208 Staples Mill Rd",
    "sg:city":"Glen Allen",
    "sg:classifiers":[
        {
            "category":"Bakery",
            "type":"Food & Drink"
        }
    ],
    "sg:menulink":"http://www.allmenus.com/va/brookland/224062-cinnabon/menu/",
    "sg:phone":"+1 804 756 6004",
    "sg:postcode":"23060",
    "sg:province":"VA",
    "sg:tags":[
        "american",
        "pastry"
    ],
    "wof:name":"Cinnabon",
    "wof:placetype":"venue"
},
  "geometry": {"coordinates":[-77.523939,37.657402],"type":"Point"}
}