{
  "type": "Feature",
  "properties": {
    "iso:country":"US",
    "sg:address":"231 28th St",
    "sg:city":"Newport News",
    "sg:classifiers":[
        {
            "category":"Airline",
            "type":"Transportation"
        }
    ],
    "sg:phone":"+1 757 244 5004",
    "sg:postcode":"23607",
    "sg:province":"VA",
    "sg:tags":[
        "cargo",
        "air"
    ],
    "wof:name":"Landstar Express America Inc",
    "wof:placetype":"venue"
},
  "geometry": {"coordinates":[-76.43024699999999,36.980221],"type":"Point"}
}