{
  "type": "Feature",
  "properties": {
    "iso:country":"US",
    "sg:address":"84 Tardy Mountain Rd",
    "sg:city":"Altavista",
    "sg:classifiers":[
        {
            "category":"Wholesale",
            "subcategory":"Construction Materials",
            "type":"Manufacturing & Wholesale Goods"
        }
    ],
    "sg:phone":"+1 434 369 5429",
    "sg:postcode":"24517",
    "sg:province":"VA",
    "sg:tags":[
        "retail",
        "lumber"
    ],
    "wof:name":"Dalton Lumber Corporation",
    "wof:placetype":"venue"
},
  "geometry": {"coordinates":[-79.266453,37.145856],"type":"Point"}
}