{
  "type": "Feature",
  "properties": {
    "iso:country":"US",
    "sg:address":"2408 Laguard Dr",
    "sg:city":"Hampton",
    "sg:classifiers":[
        {
            "category":"Building & Trades",
            "subcategory":"Construction",
            "type":"Services"
        }
    ],
    "sg:phone":"+1 757 727 9253",
    "sg:postcode":"23661",
    "sg:province":"VA",
    "sg:tags":[
        "concrete",
        "contractor"
    ],
    "wof:name":"Phillip Davis Concrete Cnstr",
    "wof:placetype":"venue"
},
  "geometry": {"coordinates":[-76.38060299999999,37.006722],"type":"Point"}
}