{
  "type": "Feature",
  "properties": {
    "addr:full":"2516 Logan Wood Dr Herndon VA 20171",
    "addr:housenumber":"2516",
    "addr:postcode":"20171",
    "addr:street":"Logan Wood Dr",
    "iso:country":"US",
    "sg:address":"2516 Logan Wood Dr",
    "sg:city":"Herndon",
    "sg:classifiers":[
        {
            "category":"Professional",
            "subcategory":"Computer Services",
            "type":"Services"
        }
    ],
    "sg:phone":"+1 703 921 1249",
    "sg:postcode":"20171",
    "sg:province":"VA",
    "sg:tags":[
        "programing",
        "custom"
    ],
    "wof:name":"Samuel Sarpong",
    "wof:placetype":"venue"
},
  "geometry": {"coordinates":[-77.410065,38.945221],"type":"Point"}
}