{
  "type": "Feature",
  "properties": {
    "addr:full":"2720 Timber Rd Shawsville VA 24162",
    "addr:housenumber":"2720",
    "addr:postcode":"24162",
    "addr:street":"Timber Rd",
    "iso:country":"US",
    "sg:address":"2720 Timber Rd",
    "sg:city":"Shawsville",
    "sg:classifiers":[
        {
            "category":"Shopping",
            "subcategory":"Gifts & Souvenirs",
            "type":"Retail Goods"
        }
    ],
    "sg:phone":"+1 540 268 1684",
    "sg:postcode":"24162",
    "sg:province":"VA",
    "wof:name":"Graffiti Graphics",
    "wof:placetype":"venue"
},
  "geometry": {"coordinates":[-80.268564,37.098925],"type":"Point"}
}