{
  "type": "Feature",
  "properties": {
    "addr:full":"2405 Carey Ln Vienna VA 22181",
    "addr:housenumber":"2405",
    "addr:postcode":"22181",
    "addr:street":"Carey Ln",
    "iso:country":"US",
    "sg:address":"2405 Carey Ln",
    "sg:city":"Vienna",
    "sg:classifiers":[
        {
            "category":"Professional",
            "subcategory":"Management & Consulting",
            "type":"Services"
        }
    ],
    "sg:phone":"+1 703 281 5170",
    "sg:postcode":"22181",
    "sg:province":"VA",
    "wof:name":"Railroad Management Services",
    "wof:placetype":"venue"
},
  "geometry": {"coordinates":[-77.284068,38.899061],"type":"Point"}
}