{
  "type": "Feature",
  "properties": {
    "addr:full":"14700 Flint Lee Rd Chantilly VA 20151",
    "addr:housenumber":"14700",
    "addr:postcode":"20151",
    "addr:street":"Flint Lee Rd",
    "iso:country":"US",
    "sg:address":"14700 Flint Lee Rd",
    "sg:city":"Chantilly",
    "sg:classifiers":[
        {
            "category":"Manufacturing",
            "subcategory":"Printing",
            "type":"Manufacturing & Wholesale Goods"
        }
    ],
    "sg:phone":"+1 703 378 8660",
    "sg:postcode":"20151",
    "sg:province":"VA",
    "sg:tags":[
        "lithographic",
        "commercial"
    ],
    "wof:name":"Bruce Moore Printing Co",
    "wof:placetype":"venue"
},
  "geometry": {"coordinates":[-77.45643800000001,38.894185],"type":"Point"}
}