{
  "type": "Feature",
  "properties": {
    "addr:full":"350 Effingham St Portsmouth VA 23704",
    "addr:housenumber":"350",
    "addr:postcode":"23704",
    "addr:street":"Effingham St",
    "iso:country":"US",
    "sg:address":"350 Effingham St",
    "sg:city":"Portsmouth",
    "sg:classifiers":[
        {
            "category":"Restaurant",
            "type":"Food & Drink"
        }
    ],
    "sg:menulink":"http://www.allmenus.com/va/portsmouth/13053-churchs-chicken/menu/",
    "sg:phone":"+1 757 397 8852",
    "sg:postcode":"23704",
    "sg:province":"VA",
    "sg:tags":[
        "chicken",
        "wing"
    ],
    "wof:name":"Church's Chicken",
    "wof:placetype":"venue"
},
  "geometry": {"coordinates":[-76.307061,36.838226],"type":"Point"}
}