{
  "type": "Feature",
  "properties": {
    "iso:country":"US",
    "sg:address":"29 Reynolds Dr",
    "sg:city":"Front Royal",
    "sg:classifiers":[
        {
            "category":"Retail",
            "subcategory":"Repair Shop",
            "type":"Services"
        }
    ],
    "sg:phone":"+1 540 622 6983",
    "sg:postcode":"22630",
    "sg:province":"VA",
    "sg:tags":[
        "related"
    ],
    "wof:name":"M T Ball Plumbing & Home Rpr",
    "wof:placetype":"venue"
},
  "geometry": {"coordinates":[-78.059712,38.973626],"type":"Point"}
}