{
  "type": "Feature",
  "properties": {
    "iso:country":"US",
    "sg:address":"3543 W Braddock Rd Ste E1",
    "sg:city":"Alexandria",
    "sg:classifiers":[
        {
            "category":"Health Services",
            "subcategory":"Dentist",
            "type":"Services"
        }
    ],
    "sg:phone":"+1 703 931 6600",
    "sg:postcode":"22302",
    "sg:province":"VA",
    "wof:name":"Kotler Lawrence DDS Ms",
    "wof:placetype":"venue"
},
  "geometry": {"coordinates":[-77.090288,38.82726],"type":"Point"}
}