{
  "type": "Feature",
  "properties": {
    "addr:full":"2261 Shadow Lake Ct Virginia Beach VA 23454",
    "addr:housenumber":"2261",
    "addr:postcode":"23454",
    "addr:street":"Shadow Lake Ct",
    "iso:country":"US",
    "sg:address":"2261 Shadow Lake Ct",
    "sg:city":"Virginia Beach",
    "sg:classifiers":[
        {
            "category":"Real Estate",
            "subcategory":"Real Estate Operator",
            "type":"Services"
        }
    ],
    "sg:phone":"+1 757 481 3116",
    "sg:postcode":"23454",
    "sg:province":"VA",
    "sg:tags":[
        "property",
        "lessor"
    ],
    "wof:name":"Delaura Property",
    "wof:placetype":"venue"
},
  "geometry": {"coordinates":[-76.046528,36.869879],"type":"Point"}
}