{
  "type": "Feature",
  "properties": {
    "addr:full":"1513 Willow St Big Stone Gap VA 24219",
    "addr:housenumber":"1513",
    "addr:postcode":"24219",
    "addr:street":"Willow St",
    "iso:country":"US",
    "sg:address":"1513 Willow St",
    "sg:city":"Big Stone Gap",
    "sg:classifiers":[
        {
            "category":"Freight",
            "type":"Transportation"
        }
    ],
    "sg:phone":"+1 276 523 1556",
    "sg:postcode":"24219",
    "sg:province":"VA",
    "sg:tags":[
        "operator",
        "local",
        "trucking"
    ],
    "wof:name":"Terry Mc Kinney Trucking Co",
    "wof:placetype":"venue"
},
  "geometry": {"coordinates":[-82.709762,36.85141],"type":"Point"}
}