{
  "type": "Feature",
  "properties": {
    "addr:full":"2320 Lovers Ln Vinton VA 24179",
    "addr:housenumber":"2320",
    "addr:postcode":"24179",
    "addr:street":"Lovers Ln",
    "iso:country":"US",
    "sg:address":"2320 Lovers Ln",
    "sg:city":"Vinton",
    "sg:classifiers":[
        {
            "category":"Organizations",
            "subcategory":"Religious Organization",
            "type":"Services"
        }
    ],
    "sg:phone":"+1 540 890 3391",
    "sg:postcode":"24179",
    "sg:province":"VA",
    "wof:name":"Charity Baptist Church",
    "wof:placetype":"venue"
},
  "geometry": {"coordinates":[-79.766976,37.275769],"type":"Point"}
}