{
  "type": "Feature",
  "properties": {
    "addr:full":"1735 N Wayne St Arlington VA 22201",
    "addr:housenumber":"1735",
    "addr:postcode":"22201",
    "addr:street":"N Wayne St",
    "iso:country":"US",
    "sg:address":"1735 N Wayne St",
    "sg:city":"Arlington",
    "sg:classifiers":[
        {
            "category":"Education",
            "subcategory":"Vocational School",
            "type":"Public Place"
        }
    ],
    "sg:phone":"+1 703 525 9014",
    "sg:postcode":"22201",
    "sg:province":"VA",
    "sg:tags":[
        "processing",
        "datum"
    ],
    "wof:name":"Republic Res Training Ctrs",
    "wof:placetype":"venue"
},
  "geometry": {"coordinates":[-77.08726,38.89396],"type":"Point"}
}