{
  "type": "Feature",
  "properties": {
    "iso:country":"US",
    "sg:address":"4417 John Jay Ln",
    "sg:city":"Virginia Beach",
    "sg:classifiers":[
        {
            "category":"Building & Trades",
            "subcategory":"Construction",
            "type":"Services"
        }
    ],
    "sg:phone":"+1 757 490 3865",
    "sg:postcode":"23462",
    "sg:province":"VA",
    "sg:tags":[
        "house"
    ],
    "wof:name":"Jims Improvements",
    "wof:placetype":"venue"
},
  "geometry": {"coordinates":[-76.131558,36.852078],"type":"Point"}
}