{
  "type": "Feature",
  "properties": {
    "addr:full":"525 N Birdneck Rd Virginia Beach VA 23451",
    "addr:housenumber":"525",
    "addr:postcode":"23451",
    "addr:street":"N Birdneck Rd",
    "iso:country":"US",
    "sg:address":"525 N Birdneck Rd",
    "sg:city":"Virginia Beach",
    "sg:classifiers":[
        {
            "category":"Restaurant",
            "type":"Food & Drink"
        }
    ],
    "sg:phone":"+1 757 422 6010",
    "sg:postcode":"23451",
    "sg:province":"VA",
    "sg:tags":[
        "eating"
    ],
    "wof:name":"Machismo Burrito Bar",
    "wof:placetype":"venue"
},
  "geometry": {"coordinates":[-75.994393,36.847874],"type":"Point"}
}