{
  "type": "Feature",
  "properties": {
    "addr:full":"8436 Alban Rd Springfield VA 22150",
    "addr:housenumber":"8436",
    "addr:postcode":"22150",
    "addr:street":"Alban Rd",
    "iso:country":"US",
    "sg:address":"8436 Alban Rd",
    "sg:city":"Springfield",
    "sg:classifiers":[
        {
            "category":"Building & Trades",
            "subcategory":"Equipment Rental",
            "type":"Services"
        }
    ],
    "sg:phone":"+1 703 451 3390",
    "sg:postcode":"22150",
    "sg:province":"VA",
    "wof:name":"L & A Tent Rentals",
    "wof:placetype":"venue"
},
  "geometry": {"coordinates":[-77.196691,38.733201],"type":"Point"}
}