{
  "type": "Feature",
  "properties": {
    "addr:full":"6904 Full Rack Ct Midlothian VA 23112",
    "addr:housenumber":"6904",
    "addr:postcode":"23112",
    "addr:street":"Full Rack Ct",
    "iso:country":"US",
    "sg:address":"6904 Full Rack Ct",
    "sg:city":"Midlothian",
    "sg:classifiers":[
        {
            "category":"Professional",
            "subcategory":"Business Services",
            "type":"Services"
        }
    ],
    "sg:phone":"+1 804 739 7699",
    "sg:postcode":"23112",
    "sg:province":"VA",
    "wof:name":"Mercado Solutions",
    "wof:placetype":"venue"
},
  "geometry": {"coordinates":[-77.646672,37.40488],"type":"Point"}
}