{
  "type": "Feature",
  "properties": {
    "iso:country":"US",
    "sg:address":"303 Rucker Rd",
    "sg:city":"Blacksburg",
    "sg:classifiers":[
        {
            "category":"Insurance",
            "subcategory":"Insurance Agent",
            "type":"Services"
        }
    ],
    "sg:phone":"+1 540 552 2227",
    "sg:postcode":"24060",
    "sg:province":"VA",
    "wof:name":"Southwstern Assoc Blcksburg In",
    "wof:placetype":"venue"
},
  "geometry": {"coordinates":[-80.402109,37.242246],"type":"Point"}
}