{
  "type": "Feature",
  "properties": {
    "addr:full":"8900 Three Chopt Rd Richmond VA 23229",
    "addr:housenumber":"8900",
    "addr:postcode":"23229",
    "addr:street":"Three Chopt Rd",
    "iso:country":"US",
    "sg:address":"8900 Three Chopt Rd",
    "sg:city":"Richmond",
    "sg:classifiers":[
        {
            "category":"Real Estate",
            "subcategory":"Real Estate Agent",
            "type":"Services"
        }
    ],
    "sg:phone":"+1 804 288 1978",
    "sg:postcode":"23229",
    "sg:province":"VA",
    "wof:name":"Prudentl Slatr JMS Rv Real",
    "wof:placetype":"venue"
},
  "geometry": {"coordinates":[-77.559721,37.603859],"type":"Point"}
}