{
  "type": "Feature",
  "properties": {
    "addr:full":"1265 Travelers Rd Huddleston VA 24104",
    "addr:housenumber":"1265",
    "addr:postcode":"24104",
    "addr:street":"Travelers Rd",
    "iso:country":"US",
    "sg:address":"1265 Travelers Rd",
    "sg:city":"Huddleston",
    "sg:classifiers":[
        {
            "category":"Building & Trades",
            "subcategory":"Plumbing",
            "type":"Services"
        }
    ],
    "sg:phone":"+1 540 297 6365",
    "sg:postcode":"24104",
    "sg:province":"VA",
    "sg:tags":[
        "contractor"
    ],
    "wof:name":"Area Plumbing & Remodeling",
    "wof:placetype":"venue"
},
  "geometry": {"coordinates":[-79.56306499999999,37.108542],"type":"Point"}
}