{
  "type": "Feature",
  "properties": {
    "addr:full":"3281 Broad St Exmore VA 23350",
    "addr:housenumber":"3281",
    "addr:postcode":"23350",
    "addr:street":"Broad St",
    "iso:country":"US",
    "sg:address":"3281 Broad St",
    "sg:city":"Exmore",
    "sg:classifiers":[
        {
            "category":"Social Services",
            "type":"Services"
        }
    ],
    "sg:phone":"+1 757 442 4509",
    "sg:postcode":"23350",
    "sg:province":"VA",
    "sg:tags":[
        "organization",
        "welfare"
    ],
    "wof:name":"Veseehc",
    "wof:placetype":"venue"
},
  "geometry": {"coordinates":[-75.823892,37.531468],"type":"Point"}
}