{
  "type": "Feature",
  "properties": {
    "addr:full":"3004 Lee Hwy Arlington VA 22201",
    "addr:housenumber":"3004",
    "addr:postcode":"22201",
    "addr:street":"Lee Hwy",
    "iso:country":"US",
    "sg:address":"3004 Lee Hwy",
    "sg:city":"Arlington",
    "sg:classifiers":[
        {
            "category":"Real Estate",
            "subcategory":"Real Estate Operator",
            "type":"Services"
        }
    ],
    "sg:phone":"+1 703 465 9700",
    "sg:postcode":"22201",
    "sg:province":"VA",
    "sg:tags":[
        "apartment"
    ],
    "sg:website":"www.lyonvillageapartments.com",
    "wof:name":"Lyon Village Apartments",
    "wof:placetype":"venue"
},
  "geometry": {"coordinates":[-77.093498,38.8885],"type":"Point"}
}