{
  "type": "Feature",
  "properties": {
    "iso:country":"US",
    "sg:address":"7207 Drifter Ct",
    "sg:city":"Burke",
    "sg:classifiers":[
        {
            "category":"Communications",
            "subcategory":"Radio Station",
            "type":"Services"
        }
    ],
    "sg:phone":"+1 703 440 8766",
    "sg:postcode":"22015",
    "sg:province":"VA",
    "sg:tags":[
        "jewish",
        "religious"
    ],
    "wof:name":"Sidney G Rabinowitz",
    "wof:placetype":"venue"
},
  "geometry": {"coordinates":[-77.276414,38.7589],"type":"Point"}
}