{
  "type": "Feature",
  "properties": {
    "iso:country":"US",
    "sg:address":"8919 Three Chopt Rd",
    "sg:city":"Richmond",
    "sg:classifiers":[
        {
            "category":"Health Services",
            "subcategory":"Doctor",
            "type":"Services"
        }
    ],
    "sg:phone":"+1 804 285 4763",
    "sg:postcode":"23229",
    "sg:province":"VA",
    "sg:tags":[
        "medical"
    ],
    "wof:name":"Tuckahoe Surgery Center Inc",
    "wof:placetype":"venue"
},
  "geometry": {"coordinates":[-77.559297,37.6032],"type":"Point"}
}