{
  "type": "Feature",
  "properties": {
    "addr:full":"10201 Warwick Blvd Newport News VA 23601",
    "addr:housenumber":"10201",
    "addr:postcode":"23601",
    "addr:street":"Warwick Blvd",
    "iso:country":"US",
    "sg:address":"10201 Warwick Blvd",
    "sg:city":"Newport News",
    "sg:classifiers":[
        {
            "category":"Home & Garden",
            "subcategory":"Garden Supply",
            "type":"Retail Goods"
        }
    ],
    "sg:phone":"+1 757 595 3099",
    "sg:postcode":"23601",
    "sg:province":"VA",
    "sg:tags":[
        "landscaping",
        "equipment"
    ],
    "wof:name":"Red Bark Mulch Co",
    "wof:placetype":"venue"
},
  "geometry": {"coordinates":[-76.458585,37.031053],"type":"Point"}
}