{
  "type": "Feature",
  "properties": {
    "addr:full":"87 E Lee Hwy Warrenton VA 20186",
    "addr:housenumber":"87",
    "addr:postcode":"20186",
    "addr:street":"E Lee Hwy",
    "iso:country":"US",
    "sg:address":"87 E Lee Hwy",
    "sg:city":"Warrenton",
    "sg:classifiers":[
        {
            "category":"Government",
            "subcategory":"Court House",
            "type":"Public Place"
        }
    ],
    "sg:phone":"+1 540 349 3138",
    "sg:postcode":"20186",
    "sg:province":"VA",
    "sg:tags":[
        "county"
    ],
    "wof:name":"Office Of Adult Court Svc",
    "wof:placetype":"venue"
},
  "geometry": {"coordinates":[-77.78847399999999,38.727829],"type":"Point"}
}