{
  "type": "Feature",
  "properties": {
    "iso:country":"US",
    "sg:address":"932 Laskin Rd",
    "sg:city":"Virginia Beach",
    "sg:classifiers":[
        {
            "category":"Building & Trades",
            "subcategory":"Equipment Rental",
            "type":"Services"
        }
    ],
    "sg:phone":"+1 757 858 1500",
    "sg:postcode":"23451",
    "sg:province":"VA",
    "sg:tags":[
        "aircraft",
        "leasing",
        "charter"
    ],
    "sg:website":"www.jetaircharter.net",
    "wof:name":"Jet Air Charter LLC",
    "wof:placetype":"venue"
},
  "geometry": {"coordinates":[-75.989823,36.857374],"type":"Point"}
}