{
  "type": "Feature",
  "properties": {
    "addr:full":"9912 Jefferson Ave Newport News VA 23605",
    "addr:housenumber":"9912",
    "addr:postcode":"23605",
    "addr:street":"Jefferson Ave",
    "iso:country":"US",
    "sg:address":"9912 Jefferson Ave",
    "sg:city":"Newport News",
    "sg:classifiers":[
        {
            "category":"Retail",
            "subcategory":"Auto Repair",
            "type":"Services"
        }
    ],
    "sg:phone":"+1 757 873 5901",
    "sg:postcode":"23605",
    "sg:province":"VA",
    "sg:tags":[
        "repairing",
        "automobile"
    ],
    "wof:name":"Preston's Auto",
    "wof:placetype":"venue"
},
  "geometry": {"coordinates":[-76.451896,37.031179],"type":"Point"}
}