{
  "type": "Feature",
  "properties": {
    "addr:full":"211 Jarratt Ave Jarratt VA 23867",
    "addr:housenumber":"211",
    "addr:postcode":"23867",
    "addr:street":"Jarratt Ave",
    "iso:country":"US",
    "sg:address":"211 Jarratt Ave",
    "sg:city":"Jarratt",
    "sg:classifiers":[
        {
            "category":"Banks & Credit Unions",
            "subcategory":"Bank",
            "type":"Services"
        }
    ],
    "sg:phone":"+1 434 535 8545",
    "sg:postcode":"23867",
    "sg:province":"VA",
    "wof:name":"Bank Of Southside Virginia",
    "wof:placetype":"venue"
},
  "geometry": {"coordinates":[-77.468441,36.814253],"type":"Point"}
}