{
  "type": "Feature",
  "properties": {
    "addr:full":"6084 Argyle Dr Falls Church VA 22041",
    "addr:housenumber":"6084",
    "addr:postcode":"22041",
    "addr:street":"Argyle Dr",
    "iso:country":"US",
    "sg:address":"6084 Argyle Dr",
    "sg:city":"Falls Church",
    "sg:classifiers":[
        {
            "category":"Real Estate",
            "subcategory":"Real Estate Operator",
            "type":"Services"
        }
    ],
    "sg:phone":"+1 703 820 6700",
    "sg:postcode":"22041",
    "sg:province":"VA",
    "sg:tags":[
        "apartment"
    ],
    "wof:name":"Olde Salem Village",
    "wof:placetype":"venue"
},
  "geometry": {"coordinates":[-77.141316,38.855349],"type":"Point"}
}