{
  "type": "Feature",
  "properties": {
    "addr:full":"14216 Benns Church Blvd Smithfield VA 23430",
    "addr:postcode":"14216;23430",
    "addr:street":"Benns Church Blvd",
    "iso:country":"US",
    "sg:address":"14216 Benns Church Blvd",
    "sg:city":"Smithfield",
    "sg:classifiers":[
        {
            "category":"Retail",
            "subcategory":"Portrait Studio",
            "type":"Services"
        }
    ],
    "sg:phone":"+1 757 365 9032",
    "sg:postcode":"23430",
    "sg:province":"VA",
    "sg:tags":[
        "photographer"
    ],
    "wof:name":"Haynes Studio",
    "wof:placetype":"venue"
},
  "geometry": {"coordinates":[-76.591719,36.9444],"type":"Point"}
}