{
  "type": "Feature",
  "properties": {
    "addr:full":"503 Faulconer Dr Ste 4A Charlottesville VA 22903",
    "addr:housenumber":"503",
    "addr:postcode":"22903",
    "addr:street":"Faulconer Dr Ste 4A",
    "iso:country":"US",
    "sg:address":"503 Faulconer Dr Ste 4A",
    "sg:city":"Charlottesville",
    "sg:classifiers":[
        {
            "category":"Health Services",
            "subcategory":"Doctor",
            "type":"Services"
        }
    ],
    "sg:phone":"+1 434 977 3621",
    "sg:postcode":"22903",
    "sg:province":"VA",
    "sg:tags":[
        "psychiatrist"
    ],
    "wof:name":"Josephthal Daniel H MD",
    "wof:placetype":"venue"
},
  "geometry": {"coordinates":[-78.52490299999999,38.050657],"type":"Point"}
}