{
  "type": "Feature",
  "properties": {
    "iso:country":"US",
    "sg:address":"7007 Flat Ridge Rd",
    "sg:city":"Troutdale",
    "sg:classifiers":[
        {
            "category":"Organizations",
            "subcategory":"Religious Organization",
            "type":"Services"
        }
    ],
    "sg:phone":"+1 276 655 4395",
    "sg:postcode":"24378",
    "sg:province":"VA",
    "sg:tags":[
        "clergy"
    ],
    "wof:name":"Koinonia Ministries Inc",
    "wof:placetype":"venue"
},
  "geometry": {"coordinates":[-81.332154,36.683025],"type":"Point"}
}