{
  "type": "Feature",
  "properties": {
    "iso:country":"US",
    "sg:address":"201 N 23rd St",
    "sg:city":"Purcellville",
    "sg:classifiers":[
        {
            "category":"Real Estate",
            "subcategory":"Real Estate Agent",
            "type":"Services"
        }
    ],
    "sg:phone":"+1 540 338 9926",
    "sg:postcode":"20132",
    "sg:province":"VA",
    "wof:name":"Mitchell & Best Home Builders",
    "wof:placetype":"venue"
},
  "geometry": {"coordinates":[-77.716612,39.138017],"type":"Point"}
}