{
  "type": "Feature",
  "properties": {
    "iso:country":"US",
    "sg:address":"2600 Eltham Ave",
    "sg:city":"Norfolk",
    "sg:classifiers":[
        {
            "category":"Utilities",
            "subcategory":"Telephone",
            "type":"Services"
        }
    ],
    "sg:phone":"+1 757 777 7770",
    "sg:postcode":"23513",
    "sg:province":"VA",
    "sg:tags":[
        "communications"
    ],
    "wof:name":"Telcove Inc",
    "wof:placetype":"venue"
},
  "geometry": {"coordinates":[-76.220814,36.876602],"type":"Point"}
}