{
  "type": "Feature",
  "properties": {
    "iso:country":"US",
    "sg:address":"5219 Cobble Hill Rd",
    "sg:city":"Portsmouth",
    "sg:classifiers":[
        {
            "category":"Real Estate",
            "subcategory":"Real Estate Agent",
            "type":"Services"
        }
    ],
    "sg:phone":"+1 757 483 4279",
    "sg:postcode":"23703",
    "sg:province":"VA",
    "wof:name":"Ann Stewart Realty",
    "wof:placetype":"venue"
},
  "geometry": {"coordinates":[-76.38246700000001,36.855678],"type":"Point"}
}