{
  "type": "Feature",
  "properties": {
    "addr:full":"7628 George Washington Memorial Hwy Grafton VA 23692",
    "addr:housenumber":"7628",
    "addr:postcode":"23692",
    "addr:street":"George Washington Memorial Hwy",
    "iso:country":"US",
    "sg:address":"7628 George Washington Memorial Hwy",
    "sg:city":"Grafton",
    "sg:classifiers":[
        {
            "category":"Home & Garden",
            "subcategory":"Garden Supply",
            "type":"Retail Goods"
        }
    ],
    "sg:phone":"+1 757 898 5445",
    "sg:postcode":"23692",
    "sg:province":"VA",
    "sg:tags":[
        "landscaping",
        "equipment"
    ],
    "wof:name":"Metro Building Supply Co",
    "wof:placetype":"venue"
},
  "geometry": {"coordinates":[-76.484163,37.184642],"type":"Point"}
}