{
  "type": "Feature",
  "properties": {
    "addr:full":"87 W Mercury Blvd Hampton VA 23669",
    "addr:housenumber":"87",
    "addr:postcode":"23669",
    "addr:street":"W Mercury Blvd",
    "iso:country":"US",
    "sg:address":"87 W Mercury Blvd",
    "sg:city":"Hampton",
    "sg:classifiers":[
        {
            "category":"Insurance",
            "subcategory":"Insurance Agent",
            "type":"Services"
        }
    ],
    "sg:phone":"+1 757 722 2889",
    "sg:postcode":"23669",
    "sg:province":"VA",
    "sg:website":"www.wardinsurance.com",
    "wof:name":"Ward Insurance Service",
    "wof:placetype":"venue"
},
  "geometry": {"coordinates":[-76.35477,37.04347],"type":"Point"}
}