{
  "type": "Feature",
  "properties": {
    "addr:full":"8791 Commerce Ct Manassas VA 20110",
    "addr:housenumber":"8791",
    "addr:postcode":"20110",
    "addr:street":"Commerce Ct",
    "iso:country":"US",
    "sg:address":"8791 Commerce Ct",
    "sg:city":"Manassas",
    "sg:classifiers":[
        {
            "category":"Professional",
            "subcategory":"Computer Services",
            "type":"Services"
        }
    ],
    "sg:phone":"+1 703 361 9553",
    "sg:postcode":"20110",
    "sg:province":"VA",
    "sg:tags":[
        "maintenance"
    ],
    "wof:name":"Verizon",
    "wof:placetype":"venue"
},
  "geometry": {"coordinates":[-77.45957300000001,38.759743],"type":"Point"}
}