{
  "type": "Feature",
  "properties": {
    "addr:full":"61 Catoctin Cir NE Leesburg VA 20176",
    "addr:housenumber":"61",
    "addr:postcode":"20176",
    "addr:street":"Catoctin Cir Ne",
    "iso:country":"US",
    "sg:address":"61 Catoctin Cir NE",
    "sg:city":"Leesburg",
    "sg:classifiers":[
        {
            "category":"Food & Beverages",
            "subcategory":"Groceries & Convenience Stores",
            "type":"Retail Goods"
        }
    ],
    "sg:phone":"+1 703 771 1899",
    "sg:postcode":"20176",
    "sg:province":"VA",
    "sg:tags":[
        "grocer"
    ],
    "sg:website":"www.giantfood.com",
    "wof:name":"Giant Food",
    "wof:placetype":"venue"
},
  "geometry": {"coordinates":[-77.554603,39.112033],"type":"Point"}
}