{
  "type": "Feature",
  "properties": {
    "addr:full":"2934 Piney Grove Ct Fairfax VA 22031",
    "addr:housenumber":"2934",
    "addr:postcode":"22031",
    "addr:street":"Piney Grove Ct",
    "iso:country":"US",
    "sg:address":"2934 Piney Grove Ct",
    "sg:city":"Fairfax",
    "sg:classifiers":[
        {
            "category":"Professional",
            "subcategory":"Business Services",
            "type":"Services"
        }
    ],
    "sg:phone":"+1 703 280 0425",
    "sg:postcode":"22031",
    "sg:province":"VA",
    "sg:tags":[
        "translation"
    ],
    "wof:name":"Smith Land Reconsultant",
    "wof:placetype":"venue"
},
  "geometry": {"coordinates":[-77.257715,38.870256],"type":"Point"}
}