{
  "type": "Feature",
  "properties": {
    "addr:full":"11490 Rothbury Sq Fairfax VA 22030",
    "addr:housenumber":"11490",
    "addr:postcode":"22030",
    "addr:street":"Rothbury Sq",
    "iso:country":"US",
    "sg:address":"11490 Rothbury Sq",
    "sg:city":"Fairfax",
    "sg:classifiers":[
        {
            "category":"Building & Trades",
            "subcategory":"Landscaping Services",
            "type":"Services"
        }
    ],
    "sg:phone":"+1 703 653 3605",
    "sg:postcode":"22030",
    "sg:province":"VA",
    "sg:tags":[
        "plant",
        "care"
    ],
    "wof:name":"Carmella Landscaping Inc",
    "wof:placetype":"venue"
},
  "geometry": {"coordinates":[-77.343461,38.856571],"type":"Point"}
}