{
  "type": "Feature",
  "properties": {
    "addr:full":"135 Knollwood Dr Troutville VA 24175",
    "addr:housenumber":"135",
    "addr:postcode":"24175",
    "addr:street":"Knollwood Dr",
    "iso:country":"US",
    "sg:address":"135 Knollwood Dr",
    "sg:city":"Troutville",
    "sg:classifiers":[
        {
            "category":"Arts & Performance",
            "subcategory":"Theater",
            "type":"Entertainment"
        }
    ],
    "sg:phone":"+1 540 977 8466",
    "sg:postcode":"24175",
    "sg:province":"VA",
    "sg:tags":[
        "group"
    ],
    "wof:name":"Tony James Group",
    "wof:placetype":"venue"
},
  "geometry": {"coordinates":[-79.844263,37.349485],"type":"Point"}
}