{
  "type": "Feature",
  "properties": {
    "addr:full":"2501 Fall Hill Ave Fredericksburg VA 22401",
    "addr:housenumber":"2501",
    "addr:postcode":"22401",
    "addr:street":"Fall Hill Ave",
    "iso:country":"US",
    "sg:address":"2501 Fall Hill Ave",
    "sg:city":"Fredericksburg",
    "sg:classifiers":[
        {
            "category":"Personal",
            "subcategory":"Beauty Salon",
            "type":"Services"
        }
    ],
    "sg:phone":"+1 540 368 0006",
    "sg:postcode":"22401",
    "sg:province":"VA",
    "sg:tags":[
        "shop"
    ],
    "wof:name":"Stephanie Ferguson",
    "wof:placetype":"venue"
},
  "geometry": {"coordinates":[-77.47369399999999,38.313789],"type":"Point"}
}