{
  "type": "Feature",
  "properties": {
    "addr:full":"3285 Virginia Beach Blvd Virginia Beach VA 23452",
    "addr:housenumber":"3285",
    "addr:postcode":"23452",
    "addr:street":"Virginia Beach Blvd",
    "iso:country":"US",
    "sg:address":"3285 Virginia Beach Blvd",
    "sg:city":"Virginia Beach",
    "sg:classifiers":[
        {
            "category":"Retail",
            "subcategory":"Auto Repair",
            "type":"Services"
        },
        {
            "category":"Autos & Motor Vehicles",
            "subcategory":"Auto Supplies",
            "type":"Retail Goods"
        }
    ],
    "sg:phone":"+1 757 486 9726",
    "sg:postcode":"23452",
    "sg:province":"VA",
    "sg:tags":[
        "brake"
    ],
    "sg:website":"www.tirekingdom.com",
    "wof:name":"Merchants Tire & Auto Center",
    "wof:placetype":"venue"
},
  "geometry": {"coordinates":[-76.086015,36.842041],"type":"Point"}
}