{
  "type": "Feature",
  "properties": {
    "addr:full":"2297 Seminole Ln Charlottesville VA 22901",
    "addr:housenumber":"2297",
    "addr:postcode":"22901",
    "addr:street":"Seminole Ln",
    "iso:country":"US",
    "sg:address":"2297 Seminole Ln",
    "sg:city":"Charlottesville",
    "sg:classifiers":[
        {
            "category":"Home & Garden",
            "subcategory":"Household Appliances",
            "type":"Retail Goods"
        },
        {
            "category":"Retail",
            "subcategory":"Repair Shop",
            "type":"Services"
        }
    ],
    "sg:phone":"+1 434 964 1822",
    "sg:postcode":"22901",
    "sg:province":"VA",
    "sg:tags":[
        "purifying",
        "cleaners-household-dealers",
        "system",
        "appliances-small",
        "air",
        "equipment",
        "cleaners-repair",
        "cleaning",
        "vacuum"
    ],
    "wof:name":"Oreck",
    "wof:placetype":"venue"
},
  "geometry": {"coordinates":[-78.464259,38.097244],"type":"Point"}
}