{
  "type": "Feature",
  "properties": {
    "addr:full":"1020 First Colonial Rd Virginia Beach VA 23454",
    "addr:housenumber":"1020",
    "addr:postcode":"23454",
    "addr:street":"First Colonial Rd",
    "iso:country":"US",
    "sg:address":"1020 First Colonial Rd",
    "sg:city":"Virginia Beach",
    "sg:classifiers":[
        {
            "category":"Health Services",
            "subcategory":"Doctor",
            "type":"Services"
        }
    ],
    "sg:phone":"+1 757 481 2313",
    "sg:postcode":"23454",
    "sg:province":"VA",
    "sg:tags":[
        "medical"
    ],
    "wof:name":"Joseph M Dalton Dr",
    "wof:placetype":"venue"
},
  "geometry": {"coordinates":[-76.02766,36.862883],"type":"Point"}
}