{
  "type": "Feature",
  "properties": {
    "iso:country":"US",
    "sg:address":"250 N Poplar Ave",
    "sg:city":"Waynesboro",
    "sg:classifiers":[
        {
            "category":"Banks & Credit Unions",
            "subcategory":"Bank",
            "type":"Services"
        }
    ],
    "sg:phone":"+1 540 932 3083",
    "sg:postcode":"22980",
    "sg:province":"VA",
    "sg:tags":[
        "cashing",
        "check"
    ],
    "wof:name":"Crusader Cash Advance",
    "wof:placetype":"venue"
},
  "geometry": {"coordinates":[-78.897031,38.07317],"type":"Point"}
}