{
  "type": "Feature",
  "properties": {
    "addr:full":"5431 Peters Creek Rd NW Roanoke VA 24019",
    "addr:housenumber":"5431",
    "addr:postcode":"24019",
    "addr:street":"Peters Creek Rd Nw",
    "iso:country":"US",
    "sg:address":"5431 Peters Creek Rd NW",
    "sg:city":"Roanoke",
    "sg:classifiers":[
        {
            "category":"Insurance",
            "subcategory":"Insurance Agent",
            "type":"Services"
        }
    ],
    "sg:phone":"+1 540 563 8899",
    "sg:postcode":"24019",
    "sg:province":"VA",
    "wof:name":"Pat Hall & Assoc",
    "wof:placetype":"venue"
},
  "geometry": {"coordinates":[-79.973804,37.335483],"type":"Point"}
}