{
  "type": "Feature",
  "properties": {
    "addr:full":"217 E Main St Wise VA 24293",
    "addr:housenumber":"217",
    "addr:postcode":"24293",
    "addr:street":"E Main St",
    "iso:country":"US",
    "sg:address":"217 E Main St",
    "sg:city":"Wise",
    "sg:classifiers":[
        {
            "category":"Personal",
            "subcategory":"Beauty Salon",
            "type":"Services"
        }
    ],
    "sg:phone":"+1 276 328 4306",
    "sg:postcode":"24293",
    "sg:province":"VA",
    "wof:name":"Head Hunters",
    "wof:placetype":"venue"
},
  "geometry": {"coordinates":[-82.579419,36.977399],"type":"Point"}
}