{
  "type": "Feature",
  "properties": {
    "addr:full":"89 Nelson Dr Newport News VA 23601",
    "addr:housenumber":"89",
    "addr:postcode":"23601",
    "addr:street":"Nelson Dr",
    "iso:country":"US",
    "sg:address":"89 Nelson Dr",
    "sg:city":"Newport News",
    "sg:classifiers":[
        {
            "category":"Recreation",
            "type":"Entertainment"
        }
    ],
    "sg:phone":"+1 757 591 2800",
    "sg:postcode":"23601",
    "sg:province":"VA",
    "wof:name":"Play A Round Golfing Games",
    "wof:placetype":"venue"
},
  "geometry": {"coordinates":[-76.47067199999999,37.046115],"type":"Point"}
}