{
  "type": "Feature",
  "properties": {
    "iso:country":"US",
    "sg:address":"201 W 7th St",
    "sg:city":"Richmond",
    "sg:classifiers":[
        {
            "category":"Wholesale",
            "subcategory":"Furniture",
            "type":"Manufacturing & Wholesale Goods"
        }
    ],
    "sg:phone":"+1 804 232 8900",
    "sg:postcode":"23224",
    "sg:province":"VA",
    "sg:tags":[
        "furniture-wholesale",
        "manufacturer"
    ],
    "wof:name":"Porter Street Purchasing",
    "wof:placetype":"venue"
},
  "geometry": {"coordinates":[-77.441841,37.525139],"type":"Point"}
}