{
  "type": "Feature",
  "properties": {
    "addr:full":"47 E Queens Way Hampton VA 23669",
    "addr:housenumber":"47",
    "addr:postcode":"23669",
    "addr:street":"E Queens Way",
    "iso:country":"US",
    "sg:address":"47 E Queens Way",
    "sg:city":"Hampton",
    "sg:classifiers":[
        {
            "category":"Shopping",
            "type":"Retail Goods"
        }
    ],
    "sg:phone":"+1 757 723 6400",
    "sg:postcode":"23669",
    "sg:province":"VA",
    "sg:tags":[
        "merchandise"
    ],
    "wof:name":"Harbor Gallery",
    "wof:placetype":"venue"
},
  "geometry": {"coordinates":[-76.343424,37.025865],"type":"Point"}
}