{
  "type": "Feature",
  "properties": {
    "addr:full":"238 Dominion Dr Newport News VA 23602",
    "addr:housenumber":"238",
    "addr:postcode":"23602",
    "addr:street":"Dominion Dr",
    "iso:country":"US",
    "sg:address":"238 Dominion Dr",
    "sg:city":"Newport News",
    "sg:classifiers":[
        {
            "category":"Professional",
            "subcategory":"Accounting & Tax Preparation",
            "type":"Services"
        }
    ],
    "sg:phone":"+1 757 249 0979",
    "sg:postcode":"23602",
    "sg:province":"VA",
    "sg:tags":[
        "accountant"
    ],
    "wof:name":"William C Morrison",
    "wof:placetype":"venue"
},
  "geometry": {"coordinates":[-76.507054,37.099826],"type":"Point"}
}