{
  "type": "Feature",
  "properties": {
    "addr:full":"717 Freeman St Fredericksburg VA 22401",
    "addr:housenumber":"717",
    "addr:postcode":"22401",
    "addr:street":"Freeman St",
    "iso:country":"US",
    "sg:address":"717 Freeman St",
    "sg:city":"Fredericksburg",
    "sg:classifiers":[
        {
            "category":"Government",
            "subcategory":"Police Station",
            "type":"Public Place"
        }
    ],
    "sg:phone":"+1 540 373 0070",
    "sg:postcode":"22401",
    "sg:province":"VA",
    "sg:tags":[
        "protection"
    ],
    "wof:name":"Sons of Confederate Veterans",
    "wof:placetype":"venue"
},
  "geometry": {"coordinates":[-77.46785300000001,38.296953],"type":"Point"}
}