{
  "type": "Feature",
  "properties": {
    "addr:full":"7112 Carol Ln Falls Church VA 22042",
    "addr:housenumber":"7112",
    "addr:postcode":"22042",
    "addr:street":"Carol Ln",
    "iso:country":"US",
    "sg:address":"7112 Carol Ln",
    "sg:city":"Falls Church",
    "sg:classifiers":[
        {
            "category":"Real Estate",
            "subcategory":"Real Estate Agent",
            "type":"Services"
        }
    ],
    "sg:phone":"+1 703 573 4560",
    "sg:postcode":"22042",
    "sg:province":"VA",
    "sg:website":"www.gattonrealtor.com",
    "wof:name":"Gatton Clarence E Realtor",
    "wof:placetype":"venue"
},
  "geometry": {"coordinates":[-77.193546,38.856857],"type":"Point"}
}