{
  "type": "Feature",
  "properties": {
    "iso:country":"US",
    "sg:address":"1272 Mill Dam Rd",
    "sg:city":"Virginia Beach",
    "sg:classifiers":[
        {
            "category":"Education",
            "subcategory":"School",
            "type":"Public Place"
        }
    ],
    "sg:phone":"+1 757 496 6711",
    "sg:postcode":"23454",
    "sg:province":"VA",
    "sg:website":"www.firstcolonialhs.vbcps.k12.va.us",
    "wof:name":"First Colonial High School",
    "wof:placetype":"venue"
},
  "geometry": {"coordinates":[-76.03125900000001,36.871015],"type":"Point"}
}