{
  "type": "Feature",
  "properties": {
    "addr:full":"508 Acorn Ln Damascus VA 24202",
    "addr:housenumber":"508",
    "addr:postcode":"24202",
    "addr:street":"Acorn Ln",
    "iso:country":"US",
    "sg:address":"508 Acorn Ln",
    "sg:city":"Damascus",
    "sg:classifiers":[
        {
            "category":"Retail",
            "subcategory":"Auto Repair",
            "type":"Services"
        }
    ],
    "sg:phone":"+1 276 388 3799",
    "sg:postcode":"24202",
    "sg:province":"VA",
    "sg:tags":[
        "repairing",
        "automobile"
    ],
    "wof:name":"Konnarock Automotive Svc",
    "wof:placetype":"venue"
},
  "geometry": {"coordinates":[-82.11959899999999,36.666039],"type":"Point"}
}