{
  "type": "Feature",
  "properties": {
    "iso:country":"US",
    "sg:address":"7041 Kenny Ln",
    "sg:city":"Portsmouth",
    "sg:classifiers":[
        {
            "category":"Real Estate",
            "subcategory":"Real Estate Operator",
            "type":"Services"
        }
    ],
    "sg:phone":"+1 757 484 4674",
    "sg:postcode":"23703",
    "sg:province":"VA",
    "sg:tags":[
        "manages",
        "apartment"
    ],
    "wof:name":"Churchland Square Apartments",
    "wof:placetype":"venue"
},
  "geometry": {"coordinates":[-76.408333,36.867976],"type":"Point"}
}