{
  "type": "Feature",
  "properties": {
    "iso:country":"US",
    "sg:address":"4213 Duke St",
    "sg:city":"Alexandria",
    "sg:classifiers":[
        {
            "category":"Autos & Motor Vehicles",
            "subcategory":"Automobile Sales",
            "type":"Retail Goods"
        },
        {
            "category":"Retail",
            "subcategory":"Auto Rental",
            "type":"Services"
        }
    ],
    "sg:phone":"+1 703 212 4700",
    "sg:postcode":"22304",
    "sg:province":"VA",
    "sg:tags":[
        "car",
        "leasing",
        "truck"
    ],
    "sg:website":"http://www.enterprise.com/car_rental/deeplinkmap.do?gpbr=161L&bid=004&cnty=US&arc=YPTRL01&cm_mmc=Yellowpages.com-_-IYP-_-Tradelisting-_-branch",
    "wof:name":"Enterprise Rent-A-Car",
    "wof:placetype":"venue"
},
  "geometry": {"coordinates":[-77.104021,38.811607],"type":"Point"}
}