{
  "type": "Feature",
  "properties": {
    "iso:country":"US",
    "sg:address":"4512 32nd Rd N",
    "sg:city":"Arlington",
    "sg:classifiers":[
        {
            "category":"Professional",
            "subcategory":"Research",
            "type":"Services"
        }
    ],
    "sg:phone":"+1 703 533 8408",
    "sg:postcode":"22207",
    "sg:province":"VA",
    "sg:tags":[
        "commercial",
        "physical"
    ],
    "wof:name":"Ehb Consulting Ltd",
    "wof:placetype":"venue"
},
  "geometry": {"coordinates":[-77.127985,38.911725],"type":"Point"}
}