{
  "type": "Feature",
  "properties": {
    "iso:country":"US",
    "sg:address":"7534 Diplomat Dr",
    "sg:city":"Manassas",
    "sg:classifiers":[
        {
            "category":"Social Services",
            "type":"Services"
        }
    ],
    "sg:phone":"+1 703 369 2643",
    "sg:postcode":"20109",
    "sg:province":"VA",
    "sg:tags":[
        "counselor",
        "marriage",
        "family"
    ],
    "wof:name":"Daniel H Decker",
    "wof:placetype":"venue"
},
  "geometry": {"coordinates":[-77.518248,38.794556],"type":"Point"}
}