{
  "type": "Feature",
  "properties": {
    "addr:full":"2012 Blueberry Rd Virginia Beach VA 23451",
    "addr:housenumber":"2012",
    "addr:postcode":"23451",
    "addr:street":"Blueberry Rd",
    "iso:country":"US",
    "sg:address":"2012 Blueberry Rd",
    "sg:city":"Virginia Beach",
    "sg:classifiers":[
        {
            "category":"Organizations",
            "subcategory":"Community Association",
            "type":"Services"
        }
    ],
    "sg:phone":"+1 757 481 2473",
    "sg:postcode":"23451",
    "sg:province":"VA",
    "wof:name":"Kiwanis International Inc",
    "wof:placetype":"venue"
},
  "geometry": {"coordinates":[-76.054158,36.907219],"type":"Point"}
}