{
  "type": "Feature",
  "properties": {
    "addr:full":"4218 Virgilina Rd Virgilina NC 24598",
    "addr:housenumber":"4218",
    "addr:postcode":"24598",
    "addr:street":"Virgilina Rd",
    "iso:country":"US",
    "sg:address":"4218 Virgilina Rd",
    "sg:city":"Virgilina",
    "sg:classifiers":[
        {
            "category":"Organizations",
            "subcategory":"Non-profit Organization",
            "type":"Services"
        }
    ],
    "sg:phone":"+1 434 585 3352",
    "sg:postcode":"24598",
    "sg:province":"NC",
    "wof:name":"High Plains Indians Inc",
    "wof:placetype":"venue"
},
  "geometry": {"coordinates":[-78.83838799999999,36.549523],"type":"Point"}
}