{
  "type": "Feature",
  "properties": {
    "iso:country":"US",
    "sg:address":"1225 Canary Dr",
    "sg:city":"Virginia Beach",
    "sg:classifiers":[
        {
            "category":"Wholesale",
            "subcategory":"Non-durable Goods",
            "type":"Manufacturing & Wholesale Goods"
        }
    ],
    "sg:phone":"+1 757 468 3059",
    "sg:postcode":"23453",
    "sg:province":"VA",
    "sg:tags":[
        "medal",
        "holder"
    ],
    "wof:name":"Friends & Family Inc",
    "wof:placetype":"venue"
},
  "geometry": {"coordinates":[-76.07622499999999,36.797296],"type":"Point"}
}