{
  "type": "Feature",
  "properties": {
    "addr:full":"2915 Hunter Mill Rd Oakton VA 22124",
    "addr:housenumber":"2915",
    "addr:postcode":"22124",
    "addr:street":"Hunter Mill Rd",
    "iso:country":"US",
    "sg:address":"2915 Hunter Mill Rd",
    "sg:city":"Oakton",
    "sg:classifiers":[
        {
            "category":"Professional",
            "subcategory":"Lawyer & Legal Services",
            "type":"Services"
        }
    ],
    "sg:phone":"+1 703 349 7209",
    "sg:postcode":"22124",
    "sg:province":"VA",
    "sg:tags":[
        "attorney",
        "dwi",
        "plan",
        "duo"
    ],
    "sg:website":"http://www.nicewicz.com/",
    "wof:name":"Nicewicz, Mark A.",
    "wof:placetype":"venue"
},
  "geometry": {"coordinates":[-77.301164,38.88429],"type":"Point"}
}