{
  "type": "Feature",
  "properties": {
    "addr:full":"136 Ferndale Dr Collinsville VA 24078",
    "addr:housenumber":"136",
    "addr:postcode":"24078",
    "addr:street":"Ferndale Dr",
    "iso:country":"US",
    "sg:address":"136 Ferndale Dr",
    "sg:city":"Collinsville",
    "sg:classifiers":[
        {
            "category":"Building & Trades",
            "subcategory":"Electrical",
            "type":"Services"
        }
    ],
    "sg:phone":"+1 276 647 3673",
    "sg:postcode":"24078",
    "sg:province":"VA",
    "sg:tags":[
        "electric",
        "contractor"
    ],
    "wof:name":"Jones Electric Co",
    "wof:placetype":"venue"
},
  "geometry": {"coordinates":[-79.904866,36.73303],"type":"Point"}
}