{
  "type": "Feature",
  "properties": {
    "iso:country":"US",
    "sg:address":"825 Diligence Dr",
    "sg:city":"Newport News",
    "sg:classifiers":[
        {
            "category":"Professional",
            "subcategory":"Computer Services",
            "type":"Services"
        }
    ],
    "sg:phone":"+1 757 591 5383",
    "sg:postcode":"23606",
    "sg:province":"VA",
    "sg:tags":[
        "consultant",
        "designer"
    ],
    "wof:name":"SRA Intl Inc",
    "wof:placetype":"venue"
},
  "geometry": {"coordinates":[-76.460911,37.084694],"type":"Point"}
}