{
  "type": "Feature",
  "properties": {
    "addr:full":"2222 S Shirlington Rd Arlington VA 22206",
    "addr:housenumber":"2222",
    "addr:postcode":"22206",
    "addr:street":"S Shirlington Rd",
    "iso:country":"US",
    "sg:address":"2222 S Shirlington Rd",
    "sg:city":"Arlington",
    "sg:classifiers":[
        {
            "category":"Professional",
            "subcategory":"Accounting & Tax Preparation",
            "type":"Services"
        }
    ],
    "sg:phone":"+1 703 769 7870",
    "sg:postcode":"22206",
    "sg:province":"VA",
    "sg:tags":[
        "consultant"
    ],
    "wof:name":"Tax Consultants & Business Specialists",
    "wof:placetype":"venue"
},
  "geometry": {"coordinates":[-77.084626,38.849863],"type":"Point"}
}