{
  "type": "Feature",
  "properties": {
    "iso:country":"US",
    "sg:address":"10595 Hannah Farm Rd",
    "sg:city":"Oakton",
    "sg:classifiers":[
        {
            "category":"Professional",
            "subcategory":"Management & Consulting",
            "type":"Services"
        }
    ],
    "sg:phone":"+1 703 319 3657",
    "sg:postcode":"22124",
    "sg:province":"VA",
    "sg:tags":[
        "financial"
    ],
    "wof:name":"Victor H Brown",
    "wof:placetype":"venue"
},
  "geometry": {"coordinates":[-77.30981199999999,38.901213],"type":"Point"}
}