{
  "type": "Feature",
  "properties": {
    "addr:full":"37928 Wright Farm Dr Purcellville VA 20132",
    "addr:housenumber":"37928",
    "addr:postcode":"20132",
    "addr:street":"Wright Farm Dr",
    "iso:country":"US",
    "sg:address":"37928 Wright Farm Dr",
    "sg:city":"Purcellville",
    "sg:classifiers":[
        {
            "category":"Building & Trades",
            "subcategory":"Construction",
            "type":"Services"
        }
    ],
    "sg:phone":"+1 540 751 0484",
    "sg:postcode":"20132",
    "sg:province":"VA",
    "sg:tags":[
        "home",
        "builder"
    ],
    "wof:name":"Us Homes Corp",
    "wof:placetype":"venue"
},
  "geometry": {"coordinates":[-77.693517,39.150575],"type":"Point"}
}