{
  "type": "Feature",
  "properties": {
    "iso:country":"US",
    "sg:address":"3903 Carolina Ave",
    "sg:city":"Richmond",
    "sg:classifiers":[
        {
            "category":"Professional",
            "subcategory":"Business Services",
            "type":"Services"
        }
    ],
    "sg:phone":"+1 804 422 0007",
    "sg:postcode":"23222",
    "sg:province":"VA",
    "wof:name":"Fleming & Associates",
    "wof:placetype":"venue"
},
  "geometry": {"coordinates":[-77.41482499999999,37.585132],"type":"Point"}
}