{
  "type": "Feature",
  "properties": {
    "addr:full":"1426 Simpson Ct Norfolk VA 23503",
    "addr:housenumber":"1426",
    "addr:postcode":"23503",
    "addr:street":"Simpson Ct",
    "iso:country":"US",
    "sg:address":"1426 Simpson Ct",
    "sg:city":"Norfolk",
    "sg:classifiers":[
        {
            "category":"Building & Trades",
            "subcategory":"Landscaping Services",
            "type":"Services"
        }
    ],
    "sg:phone":"+1 757 583 1740",
    "sg:postcode":"23503",
    "sg:province":"VA",
    "wof:name":"Evercare Lawn Maintenance",
    "wof:placetype":"venue"
},
  "geometry": {"coordinates":[-76.23275599999999,36.939125],"type":"Point"}
}