{
  "type": "Feature",
  "properties": {
    "iso:country":"US",
    "sg:address":"310 Briarwood Dr",
    "sg:city":"Christiansburg",
    "sg:classifiers":[
        {
            "category":"Arts & Performance",
            "subcategory":"Dance",
            "type":"Entertainment"
        }
    ],
    "sg:phone":"+1 540 521 2121",
    "sg:postcode":"24073",
    "sg:province":"VA",
    "sg:tags":[
        "instruction",
        "dancing"
    ],
    "wof:name":"Urban Mjuan's Dance Studio",
    "wof:placetype":"venue"
},
  "geometry": {"coordinates":[-80.40801999999999,37.118394],"type":"Point"}
}