{
  "type": "Feature",
  "properties": {
    "addr:full":"517 Front St E Coeburn VA 24230",
    "addr:housenumber":"517",
    "addr:postcode":"24230",
    "addr:street":"Front St E",
    "iso:country":"US",
    "sg:address":"517 Front St E",
    "sg:city":"Coeburn",
    "sg:classifiers":[
        {
            "category":"Retail",
            "subcategory":"Repair Shop",
            "type":"Services"
        }
    ],
    "sg:phone":"+1 276 395 3983",
    "sg:postcode":"24230",
    "sg:province":"VA",
    "sg:tags":[
        "television",
        "radio"
    ],
    "wof:name":"Sunburst Electronics",
    "wof:placetype":"venue"
},
  "geometry": {"coordinates":[-82.464271,36.94352],"type":"Point"}
}