{
  "type": "Feature",
  "properties": {
    "iso:country":"US",
    "sg:address":"5719 Arrowhead Dr",
    "sg:city":"Virginia Beach",
    "sg:classifiers":[
        {
            "category":"Home & Garden",
            "subcategory":"Carpets & Floor Coverings",
            "type":"Retail Goods"
        }
    ],
    "sg:phone":"+1 757 497 2686",
    "sg:postcode":"23462",
    "sg:province":"VA",
    "sg:tags":[
        "tile",
        "wood",
        "including",
        "vinyl",
        "flo"
    ],
    "wof:name":"Carpet Hut The",
    "wof:placetype":"venue"
},
  "geometry": {"coordinates":[-76.18422,36.840513],"type":"Point"}
}