{
  "type": "Feature",
  "properties": {
    "iso:country":"US",
    "sg:address":"101 York Ln",
    "sg:city":"Yorktown",
    "sg:classifiers":[
        {
            "category":"Health Services",
            "subcategory":"Doctor",
            "type":"Services"
        }
    ],
    "sg:phone":"+1 757 898 7737",
    "sg:postcode":"23692",
    "sg:province":"VA",
    "sg:tags":[
        "physician",
        "surgeon"
    ],
    "wof:name":"Tidewater Physicians Group",
    "wof:placetype":"venue"
},
  "geometry": {"coordinates":[-76.49710899999999,37.198474],"type":"Point"}
}