{
  "type": "Feature",
  "properties": {
    "iso:country":"US",
    "sg:address":"203 Mason Ave",
    "sg:city":"Cape Charles",
    "sg:classifiers":[
        {
            "category":"Restaurant",
            "type":"Food & Drink"
        }
    ],
    "sg:phone":"+1 757 331 3005",
    "sg:postcode":"23310",
    "sg:province":"VA",
    "sg:tags":[
        "eating"
    ],
    "wof:name":"Harbor Grille",
    "wof:placetype":"venue"
},
  "geometry": {"coordinates":[-76.019791,37.267077],"type":"Point"}
}