{
  "type": "Feature",
  "properties": {
    "iso:country":"US",
    "sg:address":"10967 Richardson Rd",
    "sg:city":"Ashland",
    "sg:classifiers":[
        {
            "category":"Retail",
            "subcategory":"Auto Repair",
            "type":"Services"
        }
    ],
    "sg:phone":"+1 804 550 3772",
    "sg:postcode":"23005",
    "sg:province":"VA",
    "sg:tags":[
        "general"
    ],
    "wof:name":"Mikes Automotive",
    "wof:placetype":"venue"
},
  "geometry": {"coordinates":[-77.441113,37.696745],"type":"Point"}
}