{
  "type": "Feature",
  "properties": {
    "iso:country":"US",
    "sg:address":"4449 Cox Rd",
    "sg:city":"Glen Allen",
    "sg:classifiers":[
        {
            "category":"Professional",
            "subcategory":"Computer Services",
            "type":"Services"
        }
    ],
    "sg:phone":"+1 804 290 4205",
    "sg:postcode":"23060",
    "sg:province":"VA",
    "sg:tags":[
        "technical"
    ],
    "wof:name":"A PC Helpdeskcom LLC",
    "wof:placetype":"venue"
},
  "geometry": {"coordinates":[-77.575351,37.658169],"type":"Point"}
}