{
  "type": "Feature",
  "properties": {
    "addr:full":"24365 Gum Spring Rd Sterling VA 20166",
    "addr:housenumber":"24365",
    "addr:postcode":"20166",
    "addr:street":"Gum Spring Rd",
    "iso:country":"US",
    "sg:address":"24365 Gum Spring Rd",
    "sg:city":"Sterling",
    "sg:classifiers":[
        {
            "category":"Building & Trades",
            "subcategory":"Landscaping Services",
            "type":"Services"
        }
    ],
    "sg:phone":"+1 703 996 8636",
    "sg:postcode":"20166",
    "sg:province":"VA",
    "wof:name":"Ultra Turf Inc",
    "wof:placetype":"venue"
},
  "geometry": {"coordinates":[-77.541269,38.938797],"type":"Point"}
}