{
  "type": "Feature",
  "properties": {
    "addr:full":"9915 Greenwood Rd Glen Allen VA 23060",
    "addr:housenumber":"9915",
    "addr:postcode":"23060",
    "addr:street":"Greenwood Rd",
    "iso:country":"US",
    "sg:address":"9915 Greenwood Rd",
    "sg:city":"Glen Allen",
    "sg:classifiers":[
        {
            "category":"Professional",
            "subcategory":"Management & Consulting",
            "type":"Services"
        }
    ],
    "sg:phone":"+1 804 553 9933",
    "sg:postcode":"23060",
    "sg:province":"VA",
    "sg:tags":[
        "business"
    ],
    "wof:name":"Hib Consulting LLC",
    "wof:placetype":"venue"
},
  "geometry": {"coordinates":[-77.46990700000001,37.652584],"type":"Point"}
}