{
  "type": "Feature",
  "properties": {
    "iso:country":"US",
    "sg:address":"1708 Whitewood Ln",
    "sg:city":"Herndon",
    "sg:classifiers":[
        {
            "category":"Shopping",
            "subcategory":"Gifts & Souvenirs",
            "type":"Retail Goods"
        }
    ],
    "sg:phone":"+1 703 793 3066",
    "sg:postcode":"20170",
    "sg:province":"VA",
    "wof:name":"Stans Gifts",
    "wof:placetype":"venue"
},
  "geometry": {"coordinates":[-77.399002,38.984312],"type":"Point"}
}