{
  "type": "Feature",
  "properties": {
    "iso:country":"US",
    "sg:address":"6275 E Virginia Beach Blvd",
    "sg:city":"Norfolk",
    "sg:classifiers":[
        {
            "category":"Health Services",
            "subcategory":"Health Practitioner",
            "type":"Services"
        },
        {
            "category":"Health Services",
            "subcategory":"Doctor",
            "type":"Services"
        }
    ],
    "sg:phone":"+1 757 461 1688",
    "sg:postcode":"23502",
    "sg:province":"VA",
    "sg:tags":[
        "surgeon",
        "therapist",
        "orthopedic",
        "physical"
    ],
    "wof:name":"Therapy Associates",
    "wof:placetype":"venue"
},
  "geometry": {"coordinates":[-76.193006,36.855027],"type":"Point"}
}