{
  "type": "Feature",
  "properties": {
    "addr:full":"1935 Thomson Dr Lynchburg VA 24501",
    "addr:housenumber":"1935",
    "addr:postcode":"24501",
    "addr:street":"Thomson Dr",
    "iso:country":"US",
    "sg:address":"1935 Thomson Dr",
    "sg:city":"Lynchburg",
    "sg:classifiers":[
        {
            "category":"Social Services",
            "type":"Services"
        }
    ],
    "sg:phone":"+1 434 528 0896",
    "sg:postcode":"24501",
    "sg:province":"VA",
    "wof:name":"Brenda S Waller MD",
    "wof:placetype":"venue"
},
  "geometry": {"coordinates":[-79.177209,37.419324],"type":"Point"}
}