{
  "type": "Feature",
  "properties": {
    "addr:full":"12793 Hunterbrook Dr Woodbridge VA 22192",
    "addr:housenumber":"12793",
    "addr:postcode":"22192",
    "addr:street":"Hunterbrook Dr",
    "iso:country":"US",
    "sg:address":"12793 Hunterbrook Dr",
    "sg:city":"Woodbridge",
    "sg:classifiers":[
        {
            "category":"Professional",
            "subcategory":"Computer Services",
            "type":"Services"
        }
    ],
    "sg:phone":"+1 703 492 8424",
    "sg:postcode":"22192",
    "sg:province":"VA",
    "sg:tags":[
        "support",
        "providing",
        "system"
    ],
    "wof:name":"Mjnr Llc",
    "wof:placetype":"venue"
},
  "geometry": {"coordinates":[-77.275386,38.677488],"type":"Point"}
}