{
  "type": "Feature",
  "properties": {
    "iso:country":"US",
    "sg:address":"921 S Church St Ste A",
    "sg:city":"Smithfield",
    "sg:classifiers":[
        {
            "category":"Arts & Performance",
            "subcategory":"Arts Center",
            "type":"Entertainment"
        },
        {
            "category":"School Buses",
            "type":"Transportation"
        },
        {
            "category":"Arts & Performance",
            "subcategory":"Dance",
            "type":"Entertainment"
        }
    ],
    "sg:phone":"+1 757 357 5807",
    "sg:postcode":"23430",
    "sg:province":"VA",
    "sg:tags":[
        "performing",
        "acting",
        "instruction",
        "workshop",
        "dancing"
    ],
    "sg:website":"www.europeandancestudio.com",
    "wof:name":"European Dance Studio",
    "wof:placetype":"venue"
},
  "geometry": {"coordinates":[-76.612289,36.978522],"type":"Point"}
}