{
  "type": "Feature",
  "properties": {
    "addr:full":"6519 Marye Rd Woodford VA 22580",
    "addr:housenumber":"6519",
    "addr:postcode":"22580",
    "addr:street":"Marye Rd",
    "iso:country":"US",
    "sg:address":"6519 Marye Rd",
    "sg:city":"Woodford",
    "sg:classifiers":[
        {
            "category":"Organizations",
            "subcategory":"Religious Organization",
            "type":"Services"
        }
    ],
    "sg:phone":"+1 804 448 3508",
    "sg:postcode":"22580",
    "sg:province":"VA",
    "wof:name":"Bethany Baptist Church",
    "wof:placetype":"venue"
},
  "geometry": {"coordinates":[-77.562248,38.082801],"type":"Point"}
}