{
  "type": "Feature",
  "properties": {
    "iso:country":"US",
    "sg:address":"1005 Parkland Ln",
    "sg:city":"Virginia Beach",
    "sg:classifiers":[
        {
            "category":"Organizations",
            "subcategory":"Religious Organization",
            "type":"Services"
        }
    ],
    "sg:phone":"+1 757 420 9255",
    "sg:postcode":"23464",
    "sg:province":"VA",
    "sg:tags":[
        "clergy"
    ],
    "wof:name":"Jose Ramirez",
    "wof:placetype":"venue"
},
  "geometry": {"coordinates":[-76.18589,36.80612],"type":"Point"}
}