{
  "type": "Feature",
  "properties": {
    "iso:country":"US",
    "sg:address":"152 Downing Dr",
    "sg:city":"Chesapeake",
    "sg:classifiers":[
        {
            "category":"Wholesale",
            "subcategory":"Furniture",
            "type":"Manufacturing & Wholesale Goods"
        }
    ],
    "sg:phone":"+1 757 482 4344",
    "sg:postcode":"23322",
    "sg:province":"VA",
    "sg:tags":[
        "equipment",
        "material",
        "fixture",
        "handling"
    ],
    "wof:name":"Indoff 119",
    "wof:placetype":"venue"
},
  "geometry": {"coordinates":[-76.206373,36.713394],"type":"Point"}
}