{
  "type": "Feature",
  "properties": {
    "iso:country":"US",
    "sg:address":"450 W Main St",
    "sg:city":"Danville",
    "sg:classifiers":[
        {
            "category":"Social Services",
            "subcategory":"Child Care",
            "type":"Services"
        }
    ],
    "sg:phone":"+1 434 792 5960",
    "sg:postcode":"24541",
    "sg:province":"VA",
    "sg:tags":[
        "kindergarten",
        "academic",
        "school"
    ],
    "wof:name":"Wee Center",
    "wof:placetype":"venue"
},
  "geometry": {"coordinates":[-79.41408,36.576502],"type":"Point"}
}