{
  "type": "Feature",
  "properties": {
    "iso:country":"US",
    "sg:address":"2859 Duke St",
    "sg:city":"Alexandria",
    "sg:classifiers":[
        {
            "category":"Professional",
            "subcategory":"Business Services",
            "type":"Services"
        }
    ],
    "sg:phone":"+1 703 740 5300",
    "sg:postcode":"22314",
    "sg:province":"VA",
    "sg:tags":[
        "paging",
        "answering"
    ],
    "wof:name":"A Better Answer",
    "wof:placetype":"venue"
},
  "geometry": {"coordinates":[-77.079764,38.807239],"type":"Point"}
}