{
  "type": "Feature",
  "properties": {
    "addr:full":"607 Industrial Park Dr Newport News VA 23608",
    "addr:housenumber":"607",
    "addr:postcode":"23608",
    "addr:street":"Industrial Park Dr",
    "iso:country":"US",
    "sg:address":"607 Industrial Park Dr",
    "sg:city":"Newport News",
    "sg:classifiers":[
        {
            "category":"Building & Trades",
            "subcategory":"Construction",
            "type":"Services"
        }
    ],
    "sg:phone":"+1 757 833 0400",
    "sg:postcode":"23608",
    "sg:province":"VA",
    "sg:tags":[
        "house"
    ],
    "wof:name":"B&B Boat & Home Repair",
    "wof:placetype":"venue"
},
  "geometry": {"coordinates":[-76.54107999999999,37.164778],"type":"Point"}
}