{
  "type": "Feature",
  "properties": {
    "addr:full":"4704 Princess Anne Rd Virginia Beach VA 23462",
    "addr:housenumber":"4704",
    "addr:postcode":"23462",
    "addr:street":"Princess Anne Rd",
    "iso:country":"US",
    "sg:address":"4704 Princess Anne Rd",
    "sg:city":"Virginia Beach",
    "sg:classifiers":[
        {
            "category":"Restaurant",
            "type":"Food & Drink"
        }
    ],
    "sg:phone":"+1 757 495 8877",
    "sg:postcode":"23462",
    "sg:province":"VA",
    "sg:website":"www.homedelivery2you.com",
    "wof:name":"Shrimpboat Restaurant",
    "wof:placetype":"venue"
},
  "geometry": {"coordinates":[-76.142394,36.813753],"type":"Point"}
}