{
  "type": "Feature",
  "properties": {
    "addr:full":"1403 Gilliam Rd Brookneal VA 24528",
    "addr:housenumber":"1403",
    "addr:postcode":"24528",
    "addr:street":"Gilliam Rd",
    "iso:country":"US",
    "sg:address":"1403 Gilliam Rd",
    "sg:city":"Brookneal",
    "sg:classifiers":[
        {
            "category":"Farming",
            "subcategory":"Livestock Farm",
            "type":"Manufacturing & Wholesale Goods"
        }
    ],
    "sg:phone":"+1 434 376 2637",
    "sg:postcode":"24528",
    "sg:province":"VA",
    "sg:tags":[
        "beef",
        "feedlot",
        "tobacco",
        "cattle"
    ],
    "wof:name":"Paul Gilliam",
    "wof:placetype":"venue"
},
  "geometry": {"coordinates":[-78.87106799999999,37.150698],"type":"Point"}
}