{
  "type": "Feature",
  "properties": {
    "iso:country":"US",
    "sg:address":"1759 Redwood Rd",
    "sg:city":"Gladehill",
    "sg:classifiers":[
        {
            "category":"Freight",
            "type":"Transportation"
        }
    ],
    "sg:phone":"+1 540 483 4729",
    "sg:postcode":"24092",
    "sg:province":"VA",
    "sg:tags":[
        "operator",
        "trucking"
    ],
    "wof:name":"Hudson Kathy W Hauling",
    "wof:placetype":"venue"
},
  "geometry": {"coordinates":[-79.825625,37.038064],"type":"Point"}
}