{
  "type": "Feature",
  "properties": {
    "addr:full":"7307 Arlington Blvd Falls Church VA 22042",
    "addr:housenumber":"7307",
    "addr:postcode":"22042",
    "addr:street":"Arlington Blvd",
    "iso:country":"US",
    "sg:address":"7307 Arlington Blvd",
    "sg:city":"Falls Church",
    "sg:classifiers":[
        {
            "category":"Professional",
            "subcategory":"Management & Consulting",
            "type":"Services"
        }
    ],
    "sg:phone":"+1 703 505 8748",
    "sg:postcode":"22042",
    "sg:province":"VA",
    "sg:tags":[
        "economic"
    ],
    "wof:name":"Rosetta Research & Consulting",
    "wof:placetype":"venue"
},
  "geometry": {"coordinates":[-77.198983,38.86604],"type":"Point"}
}