{
  "type": "Feature",
  "properties": {
    "iso:country":"US",
    "sg:address":"1303 Jamestown Rd",
    "sg:city":"Williamsburg",
    "sg:classifiers":[
        {
            "category":"Shopping",
            "subcategory":"Florist",
            "type":"Retail Goods"
        }
    ],
    "sg:phone":"+1 757 220 1242",
    "sg:postcode":"23185",
    "sg:province":"VA",
    "wof:name":"Morrison's Flowers & Gifts",
    "wof:placetype":"venue"
},
  "geometry": {"coordinates":[-76.732697,37.253141],"type":"Point"}
}