{
  "type": "Feature",
  "properties": {
    "addr:full":"22 Elliewood Ave Charlottesville VA 22903",
    "addr:housenumber":"22",
    "addr:postcode":"22903",
    "addr:street":"Elliewood Ave",
    "iso:country":"US",
    "sg:address":"22 Elliewood Ave",
    "sg:city":"Charlottesville",
    "sg:classifiers":[
        {
            "category":"Personal",
            "subcategory":"Beauty Salon",
            "type":"Services"
        }
    ],
    "sg:phone":"+1 434 295 1242",
    "sg:postcode":"22903",
    "sg:province":"VA",
    "sg:tags":[
        "shop"
    ],
    "wof:name":"Willie's Hair Design",
    "wof:placetype":"venue"
},
  "geometry": {"coordinates":[-78.500125,38.036741],"type":"Point"}
}