{
  "type": "Feature",
  "properties": {
    "iso:country":"US",
    "sg:address":"1515 Jefferson Davis Hwy",
    "sg:city":"Arlington",
    "sg:classifiers":[
        {
            "category":"Real Estate",
            "subcategory":"Real Estate Operator",
            "type":"Services"
        }
    ],
    "sg:phone":"+1 877 216 6802",
    "sg:postcode":"22202",
    "sg:province":"VA",
    "sg:tags":[
        "apartment"
    ],
    "sg:website":"http://local.ingenio.com/Listings/Details.aspx?NUM=a%3a10271598%3a13%3a4859924%3a14%3a0%3a7",
    "wof:name":"Crystal Square",
    "wof:placetype":"venue"
},
  "geometry": {"coordinates":[-77.05291,38.84395],"type":"Point"}
}