{
  "type": "Feature",
  "properties": {
    "iso:country":"US",
    "sg:address":"2600 Washington Ave",
    "sg:city":"Newport News",
    "sg:classifiers":[
        {
            "category":"Professional",
            "subcategory":"Lawyer & Legal Services",
            "type":"Services"
        }
    ],
    "sg:phone":"+1 757 244 4445",
    "sg:postcode":"23607",
    "sg:province":"VA",
    "sg:tags":[
        "attorney"
    ],
    "wof:name":"James S Ellenson",
    "wof:placetype":"venue"
},
  "geometry": {"coordinates":[-76.430885,36.978662],"type":"Point"}
}