{
  "type": "Feature",
  "properties": {
    "iso:country":"US",
    "sg:address":"2341 Jefferson Davis Hwy",
    "sg:city":"Arlington",
    "sg:classifiers":[
        {
            "category":"Fast Food",
            "type":"Food & Drink"
        },
        {
            "category":"Deli",
            "type":"Food & Drink"
        },
        {
            "category":"Restaurant",
            "type":"Food & Drink"
        },
        {
            "category":"Wholesale",
            "subcategory":"Wine & Distilled Alcoholic Beverages",
            "type":"Manufacturing & Wholesale Goods"
        }
    ],
    "sg:phone":"+1 703 418 0294",
    "sg:postcode":"22202",
    "sg:province":"VA",
    "sg:tags":[
        "broker",
        "take"
    ],
    "wof:name":"Cedar Deli",
    "wof:placetype":"venue"
},
  "geometry": {"coordinates":[-77.052002,38.853001],"type":"Point"}
}