{
  "type": "Feature",
  "properties": {
    "iso:country":"US",
    "sg:address":"41 Court Sq",
    "sg:city":"Harrisonburg",
    "sg:classifiers":[
        {
            "category":"Restaurant",
            "type":"Food & Drink"
        }
    ],
    "sg:phone":"+1 540 434 8777",
    "sg:postcode":"22801",
    "sg:province":"VA",
    "sg:website":"www.calhounsbrewery.com",
    "wof:name":"Calhoun's Restaurant & Brewing",
    "wof:placetype":"venue"
},
  "geometry": {"coordinates":[-78.869379,38.449943],"type":"Point"}
}