{
  "type": "Feature",
  "properties": {
    "addr:full":"101 Gilley Ave E Big Stone Gap VA 24219",
    "addr:housenumber":"101",
    "addr:postcode":"24219",
    "addr:street":"Gilley Ave E",
    "iso:country":"US",
    "sg:address":"101 Gilley Ave E",
    "sg:city":"Big Stone Gap",
    "sg:classifiers":[
        {
            "category":"Organizations",
            "subcategory":"Religious Organization",
            "type":"Services"
        }
    ],
    "sg:phone":"+1 276 523 3025",
    "sg:postcode":"24219",
    "sg:province":"VA",
    "sg:tags":[
        "church"
    ],
    "wof:name":"United Methodist Church",
    "wof:placetype":"venue"
},
  "geometry": {"coordinates":[-82.77427900000001,36.863354],"type":"Point"}
}