{
  "type": "Feature",
  "properties": {
    "addr:full":"2525 Linkhorne Dr Lynchburg VA 24503",
    "addr:housenumber":"2525",
    "addr:postcode":"24503",
    "addr:street":"Linkhorne Dr",
    "iso:country":"US",
    "sg:address":"2525 Linkhorne Dr",
    "sg:city":"Lynchburg",
    "sg:classifiers":[
        {
            "category":"Utilities",
            "subcategory":"Mobile Phone",
            "type":"Services"
        }
    ],
    "sg:phone":"+1 434 384 4334",
    "sg:postcode":"24503",
    "sg:province":"VA",
    "sg:tags":[
        "telephone",
        "cellular"
    ],
    "wof:name":"Alltel Communications",
    "wof:placetype":"venue"
},
  "geometry": {"coordinates":[-79.196145,37.417909],"type":"Point"}
}