{
  "type": "Feature",
  "properties": {
    "iso:country":"US",
    "sg:address":"6095 High St W",
    "sg:city":"Portsmouth",
    "sg:classifiers":[
        {
            "category":"Professional",
            "type":"Services"
        }
    ],
    "sg:phone":"+1 757 686 1771",
    "sg:postcode":"23703",
    "sg:province":"VA",
    "wof:name":"7 Five 7",
    "wof:placetype":"venue"
},
  "geometry": {"coordinates":[-76.39790600000001,36.860916],"type":"Point"}
}