{
  "type": "Feature",
  "properties": {
    "addr:full":"14520 Bakersfield St Woodbridge VA 22193",
    "addr:housenumber":"14520",
    "addr:postcode":"22193",
    "addr:street":"Bakersfield St",
    "iso:country":"US",
    "sg:address":"14520 Bakersfield St",
    "sg:city":"Woodbridge",
    "sg:classifiers":[
        {
            "category":"Shopping",
            "type":"Retail Goods"
        }
    ],
    "sg:phone":"+1 703 680 5325",
    "sg:postcode":"22193",
    "sg:province":"VA",
    "sg:tags":[
        "merchandise"
    ],
    "wof:name":"Beverly Ruane",
    "wof:placetype":"venue"
},
  "geometry": {"coordinates":[-77.31825000000001,38.637481],"type":"Point"}
}