{
  "type": "Feature",
  "properties": {
    "addr:full":"1207 Perry St Chesapeake VA 23324",
    "addr:housenumber":"1207",
    "addr:postcode":"23324",
    "addr:street":"Perry St",
    "iso:country":"US",
    "sg:address":"1207 Perry St",
    "sg:city":"Chesapeake",
    "sg:classifiers":[
        {
            "category":"Organizations",
            "subcategory":"Religious Organization",
            "type":"Services"
        }
    ],
    "sg:phone":"+1 757 545 5532",
    "sg:postcode":"23324",
    "sg:province":"VA",
    "sg:tags":[
        "baptist",
        "church"
    ],
    "wof:name":"Southside Baptist Church Inc",
    "wof:placetype":"venue"
},
  "geometry": {"coordinates":[-76.279143,36.813491],"type":"Point"}
}