{
  "type": "Feature",
  "properties": {
    "addr:full":"10480 Twin Oaks Ln Unionville VA 22567",
    "addr:housenumber":"10480",
    "addr:postcode":"22567",
    "addr:street":"Twin Oaks Ln",
    "iso:country":"US",
    "sg:address":"10480 Twin Oaks Ln",
    "sg:city":"Unionville",
    "sg:classifiers":[
        {
            "category":"Freight",
            "type":"Transportation"
        }
    ],
    "sg:phone":"+1 540 854 4432",
    "sg:postcode":"22567",
    "sg:province":"VA",
    "sg:tags":[
        "local",
        "hauling"
    ],
    "wof:name":"Jay R Marshall Inc",
    "wof:placetype":"venue"
},
  "geometry": {"coordinates":[-77.97747200000001,38.259401],"type":"Point"}
}