{
  "type": "Feature",
  "properties": {
    "addr:full":"4805 Courthouse Rd Williamsburg VA 23124",
    "addr:housenumber":"4805",
    "addr:postcode":"23124",
    "addr:street":"Courthouse Rd",
    "iso:country":"US",
    "sg:address":"4805 Courthouse Rd",
    "sg:city":"Williamsburg",
    "sg:classifiers":[
        {
            "category":"Recreation",
            "type":"Entertainment"
        }
    ],
    "sg:phone":"+1 757 220 0808",
    "sg:postcode":"23124",
    "sg:province":"VA",
    "sg:tags":[
        "parlor",
        "billiard"
    ],
    "wof:name":"Corner Pocket",
    "wof:placetype":"venue"
},
  "geometry": {"coordinates":[-77.008911,37.523332],"type":"Point"}
}