{
  "type": "Feature",
  "properties": {
    "addr:full":"184 Vista Dr Roanoke VA 24019",
    "addr:housenumber":"184",
    "addr:postcode":"24019",
    "addr:street":"Vista Dr",
    "iso:country":"US",
    "sg:address":"184 Vista Dr",
    "sg:city":"Roanoke",
    "sg:classifiers":[
        {
            "category":"Manufacturing",
            "subcategory":"Motor Vehicles & Parts",
            "type":"Manufacturing & Wholesale Goods"
        }
    ],
    "sg:phone":"+1 540 966 5300",
    "sg:postcode":"24019",
    "sg:province":"VA",
    "sg:tags":[
        "truck"
    ],
    "wof:name":"Metalsa",
    "wof:placetype":"venue"
},
  "geometry": {"coordinates":[-79.922933,37.361021],"type":"Point"}
}