{
  "type": "Feature",
  "properties": {
    "iso:country":"US",
    "sg:address":"120 Maple Ave E",
    "sg:city":"Vienna",
    "sg:classifiers":[
        {
            "category":"Food & Beverages",
            "subcategory":"Liquor & Beverages",
            "type":"Retail Goods"
        }
    ],
    "sg:phone":"+1 703 938 9548",
    "sg:postcode":"22180",
    "sg:province":"VA",
    "sg:tags":[
        "beer",
        "ale",
        "lodging"
    ],
    "sg:website":"http://www.viennainn.com",
    "wof:name":"Vienna Inn",
    "wof:placetype":"venue"
},
  "geometry": {"coordinates":[-77.26459699999999,38.902053],"type":"Point"}
}