{
  "type": "Feature",
  "properties": {
    "iso:country":"US",
    "sg:address":"5130 Rollingway Rd",
    "sg:city":"Chesterfield",
    "sg:classifiers":[
        {
            "category":"Retail",
            "subcategory":"Portrait Studio",
            "type":"Services"
        }
    ],
    "sg:phone":"+1 804 763 4062",
    "sg:postcode":"23832",
    "sg:province":"VA",
    "sg:tags":[
        "photographer"
    ],
    "wof:name":"Cheap Shots",
    "wof:placetype":"venue"
},
  "geometry": {"coordinates":[-77.589637,37.422823],"type":"Point"}
}