{
  "type": "Feature",
  "properties": {
    "iso:country":"US",
    "sg:address":"900 Winfield Rd",
    "sg:city":"Petersburg",
    "sg:classifiers":[
        {
            "category":"Travel",
            "subcategory":"Hotels & Motels",
            "type":"Entertainment"
        }
    ],
    "sg:phone":"+1 804 861 8400",
    "sg:postcode":"23803",
    "sg:province":"VA",
    "wof:name":"Armada Inn",
    "wof:placetype":"venue"
},
  "geometry": {"coordinates":[-77.37643,37.215356],"type":"Point"}
}