{
  "type": "Feature",
  "properties": {
    "iso:country":"US",
    "sg:address":"22825 Davis Dr",
    "sg:city":"Sterling",
    "sg:classifiers":[
        {
            "category":"Professional",
            "subcategory":"Business Services",
            "type":"Services"
        }
    ],
    "sg:phone":"+1 703 708 7250",
    "sg:postcode":"20164",
    "sg:province":"VA",
    "sg:tags":[
        "interior",
        "consultant",
        "design",
        "decorator"
    ],
    "sg:website":"www.marthachild.com",
    "wof:name":"Martha Child Interior",
    "wof:placetype":"venue"
},
  "geometry": {"coordinates":[-77.413267,38.987232],"type":"Point"}
}