{
  "type": "Feature",
  "properties": {
    "addr:full":"8802 Four Seasons Ct Alexandria VA 22309",
    "addr:housenumber":"8802",
    "addr:postcode":"22309",
    "addr:street":"Four Seasons Ct",
    "iso:country":"US",
    "sg:address":"8802 Four Seasons Ct",
    "sg:city":"Alexandria",
    "sg:classifiers":[
        {
            "category":"Professional",
            "subcategory":"Computer Services",
            "type":"Services"
        }
    ],
    "sg:phone":"+1 703 248 4660",
    "sg:postcode":"22309",
    "sg:province":"VA",
    "sg:tags":[
        "related"
    ],
    "wof:name":"Applied Business Computech",
    "wof:placetype":"venue"
},
  "geometry": {"coordinates":[-77.090469,38.717482],"type":"Point"}
}