{
  "type": "Feature",
  "properties": {
    "addr:full":"6179 Beach Rd Midland VA 22728",
    "addr:housenumber":"6179",
    "addr:postcode":"22728",
    "addr:street":"Beach Rd",
    "iso:country":"US",
    "sg:address":"6179 Beach Rd",
    "sg:city":"Midland",
    "sg:classifiers":[
        {
            "category":"Social Services",
            "type":"Services"
        }
    ],
    "sg:phone":"+1 540 349 4556",
    "sg:postcode":"22728",
    "sg:province":"VA",
    "wof:name":"Construction Intervention Spec",
    "wof:placetype":"venue"
},
  "geometry": {"coordinates":[-77.76133799999999,38.651761],"type":"Point"}
}