{
  "type": "Feature",
  "properties": {
    "addr:full":"112 Arabian Trl Smithfield VA 23430",
    "addr:housenumber":"112",
    "addr:postcode":"23430",
    "addr:street":"Arabian Trl",
    "iso:country":"US",
    "sg:address":"112 Arabian Trl",
    "sg:city":"Smithfield",
    "sg:classifiers":[
        {
            "category":"Building & Trades",
            "subcategory":"Plumbing",
            "type":"Services"
        }
    ],
    "sg:phone":"+1 757 255 2911",
    "sg:postcode":"23430",
    "sg:province":"VA",
    "sg:tags":[
        "contractor"
    ],
    "wof:name":"D & D Contracting Inc",
    "wof:placetype":"venue"
},
  "geometry": {"coordinates":[-76.609185,36.899707],"type":"Point"}
}