{
  "type": "Feature",
  "properties": {
    "iso:country":"US",
    "sg:address":"6059 Providence Rd",
    "sg:city":"Virginia Beach",
    "sg:classifiers":[
        {
            "category":"Retail",
            "subcategory":"Auto Repair",
            "type":"Services"
        }
    ],
    "sg:phone":"+1 757 816 0440",
    "sg:postcode":"23464",
    "sg:province":"VA",
    "sg:tags":[
        "automotive"
    ],
    "wof:name":"Accurate Cylinder Headservice",
    "wof:placetype":"venue"
},
  "geometry": {"coordinates":[-76.203377,36.812774],"type":"Point"}
}