{
  "type": "Feature",
  "properties": {
    "iso:country":"US",
    "sg:address":"2327 Duke St",
    "sg:city":"Alexandria",
    "sg:classifiers":[
        {
            "category":"Manufacturing",
            "subcategory":"Toys & Sporting Goods",
            "type":"Manufacturing & Wholesale Goods"
        },
        {
            "category":"Shopping",
            "subcategory":"Bicycles & Sporting Goods",
            "type":"Retail Goods"
        }
    ],
    "sg:phone":"+1 703 535 3190",
    "sg:postcode":"22314",
    "sg:province":"VA",
    "sg:tags":[
        "goods-wholesale",
        "manufacturer"
    ],
    "wof:name":"High Sierra Pools",
    "wof:placetype":"venue"
},
  "geometry": {"coordinates":[-77.069684,38.805543],"type":"Point"}
}