{
  "type": "Feature",
  "properties": {
    "addr:full":"7437 Richmond Rd Williamsburg VA 23188",
    "addr:housenumber":"7437",
    "addr:postcode":"23188",
    "addr:street":"Richmond Rd",
    "iso:country":"US",
    "sg:address":"7437 Richmond Rd",
    "sg:city":"Williamsburg",
    "sg:classifiers":[
        {
            "category":"Wholesale",
            "subcategory":"Durable Goods & Equipment",
            "type":"Manufacturing & Wholesale Goods"
        }
    ],
    "sg:phone":"+1 757 259 9400",
    "sg:postcode":"23188",
    "sg:province":"VA",
    "sg:tags":[
        "professional",
        "mi"
    ],
    "wof:name":"Details In Design",
    "wof:placetype":"venue"
},
  "geometry": {"coordinates":[-76.771373,37.368524],"type":"Point"}
}