{
  "type": "Feature",
  "properties": {
    "addr:full":"14400 New Braddock Rd Centreville VA 20121",
    "addr:housenumber":"14400",
    "addr:postcode":"20121",
    "addr:street":"New Braddock Rd",
    "iso:country":"US",
    "sg:address":"14400 New Braddock Rd",
    "sg:city":"Centreville",
    "sg:classifiers":[
        {
            "category":"Education",
            "subcategory":"School",
            "type":"Public Place"
        }
    ],
    "sg:phone":"+1 703 227 2600",
    "sg:postcode":"20121",
    "sg:province":"VA",
    "sg:tags":[
        "elementary"
    ],
    "wof:name":"Centre Ridge Elementary School",
    "wof:placetype":"venue"
},
  "geometry": {"coordinates":[-77.444498,38.825026],"type":"Point"}
}