{
  "type": "Feature",
  "properties": {
    "addr:full":"3017 S Military Hwy Chesapeake VA 23323",
    "addr:housenumber":"3017",
    "addr:postcode":"23323",
    "addr:street":"S Military Hwy",
    "iso:country":"US",
    "sg:address":"3017 S Military Hwy",
    "sg:city":"Chesapeake",
    "sg:classifiers":[
        {
            "category":"Shopping",
            "subcategory":"Used Merchandise",
            "type":"Retail Goods"
        }
    ],
    "sg:phone":"+1 757 485 1656",
    "sg:postcode":"23323",
    "sg:province":"VA",
    "wof:name":"Frans Antiques",
    "wof:placetype":"venue"
},
  "geometry": {"coordinates":[-76.327189,36.772896],"type":"Point"}
}