{
  "type": "Feature",
  "properties": {
    "iso:country":"US",
    "sg:address":"1441 Valley Dr",
    "sg:city":"Fieldale",
    "sg:classifiers":[
        {
            "category":"Professional",
            "subcategory":"Management & Consulting",
            "type":"Services"
        }
    ],
    "sg:phone":"+1 276 673 6451",
    "sg:postcode":"24089",
    "sg:province":"VA",
    "sg:tags":[
        "educational"
    ],
    "wof:name":"Dianne Vann",
    "wof:placetype":"venue"
},
  "geometry": {"coordinates":[-79.994435,36.702844],"type":"Point"}
}