{
  "type": "Feature",
  "properties": {
    "addr:full":"2115 Spencer Rd Richmond VA 23230",
    "addr:housenumber":"2115",
    "addr:postcode":"23230",
    "addr:street":"Spencer Rd",
    "iso:country":"US",
    "sg:address":"2115 Spencer Rd",
    "sg:city":"Richmond",
    "sg:classifiers":[
        {
            "category":"Professional",
            "subcategory":"Art Services",
            "type":"Services"
        },
        {
            "category":"Professional",
            "subcategory":"Business Services",
            "type":"Services"
        }
    ],
    "sg:phone":"+1 804 285 5770",
    "sg:postcode":"23230",
    "sg:province":"VA",
    "sg:tags":[
        "development",
        "product",
        "designer",
        "designers-industrial",
        "marketing",
        "commercial",
        "design",
        "interior",
        "decorator"
    ],
    "sg:website":"http://www.creativeindustries.com",
    "wof:name":"Creative Industries, Inc.",
    "wof:placetype":"venue"
},
  "geometry": {"coordinates":[-77.50205099999999,37.59028],"type":"Point"}
}