{
  "type": "Feature",
  "properties": {
    "addr:full":"6711 Virginia Ave Ettrick VA 23803",
    "addr:housenumber":"6711",
    "addr:postcode":"23803",
    "addr:street":"Virginia Ave",
    "iso:country":"US",
    "sg:address":"6711 Virginia Ave",
    "sg:city":"Ettrick",
    "sg:classifiers":[
        {
            "category":"Building & Trades",
            "subcategory":"Construction",
            "type":"Services"
        }
    ],
    "sg:phone":"+1 804 590 9268",
    "sg:postcode":"23803",
    "sg:province":"VA",
    "sg:tags":[
        "contractor",
        "masonry",
        "footing",
        "general"
    ],
    "wof:name":"Sturt Footing & Masonry Co",
    "wof:placetype":"venue"
},
  "geometry": {"coordinates":[-77.483969,37.228562],"type":"Point"}
}