{
  "type": "Feature",
  "properties": {
    "addr:full":"1630 Pleasure House Rd Virginia Beach VA 23455",
    "addr:housenumber":"1630",
    "addr:postcode":"23455",
    "addr:street":"Pleasure House Rd",
    "iso:country":"US",
    "sg:address":"1630 Pleasure House Rd",
    "sg:city":"Virginia Beach",
    "sg:classifiers":[
        {
            "category":"Retail",
            "subcategory":"Funeral Services",
            "type":"Services"
        }
    ],
    "sg:phone":"+1 757 464 1211",
    "sg:postcode":"23455",
    "sg:province":"VA",
    "sg:tags":[
        "director"
    ],
    "wof:name":"Altmeyer Funeral Home",
    "wof:placetype":"venue"
},
  "geometry": {"coordinates":[-76.14022799999999,36.895807],"type":"Point"}
}