{
  "type": "Feature",
  "properties": {
    "addr:full":"7926 Jones Branch Dr Mc Lean VA 22102",
    "addr:housenumber":"7926",
    "addr:postcode":"22102",
    "addr:street":"Jones Branch Dr",
    "iso:country":"US",
    "sg:address":"7926 Jones Branch Dr",
    "sg:city":"Mc Lean",
    "sg:classifiers":[
        {
            "category":"Banks & Credit Unions",
            "subcategory":"Bank",
            "type":"Services"
        }
    ],
    "sg:phone":"+1 703 761 3192",
    "sg:postcode":"22102",
    "sg:province":"VA",
    "sg:tags":[
        "mortgage"
    ],
    "wof:name":"Wells Fargo",
    "wof:placetype":"venue"
},
  "geometry": {"coordinates":[-77.216503,38.928976],"type":"Point"}
}