{
  "type": "Feature",
  "properties": {
    "addr:full":"235 N Military Hwy Norfolk VA 23502",
    "addr:housenumber":"235",
    "addr:postcode":"23502",
    "addr:street":"N Military Hwy",
    "iso:country":"US",
    "sg:address":"235 N Military Hwy",
    "sg:city":"Norfolk",
    "sg:classifiers":[
        {
            "category":"Travel",
            "subcategory":"Hotels & Motels",
            "type":"Entertainment"
        }
    ],
    "sg:phone":"+1 757 461 6600",
    "sg:postcode":"23502",
    "sg:province":"VA",
    "wof:name":"Best Western Inn",
    "wof:placetype":"venue"
},
  "geometry": {"coordinates":[-76.21033,36.845639],"type":"Point"}
}