{
  "type": "Feature",
  "properties": {
    "addr:full":"6412 Jumet Ct Fairfax Station VA 22039",
    "addr:postcode":"6412;22039",
    "addr:street":"Jumet Ct",
    "iso:country":"US",
    "sg:address":"6412 Jumet Ct",
    "sg:city":"Fairfax Station",
    "sg:classifiers":[
        {
            "category":"Professional",
            "subcategory":"Management & Consulting",
            "type":"Services"
        }
    ],
    "sg:phone":"+1 703 978 5668",
    "sg:postcode":"22039",
    "sg:province":"VA",
    "sg:tags":[
        "business"
    ],
    "wof:name":"Schrader & Associates",
    "wof:placetype":"venue"
},
  "geometry": {"coordinates":[-77.316487,38.778122],"type":"Point"}
}