{
  "type": "Feature",
  "properties": {
    "iso:country":"US",
    "sg:address":"10148 Yorktown Dr",
    "sg:city":"Great Falls",
    "sg:classifiers":[
        {
            "category":"Building & Trades",
            "subcategory":"Construction",
            "type":"Services"
        }
    ],
    "sg:phone":"+1 703 404 8929",
    "sg:postcode":"22066",
    "sg:province":"VA",
    "sg:tags":[
        "painter"
    ],
    "wof:name":"Express General Svc",
    "wof:placetype":"venue"
},
  "geometry": {"coordinates":[-77.356043,39.03276],"type":"Point"}
}