{
  "type": "Feature",
  "properties": {
    "addr:full":"7512 Granby St Norfolk VA 23505",
    "addr:housenumber":"7512",
    "addr:postcode":"23505",
    "addr:street":"Granby St",
    "iso:country":"US",
    "sg:address":"7512 Granby St",
    "sg:city":"Norfolk",
    "sg:classifiers":[
        {
            "category":"Restaurant",
            "type":"Food & Drink"
        }
    ],
    "sg:phone":"+1 757 480 7900",
    "sg:postcode":"23505",
    "sg:province":"VA",
    "sg:tags":[
        "eating"
    ],
    "wof:name":"Rom Thai",
    "wof:placetype":"venue"
},
  "geometry": {"coordinates":[-76.27283799999999,36.913816],"type":"Point"}
}