{
  "type": "Feature",
  "properties": {
    "addr:full":"7116 Old Keene Mill Rd Springfield VA 22150",
    "addr:housenumber":"7116",
    "addr:postcode":"22150",
    "addr:street":"Old Keene Mill Rd",
    "iso:country":"US",
    "sg:address":"7116 Old Keene Mill Rd",
    "sg:city":"Springfield",
    "sg:classifiers":[
        {
            "category":"Restaurant",
            "type":"Food & Drink"
        }
    ],
    "sg:menulink":"http://www.allmenus.com/va/lee/188128-mcdonalds/menu/",
    "sg:phone":"+1 703 913 8018",
    "sg:postcode":"22150",
    "sg:province":"VA",
    "sg:tags":[
        "burger",
        "american"
    ],
    "wof:name":"McDonald's",
    "wof:placetype":"venue"
},
  "geometry": {"coordinates":[-77.189414,38.778641],"type":"Point"}
}