{
  "type": "Feature",
  "properties": {
    "addr:full":"8917 S Quay Rd Suffolk VA 23437",
    "addr:housenumber":"8917",
    "addr:postcode":"23437",
    "addr:street":"S Quay Rd",
    "iso:country":"US",
    "sg:address":"8917 S Quay Rd",
    "sg:city":"Suffolk",
    "sg:classifiers":[
        {
            "category":"Autos & Motor Vehicles",
            "subcategory":"Fuel & Gas Station",
            "type":"Retail Goods"
        }
    ],
    "sg:phone":"+1 757 657 2366",
    "sg:postcode":"23437",
    "sg:province":"VA",
    "sg:tags":[
        "station",
        "gasoline"
    ],
    "wof:name":"Route 58 Food Mart",
    "wof:placetype":"venue"
},
  "geometry": {"coordinates":[-76.84637499999999,36.650724],"type":"Point"}
}