{
  "type": "Feature",
  "properties": {
    "addr:full":"511 W Grace St Richmond VA 23220",
    "addr:housenumber":"511",
    "addr:postcode":"23220",
    "addr:street":"W Grace St",
    "iso:country":"US",
    "sg:address":"511 W Grace St",
    "sg:city":"Richmond",
    "sg:classifiers":[
        {
            "category":"Organizations",
            "subcategory":"Non-profit Organization",
            "type":"Services"
        },
        {
            "category":"Social Services",
            "type":"Services"
        }
    ],
    "sg:phone":"+1 804 649 8407",
    "sg:postcode":"23220",
    "sg:province":"VA",
    "sg:website":"www.urbanleaguerichmond.org",
    "wof:name":"Urban League Greater Richmond",
    "wof:placetype":"venue"
},
  "geometry": {"coordinates":[-77.447934,37.547779],"type":"Point"}
}