{
  "type": "Feature",
  "properties": {
    "addr:full":"11080 Slings Gap Rd Bent Mountain VA 24059",
    "addr:housenumber":"11080",
    "addr:postcode":"24059",
    "addr:street":"Slings Gap Rd;Mountain",
    "iso:country":"US",
    "sg:address":"11080 Slings Gap Rd",
    "sg:city":"Bent Mountain",
    "sg:classifiers":[
        {
            "category":"Building & Trades",
            "subcategory":"Cleaning & Sanitation",
            "type":"Services"
        },
        {
            "category":"Building & Trades",
            "subcategory":"Construction",
            "type":"Services"
        }
    ],
    "sg:phone":"+1 540 929 4194",
    "sg:postcode":"24059",
    "sg:province":"VA",
    "sg:tags":[
        "handyman",
        "maintenance"
    ],
    "wof:name":"Maintenance Man LLC",
    "wof:placetype":"venue"
},
  "geometry": {"coordinates":[-80.072666,37.164937],"type":"Point"}
}