{
  "type": "Feature",
  "properties": {
    "iso:country":"US",
    "sg:address":"209 Starling Ave",
    "sg:city":"Martinsville",
    "sg:classifiers":[
        {
            "category":"Professional",
            "type":"Services"
        }
    ],
    "sg:phone":"+1 276 638 1788",
    "sg:postcode":"24112",
    "sg:province":"VA",
    "sg:tags":[
        "establishment"
    ],
    "wof:name":"Adair Group",
    "wof:placetype":"venue"
},
  "geometry": {"coordinates":[-79.865538,36.685168],"type":"Point"}
}