{
  "type": "Feature",
  "properties": {
    "addr:full":"1200 Armory Dr Franklin VA 23851",
    "addr:housenumber":"1200",
    "addr:postcode":"23851",
    "addr:street":"Armory Dr",
    "iso:country":"US",
    "sg:address":"1200 Armory Dr",
    "sg:city":"Franklin",
    "sg:classifiers":[
        {
            "category":"Bars & Pubs",
            "type":"Food & Drink"
        }
    ],
    "sg:menulink":"http://www.allmenus.com/va/franklin/36728-blackwater-restaurant--steam-bar/menu/",
    "sg:phone":"+1 757 516 2598",
    "sg:postcode":"23851",
    "sg:province":"VA",
    "sg:tags":[
        "american"
    ],
    "wof:name":"Blackwater Restaurant & Steam Bar",
    "wof:placetype":"venue"
},
  "geometry": {"coordinates":[-76.943048,36.67125],"type":"Point"}
}