{
  "type": "Feature",
  "properties": {
    "iso:country":"US",
    "sg:address":"2519 Chamberlayne Ave",
    "sg:city":"Richmond",
    "sg:classifiers":[
        {
            "category":"Real Estate",
            "subcategory":"Real Estate Agent",
            "type":"Services"
        }
    ],
    "sg:phone":"+1 804 321 8002",
    "sg:postcode":"23222",
    "sg:province":"VA",
    "wof:name":"Kentre Antiques & Collectibles",
    "wof:placetype":"venue"
},
  "geometry": {"coordinates":[-77.44408300000001,37.566432],"type":"Point"}
}