{
  "type": "Feature",
  "properties": {
    "addr:full":"7313 Tee Cir Richmond VA 23225",
    "addr:housenumber":"7313",
    "addr:postcode":"23225",
    "addr:street":"Tee Cir",
    "iso:country":"US",
    "sg:address":"7313 Tee Cir",
    "sg:city":"Richmond",
    "sg:classifiers":[
        {
            "category":"Real Estate",
            "subcategory":"Real Estate Agent",
            "type":"Services"
        }
    ],
    "sg:phone":"+1 804 320 1309",
    "sg:postcode":"23225",
    "sg:province":"VA",
    "wof:name":"Robertson RE Holdings I LLC",
    "wof:placetype":"venue"
},
  "geometry": {"coordinates":[-77.523912,37.546381],"type":"Point"}
}