{
  "type": "Feature",
  "properties": {
    "iso:country":"US",
    "sg:address":"1020 N Livingston St",
    "sg:city":"Arlington",
    "sg:classifiers":[
        {
            "category":"Professional",
            "subcategory":"Management & Consulting",
            "type":"Services"
        }
    ],
    "sg:phone":"+1 703 241 1369",
    "sg:postcode":"22205",
    "sg:province":"VA",
    "sg:tags":[
        "communication"
    ],
    "wof:name":"Keyes Communications LLC",
    "wof:placetype":"venue"
},
  "geometry": {"coordinates":[-77.140387,38.875875],"type":"Point"}
}