{
  "type": "Feature",
  "properties": {
    "iso:country":"US",
    "sg:address":"43141 Town Hall Plz",
    "sg:city":"Chantilly",
    "sg:classifiers":[
        {
            "category":"Autos & Motor Vehicles",
            "subcategory":"Auto Supplies",
            "type":"Retail Goods"
        },
        {
            "category":"Retail",
            "subcategory":"Auto Repair",
            "type":"Services"
        }
    ],
    "sg:phone":"+1 703 327 5727",
    "sg:postcode":"20152",
    "sg:province":"VA",
    "sg:tags":[
        "tire"
    ],
    "sg:website":"www.mainstreettireandauto.com",
    "wof:name":"Main Street Tire & Auto Center",
    "wof:placetype":"venue"
},
  "geometry": {"coordinates":[-77.50985799999999,38.924464],"type":"Point"}
}