{
  "type": "Feature",
  "properties": {
    "iso:country":"US",
    "sg:address":"1483 S Boston Rd",
    "sg:city":"Danville",
    "sg:classifiers":[
        {
            "category":"Travel",
            "subcategory":"Hotels & Motels",
            "type":"Entertainment"
        },
        {
            "category":"Professional",
            "subcategory":"Management & Consulting",
            "type":"Services"
        }
    ],
    "sg:phone":"+1 434 793 6090",
    "sg:postcode":"24540",
    "sg:province":"VA",
    "sg:tags":[
        "consultant",
        "lodging"
    ],
    "sg:website":"http://www.sleepinn.com/hotel-danville-virginia-VA372?promo=splocal",
    "wof:name":"Sleep Inn , Inn & Suites",
    "wof:placetype":"venue"
},
  "geometry": {"coordinates":[-79.33696,36.58107],"type":"Point"}
}