{
  "type": "Feature",
  "properties": {
    "addr:full":"400 E Amhurst St Sterling VA 20164",
    "addr:housenumber":"400",
    "addr:postcode":"20164",
    "addr:street":"E Amhurst St",
    "iso:country":"US",
    "sg:address":"400 E Amhurst St",
    "sg:city":"Sterling",
    "sg:classifiers":[
        {
            "category":"Building & Trades",
            "subcategory":"Cleaning & Sanitation",
            "type":"Services"
        }
    ],
    "sg:phone":"+1 703 444 3149",
    "sg:postcode":"20164",
    "sg:province":"VA",
    "sg:tags":[
        "maintenance"
    ],
    "wof:name":"H&R Maids Inc",
    "wof:placetype":"venue"
},
  "geometry": {"coordinates":[-77.382426,39.018201],"type":"Point"}
}