{
  "type": "Feature",
  "properties": {
    "addr:full":"4535 Augusta Ave Richmond VA 23230",
    "addr:housenumber":"4535",
    "addr:postcode":"23230",
    "addr:street":"Augusta Ave",
    "iso:country":"US",
    "sg:address":"4535 Augusta Ave",
    "sg:city":"Richmond",
    "sg:classifiers":[
        {
            "category":"Professional",
            "subcategory":"Accounting & Tax Preparation",
            "type":"Services"
        }
    ],
    "sg:phone":"+1 804 353 5339",
    "sg:postcode":"23230",
    "sg:province":"VA",
    "wof:name":"Automated Medical Billing",
    "wof:placetype":"venue"
},
  "geometry": {"coordinates":[-77.4905,37.575554],"type":"Point"}
}