{
  "type": "Feature",
  "properties": {
    "addr:full":"2500 Grenoble Rd Richmond VA 23294",
    "addr:housenumber":"2500",
    "addr:postcode":"23294",
    "addr:street":"Grenoble Rd",
    "iso:country":"US",
    "sg:address":"2500 Grenoble Rd",
    "sg:city":"Richmond",
    "sg:classifiers":[
        {
            "category":"Organizations",
            "subcategory":"Professional Association",
            "type":"Services"
        }
    ],
    "sg:phone":"+1 804 672 3353",
    "sg:postcode":"23294",
    "sg:province":"VA",
    "sg:website":"www.avaintl.org",
    "wof:name":"Association For Volunteer Adm",
    "wof:placetype":"venue"
},
  "geometry": {"coordinates":[-77.52472299999999,37.613595],"type":"Point"}
}