{
  "type": "Feature",
  "properties": {
    "addr:full":"716 Front St E Coeburn VA 24230",
    "addr:housenumber":"716",
    "addr:postcode":"24230",
    "addr:street":"Front St E",
    "iso:country":"US",
    "sg:address":"716 Front St E",
    "sg:city":"Coeburn",
    "sg:classifiers":[
        {
            "category":"Government",
            "subcategory":"Fire Station",
            "type":"Public Place"
        }
    ],
    "sg:phone":"+1 276 395 7330",
    "sg:postcode":"24230",
    "sg:province":"VA",
    "sg:tags":[
        "department"
    ],
    "wof:name":"Coeburn Fire Dept",
    "wof:placetype":"venue"
},
  "geometry": {"coordinates":[-82.460706,36.942765],"type":"Point"}
}