{
  "type": "Feature",
  "properties": {
    "addr:full":"10216 Bushman Dr Oakton VA 22124",
    "addr:housenumber":"10216",
    "addr:postcode":"22124",
    "addr:street":"Bushman Dr",
    "iso:country":"US",
    "sg:address":"10216 Bushman Dr",
    "sg:city":"Oakton",
    "sg:classifiers":[
        {
            "category":"Professional",
            "subcategory":"Business Services",
            "type":"Services"
        }
    ],
    "sg:phone":"+1 703 242 1816",
    "sg:postcode":"22124",
    "sg:province":"VA",
    "wof:name":"Rachel Fedoseyev",
    "wof:placetype":"venue"
},
  "geometry": {"coordinates":[-77.29520599999999,38.872016],"type":"Point"}
}