{
  "type": "Feature",
  "properties": {
    "addr:full":"523 Old Bermuda Hundred Rd Chester VA 23836",
    "addr:housenumber":"523",
    "addr:postcode":"23836",
    "addr:street":"Old;Hundred Rd",
    "iso:country":"US",
    "sg:address":"523 Old Bermuda Hundred Rd",
    "sg:city":"Chester",
    "sg:classifiers":[
        {
            "category":"Freight",
            "type":"Transportation"
        }
    ],
    "sg:phone":"+1 804 530 4301",
    "sg:postcode":"23836",
    "sg:province":"VA",
    "sg:tags":[
        "mobile",
        "home",
        "local",
        "trucking"
    ],
    "wof:name":"Central City Movers",
    "wof:placetype":"venue"
},
  "geometry": {"coordinates":[-77.373501,37.344055],"type":"Point"}
}