{
  "type": "Feature",
  "properties": {
    "iso:country":"US",
    "sg:address":"2533 Wilson Blvd",
    "sg:city":"Arlington",
    "sg:classifiers":[
        {
            "category":"Building & Trades",
            "subcategory":"Construction",
            "type":"Services"
        }
    ],
    "sg:phone":"+1 703 524 5600",
    "sg:postcode":"22201",
    "sg:province":"VA",
    "sg:tags":[
        "interior",
        "design"
    ],
    "wof:name":"Fanelli McClain Design Studios",
    "wof:placetype":"venue"
},
  "geometry": {"coordinates":[-77.089056,38.890384],"type":"Point"}
}