{
  "type": "Feature",
  "properties": {
    "addr:full":"11622 Busy St Richmond VA 23236",
    "addr:housenumber":"11622",
    "addr:postcode":"23236",
    "addr:street":"Busy St",
    "iso:country":"US",
    "sg:address":"11622 Busy St",
    "sg:city":"Richmond",
    "sg:classifiers":[
        {
            "category":"Manufacturing",
            "subcategory":"Electronics",
            "type":"Manufacturing & Wholesale Goods"
        },
        {
            "category":"Building & Trades",
            "subcategory":"Electrical",
            "type":"Services"
        }
    ],
    "sg:phone":"+1 804 794 3400",
    "sg:postcode":"23236",
    "sg:province":"VA",
    "sg:tags":[
        "control",
        "system",
        "controls",
        "regulator",
        "regulators-control",
        "panel"
    ],
    "sg:website":"http://www.ottecontrols.com",
    "wof:name":"Otte Controls Incorporated",
    "wof:placetype":"venue"
},
  "geometry": {"coordinates":[-77.61114999999999,37.50238],"type":"Point"}
}