{
  "type": "Feature",
  "properties": {
    "iso:country":"US",
    "sg:address":"325 N Manchester St",
    "sg:city":"Arlington",
    "sg:classifiers":[
        {
            "category":"Retail",
            "subcategory":"Portrait Studio",
            "type":"Services"
        }
    ],
    "sg:phone":"+1 703 524 6274",
    "sg:postcode":"22203",
    "sg:province":"VA",
    "sg:tags":[
        "photo"
    ],
    "wof:name":"Roger Foley Photography",
    "wof:placetype":"venue"
},
  "geometry": {"coordinates":[-77.13276399999999,38.869111],"type":"Point"}
}