{
  "type": "Feature",
  "properties": {
    "addr:full":"801 15th St S Arlington VA 22202",
    "addr:housenumber":"801",
    "addr:postcode":"22202",
    "addr:street":"15Th St S",
    "iso:country":"US",
    "sg:address":"801 15th St S",
    "sg:city":"Arlington",
    "sg:classifiers":[
        {
            "category":"Building & Trades",
            "subcategory":"Construction",
            "type":"Services"
        }
    ],
    "sg:phone":"+1 202 368 1319",
    "sg:postcode":"22202",
    "sg:province":"VA",
    "sg:tags":[
        "restoration",
        "preservation"
    ],
    "wof:name":"Sixteenth Street Restoration",
    "wof:placetype":"venue"
},
  "geometry": {"coordinates":[-77.06245800000001,38.860911],"type":"Point"}
}