{
  "type": "Feature",
  "properties": {
    "addr:full":"2012 Lakeside Dr Lynchburg VA 24501",
    "addr:housenumber":"2012",
    "addr:postcode":"24501",
    "addr:street":"Lakeside Dr",
    "iso:country":"US",
    "sg:address":"2012 Lakeside Dr",
    "sg:city":"Lynchburg",
    "sg:classifiers":[
        {
            "category":"Shopping",
            "subcategory":"Discount & Variety Stores",
            "type":"Retail Goods"
        }
    ],
    "sg:phone":"+1 434 316 9647",
    "sg:postcode":"24501",
    "sg:province":"VA",
    "sg:tags":[
        "merchandise",
        "general"
    ],
    "wof:name":"TAMC Inc",
    "wof:placetype":"venue"
},
  "geometry": {"coordinates":[-79.19856900000001,37.402194],"type":"Point"}
}