{
  "type": "Feature",
  "properties": {
    "addr:full":"321 Midway Medical Park Bristol VA 37620",
    "addr:housenumber":"321",
    "addr:postcode":"37620",
    "addr:street":"Midway Medical Park",
    "iso:country":"US",
    "sg:address":"321 Midway Medical Park",
    "sg:city":"Bristol",
    "sg:classifiers":[
        {
            "category":"Health Services",
            "subcategory":"Optometrist",
            "type":"Services"
        }
    ],
    "sg:phone":"+1 423 968 3441",
    "sg:postcode":"37620",
    "sg:province":"VA",
    "sg:tags":[
        "medical"
    ],
    "wof:name":"Midway Eye Care",
    "wof:placetype":"venue"
},
  "geometry": {"coordinates":[-82.22037,36.593602],"type":"Point"}
}