{
  "type": "Feature",
  "properties": {
    "addr:full":"7021 Haycock Rd Falls Church VA 22043",
    "addr:housenumber":"7021",
    "addr:postcode":"22043",
    "addr:street":"Haycock Rd",
    "iso:country":"US",
    "sg:address":"7021 Haycock Rd",
    "sg:city":"Falls Church",
    "sg:classifiers":[
        {
            "category":"Manufacturing",
            "subcategory":"Tools & Machinery",
            "type":"Manufacturing & Wholesale Goods"
        }
    ],
    "sg:phone":"+1 703 241 1644",
    "sg:postcode":"22043",
    "sg:province":"VA",
    "sg:tags":[
        "computer",
        "storage",
        "devices"
    ],
    "wof:name":"Ciprico Inc",
    "wof:placetype":"venue"
},
  "geometry": {"coordinates":[-77.18764,38.89716],"type":"Point"}
}