{
  "type": "Feature",
  "properties": {
    "iso:country":"US",
    "sg:address":"3001 Space Rd",
    "sg:city":"Richmond",
    "sg:classifiers":[
        {
            "category":"Building & Trades",
            "subcategory":"Construction",
            "type":"Services"
        },
        {
            "category":"Building & Trades",
            "subcategory":"Plumbing",
            "type":"Services"
        }
    ],
    "sg:phone":"+1 804 714 2640",
    "sg:postcode":"23234",
    "sg:province":"VA",
    "sg:tags":[
        "heavy",
        "contractor",
        "mechanical"
    ],
    "wof:name":"Frank Lill & Son Inc",
    "wof:placetype":"venue"
},
  "geometry": {"coordinates":[-77.457803,37.459043],"type":"Point"}
}