{
  "type": "Feature",
  "properties": {
    "iso:country":"US",
    "sg:address":"120 N Main St",
    "sg:city":"Pearisburg",
    "sg:classifiers":[
        {
            "category":"Government",
            "subcategory":"Court House",
            "type":"Public Place"
        }
    ],
    "sg:phone":"+1 540 921 2428",
    "sg:postcode":"24134",
    "sg:province":"VA",
    "sg:tags":[
        "county"
    ],
    "wof:name":"Circuit Court Judge",
    "wof:placetype":"venue"
},
  "geometry": {"coordinates":[-80.735191,37.326615],"type":"Point"}
}