{
  "type": "Feature",
  "properties": {
    "addr:full":"1302 Arce Ct Chesapeake VA 23322",
    "addr:housenumber":"1302",
    "addr:postcode":"23322",
    "addr:street":"Arce Ct",
    "iso:country":"US",
    "sg:address":"1302 Arce Ct",
    "sg:city":"Chesapeake",
    "sg:classifiers":[
        {
            "category":"Building & Trades",
            "subcategory":"Cleaning & Sanitation",
            "type":"Services"
        }
    ],
    "sg:phone":"+1 757 938 9600",
    "sg:postcode":"23322",
    "sg:province":"VA",
    "wof:name":"Service Master Professional",
    "wof:placetype":"venue"
},
  "geometry": {"coordinates":[-76.293093,36.711898],"type":"Point"}
}