{
  "type": "Feature",
  "properties": {
    "iso:country":"US",
    "sg:address":"14207 Pond Chase Pl",
    "sg:city":"Midlothian",
    "sg:classifiers":[
        {
            "category":"Professional",
            "subcategory":"Engineering",
            "type":"Services"
        }
    ],
    "sg:phone":"+1 804 938 8864",
    "sg:postcode":"23113",
    "sg:province":"VA",
    "sg:tags":[
        "civil",
        "engineer"
    ],
    "wof:name":"Sekiv Solutions",
    "wof:placetype":"venue"
},
  "geometry": {"coordinates":[-77.66498300000001,37.550685],"type":"Point"}
}