{
  "type": "Feature",
  "properties": {
    "addr:full":"303 Church St SE Blacksburg VA 24060",
    "addr:housenumber":"303",
    "addr:postcode":"24060",
    "addr:street":"Church St Se",
    "iso:country":"US",
    "sg:address":"303 Church St SE",
    "sg:city":"Blacksburg",
    "sg:classifiers":[
        {
            "category":"Health Services",
            "subcategory":"Hospital",
            "type":"Services"
        }
    ],
    "sg:phone":"+1 540 951 4990",
    "sg:postcode":"24060",
    "sg:province":"VA",
    "sg:tags":[
        "mental"
    ],
    "wof:name":"Mental Health Assn-New River",
    "wof:placetype":"venue"
},
  "geometry": {"coordinates":[-80.411552,37.228534],"type":"Point"}
}