{
  "type": "Feature",
  "properties": {
    "addr:full":"919 E Church St Martinsville VA 24112",
    "addr:housenumber":"919",
    "addr:postcode":"24112",
    "addr:street":"E Church St",
    "iso:country":"US",
    "sg:address":"919 E Church St",
    "sg:city":"Martinsville",
    "sg:classifiers":[
        {
            "category":"Retail",
            "subcategory":"Repair Shop",
            "type":"Services"
        }
    ],
    "sg:phone":"+1 276 632 1186",
    "sg:postcode":"24112",
    "sg:province":"VA",
    "sg:tags":[
        "welding"
    ],
    "wof:name":"Whitener Welding",
    "wof:placetype":"venue"
},
  "geometry": {"coordinates":[-79.85262299999999,36.692556],"type":"Point"}
}