{
  "type": "Feature",
  "properties": {
    "iso:country":"US",
    "sg:address":"743 Mountainwood Rd",
    "sg:city":"Charlottesville",
    "sg:classifiers":[
        {
            "category":"Real Estate",
            "subcategory":"Real Estate Operator",
            "type":"Services"
        }
    ],
    "sg:phone":"+1 434 977 4710",
    "sg:postcode":"22903",
    "sg:province":"VA",
    "sg:tags":[
        "apartment"
    ],
    "wof:name":"Meadows The",
    "wof:placetype":"venue"
},
  "geometry": {"coordinates":[-78.525177,38.007491],"type":"Point"}
}