{
  "type": "Feature",
  "properties": {
    "addr:full":"12719 Cottage Mill Rd Midlothian VA 23114",
    "addr:housenumber":"12719",
    "addr:postcode":"23114",
    "addr:street":"Cottage Mill Rd",
    "iso:country":"US",
    "sg:address":"12719 Cottage Mill Rd",
    "sg:city":"Midlothian",
    "sg:classifiers":[
        {
            "category":"Wholesale",
            "subcategory":"Machinery & Supplies",
            "type":"Manufacturing & Wholesale Goods"
        }
    ],
    "sg:phone":"+1 804 594 0591",
    "sg:postcode":"23114",
    "sg:province":"VA",
    "sg:tags":[
        "equipment",
        "industrial"
    ],
    "wof:name":"KSB North East",
    "wof:placetype":"venue"
},
  "geometry": {"coordinates":[-77.636987,37.470916],"type":"Point"}
}