{
  "type": "Feature",
  "properties": {
    "iso:country":"US",
    "sg:address":"4311 Chamberlayne Ave",
    "sg:city":"Richmond",
    "sg:classifiers":[
        {
            "category":"Building & Trades",
            "subcategory":"Construction",
            "type":"Services"
        }
    ],
    "sg:phone":"+1 804 261 5642",
    "sg:postcode":"23227",
    "sg:province":"VA",
    "sg:tags":[
        "house"
    ],
    "wof:name":"Jet Paint & Decorator Co",
    "wof:placetype":"venue"
},
  "geometry": {"coordinates":[-77.449286,37.597003],"type":"Point"}
}