{
  "type": "Feature",
  "properties": {
    "iso:country":"US",
    "sg:address":"1926 Elly Rd",
    "sg:city":"Aroda",
    "sg:classifiers":[
        {
            "category":"Organizations",
            "subcategory":"Religious Organization",
            "type":"Services"
        }
    ],
    "sg:phone":"+1 540 948 6834",
    "sg:postcode":"22709",
    "sg:province":"VA",
    "sg:tags":[
        "church"
    ],
    "wof:name":"Gospel Light Mennonite Church",
    "wof:placetype":"venue"
},
  "geometry": {"coordinates":[-78.20373600000001,38.341835],"type":"Point"}
}