{
  "type": "Feature",
  "properties": {
    "addr:full":"14220 Sullyfield Cir Chantilly VA 20151",
    "addr:housenumber":"14220",
    "addr:postcode":"20151",
    "addr:street":"Sullyfield Cir",
    "iso:country":"US",
    "sg:address":"14220 Sullyfield Cir",
    "sg:city":"Chantilly",
    "sg:classifiers":[
        {
            "category":"Home & Garden",
            "subcategory":"Furniture",
            "type":"Retail Goods"
        }
    ],
    "sg:phone":"+1 703 968 0526",
    "sg:postcode":"20151",
    "sg:province":"VA",
    "wof:name":"Village Antiques & Rprdctns",
    "wof:placetype":"venue"
},
  "geometry": {"coordinates":[-77.437618,38.894438],"type":"Point"}
}