{
  "type": "Feature",
  "properties": {
    "iso:country":"US",
    "sg:address":"10000 Brook Rd",
    "sg:city":"Glen Allen",
    "sg:classifiers":[
        {
            "category":"Restaurant",
            "type":"Food & Drink"
        }
    ],
    "sg:menulink":"http://www.allmenus.com/va/fairfield/187889-mcdonalds/menu/",
    "sg:postcode":"23059",
    "sg:province":"VA",
    "sg:tags":[
        "burger",
        "american"
    ],
    "wof:name":"McDonald's",
    "wof:placetype":"venue"
},
  "geometry": {"coordinates":[-77.461477,37.671894],"type":"Point"}
}