{
  "type": "Feature",
  "properties": {
    "iso:country":"US",
    "sg:address":"10719 Catharpin Rd",
    "sg:city":"Spotsylvania",
    "sg:classifiers":[
        {
            "category":"Food & Beverages",
            "subcategory":"Groceries & Convenience Stores",
            "type":"Retail Goods"
        }
    ],
    "sg:phone":"+1 540 972 4335",
    "sg:postcode":"22553",
    "sg:province":"VA",
    "wof:name":"Todd's Tavern Market Inc",
    "wof:placetype":"venue"
},
  "geometry": {"coordinates":[-77.667202,38.248666],"type":"Point"}
}