{
  "type": "Feature",
  "properties": {
    "iso:country":"US",
    "sg:address":"7 Radford St",
    "sg:city":"Christiansburg",
    "sg:classifiers":[
        {
            "category":"Professional",
            "subcategory":"Lawyer & Legal Services",
            "type":"Services"
        }
    ],
    "sg:phone":"+1 540 382 6633",
    "sg:postcode":"24073",
    "sg:province":"VA",
    "wof:name":"John S Huntington",
    "wof:placetype":"venue"
},
  "geometry": {"coordinates":[-80.413566,37.126862],"type":"Point"}
}