{
  "type": "Feature",
  "properties": {
    "addr:full":"15217 Nottingham Dr Manassas VA 20112",
    "addr:housenumber":"15217",
    "addr:postcode":"20112",
    "addr:street":"Nottingham Dr",
    "iso:country":"US",
    "sg:address":"15217 Nottingham Dr",
    "sg:city":"Manassas",
    "sg:classifiers":[
        {
            "category":"Building & Trades",
            "subcategory":"Construction",
            "type":"Services"
        }
    ],
    "sg:phone":"+1 703 583 2260",
    "sg:postcode":"20112",
    "sg:province":"VA",
    "sg:tags":[
        "general",
        "contractor"
    ],
    "wof:name":"Moore Brothers Co Inc",
    "wof:placetype":"venue"
},
  "geometry": {"coordinates":[-77.40453599999999,38.620019],"type":"Point"}
}