{
  "type": "Feature",
  "properties": {
    "iso:country":"US",
    "sg:address":"1401 Johnston Willis Dr",
    "sg:city":"Richmond",
    "sg:classifiers":[
        {
            "category":"Health Services",
            "subcategory":"Doctor",
            "type":"Services"
        }
    ],
    "sg:phone":"+1 804 330 2164",
    "sg:postcode":"23235",
    "sg:province":"VA",
    "sg:tags":[
        "physician",
        "surgeon"
    ],
    "wof:name":"Johns Radiation Oncology",
    "wof:placetype":"venue"
},
  "geometry": {"coordinates":[-77.597387,37.51084],"type":"Point"}
}