{
  "type": "Feature",
  "properties": {
    "iso:country":"US",
    "sg:address":"108 Tally-Ho Dr",
    "sg:city":"Charlottesville",
    "sg:classifiers":[
        {
            "category":"Professional",
            "subcategory":"Management & Consulting",
            "type":"Services"
        }
    ],
    "sg:phone":"+1 434 979 3489",
    "sg:postcode":"22901",
    "sg:province":"VA",
    "wof:name":"Norwood Management L L C",
    "wof:placetype":"venue"
},
  "geometry": {"coordinates":[-78.526151,38.065091],"type":"Point"}
}