{
  "type": "Feature",
  "properties": {
    "iso:country":"US",
    "sg:address":"4328 Horse Shoe Bend Rd",
    "sg:city":"Roanoke",
    "sg:classifiers":[
        {
            "category":"Professional",
            "subcategory":"Art Services",
            "type":"Services"
        }
    ],
    "sg:phone":"+1 540 427 1446",
    "sg:postcode":"24014",
    "sg:province":"VA",
    "sg:tags":[
        "designer",
        "display",
        "producer"
    ],
    "wof:name":"Eastwood Design Inc",
    "wof:placetype":"venue"
},
  "geometry": {"coordinates":[-79.87373100000001,37.231735],"type":"Point"}
}