{
  "type": "Feature",
  "properties": {
    "iso:country":"US",
    "sg:address":"3552 Seminole Trl",
    "sg:city":"Charlottesville",
    "sg:classifiers":[
        {
            "category":"Wholesale",
            "subcategory":"Electrical",
            "type":"Manufacturing & Wholesale Goods"
        }
    ],
    "sg:phone":"+1 434 975 3275",
    "sg:postcode":"22911",
    "sg:province":"VA",
    "sg:tags":[
        "generator"
    ],
    "wof:name":"Never Dark Whole Hse Gnrtrs",
    "wof:placetype":"venue"
},
  "geometry": {"coordinates":[-78.434791,38.133006],"type":"Point"}
}