{
  "type": "Feature",
  "properties": {
    "addr:full":"91 Washington Square Plz Fredericksburg VA 22405",
    "addr:housenumber":"91",
    "addr:postcode":"22405",
    "addr:street":"Washington Square Plz",
    "iso:country":"US",
    "sg:address":"91 Washington Square Plz",
    "sg:city":"Fredericksburg",
    "sg:classifiers":[
        {
            "category":"Restaurant",
            "type":"Food & Drink"
        }
    ],
    "sg:menulink":"http://www.allmenus.com/va/george-washington/147657-subway/menu/",
    "sg:phone":"+1 540 373 5383",
    "sg:postcode":"22405",
    "sg:province":"VA",
    "sg:tags":[
        "american",
        "sandwich"
    ],
    "wof:name":"Subway",
    "wof:placetype":"venue"
},
  "geometry": {"coordinates":[-77.437479,38.28553],"type":"Point"}
}