{
  "type": "Feature",
  "properties": {
    "iso:country":"US",
    "sg:address":"11976 Old Washington Hwy",
    "sg:city":"Glen Allen",
    "sg:classifiers":[
        {
            "category":"Professional",
            "subcategory":"Advertising",
            "type":"Services"
        }
    ],
    "sg:phone":"+1 804 261 0003",
    "sg:postcode":"23059",
    "sg:province":"VA",
    "sg:website":"www.impactmedia-va.com",
    "wof:name":"Impact Media",
    "wof:placetype":"venue"
},
  "geometry": {"coordinates":[-77.49229,37.693816],"type":"Point"}
}