{
  "type": "Feature",
  "properties": {
    "iso:country":"US",
    "sg:address":"1508 Mercer Rd.",
    "sg:city":"Haymarket",
    "sg:classifiers":[
        {
            "category":"Building & Trades",
            "subcategory":"Landscaping Services",
            "type":"Services"
        }
    ],
    "sg:phone":"+1 703 753 1354",
    "sg:postcode":"20169",
    "sg:province":"VA",
    "sg:website":"landscapeanddesigncenter.com",
    "wof:name":"Landscape & Design Center",
    "wof:placetype":"venue"
},
  "geometry": {"coordinates":[-77.655359,38.926393],"type":"Point"}
}