{
  "type": "Feature",
  "properties": {
    "iso:country":"US",
    "sg:address":"2780 General Puller Hwy",
    "sg:city":"Saluda",
    "sg:classifiers":[
        {
            "category":"Health Services",
            "subcategory":"Clinic",
            "type":"Services"
        }
    ],
    "sg:phone":"+1 804 758 0330",
    "sg:postcode":"23149",
    "sg:province":"VA",
    "sg:tags":[
        "agency",
        "welfare"
    ],
    "wof:name":"Middlesex Health Dept Environ",
    "wof:placetype":"venue"
},
  "geometry": {"coordinates":[-76.564151,37.601985],"type":"Point"}
}