{
  "type": "Feature",
  "properties": {
    "iso:country":"US",
    "sg:address":"23 N King St 2nd Fl",
    "sg:city":"Leesburg",
    "sg:classifiers":[
        {
            "category":"Professional",
            "subcategory":"Lawyer & Legal Services",
            "type":"Services"
        }
    ],
    "sg:phone":"+1 703 779 4019",
    "sg:postcode":"20176",
    "sg:province":"VA",
    "sg:tags":[
        "attorney",
        "law",
        "family",
        "divorce",
        "plan",
        "criminal"
    ],
    "wof:name":"Hendrix/Harrington Pc",
    "wof:placetype":"venue"
},
  "geometry": {"coordinates":[-77.564414,39.11572],"type":"Point"}
}