{
  "type": "Feature",
  "properties": {
    "addr:full":"101 Hurdle Dr Chesapeake VA 23322",
    "addr:housenumber":"101",
    "addr:postcode":"23322",
    "addr:street":"Hurdle Dr",
    "iso:country":"US",
    "sg:address":"101 Hurdle Dr",
    "sg:city":"Chesapeake",
    "sg:classifiers":[
        {
            "category":"Organizations",
            "subcategory":"Religious Organization",
            "type":"Services"
        }
    ],
    "sg:phone":"+1 757 482 2213",
    "sg:postcode":"23322",
    "sg:province":"VA",
    "wof:name":"Great Bridge Church Of Christ",
    "wof:placetype":"venue"
},
  "geometry": {"coordinates":[-76.23728,36.701502],"type":"Point"}
}