{
  "type": "Feature",
  "properties": {
    "addr:full":"8412 Old Keene Mill Rd Springfield VA 22152",
    "addr:housenumber":"8412",
    "addr:postcode":"22152",
    "addr:street":"Old Keene Mill Rd",
    "iso:country":"US",
    "sg:address":"8412 Old Keene Mill Rd",
    "sg:city":"Springfield",
    "sg:classifiers":[
        {
            "category":"Personal",
            "subcategory":"Beauty Salon",
            "type":"Services"
        },
        {
            "category":"Personal",
            "subcategory":"Skin Care",
            "type":"Services"
        }
    ],
    "sg:phone":"+1 703 913 3223",
    "sg:postcode":"22152",
    "sg:province":"VA",
    "wof:name":"Beaux Visages European Skin Care Center",
    "wof:placetype":"venue"
},
  "geometry": {"coordinates":[-77.234224,38.779071],"type":"Point"}
}