{
  "type": "Feature",
  "properties": {
    "addr:full":"3042 Poor House Rd Goochland VA 23063",
    "addr:housenumber":"3042",
    "addr:postcode":"23063",
    "addr:street":"Poor House Rd",
    "iso:country":"US",
    "sg:address":"3042 Poor House Rd",
    "sg:city":"Goochland",
    "sg:phone":"+1 804 556 6229",
    "sg:postcode":"23063",
    "sg:province":"VA",
    "sg:tags":[
        "farm",
        "field",
        "crop"
    ],
    "wof:name":"Hidaway Farm",
    "wof:placetype":"venue"
},
  "geometry": {"coordinates":[-77.886872,37.726308],"type":"Point"}
}