{
  "type": "Feature",
  "properties": {
    "iso:country":"US",
    "sg:address":"6400 Grovedale Dr",
    "sg:city":"Alexandria",
    "sg:classifiers":[
        {
            "category":"Professional",
            "subcategory":"Computer Services",
            "type":"Services"
        }
    ],
    "sg:phone":"+1 703 683 7287",
    "sg:postcode":"22310",
    "sg:province":"VA",
    "sg:tags":[
        "information",
        "technology"
    ],
    "wof:name":"Anteon Corporation (va)",
    "wof:placetype":"venue"
},
  "geometry": {"coordinates":[-77.148246,38.778558],"type":"Point"}
}