{
  "type": "Feature",
  "properties": {
    "addr:full":"225 N Court Ave Covington VA 24426",
    "addr:housenumber":"225",
    "addr:postcode":"24426",
    "addr:street":"N Court Ave",
    "iso:country":"US",
    "sg:address":"225 N Court Ave",
    "sg:city":"Covington",
    "sg:classifiers":[
        {
            "category":"Organizations",
            "subcategory":"Religious Organization",
            "type":"Services"
        }
    ],
    "sg:phone":"+1 540 962 9098",
    "sg:postcode":"24426",
    "sg:province":"VA",
    "sg:tags":[
        "church"
    ],
    "wof:name":"Church Of God",
    "wof:placetype":"venue"
},
  "geometry": {"coordinates":[-79.99551700000001,37.792187],"type":"Point"}
}