{
  "type": "Feature",
  "properties": {
    "addr:full":"1816 N Alanton Dr Virginia Beach VA 23454",
    "addr:housenumber":"1816",
    "addr:postcode":"23454",
    "addr:street":"N Alanton Dr",
    "iso:country":"US",
    "sg:address":"1816 N Alanton Dr",
    "sg:city":"Virginia Beach",
    "sg:classifiers":[
        {
            "category":"Organizations",
            "subcategory":"Membership Organization",
            "type":"Services"
        }
    ],
    "sg:phone":"+1 757 481 7332",
    "sg:postcode":"23454",
    "sg:province":"VA",
    "wof:name":"Bellissima Inc",
    "wof:placetype":"venue"
},
  "geometry": {"coordinates":[-76.027221,36.887035],"type":"Point"}
}