{
  "type": "Feature",
  "properties": {
    "addr:full":"6351 Cotswold Way Herndon VA 20187",
    "addr:housenumber":"6351",
    "addr:postcode":"20187",
    "addr:street":"Cotswold Way",
    "iso:country":"US",
    "sg:address":"6351 Cotswold Way",
    "sg:city":"Herndon",
    "sg:classifiers":[
        {
            "category":"Retail",
            "subcategory":"Repair Shop",
            "type":"Services"
        }
    ],
    "sg:phone":"+1 703 471 4471",
    "sg:postcode":"20187",
    "sg:province":"VA",
    "wof:name":"Net Wide Computing",
    "wof:placetype":"venue"
},
  "geometry": {"coordinates":[-77.73984299999999,38.776798],"type":"Point"}
}