{
  "type": "Feature",
  "properties": {
    "addr:full":"8766 Simmers Valley Rd Harrisonburg VA 22802",
    "addr:postcode":"8766;22802",
    "addr:street":"Simmers Valley Rd",
    "iso:country":"US",
    "sg:address":"8766 Simmers Valley Rd",
    "sg:city":"Harrisonburg",
    "sg:classifiers":[
        {
            "category":"Retail",
            "subcategory":"Animal Services",
            "type":"Services"
        }
    ],
    "sg:phone":"+1 540 833 6309",
    "sg:postcode":"22802",
    "sg:province":"VA",
    "wof:name":"David Simmers",
    "wof:placetype":"venue"
},
  "geometry": {"coordinates":[-78.799285,38.540689],"type":"Point"}
}