{
  "type": "Feature",
  "properties": {
    "iso:country":"US",
    "sg:address":"2514 Franklin Rd SW",
    "sg:city":"Roanoke",
    "sg:classifiers":[
        {
            "category":"Health Services",
            "subcategory":"Clinic",
            "type":"Services"
        }
    ],
    "sg:phone":"+1 540 342 6539",
    "sg:postcode":"24014",
    "sg:province":"VA",
    "sg:tags":[
        "home",
        "care"
    ],
    "wof:name":"Medi Home Care",
    "wof:placetype":"venue"
},
  "geometry": {"coordinates":[-79.959383,37.246839],"type":"Point"}
}