{
  "type": "Feature",
  "properties": {
    "iso:country":"US",
    "sg:address":"105 28th St",
    "sg:city":"Newport News",
    "sg:classifiers":[
        {
            "category":"Restaurant",
            "type":"Food & Drink"
        }
    ],
    "sg:phone":"+1 757 244 1724",
    "sg:postcode":"23607",
    "sg:province":"VA",
    "wof:name":"Family Shack Restaurant Inc",
    "wof:placetype":"venue"
},
  "geometry": {"coordinates":[-76.43163199999999,36.979701],"type":"Point"}
}