{
  "type": "Feature",
  "properties": {
    "iso:country":"US",
    "sg:address":"4732 Harrison Rd",
    "sg:city":"Fredericksburg",
    "sg:classifiers":[
        {
            "category":"Building & Trades",
            "subcategory":"Construction",
            "type":"Services"
        }
    ],
    "sg:phone":"+1 540 898 8420",
    "sg:postcode":"22408",
    "sg:province":"VA",
    "sg:tags":[
        "contractor"
    ],
    "wof:name":"Pool Crafts",
    "wof:placetype":"venue"
},
  "geometry": {"coordinates":[-77.500497,38.266615],"type":"Point"}
}