{
  "type": "Feature",
  "properties": {
    "iso:country":"US",
    "sg:address":"6351 Brampton Ct",
    "sg:city":"Alexandria",
    "sg:classifiers":[
        {
            "category":"Communications",
            "type":"Services"
        }
    ],
    "sg:phone":"+1 703 751 5621",
    "sg:postcode":"22304",
    "sg:province":"VA",
    "sg:tags":[
        "consultant",
        "telecommunication"
    ],
    "wof:name":"Bennett Consultant",
    "wof:placetype":"venue"
},
  "geometry": {"coordinates":[-77.14672,38.810602],"type":"Point"}
}