{
  "type": "Feature",
  "properties": {
    "iso:country":"US",
    "sg:address":"7207 Lockport Pl",
    "sg:city":"Lorton",
    "sg:classifiers":[
        {
            "category":"Manufacturing",
            "subcategory":"Tools & Machinery",
            "type":"Manufacturing & Wholesale Goods"
        }
    ],
    "sg:phone":"+1 703 339 7001",
    "sg:postcode":"22079",
    "sg:province":"VA",
    "sg:tags":[
        "equipment",
        "cleaning",
        "sanitation",
        "mfg"
    ],
    "wof:name":"Sanitech",
    "wof:placetype":"venue"
},
  "geometry": {"coordinates":[-77.193837,38.715035],"type":"Point"}
}