{
  "type": "Feature",
  "properties": {
    "iso:country":"US",
    "sg:address":"3205 Camellia Dr",
    "sg:city":"Portsmouth",
    "sg:classifiers":[
        {
            "category":"Shopping",
            "subcategory":"Clothing, Apparel, & Fashions",
            "type":"Retail Goods"
        }
    ],
    "sg:phone":"+1 757 686 5686",
    "sg:postcode":"23703",
    "sg:province":"VA",
    "sg:tags":[
        "lingerie"
    ],
    "wof:name":"Delicate Touch",
    "wof:placetype":"venue"
},
  "geometry": {"coordinates":[-76.386527,36.862358],"type":"Point"}
}