{
  "type": "Feature",
  "properties": {
    "iso:country":"US",
    "sg:address":"3206 Barnes Spring Ter",
    "sg:city":"Midlothian",
    "sg:classifiers":[
        {
            "category":"Retail",
            "subcategory":"Repair Shop",
            "type":"Services"
        }
    ],
    "sg:phone":"+1 804 763 1441",
    "sg:postcode":"23112",
    "sg:province":"VA",
    "wof:name":"ServiceMaster",
    "wof:placetype":"venue"
},
  "geometry": {"coordinates":[-77.65810999999999,37.444284],"type":"Point"}
}