{
  "type": "Feature",
  "properties": {
    "addr:full":"2507 N Florida St Arlington VA 22207",
    "addr:housenumber":"2507",
    "addr:postcode":"22207",
    "addr:street":"N Florida St",
    "iso:country":"US",
    "sg:address":"2507 N Florida St",
    "sg:city":"Arlington",
    "sg:classifiers":[
        {
            "category":"Professional",
            "subcategory":"Art Services",
            "type":"Services"
        }
    ],
    "sg:phone":"+1 703 536 6398",
    "sg:postcode":"22207",
    "sg:province":"VA",
    "sg:tags":[
        "commercial",
        "design"
    ],
    "wof:name":"Ann Pellegrino",
    "wof:placetype":"venue"
},
  "geometry": {"coordinates":[-77.13624,38.898753],"type":"Point"}
}