{
  "type": "Feature",
  "properties": {
    "addr:full":"16126 Lee Hwy Gainesville VA 20155",
    "addr:housenumber":"16126",
    "addr:postcode":"20155",
    "addr:street":"Lee Hwy",
    "iso:country":"US",
    "sg:address":"16126 Lee Hwy",
    "sg:city":"Gainesville",
    "sg:classifiers":[
        {
            "category":"Wholesale",
            "subcategory":"Computers",
            "type":"Manufacturing & Wholesale Goods"
        }
    ],
    "sg:phone":"+1 703 753 4350",
    "sg:postcode":"20155",
    "sg:province":"VA",
    "sg:tags":[
        "system"
    ],
    "wof:name":"Conservative Computer Inc",
    "wof:placetype":"venue"
},
  "geometry": {"coordinates":[-77.669073,38.781661],"type":"Point"}
}