{
  "type": "Feature",
  "properties": {
    "addr:full":"43277 Spinks Ferry Rd Leesburg VA 20176",
    "addr:postcode":"43277;20176",
    "addr:street":"Spinks Ferry Rd",
    "iso:country":"US",
    "sg:address":"43277 Spinks Ferry Rd",
    "sg:city":"Leesburg",
    "sg:classifiers":[
        {
            "category":"Shopping",
            "subcategory":"Beauty & Cosmetics",
            "type":"Retail Goods"
        }
    ],
    "sg:phone":"+1 703 443 9836",
    "sg:postcode":"20176",
    "sg:province":"VA",
    "sg:tags":[
        "surgical",
        "appliance"
    ],
    "wof:name":"Lost Creek Vineyard & Winery",
    "wof:placetype":"venue"
},
  "geometry": {"coordinates":[-77.500466,39.208156],"type":"Point"}
}