{
  "type": "Feature",
  "properties": {
    "iso:country":"US",
    "sg:address":"5881 Starkey Rd",
    "sg:city":"Roanoke",
    "sg:classifiers":[
        {
            "category":"Home & Garden",
            "subcategory":"Garden Supply",
            "type":"Retail Goods"
        },
        {
            "category":"Shopping",
            "subcategory":"Florist",
            "type":"Retail Goods"
        }
    ],
    "sg:phone":"+1 540 989 2122",
    "sg:postcode":"24018",
    "sg:province":"VA",
    "wof:name":"Greenbrier Nurseries",
    "wof:placetype":"venue"
},
  "geometry": {"coordinates":[-79.995132,37.202006],"type":"Point"}
}