{
  "type": "Feature",
  "properties": {
    "addr:full":"3701 5th St S Arlington VA 22204",
    "addr:housenumber":"3701",
    "addr:postcode":"22204",
    "addr:street":"5Th St S",
    "iso:country":"US",
    "sg:address":"3701 5th St S",
    "sg:city":"Arlington",
    "sg:classifiers":[
        {
            "category":"Personal",
            "type":"Services"
        }
    ],
    "sg:phone":"+1 703 587 4059",
    "sg:postcode":"22204",
    "sg:province":"VA",
    "sg:tags":[
        "bureau"
    ],
    "wof:name":"P Y Enterprises",
    "wof:placetype":"venue"
},
  "geometry": {"coordinates":[-77.097053,38.866943],"type":"Point"}
}