{
  "type": "Feature",
  "properties": {
    "addr:full":"7716 Richmond Hwy Alexandria VA 22306",
    "addr:housenumber":"7716",
    "addr:postcode":"22306",
    "addr:street":"Richmond Hwy",
    "iso:country":"US",
    "sg:address":"7716 Richmond Hwy",
    "sg:city":"Alexandria",
    "sg:classifiers":[
        {
            "category":"Personal",
            "subcategory":"Beauty Salon",
            "type":"Services"
        }
    ],
    "sg:phone":"+1 703 360 0962",
    "sg:postcode":"22306",
    "sg:province":"VA",
    "sg:tags":[
        "shop",
        "manicuring"
    ],
    "wof:name":"Happy Nails II",
    "wof:placetype":"venue"
},
  "geometry": {"coordinates":[-77.08316000000001,38.748036],"type":"Point"}
}