{
  "type": "Feature",
  "properties": {
    "iso:country":"US",
    "sg:address":"97 Market St",
    "sg:city":"Onancock",
    "sg:classifiers":[
        {
            "category":"Banks & Credit Unions",
            "subcategory":"Investment Brokerage",
            "type":"Services"
        }
    ],
    "sg:phone":"+1 757 787 4041",
    "sg:postcode":"23417",
    "sg:province":"VA",
    "sg:tags":[
        "consultant",
        "planning",
        "financial"
    ],
    "wof:name":"Lawrence C Lees",
    "wof:placetype":"venue"
},
  "geometry": {"coordinates":[-75.743407,37.711035],"type":"Point"}
}