{
  "type": "Feature",
  "properties": {
    "iso:country":"US",
    "sg:address":"4600 King St",
    "sg:city":"Alexandria",
    "sg:classifiers":[
        {
            "category":"Professional",
            "subcategory":"Management & Consulting",
            "type":"Services"
        }
    ],
    "sg:phone":"+1 703 998 6091",
    "sg:postcode":"22302",
    "sg:province":"VA",
    "sg:tags":[
        "consultant",
        "business"
    ],
    "wof:name":"International Research Cons",
    "wof:placetype":"venue"
},
  "geometry": {"coordinates":[-77.106565,38.840731],"type":"Point"}
}