{
  "type": "Feature",
  "properties": {
    "addr:full":"309 Bank St Franklin VA 23890",
    "addr:housenumber":"309",
    "addr:postcode":"23890",
    "addr:street":"Bank St",
    "iso:country":"US",
    "sg:address":"309 Bank St",
    "sg:city":"Franklin",
    "sg:classifiers":[
        {
            "category":"Freight",
            "type":"Transportation"
        }
    ],
    "sg:phone":"+1 757 569 0960",
    "sg:postcode":"23890",
    "sg:province":"VA",
    "sg:tags":[
        "local",
        "storage",
        "trucking"
    ],
    "wof:name":"Scott Enterprises",
    "wof:placetype":"venue"
},
  "geometry": {"coordinates":[-77.089579,37.025961],"type":"Point"}
}