{
  "type": "Feature",
  "properties": {
    "addr:full":"777 Beards Creek Rd Ferrum VA 24088",
    "addr:housenumber":"777",
    "addr:postcode":"24088",
    "addr:street":"Beards Creek Rd",
    "iso:country":"US",
    "sg:address":"777 Beards Creek Rd",
    "sg:city":"Ferrum",
    "sg:classifiers":[
        {
            "category":"Personal",
            "subcategory":"Beauty Salon",
            "type":"Services"
        }
    ],
    "sg:phone":"+1 540 365 2929",
    "sg:postcode":"24088",
    "sg:province":"VA",
    "wof:name":"Linda's Beauty Salon",
    "wof:placetype":"venue"
},
  "geometry": {"coordinates":[-80.096953,36.900449],"type":"Point"}
}