{
  "type": "Feature",
  "properties": {
    "iso:country":"US",
    "sg:address":"1503 Santa Rosa Rd",
    "sg:city":"Richmond",
    "sg:classifiers":[
        {
            "category":"Health Services",
            "subcategory":"Clinic",
            "type":"Services"
        }
    ],
    "sg:phone":"+1 804 282 3113",
    "sg:postcode":"23229",
    "sg:province":"VA",
    "wof:name":"Va Health Ctr Inc",
    "wof:placetype":"venue"
},
  "geometry": {"coordinates":[-77.548474,37.60221],"type":"Point"}
}