{
  "type": "Feature",
  "properties": {
    "addr:full":"20080 Brewers Neck Blvd Carrollton VA 23314",
    "addr:housenumber":"20080",
    "addr:postcode":"23314",
    "addr:street":"Brewers Neck Blvd",
    "iso:country":"US",
    "sg:address":"20080 Brewers Neck Blvd",
    "sg:city":"Carrollton",
    "sg:classifiers":[
        {
            "category":"Building & Trades",
            "subcategory":"Construction",
            "type":"Services"
        }
    ],
    "sg:phone":"+1 757 249 2400",
    "sg:postcode":"23314",
    "sg:province":"VA",
    "sg:tags":[
        "nonresidential"
    ],
    "wof:name":"Econo Lodge",
    "wof:placetype":"venue"
},
  "geometry": {"coordinates":[-76.57032599999999,36.940363],"type":"Point"}
}