{
  "type": "Feature",
  "properties": {
    "addr:full":"675 Peter Jefferson Pkwy Charlottesville VA 22911",
    "addr:housenumber":"675",
    "addr:postcode":"22911",
    "addr:street":"Peter Jefferson Pkwy",
    "iso:country":"US",
    "sg:address":"675 Peter Jefferson Pkwy",
    "sg:city":"Charlottesville",
    "sg:classifiers":[
        {
            "category":"Utilities",
            "subcategory":"Electric",
            "type":"Services"
        }
    ],
    "sg:phone":"+1 434 979 2500",
    "sg:postcode":"22911",
    "sg:province":"VA",
    "wof:name":"Westmorland Resources",
    "wof:placetype":"venue"
},
  "geometry": {"coordinates":[-78.435351,38.023551],"type":"Point"}
}