{
  "type": "Feature",
  "properties": {
    "addr:full":"521 Rookwood Dr Charlottesville VA 22903",
    "addr:housenumber":"521",
    "addr:postcode":"22903",
    "addr:street":"Rookwood Dr",
    "iso:country":"US",
    "sg:address":"521 Rookwood Dr",
    "sg:city":"Charlottesville",
    "sg:classifiers":[
        {
            "category":"Professional",
            "subcategory":"Management & Consulting",
            "type":"Services"
        }
    ],
    "sg:phone":"+1 434 296 1785",
    "sg:postcode":"22903",
    "sg:province":"VA",
    "wof:name":"Meffert Enterprises Ltd Inc",
    "wof:placetype":"venue"
},
  "geometry": {"coordinates":[-78.554419,38.037138],"type":"Point"}
}