{
  "type": "Feature",
  "properties": {
    "addr:full":"6224 Old Dominion Dr Mc Lean VA 22101",
    "addr:housenumber":"6224",
    "addr:postcode":"22101",
    "addr:street":"Old Dominion Dr",
    "iso:country":"US",
    "sg:address":"6224 Old Dominion Dr",
    "sg:city":"Mc Lean",
    "sg:classifiers":[
        {
            "category":"Cinema",
            "subcategory":"Movie Rental",
            "type":"Entertainment"
        }
    ],
    "sg:phone":"+1 703 536 5093",
    "sg:postcode":"22101",
    "sg:province":"VA",
    "sg:tags":[
        "leasing",
        "video",
        "disc",
        "tape"
    ],
    "wof:name":"Forbes Video",
    "wof:placetype":"venue"
},
  "geometry": {"coordinates":[-77.152736,38.921091],"type":"Point"}
}