{
  "type": "Feature",
  "properties": {
    "addr:full":"500 Gate City Hwy Bristol VA 24201",
    "addr:housenumber":"500",
    "addr:postcode":"24201",
    "addr:street":"Gate City Hwy",
    "iso:country":"US",
    "sg:address":"500 Gate City Hwy",
    "sg:city":"Bristol",
    "sg:classifiers":[
        {
            "category":"Shopping",
            "subcategory":"Gifts & Souvenirs",
            "type":"Retail Goods"
        }
    ],
    "sg:phone":"+1 276 645 0111",
    "sg:postcode":"24201",
    "sg:province":"VA",
    "sg:tags":[
        "shop"
    ],
    "wof:name":"Birthplace Of Country Music",
    "wof:placetype":"venue"
},
  "geometry": {"coordinates":[-82.21594399999999,36.599123],"type":"Point"}
}