{
  "type": "Feature",
  "properties": {
    "addr:full":"8501 Stonewall Dr Vienna VA 22180",
    "addr:housenumber":"8501",
    "addr:postcode":"22180",
    "addr:street":"Stonewall Dr",
    "iso:country":"US",
    "sg:address":"8501 Stonewall Dr",
    "sg:city":"Vienna",
    "sg:classifiers":[
        {
            "category":"Health Services",
            "subcategory":"Doctor",
            "type":"Services"
        }
    ],
    "sg:phone":"+1 703 560 2663",
    "sg:postcode":"22180",
    "sg:province":"VA",
    "sg:tags":[
        "medical"
    ],
    "wof:name":"Palmetto Psychtric Medicine PA",
    "wof:placetype":"venue"
},
  "geometry": {"coordinates":[-77.23923499999999,38.890065],"type":"Point"}
}