{
  "type": "Feature",
  "properties": {
    "iso:country":"US",
    "sg:address":"1005 Sheffield Dr",
    "sg:city":"Lynchburg",
    "sg:classifiers":[
        {
            "category":"Autos & Motor Vehicles",
            "subcategory":"Auto Supplies",
            "type":"Retail Goods"
        }
    ],
    "sg:phone":"+1 434 237 6469",
    "sg:postcode":"24502",
    "sg:province":"VA",
    "sg:tags":[
        "tire"
    ],
    "wof:name":"KERR Tire & Automotive",
    "wof:placetype":"venue"
},
  "geometry": {"coordinates":[-79.183953,37.370266],"type":"Point"}
}