{
  "type": "Feature",
  "properties": {
    "iso:country":"US",
    "sg:address":"520 Woodlake Cir",
    "sg:city":"Chesapeake",
    "sg:classifiers":[
        {
            "category":"Wholesale",
            "subcategory":"Machinery & Supplies",
            "type":"Manufacturing & Wholesale Goods"
        }
    ],
    "sg:phone":"+1 757 366 9340",
    "sg:postcode":"23320",
    "sg:province":"VA",
    "sg:tags":[
        "equipment",
        "industrial"
    ],
    "sg:website":"www.iscmro.com",
    "wof:name":"Industrial Supply Corporation",
    "wof:placetype":"venue"
},
  "geometry": {"coordinates":[-76.24200500000001,36.783582],"type":"Point"}
}