{
  "type": "Feature",
  "properties": {
    "iso:country":"US",
    "sg:address":"337 High St",
    "sg:city":"Portsmouth",
    "sg:classifiers":[
        {
            "category":"Restaurant",
            "type":"Food & Drink"
        }
    ],
    "sg:phone":"+1 757 397 2728",
    "sg:postcode":"23704",
    "sg:province":"VA",
    "sg:tags":[
        "eating"
    ],
    "wof:name":"Lobscouser Restaurant",
    "wof:placetype":"venue"
},
  "geometry": {"coordinates":[-76.300425,36.835247],"type":"Point"}
}