{
  "type": "Feature",
  "properties": {
    "addr:full":"4975 River Rd W Goochland VA 23063",
    "addr:housenumber":"4975",
    "addr:postcode":"23063",
    "addr:street":"River Rd W Goochland",
    "iso:country":"US",
    "sg:address":"4975 River Rd W",
    "sg:city":"Goochland",
    "sg:classifiers":[
        {
            "category":"Retail",
            "subcategory":"Repair Shop",
            "type":"Services"
        }
    ],
    "sg:phone":"+1 804 457 4138",
    "sg:postcode":"23063",
    "sg:province":"VA",
    "wof:name":"Rapalee Taxidermy Inc",
    "wof:placetype":"venue"
},
  "geometry": {"coordinates":[-78.03116799999999,37.730557],"type":"Point"}
}