{
  "type": "Feature",
  "properties": {
    "iso:country":"US",
    "sg:address":"910 Triangle St",
    "sg:city":"Blacksburg",
    "sg:classifiers":[
        {
            "category":"Fast Food",
            "type":"Food & Drink"
        },
        {
            "category":"Restaurant",
            "type":"Food & Drink"
        }
    ],
    "sg:phone":"+1 540 552 7718",
    "sg:postcode":"24060",
    "sg:province":"VA",
    "sg:tags":[
        "take"
    ],
    "wof:name":"Erw Inc",
    "wof:placetype":"venue"
},
  "geometry": {"coordinates":[-80.413596,37.179971],"type":"Point"}
}