{
  "type": "Feature",
  "properties": {
    "addr:full":"5101 Rochelle Rd Virginia Beach VA 23464",
    "addr:housenumber":"5101",
    "addr:postcode":"23464",
    "addr:street":"Rochelle Rd",
    "iso:country":"US",
    "sg:address":"5101 Rochelle Rd",
    "sg:city":"Virginia Beach",
    "sg:classifiers":[
        {
            "category":"Wholesale",
            "subcategory":"Seafood",
            "type":"Manufacturing & Wholesale Goods"
        }
    ],
    "sg:phone":"+1 757 467 9318",
    "sg:postcode":"23464",
    "sg:province":"VA",
    "wof:name":"Tapman Seafood",
    "wof:placetype":"venue"
},
  "geometry": {"coordinates":[-76.161474,36.818411],"type":"Point"}
}