{
  "type": "Feature",
  "properties": {
    "addr:full":"14019 Glenkirk Rd Gainesville VA 20155",
    "addr:housenumber":"14019",
    "addr:postcode":"20155",
    "addr:street":"Glenkirk Rd",
    "iso:country":"US",
    "sg:address":"14019 Glenkirk Rd",
    "sg:city":"Gainesville",
    "sg:classifiers":[
        {
            "category":"Organizations",
            "subcategory":"Religious Organization",
            "type":"Services"
        }
    ],
    "sg:phone":"+1 703 754 7712",
    "sg:postcode":"20155",
    "sg:province":"VA",
    "sg:tags":[
        "church"
    ],
    "wof:name":"Northern Virginia Baptist Ctr",
    "wof:placetype":"venue"
},
  "geometry": {"coordinates":[-77.61268800000001,38.773927],"type":"Point"}
}