{
  "type": "Feature",
  "properties": {
    "iso:country":"US",
    "sg:address":"1326 Oleander Ave",
    "sg:city":"Chesapeake",
    "sg:classifiers":[
        {
            "category":"Bus Charters",
            "type":"Transportation"
        }
    ],
    "sg:phone":"+1 757 424 0631",
    "sg:postcode":"23325",
    "sg:province":"VA",
    "wof:name":"Flatland Transportation Corp",
    "wof:placetype":"venue"
},
  "geometry": {"coordinates":[-76.237438,36.815822],"type":"Point"}
}