{
  "type": "Feature",
  "properties": {
    "iso:country":"US",
    "sg:address":"2810 Romaron St",
    "sg:city":"Chesapeake",
    "sg:classifiers":[
        {
            "category":"Building & Trades",
            "subcategory":"Cleaning & Sanitation",
            "type":"Services"
        }
    ],
    "sg:phone":"+1 757 485 5705",
    "sg:postcode":"23323",
    "sg:province":"VA",
    "sg:tags":[
        "reside",
        "salon",
        "construction",
        "beauty",
        "clean"
    ],
    "wof:name":"Bullco Enterprises Inc",
    "wof:placetype":"venue"
},
  "geometry": {"coordinates":[-76.345275,36.785597],"type":"Point"}
}