{
  "type": "Feature",
  "properties": {
    "addr:full":"451 Sherando Ln Stephens City VA 22655",
    "addr:housenumber":"451",
    "addr:postcode":"22655",
    "addr:street":"Sherando Ln",
    "iso:country":"US",
    "sg:address":"451 Sherando Ln",
    "sg:city":"Stephens City",
    "sg:classifiers":[
        {
            "category":"Freight",
            "type":"Transportation"
        }
    ],
    "sg:phone":"+1 540 868 0698",
    "sg:postcode":"22655",
    "sg:province":"VA",
    "sg:tags":[
        "local",
        "storage",
        "trucking"
    ],
    "wof:name":"Dezarn and Son",
    "wof:placetype":"venue"
},
  "geometry": {"coordinates":[-78.191772,39.07113],"type":"Point"}
}