{
  "type": "Feature",
  "properties": {
    "addr:full":"4808 Jefferson Davis Hwy Fredericksburg VA 22408",
    "addr:housenumber":"4808",
    "addr:postcode":"22408",
    "addr:street":"Jefferson Davis Hwy",
    "iso:country":"US",
    "sg:address":"4808 Jefferson Davis Hwy",
    "sg:city":"Fredericksburg",
    "sg:classifiers":[
        {
            "category":"Manufacturing",
            "subcategory":"Printing",
            "type":"Manufacturing & Wholesale Goods"
        }
    ],
    "sg:phone":"+1 540 891 7700",
    "sg:postcode":"22408",
    "sg:province":"VA",
    "sg:tags":[
        "screen"
    ],
    "wof:name":"Jonathan Promotions",
    "wof:placetype":"venue"
},
  "geometry": {"coordinates":[-77.496482,38.260541],"type":"Point"}
}