{
  "type": "Feature",
  "properties": {
    "iso:country":"US",
    "sg:address":"1509 Presidential Dr",
    "sg:city":"Richmond",
    "sg:classifiers":[
        {
            "category":"Manufacturing",
            "subcategory":"Printing",
            "type":"Manufacturing & Wholesale Goods"
        }
    ],
    "sg:phone":"+1 804 627 0028",
    "sg:postcode":"23228",
    "sg:province":"VA",
    "sg:tags":[
        "book"
    ],
    "wof:name":"Novellasmith",
    "wof:placetype":"venue"
},
  "geometry": {"coordinates":[-77.466103,37.635656],"type":"Point"}
}