{
  "type": "Feature",
  "properties": {
    "addr:full":"10202 Balls Ford Rd Manassas VA 20109",
    "addr:housenumber":"10202",
    "addr:postcode":"20109",
    "addr:street":"Balls Ford Rd",
    "iso:country":"US",
    "sg:address":"10202 Balls Ford Rd",
    "sg:city":"Manassas",
    "sg:classifiers":[
        {
            "category":"Building & Trades",
            "subcategory":"Electrical",
            "type":"Services"
        }
    ],
    "sg:phone":"+1 703 368 2065",
    "sg:postcode":"20109",
    "sg:province":"VA",
    "sg:tags":[
        "electrician"
    ],
    "wof:name":"Jomar Electric Corp",
    "wof:placetype":"venue"
},
  "geometry": {"coordinates":[-77.503197,38.8036],"type":"Point"}
}