{
  "type": "Feature",
  "properties": {
    "addr:full":"5201 Portsmouth Blvd Portsmouth VA 23701",
    "addr:housenumber":"5201",
    "addr:postcode":"23701",
    "addr:street":"Portsmouth Blvd",
    "iso:country":"US",
    "sg:address":"5201 Portsmouth Blvd",
    "sg:city":"Portsmouth",
    "sg:classifiers":[
        {
            "category":"Retail",
            "subcategory":"Funeral Services",
            "type":"Services"
        }
    ],
    "sg:phone":"+1 757 488 8348",
    "sg:postcode":"23701",
    "sg:province":"VA",
    "sg:tags":[
        "director",
        "home"
    ],
    "wof:name":"Sturtevant Funeral Home Inc",
    "wof:placetype":"venue"
},
  "geometry": {"coordinates":[-76.37612799999999,36.81885],"type":"Point"}
}