{
  "type": "Feature",
  "properties": {
    "iso:country":"US",
    "sg:address":"2946 Sleepy Hollow Rd",
    "sg:city":"Falls Church",
    "sg:classifiers":[
        {
            "category":"Social Services",
            "type":"Services"
        }
    ],
    "sg:phone":"+1 703 237 4766",
    "sg:postcode":"22044",
    "sg:province":"VA",
    "sg:tags":[
        "youth",
        "organization",
        "center"
    ],
    "wof:name":"Family and Youth Outreach Svcs",
    "wof:placetype":"venue"
},
  "geometry": {"coordinates":[-77.156848,38.870961],"type":"Point"}
}