{
  "type": "Feature",
  "properties": {
    "addr:full":"210 Brush Mountain Rd Blacksburg VA 24060",
    "addr:housenumber":"210",
    "addr:postcode":"24060",
    "addr:street":"Brush Mountain Rd",
    "iso:country":"US",
    "sg:address":"210 Brush Mountain Rd",
    "sg:city":"Blacksburg",
    "sg:classifiers":[
        {
            "category":"Professional",
            "type":"Services"
        }
    ],
    "sg:phone":"+1 540 552 9074",
    "sg:postcode":"24060",
    "sg:province":"VA",
    "wof:name":"Lawrence McDonald",
    "wof:placetype":"venue"
},
  "geometry": {"coordinates":[-80.42101599999999,37.275817],"type":"Point"}
}