{
  "type": "Feature",
  "properties": {
    "addr:full":"4127 Granby Rd Woodbridge VA 22193",
    "addr:housenumber":"4127",
    "addr:postcode":"22193",
    "addr:street":"Granby Rd",
    "iso:country":"US",
    "sg:address":"4127 Granby Rd",
    "sg:city":"Woodbridge",
    "sg:classifiers":[
        {
            "category":"Building & Trades",
            "subcategory":"Construction",
            "type":"Services"
        }
    ],
    "sg:phone":"+1 703 670 9131",
    "sg:postcode":"22193",
    "sg:province":"VA",
    "sg:tags":[
        "general",
        "contractor"
    ],
    "wof:name":"NJF Construction",
    "wof:placetype":"venue"
},
  "geometry": {"coordinates":[-77.33410600000001,38.656741],"type":"Point"}
}