{
  "type": "Feature",
  "properties": {
    "iso:country":"US",
    "sg:address":"6111 Ramshorn Pl",
    "sg:city":"Mc Lean",
    "sg:classifiers":[
        {
            "category":"Building & Trades",
            "subcategory":"Landscaping Services",
            "type":"Services"
        }
    ],
    "sg:phone":"+1 703 356 1986",
    "sg:postcode":"22101",
    "sg:province":"VA",
    "wof:name":"Jed L Goehring Landscaping",
    "wof:placetype":"venue"
},
  "geometry": {"coordinates":[-77.145144,38.94041],"type":"Point"}
}