{
  "type": "Feature",
  "properties": {
    "addr:full":"1127 S Main St Farmville VA 23901",
    "addr:housenumber":"1127",
    "addr:postcode":"23901",
    "addr:street":"S Main St",
    "iso:country":"US",
    "sg:address":"1127 S Main St",
    "sg:city":"Farmville",
    "sg:classifiers":[
        {
            "category":"Shopping",
            "subcategory":"Clothing, Apparel, & Fashions",
            "type":"Retail Goods"
        }
    ],
    "sg:phone":"+1 434 315 0405",
    "sg:postcode":"23901",
    "sg:province":"VA",
    "sg:tags":[
        "furnishing"
    ],
    "wof:name":"Beauty & Fashion",
    "wof:placetype":"venue"
},
  "geometry": {"coordinates":[-78.39743,37.288786],"type":"Point"}
}