{
  "type": "Feature",
  "properties": {
    "iso:country":"US",
    "sg:address":"14791 Build America Dr",
    "sg:city":"Woodbridge",
    "sg:classifiers":[
        {
            "category":"Recreation",
            "subcategory":"Amusement Park",
            "type":"Entertainment"
        },
        {
            "category":"Shopping",
            "subcategory":"Hobbies, Toys, & Games",
            "type":"Retail Goods"
        },
        {
            "category":"Shopping",
            "subcategory":"Bicycles & Sporting Goods",
            "type":"Retail Goods"
        },
        {
            "category":"Personal",
            "subcategory":"Day Spa",
            "type":"Services"
        },
        {
            "category":"Bars & Pubs",
            "subcategory":"Sports Bar",
            "type":"Food & Drink"
        }
    ],
    "sg:phone":"+1 703 490 1111",
    "sg:postcode":"22191",
    "sg:province":"VA",
    "sg:tags":[
        "toy",
        "supply",
        "equipment",
        "hot",
        "billiard",
        "pool",
        "device",
        "tub",
        "hall",
        "store"
    ],
    "wof:name":"Atlantic Billiards Supply",
    "wof:placetype":"venue"
},
  "geometry": {"coordinates":[-77.272308,38.631859],"type":"Point"}
}