{
  "type": "Feature",
  "properties": {
    "addr:full":"5001 Park Cmns Lp Glen Allen VA 23059",
    "addr:housenumber":"5001",
    "addr:postcode":"23059",
    "addr:street":"Park Cmns Lp",
    "iso:country":"US",
    "sg:address":"5001 Park Cmns Lp",
    "sg:city":"Glen Allen",
    "sg:classifiers":[
        {
            "category":"Building & Trades",
            "subcategory":"Construction",
            "type":"Services"
        }
    ],
    "sg:phone":"+1 804 360 3202",
    "sg:postcode":"23059",
    "sg:province":"VA",
    "sg:tags":[
        "house"
    ],
    "wof:name":"Boone Homes",
    "wof:placetype":"venue"
},
  "geometry": {"coordinates":[-77.59284599999999,37.674957],"type":"Point"}
}