{
  "type": "Feature",
  "properties": {
    "addr:full":"4085 Chain Bridge Rd Fairfax VA 22030",
    "addr:housenumber":"4085",
    "addr:postcode":"22030",
    "addr:street":"Chain Bridge Rd",
    "iso:country":"US",
    "sg:address":"4085 Chain Bridge Rd",
    "sg:city":"Fairfax",
    "sg:classifiers":[
        {
            "category":"Real Estate",
            "subcategory":"Real Estate Services",
            "type":"Services"
        }
    ],
    "sg:phone":"+1 703 330 6049",
    "sg:postcode":"22030",
    "sg:province":"VA",
    "wof:name":"Court Hse Srch of Nthrn Vrgnia",
    "wof:placetype":"venue"
},
  "geometry": {"coordinates":[-77.307787,38.844313],"type":"Point"}
}