{
  "type": "Feature",
  "properties": {
    "addr:full":"5440 Peters Creek Rd NW Roanoke VA 24019",
    "addr:housenumber":"5440",
    "addr:postcode":"24019",
    "addr:street":"Peters Creek Rd Nw",
    "iso:country":"US",
    "sg:address":"5440 Peters Creek Rd NW",
    "sg:city":"Roanoke",
    "sg:classifiers":[
        {
            "category":"Professional",
            "subcategory":"Accounting & Tax Preparation",
            "type":"Services"
        }
    ],
    "sg:phone":"+1 540 362 2760",
    "sg:postcode":"24019",
    "sg:province":"VA",
    "sg:tags":[
        "accountant"
    ],
    "wof:name":"Bert W Holloway CPA",
    "wof:placetype":"venue"
},
  "geometry": {"coordinates":[-79.973586,37.336062],"type":"Point"}
}