{
  "type": "Feature",
  "properties": {
    "addr:full":"7459 Old Hickory Dr Mechanicsville VA 23111",
    "addr:housenumber":"7459",
    "addr:postcode":"23111",
    "addr:street":"Old Hickory Dr",
    "iso:country":"US",
    "sg:address":"7459 Old Hickory Dr",
    "sg:city":"Mechanicsville",
    "sg:classifiers":[
        {
            "category":"Insurance",
            "subcategory":"Title Insurance",
            "type":"Services"
        },
        {
            "category":"Real Estate",
            "subcategory":"Real Estate Services",
            "type":"Services"
        }
    ],
    "sg:phone":"+1 804 427 7400",
    "sg:postcode":"23111",
    "sg:province":"VA",
    "sg:tags":[
        "company",
        "carrier"
    ],
    "wof:name":"C & Z Settlement Services LLC",
    "wof:placetype":"venue"
},
  "geometry": {"coordinates":[-77.34298,37.612601],"type":"Point"}
}