{
  "type": "Feature",
  "properties": {
    "iso:country":"US",
    "sg:address":"2306 Ivy Rd",
    "sg:city":"Charlottesville",
    "sg:classifiers":[
        {
            "category":"Government",
            "subcategory":"Office",
            "type":"Public Place"
        }
    ],
    "sg:phone":"+1 434 977 9041",
    "sg:postcode":"22903",
    "sg:province":"VA",
    "sg:tags":[
        "village"
    ],
    "wof:name":"Charlottesville Emergency Comm",
    "wof:placetype":"venue"
},
  "geometry": {"coordinates":[-78.522453,38.046745],"type":"Point"}
}