{
  "type": "Feature",
  "properties": {
    "addr:full":"33484 Old Valley Pike Strasburg VA 22657",
    "addr:housenumber":"33484",
    "addr:postcode":"22657",
    "addr:street":"Old Valley Pike",
    "iso:country":"US",
    "sg:address":"33484 Old Valley Pike",
    "sg:city":"Strasburg",
    "sg:classifiers":[
        {
            "category":"Manufacturing",
            "subcategory":"Signs",
            "type":"Manufacturing & Wholesale Goods"
        }
    ],
    "sg:phone":"+1 540 465 3103",
    "sg:postcode":"22657",
    "sg:province":"VA",
    "wof:name":"Al's Sign Shop",
    "wof:placetype":"venue"
},
  "geometry": {"coordinates":[-78.35328,38.996154],"type":"Point"}
}