{
  "type": "Feature",
  "properties": {
    "addr:full":"20 Rock Pointe Ln Ste 201 Warrenton VA 20186",
    "addr:housenumber":"20",
    "addr:postcode":"20186",
    "addr:street":"Rock Pointe Ln Ste 201",
    "iso:country":"US",
    "sg:address":"20 Rock Pointe Ln Ste 201",
    "sg:city":"Warrenton",
    "sg:classifiers":[
        {
            "category":"Health Services",
            "subcategory":"Doctor",
            "type":"Services"
        }
    ],
    "sg:phone":"+1 540 349 1882",
    "sg:postcode":"20186",
    "sg:province":"VA",
    "wof:name":"Virginia Retina Center",
    "wof:placetype":"venue"
},
  "geometry": {"coordinates":[-77.790764,38.722797],"type":"Point"}
}