{
  "type": "Feature",
  "properties": {
    "addr:full":"1309 A L Philpott Hwy Axton VA 24054",
    "addr:housenumber":"1309 a",
    "addr:postcode":"24054",
    "addr:street":"L Philpott Hwy Axton",
    "iso:country":"US",
    "sg:address":"1309 A L Philpott Hwy",
    "sg:city":"Axton",
    "sg:classifiers":[
        {
            "category":"Wholesale",
            "subcategory":"Durable Goods & Equipment",
            "type":"Manufacturing & Wholesale Goods"
        }
    ],
    "sg:phone":"+1 276 650 1111",
    "sg:postcode":"24054",
    "sg:province":"VA",
    "sg:tags":[
        "merchandise"
    ],
    "wof:name":"Candle Barn",
    "wof:placetype":"venue"
},
  "geometry": {"coordinates":[-79.709678,36.658983],"type":"Point"}
}