{
  "type": "Feature",
  "properties": {
    "iso:country":"US",
    "sg:address":"2706 S Crater Rd",
    "sg:city":"Petersburg",
    "sg:classifiers":[
        {
            "category":"Food & Beverages",
            "subcategory":"Groceries & Convenience Stores",
            "type":"Retail Goods"
        }
    ],
    "sg:phone":"+1 804 732 0231",
    "sg:postcode":"23805",
    "sg:province":"VA",
    "sg:tags":[
        "grocer"
    ],
    "wof:name":"Market Place",
    "wof:placetype":"venue"
},
  "geometry": {"coordinates":[-77.375927,37.195304],"type":"Point"}
}