{
  "type": "Feature",
  "properties": {
    "iso:country":"US",
    "sg:address":"4101 Pepsi Pl",
    "sg:city":"Chantilly",
    "sg:classifiers":[
        {
            "category":"Manufacturing",
            "subcategory":"Food",
            "type":"Manufacturing & Wholesale Goods"
        }
    ],
    "sg:phone":"+1 703 631 2501",
    "sg:postcode":"20151",
    "sg:province":"VA",
    "sg:tags":[
        "grocery",
        "drink",
        "soft",
        "mfg"
    ],
    "wof:name":"Pepsi-Cola",
    "wof:placetype":"venue"
},
  "geometry": {"coordinates":[-77.458319,38.902336],"type":"Point"}
}