{
  "type": "Feature",
  "properties": {
    "addr:full":"228 Birchside Cir Locust Grove VA 22508",
    "addr:housenumber":"228",
    "addr:postcode":"22508",
    "addr:street":"Birchside Cir",
    "iso:country":"US",
    "sg:address":"228 Birchside Cir",
    "sg:city":"Locust Grove",
    "sg:classifiers":[
        {
            "category":"Professional",
            "subcategory":"Management & Consulting",
            "type":"Services"
        }
    ],
    "sg:phone":"+1 540 972 3305",
    "sg:postcode":"22508",
    "sg:province":"VA",
    "sg:tags":[
        "consultant",
        "business"
    ],
    "wof:name":"HIG Inc",
    "wof:placetype":"venue"
},
  "geometry": {"coordinates":[-77.758195,38.336099],"type":"Point"}
}