{
  "type": "Feature",
  "properties": {
    "iso:country":"US",
    "sg:address":"107 W 4th Ave",
    "sg:city":"Franklin",
    "sg:classifiers":[
        {
            "category":"Autos & Motor Vehicles",
            "subcategory":"Automobile Sales",
            "type":"Retail Goods"
        }
    ],
    "sg:phone":"+1 757 562 2243",
    "sg:postcode":"23851",
    "sg:province":"VA",
    "sg:tags":[
        "body",
        "shop",
        "used",
        "sales",
        "car"
    ],
    "wof:name":"Vics Sign & Engraving",
    "wof:placetype":"venue"
},
  "geometry": {"coordinates":[-76.923694,36.678871],"type":"Point"}
}