{
  "type": "Feature",
  "properties": {
    "iso:country":"US",
    "sg:address":"7630 Little River Tpke",
    "sg:city":"Annandale",
    "sg:classifiers":[
        {
            "category":"Banks & Credit Unions",
            "subcategory":"Investment Brokerage",
            "type":"Services"
        }
    ],
    "sg:phone":"+1 703 914 9555",
    "sg:postcode":"22003",
    "sg:province":"VA",
    "sg:tags":[
        "consultant",
        "planning",
        "financial"
    ],
    "wof:name":"Manna Financial Svc Corp",
    "wof:placetype":"venue"
},
  "geometry": {"coordinates":[-77.210081,38.832738],"type":"Point"}
}