{
  "type": "Feature",
  "properties": {
    "iso:country":"US",
    "sg:address":"410 Stallings Ct",
    "sg:city":"Newport News",
    "sg:classifiers":[
        {
            "category":"Retail",
            "subcategory":"Laundry & Dry Cleaning",
            "type":"Services"
        }
    ],
    "sg:phone":"+1 757 593 2726",
    "sg:postcode":"23608",
    "sg:province":"VA",
    "sg:tags":[
        "garment",
        "agent"
    ],
    "wof:name":"VIP Cleaners",
    "wof:placetype":"venue"
},
  "geometry": {"coordinates":[-76.54483500000001,37.153255],"type":"Point"}
}