{
  "type": "Feature",
  "properties": {
    "addr:full":"9483 Kings Hwy King George VA 22485",
    "addr:housenumber":"9483",
    "addr:postcode":"22485",
    "addr:street":"Kings Hwy",
    "iso:country":"US",
    "sg:address":"9483 Kings Hwy",
    "sg:city":"King George",
    "sg:classifiers":[
        {
            "category":"Government",
            "subcategory":"Office",
            "type":"Public Place"
        }
    ],
    "sg:phone":"+1 540 775 0896",
    "sg:postcode":"22485",
    "sg:province":"VA",
    "wof:name":"Victim Witness Program",
    "wof:placetype":"venue"
},
  "geometry": {"coordinates":[-77.179723,38.266117],"type":"Point"}
}