{
  "type": "Feature",
  "properties": {
    "addr:full":"6728 Curran St Mc Lean VA 22101",
    "addr:housenumber":"6728",
    "addr:postcode":"22101",
    "addr:street":"Curran St Mc Lean",
    "iso:country":"US",
    "sg:address":"6728 Curran St",
    "sg:city":"Mc Lean",
    "sg:classifiers":[
        {
            "category":"Real Estate",
            "subcategory":"Architect",
            "type":"Services"
        }
    ],
    "sg:phone":"+1 703 288 4412",
    "sg:postcode":"22101",
    "sg:province":"VA",
    "wof:name":"Michael Nawrocki Architecture",
    "wof:placetype":"venue"
},
  "geometry": {"coordinates":[-77.177505,38.935573],"type":"Point"}
}