{
  "type": "Feature",
  "properties": {
    "iso:country":"US",
    "sg:address":"6408 Natrona Ave",
    "sg:city":"Norfolk",
    "sg:classifiers":[
        {
            "category":"Manufacturing",
            "subcategory":"Retail Goods",
            "type":"Manufacturing & Wholesale Goods"
        }
    ],
    "sg:phone":"+1 757 857 4790",
    "sg:postcode":"23509",
    "sg:province":"VA",
    "sg:tags":[
        "pencil",
        "mfg"
    ],
    "wof:name":"Pens & Knives",
    "wof:placetype":"venue"
},
  "geometry": {"coordinates":[-76.25885700000001,36.897631],"type":"Point"}
}