{
  "type": "Feature",
  "properties": {
    "addr:full":"4807 Valley View Blvd NW Roanoke VA 24012",
    "addr:housenumber":"4807",
    "addr:postcode":"24012",
    "addr:street":"Valley View Blvd Nw",
    "iso:country":"US",
    "sg:address":"4807 Valley View Blvd NW",
    "sg:city":"Roanoke",
    "sg:classifiers":[
        {
            "category":"Restaurant",
            "type":"Food & Drink"
        }
    ],
    "sg:menulink":"http://www.allmenus.com/va/roanoke/188068-mcdonalds/menu/",
    "sg:phone":"+1 540 265 8662",
    "sg:postcode":"24012",
    "sg:province":"VA",
    "sg:tags":[
        "burger",
        "american"
    ],
    "wof:name":"McDonald's",
    "wof:placetype":"venue"
},
  "geometry": {"coordinates":[-79.96206100000001,37.308125],"type":"Point"}
}