{
  "type": "Feature",
  "properties": {
    "addr:full":"113 Front Dr Winchester VA 22602",
    "addr:housenumber":"113",
    "addr:postcode":"22602",
    "addr:street":"Front Dr",
    "iso:country":"US",
    "sg:address":"113 Front Dr",
    "sg:city":"Winchester",
    "sg:classifiers":[
        {
            "category":"Building & Trades",
            "subcategory":"Construction",
            "type":"Services"
        }
    ],
    "sg:phone":"+1 540 888 4999",
    "sg:postcode":"22602",
    "sg:province":"VA",
    "sg:tags":[
        "contractor"
    ],
    "wof:name":"Fowler Homes",
    "wof:placetype":"venue"
},
  "geometry": {"coordinates":[-78.161147,39.147717],"type":"Point"}
}