{
  "type": "Feature",
  "properties": {
    "addr:full":"2217 Crystal Spring Ave SW Roanoke VA 24014",
    "addr:housenumber":"2217",
    "addr:postcode":"24014",
    "addr:street":"Crystal Spring Ave Sw",
    "iso:country":"US",
    "sg:address":"2217 Crystal Spring Ave SW",
    "sg:city":"Roanoke",
    "sg:classifiers":[
        {
            "category":"Banks & Credit Unions",
            "subcategory":"Investment Brokerage",
            "type":"Services"
        }
    ],
    "sg:phone":"+1 540 344 4422",
    "sg:postcode":"24014",
    "sg:province":"VA",
    "sg:tags":[
        "stock",
        "bond"
    ],
    "wof:name":"Mid-Atlantic Securities Inc",
    "wof:placetype":"venue"
},
  "geometry": {"coordinates":[-79.94726,37.247811],"type":"Point"}
}