{
  "type": "Feature",
  "properties": {
    "iso:country":"US",
    "sg:address":"705 N Argonne Ave",
    "sg:city":"Sterling",
    "sg:classifiers":[
        {
            "category":"Wholesale",
            "subcategory":"Machinery & Supplies",
            "type":"Manufacturing & Wholesale Goods"
        }
    ],
    "sg:phone":"+1 703 450 5540",
    "sg:postcode":"20164",
    "sg:province":"VA",
    "sg:tags":[
        "equipment",
        "industrial",
        "auto"
    ],
    "wof:name":"V I P Sales",
    "wof:placetype":"venue"
},
  "geometry": {"coordinates":[-77.393434,39.010469],"type":"Point"}
}