{
  "type": "Feature",
  "properties": {
    "iso:country":"US",
    "sg:address":"127 Beech St",
    "sg:city":"Gate City",
    "sg:classifiers":[
        {
            "category":"Education",
            "subcategory":"School",
            "type":"Public Place"
        }
    ],
    "sg:phone":"+1 276 386 7522",
    "sg:postcode":"24251",
    "sg:province":"VA",
    "sg:tags":[
        "executive"
    ],
    "sg:website":"www.scott.k12.va.us",
    "wof:name":"Gate City High School",
    "wof:placetype":"venue"
},
  "geometry": {"coordinates":[-82.564679,36.641752],"type":"Point"}
}