{
  "type": "Feature",
  "properties": {
    "addr:full":"1100 Dryden Ln Charlottesville VA 22903",
    "addr:housenumber":"1100",
    "addr:postcode":"22903",
    "addr:street":"Dryden Ln",
    "iso:country":"US",
    "sg:address":"1100 Dryden Ln",
    "sg:city":"Charlottesville",
    "sg:classifiers":[
        {
            "category":"Real Estate",
            "subcategory":"Real Estate Agent",
            "type":"Services"
        }
    ],
    "sg:phone":"+1 434 951 5125",
    "sg:postcode":"22903",
    "sg:province":"VA",
    "wof:name":"Responsive Sales Inc",
    "wof:placetype":"venue"
},
  "geometry": {"coordinates":[-78.538431,38.051705],"type":"Point"}
}