{
  "type": "Feature",
  "properties": {
    "addr:full":"18 Taylor Rd Richmond VA 23223",
    "addr:housenumber":"18",
    "addr:postcode":"23223",
    "addr:street":"Taylor Rd",
    "iso:country":"US",
    "sg:address":"18 Taylor Rd",
    "sg:city":"Richmond",
    "sg:classifiers":[
        {
            "category":"Health Services",
            "subcategory":"Doctor",
            "type":"Services"
        }
    ],
    "sg:phone":"+1 804 908 2635",
    "sg:postcode":"23223",
    "sg:province":"VA",
    "sg:tags":[
        "medicine",
        "physician",
        "addiction",
        "surgeons"
    ],
    "wof:name":"Halcyon Women's Center",
    "wof:placetype":"venue"
},
  "geometry": {"coordinates":[-77.381912,37.540553],"type":"Point"}
}