{
  "type": "Feature",
  "properties": {
    "iso:country":"US",
    "sg:address":"8216 Crown Court Rd",
    "sg:city":"Alexandria",
    "sg:classifiers":[
        {
            "category":"Professional",
            "subcategory":"Business Services",
            "type":"Services"
        }
    ],
    "sg:phone":"+1 703 780 4089",
    "sg:postcode":"22308",
    "sg:province":"VA",
    "wof:name":"Executive Assistant",
    "wof:placetype":"venue"
},
  "geometry": {"coordinates":[-77.068969,38.734039],"type":"Point"}
}