{
  "type": "Feature",
  "properties": {
    "addr:full":"4910 Shadow Valley Dr Fairfax VA 22030",
    "addr:housenumber":"4910",
    "addr:postcode":"22030",
    "addr:street":"Shadow Valley Dr",
    "iso:country":"US",
    "sg:address":"4910 Shadow Valley Dr",
    "sg:city":"Fairfax",
    "sg:classifiers":[
        {
            "category":"Building & Trades",
            "subcategory":"Construction",
            "type":"Services"
        }
    ],
    "sg:phone":"+1 703 691 3023",
    "sg:postcode":"22030",
    "sg:province":"VA",
    "sg:tags":[
        "house"
    ],
    "wof:name":"Home Repair Services Unlimited",
    "wof:placetype":"venue"
},
  "geometry": {"coordinates":[-77.324428,38.82895],"type":"Point"}
}