{
  "type": "Feature",
  "properties": {
    "addr:full":"5521 Huntingcreek Dr Richmond VA 23237",
    "addr:housenumber":"5521",
    "addr:postcode":"23237",
    "addr:street":"Huntingcreek Dr",
    "iso:country":"US",
    "sg:address":"5521 Huntingcreek Dr",
    "sg:city":"Richmond",
    "sg:classifiers":[
        {
            "category":"Home & Garden",
            "subcategory":"Carpets & Floor Coverings",
            "type":"Retail Goods"
        }
    ],
    "sg:phone":"+1 804 271 6800",
    "sg:postcode":"23237",
    "sg:province":"VA",
    "wof:name":"B&B Floors Inc",
    "wof:placetype":"venue"
},
  "geometry": {"coordinates":[-77.484088,37.395424],"type":"Point"}
}