{
  "type": "Feature",
  "properties": {
    "iso:country":"US",
    "sg:address":"825 Greenbrier Cir",
    "sg:city":"Chesapeake",
    "sg:classifiers":[
        {
            "category":"Professional",
            "subcategory":"Research",
            "type":"Services"
        }
    ],
    "sg:phone":"+1 757 424 4779",
    "sg:postcode":"23320",
    "sg:province":"VA",
    "sg:tags":[
        "scientific"
    ],
    "wof:name":"Batelle Tidewater Operations",
    "wof:placetype":"venue"
},
  "geometry": {"coordinates":[-76.229732,36.791527],"type":"Point"}
}