{
  "type": "Feature",
  "properties": {
    "addr:full":"1508 Fairhope Rd NW Roanoke VA 24017",
    "addr:housenumber":"1508",
    "addr:postcode":"24017",
    "addr:street":"Fairhope Rd Nw",
    "iso:country":"US",
    "sg:address":"1508 Fairhope Rd NW",
    "sg:city":"Roanoke",
    "sg:classifiers":[
        {
            "category":"Organizations",
            "subcategory":"Community Association",
            "type":"Services"
        }
    ],
    "sg:phone":"+1 540 563 0288",
    "sg:postcode":"24017",
    "sg:province":"VA",
    "wof:name":"Kappa Alpha PSI Fraternity",
    "wof:placetype":"venue"
},
  "geometry": {"coordinates":[-79.992116,37.303583],"type":"Point"}
}