{
  "type": "Feature",
  "properties": {
    "addr:full":"3703 Cameron Mills Rd Alexandria VA 22305",
    "addr:housenumber":"3703",
    "addr:postcode":"22305",
    "addr:street":"Cameron Mills Rd",
    "iso:country":"US",
    "sg:address":"3703 Cameron Mills Rd",
    "sg:city":"Alexandria",
    "sg:classifiers":[
        {
            "category":"Place Of Worship",
            "type":"Public Place"
        }
    ],
    "sg:phone":"+1 703 299 3005",
    "sg:postcode":"22305",
    "sg:province":"VA",
    "sg:tags":[
        "church"
    ],
    "wof:name":"Catholic Athletes For Christ",
    "wof:placetype":"venue"
},
  "geometry": {"coordinates":[-77.075276,38.839162],"type":"Point"}
}