{
  "type": "Feature",
  "properties": {
    "iso:country":"US",
    "sg:address":"3900 Bonney Rd",
    "sg:city":"Virginia Beach",
    "sg:classifiers":[
        {
            "category":"Shopping",
            "subcategory":"Hobbies, Toys, & Games",
            "type":"Retail Goods"
        }
    ],
    "sg:phone":"+1 757 463 1240",
    "sg:postcode":"23452",
    "sg:province":"VA",
    "sg:tags":[
        "model",
        "supply"
    ],
    "wof:name":"Engine House Trains",
    "wof:placetype":"venue"
},
  "geometry": {"coordinates":[-76.11077299999999,36.838744],"type":"Point"}
}