{
  "type": "Feature",
  "properties": {
    "iso:country":"US",
    "sg:address":"7925 Greeley Blvd",
    "sg:city":"Springfield",
    "sg:classifiers":[
        {
            "category":"Education",
            "subcategory":"Special Training",
            "type":"Public Place"
        }
    ],
    "sg:phone":"+1 703 698 8867",
    "sg:postcode":"22152",
    "sg:province":"VA",
    "wof:name":"My Tutor",
    "wof:placetype":"venue"
},
  "geometry": {"coordinates":[-77.22152699999999,38.770047],"type":"Point"}
}