{
  "type": "Feature",
  "properties": {
    "addr:full":"1179 American Legion Rd Stuart VA 24171",
    "addr:housenumber":"1179",
    "addr:postcode":"24171",
    "addr:street":"American Legion Rd",
    "iso:country":"US",
    "sg:address":"1179 American Legion Rd",
    "sg:city":"Stuart",
    "sg:classifiers":[
        {
            "category":"Freight",
            "type":"Transportation"
        }
    ],
    "sg:phone":"+1 276 694 5429",
    "sg:postcode":"24171",
    "sg:province":"VA",
    "sg:tags":[
        "operator",
        "local",
        "trucking"
    ],
    "wof:name":"Charlie G Handy Trucking",
    "wof:placetype":"venue"
},
  "geometry": {"coordinates":[-80.218467,36.625863],"type":"Point"}
}