{
  "type": "Feature",
  "properties": {
    "addr:full":"1044 Volvo Pkwy Chesapeake VA 23320",
    "addr:housenumber":"1044",
    "addr:postcode":"23320",
    "addr:street":"Volvo Pkwy",
    "iso:country":"US",
    "sg:address":"1044 Volvo Pkwy",
    "sg:city":"Chesapeake",
    "sg:classifiers":[
        {
            "category":"Shopping",
            "type":"Retail Goods"
        },
        {
            "category":"Shopping",
            "subcategory":"Beauty & Cosmetics",
            "type":"Retail Goods"
        }
    ],
    "sg:phone":"+1 757 382 9383",
    "sg:postcode":"23320",
    "sg:province":"VA",
    "sg:tags":[
        "merchandise",
        "perfume"
    ],
    "wof:name":"Merle Norman Cosmetics",
    "wof:placetype":"venue"
},
  "geometry": {"coordinates":[-76.222793,36.769467],"type":"Point"}
}