{
  "type": "Feature",
  "properties": {
    "addr:full":"1977 Summit Point Rd Berryville VA 22611",
    "addr:housenumber":"1977",
    "addr:postcode":"22611",
    "addr:street":"Summit Point Rd",
    "iso:country":"US",
    "sg:address":"1977 Summit Point Rd",
    "sg:city":"Berryville",
    "sg:classifiers":[
        {
            "category":"Organizations",
            "subcategory":"Community Association",
            "type":"Services"
        }
    ],
    "sg:phone":"+1 540 955 1947",
    "sg:postcode":"22611",
    "sg:province":"VA",
    "wof:name":"Ruritan Club of Clarke Co",
    "wof:placetype":"venue"
},
  "geometry": {"coordinates":[-77.97188,39.181827],"type":"Point"}
}