{
  "type": "Feature",
  "properties": {
    "addr:full":"372 S Independence Blvd Virginia Beach VA 23452",
    "addr:housenumber":"372",
    "addr:postcode":"23452",
    "addr:street":"S Independence Blvd",
    "iso:country":"US",
    "sg:address":"372 S Independence Blvd",
    "sg:city":"Virginia Beach",
    "sg:classifiers":[
        {
            "category":"Real Estate",
            "subcategory":"Real Estate Agent",
            "type":"Services"
        }
    ],
    "sg:phone":"+1 757 554 0900",
    "sg:postcode":"23452",
    "sg:province":"VA",
    "wof:name":"Claudia Aristizabal Inc",
    "wof:placetype":"venue"
},
  "geometry": {"coordinates":[-76.13538800000001,36.829287],"type":"Point"}
}