{
  "type": "Feature",
  "properties": {
    "addr:full":"28494 Old Saltworks Rd Meadowview VA 24361",
    "addr:housenumber":"28494",
    "addr:postcode":"24361",
    "addr:street":"Old Saltworks Rd",
    "iso:country":"US",
    "sg:address":"28494 Old Saltworks Rd",
    "sg:city":"Meadowview",
    "sg:classifiers":[
        {
            "category":"Professional",
            "type":"Services"
        }
    ],
    "sg:phone":"+1 276 566 4153",
    "sg:postcode":"24361",
    "sg:province":"VA",
    "wof:name":"Dusty Coal Inc",
    "wof:placetype":"venue"
},
  "geometry": {"coordinates":[-81.86872099999999,36.795136],"type":"Point"}
}