{
  "type": "Feature",
  "properties": {
    "iso:country":"US",
    "sg:address":"1965 Bentonville-Browntown Rd",
    "sg:city":"Bentonville",
    "sg:classifiers":[
        {
            "category":"Farming",
            "subcategory":"Farm",
            "type":"Manufacturing & Wholesale Goods"
        }
    ],
    "sg:phone":"+1 540 636 9614",
    "sg:postcode":"22610",
    "sg:province":"VA",
    "sg:tags":[
        "crop",
        "general"
    ],
    "wof:name":"Smelser Farm",
    "wof:placetype":"venue"
},
  "geometry": {"coordinates":[-78.28451,38.819007],"type":"Point"}
}