{
  "type": "Feature",
  "properties": {
    "addr:full":"121 Sycamore Ave NE Roanoke VA 24012",
    "addr:housenumber":"121",
    "addr:postcode":"24012",
    "addr:street":"Sycamore Ave Ne",
    "iso:country":"US",
    "sg:address":"121 Sycamore Ave NE",
    "sg:city":"Roanoke",
    "sg:classifiers":[
        {
            "category":"Manufacturing",
            "subcategory":"Paper Products",
            "type":"Manufacturing & Wholesale Goods"
        }
    ],
    "sg:phone":"+1 540 982 3915",
    "sg:postcode":"24012",
    "sg:province":"VA",
    "sg:tags":[
        "label"
    ],
    "sg:website":"www.shimchockslabel.com",
    "wof:name":"Shimchock's Litho Svc Inc",
    "wof:placetype":"venue"
},
  "geometry": {"coordinates":[-79.93391800000001,37.28724],"type":"Point"}
}