{
  "type": "Feature",
  "properties": {
    "addr:full":"111 Banner St Danville VA 24541",
    "addr:housenumber":"111",
    "addr:postcode":"24541",
    "addr:street":"Banner St",
    "iso:country":"US",
    "sg:address":"111 Banner St",
    "sg:city":"Danville",
    "sg:classifiers":[
        {
            "category":"Home & Garden",
            "subcategory":"Building Materials",
            "type":"Retail Goods"
        }
    ],
    "sg:phone":"+1 434 793 6008",
    "sg:postcode":"24541",
    "sg:province":"VA",
    "wof:name":"Piedmont Paint Co",
    "wof:placetype":"venue"
},
  "geometry": {"coordinates":[-79.414034,36.557401],"type":"Point"}
}