{
  "type": "Feature",
  "properties": {
    "addr:full":"1432 Lyndhurst Rd Waynesboro VA 22980",
    "addr:housenumber":"1432",
    "addr:postcode":"22980",
    "addr:street":"Lyndhurst Rd",
    "iso:country":"US",
    "sg:address":"1432 Lyndhurst Rd",
    "sg:city":"Waynesboro",
    "sg:classifiers":[
        {
            "category":"Shopping",
            "subcategory":"Used Merchandise",
            "type":"Retail Goods"
        }
    ],
    "sg:phone":"+1 540 949 8522",
    "sg:postcode":"22980",
    "sg:province":"VA",
    "wof:name":"Apple Acres Antiques",
    "wof:placetype":"venue"
},
  "geometry": {"coordinates":[-78.909183,38.056022],"type":"Point"}
}