{
  "type": "Feature",
  "properties": {
    "addr:full":"3018 River Rd W Goochland VA 23063",
    "addr:housenumber":"3018",
    "addr:postcode":"23063",
    "addr:street":"River Rd W Goochland",
    "iso:country":"US",
    "sg:address":"3018 River Rd W",
    "sg:city":"Goochland",
    "sg:classifiers":[
        {
            "category":"Banks & Credit Unions",
            "subcategory":"Bank",
            "type":"Services"
        }
    ],
    "sg:phone":"+1 804 556 3700",
    "sg:postcode":"23063",
    "sg:province":"VA",
    "wof:name":"South Trust Bank",
    "wof:placetype":"venue"
},
  "geometry": {"coordinates":[-77.885558,37.687348],"type":"Point"}
}