{
  "type": "Feature",
  "properties": {
    "iso:country":"US",
    "sg:address":"501 Church St NE",
    "sg:city":"Vienna",
    "sg:classifiers":[
        {
            "category":"Building & Trades",
            "subcategory":"Plumbing",
            "type":"Services"
        }
    ],
    "sg:phone":"+1 703 281 6300",
    "sg:postcode":"22180",
    "sg:province":"VA",
    "sg:tags":[
        "conditioning",
        "air",
        "system",
        "contractor"
    ],
    "wof:name":"Argent Heating & Cooling LLC",
    "wof:placetype":"venue"
},
  "geometry": {"coordinates":[-77.257094,38.910187],"type":"Point"}
}