{
  "type": "Feature",
  "properties": {
    "addr:full":"282 Cedar Ln SE Vienna VA 22180",
    "addr:housenumber":"282",
    "addr:postcode":"22180",
    "addr:street":"Cedar Ln Se",
    "iso:country":"US",
    "sg:address":"282 Cedar Ln SE",
    "sg:city":"Vienna",
    "sg:classifiers":[
        {
            "category":"Restaurant",
            "type":"Food & Drink"
        }
    ],
    "sg:menulink":"http://www.allmenus.com/va/providence/188008-mcdonalds/menu/",
    "sg:phone":"+1 703 876 9239",
    "sg:postcode":"22180",
    "sg:province":"VA",
    "sg:tags":[
        "burger",
        "american"
    ],
    "wof:name":"McDonald's",
    "wof:placetype":"venue"
},
  "geometry": {"coordinates":[-77.242581,38.88754],"type":"Point"}
}