{
  "type": "Feature",
  "properties": {
    "iso:country":"US",
    "sg:address":"5436 Sunnywood Dr",
    "sg:city":"Virginia Beach",
    "sg:classifiers":[
        {
            "category":"Recreation",
            "type":"Entertainment"
        }
    ],
    "sg:phone":"+1 757 464 4680",
    "sg:postcode":"23455",
    "sg:province":"VA",
    "sg:tags":[
        "party",
        "fishing"
    ],
    "wof:name":"Four Winds Chartering",
    "wof:placetype":"venue"
},
  "geometry": {"coordinates":[-76.169276,36.895971],"type":"Point"}
}