{
  "type": "Feature",
  "properties": {
    "addr:full":"12998 Cross County Rd Mineral VA 23117",
    "addr:housenumber":"12998",
    "addr:postcode":"23117",
    "addr:street":"Cross County Rd",
    "iso:country":"US",
    "sg:address":"12998 Cross County Rd",
    "sg:city":"Mineral",
    "sg:classifiers":[
        {
            "category":"Manufacturing",
            "subcategory":"Pottery",
            "type":"Manufacturing & Wholesale Goods"
        }
    ],
    "sg:phone":"+1 540 894 5597",
    "sg:postcode":"23117",
    "sg:province":"VA",
    "sg:tags":[
        "product",
        "mfg"
    ],
    "wof:name":"Cherry Hill Pottery Inc",
    "wof:placetype":"venue"
},
  "geometry": {"coordinates":[-77.898385,37.917014],"type":"Point"}
}