{
  "type": "Feature",
  "properties": {
    "addr:full":"Suffolk W Shoppin Suffolk VA 23432",
    "addr:postcode":"23432",
    "addr:street":"W",
    "iso:country":"US",
    "sg:address":"Suffolk W Shoppin",
    "sg:city":"Suffolk",
    "sg:classifiers":[
        {
            "category":"Restaurant",
            "type":"Food & Drink"
        }
    ],
    "sg:phone":"+1 757 539 0484",
    "sg:postcode":"23432",
    "sg:province":"VA",
    "sg:website":"www.hardees.com",
    "wof:name":"Hardee's of Suffolk",
    "wof:placetype":"venue"
},
  "geometry": {"coordinates":[-76.553299,36.870899],"type":"Point"}
}