{
  "type": "Feature",
  "properties": {
    "iso:country":"US",
    "sg:address":"5102B Park Dr.",
    "sg:city":"Fredericksburg",
    "sg:classifiers":[
        {
            "category":"Autos & Motor Vehicles",
            "subcategory":"Auto Supplies",
            "type":"Retail Goods"
        },
        {
            "category":"Retail",
            "subcategory":"Auto Repair",
            "type":"Services"
        }
    ],
    "sg:phone":"+1 540 898 4450",
    "sg:postcode":"22408",
    "sg:province":"VA",
    "sg:tags":[
        "transmission",
        "automobile",
        "diagnostic",
        "equipment",
        "transmissions-truck",
        "car",
        "performance",
        "sport",
        "racing",
        "tractor"
    ],
    "sg:website":"http://www.seatstransmission.com",
    "wof:name":"Seats Transmission Service",
    "wof:placetype":"venue"
},
  "geometry": {"coordinates":[-77.502026,38.256853],"type":"Point"}
}