{
  "type": "Feature",
  "properties": {
    "iso:country":"US",
    "sg:address":"3265 Eastbrook Rd",
    "sg:city":"Lynchburg",
    "sg:classifiers":[
        {
            "category":"Freight",
            "type":"Transportation"
        }
    ],
    "sg:phone":"+1 434 846 2334",
    "sg:postcode":"24501",
    "sg:province":"VA",
    "sg:tags":[
        "operator",
        "local",
        "trucking"
    ],
    "wof:name":"Marvin E Ware Trucking",
    "wof:placetype":"venue"
},
  "geometry": {"coordinates":[-79.10382799999999,37.368481],"type":"Point"}
}