{
  "type": "Feature",
  "properties": {
    "addr:full":"3248 Academy Ave Portsmouth VA 23703",
    "addr:housenumber":"3248",
    "addr:postcode":"23703",
    "addr:street":"Academy Ave",
    "iso:country":"US",
    "sg:address":"3248 Academy Ave",
    "sg:city":"Portsmouth",
    "sg:classifiers":[
        {
            "category":"Government",
            "subcategory":"Office",
            "type":"Public Place"
        }
    ],
    "sg:phone":"+1 757 686 5004",
    "sg:postcode":"23703",
    "sg:province":"VA",
    "sg:tags":[
        "state",
        "program"
    ],
    "sg:website":"www.gov.com",
    "wof:name":"Rehabilitative Services Dept",
    "wof:placetype":"venue"
},
  "geometry": {"coordinates":[-76.397263,36.862837],"type":"Point"}
}