{
  "type": "Feature",
  "properties": {
    "iso:country":"US",
    "sg:address":"3740 S Main St",
    "sg:city":"Blacksburg",
    "sg:classifiers":[
        {
            "category":"Retail",
            "subcategory":"Repair Shop",
            "type":"Services"
        }
    ],
    "sg:phone":"+1 540 951 4304",
    "sg:postcode":"24060",
    "sg:province":"VA",
    "sg:tags":[
        "auto",
        "automotive",
        "general"
    ],
    "wof:name":"Valley Towing",
    "wof:placetype":"venue"
},
  "geometry": {"coordinates":[-80.408738,37.185563],"type":"Point"}
}