{
  "type": "Feature",
  "properties": {
    "addr:full":"1930 Sandy Hook Rd Goochland VA 23063",
    "addr:housenumber":"1930",
    "addr:postcode":"23063",
    "addr:street":"Sandy Hook Rd",
    "iso:country":"US",
    "sg:address":"1930 Sandy Hook Rd",
    "sg:city":"Goochland",
    "sg:classifiers":[
        {
            "category":"Restaurant",
            "type":"Food & Drink"
        }
    ],
    "sg:phone":"+1 804 556 3434",
    "sg:postcode":"23063",
    "sg:province":"VA",
    "sg:tags":[
        "eating"
    ],
    "wof:name":"Roccos Italian Restaurant",
    "wof:placetype":"venue"
},
  "geometry": {"coordinates":[-77.88882,37.699099],"type":"Point"}
}