{
  "type": "Feature",
  "properties": {
    "addr:full":"101 N Pinetta Dr Richmond VA 23235",
    "addr:housenumber":"101",
    "addr:postcode":"23235",
    "addr:street":"N Pinetta Dr",
    "iso:country":"US",
    "sg:address":"101 N Pinetta Dr",
    "sg:city":"Richmond",
    "sg:classifiers":[
        {
            "category":"Professional",
            "subcategory":"Business Services",
            "type":"Services"
        },
        {
            "category":"Government",
            "subcategory":"Post Office",
            "type":"Public Place"
        }
    ],
    "sg:phone":"+1 800 275 8777",
    "sg:postcode":"23235",
    "sg:province":"VA",
    "sg:tags":[
        "mail",
        "shipping"
    ],
    "sg:website":"http://www.usps.com",
    "wof:name":"United States Postal Service",
    "wof:placetype":"venue"
},
  "geometry": {"coordinates":[-77.567398,37.497429],"type":"Point"}
}