{
  "type": "Feature",
  "properties": {
    "iso:country":"US",
    "sg:address":"11815 Rock Landing Dr",
    "sg:city":"Newport News",
    "sg:classifiers":[
        {
            "category":"Professional",
            "subcategory":"Accounting & Tax Preparation",
            "type":"Services"
        }
    ],
    "sg:phone":"+1 757 873 8585",
    "sg:postcode":"23606",
    "sg:province":"VA",
    "sg:tags":[
        "accountant"
    ],
    "sg:website":"www.carminesrobbins.com",
    "wof:name":"Carmines Robbins & Co",
    "wof:placetype":"venue"
},
  "geometry": {"coordinates":[-76.464271,37.088902],"type":"Point"}
}