{
  "type": "Feature",
  "properties": {
    "iso:country":"US",
    "sg:address":"11501 Washington Hwy",
    "sg:city":"Ashland",
    "sg:classifiers":[
        {
            "category":"Manufacturing",
            "subcategory":"Buildings",
            "type":"Manufacturing & Wholesale Goods"
        },
        {
            "category":"Manufacturing",
            "subcategory":"Building Materials",
            "type":"Manufacturing & Wholesale Goods"
        }
    ],
    "sg:phone":"+1 804 752 2995",
    "sg:postcode":"23005",
    "sg:province":"VA",
    "sg:tags":[
        "modular",
        "buildings-metal-wholesale",
        "buildings-pre-cut",
        "manufacturer",
        "prefabricated"
    ],
    "wof:name":"Steel Tube Buildings",
    "wof:placetype":"venue"
},
  "geometry": {"coordinates":[-77.46866900000001,37.718662],"type":"Point"}
}