{
  "type": "Feature",
  "properties": {
    "iso:country":"US",
    "sg:address":"1816 South St",
    "sg:city":"Franklin",
    "sg:classifiers":[
        {
            "category":"Organizations",
            "subcategory":"Religious Organization",
            "type":"Services"
        }
    ],
    "sg:phone":"+1 757 562 7079",
    "sg:postcode":"23851",
    "sg:province":"VA",
    "wof:name":"Scotts Revival Center",
    "wof:placetype":"venue"
},
  "geometry": {"coordinates":[-76.93507099999999,36.666339],"type":"Point"}
}