{
  "type": "Feature",
  "properties": {
    "addr:full":"901 Woodnor Dr NE Vienna VA 22180",
    "addr:housenumber":"901",
    "addr:postcode":"22180",
    "addr:street":"Woodnor Dr Ne",
    "iso:country":"US",
    "sg:address":"901 Woodnor Dr NE",
    "sg:city":"Vienna",
    "sg:classifiers":[
        {
            "category":"Professional",
            "subcategory":"Business Services",
            "type":"Services"
        }
    ],
    "sg:phone":"+1 703 281 0557",
    "sg:postcode":"22180",
    "sg:province":"VA",
    "wof:name":"Carson Technologies",
    "wof:placetype":"venue"
},
  "geometry": {"coordinates":[-77.255515,38.917083],"type":"Point"}
}