{
  "type": "Feature",
  "properties": {
    "iso:country":"US",
    "sg:address":"750 Independence Blvd",
    "sg:city":"Virginia Beach",
    "sg:classifiers":[
        {
            "category":"Professional",
            "type":"Services"
        }
    ],
    "sg:phone":"+1 757 456 5060",
    "sg:postcode":"23455",
    "sg:province":"VA",
    "wof:name":"Dollar Avenue",
    "wof:placetype":"venue"
},
  "geometry": {"coordinates":[-76.13212300000001,36.862463],"type":"Point"}
}