{
  "type": "Feature",
  "properties": {
    "iso:country":"US",
    "sg:address":"19631 Genito Rd",
    "sg:city":"Amelia Court House",
    "sg:classifiers":[
        {
            "category":"Building & Trades",
            "subcategory":"Construction",
            "type":"Services"
        }
    ],
    "sg:phone":"+1 804 561 4754",
    "sg:postcode":"23002",
    "sg:province":"VA",
    "sg:tags":[
        "house"
    ],
    "wof:name":"A R Reams Builders Inc",
    "wof:placetype":"venue"
},
  "geometry": {"coordinates":[-78.03779400000001,37.436745],"type":"Point"}
}