{
  "type": "Feature",
  "properties": {
    "addr:full":"19430 Saxis Rd Saxis VA 23427",
    "addr:postcode":"19430;23427",
    "addr:street":"Saxis Rd",
    "iso:country":"US",
    "sg:address":"19430 Saxis Rd",
    "sg:city":"Saxis",
    "sg:classifiers":[
        {
            "category":"Home & Garden",
            "subcategory":"Furniture",
            "type":"Retail Goods"
        }
    ],
    "sg:phone":"+1 757 824 3900",
    "sg:postcode":"23427",
    "sg:province":"VA",
    "sg:tags":[
        "cabinet"
    ],
    "wof:name":"Pete Bonawell Custom Cabinets",
    "wof:placetype":"venue"
},
  "geometry": {"coordinates":[-75.72918,37.92028],"type":"Point"}
}