{
  "type": "Feature",
  "properties": {
    "addr:full":"3823 Main St Chincoteague VA 23336",
    "addr:housenumber":"3823",
    "addr:postcode":"23336",
    "addr:street":"Main St",
    "iso:country":"US",
    "sg:address":"3823 Main St",
    "sg:city":"Chincoteague",
    "sg:classifiers":[
        {
            "category":"Government",
            "subcategory":"Office",
            "type":"Public Place"
        }
    ],
    "sg:phone":"+1 757 336 2814",
    "sg:postcode":"23336",
    "sg:province":"VA",
    "sg:tags":[
        "guard",
        "unit",
        "coast"
    ],
    "wof:name":"Coast Guard Group",
    "wof:placetype":"venue"
},
  "geometry": {"coordinates":[-75.381612,37.930816],"type":"Point"}
}