{
  "type": "Feature",
  "properties": {
    "addr:full":"188 John Randolph Rd Farmville VA 23901",
    "addr:housenumber":"188",
    "addr:postcode":"23901",
    "addr:street":"John Randolph Rd",
    "iso:country":"US",
    "sg:address":"188 John Randolph Rd",
    "sg:city":"Farmville",
    "sg:classifiers":[
        {
            "category":"Farming",
            "subcategory":"Livestock Farm",
            "type":"Manufacturing & Wholesale Goods"
        }
    ],
    "sg:phone":"+1 434 392 4571",
    "sg:postcode":"23901",
    "sg:province":"VA",
    "sg:tags":[
        "beef",
        "feedlot",
        "cattle"
    ],
    "wof:name":"Wilck Family LP",
    "wof:placetype":"venue"
},
  "geometry": {"coordinates":[-78.35456000000001,37.377767],"type":"Point"}
}