{
  "type": "Feature",
  "properties": {
    "iso:country":"US",
    "sg:address":"938 Artisan Ave",
    "sg:city":"Chesapeake",
    "sg:classifiers":[
        {
            "category":"Building & Trades",
            "subcategory":"Landscaping Services",
            "type":"Services"
        }
    ],
    "sg:phone":"+1 757 572 5296",
    "sg:postcode":"23323",
    "sg:province":"VA",
    "sg:tags":[
        "landscape"
    ],
    "wof:name":"Southside Grounds Maintenance",
    "wof:placetype":"venue"
},
  "geometry": {"coordinates":[-76.331203,36.715976],"type":"Point"}
}