{
  "type": "Feature",
  "properties": {
    "addr:full":"723 Blue Crab Rd Newport News VA 23606",
    "addr:housenumber":"723",
    "addr:postcode":"23606",
    "addr:street":"Blue Crab Rd",
    "iso:country":"US",
    "sg:address":"723 Blue Crab Rd",
    "sg:city":"Newport News",
    "sg:classifiers":[
        {
            "category":"Building & Trades",
            "subcategory":"Construction",
            "type":"Services"
        }
    ],
    "sg:phone":"+1 757 873 8887",
    "sg:postcode":"23606",
    "sg:province":"VA",
    "sg:tags":[
        "mfg",
        "contractor",
        "wood",
        "cabinet",
        "maker",
        "special",
        "kitchen"
    ],
    "wof:name":"Kitchen Design Inc",
    "wof:placetype":"venue"
},
  "geometry": {"coordinates":[-76.47551199999999,37.089704],"type":"Point"}
}