{
  "type": "Feature",
  "properties": {
    "addr:full":"26 Buck Dr Ruckersville VA 22968",
    "addr:housenumber":"26",
    "addr:postcode":"22968",
    "addr:street":"Buck Dr",
    "iso:country":"US",
    "sg:address":"26 Buck Dr",
    "sg:city":"Ruckersville",
    "sg:classifiers":[
        {
            "category":"Banks & Credit Unions",
            "subcategory":"Investment Brokerage",
            "type":"Services"
        }
    ],
    "sg:phone":"+1 434 990 8377",
    "sg:postcode":"22968",
    "sg:province":"VA",
    "sg:tags":[
        "security"
    ],
    "wof:name":"Edward Jones 17617",
    "wof:placetype":"venue"
},
  "geometry": {"coordinates":[-78.382459,38.213633],"type":"Point"}
}