{
  "type": "Feature",
  "properties": {
    "addr:full":"1777 N Kent St Arlington VA 22209",
    "addr:housenumber":"1777",
    "addr:postcode":"22209",
    "addr:street":"N Kent St",
    "iso:country":"US",
    "sg:address":"1777 N Kent St",
    "sg:city":"Arlington",
    "sg:classifiers":[
        {
            "category":"Government",
            "subcategory":"Office",
            "type":"Public Place"
        }
    ],
    "sg:phone":"+1 703 588 1584",
    "sg:postcode":"22209",
    "sg:province":"VA",
    "sg:tags":[
        "national",
        "security"
    ],
    "wof:name":"Federal Vting Assstnce Program",
    "wof:placetype":"venue"
},
  "geometry": {"coordinates":[-77.069346,38.895612],"type":"Point"}
}