{
  "type": "Feature",
  "properties": {
    "addr:full":"3007 Seminary Ave Richmond VA 23227",
    "addr:housenumber":"3007",
    "addr:postcode":"23227",
    "addr:street":"Seminary Ave",
    "iso:country":"US",
    "sg:address":"3007 Seminary Ave",
    "sg:city":"Richmond",
    "sg:classifiers":[
        {
            "category":"Health Services",
            "subcategory":"Health Practitioner",
            "type":"Services"
        }
    ],
    "sg:phone":"+1 804 353 5758",
    "sg:postcode":"23227",
    "sg:province":"VA",
    "wof:name":"Weinbaum Dr Louis PC",
    "wof:placetype":"venue"
},
  "geometry": {"coordinates":[-77.447615,37.575106],"type":"Point"}
}