{
  "type": "Feature",
  "properties": {
    "addr:full":"6517 Potomac Ave Apt B2 Alexandria VA 22307",
    "addr:housenumber":"6517",
    "addr:postcode":"22307",
    "addr:street":"Potomac Ave Apt B2",
    "iso:country":"US",
    "sg:address":"6517 Potomac Ave Apt B2",
    "sg:city":"Alexandria",
    "sg:classifiers":[
        {
            "category":"Utilities",
            "subcategory":"Water",
            "type":"Services"
        }
    ],
    "sg:phone":"+1 703 768 9274",
    "sg:postcode":"22307",
    "sg:province":"VA",
    "sg:tags":[
        "company-utility",
        "system",
        "supply"
    ],
    "wof:name":"Wash Usa",
    "wof:placetype":"venue"
},
  "geometry": {"coordinates":[-77.05685800000001,38.77644],"type":"Point"}
}