{
  "type": "Feature",
  "properties": {
    "addr:full":"2422 S Oxford St Arlington VA 22206",
    "addr:housenumber":"2422",
    "addr:postcode":"22206",
    "addr:street":"S Oxford St",
    "iso:country":"US",
    "sg:address":"2422 S Oxford St",
    "sg:city":"Arlington",
    "sg:classifiers":[
        {
            "category":"Building & Trades",
            "subcategory":"Construction",
            "type":"Services"
        }
    ],
    "sg:phone":"+1 703 685 8821",
    "sg:postcode":"22206",
    "sg:province":"VA",
    "sg:tags":[
        "house"
    ],
    "wof:name":"Jvr Construction",
    "wof:placetype":"venue"
},
  "geometry": {"coordinates":[-77.09148399999999,38.846853],"type":"Point"}
}