{
  "type": "Feature",
  "properties": {
    "iso:country":"US",
    "sg:address":"1561 Bordeaux Pl",
    "sg:city":"Norfolk",
    "sg:classifiers":[
        {
            "category":"Professional",
            "subcategory":"Engineering",
            "type":"Services"
        }
    ],
    "sg:phone":"+1 757 622 5501",
    "sg:postcode":"23509",
    "sg:province":"VA",
    "sg:tags":[
        "engineer"
    ],
    "wof:name":"Redi Check Intl",
    "wof:placetype":"venue"
},
  "geometry": {"coordinates":[-76.26468199999999,36.885232],"type":"Point"}
}