{
  "type": "Feature",
  "properties": {
    "addr:full":"320 Maple Ave E Vienna VA 22180",
    "addr:housenumber":"320",
    "addr:postcode":"22180",
    "addr:street":"Maple Ave E",
    "iso:country":"US",
    "sg:address":"320 Maple Ave E",
    "sg:city":"Vienna",
    "sg:classifiers":[
        {
            "category":"Retail",
            "subcategory":"Veterinary Services",
            "type":"Services"
        }
    ],
    "sg:phone":"+1 703 938 2800",
    "sg:postcode":"22180",
    "sg:province":"VA",
    "sg:tags":[
        "clinic",
        "hospital",
        "veterinarian",
        "specialty"
    ],
    "wof:name":"Charles W Blevins",
    "wof:placetype":"venue"
},
  "geometry": {"coordinates":[-77.2608,38.905079],"type":"Point"}
}