{
  "type": "Feature",
  "properties": {
    "addr:full":"5904 George Washington Memorial Hwy Grafton VA 23692",
    "addr:housenumber":"5904",
    "addr:postcode":"23692",
    "addr:street":"George Washington Memorial Hwy",
    "iso:country":"US",
    "sg:address":"5904 George Washington Memorial Hwy",
    "sg:city":"Grafton",
    "sg:classifiers":[
        {
            "category":"Retail",
            "subcategory":"Laundry & Dry Cleaning",
            "type":"Services"
        },
        {
            "category":"Personal",
            "type":"Services"
        }
    ],
    "sg:phone":"+1 757 898 5050",
    "sg:postcode":"23692",
    "sg:province":"VA",
    "sg:tags":[
        "rental",
        "wear",
        "formal"
    ],
    "wof:name":"Formal Masters Inc",
    "wof:placetype":"venue"
},
  "geometry": {"coordinates":[-76.466292,37.165718],"type":"Point"}
}