{
  "type": "Feature",
  "properties": {
    "addr:full":"350 Pottery Rd Fancy Gap VA 24328",
    "addr:housenumber":"350",
    "addr:postcode":"24328",
    "addr:street":"Pottery Rd",
    "iso:country":"US",
    "sg:address":"350 Pottery Rd",
    "sg:city":"Fancy Gap",
    "sg:classifiers":[
        {
            "category":"Professional",
            "type":"Services"
        }
    ],
    "sg:phone":"+1 276 728 0202",
    "sg:postcode":"24328",
    "sg:province":"VA",
    "wof:name":"H & S Ebterprises",
    "wof:placetype":"venue"
},
  "geometry": {"coordinates":[-80.710384,36.668829],"type":"Point"}
}