{
  "type": "Feature",
  "properties": {
    "iso:country":"US",
    "sg:address":"4124 Starwood Arch",
    "sg:city":"Virginia Beach",
    "sg:classifiers":[
        {
            "category":"Home & Garden",
            "subcategory":"Building Materials",
            "type":"Retail Goods"
        }
    ],
    "sg:phone":"+1 757 471 9785",
    "sg:postcode":"23456",
    "sg:province":"VA",
    "sg:tags":[
        "line",
        "gift",
        "handcrafted"
    ],
    "wof:name":"Cathys Creations",
    "wof:placetype":"venue"
},
  "geometry": {"coordinates":[-76.120228,36.772105],"type":"Point"}
}