{
  "type": "Feature",
  "properties": {
    "addr:full":"10136 Hull Street Rd Midlothian VA 23112",
    "addr:housenumber":"10136",
    "addr:postcode":"23112",
    "addr:street":"Hull Street Rd",
    "iso:country":"US",
    "sg:address":"10136 Hull Street Rd",
    "sg:city":"Midlothian",
    "sg:classifiers":[
        {
            "category":"Building & Trades",
            "subcategory":"Plumbing",
            "type":"Services"
        }
    ],
    "sg:phone":"+1 804 276 2424",
    "sg:postcode":"23112",
    "sg:province":"VA",
    "sg:tags":[
        "plumbing",
        "contractor"
    ],
    "wof:name":"Bill's Plumbing Svc",
    "wof:placetype":"venue"
},
  "geometry": {"coordinates":[-77.583516,37.442698],"type":"Point"}
}