{
  "type": "Feature",
  "properties": {
    "addr:full":"912 Alexis Rd Woodbridge VA 22191",
    "addr:housenumber":"912",
    "addr:postcode":"22191",
    "addr:street":"Alexis Rd",
    "iso:country":"US",
    "sg:address":"912 Alexis Rd",
    "sg:city":"Woodbridge",
    "sg:classifiers":[
        {
            "category":"Building & Trades",
            "subcategory":"Construction",
            "type":"Services"
        }
    ],
    "sg:phone":"+1 703 492 8145",
    "sg:postcode":"22191",
    "sg:province":"VA",
    "sg:tags":[
        "home",
        "improvement"
    ],
    "wof:name":"Builders Unlimited Co",
    "wof:placetype":"venue"
},
  "geometry": {"coordinates":[-77.24470100000001,38.655942],"type":"Point"}
}