{
  "type": "Feature",
  "properties": {
    "iso:country":"US",
    "sg:address":"10630 Crestwood Dr Ste B",
    "sg:city":"Manassas",
    "sg:classifiers":[
        {
            "category":"Health Services",
            "subcategory":"Dentist",
            "type":"Services"
        }
    ],
    "sg:phone":"+1 703 330 5578",
    "sg:postcode":"20109",
    "sg:province":"VA",
    "sg:tags":[
        "orthodontist",
        "pediatric"
    ],
    "sg:website":"www.yourvadentist.com",
    "wof:name":"Taheri Bruce DDS",
    "wof:placetype":"venue"
},
  "geometry": {"coordinates":[-77.512243,38.779271],"type":"Point"}
}