{
  "type": "Feature",
  "properties": {
    "addr:full":"114 Garfield Ave Colonial Beach VA 22443",
    "addr:housenumber":"114",
    "addr:postcode":"beach;22443",
    "addr:street":"Garfield Ave",
    "iso:country":"US",
    "sg:address":"114 Garfield Ave",
    "sg:city":"Colonial Beach",
    "sg:classifiers":[
        {
            "category":"Retail",
            "subcategory":"Car Wash",
            "type":"Services"
        },
        {
            "category":"Professional",
            "type":"Services"
        }
    ],
    "sg:phone":"+1 804 224 8883",
    "sg:postcode":"22443",
    "sg:province":"VA",
    "sg:tags":[
        "automobile",
        "detail",
        "clean"
    ],
    "wof:name":"Johnson's Detailing",
    "wof:placetype":"venue"
},
  "geometry": {"coordinates":[-76.965166,38.251488],"type":"Point"}
}