{
  "type": "Feature",
  "properties": {
    "iso:country":"US",
    "sg:address":"815 Main St",
    "sg:city":"Danville",
    "sg:classifiers":[
        {
            "category":"Retail",
            "subcategory":"Animal Services",
            "type":"Services"
        }
    ],
    "sg:phone":"+1 434 793 7117",
    "sg:postcode":"24541",
    "sg:province":"VA",
    "wof:name":"Animal Hospital North Buncombe",
    "wof:placetype":"venue"
},
  "geometry": {"coordinates":[-79.39836699999999,36.583155],"type":"Point"}
}