{
  "type": "Feature",
  "properties": {
    "addr:full":"104 Hillside Dr Locust Grove VA 22508",
    "addr:housenumber":"104",
    "addr:postcode":"22508",
    "addr:street":"Hillside Dr",
    "iso:country":"US",
    "sg:address":"104 Hillside Dr",
    "sg:city":"Locust Grove",
    "sg:classifiers":[
        {
            "category":"Autos & Motor Vehicles",
            "subcategory":"Automobile Sales",
            "type":"Retail Goods"
        }
    ],
    "sg:phone":"+1 540 972 9384",
    "sg:postcode":"22508",
    "sg:province":"VA",
    "sg:tags":[
        "consulting",
        "sales"
    ],
    "wof:name":"Christensen Assoc",
    "wof:placetype":"venue"
},
  "geometry": {"coordinates":[-77.766564,38.345055],"type":"Point"}
}