{
  "type": "Feature",
  "properties": {
    "addr:full":"18640 Potomac Station Dr NW Leesburg VA 20176",
    "addr:housenumber":"18640",
    "addr:postcode":"20176",
    "addr:street":"Potomac Station Dr Nw",
    "iso:country":"US",
    "sg:address":"18640 Potomac Station Dr NW",
    "sg:city":"Leesburg",
    "sg:classifiers":[
        {
            "category":"Real Estate",
            "subcategory":"Real Estate Agent",
            "type":"Services"
        }
    ],
    "sg:phone":"+1 703 669 2627",
    "sg:postcode":"20176",
    "sg:province":"VA",
    "wof:name":"Kmp Enterprises LLC",
    "wof:placetype":"venue"
},
  "geometry": {"coordinates":[-77.509497,39.100677],"type":"Point"}
}