{
  "type": "Feature",
  "properties": {
    "addr:full":"128 S Turnberry Williamsburg VA 23188",
    "addr:housenumber":"128",
    "addr:postcode":"23188",
    "addr:street":"S Turnberry",
    "iso:country":"US",
    "sg:address":"128 S Turnberry",
    "sg:city":"Williamsburg",
    "sg:classifiers":[
        {
            "category":"Building & Trades",
            "subcategory":"Construction",
            "type":"Services"
        }
    ],
    "sg:phone":"+1 757 258 9530",
    "sg:postcode":"23188",
    "sg:province":"VA",
    "sg:tags":[
        "house"
    ],
    "wof:name":"Crawford Const Co of VA",
    "wof:placetype":"venue"
},
  "geometry": {"coordinates":[-76.77242699999999,37.287977],"type":"Point"}
}