{
  "type": "Feature",
  "properties": {
    "iso:country":"US",
    "sg:address":"102 Harbour Dr",
    "sg:city":"Yorktown",
    "sg:classifiers":[
        {
            "category":"Professional",
            "subcategory":"Business Services",
            "type":"Services"
        }
    ],
    "sg:phone":"+1 757 898 1126",
    "sg:postcode":"23692",
    "sg:province":"VA",
    "wof:name":"Saffron Business Services Inc",
    "wof:placetype":"venue"
},
  "geometry": {"coordinates":[-76.472458,37.209117],"type":"Point"}
}