{
  "type": "Feature",
  "properties": {
    "iso:country":"US",
    "sg:address":"116 E Main St",
    "sg:city":"Bedford",
    "sg:classifiers":[
        {
            "category":"Professional",
            "subcategory":"Lawyer & Legal Services",
            "type":"Services"
        }
    ],
    "sg:phone":"+1 540 586 1034",
    "sg:postcode":"24523",
    "sg:province":"VA",
    "sg:tags":[
        "attorney"
    ],
    "wof:name":"Garrett & Garrett",
    "wof:placetype":"venue"
},
  "geometry": {"coordinates":[-79.52336,37.334334],"type":"Point"}
}