{
  "type": "Feature",
  "properties": {
    "addr:full":"204 Whitney Pl NE Leesburg VA 20176",
    "addr:housenumber":"204",
    "addr:postcode":"20176",
    "addr:street":"Whitney Pl Ne",
    "iso:country":"US",
    "sg:address":"204 Whitney Pl NE",
    "sg:city":"Leesburg",
    "sg:classifiers":[
        {
            "category":"Personal",
            "subcategory":"Hair Removal",
            "type":"Services"
        }
    ],
    "sg:phone":"+1 703 777 3704",
    "sg:postcode":"20176",
    "sg:province":"VA",
    "wof:name":"Jones Enterprises",
    "wof:placetype":"venue"
},
  "geometry": {"coordinates":[-77.55685800000001,39.12263],"type":"Point"}
}