{
  "type": "Feature",
  "properties": {
    "iso:country":"US",
    "sg:address":"5520 Richmond Tappahannock Hwy",
    "sg:city":"King William",
    "sg:classifiers":[
        {
            "category":"Insurance",
            "subcategory":"Insurance Agent",
            "type":"Services"
        }
    ],
    "sg:phone":"+1 804 769 7565",
    "sg:postcode":"23086",
    "sg:province":"VA",
    "wof:name":"Virginia Farm Bureau Claims",
    "wof:placetype":"venue"
},
  "geometry": {"coordinates":[-77.13189800000001,37.746913],"type":"Point"}
}