{
  "type": "Feature",
  "properties": {
    "iso:country":"US",
    "sg:address":"209 Madison St",
    "sg:city":"Alexandria",
    "sg:classifiers":[
        {
            "category":"Restaurant",
            "type":"Food & Drink"
        }
    ],
    "sg:phone":"+1 703 836 6161",
    "sg:postcode":"22314",
    "sg:province":"VA",
    "sg:tags":[
        "fast"
    ],
    "wof:name":"Waterfront Cafe",
    "wof:placetype":"venue"
},
  "geometry": {"coordinates":[-77.038721,38.812186],"type":"Point"}
}