{
  "type": "Feature",
  "properties": {
    "addr:full":"812 Catalina Dr Newport News VA 23608",
    "addr:housenumber":"812",
    "addr:postcode":"23608",
    "addr:street":"Catalina Dr",
    "iso:country":"US",
    "sg:address":"812 Catalina Dr",
    "sg:city":"Newport News",
    "sg:classifiers":[
        {
            "category":"Real Estate",
            "subcategory":"Real Estate Operator",
            "type":"Services"
        }
    ],
    "sg:phone":"+1 757 875 0044",
    "sg:postcode":"23608",
    "sg:province":"VA",
    "sg:tags":[
        "invest",
        "improvement"
    ],
    "wof:name":"Wb Enterprise Inc",
    "wof:placetype":"venue"
},
  "geometry": {"coordinates":[-76.55905199999999,37.124662],"type":"Point"}
}