{
  "type": "Feature",
  "properties": {
    "addr:full":"11822 Canon Blvd Newport News VA 23606",
    "addr:housenumber":"11822",
    "addr:postcode":"23606",
    "addr:street":"Canon Blvd",
    "iso:country":"US",
    "sg:address":"11822 Canon Blvd",
    "sg:city":"Newport News",
    "sg:classifiers":[
        {
            "category":"Utilities",
            "subcategory":"Telephone",
            "type":"Services"
        }
    ],
    "sg:phone":"+1 757 873 8363",
    "sg:postcode":"23606",
    "sg:province":"VA",
    "sg:tags":[
        "communications",
        "computer",
        "programing",
        "custom"
    ],
    "wof:name":"Venturenet Inc",
    "wof:placetype":"venue"
},
  "geometry": {"coordinates":[-76.46945599999999,37.086478],"type":"Point"}
}