{
  "type": "Feature",
  "properties": {
    "addr:full":"480 Gougher Ln Heathsville VA 22473",
    "addr:housenumber":"480",
    "addr:postcode":"22473",
    "addr:street":"Gougher Ln",
    "iso:country":"US",
    "sg:address":"480 Gougher Ln",
    "sg:city":"Heathsville",
    "sg:classifiers":[
        {
            "category":"Building & Trades",
            "subcategory":"Construction",
            "type":"Services"
        }
    ],
    "sg:phone":"+1 804 580 5605",
    "sg:postcode":"22473",
    "sg:province":"VA",
    "sg:tags":[
        "residential"
    ],
    "wof:name":"Rh Construction",
    "wof:placetype":"venue"
},
  "geometry": {"coordinates":[-76.330994,37.834747],"type":"Point"}
}