{
  "type": "Feature",
  "properties": {
    "addr:full":"2485 Entrada Dr Virginia Beach VA 23456",
    "addr:housenumber":"2485",
    "addr:postcode":"23456",
    "addr:street":"Entrada Dr",
    "iso:country":"US",
    "sg:address":"2485 Entrada Dr",
    "sg:city":"Virginia Beach",
    "sg:classifiers":[
        {
            "category":"Building & Trades",
            "subcategory":"Construction",
            "type":"Services"
        }
    ],
    "sg:phone":"+1 757 426 5442",
    "sg:postcode":"23456",
    "sg:province":"VA",
    "sg:tags":[
        "water",
        "well",
        "drilling"
    ],
    "wof:name":"Atlantic Drilling Services",
    "wof:placetype":"venue"
},
  "geometry": {"coordinates":[-75.989287,36.752144],"type":"Point"}
}