{
  "type": "Feature",
  "properties": {
    "addr:full":"5912 16th St N Arlington VA 22205",
    "addr:housenumber":"5912",
    "addr:postcode":"22205",
    "addr:street":"16Th St N",
    "iso:country":"US",
    "sg:address":"5912 16th St N",
    "sg:city":"Arlington",
    "sg:classifiers":[
        {
            "category":"Wholesale",
            "subcategory":"Machinery & Supplies",
            "type":"Manufacturing & Wholesale Goods"
        }
    ],
    "sg:phone":"+1 703 241 0900",
    "sg:postcode":"22205",
    "sg:province":"VA",
    "sg:tags":[
        "equipment",
        "printing"
    ],
    "wof:name":"L W LA Fever Inc",
    "wof:placetype":"venue"
},
  "geometry": {"coordinates":[-77.144548,38.885398],"type":"Point"}
}