{
  "type": "Feature",
  "properties": {
    "iso:country":"US",
    "sg:address":"1712 Chestnut Ave",
    "sg:city":"Newport News",
    "sg:classifiers":[
        {
            "category":"Recreation",
            "type":"Entertainment"
        }
    ],
    "sg:phone":"+1 757 247 8504",
    "sg:postcode":"23607",
    "sg:province":"VA",
    "sg:tags":[
        "center"
    ],
    "wof:name":"Magruder Recreation Ctr",
    "wof:placetype":"venue"
},
  "geometry": {"coordinates":[-76.403083,36.982107],"type":"Point"}
}