{
  "type": "Feature",
  "properties": {
    "addr:full":"1439 Tunbridge Rd Lynchburg VA 24501",
    "addr:housenumber":"1439",
    "addr:postcode":"24501",
    "addr:street":"Tunbridge Rd",
    "iso:country":"US",
    "sg:address":"1439 Tunbridge Rd",
    "sg:city":"Lynchburg",
    "sg:classifiers":[
        {
            "category":"Professional",
            "subcategory":"Business Services",
            "type":"Services"
        }
    ],
    "sg:phone":"+1 434 385 9168",
    "sg:postcode":"24501",
    "sg:province":"VA",
    "sg:tags":[
        "notary"
    ],
    "wof:name":"Brown Closing Svc",
    "wof:placetype":"venue"
},
  "geometry": {"coordinates":[-79.224631,37.414438],"type":"Point"}
}