{
  "type": "Feature",
  "properties": {
    "addr:full":"3129 Hidden Oak Rd SW Roanoke VA 24018",
    "addr:housenumber":"3129",
    "addr:postcode":"24018",
    "addr:street":"Hidden Oak Rd Sw",
    "iso:country":"US",
    "sg:address":"3129 Hidden Oak Rd SW",
    "sg:city":"Roanoke",
    "sg:classifiers":[
        {
            "category":"Banks & Credit Unions",
            "subcategory":"Investment Brokerage",
            "type":"Services"
        }
    ],
    "sg:phone":"+1 540 772 2599",
    "sg:postcode":"24018",
    "sg:province":"VA",
    "sg:tags":[
        "security"
    ],
    "wof:name":"Carolina Investments Inc",
    "wof:placetype":"venue"
},
  "geometry": {"coordinates":[-80.00369600000001,37.25645],"type":"Point"}
}