{
  "type": "Feature",
  "properties": {
    "addr:full":"3610 Campbell Ave Lynchburg VA 24501",
    "addr:housenumber":"3610",
    "addr:postcode":"24501",
    "addr:street":"Campbell Ave",
    "iso:country":"US",
    "sg:address":"3610 Campbell Ave",
    "sg:city":"Lynchburg",
    "sg:classifiers":[
        {
            "category":"Building & Trades",
            "subcategory":"Plumbing",
            "type":"Services"
        }
    ],
    "sg:phone":"+1 434 528 8133",
    "sg:postcode":"24501",
    "sg:province":"VA",
    "sg:tags":[
        "contractor"
    ],
    "wof:name":"Randy The Plumber",
    "wof:placetype":"venue"
},
  "geometry": {"coordinates":[-79.140154,37.382685],"type":"Point"}
}