{
  "type": "Feature",
  "properties": {
    "iso:country":"US",
    "sg:address":"1265 Diamond Springs Rd",
    "sg:city":"Virginia Beach",
    "sg:classifiers":[
        {
            "category":"Wholesale",
            "subcategory":"Groceries",
            "type":"Manufacturing & Wholesale Goods"
        }
    ],
    "sg:phone":"+1 757 464 3551",
    "sg:postcode":"23455",
    "sg:province":"VA",
    "sg:tags":[
        "food",
        "product"
    ],
    "sg:website":"www.usfoodservice.com",
    "wof:name":"US Foodservice",
    "wof:placetype":"venue"
},
  "geometry": {"coordinates":[-76.177268,36.883836],"type":"Point"}
}