{
  "type": "Feature",
  "properties": {
    "iso:country":"US",
    "sg:address":"121 N Commerce Ave",
    "sg:city":"Waynesboro",
    "sg:classifiers":[
        {
            "category":"Retail",
            "subcategory":"Repair Shop",
            "type":"Services"
        }
    ],
    "sg:phone":"+1 540 942 5195",
    "sg:postcode":"22980",
    "sg:province":"VA",
    "sg:tags":[
        "upholsterer"
    ],
    "wof:name":"Waynesboro Custom Upholstery",
    "wof:placetype":"venue"
},
  "geometry": {"coordinates":[-78.877655,38.067178],"type":"Point"}
}