{
  "type": "Feature",
  "properties": {
    "iso:country":"US",
    "sg:address":"1398 General Booth Blvd",
    "sg:city":"Virginia Beach",
    "sg:classifiers":[
        {
            "category":"Recreation",
            "type":"Entertainment"
        }
    ],
    "sg:phone":"+1 757 437 4847",
    "sg:postcode":"23451",
    "sg:province":"VA",
    "sg:tags":[
        "parks"
    ],
    "wof:name":"Redwing Park",
    "wof:placetype":"venue"
},
  "geometry": {"coordinates":[-75.99420000000001,36.797508],"type":"Point"}
}