{
  "type": "Feature",
  "properties": {
    "addr:full":"6108 Peters Creek Rd NW Roanoke VA 24019",
    "addr:housenumber":"6108",
    "addr:postcode":"24019",
    "addr:street":"Peters Creek Rd Nw",
    "iso:country":"US",
    "sg:address":"6108 Peters Creek Rd NW",
    "sg:city":"Roanoke",
    "sg:classifiers":[
        {
            "category":"Health Services",
            "subcategory":"Doctor",
            "type":"Services"
        }
    ],
    "sg:phone":"+1 540 366 8662",
    "sg:postcode":"24019",
    "sg:province":"VA",
    "sg:tags":[
        "dentist"
    ],
    "wof:name":"Robert W Kaiser DDS",
    "wof:placetype":"venue"
},
  "geometry": {"coordinates":[-79.96961,37.341246],"type":"Point"}
}