{
  "type": "Feature",
  "properties": {
    "iso:country":"US",
    "sg:address":"239 W Washington St",
    "sg:city":"Suffolk",
    "sg:classifiers":[
        {
            "category":"Restaurant",
            "type":"Food & Drink"
        }
    ],
    "sg:phone":"+1 757 539 9966",
    "sg:postcode":"23434",
    "sg:province":"VA",
    "wof:name":"Art's Kitchen & Art Boutique",
    "wof:placetype":"venue"
},
  "geometry": {"coordinates":[-76.58525,36.729101],"type":"Point"}
}