{
  "type": "Feature",
  "properties": {
    "iso:country":"US",
    "sg:address":"3100 Queens Crown Dr",
    "sg:city":"Midlothian",
    "sg:classifiers":[
        {
            "category":"Professional",
            "subcategory":"Management & Consulting",
            "type":"Services"
        }
    ],
    "sg:phone":"+1 804 379 5678",
    "sg:postcode":"23113",
    "sg:province":"VA",
    "sg:tags":[
        "computer"
    ],
    "wof:name":"Bria Technologies",
    "wof:placetype":"venue"
},
  "geometry": {"coordinates":[-77.607072,37.532264],"type":"Point"}
}