{
  "type": "Feature",
  "properties": {
    "addr:full":"808 Battlefield Blvd S Chesapeake VA 23322",
    "addr:housenumber":"808",
    "addr:postcode":"23322",
    "addr:street":"Battlefield Blvd",
    "iso:country":"US",
    "sg:address":"808 Battlefield Blvd S",
    "sg:city":"Chesapeake",
    "sg:classifiers":[
        {
            "category":"Health Services",
            "subcategory":"Doctor",
            "type":"Services"
        }
    ],
    "sg:phone":"+1 757 482 4721",
    "sg:postcode":"23322",
    "sg:province":"VA",
    "sg:tags":[
        "physician",
        "surgeon",
        "medical"
    ],
    "wof:name":"Louis N Carideo MD Inc",
    "wof:placetype":"venue"
},
  "geometry": {"coordinates":[-76.233546,36.697741],"type":"Point"}
}