{
  "type": "Feature",
  "properties": {
    "addr:full":"2209 Baylake Rd Virginia Beach VA 23455",
    "addr:housenumber":"2209",
    "addr:postcode":"23455",
    "addr:street":"Baylake Rd",
    "iso:country":"US",
    "sg:address":"2209 Baylake Rd",
    "sg:city":"Virginia Beach",
    "sg:classifiers":[
        {
            "category":"Manufacturing",
            "subcategory":"Signs",
            "type":"Manufacturing & Wholesale Goods"
        }
    ],
    "sg:phone":"+1 757 621 1212",
    "sg:postcode":"23455",
    "sg:province":"VA",
    "wof:name":"Signmakers",
    "wof:placetype":"venue"
},
  "geometry": {"coordinates":[-76.11615999999999,36.907418],"type":"Point"}
}