{
  "type": "Feature",
  "properties": {
    "addr:full":"1459 N Main St Suffolk VA 23434",
    "addr:housenumber":"1459",
    "addr:postcode":"23434",
    "addr:street":"N Main St",
    "iso:country":"US",
    "sg:address":"1459 N Main St",
    "sg:city":"Suffolk",
    "sg:classifiers":[
        {
            "category":"Wholesale",
            "subcategory":"Electrical",
            "type":"Manufacturing & Wholesale Goods"
        }
    ],
    "sg:phone":"+1 757 539 0095",
    "sg:postcode":"23434",
    "sg:province":"VA",
    "sg:tags":[
        "electronic"
    ],
    "wof:name":"GTE",
    "wof:placetype":"venue"
},
  "geometry": {"coordinates":[-76.58339100000001,36.750091],"type":"Point"}
}