{
  "type": "Feature",
  "properties": {
    "iso:country":"US",
    "sg:address":"200 E Main St",
    "sg:city":"Purcellville",
    "sg:classifiers":[
        {
            "category":"Social Services",
            "type":"Services"
        }
    ],
    "sg:phone":"+1 540 751 0710",
    "sg:postcode":"20134",
    "sg:province":"VA",
    "wof:name":"Linda Kinney",
    "wof:placetype":"venue"
},
  "geometry": {"coordinates":[-77.712788,39.136609],"type":"Point"}
}