{
  "type": "Feature",
  "properties": {
    "addr:full":"714 N Sheppard St Richmond VA 23221",
    "addr:housenumber":"714",
    "addr:postcode":"23221",
    "addr:street":"N Sheppard St",
    "iso:country":"US",
    "sg:address":"714 N Sheppard St",
    "sg:city":"Richmond",
    "sg:classifiers":[
        {
            "category":"Personal",
            "subcategory":"Beauty Salon",
            "type":"Services"
        }
    ],
    "sg:phone":"+1 804 359 2544",
    "sg:postcode":"23221",
    "sg:province":"VA",
    "sg:tags":[
        "shop"
    ],
    "wof:name":"Underground A Salon",
    "wof:placetype":"venue"
},
  "geometry": {"coordinates":[-77.47388599999999,37.56092],"type":"Point"}
}