{
  "type": "Feature",
  "properties": {
    "addr:full":"5721 Littleton Rd Roanoke VA 24012",
    "addr:housenumber":"5721",
    "addr:postcode":"24012",
    "addr:street":"Littleton Rd",
    "iso:country":"US",
    "sg:address":"5721 Littleton Rd",
    "sg:city":"Roanoke",
    "sg:classifiers":[
        {
            "category":"Building & Trades",
            "subcategory":"Electrical",
            "type":"Services"
        }
    ],
    "sg:phone":"+1 540 362 5721",
    "sg:postcode":"24012",
    "sg:province":"VA",
    "sg:tags":[
        "electrical",
        "electric",
        "contractor"
    ],
    "wof:name":"Wood-Phillips Electrical Contr",
    "wof:placetype":"venue"
},
  "geometry": {"coordinates":[-79.95849200000001,37.32789],"type":"Point"}
}