{
  "type": "Feature",
  "properties": {
    "iso:country":"US",
    "sg:address":"150 Olde Greenwich Dr",
    "sg:city":"Fredericksburg",
    "sg:classifiers":[
        {
            "category":"Real Estate",
            "subcategory":"Real Estate Agent",
            "type":"Services"
        }
    ],
    "sg:phone":"+1 540 891 6460",
    "sg:postcode":"22408",
    "sg:province":"VA",
    "sg:tags":[
        "appraiser"
    ],
    "wof:name":"K B Appraisials",
    "wof:placetype":"venue"
},
  "geometry": {"coordinates":[-77.48202999999999,38.27145],"type":"Point"}
}