{
  "type": "Feature",
  "properties": {
    "addr:full":"6707 Tahalla Dr Alexandria VA 22306",
    "addr:housenumber":"6707",
    "addr:postcode":"22306",
    "addr:street":"Tahalla Dr",
    "iso:country":"US",
    "sg:address":"6707 Tahalla Dr",
    "sg:city":"Alexandria",
    "sg:classifiers":[
        {
            "category":"Professional",
            "subcategory":"Computer Services",
            "type":"Services"
        }
    ],
    "sg:phone":"+1 703 717 0000",
    "sg:postcode":"22306",
    "sg:province":"VA",
    "wof:name":"High Stepper Consulting Inc",
    "wof:placetype":"venue"
},
  "geometry": {"coordinates":[-77.09749100000001,38.771461],"type":"Point"}
}