{
  "type": "Feature",
  "properties": {
    "addr:full":"1955 Jonesboro Church Rd Blackstone VA 23824",
    "addr:housenumber":"1955",
    "addr:postcode":"23824",
    "addr:street":"Jonesboro Church Rd",
    "iso:country":"US",
    "sg:address":"1955 Jonesboro Church Rd",
    "sg:city":"Blackstone",
    "sg:classifiers":[
        {
            "category":"Organizations",
            "subcategory":"Religious Organization",
            "type":"Services"
        }
    ],
    "sg:phone":"+1 434 676 8923",
    "sg:postcode":"23824",
    "sg:province":"VA",
    "sg:tags":[
        "church"
    ],
    "wof:name":"Jonesboro Baptist Church",
    "wof:placetype":"venue"
},
  "geometry": {"coordinates":[-77.98537,36.989295],"type":"Point"}
}