{
  "type": "Feature",
  "properties": {
    "addr:full":"4806 Jefferson Davis Hwy Fredericksburg VA 22408",
    "addr:housenumber":"4806",
    "addr:postcode":"22408",
    "addr:street":"Jefferson Davis Hwy",
    "iso:country":"US",
    "sg:address":"4806 Jefferson Davis Hwy",
    "sg:city":"Fredericksburg",
    "sg:classifiers":[
        {
            "category":"Home & Garden",
            "subcategory":"Building Materials",
            "type":"Retail Goods"
        }
    ],
    "sg:phone":"+1 540 898 0208",
    "sg:postcode":"22408",
    "sg:province":"VA",
    "wof:name":"Duron Pints Wallcoverings 101",
    "wof:placetype":"venue"
},
  "geometry": {"coordinates":[-77.496478,38.260566],"type":"Point"}
}