{
  "type": "Feature",
  "properties": {
    "addr:full":"13700 Thorngate Rd Midlothian VA 23113",
    "addr:housenumber":"13700",
    "addr:postcode":"23113",
    "addr:street":"Thorngate Rd",
    "iso:country":"US",
    "sg:address":"13700 Thorngate Rd",
    "sg:city":"Midlothian",
    "sg:classifiers":[
        {
            "category":"Wholesale",
            "subcategory":"Non-durable Goods",
            "type":"Manufacturing & Wholesale Goods"
        }
    ],
    "sg:phone":"+1 804 379 1388",
    "sg:postcode":"23113",
    "sg:province":"VA",
    "sg:tags":[
        "basket",
        "handcrafted"
    ],
    "wof:name":"Longaberger Baskets",
    "wof:placetype":"venue"
},
  "geometry": {"coordinates":[-77.65440099999999,37.514666],"type":"Point"}
}