{
  "type": "Feature",
  "properties": {
    "addr:full":"17861 Stoneleigh Dr Round Hill VA 20141",
    "addr:postcode":"17861;20141",
    "addr:street":"Stoneleigh Dr",
    "iso:country":"US",
    "sg:address":"17861 Stoneleigh Dr",
    "sg:city":"Round Hill",
    "sg:classifiers":[
        {
            "category":"Health Services",
            "subcategory":"Doctor",
            "type":"Services"
        }
    ],
    "sg:phone":"+1 540 751 0058",
    "sg:postcode":"20141",
    "sg:province":"VA",
    "sg:tags":[
        "medical"
    ],
    "wof:name":"Psycon",
    "wof:placetype":"venue"
},
  "geometry": {"coordinates":[-77.786807,39.125067],"type":"Point"}
}