{
  "type": "Feature",
  "properties": {
    "iso:country":"US",
    "sg:address":"1865 Jones Ridge Rd",
    "sg:city":"Axton",
    "sg:classifiers":[
        {
            "category":"Communications",
            "type":"Services"
        }
    ],
    "sg:phone":"+1 276 650 3887",
    "sg:postcode":"24054",
    "sg:province":"VA",
    "sg:tags":[
        "communication"
    ],
    "wof:name":"Eddies Satellite Sales & Svc",
    "wof:placetype":"venue"
},
  "geometry": {"coordinates":[-79.714896,36.683228],"type":"Point"}
}