{
  "type": "Feature",
  "properties": {
    "addr:full":"221 Kessler Mill Rd Salem VA 24153",
    "addr:housenumber":"221",
    "addr:postcode":"24153",
    "addr:street":"Kessler Mill Rd",
    "iso:country":"US",
    "sg:address":"221 Kessler Mill Rd",
    "sg:city":"Salem",
    "sg:classifiers":[
        {
            "category":"Building & Trades",
            "subcategory":"Construction",
            "type":"Services"
        }
    ],
    "sg:phone":"+1 540 389 2927",
    "sg:postcode":"24153",
    "sg:province":"VA",
    "sg:tags":[
        "general",
        "contractor"
    ],
    "wof:name":"Con Line Inc",
    "wof:placetype":"venue"
},
  "geometry": {"coordinates":[-80.031297,37.29804],"type":"Point"}
}