{
  "type": "Feature",
  "properties": {
    "iso:country":"US",
    "sg:address":"11007 Harpine Hwy",
    "sg:city":"Broadway",
    "sg:classifiers":[
        {
            "category":"Arts & Performance",
            "subcategory":"Theater",
            "type":"Entertainment"
        }
    ],
    "sg:phone":"+1 540 896 9270",
    "sg:postcode":"22815",
    "sg:province":"VA",
    "sg:tags":[
        "live",
        "music"
    ],
    "wof:name":"Rick Rowe",
    "wof:placetype":"venue"
},
  "geometry": {"coordinates":[-78.80897299999999,38.592676],"type":"Point"}
}