{
  "type": "Feature",
  "properties": {
    "addr:full":"6526 Milva Ln Springfield VA 22150",
    "addr:housenumber":"6526",
    "addr:postcode":"22150",
    "addr:street":"Milva Ln",
    "iso:country":"US",
    "sg:address":"6526 Milva Ln",
    "sg:city":"Springfield",
    "sg:classifiers":[
        {
            "category":"Shopping",
            "subcategory":"Computers & Home Electronics",
            "type":"Retail Goods"
        }
    ],
    "sg:phone":"+1 703 912 9780",
    "sg:postcode":"22150",
    "sg:province":"VA",
    "sg:tags":[
        "software"
    ],
    "wof:name":"Lab Connect Inc",
    "wof:placetype":"venue"
},
  "geometry": {"coordinates":[-77.198848,38.776738],"type":"Point"}
}