{
  "type": "Feature",
  "properties": {
    "iso:country":"US",
    "sg:address":"640 Denbigh Blvd",
    "sg:city":"Newport News",
    "sg:classifiers":[
        {
            "category":"Health Services",
            "subcategory":"Doctor",
            "type":"Services"
        }
    ],
    "sg:phone":"+1 757 890 6121",
    "sg:postcode":"23608",
    "sg:province":"VA",
    "sg:tags":[
        "physician",
        "surgeon"
    ],
    "wof:name":"Hemorrhoid Clinic",
    "wof:placetype":"venue"
},
  "geometry": {"coordinates":[-76.52048499999999,37.138063],"type":"Point"}
}