{
  "type": "Feature",
  "properties": {
    "addr:full":"229 Lakeside Dr Stephens City VA 22655",
    "addr:housenumber":"229",
    "addr:postcode":"22655",
    "addr:street":"Lakeside Dr Stephens",
    "iso:country":"US",
    "sg:address":"229 Lakeside Dr",
    "sg:city":"Stephens City",
    "sg:classifiers":[
        {
            "category":"Building & Trades",
            "subcategory":"Plumbing",
            "type":"Services"
        }
    ],
    "sg:phone":"+1 540 868 1109",
    "sg:postcode":"22655",
    "sg:province":"VA",
    "sg:tags":[
        "plumbing",
        "contractor"
    ],
    "wof:name":"Shanandoah Valley Plumbing",
    "wof:placetype":"venue"
},
  "geometry": {"coordinates":[-78.18246000000001,39.102202],"type":"Point"}
}