{
  "type": "Feature",
  "properties": {
    "addr:full":"10431 Verdon Rd Doswell VA 23047",
    "addr:postcode":"10431;23047",
    "addr:street":"Verdon Rd",
    "iso:country":"US",
    "sg:address":"10431 Verdon Rd",
    "sg:city":"Doswell",
    "sg:classifiers":[
        {
            "category":"Home & Garden",
            "subcategory":"Building Materials",
            "type":"Retail Goods"
        }
    ],
    "sg:phone":"+1 804 270 6779",
    "sg:postcode":"23047",
    "sg:province":"VA",
    "sg:tags":[
        "glass",
        "window",
        "plate"
    ],
    "wof:name":"Super Glass Windshield Repair",
    "wof:placetype":"venue"
},
  "geometry": {"coordinates":[-77.468903,37.865597],"type":"Point"}
}