{
  "type": "Feature",
  "properties": {
    "addr:full":"3533 Pruden Blvd Suffolk VA 23434",
    "addr:postcode":"3533;23434",
    "addr:street":"Pruden Blvd",
    "iso:country":"US",
    "sg:address":"3533 Pruden Blvd",
    "sg:city":"Suffolk",
    "sg:classifiers":[
        {
            "category":"Shopping",
            "subcategory":"Used Merchandise",
            "type":"Retail Goods"
        }
    ],
    "sg:phone":"+1 757 539 6269",
    "sg:postcode":"23434",
    "sg:province":"VA",
    "wof:name":"Nansemond Antique Shop",
    "wof:placetype":"venue"
},
  "geometry": {"coordinates":[-76.622731,36.778629],"type":"Point"}
}