{
  "type": "Feature",
  "properties": {
    "addr:full":"2622 Southern Blvd Virginia Beach VA 23452",
    "addr:housenumber":"2622",
    "addr:postcode":"23452",
    "addr:street":"Southern Blvd",
    "iso:country":"US",
    "sg:address":"2622 Southern Blvd",
    "sg:city":"Virginia Beach",
    "sg:classifiers":[
        {
            "category":"Building & Trades",
            "subcategory":"Construction",
            "type":"Services"
        }
    ],
    "sg:phone":"+1 757 435 0326",
    "sg:postcode":"23452",
    "sg:province":"VA",
    "sg:tags":[
        "residential"
    ],
    "wof:name":"K & V Homes LLC",
    "wof:placetype":"venue"
},
  "geometry": {"coordinates":[-76.06385,36.83905],"type":"Point"}
}