{
  "type": "Feature",
  "properties": {
    "addr:full":"114 Sheraton Dr Salem VA 24153",
    "addr:housenumber":"114",
    "addr:postcode":"24153",
    "addr:street":"Sheraton Dr",
    "iso:country":"US",
    "sg:address":"114 Sheraton Dr",
    "sg:city":"Salem",
    "sg:classifiers":[
        {
            "category":"Fast Food",
            "type":"Food & Drink"
        },
        {
            "category":"Food & Beverages",
            "subcategory":"Meat & Fish",
            "type":"Retail Goods"
        }
    ],
    "sg:phone":"+1 540 562 2578",
    "sg:postcode":"24153",
    "sg:province":"VA",
    "sg:tags":[
        "burger",
        "hot",
        "dog"
    ],
    "sg:website":"www.burgerking.com",
    "wof:name":"Burger King",
    "wof:placetype":"venue"
},
  "geometry": {"coordinates":[-80.031387,37.31993],"type":"Point"}
}