{
  "type": "Feature",
  "properties": {
    "addr:full":"2774 Beaverrun Rd Powhatan VA 23139",
    "addr:housenumber":"2774",
    "addr:postcode":"23139",
    "addr:street":"Beaverrun Rd",
    "iso:country":"US",
    "sg:address":"2774 Beaverrun Rd",
    "sg:city":"Powhatan",
    "sg:classifiers":[
        {
            "category":"Building & Trades",
            "subcategory":"Construction",
            "type":"Services"
        }
    ],
    "sg:phone":"+1 804 598 5433",
    "sg:postcode":"23139",
    "sg:province":"VA",
    "sg:tags":[
        "hanging",
        "contractor"
    ],
    "wof:name":"MB Rickard Painting",
    "wof:placetype":"venue"
},
  "geometry": {"coordinates":[-77.85309100000001,37.572038],"type":"Point"}
}