{
  "type": "Feature",
  "properties": {
    "addr:full":"4451 Brookfield Corporate Dr Chantilly VA 20151",
    "addr:housenumber":"4451",
    "addr:postcode":"20151",
    "addr:street":"Brookfield Corporate Dr",
    "iso:country":"US",
    "sg:address":"4451 Brookfield Corporate Dr",
    "sg:city":"Chantilly",
    "sg:classifiers":[
        {
            "category":"Real Estate",
            "subcategory":"Real Estate Agent",
            "type":"Services"
        }
    ],
    "sg:phone":"+1 703 802 1061",
    "sg:postcode":"20151",
    "sg:province":"VA",
    "wof:name":"Quest Management Services Inc",
    "wof:placetype":"venue"
},
  "geometry": {"coordinates":[-77.43903,38.886953],"type":"Point"}
}