{
  "type": "Feature",
  "properties": {
    "addr:full":"820 W Broadway Ave Hopewell VA 23860",
    "addr:housenumber":"820",
    "addr:postcode":"23860",
    "addr:street":"W Broadway Ave",
    "iso:country":"US",
    "sg:address":"820 W Broadway Ave",
    "sg:city":"Hopewell",
    "sg:classifiers":[
        {
            "category":"Retail",
            "subcategory":"Funeral Services",
            "type":"Services"
        }
    ],
    "sg:phone":"+1 804 458 8516",
    "sg:postcode":"23860",
    "sg:province":"VA",
    "sg:tags":[
        "director"
    ],
    "sg:website":"www.jtmorriss.com",
    "wof:name":"J T Morriss & Son Inc",
    "wof:placetype":"venue"
},
  "geometry": {"coordinates":[-77.29461499999999,37.303354],"type":"Point"}
}