{
  "type": "Feature",
  "properties": {
    "iso:country":"US",
    "sg:address":"805 Balls Hill Rd",
    "sg:city":"Mc Lean",
    "sg:classifiers":[
        {
            "category":"Professional",
            "type":"Services"
        }
    ],
    "sg:phone":"+1 703 893 0748",
    "sg:postcode":"22101",
    "sg:province":"VA",
    "wof:name":"Al Etifakiyat Al Alameia Corp",
    "wof:placetype":"venue"
},
  "geometry": {"coordinates":[-77.191439,38.958184],"type":"Point"}
}