{
  "type": "Feature",
  "properties": {
    "addr:full":"600 Madison St Alexandria VA 22314",
    "addr:housenumber":"600",
    "addr:postcode":"22314",
    "addr:street":"Madison St",
    "iso:country":"US",
    "sg:address":"600 Madison St",
    "sg:city":"Alexandria",
    "sg:classifiers":[
        {
            "category":"Personal",
            "type":"Services"
        },
        {
            "category":"Retail",
            "subcategory":"Portrait Studio",
            "type":"Services"
        },
        {
            "category":"Professional",
            "subcategory":"Art Services",
            "type":"Services"
        }
    ],
    "sg:phone":"+1 703 548 1669",
    "sg:postcode":"22314",
    "sg:province":"VA",
    "sg:tags":[
        "photographers-portrait",
        "videography",
        "darkroom",
        "rental",
        "photography",
        "wedding",
        "photographic"
    ],
    "wof:name":"Matt Mendelsohn Photography",
    "wof:placetype":"venue"
},
  "geometry": {"coordinates":[-77.044113,38.812859],"type":"Point"}
}