{
  "type": "Feature",
  "properties": {
    "addr:full":"1320 Ohio St Waynesboro VA 22980",
    "addr:housenumber":"1320",
    "addr:postcode":"22980",
    "addr:street":"Ohio St",
    "iso:country":"US",
    "sg:address":"1320 Ohio St",
    "sg:city":"Waynesboro",
    "sg:classifiers":[
        {
            "category":"Manufacturing",
            "subcategory":"Tobacco Products",
            "type":"Manufacturing & Wholesale Goods"
        }
    ],
    "sg:phone":"+1 540 943 8554",
    "sg:postcode":"22980",
    "sg:province":"VA",
    "wof:name":"Lorillard Tobacco Co",
    "wof:placetype":"venue"
},
  "geometry": {"coordinates":[-78.898082,38.074677],"type":"Point"}
}