{
  "type": "Feature",
  "properties": {
    "addr:full":"820 Greenbrier Pkwy Chesapeake VA 23320",
    "addr:housenumber":"820",
    "addr:postcode":"23320",
    "addr:street":"Greenbrier Pkwy",
    "iso:country":"US",
    "sg:address":"820 Greenbrier Pkwy",
    "sg:city":"Chesapeake",
    "sg:classifiers":[
        {
            "category":"Manufacturing",
            "subcategory":"Watercraft",
            "type":"Manufacturing & Wholesale Goods"
        }
    ],
    "sg:phone":"+1 757 420 5886",
    "sg:postcode":"23320",
    "sg:province":"VA",
    "sg:tags":[
        "navy",
        "on",
        "install",
        "vessel",
        "deck"
    ],
    "wof:name":"Paige Flrg Cverings Specialist",
    "wof:placetype":"venue"
},
  "geometry": {"coordinates":[-76.223316,36.747651],"type":"Point"}
}