{
  "type": "Feature",
  "properties": {
    "iso:country":"US",
    "sg:address":"1809 Greenbrier Pkwy",
    "sg:city":"Chesapeake",
    "sg:classifiers":[
        {
            "category":"Banks & Credit Unions",
            "subcategory":"Bank",
            "type":"Services"
        }
    ],
    "sg:phone":"+1 757 523 4461",
    "sg:postcode":"23320",
    "sg:province":"VA",
    "sg:tags":[
        "commercial"
    ],
    "wof:name":"BB&T",
    "wof:placetype":"venue"
},
  "geometry": {"coordinates":[-76.238575,36.79074],"type":"Point"}
}