{
  "type": "Feature",
  "properties": {
    "addr:full":"25108 Custis Neck Rd Accomac VA 23301",
    "addr:postcode":"25108;23301",
    "addr:street":"Custis Neck Rd",
    "iso:country":"US",
    "sg:address":"25108 Custis Neck Rd",
    "sg:city":"Accomac",
    "sg:phone":"+1 757 787 8057",
    "sg:postcode":"23301",
    "sg:province":"VA",
    "sg:tags":[
        "farm"
    ],
    "wof:name":"Bill Wolfram",
    "wof:placetype":"venue"
},
  "geometry": {"coordinates":[-75.645292,37.686476],"type":"Point"}
}