{
  "type": "Feature",
  "properties": {
    "addr:full":"9040 Pams Ave Richmond VA 23237",
    "addr:postcode":"9040;23237",
    "addr:street":"Pams Ave",
    "iso:country":"US",
    "sg:address":"9040 Pams Ave",
    "sg:city":"Richmond",
    "sg:classifiers":[
        {
            "category":"Travel",
            "subcategory":"Hotels & Motels",
            "type":"Entertainment"
        }
    ],
    "sg:phone":"+1 804 743 0770",
    "sg:postcode":"23237",
    "sg:province":"VA",
    "wof:name":"Ram & Sam Corp",
    "wof:placetype":"venue"
},
  "geometry": {"coordinates":[-77.427491,37.400976],"type":"Point"}
}