{
  "type": "Feature",
  "properties": {
    "addr:full":"225 Joshua Rd Stafford VA 22556",
    "addr:housenumber":"225",
    "addr:postcode":"22556",
    "addr:street":"Joshua Rd",
    "iso:country":"US",
    "sg:address":"225 Joshua Rd",
    "sg:city":"Stafford",
    "sg:classifiers":[
        {
            "category":"Freight",
            "type":"Transportation"
        }
    ],
    "sg:phone":"+1 540 659 1548",
    "sg:postcode":"22556",
    "sg:province":"VA",
    "sg:tags":[
        "local",
        "trucking"
    ],
    "wof:name":"Cottoms Trucking, Inc.",
    "wof:placetype":"venue"
},
  "geometry": {"coordinates":[-77.500202,38.477702],"type":"Point"}
}