{
  "type": "Feature",
  "properties": {
    "addr:full":"307 Main St Washington VA 22747",
    "addr:housenumber":"307",
    "addr:postcode":"22747",
    "addr:street":"Main St",
    "iso:country":"US",
    "sg:address":"307 Main St",
    "sg:city":"Washington",
    "sg:classifiers":[
        {
            "category":"Shopping",
            "type":"Retail Goods"
        }
    ],
    "sg:phone":"+1 540 675 1113",
    "sg:postcode":"22747",
    "sg:province":"VA",
    "sg:tags":[
        "art",
        "gallery",
        "dealer"
    ],
    "wof:name":"Tanya M Richey Gallery",
    "wof:placetype":"venue"
},
  "geometry": {"coordinates":[-78.159963,38.712729],"type":"Point"}
}