{
  "type": "Feature",
  "properties": {
    "addr:full":"952 Thomas Nelson Hwy Arrington VA 22922",
    "addr:housenumber":"952 thomas",
    "addr:postcode":"22922",
    "addr:street":"Nelson Hwy",
    "iso:country":"US",
    "sg:address":"952 Thomas Nelson Hwy",
    "sg:city":"Arrington",
    "sg:classifiers":[
        {
            "category":"Building & Trades",
            "subcategory":"Construction",
            "type":"Services"
        }
    ],
    "sg:phone":"+1 434 263 4287",
    "sg:postcode":"22922",
    "sg:province":"VA",
    "sg:tags":[
        "general",
        "contractor"
    ],
    "wof:name":"Hall's Well & Pump Co",
    "wof:placetype":"venue"
},
  "geometry": {"coordinates":[-78.953191,37.668622],"type":"Point"}
}