{
  "type": "Feature",
  "properties": {
    "addr:full":"409 N Ridge Rd Richmond VA 23229",
    "addr:housenumber":"409",
    "addr:postcode":"23229",
    "addr:street":"N Ridge Rd",
    "iso:country":"US",
    "sg:address":"409 N Ridge Rd",
    "sg:city":"Richmond",
    "sg:classifiers":[
        {
            "category":"Personal",
            "subcategory":"Barber",
            "type":"Services"
        }
    ],
    "sg:phone":"+1 804 288 4736",
    "sg:postcode":"23229",
    "sg:province":"VA",
    "sg:tags":[
        "shop"
    ],
    "wof:name":"Bubba's Barber Shop",
    "wof:placetype":"venue"
},
  "geometry": {"coordinates":[-77.555089,37.582302],"type":"Point"}
}