{
  "type": "Feature",
  "properties": {
    "addr:full":"1284 W Main St Abingdon VA 24210",
    "addr:housenumber":"1284",
    "addr:postcode":"24210",
    "addr:street":"W Main St",
    "iso:country":"US",
    "sg:address":"1284 W Main St",
    "sg:city":"Abingdon",
    "sg:classifiers":[
        {
            "category":"Retail",
            "subcategory":"Auto Repair",
            "type":"Services"
        }
    ],
    "sg:phone":"+1 276 628 5179",
    "sg:postcode":"24210",
    "sg:province":"VA",
    "sg:tags":[
        "shop",
        "automobile",
        "machine",
        "general",
        "supply"
    ],
    "wof:name":"Abingdon Auto Machine Co Inc",
    "wof:placetype":"venue"
},
  "geometry": {"coordinates":[-82.017636,36.695199],"type":"Point"}
}