{
  "type": "Feature",
  "properties": {
    "addr:full":"8315-B Leesburg Pke Vienna VA 22182",
    "addr:housenumber":"8315-b",
    "addr:postcode":"22182",
    "addr:street":"Leesburg Pke",
    "iso:country":"US",
    "sg:address":"8315-B Leesburg Pke",
    "sg:city":"Vienna",
    "sg:classifiers":[
        {
            "category":"Restaurant",
            "type":"Food & Drink"
        }
    ],
    "sg:phone":"+1 703 893 2333",
    "sg:postcode":"22182",
    "sg:province":"VA",
    "sg:tags":[
        "afghan"
    ],
    "sg:website":"foodcornerkabob.com",
    "wof:name":"Food Corner Kabob House",
    "wof:placetype":"venue"
},
  "geometry": {"coordinates":[-77.23513699999999,38.919728],"type":"Point"}
}