{
  "type": "Feature",
  "properties": {
    "addr:full":"178 Dusty Ln Ararat VA 24053",
    "addr:housenumber":"178",
    "addr:postcode":"24053",
    "addr:street":"Dusty Ln",
    "iso:country":"US",
    "sg:address":"178 Dusty Ln",
    "sg:city":"Ararat",
    "sg:classifiers":[
        {
            "category":"Professional",
            "type":"Services"
        }
    ],
    "sg:phone":"+1 276 251 8393",
    "sg:postcode":"24053",
    "sg:province":"VA",
    "wof:name":"Ricky F Smith",
    "wof:placetype":"venue"
},
  "geometry": {"coordinates":[-80.58915399999999,36.614362],"type":"Point"}
}