{
  "type": "Feature",
  "properties": {
    "addr:full":"12000 Canon Blvd Newport News VA 23606",
    "addr:housenumber":"12000",
    "addr:postcode":"23606",
    "addr:street":"Canon Blvd",
    "iso:country":"US",
    "sg:address":"12000 Canon Blvd",
    "sg:city":"Newport News",
    "sg:classifiers":[
        {
            "category":"Restaurant",
            "type":"Food & Drink"
        }
    ],
    "sg:phone":"+1 757 881 6192",
    "sg:postcode":"23606",
    "sg:province":"VA",
    "sg:tags":[
        "eating"
    ],
    "wof:name":"Aramark",
    "wof:placetype":"venue"
},
  "geometry": {"coordinates":[-76.47972300000001,37.101957],"type":"Point"}
}