{
  "type": "Feature",
  "properties": {
    "iso:country":"US",
    "sg:address":"7257 Spring Side Way",
    "sg:city":"Mc Lean",
    "sg:classifiers":[
        {
            "category":"Professional",
            "subcategory":"Computer Services",
            "type":"Services"
        }
    ],
    "sg:phone":"+1 703 362 6657",
    "sg:postcode":"22101",
    "sg:province":"VA",
    "sg:tags":[
        "programing",
        "custom"
    ],
    "wof:name":"Outfront Tech LLC",
    "wof:placetype":"venue"
},
  "geometry": {"coordinates":[-77.194851,38.937194],"type":"Point"}
}