{
  "type": "Feature",
  "properties": {
    "addr:full":"1386 Lawson Cir Suffolk VA 23434",
    "addr:housenumber":"1386",
    "addr:postcode":"23434",
    "addr:street":"Lawson Cir",
    "iso:country":"US",
    "sg:address":"1386 Lawson Cir",
    "sg:city":"Suffolk",
    "sg:classifiers":[
        {
            "category":"Professional",
            "subcategory":"Business Services",
            "type":"Services"
        }
    ],
    "sg:phone":"+1 757 934 1103",
    "sg:postcode":"23434",
    "sg:province":"VA",
    "wof:name":"Laura Timmons",
    "wof:placetype":"venue"
},
  "geometry": {"coordinates":[-76.62142,36.702142],"type":"Point"}
}