{
  "type": "Feature",
  "properties": {
    "iso:country":"US",
    "sg:address":"1859 N Cameron St",
    "sg:city":"Arlington",
    "sg:classifiers":[
        {
            "category":"Building & Trades",
            "subcategory":"Locksmith",
            "type":"Services"
        }
    ],
    "sg:phone":"+1 703 399 3101",
    "sg:postcode":"22207",
    "sg:province":"VA",
    "sg:tags":[
        "key"
    ],
    "wof:name":"AAA Emergency Locksmith Service",
    "wof:placetype":"venue"
},
  "geometry": {"coordinates":[-77.124349,38.892444],"type":"Point"}
}