{
  "type": "Feature",
  "properties": {
    "addr:full":"7759 New Providence Dr Falls Church VA 22042",
    "addr:housenumber":"7759",
    "addr:postcode":"22042",
    "addr:street":"New Providence Dr",
    "iso:country":"US",
    "sg:address":"7759 New Providence Dr",
    "sg:city":"Falls Church",
    "sg:classifiers":[
        {
            "category":"Professional",
            "type":"Services"
        }
    ],
    "sg:phone":"+1 703 560 5927",
    "sg:postcode":"22042",
    "sg:province":"VA",
    "wof:name":"SOO H Moon",
    "wof:placetype":"venue"
},
  "geometry": {"coordinates":[-77.21259499999999,38.87272],"type":"Point"}
}