{
  "type": "Feature",
  "properties": {
    "iso:country":"US",
    "sg:address":"528 W 35th St",
    "sg:city":"Norfolk",
    "sg:classifiers":[
        {
            "category":"Retail",
            "subcategory":"Repair Shop",
            "type":"Services"
        }
    ],
    "sg:phone":"+1 757 627 5997",
    "sg:postcode":"23508",
    "sg:province":"VA",
    "sg:tags":[
        "television",
        "radio"
    ],
    "wof:name":"May's Radio & TV Svc",
    "wof:placetype":"venue"
},
  "geometry": {"coordinates":[-76.289974,36.878187],"type":"Point"}
}