{
  "type": "Feature",
  "properties": {
    "addr:full":"10443 Balls Ford Rd Manassas VA 20109",
    "addr:housenumber":"10443",
    "addr:postcode":"20109",
    "addr:street":"Balls Ford Rd",
    "iso:country":"US",
    "sg:address":"10443 Balls Ford Rd",
    "sg:city":"Manassas",
    "sg:classifiers":[
        {
            "category":"Manufacturing",
            "subcategory":"Printing",
            "type":"Manufacturing & Wholesale Goods"
        }
    ],
    "sg:phone":"+1 703 335 5663",
    "sg:postcode":"20109",
    "sg:province":"VA",
    "sg:tags":[
        "commercial",
        "printer",
        "off"
    ],
    "wof:name":"Century Press Inc",
    "wof:placetype":"venue"
},
  "geometry": {"coordinates":[-77.505758,38.802326],"type":"Point"}
}