{
  "type": "Feature",
  "properties": {
    "addr:full":"8286 Humphrey Ln Manassas VA 20109",
    "addr:housenumber":"8286",
    "addr:postcode":"20109",
    "addr:street":"Humphrey Ln",
    "iso:country":"US",
    "sg:address":"8286 Humphrey Ln",
    "sg:city":"Manassas",
    "sg:classifiers":[
        {
            "category":"Organizations",
            "subcategory":"Religious Organization",
            "type":"Services"
        }
    ],
    "sg:phone":"+1 703 392 3691",
    "sg:postcode":"20109",
    "sg:province":"VA",
    "wof:name":"Friends & Fellowship Inc",
    "wof:placetype":"venue"
},
  "geometry": {"coordinates":[-77.527462,38.777246],"type":"Point"}
}