{
  "type": "Feature",
  "properties": {
    "addr:full":"506 Jordan Ave Smithfield VA 23430",
    "addr:housenumber":"506",
    "addr:postcode":"23430",
    "addr:street":"Jordan Ave",
    "iso:country":"US",
    "sg:address":"506 Jordan Ave",
    "sg:city":"Smithfield",
    "sg:classifiers":[
        {
            "category":"Autos & Motor Vehicles",
            "subcategory":"Fuel & Gas Station",
            "type":"Retail Goods"
        }
    ],
    "sg:phone":"+1 757 365 9905",
    "sg:postcode":"23430",
    "sg:province":"VA",
    "sg:tags":[
        "station",
        "gasoline"
    ],
    "wof:name":"West Norfolk Service Station",
    "wof:placetype":"venue"
},
  "geometry": {"coordinates":[-76.61781999999999,36.988594],"type":"Point"}
}