{
  "type": "Feature",
  "properties": {
    "addr:full":"1108 Turtle Rock Trce Chesapeake VA 23320",
    "addr:housenumber":"1108",
    "addr:postcode":"23320",
    "addr:street":"Turtle Rock Trce",
    "iso:country":"US",
    "sg:address":"1108 Turtle Rock Trce",
    "sg:city":"Chesapeake",
    "sg:classifiers":[
        {
            "category":"Social Services",
            "subcategory":"Child Care",
            "type":"Services"
        }
    ],
    "sg:phone":"+1 757 548 3523",
    "sg:postcode":"23320",
    "sg:province":"VA",
    "sg:tags":[
        "day"
    ],
    "wof:name":"Patricia B Hillman",
    "wof:placetype":"venue"
},
  "geometry": {"coordinates":[-76.225734,36.771624],"type":"Point"}
}