{
  "type": "Feature",
  "properties": {
    "iso:country":"US",
    "sg:address":"2070 Mount Tabor Rd",
    "sg:city":"Blacksburg",
    "sg:classifiers":[
        {
            "category":"Education",
            "subcategory":"Special Training",
            "type":"Public Place"
        }
    ],
    "sg:phone":"+1 540 552 1383",
    "sg:postcode":"24060",
    "sg:province":"VA",
    "wof:name":"Renaissance Music",
    "wof:placetype":"venue"
},
  "geometry": {"coordinates":[-80.367616,37.295809],"type":"Point"}
}