{
  "type": "Feature",
  "properties": {
    "addr:full":"5607 Michael Ln Portsmouth VA 23703",
    "addr:housenumber":"5607",
    "addr:postcode":"23703",
    "addr:street":"Michael Ln",
    "iso:country":"US",
    "sg:address":"5607 Michael Ln",
    "sg:city":"Portsmouth",
    "sg:classifiers":[
        {
            "category":"Organizations",
            "subcategory":"Membership Organization",
            "type":"Services"
        }
    ],
    "sg:phone":"+1 757 638 6500",
    "sg:postcode":"23703",
    "sg:province":"VA",
    "wof:name":"Churchland Little League",
    "wof:placetype":"venue"
},
  "geometry": {"coordinates":[-76.384632,36.858939],"type":"Point"}
}