{
  "type": "Feature",
  "properties": {
    "addr:full":"113 E Lee Ave Vinton VA 24179",
    "addr:housenumber":"113",
    "addr:postcode":"24179",
    "addr:street":"E Lee Ave",
    "iso:country":"US",
    "sg:address":"113 E Lee Ave",
    "sg:city":"Vinton",
    "sg:classifiers":[
        {
            "category":"Professional",
            "subcategory":"Lawyer & Legal Services",
            "type":"Services"
        }
    ],
    "sg:phone":"+1 540 982 1212",
    "sg:postcode":"24179",
    "sg:province":"VA",
    "sg:tags":[
        "attorney"
    ],
    "wof:name":"Valeria Cook Law Offices",
    "wof:placetype":"venue"
},
  "geometry": {"coordinates":[-79.89661700000001,37.279707],"type":"Point"}
}