{
  "type": "Feature",
  "properties": {
    "iso:country":"US",
    "sg:address":"2250 Murrell Rd",
    "sg:city":"Lynchburg",
    "sg:classifiers":[
        {
            "category":"Health Services",
            "subcategory":"Hospital",
            "type":"Services"
        },
        {
            "category":"Social Services",
            "type":"Services"
        }
    ],
    "sg:phone":"+1 434 846 6744",
    "sg:postcode":"24501",
    "sg:province":"VA",
    "sg:tags":[
        "mental"
    ],
    "wof:name":"Capstone Counseling Assoc Pllc",
    "wof:placetype":"venue"
},
  "geometry": {"coordinates":[-79.170422,37.408106],"type":"Point"}
}