{
  "type": "Feature",
  "properties": {
    "addr:full":"13449 Cobra Dr Herndon VA 20171",
    "addr:housenumber":"13449",
    "addr:postcode":"20171",
    "addr:street":"Cobra Dr",
    "iso:country":"US",
    "sg:address":"13449 Cobra Dr",
    "sg:city":"Herndon",
    "sg:classifiers":[
        {
            "category":"Professional",
            "subcategory":"Computer Services",
            "type":"Services"
        }
    ],
    "sg:phone":"+1 703 742 0043",
    "sg:postcode":"20171",
    "sg:province":"VA",
    "sg:tags":[
        "programming"
    ],
    "wof:name":"M&N Technology Inc",
    "wof:placetype":"venue"
},
  "geometry": {"coordinates":[-77.409808,38.919077],"type":"Point"}
}