{
  "type": "Feature",
  "properties": {
    "addr:full":"609 Hopewell Dr Chesapeake VA 23323",
    "addr:housenumber":"609",
    "addr:postcode":"23323",
    "addr:street":"Hopewell Dr",
    "iso:country":"US",
    "sg:address":"609 Hopewell Dr",
    "sg:city":"Chesapeake",
    "sg:classifiers":[
        {
            "category":"Building & Trades",
            "subcategory":"Construction",
            "type":"Services"
        }
    ],
    "sg:phone":"+1 757 487 8510",
    "sg:postcode":"23323",
    "sg:province":"VA",
    "sg:tags":[
        "resurfacing",
        "laying",
        "refinishing",
        "floor"
    ],
    "wof:name":"Wimbley's Floor Svc",
    "wof:placetype":"venue"
},
  "geometry": {"coordinates":[-76.333431,36.764841],"type":"Point"}
}