{
  "type": "Feature",
  "properties": {
    "addr:full":"200 21st St Virginia Beach VA 23451",
    "addr:housenumber":"200",
    "addr:postcode":"23451",
    "addr:street":"21St St",
    "iso:country":"US",
    "sg:address":"200 21st St",
    "sg:city":"Virginia Beach",
    "sg:classifiers":[
        {
            "category":"Restaurant",
            "type":"Food & Drink"
        }
    ],
    "sg:phone":"+1 757 425 6955",
    "sg:postcode":"23451",
    "sg:province":"VA",
    "wof:name":"Subway Sandwiches & Salads",
    "wof:placetype":"venue"
},
  "geometry": {"coordinates":[-75.976567,36.849038],"type":"Point"}
}