{
  "type": "Feature",
  "properties": {
    "addr:full":"2111 Wilson Blvd Ste 1025 Arlington VA 22201",
    "addr:housenumber":"2111",
    "addr:postcode":"22201",
    "addr:street":"Wilson Blvd Ste 1025",
    "iso:country":"US",
    "sg:address":"2111 Wilson Blvd Ste 1025",
    "sg:city":"Arlington",
    "sg:classifiers":[
        {
            "category":"Real Estate",
            "subcategory":"Real Estate Services",
            "type":"Services"
        }
    ],
    "sg:phone":"+1 703 527 9444",
    "sg:postcode":"22201",
    "sg:province":"VA",
    "sg:tags":[
        "management",
        "property"
    ],
    "wof:name":"Colonial Place",
    "wof:placetype":"venue"
},
  "geometry": {"coordinates":[-77.0849,38.891499],"type":"Point"}
}