{
  "type": "Feature",
  "properties": {
    "addr:full":"9205 Vassau Ct Manassas Park VA 20111",
    "addr:housenumber":"9205",
    "addr:postcode":"20111",
    "addr:street":"Vassau Ct;Park",
    "iso:country":"US",
    "sg:address":"9205 Vassau Ct",
    "sg:city":"Manassas Park",
    "sg:classifiers":[
        {
            "category":"Manufacturing",
            "subcategory":"Building Materials",
            "type":"Manufacturing & Wholesale Goods"
        },
        {
            "category":"Building & Trades",
            "subcategory":"Construction",
            "type":"Services"
        }
    ],
    "sg:phone":"+1 703 335 9655",
    "sg:postcode":"20111",
    "sg:province":"VA",
    "sg:tags":[
        "mfg",
        "contractor",
        "wood",
        "carpentry",
        "cabinet",
        "maker",
        "furn"
    ],
    "wof:name":"Interior Building Systems Corp",
    "wof:placetype":"venue"
},
  "geometry": {"coordinates":[-77.438669,38.778071],"type":"Point"}
}