{
  "type": "Feature",
  "properties": {
    "iso:country":"US",
    "sg:address":"2301 Hilliard Rd",
    "sg:city":"Richmond",
    "sg:classifiers":[
        {
            "category":"Health Services",
            "subcategory":"Doctor",
            "type":"Services"
        }
    ],
    "sg:phone":"+1 804 262 9563",
    "sg:postcode":"23228",
    "sg:province":"VA",
    "sg:tags":[
        "dentist"
    ],
    "wof:name":"David R Coward DDS",
    "wof:placetype":"venue"
},
  "geometry": {"coordinates":[-77.476691,37.616507],"type":"Point"}
}