{
  "type": "Feature",
  "properties": {
    "iso:country":"US",
    "sg:address":"12839 Old Bridge Ln",
    "sg:city":"Woodbridge",
    "sg:classifiers":[
        {
            "category":"Shopping",
            "type":"Retail Goods"
        }
    ],
    "sg:phone":"+1 703 730 2455",
    "sg:postcode":"22192",
    "sg:province":"VA",
    "sg:tags":[
        "merchandise"
    ],
    "wof:name":"Angies Shops",
    "wof:placetype":"venue"
},
  "geometry": {"coordinates":[-77.328605,38.676536],"type":"Point"}
}