{
  "type": "Feature",
  "properties": {
    "iso:country":"US",
    "sg:address":"1195 Elkton Farm Rd",
    "sg:city":"Forest",
    "sg:classifiers":[
        {
            "category":"Building & Trades",
            "subcategory":"Construction",
            "type":"Services"
        }
    ],
    "sg:phone":"+1 434 525 1019",
    "sg:postcode":"24551",
    "sg:province":"VA",
    "sg:tags":[
        "excavating",
        "contractor"
    ],
    "wof:name":"Cricket Excavating",
    "wof:placetype":"venue"
},
  "geometry": {"coordinates":[-79.299178,37.364309],"type":"Point"}
}