{
  "type": "Feature",
  "properties": {
    "iso:country":"US",
    "sg:address":"13884 Park Center Rd",
    "sg:city":"Herndon",
    "sg:classifiers":[
        {
            "category":"Manufacturing",
            "subcategory":"Chemicals & Compounds",
            "type":"Manufacturing & Wholesale Goods"
        }
    ],
    "sg:phone":"+1 703 471 5955",
    "sg:postcode":"20171",
    "sg:province":"VA",
    "sg:tags":[
        "biological",
        "product",
        "mfg"
    ],
    "wof:name":"Cellgro",
    "wof:placetype":"venue"
},
  "geometry": {"coordinates":[-77.426219,38.933519],"type":"Point"}
}