{
  "type": "Feature",
  "properties": {
    "addr:full":"372 County Bridge Rd Warsaw VA 22572",
    "addr:housenumber":"372",
    "addr:postcode":"22572",
    "addr:street":"County Bridge Rd",
    "iso:country":"US",
    "sg:address":"372 County Bridge Rd",
    "sg:city":"Warsaw",
    "sg:classifiers":[
        {
            "category":"Place Of Worship",
            "type":"Public Place"
        },
        {
            "category":"Organizations",
            "subcategory":"Religious Organization",
            "type":"Services"
        }
    ],
    "sg:phone":"+1 804 333 3072",
    "sg:postcode":"22572",
    "sg:province":"VA",
    "sg:tags":[
        "church"
    ],
    "wof:name":"Newland Church Of Christ Pa Rs",
    "wof:placetype":"venue"
},
  "geometry": {"coordinates":[-76.85522,38.040059],"type":"Point"}
}