{
  "type": "Feature",
  "properties": {
    "addr:full":"233 W Bute St Norfolk VA 23510",
    "addr:housenumber":"233",
    "addr:postcode":"23510",
    "addr:street":"W Bute St",
    "iso:country":"US",
    "sg:address":"233 W Bute St",
    "sg:city":"Norfolk",
    "sg:classifiers":[
        {
            "category":"Professional",
            "subcategory":"Printing & Photocopies",
            "type":"Services"
        }
    ],
    "sg:phone":"+1 757 625 2895",
    "sg:postcode":"23510",
    "sg:province":"VA",
    "sg:tags":[
        "photocopying"
    ],
    "wof:name":"Ridgways Ltd",
    "wof:placetype":"venue"
},
  "geometry": {"coordinates":[-76.29071999999999,36.853],"type":"Point"}
}