{
  "type": "Feature",
  "properties": {
    "iso:country":"US",
    "sg:address":"901 48th St",
    "sg:city":"Newport News",
    "sg:classifiers":[
        {
            "category":"Building & Trades",
            "subcategory":"Plumbing",
            "type":"Services"
        }
    ],
    "sg:phone":"+1 757 366 4389",
    "sg:postcode":"23607",
    "sg:province":"VA",
    "sg:tags":[
        "refrigeration",
        "contractor"
    ],
    "wof:name":"Southern Air Incorporated",
    "wof:placetype":"venue"
},
  "geometry": {"coordinates":[-76.424649,36.998376],"type":"Point"}
}