{
  "type": "Feature",
  "properties": {
    "iso:country":"US",
    "sg:address":"4889 Princess Anne Rd",
    "sg:city":"Virginia Beach",
    "sg:classifiers":[
        {
            "category":"Retail",
            "subcategory":"Funeral Services",
            "type":"Services"
        }
    ],
    "sg:phone":"+1 757 490 2727",
    "sg:postcode":"23462",
    "sg:province":"VA",
    "sg:tags":[
        "home"
    ],
    "wof:name":"Smith and Williams Fnrl Homes",
    "wof:placetype":"venue"
},
  "geometry": {"coordinates":[-76.150949,36.821811],"type":"Point"}
}