{
  "type": "Feature",
  "properties": {
    "addr:full":"1209 Amherst Ave Fredericksburg VA 22405",
    "addr:housenumber":"1209",
    "addr:postcode":"22405",
    "addr:street":"Amherst Ave",
    "iso:country":"US",
    "sg:address":"1209 Amherst Ave",
    "sg:city":"Fredericksburg",
    "sg:classifiers":[
        {
            "category":"Building & Trades",
            "subcategory":"Plumbing",
            "type":"Services"
        }
    ],
    "sg:phone":"+1 540 371 0686",
    "sg:postcode":"22405",
    "sg:province":"VA",
    "sg:tags":[
        "conditioning",
        "air",
        "system",
        "contractor"
    ],
    "wof:name":"Certified Maintenance Company",
    "wof:placetype":"venue"
},
  "geometry": {"coordinates":[-77.430555,38.334005],"type":"Point"}
}