{
  "type": "Feature",
  "properties": {
    "addr:full":"6711 Jefferson St Haymarket VA 20169",
    "addr:housenumber":"6711",
    "addr:postcode":"20169",
    "addr:street":"Jefferson St",
    "iso:country":"US",
    "sg:address":"6711 Jefferson St",
    "sg:city":"Haymarket",
    "sg:classifiers":[
        {
            "category":"Organizations",
            "subcategory":"Non-profit Organization",
            "type":"Services"
        }
    ],
    "sg:phone":"+1 540 788 9547",
    "sg:postcode":"20169",
    "sg:province":"VA",
    "sg:tags":[
        "service/non-profit",
        "community"
    ],
    "sg:website":"www.haymarket313.org",
    "wof:name":"Haymarket Masonic Lodge",
    "wof:placetype":"venue"
},
  "geometry": {"coordinates":[-77.636758,38.811543],"type":"Point"}
}