{
  "type": "Feature",
  "properties": {
    "addr:full":"6170 Charles City Rd Richmond VA 23231",
    "addr:housenumber":"6170",
    "addr:postcode":"23231",
    "addr:street":"Charles City Rd",
    "iso:country":"US",
    "sg:address":"6170 Charles City Rd",
    "sg:city":"Richmond",
    "sg:classifiers":[
        {
            "category":"Autos & Motor Vehicles",
            "subcategory":"Automobile Sales",
            "type":"Retail Goods"
        }
    ],
    "sg:phone":"+1 804 795 7977",
    "sg:postcode":"23231",
    "sg:province":"VA",
    "wof:name":"H & S Auto Sales",
    "wof:placetype":"venue"
},
  "geometry": {"coordinates":[-77.23339,37.445888],"type":"Point"}
}