{
  "type": "Feature",
  "properties": {
    "addr:full":"408 Brickby Rd Norfolk VA 23505",
    "addr:housenumber":"408",
    "addr:postcode":"23505",
    "addr:street":"Brickby Rd",
    "iso:country":"US",
    "sg:address":"408 Brickby Rd",
    "sg:city":"Norfolk",
    "sg:classifiers":[
        {
            "category":"Professional",
            "type":"Services"
        }
    ],
    "sg:phone":"+1 757 333 6388",
    "sg:postcode":"23505",
    "sg:province":"VA",
    "sg:tags":[
        "establishment"
    ],
    "wof:name":"Gray & Gray",
    "wof:placetype":"venue"
},
  "geometry": {"coordinates":[-76.264315,36.907081],"type":"Point"}
}