{
  "type": "Feature",
  "properties": {
    "addr:full":"60 Spencer Penn Rd Spencer VA 24165",
    "addr:housenumber":"60",
    "addr:postcode":"24165",
    "addr:street":"Spencer Penn Rd",
    "iso:country":"US",
    "sg:address":"60 Spencer Penn Rd",
    "sg:city":"Spencer",
    "sg:classifiers":[
        {
            "category":"Wholesale",
            "subcategory":"Farm Supplies",
            "type":"Manufacturing & Wholesale Goods"
        }
    ],
    "sg:phone":"+1 276 957 9919",
    "sg:postcode":"24165",
    "sg:province":"VA",
    "sg:tags":[
        "feed"
    ],
    "wof:name":"Commodity Specialist Co",
    "wof:placetype":"venue"
},
  "geometry": {"coordinates":[-80.008092,36.618968],"type":"Point"}
}