{
  "type": "Feature",
  "properties": {
    "addr:full":"165 Wadsworth Dr Richmond VA 23236",
    "addr:housenumber":"165",
    "addr:postcode":"23236",
    "addr:street":"Wadsworth Dr",
    "iso:country":"US",
    "sg:address":"165 Wadsworth Dr",
    "sg:city":"Richmond",
    "sg:classifiers":[
        {
            "category":"Shopping",
            "subcategory":"Discount & Variety Stores",
            "type":"Retail Goods"
        }
    ],
    "sg:phone":"+1 804 272 3126",
    "sg:postcode":"23236",
    "sg:province":"VA",
    "wof:name":"Dollar Tree",
    "wof:placetype":"venue"
},
  "geometry": {"coordinates":[-77.556061,37.494929],"type":"Point"}
}