{
  "type": "Feature",
  "properties": {
    "addr:full":"224 Applegate Ln Bassett VA 24055",
    "addr:housenumber":"224",
    "addr:postcode":"24055",
    "addr:street":"Applegate Ln",
    "iso:country":"US",
    "sg:address":"224 Applegate Ln",
    "sg:city":"Bassett",
    "sg:classifiers":[
        {
            "category":"Building & Trades",
            "subcategory":"Plumbing",
            "type":"Services"
        }
    ],
    "sg:phone":"+1 276 647 8191",
    "sg:postcode":"24055",
    "sg:province":"VA",
    "sg:tags":[
        "septic"
    ],
    "wof:name":"Walker Brothers Septic Tank",
    "wof:placetype":"venue"
},
  "geometry": {"coordinates":[-79.92665,36.756528],"type":"Point"}
}