{
  "type": "Feature",
  "properties": {
    "addr:full":"3809 Patterson Ave Richmond VA 23221",
    "addr:housenumber":"3809",
    "addr:postcode":"23221",
    "addr:street":"Patterson Ave",
    "iso:country":"US",
    "sg:address":"3809 Patterson Ave",
    "sg:city":"Richmond",
    "sg:classifiers":[
        {
            "category":"Education",
            "subcategory":"School",
            "type":"Public Place"
        }
    ],
    "sg:phone":"+1 804 353 0036",
    "sg:postcode":"23221",
    "sg:province":"VA",
    "wof:name":"Paterson Ave Seventh Day",
    "wof:placetype":"venue"
},
  "geometry": {"coordinates":[-77.487014,37.564714],"type":"Point"}
}