{
  "type": "Feature",
  "properties": {
    "addr:full":"15371 Lee Hwy Bristol VA 24202",
    "addr:housenumber":"15371",
    "addr:postcode":"24202",
    "addr:street":"Lee Hwy",
    "iso:country":"US",
    "sg:address":"15371 Lee Hwy",
    "sg:city":"Bristol",
    "sg:classifiers":[
        {
            "category":"Autos & Motor Vehicles",
            "subcategory":"Automobile Sales",
            "type":"Retail Goods"
        }
    ],
    "sg:phone":"+1 276 669 1020",
    "sg:postcode":"24202",
    "sg:province":"VA",
    "sg:tags":[
        "used"
    ],
    "wof:name":"Just Trucks",
    "wof:placetype":"venue"
},
  "geometry": {"coordinates":[-82.08843299999999,36.651739],"type":"Point"}
}