{
  "type": "Feature",
  "properties": {
    "iso:country":"US",
    "sg:address":"2014 S Loudoun St",
    "sg:city":"Winchester",
    "sg:classifiers":[
        {
            "category":"Autos & Motor Vehicles",
            "subcategory":"Auto Supplies",
            "type":"Retail Goods"
        }
    ],
    "sg:phone":"+1 540 722 6744",
    "sg:postcode":"22601",
    "sg:province":"VA",
    "sg:tags":[
        "automobile",
        "accessory"
    ],
    "sg:website":"www.tricktrucks.com",
    "wof:name":"Trick Trucks Seven Inc",
    "wof:placetype":"venue"
},
  "geometry": {"coordinates":[-78.17184,39.164997],"type":"Point"}
}