{
  "type": "Feature",
  "properties": {
    "iso:country":"US",
    "sg:address":"8100 Mechanicsville Tpke",
    "sg:city":"Mechanicsville",
    "sg:classifiers":[
        {
            "category":"Shopping",
            "type":"Retail Goods"
        }
    ],
    "sg:phone":"+1 804 569 1331",
    "sg:postcode":"23111",
    "sg:province":"VA",
    "sg:tags":[
        "merchandise"
    ],
    "wof:name":"Southern Scents Candleshop",
    "wof:placetype":"venue"
},
  "geometry": {"coordinates":[-77.374588,37.602492],"type":"Point"}
}