{
  "type": "Feature",
  "properties": {
    "addr:full":"3600 Mountain Rd Glen Allen VA 23060",
    "addr:housenumber":"3600",
    "addr:postcode":"23060",
    "addr:street":"Mountain Rd",
    "iso:country":"US",
    "sg:address":"3600 Mountain Rd",
    "sg:city":"Glen Allen",
    "sg:classifiers":[
        {
            "category":"Health Services",
            "subcategory":"Nursing And Care Facility",
            "type":"Services"
        }
    ],
    "sg:phone":"+1 804 672 8725",
    "sg:postcode":"23060",
    "sg:province":"VA",
    "sg:tags":[
        "home",
        "convalescent"
    ],
    "wof:name":"Elizabeth Adam Crump Manor",
    "wof:placetype":"venue"
},
  "geometry": {"coordinates":[-77.52139,37.672507],"type":"Point"}
}