{
  "type": "Feature",
  "properties": {
    "addr:full":"12493 Fox View Way Reston VA 20191",
    "addr:housenumber":"12493",
    "addr:postcode":"20191",
    "addr:street":"Fox View Way",
    "iso:country":"US",
    "sg:address":"12493 Fox View Way",
    "sg:city":"Reston",
    "sg:classifiers":[
        {
            "category":"Professional",
            "subcategory":"Computer Services",
            "type":"Services"
        }
    ],
    "sg:phone":"+1 703 716 7779",
    "sg:postcode":"20191",
    "sg:province":"VA",
    "sg:tags":[
        "related"
    ],
    "wof:name":"American Business Consultants",
    "wof:placetype":"venue"
},
  "geometry": {"coordinates":[-77.375484,38.935901],"type":"Point"}
}