{
  "type": "Feature",
  "properties": {
    "addr:full":"5598 Roanoke Rd Fincastle VA 24090",
    "addr:housenumber":"5598",
    "addr:postcode":"24090",
    "addr:street":"Roanoke Rd",
    "iso:country":"US",
    "sg:address":"5598 Roanoke Rd",
    "sg:city":"Fincastle",
    "sg:classifiers":[
        {
            "category":"Retail",
            "subcategory":"Veterinary Services",
            "type":"Services"
        }
    ],
    "sg:phone":"+1 540 992 2711",
    "sg:postcode":"24090",
    "sg:province":"VA",
    "sg:tags":[
        "hospital",
        "animal"
    ],
    "wof:name":"Botetourt Veterinary Hospital",
    "wof:placetype":"venue"
},
  "geometry": {"coordinates":[-79.88762,37.457157],"type":"Point"}
}