{
  "type": "Feature",
  "properties": {
    "addr:full":"1308 S Mount Vernon Ave Williamsburg VA 23185",
    "addr:housenumber":"1308",
    "addr:postcode":"23185",
    "addr:street":"S Mount Vernon Ave",
    "iso:country":"US",
    "sg:address":"1308 S Mount Vernon Ave",
    "sg:city":"Williamsburg",
    "sg:classifiers":[
        {
            "category":"Health Services",
            "subcategory":"Doctor",
            "type":"Services"
        }
    ],
    "sg:phone":"+1 757 736 0100",
    "sg:postcode":"23185",
    "sg:province":"VA",
    "sg:tags":[
        "physician",
        "surgeon"
    ],
    "wof:name":"Sentara Williamsburg Comm",
    "wof:placetype":"venue"
},
  "geometry": {"coordinates":[-76.723501,37.283712],"type":"Point"}
}