{
  "type": "Feature",
  "properties": {
    "iso:country":"US",
    "sg:address":"6156 N Wilson Blvd",
    "sg:city":"Arlington",
    "sg:classifiers":[
        {
            "category":"Government",
            "subcategory":"Office",
            "type":"Public Place"
        }
    ],
    "sg:phone":"+1 703 237 4890",
    "sg:postcode":"22205",
    "sg:province":"VA",
    "sg:tags":[
        "state",
        "program",
        "health"
    ],
    "wof:name":"Fellowship Health Resources",
    "wof:placetype":"venue"
},
  "geometry": {"coordinates":[-77.14608200000001,38.873203],"type":"Point"}
}