{
  "type": "Feature",
  "properties": {
    "addr:full":"14595 Potomac Mills Rd Woodbridge VA 22192",
    "addr:housenumber":"14595",
    "addr:postcode":"22192",
    "addr:street":"Potomac Mills Rd",
    "iso:country":"US",
    "sg:address":"14595 Potomac Mills Rd",
    "sg:city":"Woodbridge",
    "sg:classifiers":[
        {
            "category":"Restaurant",
            "type":"Food & Drink"
        }
    ],
    "sg:menulink":"http://www.allmenus.com/va/neabsco/256916-sakura/menu/",
    "sg:phone":"+1 703 492 8464",
    "sg:postcode":"22192",
    "sg:province":"VA",
    "sg:tags":[
        "japanese",
        "asian"
    ],
    "wof:name":"Sakura",
    "wof:placetype":"venue"
},
  "geometry": {"coordinates":[-77.29789100000001,38.635407],"type":"Point"}
}