{
  "type": "Feature",
  "properties": {
    "iso:country":"US",
    "sg:address":"2719 Hunter Mill Rd",
    "sg:city":"Oakton",
    "sg:classifiers":[
        {
            "category":"Organizations",
            "subcategory":"Religious Organization",
            "type":"Services"
        }
    ],
    "sg:phone":"+1 703 281 1805",
    "sg:postcode":"22124",
    "sg:province":"VA",
    "sg:tags":[
        "latter-day",
        "churches-church",
        "christ",
        "saint",
        "jesus"
    ],
    "wof:name":"Oakton Virginia Stake",
    "wof:placetype":"venue"
},
  "geometry": {"coordinates":[-77.30444300000001,38.891972],"type":"Point"}
}