{
  "type": "Feature",
  "properties": {
    "iso:country":"US",
    "sg:address":"209 Dillin Dr",
    "sg:city":"Lancaster",
    "sg:classifiers":[
        {
            "category":"Professional",
            "subcategory":"Computer Services",
            "type":"Services"
        }
    ],
    "sg:phone":"+1 804 272 6078",
    "sg:postcode":"22503",
    "sg:province":"VA",
    "sg:tags":[
        "datum"
    ],
    "wof:name":"Csd Inc",
    "wof:placetype":"venue"
},
  "geometry": {"coordinates":[-76.559333,37.727163],"type":"Point"}
}