{
  "type": "Feature",
  "properties": {
    "addr:full":"130 Legrande Ave Charlotte Ct Hse VA 23923",
    "addr:housenumber":"130",
    "addr:postcode":"23923",
    "addr:street":"Legrande Ave Charlotte Ct",
    "iso:country":"US",
    "sg:address":"130 Legrande Ave",
    "sg:city":"Charlotte Ct Hse",
    "sg:classifiers":[
        {
            "category":"Government",
            "subcategory":"Office",
            "type":"Public Place"
        }
    ],
    "sg:phone":"+1 434 542 5301",
    "sg:postcode":"23923",
    "sg:province":"VA",
    "wof:name":"Charlotte County American Red",
    "wof:placetype":"venue"
},
  "geometry": {"coordinates":[-78.637829,37.055597],"type":"Point"}
}