{
  "type": "Feature",
  "properties": {
    "addr:full":"43986 Maiden Creek Ct Ashburn VA 20147",
    "addr:postcode":"43986;20147",
    "addr:street":"Maiden Creek Ct",
    "iso:country":"US",
    "sg:address":"43986 Maiden Creek Ct",
    "sg:city":"Ashburn",
    "sg:classifiers":[
        {
            "category":"Shopping",
            "subcategory":"Musical Instruments",
            "type":"Retail Goods"
        }
    ],
    "sg:phone":"+1 703 726 0406",
    "sg:postcode":"20147",
    "sg:province":"VA",
    "wof:name":"Specialty Guitars & Musical In",
    "wof:placetype":"venue"
},
  "geometry": {"coordinates":[-77.478674,39.040567],"type":"Point"}
}