{
  "type": "Feature",
  "properties": {
    "addr:full":"17440 Wyatts Way Evington VA 24550",
    "addr:postcode":"17440;24550",
    "addr:street":"Wyatts Way",
    "iso:country":"US",
    "sg:address":"17440 Wyatts Way",
    "sg:city":"Evington",
    "sg:classifiers":[
        {
            "category":"Organizations",
            "subcategory":"Religious Organization",
            "type":"Services"
        }
    ],
    "sg:phone":"+1 540 297 4786",
    "sg:postcode":"24550",
    "sg:province":"VA",
    "sg:tags":[
        "church"
    ],
    "wof:name":"Bethlehem Baptist Church",
    "wof:placetype":"venue"
},
  "geometry": {"coordinates":[-79.363106,37.232761],"type":"Point"}
}