{
  "type": "Feature",
  "properties": {
    "iso:country":"US",
    "sg:address":"41465 Red Hill Rd",
    "sg:city":"Leesburg",
    "sg:classifiers":[
        {
            "category":"Retail",
            "subcategory":"Auto Repair",
            "type":"Services"
        }
    ],
    "sg:phone":"+1 703 281 1821",
    "sg:postcode":"20175",
    "sg:province":"VA",
    "sg:tags":[
        "automotive"
    ],
    "wof:name":"Vienna Radiator & AC",
    "wof:placetype":"venue"
},
  "geometry": {"coordinates":[-77.564024,38.992364],"type":"Point"}
}