{
  "type": "Feature",
  "properties": {
    "addr:full":"21 Buford Rd Richmond VA 23235",
    "addr:housenumber":"21",
    "addr:postcode":"23235",
    "addr:street":"Buford Rd",
    "iso:country":"US",
    "sg:address":"21 Buford Rd",
    "sg:city":"Richmond",
    "sg:classifiers":[
        {
            "category":"Organizations",
            "subcategory":"Religious Organization",
            "type":"Services"
        }
    ],
    "sg:phone":"+1 804 864 2850",
    "sg:postcode":"23235",
    "sg:province":"VA",
    "sg:tags":[
        "church"
    ],
    "wof:name":"Kingdom Harvest Intl Church",
    "wof:placetype":"venue"
},
  "geometry": {"coordinates":[-77.545129,37.497614],"type":"Point"}
}