{
  "type": "Feature",
  "properties": {
    "addr:full":"212 Burke's Mill Rd Weyers Cave VA 24467",
    "addr:housenumber":"212",
    "addr:postcode":"24467",
    "addr:street":"Burke'S Mill Rd",
    "iso:country":"US",
    "sg:address":"212 Burke's Mill Rd",
    "sg:city":"Weyers Cave",
    "sg:classifiers":[
        {
            "category":"Shopping",
            "subcategory":"Catalog Store",
            "type":"Retail Goods"
        }
    ],
    "sg:phone":"+1 540 234 9371",
    "sg:postcode":"24467",
    "sg:province":"VA",
    "sg:tags":[
        "fashion",
        "jewelry"
    ],
    "wof:name":"Rosemarys Jewelry",
    "wof:placetype":"venue"
},
  "geometry": {"coordinates":[-78.966095,38.287228],"type":"Point"}
}