{
  "type": "Feature",
  "properties": {
    "iso:country":"US",
    "sg:address":"12327 Field Lark Ct",
    "sg:city":"Fairfax",
    "sg:classifiers":[
        {
            "category":"Shopping",
            "type":"Retail Goods"
        }
    ],
    "sg:phone":"+1 703 352 1159",
    "sg:postcode":"22033",
    "sg:province":"VA",
    "sg:tags":[
        "pet",
        "food",
        "supply"
    ],
    "wof:name":"D J Feathers Aviary",
    "wof:placetype":"venue"
},
  "geometry": {"coordinates":[-77.37242999999999,38.86786],"type":"Point"}
}