{
  "type": "Feature",
  "properties": {
    "iso:country":"US",
    "sg:address":"13591 Midlothian Tpke",
    "sg:city":"Midlothian",
    "sg:classifiers":[
        {
            "category":"Shopping",
            "subcategory":"Used Merchandise",
            "type":"Retail Goods"
        }
    ],
    "sg:phone":"+1 804 897 4913",
    "sg:postcode":"23113",
    "sg:province":"VA",
    "wof:name":"Midlothian Antique Center",
    "wof:placetype":"venue"
},
  "geometry": {"coordinates":[-77.649334,37.50288],"type":"Point"}
}