{
  "type": "Feature",
  "properties": {
    "iso:country":"US",
    "sg:address":"5948 2nd St N",
    "sg:city":"Arlington",
    "sg:classifiers":[
        {
            "category":"Insurance",
            "subcategory":"Insurance Agent",
            "type":"Services"
        }
    ],
    "sg:phone":"+1 703 525 9192",
    "sg:postcode":"22203",
    "sg:province":"VA",
    "wof:name":"O'Brien Insurance",
    "wof:placetype":"venue"
},
  "geometry": {"coordinates":[-77.13506099999999,38.867735],"type":"Point"}
}