{
  "type": "Feature",
  "properties": {
    "addr:full":"9100 Meadowcreek Ln Lorton VA 22079",
    "addr:housenumber":"9100",
    "addr:postcode":"22079",
    "addr:street":"Meadowcreek Ln",
    "iso:country":"US",
    "sg:address":"9100 Meadowcreek Ln",
    "sg:city":"Lorton",
    "sg:classifiers":[
        {
            "category":"Professional",
            "subcategory":"Business Services",
            "type":"Services"
        }
    ],
    "sg:phone":"+1 703 690 0999",
    "sg:postcode":"22079",
    "sg:province":"VA",
    "wof:name":"La Roach & Assoc",
    "wof:placetype":"venue"
},
  "geometry": {"coordinates":[-77.26161399999999,38.712865],"type":"Point"}
}