{
  "type": "Feature",
  "properties": {
    "addr:full":"87 Old Waterloo Rd Boyce VA 22620",
    "addr:housenumber":"87",
    "addr:postcode":"22620",
    "addr:street":"Old Waterloo Rd",
    "iso:country":"US",
    "sg:address":"87 Old Waterloo Rd",
    "sg:city":"Boyce",
    "sg:classifiers":[
        {
            "category":"Building & Trades",
            "subcategory":"Construction",
            "type":"Services"
        }
    ],
    "sg:phone":"+1 540 837 1201",
    "sg:postcode":"22620",
    "sg:province":"VA",
    "sg:tags":[
        "home",
        "improvement"
    ],
    "wof:name":"UNT Inc",
    "wof:placetype":"venue"
},
  "geometry": {"coordinates":[-78.07384,39.086244],"type":"Point"}
}