{
  "type": "Feature",
  "properties": {
    "addr:full":"1139 Stonegate Ct Forest VA 24551",
    "addr:housenumber":"1139",
    "addr:postcode":"24551",
    "addr:street":"Stonegate Ct",
    "iso:country":"US",
    "sg:address":"1139 Stonegate Ct",
    "sg:city":"Forest",
    "sg:classifiers":[
        {
            "category":"Building & Trades",
            "subcategory":"Construction",
            "type":"Services"
        }
    ],
    "sg:phone":"+1 434 525 5145",
    "sg:postcode":"24551",
    "sg:province":"VA",
    "sg:tags":[
        "house"
    ],
    "wof:name":"David Brown Construction Inc",
    "wof:placetype":"venue"
},
  "geometry": {"coordinates":[-79.334785,37.402653],"type":"Point"}
}