{
  "type": "Feature",
  "properties": {
    "iso:country":"US",
    "sg:address":"6740 Wilson Ln",
    "sg:city":"Bethesda",
    "sg:classifiers":[
        {
            "category":"Building & Trades",
            "subcategory":"Construction",
            "type":"Services"
        }
    ],
    "sg:phone":"+1 301 229 6025",
    "sg:postcode":"20817",
    "sg:province":"MD",
    "sg:tags":[
        "contractor"
    ],
    "wof:name":"Williard's Crest",
    "wof:placetype":"venue"
},
  "geometry": {"coordinates":[-77.137356,38.983728],"type":"Point"}
}