{
  "type": "Feature",
  "properties": {
    "addr:full":"300 Lincoln St Hampton VA 23669",
    "addr:housenumber":"300",
    "addr:postcode":"23669",
    "addr:street":"Lincoln St",
    "iso:country":"US",
    "sg:address":"300 Lincoln St",
    "sg:city":"Hampton",
    "sg:classifiers":[
        {
            "category":"Organizations",
            "subcategory":"Religious Organization",
            "type":"Services"
        }
    ],
    "sg:phone":"+1 757 723 6746",
    "sg:postcode":"23669",
    "sg:province":"VA",
    "wof:name":"Gospel Spreading Church",
    "wof:placetype":"venue"
},
  "geometry": {"coordinates":[-76.35277000000001,37.027431],"type":"Point"}
}