{
  "type": "Feature",
  "properties": {
    "addr:full":"4901 Seminary Rd Ste 120 Alexandria VA 22311",
    "addr:housenumber":"4901",
    "addr:postcode":"22311",
    "addr:street":"Seminary Rd Ste 120",
    "iso:country":"US",
    "sg:address":"4901 Seminary Rd Ste 120",
    "sg:city":"Alexandria",
    "sg:classifiers":[
        {
            "category":"Health Services",
            "subcategory":"Dentist",
            "type":"Services"
        }
    ],
    "sg:phone":"+1 703 931 3141",
    "sg:postcode":"22311",
    "sg:province":"VA",
    "wof:name":"Drs Finkelstein & Sklar",
    "wof:placetype":"venue"
},
  "geometry": {"coordinates":[-77.115073,38.832231],"type":"Point"}
}