{
  "type": "Feature",
  "properties": {
    "addr:full":"1518 Kingswood St Richmond VA 23224",
    "addr:housenumber":"1518",
    "addr:postcode":"23224",
    "addr:street":"Kingswood St",
    "iso:country":"US",
    "sg:address":"1518 Kingswood St",
    "sg:city":"Richmond",
    "sg:classifiers":[
        {
            "category":"Building & Trades",
            "subcategory":"Construction",
            "type":"Services"
        }
    ],
    "sg:phone":"+1 804 231 4469",
    "sg:postcode":"23224",
    "sg:province":"VA",
    "sg:tags":[
        "general",
        "contractor"
    ],
    "wof:name":"Dream Wright Construction Inc",
    "wof:placetype":"venue"
},
  "geometry": {"coordinates":[-77.477255,37.492894],"type":"Point"}
}