{
  "type": "Feature",
  "properties": {
    "addr:full":"1525 Rugby Ave Charlottesville VA 22903",
    "addr:housenumber":"1525",
    "addr:postcode":"22903",
    "addr:street":"Rugby Ave",
    "iso:country":"US",
    "sg:address":"1525 Rugby Ave",
    "sg:city":"Charlottesville",
    "sg:classifiers":[
        {
            "category":"Organizations",
            "subcategory":"Religious Organization",
            "type":"Services"
        }
    ],
    "sg:phone":"+1 434 296 4813",
    "sg:postcode":"22903",
    "sg:province":"VA",
    "sg:website":"www.church-of-christ.org",
    "wof:name":"Church of Christ",
    "wof:placetype":"venue"
},
  "geometry": {"coordinates":[-78.485901,38.045502],"type":"Point"}
}