{
  "type": "Feature",
  "properties": {
    "iso:country":"US",
    "sg:address":"1489 Big Spring Dr",
    "sg:city":"Lexington",
    "sg:classifiers":[
        {
            "category":"Building & Trades",
            "subcategory":"Landscaping Services",
            "type":"Services"
        },
        {
            "category":"Wholesale",
            "subcategory":"Construction Materials",
            "type":"Manufacturing & Wholesale Goods"
        },
        {
            "category":"Building & Trades",
            "subcategory":"Construction",
            "type":"Services"
        }
    ],
    "sg:phone":"+1 540 463 2082",
    "sg:postcode":"24450",
    "sg:province":"VA",
    "sg:tags":[
        "control",
        "lawn",
        "excavation",
        "tree",
        "snow",
        "removal",
        "contractor",
        "erosion",
        "landscape"
    ],
    "wof:name":"Jerry's Lawn Care Services",
    "wof:placetype":"venue"
},
  "geometry": {"coordinates":[-79.464258,37.843177],"type":"Point"}
}