{
  "type": "Feature",
  "properties": {
    "iso:country":"US",
    "sg:address":"7419 Tower St",
    "sg:city":"Falls Church",
    "sg:classifiers":[
        {
            "category":"Banks & Credit Unions",
            "subcategory":"Financial Services",
            "type":"Services"
        }
    ],
    "sg:phone":"+1 703 876 0444",
    "sg:postcode":"22046",
    "sg:province":"VA",
    "sg:tags":[
        "investor"
    ],
    "wof:name":"Mariposa Funding LLC",
    "wof:placetype":"venue"
},
  "geometry": {"coordinates":[-77.204617,38.886008],"type":"Point"}
}