{
  "type": "Feature",
  "properties": {
    "iso:country":"US",
    "sg:address":"7904 W Broad St",
    "sg:city":"Richmond",
    "sg:classifiers":[
        {
            "category":"Building & Trades",
            "subcategory":"Plumbing",
            "type":"Services"
        }
    ],
    "sg:phone":"+1 804 763 1444",
    "sg:postcode":"23294",
    "sg:province":"VA",
    "sg:tags":[
        "plumbing",
        "contractor"
    ],
    "wof:name":"GPA Plumbing & Heating",
    "wof:placetype":"venue"
},
  "geometry": {"coordinates":[-77.52845600000001,37.623936],"type":"Point"}
}