{
  "type": "Feature",
  "properties": {
    "addr:full":"10 E Washington St Lexington VA 24450",
    "addr:housenumber":"10",
    "addr:postcode":"24450",
    "addr:street":"E Washington St",
    "iso:country":"US",
    "sg:address":"10 E Washington St",
    "sg:city":"Lexington",
    "sg:classifiers":[
        {
            "category":"Professional",
            "subcategory":"Art Services",
            "type":"Services"
        }
    ],
    "sg:phone":"+1 540 463 6911",
    "sg:postcode":"24450",
    "sg:province":"VA",
    "sg:tags":[
        "commercial",
        "design"
    ],
    "wof:name":"Animania",
    "wof:placetype":"venue"
},
  "geometry": {"coordinates":[-79.44185899999999,37.785057],"type":"Point"}
}