{
  "type": "Feature",
  "properties": {
    "iso:country":"US",
    "sg:address":"457 Rockwell Rd",
    "sg:city":"Hampton",
    "sg:classifiers":[
        {
            "category":"Building & Trades",
            "subcategory":"Construction",
            "type":"Services"
        }
    ],
    "sg:phone":"+1 757 850 5873",
    "sg:postcode":"23669",
    "sg:province":"VA",
    "sg:tags":[
        "general",
        "contractor"
    ],
    "wof:name":"Mc Vay Construction",
    "wof:placetype":"venue"
},
  "geometry": {"coordinates":[-76.33465,37.075095],"type":"Point"}
}