{
  "type": "Feature",
  "properties": {
    "iso:country":"US",
    "sg:address":"Virginia Gateway 13246 Gateway Center Dr",
    "sg:city":"Gainesville",
    "sg:classifiers":[
        {
            "category":"Autos & Motor Vehicles",
            "subcategory":"Fuel & Gas Station",
            "type":"Retail Goods"
        }
    ],
    "sg:phone":"+1 703 754 1180",
    "sg:postcode":"20155",
    "sg:province":"VA",
    "sg:website":"www.citgo.com",
    "wof:name":"Gateway Citgo",
    "wof:placetype":"venue"
},
  "geometry": {"coordinates":[-77.605863,38.796587],"type":"Point"}
}