{
  "type": "Feature",
  "properties": {
    "addr:full":"5900 Borden Grant Trl Raphine VA 24472",
    "addr:housenumber":"5900",
    "addr:postcode":"24472",
    "addr:street":"Borden Grant Trl",
    "iso:country":"US",
    "sg:address":"5900 Borden Grant Trl",
    "sg:city":"Raphine",
    "sg:classifiers":[
        {
            "category":"Building & Trades",
            "subcategory":"Construction",
            "type":"Services"
        }
    ],
    "sg:phone":"+1 540 377 6633",
    "sg:postcode":"24472",
    "sg:province":"VA",
    "sg:tags":[
        "home",
        "builder"
    ],
    "wof:name":"Seed & Harvest",
    "wof:placetype":"venue"
},
  "geometry": {"coordinates":[-79.23514900000001,37.889548],"type":"Point"}
}