{
  "type": "Feature",
  "properties": {
    "addr:full":"2609 Build America Dr Hampton VA 23666",
    "addr:postcode":"2609;23666",
    "addr:street":"America Dr",
    "iso:country":"US",
    "sg:address":"2609 Build America Dr",
    "sg:city":"Hampton",
    "sg:classifiers":[
        {
            "category":"Shopping",
            "subcategory":"Computers & Home Electronics",
            "type":"Retail Goods"
        }
    ],
    "sg:phone":"+1 757 826 5202",
    "sg:postcode":"23666",
    "sg:province":"VA",
    "sg:tags":[
        "trade",
        "merchandise",
        "con"
    ],
    "wof:name":"Sure Sound",
    "wof:placetype":"venue"
},
  "geometry": {"coordinates":[-76.40071399999999,37.041049],"type":"Point"}
}