{
  "type": "Feature",
  "properties": {
    "addr:full":"2617 Potato Creek Rd Mouth Of Wilson VA 24363",
    "addr:housenumber":"2617",
    "addr:postcode":"24363",
    "addr:street":"Potato Creek Rd",
    "iso:country":"US",
    "sg:address":"2617 Potato Creek Rd",
    "sg:city":"Mouth Of Wilson",
    "sg:classifiers":[
        {
            "category":"Manufacturing",
            "subcategory":"Lumber",
            "type":"Manufacturing & Wholesale Goods"
        }
    ],
    "sg:phone":"+1 276 579 7733",
    "sg:postcode":"24363",
    "sg:province":"VA",
    "sg:tags":[
        "tree",
        "christmas"
    ],
    "wof:name":"Carolina Fraser Fir Co",
    "wof:placetype":"venue"
},
  "geometry": {"coordinates":[-81.276203,36.583299],"type":"Point"}
}