{
  "type": "Feature",
  "properties": {
    "addr:full":"103 E Blue Ridge St Stuart VA 24171",
    "addr:housenumber":"103",
    "addr:postcode":"24171",
    "addr:street":"E Blue Ridge St",
    "iso:country":"US",
    "sg:address":"103 E Blue Ridge St",
    "sg:city":"Stuart",
    "sg:classifiers":[
        {
            "category":"Professional",
            "subcategory":"Lawyer & Legal Services",
            "type":"Services"
        }
    ],
    "sg:phone":"+1 276 694 9000",
    "sg:postcode":"24171",
    "sg:province":"VA",
    "sg:tags":[
        "attorney"
    ],
    "wof:name":"Gardner Gardner Barrow",
    "wof:placetype":"venue"
},
  "geometry": {"coordinates":[-80.268451,36.641948],"type":"Point"}
}