{
  "type": "Feature",
  "properties": {
    "iso:country":"US",
    "sg:address":"109 McConville Rd",
    "sg:city":"Lynchburg",
    "sg:classifiers":[
        {
            "category":"Building & Trades",
            "subcategory":"Construction",
            "type":"Services"
        }
    ],
    "sg:phone":"+1 434 316 9724",
    "sg:postcode":"24502",
    "sg:province":"VA",
    "sg:tags":[
        "paving",
        "contractor"
    ],
    "wof:name":"Tri-Gen Paving",
    "wof:placetype":"venue"
},
  "geometry": {"coordinates":[-79.21189099999999,37.39767],"type":"Point"}
}