{
  "type": "Feature",
  "properties": {
    "iso:country":"US",
    "sg:address":"12638 Jefferson Ave",
    "sg:city":"Newport News",
    "sg:classifiers":[
        {
            "category":"Personal",
            "subcategory":"Tanning Parlor",
            "type":"Services"
        },
        {
            "category":"Personal",
            "type":"Services"
        }
    ],
    "sg:phone":"+1 757 872 6868",
    "sg:postcode":"23602",
    "sg:province":"VA",
    "sg:tags":[
        "salon"
    ],
    "wof:name":"All Around Brown Tanning Salon",
    "wof:placetype":"venue"
},
  "geometry": {"coordinates":[-76.514141,37.131118],"type":"Point"}
}