{
  "type": "Feature",
  "properties": {
    "addr:full":"3348 Grandin Rd SW Roanoke VA 24018",
    "addr:housenumber":"3348",
    "addr:postcode":"24018",
    "addr:street":"Grandin Rd Sw",
    "iso:country":"US",
    "sg:address":"3348 Grandin Rd SW",
    "sg:city":"Roanoke",
    "sg:classifiers":[
        {
            "category":"Travel",
            "subcategory":"Hotels & Motels",
            "type":"Entertainment"
        }
    ],
    "sg:phone":"+1 540 989 9599",
    "sg:postcode":"24018",
    "sg:province":"VA",
    "sg:tags":[
        "operation"
    ],
    "wof:name":"Lone Oaks Bed & Breakfast",
    "wof:placetype":"venue"
},
  "geometry": {"coordinates":[-80.00561,37.24931],"type":"Point"}
}