{
  "type": "Feature",
  "properties": {
    "iso:country":"US",
    "sg:address":"145 Kale Ave",
    "sg:city":"Sterling",
    "sg:classifiers":[
        {
            "category":"Professional",
            "subcategory":"Computer Services",
            "type":"Services"
        }
    ],
    "sg:phone":"+1 703 444 4073",
    "sg:postcode":"20164",
    "sg:province":"VA",
    "sg:tags":[
        "related"
    ],
    "wof:name":"Tech-Aide Computer Resources",
    "wof:placetype":"venue"
},
  "geometry": {"coordinates":[-77.37992300000001,39.03642],"type":"Point"}
}