{
  "type": "Feature",
  "properties": {
    "addr:full":"1364 Beverly Rd Mc Lean VA 22101",
    "addr:housenumber":"1364",
    "addr:postcode":"22101",
    "addr:street":"Beverly Rd",
    "iso:country":"US",
    "sg:address":"1364 Beverly Rd",
    "sg:city":"Mc Lean",
    "sg:classifiers":[
        {
            "category":"Professional",
            "subcategory":"Lawyer & Legal Services",
            "type":"Services"
        }
    ],
    "sg:phone":"+1 703 893 9600",
    "sg:postcode":"22101",
    "sg:province":"VA",
    "wof:name":"Earman Susan",
    "wof:placetype":"venue"
},
  "geometry": {"coordinates":[-77.177299,38.938301],"type":"Point"}
}