{
  "type": "Feature",
  "properties": {
    "iso:country":"US",
    "sg:address":"3604 Brambleton Ave",
    "sg:city":"Roanoke",
    "sg:classifiers":[
        {
            "category":"Restaurant",
            "type":"Food & Drink"
        }
    ],
    "sg:phone":"+1 540 725 4112",
    "sg:postcode":"24018",
    "sg:province":"VA",
    "sg:tags":[
        "eating"
    ],
    "wof:name":"Fast Freddys",
    "wof:placetype":"venue"
},
  "geometry": {"coordinates":[-80.00203999999999,37.236727],"type":"Point"}
}