{
  "type": "Feature",
  "properties": {
    "addr:full":"7435 Spring Summit Rd Springfield VA 22150",
    "addr:housenumber":"7435",
    "addr:postcode":"22150",
    "addr:street":"Spring Summit Rd",
    "iso:country":"US",
    "sg:address":"7435 Spring Summit Rd",
    "sg:city":"Springfield",
    "sg:classifiers":[
        {
            "category":"Professional",
            "subcategory":"Management & Consulting",
            "type":"Services"
        }
    ],
    "sg:phone":"+1 703 440 8874",
    "sg:postcode":"22150",
    "sg:province":"VA",
    "sg:tags":[
        "business"
    ],
    "wof:name":"John R Sperling & Associates",
    "wof:placetype":"venue"
},
  "geometry": {"coordinates":[-77.20250900000001,38.770275],"type":"Point"}
}