{
  "type": "Feature",
  "properties": {
    "addr:full":"100 Maple St Blackstone VA 23824",
    "addr:housenumber":"100",
    "addr:postcode":"23824",
    "addr:street":"Maple St",
    "iso:country":"US",
    "sg:address":"100 Maple St",
    "sg:city":"Blackstone",
    "sg:classifiers":[
        {
            "category":"Insurance",
            "subcategory":"Insurance Agent",
            "type":"Services"
        }
    ],
    "sg:phone":"+1 434 292 5783",
    "sg:postcode":"23824",
    "sg:province":"VA",
    "wof:name":"Connellys Financial Service",
    "wof:placetype":"venue"
},
  "geometry": {"coordinates":[-77.997676,37.078437],"type":"Point"}
}