{
  "type": "Feature",
  "properties": {
    "addr:full":"7210 Old Keene Mill Rd Springfield VA 22150",
    "addr:housenumber":"7210",
    "addr:postcode":"22150",
    "addr:street":"Old Keene Mill Rd",
    "iso:country":"US",
    "sg:address":"7210 Old Keene Mill Rd",
    "sg:city":"Springfield",
    "sg:classifiers":[
        {
            "category":"Professional",
            "subcategory":"Management & Consulting",
            "type":"Services"
        }
    ],
    "sg:phone":"+1 571 321 0460",
    "sg:postcode":"22150",
    "sg:province":"VA",
    "sg:tags":[
        "consultant",
        "business"
    ],
    "wof:name":"Dynamic Systems Technology",
    "wof:placetype":"venue"
},
  "geometry": {"coordinates":[-77.192787,38.778109],"type":"Point"}
}