{
  "type": "Feature",
  "properties": {
    "iso:country":"US",
    "sg:address":"1929 Coliseum Dr",
    "sg:city":"Hampton",
    "sg:classifiers":[
        {
            "category":"Banks & Credit Unions",
            "subcategory":"Bank",
            "type":"Services"
        }
    ],
    "sg:phone":"+1 757 838 2862",
    "sg:postcode":"23666",
    "sg:province":"VA",
    "sg:tags":[
        "mortgage"
    ],
    "wof:name":"B F Saul Mortgage Company",
    "wof:placetype":"venue"
},
  "geometry": {"coordinates":[-76.38847199999999,37.041561],"type":"Point"}
}