{
  "type": "Feature",
  "properties": {
    "addr:full":"7468 Zorbas Ln Mechanicsville VA 23111",
    "addr:housenumber":"7468",
    "addr:postcode":"23111",
    "addr:street":"Zorbas Ln",
    "iso:country":"US",
    "sg:address":"7468 Zorbas Ln",
    "sg:city":"Mechanicsville",
    "sg:classifiers":[
        {
            "category":"Retail",
            "subcategory":"Repair Shop",
            "type":"Services"
        }
    ],
    "sg:phone":"+1 804 730 6464",
    "sg:postcode":"23111",
    "sg:province":"VA",
    "sg:tags":[
        "appliance"
    ],
    "wof:name":"Dale Dillon Repair Svc",
    "wof:placetype":"venue"
},
  "geometry": {"coordinates":[-77.368835,37.615745],"type":"Point"}
}