{
  "type": "Feature",
  "properties": {
    "addr:full":"980 Edwards Ferry Rd NE Leesburg VA 20176",
    "addr:housenumber":"980",
    "addr:postcode":"20176",
    "addr:street":"Edwards Ferry Rd Ne",
    "iso:country":"US",
    "sg:address":"980 Edwards Ferry Rd NE",
    "sg:city":"Leesburg",
    "sg:classifiers":[
        {
            "category":"Restaurant",
            "type":"Food & Drink"
        }
    ],
    "sg:menulink":"http://www.allmenus.com/va/leesburg/95321-ihop/menu/",
    "sg:phone":"+1 703 779 7501",
    "sg:postcode":"20176",
    "sg:province":"VA",
    "sg:tags":[
        "sandwich",
        "salad",
        "burger",
        "soup",
        "american",
        "steakhouse",
        "wrap"
    ],
    "wof:name":"IHOP",
    "wof:placetype":"venue"
},
  "geometry": {"coordinates":[-77.538881,39.113697],"type":"Point"}
}