{
  "type": "Feature",
  "properties": {
    "addr:full":"2032 Plank Rd Fredericksburg VA 22401",
    "addr:housenumber":"2032",
    "addr:postcode":"22401",
    "addr:street":"Plank Rd",
    "iso:country":"US",
    "sg:address":"2032 Plank Rd",
    "sg:city":"Fredericksburg",
    "sg:classifiers":[
        {
            "category":"Restaurant",
            "type":"Food & Drink"
        }
    ],
    "sg:phone":"+1 540 899 1907",
    "sg:postcode":"22401",
    "sg:province":"VA",
    "wof:name":"Diamond Of India",
    "wof:placetype":"venue"
},
  "geometry": {"coordinates":[-77.495255,38.295772],"type":"Point"}
}