{
  "type": "Feature",
  "properties": {
    "addr:full":"2613 S Walter Reed Dr Arlington VA 22206",
    "addr:housenumber":"2613",
    "addr:postcode":"22206",
    "addr:street":"S Walter Reed Dr",
    "iso:country":"US",
    "sg:address":"2613 S Walter Reed Dr",
    "sg:city":"Arlington",
    "sg:classifiers":[
        {
            "category":"Professional",
            "subcategory":"Management & Consulting",
            "type":"Services"
        }
    ],
    "sg:phone":"+1 703 379 1717",
    "sg:postcode":"22206",
    "sg:province":"VA",
    "sg:tags":[
        "retail",
        "direct",
        "sales"
    ],
    "wof:name":"R D Avon",
    "wof:placetype":"venue"
},
  "geometry": {"coordinates":[-77.09944,38.844664],"type":"Point"}
}