{
  "type": "Feature",
  "properties": {
    "iso:country":"US",
    "sg:address":"1009 S Main St",
    "sg:city":"Blackstone",
    "sg:classifiers":[
        {
            "category":"Autos & Motor Vehicles",
            "subcategory":"Automobile Sales",
            "type":"Retail Goods"
        }
    ],
    "sg:phone":"+1 434 292 5557",
    "sg:postcode":"23824",
    "sg:province":"VA",
    "sg:tags":[
        "used"
    ],
    "wof:name":"Virginia Automotive Exchange",
    "wof:placetype":"venue"
},
  "geometry": {"coordinates":[-78.003664,37.068268],"type":"Point"}
}