{
  "type": "Feature",
  "properties": {
    "addr:full":"213 N Main St Farmville VA 23901",
    "addr:housenumber":"213",
    "addr:postcode":"23901",
    "addr:street":"N Main St",
    "iso:country":"US",
    "sg:address":"213 N Main St",
    "sg:city":"Farmville",
    "sg:classifiers":[
        {
            "category":"Shopping",
            "subcategory":"Discount & Variety Stores",
            "type":"Retail Goods"
        }
    ],
    "sg:phone":"+1 434 392 6865",
    "sg:postcode":"23901",
    "sg:province":"VA",
    "sg:tags":[
        "merchandise",
        "general"
    ],
    "wof:name":"Goodwill Industries Farmville",
    "wof:placetype":"venue"
},
  "geometry": {"coordinates":[-78.391576,37.303662],"type":"Point"}
}