{
  "type": "Feature",
  "properties": {
    "addr:full":"1425 25th St Newport News VA 23607",
    "addr:housenumber":"1425",
    "addr:postcode":"23607",
    "addr:street":"25Th St",
    "iso:country":"US",
    "sg:address":"1425 25th St",
    "sg:city":"Newport News",
    "sg:classifiers":[
        {
            "category":"Personal",
            "subcategory":"Beauty Salon",
            "type":"Services"
        }
    ],
    "sg:phone":"+1 757 246 9637",
    "sg:postcode":"23607",
    "sg:province":"VA",
    "sg:tags":[
        "shop"
    ],
    "wof:name":"New Hair Styles Beauty Salon",
    "wof:placetype":"venue"
},
  "geometry": {"coordinates":[-76.400477,36.989638],"type":"Point"}
}