{
  "type": "Feature",
  "properties": {
    "addr:full":"3800 Florida Ave Richmond VA 23222",
    "addr:housenumber":"3800",
    "addr:postcode":"23222",
    "addr:street":"Florida Ave",
    "iso:country":"US",
    "sg:address":"3800 Florida Ave",
    "sg:city":"Richmond",
    "sg:classifiers":[
        {
            "category":"Communications",
            "type":"Services"
        }
    ],
    "sg:phone":"+1 804 640 8292",
    "sg:postcode":"23222",
    "sg:province":"VA",
    "sg:tags":[
        "communication"
    ],
    "wof:name":"J T Williams Communication",
    "wof:placetype":"venue"
},
  "geometry": {"coordinates":[-77.417975,37.584329],"type":"Point"}
}