{
  "type": "Feature",
  "properties": {
    "addr:full":"1136 S Main St Galax VA 24333",
    "addr:housenumber":"1136",
    "addr:postcode":"24333",
    "addr:street":"S Main St",
    "iso:country":"US",
    "sg:address":"1136 S Main St",
    "sg:city":"Galax",
    "sg:classifiers":[
        {
            "category":"Autos & Motor Vehicles",
            "subcategory":"Automobile Sales",
            "type":"Retail Goods"
        }
    ],
    "sg:phone":"+1 276 238 8778",
    "sg:postcode":"24333",
    "sg:province":"VA",
    "sg:tags":[
        "car",
        "dealer"
    ],
    "wof:name":"Cox Auto Sales",
    "wof:placetype":"venue"
},
  "geometry": {"coordinates":[-80.91798199999999,36.635933],"type":"Point"}
}