{
  "type": "Feature",
  "properties": {
    "addr:full":"212 W Main St Waynesboro VA 22980",
    "addr:housenumber":"212",
    "addr:postcode":"22980",
    "addr:street":"W Main St",
    "iso:country":"US",
    "sg:address":"212 W Main St",
    "sg:city":"Waynesboro",
    "sg:classifiers":[
        {
            "category":"Retail",
            "subcategory":"Animal Services",
            "type":"Services"
        }
    ],
    "sg:phone":"+1 540 943 7976",
    "sg:postcode":"22980",
    "sg:province":"VA",
    "sg:tags":[
        "pet",
        "grooming",
        "washing"
    ],
    "wof:name":"K 9 Klip'n",
    "wof:placetype":"venue"
},
  "geometry": {"coordinates":[-78.88592800000001,38.068177],"type":"Point"}
}