{
  "type": "Feature",
  "properties": {
    "iso:country":"US",
    "sg:address":"7908 Kincannon Pl",
    "sg:city":"Lorton",
    "sg:classifiers":[
        {
            "category":"Shopping",
            "subcategory":"Used Merchandise",
            "type":"Retail Goods"
        },
        {
            "category":"Home & Garden",
            "subcategory":"Carpets & Floor Coverings",
            "type":"Retail Goods"
        }
    ],
    "sg:phone":"+1 703 550 9192",
    "sg:postcode":"22079",
    "sg:province":"VA",
    "sg:tags":[
        "dealer",
        "rug"
    ],
    "wof:name":"Josef Oriental Rugs Inc",
    "wof:placetype":"venue"
},
  "geometry": {"coordinates":[-77.17636899999999,38.74094],"type":"Point"}
}