{
  "type": "Feature",
  "properties": {
    "addr:full":"7770 Croaker Rd Williamsburg VA 23188",
    "addr:housenumber":"7770",
    "addr:postcode":"23188",
    "addr:street":"Croaker Rd",
    "iso:country":"US",
    "sg:address":"7770 Croaker Rd",
    "sg:city":"Williamsburg",
    "sg:classifiers":[
        {
            "category":"Education",
            "subcategory":"Library",
            "type":"Public Place"
        }
    ],
    "sg:phone":"+1 757 259 7720",
    "sg:postcode":"23188",
    "sg:province":"VA",
    "sg:website":"www.wrl.org",
    "wof:name":"James City County Library",
    "wof:placetype":"venue"
},
  "geometry": {"coordinates":[-76.77250600000001,37.376928],"type":"Point"}
}