{
  "type": "Feature",
  "properties": {
    "addr:full":"2213 Youngs Dr Haymarket VA 20169",
    "addr:housenumber":"2213",
    "addr:postcode":"20169",
    "addr:street":"Youngs Dr",
    "iso:country":"US",
    "sg:address":"2213 Youngs Dr",
    "sg:city":"Haymarket",
    "sg:classifiers":[
        {
            "category":"Real Estate",
            "subcategory":"Real Estate Agent",
            "type":"Services"
        }
    ],
    "sg:phone":"+1 703 754 1638",
    "sg:postcode":"20169",
    "sg:province":"VA",
    "wof:name":"Today S Income Com",
    "wof:placetype":"venue"
},
  "geometry": {"coordinates":[-77.661013,38.910007],"type":"Point"}
}