{
  "type": "Feature",
  "properties": {
    "iso:country":"US",
    "sg:address":"4627 Quarter Charge Dr",
    "sg:city":"Annandale",
    "sg:classifiers":[
        {
            "category":"Education",
            "subcategory":"Special Training",
            "type":"Public Place"
        }
    ],
    "sg:phone":"+1 703 978 4424",
    "sg:postcode":"22003",
    "sg:province":"VA",
    "wof:name":"Music Lessons By A Sharp",
    "wof:placetype":"venue"
},
  "geometry": {"coordinates":[-77.231211,38.822018],"type":"Point"}
}