{
  "type": "Feature",
  "properties": {
    "iso:country":"US",
    "sg:address":"436 Orchard St NW",
    "sg:city":"Vienna",
    "sg:classifiers":[
        {
            "category":"Local Transit",
            "type":"Transportation"
        }
    ],
    "sg:phone":"+1 703 319 9429",
    "sg:postcode":"22180",
    "sg:province":"VA",
    "sg:tags":[
        "passenger"
    ],
    "wof:name":"Astro Limo Company",
    "wof:placetype":"venue"
},
  "geometry": {"coordinates":[-77.277109,38.900239],"type":"Point"}
}