{
  "type": "Feature",
  "properties": {
    "iso:country":"US",
    "sg:address":"50 S Pickett St",
    "sg:city":"Alexandria",
    "sg:classifiers":[
        {
            "category":"Social Services",
            "type":"Services"
        }
    ],
    "sg:phone":"+1 703 823 0801",
    "sg:postcode":"22304",
    "sg:province":"VA",
    "sg:tags":[
        "counselor",
        "marriage",
        "family"
    ],
    "wof:name":"Mary Halas",
    "wof:placetype":"venue"
},
  "geometry": {"coordinates":[-77.12180499999999,38.811734],"type":"Point"}
}