{
  "type": "Feature",
  "properties": {
    "iso:country":"US",
    "sg:address":"404 N Henry St",
    "sg:city":"Williamsburg",
    "sg:classifiers":[
        {
            "category":"Building & Trades",
            "subcategory":"Construction",
            "type":"Services"
        }
    ],
    "sg:phone":"+1 757 220 3900",
    "sg:postcode":"23185",
    "sg:province":"VA",
    "sg:tags":[
        "hanging",
        "contractor"
    ],
    "wof:name":"Quality First Painting",
    "wof:placetype":"venue"
},
  "geometry": {"coordinates":[-76.706097,37.276313],"type":"Point"}
}