{
  "type": "Feature",
  "properties": {
    "addr:full":"211 S College Ave Salem VA 24153",
    "addr:housenumber":"211",
    "addr:postcode":"24153",
    "addr:street":"S College Ave",
    "iso:country":"US",
    "sg:address":"211 S College Ave",
    "sg:city":"Salem",
    "sg:phone":"+1 540 375 0789",
    "sg:postcode":"24153",
    "sg:province":"VA",
    "wof:name":"Salon Capelli",
    "wof:placetype":"venue"
},
  "geometry": {"coordinates":[-80.05703099999999,37.294659],"type":"Point"}
}