{
  "type": "Feature",
  "properties": {
    "addr:full":"315 Campbell Ave SW Roanoke VA 24016",
    "addr:housenumber":"315",
    "addr:postcode":"24016",
    "addr:street":"Campbell Ave Sw",
    "iso:country":"US",
    "sg:address":"315 Campbell Ave SW",
    "sg:city":"Roanoke",
    "sg:classifiers":[
        {
            "category":"Professional",
            "subcategory":"Lawyer & Legal Services",
            "type":"Services"
        }
    ],
    "sg:phone":"+1 540 342 4545",
    "sg:postcode":"24016",
    "sg:province":"VA",
    "sg:tags":[
        "attorney"
    ],
    "wof:name":"Leon P Ferrance",
    "wof:placetype":"venue"
},
  "geometry": {"coordinates":[-79.948263,37.271474],"type":"Point"}
}