{
  "type": "Feature",
  "properties": {
    "addr:full":"6501 29th St N Arlington VA 22213",
    "addr:housenumber":"6501",
    "addr:postcode":"22213",
    "addr:street":"29Th St N",
    "iso:country":"US",
    "sg:address":"6501 29th St N",
    "sg:city":"Arlington",
    "sg:classifiers":[
        {
            "category":"Education",
            "subcategory":"Music School",
            "type":"Public Place"
        }
    ],
    "sg:phone":"+1 703 534 4801",
    "sg:postcode":"22213",
    "sg:province":"VA",
    "sg:tags":[
        "instrument",
        "teacher",
        "musical"
    ],
    "sg:website":"www.actionguitar.com",
    "wof:name":"Action Music Ltd",
    "wof:placetype":"venue"
},
  "geometry": {"coordinates":[-77.156998,38.898899],"type":"Point"}
}