{
  "type": "Feature",
  "properties": {
    "addr:full":"6700 Telegraph Rd Alexandria VA 22310",
    "addr:housenumber":"6700",
    "addr:postcode":"22310",
    "addr:street":"Telegraph Rd",
    "iso:country":"US",
    "sg:address":"6700 Telegraph Rd",
    "sg:city":"Alexandria",
    "sg:classifiers":[
        {
            "category":"Sports & Exercise",
            "subcategory":"Golf",
            "type":"Entertainment"
        }
    ],
    "sg:phone":"+1 703 971 6170",
    "sg:postcode":"22310",
    "sg:province":"VA",
    "sg:tags":[
        "course"
    ],
    "wof:name":"Greendale Golf Course",
    "wof:placetype":"venue"
},
  "geometry": {"coordinates":[-77.11559200000001,38.771743],"type":"Point"}
}