{
  "type": "Feature",
  "properties": {
    "addr:full":"4902 Gilmour Rd Sandston VA 23150",
    "addr:housenumber":"4902",
    "addr:postcode":"23150",
    "addr:street":"Gilmour Rd",
    "iso:country":"US",
    "sg:address":"4902 Gilmour Rd",
    "sg:city":"Sandston",
    "sg:classifiers":[
        {
            "category":"Organizations",
            "subcategory":"Community Association",
            "type":"Services"
        }
    ],
    "sg:phone":"+1 804 222 3040",
    "sg:postcode":"23150",
    "sg:province":"VA",
    "wof:name":"Gray Home Owners Svc",
    "wof:placetype":"venue"
},
  "geometry": {"coordinates":[-77.335933,37.520395],"type":"Point"}
}