{
  "type": "Feature",
  "properties": {
    "addr:full":"626 Brussels Ave Clifton Forge VA 24422",
    "addr:housenumber":"626",
    "addr:postcode":"24422",
    "addr:street":"Brussels Ave",
    "iso:country":"US",
    "sg:address":"626 Brussels Ave",
    "sg:city":"Clifton Forge",
    "sg:classifiers":[
        {
            "category":"Building & Trades",
            "subcategory":"Landscaping Services",
            "type":"Services"
        }
    ],
    "sg:phone":"+1 540 862 0469",
    "sg:postcode":"24422",
    "sg:province":"VA",
    "sg:tags":[
        "shrubbery",
        "tree"
    ],
    "wof:name":"Robert L Ryder",
    "wof:placetype":"venue"
},
  "geometry": {"coordinates":[-79.828881,37.820507],"type":"Point"}
}