{
  "type": "Feature",
  "properties": {
    "iso:country":"US",
    "sg:address":"4401 Double Bridges Rd",
    "sg:city":"Meherrin",
    "sg:classifiers":[
        {
            "category":"Home & Garden",
            "subcategory":"Building Materials",
            "type":"Retail Goods"
        }
    ],
    "sg:phone":"+1 434 696 2333",
    "sg:postcode":"23954",
    "sg:province":"VA",
    "sg:tags":[
        "windows"
    ],
    "wof:name":"Austin Windows & Siding",
    "wof:placetype":"venue"
},
  "geometry": {"coordinates":[-78.342015,37.020555],"type":"Point"}
}