{
  "type": "Feature",
  "properties": {
    "addr:full":"10085 Poplar Hall Ct Mechanicsville VA 23116",
    "addr:housenumber":"10085",
    "addr:postcode":"23116",
    "addr:street":"Poplar Hall Ct",
    "iso:country":"US",
    "sg:address":"10085 Poplar Hall Ct",
    "sg:city":"Mechanicsville",
    "sg:classifiers":[
        {
            "category":"Professional",
            "type":"Services"
        }
    ],
    "sg:phone":"+1 804 550 3040",
    "sg:postcode":"23116",
    "sg:province":"VA",
    "wof:name":"Mark Limited LLC",
    "wof:placetype":"venue"
},
  "geometry": {"coordinates":[-77.416246,37.677107],"type":"Point"}
}