{
  "type": "Feature",
  "properties": {
    "addr:full":"3345 N Franklin St Christiansburg VA 24073",
    "addr:housenumber":"3345",
    "addr:postcode":"24073",
    "addr:street":"N Franklin St",
    "iso:country":"US",
    "sg:address":"3345 N Franklin St",
    "sg:city":"Christiansburg",
    "sg:classifiers":[
        {
            "category":"Food & Beverages",
            "subcategory":"Groceries & Convenience Stores",
            "type":"Retail Goods"
        }
    ],
    "sg:phone":"+1 540 382 6518",
    "sg:postcode":"24073",
    "sg:province":"VA",
    "wof:name":"Food Time 92",
    "wof:placetype":"venue"
},
  "geometry": {"coordinates":[-80.41851800000001,37.175541],"type":"Point"}
}