{
  "type": "Feature",
  "properties": {
    "addr:full":"1761 Mountainside Dr Blacksburg VA 24060",
    "addr:housenumber":"1761",
    "addr:postcode":"24060",
    "addr:street":"Mountainside Dr",
    "iso:country":"US",
    "sg:address":"1761 Mountainside Dr",
    "sg:city":"Blacksburg",
    "sg:classifiers":[
        {
            "category":"Professional",
            "subcategory":"Management & Consulting",
            "type":"Services"
        },
        {
            "category":"Banks & Credit Unions",
            "subcategory":"Financial Services",
            "type":"Services"
        }
    ],
    "sg:phone":"+1 540 953 1713",
    "sg:postcode":"24060",
    "sg:province":"VA",
    "sg:tags":[
        "consultant",
        "financing",
        "planning"
    ],
    "wof:name":"Financial Link Consulting",
    "wof:placetype":"venue"
},
  "geometry": {"coordinates":[-80.349701,37.21582],"type":"Point"}
}