{
  "type": "Feature",
  "properties": {
    "addr:full":"151 N Loudoun St Winchester VA 22601",
    "addr:housenumber":"151",
    "addr:postcode":"22601",
    "addr:street":"N Loudoun St",
    "iso:country":"US",
    "sg:address":"151 N Loudoun St",
    "sg:city":"Winchester",
    "sg:classifiers":[
        {
            "category":"Shopping",
            "subcategory":"Gifts & Souvenirs",
            "type":"Retail Goods"
        }
    ],
    "sg:phone":"+1 540 667 2046",
    "sg:postcode":"22601",
    "sg:province":"VA",
    "sg:tags":[
        "basket",
        "parcel"
    ],
    "wof:name":"Confetti Personal Touch Gift",
    "wof:placetype":"venue"
},
  "geometry": {"coordinates":[-78.16564,39.184142],"type":"Point"}
}