{
  "type": "Feature",
  "properties": {
    "iso:country":"US",
    "sg:address":"1016 Delaware St",
    "sg:city":"Salem",
    "sg:classifiers":[
        {
            "category":"Wholesale",
            "subcategory":"Machinery & Supplies",
            "type":"Manufacturing & Wholesale Goods"
        }
    ],
    "sg:phone":"+1 540 389 7296",
    "sg:postcode":"24153",
    "sg:province":"VA",
    "sg:tags":[
        "engine"
    ],
    "sg:website":"www.blueridgediesel.com",
    "wof:name":"Blue Ridge Diesel Injection",
    "wof:placetype":"venue"
},
  "geometry": {"coordinates":[-80.048603,37.281471],"type":"Point"}
}