{
  "type": "Feature",
  "properties": {
    "iso:country":"US",
    "sg:address":"316 Commerce St",
    "sg:city":"Alexandria",
    "sg:classifiers":[
        {
            "category":"Social Services",
            "type":"Services"
        }
    ],
    "sg:phone":"+1 703 684 3543",
    "sg:postcode":"22314",
    "sg:province":"VA",
    "sg:tags":[
        "worker"
    ],
    "wof:name":"Marsha Campbell",
    "wof:placetype":"venue"
},
  "geometry": {"coordinates":[-77.05670000000001,38.804284],"type":"Point"}
}