{
  "type": "Feature",
  "properties": {
    "iso:country":"US",
    "sg:address":"730 E Little Creek Rd",
    "sg:city":"Norfolk",
    "sg:classifiers":[
        {
            "category":"Restaurant",
            "type":"Food & Drink"
        }
    ],
    "sg:menulink":"http://www.allmenus.com/va/norfolk/166133-arbys/menu/",
    "sg:phone":"+1 757 583 3436",
    "sg:postcode":"23518",
    "sg:province":"VA",
    "sg:tags":[
        "burger",
        "american"
    ],
    "wof:name":"Arby's",
    "wof:placetype":"venue"
},
  "geometry": {"coordinates":[-76.25247899999999,36.915844],"type":"Point"}
}