{
  "type": "Feature",
  "properties": {
    "addr:full":"1217 E Eva Blvd Chesapeake VA 23320",
    "addr:housenumber":"1217",
    "addr:postcode":"23320",
    "addr:street":"E Eva Blvd",
    "iso:country":"US",
    "sg:address":"1217 E Eva Blvd",
    "sg:city":"Chesapeake",
    "sg:classifiers":[
        {
            "category":"Personal",
            "type":"Services"
        }
    ],
    "sg:phone":"+1 757 545 5381",
    "sg:postcode":"23320",
    "sg:province":"VA",
    "wof:name":"Sparrow Sons",
    "wof:placetype":"venue"
},
  "geometry": {"coordinates":[-76.274278,36.76794],"type":"Point"}
}