{
  "type": "Feature",
  "properties": {
    "iso:country":"US",
    "sg:address":"5406 High St W",
    "sg:city":"Portsmouth",
    "sg:classifiers":[
        {
            "category":"Real Estate",
            "subcategory":"Real Estate Agent",
            "type":"Services"
        }
    ],
    "sg:phone":"+1 757 484 6551",
    "sg:postcode":"23703",
    "sg:province":"VA",
    "wof:name":"Leon Coppedge Realty Ltd",
    "wof:placetype":"venue"
},
  "geometry": {"coordinates":[-76.387258,36.857839],"type":"Point"}
}