{
  "type": "Feature",
  "properties": {
    "iso:country":"US",
    "sg:address":"5877 Monticello Rd",
    "sg:city":"Alexandria",
    "sg:classifiers":[
        {
            "category":"Real Estate",
            "subcategory":"Real Estate Operator",
            "type":"Services"
        }
    ],
    "sg:phone":"+1 703 960 8058",
    "sg:postcode":"22303",
    "sg:province":"VA",
    "sg:tags":[
        "building",
        "apartment"
    ],
    "wof:name":"Jefferson Garden Apartments",
    "wof:placetype":"venue"
},
  "geometry": {"coordinates":[-77.078276,38.789934],"type":"Point"}
}