{
  "type": "Feature",
  "properties": {
    "iso:country":"US",
    "sg:address":"335 Centerville Tpke N",
    "sg:city":"Chesapeake",
    "sg:classifiers":[
        {
            "category":"Restaurant",
            "type":"Food & Drink"
        }
    ],
    "sg:phone":"+1 757 482 9614",
    "sg:postcode":"23320",
    "sg:province":"VA",
    "wof:name":"Angies Family Restaurant",
    "wof:placetype":"venue"
},
  "geometry": {"coordinates":[-76.187217,36.730445],"type":"Point"}
}