{
  "type": "Feature",
  "properties": {
    "iso:country":"US",
    "sg:address":"6402 Battle Rock Dr",
    "sg:city":"Clifton",
    "sg:classifiers":[
        {
            "category":"Professional",
            "subcategory":"Accounting & Tax Preparation",
            "type":"Services"
        }
    ],
    "sg:phone":"+1 703 830 0276",
    "sg:postcode":"20124",
    "sg:province":"VA",
    "wof:name":"Frank R Kistner Cpa Pl",
    "wof:placetype":"venue"
},
  "geometry": {"coordinates":[-77.41736,38.815612],"type":"Point"}
}