{
  "type": "Feature",
  "properties": {
    "addr:full":"1943 Elbow Rd Chesapeake VA 23320",
    "addr:housenumber":"1943",
    "addr:postcode":"23320",
    "addr:street":"Elbow Rd",
    "iso:country":"US",
    "sg:address":"1943 Elbow Rd",
    "sg:city":"Chesapeake",
    "sg:classifiers":[
        {
            "category":"Building & Trades",
            "subcategory":"Landscaping Services",
            "type":"Services"
        }
    ],
    "sg:phone":"+1 757 479 0080",
    "sg:postcode":"23320",
    "sg:province":"VA",
    "sg:website":"www.landscape4u.com",
    "wof:name":"Colonial Tree Care",
    "wof:placetype":"venue"
},
  "geometry": {"coordinates":[-76.170817,36.738884],"type":"Point"}
}