{
  "type": "Feature",
  "properties": {
    "addr:full":"1847 Turkey Knob Rd Fries VA 24330",
    "addr:housenumber":"1847",
    "addr:postcode":"24330",
    "addr:street":"Turkey Knob Rd",
    "iso:country":"US",
    "sg:address":"1847 Turkey Knob Rd",
    "sg:city":"Fries",
    "sg:classifiers":[
        {
            "category":"Organizations",
            "subcategory":"Religious Organization",
            "type":"Services"
        }
    ],
    "sg:phone":"+1 276 744 7729",
    "sg:postcode":"24330",
    "sg:province":"VA",
    "sg:tags":[
        "church"
    ],
    "wof:name":"Turkey Knob Church",
    "wof:placetype":"venue"
},
  "geometry": {"coordinates":[-81.03909400000001,36.691958],"type":"Point"}
}