{
  "type": "Feature",
  "properties": {
    "addr:full":"937 Mackall Ave Mc Lean VA 22101",
    "addr:housenumber":"937",
    "addr:postcode":"22101",
    "addr:street":"Mackall Ave Mc Lean",
    "iso:country":"US",
    "sg:address":"937 Mackall Ave",
    "sg:city":"Mc Lean",
    "sg:classifiers":[
        {
            "category":"Health Services",
            "subcategory":"Doctor",
            "type":"Services"
        }
    ],
    "sg:phone":"+1 703 893 8429",
    "sg:postcode":"22101",
    "sg:province":"VA",
    "wof:name":"Depalma R G MD & M T",
    "wof:placetype":"venue"
},
  "geometry": {"coordinates":[-77.1735,38.950901],"type":"Point"}
}