{
  "type": "Feature",
  "properties": {
    "addr:full":"24 Mary Ann Dr Hampton VA 23666",
    "addr:housenumber":"24",
    "addr:postcode":"23666",
    "addr:street":"Mary Ann Dr",
    "iso:country":"US",
    "sg:address":"24 Mary Ann Dr",
    "sg:city":"Hampton",
    "sg:classifiers":[
        {
            "category":"Organizations",
            "subcategory":"Religious Organization",
            "type":"Services"
        }
    ],
    "sg:phone":"+1 757 827 9016",
    "sg:postcode":"23666",
    "sg:province":"VA",
    "sg:tags":[
        "baptist",
        "church"
    ],
    "wof:name":"Peninsula Mssnary Bptst Church",
    "wof:placetype":"venue"
},
  "geometry": {"coordinates":[-76.448611,37.044895],"type":"Point"}
}