{
  "type": "Feature",
  "properties": {
    "iso:country":"US",
    "sg:address":"14000 Thunderbolt Pl",
    "sg:city":"Chantilly",
    "sg:classifiers":[
        {
            "category":"Building & Trades",
            "subcategory":"Construction",
            "type":"Services"
        }
    ],
    "sg:phone":"+1 703 968 8800",
    "sg:postcode":"20151",
    "sg:province":"VA",
    "sg:tags":[
        "designer",
        "dealer",
        "pool",
        "swimming"
    ],
    "sg:website":"www.nvpools.com",
    "wof:name":"N V Pool & Patio",
    "wof:placetype":"venue"
},
  "geometry": {"coordinates":[-77.433548,38.898967],"type":"Point"}
}