{
  "type": "Feature",
  "properties": {
    "addr:full":"14200 Sullyfield Cir Chantilly VA 20151",
    "addr:housenumber":"14200",
    "addr:postcode":"20151",
    "addr:street":"Sullyfield Cir",
    "iso:country":"US",
    "sg:address":"14200 Sullyfield Cir",
    "sg:city":"Chantilly",
    "sg:classifiers":[
        {
            "category":"Wholesale",
            "subcategory":"Chemicals & Plastics",
            "type":"Manufacturing & Wholesale Goods"
        }
    ],
    "sg:phone":"+1 703 222 5547",
    "sg:postcode":"20151",
    "sg:province":"VA",
    "sg:tags":[
        "toy",
        "particleboard"
    ],
    "wof:name":"Ys Corporation",
    "wof:placetype":"venue"
},
  "geometry": {"coordinates":[-77.437044,38.894508],"type":"Point"}
}