{
  "type": "Feature",
  "properties": {
    "addr:full":"4909 Rock Spring Rd Arlington VA 22207",
    "addr:housenumber":"4909",
    "addr:postcode":"22207",
    "addr:street":"Rock Spring Rd",
    "iso:country":"US",
    "sg:address":"4909 Rock Spring Rd",
    "sg:city":"Arlington",
    "sg:classifiers":[
        {
            "category":"Professional",
            "subcategory":"Lawyer & Legal Services",
            "type":"Services"
        }
    ],
    "sg:phone":"+1 703 532 7718",
    "sg:postcode":"22207",
    "sg:province":"VA",
    "wof:name":"Brown Gary W",
    "wof:placetype":"venue"
},
  "geometry": {"coordinates":[-77.13536499999999,38.907557],"type":"Point"}
}