{
  "type": "Feature",
  "properties": {
    "addr:full":"6000 Edsall Rd Alexandria VA 22304",
    "addr:housenumber":"6000",
    "addr:postcode":"22304",
    "addr:street":"Edsall Rd",
    "iso:country":"US",
    "sg:address":"6000 Edsall Rd",
    "sg:city":"Alexandria",
    "sg:classifiers":[
        {
            "category":"Banks & Credit Unions",
            "subcategory":"Investment Brokerage",
            "type":"Services"
        }
    ],
    "sg:phone":"+1 703 823 5501",
    "sg:postcode":"22304",
    "sg:province":"VA",
    "sg:tags":[
        "security"
    ],
    "wof:name":"Mulberry Mortgage",
    "wof:placetype":"venue"
},
  "geometry": {"coordinates":[-77.13502099999999,38.807481],"type":"Point"}
}