{
  "type": "Feature",
  "properties": {
    "iso:country":"US",
    "sg:address":"822 Mattmoore Pl",
    "sg:city":"Newport News",
    "sg:classifiers":[
        {
            "category":"Real Estate",
            "subcategory":"Real Estate Agent",
            "type":"Services"
        }
    ],
    "sg:phone":"+1 757 599 0843",
    "sg:postcode":"23601",
    "sg:province":"VA",
    "wof:name":"Carter Weddy Real Estate Inc",
    "wof:placetype":"venue"
},
  "geometry": {"coordinates":[-76.452776,37.062892],"type":"Point"}
}