{
  "type": "Feature",
  "properties": {
    "iso:country":"US",
    "sg:address":"5457 Greenwich Rd",
    "sg:city":"Virginia Beach",
    "sg:classifiers":[
        {
            "category":"Professional",
            "subcategory":"Advertising",
            "type":"Services"
        }
    ],
    "sg:phone":"+1 757 222 5460",
    "sg:postcode":"23462",
    "sg:province":"VA",
    "sg:tags":[
        "mail"
    ],
    "sg:website":"www.pilotdirect.com",
    "wof:name":"Pilot Direct",
    "wof:placetype":"venue"
},
  "geometry": {"coordinates":[-76.17227200000001,36.842415],"type":"Point"}
}