{
  "type": "Feature",
  "properties": {
    "addr:full":"4504 Colley Ave Norfolk VA 23508",
    "addr:housenumber":"4504",
    "addr:postcode":"23508",
    "addr:street":"Colley Ave",
    "iso:country":"US",
    "sg:address":"4504 Colley Ave",
    "sg:city":"Norfolk",
    "sg:classifiers":[
        {
            "category":"Professional",
            "subcategory":"Lawyer & Legal Services",
            "type":"Services"
        }
    ],
    "sg:phone":"+1 757 489 2812",
    "sg:postcode":"23508",
    "sg:province":"VA",
    "wof:name":"Thomas B Reed",
    "wof:placetype":"venue"
},
  "geometry": {"coordinates":[-76.29490199999999,36.885732],"type":"Point"}
}