{
  "type": "Feature",
  "properties": {
    "iso:country":"US",
    "sg:address":"625 Duxbury Rd",
    "sg:city":"Salem",
    "sg:classifiers":[
        {
            "category":"Bars & Pubs",
            "type":"Food & Drink"
        }
    ],
    "sg:phone":"+1 540 389 3347",
    "sg:postcode":"24153",
    "sg:province":"VA",
    "sg:tags":[
        "drinking"
    ],
    "wof:name":"Silver Spur",
    "wof:placetype":"venue"
},
  "geometry": {"coordinates":[-80.11264,37.293042],"type":"Point"}
}