{
  "type": "Feature",
  "properties": {
    "iso:country":"US",
    "sg:address":"8474 Tyco Rd",
    "sg:city":"Vienna",
    "sg:classifiers":[
        {
            "category":"Professional",
            "subcategory":"Printing & Photocopies",
            "type":"Services"
        }
    ],
    "sg:phone":"+1 703 917 0057",
    "sg:postcode":"22182",
    "sg:province":"VA",
    "sg:tags":[
        "photocopying"
    ],
    "wof:name":"First Copy",
    "wof:placetype":"venue"
},
  "geometry": {"coordinates":[-77.23753600000001,38.931486],"type":"Point"}
}