{
  "type": "Feature",
  "properties": {
    "addr:full":"1064 Elden St Herndon VA 20170",
    "addr:housenumber":"1064",
    "addr:postcode":"20170",
    "addr:street":"Elden St",
    "iso:country":"US",
    "sg:address":"1064 Elden St",
    "sg:city":"Herndon",
    "sg:classifiers":[
        {
            "category":"Real Estate",
            "subcategory":"Real Estate Agent",
            "type":"Services"
        }
    ],
    "sg:phone":"+1 703 742 6900",
    "sg:postcode":"20170",
    "sg:province":"VA",
    "wof:name":"ERA",
    "wof:placetype":"venue"
},
  "geometry": {"coordinates":[-77.39591299999999,38.967456],"type":"Point"}
}