{
  "type": "Feature",
  "properties": {
    "iso:country":"US",
    "sg:address":"13 Estate Dr",
    "sg:city":"Hampton",
    "sg:classifiers":[
        {
            "category":"Professional",
            "type":"Services"
        }
    ],
    "sg:phone":"+1 757 826 8482",
    "sg:postcode":"23666",
    "sg:province":"VA",
    "sg:tags":[
        "establishment"
    ],
    "wof:name":"Carter & Carter",
    "wof:placetype":"venue"
},
  "geometry": {"coordinates":[-76.444951,37.049718],"type":"Point"}
}