{
  "type": "Feature",
  "properties": {
    "addr:full":"5400 Byrdhill Rd Richmond VA 23228",
    "addr:postcode":"5400;23228",
    "addr:street":"Byrdhill Rd",
    "iso:country":"US",
    "sg:address":"5400 Byrdhill Rd",
    "sg:city":"Richmond",
    "sg:classifiers":[
        {
            "category":"Wholesale",
            "subcategory":"Durable Goods & Equipment",
            "type":"Manufacturing & Wholesale Goods"
        }
    ],
    "sg:phone":"+1 804 261 3700",
    "sg:postcode":"23228",
    "sg:province":"VA",
    "sg:tags":[
        "laboratory",
        "supply"
    ],
    "wof:name":"Virginia Lab Supply Corp",
    "wof:placetype":"venue"
},
  "geometry": {"coordinates":[-77.48741099999999,37.603631],"type":"Point"}
}