{
  "type": "Feature",
  "properties": {
    "addr:full":"4615 Kingsrow Dr Glen Allen VA 23060",
    "addr:postcode":"4615;23060",
    "addr:street":"Kingsrow Dr",
    "iso:country":"US",
    "sg:address":"4615 Kingsrow Dr",
    "sg:city":"Glen Allen",
    "sg:classifiers":[
        {
            "category":"Shopping",
            "subcategory":"Computers & Home Electronics",
            "type":"Retail Goods"
        }
    ],
    "sg:phone":"+1 804 273 1778",
    "sg:postcode":"23060",
    "sg:province":"VA",
    "wof:name":"Capital Communications",
    "wof:placetype":"venue"
},
  "geometry": {"coordinates":[-77.53879999999999,37.651675],"type":"Point"}
}