{
  "type": "Feature",
  "properties": {
    "addr:full":"5419 Hickory Ridge Rd Spotsylvania VA 22551",
    "addr:housenumber":"5419",
    "addr:postcode":"22551",
    "addr:street":"Hickory Ridge Rd",
    "iso:country":"US",
    "sg:address":"5419 Hickory Ridge Rd",
    "sg:city":"Spotsylvania",
    "sg:classifiers":[
        {
            "category":"Building & Trades",
            "subcategory":"Construction",
            "type":"Services"
        }
    ],
    "sg:phone":"+1 540 582 3134",
    "sg:postcode":"22551",
    "sg:province":"VA",
    "sg:tags":[
        "contractor"
    ],
    "wof:name":"Ni River Utilities",
    "wof:placetype":"venue"
},
  "geometry": {"coordinates":[-77.520049,38.168696],"type":"Point"}
}