{
  "type": "Feature",
  "properties": {
    "addr:full":"500 Gate City Hwy Bristol VA 24201",
    "addr:housenumber":"500",
    "addr:postcode":"24201",
    "addr:street":"Gate City Hwy",
    "iso:country":"US",
    "sg:address":"500 Gate City Hwy",
    "sg:city":"Bristol",
    "sg:classifiers":[
        {
            "category":"Food & Beverages",
            "subcategory":"Bakery",
            "type":"Retail Goods"
        },
        {
            "category":"Bakery",
            "type":"Food & Drink"
        }
    ],
    "sg:menulink":"http://www.allmenus.com/va/bristol/234457-pretzel-twister/menu/",
    "sg:phone":"+1 276 466 1081",
    "sg:postcode":"24201",
    "sg:province":"VA",
    "sg:tags":[
        "new",
        "american",
        "bakery",
        "pastry"
    ],
    "wof:name":"Pretzel Twister",
    "wof:placetype":"venue"
},
  "geometry": {"coordinates":[-82.215874,36.599117],"type":"Point"}
}