{
  "type": "Feature",
  "properties": {
    "iso:country":"US",
    "sg:address":"151 Madison Cir",
    "sg:city":"Madison Heights",
    "sg:classifiers":[
        {
            "category":"Manufacturing",
            "subcategory":"Apparel",
            "type":"Manufacturing & Wholesale Goods"
        }
    ],
    "sg:phone":"+1 434 846 5142",
    "sg:postcode":"24572",
    "sg:province":"VA",
    "sg:website":"www.scrubsusa.com",
    "wof:name":"RNE Corp",
    "wof:placetype":"venue"
},
  "geometry": {"coordinates":[-79.133728,37.423314],"type":"Point"}
}