{
  "type": "Feature",
  "properties": {
    "iso:country":"US",
    "sg:address":"1 Harrison St SE",
    "sg:city":"Leesburg",
    "sg:classifiers":[
        {
            "category":"Government",
            "subcategory":"Office",
            "type":"Public Place"
        }
    ],
    "sg:phone":"+1 703 777 0204",
    "sg:postcode":"20175",
    "sg:province":"VA",
    "sg:tags":[
        "county"
    ],
    "sg:website":"www.loudoun.gov",
    "wof:name":"Loudoun Board Of Supervisors",
    "wof:placetype":"venue"
},
  "geometry": {"coordinates":[-77.561458,39.113957],"type":"Point"}
}