{
  "type": "Feature",
  "properties": {
    "iso:country":"US",
    "sg:address":"1301 Gaskins Rd",
    "sg:city":"Richmond",
    "sg:classifiers":[
        {
            "category":"Utilities",
            "subcategory":"Refuse",
            "type":"Services"
        }
    ],
    "sg:phone":"+1 804 741 9030",
    "sg:postcode":"23238",
    "sg:province":"VA",
    "sg:tags":[
        "system"
    ],
    "wof:name":"Gittings Refuse",
    "wof:placetype":"venue"
},
  "geometry": {"coordinates":[-77.590833,37.605415],"type":"Point"}
}