{
  "type": "Feature",
  "properties": {
    "iso:country":"US",
    "sg:address":"317 Hospital Dr",
    "sg:city":"Martinsville",
    "sg:classifiers":[
        {
            "category":"Wholesale",
            "subcategory":"Medical Equipment & Supplies",
            "type":"Manufacturing & Wholesale Goods"
        },
        {
            "category":"Building & Trades",
            "subcategory":"Equipment Rental",
            "type":"Services"
        }
    ],
    "sg:phone":"+1 276 638 3353",
    "sg:postcode":"24112",
    "sg:province":"VA",
    "sg:tags":[
        "home",
        "hospital",
        "health",
        "rent",
        "care"
    ],
    "wof:name":"Apria Healthcare Inc",
    "wof:placetype":"venue"
},
  "geometry": {"coordinates":[-79.864862,36.696689],"type":"Point"}
}