{
  "type": "Feature",
  "properties": {
    "addr:full":"6800 Atmore Dr Richmond VA 23225",
    "addr:postcode":"6800;23225",
    "addr:street":"Atmore Dr",
    "iso:country":"US",
    "sg:address":"6800 Atmore Dr",
    "sg:city":"Richmond",
    "sg:classifiers":[
        {
            "category":"Insurance",
            "subcategory":"Insurance Agent",
            "type":"Services"
        }
    ],
    "sg:phone":"+1 804 745 4416",
    "sg:postcode":"23225",
    "sg:province":"VA",
    "wof:name":"Jack W Dempsey Insurance Agcy",
    "wof:placetype":"venue"
},
  "geometry": {"coordinates":[-77.523425,37.503758],"type":"Point"}
}