{
  "type": "Feature",
  "properties": {
    "iso:country":"US",
    "sg:address":"100 5th St",
    "sg:city":"Bristol",
    "sg:classifiers":[
        {
            "category":"Wholesale",
            "subcategory":"Drugs",
            "type":"Manufacturing & Wholesale Goods"
        }
    ],
    "sg:phone":"+1 423 989 9192",
    "sg:postcode":"37620",
    "sg:province":"VA",
    "sg:tags":[
        "mfg"
    ],
    "wof:name":"Lotus Biochemical Corporation",
    "wof:placetype":"venue"
},
  "geometry": {"coordinates":[-82.17047599999999,36.577281],"type":"Point"}
}