{
  "type": "Feature",
  "properties": {
    "addr:full":"147 Junction Dr Ashland VA 23005",
    "addr:housenumber":"147",
    "addr:postcode":"23005",
    "addr:street":"Junction Dr",
    "iso:country":"US",
    "sg:address":"147 Junction Dr",
    "sg:city":"Ashland",
    "sg:classifiers":[
        {
            "category":"Shopping",
            "subcategory":"Hobbies, Toys, & Games",
            "type":"Retail Goods"
        }
    ],
    "sg:phone":"+1 804 798 2678",
    "sg:postcode":"23005",
    "sg:province":"VA",
    "wof:name":"Lanshark Pcs & Gaming",
    "wof:placetype":"venue"
},
  "geometry": {"coordinates":[-77.471445,37.754923],"type":"Point"}
}