{
  "type": "Feature",
  "properties": {
    "iso:country":"US",
    "sg:address":"390 Salters Creek Rd",
    "sg:city":"Hampton",
    "sg:classifiers":[
        {
            "category":"Recreation",
            "type":"Entertainment"
        }
    ],
    "sg:phone":"+1 757 723 4966",
    "sg:postcode":"23661",
    "sg:province":"VA",
    "sg:website":"www.gymnastics-inc.com",
    "wof:name":"Gymnastics Inc",
    "wof:placetype":"venue"
},
  "geometry": {"coordinates":[-76.378244,37.020734],"type":"Point"}
}