{
  "type": "Feature",
  "properties": {
    "addr:full":"66 Canal Center Plz Ste 555 Alexandria VA 22314",
    "addr:housenumber":"66",
    "addr:postcode":"22314",
    "addr:street":"Canal Center Plz Ste 555",
    "iso:country":"US",
    "sg:address":"66 Canal Center Plz Ste 555",
    "sg:city":"Alexandria",
    "sg:classifiers":[
        {
            "category":"Professional",
            "subcategory":"Engineering",
            "type":"Services"
        },
        {
            "category":"Professional",
            "subcategory":"Business Services",
            "type":"Services"
        }
    ],
    "sg:phone":"+1 703 535 8517",
    "sg:postcode":"22314",
    "sg:province":"VA",
    "sg:tags":[
        "consultant",
        "consulting",
        "coach",
        "engineer"
    ],
    "wof:name":"Target Point Consulting",
    "wof:placetype":"venue"
},
  "geometry": {"coordinates":[-77.039047,38.814513],"type":"Point"}
}