{
  "type": "Feature",
  "properties": {
    "addr:full":"1514 Harborough Rd Richmond VA 23238",
    "addr:housenumber":"1514",
    "addr:postcode":"23238",
    "addr:street":"Harborough Rd",
    "iso:country":"US",
    "sg:address":"1514 Harborough Rd",
    "sg:city":"Richmond",
    "sg:classifiers":[
        {
            "category":"Professional",
            "subcategory":"Management & Consulting",
            "type":"Services"
        }
    ],
    "sg:phone":"+1 804 740 0740",
    "sg:postcode":"23238",
    "sg:province":"VA",
    "sg:tags":[
        "business"
    ],
    "wof:name":"Boice Consulting",
    "wof:placetype":"venue"
},
  "geometry": {"coordinates":[-77.611071,37.601467],"type":"Point"}
}