{
  "type": "Feature",
  "properties": {
    "addr:full":"1546 W Morgan Ave Pennington Gap VA 24277",
    "addr:housenumber":"1546",
    "addr:postcode":"24277",
    "addr:street":"W Morgan Ave",
    "iso:country":"US",
    "sg:address":"1546 W Morgan Ave",
    "sg:city":"Pennington Gap",
    "sg:classifiers":[
        {
            "category":"Shopping",
            "subcategory":"Florist",
            "type":"Retail Goods"
        }
    ],
    "sg:phone":"+1 276 546 4236",
    "sg:postcode":"24277",
    "sg:province":"VA",
    "wof:name":"Four Seasons Floral & Gift",
    "wof:placetype":"venue"
},
  "geometry": {"coordinates":[-83.044809,36.750777],"type":"Point"}
}