{
  "type": "Feature",
  "properties": {
    "addr:full":"390 W Spring St Wytheville VA 24382",
    "addr:housenumber":"390",
    "addr:postcode":"24382",
    "addr:street":"W Spring St",
    "iso:country":"US",
    "sg:address":"390 W Spring St",
    "sg:city":"Wytheville",
    "sg:classifiers":[
        {
            "category":"Professional",
            "subcategory":"Employment Agencies",
            "type":"Services"
        }
    ],
    "sg:phone":"+1 276 223 1688",
    "sg:postcode":"24382",
    "sg:province":"VA",
    "sg:tags":[
        "temporary",
        "help"
    ],
    "wof:name":"Bright Personnel and Bus Cons",
    "wof:placetype":"venue"
},
  "geometry": {"coordinates":[-81.085161,36.947236],"type":"Point"}
}