{
  "type": "Feature",
  "properties": {
    "addr:full":"1701 Allied St Charlottesville VA 22903",
    "addr:housenumber":"1701",
    "addr:postcode":"22903",
    "addr:street":"Allied St",
    "iso:country":"US",
    "sg:address":"1701 Allied St",
    "sg:city":"Charlottesville",
    "sg:classifiers":[
        {
            "category":"Insurance",
            "subcategory":"Health Insurance",
            "type":"Services"
        }
    ],
    "sg:phone":"+1 434 296 7048",
    "sg:postcode":"22903",
    "sg:province":"VA",
    "sg:tags":[
        "market"
    ],
    "wof:name":"Animal Connection Llc",
    "wof:placetype":"venue"
},
  "geometry": {"coordinates":[-78.47930100000001,38.0411],"type":"Point"}
}