{
  "type": "Feature",
  "properties": {
    "iso:country":"US",
    "sg:address":"177 Maxwelton Rd",
    "sg:city":"Charlottesville",
    "sg:classifiers":[
        {
            "category":"Farming",
            "subcategory":"Farm",
            "type":"Manufacturing & Wholesale Goods"
        }
    ],
    "sg:phone":"+1 434 296 4417",
    "sg:postcode":"22903",
    "sg:province":"VA",
    "sg:tags":[
        "crop",
        "general"
    ],
    "wof:name":"Maxwelton Farm and Timber Corp",
    "wof:placetype":"venue"
},
  "geometry": {"coordinates":[-78.57625400000001,38.042626],"type":"Point"}
}