{
  "type": "Feature",
  "properties": {
    "iso:country":"US",
    "sg:address":"400 Market St",
    "sg:city":"Suffolk",
    "sg:classifiers":[
        {
            "category":"Government",
            "subcategory":"Fire Station",
            "type":"Public Place"
        }
    ],
    "sg:phone":"+1 757 925 5745",
    "sg:postcode":"23434",
    "sg:province":"VA",
    "sg:tags":[
        "department"
    ],
    "wof:name":"Suffolk Fire Marshall",
    "wof:placetype":"venue"
},
  "geometry": {"coordinates":[-76.586721,36.730995],"type":"Point"}
}