{
  "type": "Feature",
  "properties": {
    "addr:full":"6609 Greenleaf St Springfield VA 22150",
    "addr:housenumber":"6609",
    "addr:postcode":"22150",
    "addr:street":"Greenleaf St",
    "iso:country":"US",
    "sg:address":"6609 Greenleaf St",
    "sg:city":"Springfield",
    "sg:classifiers":[
        {
            "category":"Building & Trades",
            "subcategory":"Construction",
            "type":"Services"
        }
    ],
    "sg:phone":"+1 703 313 7068",
    "sg:postcode":"22150",
    "sg:province":"VA",
    "sg:tags":[
        "home",
        "improvement"
    ],
    "wof:name":"Home Doctor",
    "wof:placetype":"venue"
},
  "geometry": {"coordinates":[-77.16539400000001,38.776031],"type":"Point"}
}