{
  "type": "Feature",
  "properties": {
    "iso:country":"US",
    "sg:address":"1130 George Washington Hwy N",
    "sg:city":"Chesapeake",
    "sg:classifiers":[
        {
            "category":"Autos & Motor Vehicles",
            "subcategory":"Auto Supplies",
            "type":"Retail Goods"
        }
    ],
    "sg:phone":"+1 757 487 1966",
    "sg:postcode":"23323",
    "sg:province":"VA",
    "sg:tags":[
        "automobile",
        "parts"
    ],
    "wof:name":"Autozone",
    "wof:placetype":"venue"
},
  "geometry": {"coordinates":[-76.33467400000001,36.78279],"type":"Point"}
}