{
  "type": "Feature",
  "properties": {
    "iso:country":"US",
    "sg:address":"1148 Corporate Park Dr",
    "sg:city":"Forest",
    "sg:classifiers":[
        {
            "category":"Organizations",
            "subcategory":"Non-profit Organization",
            "type":"Services"
        }
    ],
    "sg:phone":"+1 434 525 6829",
    "sg:postcode":"24551",
    "sg:province":"VA",
    "sg:website":"www.worldhelp.net",
    "wof:name":"World Help",
    "wof:placetype":"venue"
},
  "geometry": {"coordinates":[-79.29843099999999,37.371575],"type":"Point"}
}