{
  "type": "Feature",
  "properties": {
    "iso:country":"US",
    "sg:address":"5037 Shore Dr",
    "sg:city":"Virginia Beach",
    "sg:classifiers":[
        {
            "category":"Retail",
            "subcategory":"Auto Rental",
            "type":"Services"
        }
    ],
    "sg:phone":"+1 757 460 5951",
    "sg:postcode":"23455",
    "sg:province":"VA",
    "sg:tags":[
        "renting",
        "truck",
        "leasing"
    ],
    "wof:name":"U-Haul Co",
    "wof:placetype":"venue"
},
  "geometry": {"coordinates":[-76.147081,36.905848],"type":"Point"}
}