{
  "type": "Feature",
  "properties": {
    "addr:full":"52 George Ct Hampton VA 23663",
    "addr:housenumber":"52",
    "addr:postcode":"23663",
    "addr:street":"George Ct",
    "iso:country":"US",
    "sg:address":"52 George Ct",
    "sg:city":"Hampton",
    "sg:classifiers":[
        {
            "category":"Building & Trades",
            "subcategory":"Landscaping Services",
            "type":"Services"
        }
    ],
    "sg:phone":"+1 757 848 4379",
    "sg:postcode":"23663",
    "sg:province":"VA",
    "sg:tags":[
        "designer",
        "landscape"
    ],
    "wof:name":"SOS",
    "wof:placetype":"venue"
},
  "geometry": {"coordinates":[-76.320125,37.040783],"type":"Point"}
}