{
  "type": "Feature",
  "properties": {
    "addr:full":"2925 W Strathmore Rd Richmond VA 23237",
    "addr:housenumber":"2925",
    "addr:postcode":"23237",
    "addr:street":"W Strathmore Rd",
    "iso:country":"US",
    "sg:address":"2925 W Strathmore Rd",
    "sg:city":"Richmond",
    "sg:classifiers":[
        {
            "category":"Social Services",
            "subcategory":"Child Care",
            "type":"Services"
        }
    ],
    "sg:phone":"+1 804 271 9202",
    "sg:postcode":"23237",
    "sg:province":"VA",
    "sg:tags":[
        "day"
    ],
    "wof:name":"Delores Child Care",
    "wof:placetype":"venue"
},
  "geometry": {"coordinates":[-77.447682,37.43125],"type":"Point"}
}