{
  "type": "Feature",
  "properties": {
    "iso:country":"US",
    "sg:address":"1908 Armand Ct",
    "sg:city":"Falls Church",
    "sg:classifiers":[
        {
            "category":"Professional",
            "subcategory":"Computer Services",
            "type":"Services"
        }
    ],
    "sg:phone":"+1 703 534 6014",
    "sg:postcode":"22043",
    "sg:province":"VA",
    "sg:tags":[
        "related"
    ],
    "wof:name":"Pusat Data Co",
    "wof:placetype":"venue"
},
  "geometry": {"coordinates":[-77.176044,38.910732],"type":"Point"}
}