{
  "type": "Feature",
  "properties": {
    "addr:full":"10359 Fitzpatrick Ln Oakton VA 22124",
    "addr:housenumber":"10359",
    "addr:postcode":"22124",
    "addr:street":"Fitzpatrick Ln",
    "iso:country":"US",
    "sg:address":"10359 Fitzpatrick Ln",
    "sg:city":"Oakton",
    "sg:classifiers":[
        {
            "category":"Building & Trades",
            "subcategory":"Construction",
            "type":"Services"
        }
    ],
    "sg:phone":"+1 703 255 1393",
    "sg:postcode":"22124",
    "sg:province":"VA",
    "sg:tags":[
        "residential",
        "commercial",
        "general",
        "bu",
        "home",
        "contractor"
    ],
    "wof:name":"Bocam",
    "wof:placetype":"venue"
},
  "geometry": {"coordinates":[-77.303342,38.878145],"type":"Point"}
}