{
  "type": "Feature",
  "properties": {
    "iso:country":"US",
    "sg:address":"5312 Richmond Henrico Tpke",
    "sg:city":"Richmond",
    "sg:classifiers":[
        {
            "category":"Freight",
            "type":"Transportation"
        }
    ],
    "sg:phone":"+1 804 329 4005",
    "sg:postcode":"23227",
    "sg:province":"VA",
    "sg:tags":[
        "mover",
        "general"
    ],
    "wof:name":"United Stor All of Richmond",
    "wof:placetype":"venue"
},
  "geometry": {"coordinates":[-77.41482000000001,37.607133],"type":"Point"}
}