{
  "type": "Feature",
  "properties": {
    "iso:country":"US",
    "sg:address":"6531 Little River Tpke",
    "sg:city":"Alexandria",
    "sg:classifiers":[
        {
            "category":"Food & Beverages",
            "subcategory":"Groceries & Convenience Stores",
            "type":"Retail Goods"
        }
    ],
    "sg:phone":"+1 703 813 8188",
    "sg:postcode":"22312",
    "sg:province":"VA",
    "wof:name":"MI Tierra Mercado Latino",
    "wof:placetype":"venue"
},
  "geometry": {"coordinates":[-77.15971399999999,38.821691],"type":"Point"}
}