{
  "type": "Feature",
  "properties": {
    "iso:country":"US",
    "sg:address":"2413 Pomona Rd",
    "sg:city":"Colonial Beach",
    "sg:classifiers":[
        {
            "category":"Building & Trades",
            "subcategory":"Landscaping Services",
            "type":"Services"
        }
    ],
    "sg:phone":"+1 804 224 1893",
    "sg:postcode":"22443",
    "sg:province":"VA",
    "wof:name":"Tate Lawn Service",
    "wof:placetype":"venue"
},
  "geometry": {"coordinates":[-77.040334,38.223859],"type":"Point"}
}