{
  "type": "Feature",
  "properties": {
    "iso:country":"US",
    "sg:address":"4238 N Wilson Blvd",
    "sg:city":"Arlington",
    "sg:classifiers":[
        {
            "category":"Utilities",
            "subcategory":"Mobile Phone",
            "type":"Services"
        }
    ],
    "sg:phone":"+1 703 465 8300",
    "sg:postcode":"22203",
    "sg:province":"VA",
    "sg:tags":[
        "communication",
        "radiotelephone"
    ],
    "wof:name":"Intouch Wireless Of Boston",
    "wof:placetype":"venue"
},
  "geometry": {"coordinates":[-77.110657,38.879816],"type":"Point"}
}