{
  "type": "Feature",
  "properties": {
    "addr:full":"39 Winter Berry Rd Galax VA 24333",
    "addr:housenumber":"39",
    "addr:postcode":"24333",
    "addr:street":"Winter Berry Rd",
    "iso:country":"US",
    "sg:address":"39 Winter Berry Rd",
    "sg:city":"Galax",
    "sg:classifiers":[
        {
            "category":"Real Estate",
            "subcategory":"Real Estate Agent",
            "type":"Services"
        }
    ],
    "sg:phone":"+1 276 238 2327",
    "sg:postcode":"24333",
    "sg:province":"VA",
    "sg:website":"www.choicehomehotline.com",
    "wof:name":"Choice Real Estate Svc Inc",
    "wof:placetype":"venue"
},
  "geometry": {"coordinates":[-80.868728,36.697588],"type":"Point"}
}