{
  "type": "Feature",
  "properties": {
    "iso:country":"US",
    "sg:address":"1784 Clovermeadow Dr",
    "sg:city":"Vienna",
    "sg:classifiers":[
        {
            "category":"Professional",
            "subcategory":"Art Services",
            "type":"Services"
        }
    ],
    "sg:phone":"+1 703 757 3326",
    "sg:postcode":"22182",
    "sg:province":"VA",
    "sg:tags":[
        "motion",
        "commercial",
        "prod",
        "design"
    ],
    "wof:name":"Dialogue Films LLC",
    "wof:placetype":"venue"
},
  "geometry": {"coordinates":[-77.311291,38.945464],"type":"Point"}
}