{
  "type": "Feature",
  "properties": {
    "iso:country":"US",
    "sg:address":"610 Thimble Shoals Blvd",
    "sg:city":"Newport News",
    "sg:classifiers":[
        {
            "category":"Shopping",
            "type":"Retail Goods"
        },
        {
            "category":"Health Services",
            "subcategory":"Health Practitioner",
            "type":"Services"
        }
    ],
    "sg:phone":"+1 757 873 8794",
    "sg:postcode":"23606",
    "sg:province":"VA",
    "sg:tags":[
        "audiologists",
        "merchandise"
    ],
    "wof:name":"Maico Audiological Services",
    "wof:placetype":"venue"
},
  "geometry": {"coordinates":[-76.483062,37.082987],"type":"Point"}
}