{
  "type": "Feature",
  "properties": {
    "iso:country":"US",
    "sg:address":"2901 Chamberlayne Ave",
    "sg:city":"Richmond",
    "sg:classifiers":[
        {
            "category":"Retail",
            "subcategory":"Auto Repair",
            "type":"Services"
        }
    ],
    "sg:phone":"+1 804 329 5228",
    "sg:postcode":"23222",
    "sg:province":"VA",
    "sg:tags":[
        "general"
    ],
    "wof:name":"Roachs Auto Service Inc",
    "wof:placetype":"venue"
},
  "geometry": {"coordinates":[-77.445105,37.572078],"type":"Point"}
}