{
  "type": "Feature",
  "properties": {
    "addr:full":"125 Executive Dr Danville VA 24541",
    "addr:housenumber":"125",
    "addr:postcode":"24541",
    "addr:street":"Executive Dr",
    "iso:country":"US",
    "sg:address":"125 Executive Dr",
    "sg:city":"Danville",
    "sg:classifiers":[
        {
            "category":"Health Services",
            "subcategory":"Doctor",
            "type":"Services"
        }
    ],
    "sg:phone":"+1 434 793 0044",
    "sg:postcode":"24541",
    "sg:province":"VA",
    "sg:tags":[
        "physician",
        "surgeon"
    ],
    "wof:name":"Danville Hematology Inc",
    "wof:placetype":"venue"
},
  "geometry": {"coordinates":[-79.43118699999999,36.593299],"type":"Point"}
}