{
  "type": "Feature",
  "properties": {
    "addr:full":"612 Jerusalem Rd Boydton VA 23917",
    "addr:housenumber":"612",
    "addr:postcode":"23917",
    "addr:street":"Jerusalem Rd",
    "iso:country":"US",
    "sg:address":"612 Jerusalem Rd",
    "sg:city":"Boydton",
    "sg:classifiers":[
        {
            "category":"Organizations",
            "subcategory":"Religious Organization",
            "type":"Services"
        }
    ],
    "sg:phone":"+1 434 689 2314",
    "sg:postcode":"23917",
    "sg:province":"VA",
    "sg:tags":[
        "church"
    ],
    "wof:name":"Jerusalem United Church",
    "wof:placetype":"venue"
},
  "geometry": {"coordinates":[-78.264017,36.580466],"type":"Point"}
}