{
  "type": "Feature",
  "properties": {
    "addr:full":"13605 Hampstead Ct Chantilly VA 20151",
    "addr:housenumber":"13605",
    "addr:postcode":"20151",
    "addr:street":"Hampstead Ct",
    "iso:country":"US",
    "sg:address":"13605 Hampstead Ct",
    "sg:city":"Chantilly",
    "sg:classifiers":[
        {
            "category":"Professional",
            "type":"Services"
        }
    ],
    "sg:phone":"+1 703 707 8416",
    "sg:postcode":"20151",
    "sg:province":"VA",
    "wof:name":"Mako Swimming LLC",
    "wof:placetype":"venue"
},
  "geometry": {"coordinates":[-77.416871,38.899445],"type":"Point"}
}