{
  "type": "Feature",
  "properties": {
    "addr:full":"239 W Washington St Suffolk VA 23434",
    "addr:housenumber":"239",
    "addr:postcode":"23434",
    "addr:street":"W Washington St",
    "iso:country":"US",
    "sg:address":"239 W Washington St",
    "sg:city":"Suffolk",
    "sg:classifiers":[
        {
            "category":"Restaurant",
            "type":"Food & Drink"
        }
    ],
    "sg:menulink":"http://www.allmenus.com/va/suffolk/284634-sushi-aka/menu/",
    "sg:phone":"+1 757 934 2235",
    "sg:postcode":"23434",
    "sg:province":"VA",
    "sg:tags":[
        "japanese",
        "asian"
    ],
    "wof:name":"Sushi Aka",
    "wof:placetype":"venue"
},
  "geometry": {"coordinates":[-76.585684,36.728924],"type":"Point"}
}