{
  "type": "Feature",
  "properties": {
    "addr:full":"5637 Princess Anne Rd Virginia Beach VA 23462",
    "addr:housenumber":"5637",
    "addr:postcode":"23462",
    "addr:street":"Princess Anne Rd",
    "iso:country":"US",
    "sg:address":"5637 Princess Anne Rd",
    "sg:city":"Virginia Beach",
    "sg:classifiers":[
        {
            "category":"Manufacturing",
            "subcategory":"Printing",
            "type":"Manufacturing & Wholesale Goods"
        }
    ],
    "sg:phone":"+1 757 490 9679",
    "sg:postcode":"23462",
    "sg:province":"VA",
    "sg:tags":[
        "commercial",
        "letterpress",
        "offset"
    ],
    "wof:name":"Bryan Printing Co",
    "wof:placetype":"venue"
},
  "geometry": {"coordinates":[-76.18125499999999,36.839044],"type":"Point"}
}