{
  "type": "Feature",
  "properties": {
    "iso:country":"US",
    "sg:address":"5202 Aviation Dr NW",
    "sg:city":"Roanoke",
    "sg:classifiers":[
        {
            "category":"Airline",
            "type":"Transportation"
        }
    ],
    "sg:phone":"+1 540 265 3434",
    "sg:postcode":"24012",
    "sg:province":"VA",
    "sg:tags":[
        "scheduled",
        "air"
    ],
    "wof:name":"US Airways",
    "wof:placetype":"venue"
},
  "geometry": {"coordinates":[-79.968059,37.317701],"type":"Point"}
}