{
  "type": "Feature",
  "properties": {
    "addr:full":"5801 Jefferson Davis Hwy Richmond VA 23234",
    "addr:housenumber":"5801",
    "addr:postcode":"23234",
    "addr:street":"Jefferson Davis Hwy",
    "iso:country":"US",
    "sg:address":"5801 Jefferson Davis Hwy",
    "sg:city":"Richmond",
    "sg:classifiers":[
        {
            "category":"Autos & Motor Vehicles",
            "subcategory":"Fuel & Gas Station",
            "type":"Retail Goods"
        }
    ],
    "sg:phone":"+1 804 743 0360",
    "sg:postcode":"23234",
    "sg:province":"VA",
    "sg:tags":[
        "oil"
    ],
    "wof:name":"Texaco-Star Enterprise",
    "wof:placetype":"venue"
},
  "geometry": {"coordinates":[-77.44067099999999,37.445621],"type":"Point"}
}