{
  "type": "Feature",
  "properties": {
    "iso:country":"US",
    "sg:address":"5912 Talmadge Dr",
    "sg:city":"Woodbridge",
    "sg:classifiers":[
        {
            "category":"Personal",
            "type":"Services"
        }
    ],
    "sg:phone":"+1 703 946 1356",
    "sg:postcode":"22193",
    "sg:province":"VA",
    "wof:name":"Aka Crew",
    "wof:placetype":"venue"
},
  "geometry": {"coordinates":[-77.383982,38.673014],"type":"Point"}
}