{
  "type": "Feature",
  "properties": {
    "iso:country":"US",
    "sg:address":"3319 W Cary St",
    "sg:city":"Richmond",
    "sg:classifiers":[
        {
            "category":"Shopping",
            "subcategory":"Florist",
            "type":"Retail Goods"
        }
    ],
    "sg:phone":"+1 804 358 4880",
    "sg:postcode":"23221",
    "sg:province":"VA",
    "wof:name":"Garden Lily Inc",
    "wof:placetype":"venue"
},
  "geometry": {"coordinates":[-77.483259,37.553961],"type":"Point"}
}