{
  "type": "Feature",
  "properties": {
    "addr:full":"1342 Armory Dr Franklin VA 23851",
    "addr:housenumber":"1342",
    "addr:postcode":"23851",
    "addr:street":"Armory Dr",
    "iso:country":"US",
    "sg:address":"1342 Armory Dr",
    "sg:city":"Franklin",
    "sg:classifiers":[
        {
            "category":"Restaurant",
            "type":"Food & Drink"
        }
    ],
    "sg:menulink":"http://www.allmenus.com/va/franklin/147642-subway/menu/",
    "sg:phone":"+1 757 562 2415",
    "sg:postcode":"23851",
    "sg:province":"VA",
    "sg:tags":[
        "american",
        "sandwich"
    ],
    "wof:name":"Subway",
    "wof:placetype":"venue"
},
  "geometry": {"coordinates":[-76.94797800000001,36.669555],"type":"Point"}
}