{
  "type": "Feature",
  "properties": {
    "addr:full":"11108 Fox Meadow Dr Richmond VA 23233",
    "addr:housenumber":"11108",
    "addr:postcode":"23233",
    "addr:street":"Fox Meadow Dr",
    "iso:country":"US",
    "sg:address":"11108 Fox Meadow Dr",
    "sg:city":"Richmond",
    "sg:classifiers":[
        {
            "category":"Shopping",
            "type":"Retail Goods"
        }
    ],
    "sg:phone":"+1 804 360 1033",
    "sg:postcode":"23233",
    "sg:province":"VA",
    "sg:tags":[
        "merchandise"
    ],
    "wof:name":"Road Publishing Co",
    "wof:placetype":"venue"
},
  "geometry": {"coordinates":[-77.630826,37.627548],"type":"Point"}
}