{
  "type": "Feature",
  "properties": {
    "addr:full":"414 Algonquin Rd Hampton VA 23661",
    "addr:housenumber":"414",
    "addr:postcode":"23661",
    "addr:street":"Algonquin Rd",
    "iso:country":"US",
    "sg:address":"414 Algonquin Rd",
    "sg:city":"Hampton",
    "sg:classifiers":[
        {
            "category":"Health Services",
            "subcategory":"Nursing And Care Facility",
            "type":"Services"
        }
    ],
    "sg:phone":"+1 757 722 9881",
    "sg:postcode":"23661",
    "sg:province":"VA",
    "sg:tags":[
        "home",
        "convalescent"
    ],
    "wof:name":"Riverside Convalescent Ctr",
    "wof:placetype":"venue"
},
  "geometry": {"coordinates":[-76.36558599999999,37.012443],"type":"Point"}
}