{
  "type": "Feature",
  "properties": {
    "iso:country":"US",
    "sg:address":"1439 Center St",
    "sg:city":"Mc Lean",
    "sg:classifiers":[
        {
            "category":"Personal",
            "subcategory":"Beauty Salon",
            "type":"Services"
        }
    ],
    "sg:phone":"+1 703 356 1756",
    "sg:postcode":"22101",
    "sg:province":"VA",
    "sg:tags":[
        "shop"
    ],
    "wof:name":"Figuroe's",
    "wof:placetype":"venue"
},
  "geometry": {"coordinates":[-77.178707,38.933788],"type":"Point"}
}