{
  "type": "Feature",
  "properties": {
    "addr:full":"7323 Churchill Rd Mc Lean VA 22101",
    "addr:housenumber":"7323",
    "addr:postcode":"22101",
    "addr:street":"Churchill Rd",
    "iso:country":"US",
    "sg:address":"7323 Churchill Rd",
    "sg:city":"Mc Lean",
    "sg:classifiers":[
        {
            "category":"Professional",
            "type":"Services"
        }
    ],
    "sg:phone":"+1 703 522 7885",
    "sg:postcode":"22101",
    "sg:province":"VA",
    "sg:tags":[
        "psychological",
        "consultant",
        "industrial"
    ],
    "wof:name":"Elaine Pulaskos",
    "wof:placetype":"venue"
},
  "geometry": {"coordinates":[-77.198053,38.947887],"type":"Point"}
}