{
  "type": "Feature",
  "properties": {
    "addr:full":"13600 Lee Jackson Memorial Hwy Chantilly VA 20151",
    "addr:housenumber":"13600",
    "addr:postcode":"20151",
    "addr:street":"Lee Jackson Memorial Hwy",
    "iso:country":"US",
    "sg:address":"13600 Lee Jackson Memorial Hwy",
    "sg:city":"Chantilly",
    "sg:classifiers":[
        {
            "category":"Real Estate",
            "subcategory":"Real Estate Services",
            "type":"Services"
        },
        {
            "category":"Shopping Center",
            "type":"Public Place"
        }
    ],
    "sg:phone":"+1 703 378 9894",
    "sg:postcode":"20151",
    "sg:province":"VA",
    "sg:tags":[
        "mall",
        "management"
    ],
    "wof:name":"Chantilly Mall",
    "wof:placetype":"venue"
},
  "geometry": {"coordinates":[-77.418312,38.889252],"type":"Point"}
}