{
  "type": "Feature",
  "properties": {
    "addr:full":"33 Pear Ave Newport News VA 23607",
    "addr:housenumber":"33",
    "addr:postcode":"23607",
    "addr:street":"Pear Ave",
    "iso:country":"US",
    "sg:address":"33 Pear Ave",
    "sg:city":"Newport News",
    "sg:classifiers":[
        {
            "category":"Professional",
            "subcategory":"Business Services",
            "type":"Services"
        }
    ],
    "sg:phone":"+1 757 244 7719",
    "sg:postcode":"23607",
    "sg:province":"VA",
    "sg:tags":[
        "notary"
    ],
    "wof:name":"Mobile Notary Svc",
    "wof:placetype":"venue"
},
  "geometry": {"coordinates":[-76.38806700000001,36.989735],"type":"Point"}
}