{
  "type": "Feature",
  "properties": {
    "addr:full":"11722 Henderson Rd Clifton VA 20124",
    "addr:housenumber":"11722",
    "addr:postcode":"20124",
    "addr:street":"Henderson Rd",
    "iso:country":"US",
    "sg:address":"11722 Henderson Rd",
    "sg:city":"Clifton",
    "sg:classifiers":[
        {
            "category":"Professional",
            "type":"Services"
        }
    ],
    "sg:phone":"+1 703 869 5798",
    "sg:postcode":"20124",
    "sg:province":"VA",
    "sg:tags":[
        "establishment"
    ],
    "wof:name":"Synergetics",
    "wof:placetype":"venue"
},
  "geometry": {"coordinates":[-77.355991,38.736184],"type":"Point"}
}