{
  "type": "Feature",
  "properties": {
    "iso:country":"US",
    "sg:address":"3000 10th St N Ste B",
    "sg:city":"Arlington",
    "sg:classifiers":[
        {
            "category":"Home & Garden",
            "subcategory":"Furniture",
            "type":"Retail Goods"
        }
    ],
    "sg:phone":"+1 703 527 0088",
    "sg:postcode":"22201",
    "sg:province":"VA",
    "sg:tags":[
        "store"
    ],
    "sg:website":"www.ellensfuton.com",
    "wof:name":"Ellen's Futons",
    "wof:placetype":"venue"
},
  "geometry": {"coordinates":[-77.094024,38.884287],"type":"Point"}
}