{
  "type": "Feature",
  "properties": {
    "addr:full":"110 Star St Amherst VA 24521",
    "addr:housenumber":"110",
    "addr:postcode":"24521",
    "addr:street":"Star St",
    "iso:country":"US",
    "sg:address":"110 Star St",
    "sg:city":"Amherst",
    "sg:classifiers":[
        {
            "category":"Organizations",
            "subcategory":"Religious Organization",
            "type":"Services"
        }
    ],
    "sg:phone":"+1 434 946 7285",
    "sg:postcode":"24521",
    "sg:province":"VA",
    "sg:tags":[
        "church"
    ],
    "wof:name":"Morning Star Baptist Church",
    "wof:placetype":"venue"
},
  "geometry": {"coordinates":[-79.05047999999999,37.586535],"type":"Point"}
}