{
  "type": "Feature",
  "properties": {
    "iso:country":"US",
    "sg:address":"950 North Stafford St",
    "sg:city":"Arlington",
    "sg:classifiers":[
        {
            "category":"Travel",
            "subcategory":"Hotels & Motels",
            "type":"Entertainment"
        }
    ],
    "sg:phone":"+1 800 785 9319",
    "sg:postcode":"22203",
    "sg:province":"VA",
    "sg:website":"www1.hilton.com/",
    "wof:name":"Hilton Arlington",
    "wof:placetype":"venue"
},
  "geometry": {"coordinates":[-77.110478,38.881823],"type":"Point"}
}