{
  "type": "Feature",
  "properties": {
    "addr:full":"2732 Martinsburg Pike Stephenson VA 22656",
    "addr:housenumber":"2732",
    "addr:postcode":"22656",
    "addr:street":"Martinsburg Pike",
    "iso:country":"US",
    "sg:address":"2732 Martinsburg Pike",
    "sg:city":"Stephenson",
    "sg:classifiers":[
        {
            "category":"Organizations",
            "subcategory":"Religious Organization",
            "type":"Services"
        }
    ],
    "sg:phone":"+1 540 662 1269",
    "sg:postcode":"22656",
    "sg:province":"VA",
    "sg:tags":[
        "church"
    ],
    "wof:name":"Emmanuel United Methodist Chr",
    "wof:placetype":"venue"
},
  "geometry": {"coordinates":[-78.109342,39.237914],"type":"Point"}
}