{
  "type": "Feature",
  "properties": {
    "addr:full":"4608 Deep Creek Blvd Portsmouth VA 23702",
    "addr:housenumber":"4608",
    "addr:postcode":"23702",
    "addr:street":"Deep Creek Blvd",
    "iso:country":"US",
    "sg:address":"4608 Deep Creek Blvd",
    "sg:city":"Portsmouth",
    "sg:classifiers":[
        {
            "category":"Organizations",
            "subcategory":"Religious Organization",
            "type":"Services"
        }
    ],
    "sg:phone":"+1 757 487 3112",
    "sg:postcode":"23702",
    "sg:province":"VA",
    "wof:name":"Asbury United Methodist Church",
    "wof:placetype":"venue"
},
  "geometry": {"coordinates":[-76.33248500000001,36.800028],"type":"Point"}
}