{
  "type": "Feature",
  "properties": {
    "addr:full":"28599 Grizzard Rd Emporia VA 23847",
    "addr:postcode":"28599;23847",
    "addr:street":"Grizzard Rd",
    "iso:country":"US",
    "sg:address":"28599 Grizzard Rd",
    "sg:city":"Emporia",
    "sg:classifiers":[
        {
            "category":"Real Estate",
            "subcategory":"Real Estate Agent",
            "type":"Services"
        }
    ],
    "sg:phone":"+1 434 634 3876",
    "sg:postcode":"23847",
    "sg:province":"VA",
    "sg:tags":[
        "leasing"
    ],
    "wof:name":"Bob Harrell",
    "wof:placetype":"venue"
},
  "geometry": {"coordinates":[-77.435592,36.72823],"type":"Point"}
}