{
  "type": "Feature",
  "properties": {
    "addr:full":"3711 Cliffwood Rd Richmond VA 23234",
    "addr:housenumber":"3711",
    "addr:postcode":"23234",
    "addr:street":"Cliffwood Rd",
    "iso:country":"US",
    "sg:address":"3711 Cliffwood Rd",
    "sg:city":"Richmond",
    "sg:phone":"+1 804 275 7377",
    "sg:postcode":"23234",
    "sg:province":"VA",
    "sg:tags":[
        "farm",
        "field",
        "carrier",
        "insurance",
        "crop"
    ],
    "wof:name":"Soyars Glynn",
    "wof:placetype":"venue"
},
  "geometry": {"coordinates":[-77.465377,37.442054],"type":"Point"}
}