{
  "type": "Feature",
  "properties": {
    "addr:full":"608 William St Fredericksburg VA 22401",
    "addr:housenumber":"608",
    "addr:postcode":"22401",
    "addr:street":"William St",
    "iso:country":"US",
    "sg:address":"608 William St",
    "sg:city":"Fredericksburg",
    "sg:classifiers":[
        {
            "category":"Banks & Credit Unions",
            "subcategory":"Investment Brokerage",
            "type":"Services"
        }
    ],
    "sg:phone":"+1 540 370 4991",
    "sg:postcode":"22401",
    "sg:province":"VA",
    "sg:tags":[
        "consultant",
        "planning",
        "financial"
    ],
    "wof:name":"American Express Financial Adv",
    "wof:placetype":"venue"
},
  "geometry": {"coordinates":[-77.46400800000001,38.301895],"type":"Point"}
}