{
  "type": "Feature",
  "properties": {
    "iso:country":"US",
    "sg:address":"129 Center Dr",
    "sg:city":"Forest",
    "sg:classifiers":[
        {
            "category":"Utilities",
            "subcategory":"Telephone",
            "type":"Services"
        },
        {
            "category":"Professional",
            "subcategory":"Business Services",
            "type":"Services"
        }
    ],
    "sg:phone":"+1 434 316 7400",
    "sg:postcode":"24550",
    "sg:province":"VA",
    "sg:tags":[
        "telecommunication",
        "telemarketing"
    ],
    "sg:website":"www.armycash.com",
    "wof:name":"In Service America Inc",
    "wof:placetype":"venue"
},
  "geometry": {"coordinates":[-79.265298,37.308791],"type":"Point"}
}