{
  "type": "Feature",
  "properties": {
    "addr:full":"6656 Mountain Light Pl Crozet VA 22932",
    "addr:housenumber":"6656",
    "addr:postcode":"22932",
    "addr:street":"Mountain Light Pl",
    "iso:country":"US",
    "sg:address":"6656 Mountain Light Pl",
    "sg:city":"Crozet",
    "sg:classifiers":[
        {
            "category":"Professional",
            "type":"Services"
        }
    ],
    "sg:phone":"+1 434 978 7770",
    "sg:postcode":"22932",
    "sg:province":"VA",
    "sg:tags":[
        "establishment"
    ],
    "wof:name":"Mountain Light Retreat Ctr",
    "wof:placetype":"venue"
},
  "geometry": {"coordinates":[-78.626997,38.224813],"type":"Point"}
}