{
  "type": "Feature",
  "properties": {
    "addr:full":"1312 Kingston Ave Alexandria VA 22302",
    "addr:housenumber":"1312",
    "addr:postcode":"22302",
    "addr:street":"Kingston Ave",
    "iso:country":"US",
    "sg:address":"1312 Kingston Ave",
    "sg:city":"Alexandria",
    "sg:classifiers":[
        {
            "category":"Railroad",
            "type":"Transportation"
        }
    ],
    "sg:phone":"+1 571 277 7955",
    "sg:postcode":"22302",
    "sg:province":"VA",
    "sg:tags":[
        "equipment",
        "supply"
    ],
    "wof:name":"Ecorapidtransit",
    "wof:placetype":"venue"
},
  "geometry": {"coordinates":[-77.08354199999999,38.817341],"type":"Point"}
}