{
  "type": "Feature",
  "properties": {
    "iso:country":"US",
    "sg:address":"1490 Mahone St",
    "sg:city":"Christiansburg",
    "sg:classifiers":[
        {
            "category":"Building & Trades",
            "subcategory":"Construction",
            "type":"Services"
        }
    ],
    "sg:phone":"+1 540 382 7983",
    "sg:postcode":"24073",
    "sg:province":"VA",
    "sg:tags":[
        "painter"
    ],
    "wof:name":"Graves Painting",
    "wof:placetype":"venue"
},
  "geometry": {"coordinates":[-80.436893,37.124791],"type":"Point"}
}