{
  "type": "Feature",
  "properties": {
    "iso:country":"US",
    "sg:address":"5445 Main St",
    "sg:city":"Stephens City",
    "sg:classifiers":[
        {
            "category":"Professional",
            "type":"Services"
        }
    ],
    "sg:phone":"+1 540 868 1822",
    "sg:postcode":"22655",
    "sg:province":"VA",
    "wof:name":"Pharmlands",
    "wof:placetype":"venue"
},
  "geometry": {"coordinates":[-78.219193,39.082222],"type":"Point"}
}