{
  "type": "Feature",
  "properties": {
    "iso:country":"US",
    "sg:address":"9 Ward Dr",
    "sg:city":"Hampton",
    "sg:classifiers":[
        {
            "category":"Professional",
            "subcategory":"Employment Agencies",
            "type":"Services"
        }
    ],
    "sg:phone":"+1 757 838 2501",
    "sg:postcode":"23669",
    "sg:province":"VA",
    "sg:tags":[
        "help",
        "supply"
    ],
    "wof:name":"Tidewater Transcription Svc",
    "wof:placetype":"venue"
},
  "geometry": {"coordinates":[-76.389849,37.024788],"type":"Point"}
}