{
  "type": "Feature",
  "properties": {
    "addr:full":"784 Timberlake Dr Virginia Beach VA 23464",
    "addr:housenumber":"784",
    "addr:postcode":"23464",
    "addr:street":"Timberlake Dr",
    "iso:country":"US",
    "sg:address":"784 Timberlake Dr",
    "sg:city":"Virginia Beach",
    "sg:classifiers":[
        {
            "category":"Building & Trades",
            "subcategory":"Construction",
            "type":"Services"
        }
    ],
    "sg:phone":"+1 757 496 2884",
    "sg:postcode":"23464",
    "sg:province":"VA",
    "sg:tags":[
        "housing"
    ],
    "wof:name":"Georgio Construction",
    "wof:placetype":"venue"
},
  "geometry": {"coordinates":[-76.13885999999999,36.811005],"type":"Point"}
}