{
  "type": "Feature",
  "properties": {
    "addr:full":"176 Skimino Rd Williamsburg VA 23188",
    "addr:housenumber":"176",
    "addr:postcode":"23188",
    "addr:street":"Skimino Rd",
    "iso:country":"US",
    "sg:address":"176 Skimino Rd",
    "sg:city":"Williamsburg",
    "sg:classifiers":[
        {
            "category":"Real Estate",
            "subcategory":"Developer",
            "type":"Services"
        }
    ],
    "sg:phone":"+1 757 565 2097",
    "sg:postcode":"23188",
    "sg:province":"VA",
    "wof:name":"Jay Levinson Construction Co",
    "wof:placetype":"venue"
},
  "geometry": {"coordinates":[-76.695392,37.355555],"type":"Point"}
}