{
  "type": "Feature",
  "properties": {
    "iso:country":"US",
    "sg:address":"628 N Washington St",
    "sg:city":"Alexandria",
    "sg:classifiers":[
        {
            "category":"Manufacturing",
            "subcategory":"Wood Products",
            "type":"Manufacturing & Wholesale Goods"
        }
    ],
    "sg:phone":"+1 703 549 1616",
    "sg:postcode":"22314",
    "sg:province":"VA",
    "sg:tags":[
        "picture",
        "framing",
        "gallery"
    ],
    "sg:website":"http://www.ericksonandripper.com",
    "wof:name":"Erickson & Ripper Gallery",
    "wof:placetype":"venue"
},
  "geometry": {"coordinates":[-77.045687,38.811058],"type":"Point"}
}