{
  "type": "Feature",
  "properties": {
    "addr:full":"4308 Evergreen Ln Annandale VA 22003",
    "addr:housenumber":"4308",
    "addr:postcode":"22003",
    "addr:street":"Evergreen Ln",
    "iso:country":"US",
    "sg:address":"4308 Evergreen Ln",
    "sg:city":"Annandale",
    "sg:classifiers":[
        {
            "category":"Organizations",
            "subcategory":"Labor Organization",
            "type":"Services"
        }
    ],
    "sg:phone":"+1 703 256 2200",
    "sg:postcode":"22003",
    "sg:province":"VA",
    "sg:website":"www.cwa2222.org",
    "wof:name":"Communications Workers America",
    "wof:placetype":"venue"
},
  "geometry": {"coordinates":[-77.185833,38.83096],"type":"Point"}
}