{
  "type": "Feature",
  "properties": {
    "iso:country":"US",
    "sg:address":"319 W Morgan Ave",
    "sg:city":"Pennington Gap",
    "sg:classifiers":[
        {
            "category":"Retail",
            "subcategory":"Laundry & Dry Cleaning",
            "type":"Services"
        }
    ],
    "sg:phone":"+1 276 546 0126",
    "sg:postcode":"24277",
    "sg:province":"VA",
    "sg:tags":[
        "cleaners",
        "rug",
        "carpet"
    ],
    "wof:name":"Maid II Clean",
    "wof:placetype":"venue"
},
  "geometry": {"coordinates":[-83.02959199999999,36.757093],"type":"Point"}
}