{
  "type": "Feature",
  "properties": {
    "iso:country":"US",
    "sg:address":"2341 Virginia Beach Blvd",
    "sg:city":"Virginia Beach",
    "sg:classifiers":[
        {
            "category":"Autos & Motor Vehicles",
            "subcategory":"Automobile Sales",
            "type":"Retail Goods"
        }
    ],
    "sg:phone":"+1 757 486 6330",
    "sg:postcode":"23454",
    "sg:province":"VA",
    "sg:tags":[
        "used"
    ],
    "wof:name":"Winslows Lndon Bridge Auto Sls",
    "wof:placetype":"venue"
},
  "geometry": {"coordinates":[-76.05002,36.841523],"type":"Point"}
}