{
  "type": "Feature",
  "properties": {
    "iso:country":"US",
    "sg:address":"16063 Hamilton Station Rd",
    "sg:city":"Waterford",
    "sg:classifiers":[
        {
            "category":"Real Estate",
            "subcategory":"Real Estate Services",
            "type":"Services"
        },
        {
            "category":"Real Estate",
            "subcategory":"Real Estate Agent",
            "type":"Services"
        }
    ],
    "sg:phone":"+1 703 437 3800",
    "sg:postcode":"20197",
    "sg:province":"VA",
    "sg:tags":[
        "buyer",
        "management",
        "broker"
    ],
    "sg:website":"http://www.longandfoster.com",
    "wof:name":"Hamilton Station",
    "wof:placetype":"venue"
},
  "geometry": {"coordinates":[-77.622451,39.174295],"type":"Point"}
}