{
  "type": "Feature",
  "properties": {
    "addr:full":"7229 Forest Ave Ste 102 Richmond VA 23226",
    "addr:housenumber":"7229",
    "addr:postcode":"23226",
    "addr:street":"Forest Ave Ste 102",
    "iso:country":"US",
    "sg:address":"7229 Forest Ave Ste 102",
    "sg:city":"Richmond",
    "sg:classifiers":[
        {
            "category":"Banks & Credit Unions",
            "subcategory":"Bank",
            "type":"Services"
        },
        {
            "category":"Banks & Credit Unions",
            "subcategory":"Financial Services",
            "type":"Services"
        }
    ],
    "sg:phone":"+1 804 673 0944",
    "sg:postcode":"23226",
    "sg:province":"VA",
    "sg:tags":[
        "saving",
        "loan",
        "commercial"
    ],
    "sg:website":"http://www.suntrust.com",
    "wof:name":"Suntrust",
    "wof:placetype":"venue"
},
  "geometry": {"coordinates":[-77.52870900000001,37.605388],"type":"Point"}
}