{
  "type": "Feature",
  "properties": {
    "addr:full":"1716 Wilson St SE Roanoke VA 24013",
    "addr:housenumber":"1716",
    "addr:postcode":"24013",
    "addr:street":"Wilson St Se",
    "iso:country":"US",
    "sg:address":"1716 Wilson St SE",
    "sg:city":"Roanoke",
    "sg:classifiers":[
        {
            "category":"Education",
            "subcategory":"School",
            "type":"Public Place"
        }
    ],
    "sg:phone":"+1 540 853 2991",
    "sg:postcode":"24013",
    "sg:province":"VA",
    "sg:tags":[
        "elementary"
    ],
    "wof:name":"Roanoke City Sch Dist",
    "wof:placetype":"venue"
},
  "geometry": {"coordinates":[-79.921784,37.261013],"type":"Point"}
}