{
  "type": "Feature",
  "properties": {
    "addr:full":"84 Pleasant Valley Rd Harrisonburg VA 22801",
    "addr:housenumber":"84",
    "addr:postcode":"22801",
    "addr:street":"Pleasant Valley Rd",
    "iso:country":"US",
    "sg:address":"84 Pleasant Valley Rd",
    "sg:city":"Harrisonburg",
    "sg:classifiers":[
        {
            "category":"Home & Garden",
            "subcategory":"Building Materials",
            "type":"Retail Goods"
        }
    ],
    "sg:phone":"+1 540 434 8468",
    "sg:postcode":"22801",
    "sg:province":"VA",
    "sg:tags":[
        "lumber"
    ],
    "wof:name":"84 Lumber",
    "wof:placetype":"venue"
},
  "geometry": {"coordinates":[-78.906491,38.4056],"type":"Point"}
}