{
  "type": "Feature",
  "properties": {
    "addr:full":"107 Executive Ct Danville VA 24541",
    "addr:housenumber":"107",
    "addr:postcode":"24541",
    "addr:street":"Executive Ct",
    "iso:country":"US",
    "sg:address":"107 Executive Ct",
    "sg:city":"Danville",
    "sg:classifiers":[
        {
            "category":"Restaurant",
            "type":"Food & Drink"
        }
    ],
    "sg:menulink":"http://www.allmenus.com/va/danville/105374-ryans/menu/",
    "sg:phone":"+1 434 799 7926",
    "sg:postcode":"24541",
    "sg:province":"VA",
    "sg:tags":[
        "american"
    ],
    "wof:name":"Ryan's",
    "wof:placetype":"venue"
},
  "geometry": {"coordinates":[-79.430128,36.5923],"type":"Point"}
}