{
  "type": "Feature",
  "properties": {
    "addr:full":"2721 Embassy Dr Roanoke VA 24019",
    "addr:housenumber":"2721",
    "addr:postcode":"24019",
    "addr:street":"Embassy Dr",
    "iso:country":"US",
    "sg:address":"2721 Embassy Dr",
    "sg:city":"Roanoke",
    "sg:classifiers":[
        {
            "category":"Farming",
            "subcategory":"Dairy Farm",
            "type":"Manufacturing & Wholesale Goods"
        }
    ],
    "sg:phone":"+1 540 562 1970",
    "sg:postcode":"24019",
    "sg:province":"VA",
    "wof:name":"Lauren L & Peggy Schmidt",
    "wof:placetype":"venue"
},
  "geometry": {"coordinates":[-80.020246,37.3153],"type":"Point"}
}