{
  "type": "Feature",
  "properties": {
    "addr:full":"1071 W 39th St Norfolk VA 23508",
    "addr:housenumber":"1071",
    "addr:postcode":"23508",
    "addr:street":"W 39Th St",
    "iso:country":"US",
    "sg:address":"1071 W 39th St",
    "sg:city":"Norfolk",
    "sg:classifiers":[
        {
            "category":"Building & Trades",
            "subcategory":"Construction",
            "type":"Services"
        }
    ],
    "sg:phone":"+1 757 489 8676",
    "sg:postcode":"23508",
    "sg:province":"VA",
    "sg:tags":[
        "home",
        "improvement"
    ],
    "sg:website":"www.wiscocorp.com",
    "wof:name":"WISCO",
    "wof:placetype":"venue"
},
  "geometry": {"coordinates":[-76.301501,36.880481],"type":"Point"}
}