{
  "type": "Feature",
  "properties": {
    "iso:country":"US",
    "sg:address":"1105 Seaford Rd",
    "sg:city":"Seaford",
    "sg:classifiers":[
        {
            "category":"Education",
            "subcategory":"School",
            "type":"Public Place"
        }
    ],
    "sg:phone":"+1 757 875 2347",
    "sg:postcode":"23696",
    "sg:province":"VA",
    "sg:tags":[
        "executive"
    ],
    "sg:website":"www.yorkcountyschools.org",
    "wof:name":"Seaford Elementary School",
    "wof:placetype":"venue"
},
  "geometry": {"coordinates":[-76.44535399999999,37.185264],"type":"Point"}
}