{
  "type": "Feature",
  "properties": {
    "addr:full":"1552 Sheppard Town Rd Crozier VA 23039",
    "addr:housenumber":"1552",
    "addr:postcode":"23039",
    "addr:street":"Sheppard Town Rd",
    "iso:country":"US",
    "sg:address":"1552 Sheppard Town Rd",
    "sg:city":"Crozier",
    "sg:classifiers":[
        {
            "category":"Education",
            "subcategory":"School",
            "type":"Public Place"
        }
    ],
    "sg:phone":"+1 804 556 5385",
    "sg:postcode":"23039",
    "sg:province":"VA",
    "wof:name":"Randolph Elementary School",
    "wof:placetype":"venue"
},
  "geometry": {"coordinates":[-77.79436699999999,37.684573],"type":"Point"}
}