{
  "type": "Feature",
  "properties": {
    "iso:country":"US",
    "sg:address":"10 Old Logging Rd",
    "sg:city":"Flint Hill",
    "sg:classifiers":[
        {
            "category":"Professional",
            "subcategory":"Management & Consulting",
            "type":"Services"
        }
    ],
    "sg:phone":"+1 540 364 1841",
    "sg:postcode":"22642",
    "sg:province":"VA",
    "sg:tags":[
        "business"
    ],
    "wof:name":"Cebi Inc",
    "wof:placetype":"venue"
},
  "geometry": {"coordinates":[-78.02999699999999,38.95276],"type":"Point"}
}