{
  "type": "Feature",
  "properties": {
    "addr:full":"440 Wright Rd Keysville VA 23937",
    "addr:housenumber":"440",
    "addr:postcode":"23937",
    "addr:street":"Wright Rd",
    "iso:country":"US",
    "sg:address":"440 Wright Rd",
    "sg:city":"Keysville",
    "sg:classifiers":[
        {
            "category":"Freight",
            "type":"Transportation"
        }
    ],
    "sg:phone":"+1 434 736 8940",
    "sg:postcode":"23937",
    "sg:province":"VA",
    "sg:tags":[
        "operator",
        "local",
        "trucking"
    ],
    "wof:name":"Tim Pride Trucking",
    "wof:placetype":"venue"
},
  "geometry": {"coordinates":[-78.48491799999999,37.011042],"type":"Point"}
}