{
  "type": "Feature",
  "properties": {
    "addr:full":"2000 Clarendon Blvd Ste 300 Arlington VA 22201",
    "addr:housenumber":"2000",
    "addr:postcode":"22201",
    "addr:street":"Clarendon Blvd Ste 300",
    "iso:country":"US",
    "sg:address":"2000 Clarendon Blvd Ste 300",
    "sg:city":"Arlington",
    "sg:phone":"+1 703 465 0222",
    "sg:postcode":"22201",
    "sg:province":"VA",
    "wof:name":"Williams Mechanical Corp",
    "wof:placetype":"venue"
},
  "geometry": {"coordinates":[-77.083341,38.891555],"type":"Point"}
}