{
  "type": "Feature",
  "properties": {
    "addr:full":"1323 Kenwood Ln Charlottesville VA 22901",
    "addr:housenumber":"1323",
    "addr:postcode":"22901",
    "addr:street":"Kenwood Ln",
    "iso:country":"US",
    "sg:address":"1323 Kenwood Ln",
    "sg:city":"Charlottesville",
    "sg:classifiers":[
        {
            "category":"Professional",
            "subcategory":"Engineering",
            "type":"Services"
        }
    ],
    "sg:phone":"+1 434 466 2843",
    "sg:postcode":"22901",
    "sg:province":"VA",
    "wof:name":"DFI",
    "wof:placetype":"venue"
},
  "geometry": {"coordinates":[-78.47359299999999,38.055691],"type":"Point"}
}