{
  "type": "Feature",
  "properties": {
    "addr:full":"7778 Gunston Plz Lorton VA 22079",
    "addr:housenumber":"7778",
    "addr:postcode":"22079",
    "addr:street":"Gunston Plz",
    "iso:country":"US",
    "sg:address":"7778 Gunston Plz",
    "sg:city":"Lorton",
    "sg:classifiers":[
        {
            "category":"Building & Trades",
            "subcategory":"Construction",
            "type":"Services"
        }
    ],
    "sg:phone":"+1 703 339 4931",
    "sg:postcode":"22079",
    "sg:province":"VA",
    "sg:tags":[
        "resurfacing",
        "laying",
        "refinishing",
        "floor"
    ],
    "wof:name":"Floor & Rug Station",
    "wof:placetype":"venue"
},
  "geometry": {"coordinates":[-77.20951100000001,38.703696],"type":"Point"}
}