{
  "type": "Feature",
  "properties": {
    "iso:country":"US",
    "sg:address":"1933 Patrick Henry Hwy",
    "sg:city":"Amherst",
    "sg:classifiers":[
        {
            "category":"Food & Beverages",
            "subcategory":"Groceries & Convenience Stores",
            "type":"Retail Goods"
        }
    ],
    "sg:phone":"+1 434 277 8403",
    "sg:postcode":"24521",
    "sg:province":"VA",
    "wof:name":"Hill Top Market",
    "wof:placetype":"venue"
},
  "geometry": {"coordinates":[-79.01074800000001,37.657642],"type":"Point"}
}