{
  "type": "Feature",
  "properties": {
    "iso:country":"US",
    "sg:address":"1615 Brook Rd",
    "sg:city":"Richmond",
    "sg:classifiers":[
        {
            "category":"Retail",
            "subcategory":"Auto Repair",
            "type":"Services"
        }
    ],
    "sg:phone":"+1 804 225 8122",
    "sg:postcode":"23220",
    "sg:province":"VA",
    "sg:tags":[
        "transmission"
    ],
    "wof:name":"Steve's Transmissions",
    "wof:placetype":"venue"
},
  "geometry": {"coordinates":[-77.446755,37.558749],"type":"Point"}
}