{
  "type": "Feature",
  "properties": {
    "addr:full":"2697 International Pkwy Virginia Beach VA 23452",
    "addr:housenumber":"2697",
    "addr:postcode":"23452",
    "addr:street":"International Pkwy",
    "iso:country":"US",
    "sg:address":"2697 International Pkwy",
    "sg:city":"Virginia Beach",
    "sg:classifiers":[
        {
            "category":"Health Services",
            "subcategory":"Medical Lab",
            "type":"Services"
        }
    ],
    "sg:phone":"+1 757 468 1605",
    "sg:postcode":"23452",
    "sg:province":"VA",
    "sg:tags":[
        "laboratory",
        "dental"
    ],
    "wof:name":"Winn Dental Lab",
    "wof:placetype":"venue"
},
  "geometry": {"coordinates":[-76.063249,36.815915],"type":"Point"}
}