{
  "type": "Feature",
  "properties": {
    "addr:full":"The Pentagon Arlington VA 22216",
    "addr:postcode":"22216",
    "iso:country":"US",
    "sg:address":"The Pentagon",
    "sg:city":"Arlington",
    "sg:classifiers":[
        {
            "category":"Restaurant",
            "type":"Food & Drink"
        }
    ],
    "sg:postcode":"22216",
    "sg:province":"VA",
    "sg:tags":[
        "flavor",
        "local"
    ],
    "wof:name":"Army Ten-Miler",
    "wof:placetype":"venue"
},
  "geometry": {"coordinates":[-77.054429,38.872982],"type":"Point"}
}