{
  "type": "Feature",
  "properties": {
    "iso:country":"US",
    "sg:address":"5248 Willow Oak Rd",
    "sg:city":"Eastville",
    "sg:classifiers":[
        {
            "category":"Social Services",
            "type":"Services"
        }
    ],
    "sg:phone":"+1 757 678 7157",
    "sg:postcode":"23310",
    "sg:province":"VA",
    "sg:tags":[
        "organization",
        "welfare"
    ],
    "sg:website":"www.cbes.org",
    "wof:name":"Citizens For A Better E Shore",
    "wof:placetype":"venue"
},
  "geometry": {"coordinates":[-75.946072,37.353006],"type":"Point"}
}