{
  "type": "Feature",
  "properties": {
    "addr:full":"5855 Leesburg Pike Falls Church VA 22041",
    "addr:housenumber":"5855",
    "addr:postcode":"22041",
    "addr:street":"Leesburg Pike",
    "iso:country":"US",
    "sg:address":"5855 Leesburg Pike",
    "sg:city":"Falls Church",
    "sg:classifiers":[
        {
            "category":"Restaurant",
            "type":"Food & Drink"
        }
    ],
    "sg:menulink":"http://www.allmenus.com/va/mason/89706-moes-southwest-grill/menu/",
    "sg:phone":"+1 703 578 6637",
    "sg:postcode":"22041",
    "sg:province":"VA",
    "sg:tags":[
        "mexican"
    ],
    "wof:name":"Moe's Southwest Grill",
    "wof:placetype":"venue"
},
  "geometry": {"coordinates":[-77.1323,38.8519],"type":"Point"}
}