{
  "type": "Feature",
  "properties": {
    "addr:full":"800 Baker Rd Virginia Beach VA 23462",
    "addr:housenumber":"800",
    "addr:postcode":"23462",
    "addr:street":"Baker Rd",
    "iso:country":"US",
    "sg:address":"800 Baker Rd",
    "sg:city":"Virginia Beach",
    "sg:classifiers":[
        {
            "category":"Organizations",
            "subcategory":"Religious Organization",
            "type":"Services"
        }
    ],
    "sg:phone":"+1 757 497 6247",
    "sg:postcode":"23462",
    "sg:province":"VA",
    "sg:tags":[
        "church"
    ],
    "wof:name":"Rhema Outreach Center",
    "wof:placetype":"venue"
},
  "geometry": {"coordinates":[-76.180352,36.867267],"type":"Point"}
}