{
  "type": "Feature",
  "properties": {
    "addr:full":"7262 Columbia Pike Annandale VA 22003",
    "addr:housenumber":"7262",
    "addr:postcode":"22003",
    "addr:street":"Columbia Pike",
    "iso:country":"US",
    "sg:address":"7262 Columbia Pike",
    "sg:city":"Annandale",
    "sg:classifiers":[
        {
            "category":"Autos & Motor Vehicles",
            "subcategory":"Auto Supplies",
            "type":"Retail Goods"
        }
    ],
    "sg:phone":"+1 703 256 8100",
    "sg:postcode":"22003",
    "sg:province":"VA",
    "sg:tags":[
        "automobile",
        "parts"
    ],
    "wof:name":"J K Auto Parts Inc",
    "wof:placetype":"venue"
},
  "geometry": {"coordinates":[-77.195588,38.830874],"type":"Point"}
}