{
  "type": "Feature",
  "properties": {
    "iso:country":"US",
    "sg:address":"360 Arrowhead Trl",
    "sg:city":"Christiansburg",
    "sg:classifiers":[
        {
            "category":"Professional",
            "subcategory":"Accounting & Tax Preparation",
            "type":"Services"
        }
    ],
    "sg:phone":"+1 540 381 3650",
    "sg:postcode":"24073",
    "sg:province":"VA",
    "wof:name":"Margaret Zelinski",
    "wof:placetype":"venue"
},
  "geometry": {"coordinates":[-80.388462,37.12992],"type":"Point"}
}