{
  "type": "Feature",
  "properties": {
    "iso:country":"US",
    "sg:address":"8080 Angel Ln",
    "sg:city":"Roanoke",
    "sg:classifiers":[
        {
            "category":"Organizations",
            "subcategory":"Religious Organization",
            "type":"Services"
        }
    ],
    "sg:phone":"+1 540 563 0685",
    "sg:postcode":"24019",
    "sg:province":"VA",
    "sg:tags":[
        "clergy"
    ],
    "wof:name":"David E Hagee",
    "wof:placetype":"venue"
},
  "geometry": {"coordinates":[-79.96930500000001,37.360877],"type":"Point"}
}