{
  "type": "Feature",
  "properties": {
    "addr:full":"2931 Chamberlayne Ave Richmond VA 23222",
    "addr:housenumber":"2931",
    "addr:postcode":"23222",
    "addr:street":"Chamberlayne Ave",
    "iso:country":"US",
    "sg:address":"2931 Chamberlayne Ave",
    "sg:city":"Richmond",
    "sg:classifiers":[
        {
            "category":"Autos & Motor Vehicles",
            "subcategory":"Fuel & Gas Station",
            "type":"Retail Goods"
        },
        {
            "category":"Shopping",
            "type":"Retail Goods"
        },
        {
            "category":"Food & Beverages",
            "subcategory":"Groceries & Convenience Stores",
            "type":"Retail Goods"
        }
    ],
    "sg:phone":"+1 804 329 9403",
    "sg:postcode":"23222",
    "sg:province":"VA",
    "sg:tags":[
        "merchandise"
    ],
    "wof:name":"Bp. Food Shop",
    "wof:placetype":"venue"
},
  "geometry": {"coordinates":[-77.44499500000001,37.571401],"type":"Point"}
}