{
  "type": "Feature",
  "properties": {
    "iso:country":"US",
    "sg:address":"8411 Oakview Ave",
    "sg:city":"Richmond",
    "sg:classifiers":[
        {
            "category":"Home & Garden",
            "subcategory":"Building Materials",
            "type":"Retail Goods"
        }
    ],
    "sg:phone":"+1 804 264 2755",
    "sg:postcode":"23228",
    "sg:province":"VA",
    "sg:tags":[
        "glass",
        "window",
        "plate"
    ],
    "wof:name":"Old Dominion Glass Inc",
    "wof:placetype":"venue"
},
  "geometry": {"coordinates":[-77.50042999999999,37.62791],"type":"Point"}
}