{
  "type": "Feature",
  "properties": {
    "addr:full":"7342 Lee Hwy Falls Church VA 22046",
    "addr:housenumber":"7342",
    "addr:postcode":"22046",
    "addr:street":"Lee Hwy",
    "iso:country":"US",
    "sg:address":"7342 Lee Hwy",
    "sg:city":"Falls Church",
    "sg:classifiers":[
        {
            "category":"Organizations",
            "subcategory":"Religious Organization",
            "type":"Services"
        }
    ],
    "sg:phone":"+1 703 645 0164",
    "sg:postcode":"22046",
    "sg:province":"VA",
    "sg:tags":[
        "church"
    ],
    "wof:name":"Noon Prayer Mission",
    "wof:placetype":"venue"
},
  "geometry": {"coordinates":[-77.195357,38.876897],"type":"Point"}
}