{
  "type": "Feature",
  "properties": {
    "addr:full":"1000c Main St Altavista VA 24517",
    "addr:housenumber":"1000c",
    "addr:postcode":"24517",
    "addr:street":"Main St",
    "iso:country":"US",
    "sg:address":"1000c Main St",
    "sg:city":"Altavista",
    "sg:classifiers":[
        {
            "category":"Restaurant",
            "type":"Food & Drink"
        }
    ],
    "sg:menulink":"http://www.allmenus.com/va/altavista/80449-dominos-pizza/menu/",
    "sg:phone":"+1 434 369 6767",
    "sg:postcode":"24517",
    "sg:province":"VA",
    "sg:tags":[
        "american",
        "wing",
        "pizza"
    ],
    "wof:name":"Domino's Pizza",
    "wof:placetype":"venue"
},
  "geometry": {"coordinates":[-79.282805,37.113743],"type":"Point"}
}