{
  "type": "Feature",
  "properties": {
    "iso:country":"US",
    "sg:address":"7209 Burtonwood Dr",
    "sg:city":"Alexandria",
    "sg:classifiers":[
        {
            "category":"Professional",
            "subcategory":"Computer Services",
            "type":"Services"
        }
    ],
    "sg:phone":"+1 703 768 8615",
    "sg:postcode":"22307",
    "sg:province":"VA",
    "sg:tags":[
        "programing",
        "custom"
    ],
    "wof:name":"Z G I",
    "wof:placetype":"venue"
},
  "geometry": {"coordinates":[-77.054062,38.758928],"type":"Point"}
}