{
  "type": "Feature",
  "properties": {
    "addr:full":"2533 Potters Rd Virginia Beach VA 23454",
    "addr:housenumber":"2533",
    "addr:postcode":"23454",
    "addr:street":"Potters Rd",
    "iso:country":"US",
    "sg:address":"2533 Potters Rd",
    "sg:city":"Virginia Beach",
    "sg:classifiers":[
        {
            "category":"Building & Trades",
            "subcategory":"Construction",
            "type":"Services"
        }
    ],
    "sg:phone":"+1 757 486 0167",
    "sg:postcode":"23454",
    "sg:province":"VA",
    "sg:tags":[
        "contractor"
    ],
    "wof:name":"Bernies Pressure Washing",
    "wof:placetype":"venue"
},
  "geometry": {"coordinates":[-76.05771799999999,36.835682],"type":"Point"}
}