{
  "type": "Feature",
  "properties": {
    "iso:country":"US",
    "sg:address":"1182 Panorama Acres Rd",
    "sg:city":"Big Island",
    "sg:classifiers":[
        {
            "category":"Restaurant",
            "type":"Food & Drink"
        }
    ],
    "sg:phone":"+1 434 299 5657",
    "sg:postcode":"24526",
    "sg:province":"VA",
    "sg:tags":[
        "eating"
    ],
    "wof:name":"Big Island Antique Engine Rest",
    "wof:placetype":"venue"
},
  "geometry": {"coordinates":[-79.406738,37.526803],"type":"Point"}
}