{
  "type": "Feature",
  "properties": {
    "addr:full":"648 Elden St Herndon VA 20170",
    "addr:housenumber":"648",
    "addr:postcode":"20170",
    "addr:street":"Elden St",
    "iso:country":"US",
    "sg:address":"648 Elden St",
    "sg:city":"Herndon",
    "sg:classifiers":[
        {
            "category":"Restaurant",
            "type":"Food & Drink"
        }
    ],
    "sg:menulink":"http://www.allmenus.com/va/dranesville/24794-the-tortilla-factory/menu/",
    "sg:phone":"+1 703 578 4325",
    "sg:postcode":"20170",
    "sg:province":"VA",
    "sg:tags":[
        "american",
        "southwestern"
    ],
    "wof:name":"The Tortilla Factory",
    "wof:placetype":"venue"
},
  "geometry": {"coordinates":[-77.38206700000001,38.96933],"type":"Point"}
}