{
  "type": "Feature",
  "properties": {
    "addr:full":"342 N Court Ave Covington VA 24426",
    "addr:housenumber":"342",
    "addr:postcode":"24426",
    "addr:street":"N Court Ave",
    "iso:country":"US",
    "sg:address":"342 N Court Ave",
    "sg:city":"Covington",
    "sg:classifiers":[
        {
            "category":"Utilities",
            "subcategory":"Telephone",
            "type":"Services"
        }
    ],
    "sg:phone":"+1 540 965 2255",
    "sg:postcode":"24426",
    "sg:province":"VA",
    "sg:tags":[
        "company"
    ],
    "wof:name":"Ntelos",
    "wof:placetype":"venue"
},
  "geometry": {"coordinates":[-79.99627599999999,37.792825],"type":"Point"}
}