{
  "type": "Feature",
  "properties": {
    "addr:full":"20911 Timberlake Rd Lynchburg VA 24502",
    "addr:housenumber":"20911",
    "addr:postcode":"24502",
    "addr:street":"Timberlake Rd",
    "iso:country":"US",
    "sg:address":"20911 Timberlake Rd",
    "sg:city":"Lynchburg",
    "sg:classifiers":[
        {
            "category":"Personal",
            "subcategory":"Beauty Salon",
            "type":"Services"
        }
    ],
    "sg:phone":"+1 434 239 4779",
    "sg:postcode":"24502",
    "sg:province":"VA",
    "sg:tags":[
        "shop"
    ],
    "wof:name":"Abrakadabra",
    "wof:placetype":"venue"
},
  "geometry": {"coordinates":[-79.241139,37.335974],"type":"Point"}
}