{
  "type": "Feature",
  "properties": {
    "addr:full":"1400 S Joyce St Arlington VA 22202",
    "addr:housenumber":"1400",
    "addr:postcode":"22202",
    "addr:street":"S Joyce St",
    "iso:country":"US",
    "sg:address":"1400 S Joyce St",
    "sg:city":"Arlington",
    "sg:classifiers":[
        {
            "category":"Professional",
            "subcategory":"Management & Consulting",
            "type":"Services"
        }
    ],
    "sg:phone":"+1 703 892 1905",
    "sg:postcode":"22202",
    "sg:province":"VA",
    "sg:tags":[
        "consultant",
        "business"
    ],
    "sg:website":"www.omegainc.com",
    "wof:name":"Omega Systems Group Inc",
    "wof:placetype":"venue"
},
  "geometry": {"coordinates":[-77.062865,38.865848],"type":"Point"}
}