{
  "type": "Feature",
  "properties": {
    "iso:country":"US",
    "sg:address":"330 Commonwealth Dr",
    "sg:city":"Wytheville",
    "sg:classifiers":[
        {
            "category":"Health Services",
            "subcategory":"Health Practitioner",
            "type":"Services"
        }
    ],
    "sg:phone":"+1 276 223 1482",
    "sg:postcode":"24333",
    "sg:province":"VA",
    "sg:tags":[
        "nutritionist"
    ],
    "wof:name":"Nutrition America",
    "wof:placetype":"venue"
},
  "geometry": {"coordinates":[-80.84785100000001,36.70974],"type":"Point"}
}