{
  "type": "Feature",
  "properties": {
    "addr:full":"533 Highland Ave Suffolk VA 23434",
    "addr:housenumber":"533",
    "addr:postcode":"23434",
    "addr:street":"Highland Ave",
    "iso:country":"US",
    "sg:address":"533 Highland Ave",
    "sg:city":"Suffolk",
    "sg:classifiers":[
        {
            "category":"Professional",
            "subcategory":"Secretarial Services",
            "type":"Services"
        }
    ],
    "sg:phone":"+1 757 934 3725",
    "sg:postcode":"23434",
    "sg:province":"VA",
    "sg:tags":[
        "typing"
    ],
    "wof:name":"C E & B Financial Svc",
    "wof:placetype":"venue"
},
  "geometry": {"coordinates":[-76.571155,36.737438],"type":"Point"}
}