{
  "type": "Feature",
  "properties": {
    "addr:full":"231 Raines Tavern Rd Farmville VA 23901",
    "addr:housenumber":"231",
    "addr:postcode":"23901",
    "addr:street":"Raines Tavern Rd",
    "iso:country":"US",
    "sg:address":"231 Raines Tavern Rd",
    "sg:city":"Farmville",
    "sg:classifiers":[
        {
            "category":"Building & Trades",
            "subcategory":"Construction",
            "type":"Services"
        }
    ],
    "sg:phone":"+1 434 392 3695",
    "sg:postcode":"23901",
    "sg:province":"VA",
    "sg:tags":[
        "contractor"
    ],
    "wof:name":"Troyer Custom Cnstr & Masnry",
    "wof:placetype":"venue"
},
  "geometry": {"coordinates":[-78.397233,37.370736],"type":"Point"}
}