{
  "type": "Feature",
  "properties": {
    "addr:full":"6407 Mechanicsville Tpke Mechanicsville VA 23111",
    "addr:housenumber":"6407",
    "addr:postcode":"23111",
    "addr:street":"Mechanicsville Tpke",
    "iso:country":"US",
    "sg:address":"6407 Mechanicsville Tpke",
    "sg:city":"Mechanicsville",
    "sg:classifiers":[
        {
            "category":"Insurance",
            "subcategory":"Insurance Agent",
            "type":"Services"
        }
    ],
    "sg:phone":"+1 804 559 9178",
    "sg:postcode":"23111",
    "sg:province":"VA",
    "wof:name":"Tucker Franklin Insurance Grp",
    "wof:placetype":"venue"
},
  "geometry": {"coordinates":[-77.324657,37.615037],"type":"Point"}
}