{
  "type": "Feature",
  "properties": {
    "iso:country":"US",
    "sg:address":"716 Hardy Rd",
    "sg:city":"Vinton",
    "sg:classifiers":[
        {
            "category":"Restaurant",
            "type":"Food & Drink"
        }
    ],
    "sg:menulink":"http://www.allmenus.com/va/vinton/218485-burger-king/menu/",
    "sg:phone":"+1 703 345 4051",
    "sg:postcode":"24179",
    "sg:province":"VA",
    "sg:tags":[
        "american"
    ],
    "wof:name":"Burger King",
    "wof:placetype":"venue"
},
  "geometry": {"coordinates":[-79.890765,37.273364],"type":"Point"}
}