{
  "type": "Feature",
  "properties": {
    "iso:country":"US",
    "sg:address":"4019 Granby St",
    "sg:city":"Norfolk",
    "sg:classifiers":[
        {
            "category":"Restaurant",
            "type":"Food & Drink"
        }
    ],
    "sg:phone":"+1 757 626 0871",
    "sg:postcode":"23504",
    "sg:province":"VA",
    "sg:tags":[
        "eating"
    ],
    "wof:name":"Tabb's At Riverview",
    "wof:placetype":"venue"
},
  "geometry": {"coordinates":[-76.28168700000001,36.883808],"type":"Point"}
}