{
  "type": "Feature",
  "properties": {
    "addr:full":"217 S Pollard St Vinton VA 24179",
    "addr:housenumber":"217",
    "addr:postcode":"24179",
    "addr:street":"S Pollard St",
    "iso:country":"US",
    "sg:address":"217 S Pollard St",
    "sg:city":"Vinton",
    "sg:classifiers":[
        {
            "category":"Food & Beverages",
            "subcategory":"Groceries & Convenience Stores",
            "type":"Retail Goods"
        }
    ],
    "sg:phone":"+1 540 343 9677",
    "sg:postcode":"24179",
    "sg:province":"VA",
    "wof:name":"Azteca De Oro",
    "wof:placetype":"venue"
},
  "geometry": {"coordinates":[-79.897842,37.27969],"type":"Point"}
}