{
  "type": "Feature",
  "properties": {
    "addr:full":"1096 Virginia Beach Blvd Virginia Beach VA 23451",
    "addr:housenumber":"1096",
    "addr:postcode":"23451",
    "addr:street":"Virginia Beach Blvd",
    "iso:country":"US",
    "sg:address":"1096 Virginia Beach Blvd",
    "sg:city":"Virginia Beach",
    "sg:classifiers":[
        {
            "category":"Autos & Motor Vehicles",
            "subcategory":"Auto Supplies",
            "type":"Retail Goods"
        }
    ],
    "sg:phone":"+1 757 422 8473",
    "sg:postcode":"23451",
    "sg:province":"VA",
    "sg:tags":[
        "tire"
    ],
    "wof:name":"Ronnie's Tires & Rims",
    "wof:placetype":"venue"
},
  "geometry": {"coordinates":[-75.994415,36.841826],"type":"Point"}
}