{
  "type": "Feature",
  "properties": {
    "addr:full":"234 W Broad St Falls Church VA 22046",
    "addr:housenumber":"234",
    "addr:postcode":"22046",
    "addr:street":"W Broad St",
    "iso:country":"US",
    "sg:address":"234 W Broad St",
    "sg:city":"Falls Church",
    "sg:classifiers":[
        {
            "category":"Shopping",
            "subcategory":"Optical Goods",
            "type":"Retail Goods"
        }
    ],
    "sg:phone":"+1 703 241 0778",
    "sg:postcode":"22046",
    "sg:province":"VA",
    "wof:name":"For Eyes Optical Co",
    "wof:placetype":"venue"
},
  "geometry": {"coordinates":[-77.172996,38.883498],"type":"Point"}
}