{
  "type": "Feature",
  "properties": {
    "iso:country":"US",
    "sg:address":"3556 Dam Neck Rd",
    "sg:city":"Virginia Beach",
    "sg:classifiers":[
        {
            "category":"Government",
            "subcategory":"Office",
            "type":"Public Place"
        }
    ],
    "sg:phone":"+1 757 563 1470",
    "sg:postcode":"23453",
    "sg:province":"VA",
    "sg:tags":[
        "village"
    ],
    "wof:name":"Virginia Beach Bridge Mntnc",
    "wof:placetype":"venue"
},
  "geometry": {"coordinates":[-76.087219,36.77793],"type":"Point"}
}