{
  "type": "Feature",
  "properties": {
    "addr:full":"9117 Westerholme Way Vienna VA 22182",
    "addr:housenumber":"9117",
    "addr:postcode":"22182",
    "addr:street":"Westerholme Way",
    "iso:country":"US",
    "sg:address":"9117 Westerholme Way",
    "sg:city":"Vienna",
    "sg:classifiers":[
        {
            "category":"Recreation",
            "type":"Entertainment"
        }
    ],
    "sg:phone":"+1 703 938 0858",
    "sg:postcode":"22182",
    "sg:province":"VA",
    "sg:tags":[
        "pool",
        "swimming"
    ],
    "wof:name":"Cardinal Hill Swim & Racquet",
    "wof:placetype":"venue"
},
  "geometry": {"coordinates":[-77.261222,38.922112],"type":"Point"}
}