{
  "type": "Feature",
  "properties": {
    "iso:country":"US",
    "sg:address":"208 N Providence Rd",
    "sg:city":"Richmond",
    "sg:classifiers":[
        {
            "category":"Social Services",
            "subcategory":"Child Care",
            "type":"Services"
        }
    ],
    "sg:phone":"+1 804 560 7808",
    "sg:postcode":"23235",
    "sg:province":"VA",
    "sg:tags":[
        "day"
    ],
    "sg:website":"http://www.learning-playhouse.net",
    "wof:name":"Learning Playhouse",
    "wof:placetype":"venue"
},
  "geometry": {"coordinates":[-77.547434,37.499086],"type":"Point"}
}