{
  "type": "Feature",
  "properties": {
    "addr:full":"3541 W Braddock Rd Alexandria VA 22302",
    "addr:housenumber":"3541",
    "addr:postcode":"22302",
    "addr:street":"W Braddock Rd",
    "iso:country":"US",
    "sg:address":"3541 W Braddock Rd",
    "sg:city":"Alexandria",
    "sg:classifiers":[
        {
            "category":"Real Estate",
            "subcategory":"Real Estate Services",
            "type":"Services"
        },
        {
            "category":"Banks & Credit Unions",
            "subcategory":"Financial Services",
            "type":"Services"
        },
        {
            "category":"Real Estate",
            "subcategory":"Real Estate Agent",
            "type":"Services"
        }
    ],
    "sg:phone":"+1 703 740 9174",
    "sg:postcode":"22302",
    "sg:province":"VA",
    "sg:tags":[
        "broker",
        "mortgage"
    ],
    "sg:website":"www.homepreviewtoday.com",
    "wof:name":"Weichert Realtors",
    "wof:placetype":"venue"
},
  "geometry": {"coordinates":[-77.09074699999999,38.827395],"type":"Point"}
}