{
  "type": "Feature",
  "properties": {
    "addr:full":"9306 Shiloh Dr Richmond VA 23237",
    "addr:housenumber":"9306",
    "addr:postcode":"23237",
    "addr:street":"Shiloh Dr",
    "iso:country":"US",
    "sg:address":"9306 Shiloh Dr",
    "sg:city":"Richmond",
    "sg:classifiers":[
        {
            "category":"Organizations",
            "subcategory":"Religious Organization",
            "type":"Services"
        }
    ],
    "sg:phone":"+1 804 748 9893",
    "sg:postcode":"23237",
    "sg:province":"VA",
    "wof:name":"Salt & Light Ministries",
    "wof:placetype":"venue"
},
  "geometry": {"coordinates":[-77.47054900000001,37.387303],"type":"Point"}
}