{
  "type": "Feature",
  "properties": {
    "iso:country":"US",
    "sg:address":"4596 Gilbert Station Rd",
    "sg:city":"Barboursville",
    "sg:classifiers":[
        {
            "category":"Professional",
            "subcategory":"Business Services",
            "type":"Services"
        }
    ],
    "sg:phone":"+1 434 973 1435",
    "sg:postcode":"22923",
    "sg:province":"VA",
    "sg:tags":[
        "transcribing",
        "disc"
    ],
    "wof:name":"Word Work",
    "wof:placetype":"venue"
},
  "geometry": {"coordinates":[-78.37232299999999,38.161991],"type":"Point"}
}