{
  "type": "Feature",
  "properties": {
    "addr:full":"570 Industrial Park Dr Newport News VA 23608",
    "addr:housenumber":"570",
    "addr:postcode":"23608",
    "addr:street":"Industrial Park Dr",
    "iso:country":"US",
    "sg:address":"570 Industrial Park Dr",
    "sg:city":"Newport News",
    "sg:classifiers":[
        {
            "category":"Building & Trades",
            "subcategory":"Electrical",
            "type":"Services"
        }
    ],
    "sg:phone":"+1 757 875 5820",
    "sg:postcode":"23608",
    "sg:province":"VA",
    "sg:tags":[
        "electrical",
        "contractor"
    ],
    "wof:name":"Jarrett Gary Electrical Htg",
    "wof:placetype":"venue"
},
  "geometry": {"coordinates":[-76.542839,37.16213],"type":"Point"}
}