{
  "type": "Feature",
  "properties": {
    "iso:country":"US",
    "sg:address":"806 Meads Ct",
    "sg:city":"Chesapeake",
    "sg:classifiers":[
        {
            "category":"Manufacturing",
            "subcategory":"Watercraft",
            "type":"Manufacturing & Wholesale Goods"
        }
    ],
    "sg:phone":"+1 757 487 5100",
    "sg:postcode":"23323",
    "sg:province":"VA",
    "sg:tags":[
        "automotive",
        "repair",
        "utility"
    ],
    "wof:name":"Container-Care Virginia",
    "wof:placetype":"venue"
},
  "geometry": {"coordinates":[-76.349059,36.769862],"type":"Point"}
}