{
  "type": "Feature",
  "properties": {
    "addr:full":"747 Hunters Quay Chesapeake VA 23320",
    "addr:housenumber":"747",
    "addr:postcode":"23320",
    "addr:street":"Hunters Quay",
    "iso:country":"US",
    "sg:address":"747 Hunters Quay",
    "sg:city":"Chesapeake",
    "sg:classifiers":[
        {
            "category":"Real Estate",
            "subcategory":"Real Estate Agent",
            "type":"Services"
        }
    ],
    "sg:phone":"+1 757 410 3167",
    "sg:postcode":"23320",
    "sg:province":"VA",
    "sg:tags":[
        "developer"
    ],
    "wof:name":"Eds LLC",
    "wof:placetype":"venue"
},
  "geometry": {"coordinates":[-76.26973,36.753633],"type":"Point"}
}