{
  "type": "Feature",
  "properties": {
    "iso:country":"US",
    "sg:address":"1131 5th St SW",
    "sg:city":"Charlottesville",
    "sg:classifiers":[
        {
            "category":"Building & Trades",
            "subcategory":"Locksmith",
            "type":"Services"
        }
    ],
    "sg:phone":"+1 434 422 9208",
    "sg:postcode":"22902",
    "sg:province":"VA",
    "sg:tags":[
        "key"
    ],
    "wof:name":"A 1 Locksmith Services",
    "wof:placetype":"venue"
},
  "geometry": {"coordinates":[-78.500817,38.014085],"type":"Point"}
}