{
  "type": "Feature",
  "properties": {
    "addr:full":"3041 Scottsville Rd Charlottesville VA 22902",
    "addr:housenumber":"3041",
    "addr:postcode":"22902",
    "addr:street":"Scottsville Rd",
    "iso:country":"US",
    "sg:address":"3041 Scottsville Rd",
    "sg:city":"Charlottesville",
    "sg:classifiers":[
        {
            "category":"Building & Trades",
            "subcategory":"Construction",
            "type":"Services"
        }
    ],
    "sg:phone":"+1 434 296 6881",
    "sg:postcode":"22902",
    "sg:province":"VA",
    "sg:tags":[
        "hanging",
        "contractor"
    ],
    "wof:name":"Herring Painting & Roofing",
    "wof:placetype":"venue"
},
  "geometry": {"coordinates":[-78.530716,37.952853],"type":"Point"}
}