{
  "type": "Feature",
  "properties": {
    "iso:country":"US",
    "sg:address":"18013 Forest Rd",
    "sg:city":"Forest",
    "sg:classifiers":[
        {
            "category":"Banks & Credit Unions",
            "subcategory":"Bank",
            "type":"Services"
        }
    ],
    "sg:phone":"+1 434 385 6680",
    "sg:postcode":"24551",
    "sg:province":"VA",
    "sg:tags":[
        "banker",
        "mortgage"
    ],
    "wof:name":"Countrywide",
    "wof:placetype":"venue"
},
  "geometry": {"coordinates":[-79.248717,37.376793],"type":"Point"}
}