{
  "type": "Feature",
  "properties": {
    "addr:full":"9412 Warwick Blvd Newport News VA 23601",
    "addr:housenumber":"9412",
    "addr:postcode":"23601",
    "addr:street":"Warwick Blvd",
    "iso:country":"US",
    "sg:address":"9412 Warwick Blvd",
    "sg:city":"Newport News",
    "sg:classifiers":[
        {
            "category":"Retail",
            "subcategory":"Auto Repair",
            "type":"Services"
        }
    ],
    "sg:phone":"+1 757 599 5823",
    "sg:postcode":"23601",
    "sg:province":"VA",
    "sg:tags":[
        "repairing",
        "automobile"
    ],
    "wof:name":"Stirling's Auto Repair",
    "wof:placetype":"venue"
},
  "geometry": {"coordinates":[-76.453625,37.023294],"type":"Point"}
}