{
  "type": "Feature",
  "properties": {
    "iso:country":"US",
    "sg:address":"1207 Monocan Dr",
    "sg:city":"Nellysford",
    "sg:classifiers":[
        {
            "category":"Professional",
            "subcategory":"Art Services",
            "type":"Services"
        }
    ],
    "sg:phone":"+1 434 979 7889",
    "sg:postcode":"22958",
    "sg:province":"VA",
    "sg:tags":[
        "commercial",
        "c",
        "computer",
        "design",
        "system"
    ],
    "wof:name":"Campbell Associates Inc",
    "wof:placetype":"venue"
},
  "geometry": {"coordinates":[-78.883297,37.900749],"type":"Point"}
}