{
  "type": "Feature",
  "properties": {
    "addr:full":"1816 Main St Victoria VA 23974",
    "addr:housenumber":"1816",
    "addr:postcode":"23974",
    "addr:street":"Main St",
    "iso:country":"US",
    "sg:address":"1816 Main St",
    "sg:city":"Victoria",
    "sg:classifiers":[
        {
            "category":"Home & Garden",
            "subcategory":"Carpets & Floor Coverings",
            "type":"Retail Goods"
        }
    ],
    "sg:phone":"+1 434 696 2609",
    "sg:postcode":"23974",
    "sg:province":"VA",
    "sg:tags":[
        "dealer",
        "rug"
    ],
    "wof:name":"Southside Furniture Inc",
    "wof:placetype":"venue"
},
  "geometry": {"coordinates":[-78.227054,36.994568],"type":"Point"}
}