{
  "type": "Feature",
  "properties": {
    "addr:full":"209 4th St Clarksville VA 23927",
    "addr:housenumber":"209",
    "addr:postcode":"23927",
    "addr:street":"4Th St",
    "iso:country":"US",
    "sg:address":"209 4th St",
    "sg:city":"Clarksville",
    "sg:classifiers":[
        {
            "category":"Organizations",
            "subcategory":"Religious Organization",
            "type":"Services"
        }
    ],
    "sg:phone":"+1 434 374 4611",
    "sg:postcode":"23927",
    "sg:province":"VA",
    "sg:tags":[
        "church"
    ],
    "wof:name":"Second Baptist Church",
    "wof:placetype":"venue"
},
  "geometry": {"coordinates":[-78.55584500000001,36.624126],"type":"Point"}
}