{
  "type": "Feature",
  "properties": {
    "addr:full":"1956 Hayes Rd Gloucester Point VA 23062",
    "addr:housenumber":"1956",
    "addr:postcode":"23062",
    "addr:street":"Hayes Rd",
    "iso:country":"US",
    "sg:address":"1956 Hayes Rd",
    "sg:city":"Gloucester Point",
    "sg:classifiers":[
        {
            "category":"Personal",
            "subcategory":"Beauty Salon",
            "type":"Services"
        }
    ],
    "sg:phone":"+1 804 642 7523",
    "sg:postcode":"23062",
    "sg:province":"VA",
    "sg:tags":[
        "shop"
    ],
    "wof:name":"Head To Toes",
    "wof:placetype":"venue"
},
  "geometry": {"coordinates":[-76.495104,37.262926],"type":"Point"}
}