{
  "type": "Feature",
  "properties": {
    "addr:full":"4175 Bell Ridge Ct Chantilly VA 20151",
    "addr:housenumber":"4175",
    "addr:postcode":"20151",
    "addr:street":"Bell Ridge Ct",
    "iso:country":"US",
    "sg:address":"4175 Bell Ridge Ct",
    "sg:city":"Chantilly",
    "sg:classifiers":[
        {
            "category":"Wholesale",
            "subcategory":"Medical Equipment & Supplies",
            "type":"Manufacturing & Wholesale Goods"
        }
    ],
    "sg:phone":"+1 703 263 9522",
    "sg:postcode":"20151",
    "sg:province":"VA",
    "sg:tags":[
        "physician",
        "surgeon"
    ],
    "wof:name":"Alliance Medical",
    "wof:placetype":"venue"
},
  "geometry": {"coordinates":[-77.431144,38.888807],"type":"Point"}
}