{
  "type": "Feature",
  "properties": {
    "iso:country":"US",
    "sg:address":"6718 Whittier Ave",
    "sg:city":"Mc Lean",
    "sg:classifiers":[
        {
            "category":"Real Estate",
            "subcategory":"Developer",
            "type":"Services"
        }
    ],
    "sg:phone":"+1 703 356 8800",
    "sg:postcode":"22101",
    "sg:province":"VA",
    "sg:tags":[
        "property",
        "commercial"
    ],
    "wof:name":"Young Group Inc",
    "wof:placetype":"venue"
},
  "geometry": {"coordinates":[-77.177789,38.931171],"type":"Point"}
}