{
  "type": "Feature",
  "properties": {
    "iso:country":"US",
    "sg:address":"13227 Delaney Rd",
    "sg:city":"Woodbridge",
    "sg:classifiers":[
        {
            "category":"Manufacturing",
            "subcategory":"Building Materials",
            "type":"Manufacturing & Wholesale Goods"
        },
        {
            "category":"Building & Trades",
            "subcategory":"Construction",
            "type":"Services"
        }
    ],
    "sg:phone":"+1 703 590 1642",
    "sg:postcode":"22193",
    "sg:province":"VA",
    "sg:tags":[
        "mfg",
        "carpentry",
        "contractor",
        "woodworker"
    ],
    "wof:name":"Bob's Creative Woodworking",
    "wof:placetype":"venue"
},
  "geometry": {"coordinates":[-77.35324799999999,38.66502],"type":"Point"}
}