{
  "type": "Feature",
  "properties": {
    "addr:full":"9680 Osborne Tpke Richmond VA 23231",
    "addr:housenumber":"9680",
    "addr:postcode":"23231",
    "addr:street":"Osborne Tpke",
    "iso:country":"US",
    "sg:address":"9680 Osborne Tpke",
    "sg:city":"Richmond",
    "sg:classifiers":[
        {
            "category":"Autos & Motor Vehicles",
            "subcategory":"Boat Sales",
            "type":"Retail Goods"
        },
        {
            "category":"Recreation",
            "subcategory":"Marina",
            "type":"Entertainment"
        }
    ],
    "sg:phone":"+1 804 795 1213",
    "sg:postcode":"23231",
    "sg:province":"VA",
    "sg:tags":[
        "a",
        "as",
        "sales",
        "dealer",
        "operates"
    ],
    "wof:name":"Kingsland Reach Marina LLC",
    "wof:placetype":"venue"
},
  "geometry": {"coordinates":[-77.38108099999999,37.398858],"type":"Point"}
}