{
  "type": "Feature",
  "properties": {
    "addr:full":"2210 Belle Haven Rd Alexandria VA 22307",
    "addr:housenumber":"2210",
    "addr:postcode":"22307",
    "addr:street":"Belle Haven Rd",
    "iso:country":"US",
    "sg:address":"2210 Belle Haven Rd",
    "sg:city":"Alexandria",
    "sg:classifiers":[
        {
            "category":"Professional",
            "type":"Services"
        }
    ],
    "sg:phone":"+1 703 960 9626",
    "sg:postcode":"22307",
    "sg:province":"VA",
    "sg:tags":[
        "establishment"
    ],
    "wof:name":"Fairfax House Intl",
    "wof:placetype":"venue"
},
  "geometry": {"coordinates":[-77.066937,38.781013],"type":"Point"}
}