{
  "type": "Feature",
  "properties": {
    "addr:full":"1301 S Arlington Ridge Rd Arlington VA 22202",
    "addr:housenumber":"1301",
    "addr:postcode":"22202",
    "addr:street":"S Arlington Ridge Rd",
    "iso:country":"US",
    "sg:address":"1301 S Arlington Ridge Rd",
    "sg:city":"Arlington",
    "sg:classifiers":[
        {
            "category":"Professional",
            "type":"Services"
        }
    ],
    "sg:phone":"+1 703 920 0783",
    "sg:postcode":"22202",
    "sg:province":"VA",
    "wof:name":"Rainbow Surfer Inst",
    "wof:placetype":"venue"
},
  "geometry": {"coordinates":[-77.066282,38.863082],"type":"Point"}
}