{
  "type": "Feature",
  "properties": {
    "addr:full":"4007 Burdette Rd Carrsville VA 23315",
    "addr:housenumber":"4007",
    "addr:postcode":"23315",
    "addr:street":"Burdette Rd",
    "iso:country":"US",
    "sg:address":"4007 Burdette Rd",
    "sg:city":"Carrsville",
    "sg:classifiers":[
        {
            "category":"Social Services",
            "type":"Services"
        }
    ],
    "sg:phone":"+1 757 562 7270",
    "sg:postcode":"23315",
    "sg:province":"VA",
    "wof:name":"Correctional Services Corp",
    "wof:placetype":"venue"
},
  "geometry": {"coordinates":[-76.86081,36.765466],"type":"Point"}
}