{
  "type": "Feature",
  "properties": {
    "addr:full":"255 Kent Cove Ln Kilmarnock VA 22482",
    "addr:housenumber":"255",
    "addr:postcode":"22482",
    "addr:street":"Kent Cove Ln",
    "iso:country":"US",
    "sg:address":"255 Kent Cove Ln",
    "sg:city":"Kilmarnock",
    "sg:classifiers":[
        {
            "category":"Shopping",
            "subcategory":"Computers & Home Electronics",
            "type":"Retail Goods"
        }
    ],
    "sg:phone":"+1 804 436 9119",
    "sg:postcode":"22482",
    "sg:province":"VA",
    "wof:name":"Marine Installation Inc",
    "wof:placetype":"venue"
},
  "geometry": {"coordinates":[-76.325326,37.72114],"type":"Point"}
}