{
  "type": "Feature",
  "properties": {
    "iso:country":"US",
    "sg:address":"7308 Pullen Dr",
    "sg:city":"Fredericksburg",
    "sg:classifiers":[
        {
            "category":"Real Estate",
            "subcategory":"Real Estate Operator",
            "type":"Services"
        }
    ],
    "sg:phone":"+1 540 786 1576",
    "sg:postcode":"22407",
    "sg:province":"VA",
    "sg:tags":[
        "property",
        "lessor"
    ],
    "wof:name":"Collins John",
    "wof:placetype":"venue"
},
  "geometry": {"coordinates":[-77.590935,38.281355],"type":"Point"}
}