{
  "type": "Feature",
  "properties": {
    "addr:full":"4418 Sandy Valley Rd Mechanicsville VA 23111",
    "addr:housenumber":"4418",
    "addr:postcode":"23111",
    "addr:street":"Sandy Valley Rd",
    "iso:country":"US",
    "sg:address":"4418 Sandy Valley Rd",
    "sg:city":"Mechanicsville",
    "sg:classifiers":[
        {
            "category":"Shopping",
            "subcategory":"Comic Books",
            "type":"Retail Goods"
        }
    ],
    "sg:phone":"+1 804 781 6831",
    "sg:postcode":"23111",
    "sg:province":"VA",
    "wof:name":"Coruscant Enterprises",
    "wof:placetype":"venue"
},
  "geometry": {"coordinates":[-77.25788799999999,37.617702],"type":"Point"}
}