{
  "type": "Feature",
  "properties": {
    "iso:country":"US",
    "sg:address":"12512 Second Branch Rd",
    "sg:city":"Chesterfield",
    "sg:classifiers":[
        {
            "category":"Arts & Performance",
            "subcategory":"Theater",
            "type":"Entertainment"
        }
    ],
    "sg:phone":"+1 804 639 2569",
    "sg:postcode":"23838",
    "sg:province":"VA",
    "sg:tags":[
        "group"
    ],
    "wof:name":"Dimples & Honee-Be Clowns",
    "wof:placetype":"venue"
},
  "geometry": {"coordinates":[-77.638487,37.330157],"type":"Point"}
}