{
  "type": "Feature",
  "properties": {
    "iso:country":"US",
    "sg:address":"3919 Pruett Dr",
    "sg:city":"Hopewell",
    "sg:classifiers":[
        {
            "category":"Insurance",
            "subcategory":"Insurance Agent",
            "type":"Services"
        }
    ],
    "sg:phone":"+1 804 541 0249",
    "sg:postcode":"23860",
    "sg:province":"VA",
    "wof:name":"Divas 4 Life Ladies Social CLB",
    "wof:placetype":"venue"
},
  "geometry": {"coordinates":[-77.313385,37.264454],"type":"Point"}
}