{
  "type": "Feature",
  "properties": {
    "addr:full":"410 Park Ave Farmville VA 23901",
    "addr:housenumber":"410",
    "addr:postcode":"23901",
    "addr:street":"Park Ave",
    "iso:country":"US",
    "sg:address":"410 Park Ave",
    "sg:city":"Farmville",
    "sg:classifiers":[
        {
            "category":"Social Services",
            "type":"Services"
        }
    ],
    "sg:phone":"+1 434 392 8526",
    "sg:postcode":"23901",
    "sg:province":"VA",
    "wof:name":"Youth Empowerment Center Inc",
    "wof:placetype":"venue"
},
  "geometry": {"coordinates":[-78.38664199999999,37.30375],"type":"Point"}
}