{
  "type": "Feature",
  "properties": {
    "iso:country":"US",
    "sg:address":"1516 Johnstons Rd",
    "sg:city":"Norfolk",
    "sg:classifiers":[
        {
            "category":"Organizations",
            "subcategory":"Religious Organization",
            "type":"Services"
        }
    ],
    "sg:phone":"+1 757 855 3210",
    "sg:postcode":"23518",
    "sg:province":"VA",
    "sg:tags":[
        "church"
    ],
    "wof:name":"Saint Job Cogic Mission",
    "wof:placetype":"venue"
},
  "geometry": {"coordinates":[-76.232319,36.909882],"type":"Point"}
}