{
  "type": "Feature",
  "properties": {
    "addr:full":"14142 Minnieville Rd Woodbridge VA 22193",
    "addr:housenumber":"14142",
    "addr:postcode":"22193",
    "addr:street":"Minnieville Rd",
    "iso:country":"US",
    "sg:address":"14142 Minnieville Rd",
    "sg:city":"Woodbridge",
    "sg:classifiers":[
        {
            "category":"Insurance",
            "subcategory":"Insurance Agent",
            "type":"Services"
        }
    ],
    "sg:phone":"+1 703 730 1515",
    "sg:postcode":"22193",
    "sg:province":"VA",
    "sg:website":"www.insurestor.com",
    "wof:name":"Nationwide Mutual Insurance",
    "wof:placetype":"venue"
},
  "geometry": {"coordinates":[-77.33546200000001,38.646813],"type":"Point"}
}