{
  "type": "Feature",
  "properties": {
    "addr:full":"2400 Washington Ave Newport News VA 23607",
    "addr:housenumber":"2400",
    "addr:postcode":"23607",
    "addr:street":"Washington Ave",
    "iso:country":"US",
    "sg:address":"2400 Washington Ave",
    "sg:city":"Newport News",
    "sg:classifiers":[
        {
            "category":"Government",
            "subcategory":"Office",
            "type":"Public Place"
        }
    ],
    "sg:phone":"+1 757 247 8733",
    "sg:postcode":"23607",
    "sg:province":"VA",
    "sg:tags":[
        "evaluation",
        "budget"
    ],
    "wof:name":"Department Budget & Evaluation",
    "wof:placetype":"venue"
},
  "geometry": {"coordinates":[-76.430751,36.978387],"type":"Point"}
}