{
  "type": "Feature",
  "properties": {
    "addr:full":"9635 Salem St Norfolk VA 23503",
    "addr:housenumber":"9635",
    "addr:postcode":"23503",
    "addr:street":"Salem St",
    "iso:country":"US",
    "sg:address":"9635 Salem St",
    "sg:city":"Norfolk",
    "sg:classifiers":[
        {
            "category":"Professional",
            "subcategory":"Business Services",
            "type":"Services"
        }
    ],
    "sg:phone":"+1 757 480 5330",
    "sg:postcode":"23503",
    "sg:province":"VA",
    "wof:name":"K A D K A Marketing Services",
    "wof:placetype":"venue"
},
  "geometry": {"coordinates":[-76.27677799999999,36.966205],"type":"Point"}
}