{
  "type": "Feature",
  "properties": {
    "addr:full":"18243 Forest Rd Lynchburg VA 24502",
    "addr:housenumber":"18243",
    "addr:postcode":"24502",
    "addr:street":"Forest Rd",
    "iso:country":"US",
    "sg:address":"18243 Forest Rd",
    "sg:city":"Lynchburg",
    "sg:classifiers":[
        {
            "category":"Shopping",
            "subcategory":"Clothing, Apparel, & Fashions",
            "type":"Retail Goods"
        }
    ],
    "sg:phone":"+1 434 455 3036",
    "sg:postcode":"24502",
    "sg:province":"VA",
    "sg:tags":[
        "infant",
        "wear"
    ],
    "wof:name":"Mother Goose",
    "wof:placetype":"venue"
},
  "geometry": {"coordinates":[-79.247066,37.380499],"type":"Point"}
}