{
  "type": "Feature",
  "properties": {
    "addr:full":"3001 Park Center Dr Alexandria VA 22302",
    "addr:housenumber":"3001",
    "addr:postcode":"22302",
    "addr:street":"Park Center Dr",
    "iso:country":"US",
    "sg:address":"3001 Park Center Dr",
    "sg:city":"Alexandria",
    "sg:classifiers":[
        {
            "category":"Professional",
            "subcategory":"Management & Consulting",
            "type":"Services"
        }
    ],
    "sg:phone":"+1 703 820 7901",
    "sg:postcode":"22302",
    "sg:province":"VA",
    "wof:name":"Allen & Lockhart",
    "wof:placetype":"venue"
},
  "geometry": {"coordinates":[-77.103556,38.835862],"type":"Point"}
}