{
  "type": "Feature",
  "properties": {
    "addr:full":"3330 N Washington Blvd Arlington VA 22201",
    "addr:housenumber":"3330",
    "addr:postcode":"22201",
    "addr:street":"N Washington Blvd",
    "iso:country":"US",
    "sg:address":"3330 N Washington Blvd",
    "sg:city":"Arlington",
    "sg:classifiers":[
        {
            "category":"Organizations",
            "subcategory":"Non-profit Organization",
            "type":"Services"
        }
    ],
    "sg:phone":"+1 703 294 6596",
    "sg:postcode":"22201",
    "sg:province":"VA",
    "wof:name":"National Center On Nonprofit",
    "wof:placetype":"venue"
},
  "geometry": {"coordinates":[-77.099914,38.885893],"type":"Point"}
}