{
  "type": "Feature",
  "properties": {
    "addr:full":"44845 Falcon Pl Sterling VA 20166",
    "addr:housenumber":"44845",
    "addr:postcode":"20166",
    "addr:street":"Falcon Pl",
    "iso:country":"US",
    "sg:address":"44845 Falcon Pl",
    "sg:city":"Sterling",
    "sg:classifiers":[
        {
            "category":"Professional",
            "type":"Services"
        }
    ],
    "sg:phone":"+1 703 736 9600",
    "sg:postcode":"20166",
    "sg:province":"VA",
    "wof:name":"Marvin Window & Door Showplace",
    "wof:placetype":"venue"
},
  "geometry": {"coordinates":[-77.448615,38.979537],"type":"Point"}
}