{
  "type": "Feature",
  "properties": {
    "addr:full":"2916 Cessna Dr Virginia Beach VA 23452",
    "addr:housenumber":"2916",
    "addr:postcode":"23452",
    "addr:street":"Cessna Dr",
    "iso:country":"US",
    "sg:address":"2916 Cessna Dr",
    "sg:city":"Virginia Beach",
    "sg:classifiers":[
        {
            "category":"Retail",
            "subcategory":"Portrait Studio",
            "type":"Services"
        }
    ],
    "sg:phone":"+1 757 486 8779",
    "sg:postcode":"23452",
    "sg:province":"VA",
    "sg:tags":[
        "photo"
    ],
    "wof:name":"Dee Akright Photographers",
    "wof:placetype":"venue"
},
  "geometry": {"coordinates":[-76.075461,36.846479],"type":"Point"}
}