{
  "type": "Feature",
  "properties": {
    "addr:full":"4680 Monticello Ave Williamsburg VA 23188",
    "addr:housenumber":"4680",
    "addr:postcode":"23188",
    "addr:street":"Monticello Ave",
    "iso:country":"US",
    "sg:address":"4680 Monticello Ave",
    "sg:city":"Williamsburg",
    "sg:classifiers":[
        {
            "category":"Health Services",
            "subcategory":"Doctor",
            "type":"Services"
        }
    ],
    "sg:phone":"+1 757 258 1042",
    "sg:postcode":"23188",
    "sg:province":"VA",
    "sg:tags":[
        "dentist"
    ],
    "wof:name":"Sam E English & Assoc",
    "wof:placetype":"venue"
},
  "geometry": {"coordinates":[-76.756912,37.270431],"type":"Point"}
}