{
  "type": "Feature",
  "properties": {
    "addr:full":"405 Glenn Dr Sterling VA 20164",
    "addr:housenumber":"405",
    "addr:postcode":"20164",
    "addr:street":"Glenn Dr",
    "iso:country":"US",
    "sg:address":"405 Glenn Dr",
    "sg:city":"Sterling",
    "sg:classifiers":[
        {
            "category":"Shopping",
            "subcategory":"Computers & Home Electronics",
            "type":"Retail Goods"
        }
    ],
    "sg:phone":"+1 703 421 0300",
    "sg:postcode":"20164",
    "sg:province":"VA",
    "sg:tags":[
        "equipment",
        "dealer"
    ],
    "sg:website":"www.digitek.com",
    "wof:name":"Digitek Computer Products Inc",
    "wof:placetype":"venue"
},
  "geometry": {"coordinates":[-77.42677999999999,38.996357],"type":"Point"}
}