{
  "type": "Feature",
  "properties": {
    "iso:country":"US",
    "sg:address":"10266 Main St",
    "sg:city":"Fairfax",
    "sg:classifiers":[
        {
            "category":"Restaurant",
            "type":"Food & Drink"
        }
    ],
    "sg:menulink":"http://www.allmenus.com/va/fairfax/283892-coyote-grille--cantina/menu/",
    "sg:phone":"+1 703 591 0006",
    "sg:postcode":"22030",
    "sg:province":"VA",
    "sg:tags":[
        "american",
        "southwestern"
    ],
    "wof:name":"Coyote Grille & Cantina",
    "wof:placetype":"venue"
},
  "geometry": {"coordinates":[-77.301221,38.845301],"type":"Point"}
}