{
  "type": "Feature",
  "properties": {
    "addr:full":"1751 Pinnacle Dr Mc Lean VA 22102",
    "addr:housenumber":"1751",
    "addr:postcode":"22102",
    "addr:street":"Pinnacle Dr",
    "iso:country":"US",
    "sg:address":"1751 Pinnacle Dr",
    "sg:city":"Mc Lean",
    "sg:classifiers":[
        {
            "category":"Professional",
            "type":"Services"
        }
    ],
    "sg:phone":"+1 703 610 8675",
    "sg:postcode":"22102",
    "sg:province":"VA",
    "wof:name":"Howard Kelly",
    "wof:placetype":"venue"
},
  "geometry": {"coordinates":[-77.231658,38.920232],"type":"Point"}
}