{
  "type": "Feature",
  "properties": {
    "iso:country":"US",
    "sg:address":"2038 Midshipman Dr",
    "sg:city":"Stafford",
    "sg:classifiers":[
        {
            "category":"Retail",
            "subcategory":"Repair Shop",
            "type":"Services"
        }
    ],
    "sg:phone":"+1 540 657 6911",
    "sg:postcode":"22554",
    "sg:province":"VA",
    "sg:tags":[
        "boiler",
        "heating"
    ],
    "wof:name":"Precision Mechanical Service",
    "wof:placetype":"venue"
},
  "geometry": {"coordinates":[-77.369888,38.466963],"type":"Point"}
}