{
  "type": "Feature",
  "properties": {
    "iso:country":"US",
    "sg:address":"4025 Gallows Rd",
    "sg:city":"Annandale",
    "sg:classifiers":[
        {
            "category":"Arts & Performance",
            "subcategory":"Music",
            "type":"Entertainment"
        }
    ],
    "sg:phone":"+1 703 593 6187",
    "sg:postcode":"22003",
    "sg:province":"VA",
    "sg:tags":[
        "jockey",
        "disc"
    ],
    "wof:name":"Mario Macias",
    "wof:placetype":"venue"
},
  "geometry": {"coordinates":[-77.190258,38.836351],"type":"Point"}
}