{
  "type": "Feature",
  "properties": {
    "addr:full":"315 Leeward Way Newport News VA 23601",
    "addr:housenumber":"315",
    "addr:postcode":"23601",
    "addr:street":"Leeward Way",
    "iso:country":"US",
    "sg:address":"315 Leeward Way",
    "sg:city":"Newport News",
    "sg:classifiers":[
        {
            "category":"Professional",
            "type":"Services"
        }
    ],
    "sg:phone":"+1 757 223 1749",
    "sg:postcode":"23601",
    "sg:province":"VA",
    "wof:name":"Leslie H Halstead",
    "wof:placetype":"venue"
},
  "geometry": {"coordinates":[-76.451291,37.094157],"type":"Point"}
}