{
  "type": "Feature",
  "properties": {
    "iso:country":"US",
    "sg:address":"8500 Leesburg Pike",
    "sg:city":"Vienna",
    "sg:classifiers":[
        {
            "category":"Professional",
            "subcategory":"Management & Consulting",
            "type":"Services"
        }
    ],
    "sg:phone":"+1 703 893 1456",
    "sg:postcode":"22182",
    "sg:province":"VA",
    "sg:tags":[
        "consultant",
        "business"
    ],
    "wof:name":"Cheiron",
    "wof:placetype":"venue"
},
  "geometry": {"coordinates":[-77.23980299999999,38.927435],"type":"Point"}
}