{
  "type": "Feature",
  "properties": {
    "addr:full":"1132 Glendale Rd Galax VA 24333",
    "addr:housenumber":"1132",
    "addr:postcode":"24333",
    "addr:street":"Glendale Rd",
    "iso:country":"US",
    "sg:address":"1132 Glendale Rd",
    "sg:city":"Galax",
    "sg:classifiers":[
        {
            "category":"Building & Trades",
            "subcategory":"Cleaning & Sanitation",
            "type":"Services"
        }
    ],
    "sg:phone":"+1 276 236 6941",
    "sg:postcode":"24333",
    "sg:province":"VA",
    "sg:tags":[
        "house"
    ],
    "wof:name":"Sherry's Home & Office Clnng",
    "wof:placetype":"venue"
},
  "geometry": {"coordinates":[-80.88458199999999,36.693922],"type":"Point"}
}