{
  "type": "Feature",
  "properties": {
    "addr:full":"11186 Harbor Ct Reston VA 20191",
    "addr:housenumber":"11186",
    "addr:postcode":"20191",
    "addr:street":"Harbor Ct",
    "iso:country":"US",
    "sg:address":"11186 Harbor Ct",
    "sg:city":"Reston",
    "sg:classifiers":[
        {
            "category":"Sports & Exercise",
            "subcategory":"Gym",
            "type":"Entertainment"
        }
    ],
    "sg:phone":"+1 703 390 5811",
    "sg:postcode":"20191",
    "sg:province":"VA",
    "sg:tags":[
        "fitness",
        "physical",
        "facility"
    ],
    "wof:name":"90 Day Body Shaping Program",
    "wof:placetype":"venue"
},
  "geometry": {"coordinates":[-77.33071200000001,38.937418],"type":"Point"}
}