{
  "type": "Feature",
  "properties": {
    "addr:full":"20020 Eastside Ln Dinwiddie VA 23841",
    "addr:housenumber":"20020",
    "addr:postcode":"23841",
    "addr:street":"Eastside Ln",
    "iso:country":"US",
    "sg:address":"20020 Eastside Ln",
    "sg:city":"Dinwiddie",
    "sg:classifiers":[
        {
            "category":"Retail",
            "subcategory":"Animal Services",
            "type":"Services"
        }
    ],
    "sg:phone":"+1 804 469 7183",
    "sg:postcode":"23841",
    "sg:province":"VA",
    "sg:tags":[
        "pet",
        "grooming",
        "washing"
    ],
    "wof:name":"Kathryn's Tlc Pet Svc",
    "wof:placetype":"venue"
},
  "geometry": {"coordinates":[-77.560554,37.103873],"type":"Point"}
}