{
  "type": "Feature",
  "properties": {
    "addr:full":"635 Thompson Ridge Cl Ferrum VA 24088",
    "addr:housenumber":"635",
    "addr:postcode":"24088",
    "addr:street":"Thompson Ridge;Ferrum",
    "iso:country":"US",
    "sg:address":"635 Thompson Ridge Cl",
    "sg:city":"Ferrum",
    "sg:classifiers":[
        {
            "category":"Manufacturing",
            "subcategory":"Tools & Machinery",
            "type":"Manufacturing & Wholesale Goods"
        }
    ],
    "sg:phone":"+1 540 365 2874",
    "sg:postcode":"24088",
    "sg:province":"VA",
    "sg:tags":[
        "textile",
        "parts"
    ],
    "wof:name":"Abstruse Technical Svc Inc",
    "wof:placetype":"venue"
},
  "geometry": {"coordinates":[-80.088038,36.888751],"type":"Point"}
}