{
  "type": "Feature",
  "properties": {
    "iso:country":"US",
    "sg:address":"11325 Lee Hwy",
    "sg:city":"Fairfax",
    "sg:classifiers":[
        {
            "category":"Professional",
            "subcategory":"Detective & Security Services",
            "type":"Services"
        }
    ],
    "sg:phone":"+1 703 273 9373",
    "sg:postcode":"22030",
    "sg:province":"VA",
    "sg:tags":[
        "system"
    ],
    "wof:name":"Alarm-It",
    "wof:placetype":"venue"
},
  "geometry": {"coordinates":[-77.336839,38.851129],"type":"Point"}
}