{
  "type": "Feature",
  "properties": {
    "iso:country":"US",
    "sg:address":"12451 Hedges Run Dr",
    "sg:city":"Woodbridge",
    "sg:classifiers":[
        {
            "category":"Banks & Credit Unions",
            "subcategory":"Bank",
            "type":"Services"
        }
    ],
    "sg:phone":"+1 703 490 7139",
    "sg:postcode":"22192",
    "sg:province":"VA",
    "wof:name":"Provident Bank",
    "wof:placetype":"venue"
},
  "geometry": {"coordinates":[-77.312754,38.685546],"type":"Point"}
}