{
  "type": "Feature",
  "properties": {
    "iso:country":"US",
    "sg:address":"6904 Benjamin St",
    "sg:city":"Mc Lean",
    "sg:classifiers":[
        {
            "category":"Professional",
            "subcategory":"Business Services",
            "type":"Services"
        }
    ],
    "sg:phone":"+1 703 288 2881",
    "sg:postcode":"22101",
    "sg:province":"VA",
    "wof:name":"Pale Blue Glow Imaging PC",
    "wof:placetype":"venue"
},
  "geometry": {"coordinates":[-77.182565,38.956029],"type":"Point"}
}