{
  "type": "Feature",
  "properties": {
    "addr:full":"587 Norcross Rd Ripplemead VA 24150",
    "addr:housenumber":"587",
    "addr:postcode":"24150",
    "addr:street":"Norcross Rd",
    "iso:country":"US",
    "sg:address":"587 Norcross Rd",
    "sg:city":"Ripplemead",
    "sg:classifiers":[
        {
            "category":"Professional",
            "type":"Services"
        }
    ],
    "sg:phone":"+1 540 626 3944",
    "sg:postcode":"24150",
    "sg:province":"VA",
    "wof:name":"United Daughters of Confe",
    "wof:placetype":"venue"
},
  "geometry": {"coordinates":[-80.68649000000001,37.355697],"type":"Point"}
}