{
  "type": "Feature",
  "properties": {
    "iso:country":"US",
    "sg:address":"1225 S Jefferson Davis Hwy",
    "sg:city":"Arlington",
    "sg:classifiers":[
        {
            "category":"Professional",
            "subcategory":"Accounting & Tax Preparation",
            "type":"Services"
        }
    ],
    "sg:phone":"+1 703 486 5632",
    "sg:postcode":"22202",
    "sg:province":"VA",
    "sg:tags":[
        "bookkeeping",
        "general"
    ],
    "wof:name":"Account A Call",
    "wof:placetype":"venue"
},
  "geometry": {"coordinates":[-77.051782,38.861228],"type":"Point"}
}