{
  "type": "Feature",
  "properties": {
    "addr:full":"2504 Ridge Rd Charlottesville VA 22901",
    "addr:housenumber":"2504",
    "addr:postcode":"22901",
    "addr:street":"Ridge Rd",
    "iso:country":"US",
    "sg:address":"2504 Ridge Rd",
    "sg:city":"Charlottesville",
    "sg:classifiers":[
        {
            "category":"Social Services",
            "type":"Services"
        }
    ],
    "sg:phone":"+1 434 978 4619",
    "sg:postcode":"22901",
    "sg:province":"VA",
    "sg:tags":[
        "home",
        "referral",
        "nursing",
        "information"
    ],
    "wof:name":"Adult Care Education Conslnt",
    "wof:placetype":"venue"
},
  "geometry": {"coordinates":[-78.600241,38.104667],"type":"Point"}
}