{
  "type": "Feature",
  "properties": {
    "iso:country":"US",
    "sg:address":"250 Twin Oaks Dr",
    "sg:city":"Waverly",
    "sg:classifiers":[
        {
            "category":"Retail",
            "subcategory":"Veterinary Services",
            "type":"Services"
        }
    ],
    "sg:phone":"+1 804 834 8121",
    "sg:postcode":"23890",
    "sg:province":"VA",
    "sg:tags":[
        "veterinarian"
    ],
    "wof:name":"Mike C Chesson DVM",
    "wof:placetype":"venue"
},
  "geometry": {"coordinates":[-77.081912,37.043248],"type":"Point"}
}