{
  "type": "Feature",
  "properties": {
    "addr:full":"207 E Holly Ave Sterling VA 20164",
    "addr:housenumber":"207",
    "addr:postcode":"20164",
    "addr:street":"E Holly Ave",
    "iso:country":"US",
    "sg:address":"207 E Holly Ave",
    "sg:city":"Sterling",
    "sg:classifiers":[
        {
            "category":"Health Services",
            "subcategory":"Doctor",
            "type":"Services"
        }
    ],
    "sg:phone":"+1 703 450 4810",
    "sg:postcode":"20164",
    "sg:province":"VA",
    "sg:tags":[
        "physician",
        "medical",
        "surgeon"
    ],
    "wof:name":"Howard L Cohn MD",
    "wof:placetype":"venue"
},
  "geometry": {"coordinates":[-77.401138,38.999932],"type":"Point"}
}