{
  "type": "Feature",
  "properties": {
    "iso:country":"US",
    "sg:address":"1525 Ableway Dr",
    "sg:city":"Midlothian",
    "sg:classifiers":[
        {
            "category":"Professional",
            "subcategory":"Computer Services",
            "type":"Services"
        }
    ],
    "sg:phone":"+1 804 379 2423",
    "sg:postcode":"23114",
    "sg:province":"VA",
    "sg:tags":[
        "related"
    ],
    "wof:name":"Microland Systems Inc",
    "wof:placetype":"venue"
},
  "geometry": {"coordinates":[-77.642837,37.473694],"type":"Point"}
}