{
  "type": "Feature",
  "properties": {
    "iso:country":"US",
    "sg:address":"1306 E Brookland Park Blvd",
    "sg:city":"Richmond",
    "sg:classifiers":[
        {
            "category":"Personal",
            "subcategory":"Beauty Salon",
            "type":"Services"
        }
    ],
    "sg:phone":"+1 804 358 3977",
    "sg:postcode":"23222",
    "sg:province":"VA",
    "wof:name":"Stay Focus",
    "wof:placetype":"venue"
},
  "geometry": {"coordinates":[-77.417231,37.569326],"type":"Point"}
}