{
  "type": "Feature",
  "properties": {
    "addr:full":"2410 Greensboro Rd Martinsville VA 24112",
    "addr:housenumber":"2410",
    "addr:postcode":"24112",
    "addr:street":"Greensboro Rd",
    "iso:country":"US",
    "sg:address":"2410 Greensboro Rd",
    "sg:city":"Martinsville",
    "sg:classifiers":[
        {
            "category":"Shopping",
            "subcategory":"Discount & Variety Stores",
            "type":"Retail Goods"
        },
        {
            "category":"Shopping",
            "subcategory":"Department Store",
            "type":"Retail Goods"
        }
    ],
    "sg:phone":"+1 276 638 2714",
    "sg:postcode":"24112",
    "sg:province":"VA",
    "sg:tags":[
        "shop"
    ],
    "wof:name":"Family Dollar Stores",
    "wof:placetype":"venue"
},
  "geometry": {"coordinates":[-79.87871699999999,36.656856],"type":"Point"}
}