{
  "type": "Feature",
  "properties": {
    "addr:full":"209 Draft Ave Stuarts Draft VA 24477",
    "addr:housenumber":"209",
    "addr:postcode":"24477",
    "addr:street":"Draft Ave",
    "iso:country":"US",
    "sg:address":"209 Draft Ave",
    "sg:city":"Stuarts Draft",
    "sg:classifiers":[
        {
            "category":"Retail",
            "subcategory":"Veterinary Services",
            "type":"Services"
        }
    ],
    "sg:phone":"+1 540 337 5005",
    "sg:postcode":"24477",
    "sg:province":"VA",
    "sg:tags":[
        "hospital",
        "animal"
    ],
    "sg:website":"www.drjune.com",
    "wof:name":"Animal Hospital-Stuarts Draft",
    "wof:placetype":"venue"
},
  "geometry": {"coordinates":[-79.03348,38.025756],"type":"Point"}
}