{
  "type": "Feature",
  "properties": {
    "addr:full":"6025 Empire Lakes Ct Haymarket VA 20169",
    "addr:housenumber":"6025",
    "addr:postcode":"20169",
    "addr:street":"Empire Lakes Ct",
    "iso:country":"US",
    "sg:address":"6025 Empire Lakes Ct",
    "sg:city":"Haymarket",
    "sg:classifiers":[
        {
            "category":"Professional",
            "subcategory":"Accounting & Tax Preparation",
            "type":"Services"
        }
    ],
    "sg:phone":"+1 703 753 4488",
    "sg:postcode":"20169",
    "sg:province":"VA",
    "sg:tags":[
        "accountant"
    ],
    "wof:name":"Brian Smith & Assoc",
    "wof:placetype":"venue"
},
  "geometry": {"coordinates":[-77.643845,38.830838],"type":"Point"}
}