{
  "type": "Feature",
  "properties": {
    "iso:country":"US",
    "sg:address":"21 Granite Spring Rd",
    "sg:city":"Richmond",
    "sg:classifiers":[
        {
            "category":"Building & Trades",
            "subcategory":"Equipment Rental",
            "type":"Services"
        },
        {
            "category":"Wholesale",
            "subcategory":"Chemicals & Plastics",
            "type":"Manufacturing & Wholesale Goods"
        }
    ],
    "sg:phone":"+1 804 745 9677",
    "sg:postcode":"23225",
    "sg:province":"VA",
    "sg:tags":[
        "medical",
        "merchandise",
        "oxygen"
    ],
    "wof:name":"Richmond Respiratory & Med Sup",
    "wof:placetype":"venue"
},
  "geometry": {"coordinates":[-77.53113500000001,37.49663],"type":"Point"}
}