{
  "type": "Feature",
  "properties": {
    "iso:country":"US",
    "sg:address":"7611 Mineral Spring Ct",
    "sg:city":"Springfield",
    "sg:classifiers":[
        {
            "category":"Wholesale",
            "subcategory":"Durable Goods & Equipment",
            "type":"Manufacturing & Wholesale Goods"
        }
    ],
    "sg:phone":"+1 703 440 3711",
    "sg:postcode":"22153",
    "sg:province":"VA",
    "wof:name":"Navarre Corporation",
    "wof:placetype":"venue"
},
  "geometry": {"coordinates":[-77.217421,38.748834],"type":"Point"}
}