{
  "type": "Feature",
  "properties": {
    "addr:full":"21645 Piccadilly Circus Ct Ashburn VA 20147",
    "addr:postcode":"21645;20147",
    "addr:street":"Piccadilly Circus Ct",
    "iso:country":"US",
    "sg:address":"21645 Piccadilly Circus Ct",
    "sg:city":"Ashburn",
    "sg:classifiers":[
        {
            "category":"Professional",
            "subcategory":"Art Services",
            "type":"Services"
        }
    ],
    "sg:phone":"+1 703 729 7660",
    "sg:postcode":"20147",
    "sg:province":"VA",
    "sg:tags":[
        "commercial",
        "calligrapher",
        "design"
    ],
    "wof:name":"Pat Blair Calligraphy & Design",
    "wof:placetype":"venue"
},
  "geometry": {"coordinates":[-77.501591,39.017684],"type":"Point"}
}