{
  "type": "Feature",
  "properties": {
    "addr:full":"220 Battlefield Blvd S Chesapeake VA 23322",
    "addr:housenumber":"220",
    "addr:postcode":"23322",
    "addr:street":"Battlefield Blvd",
    "iso:country":"US",
    "sg:address":"220 Battlefield Blvd S",
    "sg:city":"Chesapeake",
    "sg:classifiers":[
        {
            "category":"Retail",
            "subcategory":"Auto Repair",
            "type":"Services"
        }
    ],
    "sg:phone":"+1 757 546 0700",
    "sg:postcode":"23322",
    "sg:province":"VA",
    "sg:tags":[
        "exhaust"
    ],
    "wof:name":"Big Als Mufflers",
    "wof:placetype":"venue"
},
  "geometry": {"coordinates":[-76.23936,36.717299],"type":"Point"}
}