{
  "type": "Feature",
  "properties": {
    "iso:country":"US",
    "sg:address":"525 Airport Rd",
    "sg:city":"Martinsville",
    "sg:classifiers":[
        {
            "category":"Freight",
            "type":"Transportation"
        }
    ],
    "sg:phone":"+1 276 957 4100",
    "sg:postcode":"24112",
    "sg:province":"VA",
    "sg:tags":[
        "trucking"
    ],
    "wof:name":"J C Joyce Trucking & Paving Co",
    "wof:placetype":"venue"
},
  "geometry": {"coordinates":[-80.007182,36.62751],"type":"Point"}
}