{
  "type": "Feature",
  "properties": {
    "addr:full":"6557 Wolftree Ln Annandale VA 22003",
    "addr:housenumber":"6557",
    "addr:postcode":"22003",
    "addr:street":"Wolftree Ln",
    "iso:country":"US",
    "sg:address":"6557 Wolftree Ln",
    "sg:city":"Annandale",
    "sg:classifiers":[
        {
            "category":"Professional",
            "subcategory":"Management & Consulting",
            "type":"Services"
        }
    ],
    "sg:phone":"+1 703 256 0299",
    "sg:postcode":"22003",
    "sg:province":"VA",
    "wof:name":"Ancona International",
    "wof:placetype":"venue"
},
  "geometry": {"coordinates":[-77.170676,38.832646],"type":"Point"}
}