{
  "type": "Feature",
  "properties": {
    "addr:full":"132 Knell's Ridge Blvd Chesapeake VA 23320",
    "addr:housenumber":"132",
    "addr:postcode":"23320",
    "addr:street":"Knell'S Ridge Blvd",
    "iso:country":"US",
    "sg:address":"132 Knell's Ridge Blvd",
    "sg:city":"Chesapeake",
    "sg:classifiers":[
        {
            "category":"Building & Trades",
            "subcategory":"Construction",
            "type":"Services"
        }
    ],
    "sg:phone":"+1 757 312 0537",
    "sg:postcode":"23320",
    "sg:province":"VA",
    "sg:tags":[
        "general",
        "contractor"
    ],
    "wof:name":"Classic Construction Corp-Va",
    "wof:placetype":"venue"
},
  "geometry": {"coordinates":[-76.24262299999999,36.750984],"type":"Point"}
}