{
  "type": "Feature",
  "properties": {
    "iso:country":"US",
    "sg:address":"2508 Hemple St",
    "sg:city":"Chesapeake",
    "sg:classifiers":[
        {
            "category":"Organizations",
            "subcategory":"Religious Organization",
            "type":"Services"
        }
    ],
    "sg:phone":"+1 757 543 9788",
    "sg:postcode":"23324",
    "sg:province":"VA",
    "sg:tags":[
        "church"
    ],
    "wof:name":"Powerhouse Fellowship Church",
    "wof:placetype":"venue"
},
  "geometry": {"coordinates":[-76.259524,36.794455],"type":"Point"}
}