{
  "type": "Feature",
  "properties": {
    "addr:full":"525 Cameron Station Blvd Alexandria VA 22304",
    "addr:housenumber":"525",
    "addr:postcode":"22304",
    "addr:street":"Cameron Station Blvd",
    "iso:country":"US",
    "sg:address":"525 Cameron Station Blvd",
    "sg:city":"Alexandria",
    "sg:classifiers":[
        {
            "category":"Professional",
            "subcategory":"Business Services",
            "type":"Services"
        }
    ],
    "sg:phone":"+1 703 567 4744",
    "sg:postcode":"22304",
    "sg:province":"VA",
    "wof:name":"Physicians First Inc",
    "wof:placetype":"venue"
},
  "geometry": {"coordinates":[-77.126695,38.806002],"type":"Point"}
}