{
  "type": "Feature",
  "properties": {
    "addr:full":"4440 Massaponax Church Rd Fredericksburg VA 22408",
    "addr:housenumber":"4440",
    "addr:postcode":"22408",
    "addr:street":"Massaponax Church Rd",
    "iso:country":"US",
    "sg:address":"4440 Massaponax Church Rd",
    "sg:city":"Fredericksburg",
    "sg:classifiers":[
        {
            "category":"Food & Beverages",
            "subcategory":"Specialty",
            "type":"Retail Goods"
        }
    ],
    "sg:phone":"+1 540 898 7990",
    "sg:postcode":"22408",
    "sg:province":"VA",
    "sg:tags":[
        "personal"
    ],
    "wof:name":"Health & Happiness",
    "wof:placetype":"venue"
},
  "geometry": {"coordinates":[-77.484731,38.191632],"type":"Point"}
}