{
  "type": "Feature",
  "properties": {
    "iso:country":"US",
    "sg:address":"421 Hollomon Dr",
    "sg:city":"Hampton",
    "sg:classifiers":[
        {
            "category":"Home & Garden",
            "subcategory":"Carpets & Floor Coverings",
            "type":"Retail Goods"
        }
    ],
    "sg:phone":"+1 757 826 5630",
    "sg:postcode":"23666",
    "sg:province":"VA",
    "sg:tags":[
        "installation"
    ],
    "wof:name":"Interstate Floor Covering Inc",
    "wof:placetype":"venue"
},
  "geometry": {"coordinates":[-76.42070699999999,37.03286],"type":"Point"}
}