{
  "type": "Feature",
  "properties": {
    "iso:country":"US",
    "sg:address":"808 N 18th St",
    "sg:city":"Richmond",
    "sg:classifiers":[
        {
            "category":"Wholesale",
            "subcategory":"Groceries",
            "type":"Manufacturing & Wholesale Goods"
        }
    ],
    "sg:phone":"+1 804 644 0335",
    "sg:postcode":"23223",
    "sg:province":"VA",
    "sg:tags":[
        "grocer"
    ],
    "wof:name":"B Green & Co",
    "wof:placetype":"venue"
},
  "geometry": {"coordinates":[-77.42296399999999,37.539025],"type":"Point"}
}