{
  "type": "Feature",
  "properties": {
    "iso:country":"US",
    "sg:address":"301 Jefferson Davis Hwy",
    "sg:city":"Richmond",
    "sg:classifiers":[
        {
            "category":"Wholesale",
            "subcategory":"Machinery & Supplies",
            "type":"Manufacturing & Wholesale Goods"
        },
        {
            "category":"Retail",
            "subcategory":"Auto Repair",
            "type":"Services"
        }
    ],
    "sg:phone":"+1 804 233 4396",
    "sg:postcode":"23224",
    "sg:province":"VA",
    "sg:tags":[
        "repairing",
        "automobile",
        "pump",
        "installation",
        "water"
    ],
    "wof:name":"Atlantic Pump & Equipment Co",
    "wof:placetype":"venue"
},
  "geometry": {"coordinates":[-77.44793,37.513023],"type":"Point"}
}