{
  "type": "Feature",
  "properties": {
    "addr:full":"2059 Timber Ridge Rd Bedford VA 24523",
    "addr:housenumber":"2059",
    "addr:postcode":"24523",
    "addr:street":"Timber Ridge Rd",
    "iso:country":"US",
    "sg:address":"2059 Timber Ridge Rd",
    "sg:city":"Bedford",
    "sg:classifiers":[
        {
            "category":"Manufacturing",
            "subcategory":"Retail Goods",
            "type":"Manufacturing & Wholesale Goods"
        }
    ],
    "sg:phone":"+1 540 586 1097",
    "sg:postcode":"24523",
    "sg:province":"VA",
    "sg:tags":[
        "cards",
        "product",
        "greeting",
        "mfg"
    ],
    "wof:name":"Heart Tones",
    "wof:placetype":"venue"
},
  "geometry": {"coordinates":[-79.45500199999999,37.344686],"type":"Point"}
}