{
  "type": "Feature",
  "properties": {
    "iso:country":"US",
    "sg:address":"7011 Otterdale Rd",
    "sg:city":"Moseley",
    "sg:classifiers":[
        {
            "category":"Retail",
            "subcategory":"Veterinary Services",
            "type":"Services"
        }
    ],
    "sg:phone":"+1 804 743 4818",
    "sg:postcode":"23120",
    "sg:province":"VA",
    "sg:tags":[
        "veterinarian"
    ],
    "wof:name":"Animal House Call",
    "wof:placetype":"venue"
},
  "geometry": {"coordinates":[-77.71596,37.405805],"type":"Point"}
}