{
  "type": "Feature",
  "properties": {
    "iso:country":"US",
    "sg:address":"3709 Gazebo Dr",
    "sg:city":"Shawsville",
    "sg:classifiers":[
        {
            "category":"Organizations",
            "subcategory":"Community Association",
            "type":"Services"
        }
    ],
    "sg:phone":"+1 540 268 2173",
    "sg:postcode":"24162",
    "sg:province":"VA",
    "wof:name":"Intl Assoc of Lions",
    "wof:placetype":"venue"
},
  "geometry": {"coordinates":[-80.262512,37.128224],"type":"Point"}
}