{
  "type": "Feature",
  "properties": {
    "addr:full":"324 24th St NW Roanoke VA 24017",
    "addr:housenumber":"324",
    "addr:postcode":"24017",
    "addr:street":"24Th St Nw",
    "iso:country":"US",
    "sg:address":"324 24th St NW",
    "sg:city":"Roanoke",
    "sg:classifiers":[
        {
            "category":"Shopping",
            "subcategory":"Discount & Variety Stores",
            "type":"Retail Goods"
        },
        {
            "category":"Shopping",
            "subcategory":"Department Store",
            "type":"Retail Goods"
        }
    ],
    "sg:phone":"+1 540 344 2989",
    "sg:postcode":"24017",
    "sg:province":"VA",
    "sg:tags":[
        "shop"
    ],
    "wof:name":"Family Dollar Stores",
    "wof:placetype":"venue"
},
  "geometry": {"coordinates":[-79.976606,37.284424],"type":"Point"}
}