{
  "type": "Feature",
  "properties": {
    "iso:country":"US",
    "sg:address":"717 Battlefield Blvd S",
    "sg:city":"Chesapeake",
    "sg:classifiers":[
        {
            "category":"Cinema",
            "subcategory":"Movie Rental",
            "type":"Entertainment"
        }
    ],
    "sg:phone":"+1 757 482 0668",
    "sg:postcode":"23322",
    "sg:province":"VA",
    "sg:tags":[
        "video",
        "disc",
        "leasing",
        "tape"
    ],
    "wof:name":"Movie Gallery",
    "wof:placetype":"venue"
},
  "geometry": {"coordinates":[-76.234342,36.700941],"type":"Point"}
}