{
  "type": "Feature",
  "properties": {
    "addr:full":"4000 Virginia Beach Blvd Virginia Beach VA 23452",
    "addr:housenumber":"4000",
    "addr:postcode":"23452",
    "addr:street":"Virginia Beach Blvd",
    "iso:country":"US",
    "sg:address":"4000 Virginia Beach Blvd",
    "sg:city":"Virginia Beach",
    "sg:classifiers":[
        {
            "category":"Shopping",
            "subcategory":"Hobbies, Toys, & Games",
            "type":"Retail Goods"
        }
    ],
    "sg:phone":"+1 757 306 4760",
    "sg:postcode":"23452",
    "sg:province":"VA",
    "sg:tags":[
        "model",
        "supply"
    ],
    "sg:website":"www.hobbytown.com",
    "wof:name":"Hobbytown USA",
    "wof:placetype":"venue"
},
  "geometry": {"coordinates":[-76.115081,36.842309],"type":"Point"}
}