{
  "type": "Feature",
  "properties": {
    "addr:full":"1219 High Point Ave Richmond VA 23230",
    "addr:housenumber":"1219",
    "addr:postcode":"23230",
    "addr:street":"High Point Ave",
    "iso:country":"US",
    "sg:address":"1219 High Point Ave",
    "sg:city":"Richmond",
    "sg:classifiers":[
        {
            "category":"Shopping",
            "subcategory":"Clothing, Apparel, & Fashions",
            "type":"Retail Goods"
        }
    ],
    "sg:phone":"+1 804 359 2000",
    "sg:postcode":"23230",
    "sg:province":"VA",
    "sg:tags":[
        "tailor"
    ],
    "wof:name":"Hong Kong Tailor",
    "wof:placetype":"venue"
},
  "geometry": {"coordinates":[-77.473833,37.566586],"type":"Point"}
}