{
  "type": "Feature",
  "properties": {
    "addr:full":"203 Greenmont Way NE Leesburg VA 20176",
    "addr:housenumber":"203",
    "addr:postcode":"20176",
    "addr:street":"Greenmont Way Ne",
    "iso:country":"US",
    "sg:address":"203 Greenmont Way NE",
    "sg:city":"Leesburg",
    "sg:classifiers":[
        {
            "category":"Organizations",
            "subcategory":"Professional Association",
            "type":"Services"
        }
    ],
    "sg:phone":"+1 703 777 1474",
    "sg:postcode":"20176",
    "sg:province":"VA",
    "sg:tags":[
        "e",
        "solution",
        "provider"
    ],
    "wof:name":"Nextstep Commerce Inc",
    "wof:placetype":"venue"
},
  "geometry": {"coordinates":[-77.557868,39.123078],"type":"Point"}
}