{
  "type": "Feature",
  "properties": {
    "addr:full":"9243 George Washington Memorial Hwy Zanoni VA 23061",
    "addr:housenumber":"9243",
    "addr:postcode":"23061",
    "addr:street":"George Washington Memorial Hwy Zanoni",
    "iso:country":"US",
    "sg:address":"9243 George Washington Memorial Hwy",
    "sg:city":"Zanoni",
    "sg:classifiers":[
        {
            "category":"Wholesale",
            "subcategory":"Auto Parts",
            "type":"Manufacturing & Wholesale Goods"
        }
    ],
    "sg:phone":"+1 804 693 5860",
    "sg:postcode":"23061",
    "sg:province":"VA",
    "sg:tags":[
        "automobile",
        "rebuilt"
    ],
    "wof:name":"Dickey Auto Recyclers",
    "wof:placetype":"venue"
},
  "geometry": {"coordinates":[-76.57369799999999,37.436996],"type":"Point"}
}