{
  "type": "Feature",
  "properties": {
    "addr:full":"10387 Main St Fairfax VA 22030",
    "addr:housenumber":"10387",
    "addr:postcode":"22030",
    "addr:street":"Main St",
    "iso:country":"US",
    "sg:address":"10387 Main St",
    "sg:city":"Fairfax",
    "sg:classifiers":[
        {
            "category":"Building & Trades",
            "subcategory":"Construction",
            "type":"Services"
        }
    ],
    "sg:phone":"+1 703 385 0310",
    "sg:postcode":"22030",
    "sg:province":"VA",
    "sg:tags":[
        "general",
        "contractor"
    ],
    "wof:name":"High Temperature Lines",
    "wof:placetype":"venue"
},
  "geometry": {"coordinates":[-77.304525,38.845676],"type":"Point"}
}