{
  "type": "Feature",
  "properties": {
    "addr:full":"3006 W Main St Danville VA 24541",
    "addr:housenumber":"3006",
    "addr:postcode":"24541",
    "addr:street":"W Main St",
    "iso:country":"US",
    "sg:address":"3006 W Main St",
    "sg:city":"Danville",
    "sg:classifiers":[
        {
            "category":"Restaurant",
            "type":"Food & Drink"
        }
    ],
    "sg:phone":"+1 434 799 1334",
    "sg:postcode":"24541",
    "sg:province":"VA",
    "sg:tags":[
        "eating",
        "drinking",
        "station",
        "gasoline",
        "ge"
    ],
    "wof:name":"Wayside Diner Inc",
    "wof:placetype":"venue"
},
  "geometry": {"coordinates":[-79.461974,36.546652],"type":"Point"}
}