{
  "type": "Feature",
  "properties": {
    "addr:full":"18536 Pineview Sq Leesburg VA 20176",
    "addr:housenumber":"18536",
    "addr:postcode":"20176",
    "addr:street":"Pineview Sq",
    "iso:country":"US",
    "sg:address":"18536 Pineview Sq",
    "sg:city":"Leesburg",
    "sg:classifiers":[
        {
            "category":"Professional",
            "subcategory":"Business Services",
            "type":"Services"
        }
    ],
    "sg:phone":"+1 703 967 1727",
    "sg:postcode":"20176",
    "sg:province":"VA",
    "wof:name":"Shire Cpas",
    "wof:placetype":"venue"
},
  "geometry": {"coordinates":[-77.52176,39.102882],"type":"Point"}
}