{
  "type": "Feature",
  "properties": {
    "addr:full":"7232 New Market Ct Manassas VA 20109",
    "addr:housenumber":"7232",
    "addr:postcode":"20109",
    "addr:street":"New Market Ct",
    "iso:country":"US",
    "sg:address":"7232 New Market Ct",
    "sg:city":"Manassas",
    "sg:classifiers":[
        {
            "category":"Home & Garden",
            "subcategory":"Furniture",
            "type":"Retail Goods"
        }
    ],
    "sg:phone":"+1 703 257 5926",
    "sg:postcode":"20109",
    "sg:province":"VA",
    "wof:name":"Thomasville Tradition",
    "wof:placetype":"venue"
},
  "geometry": {"coordinates":[-77.52145899999999,38.799943],"type":"Point"}
}