{
  "type": "Feature",
  "properties": {
    "addr:full":"3202 Valley Pike Winchester VA 22602",
    "addr:housenumber":"3202",
    "addr:postcode":"22602",
    "addr:street":"Valley Pike",
    "iso:country":"US",
    "sg:address":"3202 Valley Pike",
    "sg:city":"Winchester",
    "sg:classifiers":[
        {
            "category":"Real Estate",
            "subcategory":"Real Estate Agent",
            "type":"Services"
        }
    ],
    "sg:phone":"+1 540 662 6565",
    "sg:postcode":"22602",
    "sg:province":"VA",
    "sg:tags":[
        "general",
        "broker",
        "contractor"
    ],
    "wof:name":"A B A Realtors",
    "wof:placetype":"venue"
},
  "geometry": {"coordinates":[-78.19075599999999,39.137327],"type":"Point"}
}