{
  "type": "Feature",
  "properties": {
    "iso:country":"US",
    "sg:address":"2700 Potomac Mills Cir",
    "sg:city":"Woodbridge",
    "sg:classifiers":[
        {
            "category":"Professional",
            "subcategory":"Research",
            "type":"Services"
        }
    ],
    "sg:phone":"+1 703 497 4444",
    "sg:postcode":"22192",
    "sg:province":"VA",
    "sg:tags":[
        "market",
        "analysis"
    ],
    "wof:name":"Car-Lene Research Inc",
    "wof:placetype":"venue"
},
  "geometry": {"coordinates":[-77.29342699999999,38.64654],"type":"Point"}
}