{
  "type": "Feature",
  "properties": {
    "addr:full":"1010 N Glebe Rd Ste 120 Arlington VA 22201",
    "addr:housenumber":"1010",
    "addr:postcode":"22201",
    "addr:street":"N Glebe Rd Ste 120",
    "iso:country":"US",
    "sg:address":"1010 N Glebe Rd Ste 120",
    "sg:city":"Arlington",
    "sg:classifiers":[
        {
            "category":"Building & Trades",
            "subcategory":"Construction",
            "type":"Services"
        }
    ],
    "sg:phone":"+1 703 841 9411",
    "sg:postcode":"22201",
    "sg:province":"VA",
    "sg:tags":[
        "contractor"
    ],
    "wof:name":"Building Service Management Inc",
    "wof:placetype":"venue"
},
  "geometry": {"coordinates":[-77.116302,38.8829],"type":"Point"}
}