{
  "type": "Feature",
  "properties": {
    "iso:country":"US",
    "sg:address":"1702 Chestnut Ave",
    "sg:city":"Buena Vista",
    "sg:classifiers":[
        {
            "category":"Organizations",
            "subcategory":"Religious Organization",
            "type":"Services"
        }
    ],
    "sg:phone":"+1 540 261 6596",
    "sg:postcode":"24416",
    "sg:province":"VA",
    "sg:tags":[
        "church"
    ],
    "sg:website":"www.bvphc.org",
    "wof:name":"Pentecostal Holiness Church",
    "wof:placetype":"venue"
},
  "geometry": {"coordinates":[-79.353527,37.730215],"type":"Point"}
}