{
  "type": "Feature",
  "properties": {
    "addr:full":"402 Wood Ave W Big Stone Gap VA 24219",
    "addr:housenumber":"402",
    "addr:postcode":"24219",
    "addr:street":"Wood Ave W",
    "iso:country":"US",
    "sg:address":"402 Wood Ave W",
    "sg:city":"Big Stone Gap",
    "sg:classifiers":[
        {
            "category":"Home & Garden",
            "subcategory":"Carpets & Floor Coverings",
            "type":"Retail Goods"
        }
    ],
    "sg:phone":"+1 276 523 2303",
    "sg:postcode":"24219",
    "sg:province":"VA",
    "sg:tags":[
        "dealer",
        "rug"
    ],
    "wof:name":"Tri-State Rug Co Inc",
    "wof:placetype":"venue"
},
  "geometry": {"coordinates":[-82.78184299999999,36.861445],"type":"Point"}
}