{
  "type": "Feature",
  "properties": {
    "iso:country":"US",
    "sg:address":"1483 Chain Bridge Rd",
    "sg:city":"Mc Lean",
    "sg:classifiers":[
        {
            "category":"Building & Trades",
            "subcategory":"Construction",
            "type":"Services"
        }
    ],
    "sg:phone":"+1 703 748 0948",
    "sg:postcode":"22101",
    "sg:province":"VA",
    "sg:tags":[
        "interior",
        "design"
    ],
    "wof:name":"Asid-American Society of Interior Designers",
    "wof:placetype":"venue"
},
  "geometry": {"coordinates":[-77.18090100000001,38.931301],"type":"Point"}
}