{
  "type": "Feature",
  "properties": {
    "addr:full":"1348 Pine Tree Rd Mc Lean VA 22101",
    "addr:housenumber":"1348",
    "addr:postcode":"22101",
    "addr:street":"Pine Tree Rd",
    "iso:country":"US",
    "sg:address":"1348 Pine Tree Rd",
    "sg:city":"Mc Lean",
    "sg:classifiers":[
        {
            "category":"Professional",
            "subcategory":"Management & Consulting",
            "type":"Services"
        }
    ],
    "sg:phone":"+1 703 841 1204",
    "sg:postcode":"22101",
    "sg:province":"VA",
    "wof:name":"International Space Services",
    "wof:placetype":"venue"
},
  "geometry": {"coordinates":[-77.13661399999999,38.936049],"type":"Point"}
}