{
  "type": "Feature",
  "properties": {
    "addr:full":"43781 Parkhurst Plz Ashburn VA 20147",
    "addr:housenumber":"43781",
    "addr:postcode":"20147",
    "addr:street":"Parkhurst Plz",
    "iso:country":"US",
    "sg:address":"43781 Parkhurst Plz",
    "sg:city":"Ashburn",
    "sg:classifiers":[
        {
            "category":"Autos & Motor Vehicles",
            "subcategory":"Auto Supplies",
            "type":"Retail Goods"
        },
        {
            "category":"Retail",
            "subcategory":"Auto Repair",
            "type":"Services"
        }
    ],
    "sg:phone":"+1 703 724 9000",
    "sg:postcode":"20147",
    "sg:province":"VA",
    "sg:tags":[
        "repairing",
        "automobile"
    ],
    "sg:website":"www.ashburngoodyear.com",
    "wof:name":"Ashburn Automotive Service",
    "wof:placetype":"venue"
},
  "geometry": {"coordinates":[-77.48832400000001,39.028918],"type":"Point"}
}