{
  "type": "Feature",
  "properties": {
    "addr:full":"714 E Franklin St Richmond VA 23219",
    "addr:housenumber":"714",
    "addr:postcode":"23219",
    "addr:street":"E Franklin St",
    "iso:country":"US",
    "sg:address":"714 E Franklin St",
    "sg:city":"Richmond",
    "sg:classifiers":[
        {
            "category":"Personal",
            "subcategory":"Shoe Repair & Shine",
            "type":"Services"
        }
    ],
    "sg:phone":"+1 804 782 6959",
    "sg:postcode":"23219",
    "sg:province":"VA",
    "sg:tags":[
        "parlor"
    ],
    "wof:name":"Guss Shoe Repair",
    "wof:placetype":"venue"
},
  "geometry": {"coordinates":[-77.43644500000001,37.539748],"type":"Point"}
}