{
  "type": "Feature",
  "properties": {
    "addr:full":"5131 Broad Run Church Rd Warrenton VA 20187",
    "addr:housenumber":"5131",
    "addr:postcode":"20187",
    "addr:street":"Broad Run Church Rd",
    "iso:country":"US",
    "sg:address":"5131 Broad Run Church Rd",
    "sg:city":"Warrenton",
    "sg:classifiers":[
        {
            "category":"Building & Trades",
            "subcategory":"Cleaning & Sanitation",
            "type":"Services"
        }
    ],
    "sg:phone":"+1 540 349 5110",
    "sg:postcode":"20187",
    "sg:province":"VA",
    "sg:tags":[
        "maintenance"
    ],
    "wof:name":"Be Cleaning Service Inc",
    "wof:placetype":"venue"
},
  "geometry": {"coordinates":[-77.71704699999999,38.765444],"type":"Point"}
}