{
  "type": "Feature",
  "properties": {
    "iso:country":"US",
    "sg:address":"4605 Pembroke Lake Cir",
    "sg:city":"Virginia Beach",
    "sg:classifiers":[
        {
            "category":"Banks & Credit Unions",
            "subcategory":"Investment Brokerage",
            "type":"Services"
        }
    ],
    "sg:phone":"+1 757 499 6500",
    "sg:postcode":"23455",
    "sg:province":"VA",
    "sg:tags":[
        "consultant",
        "planning",
        "financial"
    ],
    "wof:name":"Uspa & Ira Mid-Atlantic Inc",
    "wof:placetype":"venue"
},
  "geometry": {"coordinates":[-76.1332,36.861279],"type":"Point"}
}