{
  "type": "Feature",
  "properties": {
    "addr:full":"3504 Joyce Ct Chesapeake VA 23321",
    "addr:housenumber":"3504",
    "addr:postcode":"23321",
    "addr:street":"Joyce Ct",
    "iso:country":"US",
    "sg:address":"3504 Joyce Ct",
    "sg:city":"Chesapeake",
    "sg:classifiers":[
        {
            "category":"Real Estate",
            "subcategory":"Real Estate Operator",
            "type":"Services"
        }
    ],
    "sg:phone":"+1 757 484 6631",
    "sg:postcode":"23321",
    "sg:province":"VA",
    "sg:tags":[
        "building",
        "apartment"
    ],
    "wof:name":"Woodhaven Apartments",
    "wof:placetype":"venue"
},
  "geometry": {"coordinates":[-76.40266200000001,36.865694],"type":"Point"}
}