{
  "type": "Feature",
  "properties": {
    "iso:country":"US",
    "sg:address":"30 Walnut Ave",
    "sg:city":"Vinton",
    "sg:classifiers":[
        {
            "category":"Organizations",
            "subcategory":"Religious Organization",
            "type":"Services"
        }
    ],
    "sg:phone":"+1 540 342 1189",
    "sg:postcode":"24179",
    "sg:province":"VA",
    "wof:name":"Reed Street Baptist",
    "wof:placetype":"venue"
},
  "geometry": {"coordinates":[-79.90014499999999,37.279246],"type":"Point"}
}