{
  "type": "Feature",
  "properties": {
    "iso:country":"US",
    "sg:address":"4000 Mechanicsville Pike",
    "sg:city":"Richmond",
    "sg:classifiers":[
        {
            "category":"Personal",
            "subcategory":"Beauty Salon",
            "type":"Services"
        }
    ],
    "sg:phone":"+1 804 321 6610",
    "sg:postcode":"23223",
    "sg:province":"VA",
    "wof:name":"Perfect Touch",
    "wof:placetype":"venue"
},
  "geometry": {"coordinates":[-77.39438800000001,37.579553],"type":"Point"}
}