{
  "type": "Feature",
  "properties": {
    "addr:full":"1000 E Main St Purcellville VA 20134",
    "addr:housenumber":"1000",
    "addr:postcode":"20134",
    "addr:street":"E Main St",
    "iso:country":"US",
    "sg:address":"1000 E Main St",
    "sg:city":"Purcellville",
    "sg:classifiers":[
        {
            "category":"Food & Beverages",
            "subcategory":"Groceries & Convenience Stores",
            "type":"Retail Goods"
        }
    ],
    "sg:phone":"+1 703 443 6360",
    "sg:postcode":"20134",
    "sg:province":"VA",
    "sg:tags":[
        "grocer"
    ],
    "wof:name":"Giant Food Inc",
    "wof:placetype":"venue"
},
  "geometry": {"coordinates":[-77.69749299999999,39.135805],"type":"Point"}
}