{
  "type": "Feature",
  "properties": {
    "iso:country":"US",
    "sg:address":"12159 Old Belfield Rd",
    "sg:city":"Capron",
    "sg:classifiers":[
        {
            "category":"Building & Trades",
            "subcategory":"Construction",
            "type":"Services"
        }
    ],
    "sg:phone":"+1 434 658 4395",
    "sg:postcode":"23829",
    "sg:province":"VA",
    "sg:tags":[
        "house"
    ],
    "wof:name":"Beargate Construction",
    "wof:placetype":"venue"
},
  "geometry": {"coordinates":[-77.296935,36.718877],"type":"Point"}
}