{
  "type": "Feature",
  "properties": {
    "addr:full":"2250 Old Ivy Rd Charlottesville VA 22903",
    "addr:housenumber":"2250",
    "addr:postcode":"22903",
    "addr:street":"Old Ivy Rd",
    "iso:country":"US",
    "sg:address":"2250 Old Ivy Rd",
    "sg:city":"Charlottesville",
    "sg:classifiers":[
        {
            "category":"Insurance",
            "subcategory":"Insurance Agent",
            "type":"Services"
        }
    ],
    "sg:phone":"+1 434 979 0248",
    "sg:postcode":"22903",
    "sg:province":"VA",
    "wof:name":"Northwestern Mutual Financial",
    "wof:placetype":"venue"
},
  "geometry": {"coordinates":[-78.51555500000001,38.045745],"type":"Point"}
}