{
  "type": "Feature",
  "properties": {
    "addr:full":"2030 Shenandoah Valley Ave NE Roanoke VA 24012",
    "addr:housenumber":"2030",
    "addr:postcode":"24012",
    "addr:street":"Shenandoah Valley Ave Ne",
    "iso:country":"US",
    "sg:address":"2030 Shenandoah Valley Ave NE",
    "sg:city":"Roanoke",
    "sg:classifiers":[
        {
            "category":"Retail",
            "subcategory":"Auto Repair",
            "type":"Services"
        }
    ],
    "sg:phone":"+1 540 344 1647",
    "sg:postcode":"24012",
    "sg:province":"VA",
    "sg:tags":[
        "transmission"
    ],
    "wof:name":"AAMCO Transmissions",
    "wof:placetype":"venue"
},
  "geometry": {"coordinates":[-79.92856,37.294309],"type":"Point"}
}