{
  "type": "Feature",
  "properties": {
    "addr:full":"3373 Forest Ct Roanoke VA 24018",
    "addr:housenumber":"3373",
    "addr:postcode":"24018",
    "addr:street":"Forest Ct",
    "iso:country":"US",
    "sg:address":"3373 Forest Ct",
    "sg:city":"Roanoke",
    "sg:classifiers":[
        {
            "category":"Banks & Credit Unions",
            "subcategory":"Investment Brokerage",
            "type":"Services"
        }
    ],
    "sg:phone":"+1 540 989 8627",
    "sg:postcode":"24018",
    "sg:province":"VA",
    "sg:tags":[
        "security"
    ],
    "wof:name":"Erin S Jones Edward Granl Sln",
    "wof:placetype":"venue"
},
  "geometry": {"coordinates":[-79.996889,37.214432],"type":"Point"}
}