{
  "type": "Feature",
  "properties": {
    "addr:full":"109 N Johnson Dr Pennington Gap VA 24277",
    "addr:housenumber":"109",
    "addr:postcode":"24277",
    "addr:street":"N Johnson Dr",
    "iso:country":"US",
    "sg:address":"109 N Johnson Dr",
    "sg:city":"Pennington Gap",
    "sg:classifiers":[
        {
            "category":"Health Services",
            "subcategory":"Chiropractor",
            "type":"Services"
        }
    ],
    "sg:phone":"+1 276 546 5060",
    "sg:postcode":"24277",
    "sg:province":"VA",
    "wof:name":"Haynes Chiropractic Office",
    "wof:placetype":"venue"
},
  "geometry": {"coordinates":[-83.027192,36.7595],"type":"Point"}
}