{
  "type": "Feature",
  "properties": {
    "addr:full":"739 Cummings St Abingdon VA 24211",
    "addr:housenumber":"739",
    "addr:postcode":"24211",
    "addr:street":"Cummings St",
    "iso:country":"US",
    "sg:address":"739 Cummings St",
    "sg:city":"Abingdon",
    "sg:classifiers":[
        {
            "category":"Autos & Motor Vehicles",
            "subcategory":"Boat Sales",
            "type":"Retail Goods"
        }
    ],
    "sg:phone":"+1 276 628 6237",
    "sg:postcode":"24211",
    "sg:province":"VA",
    "sg:tags":[
        "dealer",
        "sales"
    ],
    "wof:name":"Green Spring Sport Ctr Inc",
    "wof:placetype":"venue"
},
  "geometry": {"coordinates":[-81.97382399999999,36.696879],"type":"Point"}
}