{
  "type": "Feature",
  "properties": {
    "addr:full":"9306 Cape View Ave Norfolk VA 23503",
    "addr:housenumber":"9306",
    "addr:postcode":"23503",
    "addr:street":"Cape View Ave",
    "iso:country":"US",
    "sg:address":"9306 Cape View Ave",
    "sg:city":"Norfolk",
    "sg:classifiers":[
        {
            "category":"Building & Trades",
            "subcategory":"Cleaning & Sanitation",
            "type":"Services"
        }
    ],
    "sg:phone":"+1 757 749 8758",
    "sg:postcode":"23503",
    "sg:province":"VA",
    "sg:tags":[
        "commercial"
    ],
    "wof:name":"Jani-King",
    "wof:placetype":"venue"
},
  "geometry": {"coordinates":[-76.22461300000001,36.933762],"type":"Point"}
}