{
  "type": "Feature",
  "properties": {
    "addr:full":"3031 Clintwood Rd Midlothian VA 23112",
    "addr:postcode":"3031;23112",
    "addr:street":"Clintwood Rd",
    "iso:country":"US",
    "sg:address":"3031 Clintwood Rd",
    "sg:city":"Midlothian",
    "sg:classifiers":[
        {
            "category":"Building & Trades",
            "subcategory":"Plumbing",
            "type":"Services"
        }
    ],
    "sg:phone":"+1 804 744 3030",
    "sg:postcode":"23112",
    "sg:province":"VA",
    "sg:tags":[
        "contractor"
    ],
    "wof:name":"Pyramid Heating and AC Contr",
    "wof:placetype":"venue"
},
  "geometry": {"coordinates":[-77.60538699999999,37.447588],"type":"Point"}
}