{
  "type": "Feature",
  "properties": {
    "addr:full":"16501 Meadowview Ct Leesburg VA 20175",
    "addr:housenumber":"16501",
    "addr:postcode":"20175",
    "addr:street":"Meadowview Ct",
    "iso:country":"US",
    "sg:address":"16501 Meadowview Ct",
    "sg:city":"Leesburg",
    "sg:classifiers":[
        {
            "category":"Social Services",
            "type":"Services"
        }
    ],
    "sg:phone":"+1 703 771 5334",
    "sg:postcode":"20175",
    "sg:province":"VA",
    "wof:name":"Adult Day Care",
    "wof:placetype":"venue"
},
  "geometry": {"coordinates":[-77.550538,39.078072],"type":"Point"}
}