{
  "type": "Feature",
  "properties": {
    "addr:full":"288 N Main St Harrisonburg VA 22802",
    "addr:housenumber":"288",
    "addr:postcode":"22802",
    "addr:street":"N Main St",
    "iso:country":"US",
    "sg:address":"288 N Main St",
    "sg:city":"Harrisonburg",
    "sg:classifiers":[
        {
            "category":"Local Transit",
            "type":"Transportation"
        }
    ],
    "sg:phone":"+1 540 442 8223",
    "sg:postcode":"22802",
    "sg:province":"VA",
    "sg:tags":[
        "limousine"
    ],
    "wof:name":"Gem Limousine Svc",
    "wof:placetype":"venue"
},
  "geometry": {"coordinates":[-78.867969,38.451472],"type":"Point"}
}