{
  "type": "Feature",
  "properties": {
    "addr:full":"2124 Salt Kettle Way Reston VA 20191",
    "addr:housenumber":"2124",
    "addr:postcode":"20191",
    "addr:street":"Salt Kettle Way",
    "iso:country":"US",
    "sg:address":"2124 Salt Kettle Way",
    "sg:city":"Reston",
    "sg:classifiers":[
        {
            "category":"Professional",
            "subcategory":"Computer Services",
            "type":"Services"
        }
    ],
    "sg:phone":"+1 703 391 0935",
    "sg:postcode":"20191",
    "sg:province":"VA",
    "sg:tags":[
        "development",
        "software"
    ],
    "wof:name":"C Ware Inc",
    "wof:placetype":"venue"
},
  "geometry": {"coordinates":[-77.33390900000001,38.934057],"type":"Point"}
}