{
  "type": "Feature",
  "properties": {
    "iso:country":"US",
    "sg:address":"9030 Liberia Ave",
    "sg:city":"Manassas",
    "sg:classifiers":[
        {
            "category":"Retail",
            "subcategory":"Auto Repair",
            "type":"Services"
        }
    ],
    "sg:phone":"+1 703 368 8101",
    "sg:postcode":"20110",
    "sg:province":"VA",
    "sg:tags":[
        "repairing",
        "automobile"
    ],
    "wof:name":"Leggett Tire & Auto Svc",
    "wof:placetype":"venue"
},
  "geometry": {"coordinates":[-77.459639,38.761763],"type":"Point"}
}