{
  "type": "Feature",
  "properties": {
    "iso:country":"US",
    "sg:address":"710 Settlers Landing Rd",
    "sg:city":"Hampton",
    "sg:classifiers":[
        {
            "category":"Government",
            "subcategory":"Office",
            "type":"Public Place"
        }
    ],
    "sg:phone":"+1 757 727 1102",
    "sg:postcode":"23669",
    "sg:province":"VA",
    "sg:tags":[
        "city",
        "program",
        "adm"
    ],
    "sg:website":"www.hamptonroadsconventioncenter.com",
    "wof:name":"Hampton Conventions & Tourism",
    "wof:placetype":"venue"
},
  "geometry": {"coordinates":[-76.343619,37.024549],"type":"Point"}
}