{
  "type": "Feature",
  "properties": {
    "addr:full":"5773 Arrowhead Dr Virginia Beach VA 23462",
    "addr:housenumber":"5773",
    "addr:postcode":"23462",
    "addr:street":"Arrowhead Dr",
    "iso:country":"US",
    "sg:address":"5773 Arrowhead Dr",
    "sg:city":"Virginia Beach",
    "sg:classifiers":[
        {
            "category":"Manufacturing",
            "subcategory":"Signs",
            "type":"Manufacturing & Wholesale Goods"
        }
    ],
    "sg:phone":"+1 757 499 9175",
    "sg:postcode":"23462",
    "sg:province":"VA",
    "sg:tags":[
        "specialty",
        "mfg"
    ],
    "wof:name":"Sign Technologies",
    "wof:placetype":"venue"
},
  "geometry": {"coordinates":[-76.18422,36.840513],"type":"Point"}
}