{
  "type": "Feature",
  "properties": {
    "addr:full":"115 Weems Ln Winchester VA 22601",
    "addr:housenumber":"115",
    "addr:postcode":"22601",
    "addr:street":"Weems Ln",
    "iso:country":"US",
    "sg:address":"115 Weems Ln",
    "sg:city":"Winchester",
    "sg:classifiers":[
        {
            "category":"Banks & Credit Unions",
            "subcategory":"Bank",
            "type":"Services"
        }
    ],
    "sg:phone":"+1 540 665 9028",
    "sg:postcode":"22601",
    "sg:province":"VA",
    "sg:tags":[
        "depository",
        "banking"
    ],
    "wof:name":"Allied Cash Advance",
    "wof:placetype":"venue"
},
  "geometry": {"coordinates":[-78.17841,39.161324],"type":"Point"}
}