{
  "type": "Feature",
  "properties": {
    "iso:country":"US",
    "sg:address":"2300 Corporate Park Drive",
    "sg:city":"Herndon",
    "sg:classifiers":[
        {
            "category":"Professional",
            "subcategory":"Computer Services",
            "type":"Services"
        }
    ],
    "sg:phone":"+1 866 283 0300",
    "sg:postcode":"20171",
    "sg:province":"VA",
    "sg:website":"http://www.k12.com",
    "wof:name":"K12",
    "wof:placetype":"venue"
},
  "geometry": {"coordinates":[-77.395914,38.951092],"type":"Point"}
}