{
  "type": "Feature",
  "properties": {
    "addr:full":"135 The Maine Williamsburg VA 23185",
    "addr:housenumber":"135",
    "addr:postcode":"23185",
    "addr:street":"The Maine",
    "iso:country":"US",
    "sg:address":"135 The Maine",
    "sg:city":"Williamsburg",
    "sg:classifiers":[
        {
            "category":"Building & Trades",
            "subcategory":"Landscaping Services",
            "type":"Services"
        }
    ],
    "sg:phone":"+1 757 259 9237",
    "sg:postcode":"23185",
    "sg:province":"VA",
    "sg:tags":[
        "landscape",
        "contractor"
    ],
    "wof:name":"Larson Landscaping Co",
    "wof:placetype":"venue"
},
  "geometry": {"coordinates":[-76.79737799999999,37.240016],"type":"Point"}
}