{
  "type": "Feature",
  "properties": {
    "iso:country":"US",
    "sg:address":"1063 Riverside Dr",
    "sg:city":"Danville",
    "sg:classifiers":[
        {
            "category":"Retail",
            "subcategory":"Auto Repair",
            "type":"Services"
        }
    ],
    "sg:phone":"+1 434 766 0019",
    "sg:postcode":"24540",
    "sg:province":"VA",
    "sg:tags":[
        "repairing",
        "automobile"
    ],
    "sg:website":"www.woodallauto.com",
    "wof:name":"Robert Woodall Auto Repair",
    "wof:placetype":"venue"
},
  "geometry": {"coordinates":[-79.402445,36.596058],"type":"Point"}
}