{
  "type": "Feature",
  "properties": {
    "addr:full":"6349 Hudson Ave Norfolk VA 23502",
    "addr:housenumber":"6349",
    "addr:postcode":"23502",
    "addr:street":"Hudson Ave",
    "iso:country":"US",
    "sg:address":"6349 Hudson Ave",
    "sg:city":"Norfolk",
    "sg:classifiers":[
        {
            "category":"Professional",
            "subcategory":"Secretarial Services",
            "type":"Services"
        }
    ],
    "sg:phone":"+1 757 466 1955",
    "sg:postcode":"23502",
    "sg:province":"VA",
    "sg:tags":[
        "reporting"
    ],
    "wof:name":"Judy S Medical Transcription",
    "wof:placetype":"venue"
},
  "geometry": {"coordinates":[-76.186956,36.856173],"type":"Point"}
}