{
  "type": "Feature",
  "properties": {
    "addr:full":"4301 Columbia Pke Arlington VA 22204",
    "addr:housenumber":"4301",
    "addr:postcode":"22204",
    "addr:street":"Columbia Pke",
    "iso:country":"US",
    "sg:address":"4301 Columbia Pke",
    "sg:city":"Arlington",
    "sg:classifiers":[
        {
            "category":"Real Estate",
            "subcategory":"Real Estate Operator",
            "type":"Services"
        }
    ],
    "sg:postcode":"22204",
    "sg:province":"VA",
    "sg:tags":[
        "apartment"
    ],
    "sg:website":"udr.com/community359.htm",
    "wof:name":"The Whitmore Apartments",
    "wof:placetype":"venue"
},
  "geometry": {"coordinates":[-77.103639,38.858107],"type":"Point"}
}