{
  "type": "Feature",
  "properties": {
    "addr:full":"10052 Ivor Rd Ivor VA 23866",
    "addr:postcode":"10052;23866",
    "addr:street":"Ivor Rd",
    "iso:country":"US",
    "sg:address":"10052 Ivor Rd",
    "sg:city":"Ivor",
    "sg:classifiers":[
        {
            "category":"Building & Trades",
            "subcategory":"Cleaning & Sanitation",
            "type":"Services"
        }
    ],
    "sg:phone":"+1 757 859 6667",
    "sg:postcode":"23866",
    "sg:province":"VA",
    "sg:tags":[
        "janitorial"
    ],
    "wof:name":"Owens Custodial Service",
    "wof:placetype":"venue"
},
  "geometry": {"coordinates":[-76.946383,36.888196],"type":"Point"}
}