{
  "type": "Feature",
  "properties": {
    "addr:full":"100 Main St Warrenton VA 20186",
    "addr:housenumber":"100",
    "addr:postcode":"20186",
    "addr:street":"Main St",
    "iso:country":"US",
    "sg:address":"100 Main St",
    "sg:city":"Warrenton",
    "sg:classifiers":[
        {
            "category":"Organizations",
            "subcategory":"Non-profit Organization",
            "type":"Services"
        }
    ],
    "sg:phone":"+1 540 341 0175",
    "sg:postcode":"20186",
    "sg:province":"VA",
    "sg:tags":[
        "service/non-profit",
        "community"
    ],
    "wof:name":"Piedmont Envrnmntl",
    "wof:placetype":"venue"
},
  "geometry": {"coordinates":[-77.792911,38.71234],"type":"Point"}
}