{
  "type": "Feature",
  "properties": {
    "addr:full":"2001 International Dr Mc Lean VA 22102",
    "addr:housenumber":"2001",
    "addr:postcode":"22102",
    "addr:street":"International Dr",
    "iso:country":"US",
    "sg:address":"2001 International Dr",
    "sg:city":"Mc Lean",
    "sg:classifiers":[
        {
            "category":"Personal",
            "subcategory":"Beauty Salon",
            "type":"Services"
        },
        {
            "category":"Personal",
            "subcategory":"Barber",
            "type":"Services"
        }
    ],
    "sg:phone":"+1 703 821 8136",
    "sg:postcode":"22102",
    "sg:province":"VA",
    "sg:tags":[
        "hair"
    ],
    "wof:name":"Salon Cielo",
    "wof:placetype":"venue"
},
  "geometry": {"coordinates":[-77.224982,38.923259],"type":"Point"}
}