{
  "type": "Feature",
  "properties": {
    "addr:full":"7769 Euclid Way Springfield VA 22153",
    "addr:housenumber":"7769",
    "addr:postcode":"22153",
    "addr:street":"Euclid Way",
    "iso:country":"US",
    "sg:address":"7769 Euclid Way",
    "sg:city":"Springfield",
    "sg:classifiers":[
        {
            "category":"Travel",
            "subcategory":"Travel Agent",
            "type":"Entertainment"
        }
    ],
    "sg:phone":"+1 703 455 9375",
    "sg:postcode":"22153",
    "sg:province":"VA",
    "sg:tags":[
        "agency"
    ],
    "wof:name":"Second Childhood Vacations",
    "wof:placetype":"venue"
},
  "geometry": {"coordinates":[-77.21483499999999,38.733602],"type":"Point"}
}