{
  "type": "Feature",
  "properties": {
    "iso:country":"US",
    "sg:address":"3411 Valley Dr",
    "sg:city":"Alexandria",
    "sg:classifiers":[
        {
            "category":"Professional",
            "type":"Services"
        }
    ],
    "sg:phone":"+1 703 379 4441",
    "sg:postcode":"22302",
    "sg:province":"VA",
    "sg:tags":[
        "establishment"
    ],
    "wof:name":"KOVA",
    "wof:placetype":"venue"
},
  "geometry": {"coordinates":[-77.07932599999999,38.836991],"type":"Point"}
}