{
  "type": "Feature",
  "properties": {
    "iso:country":"US",
    "sg:address":"4968 Rugby Rd",
    "sg:city":"Virginia Beach",
    "sg:classifiers":[
        {
            "category":"Building & Trades",
            "subcategory":"Landscaping Services",
            "type":"Services"
        }
    ],
    "sg:phone":"+1 757 495 4565",
    "sg:postcode":"23464",
    "sg:province":"VA",
    "wof:name":"M & M Tree Services",
    "wof:placetype":"venue"
},
  "geometry": {"coordinates":[-76.159638,36.788115],"type":"Point"}
}