{
  "type": "Feature",
  "properties": {
    "addr:full":"5304 Lindsay St Fairfax VA 22032",
    "addr:housenumber":"5304",
    "addr:postcode":"22032",
    "addr:street":"Lindsay St",
    "iso:country":"US",
    "sg:address":"5304 Lindsay St",
    "sg:city":"Fairfax",
    "sg:classifiers":[
        {
            "category":"Professional",
            "type":"Services"
        }
    ],
    "sg:phone":"+1 703 591 8213",
    "sg:postcode":"22032",
    "sg:province":"VA",
    "sg:tags":[
        "establishment"
    ],
    "wof:name":"Bradley & Bradley",
    "wof:placetype":"venue"
},
  "geometry": {"coordinates":[-77.320893,38.813812],"type":"Point"}
}