{
  "type": "Feature",
  "properties": {
    "addr:full":"427 S Main St Emporia VA 23847",
    "addr:housenumber":"427",
    "addr:postcode":"23847",
    "addr:street":"S Main St",
    "iso:country":"US",
    "sg:address":"427 S Main St",
    "sg:city":"Emporia",
    "sg:classifiers":[
        {
            "category":"Organizations",
            "subcategory":"Community Association",
            "type":"Services"
        }
    ],
    "sg:phone":"+1 434 634 2822",
    "sg:postcode":"23847",
    "sg:province":"VA",
    "sg:tags":[
        "fraternal"
    ],
    "wof:name":"Widow's Son Lodge 150",
    "wof:placetype":"venue"
},
  "geometry": {"coordinates":[-77.543155,36.685322],"type":"Point"}
}