{
  "type": "Feature",
  "properties": {
    "iso:country":"US",
    "sg:address":"1008 Bowen Ct",
    "sg:city":"Great Falls",
    "sg:classifiers":[
        {
            "category":"Professional",
            "subcategory":"Business Services",
            "type":"Services"
        }
    ],
    "sg:phone":"+1 703 444 0404",
    "sg:postcode":"22066",
    "sg:province":"VA",
    "wof:name":"Autumn Hl Assoc Ltd Partnersh",
    "wof:placetype":"venue"
},
  "geometry": {"coordinates":[-77.331103,38.997658],"type":"Point"}
}