{
  "type": "Feature",
  "properties": {
    "addr:full":"2603 Mount Vernon Ave Alexandria VA 22301",
    "addr:housenumber":"2603",
    "addr:postcode":"22301",
    "addr:street":"Mount Vernon Ave",
    "iso:country":"US",
    "sg:address":"2603 Mount Vernon Ave",
    "sg:city":"Alexandria",
    "sg:classifiers":[
        {
            "category":"Restaurant",
            "type":"Food & Drink"
        }
    ],
    "sg:phone":"+1 703 518 8880",
    "sg:postcode":"22301",
    "sg:province":"VA",
    "sg:tags":[
        "asian",
        "chinese",
        "pan"
    ],
    "sg:website":"http://www.davecheng.com",
    "wof:name":"Tsim Yung Restaurant",
    "wof:placetype":"venue"
},
  "geometry": {"coordinates":[-77.059196,38.828602],"type":"Point"}
}