{
  "type": "Feature",
  "properties": {
    "addr:full":"26412 N Fork River Rd Saltville VA 24370",
    "addr:housenumber":"26412",
    "addr:postcode":"24370",
    "addr:street":"N Fork River Rd",
    "iso:country":"US",
    "sg:address":"26412 N Fork River Rd",
    "sg:city":"Saltville",
    "sg:classifiers":[
        {
            "category":"Professional",
            "subcategory":"Business Services",
            "type":"Services"
        }
    ],
    "sg:phone":"+1 276 944 3635",
    "sg:postcode":"24370",
    "sg:province":"VA",
    "sg:tags":[
        "telemarketing"
    ],
    "wof:name":"Successful Living",
    "wof:placetype":"venue"
},
  "geometry": {"coordinates":[-81.905181,36.831475],"type":"Point"}
}