{
  "type": "Feature",
  "properties": {
    "addr:full":"2699 Lee Hwy Troutville VA 24175",
    "addr:housenumber":"2699",
    "addr:postcode":"24175",
    "addr:street":"Lee Hwy",
    "iso:country":"US",
    "sg:address":"2699 Lee Hwy",
    "sg:city":"Troutville",
    "sg:classifiers":[
        {
            "category":"Home & Garden",
            "subcategory":"Building Materials",
            "type":"Retail Goods"
        }
    ],
    "sg:phone":"+1 540 992 1084",
    "sg:postcode":"24175",
    "sg:province":"VA",
    "sg:tags":[
        "lumber"
    ],
    "wof:name":"84 Lumber Co",
    "wof:placetype":"venue"
},
  "geometry": {"coordinates":[-79.903008,37.385497],"type":"Point"}
}