{
  "type": "Feature",
  "properties": {
    "iso:country":"US",
    "sg:address":"6566 Springfield Blvd",
    "sg:city":"Springfield",
    "sg:classifiers":[
        {
            "category":"Shopping",
            "subcategory":"Shoes",
            "type":"Retail Goods"
        }
    ],
    "sg:phone":"+1 703 924 0849",
    "sg:postcode":"22150",
    "sg:province":"VA",
    "sg:website":"www.journeys.com",
    "wof:name":"Journeys",
    "wof:placetype":"venue"
},
  "geometry": {"coordinates":[-77.18519499999999,38.777932],"type":"Point"}
}