{
  "type": "Feature",
  "properties": {
    "addr:full":"2700 S Quincy St Arlington VA 22206",
    "addr:housenumber":"2700",
    "addr:postcode":"22206",
    "addr:street":"S Quincy St",
    "iso:country":"US",
    "sg:address":"2700 S Quincy St",
    "sg:city":"Arlington",
    "sg:classifiers":[
        {
            "category":"Real Estate",
            "subcategory":"Real Estate Operator",
            "type":"Services"
        }
    ],
    "sg:phone":"+1 703 379 0007",
    "sg:postcode":"22206",
    "sg:province":"VA",
    "sg:tags":[
        "mall",
        "shopping",
        "center"
    ],
    "wof:name":"Federal Realty",
    "wof:placetype":"venue"
},
  "geometry": {"coordinates":[-77.086748,38.840796],"type":"Point"}
}