{
  "type": "Feature",
  "properties": {
    "addr:full":"21600 Cedar Ln Sterling VA 20166",
    "addr:housenumber":"21600",
    "addr:postcode":"20166",
    "addr:street":"Cedar Ln",
    "iso:country":"US",
    "sg:address":"21600 Cedar Ln",
    "sg:city":"Sterling",
    "sg:classifiers":[
        {
            "category":"Retail",
            "subcategory":"Auto Repair",
            "type":"Services"
        }
    ],
    "sg:phone":"+1 703 433 9100",
    "sg:postcode":"20166",
    "sg:province":"VA",
    "sg:tags":[
        "repairing",
        "automobile",
        "recreational",
        "campers-repair",
        "vehicle"
    ],
    "sg:website":"http://www.perfectionautocare.com",
    "wof:name":"Perfection Automotive Inc",
    "wof:placetype":"venue"
},
  "geometry": {"coordinates":[-77.420433,39.018801],"type":"Point"}
}