{
  "type": "Feature",
  "properties": {
    "addr:full":"108 Mactanley Staunton VA 24401",
    "addr:housenumber":"108",
    "addr:postcode":"24401",
    "addr:street":"Mactanley",
    "iso:country":"US",
    "sg:address":"108 Mactanley",
    "sg:city":"Staunton",
    "sg:classifiers":[
        {
            "category":"Health Services",
            "subcategory":"Doctor",
            "type":"Services"
        }
    ],
    "sg:phone":"+1 540 885 1281",
    "sg:postcode":"24401",
    "sg:province":"VA",
    "sg:tags":[
        "medical"
    ],
    "wof:name":"Godette George A Dr",
    "wof:placetype":"venue"
},
  "geometry": {"coordinates":[-79.05614799999999,38.168151],"type":"Point"}
}