{
  "type": "Feature",
  "properties": {
    "iso:country":"US",
    "sg:address":"3700 N Delaware St",
    "sg:city":"Arlington",
    "sg:classifiers":[
        {
            "category":"Building & Trades",
            "subcategory":"Electrical",
            "type":"Services"
        }
    ],
    "sg:phone":"+1 703 534 8820",
    "sg:postcode":"22207",
    "sg:province":"VA",
    "sg:tags":[
        "electrical",
        "contractor"
    ],
    "wof:name":"Coleys Electrical Service Inc",
    "wof:placetype":"venue"
},
  "geometry": {"coordinates":[-77.137406,38.91787],"type":"Point"}
}