{
  "type": "Feature",
  "properties": {
    "addr:full":"322 Oyster Point Rd Newport News VA 23602",
    "addr:housenumber":"322",
    "addr:postcode":"23602",
    "addr:street":"Oyster Point Rd",
    "iso:country":"US",
    "sg:address":"322 Oyster Point Rd",
    "sg:city":"Newport News",
    "sg:classifiers":[
        {
            "category":"Insurance",
            "subcategory":"Insurance Agent",
            "type":"Services"
        }
    ],
    "sg:phone":"+1 757 595 6677",
    "sg:postcode":"23602",
    "sg:province":"VA",
    "wof:name":"Allstate",
    "wof:placetype":"venue"
},
  "geometry": {"coordinates":[-76.507136,37.105792],"type":"Point"}
}