{
  "type": "Feature",
  "properties": {
    "addr:full":"15134 Abner Church Rd Glen Allen VA 23059",
    "addr:postcode":"15134;23059",
    "addr:street":"Church Rd",
    "iso:country":"US",
    "sg:address":"15134 Abner Church Rd",
    "sg:city":"Glen Allen",
    "sg:classifiers":[
        {
            "category":"Professional",
            "subcategory":"Advertising",
            "type":"Services"
        }
    ],
    "sg:phone":"+1 804 749 4062",
    "sg:postcode":"23059",
    "sg:province":"VA",
    "sg:tags":[
        "agency"
    ],
    "wof:name":"Amy Mendelson Design Inc",
    "wof:placetype":"venue"
},
  "geometry": {"coordinates":[-77.617784,37.722194],"type":"Point"}
}