{
  "type": "Feature",
  "properties": {
    "addr:full":"100 Arboretum Pl Richmond VA 23236",
    "addr:housenumber":"100",
    "addr:postcode":"23236",
    "addr:street":"Arboretum Pl",
    "iso:country":"US",
    "sg:address":"100 Arboretum Pl",
    "sg:city":"Richmond",
    "sg:classifiers":[
        {
            "category":"Personal",
            "subcategory":"Beauty Salon",
            "type":"Services"
        }
    ],
    "sg:phone":"+1 804 560 1780",
    "sg:postcode":"23236",
    "sg:province":"VA",
    "wof:name":"Carlson Studio's",
    "wof:placetype":"venue"
},
  "geometry": {"coordinates":[-77.567762,37.496503],"type":"Point"}
}