{
  "type": "Feature",
  "properties": {
    "iso:country":"US",
    "sg:address":"44 Summer E",
    "sg:city":"Williamsburg",
    "sg:classifiers":[
        {
            "category":"Real Estate",
            "subcategory":"Real Estate Agent",
            "type":"Services"
        }
    ],
    "sg:phone":"+1 757 229 6666",
    "sg:postcode":"23188",
    "sg:province":"VA",
    "wof:name":"C A Roemer Homes & Properties",
    "wof:placetype":"venue"
},
  "geometry": {"coordinates":[-76.75917699999999,37.320971],"type":"Point"}
}