{
  "type": "Feature",
  "properties": {
    "addr:full":"917 Rougemont Ave Charlottesville VA 22902",
    "addr:housenumber":"917",
    "addr:postcode":"22902",
    "addr:street":"Rougemont Ave",
    "iso:country":"US",
    "sg:address":"917 Rougemont Ave",
    "sg:city":"Charlottesville",
    "sg:classifiers":[
        {
            "category":"Home & Garden",
            "subcategory":"Building Materials",
            "type":"Retail Goods"
        }
    ],
    "sg:phone":"+1 434 295 0711",
    "sg:postcode":"22902",
    "sg:province":"VA",
    "sg:tags":[
        "construction",
        "electrical"
    ],
    "wof:name":"Southern Lights LLC",
    "wof:placetype":"venue"
},
  "geometry": {"coordinates":[-78.48017900000001,38.014673],"type":"Point"}
}