{
  "type": "Feature",
  "properties": {
    "addr:full":"407 S Washington St Alexandria VA 22314",
    "addr:housenumber":"407",
    "addr:postcode":"22314",
    "addr:street":"S Washington St",
    "iso:country":"US",
    "sg:address":"407 S Washington St",
    "sg:city":"Alexandria",
    "sg:classifiers":[
        {
            "category":"Personal",
            "subcategory":"Beauty Salon",
            "type":"Services"
        }
    ],
    "sg:phone":"+1 703 683 4321",
    "sg:postcode":"22314",
    "sg:province":"VA",
    "sg:tags":[
        "shop"
    ],
    "wof:name":"Silhouette Hair Design",
    "wof:placetype":"venue"
},
  "geometry": {"coordinates":[-77.048002,38.800589],"type":"Point"}
}