{
  "type": "Feature",
  "properties": {
    "addr:full":"417 Fairfax Way Williamsburg VA 23185",
    "addr:housenumber":"417",
    "addr:postcode":"23185",
    "addr:street":"Fairfax Way",
    "iso:country":"US",
    "sg:address":"417 Fairfax Way",
    "sg:city":"Williamsburg",
    "sg:classifiers":[
        {
            "category":"Professional",
            "subcategory":"Business Services",
            "type":"Services"
        }
    ],
    "sg:phone":"+1 203 366 5396",
    "sg:postcode":"23185",
    "sg:province":"VA",
    "wof:name":"A Pleasant Place",
    "wof:placetype":"venue"
},
  "geometry": {"coordinates":[-76.68436,37.23038],"type":"Point"}
}