{
  "type": "Feature",
  "properties": {
    "addr:full":"8611 Woodwren Ln Fairfax Station VA 22039",
    "addr:housenumber":"8611",
    "addr:postcode":"22039",
    "addr:street":"Woodwren Ln",
    "iso:country":"US",
    "sg:address":"8611 Woodwren Ln",
    "sg:city":"Fairfax Station",
    "sg:classifiers":[
        {
            "category":"Professional",
            "subcategory":"Management & Consulting",
            "type":"Services"
        }
    ],
    "sg:phone":"+1 703 690 4289",
    "sg:postcode":"22039",
    "sg:province":"VA",
    "sg:tags":[
        "business"
    ],
    "wof:name":"West Edie",
    "wof:placetype":"venue"
},
  "geometry": {"coordinates":[-77.278346,38.722943],"type":"Point"}
}