{
  "type": "Feature",
  "properties": {
    "addr:full":"3160 Kings Mountain Rd Martinsville VA 24112",
    "addr:housenumber":"3160",
    "addr:postcode":"24112",
    "addr:street":"Kings Mountain Rd",
    "iso:country":"US",
    "sg:address":"3160 Kings Mountain Rd",
    "sg:city":"Martinsville",
    "sg:classifiers":[
        {
            "category":"Government",
            "subcategory":"Court House",
            "type":"Public Place"
        }
    ],
    "sg:phone":"+1 276 634 4880",
    "sg:postcode":"24112",
    "sg:province":"VA",
    "wof:name":"Martinsville City Circuit Crt",
    "wof:placetype":"venue"
},
  "geometry": {"coordinates":[-79.88862399999999,36.740985],"type":"Point"}
}