{
  "type": "Feature",
  "properties": {
    "iso:country":"US",
    "sg:address":"3000 Goodwin Neck Rd",
    "sg:city":"Yorktown",
    "sg:classifiers":[
        {
            "category":"Recreation",
            "type":"Entertainment"
        }
    ],
    "sg:phone":"+1 757 890 3850",
    "sg:postcode":"23692",
    "sg:province":"VA",
    "sg:tags":[
        "parks"
    ],
    "wof:name":"Back Creek Park",
    "wof:placetype":"venue"
},
  "geometry": {"coordinates":[-76.438045,37.207969],"type":"Point"}
}