{
  "type": "Feature",
  "properties": {
    "addr:full":"18729 Fuller Heights Rd Triangle VA 22172",
    "addr:housenumber":"18729",
    "addr:postcode":"22172",
    "addr:street":"Fuller Heights Rd",
    "iso:country":"US",
    "sg:address":"18729 Fuller Heights Rd",
    "sg:city":"Triangle",
    "sg:classifiers":[
        {
            "category":"Autos & Motor Vehicles",
            "subcategory":"Fuel & Gas Station",
            "type":"Retail Goods"
        }
    ],
    "sg:phone":"+1 703 221 4747",
    "sg:postcode":"22172",
    "sg:province":"VA",
    "sg:tags":[
        "automotive",
        "station",
        "gasoline",
        "tire"
    ],
    "wof:name":"Triangle Recap & Auto Service",
    "wof:placetype":"venue"
},
  "geometry": {"coordinates":[-77.333004,38.545181],"type":"Point"}
}