{
  "type": "Feature",
  "properties": {
    "iso:country":"US",
    "sg:address":"3315 Duke St",
    "sg:city":"Alexandria",
    "sg:classifiers":[
        {
            "category":"Professional",
            "subcategory":"Employment Agencies",
            "type":"Services"
        }
    ],
    "sg:phone":"+1 703 504 6999",
    "sg:postcode":"22314",
    "sg:province":"VA",
    "sg:tags":[
        "help",
        "supply"
    ],
    "wof:name":"Commgroup Inc",
    "wof:placetype":"venue"
},
  "geometry": {"coordinates":[-77.088497,38.808551],"type":"Point"}
}