{
  "type": "Feature",
  "properties": {
    "addr:full":"6525 Scandia Lakes Pl Sandston VA 23150",
    "addr:postcode":"6525;23150",
    "addr:street":"Scandia Lakes Pl",
    "iso:country":"US",
    "sg:address":"6525 Scandia Lakes Pl",
    "sg:city":"Sandston",
    "sg:classifiers":[
        {
            "category":"Professional",
            "type":"Services"
        }
    ],
    "sg:phone":"+1 804 328 0813",
    "sg:postcode":"23150",
    "sg:province":"VA",
    "wof:name":"Scandia Corporation",
    "wof:placetype":"venue"
},
  "geometry": {"coordinates":[-77.194419,37.483529],"type":"Point"}
}