{
  "type": "Feature",
  "properties": {
    "addr:full":"1610 Chapman Ave SW Roanoke VA 24016",
    "addr:housenumber":"1610",
    "addr:postcode":"24016",
    "addr:street":"Chapman Ave Sw",
    "iso:country":"US",
    "sg:address":"1610 Chapman Ave SW",
    "sg:city":"Roanoke",
    "sg:classifiers":[
        {
            "category":"Building & Trades",
            "subcategory":"Construction",
            "type":"Services"
        }
    ],
    "sg:phone":"+1 540 343 0001",
    "sg:postcode":"24016",
    "sg:province":"VA",
    "sg:tags":[
        "contractor"
    ],
    "wof:name":"Dirt Cheap Roofing",
    "wof:placetype":"venue"
},
  "geometry": {"coordinates":[-79.969611,37.272597],"type":"Point"}
}