{
  "type": "Feature",
  "properties": {
    "iso:country":"US",
    "sg:address":"1880 Howard Ave Ste 101",
    "sg:city":"Vienna",
    "sg:classifiers":[
        {
            "category":"Health Services",
            "subcategory":"Clinic",
            "type":"Services"
        },
        {
            "category":"Health Services",
            "subcategory":"Health Practitioner",
            "type":"Services"
        },
        {
            "category":"Community Center",
            "type":"Public Place"
        }
    ],
    "sg:phone":"+1 703 749 0223",
    "sg:postcode":"22182",
    "sg:province":"VA",
    "sg:tags":[
        "medical",
        "therapist",
        "therapy",
        "physical"
    ],
    "wof:name":"Advanced Physical Therapy",
    "wof:placetype":"venue"
},
  "geometry": {"coordinates":[-77.234663,38.915651],"type":"Point"}
}