{
  "type": "Feature",
  "properties": {
    "iso:country":"US",
    "sg:address":"1715 N George Mason Dr Ste 402",
    "sg:city":"Arlington",
    "sg:classifiers":[
        {
            "category":"Health Services",
            "subcategory":"Doctor",
            "type":"Services"
        }
    ],
    "sg:phone":"+1 703 248 0006",
    "sg:postcode":"22205",
    "sg:province":"VA",
    "wof:name":"Allcock Edward G",
    "wof:placetype":"venue"
},
  "geometry": {"coordinates":[-77.12866699999999,38.889957],"type":"Point"}
}