{
  "type": "Feature",
  "properties": {
    "addr:full":"17 Hammett Ln Fredericksburg VA 22406",
    "addr:housenumber":"17",
    "addr:postcode":"22406",
    "addr:street":"Hammett Ln",
    "iso:country":"US",
    "sg:address":"17 Hammett Ln",
    "sg:city":"Fredericksburg",
    "sg:classifiers":[
        {
            "category":"Freight",
            "type":"Transportation"
        }
    ],
    "sg:phone":"+1 540 752 2392",
    "sg:postcode":"22406",
    "sg:province":"VA",
    "sg:tags":[
        "operator",
        "trucking"
    ],
    "wof:name":"Raelee Inc",
    "wof:placetype":"venue"
},
  "geometry": {"coordinates":[-77.539333,38.371224],"type":"Point"}
}