{
  "type": "Feature",
  "properties": {
    "iso:country":"US",
    "sg:address":"105 Eakin St SW",
    "sg:city":"Blacksburg",
    "sg:classifiers":[
        {
            "category":"Wholesale",
            "subcategory":"Machinery & Supplies",
            "type":"Manufacturing & Wholesale Goods"
        }
    ],
    "sg:phone":"+1 540 557 5699",
    "sg:postcode":"24060",
    "sg:province":"VA",
    "sg:tags":[
        "equipment",
        "industrial"
    ],
    "wof:name":"Engineered Systems & Products",
    "wof:placetype":"venue"
},
  "geometry": {"coordinates":[-80.409085,37.224768],"type":"Point"}
}