{
  "type": "Feature",
  "properties": {
    "addr:full":"66 Arden Dr Newport News VA 23601",
    "addr:housenumber":"66",
    "addr:postcode":"23601",
    "addr:street":"Arden Dr",
    "iso:country":"US",
    "sg:address":"66 Arden Dr",
    "sg:city":"Newport News",
    "sg:classifiers":[
        {
            "category":"Health Services",
            "subcategory":"Clinic",
            "type":"Services"
        }
    ],
    "sg:phone":"+1 757 591 0799",
    "sg:postcode":"23601",
    "sg:province":"VA",
    "wof:name":"American Healthcare Providers",
    "wof:placetype":"venue"
},
  "geometry": {"coordinates":[-76.45443899999999,37.055876],"type":"Point"}
}