{
  "type": "Feature",
  "properties": {
    "addr:full":"18354 Shady Pine Ln Windsor VA 23487",
    "addr:housenumber":"18354",
    "addr:postcode":"23487",
    "addr:street":"Shady Pine Ln",
    "iso:country":"US",
    "sg:address":"18354 Shady Pine Ln",
    "sg:city":"Windsor",
    "sg:classifiers":[
        {
            "category":"Building & Trades",
            "subcategory":"Landscaping Services",
            "type":"Services"
        }
    ],
    "sg:phone":"+1 757 255 4518",
    "sg:postcode":"23487",
    "sg:province":"VA",
    "wof:name":"Lawsons Septic Tank Service",
    "wof:placetype":"venue"
},
  "geometry": {"coordinates":[-76.607218,36.869175],"type":"Point"}
}