{
  "type": "Feature",
  "properties": {
    "iso:country":"US",
    "sg:address":"11166 Main St",
    "sg:city":"Fairfax",
    "sg:classifiers":[
        {
            "category":"Health Services",
            "subcategory":"Doctor",
            "type":"Services"
        }
    ],
    "sg:phone":"+1 703 691 3015",
    "sg:postcode":"22030",
    "sg:province":"VA",
    "sg:tags":[
        "dentist"
    ],
    "wof:name":"Fair Lakes Dental Svc Inc",
    "wof:placetype":"venue"
},
  "geometry": {"coordinates":[-77.32970400000001,38.855172],"type":"Point"}
}