{
  "type": "Feature",
  "properties": {
    "addr:full":"2200 Palmer St Portsmouth VA 23704",
    "addr:housenumber":"2200",
    "addr:postcode":"23704",
    "addr:street":"Palmer St",
    "iso:country":"US",
    "sg:address":"2200 Palmer St",
    "sg:city":"Portsmouth",
    "sg:classifiers":[
        {
            "category":"Organizations",
            "subcategory":"Religious Organization",
            "type":"Services"
        }
    ],
    "sg:phone":"+1 757 397 6953",
    "sg:postcode":"23704",
    "sg:province":"VA",
    "sg:tags":[
        "church"
    ],
    "wof:name":"Christian Antioch Chrch of God",
    "wof:placetype":"venue"
},
  "geometry": {"coordinates":[-76.321303,36.822707],"type":"Point"}
}