{
  "type": "Feature",
  "properties": {
    "iso:country":"US",
    "sg:address":"3830 Parkland Dr",
    "sg:city":"Fairfax",
    "sg:classifiers":[
        {
            "category":"Retail",
            "subcategory":"Repair Shop",
            "type":"Services"
        }
    ],
    "sg:phone":"+1 703 627 4054",
    "sg:postcode":"22033",
    "sg:province":"VA",
    "sg:tags":[
        "watch"
    ],
    "wof:name":"LA Precision",
    "wof:placetype":"venue"
},
  "geometry": {"coordinates":[-77.358999,38.871103],"type":"Point"}
}