{
  "type": "Feature",
  "properties": {
    "addr:full":"288 Crickett Ln Pearisburg VA 24134",
    "addr:housenumber":"288",
    "addr:postcode":"24134",
    "addr:street":"Crickett Ln",
    "iso:country":"US",
    "sg:address":"288 Crickett Ln",
    "sg:city":"Pearisburg",
    "sg:classifiers":[
        {
            "category":"Real Estate",
            "subcategory":"Architect",
            "type":"Services"
        }
    ],
    "sg:phone":"+1 540 921 2629",
    "sg:postcode":"24134",
    "sg:province":"VA",
    "sg:tags":[
        "architectural"
    ],
    "wof:name":"John W Wood III",
    "wof:placetype":"venue"
},
  "geometry": {"coordinates":[-80.700918,37.326833],"type":"Point"}
}