{
  "type": "Feature",
  "properties": {
    "addr:full":"3151 Sandy Hook Rd Sandy Hook VA 23065",
    "addr:housenumber":"3151",
    "addr:postcode":"23065",
    "addr:street":"Sandy Hook Rd",
    "iso:country":"US",
    "sg:address":"3151 Sandy Hook Rd",
    "sg:city":"Sandy Hook",
    "sg:classifiers":[
        {
            "category":"Freight",
            "type":"Transportation"
        }
    ],
    "sg:phone":"+1 804 556 6455",
    "sg:postcode":"23065",
    "sg:province":"VA",
    "sg:tags":[
        "operator",
        "local",
        "trucking"
    ],
    "wof:name":"JW Mealy Hauling Co",
    "wof:placetype":"venue"
},
  "geometry": {"coordinates":[-77.90274599999999,37.765739],"type":"Point"}
}