{
  "type": "Feature",
  "properties": {
    "addr:full":"7023 Old Dominion Dr Mc Lean VA 22101",
    "addr:housenumber":"7023",
    "addr:postcode":"22101",
    "addr:street":"Old Dominion Dr",
    "iso:country":"US",
    "sg:address":"7023 Old Dominion Dr",
    "sg:city":"Mc Lean",
    "sg:classifiers":[
        {
            "category":"Wholesale",
            "subcategory":"Construction Materials",
            "type":"Manufacturing & Wholesale Goods"
        }
    ],
    "sg:phone":"+1 703 749 6167",
    "sg:postcode":"22101",
    "sg:province":"VA",
    "sg:tags":[
        "marble"
    ],
    "wof:name":"Granite & Marble Inc",
    "wof:placetype":"venue"
},
  "geometry": {"coordinates":[-77.18768900000001,38.93776],"type":"Point"}
}