{
  "type": "Feature",
  "properties": {
    "iso:country":"US",
    "sg:address":"1102 Fishing Bay Rd",
    "sg:city":"Deltaville",
    "sg:classifiers":[
        {
            "category":"Recreation",
            "subcategory":"Marina",
            "type":"Entertainment"
        }
    ],
    "sg:phone":"+1 804 776 9776",
    "sg:postcode":"23043",
    "sg:province":"VA",
    "wof:name":"Ruark Marinas Inc",
    "wof:placetype":"venue"
},
  "geometry": {"coordinates":[-76.340423,37.542546],"type":"Point"}
}