{
  "type": "Feature",
  "properties": {
    "iso:country":"US",
    "sg:address":"2845 Subtle Ln",
    "sg:city":"Fairfax",
    "sg:classifiers":[
        {
            "category":"Professional",
            "subcategory":"Management & Consulting",
            "type":"Services"
        }
    ],
    "sg:phone":"+1 703 560 4643",
    "sg:postcode":"22031",
    "sg:province":"VA",
    "sg:tags":[
        "teacher"
    ],
    "wof:name":"Ngandu Mulumba",
    "wof:placetype":"venue"
},
  "geometry": {"coordinates":[-77.251283,38.875354],"type":"Point"}
}