{
  "type": "Feature",
  "properties": {
    "addr:full":"2602 Gay Ave Richmond VA 23231",
    "addr:housenumber":"2602",
    "addr:postcode":"23231",
    "addr:street":"Gay Ave",
    "iso:country":"US",
    "sg:address":"2602 Gay Ave",
    "sg:city":"Richmond",
    "sg:classifiers":[
        {
            "category":"Professional",
            "subcategory":"Business Services",
            "type":"Services"
        }
    ],
    "sg:phone":"+1 804 222 2602",
    "sg:postcode":"23231",
    "sg:province":"VA",
    "wof:name":"Atlas Assoc Ltd",
    "wof:placetype":"venue"
},
  "geometry": {"coordinates":[-77.38084499999999,37.525622],"type":"Point"}
}