{
  "type": "Feature",
  "properties": {
    "iso:country":"US",
    "sg:address":"17258 Doggetts Fork Rd",
    "sg:city":"Ruther Glen",
    "sg:classifiers":[
        {
            "category":"Manufacturing",
            "subcategory":"Wood Products",
            "type":"Manufacturing & Wholesale Goods"
        },
        {
            "category":"Manufacturing",
            "subcategory":"Lumber",
            "type":"Manufacturing & Wholesale Goods"
        }
    ],
    "sg:phone":"+1 804 633 9737",
    "sg:postcode":"22546",
    "sg:province":"VA",
    "sg:tags":[
        "mill",
        "logging"
    ],
    "wof:name":"W T Jones & Sons Inc",
    "wof:placetype":"venue"
},
  "geometry": {"coordinates":[-77.350787,37.899117],"type":"Point"}
}