{
  "type": "Feature",
  "properties": {
    "addr:full":"13241 Piedmont Vista Dr Haymarket VA 20169",
    "addr:housenumber":"13241",
    "addr:postcode":"20169",
    "addr:street":"Piedmont Vista Dr",
    "iso:country":"US",
    "sg:address":"13241 Piedmont Vista Dr",
    "sg:city":"Haymarket",
    "sg:classifiers":[
        {
            "category":"Real Estate",
            "subcategory":"Real Estate Services",
            "type":"Services"
        }
    ],
    "sg:phone":"+1 703 906 2175",
    "sg:postcode":"20169",
    "sg:province":"VA",
    "sg:website":"www.haymarketrealtygroup.com",
    "wof:name":"Haymarket Realty Group - RE/MAX Unlimited",
    "wof:placetype":"venue"
},
  "geometry": {"coordinates":[-77.612143,38.828551],"type":"Point"}
}