{
  "type": "Feature",
  "properties": {
    "addr:full":"8028 E Boulevard Dr Alexandria VA 22308",
    "addr:housenumber":"8028 e",
    "addr:postcode":"22308",
    "addr:street":"Boulevard Dr",
    "iso:country":"US",
    "sg:address":"8028 E Boulevard Dr",
    "sg:city":"Alexandria",
    "sg:classifiers":[
        {
            "category":"Organizations",
            "subcategory":"Religious Organization",
            "type":"Services"
        }
    ],
    "sg:phone":"+1 703 765 7565",
    "sg:postcode":"22308",
    "sg:province":"VA",
    "wof:name":"Baptist Womens Conventio",
    "wof:placetype":"venue"
},
  "geometry": {"coordinates":[-77.047316,38.740228],"type":"Point"}
}