{
  "type": "Feature",
  "properties": {
    "addr:full":"9900 Manet Rd Burke VA 22015",
    "addr:postcode":"9900;22015",
    "addr:street":"Manet Rd",
    "iso:country":"US",
    "sg:address":"9900 Manet Rd",
    "sg:city":"Burke",
    "sg:classifiers":[
        {
            "category":"Professional",
            "type":"Services"
        }
    ],
    "sg:phone":"+1 703 978 0853",
    "sg:postcode":"22015",
    "sg:province":"VA",
    "wof:name":"Lawrence Cautilli",
    "wof:placetype":"venue"
},
  "geometry": {"coordinates":[-77.28672400000001,38.780705],"type":"Point"}
}