{
  "type": "Feature",
  "properties": {
    "iso:country":"US",
    "sg:address":"5226 Chowan Ave",
    "sg:city":"Alexandria",
    "sg:classifiers":[
        {
            "category":"Professional",
            "subcategory":"Computer Services",
            "type":"Services"
        }
    ],
    "sg:phone":"+1 703 914 9155",
    "sg:postcode":"22312",
    "sg:province":"VA",
    "sg:tags":[
        "development",
        "software"
    ],
    "wof:name":"Yellow House Associates LLC",
    "wof:placetype":"venue"
},
  "geometry": {"coordinates":[-77.15885400000001,38.80864],"type":"Point"}
}