{
  "type": "Feature",
  "properties": {
    "addr:full":"4425 Turners Creek Rd Ferrum VA 24088",
    "addr:housenumber":"4425",
    "addr:postcode":"24088",
    "addr:street":"Turners Creek Rd",
    "iso:country":"US",
    "sg:address":"4425 Turners Creek Rd",
    "sg:city":"Ferrum",
    "sg:classifiers":[
        {
            "category":"Professional",
            "type":"Services"
        }
    ],
    "sg:phone":"+1 540 365 1143",
    "sg:postcode":"24088",
    "sg:province":"VA",
    "wof:name":"Nickelston",
    "wof:placetype":"venue"
},
  "geometry": {"coordinates":[-80.101291,36.953705],"type":"Point"}
}