{
  "type": "Feature",
  "properties": {
    "addr:full":"214 E Main St Front Royal VA 22630",
    "addr:housenumber":"214",
    "addr:postcode":"22630",
    "addr:street":"E Main St",
    "iso:country":"US",
    "sg:address":"214 E Main St",
    "sg:city":"Front Royal",
    "sg:classifiers":[
        {
            "category":"Shopping",
            "subcategory":"Jewelry",
            "type":"Retail Goods"
        }
    ],
    "sg:phone":"+1 540 622 2647",
    "sg:postcode":"22630",
    "sg:province":"VA",
    "sg:tags":[
        "jeweler"
    ],
    "wof:name":"Nicolle's Jewelry Designs",
    "wof:placetype":"venue"
},
  "geometry": {"coordinates":[-78.19159399999999,38.917856],"type":"Point"}
}