{
  "type": "Feature",
  "properties": {
    "iso:country":"US",
    "sg:address":"126 Quay St",
    "sg:city":"Alexandria",
    "sg:classifiers":[
        {
            "category":"Building & Trades",
            "subcategory":"Construction",
            "type":"Services"
        }
    ],
    "sg:phone":"+1 703 549 2482",
    "sg:postcode":"22314",
    "sg:province":"VA",
    "sg:tags":[
        "contractor"
    ],
    "wof:name":"Noash Nogales",
    "wof:placetype":"venue"
},
  "geometry": {"coordinates":[-77.03997699999999,38.807114],"type":"Point"}
}