{
  "type": "Feature",
  "properties": {
    "iso:country":"US",
    "sg:address":"1920 Rossini Dr",
    "sg:city":"Virginia Beach",
    "sg:classifiers":[
        {
            "category":"Professional",
            "subcategory":"Business Services",
            "type":"Services"
        }
    ],
    "sg:phone":"+1 757 721 2595",
    "sg:postcode":"23454",
    "sg:province":"VA",
    "sg:tags":[
        "evaluator",
        "program"
    ],
    "wof:name":"George H Schauer",
    "wof:placetype":"venue"
},
  "geometry": {"coordinates":[-76.004457,36.772696],"type":"Point"}
}