{
  "type": "Feature",
  "properties": {
    "iso:country":"US",
    "sg:address":"8001 Hooes Rd",
    "sg:city":"Springfield",
    "sg:classifiers":[
        {
            "category":"Professional",
            "type":"Services"
        }
    ],
    "sg:phone":"+1 703 451 5661",
    "sg:postcode":"22152",
    "sg:province":"VA",
    "wof:name":"Aarons Services",
    "wof:placetype":"venue"
},
  "geometry": {"coordinates":[-77.221887,38.75816],"type":"Point"}
}