{
  "type": "Feature",
  "properties": {
    "addr:full":"11072 Washington Hwy Glen Allen VA 23059",
    "addr:housenumber":"11072",
    "addr:postcode":"23059",
    "addr:street":"Washington Hwy",
    "iso:country":"US",
    "sg:address":"11072 Washington Hwy",
    "sg:city":"Glen Allen",
    "sg:classifiers":[
        {
            "category":"Manufacturing",
            "subcategory":"Motor Vehicles & Parts",
            "type":"Manufacturing & Wholesale Goods"
        }
    ],
    "sg:phone":"+1 804 752 2811",
    "sg:postcode":"23059",
    "sg:province":"VA",
    "sg:tags":[
        "equipment",
        "truck"
    ],
    "wof:name":"Terex Utilities",
    "wof:placetype":"venue"
},
  "geometry": {"coordinates":[-77.464952,37.703867],"type":"Point"}
}