{
  "type": "Feature",
  "properties": {
    "addr:full":"721 Candlers Mountain Rd Rustburg VA 24588",
    "addr:housenumber":"721",
    "addr:postcode":"24588",
    "addr:street":"Candlers Mountain Rd",
    "iso:country":"US",
    "sg:address":"721 Candlers Mountain Rd",
    "sg:city":"Rustburg",
    "sg:classifiers":[
        {
            "category":"Organizations",
            "subcategory":"Religious Organization",
            "type":"Services"
        }
    ],
    "sg:phone":"+1 434 237 3447",
    "sg:postcode":"24588",
    "sg:province":"VA",
    "sg:tags":[
        "church"
    ],
    "wof:name":"NSA Ministries Inc",
    "wof:placetype":"venue"
},
  "geometry": {"coordinates":[-79.16166800000001,37.328283],"type":"Point"}
}