{
  "type": "Feature",
  "properties": {
    "iso:country":"US",
    "sg:address":"2101 S Crystal Dr",
    "sg:city":"Arlington",
    "sg:classifiers":[
        {
            "category":"Shopping",
            "subcategory":"Jewelry",
            "type":"Retail Goods"
        }
    ],
    "sg:phone":"+1 703 683 2678",
    "sg:postcode":"22202",
    "sg:province":"VA",
    "sg:tags":[
        "jeweler"
    ],
    "sg:website":"www.pearl-oasis.com",
    "wof:name":"Pearl Oasis",
    "wof:placetype":"venue"
},
  "geometry": {"coordinates":[-77.04949499999999,38.854238],"type":"Point"}
}