{
  "type": "Feature",
  "properties": {
    "iso:country":"US",
    "sg:address":"9811 Nokesville Rd",
    "sg:city":"Manassas",
    "sg:classifiers":[
        {
            "category":"Retail",
            "subcategory":"Auto Repair",
            "type":"Services"
        }
    ],
    "sg:phone":"+1 703 361 8108",
    "sg:postcode":"20110",
    "sg:province":"VA",
    "sg:tags":[
        "automotive",
        "gasoline",
        "general"
    ],
    "wof:name":"Alexs Towing & Repair Service",
    "wof:placetype":"venue"
},
  "geometry": {"coordinates":[-77.493467,38.751791],"type":"Point"}
}