{
  "type": "Feature",
  "properties": {
    "iso:country":"US",
    "sg:address":"2474 E Little Creek Rd",
    "sg:city":"Norfolk",
    "sg:classifiers":[
        {
            "category":"Professional",
            "subcategory":"Lawyer & Legal Services",
            "type":"Services"
        }
    ],
    "sg:phone":"+1 757 588 2300",
    "sg:postcode":"23518",
    "sg:province":"VA",
    "wof:name":"Miller & Marx PC",
    "wof:placetype":"venue"
},
  "geometry": {"coordinates":[-76.21329299999999,36.915323],"type":"Point"}
}