{
  "type": "Feature",
  "properties": {
    "iso:country":"US",
    "sg:address":"3928 Ruthwin Ln",
    "sg:city":"Richmond",
    "sg:classifiers":[
        {
            "category":"Building & Trades",
            "subcategory":"Construction",
            "type":"Services"
        }
    ],
    "sg:phone":"+1 804 743 8607",
    "sg:postcode":"23234",
    "sg:province":"VA",
    "sg:tags":[
        "home",
        "apartment",
        "family",
        "construct",
        "contractor"
    ],
    "wof:name":"John Szilagyi General Cont",
    "wof:placetype":"venue"
},
  "geometry": {"coordinates":[-77.46601699999999,37.43378],"type":"Point"}
}