{
  "type": "Feature",
  "properties": {
    "addr:full":"228 N Donnawood Dr Virginia Beach VA 23452",
    "addr:housenumber":"228",
    "addr:postcode":"23452",
    "addr:street":"N Donnawood Dr",
    "iso:country":"US",
    "sg:address":"228 N Donnawood Dr",
    "sg:city":"Virginia Beach",
    "sg:classifiers":[
        {
            "category":"Insurance",
            "subcategory":"Insurance Agent",
            "type":"Services"
        }
    ],
    "sg:phone":"+1 757 498 7266",
    "sg:postcode":"23452",
    "sg:province":"VA",
    "wof:name":"Olson Insurance",
    "wof:placetype":"venue"
},
  "geometry": {"coordinates":[-76.099186,36.830123],"type":"Point"}
}