{
  "type": "Feature",
  "properties": {
    "addr:full":"912 Professional Pl Chesapeake VA 23320",
    "addr:housenumber":"912",
    "addr:postcode":"23320",
    "addr:street":"Professional Pl",
    "iso:country":"US",
    "sg:address":"912 Professional Pl",
    "sg:city":"Chesapeake",
    "sg:classifiers":[
        {
            "category":"Personal",
            "type":"Services"
        }
    ],
    "sg:phone":"+1 757 549 3501",
    "sg:postcode":"23320",
    "sg:province":"VA",
    "wof:name":"Peak Performance",
    "wof:placetype":"venue"
},
  "geometry": {"coordinates":[-76.232429,36.763019],"type":"Point"}
}