{
  "type": "Feature",
  "properties": {
    "addr:full":"924 Queen St Alexandria VA 22314",
    "addr:housenumber":"924",
    "addr:postcode":"22314",
    "addr:street":"Queen St",
    "iso:country":"US",
    "sg:address":"924 Queen St",
    "sg:city":"Alexandria",
    "sg:classifiers":[
        {
            "category":"Personal",
            "subcategory":"Beauty Salon",
            "type":"Services"
        }
    ],
    "sg:phone":"+1 703 683 0688",
    "sg:postcode":"22314",
    "sg:province":"VA",
    "sg:tags":[
        "manicuring"
    ],
    "wof:name":"Nail Spa 360",
    "wof:placetype":"venue"
},
  "geometry": {"coordinates":[-77.04960199999999,38.807653],"type":"Point"}
}