{
  "type": "Feature",
  "properties": {
    "addr:full":"1101 N Wilson Blvd Arlington VA 22209",
    "addr:housenumber":"1101",
    "addr:postcode":"22209",
    "addr:street":"N Wilson Blvd",
    "iso:country":"US",
    "sg:address":"1101 N Wilson Blvd",
    "sg:city":"Arlington",
    "sg:classifiers":[
        {
            "category":"Professional",
            "subcategory":"Management & Consulting",
            "type":"Services"
        },
        {
            "category":"Social Services",
            "subcategory":"Job Training",
            "type":"Services"
        }
    ],
    "sg:phone":"+1 703 524 1200",
    "sg:postcode":"22209",
    "sg:province":"VA",
    "sg:tags":[
        "consultant",
        "program"
    ],
    "sg:website":"www.gettips.com",
    "wof:name":"Health Communications Inc",
    "wof:placetype":"venue"
},
  "geometry": {"coordinates":[-77.070802,38.895091],"type":"Point"}
}