{
  "type": "Feature",
  "properties": {
    "iso:country":"US",
    "sg:address":"204 S Jefferson St",
    "sg:city":"Roanoke",
    "sg:classifiers":[
        {
            "category":"Banks & Credit Unions",
            "subcategory":"Bank",
            "type":"Services"
        }
    ],
    "sg:phone":"+1 540 342 7747",
    "sg:postcode":"24011",
    "sg:province":"VA",
    "sg:tags":[
        "mortgage"
    ],
    "wof:name":"Resource Mortgage",
    "wof:placetype":"venue"
},
  "geometry": {"coordinates":[-79.940494,37.271192],"type":"Point"}
}