{
  "type": "Feature",
  "properties": {
    "addr:full":"301 Terrie Dr Sterling VA 20165",
    "addr:housenumber":"301",
    "addr:postcode":"20165",
    "addr:street":"Terrie Dr",
    "iso:country":"US",
    "sg:address":"301 Terrie Dr",
    "sg:city":"Sterling",
    "sg:classifiers":[
        {
            "category":"Building & Trades",
            "subcategory":"Construction",
            "type":"Services"
        }
    ],
    "sg:phone":"+1 703 444 0203",
    "sg:postcode":"20165",
    "sg:province":"VA",
    "sg:tags":[
        "roofing",
        "industrial",
        "contractors-commercial",
        "contractor"
    ],
    "wof:name":"R W Hoffman Roofing Co Inc",
    "wof:placetype":"venue"
},
  "geometry": {"coordinates":[-77.403961,39.04285],"type":"Point"}
}