{
  "type": "Feature",
  "properties": {
    "addr:full":"8503 Arlington Blvd Fairfax VA 22031",
    "addr:housenumber":"8503",
    "addr:postcode":"22031",
    "addr:street":"Arlington Blvd",
    "iso:country":"US",
    "sg:address":"8503 Arlington Blvd",
    "sg:city":"Fairfax",
    "sg:classifiers":[
        {
            "category":"Health Services",
            "subcategory":"Medical Lab",
            "type":"Services"
        }
    ],
    "sg:phone":"+1 703 573 6298",
    "sg:postcode":"22031",
    "sg:province":"VA",
    "sg:tags":[
        "laboratory"
    ],
    "wof:name":"Laboratory Corporation America",
    "wof:placetype":"venue"
},
  "geometry": {"coordinates":[-77.240196,38.865352],"type":"Point"}
}