{
  "type": "Feature",
  "properties": {
    "iso:country":"US",
    "sg:address":"400 Ray C Hunt Dr",
    "sg:city":"Charlottesville",
    "sg:classifiers":[
        {
            "category":"Health Services",
            "subcategory":"Doctor",
            "type":"Services"
        }
    ],
    "sg:phone":"+1 434 243 0266",
    "sg:postcode":"22903",
    "sg:province":"VA",
    "sg:tags":[
        "physician",
        "surgeon"
    ],
    "wof:name":"Vincent Arlet MD",
    "wof:placetype":"venue"
},
  "geometry": {"coordinates":[-78.52483100000001,38.025964],"type":"Point"}
}