{
  "type": "Feature",
  "properties": {
    "addr:full":"532 Virginia Beach Blvd Virginia Beach VA 23451",
    "addr:housenumber":"532",
    "addr:postcode":"23451",
    "addr:street":"Virginia Beach Blvd",
    "iso:country":"US",
    "sg:address":"532 Virginia Beach Blvd",
    "sg:city":"Virginia Beach",
    "sg:classifiers":[
        {
            "category":"Building & Trades",
            "subcategory":"Equipment Rental",
            "type":"Services"
        }
    ],
    "sg:phone":"+1 757 428 8368",
    "sg:postcode":"23451",
    "sg:province":"VA",
    "sg:tags":[
        "party",
        "tent",
        "supply"
    ],
    "wof:name":"Affordble Tents Special Events",
    "wof:placetype":"venue"
},
  "geometry": {"coordinates":[-75.980614,36.844191],"type":"Point"}
}