{
  "type": "Feature",
  "properties": {
    "iso:country":"US",
    "sg:address":"980 N Liberty St",
    "sg:city":"Harrisonburg",
    "sg:classifiers":[
        {
            "category":"Shopping",
            "subcategory":"Bicycles & Sporting Goods",
            "type":"Retail Goods"
        }
    ],
    "sg:phone":"+1 540 432 0280",
    "sg:postcode":"22802",
    "sg:province":"VA",
    "sg:tags":[
        "snowboard",
        "parts"
    ],
    "sg:website":"www.blueridgecycleworks.com",
    "wof:name":"Blue Ridge Cycleworks Inc",
    "wof:placetype":"venue"
},
  "geometry": {"coordinates":[-78.864649,38.463631],"type":"Point"}
}