{
  "type": "Feature",
  "properties": {
    "addr:full":"19 Cleveland Ave Martinsville VA 24112",
    "addr:housenumber":"19",
    "addr:postcode":"24112",
    "addr:street":"Cleveland Ave",
    "iso:country":"US",
    "sg:address":"19 Cleveland Ave",
    "sg:city":"Martinsville",
    "sg:classifiers":[
        {
            "category":"Health Services",
            "subcategory":"Doctor",
            "type":"Services"
        }
    ],
    "sg:phone":"+1 276 632 5655",
    "sg:postcode":"24112",
    "sg:province":"VA",
    "sg:tags":[
        "dentist"
    ],
    "wof:name":"Kenneth B Midkiff LTD",
    "wof:placetype":"venue"
},
  "geometry": {"coordinates":[-79.867278,36.688354],"type":"Point"}
}