{
  "type": "Feature",
  "properties": {
    "iso:country":"US",
    "sg:address":"809 Water Elm Ct",
    "sg:city":"Chesapeake",
    "sg:classifiers":[
        {
            "category":"Professional",
            "subcategory":"Employment Agencies",
            "type":"Services"
        }
    ],
    "sg:phone":"+1 757 567 2140",
    "sg:postcode":"23320",
    "sg:province":"VA",
    "wof:name":"Luis Ortega",
    "wof:placetype":"venue"
},
  "geometry": {"coordinates":[-76.268698,36.742789],"type":"Point"}
}