{
  "type": "Feature",
  "properties": {
    "addr:full":"8665 Sudley Rd Manassas VA 20110",
    "addr:housenumber":"8665",
    "addr:postcode":"20110",
    "addr:street":"Sudley Rd",
    "iso:country":"US",
    "sg:address":"8665 Sudley Rd",
    "sg:city":"Manassas",
    "sg:classifiers":[
        {
            "category":"Arts & Performance",
            "subcategory":"Theater",
            "type":"Entertainment"
        }
    ],
    "sg:phone":"+1 703 530 8144",
    "sg:postcode":"20110",
    "sg:province":"VA",
    "sg:tags":[
        "development",
        "control",
        "medical",
        "access",
        "p",
        "card",
        "smart"
    ],
    "wof:name":"Passnet",
    "wof:placetype":"venue"
},
  "geometry": {"coordinates":[-77.485848,38.76831],"type":"Point"}
}