{
  "type": "Feature",
  "properties": {
    "iso:country":"US",
    "sg:address":"924 W Grace St",
    "sg:city":"Richmond",
    "sg:classifiers":[
        {
            "category":"Restaurant",
            "type":"Food & Drink"
        }
    ],
    "sg:menulink":"http://www.allmenus.com/va/richmond/17852-eastern-buffet/menu/",
    "sg:phone":"+1 804 340 2863",
    "sg:postcode":"23220",
    "sg:province":"VA",
    "sg:tags":[
        "asian",
        "chinese"
    ],
    "wof:name":"Eastern Buffet",
    "wof:placetype":"venue"
},
  "geometry": {"coordinates":[-77.451965,37.550212],"type":"Point"}
}