{
  "type": "Feature",
  "properties": {
    "iso:country":"US",
    "sg:address":"13452 Bethel Church Rd",
    "sg:city":"Mears",
    "sg:classifiers":[
        {
            "category":"Retail",
            "subcategory":"Auto Repair",
            "type":"Services"
        }
    ],
    "sg:phone":"+1 757 824 5841",
    "sg:postcode":"23359",
    "sg:province":"VA",
    "sg:tags":[
        "farm",
        "corn",
        "cash",
        "general",
        "grain",
        "soybean",
        "operator",
        "truck"
    ],
    "wof:name":"J & K Auto Truck Repair",
    "wof:placetype":"venue"
},
  "geometry": {"coordinates":[-75.59795,37.856774],"type":"Point"}
}