{
  "type": "Feature",
  "properties": {
    "addr:full":"62 Potomac Creek Dr Fredericksburg VA 22405",
    "addr:housenumber":"62",
    "addr:postcode":"22405",
    "addr:street":"Potomac Creek Dr",
    "iso:country":"US",
    "sg:address":"62 Potomac Creek Dr",
    "sg:city":"Fredericksburg",
    "sg:classifiers":[
        {
            "category":"Shopping",
            "subcategory":"Bicycles & Sporting Goods",
            "type":"Retail Goods"
        }
    ],
    "sg:phone":"+1 540 720 5922",
    "sg:postcode":"22405",
    "sg:province":"VA",
    "sg:tags":[
        "repair"
    ],
    "sg:website":"www.indoorrange.com",
    "wof:name":"Range",
    "wof:placetype":"venue"
},
  "geometry": {"coordinates":[-77.441858,38.380048],"type":"Point"}
}