{
  "type": "Feature",
  "properties": {
    "iso:country":"US",
    "sg:address":"4177 Drew Ridge Dr",
    "sg:city":"Louisa",
    "sg:classifiers":[
        {
            "category":"Professional",
            "subcategory":"Detective & Security Services",
            "type":"Services"
        }
    ],
    "sg:phone":"+1 804 457 2130",
    "sg:postcode":"23093",
    "sg:province":"VA",
    "sg:tags":[
        "information",
        "bureau"
    ],
    "wof:name":"Crawford & Company",
    "wof:placetype":"venue"
},
  "geometry": {"coordinates":[-78.018344,37.855171],"type":"Point"}
}