{
  "type": "Feature",
  "properties": {
    "iso:country":"US",
    "sg:address":"7701 Telegraph Rd",
    "sg:city":"Alexandria",
    "sg:classifiers":[
        {
            "category":"Building & Trades",
            "subcategory":"Construction",
            "type":"Services"
        }
    ],
    "sg:phone":"+1 703 799 1953",
    "sg:postcode":"22315",
    "sg:province":"VA",
    "wof:name":"Freestate Electrical Constr",
    "wof:placetype":"venue"
},
  "geometry": {"coordinates":[-77.142833,38.748632],"type":"Point"}
}