{
  "type": "Feature",
  "properties": {
    "iso:country":"US",
    "sg:address":"1914 Princess Anne St",
    "sg:city":"Fredericksburg",
    "sg:classifiers":[
        {
            "category":"Travel",
            "subcategory":"Hotels & Motels",
            "type":"Entertainment"
        }
    ],
    "sg:phone":"+1 540 373 5539",
    "sg:postcode":"22401",
    "sg:province":"VA",
    "wof:name":"Colonial Motel",
    "wof:placetype":"venue"
},
  "geometry": {"coordinates":[-77.466691,38.311831],"type":"Point"}
}