{
  "type": "Feature",
  "properties": {
    "addr:full":"21351 Ridgetop Cir Sterling VA 20166",
    "addr:housenumber":"21351",
    "addr:postcode":"20166",
    "addr:street":"Ridgetop Cir",
    "iso:country":"US",
    "sg:address":"21351 Ridgetop Cir",
    "sg:city":"Sterling",
    "sg:classifiers":[
        {
            "category":"Professional",
            "type":"Services"
        },
        {
            "category":"Professional",
            "subcategory":"Computer Services",
            "type":"Services"
        }
    ],
    "sg:phone":"+1 703 450 5545",
    "sg:postcode":"20166",
    "sg:province":"VA",
    "sg:tags":[
        "programming",
        "design",
        "system",
        "custom"
    ],
    "wof:name":"Matchcraft Inc",
    "wof:placetype":"venue"
},
  "geometry": {"coordinates":[-77.410752,39.031355],"type":"Point"}
}