{
  "type": "Feature",
  "properties": {
    "iso:country":"US",
    "sg:address":"1000 Centerville Tpke S",
    "sg:city":"Chesapeake",
    "sg:classifiers":[
        {
            "category":"Manufacturing",
            "subcategory":"Metals",
            "type":"Manufacturing & Wholesale Goods"
        }
    ],
    "sg:phone":"+1 757 482 5555",
    "sg:postcode":"23322",
    "sg:province":"VA",
    "sg:tags":[
        "building",
        "prefabricated",
        "m",
        "mfg"
    ],
    "wof:name":"Chesapeake Barns",
    "wof:placetype":"venue"
},
  "geometry": {"coordinates":[-76.18479499999999,36.691812],"type":"Point"}
}