{
  "type": "Feature",
  "properties": {
    "addr:full":"8350 Traford Ln Springfield VA 22152",
    "addr:housenumber":"8350",
    "addr:postcode":"22152",
    "addr:street":"Traford Ln",
    "iso:country":"US",
    "sg:address":"8350 Traford Ln",
    "sg:city":"Springfield",
    "sg:classifiers":[
        {
            "category":"Health Services",
            "subcategory":"Optometrist",
            "type":"Services"
        }
    ],
    "sg:phone":"+1 703 569 6363",
    "sg:postcode":"22152",
    "sg:province":"VA",
    "wof:name":"Michael J Davidson Od PC",
    "wof:placetype":"venue"
},
  "geometry": {"coordinates":[-77.232378,38.781444],"type":"Point"}
}