{
  "type": "Feature",
  "properties": {
    "addr:full":"799 Ripshin Rd Trout Dale VA 24378",
    "addr:housenumber":"799",
    "addr:postcode":"24378",
    "addr:street":"Ripshin Rd;Dale",
    "iso:country":"US",
    "sg:address":"799 Ripshin Rd",
    "sg:city":"Trout Dale",
    "sg:classifiers":[
        {
            "category":"Building & Trades",
            "subcategory":"Equipment Rental",
            "type":"Services"
        }
    ],
    "sg:phone":"+1 276 677 3606",
    "sg:postcode":"24378",
    "sg:province":"VA",
    "sg:tags":[
        "real",
        "property",
        "lessor"
    ],
    "wof:name":"Green Willow Farm",
    "wof:placetype":"venue"
},
  "geometry": {"coordinates":[-81.439156,36.702346],"type":"Point"}
}