{
  "type": "Feature",
  "properties": {
    "addr:full":"5537 Hempstead Way Springfield VA 22151",
    "addr:housenumber":"5537",
    "addr:postcode":"22151",
    "addr:street":"Hempstead Way",
    "iso:country":"US",
    "sg:address":"5537 Hempstead Way",
    "sg:city":"Springfield",
    "sg:phone":"+1 703 642 1120",
    "sg:postcode":"22151",
    "sg:province":"VA",
    "sg:tags":[
        "internet"
    ],
    "wof:name":"Crosslink Internet Services",
    "wof:placetype":"venue"
},
  "geometry": {"coordinates":[-77.18626,38.800035],"type":"Point"}
}