{
  "type": "Feature",
  "properties": {
    "iso:country":"US",
    "sg:address":"726 Norton Ln",
    "sg:city":"Rural Retreat",
    "sg:classifiers":[
        {
            "category":"Retail",
            "subcategory":"Repair Shop",
            "type":"Services"
        }
    ],
    "sg:phone":"+1 276 686 2074",
    "sg:postcode":"24368",
    "sg:province":"VA",
    "sg:tags":[
        "welding"
    ],
    "wof:name":"Jim Overbay Welding",
    "wof:placetype":"venue"
},
  "geometry": {"coordinates":[-81.37651200000001,36.897565],"type":"Point"}
}