{
  "type": "Feature",
  "properties": {
    "addr:full":"2711 Buford Rd Richmond VA 23235",
    "addr:housenumber":"2711",
    "addr:postcode":"23235",
    "addr:street":"Buford Rd",
    "iso:country":"US",
    "sg:address":"2711 Buford Rd",
    "sg:city":"Richmond",
    "sg:classifiers":[
        {
            "category":"Professional",
            "subcategory":"Lawyer & Legal Services",
            "type":"Services"
        }
    ],
    "sg:phone":"+1 804 379 8131",
    "sg:postcode":"23235",
    "sg:province":"VA",
    "sg:tags":[
        "attorney"
    ],
    "wof:name":"Krane & Assoc",
    "wof:placetype":"venue"
},
  "geometry": {"coordinates":[-77.561442,37.53507],"type":"Point"}
}