{
  "type": "Feature",
  "properties": {
    "addr:full":"17 Matilda Ln Montross VA 22520",
    "addr:housenumber":"17",
    "addr:postcode":"22520",
    "addr:street":"Matilda Ln",
    "iso:country":"US",
    "sg:address":"17 Matilda Ln",
    "sg:city":"Montross",
    "sg:classifiers":[
        {
            "category":"Building & Trades",
            "subcategory":"Construction",
            "type":"Services"
        }
    ],
    "sg:phone":"+1 804 493 0286",
    "sg:postcode":"22520",
    "sg:province":"VA",
    "sg:tags":[
        "carpentry",
        "contractor"
    ],
    "wof:name":"Zells Carpentry",
    "wof:placetype":"venue"
},
  "geometry": {"coordinates":[-76.801742,38.157244],"type":"Point"}
}