{
  "type": "Feature",
  "properties": {
    "addr:full":"2772 S Arlington Mill Dr Arlington VA 22206",
    "addr:housenumber":"2772",
    "addr:postcode":"22206",
    "addr:street":"S Arlington Mill Dr",
    "iso:country":"US",
    "sg:address":"2772 S Arlington Mill Dr",
    "sg:city":"Arlington",
    "sg:classifiers":[
        {
            "category":"Personal",
            "type":"Services"
        },
        {
            "category":"Sports & Exercise",
            "subcategory":"Gym",
            "type":"Entertainment"
        },
        {
            "category":"Health Services",
            "subcategory":"Health Practitioner",
            "type":"Services"
        },
        {
            "category":"Arena",
            "subcategory":"Sports Club",
            "type":"Entertainment"
        }
    ],
    "sg:phone":"+1 800 615 7352",
    "sg:postcode":"22206",
    "sg:province":"VA",
    "sg:tags":[
        "control",
        "weight",
        "consultant",
        "trainer",
        "program",
        "fitness",
        "physical"
    ],
    "sg:website":"http://washingtondc.citysearch.com/profile/external/41520307/arlington_va/curves.html?publisher=yellowpages&reference_id=1&placement=ypwebsitemip",
    "wof:name":"Curves",
    "wof:placetype":"venue"
},
  "geometry": {"coordinates":[-77.08866999999999,38.841921],"type":"Point"}
}