{
  "type": "Feature",
  "properties": {
    "addr:full":"17 N Franklin St Christiansburg VA 24073",
    "addr:housenumber":"17",
    "addr:postcode":"24073",
    "addr:street":"N Franklin St",
    "iso:country":"US",
    "sg:address":"17 N Franklin St",
    "sg:city":"Christiansburg",
    "sg:classifiers":[
        {
            "category":"Real Estate",
            "subcategory":"Real Estate Agent",
            "type":"Services"
        }
    ],
    "sg:phone":"+1 540 382 0271",
    "sg:postcode":"24073",
    "sg:province":"VA",
    "sg:tags":[
        "manager"
    ],
    "wof:name":"Dan Myers Inc",
    "wof:placetype":"venue"
},
  "geometry": {"coordinates":[-80.41042400000001,37.131102],"type":"Point"}
}