{
  "type": "Feature",
  "properties": {
    "iso:country":"US",
    "sg:address":"13518 Warwick Blvd",
    "sg:city":"Newport News",
    "sg:classifiers":[
        {
            "category":"Retail",
            "subcategory":"Laundry & Dry Cleaning",
            "type":"Services"
        }
    ],
    "sg:phone":"+1 757 886 0539",
    "sg:postcode":"23602",
    "sg:province":"VA",
    "wof:name":"Scrub A Dub",
    "wof:placetype":"venue"
},
  "geometry": {"coordinates":[-76.52134599999999,37.117266],"type":"Point"}
}