{
  "type": "Feature",
  "properties": {
    "iso:country":"US",
    "sg:address":"4391 Ironbound Rd",
    "sg:city":"Williamsburg",
    "sg:classifiers":[
        {
            "category":"Retail",
            "subcategory":"Repair Shop",
            "type":"Services"
        }
    ],
    "sg:phone":"+1 757 258 3188",
    "sg:postcode":"23188",
    "sg:province":"VA",
    "sg:tags":[
        "refinishing",
        "furniture"
    ],
    "wof:name":"Furniture Clinic",
    "wof:placetype":"venue"
},
  "geometry": {"coordinates":[-76.735846,37.283513],"type":"Point"}
}