{
  "type": "Feature",
  "properties": {
    "iso:country":"US",
    "sg:address":"304 Lewis St NW",
    "sg:city":"Vienna",
    "sg:classifiers":[
        {
            "category":"Professional",
            "type":"Services"
        }
    ],
    "sg:phone":"+1 703 242 6459",
    "sg:postcode":"22180",
    "sg:province":"VA",
    "wof:name":"Eric Peterson",
    "wof:placetype":"venue"
},
  "geometry": {"coordinates":[-77.27382,38.900364],"type":"Point"}
}