{
  "type": "Feature",
  "properties": {
    "addr:full":"11890 Sunrise Valley Dr Reston VA 20191",
    "addr:housenumber":"11890",
    "addr:postcode":"20191",
    "addr:street":"Sunrise Valley Dr",
    "iso:country":"US",
    "sg:address":"11890 Sunrise Valley Dr",
    "sg:city":"Reston",
    "sg:classifiers":[
        {
            "category":"Real Estate",
            "subcategory":"Real Estate Agent",
            "type":"Services"
        }
    ],
    "sg:phone":"+1 703 476 8451",
    "sg:postcode":"20191",
    "sg:province":"VA",
    "wof:name":"Coldwell Banker",
    "wof:placetype":"venue"
},
  "geometry": {"coordinates":[-77.35911,38.946061],"type":"Point"}
}