{
  "type": "Feature",
  "properties": {
    "addr:full":"1638 Carl D Silver Pkwy Fredericksburg VA 22401",
    "addr:housenumber":"1638",
    "addr:postcode":"22401",
    "addr:street":"Carl D Silver Pkwy",
    "iso:country":"US",
    "sg:address":"1638 Carl D Silver Pkwy",
    "sg:city":"Fredericksburg",
    "sg:classifiers":[
        {
            "category":"Restaurant",
            "type":"Food & Drink"
        }
    ],
    "sg:phone":"+1 540 548 8048",
    "sg:postcode":"22401",
    "sg:province":"VA",
    "sg:website":"www.buffalowildwings.com",
    "wof:name":"Buffalo Wild Wings Grill & Bar",
    "wof:placetype":"venue"
},
  "geometry": {"coordinates":[-77.507902,38.303318],"type":"Point"}
}