{
  "type": "Feature",
  "properties": {
    "addr:full":"7761 Cunningham Rd Bristol VA 24202",
    "addr:housenumber":"7761",
    "addr:postcode":"24202",
    "addr:street":"Cunningham Rd",
    "iso:country":"US",
    "sg:address":"7761 Cunningham Rd",
    "sg:city":"Bristol",
    "sg:classifiers":[
        {
            "category":"Professional",
            "subcategory":"Engineering",
            "type":"Services"
        }
    ],
    "sg:phone":"+1 276 466 9125",
    "sg:postcode":"24202",
    "sg:province":"VA",
    "wof:name":"Eds Enterprises Inc",
    "wof:placetype":"venue"
},
  "geometry": {"coordinates":[-82.224242,36.605779],"type":"Point"}
}