{
  "type": "Feature",
  "properties": {
    "iso:country":"US",
    "sg:address":"3415 Starboard St",
    "sg:city":"Greenbackville",
    "sg:classifiers":[
        {
            "category":"Building & Trades",
            "subcategory":"Cleaning & Sanitation",
            "type":"Services"
        }
    ],
    "sg:phone":"+1 757 854 4395",
    "sg:postcode":"23356",
    "sg:province":"VA",
    "sg:tags":[
        "maintenance"
    ],
    "wof:name":"Aardvark Janitorial Services",
    "wof:placetype":"venue"
},
  "geometry": {"coordinates":[-75.424595,37.986442],"type":"Point"}
}