{
  "type": "Feature",
  "properties": {
    "iso:country":"US",
    "sg:address":"430 Long Green Ln",
    "sg:city":"Winchester",
    "sg:classifiers":[
        {
            "category":"Professional",
            "type":"Services"
        }
    ],
    "sg:phone":"+1 540 723 0086",
    "sg:postcode":"22603",
    "sg:province":"VA",
    "sg:tags":[
        "establishment"
    ],
    "wof:name":"Wilson & Wilson",
    "wof:placetype":"venue"
},
  "geometry": {"coordinates":[-78.18889,39.223797],"type":"Point"}
}