{
  "type": "Feature",
  "properties": {
    "iso:country":"US",
    "sg:address":"4505 Kennebeck Ave",
    "sg:city":"Norfolk",
    "sg:classifiers":[
        {
            "category":"Organizations",
            "subcategory":"Community Association",
            "type":"Services"
        }
    ],
    "sg:phone":"+1 757 857 5628",
    "sg:postcode":"23513",
    "sg:province":"VA",
    "wof:name":"B T W Athletic Boosters",
    "wof:placetype":"venue"
},
  "geometry": {"coordinates":[-76.23982100000001,36.88106],"type":"Point"}
}