{
  "type": "Feature",
  "properties": {
    "addr:full":"1578 5th St Hampton VA 23665",
    "addr:housenumber":"1578",
    "addr:postcode":"23665",
    "addr:street":"5Th St",
    "iso:country":"US",
    "sg:address":"1578 5th St",
    "sg:city":"Hampton",
    "sg:classifiers":[
        {
            "category":"Real Estate",
            "subcategory":"Real Estate Agent",
            "type":"Services"
        }
    ],
    "sg:phone":"+1 757 303 1848",
    "sg:postcode":"23665",
    "sg:province":"VA",
    "wof:name":"Solution Home Buyers Inc",
    "wof:placetype":"venue"
},
  "geometry": {"coordinates":[-76.422186,37.097867],"type":"Point"}
}