{
  "type": "Feature",
  "properties": {
    "addr:full":"17065 Seals Rd Bowling Green VA 22427",
    "addr:housenumber":"17065",
    "addr:postcode":"22427",
    "addr:street":"Seals Rd",
    "iso:country":"US",
    "sg:address":"17065 Seals Rd",
    "sg:city":"Bowling Green",
    "sg:classifiers":[
        {
            "category":"Organizations",
            "subcategory":"Religious Organization",
            "type":"Services"
        }
    ],
    "sg:phone":"+1 804 633 5946",
    "sg:postcode":"22427",
    "sg:province":"VA",
    "wof:name":"First Mt Zion Baptist Church",
    "wof:placetype":"venue"
},
  "geometry": {"coordinates":[-77.223128,38.029473],"type":"Point"}
}