{
  "type": "Feature",
  "properties": {
    "addr:full":"4512 Eden Dr NW Roanoke VA 24012",
    "addr:housenumber":"4512",
    "addr:postcode":"24012",
    "addr:street":"Eden Dr Nw",
    "iso:country":"US",
    "sg:address":"4512 Eden Dr NW",
    "sg:city":"Roanoke",
    "sg:classifiers":[
        {
            "category":"Real Estate",
            "subcategory":"Real Estate Services",
            "type":"Services"
        },
        {
            "category":"Building & Trades",
            "subcategory":"Cleaning & Sanitation",
            "type":"Services"
        }
    ],
    "sg:phone":"+1 540 330 6214",
    "sg:postcode":"24012",
    "sg:province":"VA",
    "sg:tags":[
        "maintenance",
        "cleaners-interior"
    ],
    "wof:name":"Active Maintenance And Rep",
    "wof:placetype":"venue"
},
  "geometry": {"coordinates":[-79.954942,37.310446],"type":"Point"}
}