{
  "type": "Feature",
  "properties": {
    "addr:full":"3400 Old Forest Rd Lynchburg VA 24501",
    "addr:housenumber":"3400",
    "addr:postcode":"24501",
    "addr:street":"Old Forest Rd",
    "iso:country":"US",
    "sg:address":"3400 Old Forest Rd",
    "sg:city":"Lynchburg",
    "sg:classifiers":[
        {
            "category":"Retail",
            "subcategory":"Auto Repair",
            "type":"Services"
        }
    ],
    "sg:phone":"+1 434 385 8088",
    "sg:postcode":"24501",
    "sg:province":"VA",
    "sg:tags":[
        "body"
    ],
    "wof:name":"Blue Ridge Collision Inc",
    "wof:placetype":"venue"
},
  "geometry": {"coordinates":[-79.21289400000001,37.410774],"type":"Point"}
}