{
  "type": "Feature",
  "properties": {
    "iso:country":"US",
    "sg:address":"1301 Oak Hill Dr",
    "sg:city":"Charlottesville",
    "sg:classifiers":[
        {
            "category":"Professional",
            "subcategory":"Business Services",
            "type":"Services"
        }
    ],
    "sg:phone":"+1 434 977 1444",
    "sg:postcode":"22902",
    "sg:province":"VA",
    "wof:name":"A Corporate Express",
    "wof:placetype":"venue"
},
  "geometry": {"coordinates":[-78.51363600000001,38.002075],"type":"Point"}
}