{
  "type": "Feature",
  "properties": {
    "iso:country":"US",
    "sg:address":"11930 Dumfries Rd",
    "sg:city":"Manassas",
    "sg:classifiers":[
        {
            "category":"Government",
            "subcategory":"Office",
            "type":"Public Place"
        }
    ],
    "sg:phone":"+1 703 791 3181",
    "sg:postcode":"20112",
    "sg:province":"VA",
    "wof:name":"Prince William Cnty Detention",
    "wof:placetype":"venue"
},
  "geometry": {"coordinates":[-77.44253999999999,38.695651],"type":"Point"}
}