{
  "type": "Feature",
  "properties": {
    "addr:full":"713 Shamrock Dr Fredericksburg VA 22407",
    "addr:housenumber":"713",
    "addr:postcode":"22407",
    "addr:street":"Shamrock Dr",
    "iso:country":"US",
    "sg:address":"713 Shamrock Dr",
    "sg:city":"Fredericksburg",
    "sg:classifiers":[
        {
            "category":"Retail",
            "subcategory":"Car Wash",
            "type":"Services"
        }
    ],
    "sg:phone":"+1 540 786 2691",
    "sg:postcode":"22407",
    "sg:province":"VA",
    "wof:name":"Altas Power Wash",
    "wof:placetype":"venue"
},
  "geometry": {"coordinates":[-77.54874100000001,38.280887],"type":"Point"}
}