{
  "type": "Feature",
  "properties": {
    "addr:full":"8195 Smith Mill Ln Bridgewater VA 22812",
    "addr:housenumber":"8195",
    "addr:postcode":"22812",
    "addr:street":"Smith Mill Ln",
    "iso:country":"US",
    "sg:address":"8195 Smith Mill Ln",
    "sg:city":"Bridgewater",
    "sg:classifiers":[
        {
            "category":"Professional",
            "subcategory":"Business Services",
            "type":"Services"
        }
    ],
    "sg:phone":"+1 540 828 4035",
    "sg:postcode":"22812",
    "sg:province":"VA",
    "wof:name":"Rj2 Enterprises LLC",
    "wof:placetype":"venue"
},
  "geometry": {"coordinates":[-79.10043400000001,38.430438],"type":"Point"}
}