{
  "type": "Feature",
  "properties": {
    "addr:full":"14020 Thunderbolt Pl Chantilly VA 20151",
    "addr:housenumber":"14020",
    "addr:postcode":"20151",
    "addr:street":"Thunderbolt Pl",
    "iso:country":"US",
    "sg:address":"14020 Thunderbolt Pl",
    "sg:city":"Chantilly",
    "sg:classifiers":[
        {
            "category":"Professional",
            "subcategory":"Engineering",
            "type":"Services"
        }
    ],
    "sg:phone":"+1 703 464 1000",
    "sg:postcode":"20151",
    "sg:province":"VA",
    "sg:tags":[
        "civil",
        "consulting",
        "engineer"
    ],
    "sg:website":"www.bowmanconsulting.com",
    "wof:name":"Bowman Consulting Group Ltd",
    "wof:placetype":"venue"
},
  "geometry": {"coordinates":[-77.432563,38.899407],"type":"Point"}
}