{
  "type": "Feature",
  "properties": {
    "iso:country":"US",
    "sg:address":"3319 Lakecrest Rd",
    "sg:city":"Virginia Beach",
    "sg:classifiers":[
        {
            "category":"Retail",
            "subcategory":"Repair Shop",
            "type":"Services"
        }
    ],
    "sg:phone":"+1 757 631 4862",
    "sg:postcode":"23452",
    "sg:province":"VA",
    "wof:name":"Infinity Cleaning",
    "wof:placetype":"venue"
},
  "geometry": {"coordinates":[-76.089005,36.81239],"type":"Point"}
}