{
  "type": "Feature",
  "properties": {
    "iso:country":"US",
    "sg:address":"400 Old Franklin Tpke",
    "sg:city":"Rocky Mount",
    "sg:classifiers":[
        {
            "category":"Shopping",
            "type":"Retail Goods"
        }
    ],
    "sg:phone":"+1 540 489 3866",
    "sg:postcode":"24151",
    "sg:province":"VA",
    "sg:tags":[
        "merchandise"
    ],
    "wof:name":"One Stop Cellular Inc",
    "wof:placetype":"venue"
},
  "geometry": {"coordinates":[-79.872327,37.009788],"type":"Point"}
}