{
  "type": "Feature",
  "properties": {
    "addr:full":"9912 Georgetown Pike Great Falls VA 22066",
    "addr:housenumber":"9912",
    "addr:postcode":"22066",
    "addr:street":"Georgetown Pike",
    "iso:country":"US",
    "sg:address":"9912 Georgetown Pike",
    "sg:city":"Great Falls",
    "sg:classifiers":[
        {
            "category":"Wholesale",
            "subcategory":"Non-durable Goods",
            "type":"Manufacturing & Wholesale Goods"
        }
    ],
    "sg:phone":"+1 703 757 1700",
    "sg:postcode":"22066",
    "sg:province":"VA",
    "sg:tags":[
        "advertising"
    ],
    "wof:name":"Trinket Depot LLC",
    "wof:placetype":"venue"
},
  "geometry": {"coordinates":[-77.289642,38.998417],"type":"Point"}
}