{
  "type": "Feature",
  "properties": {
    "addr:full":"11120 Patterson Ave Richmond VA 23238",
    "addr:housenumber":"11120",
    "addr:postcode":"23238",
    "addr:street":"Patterson Ave",
    "iso:country":"US",
    "sg:address":"11120 Patterson Ave",
    "sg:city":"Richmond",
    "sg:classifiers":[
        {
            "category":"Food & Beverages",
            "subcategory":"Fruits & Vegetables",
            "type":"Retail Goods"
        }
    ],
    "sg:phone":"+1 804 754 0484",
    "sg:postcode":"23238",
    "sg:province":"VA",
    "sg:tags":[
        "produce"
    ],
    "wof:name":"Jim and Robins Produce",
    "wof:placetype":"venue"
},
  "geometry": {"coordinates":[-77.617304,37.597556],"type":"Point"}
}