{
  "type": "Feature",
  "properties": {
    "addr:full":"208 E Main St Richmond VA 23219",
    "addr:housenumber":"208",
    "addr:postcode":"23219",
    "addr:street":"E Main St",
    "iso:country":"US",
    "sg:address":"208 E Main St",
    "sg:city":"Richmond",
    "sg:classifiers":[
        {
            "category":"Professional",
            "subcategory":"Lawyer & Legal Services",
            "type":"Services"
        }
    ],
    "sg:phone":"+1 804 644 9431",
    "sg:postcode":"23219",
    "sg:province":"VA",
    "sg:tags":[
        "attorney"
    ],
    "wof:name":"George W Sadler Jr",
    "wof:placetype":"venue"
},
  "geometry": {"coordinates":[-77.441706,37.54154],"type":"Point"}
}