{
  "type": "Feature",
  "properties": {
    "addr:full":"4862 Woolwine Hwy Stuart VA 24171",
    "addr:postcode":"4862;24171",
    "addr:street":"Woolwine Hwy",
    "iso:country":"US",
    "sg:address":"4862 Woolwine Hwy",
    "sg:city":"Stuart",
    "sg:classifiers":[
        {
            "category":"Wholesale",
            "subcategory":"Construction Materials",
            "type":"Manufacturing & Wholesale Goods"
        }
    ],
    "sg:phone":"+1 276 930 3068",
    "sg:postcode":"24171",
    "sg:province":"VA",
    "sg:tags":[
        "lumber"
    ],
    "wof:name":"Pilson Brothers Lumber Inc",
    "wof:placetype":"venue"
},
  "geometry": {"coordinates":[-80.243602,36.729311],"type":"Point"}
}