{
  "type": "Feature",
  "properties": {
    "iso:country":"US",
    "sg:address":"400 Prince St",
    "sg:city":"Alexandria",
    "sg:classifiers":[
        {
            "category":"Shopping",
            "subcategory":"Used Merchandise",
            "type":"Retail Goods"
        }
    ],
    "sg:phone":"+1 703 836 2539",
    "sg:postcode":"22314",
    "sg:province":"VA",
    "sg:tags":[
        "antique"
    ],
    "wof:name":"Cavalier Antiques",
    "wof:placetype":"venue"
},
  "geometry": {"coordinates":[-77.04496899999999,38.803641],"type":"Point"}
}