{
  "type": "Feature",
  "properties": {
    "addr:full":"4201 Williamson Rd NW Roanoke VA 24012",
    "addr:housenumber":"4201",
    "addr:postcode":"24012",
    "addr:street":"Williamson Rd Nw",
    "iso:country":"US",
    "sg:address":"4201 Williamson Rd NW",
    "sg:city":"Roanoke",
    "sg:classifiers":[
        {
            "category":"Restaurant",
            "type":"Food & Drink"
        }
    ],
    "sg:menulink":"http://www.allmenus.com/va/roanoke/155155-hardees/menu/",
    "sg:phone":"+1 540 366 7366",
    "sg:postcode":"24012",
    "sg:province":"VA",
    "sg:tags":[
        "burger",
        "american"
    ],
    "wof:name":"Hardee's",
    "wof:placetype":"venue"
},
  "geometry": {"coordinates":[-79.949798,37.31125],"type":"Point"}
}