{
  "type": "Feature",
  "properties": {
    "iso:country":"US",
    "sg:address":"6603 W Broad St",
    "sg:city":"Richmond",
    "sg:classifiers":[
        {
            "category":"Government",
            "subcategory":"Office",
            "type":"Public Place"
        }
    ],
    "sg:phone":"+1 804 662 9914",
    "sg:postcode":"23230",
    "sg:province":"VA",
    "wof:name":"Social Work Board",
    "wof:placetype":"venue"
},
  "geometry": {"coordinates":[-77.515417,37.603576],"type":"Point"}
}