{
  "type": "Feature",
  "properties": {
    "addr:full":"1309 East Cary St Richmond VA 23219",
    "addr:housenumber":"1309",
    "addr:postcode":"23219",
    "addr:street":"East Cary St",
    "iso:country":"US",
    "sg:address":"1309 East Cary St",
    "sg:city":"Richmond",
    "sg:classifiers":[
        {
            "category":"Professional",
            "subcategory":"Business Services",
            "type":"Services"
        }
    ],
    "sg:phone":"+1 216 357 4730",
    "sg:postcode":"23219",
    "sg:province":"VA",
    "sg:tags":[
        "collaboration",
        "project-management",
        "web-2-0",
        "gtd"
    ],
    "sg:website":"http://www.OnStagePortal.com/",
    "wof:name":"OnStage",
    "wof:placetype":"venue"
},
  "geometry": {"coordinates":[-77.433279,37.534952],"type":"Point"}
}