{
  "type": "Feature",
  "properties": {
    "addr:full":"1001 Winged Foot Ct Chesapeake VA 23320",
    "addr:housenumber":"1001",
    "addr:postcode":"23320",
    "addr:street":"Winged Foot Ct",
    "iso:country":"US",
    "sg:address":"1001 Winged Foot Ct",
    "sg:city":"Chesapeake",
    "sg:classifiers":[
        {
            "category":"Building & Trades",
            "subcategory":"Construction",
            "type":"Services"
        }
    ],
    "sg:phone":"+1 757 548 1407",
    "sg:postcode":"23320",
    "sg:province":"VA",
    "sg:tags":[
        "house"
    ],
    "wof:name":"James L Brinn Bldg Inc",
    "wof:placetype":"venue"
},
  "geometry": {"coordinates":[-76.220275,36.759855],"type":"Point"}
}