{
  "type": "Feature",
  "properties": {
    "addr:full":"3287 Old Catlett Rd Catlett VA 20119",
    "addr:housenumber":"3287",
    "addr:postcode":"20119",
    "addr:street":"Old Catlett Rd",
    "iso:country":"US",
    "sg:address":"3287 Old Catlett Rd",
    "sg:city":"Catlett",
    "sg:classifiers":[
        {
            "category":"Organizations",
            "subcategory":"Religious Organization",
            "type":"Services"
        }
    ],
    "sg:phone":"+1 540 788 4160",
    "sg:postcode":"20119",
    "sg:province":"VA",
    "sg:tags":[
        "church"
    ],
    "sg:website":"www.oakshadebaptist.org",
    "wof:name":"Oak Shade Baptist Church",
    "wof:placetype":"venue"
},
  "geometry": {"coordinates":[-77.643804,38.651612],"type":"Point"}
}