{
  "type": "Feature",
  "properties": {
    "iso:country":"US",
    "sg:address":"907 Main St",
    "sg:city":"West Point",
    "sg:classifiers":[
        {
            "category":"Shopping",
            "subcategory":"Florist",
            "type":"Retail Goods"
        }
    ],
    "sg:phone":"+1 804 843 2171",
    "sg:postcode":"23181",
    "sg:province":"VA",
    "wof:name":"West Point Florist",
    "wof:placetype":"venue"
},
  "geometry": {"coordinates":[-76.79776,37.533927],"type":"Point"}
}