{
  "type": "Feature",
  "properties": {
    "iso:country":"US",
    "sg:address":"100 E Cornwell Ln",
    "sg:city":"Purcellville",
    "sg:classifiers":[
        {
            "category":"Home & Garden",
            "subcategory":"Building Materials",
            "type":"Retail Goods"
        },
        {
            "category":"Building & Trades",
            "subcategory":"Construction",
            "type":"Services"
        }
    ],
    "sg:phone":"+1 540 338 8046",
    "sg:postcode":"20132",
    "sg:province":"VA",
    "sg:tags":[
        "mixed",
        "concrete",
        "contractor"
    ],
    "wof:name":"Cardinal Concrete Company",
    "wof:placetype":"venue"
},
  "geometry": {"coordinates":[-77.71597,39.140333],"type":"Point"}
}