{
  "type": "Feature",
  "properties": {
    "iso:country":"US",
    "sg:address":"7877 Brookneal Hwy",
    "sg:city":"Gladys",
    "sg:classifiers":[
        {
            "category":"Retail",
            "subcategory":"Auto Repair",
            "type":"Services"
        }
    ],
    "sg:phone":"+1 434 283 5669",
    "sg:postcode":"24554",
    "sg:province":"VA",
    "sg:tags":[
        "repairing",
        "automobile"
    ],
    "wof:name":"Roakes Auto Repair",
    "wof:placetype":"venue"
},
  "geometry": {"coordinates":[-79.07599,37.169847],"type":"Point"}
}