{
  "type": "Feature",
  "properties": {
    "addr:full":"3030 Preston Ave NW Roanoke VA 24012",
    "addr:housenumber":"3030",
    "addr:postcode":"24012",
    "addr:street":"Preston Ave Nw",
    "iso:country":"US",
    "sg:address":"3030 Preston Ave NW",
    "sg:city":"Roanoke",
    "sg:classifiers":[
        {
            "category":"Professional",
            "type":"Services"
        }
    ],
    "sg:phone":"+1 540 563 2893",
    "sg:postcode":"24012",
    "sg:province":"VA",
    "wof:name":"Delorac Inc",
    "wof:placetype":"venue"
},
  "geometry": {"coordinates":[-79.94738099999999,37.312089],"type":"Point"}
}