{
  "type": "Feature",
  "properties": {
    "addr:full":"2932 Blue Holly Ln Herndon VA 20171",
    "addr:housenumber":"2932",
    "addr:postcode":"20171",
    "addr:street":"Blue Holly Ln",
    "iso:country":"US",
    "sg:address":"2932 Blue Holly Ln",
    "sg:city":"Herndon",
    "sg:classifiers":[
        {
            "category":"Personal",
            "subcategory":"Hair Removal",
            "type":"Services"
        }
    ],
    "sg:phone":"+1 703 707 8135",
    "sg:postcode":"20171",
    "sg:province":"VA",
    "wof:name":"American Finance LLC",
    "wof:placetype":"venue"
},
  "geometry": {"coordinates":[-77.40975,38.926192],"type":"Point"}
}