{
  "type": "Feature",
  "properties": {
    "addr:full":"6678 Arlington Blvd  Falls Church VA 22042",
    "addr:housenumber":"6678",
    "addr:postcode":"22042",
    "addr:street":"Arlington Blvd",
    "iso:country":"US",
    "sg:address":"6678 Arlington Blvd ",
    "sg:city":"Falls Church",
    "sg:classifiers":[
        {
            "category":"Restaurant",
            "type":"Food & Drink"
        }
    ],
    "sg:menulink":"http://www.allmenus.com/va/providence/284290-present-restaurant/menu/",
    "sg:phone":"+1 703 531 1881",
    "sg:postcode":"22042",
    "sg:province":"VA",
    "sg:tags":[
        "asian",
        "vietnamese"
    ],
    "wof:name":"Present Restaurant",
    "wof:placetype":"venue"
},
  "geometry": {"coordinates":[-77.17541900000001,38.869807],"type":"Point"}
}