{
  "type": "Feature",
  "properties": {
    "iso:country":"US",
    "sg:address":"695 Quesenberry St",
    "sg:city":"Christiansburg",
    "sg:classifiers":[
        {
            "category":"Personal",
            "subcategory":"Beauty Salon",
            "type":"Services"
        }
    ],
    "sg:phone":"+1 540 382 7043",
    "sg:postcode":"24073",
    "sg:province":"VA",
    "sg:tags":[
        "shop"
    ],
    "wof:name":"Pats Hair Design",
    "wof:placetype":"venue"
},
  "geometry": {"coordinates":[-80.42029700000001,37.127665],"type":"Point"}
}