{
  "type": "Feature",
  "properties": {
    "addr:full":"4428 Hunt Rd Jarratt VA 23867",
    "addr:housenumber":"4428",
    "addr:postcode":"23867",
    "addr:street":"Hunt Rd",
    "iso:country":"US",
    "sg:address":"4428 Hunt Rd",
    "sg:city":"Jarratt",
    "sg:phone":"+1 434 246 3081",
    "sg:postcode":"23867",
    "sg:province":"VA",
    "sg:tags":[
        "farm",
        "peanut"
    ],
    "wof:name":"RMC-Owen Farm",
    "wof:placetype":"venue"
},
  "geometry": {"coordinates":[-77.546818,36.864895],"type":"Point"}
}