{
  "type": "Feature",
  "properties": {
    "addr:full":"1708 Beaver Rd Highland Springs VA 23075",
    "addr:housenumber":"1708",
    "addr:postcode":"23075",
    "addr:street":"Beaver Rd",
    "iso:country":"US",
    "sg:address":"1708 Beaver Rd",
    "sg:city":"Highland Springs",
    "sg:classifiers":[
        {
            "category":"Professional",
            "subcategory":"Computer Services",
            "type":"Services"
        }
    ],
    "sg:phone":"+1 804 218 4011",
    "sg:postcode":"23075",
    "sg:province":"VA",
    "sg:tags":[
        "datum"
    ],
    "wof:name":"Global Creation",
    "wof:placetype":"venue"
},
  "geometry": {"coordinates":[-77.31293100000001,37.536612],"type":"Point"}
}