{
  "type": "Feature",
  "properties": {
    "addr:full":"705 Airport Rd Blacksburg VA 24060",
    "addr:housenumber":"705",
    "addr:postcode":"24060",
    "addr:street":"Airport Rd",
    "iso:country":"US",
    "sg:address":"705 Airport Rd",
    "sg:city":"Blacksburg",
    "sg:classifiers":[
        {
            "category":"Social Services",
            "subcategory":"Child Care",
            "type":"Services"
        }
    ],
    "sg:phone":"+1 540 951 5300",
    "sg:postcode":"24060",
    "sg:province":"VA",
    "sg:tags":[
        "day"
    ],
    "wof:name":"Adventure Club Margaret Bee",
    "wof:placetype":"venue"
},
  "geometry": {"coordinates":[-80.407785,37.214495],"type":"Point"}
}