{
  "type": "Feature",
  "properties": {
    "addr:full":"2812 Rivermont Ave Lynchburg VA 24503",
    "addr:housenumber":"2812",
    "addr:postcode":"24503",
    "addr:street":"Rivermont Ave",
    "iso:country":"US",
    "sg:address":"2812 Rivermont Ave",
    "sg:city":"Lynchburg",
    "sg:classifiers":[
        {
            "category":"Professional",
            "type":"Services"
        }
    ],
    "sg:phone":"+1 434 847 7755",
    "sg:postcode":"24503",
    "sg:province":"VA",
    "sg:tags":[
        "technical",
        "personnel"
    ],
    "wof:name":"Rowan Resources Inc",
    "wof:placetype":"venue"
},
  "geometry": {"coordinates":[-79.17400000000001,37.437152],"type":"Point"}
}