{
  "type": "Feature",
  "properties": {
    "addr:full":"439 Porterfield Hwy SW Abingdon VA 24210",
    "addr:housenumber":"439",
    "addr:postcode":"24210",
    "addr:street":"Porterfield Hwy Sw",
    "iso:country":"US",
    "sg:address":"439 Porterfield Hwy SW",
    "sg:city":"Abingdon",
    "sg:classifiers":[
        {
            "category":"Professional",
            "type":"Services"
        }
    ],
    "sg:phone":"+1 276 676 0085",
    "sg:postcode":"24210",
    "sg:province":"VA",
    "wof:name":"Lazer Lube",
    "wof:placetype":"venue"
},
  "geometry": {"coordinates":[-81.99772299999999,36.711504],"type":"Point"}
}