{
  "type": "Feature",
  "properties": {
    "addr:full":"1219 W Broad St Waynesboro VA 22980",
    "addr:housenumber":"1219",
    "addr:postcode":"22980",
    "addr:street":"W Broad St",
    "iso:country":"US",
    "sg:address":"1219 W Broad St",
    "sg:city":"Waynesboro",
    "sg:classifiers":[
        {
            "category":"Home & Garden",
            "subcategory":"Building Materials",
            "type":"Retail Goods"
        }
    ],
    "sg:phone":"+1 540 943 1500",
    "sg:postcode":"22980",
    "sg:province":"VA",
    "sg:tags":[
        "glass",
        "window",
        "plate"
    ],
    "wof:name":"Reliance Glass LLC",
    "wof:placetype":"venue"
},
  "geometry": {"coordinates":[-78.897519,38.072589],"type":"Point"}
}