{
  "type": "Feature",
  "properties": {
    "addr:full":"8507 Preakness Pl Gainesville VA 20155",
    "addr:housenumber":"8507",
    "addr:postcode":"20155",
    "addr:street":"Preakness Pl",
    "iso:country":"US",
    "sg:address":"8507 Preakness Pl",
    "sg:city":"Gainesville",
    "sg:classifiers":[
        {
            "category":"Building & Trades",
            "subcategory":"Construction",
            "type":"Services"
        }
    ],
    "sg:phone":"+1 703 980 6501",
    "sg:postcode":"20155",
    "sg:province":"VA",
    "sg:tags":[
        "altering",
        "remodeling",
        "contractor"
    ],
    "wof:name":"Specialized Home Repair",
    "wof:placetype":"venue"
},
  "geometry": {"coordinates":[-77.599322,38.772573],"type":"Point"}
}