{
  "type": "Feature",
  "properties": {
    "addr:full":"16328 Lee Hwy Gainesville VA 20155",
    "addr:housenumber":"16328",
    "addr:postcode":"20155",
    "addr:street":"Lee Hwy",
    "iso:country":"US",
    "sg:address":"16328 Lee Hwy",
    "sg:city":"Gainesville",
    "sg:classifiers":[
        {
            "category":"Food & Beverages",
            "subcategory":"Groceries & Convenience Stores",
            "type":"Retail Goods"
        }
    ],
    "sg:phone":"+1 703 754 4739",
    "sg:postcode":"20155",
    "sg:province":"VA",
    "sg:tags":[
        "market"
    ],
    "wof:name":"Buckland Farm Market",
    "wof:placetype":"venue"
},
  "geometry": {"coordinates":[-77.678135,38.779326],"type":"Point"}
}