{
  "type": "Feature",
  "properties": {
    "addr:full":"4613 34th St S Arlington VA 22206",
    "addr:housenumber":"4613",
    "addr:postcode":"22206",
    "addr:street":"34Th St S",
    "iso:country":"US",
    "sg:address":"4613 34th St S",
    "sg:city":"Arlington",
    "sg:classifiers":[
        {
            "category":"Professional",
            "subcategory":"Management & Consulting",
            "type":"Services"
        }
    ],
    "sg:phone":"+1 703 998 3060",
    "sg:postcode":"22206",
    "sg:province":"VA",
    "wof:name":"Events Analysis Inc",
    "wof:placetype":"venue"
},
  "geometry": {"coordinates":[-77.093873,38.834725],"type":"Point"}
}