{
  "type": "Feature",
  "properties": {
    "iso:country":"US",
    "sg:address":"1011 E Broadway Ave",
    "sg:city":"Hopewell",
    "sg:classifiers":[
        {
            "category":"Real Estate",
            "subcategory":"Real Estate Operator",
            "type":"Services"
        }
    ],
    "sg:phone":"+1 804 541 1011",
    "sg:postcode":"23860",
    "sg:province":"VA",
    "sg:tags":[
        "building",
        "apartment"
    ],
    "wof:name":"Heritage Garden Apartments",
    "wof:placetype":"venue"
},
  "geometry": {"coordinates":[-77.27534199999999,37.309036],"type":"Point"}
}