{
  "type": "Feature",
  "properties": {
    "addr:full":"11503 Saunders Haven Ct Great Falls VA 22066",
    "addr:housenumber":"11503",
    "addr:postcode":"22066",
    "addr:street":"Saunders Haven Ct",
    "iso:country":"US",
    "sg:address":"11503 Saunders Haven Ct",
    "sg:city":"Great Falls",
    "sg:classifiers":[
        {
            "category":"Real Estate",
            "subcategory":"Real Estate Agent",
            "type":"Services"
        }
    ],
    "sg:phone":"+1 703 444 9845",
    "sg:postcode":"22066",
    "sg:province":"VA",
    "wof:name":"James Yang Realty",
    "wof:placetype":"venue"
},
  "geometry": {"coordinates":[-77.345538,39.007926],"type":"Point"}
}