{
  "type": "Feature",
  "properties": {
    "addr:full":"1333 Berryville Ave Winchester VA 22601",
    "addr:housenumber":"1333",
    "addr:postcode":"22601",
    "addr:street":"Berryville Ave",
    "iso:country":"US",
    "sg:address":"1333 Berryville Ave",
    "sg:city":"Winchester",
    "sg:classifiers":[
        {
            "category":"Autos & Motor Vehicles",
            "subcategory":"Fuel & Gas Station",
            "type":"Retail Goods"
        }
    ],
    "sg:phone":"+1 540 667 2210",
    "sg:postcode":"22601",
    "sg:province":"VA",
    "sg:tags":[
        "oil"
    ],
    "wof:name":"Interstate Chevron",
    "wof:placetype":"venue"
},
  "geometry": {"coordinates":[-78.137826,39.184661],"type":"Point"}
}