{
  "type": "Feature",
  "properties": {
    "addr:full":"824 Monroe Ave Newport News VA 23604",
    "addr:housenumber":"824",
    "addr:postcode":"23604",
    "addr:street":"Monroe Ave",
    "iso:country":"US",
    "sg:address":"824 Monroe Ave",
    "sg:city":"Newport News",
    "sg:classifiers":[
        {
            "category":"Restaurant",
            "type":"Food & Drink"
        }
    ],
    "sg:phone":"+1 757 887 3711",
    "sg:postcode":"23604",
    "sg:province":"VA",
    "wof:name":"Thai Orchid Restaurant",
    "wof:placetype":"venue"
},
  "geometry": {"coordinates":[-76.59533999999999,37.164006],"type":"Point"}
}