{
  "type": "Feature",
  "properties": {
    "addr:full":"17179 Summer Meadow Rd Beaverdam VA 23015",
    "addr:housenumber":"17179",
    "addr:postcode":"23015",
    "addr:street":"Summer Meadow Rd",
    "iso:country":"US",
    "sg:address":"17179 Summer Meadow Rd",
    "sg:city":"Beaverdam",
    "sg:classifiers":[
        {
            "category":"Professional",
            "subcategory":"Business Services",
            "type":"Services"
        }
    ],
    "sg:phone":"+1 804 449 6613",
    "sg:postcode":"23015",
    "sg:province":"VA",
    "wof:name":"Saros Design Inc",
    "wof:placetype":"venue"
},
  "geometry": {"coordinates":[-77.690392,37.888537],"type":"Point"}
}