{
  "type": "Feature",
  "properties": {
    "iso:country":"US",
    "sg:address":"7217 Masonville Dr",
    "sg:city":"Annandale",
    "sg:classifiers":[
        {
            "category":"Professional",
            "subcategory":"Engineering",
            "type":"Services"
        }
    ],
    "sg:phone":"+1 703 573 8454",
    "sg:postcode":"22003",
    "sg:province":"VA",
    "wof:name":"Semtas Corp",
    "wof:placetype":"venue"
},
  "geometry": {"coordinates":[-77.19662700000001,38.849675],"type":"Point"}
}