{
  "type": "Feature",
  "properties": {
    "iso:country":"US",
    "sg:address":"1145 Berryville Ave",
    "sg:city":"Winchester",
    "sg:classifiers":[
        {
            "category":"Professional",
            "subcategory":"Business Services",
            "type":"Services"
        }
    ],
    "sg:phone":"+1 540 667 1644",
    "sg:postcode":"22601",
    "sg:province":"VA",
    "sg:tags":[
        "water",
        "treatment"
    ],
    "sg:website":"www.servisoftsoftwater.com",
    "wof:name":"Ecowater Of Winchester Inc",
    "wof:placetype":"venue"
},
  "geometry": {"coordinates":[-78.141311,39.185117],"type":"Point"}
}