{
  "type": "Feature",
  "properties": {
    "addr:full":"124 Greene Dr Yorktown VA 23692",
    "addr:housenumber":"124",
    "addr:postcode":"23692",
    "addr:street":"Greene Dr",
    "iso:country":"US",
    "sg:address":"124 Greene Dr",
    "sg:city":"Yorktown",
    "sg:classifiers":[
        {
            "category":"Utilities",
            "subcategory":"Refuse",
            "type":"Services"
        }
    ],
    "sg:phone":"+1 757 898 5488",
    "sg:postcode":"23692",
    "sg:province":"VA",
    "sg:tags":[
        "system"
    ],
    "wof:name":"BFI Waste Services LLC",
    "wof:placetype":"venue"
},
  "geometry": {"coordinates":[-76.484791,37.181409],"type":"Point"}
}