{
  "type": "Feature",
  "properties": {
    "addr:full":"11013 W Broad St Glen Allen VA 23060",
    "addr:housenumber":"11013",
    "addr:postcode":"23060",
    "addr:street":"W Broad St",
    "iso:country":"US",
    "sg:address":"11013 W Broad St",
    "sg:city":"Glen Allen",
    "sg:classifiers":[
        {
            "category":"Professional",
            "subcategory":"Business Services",
            "type":"Services"
        }
    ],
    "sg:phone":"+1 804 967 1637",
    "sg:postcode":"23060",
    "sg:province":"VA",
    "sg:tags":[
        "credit",
        "card"
    ],
    "wof:name":"Capital One",
    "wof:placetype":"venue"
},
  "geometry": {"coordinates":[-77.589018,37.647426],"type":"Point"}
}