{
  "type": "Feature",
  "properties": {
    "addr:full":"3500 Russell Rd Quantico VA 22134",
    "addr:housenumber":"3500",
    "addr:postcode":"22134",
    "addr:street":"Russell Rd",
    "iso:country":"US",
    "sg:address":"3500 Russell Rd",
    "sg:city":"Quantico",
    "sg:classifiers":[
        {
            "category":"Restaurant",
            "type":"Food & Drink"
        }
    ],
    "sg:phone":"+1 703 221 7377",
    "sg:postcode":"22134",
    "sg:province":"VA",
    "sg:tags":[
        "fast"
    ],
    "wof:name":"McDonalds",
    "wof:placetype":"venue"
},
  "geometry": {"coordinates":[-77.315207,38.511208],"type":"Point"}
}