{
  "type": "Feature",
  "properties": {
    "addr:full":"235 Claiborne Ave Rocky Mount VA 24151",
    "addr:housenumber":"235",
    "addr:postcode":"24151",
    "addr:street":"Claiborne Ave",
    "iso:country":"US",
    "sg:address":"235 Claiborne Ave",
    "sg:city":"Rocky Mount",
    "sg:classifiers":[
        {
            "category":"Health Services",
            "subcategory":"Clinic",
            "type":"Services"
        }
    ],
    "sg:phone":"+1 540 489 1800",
    "sg:postcode":"24151",
    "sg:province":"VA",
    "sg:tags":[
        "childbirth",
        "education"
    ],
    "sg:website":"www.fcpec.org",
    "wof:name":"Franklin County Perinatal Educ",
    "wof:placetype":"venue"
},
  "geometry": {"coordinates":[-79.891212,36.99884],"type":"Point"}
}