{
  "type": "Feature",
  "properties": {
    "addr:full":"601 Research Rd Richmond VA 23236",
    "addr:housenumber":"601",
    "addr:postcode":"23236",
    "addr:street":"Research Rd",
    "iso:country":"US",
    "sg:address":"601 Research Rd",
    "sg:city":"Richmond",
    "sg:classifiers":[
        {
            "category":"Wholesale",
            "subcategory":"Machinery & Supplies",
            "type":"Manufacturing & Wholesale Goods"
        }
    ],
    "sg:phone":"+1 804 379 2790",
    "sg:postcode":"23236",
    "sg:province":"VA",
    "sg:tags":[
        "equipment",
        "printing",
        "industrial",
        "business"
    ],
    "wof:name":"Graphic Equipment Specialist",
    "wof:placetype":"venue"
},
  "geometry": {"coordinates":[-77.60144099999999,37.501864],"type":"Point"}
}