{
  "type": "Feature",
  "properties": {
    "addr:full":"6090 N Fork Church Rd Virgilina NC 24598",
    "addr:housenumber":"6090",
    "addr:postcode":"24598",
    "addr:street":"N;Church Rd",
    "iso:country":"US",
    "sg:address":"6090 N Fork Church Rd",
    "sg:city":"Virgilina",
    "sg:classifiers":[
        {
            "category":"Freight",
            "type":"Transportation"
        }
    ],
    "sg:phone":"+1 434 585 2581",
    "sg:postcode":"24598",
    "sg:province":"NC",
    "sg:tags":[
        "hauling",
        "trucking"
    ],
    "wof:name":"R W Morris Inc",
    "wof:placetype":"venue"
},
  "geometry": {"coordinates":[-78.754031,36.594985],"type":"Point"}
}