{
  "type": "Feature",
  "properties": {
    "iso:country":"US",
    "sg:address":"3304 N Washington Blvd",
    "sg:city":"Arlington",
    "sg:classifiers":[
        {
            "category":"Social Services",
            "type":"Services"
        }
    ],
    "sg:phone":"+1 703 841 0139",
    "sg:postcode":"22201",
    "sg:province":"VA",
    "sg:website":"www.stcharleschurch.org",
    "wof:name":"Borromeo Housing Inc",
    "wof:placetype":"venue"
},
  "geometry": {"coordinates":[-77.100144,38.885892],"type":"Point"}
}