{
  "type": "Feature",
  "properties": {
    "addr:full":"100 Oakview Ave Bristol VA 24201",
    "addr:housenumber":"100",
    "addr:postcode":"24201",
    "addr:street":"Oakview Ave",
    "iso:country":"US",
    "sg:address":"100 Oakview Ave",
    "sg:city":"Bristol",
    "sg:classifiers":[
        {
            "category":"Social Services",
            "type":"Services"
        }
    ],
    "sg:phone":"+1 276 466 2312",
    "sg:postcode":"24201",
    "sg:province":"VA",
    "sg:tags":[
        "crisis",
        "intervention"
    ],
    "wof:name":"Crisis Center",
    "wof:placetype":"venue"
},
  "geometry": {"coordinates":[-82.181862,36.602823],"type":"Point"}
}