{
  "type": "Feature",
  "properties": {
    "addr:full":"202 S Main St Galax VA 24333",
    "addr:housenumber":"202",
    "addr:postcode":"24333",
    "addr:street":"S Main St",
    "iso:country":"US",
    "sg:address":"202 S Main St",
    "sg:city":"Galax",
    "sg:classifiers":[
        {
            "category":"Insurance",
            "subcategory":"Insurance Agent",
            "type":"Services"
        }
    ],
    "sg:phone":"+1 276 236 6211",
    "sg:postcode":"24333",
    "sg:province":"VA",
    "wof:name":"Frost Insurance Agency",
    "wof:placetype":"venue"
},
  "geometry": {"coordinates":[-80.924436,36.660936],"type":"Point"}
}