{
  "type": "Feature",
  "properties": {
    "iso:country":"US",
    "sg:address":"3110 Pioneer Rd NW",
    "sg:city":"Roanoke",
    "sg:classifiers":[
        {
            "category":"Organizations",
            "subcategory":"Religious Organization",
            "type":"Services"
        }
    ],
    "sg:phone":"+1 540 366 0291",
    "sg:postcode":"24012",
    "sg:province":"VA",
    "sg:tags":[
        "church"
    ],
    "wof:name":"Williamson Rd Church-Brethren",
    "wof:placetype":"venue"
},
  "geometry": {"coordinates":[-79.944228,37.304763],"type":"Point"}
}