{
  "type": "Feature",
  "properties": {
    "addr:full":"15203 Valley Stream Dr Woodbridge VA 22191",
    "addr:housenumber":"15203",
    "addr:postcode":"22191",
    "addr:street":"Valley Stream Dr",
    "iso:country":"US",
    "sg:address":"15203 Valley Stream Dr",
    "sg:city":"Woodbridge",
    "sg:classifiers":[
        {
            "category":"Health Services",
            "subcategory":"Medical Lab",
            "type":"Services"
        }
    ],
    "sg:phone":"+1 703 680 3314",
    "sg:postcode":"22191",
    "sg:province":"VA",
    "sg:tags":[
        "laboratory",
        "dental"
    ],
    "wof:name":"Pseudodontics Dental Lab",
    "wof:placetype":"venue"
},
  "geometry": {"coordinates":[-77.277327,38.621743],"type":"Point"}
}