{
  "type": "Feature",
  "properties": {
    "addr:full":"2715 Wyoming Ave Norfolk VA 23513",
    "addr:housenumber":"2715",
    "addr:postcode":"23513",
    "addr:street":"Wyoming Ave",
    "iso:country":"US",
    "sg:address":"2715 Wyoming Ave",
    "sg:city":"Norfolk",
    "sg:classifiers":[
        {
            "category":"Professional",
            "subcategory":"Business Services",
            "type":"Services"
        }
    ],
    "sg:phone":"+1 757 857 1873",
    "sg:postcode":"23513",
    "sg:province":"VA",
    "sg:tags":[
        "design",
        "kitchen",
        "galley",
        "area"
    ],
    "wof:name":"Advance Vending",
    "wof:placetype":"venue"
},
  "geometry": {"coordinates":[-76.248104,36.87254],"type":"Point"}
}