{
  "type": "Feature",
  "properties": {
    "addr:full":"1117 S High St Harrisonburg VA 22801",
    "addr:housenumber":"1117",
    "addr:postcode":"22801",
    "addr:street":"S High St",
    "iso:country":"US",
    "sg:address":"1117 S High St",
    "sg:city":"Harrisonburg",
    "sg:classifiers":[
        {
            "category":"Food & Beverages",
            "subcategory":"Bakery",
            "type":"Retail Goods"
        }
    ],
    "sg:phone":"+1 540 434 4582",
    "sg:postcode":"22801",
    "sg:province":"VA",
    "sg:tags":[
        "flower"
    ],
    "wof:name":"Sunset Flower & Pastry Shoppe",
    "wof:placetype":"venue"
},
  "geometry": {"coordinates":[-78.890822,38.437125],"type":"Point"}
}