{
  "type": "Feature",
  "properties": {
    "addr:full":"1217 Battlefield Blvd N Chesapeake VA 23320",
    "addr:housenumber":"1217",
    "addr:postcode":"23320",
    "addr:street":"Battlefield Blvd N",
    "iso:country":"US",
    "sg:address":"1217 Battlefield Blvd N",
    "sg:city":"Chesapeake",
    "sg:classifiers":[
        {
            "category":"Restaurant",
            "type":"Food & Drink"
        }
    ],
    "sg:menulink":"http://www.allmenus.com/va/chesapeake/92149-firehouse-subs/menu/",
    "sg:phone":"+1 757 410 5982",
    "sg:postcode":"23320",
    "sg:province":"VA",
    "sg:tags":[
        "wrap",
        "american",
        "sandwich"
    ],
    "wof:name":"Firehouse Subs",
    "wof:placetype":"venue"
},
  "geometry": {"coordinates":[-76.250089,36.762969],"type":"Point"}
}