{
  "type": "Feature",
  "properties": {
    "addr:full":"1000 N Main St Harrisonburg VA 22802",
    "addr:housenumber":"1000",
    "addr:postcode":"22802",
    "addr:street":"N Main St",
    "iso:country":"US",
    "sg:address":"1000 N Main St",
    "sg:city":"Harrisonburg",
    "sg:classifiers":[
        {
            "category":"Autos & Motor Vehicles",
            "subcategory":"Automobile Sales",
            "type":"Retail Goods"
        }
    ],
    "sg:phone":"+1 540 574 4839",
    "sg:postcode":"22802",
    "sg:province":"VA",
    "sg:tags":[
        "car",
        "dealer"
    ],
    "wof:name":"Snyder's Auto Sales",
    "wof:placetype":"venue"
},
  "geometry": {"coordinates":[-78.85672,38.459818],"type":"Point"}
}