{
  "type": "Feature",
  "properties": {
    "addr:full":"103 W Tabb St Petersburg VA 23803",
    "addr:housenumber":"103",
    "addr:postcode":"23803",
    "addr:street":"W Tabb",
    "iso:country":"US",
    "sg:address":"103 W Tabb St",
    "sg:city":"Petersburg",
    "sg:classifiers":[
        {
            "category":"Government",
            "subcategory":"Office",
            "type":"Public Place"
        }
    ],
    "sg:phone":"+1 804 733 2324",
    "sg:postcode":"23803",
    "sg:province":"VA",
    "sg:tags":[
        "village"
    ],
    "wof:name":"Petersburg Human Resources",
    "wof:placetype":"venue"
},
  "geometry": {"coordinates":[-77.406657,37.229915],"type":"Point"}
}