{
  "type": "Feature",
  "properties": {
    "iso:country":"US",
    "sg:address":"6521 Arlington Blvd",
    "sg:city":"Falls Church",
    "sg:classifiers":[
        {
            "category":"Professional",
            "subcategory":"Computer Services",
            "type":"Services"
        }
    ],
    "sg:phone":"+1 703 533 9200",
    "sg:postcode":"22042",
    "sg:province":"VA",
    "sg:tags":[
        "processing"
    ],
    "wof:name":"Driven Inc",
    "wof:placetype":"venue"
},
  "geometry": {"coordinates":[-77.16773000000001,38.8708],"type":"Point"}
}