{
  "type": "Feature",
  "properties": {
    "iso:country":"US",
    "sg:address":"32 Reserve Ave SW",
    "sg:city":"Roanoke",
    "sg:classifiers":[
        {
            "category":"Government",
            "subcategory":"Office",
            "type":"Public Place"
        }
    ],
    "sg:phone":"+1 540 857 7030",
    "sg:postcode":"24016",
    "sg:province":"VA",
    "sg:tags":[
        "national",
        "security"
    ],
    "wof:name":"Maitenance Shop",
    "wof:placetype":"venue"
},
  "geometry": {"coordinates":[-79.942432,37.255164],"type":"Point"}
}