{
  "type": "Feature",
  "properties": {
    "iso:country":"US",
    "sg:address":"1641 Sierra Woods Dr",
    "sg:city":"Reston",
    "sg:classifiers":[
        {
            "category":"Museum",
            "type":"Entertainment"
        }
    ],
    "sg:phone":"+1 703 435 7108",
    "sg:postcode":"20194",
    "sg:province":"VA",
    "sg:tags":[
        "organization",
        "arts",
        "information"
    ],
    "wof:name":"Art Reach Intl",
    "wof:placetype":"venue"
},
  "geometry": {"coordinates":[-77.364328,38.972594],"type":"Point"}
}