{
  "type": "Feature",
  "properties": {
    "iso:country":"US",
    "sg:address":"2601 Greenwood Dr",
    "sg:city":"Portsmouth",
    "sg:classifiers":[
        {
            "category":"Freight",
            "type":"Transportation"
        }
    ],
    "sg:phone":"+1 757 673 4669",
    "sg:postcode":"23702",
    "sg:province":"VA",
    "sg:tags":[
        "hauling",
        "trucking"
    ],
    "wof:name":"Road Runner Hauling Inc",
    "wof:placetype":"venue"
},
  "geometry": {"coordinates":[-76.33234400000001,36.806427],"type":"Point"}
}