{
  "type": "Feature",
  "properties": {
    "iso:country":"US",
    "sg:address":"77 Hawes Rd",
    "sg:city":"Stephens City",
    "sg:classifiers":[
        {
            "category":"Farming",
            "subcategory":"Farm",
            "type":"Manufacturing & Wholesale Goods"
        }
    ],
    "sg:phone":"+1 540 869 7245",
    "sg:postcode":"22655",
    "sg:province":"VA",
    "sg:tags":[
        "crop",
        "general"
    ],
    "wof:name":"James P Bailey",
    "wof:placetype":"venue"
},
  "geometry": {"coordinates":[-78.184727,39.014726],"type":"Point"}
}