{
  "type": "Feature",
  "properties": {
    "addr:full":"7802 Mulberry Bottom Ln Springfield VA 22153",
    "addr:housenumber":"7802",
    "addr:postcode":"22153",
    "addr:street":"Mulberry Bottom Ln",
    "iso:country":"US",
    "sg:address":"7802 Mulberry Bottom Ln",
    "sg:city":"Springfield",
    "sg:classifiers":[
        {
            "category":"Shopping",
            "subcategory":"Pets & Pet Supplies",
            "type":"Retail Goods"
        },
        {
            "category":"Retail",
            "subcategory":"Veterinary Services",
            "type":"Services"
        }
    ],
    "sg:phone":"+1 703 912 9313",
    "sg:postcode":"22153",
    "sg:province":"VA",
    "sg:tags":[
        "specialty"
    ],
    "wof:name":"Doggie Time",
    "wof:placetype":"venue"
},
  "geometry": {"coordinates":[-77.21572,38.748648],"type":"Point"}
}