{
  "type": "Feature",
  "properties": {
    "iso:country":"US",
    "sg:address":"700 E Main St",
    "sg:city":"Richmond",
    "sg:classifiers":[
        {
            "category":"Professional",
            "subcategory":"Management & Consulting",
            "type":"Services"
        }
    ],
    "sg:phone":"+1 804 440 9356",
    "sg:postcode":"23219",
    "sg:province":"VA",
    "sg:tags":[
        "business"
    ],
    "wof:name":"Nawire",
    "wof:placetype":"venue"
},
  "geometry": {"coordinates":[-77.437201,37.53875],"type":"Point"}
}