{
  "type": "Feature",
  "properties": {
    "iso:country":"US",
    "sg:address":"1900 Whitcomb St",
    "sg:city":"Richmond",
    "sg:classifiers":[
        {
            "category":"Place Of Worship",
            "subcategory":"Church",
            "type":"Public Place"
        },
        {
            "category":"Place Of Worship",
            "type":"Public Place"
        },
        {
            "category":"Organizations",
            "subcategory":"Religious Organization",
            "type":"Services"
        }
    ],
    "sg:phone":"+1 804 643 9244",
    "sg:postcode":"23223",
    "sg:province":"VA",
    "sg:tags":[
        "churches-baptist-general",
        "clergy",
        "churches-baptist"
    ],
    "wof:name":"Pilgrim Baptist Church",
    "wof:placetype":"venue"
},
  "geometry": {"coordinates":[-77.42227200000001,37.553429],"type":"Point"}
}