{
  "type": "Feature",
  "properties": {
    "iso:country":"US",
    "sg:address":"11804 Baron Cameron Ave",
    "sg:city":"Reston",
    "sg:classifiers":[
        {
            "category":"Restaurant",
            "type":"Food & Drink"
        }
    ],
    "sg:phone":"+1 703 435 5118",
    "sg:postcode":"20190",
    "sg:province":"VA",
    "sg:tags":[
        "barbecue",
        "seafood",
        "american"
    ],
    "sg:website":"http://www.memphisbar-b-q.com",
    "wof:name":"Memphis Bar-b-q Company",
    "wof:placetype":"venue"
},
  "geometry": {"coordinates":[-77.355205,38.966865],"type":"Point"}
}