{
  "type": "Feature",
  "properties": {
    "iso:country":"US",
    "sg:address":"6421 Partridge St",
    "sg:city":"Norfolk",
    "sg:classifiers":[
        {
            "category":"Retail",
            "subcategory":"Animal Services",
            "type":"Services"
        }
    ],
    "sg:phone":"+1 757 855 4456",
    "sg:postcode":"23513",
    "sg:province":"VA",
    "wof:name":"Doggie Date",
    "wof:placetype":"venue"
},
  "geometry": {"coordinates":[-76.245803,36.896305],"type":"Point"}
}