{
  "type": "Feature",
  "properties": {
    "addr:full":"11931 Smoketree Dr Richmond VA 23236",
    "addr:housenumber":"11931",
    "addr:postcode":"23236",
    "addr:street":"Smoketree Dr",
    "iso:country":"US",
    "sg:address":"11931 Smoketree Dr",
    "sg:city":"Richmond",
    "sg:classifiers":[
        {
            "category":"Professional",
            "subcategory":"Business Services",
            "type":"Services"
        }
    ],
    "sg:phone":"+1 804 897 0997",
    "sg:postcode":"23236",
    "sg:province":"VA",
    "wof:name":"Aurora Management Partners",
    "wof:placetype":"venue"
},
  "geometry": {"coordinates":[-77.623239,37.483941],"type":"Point"}
}