{
  "type": "Feature",
  "properties": {
    "addr:full":"9650 Main St Fairfax VA 22031",
    "addr:housenumber":"9650",
    "addr:postcode":"22031",
    "addr:street":"Main St",
    "iso:country":"US",
    "sg:address":"9650 Main St",
    "sg:city":"Fairfax",
    "sg:classifiers":[
        {
            "category":"Restaurant",
            "type":"Food & Drink"
        }
    ],
    "sg:menulink":"http://www.allmenus.com/va/fairfax/104460-old-country-buffet/menu/",
    "sg:phone":"+1 703 764 0708",
    "sg:postcode":"22031",
    "sg:province":"VA",
    "sg:tags":[
        "american"
    ],
    "wof:name":"Old Country Buffet",
    "wof:placetype":"venue"
},
  "geometry": {"coordinates":[-77.275845,38.841807],"type":"Point"}
}