{
  "type": "Feature",
  "properties": {
    "iso:country":"US",
    "sg:address":"7710 Midway Pl",
    "sg:city":"Lorton",
    "sg:classifiers":[
        {
            "category":"Real Estate",
            "subcategory":"Real Estate Agent",
            "type":"Services"
        }
    ],
    "sg:phone":"+1 703 869 4567",
    "sg:postcode":"22079",
    "sg:province":"VA",
    "wof:name":"Work Properties",
    "wof:placetype":"venue"
},
  "geometry": {"coordinates":[-77.21113200000001,38.708344],"type":"Point"}
}