{
  "type": "Feature",
  "properties": {
    "iso:country":"US",
    "sg:address":"4507 George Washington Hwy",
    "sg:city":"Portsmouth",
    "sg:classifiers":[
        {
            "category":"Restaurant",
            "type":"Food & Drink"
        }
    ],
    "sg:phone":"+1 757 487 0869",
    "sg:postcode":"23702",
    "sg:province":"VA",
    "sg:tags":[
        "eating"
    ],
    "wof:name":"Gloria's Best",
    "wof:placetype":"venue"
},
  "geometry": {"coordinates":[-76.324911,36.798855],"type":"Point"}
}