{
  "type": "Feature",
  "properties": {
    "addr:full":"1010 Kingsmill Rd Williamsburg VA 23185",
    "addr:housenumber":"1010",
    "addr:postcode":"23185",
    "addr:street":"Kingsmill Rd",
    "iso:country":"US",
    "sg:address":"1010 Kingsmill Rd",
    "sg:city":"Williamsburg",
    "sg:classifiers":[
        {
            "category":"Communications",
            "subcategory":"Film & Video Production",
            "type":"Services"
        }
    ],
    "sg:phone":"+1 757 253 8205",
    "sg:postcode":"23185",
    "sg:province":"VA",
    "sg:tags":[
        "audio"
    ],
    "wof:name":"Kingsmill Audio Visual Svc",
    "wof:placetype":"venue"
},
  "geometry": {"coordinates":[-76.659325,37.241625],"type":"Point"}
}