{
  "type": "Feature",
  "properties": {
    "addr:full":"401 Valley St Scottsville VA 24590",
    "addr:housenumber":"401",
    "addr:postcode":"24590",
    "addr:street":"Valley St",
    "iso:country":"US",
    "sg:address":"401 Valley St",
    "sg:city":"Scottsville",
    "sg:classifiers":[
        {
            "category":"Organizations",
            "subcategory":"Professional Association",
            "type":"Services"
        }
    ],
    "sg:phone":"+1 434 286 6000",
    "sg:postcode":"24590",
    "sg:province":"VA",
    "sg:tags":[
        "chambers",
        "commerce"
    ],
    "wof:name":"Scottsville Chamber-Commerce",
    "wof:placetype":"venue"
},
  "geometry": {"coordinates":[-78.49641099999999,37.800976],"type":"Point"}
}