{
  "type": "Feature",
  "properties": {
    "addr:full":"6627 Byrns Pl Mc Lean VA 22101",
    "addr:housenumber":"6627",
    "addr:postcode":"22101",
    "addr:street":"Byrns Pl Mc Lean",
    "iso:country":"US",
    "sg:address":"6627 Byrns Pl",
    "sg:city":"Mc Lean",
    "sg:classifiers":[
        {
            "category":"Health Services",
            "subcategory":"Doctor",
            "type":"Services"
        }
    ],
    "sg:phone":"+1 703 625 2733",
    "sg:postcode":"22101",
    "sg:province":"VA",
    "wof:name":"SOO W Han",
    "wof:placetype":"venue"
},
  "geometry": {"coordinates":[-77.172777,38.929778],"type":"Point"}
}