{
  "type": "Feature",
  "properties": {
    "addr:full":"2200 Senseny Rd Berryville VA 22611",
    "addr:housenumber":"2200",
    "addr:postcode":"22611",
    "addr:street":"Senseny Rd",
    "iso:country":"US",
    "sg:address":"2200 Senseny Rd",
    "sg:city":"Berryville",
    "sg:classifiers":[
        {
            "category":"Insurance",
            "subcategory":"Insurance Agent",
            "type":"Services"
        }
    ],
    "sg:phone":"+1 540 955 4500",
    "sg:postcode":"22611",
    "sg:province":"VA",
    "wof:name":"Moorris Michael H and Assoc",
    "wof:placetype":"venue"
},
  "geometry": {"coordinates":[-78.037843,39.14061],"type":"Point"}
}