{
  "type": "Feature",
  "properties": {
    "iso:country":"US",
    "sg:address":"43104 Shadow Ter",
    "sg:city":"Leesburg",
    "sg:classifiers":[
        {
            "category":"Professional",
            "subcategory":"Computer Services",
            "type":"Services"
        }
    ],
    "sg:phone":"+1 571 233 5680",
    "sg:postcode":"20176",
    "sg:province":"VA",
    "sg:tags":[
        "related"
    ],
    "wof:name":"Xpect Solutions Inc",
    "wof:placetype":"venue"
},
  "geometry": {"coordinates":[-77.512449,39.094432],"type":"Point"}
}