{
  "type": "Feature",
  "properties": {
    "addr:full":"3065 Mount Tabor Rd Blacksburg VA 24060",
    "addr:housenumber":"3065",
    "addr:postcode":"24060",
    "addr:street":"Mount Tabor Rd",
    "iso:country":"US",
    "sg:address":"3065 Mount Tabor Rd",
    "sg:city":"Blacksburg",
    "sg:classifiers":[
        {
            "category":"Building & Trades",
            "subcategory":"Construction",
            "type":"Services"
        }
    ],
    "sg:phone":"+1 540 953 1898",
    "sg:postcode":"24060",
    "sg:province":"VA",
    "sg:tags":[
        "house",
        "product",
        "wood",
        "carp",
        "mfg"
    ],
    "wof:name":"Custom Woodworking",
    "wof:placetype":"venue"
},
  "geometry": {"coordinates":[-80.36624399999999,37.295853],"type":"Point"}
}