{
  "type": "Feature",
  "properties": {
    "addr:full":"8747 Poor Mountain Rd Bent Mountain VA 24059",
    "addr:housenumber":"8747",
    "addr:postcode":"24059",
    "addr:street":"Poor Mountain Rd;Mountain",
    "iso:country":"US",
    "sg:address":"8747 Poor Mountain Rd",
    "sg:city":"Bent Mountain",
    "sg:classifiers":[
        {
            "category":"Home & Garden",
            "subcategory":"Furniture",
            "type":"Retail Goods"
        }
    ],
    "sg:phone":"+1 540 929 4358",
    "sg:postcode":"24059",
    "sg:province":"VA",
    "sg:tags":[
        "builder",
        "custom"
    ],
    "wof:name":"Peter Chapman Wood Worker",
    "wof:placetype":"venue"
},
  "geometry": {"coordinates":[-80.132463,37.172792],"type":"Point"}
}