{
  "type": "Feature",
  "properties": {
    "addr:full":"3102 Plank Rd Fredericksburg VA 22407",
    "addr:housenumber":"3102",
    "addr:postcode":"22407",
    "addr:street":"Plank Rd",
    "iso:country":"US",
    "sg:address":"3102 Plank Rd",
    "sg:city":"Fredericksburg",
    "sg:classifiers":[
        {
            "category":"Shopping",
            "subcategory":"Gifts & Souvenirs",
            "type":"Retail Goods"
        }
    ],
    "sg:phone":"+1 540 786 1018",
    "sg:postcode":"22407",
    "sg:province":"VA",
    "sg:tags":[
        "shop"
    ],
    "sg:website":"www.thingsremebered.com",
    "wof:name":"Things Remembered",
    "wof:placetype":"venue"
},
  "geometry": {"coordinates":[-77.517805,38.294267],"type":"Point"}
}