{
  "type": "Feature",
  "properties": {
    "addr:full":"5987 N Lee Hwy Fairfield VA 24435",
    "addr:housenumber":"5987",
    "addr:postcode":"24435",
    "addr:street":"N Lee Hwy",
    "iso:country":"US",
    "sg:address":"5987 N Lee Hwy",
    "sg:city":"Fairfield",
    "sg:classifiers":[
        {
            "category":"Manufacturing",
            "subcategory":"Building Materials",
            "type":"Manufacturing & Wholesale Goods"
        }
    ],
    "sg:phone":"+1 540 377 9173",
    "sg:postcode":"24435",
    "sg:province":"VA",
    "sg:tags":[
        "lumber"
    ],
    "wof:name":"Jarrett Millwork & Moldings",
    "wof:placetype":"venue"
},
  "geometry": {"coordinates":[-79.28121299999999,37.88329],"type":"Point"}
}