{
  "type": "Feature",
  "properties": {
    "addr:full":"3004 Woodlawn Dr Suffolk VA 23434",
    "addr:housenumber":"3004",
    "addr:postcode":"23434",
    "addr:street":"Woodlawn Dr",
    "iso:country":"US",
    "sg:address":"3004 Woodlawn Dr",
    "sg:city":"Suffolk",
    "sg:classifiers":[
        {
            "category":"Retail",
            "subcategory":"Repair Shop",
            "type":"Services"
        }
    ],
    "sg:phone":"+1 757 925 4568",
    "sg:postcode":"23434",
    "sg:province":"VA",
    "sg:tags":[
        "lock",
        "locksmith"
    ],
    "wof:name":"King's Fork Lock & Key",
    "wof:placetype":"venue"
},
  "geometry": {"coordinates":[-76.635452,36.78232],"type":"Point"}
}