{
  "type": "Feature",
  "properties": {
    "addr:full":"1148 Rose Hill Dr Charlottesville VA 22903",
    "addr:housenumber":"1148",
    "addr:postcode":"22903",
    "addr:street":"Rose Hill Dr",
    "iso:country":"US",
    "sg:address":"1148 Rose Hill Dr",
    "sg:city":"Charlottesville",
    "sg:classifiers":[
        {
            "category":"Professional",
            "subcategory":"Accounting & Tax Preparation",
            "type":"Services"
        }
    ],
    "sg:phone":"+1 434 293 5188",
    "sg:postcode":"22903",
    "sg:province":"VA",
    "sg:tags":[
        "accountant"
    ],
    "wof:name":"Salley Walter B Jr & Co",
    "wof:placetype":"venue"
},
  "geometry": {"coordinates":[-78.483902,38.042801],"type":"Point"}
}