{
  "type": "Feature",
  "properties": {
    "addr:full":"916 Virginia Ave Clarksville VA 23927",
    "addr:housenumber":"916",
    "addr:postcode":"23927",
    "addr:street":"Virginia Ave",
    "iso:country":"US",
    "sg:address":"916 Virginia Ave",
    "sg:city":"Clarksville",
    "sg:classifiers":[
        {
            "category":"Restaurant",
            "type":"Food & Drink"
        }
    ],
    "sg:phone":"+1 434 374 2052",
    "sg:postcode":"23927",
    "sg:province":"VA",
    "wof:name":"Subway Sandwiches & Salads",
    "wof:placetype":"venue"
},
  "geometry": {"coordinates":[-78.56468599999999,36.620751],"type":"Point"}
}