{
  "type": "Feature",
  "properties": {
    "iso:country":"US",
    "sg:address":"1518 Versailles Ave",
    "sg:city":"Norfolk",
    "sg:classifiers":[
        {
            "category":"Organizations",
            "subcategory":"Membership Organization",
            "type":"Services"
        }
    ],
    "sg:phone":"+1 757 434 0007",
    "sg:postcode":"23509",
    "sg:province":"VA",
    "wof:name":"M J D Consulting",
    "wof:placetype":"venue"
},
  "geometry": {"coordinates":[-76.269818,36.878152],"type":"Point"}
}