{
  "type": "Feature",
  "properties": {
    "iso:country":"US",
    "sg:address":"4125 Placid Lake Ct",
    "sg:city":"Chantilly",
    "sg:classifiers":[
        {
            "category":"Building & Trades",
            "subcategory":"Cleaning & Sanitation",
            "type":"Services"
        }
    ],
    "sg:phone":"+1 703 817 9889",
    "sg:postcode":"20151",
    "sg:province":"VA",
    "sg:tags":[
        "butler",
        "maid"
    ],
    "wof:name":"Best Maid Svc",
    "wof:placetype":"venue"
},
  "geometry": {"coordinates":[-77.42478,38.888596],"type":"Point"}
}