{
  "type": "Feature",
  "properties": {
    "addr:full":"861 Dry Branch Rd Buchanan VA 24066",
    "addr:housenumber":"861",
    "addr:postcode":"24066",
    "addr:street":"Dry Branch Rd",
    "iso:country":"US",
    "sg:address":"861 Dry Branch Rd",
    "sg:city":"Buchanan",
    "sg:classifiers":[
        {
            "category":"Building & Trades",
            "subcategory":"Construction",
            "type":"Services"
        }
    ],
    "sg:phone":"+1 540 254 2097",
    "sg:postcode":"24066",
    "sg:province":"VA",
    "sg:tags":[
        "excavation",
        "hauling"
    ],
    "wof:name":"Eubank Excavating & Hauling",
    "wof:placetype":"venue"
},
  "geometry": {"coordinates":[-79.64960499999999,37.590735],"type":"Point"}
}