{
  "type": "Feature",
  "properties": {
    "addr:full":"1113 Cypress Tree Pl Herndon VA 20170",
    "addr:housenumber":"1113",
    "addr:postcode":"20170",
    "addr:street":"Cypress Tree Pl",
    "iso:country":"US",
    "sg:address":"1113 Cypress Tree Pl",
    "sg:city":"Herndon",
    "sg:classifiers":[
        {
            "category":"Education",
            "subcategory":"Special Training",
            "type":"Public Place"
        }
    ],
    "sg:phone":"+1 703 481 8444",
    "sg:postcode":"20170",
    "sg:province":"VA",
    "wof:name":"Luciani Raffella Inst",
    "wof:placetype":"venue"
},
  "geometry": {"coordinates":[-77.399839,38.965086],"type":"Point"}
}