{
  "type": "Feature",
  "properties": {
    "iso:country":"US",
    "sg:address":"3950 Oak St",
    "sg:city":"Fairfax",
    "sg:classifiers":[
        {
            "category":"Building & Trades",
            "subcategory":"Electrical",
            "type":"Services"
        }
    ],
    "sg:phone":"+1 703 273 5040",
    "sg:postcode":"22030",
    "sg:province":"VA",
    "sg:tags":[
        "electrical",
        "contractor"
    ],
    "wof:name":"Moore Electrical Services Inc",
    "wof:placetype":"venue"
},
  "geometry": {"coordinates":[-77.317151,38.851042],"type":"Point"}
}