{
  "type": "Feature",
  "properties": {
    "addr:full":"12322 Fox Lake Pl Fairfax VA 22033",
    "addr:housenumber":"12322",
    "addr:postcode":"22033",
    "addr:street":"Fox;Pl",
    "iso:country":"US",
    "sg:address":"12322 Fox Lake Pl",
    "sg:city":"Fairfax",
    "sg:classifiers":[
        {
            "category":"Restaurant",
            "type":"Food & Drink"
        }
    ],
    "sg:phone":"+1 703 359 5871",
    "sg:postcode":"22033",
    "sg:province":"VA",
    "sg:tags":[
        "eating"
    ],
    "wof:name":"Potomac Yard Subway Inc",
    "wof:placetype":"venue"
},
  "geometry": {"coordinates":[-77.373757,38.866428],"type":"Point"}
}