{
  "type": "Feature",
  "properties": {
    "addr:full":"14701 Gatewood Rd Dewitt VA 23840",
    "addr:housenumber":"14701",
    "addr:postcode":"23840",
    "addr:street":"Gatewood Rd",
    "iso:country":"US",
    "sg:address":"14701 Gatewood Rd",
    "sg:city":"Dewitt",
    "sg:classifiers":[
        {
            "category":"Building & Trades",
            "subcategory":"Plumbing",
            "type":"Services"
        }
    ],
    "sg:phone":"+1 804 469 4350",
    "sg:postcode":"23840",
    "sg:province":"VA",
    "sg:tags":[
        "conditioning",
        "air",
        "system",
        "contractor"
    ],
    "wof:name":"Moody's Heating & AC",
    "wof:placetype":"venue"
},
  "geometry": {"coordinates":[-77.60709199999999,37.07378],"type":"Point"}
}