{
  "type": "Feature",
  "properties": {
    "addr:full":"1300 Army Navy Dr Arlington VA 22202",
    "addr:housenumber":"1300",
    "addr:postcode":"22202",
    "addr:street":"Army Navy Dr",
    "iso:country":"US",
    "sg:address":"1300 Army Navy Dr",
    "sg:city":"Arlington",
    "sg:classifiers":[
        {
            "category":"Professional",
            "subcategory":"Lawyer & Legal Services",
            "type":"Services"
        }
    ],
    "sg:phone":"+1 703 892 2136",
    "sg:postcode":"22202",
    "sg:province":"VA",
    "wof:name":"Hauptfuehrer Sara E Lwyr",
    "wof:placetype":"venue"
},
  "geometry": {"coordinates":[-77.066615,38.864704],"type":"Point"}
}