{
  "type": "Feature",
  "properties": {
    "addr:full":"5071 Swinging Bridge Rd Brookneal VA 24528",
    "addr:housenumber":"5071",
    "addr:postcode":"24528",
    "addr:street":"Swinging Bridge Rd",
    "iso:country":"US",
    "sg:address":"5071 Swinging Bridge Rd",
    "sg:city":"Brookneal",
    "sg:classifiers":[
        {
            "category":"Food & Beverages",
            "subcategory":"Groceries & Convenience Stores",
            "type":"Retail Goods"
        }
    ],
    "sg:phone":"+1 434 376 5057",
    "sg:postcode":"24528",
    "sg:province":"VA",
    "sg:tags":[
        "grocer"
    ],
    "wof:name":"Edward's General Store",
    "wof:placetype":"venue"
},
  "geometry": {"coordinates":[-78.91757699999999,37.075228],"type":"Point"}
}