{
  "type": "Feature",
  "properties": {
    "addr:full":"6603 Palamino St Springfield VA 22150",
    "addr:housenumber":"6603",
    "addr:postcode":"22150",
    "addr:street":"Palamino St",
    "iso:country":"US",
    "sg:address":"6603 Palamino St",
    "sg:city":"Springfield",
    "sg:classifiers":[
        {
            "category":"Building & Trades",
            "subcategory":"Construction",
            "type":"Services"
        }
    ],
    "sg:phone":"+1 703 924 6700",
    "sg:postcode":"22150",
    "sg:province":"VA",
    "sg:tags":[
        "carpentry",
        "contractor"
    ],
    "wof:name":"Homewell General",
    "wof:placetype":"venue"
},
  "geometry": {"coordinates":[-77.17419099999999,38.78585],"type":"Point"}
}