{
  "type": "Feature",
  "properties": {
    "addr:full":"4700 Stonecroft Blvd Chantilly VA 20151",
    "addr:postcode":"4700;20151",
    "addr:street":"Stonecroft Blvd",
    "iso:country":"US",
    "sg:address":"4700 Stonecroft Blvd",
    "sg:city":"Chantilly",
    "sg:classifiers":[
        {
            "category":"Education",
            "subcategory":"School",
            "type":"Public Place"
        }
    ],
    "sg:phone":"+1 703 488 6300",
    "sg:postcode":"20151",
    "sg:province":"VA",
    "sg:tags":[
        "high"
    ],
    "wof:name":"Westfield High School",
    "wof:placetype":"venue"
},
  "geometry": {"coordinates":[-77.462053,38.884315],"type":"Point"}
}