{
  "type": "Feature",
  "properties": {
    "addr:full":"2835 Dorr Ave Fairfax VA 22031",
    "addr:housenumber":"2835",
    "addr:postcode":"22031",
    "addr:street":"Dorr Ave",
    "iso:country":"US",
    "sg:address":"2835 Dorr Ave",
    "sg:city":"Fairfax",
    "sg:classifiers":[
        {
            "category":"Food & Beverages",
            "subcategory":"Groceries & Convenience Stores",
            "type":"Retail Goods"
        }
    ],
    "sg:phone":"+1 703 206 0500",
    "sg:postcode":"22031",
    "sg:province":"VA",
    "sg:tags":[
        "market"
    ],
    "wof:name":"Marvelous Markets Inc",
    "wof:placetype":"venue"
},
  "geometry": {"coordinates":[-77.233935,38.875742],"type":"Point"}
}