{
  "type": "Feature",
  "properties": {
    "addr:full":"5100 Leesburg Pike Ste 200 Alexandria VA 22302",
    "addr:housenumber":"5100",
    "addr:postcode":"22302",
    "addr:street":"Leesburg Pike Ste 200",
    "iso:country":"US",
    "sg:address":"5100 Leesburg Pike Ste 200",
    "sg:city":"Alexandria",
    "sg:classifiers":[
        {
            "category":"Real Estate",
            "subcategory":"Real Estate Services",
            "type":"Services"
        },
        {
            "category":"Real Estate",
            "subcategory":"Real Estate Agent",
            "type":"Services"
        }
    ],
    "sg:phone":"+1 703 868 5999",
    "sg:postcode":"22302",
    "sg:province":"VA",
    "sg:website":"www.dcmetroneighborhoods.com/",
    "wof:name":"Shaun Murphy - RE/MAX Allegiance",
    "wof:placetype":"venue"
},
  "geometry": {"coordinates":[-77.11508000000001,38.845459],"type":"Point"}
}