{
  "type": "Feature",
  "properties": {
    "iso:country":"US",
    "sg:address":"115 Hanover Ave",
    "sg:city":"Ashland",
    "sg:phone":"+1 804 266 5702",
    "sg:postcode":"23005",
    "sg:province":"VA",
    "sg:tags":[
        "scale"
    ],
    "wof:name":"Tidewater Scale & Butcher Spls",
    "wof:placetype":"venue"
},
  "geometry": {"coordinates":[-77.483091,37.758149],"type":"Point"}
}