{
  "type": "Feature",
  "properties": {
    "addr:full":"6067 Elko Rd Sandston VA 23150",
    "addr:postcode":"6067;23150",
    "addr:street":"Elko Rd",
    "iso:country":"US",
    "sg:address":"6067 Elko Rd",
    "sg:city":"Sandston",
    "sg:classifiers":[
        {
            "category":"Retail",
            "subcategory":"Auto Repair",
            "type":"Services"
        }
    ],
    "sg:phone":"+1 804 737 6015",
    "sg:postcode":"23150",
    "sg:province":"VA",
    "sg:tags":[
        "wrecker"
    ],
    "wof:name":"Sid's Towing Svc",
    "wof:placetype":"venue"
},
  "geometry": {"coordinates":[-77.21969300000001,37.489578],"type":"Point"}
}