{
  "type": "Feature",
  "properties": {
    "iso:country":"US",
    "sg:address":"13848 Lee Hwy",
    "sg:city":"Centreville",
    "sg:classifiers":[
        {
            "category":"Building & Trades",
            "subcategory":"Construction",
            "type":"Services"
        }
    ],
    "sg:phone":"+1 703 631 0982",
    "sg:postcode":"20120",
    "sg:province":"VA",
    "sg:tags":[
        "maker",
        "cabinet"
    ],
    "wof:name":"Total Cabinet Distributors Inc",
    "wof:placetype":"venue"
},
  "geometry": {"coordinates":[-77.425327,38.838972],"type":"Point"}
}