{
  "type": "Feature",
  "properties": {
    "addr:full":"2312 Lee Hwy Marion VA 24354",
    "addr:housenumber":"2312",
    "addr:postcode":"24354",
    "addr:street":"Lee Hwy",
    "iso:country":"US",
    "sg:address":"2312 Lee Hwy",
    "sg:city":"Marion",
    "sg:classifiers":[
        {
            "category":"Manufacturing",
            "subcategory":"Lumber",
            "type":"Manufacturing & Wholesale Goods"
        }
    ],
    "sg:phone":"+1 276 783 3331",
    "sg:postcode":"24354",
    "sg:province":"VA",
    "sg:tags":[
        "company",
        "logging"
    ],
    "wof:name":"Mountain Resources Inc",
    "wof:placetype":"venue"
},
  "geometry": {"coordinates":[-81.58762299999999,36.812325],"type":"Point"}
}