{
  "type": "Feature",
  "properties": {
    "addr:full":"9397 Peter Roy Ct Burke VA 22015",
    "addr:housenumber":"9397",
    "addr:postcode":"22015",
    "addr:street":"Peter Roy Ct",
    "iso:country":"US",
    "sg:address":"9397 Peter Roy Ct",
    "sg:city":"Burke",
    "sg:classifiers":[
        {
            "category":"Professional",
            "subcategory":"Business Services",
            "type":"Services"
        }
    ],
    "sg:phone":"+1 703 644 1238",
    "sg:postcode":"22015",
    "sg:province":"VA",
    "wof:name":"Armstrong Business Development",
    "wof:placetype":"venue"
},
  "geometry": {"coordinates":[-77.26993299999999,38.775245],"type":"Point"}
}