{
  "type": "Feature",
  "properties": {
    "addr:full":"4209 North Ave Richmond VA 23222",
    "addr:housenumber":"4209",
    "addr:postcode":"23222",
    "addr:street":"North Ave",
    "iso:country":"US",
    "sg:address":"4209 North Ave",
    "sg:city":"Richmond",
    "sg:classifiers":[
        {
            "category":"Personal",
            "subcategory":"Beauty Salon",
            "type":"Services"
        },
        {
            "category":"Wholesale",
            "subcategory":"Machinery & Supplies",
            "type":"Manufacturing & Wholesale Goods"
        }
    ],
    "sg:phone":"+1 804 329 6103",
    "sg:postcode":"23222",
    "sg:province":"VA",
    "sg:tags":[
        "salons-equipment"
    ],
    "wof:name":"Beauty Empire Inc",
    "wof:placetype":"venue"
},
  "geometry": {"coordinates":[-77.442375,37.586694],"type":"Point"}
}