{
  "type": "Feature",
  "properties": {
    "addr:full":"664 Village Hwy Rustburg VA 24588",
    "addr:housenumber":"664",
    "addr:postcode":"24588",
    "addr:street":"Village Hwy",
    "iso:country":"US",
    "sg:address":"664 Village Hwy",
    "sg:city":"Rustburg",
    "sg:classifiers":[
        {
            "category":"Social Services",
            "subcategory":"Child Care",
            "type":"Services"
        }
    ],
    "sg:phone":"+1 434 332 6078",
    "sg:postcode":"24588",
    "sg:province":"VA",
    "wof:name":"Bashful Giraffi Child Care Too",
    "wof:placetype":"venue"
},
  "geometry": {"coordinates":[-79.102778,37.275917],"type":"Point"}
}