{
  "type": "Feature",
  "properties": {
    "addr:full":"13800 Coppermine Rd Herndon VA 20171",
    "addr:housenumber":"13800",
    "addr:postcode":"20171",
    "addr:street":"Coppermine Rd",
    "iso:country":"US",
    "sg:address":"13800 Coppermine Rd",
    "sg:city":"Herndon",
    "sg:classifiers":[
        {
            "category":"Government",
            "subcategory":"Office",
            "type":"Public Place"
        }
    ],
    "sg:phone":"+1 703 234 7815",
    "sg:postcode":"20171",
    "sg:province":"VA",
    "sg:tags":[
        "agricultural",
        "regulation",
        "marketing"
    ],
    "wof:name":"Extension Group",
    "wof:placetype":"venue"
},
  "geometry": {"coordinates":[-77.419062,38.950357],"type":"Point"}
}