{
  "type": "Feature",
  "properties": {
    "iso:country":"US",
    "sg:address":"7188 Allison Ln",
    "sg:city":"Hayes",
    "sg:classifiers":[
        {
            "category":"Building & Trades",
            "subcategory":"Construction",
            "type":"Services"
        }
    ],
    "sg:phone":"+1 804 642 6852",
    "sg:postcode":"23072",
    "sg:province":"VA",
    "sg:tags":[
        "general",
        "contractor"
    ],
    "wof:name":"Bayside Construction",
    "wof:placetype":"venue"
},
  "geometry": {"coordinates":[-76.522283,37.289222],"type":"Point"}
}