{
  "type": "Feature",
  "properties": {
    "addr:full":"812 Thompson Dr Abingdon VA 24210",
    "addr:housenumber":"812",
    "addr:postcode":"24210",
    "addr:street":"Thompson Dr",
    "iso:country":"US",
    "sg:address":"812 Thompson Dr",
    "sg:city":"Abingdon",
    "sg:classifiers":[
        {
            "category":"Government",
            "subcategory":"Office",
            "type":"Public Place"
        }
    ],
    "sg:phone":"+1 276 628 1836",
    "sg:postcode":"24210",
    "sg:province":"VA",
    "sg:tags":[
        "county",
        "program",
        "adm"
    ],
    "wof:name":"Washington County Economic Dev",
    "wof:placetype":"venue"
},
  "geometry": {"coordinates":[-81.951708,36.720799],"type":"Point"}
}