{
  "type": "Feature",
  "properties": {
    "addr:full":"13480 Carrollton Blvd Carrollton VA 23314",
    "addr:housenumber":"13480",
    "addr:postcode":"23314",
    "addr:street":"Carrollton Blvd",
    "iso:country":"US",
    "sg:address":"13480 Carrollton Blvd",
    "sg:city":"Carrollton",
    "sg:classifiers":[
        {
            "category":"Banks & Credit Unions",
            "subcategory":"Bank",
            "type":"Services"
        }
    ],
    "sg:phone":"+1 757 728 1776",
    "sg:postcode":"23314",
    "sg:province":"VA",
    "wof:name":"Old Point National Bank",
    "wof:placetype":"venue"
},
  "geometry": {"coordinates":[-76.531491,36.9522],"type":"Point"}
}