{
  "type": "Feature",
  "properties": {
    "iso:country":"US",
    "sg:address":"9617 2nd Bay St",
    "sg:city":"Norfolk",
    "sg:classifiers":[
        {
            "category":"Personal",
            "type":"Services"
        }
    ],
    "sg:phone":"+1 757 480 4538",
    "sg:postcode":"23518",
    "sg:province":"VA",
    "wof:name":"Independent Herbalife Distr",
    "wof:placetype":"venue"
},
  "geometry": {"coordinates":[-76.21494199999999,36.934426],"type":"Point"}
}