{
  "type": "Feature",
  "properties": {
    "iso:country":"US",
    "sg:address":"847 W 45th St",
    "sg:city":"Norfolk",
    "sg:classifiers":[
        {
            "category":"Wholesale",
            "subcategory":"Electrical",
            "type":"Manufacturing & Wholesale Goods"
        }
    ],
    "sg:phone":"+1 757 489 3900",
    "sg:postcode":"23508",
    "sg:province":"VA",
    "sg:tags":[
        "equipment",
        "electric",
        "supply"
    ],
    "wof:name":"KWAT Enterprises Corp",
    "wof:placetype":"venue"
},
  "geometry": {"coordinates":[-76.29685499999999,36.88494],"type":"Point"}
}