{
  "type": "Feature",
  "properties": {
    "addr:full":"270 S Main St Rocky Mount VA 24151",
    "addr:housenumber":"270",
    "addr:postcode":"24151",
    "addr:street":"S Main St",
    "iso:country":"US",
    "sg:address":"270 S Main St",
    "sg:city":"Rocky Mount",
    "sg:classifiers":[
        {
            "category":"Professional",
            "subcategory":"Lawyer & Legal Services",
            "type":"Services"
        }
    ],
    "sg:phone":"+1 540 483 9488",
    "sg:postcode":"24151",
    "sg:province":"VA",
    "wof:name":"Allen Timothy W",
    "wof:placetype":"venue"
},
  "geometry": {"coordinates":[-79.88949599999999,36.994498],"type":"Point"}
}