{
  "type": "Feature",
  "properties": {
    "addr:full":"11929 Market St Reston VA 20190",
    "addr:housenumber":"11929",
    "addr:postcode":"20190",
    "addr:street":"Market St",
    "iso:country":"US",
    "sg:address":"11929 Market St",
    "sg:city":"Reston",
    "sg:classifiers":[
        {
            "category":"Shopping",
            "subcategory":"Clothing, Apparel, & Fashions",
            "type":"Retail Goods"
        }
    ],
    "sg:phone":"+1 703 904 9245",
    "sg:postcode":"20190",
    "sg:province":"VA",
    "wof:name":"Express LLC",
    "wof:placetype":"venue"
},
  "geometry": {"coordinates":[-77.357315,38.958632],"type":"Point"}
}