{
  "type": "Feature",
  "properties": {
    "addr:full":"7629 Williamson Rd Hollins VA 24019",
    "addr:housenumber":"7629",
    "addr:postcode":"24019",
    "addr:street":"Williamson Rd",
    "iso:country":"US",
    "sg:address":"7629 Williamson Rd",
    "sg:city":"Hollins",
    "sg:classifiers":[
        {
            "category":"Banks & Credit Unions",
            "subcategory":"Bank",
            "type":"Services"
        }
    ],
    "sg:phone":"+1 540 563 9000",
    "sg:postcode":"24019",
    "sg:province":"VA",
    "sg:tags":[
        "mortgage",
        "loan",
        "broker",
        "real estate"
    ],
    "sg:website":"www.dropmypayments.com",
    "wof:name":"Affordable Mortgage Corp",
    "wof:placetype":"venue"
},
  "geometry": {"coordinates":[-79.944222,37.350214],"type":"Point"}
}