{
  "type": "Feature",
  "properties": {
    "addr:full":"4906 Old Dominion Dr Arlington VA 22207",
    "addr:housenumber":"4906",
    "addr:postcode":"22207",
    "addr:street":"Old Dominion Dr",
    "iso:country":"US",
    "sg:address":"4906 Old Dominion Dr",
    "sg:city":"Arlington",
    "sg:classifiers":[
        {
            "category":"Health Services",
            "subcategory":"Dentist",
            "type":"Services"
        }
    ],
    "sg:phone":"+1 703 534 9357",
    "sg:postcode":"22207",
    "sg:province":"VA",
    "wof:name":"Burke William J DD Sc",
    "wof:placetype":"venue"
},
  "geometry": {"coordinates":[-77.138199,38.910099],"type":"Point"}
}