{
  "type": "Feature",
  "properties": {
    "addr:full":"1305 N King St Hampton VA 23669",
    "addr:housenumber":"1305",
    "addr:postcode":"23669",
    "addr:street":"N King St",
    "iso:country":"US",
    "sg:address":"1305 N King St",
    "sg:city":"Hampton",
    "sg:classifiers":[
        {
            "category":"Restaurant",
            "type":"Food & Drink"
        }
    ],
    "sg:phone":"+1 757 722 8008",
    "sg:postcode":"23669",
    "sg:province":"VA",
    "wof:name":"Great Wall Restaurant",
    "wof:placetype":"venue"
},
  "geometry": {"coordinates":[-76.347281,37.05446],"type":"Point"}
}