{
  "type": "Feature",
  "properties": {
    "iso:country":"US",
    "sg:address":"2217 Yorktown Ave",
    "sg:city":"Lynchburg",
    "sg:classifiers":[
        {
            "category":"Building & Trades",
            "subcategory":"Cleaning & Sanitation",
            "type":"Services"
        }
    ],
    "sg:phone":"+1 434 528 0130",
    "sg:postcode":"24501",
    "sg:province":"VA",
    "sg:tags":[
        "janitor"
    ],
    "wof:name":"Lorenzo's Cleaning Svc",
    "wof:placetype":"venue"
},
  "geometry": {"coordinates":[-79.176321,37.411393],"type":"Point"}
}