{
  "type": "Feature",
  "properties": {
    "addr:full":"13079 Fair Lakes Shopping Ctr Fairfax VA 22033",
    "addr:housenumber":"13079",
    "addr:postcode":"22033",
    "addr:street":"Fair Lakes Shopping Ctr",
    "iso:country":"US",
    "sg:address":"13079 Fair Lakes Shopping Ctr",
    "sg:city":"Fairfax",
    "sg:classifiers":[
        {
            "category":"Retail",
            "subcategory":"Laundry & Dry Cleaning",
            "type":"Services"
        }
    ],
    "sg:phone":"+1 703 502 1031",
    "sg:postcode":"22033",
    "sg:province":"VA",
    "sg:tags":[
        "cleaner"
    ],
    "sg:website":"http://www.fairlakes.com",
    "wof:name":"Fair Center Cleaners",
    "wof:placetype":"venue"
},
  "geometry": {"coordinates":[-77.397779,38.855858],"type":"Point"}
}