{
  "type": "Feature",
  "properties": {
    "addr:full":"13080 Toler Ln Rockville VA 23146",
    "addr:housenumber":"13080",
    "addr:postcode":"23146",
    "addr:street":"Toler Ln",
    "iso:country":"US",
    "sg:address":"13080 Toler Ln",
    "sg:city":"Rockville",
    "sg:classifiers":[
        {
            "category":"Building & Trades",
            "subcategory":"Construction",
            "type":"Services"
        }
    ],
    "sg:phone":"+1 804 749 4404",
    "sg:postcode":"23146",
    "sg:province":"VA",
    "sg:tags":[
        "hanging",
        "contractor"
    ],
    "wof:name":"Gregory A Nuckols",
    "wof:placetype":"venue"
},
  "geometry": {"coordinates":[-77.73797399999999,37.760292],"type":"Point"}
}