{
  "type": "Feature",
  "properties": {
    "addr:full":"5810 Kingstowne Ctr # 120 Alexandria VA 22315",
    "addr:housenumber":"5810",
    "addr:postcode":"22315",
    "addr:street":"Kingstowne Ctr # 120",
    "iso:country":"US",
    "sg:address":"5810 Kingstowne Ctr # 120",
    "sg:city":"Alexandria",
    "sg:classifiers":[
        {
            "category":"Banks & Credit Unions",
            "subcategory":"Financial Services",
            "type":"Services"
        }
    ],
    "sg:phone":"+1 703 971 5444",
    "sg:postcode":"22315",
    "sg:province":"VA",
    "sg:tags":[
        "information",
        "consumer"
    ],
    "sg:website":"http://www.crizerbrothers.com",
    "wof:name":"Logistics Systems Incorporated",
    "wof:placetype":"venue"
},
  "geometry": {"coordinates":[-77.136595,38.771042],"type":"Point"}
}