{
  "type": "Feature",
  "properties": {
    "addr:full":"5007 Lankford Hwy New Church VA 23415",
    "addr:housenumber":"5007",
    "addr:postcode":"church;23415",
    "addr:street":"Lankford Hwy",
    "iso:country":"US",
    "sg:address":"5007 Lankford Hwy",
    "sg:city":"New Church",
    "sg:classifiers":[
        {
            "category":"Retail",
            "subcategory":"Auto Rental",
            "type":"Services"
        }
    ],
    "sg:phone":"+1 757 824 4888",
    "sg:postcode":"23415",
    "sg:province":"VA",
    "sg:tags":[
        "renting",
        "automobile"
    ],
    "wof:name":"Rent A Ride",
    "wof:placetype":"venue"
},
  "geometry": {"coordinates":[-75.5322,37.968857],"type":"Point"}
}