{
  "type": "Feature",
  "properties": {
    "addr:full":"30889 Christanna Hwy Dundas VA 23938",
    "addr:postcode":"30889;23938",
    "addr:street":"Christanna Hwy",
    "iso:country":"US",
    "sg:address":"30889 Christanna Hwy",
    "sg:city":"Dundas",
    "sg:classifiers":[
        {
            "category":"Building & Trades",
            "subcategory":"Electrical",
            "type":"Services"
        }
    ],
    "sg:phone":"+1 434 676 1946",
    "sg:postcode":"23938",
    "sg:province":"VA",
    "sg:tags":[
        "electrical",
        "contractor"
    ],
    "wof:name":"Full Circuit",
    "wof:placetype":"venue"
},
  "geometry": {"coordinates":[-77.96158800000001,36.913058],"type":"Point"}
}