{
  "type": "Feature",
  "properties": {
    "iso:country":"US",
    "sg:address":"3165 N Franklin St",
    "sg:city":"Christiansburg",
    "sg:classifiers":[
        {
            "category":"Shopping",
            "subcategory":"Gifts & Souvenirs",
            "type":"Retail Goods"
        }
    ],
    "sg:phone":"+1 540 381 3339",
    "sg:postcode":"24073",
    "sg:province":"VA",
    "sg:tags":[
        "shop"
    ],
    "wof:name":"Tuesday Morning",
    "wof:placetype":"venue"
},
  "geometry": {"coordinates":[-80.420204,37.172724],"type":"Point"}
}