{
  "type": "Feature",
  "properties": {
    "addr:full":"17497 Old Stage Coach Rd Dumfries VA 22026",
    "addr:housenumber":"17497",
    "addr:postcode":"22026",
    "addr:street":"Old Stage Coach Rd",
    "iso:country":"US",
    "sg:address":"17497 Old Stage Coach Rd",
    "sg:city":"Dumfries",
    "sg:classifiers":[
        {
            "category":"Manufacturing",
            "subcategory":"Building Materials",
            "type":"Manufacturing & Wholesale Goods"
        },
        {
            "category":"Building & Trades",
            "subcategory":"Construction",
            "type":"Services"
        }
    ],
    "sg:phone":"+1 703 221 4788",
    "sg:postcode":"22026",
    "sg:province":"VA",
    "sg:tags":[
        "cabinet",
        "mfg",
        "maker",
        "cabinetry",
        "custom"
    ],
    "wof:name":"Clarks Lumber & Millwork",
    "wof:placetype":"venue"
},
  "geometry": {"coordinates":[-77.316536,38.571577],"type":"Point"}
}