{
  "type": "Feature",
  "properties": {
    "addr:full":"5707 Centre Square Dr Centreville VA 20120",
    "addr:housenumber":"5707",
    "addr:postcode":"20120",
    "addr:street":"Centre Square Dr",
    "iso:country":"US",
    "sg:address":"5707 Centre Square Dr",
    "sg:city":"Centreville",
    "sg:classifiers":[
        {
            "category":"Health Services",
            "subcategory":"Doctor",
            "type":"Services"
        }
    ],
    "sg:phone":"+1 703 391 0900",
    "sg:postcode":"20120",
    "sg:province":"VA",
    "sg:tags":[
        "pediatric"
    ],
    "wof:name":"Fairfax Pediatric Associates",
    "wof:placetype":"venue"
},
  "geometry": {"coordinates":[-77.430502,38.839903],"type":"Point"}
}