{
  "type": "Feature",
  "properties": {
    "addr:full":"3988 Greensboro Rd Ridgeway VA 24148",
    "addr:housenumber":"3988",
    "addr:postcode":"24148",
    "addr:street":"Greensboro Rd",
    "iso:country":"US",
    "sg:address":"3988 Greensboro Rd",
    "sg:city":"Ridgeway",
    "sg:classifiers":[
        {
            "category":"Real Estate",
            "subcategory":"Real Estate Agent",
            "type":"Services"
        }
    ],
    "sg:phone":"+1 276 656 3999",
    "sg:postcode":"24148",
    "sg:province":"VA",
    "wof:name":"Vaughn Real Estate Inc",
    "wof:placetype":"venue"
},
  "geometry": {"coordinates":[-79.859793,36.638167],"type":"Point"}
}