{
  "type": "Feature",
  "properties": {
    "addr:full":"11616 Busy St Richmond VA 23236",
    "addr:housenumber":"11616",
    "addr:postcode":"23236",
    "addr:street":"Busy St",
    "iso:country":"US",
    "sg:address":"11616 Busy St",
    "sg:city":"Richmond",
    "sg:classifiers":[
        {
            "category":"Building & Trades",
            "subcategory":"Construction",
            "type":"Services"
        }
    ],
    "sg:phone":"+1 804 378 9339",
    "sg:postcode":"23236",
    "sg:province":"VA",
    "sg:tags":[
        "house",
        "general",
        "contractor"
    ],
    "wof:name":"Retail Construction & Dev Inc",
    "wof:placetype":"venue"
},
  "geometry": {"coordinates":[-77.610393,37.502441],"type":"Point"}
}