{
  "type": "Feature",
  "properties": {
    "iso:country":"US",
    "sg:address":"4230 Electric Rd",
    "sg:city":"Roanoke",
    "sg:classifiers":[
        {
            "category":"Shopping",
            "subcategory":"Clothing, Apparel, & Fashions",
            "type":"Retail Goods"
        },
        {
            "category":"Shopping",
            "subcategory":"Department Store",
            "type":"Retail Goods"
        },
        {
            "category":"Shopping",
            "subcategory":"Discount & Variety Stores",
            "type":"Retail Goods"
        }
    ],
    "sg:phone":"+1 540 774 8224",
    "sg:postcode":"24018",
    "sg:province":"VA",
    "sg:tags":[
        "apparel",
        "men's",
        "clothing",
        "women's"
    ],
    "sg:website":"http://www.steinmart.com/",
    "wof:name":"Stein Mart",
    "wof:placetype":"venue"
},
  "geometry": {"coordinates":[-79.97923299999999,37.227379],"type":"Point"}
}