{
  "type": "Feature",
  "properties": {
    "iso:country":"US",
    "sg:address":"316 Warren Ave",
    "sg:city":"Front Royal",
    "sg:classifiers":[
        {
            "category":"Professional",
            "type":"Services"
        }
    ],
    "sg:phone":"+1 540 635 9111",
    "sg:postcode":"22630",
    "sg:province":"VA",
    "sg:tags":[
        "establishment"
    ],
    "wof:name":"Leslie Harding Certified",
    "wof:placetype":"venue"
},
  "geometry": {"coordinates":[-78.192604,38.923711],"type":"Point"}
}