{
  "type": "Feature",
  "properties": {
    "iso:country":"US",
    "sg:address":"283 Wild Rose Ln",
    "sg:city":"Independence",
    "sg:classifiers":[
        {
            "category":"Professional",
            "subcategory":"Business Services",
            "type":"Services"
        }
    ],
    "sg:phone":"+1 276 744 7689",
    "sg:postcode":"24348",
    "sg:province":"VA",
    "wof:name":"Nuckolls Transporting",
    "wof:placetype":"venue"
},
  "geometry": {"coordinates":[-81.06008,36.684227],"type":"Point"}
}