{
  "type": "Feature",
  "properties": {
    "iso:country":"US",
    "sg:address":"16025 Fairway Dr",
    "sg:city":"Dumfries",
    "sg:classifiers":[
        {
            "category":"Organizations",
            "subcategory":"Professional Association",
            "type":"Services"
        }
    ],
    "sg:phone":"+1 703 730 3040",
    "sg:postcode":"22025",
    "sg:province":"VA",
    "sg:tags":[
        "merchant"
    ],
    "wof:name":"First Data",
    "wof:placetype":"venue"
},
  "geometry": {"coordinates":[-77.338792,38.605156],"type":"Point"}
}