{
  "type": "Feature",
  "properties": {
    "iso:country":"US",
    "sg:address":"203 E Cary St",
    "sg:city":"Richmond",
    "sg:classifiers":[
        {
            "category":"Professional",
            "subcategory":"Engineering",
            "type":"Services"
        }
    ],
    "sg:phone":"+1 804 225 0348",
    "sg:postcode":"23219",
    "sg:province":"VA",
    "wof:name":"The Berger Louis Group Dom",
    "wof:placetype":"venue"
},
  "geometry": {"coordinates":[-77.442567,37.540525],"type":"Point"}
}