{
  "type": "Feature",
  "properties": {
    "addr:full":"13817 Foulger Sq Woodbridge VA 22192",
    "addr:housenumber":"13817",
    "addr:postcode":"22192",
    "addr:street":"Foulger Sq",
    "iso:country":"US",
    "sg:address":"13817 Foulger Sq",
    "sg:city":"Woodbridge",
    "sg:classifiers":[
        {
            "category":"Shopping",
            "subcategory":"Discount & Variety Stores",
            "type":"Retail Goods"
        }
    ],
    "sg:phone":"+1 703 590 6336",
    "sg:postcode":"22192",
    "sg:province":"VA",
    "wof:name":"Dollar City Plus",
    "wof:placetype":"venue"
},
  "geometry": {"coordinates":[-77.30392000000001,38.654964],"type":"Point"}
}