{
  "type": "Feature",
  "properties": {
    "addr:full":"198 Spotnap Rd Charlottesville VA 22911",
    "addr:housenumber":"198",
    "addr:postcode":"22911",
    "addr:street":"Spotnap Rd",
    "iso:country":"US",
    "sg:address":"198 Spotnap Rd",
    "sg:city":"Charlottesville",
    "sg:classifiers":[
        {
            "category":"Health Services",
            "subcategory":"Clinic",
            "type":"Services"
        }
    ],
    "sg:phone":"+1 434 984 4627",
    "sg:postcode":"22911",
    "sg:province":"VA",
    "sg:tags":[
        "organization",
        "medical",
        "surgical"
    ],
    "wof:name":"IMBS",
    "wof:placetype":"venue"
},
  "geometry": {"coordinates":[-78.45254199999999,38.031865],"type":"Point"}
}