{
  "type": "Feature",
  "properties": {
    "iso:country":"US",
    "sg:address":"1240 Tazewell Ave SE",
    "sg:city":"Roanoke",
    "sg:classifiers":[
        {
            "category":"Organizations",
            "subcategory":"Religious Organization",
            "type":"Services"
        }
    ],
    "sg:phone":"+1 540 777 7659",
    "sg:postcode":"24013",
    "sg:province":"VA",
    "sg:tags":[
        "church"
    ],
    "wof:name":"Tabernacle Of David",
    "wof:placetype":"venue"
},
  "geometry": {"coordinates":[-79.923687,37.273244],"type":"Point"}
}