{
  "type": "Feature",
  "properties": {
    "addr:full":"1390 Broad Street Rd Oilville VA 23129",
    "addr:housenumber":"1390",
    "addr:postcode":"23129",
    "addr:street":"Broad Street Rd",
    "iso:country":"US",
    "sg:address":"1390 Broad Street Rd",
    "sg:city":"Oilville",
    "sg:classifiers":[
        {
            "category":"Building & Trades",
            "subcategory":"Construction",
            "type":"Services"
        }
    ],
    "sg:phone":"+1 804 784 2679",
    "sg:postcode":"23129",
    "sg:province":"VA",
    "sg:tags":[
        "house",
        "contractor"
    ],
    "wof:name":"Thompson Builders LLC",
    "wof:placetype":"venue"
},
  "geometry": {"coordinates":[-77.781406,37.702348],"type":"Point"}
}