{
  "type": "Feature",
  "properties": {
    "iso:country":"US",
    "sg:address":"11109 Glade Dr",
    "sg:city":"Reston",
    "sg:classifiers":[
        {
            "category":"Professional",
            "subcategory":"Computer Services",
            "type":"Services"
        }
    ],
    "sg:phone":"+1 703 620 4762",
    "sg:postcode":"20191",
    "sg:province":"VA",
    "sg:tags":[
        "development",
        "software"
    ],
    "wof:name":"Ringneck Technologies Inc",
    "wof:placetype":"venue"
},
  "geometry": {"coordinates":[-77.326761,38.929808],"type":"Point"}
}