{
  "type": "Feature",
  "properties": {
    "iso:country":"US",
    "sg:address":"1714 East Washington St.",
    "sg:city":"Petersburg",
    "sg:classifiers":[
        {
            "category":"Restaurant",
            "type":"Food & Drink"
        }
    ],
    "sg:phone":"+1 804 733 7725",
    "sg:postcode":"23803",
    "sg:province":"VA",
    "sg:tags":[
        "bar",
        "seafood",
        "sushi",
        "japanese",
        "asian",
        "korean",
        "pan"
    ],
    "wof:name":"Seoul Fusion Restaurant",
    "wof:placetype":"venue"
},
  "geometry": {"coordinates":[-77.37530099999999,37.238393],"type":"Point"}
}