{
  "type": "Feature",
  "properties": {
    "iso:country":"US",
    "sg:address":"356 W Broad St",
    "sg:city":"Falls Church",
    "sg:classifiers":[
        {
            "category":"Professional",
            "subcategory":"Accounting & Tax Preparation",
            "type":"Services"
        }
    ],
    "sg:phone":"+1 703 241 9854",
    "sg:postcode":"22046",
    "sg:province":"VA",
    "sg:tags":[
        "return",
        "filing"
    ],
    "wof:name":"H & R Block Tax Svc",
    "wof:placetype":"venue"
},
  "geometry": {"coordinates":[-77.17419,38.884188],"type":"Point"}
}