{
  "type": "Feature",
  "properties": {
    "addr:full":"12300 Jefferson Ave Newport News VA 23602",
    "addr:housenumber":"12300",
    "addr:postcode":"23602",
    "addr:street":"Jefferson Ave",
    "iso:country":"US",
    "sg:address":"12300 Jefferson Ave",
    "sg:city":"Newport News",
    "sg:classifiers":[
        {
            "category":"Restaurant",
            "type":"Food & Drink"
        }
    ],
    "sg:menulink":"http://www.allmenus.com/va/newport-news/8999-red-robin/menu/",
    "sg:phone":"+1 757 882 8959",
    "sg:postcode":"23602",
    "sg:province":"VA",
    "sg:tags":[
        "american"
    ],
    "wof:name":"Red Robin",
    "wof:placetype":"venue"
},
  "geometry": {"coordinates":[-76.504981,37.119508],"type":"Point"}
}