{
  "type": "Feature",
  "properties": {
    "addr:full":"714 10th St Blackstone VA 23824",
    "addr:housenumber":"714",
    "addr:postcode":"23824",
    "addr:street":"10Th St",
    "iso:country":"US",
    "sg:address":"714 10th St",
    "sg:city":"Blackstone",
    "sg:classifiers":[
        {
            "category":"Building & Trades",
            "subcategory":"Construction",
            "type":"Services"
        }
    ],
    "sg:phone":"+1 434 292 3640",
    "sg:postcode":"23824",
    "sg:province":"VA",
    "sg:tags":[
        "contractor"
    ],
    "wof:name":"Dalton Danny K Brick Mason",
    "wof:placetype":"venue"
},
  "geometry": {"coordinates":[-78.012601,37.068317],"type":"Point"}
}