{
  "type": "Feature",
  "properties": {
    "iso:country":"US",
    "sg:address":"671 W Glebe Rd Ste 300",
    "sg:city":"Alexandria",
    "sg:classifiers":[
        {
            "category":"Banks & Credit Unions",
            "subcategory":"Investment Brokerage",
            "type":"Services"
        },
        {
            "category":"Real Estate",
            "subcategory":"Developer",
            "type":"Services"
        }
    ],
    "sg:phone":"+1 703 329 6300",
    "sg:postcode":"22305",
    "sg:province":"VA",
    "sg:tags":[
        "investing"
    ],
    "sg:website":"http://www.avalonbay.com",
    "wof:name":"Avalonbay Communities, Inc.",
    "wof:placetype":"venue"
},
  "geometry": {"coordinates":[-77.067705,38.8403],"type":"Point"}
}