{
  "type": "Feature",
  "properties": {
    "addr:full":"4620 Lee Hwy Ste 216 Arlington VA 22207",
    "addr:housenumber":"4620",
    "addr:postcode":"22207",
    "addr:street":"Lee Hwy Ste 216",
    "iso:country":"US",
    "sg:address":"4620 Lee Hwy Ste 216",
    "sg:city":"Arlington",
    "sg:classifiers":[
        {
            "category":"Professional",
            "subcategory":"Lawyer & Legal Services",
            "type":"Services"
        }
    ],
    "sg:phone":"+1 703 524 0880",
    "sg:postcode":"22207",
    "sg:province":"VA",
    "wof:name":"Behavioral Law Center",
    "wof:placetype":"venue"
},
  "geometry": {"coordinates":[-77.11990400000001,38.898602],"type":"Point"}
}