{
  "type": "Feature",
  "properties": {
    "addr:full":"800 Jefferson St Charlottesville VA 22902",
    "addr:housenumber":"800",
    "addr:postcode":"22902",
    "addr:street":"Jefferson St",
    "iso:country":"US",
    "sg:address":"800 Jefferson St",
    "sg:city":"Charlottesville",
    "sg:classifiers":[
        {
            "category":"Professional",
            "subcategory":"Engineering",
            "type":"Services"
        }
    ],
    "sg:phone":"+1 434 295 5624",
    "sg:postcode":"22902",
    "sg:province":"VA",
    "sg:tags":[
        "engineer"
    ],
    "sg:website":"www.timmons.com",
    "wof:name":"Timmons Group Inc",
    "wof:placetype":"venue"
},
  "geometry": {"coordinates":[-78.47444299999999,38.030646],"type":"Point"}
}