{
  "type": "Feature",
  "properties": {
    "iso:country":"US",
    "sg:address":"626 N Ridge St",
    "sg:city":"Danville",
    "sg:classifiers":[
        {
            "category":"Organizations",
            "subcategory":"Membership Organization",
            "type":"Services"
        },
        {
            "category":"Personal",
            "type":"Services"
        }
    ],
    "sg:phone":"+1 434 799 3307",
    "sg:postcode":"24541",
    "sg:province":"VA",
    "sg:tags":[
        "counseling",
        "debt",
        "credit"
    ],
    "wof:name":"American Fair Credit Assn",
    "wof:placetype":"venue"
},
  "geometry": {"coordinates":[-79.40009999999999,36.592425],"type":"Point"}
}