{
  "type": "Feature",
  "properties": {
    "iso:country":"US",
    "sg:address":"305 Eheart St SW",
    "sg:city":"Blacksburg",
    "sg:classifiers":[
        {
            "category":"Professional",
            "subcategory":"Research",
            "type":"Services"
        }
    ],
    "sg:phone":"+1 540 552 9563",
    "sg:postcode":"24060",
    "sg:province":"VA",
    "sg:tags":[
        "mathematical"
    ],
    "wof:name":"Ezra A Brown",
    "wof:placetype":"venue"
},
  "geometry": {"coordinates":[-80.412063,37.22428],"type":"Point"}
}