{
  "type": "Feature",
  "properties": {
    "addr:full":"3150 William Styron Sq N Newport News VA 23606",
    "addr:housenumber":"3150",
    "addr:postcode":"23606",
    "addr:street":"William Styron Sq N",
    "iso:country":"US",
    "sg:address":"3150 William Styron Sq N",
    "sg:city":"Newport News",
    "sg:classifiers":[
        {
            "category":"Restaurant",
            "type":"Food & Drink"
        }
    ],
    "sg:menulink":"http://www.allmenus.com/va/newport-news/284273-fin-seafood/menu/",
    "sg:phone":"+1 757 599 5800",
    "sg:postcode":"23606",
    "sg:province":"VA",
    "sg:tags":[
        "seafood",
        "steakhouse",
        "american"
    ],
    "wof:name":"Fin Seafood",
    "wof:placetype":"venue"
},
  "geometry": {"coordinates":[-76.487208,37.084548],"type":"Point"}
}