{
  "type": "Feature",
  "properties": {
    "addr:full":"532 14th St West Point VA 23181",
    "addr:housenumber":"532",
    "addr:postcode":"23181",
    "addr:street":"14Th St",
    "iso:country":"US",
    "sg:address":"532 14th St",
    "sg:city":"West Point",
    "sg:classifiers":[
        {
            "category":"Restaurant",
            "type":"Food & Drink"
        }
    ],
    "sg:menulink":"http://www.allmenus.com/va/west-point/188083-mcdonalds/menu/",
    "sg:phone":"+1 804 843 4139",
    "sg:postcode":"23181",
    "sg:province":"VA",
    "sg:tags":[
        "burger",
        "american"
    ],
    "wof:name":"McDonald's",
    "wof:placetype":"venue"
},
  "geometry": {"coordinates":[-76.79734000000001,37.537521],"type":"Point"}
}