{
  "type": "Feature",
  "properties": {
    "addr:full":"1401 Jefferson Davis Hwy Fredericksburg VA 22401",
    "addr:housenumber":"1401",
    "addr:postcode":"22401",
    "addr:street":"Jefferson Davis Hwy",
    "iso:country":"US",
    "sg:address":"1401 Jefferson Davis Hwy",
    "sg:city":"Fredericksburg",
    "sg:classifiers":[
        {
            "category":"Manufacturing",
            "subcategory":"Metals",
            "type":"Manufacturing & Wholesale Goods"
        },
        {
            "category":"Autos & Motor Vehicles",
            "subcategory":"Recreational Vehicle Sales",
            "type":"Retail Goods"
        }
    ],
    "sg:phone":"+1 540 373 1890",
    "sg:postcode":"22401",
    "sg:province":"VA",
    "sg:tags":[
        "building",
        "shell",
        "mfg",
        "cap",
        "prefabricated",
        "truck",
        "canopy"
    ],
    "wof:name":"Leonard Buildings Truck Acces",
    "wof:placetype":"venue"
},
  "geometry": {"coordinates":[-77.48259299999999,38.299264],"type":"Point"}
}