{
  "type": "Feature",
  "properties": {
    "iso:country":"US",
    "sg:address":"2025 Birch Ave",
    "sg:city":"Buena Vista",
    "sg:classifiers":[
        {
            "category":"Building & Trades",
            "subcategory":"Construction",
            "type":"Services"
        }
    ],
    "sg:phone":"+1 540 264 0171",
    "sg:postcode":"24416",
    "sg:province":"VA",
    "sg:tags":[
        "hanging",
        "contractor"
    ],
    "wof:name":"Triple S Painting",
    "wof:placetype":"venue"
},
  "geometry": {"coordinates":[-79.34903,37.732725],"type":"Point"}
}