{
  "type": "Feature",
  "properties": {
    "addr:full":"107 5th St SE Charlottesville VA 22902",
    "addr:housenumber":"107",
    "addr:postcode":"22902",
    "addr:street":"5Th St Se",
    "iso:country":"US",
    "sg:address":"107 5th St SE",
    "sg:city":"Charlottesville",
    "sg:classifiers":[
        {
            "category":"Banks & Credit Unions",
            "subcategory":"Bank",
            "type":"Services"
        }
    ],
    "sg:phone":"+1 434 872 0074",
    "sg:postcode":"22902",
    "sg:province":"VA",
    "wof:name":"Virginia Community Bank",
    "wof:placetype":"venue"
},
  "geometry": {"coordinates":[-78.47866,38.029865],"type":"Point"}
}