{
  "type": "Feature",
  "properties": {
    "iso:country":"US",
    "sg:address":"1553 Delphi Dr",
    "sg:city":"Charlottesville",
    "sg:classifiers":[
        {
            "category":"Social Services",
            "subcategory":"Child Care",
            "type":"Services"
        }
    ],
    "sg:phone":"+1 434 979 5223",
    "sg:postcode":"22911",
    "sg:province":"VA",
    "sg:tags":[
        "elementary",
        "school",
        "day"
    ],
    "sg:website":"www.frostmontessori.com",
    "wof:name":"Frost Montessori School the",
    "wof:placetype":"venue"
},
  "geometry": {"coordinates":[-78.446899,38.0387],"type":"Point"}
}