{
  "type": "Feature",
  "properties": {
    "iso:country":"US",
    "sg:address":"815 General Pickett Dr",
    "sg:city":"Suffolk",
    "sg:classifiers":[
        {
            "category":"Professional",
            "subcategory":"Accounting & Tax Preparation",
            "type":"Services"
        }
    ],
    "sg:phone":"+1 757 934 3585",
    "sg:postcode":"23434",
    "sg:province":"VA",
    "wof:name":"Charles S Lowder CPA",
    "wof:placetype":"venue"
},
  "geometry": {"coordinates":[-76.60799900000001,36.74171],"type":"Point"}
}