{
  "type": "Feature",
  "properties": {
    "addr:full":"219 Turner Rd Richmond VA 23225",
    "addr:housenumber":"219",
    "addr:postcode":"23225",
    "addr:street":"Turner Rd",
    "iso:country":"US",
    "sg:address":"219 Turner Rd",
    "sg:city":"Richmond",
    "sg:classifiers":[
        {
            "category":"Building & Trades",
            "subcategory":"Construction",
            "type":"Services"
        }
    ],
    "sg:phone":"+1 804 745 0000",
    "sg:postcode":"23225",
    "sg:province":"VA",
    "sg:tags":[
        "general",
        "contractor"
    ],
    "wof:name":"Prestige Cnstr Group Inc",
    "wof:placetype":"venue"
},
  "geometry": {"coordinates":[-77.53639099999999,37.496922],"type":"Point"}
}