{
  "type": "Feature",
  "properties": {
    "addr:full":"11393 Nuckols Rd Glen Allen VA 23059",
    "addr:housenumber":"11393",
    "addr:postcode":"23059",
    "addr:street":"Nuckols Rd",
    "iso:country":"US",
    "sg:address":"11393 Nuckols Rd",
    "sg:city":"Glen Allen",
    "sg:classifiers":[
        {
            "category":"Education",
            "subcategory":"School",
            "type":"Public Place"
        }
    ],
    "sg:phone":"+1 804 270 0901",
    "sg:postcode":"23059",
    "sg:province":"VA",
    "sg:website":"www.goddardschools.com",
    "wof:name":"Goddard School",
    "wof:placetype":"venue"
},
  "geometry": {"coordinates":[-77.58942500000001,37.68383],"type":"Point"}
}