{
  "type": "Feature",
  "properties": {
    "addr:full":"2760 Fariss Rd Powhatan VA 23139",
    "addr:housenumber":"2760",
    "addr:postcode":"23139",
    "addr:street":"Fariss Rd",
    "iso:country":"US",
    "sg:address":"2760 Fariss Rd",
    "sg:city":"Powhatan",
    "sg:classifiers":[
        {
            "category":"Building & Trades",
            "subcategory":"Landscaping Services",
            "type":"Services"
        }
    ],
    "sg:phone":"+1 804 598 6110",
    "sg:postcode":"23139",
    "sg:province":"VA",
    "wof:name":"Coley Bros Enterprise",
    "wof:placetype":"venue"
},
  "geometry": {"coordinates":[-77.942798,37.57232],"type":"Point"}
}