{
  "type": "Feature",
  "properties": {
    "iso:country":"US",
    "sg:address":"311 N Henry St",
    "sg:city":"Alexandria",
    "sg:classifiers":[
        {
            "category":"Retail",
            "subcategory":"Auto Repair",
            "type":"Services"
        }
    ],
    "sg:phone":"+1 703 548 0875",
    "sg:postcode":"22314",
    "sg:province":"VA",
    "sg:tags":[
        "general"
    ],
    "wof:name":"Prime Auto Care Inc",
    "wof:placetype":"venue"
},
  "geometry": {"coordinates":[-77.050747,38.808148],"type":"Point"}
}