{
  "type": "Feature",
  "properties": {
    "iso:country":"US",
    "sg:address":"1001 Cadmus Dr",
    "sg:city":"Fredericksburg",
    "sg:classifiers":[
        {
            "category":"Organizations",
            "subcategory":"Religious Organization",
            "type":"Services"
        }
    ],
    "sg:phone":"+1 540 374 1295",
    "sg:postcode":"22401",
    "sg:province":"VA",
    "wof:name":"J E Bailey Ministries Inc",
    "wof:placetype":"venue"
},
  "geometry": {"coordinates":[-77.48899,38.31087],"type":"Point"}
}