{
  "type": "Feature",
  "properties": {
    "addr:full":"4122 Terry Dr Chesapeake VA 23321",
    "addr:housenumber":"4122",
    "addr:postcode":"23321",
    "addr:street":"Terry Dr",
    "iso:country":"US",
    "sg:address":"4122 Terry Dr",
    "sg:city":"Chesapeake",
    "sg:classifiers":[
        {
            "category":"Education",
            "subcategory":"School",
            "type":"Public Place"
        }
    ],
    "sg:phone":"+1 757 638 7951",
    "sg:postcode":"23321",
    "sg:province":"VA",
    "wof:name":"Western Branch Primary School",
    "wof:placetype":"venue"
},
  "geometry": {"coordinates":[-76.401878,36.845341],"type":"Point"}
}