{
  "type": "Feature",
  "properties": {
    "addr:full":"2448 Virginia Beach Blvd Virginia Beach VA 23454",
    "addr:housenumber":"2448",
    "addr:postcode":"23454",
    "addr:street":"Virginia Beach Blvd",
    "iso:country":"US",
    "sg:address":"2448 Virginia Beach Blvd",
    "sg:city":"Virginia Beach",
    "sg:classifiers":[
        {
            "category":"Bagels",
            "type":"Food & Drink"
        },
        {
            "category":"Coffee & Tea",
            "type":"Food & Drink"
        },
        {
            "category":"Restaurant",
            "type":"Food & Drink"
        },
        {
            "category":"Bakery",
            "type":"Food & Drink"
        },
        {
            "category":"Donuts",
            "type":"Food & Drink"
        }
    ],
    "sg:menulink":"http://www.allmenus.com/va/virginia-beach/139003-dunkin-donuts/menu/",
    "sg:phone":"+1 757 486 1237",
    "sg:postcode":"23454",
    "sg:province":"VA",
    "sg:tags":[
        "coffee",
        "tea",
        "american",
        "bagel",
        "bakery",
        "pastry"
    ],
    "wof:name":"Dunkin' Donuts",
    "wof:placetype":"venue"
},
  "geometry": {"coordinates":[-76.054903,36.842004],"type":"Point"}
}