{
  "type": "Feature",
  "properties": {
    "addr:full":"3737 Seminary Rd Alexandria VA 22304",
    "addr:housenumber":"3737",
    "addr:postcode":"22304",
    "addr:street":"Seminary Rd",
    "iso:country":"US",
    "sg:address":"3737 Seminary Rd",
    "sg:city":"Alexandria",
    "sg:classifiers":[
        {
            "category":"Shopping",
            "type":"Retail Goods"
        }
    ],
    "sg:phone":"+1 703 370 6161",
    "sg:postcode":"22304",
    "sg:province":"VA",
    "sg:tags":[
        "religious"
    ],
    "wof:name":"Cokesbury Books & Church Supls",
    "wof:placetype":"venue"
},
  "geometry": {"coordinates":[-77.097849,38.821985],"type":"Point"}
}