{
  "type": "Feature",
  "properties": {
    "iso:country":"US",
    "sg:address":"7810 Belleflower Dr",
    "sg:city":"Springfield",
    "sg:classifiers":[
        {
            "category":"Building & Trades",
            "subcategory":"Construction",
            "type":"Services"
        }
    ],
    "sg:phone":"+1 703 569 7940",
    "sg:postcode":"22152",
    "sg:province":"VA",
    "sg:tags":[
        "contractor"
    ],
    "wof:name":"Long Homes Of Virginia Inc",
    "wof:placetype":"venue"
},
  "geometry": {"coordinates":[-77.211732,38.767861],"type":"Point"}
}