{
  "type": "Feature",
  "properties": {
    "iso:country":"US",
    "sg:address":"21150 Clear Creek Rd",
    "sg:city":"Bristol",
    "sg:classifiers":[
        {
            "category":"Retail",
            "subcategory":"Auto Repair",
            "type":"Services"
        }
    ],
    "sg:phone":"+1 276 669 0077",
    "sg:postcode":"24202",
    "sg:province":"VA",
    "sg:tags":[
        "body",
        "automobile",
        "painting"
    ],
    "wof:name":"Surratt's Auto Body",
    "wof:placetype":"venue"
},
  "geometry": {"coordinates":[-82.126857,36.644399],"type":"Point"}
}