{
  "type": "Feature",
  "properties": {
    "iso:country":"US",
    "sg:address":"26G Fairfax St SE",
    "sg:city":"Leesburg",
    "sg:classifiers":[
        {
            "category":"Insurance",
            "subcategory":"Insurance Agent",
            "type":"Services"
        }
    ],
    "sg:phone":"+1 703 777 4415",
    "sg:postcode":"20175",
    "sg:province":"VA",
    "sg:tags":[
        "auto"
    ],
    "sg:website":"http://www.erieinsurance.com/?utm_source=yp&utm_medium=cpc&utm_campaign=ck_yp",
    "wof:name":"RICH INSURANCE AGENCY, INC.",
    "wof:placetype":"venue"
},
  "geometry": {"coordinates":[-77.565331,39.108002],"type":"Point"}
}