{
  "type": "Feature",
  "properties": {
    "addr:full":"780 Commonwealth Ave Norton VA 24201",
    "addr:housenumber":"780",
    "addr:postcode":"24201",
    "addr:street":"Commonwealth Ave",
    "iso:country":"US",
    "sg:address":"780 Commonwealth Ave",
    "sg:city":"Norton",
    "sg:classifiers":[
        {
            "category":"Shopping",
            "subcategory":"Department Store",
            "type":"Retail Goods"
        }
    ],
    "sg:phone":"+1 276 679 1610",
    "sg:postcode":"24201",
    "sg:province":"VA",
    "wof:name":"Wal-Mart Supercenter",
    "wof:placetype":"venue"
},
  "geometry": {"coordinates":[-82.193018,36.605861],"type":"Point"}
}