{
  "type": "Feature",
  "properties": {
    "iso:country":"US",
    "sg:address":"353 Church St NE",
    "sg:city":"Vienna",
    "sg:classifiers":[
        {
            "category":"Professional",
            "subcategory":"Management & Consulting",
            "type":"Services"
        }
    ],
    "sg:phone":"+1 703 938 6712",
    "sg:postcode":"22180",
    "sg:province":"VA",
    "sg:tags":[
        "marketing",
        "consultant"
    ],
    "wof:name":"Tech Marketing",
    "wof:placetype":"venue"
},
  "geometry": {"coordinates":[-77.260947,38.907027],"type":"Point"}
}