{
  "type": "Feature",
  "properties": {
    "iso:country":"US",
    "sg:address":"3682 King St",
    "sg:city":"Alexandria",
    "sg:classifiers":[
        {
            "category":"Government",
            "subcategory":"Post Office",
            "type":"Public Place"
        }
    ],
    "sg:postcode":"22302",
    "sg:province":"VA",
    "sg:website":"www.usps.com/",
    "wof:name":"US Post Office",
    "wof:placetype":"venue"
},
  "geometry": {"coordinates":[-77.09132099999999,38.829809],"type":"Point"}
}