{
  "type": "Feature",
  "properties": {
    "addr:full":"187 Church St Poquoson VA 23662",
    "addr:housenumber":"187",
    "addr:postcode":"23662",
    "addr:street":"Church St",
    "iso:country":"US",
    "sg:address":"187 Church St",
    "sg:city":"Poquoson",
    "sg:classifiers":[
        {
            "category":"Building & Trades",
            "subcategory":"Construction",
            "type":"Services"
        }
    ],
    "sg:phone":"+1 757 868 4810",
    "sg:postcode":"23662",
    "sg:province":"VA",
    "sg:tags":[
        "carpentry",
        "contractor"
    ],
    "wof:name":"Wiggins Enterprises Ltd",
    "wof:placetype":"venue"
},
  "geometry": {"coordinates":[-76.35413800000001,37.121595],"type":"Point"}
}