{
  "type": "Feature",
  "properties": {
    "addr:full":"7928 Harold St Norfolk VA 23518",
    "addr:housenumber":"7928",
    "addr:postcode":"23518",
    "addr:street":"Harold St",
    "iso:country":"US",
    "sg:address":"7928 Harold St",
    "sg:city":"Norfolk",
    "sg:classifiers":[
        {
            "category":"Insurance",
            "subcategory":"Insurance Agent",
            "type":"Services"
        }
    ],
    "sg:phone":"+1 757 587 3416",
    "sg:postcode":"23518",
    "sg:province":"VA",
    "wof:name":"Jock B Hughes Insurance",
    "wof:placetype":"venue"
},
  "geometry": {"coordinates":[-76.252033,36.917105],"type":"Point"}
}