{
  "type": "Feature",
  "properties": {
    "iso:country":"US",
    "sg:address":"2510 Soapstone Dr",
    "sg:city":"Reston",
    "sg:classifiers":[
        {
            "category":"Professional",
            "type":"Services"
        }
    ],
    "sg:phone":"+1 703 620 0745",
    "sg:postcode":"20191",
    "sg:province":"VA",
    "sg:tags":[
        "consultant",
        "geological"
    ],
    "wof:name":"GEO Environmental Inc",
    "wof:placetype":"venue"
},
  "geometry": {"coordinates":[-77.348203,38.916647],"type":"Point"}
}