{
  "type": "Feature",
  "properties": {
    "iso:country":"US",
    "sg:address":"487 Canthook Hill Rd",
    "sg:city":"Bristol",
    "sg:classifiers":[
        {
            "category":"Organizations",
            "subcategory":"Religious Organization",
            "type":"Services"
        }
    ],
    "sg:phone":"+1 423 878 6770",
    "sg:postcode":"37620",
    "sg:province":"VA",
    "sg:tags":[
        "church"
    ],
    "wof:name":"Full Gospel Tabernacle",
    "wof:placetype":"venue"
},
  "geometry": {"coordinates":[-82.175845,36.530818],"type":"Point"}
}