{
  "type": "Feature",
  "properties": {
    "addr:full":"415 N 1st St Richmond VA 23219",
    "addr:housenumber":"415",
    "addr:postcode":"23219",
    "addr:street":"N 1St St",
    "iso:country":"US",
    "sg:address":"415 N 1st St",
    "sg:city":"Richmond",
    "sg:classifiers":[
        {
            "category":"Restaurant",
            "type":"Food & Drink"
        }
    ],
    "sg:phone":"+1 804 643 5337",
    "sg:postcode":"23219",
    "sg:province":"VA",
    "sg:tags":[
        "eating"
    ],
    "wof:name":"Anns Soul Food Restaurant",
    "wof:placetype":"venue"
},
  "geometry": {"coordinates":[-77.439452,37.546653],"type":"Point"}
}