{
  "type": "Feature",
  "properties": {
    "iso:country":"US",
    "sg:address":"3498 Leffel Rd",
    "sg:city":"Roanoke",
    "sg:classifiers":[
        {
            "category":"Retail",
            "subcategory":"Animal Services",
            "type":"Services"
        }
    ],
    "sg:phone":"+1 540 989 6956",
    "sg:postcode":"24018",
    "sg:province":"VA",
    "sg:tags":[
        "pet",
        "grooming",
        "washing"
    ],
    "wof:name":"Yuppie Puppie",
    "wof:placetype":"venue"
},
  "geometry": {"coordinates":[-79.956954,37.203309],"type":"Point"}
}