{
  "type": "Feature",
  "properties": {
    "addr:full":"3309 Magnolia Ave Falls Church VA 22041",
    "addr:housenumber":"3309",
    "addr:postcode":"22041",
    "addr:street":"Magnolia Ave",
    "iso:country":"US",
    "sg:address":"3309 Magnolia Ave",
    "sg:city":"Falls Church",
    "sg:classifiers":[
        {
            "category":"Organizations",
            "subcategory":"Religious Organization",
            "type":"Services"
        }
    ],
    "sg:phone":"+1 703 931 2262",
    "sg:postcode":"22041",
    "sg:province":"VA",
    "wof:name":"Goddess of Heaven Temple Inc",
    "wof:placetype":"venue"
},
  "geometry": {"coordinates":[-77.137731,38.855163],"type":"Point"}
}