{
  "type": "Feature",
  "properties": {
    "addr:full":"911 Taylor St Lynchburg VA 24504",
    "addr:housenumber":"911",
    "addr:postcode":"24504",
    "addr:street":"Taylor St",
    "iso:country":"US",
    "sg:address":"911 Taylor St",
    "sg:city":"Lynchburg",
    "sg:classifiers":[
        {
            "category":"Organizations",
            "subcategory":"Religious Organization",
            "type":"Services"
        }
    ],
    "sg:phone":"+1 434 845 3623",
    "sg:postcode":"24504",
    "sg:province":"VA",
    "wof:name":"Smyrna Seventh Day Adventist",
    "wof:placetype":"venue"
},
  "geometry": {"coordinates":[-79.150818,37.408955],"type":"Point"}
}