{
  "type": "Feature",
  "properties": {
    "addr:full":"9400 Coleson Rd Glen Allen VA 23060",
    "addr:postcode":"9400;23060",
    "addr:street":"Coleson Rd",
    "iso:country":"US",
    "sg:address":"9400 Coleson Rd",
    "sg:city":"Glen Allen",
    "sg:classifiers":[
        {
            "category":"Shopping",
            "subcategory":"Clothing, Apparel, & Fashions",
            "type":"Retail Goods"
        }
    ],
    "sg:phone":"+1 804 270 1485",
    "sg:postcode":"23060",
    "sg:province":"VA",
    "sg:tags":[
        "dress",
        "crochet"
    ],
    "wof:name":"Just Beautiful Hand Crochet",
    "wof:placetype":"venue"
},
  "geometry": {"coordinates":[-77.55658099999999,37.652069],"type":"Point"}
}