{
  "type": "Feature",
  "properties": {
    "iso:country":"US",
    "sg:address":"2201 Pacific Ave",
    "sg:city":"Virginia Beach",
    "sg:classifiers":[
        {
            "category":"Restaurant",
            "type":"Food & Drink"
        }
    ],
    "sg:menulink":"http://www.allmenus.com/va/virginia-beach/192052-wendys/menu/",
    "sg:phone":"+1 757 425 5524",
    "sg:postcode":"23451",
    "sg:province":"VA",
    "sg:tags":[
        "burger",
        "american",
        "soup"
    ],
    "wof:name":"Wendy's",
    "wof:placetype":"venue"
},
  "geometry": {"coordinates":[-75.976651,36.850346],"type":"Point"}
}