{
  "type": "Feature",
  "properties": {
    "addr:full":"1611 N Kent St Ste 803 Arlington VA 22209",
    "addr:housenumber":"1611",
    "addr:postcode":"22209",
    "addr:street":"N Kent St Ste 803",
    "iso:country":"US",
    "sg:address":"1611 N Kent St Ste 803",
    "sg:city":"Arlington",
    "sg:classifiers":[
        {
            "category":"Wholesale",
            "subcategory":"Computers",
            "type":"Manufacturing & Wholesale Goods"
        },
        {
            "category":"Professional",
            "subcategory":"Computer Services",
            "type":"Services"
        }
    ],
    "sg:phone":"+1 703 778 4445",
    "sg:postcode":"22209",
    "sg:province":"VA",
    "sg:tags":[
        "software",
        "publisher",
        "cd-rom",
        "developer",
        "equipment"
    ],
    "sg:website":"http://www.buysafe.net",
    "wof:name":"Buysafe, Inc.",
    "wof:placetype":"venue"
},
  "geometry": {"coordinates":[-77.069349,38.89478],"type":"Point"}
}