{
  "type": "Feature",
  "properties": {
    "iso:country":"US",
    "sg:address":"807 Florida Ave",
    "sg:city":"Portsmouth",
    "sg:classifiers":[
        {
            "category":"Wholesale",
            "subcategory":"Hardware",
            "type":"Manufacturing & Wholesale Goods"
        }
    ],
    "sg:phone":"+1 757 398 0400",
    "sg:postcode":"23707",
    "sg:province":"VA",
    "sg:tags":[
        "dust",
        "control",
        "material"
    ],
    "wof:name":"Envir O Corp",
    "wof:placetype":"venue"
},
  "geometry": {"coordinates":[-76.337215,36.840454],"type":"Point"}
}