{
  "type": "Feature",
  "properties": {
    "iso:country":"US",
    "sg:address":"12354 Dillingham Sq",
    "sg:city":"Woodbridge",
    "sg:classifiers":[
        {
            "category":"Organizations",
            "subcategory":"Religious Organization",
            "type":"Services"
        }
    ],
    "sg:phone":"+1 703 897 7373",
    "sg:postcode":"22192",
    "sg:province":"VA",
    "sg:tags":[
        "academy",
        "school",
        "center",
        "daycare"
    ],
    "wof:name":"Precious Lambs Learning Center",
    "wof:placetype":"venue"
},
  "geometry": {"coordinates":[-77.318026,38.684855],"type":"Point"}
}