{
  "type": "Feature",
  "properties": {
    "iso:country":"US",
    "sg:address":"205 Academy Dr NW",
    "sg:city":"Abingdon",
    "sg:classifiers":[
        {
            "category":"Recreation",
            "type":"Entertainment"
        }
    ],
    "sg:phone":"+1 276 676 6212",
    "sg:postcode":"24210",
    "sg:province":"VA",
    "sg:tags":[
        "parks"
    ],
    "wof:name":"Washington Recreation Dept",
    "wof:placetype":"venue"
},
  "geometry": {"coordinates":[-81.987285,36.708853],"type":"Point"}
}