{
  "type": "Feature",
  "properties": {
    "iso:country":"US",
    "sg:address":"3258 Riverside Dr",
    "sg:city":"Danville",
    "sg:classifiers":[
        {
            "category":"Government",
            "subcategory":"Office",
            "type":"Public Place"
        }
    ],
    "sg:phone":"+1 434 799 8762",
    "sg:postcode":"24541",
    "sg:province":"VA",
    "sg:tags":[
        "recruiting"
    ],
    "wof:name":"US Marine Corps Recruiting",
    "wof:placetype":"venue"
},
  "geometry": {"coordinates":[-79.42579000000001,36.58513],"type":"Point"}
}