{
  "type": "Feature",
  "properties": {
    "iso:country":"US",
    "sg:address":"3509 Nelson St",
    "sg:city":"Portsmouth",
    "sg:classifiers":[
        {
            "category":"Professional",
            "type":"Services"
        }
    ],
    "sg:phone":"+1 757 399 3407",
    "sg:postcode":"23707",
    "sg:province":"VA",
    "wof:name":"Branestorm",
    "wof:placetype":"venue"
},
  "geometry": {"coordinates":[-76.345669,36.823705],"type":"Point"}
}