{
  "type": "Feature",
  "properties": {
    "addr:full":"202 High St Farmville VA 23901",
    "addr:housenumber":"202",
    "addr:postcode":"23901",
    "addr:street":"High St",
    "iso:country":"US",
    "sg:address":"202 High St",
    "sg:city":"Farmville",
    "sg:classifiers":[
        {
            "category":"Restaurant",
            "type":"Food & Drink"
        }
    ],
    "sg:phone":"+1 434 315 8787",
    "sg:postcode":"23901",
    "sg:province":"VA",
    "sg:tags":[
        "eating"
    ],
    "sg:website":"www.restaurant.com",
    "wof:name":"Mulligan's Sports Grille",
    "wof:placetype":"venue"
},
  "geometry": {"coordinates":[-78.395442,37.301711],"type":"Point"}
}