{
  "type": "Feature",
  "properties": {
    "addr:full":"1145 Ohio St Waynesboro VA 22980",
    "addr:housenumber":"1145",
    "addr:postcode":"22980",
    "addr:street":"Ohio St",
    "iso:country":"US",
    "sg:address":"1145 Ohio St",
    "sg:city":"Waynesboro",
    "sg:classifiers":[
        {
            "category":"Personal",
            "subcategory":"Beauty Salon",
            "type":"Services"
        }
    ],
    "sg:phone":"+1 540 943 9839",
    "sg:postcode":"22980",
    "sg:province":"VA",
    "sg:tags":[
        "shop"
    ],
    "wof:name":"Debbie's Hair Design",
    "wof:placetype":"venue"
},
  "geometry": {"coordinates":[-78.89551299999999,38.073261],"type":"Point"}
}