{
  "type": "Feature",
  "properties": {
    "addr:full":"1921 Gallows Rd Vienna VA 22182",
    "addr:housenumber":"1921",
    "addr:postcode":"22182",
    "addr:street":"Gallows Rd",
    "iso:country":"US",
    "sg:address":"1921 Gallows Rd",
    "sg:city":"Vienna",
    "sg:classifiers":[
        {
            "category":"Wholesale",
            "subcategory":"Electrical",
            "type":"Manufacturing & Wholesale Goods"
        }
    ],
    "sg:phone":"+1 703 749 5080",
    "sg:postcode":"22182",
    "sg:province":"VA",
    "sg:tags":[
        "electronic"
    ],
    "wof:name":"Rockwell Automation Inc",
    "wof:placetype":"venue"
},
  "geometry": {"coordinates":[-77.22778599999999,38.913867],"type":"Point"}
}