{
  "type": "Feature",
  "properties": {
    "iso:country":"US",
    "sg:address":"105 Windsor Way",
    "sg:city":"Richmond",
    "sg:classifiers":[
        {
            "category":"Health Services",
            "subcategory":"Doctor",
            "type":"Services"
        }
    ],
    "sg:phone":"+1 804 359 3925",
    "sg:postcode":"23221",
    "sg:province":"VA",
    "sg:tags":[
        "medical"
    ],
    "wof:name":"Kelly A Fogle Dr",
    "wof:placetype":"venue"
},
  "geometry": {"coordinates":[-77.499371,37.557322],"type":"Point"}
}