{
  "type": "Feature",
  "properties": {
    "addr:full":"203 Legrande Ave Charlotte Ct Hse VA 23923",
    "addr:housenumber":"203",
    "addr:postcode":"23923",
    "addr:street":"Legrande Ave Charlotte Ct",
    "iso:country":"US",
    "sg:address":"203 Legrande Ave",
    "sg:city":"Charlotte Ct Hse",
    "sg:classifiers":[
        {
            "category":"Professional",
            "subcategory":"Computer Services",
            "type":"Services"
        }
    ],
    "sg:phone":"+1 434 542 9453",
    "sg:postcode":"23923",
    "sg:province":"VA",
    "sg:tags":[
        "internet"
    ],
    "sg:website":"www.linkabit.com",
    "wof:name":"LINKABIT.COM",
    "wof:placetype":"venue"
},
  "geometry": {"coordinates":[-78.636915,37.0543],"type":"Point"}
}