{
  "type": "Feature",
  "properties": {
    "addr:full":"440 Mount Pleasant Rd Chesapeake VA 23322",
    "addr:housenumber":"440",
    "addr:postcode":"23322",
    "addr:street":"Mount Pleasant Rd",
    "iso:country":"US",
    "sg:address":"440 Mount Pleasant Rd",
    "sg:city":"Chesapeake",
    "sg:classifiers":[
        {
            "category":"Professional",
            "type":"Services"
        }
    ],
    "sg:phone":"+1 757 724 6995",
    "sg:postcode":"23322",
    "sg:province":"VA",
    "wof:name":"Brush & Hammer",
    "wof:placetype":"venue"
},
  "geometry": {"coordinates":[-76.223343,36.707209],"type":"Point"}
}