{
  "type": "Feature",
  "properties": {
    "addr:full":"915 16th St S Arlington VA 22202",
    "addr:housenumber":"915",
    "addr:postcode":"22202",
    "addr:street":"16Th St S",
    "iso:country":"US",
    "sg:address":"915 16th St S",
    "sg:city":"Arlington",
    "sg:classifiers":[
        {
            "category":"Recreation",
            "subcategory":"Picnic Area",
            "type":"Entertainment"
        },
        {
            "category":"Community Center",
            "type":"Public Place"
        }
    ],
    "sg:phone":"+1 703 864 9160",
    "sg:postcode":"22202",
    "sg:province":"VA",
    "sg:tags":[
        "amusement",
        "arcade"
    ],
    "wof:name":"Science And Math",
    "wof:placetype":"venue"
},
  "geometry": {"coordinates":[-77.06175,38.858549],"type":"Point"}
}