{
  "type": "Feature",
  "properties": {
    "addr:full":"7301 Beverly Manor Dr Annandale VA 22003",
    "addr:housenumber":"7301",
    "addr:postcode":"22003",
    "addr:street":"Beverly Manor Dr",
    "iso:country":"US",
    "sg:address":"7301 Beverly Manor Dr",
    "sg:city":"Annandale",
    "sg:classifiers":[
        {
            "category":"Home & Garden",
            "subcategory":"Building Materials",
            "type":"Retail Goods"
        },
        {
            "category":"Building & Trades",
            "subcategory":"Construction",
            "type":"Services"
        }
    ],
    "sg:phone":"+1 703 256 9180",
    "sg:postcode":"22003",
    "sg:province":"VA",
    "sg:tags":[
        "windows-repair",
        "window",
        "installation",
        "replacement"
    ],
    "wof:name":"Kirby Quality Window Products Inc",
    "wof:placetype":"venue"
},
  "geometry": {"coordinates":[-77.195435,38.837869],"type":"Point"}
}