{
  "type": "Feature",
  "properties": {
    "addr:full":"12745 Jefferson Ave Newport News VA 23602",
    "addr:housenumber":"12745",
    "addr:postcode":"23602",
    "addr:street":"Jefferson Ave",
    "iso:country":"US",
    "sg:address":"12745 Jefferson Ave",
    "sg:city":"Newport News",
    "sg:classifiers":[
        {
            "category":"Home & Garden",
            "subcategory":"Furniture",
            "type":"Retail Goods"
        }
    ],
    "sg:phone":"+1 757 233 8909",
    "sg:postcode":"23602",
    "sg:province":"VA",
    "wof:name":"Grand Furniture Disc Stores",
    "wof:placetype":"venue"
},
  "geometry": {"coordinates":[-76.512503,37.128619],"type":"Point"}
}