{
  "type": "Feature",
  "properties": {
    "addr:full":"4800 Leesburg Pike Alexandria VA 22302",
    "addr:housenumber":"4800",
    "addr:postcode":"22302",
    "addr:street":"Leesburg Pike",
    "iso:country":"US",
    "sg:address":"4800 Leesburg Pike",
    "sg:city":"Alexandria",
    "sg:classifiers":[
        {
            "category":"Travel",
            "subcategory":"Hotels & Motels",
            "type":"Entertainment"
        }
    ],
    "sg:phone":"+1 703 671 4800",
    "sg:postcode":"22302",
    "sg:province":"VA",
    "sg:tags":[
        "operation"
    ],
    "sg:website":"www.hamptoninn.com/en/hp/hotels/...",
    "wof:name":"Hampton Inn",
    "wof:placetype":"venue"
},
  "geometry": {"coordinates":[-77.11340300000001,38.844501],"type":"Point"}
}