{
  "type": "Feature",
  "properties": {
    "addr:full":"21300 Warrior Dr Petersburg VA 23803",
    "addr:housenumber":"21300",
    "addr:postcode":"23803",
    "addr:street":"Warrior Dr",
    "iso:country":"US",
    "sg:address":"21300 Warrior Dr",
    "sg:city":"Petersburg",
    "sg:classifiers":[
        {
            "category":"Building & Trades",
            "subcategory":"Cleaning & Sanitation",
            "type":"Services"
        }
    ],
    "sg:phone":"+1 804 590 2031",
    "sg:postcode":"23803",
    "sg:province":"VA",
    "sg:tags":[
        "maintenance"
    ],
    "wof:name":"Deluxe Janitorial Care Corp",
    "wof:placetype":"venue"
},
  "geometry": {"coordinates":[-77.470893,37.234949],"type":"Point"}
}