{
  "type": "Feature",
  "properties": {
    "iso:country":"US",
    "sg:address":"4807 Colley Ave",
    "sg:city":"Norfolk",
    "sg:classifiers":[
        {
            "category":"Wholesale",
            "subcategory":"Stationery",
            "type":"Manufacturing & Wholesale Goods"
        }
    ],
    "sg:phone":"+1 757 440 1147",
    "sg:postcode":"23508",
    "sg:province":"VA",
    "sg:tags":[
        "paper"
    ],
    "wof:name":"Aufenger Box",
    "wof:placetype":"venue"
},
  "geometry": {"coordinates":[-76.295151,36.887888],"type":"Point"}
}