{
  "type": "Feature",
  "properties": {
    "addr:full":"770 Harris Street  Suite 104B Charlottesville VA 22903 ",
    "addr:housenumber":"770",
    "addr:postcode":"22903",
    "addr:street":"Harris Street Suite 104B",
    "iso:country":"US",
    "sg:address":"770 Harris Street  Suite 104B",
    "sg:city":"Charlottesville",
    "sg:classifiers":[
        {
            "category":"Professional",
            "subcategory":"Research",
            "type":"Services"
        }
    ],
    "sg:phone":"+1 434 872 0700",
    "sg:postcode":"22903 ",
    "sg:province":"VA",
    "sg:website":"http://www.wellawaresystems.com/",
    "wof:name":"WellAWARE Systems",
    "wof:placetype":"venue"
},
  "geometry": {"coordinates":[-78.483859,38.036593],"type":"Point"}
}