{
  "type": "Feature",
  "properties": {
    "iso:country":"US",
    "sg:address":"1235 Jefferson Davis Hwy",
    "sg:city":"Arlington",
    "sg:classifiers":[
        {
            "category":"Food & Beverages",
            "subcategory":"Groceries & Convenience Stores",
            "type":"Retail Goods"
        }
    ],
    "sg:phone":"+1 703 412 1500",
    "sg:postcode":"22202",
    "sg:province":"VA",
    "wof:name":"Gate Ways Suntries",
    "wof:placetype":"venue"
},
  "geometry": {"coordinates":[-77.0504,38.864601],"type":"Point"}
}