{
  "type": "Feature",
  "properties": {
    "addr:full":"12491 Hayes Ct Fairfax VA 22033",
    "addr:housenumber":"12491",
    "addr:postcode":"22033",
    "addr:street":"Hayes Ct",
    "iso:country":"US",
    "sg:address":"12491 Hayes Ct",
    "sg:city":"Fairfax",
    "sg:classifiers":[
        {
            "category":"Professional",
            "subcategory":"Management & Consulting",
            "type":"Services"
        }
    ],
    "sg:phone":"+1 703 246 9388",
    "sg:postcode":"22033",
    "sg:province":"VA",
    "sg:tags":[
        "business"
    ],
    "wof:name":"Carolyn Childs",
    "wof:placetype":"venue"
},
  "geometry": {"coordinates":[-77.379392,38.864443],"type":"Point"}
}