{
  "type": "Feature",
  "properties": {
    "addr:full":"502 E Main St Louisa VA 23093",
    "addr:housenumber":"502",
    "addr:postcode":"23093",
    "addr:street":"E Main St",
    "iso:country":"US",
    "sg:address":"502 E Main St",
    "sg:city":"Louisa",
    "sg:classifiers":[
        {
            "category":"Cinema",
            "subcategory":"Movie Rental",
            "type":"Entertainment"
        }
    ],
    "sg:phone":"+1 540 967 9672",
    "sg:postcode":"23093",
    "sg:province":"VA",
    "sg:tags":[
        "leasing",
        "video",
        "disc",
        "tape"
    ],
    "wof:name":"Video 2000",
    "wof:placetype":"venue"
},
  "geometry": {"coordinates":[-77.98950499999999,38.019341],"type":"Point"}
}