{
  "type": "Feature",
  "properties": {
    "iso:country":"US",
    "sg:address":"4008 University Dr",
    "sg:city":"Fairfax",
    "sg:classifiers":[
        {
            "category":"Restaurant",
            "type":"Food & Drink"
        }
    ],
    "sg:phone":"+1 703 385 1909",
    "sg:postcode":"22030",
    "sg:province":"VA",
    "wof:name":"Asian Express",
    "wof:placetype":"venue"
},
  "geometry": {"coordinates":[-77.3053,38.845973],"type":"Point"}
}