{
  "type": "Feature",
  "properties": {
    "addr:full":"987 Rose Hill Rd Wytheville VA 24382",
    "addr:housenumber":"987",
    "addr:postcode":"24382",
    "addr:street":"Rose Hill Rd",
    "iso:country":"US",
    "sg:address":"987 Rose Hill Rd",
    "sg:city":"Wytheville",
    "sg:classifiers":[
        {
            "category":"Recreation",
            "type":"Entertainment"
        }
    ],
    "sg:phone":"+1 276 228 5817",
    "sg:postcode":"24382",
    "sg:province":"VA",
    "sg:tags":[
        "animal"
    ],
    "wof:name":"Copper Crest Farm",
    "wof:placetype":"venue"
},
  "geometry": {"coordinates":[-81.135913,36.973799],"type":"Point"}
}