{
  "type": "Feature",
  "properties": {
    "addr:full":"8856 Bennington Blvd Lorton VA 22079",
    "addr:housenumber":"8856",
    "addr:postcode":"22079",
    "addr:street":"Bennington Blvd",
    "iso:country":"US",
    "sg:address":"8856 Bennington Blvd",
    "sg:city":"Lorton",
    "sg:classifiers":[
        {
            "category":"Retail",
            "subcategory":"Portrait Studio",
            "type":"Services"
        }
    ],
    "sg:phone":"+1 703 541 0565",
    "sg:postcode":"22079",
    "sg:province":"VA",
    "sg:tags":[
        "photo"
    ],
    "wof:name":"Boggs C Photography",
    "wof:placetype":"venue"
},
  "geometry": {"coordinates":[-77.209192,38.719511],"type":"Point"}
}