{
  "type": "Feature",
  "properties": {
    "addr:full":"4948 Richmond Rd Warsaw VA 22572",
    "addr:housenumber":"4948",
    "addr:postcode":"22572",
    "addr:street":"Richmond Rd",
    "iso:country":"US",
    "sg:address":"4948 Richmond Rd",
    "sg:city":"Warsaw",
    "sg:classifiers":[
        {
            "category":"Autos & Motor Vehicles",
            "subcategory":"Automobile Sales",
            "type":"Retail Goods"
        }
    ],
    "sg:phone":"+1 804 333 1119",
    "sg:postcode":"22572",
    "sg:province":"VA",
    "sg:tags":[
        "used"
    ],
    "wof:name":"Beauchamps Auto Sales",
    "wof:placetype":"venue"
},
  "geometry": {"coordinates":[-76.782884,37.963506],"type":"Point"}
}