{
  "type": "Feature",
  "properties": {
    "addr:full":"1000 Crowell Ave Chesapeake VA 23324",
    "addr:housenumber":"1000",
    "addr:postcode":"23324",
    "addr:street":"Crowell Ave",
    "iso:country":"US",
    "sg:address":"1000 Crowell Ave",
    "sg:city":"Chesapeake",
    "sg:classifiers":[
        {
            "category":"Organizations",
            "subcategory":"Religious Organization",
            "type":"Services"
        }
    ],
    "sg:phone":"+1 757 545 6280",
    "sg:postcode":"23324",
    "sg:province":"VA",
    "sg:website":"www.raleighheights.org",
    "wof:name":"Raleigh Heights Baptist Church",
    "wof:placetype":"venue"
},
  "geometry": {"coordinates":[-76.28137099999999,36.787239],"type":"Point"}
}