{
  "type": "Feature",
  "properties": {
    "addr:full":"9325 Joyce Ln Mechanicsville VA 23116",
    "addr:housenumber":"9325",
    "addr:postcode":"23116",
    "addr:street":"Joyce Ln",
    "iso:country":"US",
    "sg:address":"9325 Joyce Ln",
    "sg:city":"Mechanicsville",
    "sg:classifiers":[
        {
            "category":"Building & Trades",
            "subcategory":"Construction",
            "type":"Services"
        }
    ],
    "sg:phone":"+1 804 730 3765",
    "sg:postcode":"23116",
    "sg:province":"VA",
    "sg:tags":[
        "house"
    ],
    "wof:name":"Charlie Coker",
    "wof:placetype":"venue"
},
  "geometry": {"coordinates":[-77.30979000000001,37.661851],"type":"Point"}
}