{
  "type": "Feature",
  "properties": {
    "iso:country":"US",
    "sg:address":"4402 Indian River Rd",
    "sg:city":"Chesapeake",
    "sg:classifiers":[
        {
            "category":"Restaurant",
            "type":"Food & Drink"
        }
    ],
    "sg:phone":"+1 757 420 1303",
    "sg:postcode":"23325",
    "sg:province":"VA",
    "wof:name":"Lulus Hot Dogs",
    "wof:placetype":"venue"
},
  "geometry": {"coordinates":[-76.223162,36.819913],"type":"Point"}
}