{
  "type": "Feature",
  "properties": {
    "addr:full":"38 Garrett St Warrenton VA 20186",
    "addr:housenumber":"38",
    "addr:postcode":"20186",
    "addr:street":"Garrett St",
    "iso:country":"US",
    "sg:address":"38 Garrett St",
    "sg:city":"Warrenton",
    "sg:classifiers":[
        {
            "category":"Real Estate",
            "subcategory":"Real Estate Agent",
            "type":"Services"
        }
    ],
    "sg:phone":"+1 540 347 2121",
    "sg:postcode":"20186",
    "sg:province":"VA",
    "wof:name":"Burke Associates Inc",
    "wof:placetype":"venue"
},
  "geometry": {"coordinates":[-77.80642400000001,38.715986],"type":"Point"}
}