{
  "type": "Feature",
  "properties": {
    "addr:full":"8830 S Genito Rd Jetersville VA 23083",
    "addr:housenumber":"8830",
    "addr:postcode":"23083",
    "addr:street":"S Genito Rd",
    "iso:country":"US",
    "sg:address":"8830 S Genito Rd",
    "sg:city":"Jetersville",
    "sg:classifiers":[
        {
            "category":"Retail",
            "subcategory":"Repair Shop",
            "type":"Services"
        }
    ],
    "sg:phone":"+1 804 561 3133",
    "sg:postcode":"23083",
    "sg:province":"VA",
    "sg:tags":[
        "welding"
    ],
    "wof:name":"Barnes Welding Svc",
    "wof:placetype":"venue"
},
  "geometry": {"coordinates":[-78.159694,37.34349],"type":"Point"}
}