{
  "type": "Feature",
  "properties": {
    "iso:country":"US",
    "sg:address":"4736 Kenmore Ave",
    "sg:city":"Alexandria",
    "sg:classifiers":[
        {
            "category":"Freight",
            "type":"Transportation"
        }
    ],
    "sg:phone":"+1 703 823 2772",
    "sg:postcode":"22304",
    "sg:province":"VA",
    "sg:tags":[
        "operator",
        "local",
        "trucking"
    ],
    "wof:name":"Saudi American Corporate Servi",
    "wof:placetype":"venue"
},
  "geometry": {"coordinates":[-77.11179799999999,38.827788],"type":"Point"}
}