{
  "type": "Feature",
  "properties": {
    "iso:country":"US",
    "sg:address":"265 Steep Hill Rd",
    "sg:city":"Front Royal",
    "sg:classifiers":[
        {
            "category":"Freight",
            "type":"Transportation"
        }
    ],
    "sg:phone":"+1 540 636 8396",
    "sg:postcode":"22630",
    "sg:province":"VA",
    "sg:tags":[
        "operator",
        "local",
        "trucking"
    ],
    "wof:name":"Michael A Manuel Trucking Inc",
    "wof:placetype":"venue"
},
  "geometry": {"coordinates":[-78.197373,38.973256],"type":"Point"}
}