{
  "type": "Feature",
  "properties": {
    "addr:full":"8129 George Washington Memorial Hwy Yorktown VA 23692",
    "addr:housenumber":"8129",
    "addr:postcode":"23692",
    "addr:street":"George Washington Memorial Hwy",
    "iso:country":"US",
    "sg:address":"8129 George Washington Memorial Hwy",
    "sg:city":"Yorktown",
    "sg:classifiers":[
        {
            "category":"Restaurant",
            "type":"Food & Drink"
        },
        {
            "category":"Professional",
            "subcategory":"Management & Consulting",
            "type":"Services"
        }
    ],
    "sg:phone":"+1 757 898 6224",
    "sg:postcode":"23692",
    "sg:province":"VA",
    "wof:name":"Martin Shull Enterprises",
    "wof:placetype":"venue"
},
  "geometry": {"coordinates":[-76.48768699999999,37.189966],"type":"Point"}
}