{
  "type": "Feature",
  "properties": {
    "addr:full":"9310 Three Chopt Rd Richmond VA 23229",
    "addr:housenumber":"9310",
    "addr:postcode":"23229",
    "addr:street":"Three Chopt Rd",
    "iso:country":"US",
    "sg:address":"9310 Three Chopt Rd",
    "sg:city":"Richmond",
    "sg:classifiers":[
        {
            "category":"Organizations",
            "subcategory":"Community Association",
            "type":"Services"
        }
    ],
    "sg:phone":"+1 804 270 3257",
    "sg:postcode":"23229",
    "sg:province":"VA",
    "sg:tags":[
        "fraternal"
    ],
    "wof:name":"Westhampton Masonic Lodge Inc",
    "wof:placetype":"venue"
},
  "geometry": {"coordinates":[-77.568269,37.616009],"type":"Point"}
}