{
  "type": "Feature",
  "properties": {
    "iso:country":"US",
    "sg:address":"1012 S Hill Ave",
    "sg:city":"South Hill",
    "sg:classifiers":[
        {
            "category":"Real Estate",
            "subcategory":"Surveying",
            "type":"Services"
        }
    ],
    "sg:phone":"+1 434 447 8633",
    "sg:postcode":"23970",
    "sg:province":"VA",
    "sg:tags":[
        "surveyor"
    ],
    "wof:name":"Benjamin M Evans Jr Inc",
    "wof:placetype":"venue"
},
  "geometry": {"coordinates":[-78.133532,36.717622],"type":"Point"}
}