{
  "type": "Feature",
  "properties": {
    "addr:full":"5321 Merchants View Sq Haymarket VA 20169",
    "addr:housenumber":"5321",
    "addr:postcode":"20169",
    "addr:street":"Merchants View Sq",
    "iso:country":"US",
    "sg:address":"5321 Merchants View Sq",
    "sg:city":"Haymarket",
    "sg:classifiers":[
        {
            "category":"Health Services",
            "subcategory":"Dentist",
            "type":"Services"
        }
    ],
    "sg:phone":"+1 571 248 0300",
    "sg:postcode":"20169",
    "sg:province":"VA",
    "sg:tags":[
        "orthodontist"
    ],
    "wof:name":"Advanced Orthodontics",
    "wof:placetype":"venue"
},
  "geometry": {"coordinates":[-77.640432,38.843809],"type":"Point"}
}