{
  "type": "Feature",
  "properties": {
    "addr:full":"7459 McConnell Rd Roanoke VA 24019",
    "addr:housenumber":"7459",
    "addr:postcode":"24019",
    "addr:street":"Mcconnell Rd",
    "iso:country":"US",
    "sg:address":"7459 McConnell Rd",
    "sg:city":"Roanoke",
    "sg:classifiers":[
        {
            "category":"Insurance",
            "subcategory":"Hazard Insurance",
            "type":"Services"
        }
    ],
    "sg:phone":"+1 540 366 3330",
    "sg:postcode":"24019",
    "sg:province":"VA",
    "sg:tags":[
        "fund",
        "pension"
    ],
    "wof:name":"Church Insurance Co",
    "wof:placetype":"venue"
},
  "geometry": {"coordinates":[-79.952303,37.349261],"type":"Point"}
}