{
  "type": "Feature",
  "properties": {
    "addr:full":"7368 Harvest Dr Suffolk VA 23437",
    "addr:housenumber":"7368",
    "addr:postcode":"23437",
    "addr:street":"Harvest Dr",
    "iso:country":"US",
    "sg:address":"7368 Harvest Dr",
    "sg:city":"Suffolk",
    "sg:classifiers":[
        {
            "category":"Farming",
            "subcategory":"Farm",
            "type":"Manufacturing & Wholesale Goods"
        }
    ],
    "sg:phone":"+1 757 657 6762",
    "sg:postcode":"23437",
    "sg:province":"VA",
    "sg:tags":[
        "crop",
        "general"
    ],
    "wof:name":"Frank Holland Jr",
    "wof:placetype":"venue"
},
  "geometry": {"coordinates":[-76.84568400000001,36.66496],"type":"Point"}
}