{
  "type": "Feature",
  "properties": {
    "iso:country":"US",
    "sg:address":"5201 Duke St Ofc",
    "sg:city":"Alexandria",
    "sg:classifiers":[
        {
            "category":"Real Estate",
            "subcategory":"Real Estate Services",
            "type":"Services"
        }
    ],
    "sg:phone":"+1 703 751 2300",
    "sg:postcode":"22304",
    "sg:province":"VA",
    "sg:tags":[
        "management",
        "condominium"
    ],
    "sg:website":"http://www.kpamgmt.com",
    "wof:name":"Canterbury Square Condo Association",
    "wof:placetype":"venue"
},
  "geometry": {"coordinates":[-77.12205899999999,38.81258],"type":"Point"}
}