{
  "type": "Feature",
  "properties": {
    "addr:full":"3165 Key Blvd Arlington VA 22201",
    "addr:housenumber":"3165",
    "addr:postcode":"22201",
    "addr:street":"Key Blvd",
    "iso:country":"US",
    "sg:address":"3165 Key Blvd",
    "sg:city":"Arlington",
    "sg:classifiers":[
        {
            "category":"Professional",
            "subcategory":"Lawyer & Legal Services",
            "type":"Services"
        }
    ],
    "sg:phone":"+1 703 528 7981",
    "sg:postcode":"22201",
    "sg:province":"VA",
    "wof:name":"Findler William E Atty",
    "wof:placetype":"venue"
},
  "geometry": {"coordinates":[-77.098231,38.8898],"type":"Point"}
}