{
  "type": "Feature",
  "properties": {
    "addr:full":"5901 Coverdale Way Alexandria VA 22310",
    "addr:housenumber":"5901",
    "addr:postcode":"22310",
    "addr:street":"Coverdale Way",
    "iso:country":"US",
    "sg:address":"5901 Coverdale Way",
    "sg:city":"Alexandria",
    "sg:classifiers":[
        {
            "category":"Real Estate",
            "subcategory":"Real Estate Operator",
            "type":"Services"
        }
    ],
    "sg:phone":"+1 703 924 1000",
    "sg:postcode":"22310",
    "sg:province":"VA",
    "sg:tags":[
        "apartment"
    ],
    "wof:name":"Jefferson At Van Dorn Apts",
    "wof:placetype":"venue"
},
  "geometry": {"coordinates":[-77.139346,38.792382],"type":"Point"}
}