{
  "type": "Feature",
  "properties": {
    "iso:country":"US",
    "sg:address":"84 S Early St",
    "sg:city":"Alexandria",
    "sg:classifiers":[
        {
            "category":"Manufacturing",
            "subcategory":"Printing",
            "type":"Manufacturing & Wholesale Goods"
        }
    ],
    "sg:phone":"+1 703 823 0224",
    "sg:postcode":"22304",
    "sg:province":"VA",
    "sg:tags":[
        "commercial",
        "lithographic"
    ],
    "wof:name":"Potomac Printing",
    "wof:placetype":"venue"
},
  "geometry": {"coordinates":[-77.09679199999999,38.8076],"type":"Point"}
}