{
  "type": "Feature",
  "properties": {
    "addr:full":"520 Pine Dr Lynchburg VA 24503",
    "addr:housenumber":"520",
    "addr:postcode":"24503",
    "addr:street":"Pine Dr",
    "iso:country":"US",
    "sg:address":"520 Pine Dr",
    "sg:city":"Lynchburg",
    "sg:classifiers":[
        {
            "category":"Utilities",
            "subcategory":"Telephone",
            "type":"Services"
        }
    ],
    "sg:phone":"+1 434 384 1478",
    "sg:postcode":"24503",
    "sg:province":"VA",
    "sg:tags":[
        "communications"
    ],
    "wof:name":"Featherston Telephone Com",
    "wof:placetype":"venue"
},
  "geometry": {"coordinates":[-79.183716,37.448487],"type":"Point"}
}