{
  "type": "Feature",
  "properties": {
    "addr:full":"513 Forest Ave Richmond VA 23229",
    "addr:housenumber":"513",
    "addr:postcode":"23229",
    "addr:street":"Forest Ave",
    "iso:country":"US",
    "sg:address":"513 Forest Ave",
    "sg:city":"Richmond",
    "sg:classifiers":[
        {
            "category":"Social Services",
            "type":"Services"
        }
    ],
    "sg:phone":"+1 804 282 9802",
    "sg:postcode":"23229",
    "sg:province":"VA",
    "wof:name":"Suzanne Stauffer",
    "wof:placetype":"venue"
},
  "geometry": {"coordinates":[-77.55313099999999,37.585556],"type":"Point"}
}