{
  "type": "Feature",
  "properties": {
    "addr:full":"3833 Nightmuse Way Glen Allen VA 23059",
    "addr:housenumber":"3833",
    "addr:postcode":"23059",
    "addr:street":"Nightmuse Way",
    "iso:country":"US",
    "sg:address":"3833 Nightmuse Way",
    "sg:city":"Glen Allen",
    "sg:classifiers":[
        {
            "category":"Real Estate",
            "subcategory":"Real Estate Agent",
            "type":"Services"
        }
    ],
    "sg:phone":"+1 804 266 4650",
    "sg:postcode":"23059",
    "sg:province":"VA",
    "wof:name":"Premier Property MGT LLC",
    "wof:placetype":"venue"
},
  "geometry": {"coordinates":[-77.516486,37.682481],"type":"Point"}
}