{
  "type": "Feature",
  "properties": {
    "addr:full":"3415 Whiteside St NE Roanoke VA 24012",
    "addr:housenumber":"3415",
    "addr:postcode":"24012",
    "addr:street":"Whiteside St Ne",
    "iso:country":"US",
    "sg:address":"3415 Whiteside St NE",
    "sg:city":"Roanoke",
    "sg:classifiers":[
        {
            "category":"Manufacturing",
            "subcategory":"Printing",
            "type":"Manufacturing & Wholesale Goods"
        }
    ],
    "sg:phone":"+1 540 563 8833",
    "sg:postcode":"24012",
    "sg:province":"VA",
    "sg:tags":[
        "printer"
    ],
    "wof:name":"Earl Wood Printing Co",
    "wof:placetype":"venue"
},
  "geometry": {"coordinates":[-79.930897,37.306755],"type":"Point"}
}