{
  "type": "Feature",
  "properties": {
    "addr:full":"9532 Burke Rd Burke VA 22015",
    "addr:housenumber":"9532",
    "addr:postcode":"22015",
    "addr:street":"Burke Rd",
    "iso:country":"US",
    "sg:address":"9532 Burke Rd",
    "sg:city":"Burke",
    "sg:classifiers":[
        {
            "category":"Personal",
            "subcategory":"Beauty Salon",
            "type":"Services"
        }
    ],
    "sg:phone":"+1 703 978 9877",
    "sg:postcode":"22015",
    "sg:province":"VA",
    "sg:website":"www.haircuttery.com",
    "wof:name":"Hair Cuttery",
    "wof:placetype":"venue"
},
  "geometry": {"coordinates":[-77.271934,38.794116],"type":"Point"}
}