{
  "type": "Feature",
  "properties": {
    "addr:full":"204 W Washington St Lexington VA 24450",
    "addr:housenumber":"204",
    "addr:postcode":"24450",
    "addr:street":"W Washington St",
    "iso:country":"US",
    "sg:address":"204 W Washington St",
    "sg:city":"Lexington",
    "sg:classifiers":[
        {
            "category":"Education",
            "subcategory":"College",
            "type":"Public Place"
        }
    ],
    "sg:phone":"+1 540 463 8400",
    "sg:postcode":"24450",
    "sg:province":"VA",
    "sg:tags":[
        "university"
    ],
    "wof:name":"Washington & Lee University",
    "wof:placetype":"venue"
},
  "geometry": {"coordinates":[-79.44382299999999,37.786246],"type":"Point"}
}