{
  "type": "Feature",
  "properties": {
    "addr:full":"113 W Beverley St Staunton VA 24401",
    "addr:housenumber":"113",
    "addr:postcode":"24401",
    "addr:street":"W Beverley St",
    "iso:country":"US",
    "sg:address":"113 W Beverley St",
    "sg:city":"Staunton",
    "sg:classifiers":[
        {
            "category":"Manufacturing",
            "subcategory":"Printing",
            "type":"Manufacturing & Wholesale Goods"
        }
    ],
    "sg:phone":"+1 540 885 2600",
    "sg:postcode":"24401",
    "sg:province":"VA",
    "sg:tags":[
        "lithographic",
        "commercial"
    ],
    "wof:name":"Minuteman Press",
    "wof:placetype":"venue"
},
  "geometry": {"coordinates":[-79.073797,38.149477],"type":"Point"}
}