{
  "type": "Feature",
  "properties": {
    "addr:full":"2086 Defense Rd Petersburg VA 23805",
    "addr:housenumber":"2086",
    "addr:postcode":"23805",
    "addr:street":"Defense Rd",
    "iso:country":"US",
    "sg:address":"2086 Defense Rd",
    "sg:city":"Petersburg",
    "sg:classifiers":[
        {
            "category":"Arts & Performance",
            "subcategory":"Theater",
            "type":"Entertainment"
        }
    ],
    "sg:phone":"+1 804 957 5697",
    "sg:postcode":"23805",
    "sg:province":"VA",
    "sg:tags":[
        "musician"
    ],
    "wof:name":"Johnnie Skinner",
    "wof:placetype":"venue"
},
  "geometry": {"coordinates":[-77.41830400000001,37.198275],"type":"Point"}
}