{
  "type": "Feature",
  "properties": {
    "addr:full":"3704 Golf Trail Ln Fairfax VA 22033",
    "addr:housenumber":"3704",
    "addr:postcode":"22033",
    "addr:street":"Golf Trail Ln",
    "iso:country":"US",
    "sg:address":"3704 Golf Trail Ln",
    "sg:city":"Fairfax",
    "sg:classifiers":[
        {
            "category":"Real Estate",
            "subcategory":"Real Estate Agent",
            "type":"Services"
        }
    ],
    "sg:phone":"+1 703 591 1818",
    "sg:postcode":"22033",
    "sg:province":"VA",
    "wof:name":"Cardinal Management Group Inc",
    "wof:placetype":"venue"
},
  "geometry": {"coordinates":[-77.358676,38.872844],"type":"Point"}
}