{
  "type": "Feature",
  "properties": {
    "addr:full":"318 Wassona Dr Marion VA 24354",
    "addr:housenumber":"318",
    "addr:postcode":"24354",
    "addr:street":"Wassona Dr",
    "iso:country":"US",
    "sg:address":"318 Wassona Dr",
    "sg:city":"Marion",
    "sg:classifiers":[
        {
            "category":"Recreation",
            "type":"Entertainment"
        }
    ],
    "sg:phone":"+1 276 783 3024",
    "sg:postcode":"24354",
    "sg:province":"VA",
    "sg:tags":[
        "club",
        "membership"
    ],
    "wof:name":"Tennis Anyone",
    "wof:placetype":"venue"
},
  "geometry": {"coordinates":[-81.497366,36.849384],"type":"Point"}
}