{
  "type": "Feature",
  "properties": {
    "iso:country":"US",
    "sg:address":"2601 Roswell Ct",
    "sg:city":"Falls Church",
    "sg:classifiers":[
        {
            "category":"Manufacturing",
            "subcategory":"Printing",
            "type":"Manufacturing & Wholesale Goods"
        }
    ],
    "sg:phone":"+1 703 573 3730",
    "sg:postcode":"22043",
    "sg:province":"VA",
    "sg:tags":[
        "engraving"
    ],
    "wof:name":"Engraving Shop",
    "wof:placetype":"venue"
},
  "geometry": {"coordinates":[-77.216638,38.884982],"type":"Point"}
}