{
  "type": "Feature",
  "properties": {
    "addr:full":"43001 Thoroughgood Dr Chantilly VA 20152",
    "addr:postcode":"43001;20152",
    "addr:street":"Thoroughgood Dr",
    "iso:country":"US",
    "sg:address":"43001 Thoroughgood Dr",
    "sg:city":"Chantilly",
    "sg:classifiers":[
        {
            "category":"Real Estate",
            "subcategory":"Real Estate Services",
            "type":"Services"
        }
    ],
    "sg:phone":"+1 866 204 0233",
    "sg:postcode":"20152",
    "sg:province":"VA",
    "sg:tags":[
        "apartment",
        "management",
        "rental",
        "finder"
    ],
    "sg:website":"http://washingtondc.citysearch.com/profile/external/10439224/chantilly_va/the_abbey.html?publisher=yellowpages&reference_id=1&placement=ypwebsitemip",
    "wof:name":"The Abbey",
    "wof:placetype":"venue"
},
  "geometry": {"coordinates":[-77.515503,38.917389],"type":"Point"}
}