{
  "type": "Feature",
  "properties": {
    "iso:country":"US",
    "sg:address":"11319 Cross County Rd",
    "sg:city":"Mineral",
    "sg:classifiers":[
        {
            "category":"Retail",
            "subcategory":"Repair Shop",
            "type":"Services"
        }
    ],
    "sg:phone":"+1 540 894 4900",
    "sg:postcode":"23117",
    "sg:province":"VA",
    "wof:name":"Simmons Saw & Cutting Tool",
    "wof:placetype":"venue"
},
  "geometry": {"coordinates":[-77.896717,37.893157],"type":"Point"}
}