{
  "type": "Feature",
  "properties": {
    "addr:full":"1901 N Moore St Arlington VA 22209",
    "addr:housenumber":"1901",
    "addr:postcode":"22209",
    "addr:street":"N Moore St",
    "iso:country":"US",
    "sg:address":"1901 N Moore St",
    "sg:city":"Arlington",
    "sg:classifiers":[
        {
            "category":"Wholesale",
            "subcategory":"Computers",
            "type":"Manufacturing & Wholesale Goods"
        }
    ],
    "sg:phone":"+1 703 527 3703",
    "sg:postcode":"22209",
    "sg:province":"VA",
    "sg:tags":[
        "peripheral"
    ],
    "wof:name":"Xerox",
    "wof:placetype":"venue"
},
  "geometry": {"coordinates":[-77.07145,38.898261],"type":"Point"}
}