{
  "type": "Feature",
  "properties": {
    "addr:full":"3519 Pierce St Portsmouth VA 23703",
    "addr:housenumber":"3519",
    "addr:postcode":"23703",
    "addr:street":"Pierce St",
    "iso:country":"US",
    "sg:address":"3519 Pierce St",
    "sg:city":"Portsmouth",
    "sg:classifiers":[
        {
            "category":"Food & Beverages",
            "subcategory":"Bakery",
            "type":"Retail Goods"
        }
    ],
    "sg:phone":"+1 757 483 2398",
    "sg:postcode":"23703",
    "sg:province":"VA",
    "wof:name":"Great Cakes & Things",
    "wof:placetype":"venue"
},
  "geometry": {"coordinates":[-76.39909299999999,36.867838],"type":"Point"}
}