{
  "type": "Feature",
  "properties": {
    "addr:full":"1 Harrison St SE Leesburg VA 20175",
    "addr:housenumber":"1",
    "addr:postcode":"20175",
    "addr:street":"Harrison St Se",
    "iso:country":"US",
    "sg:address":"1 Harrison St SE",
    "sg:city":"Leesburg",
    "sg:classifiers":[
        {
            "category":"Professional",
            "subcategory":"Lawyer & Legal Services",
            "type":"Services"
        },
        {
            "category":"Government",
            "subcategory":"Court House",
            "type":"Public Place"
        }
    ],
    "sg:phone":"+1 703 777 0307",
    "sg:postcode":"20175",
    "sg:province":"VA",
    "sg:tags":[
        "county",
        "counsel"
    ],
    "sg:website":"www.loudoun.gov",
    "wof:name":"Loudoun County Attorney Ofc",
    "wof:placetype":"venue"
},
  "geometry": {"coordinates":[-77.561458,39.113957],"type":"Point"}
}