{
  "type": "Feature",
  "properties": {
    "addr:full":"5788 Arrowhead Dr Virginia Beach VA 23462",
    "addr:housenumber":"5788",
    "addr:postcode":"23462",
    "addr:street":"Arrowhead Dr",
    "iso:country":"US",
    "sg:address":"5788 Arrowhead Dr",
    "sg:city":"Virginia Beach",
    "sg:classifiers":[
        {
            "category":"Home & Garden",
            "subcategory":"Building Materials",
            "type":"Retail Goods"
        }
    ],
    "sg:phone":"+1 757 554 0588",
    "sg:postcode":"23462",
    "sg:province":"VA",
    "sg:tags":[
        "door"
    ],
    "wof:name":"Beach Door Svc",
    "wof:placetype":"venue"
},
  "geometry": {"coordinates":[-76.18422,36.840513],"type":"Point"}
}