{
  "type": "Feature",
  "properties": {
    "addr:full":"2527 George's Rd Powhatan VA 23139",
    "addr:housenumber":"2527",
    "addr:postcode":"23139",
    "addr:street":"George'S Rd",
    "iso:country":"US",
    "sg:address":"2527 George's Rd",
    "sg:city":"Powhatan",
    "sg:classifiers":[
        {
            "category":"Retail",
            "subcategory":"Auto Repair",
            "type":"Services"
        }
    ],
    "sg:phone":"+1 804 598 7022",
    "sg:postcode":"23139",
    "sg:province":"VA",
    "sg:tags":[
        "exchanging",
        "engine"
    ],
    "wof:name":"Bob's Small Engine Svc",
    "wof:placetype":"venue"
},
  "geometry": {"coordinates":[-77.84908799999999,37.558629],"type":"Point"}
}