{
  "type": "Feature",
  "properties": {
    "addr:full":"1132 Battlefield Blvd N Chesapeake VA 23320",
    "addr:housenumber":"1132",
    "addr:postcode":"23320",
    "addr:street":"Battlefield Blvd N",
    "iso:country":"US",
    "sg:address":"1132 Battlefield Blvd N",
    "sg:city":"Chesapeake",
    "sg:classifiers":[
        {
            "category":"Home & Garden",
            "subcategory":"Hardware",
            "type":"Retail Goods"
        }
    ],
    "sg:phone":"+1 757 436 0111",
    "sg:postcode":"23320",
    "sg:province":"VA",
    "wof:name":"Cooke Greenbriar Hardware",
    "wof:placetype":"venue"
},
  "geometry": {"coordinates":[-76.25043700000001,36.760489],"type":"Point"}
}