{
  "type": "Feature",
  "properties": {
    "addr:full":"43164 Valiant Dr Chantilly VA 20152",
    "addr:postcode":"43164;20152",
    "addr:street":"Valiant Dr",
    "iso:country":"US",
    "sg:address":"43164 Valiant Dr",
    "sg:city":"Chantilly",
    "sg:classifiers":[
        {
            "category":"Banks & Credit Unions",
            "subcategory":"Bank",
            "type":"Services"
        }
    ],
    "sg:phone":"+1 703 648 8699",
    "sg:postcode":"20152",
    "sg:province":"VA",
    "sg:tags":[
        "broker",
        "mortgage"
    ],
    "wof:name":"Equity Vision Mortgage Corp",
    "wof:placetype":"venue"
},
  "geometry": {"coordinates":[-77.508548,38.897891],"type":"Point"}
}