{
  "type": "Feature",
  "properties": {
    "iso:country":"US",
    "sg:address":"303 N Glebe Rd",
    "sg:city":"Arlington",
    "sg:classifiers":[
        {
            "category":"Restaurant",
            "type":"Food & Drink"
        }
    ],
    "sg:phone":"+1 703 807 0025",
    "sg:postcode":"22203",
    "sg:province":"VA",
    "sg:tags":[
        "eating"
    ],
    "wof:name":"Renconcito Latino",
    "wof:placetype":"venue"
},
  "geometry": {"coordinates":[-77.1054,38.873901],"type":"Point"}
}