{
  "type": "Feature",
  "properties": {
    "addr:full":"7828 Lee Ave Alexandria VA 22308",
    "addr:housenumber":"7828",
    "addr:postcode":"22308",
    "addr:street":"Lee Ave",
    "iso:country":"US",
    "sg:address":"7828 Lee Ave",
    "sg:city":"Alexandria",
    "sg:classifiers":[
        {
            "category":"Building & Trades",
            "subcategory":"Construction",
            "type":"Services"
        }
    ],
    "sg:phone":"+1 703 780 1100",
    "sg:postcode":"22308",
    "sg:province":"VA",
    "sg:tags":[
        "hanging",
        "contractor"
    ],
    "wof:name":"Ryder Paint Contractor",
    "wof:placetype":"venue"
},
  "geometry": {"coordinates":[-77.049761,38.743143],"type":"Point"}
}