{
  "type": "Feature",
  "properties": {
    "iso:country":"US",
    "sg:address":"200 W Grace St",
    "sg:city":"Richmond",
    "sg:classifiers":[
        {
            "category":"Building & Trades",
            "subcategory":"Electrical",
            "type":"Services"
        }
    ],
    "sg:phone":"+1 434 822 6674",
    "sg:postcode":"23220",
    "sg:province":"VA",
    "sg:tags":[
        "electrical",
        "contractor"
    ],
    "wof:name":"Thompson Electric Company",
    "wof:placetype":"venue"
},
  "geometry": {"coordinates":[-77.445386,37.54635],"type":"Point"}
}