{
  "type": "Feature",
  "properties": {
    "iso:country":"US",
    "sg:address":"3 E Cary St",
    "sg:city":"Richmond",
    "sg:classifiers":[
        {
            "category":"Professional",
            "subcategory":"Management & Consulting",
            "type":"Services"
        }
    ],
    "sg:phone":"+1 804 644 8741",
    "sg:postcode":"23219",
    "sg:province":"VA",
    "sg:tags":[
        "marketing",
        "consultant"
    ],
    "wof:name":"P B Huber Analysis Research",
    "wof:placetype":"venue"
},
  "geometry": {"coordinates":[-77.44437000000001,37.541605],"type":"Point"}
}