{
  "type": "Feature",
  "properties": {
    "addr:full":"106 W 5th Ave Franklin VA 23851",
    "addr:housenumber":"106",
    "addr:postcode":"23851",
    "addr:street":"W 5Th Ave",
    "iso:country":"US",
    "sg:address":"106 W 5th Ave",
    "sg:city":"Franklin",
    "sg:classifiers":[
        {
            "category":"Professional",
            "subcategory":"Art Services",
            "type":"Services"
        }
    ],
    "sg:phone":"+1 757 562 7667",
    "sg:postcode":"23851",
    "sg:province":"VA",
    "sg:tags":[
        "photography",
        "commercial"
    ],
    "wof:name":"Photos By Thaya",
    "wof:placetype":"venue"
},
  "geometry": {"coordinates":[-76.92428200000001,36.679563],"type":"Point"}
}