{
  "type": "Feature",
  "properties": {
    "addr:full":"804 Moorefield Park Dr Richmond VA 23236",
    "addr:housenumber":"804",
    "addr:postcode":"23236",
    "addr:street":"Moorefield Park Dr",
    "iso:country":"US",
    "sg:address":"804 Moorefield Park Dr",
    "sg:city":"Richmond",
    "sg:classifiers":[
        {
            "category":"Insurance",
            "subcategory":"Insurance Agent",
            "type":"Services"
        },
        {
            "category":"Insurance",
            "subcategory":"Life Insurance",
            "type":"Services"
        }
    ],
    "sg:phone":"+1 804 560 1350",
    "sg:postcode":"23236",
    "sg:province":"VA",
    "sg:tags":[
        "carrier",
        "carrie"
    ],
    "wof:name":"Monumental Life Insurance Co",
    "wof:placetype":"venue"
},
  "geometry": {"coordinates":[-77.58008,37.499366],"type":"Point"}
}