{
  "type": "Feature",
  "properties": {
    "addr:full":"8916 Jeters Chapel Rd Vinton VA 24179",
    "addr:housenumber":"8916",
    "addr:postcode":"24179",
    "addr:street":"Jeters Chapel Rd",
    "iso:country":"US",
    "sg:address":"8916 Jeters Chapel Rd",
    "sg:city":"Vinton",
    "sg:classifiers":[
        {
            "category":"Building & Trades",
            "subcategory":"Electrical",
            "type":"Services"
        }
    ],
    "sg:phone":"+1 540 890 8003",
    "sg:postcode":"24179",
    "sg:province":"VA",
    "sg:tags":[
        "electrical",
        "contractor"
    ],
    "wof:name":"Hilltop Electric",
    "wof:placetype":"venue"
},
  "geometry": {"coordinates":[-79.77758300000001,37.30576],"type":"Point"}
}