{
  "type": "Feature",
  "properties": {
    "addr:full":"204 Donmore Dr Great Falls VA 22066",
    "addr:housenumber":"204",
    "addr:postcode":"22066",
    "addr:street":"Donmore Dr",
    "iso:country":"US",
    "sg:address":"204 Donmore Dr",
    "sg:city":"Great Falls",
    "sg:classifiers":[
        {
            "category":"Professional",
            "subcategory":"Business Services",
            "type":"Services"
        }
    ],
    "sg:phone":"+1 703 430 4248",
    "sg:postcode":"22066",
    "sg:province":"VA",
    "wof:name":"Matchpoint Solutions Inc",
    "wof:placetype":"venue"
},
  "geometry": {"coordinates":[-77.333935,39.045373],"type":"Point"}
}