{
  "type": "Feature",
  "properties": {
    "addr:full":"10320 Festival Ln Manassas VA 20109",
    "addr:housenumber":"10320",
    "addr:postcode":"20109",
    "addr:street":"Festival Ln",
    "iso:country":"US",
    "sg:address":"10320 Festival Ln",
    "sg:city":"Manassas",
    "sg:classifiers":[
        {
            "category":"Food & Beverages",
            "subcategory":"Groceries & Convenience Stores",
            "type":"Retail Goods"
        }
    ],
    "sg:phone":"+1 703 365 7444",
    "sg:postcode":"20109",
    "sg:province":"VA",
    "sg:website":"theglobalfood.com/",
    "wof:name":"Global Food",
    "wof:placetype":"venue"
},
  "geometry": {"coordinates":[-77.504423,38.778258],"type":"Point"}
}