{
  "type": "Feature",
  "properties": {
    "addr:full":"2845 Moses Grandy Trl Ste A Chesapeake VA 23323",
    "addr:housenumber":"2845",
    "addr:postcode":"23323",
    "addr:street":"Moses Grandy Trl Ste A",
    "iso:country":"US",
    "sg:address":"2845 Moses Grandy Trl Ste A",
    "sg:city":"Chesapeake",
    "sg:classifiers":[
        {
            "category":"Personal",
            "subcategory":"Tanning Parlor",
            "type":"Services"
        }
    ],
    "sg:phone":"+1 757 485 8267",
    "sg:postcode":"23323",
    "sg:province":"VA",
    "sg:tags":[
        "salon"
    ],
    "wof:name":"Tanned Bum",
    "wof:placetype":"venue"
},
  "geometry": {"coordinates":[-76.34415300000001,36.740907],"type":"Point"}
}