{
  "type": "Feature",
  "properties": {
    "addr:full":"115 Ingram Rd Danville VA 24541",
    "addr:housenumber":"115",
    "addr:postcode":"24541",
    "addr:street":"Ingram Rd",
    "iso:country":"US",
    "sg:address":"115 Ingram Rd",
    "sg:city":"Danville",
    "sg:classifiers":[
        {
            "category":"Retail",
            "subcategory":"Repair Shop",
            "type":"Services"
        }
    ],
    "sg:phone":"+1 434 822 2332",
    "sg:postcode":"24541",
    "sg:province":"VA",
    "sg:tags":[
        "television",
        "radio"
    ],
    "wof:name":"Yeatts Electronics",
    "wof:placetype":"venue"
},
  "geometry": {"coordinates":[-79.457172,36.592771],"type":"Point"}
}