{
  "type": "Feature",
  "properties": {
    "addr:full":"100 Wingfield Ave Chesapeake VA 23325",
    "addr:housenumber":"100",
    "addr:postcode":"23325",
    "addr:street":"Wingfield Ave",
    "iso:country":"US",
    "sg:address":"100 Wingfield Ave",
    "sg:city":"Chesapeake",
    "sg:classifiers":[
        {
            "category":"Utilities",
            "subcategory":"Refuse",
            "type":"Services"
        }
    ],
    "sg:phone":"+1 757 523 8668",
    "sg:postcode":"23325",
    "sg:province":"VA",
    "sg:tags":[
        "landfill"
    ],
    "wof:name":"New Light Assoc",
    "wof:placetype":"venue"
},
  "geometry": {"coordinates":[-76.243053,36.83182],"type":"Point"}
}