{
  "type": "Feature",
  "properties": {
    "iso:country":"US",
    "sg:address":"136 Spanish Trl",
    "sg:city":"Hampton",
    "sg:classifiers":[
        {
            "category":"Manufacturing",
            "subcategory":"Tools & Machinery",
            "type":"Manufacturing & Wholesale Goods"
        }
    ],
    "sg:phone":"+1 757 726 2728",
    "sg:postcode":"23669",
    "sg:province":"VA",
    "sg:tags":[
        "construction",
        "mfg"
    ],
    "wof:name":"Macgregor Inc",
    "wof:placetype":"venue"
},
  "geometry": {"coordinates":[-76.34436599999999,37.036558],"type":"Point"}
}