{
  "type": "Feature",
  "properties": {
    "iso:country":"US",
    "sg:address":"8270 Greensboro Dr",
    "sg:city":"Mc Lean",
    "sg:classifiers":[
        {
            "category":"Banks & Credit Unions",
            "subcategory":"Financial Services",
            "type":"Services"
        }
    ],
    "sg:phone":"+1 703 903 9546",
    "sg:postcode":"22102",
    "sg:province":"VA",
    "sg:tags":[
        "investment",
        "closed"
    ],
    "wof:name":"Edison Venture Fund",
    "wof:placetype":"venue"
},
  "geometry": {"coordinates":[-77.230136,38.922641],"type":"Point"}
}