{
  "type": "Feature",
  "properties": {
    "addr:full":"23478 Melmore Pl Middleburg VA 20117",
    "addr:postcode":"23478;20117",
    "addr:street":"Melmore Pl",
    "iso:country":"US",
    "sg:address":"23478 Melmore Pl",
    "sg:city":"Middleburg",
    "sg:classifiers":[
        {
            "category":"Wholesale",
            "subcategory":"Electrical",
            "type":"Manufacturing & Wholesale Goods"
        }
    ],
    "sg:phone":"+1 540 687 3928",
    "sg:postcode":"20117",
    "sg:province":"VA",
    "sg:tags":[
        "nitrogen",
        "installation",
        "sales",
        "generator"
    ],
    "wof:name":"PTG Progressive Tech For Gas",
    "wof:placetype":"venue"
},
  "geometry": {"coordinates":[-77.72434,38.96953],"type":"Point"}
}