{
  "type": "Feature",
  "properties": {
    "iso:country":"US",
    "sg:address":"149 S Gum Ave",
    "sg:city":"Virginia Beach",
    "sg:classifiers":[
        {
            "category":"Building & Trades",
            "subcategory":"Landscaping Services",
            "type":"Services"
        }
    ],
    "sg:phone":"+1 757 222 1331",
    "sg:postcode":"23452",
    "sg:province":"VA",
    "wof:name":"Appearance Plus Inc",
    "wof:placetype":"venue"
},
  "geometry": {"coordinates":[-76.124351,36.837663],"type":"Point"}
}