{
  "type": "Feature",
  "properties": {
    "addr:full":"912 E Main St Salem VA 24153",
    "addr:housenumber":"912",
    "addr:postcode":"24153",
    "addr:street":"E Main St",
    "iso:country":"US",
    "sg:address":"912 E Main St",
    "sg:city":"Salem",
    "sg:classifiers":[
        {
            "category":"Restaurant",
            "type":"Food & Drink"
        }
    ],
    "sg:phone":"+1 540 375 0971",
    "sg:postcode":"24153",
    "sg:province":"VA",
    "sg:tags":[
        "eating"
    ],
    "wof:name":"Salem Sports Grill Inc",
    "wof:placetype":"venue"
},
  "geometry": {"coordinates":[-80.042411,37.295626],"type":"Point"}
}