{
  "type": "Feature",
  "properties": {
    "iso:country":"US",
    "sg:address":"2612 Whiteclift Dr",
    "sg:city":"Richmond",
    "sg:classifiers":[
        {
            "category":"Professional",
            "subcategory":"Engineering",
            "type":"Services"
        }
    ],
    "sg:phone":"+1 804 356 5066",
    "sg:postcode":"23233",
    "sg:province":"VA",
    "sg:tags":[
        "engineer"
    ],
    "wof:name":"Walter L Turnage Pe",
    "wof:placetype":"venue"
},
  "geometry": {"coordinates":[-77.59419,37.629728],"type":"Point"}
}