{
  "type": "Feature",
  "properties": {
    "iso:country":"US",
    "sg:address":"20214 Leier Pl",
    "sg:city":"Ashburn",
    "sg:classifiers":[
        {
            "category":"Real Estate",
            "subcategory":"Real Estate Agent",
            "type":"Services"
        }
    ],
    "sg:phone":"+1 703 858 1912",
    "sg:postcode":"20147",
    "sg:province":"VA",
    "wof:name":"Veritas LLC",
    "wof:placetype":"venue"
},
  "geometry": {"coordinates":[-77.50993699999999,39.05704],"type":"Point"}
}