{
  "type": "Feature",
  "properties": {
    "addr:full":"17956 Colonial Port Rd Dumfries VA 22026",
    "addr:housenumber":"17956",
    "addr:postcode":"22026",
    "addr:street":"Colonial Port Rd",
    "iso:country":"US",
    "sg:address":"17956 Colonial Port Rd",
    "sg:city":"Dumfries",
    "sg:classifiers":[
        {
            "category":"Freight",
            "type":"Transportation"
        }
    ],
    "sg:phone":"+1 703 221 7101",
    "sg:postcode":"22026",
    "sg:province":"VA",
    "sg:tags":[
        "dry",
        "bulk",
        "trucking"
    ],
    "wof:name":"Quality Carriers Inc",
    "wof:placetype":"venue"
},
  "geometry": {"coordinates":[-77.314572,38.566745],"type":"Point"}
}