{
  "type": "Feature",
  "properties": {
    "iso:country":"US",
    "sg:address":"8074 Mechanicsville Tpke",
    "sg:city":"Mechanicsville",
    "sg:classifiers":[
        {
            "category":"Banks & Credit Unions",
            "subcategory":"Bank",
            "type":"Services"
        }
    ],
    "sg:phone":"+1 804 746 3085",
    "sg:postcode":"23111",
    "sg:province":"VA",
    "wof:name":"B B & T",
    "wof:placetype":"venue"
},
  "geometry": {"coordinates":[-77.375613,37.601417],"type":"Point"}
}