{
  "type": "Feature",
  "properties": {
    "addr:full":"150 S Main St Lexington VA 24450",
    "addr:housenumber":"150",
    "addr:postcode":"24450",
    "addr:street":"S Main St",
    "iso:country":"US",
    "sg:address":"150 S Main St",
    "sg:city":"Lexington",
    "sg:classifiers":[
        {
            "category":"Government",
            "subcategory":"Office",
            "type":"Public Place"
        }
    ],
    "sg:phone":"+1 540 463 4733",
    "sg:postcode":"24450",
    "sg:province":"VA",
    "wof:name":"Rockbridge County Extension",
    "wof:placetype":"venue"
},
  "geometry": {"coordinates":[-79.443624,37.783452],"type":"Point"}
}