{
  "type": "Feature",
  "properties": {
    "addr:full":"115 Spratley Mill Rd Dendron VA 23839",
    "addr:housenumber":"115",
    "addr:postcode":"23839",
    "addr:street":"Spratley Mill Rd",
    "iso:country":"US",
    "sg:address":"115 Spratley Mill Rd",
    "sg:city":"Dendron",
    "sg:classifiers":[
        {
            "category":"Travel",
            "subcategory":"Travel Agent",
            "type":"Entertainment"
        }
    ],
    "sg:phone":"+1 757 267 2507",
    "sg:postcode":"23839",
    "sg:province":"VA",
    "sg:tags":[
        "agency",
        "bureau"
    ],
    "wof:name":"Town & Country Tours",
    "wof:placetype":"venue"
},
  "geometry": {"coordinates":[-76.92568900000001,37.057992],"type":"Point"}
}