{
  "type": "Feature",
  "properties": {
    "addr:full":"5255 Waterway Dr Dumfries VA 22025",
    "addr:housenumber":"5255",
    "addr:postcode":"22025",
    "addr:street":"Waterway Dr",
    "iso:country":"US",
    "sg:address":"5255 Waterway Dr",
    "sg:city":"Dumfries",
    "sg:classifiers":[
        {
            "category":"Personal",
            "type":"Services"
        },
        {
            "category":"Sports & Exercise",
            "subcategory":"Gym",
            "type":"Entertainment"
        },
        {
            "category":"Arena",
            "subcategory":"Sports Club",
            "type":"Entertainment"
        }
    ],
    "sg:phone":"+1 703 590 9900",
    "sg:postcode":"22025",
    "sg:province":"VA",
    "sg:tags":[
        "trainer",
        "consultant",
        "gymnasium",
        "program",
        "health",
        "fitness",
        "physical"
    ],
    "wof:name":"Anytime Fitness",
    "wof:placetype":"venue"
},
  "geometry": {"coordinates":[-77.35983299999999,38.609619],"type":"Point"}
}