{
  "type": "Feature",
  "properties": {
    "iso:country":"US",
    "sg:address":"6209 Salisbury Dr",
    "sg:city":"Spotsylvania",
    "sg:classifiers":[
        {
            "category":"Retail",
            "subcategory":"Repair Shop",
            "type":"Services"
        }
    ],
    "sg:phone":"+1 540 710 1942",
    "sg:postcode":"22553",
    "sg:province":"VA",
    "wof:name":"Hawaiian Breezes Inc",
    "wof:placetype":"venue"
},
  "geometry": {"coordinates":[-77.542441,38.234166],"type":"Point"}
}