{
  "type": "Feature",
  "properties": {
    "addr:full":"16684 Leocrie Pl Woodbridge VA 22191",
    "addr:postcode":"16684;22191",
    "addr:street":"Pl",
    "iso:country":"US",
    "sg:address":"16684 Leocrie Pl",
    "sg:city":"Woodbridge",
    "sg:classifiers":[
        {
            "category":"Professional",
            "type":"Services"
        }
    ],
    "sg:phone":"+1 703 670 7999",
    "sg:postcode":"22191",
    "sg:province":"VA",
    "wof:name":"Tengesdal & Assoc LLC",
    "wof:placetype":"venue"
},
  "geometry": {"coordinates":[-77.269488,38.594972],"type":"Point"}
}