{
  "type": "Feature",
  "properties": {
    "addr:full":"8311 Bound Brook Ln Alexandria VA 22309",
    "addr:housenumber":"8311",
    "addr:postcode":"22309",
    "addr:street":"Bound Brook Ln",
    "iso:country":"US",
    "sg:address":"8311 Bound Brook Ln",
    "sg:city":"Alexandria",
    "sg:classifiers":[
        {
            "category":"Retail",
            "subcategory":"Laundry & Dry Cleaning",
            "type":"Services"
        }
    ],
    "sg:phone":"+1 703 799 5893",
    "sg:postcode":"22309",
    "sg:province":"VA",
    "sg:tags":[
        "cleaners",
        "rug",
        "carpet"
    ],
    "wof:name":"Chem-Dry Of Arlington",
    "wof:placetype":"venue"
},
  "geometry": {"coordinates":[-77.084929,38.731467],"type":"Point"}
}