{
  "type": "Feature",
  "properties": {
    "addr:full":"9520 N Run Rd Glen Allen VA 23060",
    "addr:housenumber":"9520",
    "addr:postcode":"23060",
    "addr:street":"N Run Rd",
    "iso:country":"US",
    "sg:address":"9520 N Run Rd",
    "sg:city":"Glen Allen",
    "sg:classifiers":[
        {
            "category":"Professional",
            "subcategory":"Business Services",
            "type":"Services"
        }
    ],
    "sg:phone":"+1 804 264 3996",
    "sg:postcode":"23060",
    "sg:province":"VA",
    "wof:name":"Q World Enterprises",
    "wof:placetype":"venue"
},
  "geometry": {"coordinates":[-77.472613,37.646097],"type":"Point"}
}