{
  "type": "Feature",
  "properties": {
    "iso:country":"US",
    "sg:address":"2317 Hanover Ave",
    "sg:city":"Richmond",
    "sg:classifiers":[
        {
            "category":"Professional",
            "type":"Services"
        }
    ],
    "sg:phone":"+1 804 358 4960",
    "sg:postcode":"23220",
    "sg:province":"VA",
    "wof:name":"Mr Leroy S Uguy",
    "wof:placetype":"venue"
},
  "geometry": {"coordinates":[-77.468788,37.554187],"type":"Point"}
}