{
  "type": "Feature",
  "properties": {
    "addr:full":"1900 George Washington Memorial Hwy Yorktown VA 23693",
    "addr:housenumber":"1900",
    "addr:postcode":"23693",
    "addr:street":"George Washington Memorial Hwy",
    "iso:country":"US",
    "sg:address":"1900 George Washington Memorial Hwy",
    "sg:city":"Yorktown",
    "sg:classifiers":[
        {
            "category":"Shopping",
            "type":"Retail Goods"
        }
    ],
    "sg:phone":"+1 757 599 7000",
    "sg:postcode":"23693",
    "sg:province":"VA",
    "sg:tags":[
        "home",
        "merchandise"
    ],
    "wof:name":"Great Atlanticpools and Spas",
    "wof:placetype":"venue"
},
  "geometry": {"coordinates":[-76.45616699999999,37.112693],"type":"Point"}
}