{
  "type": "Feature",
  "properties": {
    "addr:full":"2100 N 20th St Richmond VA 23223",
    "addr:housenumber":"2100",
    "addr:postcode":"23223",
    "addr:street":"N 20Th St",
    "iso:country":"US",
    "sg:address":"2100 N 20th St",
    "sg:city":"Richmond",
    "sg:classifiers":[
        {
            "category":"Personal",
            "subcategory":"Beauty Salon",
            "type":"Services"
        }
    ],
    "sg:phone":"+1 804 780 0871",
    "sg:postcode":"23223",
    "sg:province":"VA",
    "sg:tags":[
        "shop"
    ],
    "wof:name":"Shelton's Beauty Lounge",
    "wof:placetype":"venue"
},
  "geometry": {"coordinates":[-77.409001,37.551605],"type":"Point"}
}