{
  "type": "Feature",
  "properties": {
    "addr:full":"310 W Main St Tazewell VA 24651",
    "addr:housenumber":"310",
    "addr:postcode":"24651",
    "addr:street":"W Main St",
    "iso:country":"US",
    "sg:address":"310 W Main St",
    "sg:city":"Tazewell",
    "sg:classifiers":[
        {
            "category":"Professional",
            "subcategory":"Lawyer & Legal Services",
            "type":"Services"
        }
    ],
    "sg:phone":"+1 276 988 2475",
    "sg:postcode":"24651",
    "sg:province":"VA",
    "sg:tags":[
        "attorney"
    ],
    "wof:name":"William B Talty",
    "wof:placetype":"venue"
},
  "geometry": {"coordinates":[-81.529584,37.113524],"type":"Point"}
}