{
  "type": "Feature",
  "properties": {
    "iso:country":"US",
    "sg:address":"4 Savage Ct",
    "sg:city":"Portsmouth",
    "sg:classifiers":[
        {
            "category":"Building & Trades",
            "subcategory":"Plumbing",
            "type":"Services"
        }
    ],
    "sg:phone":"+1 757 629 8520",
    "sg:postcode":"23703",
    "sg:province":"VA",
    "sg:tags":[
        "contractor"
    ],
    "wof:name":"Wra Plumbing Services",
    "wof:placetype":"venue"
},
  "geometry": {"coordinates":[-76.38590000000001,36.870763],"type":"Point"}
}