{
  "type": "Feature",
  "properties": {
    "iso:country":"US",
    "sg:address":"2303 Hungary Rd",
    "sg:city":"Richmond",
    "sg:classifiers":[
        {
            "category":"Food & Beverages",
            "subcategory":"Groceries & Convenience Stores",
            "type":"Retail Goods"
        }
    ],
    "sg:phone":"+1 804 262 7265",
    "sg:postcode":"23228",
    "sg:province":"VA",
    "sg:tags":[
        "automotive",
        "repair"
    ],
    "wof:name":"G & R Citgo",
    "wof:placetype":"venue"
},
  "geometry": {"coordinates":[-77.495457,37.64181],"type":"Point"}
}