{
  "type": "Feature",
  "properties": {
    "addr:full":"4395 Albemarle Ct King George VA 22485",
    "addr:housenumber":"4395",
    "addr:postcode":"22485",
    "addr:street":"Albemarle Ct",
    "iso:country":"US",
    "sg:address":"4395 Albemarle Ct",
    "sg:city":"King George",
    "sg:classifiers":[
        {
            "category":"Arts & Performance",
            "subcategory":"Theater",
            "type":"Entertainment"
        }
    ],
    "sg:phone":"+1 540 663 4205",
    "sg:postcode":"22485",
    "sg:province":"VA",
    "sg:tags":[
        "group"
    ],
    "wof:name":"A To Z Music",
    "wof:placetype":"venue"
},
  "geometry": {"coordinates":[-77.070435,38.348151],"type":"Point"}
}