{
  "type": "Feature",
  "properties": {
    "addr:full":"6405 Yorkshire Dr Suffolk VA 23435",
    "addr:housenumber":"6405",
    "addr:postcode":"23435",
    "addr:street":"Yorkshire Dr",
    "iso:country":"US",
    "sg:address":"6405 Yorkshire Dr",
    "sg:city":"Suffolk",
    "sg:classifiers":[
        {
            "category":"Building & Trades",
            "subcategory":"Construction",
            "type":"Services"
        }
    ],
    "sg:phone":"+1 757 647 7912",
    "sg:postcode":"23435",
    "sg:province":"VA",
    "sg:tags":[
        "contractor"
    ],
    "wof:name":"J Napier Masonry",
    "wof:placetype":"venue"
},
  "geometry": {"coordinates":[-76.41627,36.888488],"type":"Point"}
}