{
  "type": "Feature",
  "properties": {
    "addr:full":"2900 Elm Ave Portsmouth VA 23704",
    "addr:housenumber":"2900",
    "addr:postcode":"23704",
    "addr:street":"Elm Ave",
    "iso:country":"US",
    "sg:address":"2900 Elm Ave",
    "sg:city":"Portsmouth",
    "sg:classifiers":[
        {
            "category":"Organizations",
            "subcategory":"Religious Organization",
            "type":"Services"
        }
    ],
    "sg:phone":"+1 757 393 4333",
    "sg:postcode":"23704",
    "sg:province":"VA",
    "wof:name":"New Life Deliverance Evangelis",
    "wof:placetype":"venue"
},
  "geometry": {"coordinates":[-76.31204,36.816233],"type":"Point"}
}