{
  "type": "Feature",
  "properties": {
    "addr:full":"7823 Bethany Ln Warrenton VA 20187",
    "addr:housenumber":"7823",
    "addr:postcode":"20187",
    "addr:street":"Bethany Ln",
    "iso:country":"US",
    "sg:address":"7823 Bethany Ln",
    "sg:city":"Warrenton",
    "sg:classifiers":[
        {
            "category":"Organizations",
            "subcategory":"Religious Organization",
            "type":"Services"
        }
    ],
    "sg:phone":"+1 540 347 5947",
    "sg:postcode":"20187",
    "sg:province":"VA",
    "sg:tags":[
        "clergy"
    ],
    "wof:name":"Steve Hohenberger",
    "wof:placetype":"venue"
},
  "geometry": {"coordinates":[-77.77666499999999,38.705898],"type":"Point"}
}