{
  "type": "Feature",
  "properties": {
    "addr:full":"4612 Harrison Rd Fredericksburg VA 22408",
    "addr:housenumber":"4612",
    "addr:postcode":"22408",
    "addr:street":"Harrison Rd",
    "iso:country":"US",
    "sg:address":"4612 Harrison Rd",
    "sg:city":"Fredericksburg",
    "sg:classifiers":[
        {
            "category":"Autos & Motor Vehicles",
            "subcategory":"Auto Supplies",
            "type":"Retail Goods"
        },
        {
            "category":"Wholesale",
            "subcategory":"Electrical",
            "type":"Manufacturing & Wholesale Goods"
        }
    ],
    "sg:phone":"+1 540 898 7233",
    "sg:postcode":"22408",
    "sg:province":"VA",
    "sg:tags":[
        "alarm",
        "burglar",
        "system"
    ],
    "wof:name":"Dynamark Security Center",
    "wof:placetype":"venue"
},
  "geometry": {"coordinates":[-77.494919,38.263973],"type":"Point"}
}