{
  "type": "Feature",
  "properties": {
    "iso:country":"US",
    "sg:address":"16607 Russell St",
    "sg:city":"St Paul",
    "sg:classifiers":[
        {
            "category":"Wholesale",
            "subcategory":"Tobacco Products",
            "type":"Manufacturing & Wholesale Goods"
        }
    ],
    "sg:phone":"+1 276 762 7312",
    "sg:postcode":"24283",
    "sg:province":"VA",
    "sg:tags":[
        "cigarette",
        "cigar",
        "dealer"
    ],
    "wof:name":"Hileman Tobacco Outlet",
    "wof:placetype":"venue"
},
  "geometry": {"coordinates":[-82.311133,36.904311],"type":"Point"}
}