{
  "type": "Feature",
  "properties": {
    "addr:full":"902 Northfield Ct Harrisonburg VA 22802",
    "addr:housenumber":"902",
    "addr:postcode":"22802",
    "addr:street":"Northfield Ct",
    "iso:country":"US",
    "sg:address":"902 Northfield Ct",
    "sg:city":"Harrisonburg",
    "sg:classifiers":[
        {
            "category":"Professional",
            "type":"Services"
        }
    ],
    "sg:phone":"+1 540 432 3800",
    "sg:postcode":"22802",
    "sg:province":"VA",
    "wof:name":"Genyame Transport LLC",
    "wof:placetype":"venue"
},
  "geometry": {"coordinates":[-78.85449699999999,38.456887],"type":"Point"}
}