{
  "type": "Feature",
  "properties": {
    "addr:full":"366 Summit Dr Covington VA 24426",
    "addr:housenumber":"366",
    "addr:postcode":"24426",
    "addr:street":"Summit Dr",
    "iso:country":"US",
    "sg:address":"366 Summit Dr",
    "sg:city":"Covington",
    "sg:classifiers":[
        {
            "category":"Freight",
            "type":"Transportation"
        }
    ],
    "sg:phone":"+1 540 747 1008",
    "sg:postcode":"24426",
    "sg:province":"VA",
    "sg:tags":[
        "operator",
        "trucking"
    ],
    "wof:name":"Potts Creek Trucking LLC",
    "wof:placetype":"venue"
},
  "geometry": {"coordinates":[-80.095078,37.662687],"type":"Point"}
}