{
  "type": "Feature",
  "properties": {
    "addr:full":"21 Brassie Ter Palmyra VA 22963",
    "addr:housenumber":"21",
    "addr:postcode":"22963",
    "addr:street":"Brassie Ter Palmyra",
    "iso:country":"US",
    "sg:address":"21 Brassie Ter",
    "sg:city":"Palmyra",
    "sg:classifiers":[
        {
            "category":"Restaurant",
            "type":"Food & Drink"
        }
    ],
    "sg:phone":"+1 434 589 5525",
    "sg:postcode":"22963",
    "sg:province":"VA",
    "wof:name":"Domino's Pizza",
    "wof:placetype":"venue"
},
  "geometry": {"coordinates":[-78.31696599999999,37.90654],"type":"Point"}
}