{
  "type": "Feature",
  "properties": {
    "addr:full":"1405 Kiln Creek Pkwy Newport News VA 23602",
    "addr:housenumber":"1405",
    "addr:postcode":"23602",
    "addr:street":"Kiln Creek Pkwy",
    "iso:country":"US",
    "sg:address":"1405 Kiln Creek Pkwy",
    "sg:city":"Newport News",
    "sg:classifiers":[
        {
            "category":"Retail",
            "subcategory":"Veterinary Services",
            "type":"Services"
        }
    ],
    "sg:phone":"+1 757 989 8900",
    "sg:postcode":"23602",
    "sg:province":"VA",
    "sg:website":"www.specialvet.com",
    "wof:name":"Veterinary Internal Medicine",
    "wof:placetype":"venue"
},
  "geometry": {"coordinates":[-76.486586,37.120675],"type":"Point"}
}