{
  "type": "Feature",
  "properties": {
    "addr:full":"1609 Cedar Hill Rd Charlottesville VA 22901",
    "addr:housenumber":"1609",
    "addr:postcode":"22901",
    "addr:street":"Cedar Hill Rd",
    "iso:country":"US",
    "sg:address":"1609 Cedar Hill Rd",
    "sg:city":"Charlottesville",
    "sg:classifiers":[
        {
            "category":"Organizations",
            "subcategory":"Community Association",
            "type":"Services"
        }
    ],
    "sg:phone":"+1 434 293 5682",
    "sg:postcode":"22901",
    "sg:province":"VA",
    "wof:name":"International Ordr of Job",
    "wof:placetype":"venue"
},
  "geometry": {"coordinates":[-78.49919300000001,38.059034],"type":"Point"}
}