{
  "type": "Feature",
  "properties": {
    "addr:full":"286 Kelly St Harrisonburg VA 22802",
    "addr:housenumber":"286",
    "addr:postcode":"22802",
    "addr:street":"Kelly St",
    "iso:country":"US",
    "sg:address":"286 Kelly St",
    "sg:city":"Harrisonburg",
    "sg:classifiers":[
        {
            "category":"Government",
            "subcategory":"Office",
            "type":"Public Place"
        }
    ],
    "sg:phone":"+1 540 434 7386",
    "sg:postcode":"22802",
    "sg:province":"VA",
    "sg:tags":[
        "government-united",
        "state"
    ],
    "wof:name":"Harrisonburg Redevelopment & Housing Authority",
    "wof:placetype":"venue"
},
  "geometry": {"coordinates":[-78.859925,38.453906],"type":"Point"}
}