{
  "type": "Feature",
  "properties": {
    "iso:country":"US",
    "sg:address":"1945 Puddledock Rd",
    "sg:city":"Petersburg",
    "sg:classifiers":[
        {
            "category":"Manufacturing",
            "subcategory":"Paper Products",
            "type":"Manufacturing & Wholesale Goods"
        }
    ],
    "sg:phone":"+1 804 862 4155",
    "sg:postcode":"23803",
    "sg:province":"VA",
    "sg:tags":[
        "converted",
        "mfg"
    ],
    "wof:name":"Fritz Ken Tooling & Design",
    "wof:placetype":"venue"
},
  "geometry": {"coordinates":[-77.372455,37.239621],"type":"Point"}
}