{
  "type": "Feature",
  "properties": {
    "addr:full":"10159 Clarkton Rd Nathalie VA 24577",
    "addr:housenumber":"10159",
    "addr:postcode":"24577",
    "addr:street":"Clarkton Rd",
    "iso:country":"US",
    "sg:address":"10159 Clarkton Rd",
    "sg:city":"Nathalie",
    "sg:classifiers":[
        {
            "category":"Shopping",
            "subcategory":"Discount & Variety Stores",
            "type":"Retail Goods"
        }
    ],
    "sg:phone":"+1 434 376 2451",
    "sg:postcode":"24577",
    "sg:province":"VA",
    "wof:name":"John Hubbard Store",
    "wof:placetype":"venue"
},
  "geometry": {"coordinates":[-78.945808,36.979495],"type":"Point"}
}