{
  "type": "Feature",
  "properties": {
    "addr:full":"11922 Fair Oaks Mall Fairfax VA 22033",
    "addr:housenumber":"11922",
    "addr:postcode":"22033",
    "addr:street":"Fair Oaks Mall",
    "iso:country":"US",
    "sg:address":"11922 Fair Oaks Mall",
    "sg:city":"Fairfax",
    "sg:classifiers":[
        {
            "category":"Shopping",
            "subcategory":"Clothing, Apparel, & Fashions",
            "type":"Retail Goods"
        }
    ],
    "sg:phone":"+1 703 359 3524",
    "sg:postcode":"22033",
    "sg:province":"VA",
    "wof:name":"Banana Republic",
    "wof:placetype":"venue"
},
  "geometry": {"coordinates":[-77.359003,38.865202],"type":"Point"}
}