{
  "type": "Feature",
  "properties": {
    "addr:full":"2257 Senseney Ln Falls Church VA 22043",
    "addr:housenumber":"2257",
    "addr:postcode":"22043",
    "addr:street":"Senseney Ln",
    "iso:country":"US",
    "sg:address":"2257 Senseney Ln",
    "sg:city":"Falls Church",
    "sg:classifiers":[
        {
            "category":"Professional",
            "subcategory":"Computer Services",
            "type":"Services"
        }
    ],
    "sg:phone":"+1 703 876 1635",
    "sg:postcode":"22043",
    "sg:province":"VA",
    "sg:tags":[
        "programing",
        "custom"
    ],
    "wof:name":"Intelisoft Inc",
    "wof:placetype":"venue"
},
  "geometry": {"coordinates":[-77.211214,38.895762],"type":"Point"}
}