{
  "type": "Feature",
  "properties": {
    "addr:full":"63 Breezewood Rd Collinsville VA 24078",
    "addr:housenumber":"63",
    "addr:postcode":"24078",
    "addr:street":"Breezewood Rd",
    "iso:country":"US",
    "sg:address":"63 Breezewood Rd",
    "sg:city":"Collinsville",
    "sg:classifiers":[
        {
            "category":"Professional",
            "subcategory":"Management & Consulting",
            "type":"Services"
        }
    ],
    "sg:phone":"+1 276 647 8018",
    "sg:postcode":"24078",
    "sg:province":"VA",
    "wof:name":"Peak Consulting",
    "wof:placetype":"venue"
},
  "geometry": {"coordinates":[-79.898135,36.735789],"type":"Point"}
}