{
  "type": "Feature",
  "properties": {
    "addr:full":"5510 S Columbia Pike Arlington VA 22204",
    "addr:housenumber":"5510",
    "addr:postcode":"22204",
    "addr:street":"S Columbia Pike",
    "iso:country":"US",
    "sg:address":"5510 S Columbia Pike",
    "sg:city":"Arlington",
    "sg:classifiers":[
        {
            "category":"Professional",
            "subcategory":"Management & Consulting",
            "type":"Services"
        }
    ],
    "sg:phone":"+1 703 998 6804",
    "sg:postcode":"22204",
    "sg:province":"VA",
    "wof:name":"N Y P & Associates",
    "wof:placetype":"venue"
},
  "geometry": {"coordinates":[-77.12012799999999,38.853305],"type":"Point"}
}