{
  "type": "Feature",
  "properties": {
    "addr:full":"1101 Grand Hamptons Dr Herndon VA 20170",
    "addr:housenumber":"1101",
    "addr:postcode":"20170",
    "addr:street":"Grand Hamptons Dr",
    "iso:country":"US",
    "sg:address":"1101 Grand Hamptons Dr",
    "sg:city":"Herndon",
    "sg:classifiers":[
        {
            "category":"Building & Trades",
            "subcategory":"Construction",
            "type":"Services"
        }
    ],
    "sg:phone":"+1 703 406 9455",
    "sg:postcode":"20170",
    "sg:province":"VA",
    "sg:tags":[
        "general",
        "contractor"
    ],
    "wof:name":"Daniel Development Inc",
    "wof:placetype":"venue"
},
  "geometry": {"coordinates":[-77.368083,39.00709],"type":"Point"}
}