{
  "type": "Feature",
  "properties": {
    "addr:full":"13258 Updike Dr Culpeper VA 22701",
    "addr:housenumber":"13258",
    "addr:postcode":"22701",
    "addr:street":"Updike Dr",
    "iso:country":"US",
    "sg:address":"13258 Updike Dr",
    "sg:city":"Culpeper",
    "sg:classifiers":[
        {
            "category":"Retail",
            "subcategory":"Auto Rental",
            "type":"Services"
        }
    ],
    "sg:phone":"+1 540 825 8791",
    "sg:postcode":"22701",
    "sg:province":"VA",
    "sg:tags":[
        "renting",
        "leasing",
        "trailer"
    ],
    "wof:name":"Efficient Roll Off & Recycling",
    "wof:placetype":"venue"
},
  "geometry": {"coordinates":[-78.083676,38.518893],"type":"Point"}
}