{
  "type": "Feature",
  "properties": {
    "addr:full":"7109 Hadlow Dr Springfield VA 22152",
    "addr:housenumber":"7109",
    "addr:postcode":"22152",
    "addr:street":"Hadlow Dr",
    "iso:country":"US",
    "sg:address":"7109 Hadlow Dr",
    "sg:city":"Springfield",
    "sg:classifiers":[
        {
            "category":"Professional",
            "subcategory":"Business Services",
            "type":"Services"
        }
    ],
    "sg:phone":"+1 703 451 0726",
    "sg:postcode":"22152",
    "sg:province":"VA",
    "wof:name":"Triangle Assoc",
    "wof:placetype":"venue"
},
  "geometry": {"coordinates":[-77.238017,38.761308],"type":"Point"}
}