{
  "type": "Feature",
  "properties": {
    "iso:country":"US",
    "sg:address":"7118 Columbia Pike",
    "sg:city":"Annandale",
    "sg:classifiers":[
        {
            "category":"Restaurant",
            "type":"Food & Drink"
        }
    ],
    "sg:phone":"+1 703 642 3418",
    "sg:postcode":"22003",
    "sg:province":"VA",
    "wof:name":"Young's Snack",
    "wof:placetype":"venue"
},
  "geometry": {"coordinates":[-77.191925,38.832233],"type":"Point"}
}