{
  "type": "Feature",
  "properties": {
    "iso:country":"US",
    "sg:address":"10404 Patterson Ave",
    "sg:city":"Richmond",
    "sg:classifiers":[
        {
            "category":"Real Estate",
            "subcategory":"Real Estate Agent",
            "type":"Services"
        }
    ],
    "sg:phone":"+1 804 741 0234",
    "sg:postcode":"23238",
    "sg:province":"VA",
    "sg:tags":[
        "broker"
    ],
    "wof:name":"Help-U-Sell",
    "wof:placetype":"venue"
},
  "geometry": {"coordinates":[-77.607079,37.59695],"type":"Point"}
}