{
  "type": "Feature",
  "properties": {
    "addr:full":"105 Westphal Dr Hampton VA 23669",
    "addr:housenumber":"105",
    "addr:postcode":"23669",
    "addr:street":"Westphal Dr",
    "iso:country":"US",
    "sg:address":"105 Westphal Dr",
    "sg:city":"Hampton",
    "sg:classifiers":[
        {
            "category":"Building & Trades",
            "subcategory":"Construction",
            "type":"Services"
        }
    ],
    "sg:phone":"+1 757 850 3889",
    "sg:postcode":"23669",
    "sg:province":"VA",
    "sg:tags":[
        "home",
        "general",
        "family",
        "contractor"
    ],
    "wof:name":"Boston Home Improvements",
    "wof:placetype":"venue"
},
  "geometry": {"coordinates":[-76.338571,37.059311],"type":"Point"}
}