{
  "type": "Feature",
  "properties": {
    "addr:full":"201 Hanbury Rd E Chesapeake VA 23322",
    "addr:housenumber":"201",
    "addr:postcode":"23322",
    "addr:street":"Hanbury Rd E",
    "iso:country":"US",
    "sg:address":"201 Hanbury Rd E",
    "sg:city":"Chesapeake",
    "sg:classifiers":[
        {
            "category":"Wholesale",
            "subcategory":"Medical Equipment & Supplies",
            "type":"Manufacturing & Wholesale Goods"
        },
        {
            "category":"Shopping",
            "subcategory":"Beauty & Cosmetics",
            "type":"Retail Goods"
        },
        {
            "category":"Food & Beverages",
            "subcategory":"Specialty",
            "type":"Retail Goods"
        },
        {
            "category":"Shopping",
            "subcategory":"Computers & Home Electronics",
            "type":"Retail Goods"
        },
        {
            "category":"Shopping",
            "subcategory":"Optical Goods",
            "type":"Retail Goods"
        },
        {
            "category":"Personal",
            "subcategory":"Skin Care",
            "type":"Services"
        },
        {
            "category":"Manufacturing",
            "subcategory":"Chemicals & Compounds",
            "type":"Manufacturing & Wholesale Goods"
        },
        {
            "category":"Retail",
            "subcategory":"Photofinishing",
            "type":"Services"
        },
        {
            "category":"Shopping",
            "subcategory":"Pharmacy",
            "type":"Retail Goods"
        },
        {
            "category":"Health Services",
            "subcategory":"Optometrist",
            "type":"Services"
        },
        {
            "category":"Food & Beverages",
            "subcategory":"Groceries & Convenience Stores",
            "type":"Retail Goods"
        }
    ],
    "sg:phone":"+1 757 482 2563",
    "sg:postcode":"23322",
    "sg:province":"VA",
    "sg:tags":[
        "pharmaceutical",
        "product",
        "photo",
        "wheelchair",
        "vitamin",
        "perfume",
        "lens",
        "supplement",
        "contact",
        "wellness",
        "finishing",
        "consumer"
    ],
    "sg:website":"http://www.walgreens.com/default.jsp?ec=iyp_yellowpages_trademark",
    "wof:name":"Walgreens Pharmacies",
    "wof:placetype":"venue"
},
  "geometry": {"coordinates":[-76.224869,36.687778],"type":"Point"}
}