{
  "type": "Feature",
  "properties": {
    "addr:full":"360 Tim Warren Rd Bristol VA 37620",
    "addr:housenumber":"360",
    "addr:postcode":"37620",
    "addr:street":"Tim Warren Rd",
    "iso:country":"US",
    "sg:address":"360 Tim Warren Rd",
    "sg:city":"Bristol",
    "sg:classifiers":[
        {
            "category":"Farming",
            "subcategory":"Livestock Farm",
            "type":"Manufacturing & Wholesale Goods"
        }
    ],
    "sg:phone":"+1 423 878 2191",
    "sg:postcode":"37620",
    "sg:province":"VA",
    "sg:tags":[
        "animal",
        "general"
    ],
    "wof:name":"Robert D McKay",
    "wof:placetype":"venue"
},
  "geometry": {"coordinates":[-82.160488,36.516462],"type":"Point"}
}