{
  "type": "Feature",
  "properties": {
    "addr:full":"8496 Tyco Rd Ste A Vienna VA 22182",
    "addr:housenumber":"8496",
    "addr:postcode":"22182",
    "addr:street":"Tyco Rd Ste A",
    "iso:country":"US",
    "sg:address":"8496 Tyco Rd Ste A",
    "sg:city":"Vienna",
    "sg:classifiers":[
        {
            "category":"Deli",
            "type":"Food & Drink"
        }
    ],
    "sg:phone":"+1 703 734 6950",
    "sg:postcode":"22182",
    "sg:province":"VA",
    "wof:name":"Tyco Deli",
    "wof:placetype":"venue"
},
  "geometry": {"coordinates":[-77.23840300000001,38.9314],"type":"Point"}
}