{
  "type": "Feature",
  "properties": {
    "addr:full":"2737 Shenandoah Ave NW Roanoke VA 24017",
    "addr:housenumber":"2737",
    "addr:postcode":"24017",
    "addr:street":"Shenandoah Ave Nw",
    "iso:country":"US",
    "sg:address":"2737 Shenandoah Ave NW",
    "sg:city":"Roanoke",
    "sg:classifiers":[
        {
            "category":"Building & Trades",
            "subcategory":"Construction",
            "type":"Services"
        }
    ],
    "sg:phone":"+1 540 345 0519",
    "sg:postcode":"24017",
    "sg:province":"VA",
    "sg:tags":[
        "insulation",
        "heat",
        "contractor"
    ],
    "wof:name":"Walker Insulation",
    "wof:placetype":"venue"
},
  "geometry": {"coordinates":[-79.984782,37.282675],"type":"Point"}
}