{
  "type": "Feature",
  "properties": {
    "addr:full":"6225 John Barton Payne Rd Marshall VA 20115",
    "addr:housenumber":"6225",
    "addr:postcode":"20115",
    "addr:street":"John Barton Payne Rd",
    "iso:country":"US",
    "sg:address":"6225 John Barton Payne Rd",
    "sg:city":"Marshall",
    "sg:classifiers":[
        {
            "category":"Wholesale",
            "subcategory":"Fruits & Vegetables",
            "type":"Manufacturing & Wholesale Goods"
        }
    ],
    "sg:phone":"+1 540 364 1461",
    "sg:postcode":"20115",
    "sg:province":"VA",
    "wof:name":"S McConnell Farm",
    "wof:placetype":"venue"
},
  "geometry": {"coordinates":[-77.94547799999999,38.779835],"type":"Point"}
}