{
  "type": "Feature",
  "properties": {
    "iso:country":"US",
    "sg:address":"51 Thunder Rd",
    "sg:city":"Front Royal",
    "sg:classifiers":[
        {
            "category":"Professional",
            "subcategory":"Management & Consulting",
            "type":"Services"
        }
    ],
    "sg:phone":"+1 240 994 3775",
    "sg:postcode":"22630",
    "sg:province":"VA",
    "sg:tags":[
        "resource",
        "human",
        "staffing"
    ],
    "wof:name":"Itmomentumnet",
    "wof:placetype":"venue"
},
  "geometry": {"coordinates":[-78.27028300000001,38.871665],"type":"Point"}
}