{
  "type": "Feature",
  "properties": {
    "addr:full":"5717 Edsall Rd Ste A Alexandria VA 22304",
    "addr:housenumber":"5717",
    "addr:postcode":"22304",
    "addr:street":"Edsall Rd Ste A",
    "iso:country":"US",
    "sg:address":"5717 Edsall Rd Ste A",
    "sg:city":"Alexandria",
    "sg:classifiers":[
        {
            "category":"Building & Trades",
            "subcategory":"Construction",
            "type":"Services"
        }
    ],
    "sg:phone":"+1 703 751 7501",
    "sg:postcode":"22304",
    "sg:province":"VA",
    "sg:tags":[
        "system",
        "contractor",
        "air conditioning"
    ],
    "wof:name":"Allied Equipment & Supplies",
    "wof:placetype":"venue"
},
  "geometry": {"coordinates":[-77.131106,38.807663],"type":"Point"}
}