{
  "type": "Feature",
  "properties": {
    "iso:country":"US",
    "sg:address":"3308 Pleasants Rd",
    "sg:city":"Powhatan",
    "sg:classifiers":[
        {
            "category":"Building & Trades",
            "subcategory":"Construction",
            "type":"Services"
        }
    ],
    "sg:phone":"+1 804 598 4506",
    "sg:postcode":"23139",
    "sg:province":"VA",
    "sg:tags":[
        "contractor"
    ],
    "wof:name":"Davis & Son Masonry Inc",
    "wof:placetype":"venue"
},
  "geometry": {"coordinates":[-77.839598,37.608236],"type":"Point"}
}