{
  "type": "Feature",
  "properties": {
    "iso:country":"US",
    "sg:address":"12448 Petersburg St",
    "sg:city":"Chester",
    "sg:classifiers":[
        {
            "category":"Retail",
            "subcategory":"Self-service Laundry",
            "type":"Services"
        }
    ],
    "sg:phone":"+1 804 751 0229",
    "sg:postcode":"23831",
    "sg:province":"VA",
    "sg:tags":[
        "coin"
    ],
    "wof:name":"Prime Laundromat",
    "wof:placetype":"venue"
},
  "geometry": {"coordinates":[-77.43211599999999,37.351732],"type":"Point"}
}