{
  "type": "Feature",
  "properties": {
    "iso:country":"US",
    "sg:address":"5562 Neddleton Ave",
    "sg:city":"Dale City",
    "sg:classifiers":[
        {
            "category":"Food & Beverages",
            "subcategory":"Candy",
            "type":"Retail Goods"
        }
    ],
    "sg:phone":"+1 703 680 3470",
    "sg:postcode":"22193",
    "sg:province":"VA",
    "sg:tags":[
        "confectionery"
    ],
    "wof:name":"Tallent's Treasures",
    "wof:placetype":"venue"
},
  "geometry": {"coordinates":[-77.372259,38.668331],"type":"Point"}
}