{
  "type": "Feature",
  "properties": {
    "addr:full":"3828 Virginia Beach Blvd Virginia Beach VA 23452",
    "addr:housenumber":"3828",
    "addr:postcode":"23452",
    "addr:street":"Virginia Beach Blvd",
    "iso:country":"US",
    "sg:address":"3828 Virginia Beach Blvd",
    "sg:city":"Virginia Beach",
    "sg:classifiers":[
        {
            "category":"Organizations",
            "subcategory":"Religious Organization",
            "type":"Services"
        }
    ],
    "sg:phone":"+1 757 631 8300",
    "sg:postcode":"23452",
    "sg:province":"VA",
    "sg:tags":[
        "church"
    ],
    "wof:name":"Revival Temple Of Christ",
    "wof:placetype":"venue"
},
  "geometry": {"coordinates":[-76.108389,36.840185],"type":"Point"}
}