{
  "type": "Feature",
  "properties": {
    "iso:country":"US",
    "sg:address":"150 W Brambleton Ave",
    "sg:city":"Norfolk",
    "sg:classifiers":[
        {
            "category":"Manufacturing",
            "subcategory":"Printing",
            "type":"Manufacturing & Wholesale Goods"
        }
    ],
    "sg:phone":"+1 757 222 3854",
    "sg:postcode":"23510",
    "sg:province":"VA",
    "sg:tags":[
        "periodical"
    ],
    "wof:name":"Home Search Magazine",
    "wof:placetype":"venue"
},
  "geometry": {"coordinates":[-76.290604,36.854281],"type":"Point"}
}