{
  "type": "Feature",
  "properties": {
    "addr:full":"301 Rivers Bend Cir Chester VA 23836",
    "addr:housenumber":"301",
    "addr:postcode":"23836",
    "addr:street":"Rivers Bend Cir",
    "iso:country":"US",
    "sg:address":"301 Rivers Bend Cir",
    "sg:city":"Chester",
    "sg:classifiers":[
        {
            "category":"Museum",
            "type":"Entertainment"
        }
    ],
    "sg:phone":"+1 804 530 2055",
    "sg:postcode":"23836",
    "sg:province":"VA",
    "sg:tags":[
        "gallery",
        "merchandise"
    ],
    "wof:name":"Classic Distinctions",
    "wof:placetype":"venue"
},
  "geometry": {"coordinates":[-77.36765699999999,37.355545],"type":"Point"}
}