{
  "type": "Feature",
  "properties": {
    "iso:country":"US",
    "sg:address":"14151 Park Meadow Dr",
    "sg:city":"Chantilly",
    "sg:classifiers":[
        {
            "category":"Food & Beverages",
            "subcategory":"Groceries & Convenience Stores",
            "type":"Retail Goods"
        },
        {
            "category":"Restaurant",
            "type":"Food & Drink"
        }
    ],
    "sg:phone":"+1 703 263 9000",
    "sg:postcode":"20151",
    "sg:province":"VA",
    "sg:tags":[
        "delicatessen"
    ],
    "wof:name":"Sam's Deli",
    "wof:placetype":"venue"
},
  "geometry": {"coordinates":[-77.43701799999999,38.87069],"type":"Point"}
}