{
  "type": "Feature",
  "properties": {
    "addr:full":"400 Old Locke Ln Richmond VA 23226",
    "addr:housenumber":"400",
    "addr:postcode":"23226",
    "addr:street":"Old Locke Ln",
    "iso:country":"US",
    "sg:address":"400 Old Locke Ln",
    "sg:city":"Richmond",
    "sg:classifiers":[
        {
            "category":"Professional",
            "type":"Services"
        }
    ],
    "sg:phone":"+1 804 353 6711",
    "sg:postcode":"23226",
    "sg:province":"VA",
    "wof:name":"Lawson Company Incorporated",
    "wof:placetype":"venue"
},
  "geometry": {"coordinates":[-77.51027499999999,37.557235],"type":"Point"}
}