{
  "type": "Feature",
  "properties": {
    "addr:full":"1025 N Fillmore St Arlington VA 22201",
    "addr:housenumber":"1025",
    "addr:postcode":"22201",
    "addr:street":"N Fillmore St",
    "iso:country":"US",
    "sg:address":"1025 N Fillmore St",
    "sg:city":"Arlington",
    "sg:classifiers":[
        {
            "category":"Professional",
            "subcategory":"Advertising",
            "type":"Services"
        },
        {
            "category":"Internet Cafe",
            "subcategory":"None",
            "type":"Food & Drink"
        },
        {
            "category":"Communications",
            "subcategory":"Film & Video Production",
            "type":"Services"
        },
        {
            "category":"Professional",
            "subcategory":"Computer Services",
            "type":"Services"
        }
    ],
    "sg:phone":"+1 888 466 7774",
    "sg:postcode":"22201",
    "sg:province":"VA",
    "sg:tags":[
        "product",
        "medium",
        "marketing",
        "online",
        "directory",
        "guide",
        "interactive"
    ],
    "sg:website":"http://www.7mainstreet.com",
    "wof:name":"7Mainstreet",
    "wof:placetype":"venue"
},
  "geometry": {"coordinates":[-77.092714,38.884518],"type":"Point"}
}