{
  "type": "Feature",
  "properties": {
    "addr:full":"6785 Springfield Mall Springfield VA 22150",
    "addr:housenumber":"6785",
    "addr:postcode":"22150",
    "addr:street":"Springfield Mall",
    "iso:country":"US",
    "sg:address":"6785 Springfield Mall",
    "sg:city":"Springfield",
    "sg:classifiers":[
        {
            "category":"Fast Food",
            "type":"Food & Drink"
        },
        {
            "category":"Restaurant",
            "type":"Food & Drink"
        }
    ],
    "sg:phone":"+1 703 922 4574",
    "sg:postcode":"22150",
    "sg:province":"VA",
    "sg:tags":[
        "american",
        "hot",
        "hamburger",
        "dog"
    ],
    "sg:website":"http://www.bk.com",
    "wof:name":"Burger King",
    "wof:placetype":"venue"
},
  "geometry": {"coordinates":[-77.176388,38.772337],"type":"Point"}
}