{
  "type": "Feature",
  "properties": {
    "iso:country":"US",
    "sg:address":"2305 Pacific Ave",
    "sg:city":"Virginia Beach",
    "sg:classifiers":[
        {
            "category":"Professional",
            "type":"Services"
        }
    ],
    "sg:phone":"+1 757 491 1830",
    "sg:postcode":"23451",
    "sg:province":"VA",
    "wof:name":"Ocean Cove",
    "wof:placetype":"venue"
},
  "geometry": {"coordinates":[-75.977281,36.851909],"type":"Point"}
}