{
  "type": "Feature",
  "properties": {
    "addr:full":"924 Wilborn Ave South Boston VA 24592",
    "addr:housenumber":"924",
    "addr:postcode":"24592",
    "addr:street":"Wilborn Ave",
    "iso:country":"US",
    "sg:address":"924 Wilborn Ave",
    "sg:city":"South Boston",
    "sg:classifiers":[
        {
            "category":"Banks & Credit Unions",
            "subcategory":"Bank",
            "type":"Services"
        }
    ],
    "sg:phone":"+1 434 575 5066",
    "sg:postcode":"24592",
    "sg:province":"VA",
    "sg:tags":[
        "cashing",
        "check"
    ],
    "wof:name":"King Cash Advance",
    "wof:placetype":"venue"
},
  "geometry": {"coordinates":[-78.904702,36.701134],"type":"Point"}
}