{
  "type": "Feature",
  "properties": {
    "addr:full":"212 Mountain Laurel Dr Lynchburg VA 24503",
    "addr:housenumber":"212",
    "addr:postcode":"24503",
    "addr:street":"Mountain Laurel Dr",
    "iso:country":"US",
    "sg:address":"212 Mountain Laurel Dr",
    "sg:city":"Lynchburg",
    "sg:classifiers":[
        {
            "category":"Professional",
            "subcategory":"Management & Consulting",
            "type":"Services"
        }
    ],
    "sg:phone":"+1 434 942 3954",
    "sg:postcode":"24503",
    "sg:province":"VA",
    "sg:tags":[
        "business"
    ],
    "wof:name":"Kerns & Assoc",
    "wof:placetype":"venue"
},
  "geometry": {"coordinates":[-79.252196,37.448965],"type":"Point"}
}