{
  "type": "Feature",
  "properties": {
    "addr:full":"320 Wexford Dr Virginia Beach VA 23462",
    "addr:housenumber":"320",
    "addr:postcode":"23462",
    "addr:street":"Wexford Dr",
    "iso:country":"US",
    "sg:address":"320 Wexford Dr",
    "sg:city":"Virginia Beach",
    "sg:classifiers":[
        {
            "category":"Professional",
            "type":"Services"
        }
    ],
    "sg:phone":"+1 757 227 6706",
    "sg:postcode":"23462",
    "sg:province":"VA",
    "sg:tags":[
        "establishment"
    ],
    "wof:name":"J Judernatz",
    "wof:placetype":"venue"
},
  "geometry": {"coordinates":[-76.168156,36.851166],"type":"Point"}
}