{
  "type": "Feature",
  "properties": {
    "iso:country":"US",
    "sg:address":"918 Monticello Rd",
    "sg:city":"Charlottesville",
    "sg:classifiers":[
        {
            "category":"Professional",
            "subcategory":"Computer Services",
            "type":"Services"
        }
    ],
    "sg:phone":"+1 434 979 7979",
    "sg:postcode":"22902",
    "sg:province":"VA",
    "sg:tags":[
        "repair"
    ],
    "sg:website":"www.arcane-tech.com",
    "wof:name":"Arcane Technologies Inc",
    "wof:placetype":"venue"
},
  "geometry": {"coordinates":[-78.473449,38.023286],"type":"Point"}
}