{
  "type": "Feature",
  "properties": {
    "addr:full":"1035 W Main St Wytheville VA 24382",
    "addr:housenumber":"1035",
    "addr:postcode":"24382",
    "addr:street":"W Main St",
    "iso:country":"US",
    "sg:address":"1035 W Main St",
    "sg:city":"Wytheville",
    "sg:classifiers":[
        {
            "category":"Health Services",
            "subcategory":"Health Practitioner",
            "type":"Services"
        }
    ],
    "sg:phone":"+1 276 228 6900",
    "sg:postcode":"24382",
    "sg:province":"VA",
    "sg:tags":[
        "psychologist"
    ],
    "wof:name":"Southwestern Virginia Counsel",
    "wof:placetype":"venue"
},
  "geometry": {"coordinates":[-81.092237,36.943034],"type":"Point"}
}