{
  "type": "Feature",
  "properties": {
    "addr:full":"245 Culloden St Suffolk VA 23434",
    "addr:housenumber":"245",
    "addr:postcode":"23434",
    "addr:street":"Culloden St",
    "iso:country":"US",
    "sg:address":"245 Culloden St",
    "sg:city":"Suffolk",
    "sg:classifiers":[
        {
            "category":"Professional",
            "subcategory":"Management & Consulting",
            "type":"Services"
        }
    ],
    "sg:phone":"+1 757 925 3392",
    "sg:postcode":"23434",
    "sg:province":"VA",
    "wof:name":"ServiceMaster",
    "wof:placetype":"venue"
},
  "geometry": {"coordinates":[-76.58069399999999,36.72331],"type":"Point"}
}