{
  "type": "Feature",
  "properties": {
    "iso:country":"US",
    "sg:address":"610 Musket Ct",
    "sg:city":"Newport News",
    "sg:classifiers":[
        {
            "category":"Building & Trades",
            "subcategory":"Landscaping Services",
            "type":"Services"
        }
    ],
    "sg:phone":"+1 757 881 9581",
    "sg:postcode":"23602",
    "sg:province":"VA",
    "wof:name":"Larry S Nicholas",
    "wof:placetype":"venue"
},
  "geometry": {"coordinates":[-76.484943,37.111324],"type":"Point"}
}