{
  "type": "Feature",
  "properties": {
    "addr:full":"7824 Warwick Blvd Newport News VA 23607",
    "addr:housenumber":"7824",
    "addr:postcode":"23607",
    "addr:street":"Warwick Blvd",
    "iso:country":"US",
    "sg:address":"7824 Warwick Blvd",
    "sg:city":"Newport News",
    "sg:classifiers":[
        {
            "category":"Restaurant",
            "type":"Food & Drink"
        }
    ],
    "sg:phone":"+1 757 244 3054",
    "sg:postcode":"23607",
    "sg:province":"VA",
    "wof:name":"KATT",
    "wof:placetype":"venue"
},
  "geometry": {"coordinates":[-76.451003,37.019059],"type":"Point"}
}