{
  "type": "Feature",
  "properties": {
    "addr:full":"4520 Old Buckingham Rd Powhatan VA 23139",
    "addr:housenumber":"4520",
    "addr:postcode":"23139",
    "addr:street":"Old Buckingham Rd",
    "iso:country":"US",
    "sg:address":"4520 Old Buckingham Rd",
    "sg:city":"Powhatan",
    "sg:classifiers":[
        {
            "category":"Professional",
            "subcategory":"Business Services",
            "type":"Services"
        }
    ],
    "sg:phone":"+1 804 598 5817",
    "sg:postcode":"23139",
    "sg:province":"VA",
    "wof:name":"Tilman Auctions",
    "wof:placetype":"venue"
},
  "geometry": {"coordinates":[-77.96381700000001,37.521862],"type":"Point"}
}