{
  "type": "Feature",
  "properties": {
    "addr:full":"1172 Richmond Rd Charlottesville VA 22911",
    "addr:housenumber":"1172",
    "addr:postcode":"22911",
    "addr:street":"Richmond Rd",
    "iso:country":"US",
    "sg:address":"1172 Richmond Rd",
    "sg:city":"Charlottesville",
    "sg:classifiers":[
        {
            "category":"Food & Beverages",
            "subcategory":"Groceries & Convenience Stores",
            "type":"Retail Goods"
        }
    ],
    "sg:phone":"+1 434 295 1687",
    "sg:postcode":"22911",
    "sg:province":"VA",
    "wof:name":"Wilco Gas Station",
    "wof:placetype":"venue"
},
  "geometry": {"coordinates":[-78.457588,38.034129],"type":"Point"}
}