{
  "type": "Feature",
  "properties": {
    "addr:full":"200 Westmoreland Ct Chesapeake VA 23320",
    "addr:housenumber":"200",
    "addr:postcode":"23320",
    "addr:street":"Westmoreland Ct",
    "iso:country":"US",
    "sg:address":"200 Westmoreland Ct",
    "sg:city":"Chesapeake",
    "sg:classifiers":[
        {
            "category":"Organizations",
            "subcategory":"Religious Organization",
            "type":"Services"
        }
    ],
    "sg:phone":"+1 757 523 9249",
    "sg:postcode":"23320",
    "sg:province":"VA",
    "wof:name":"Covenant Partners Inc",
    "wof:placetype":"venue"
},
  "geometry": {"coordinates":[-76.24119399999999,36.752021],"type":"Point"}
}