{
  "type": "Feature",
  "properties": {
    "iso:country":"US",
    "sg:address":"1228 Progressive Dr",
    "sg:city":"Chesapeake",
    "sg:classifiers":[
        {
            "category":"Banks & Credit Unions",
            "subcategory":"Bank",
            "type":"Services"
        }
    ],
    "sg:phone":"+1 757 548 1010",
    "sg:postcode":"23320",
    "sg:province":"VA",
    "sg:tags":[
        "mortgage",
        "loan",
        "banker",
        "real estate"
    ],
    "sg:website":"www.virginiahomeloan.com",
    "wof:name":"SHM Superior Home Mortgage",
    "wof:placetype":"venue"
},
  "geometry": {"coordinates":[-76.23011,36.765878],"type":"Point"}
}