{
  "type": "Feature",
  "properties": {
    "addr:full":"4410 Menokin Rd Richmond VA 23225",
    "addr:housenumber":"4410",
    "addr:postcode":"23225",
    "addr:street":"Menokin Rd",
    "iso:country":"US",
    "sg:address":"4410 Menokin Rd",
    "sg:city":"Richmond",
    "sg:classifiers":[
        {
            "category":"Manufacturing",
            "subcategory":"Retail Goods",
            "type":"Manufacturing & Wholesale Goods"
        }
    ],
    "sg:phone":"+1 804 330 5733",
    "sg:postcode":"23225",
    "sg:province":"VA",
    "sg:tags":[
        "assembly",
        "fabricating"
    ],
    "wof:name":"Tubular Fabrication Ind",
    "wof:placetype":"venue"
},
  "geometry": {"coordinates":[-77.537177,37.557522],"type":"Point"}
}