{
  "type": "Feature",
  "properties": {
    "addr:full":"426 Elm Ave Portsmouth VA 23704",
    "addr:housenumber":"426",
    "addr:postcode":"23704",
    "addr:street":"Elm Ave",
    "iso:country":"US",
    "sg:address":"426 Elm Ave",
    "sg:city":"Portsmouth",
    "sg:classifiers":[
        {
            "category":"Freight",
            "type":"Transportation"
        }
    ],
    "sg:phone":"+1 757 399 2163",
    "sg:postcode":"23704",
    "sg:province":"VA",
    "sg:tags":[
        "commercial",
        "storage"
    ],
    "wof:name":"A-AAA Self Storage",
    "wof:placetype":"venue"
},
  "geometry": {"coordinates":[-76.31295299999999,36.838356],"type":"Point"}
}