{
  "type": "Feature",
  "properties": {
    "addr:full":"22585 Markey Ct Sterling VA 20166",
    "addr:housenumber":"22585",
    "addr:postcode":"20166",
    "addr:street":"Markey Ct",
    "iso:country":"US",
    "sg:address":"22585 Markey Ct",
    "sg:city":"Sterling",
    "sg:classifiers":[
        {
            "category":"Autos & Motor Vehicles",
            "subcategory":"Auto Supplies",
            "type":"Retail Goods"
        }
    ],
    "sg:phone":"+1 703 430 3303",
    "sg:postcode":"20166",
    "sg:province":"VA",
    "sg:tags":[
        "equipment",
        "racing",
        "car",
        "automobile"
    ],
    "wof:name":"O G Racing",
    "wof:placetype":"venue"
},
  "geometry": {"coordinates":[-77.451064,38.991776],"type":"Point"}
}