{
  "type": "Feature",
  "properties": {
    "addr:full":"6781 Madison St Haymarket VA 20169",
    "addr:housenumber":"6781",
    "addr:postcode":"20169",
    "addr:street":"Madison St",
    "iso:country":"US",
    "sg:address":"6781 Madison St",
    "sg:city":"Haymarket",
    "sg:classifiers":[
        {
            "category":"Home & Garden",
            "subcategory":"Carpets & Floor Coverings",
            "type":"Retail Goods"
        }
    ],
    "sg:phone":"+1 703 754 9864",
    "sg:postcode":"20169",
    "sg:province":"VA",
    "wof:name":"Colvins Carpets",
    "wof:placetype":"venue"
},
  "geometry": {"coordinates":[-77.635617,38.810674],"type":"Point"}
}