{
  "type": "Feature",
  "properties": {
    "addr:full":"279 Stultz Gap Rd Edinburg VA 22824",
    "addr:housenumber":"279",
    "addr:postcode":"22824",
    "addr:street":"Stultz Gap Rd",
    "iso:country":"US",
    "sg:address":"279 Stultz Gap Rd",
    "sg:city":"Edinburg",
    "sg:classifiers":[
        {
            "category":"Professional",
            "subcategory":"Business Services",
            "type":"Services"
        }
    ],
    "sg:phone":"+1 540 984 4573",
    "sg:postcode":"22824",
    "sg:province":"VA",
    "sg:tags":[
        "auctioneer"
    ],
    "wof:name":"George's Auctions",
    "wof:placetype":"venue"
},
  "geometry": {"coordinates":[-78.61288,38.891511],"type":"Point"}
}