{
  "type": "Feature",
  "properties": {
    "iso:country":"US",
    "sg:address":"5490 Ashleigh Rd",
    "sg:city":"Fairfax",
    "sg:classifiers":[
        {
            "category":"Wholesale",
            "subcategory":"Computers",
            "type":"Manufacturing & Wholesale Goods"
        }
    ],
    "sg:phone":"+1 703 222 0894",
    "sg:postcode":"22030",
    "sg:province":"VA",
    "sg:tags":[
        "resale"
    ],
    "wof:name":"US International Marketing",
    "wof:placetype":"venue"
},
  "geometry": {"coordinates":[-77.38476300000001,38.828316],"type":"Point"}
}