{
  "type": "Feature",
  "properties": {
    "addr:full":"1081 E Stuart Dr Galax VA 24333",
    "addr:housenumber":"1081",
    "addr:postcode":"24333",
    "addr:street":"E Stuart Dr",
    "iso:country":"US",
    "sg:address":"1081 E Stuart Dr",
    "sg:city":"Galax",
    "sg:classifiers":[
        {
            "category":"Restaurant",
            "type":"Food & Drink"
        }
    ],
    "sg:phone":"+1 276 236 5155",
    "sg:postcode":"24333",
    "sg:province":"VA",
    "wof:name":"Little Caesars Pizza",
    "wof:placetype":"venue"
},
  "geometry": {"coordinates":[-80.89309799999999,36.681828],"type":"Point"}
}