{
  "type": "Feature",
  "properties": {
    "iso:country":"US",
    "sg:address":"8138 Roaring Springs Rd",
    "sg:city":"Gloucester",
    "sg:classifiers":[
        {
            "category":"Food & Beverages",
            "subcategory":"Candy",
            "type":"Retail Goods"
        }
    ],
    "sg:phone":"+1 804 695 9310",
    "sg:postcode":"23061",
    "sg:province":"VA",
    "sg:tags":[
        "confectionery"
    ],
    "wof:name":"A Candy Fix",
    "wof:placetype":"venue"
},
  "geometry": {"coordinates":[-76.52954099999999,37.426667],"type":"Point"}
}