{
  "type": "Feature",
  "properties": {
    "addr:full":"11453 Rockville Rd Rockville VA 23146",
    "addr:housenumber":"11453",
    "addr:postcode":"23146",
    "addr:street":"Rockville Rd",
    "iso:country":"US",
    "sg:address":"11453 Rockville Rd",
    "sg:city":"Rockville",
    "sg:classifiers":[
        {
            "category":"Building & Trades",
            "subcategory":"Landscaping Services",
            "type":"Services"
        }
    ],
    "sg:phone":"+1 804 749 8445",
    "sg:postcode":"23146",
    "sg:province":"VA",
    "sg:tags":[
        "sod",
        "sodding"
    ],
    "wof:name":"Collier Co",
    "wof:placetype":"venue"
},
  "geometry": {"coordinates":[-77.67953,37.723475],"type":"Point"}
}