{
  "type": "Feature",
  "properties": {
    "addr:full":"9387 Kenna Way Mechanicsville VA 23116",
    "addr:housenumber":"9387",
    "addr:postcode":"23116",
    "addr:street":"Kenna Way",
    "iso:country":"US",
    "sg:address":"9387 Kenna Way",
    "sg:city":"Mechanicsville",
    "sg:classifiers":[
        {
            "category":"Food & Beverages",
            "subcategory":"Specialty",
            "type":"Retail Goods"
        }
    ],
    "sg:phone":"+1 804 730 6465",
    "sg:postcode":"23116",
    "sg:province":"VA",
    "wof:name":"Shaklee Nutrition Products",
    "wof:placetype":"venue"
},
  "geometry": {"coordinates":[-77.379053,37.665194],"type":"Point"}
}