{
  "type": "Feature",
  "properties": {
    "addr:full":"1 S Royal Ave Front Royal VA 22630",
    "addr:housenumber":"1",
    "addr:postcode":"22630",
    "addr:street":"S Royal Ave",
    "iso:country":"US",
    "sg:address":"1 S Royal Ave",
    "sg:city":"Front Royal",
    "sg:classifiers":[
        {
            "category":"Banks & Credit Unions",
            "subcategory":"Bank",
            "type":"Services"
        }
    ],
    "sg:phone":"+1 540 631 1185",
    "sg:postcode":"22630",
    "sg:province":"VA",
    "sg:tags":[
        "federal",
        "savings",
        "institution"
    ],
    "wof:name":"Greater Atlantic Bank",
    "wof:placetype":"venue"
},
  "geometry": {"coordinates":[-78.19354199999999,38.917992],"type":"Point"}
}