{
  "type": "Feature",
  "properties": {
    "addr:full":"458 Fortune Ln Hustle VA 22476",
    "addr:housenumber":"458",
    "addr:postcode":"22476",
    "addr:street":"Fortune Ln",
    "iso:country":"US",
    "sg:address":"458 Fortune Ln",
    "sg:city":"Hustle",
    "sg:classifiers":[
        {
            "category":"Professional",
            "subcategory":"Management & Consulting",
            "type":"Services"
        }
    ],
    "sg:phone":"+1 804 443 4985",
    "sg:postcode":"22476",
    "sg:province":"VA",
    "sg:tags":[
        "personnel",
        "grievance"
    ],
    "wof:name":"Walter Greenfield",
    "wof:placetype":"venue"
},
  "geometry": {"coordinates":[-77.07167699999999,38.034674],"type":"Point"}
}