{
  "type": "Feature",
  "properties": {
    "iso:country":"US",
    "sg:address":"1147 Harmony Rd",
    "sg:city":"Norfolk",
    "sg:classifiers":[
        {
            "category":"Wholesale",
            "subcategory":"Painting Supplies",
            "type":"Manufacturing & Wholesale Goods"
        }
    ],
    "sg:phone":"+1 757 461 8541",
    "sg:postcode":"23502",
    "sg:province":"VA",
    "sg:tags":[
        "paint"
    ],
    "wof:name":"Mobile Paint",
    "wof:placetype":"venue"
},
  "geometry": {"coordinates":[-76.218558,36.860987],"type":"Point"}
}