{
  "type": "Feature",
  "properties": {
    "iso:country":"US",
    "sg:address":"12541 Jefferson Ave",
    "sg:city":"Newport News",
    "sg:classifiers":[
        {
            "category":"Restaurant",
            "type":"Food & Drink"
        }
    ],
    "sg:menulink":"http://www.allmenus.com/va/newport-news/41646-smokey-bones/menu/",
    "sg:phone":"+1 757 988 0028",
    "sg:postcode":"23602",
    "sg:province":"VA",
    "sg:tags":[
        "barbecue",
        "american"
    ],
    "wof:name":"Smokey Bones",
    "wof:placetype":"venue"
},
  "geometry": {"coordinates":[-76.51131100000001,37.127323],"type":"Point"}
}