{
  "type": "Feature",
  "properties": {
    "addr:full":"140 Franklin St Rocky Mount VA 24151",
    "addr:housenumber":"140",
    "addr:postcode":"24151",
    "addr:street":"Franklin St",
    "iso:country":"US",
    "sg:address":"140 Franklin St",
    "sg:city":"Rocky Mount",
    "sg:classifiers":[
        {
            "category":"Building & Trades",
            "subcategory":"Landscaping Services",
            "type":"Services"
        }
    ],
    "sg:phone":"+1 540 489 4493",
    "sg:postcode":"24151",
    "sg:province":"VA",
    "sg:tags":[
        "lawn",
        "maintenance",
        "grounds"
    ],
    "wof:name":"Lawn Artist",
    "wof:placetype":"venue"
},
  "geometry": {"coordinates":[-79.89252999999999,37.000706],"type":"Point"}
}