{
  "type": "Feature",
  "properties": {
    "addr:full":"1585 Clarkson Rd Richmond VA 23224",
    "addr:housenumber":"1585",
    "addr:postcode":"23224",
    "addr:street":"Clarkson Rd",
    "iso:country":"US",
    "sg:address":"1585 Clarkson Rd",
    "sg:city":"Richmond",
    "sg:classifiers":[
        {
            "category":"Real Estate",
            "subcategory":"Real Estate Services",
            "type":"Services"
        },
        {
            "category":"Building & Trades",
            "subcategory":"Cleaning & Sanitation",
            "type":"Services"
        }
    ],
    "sg:phone":"+1 804 253 2351",
    "sg:postcode":"23224",
    "sg:province":"VA",
    "sg:tags":[
        "maintenance",
        "cleaners-interior"
    ],
    "wof:name":"Mallory's Cleaning Service",
    "wof:placetype":"venue"
},
  "geometry": {"coordinates":[-77.479477,37.493586],"type":"Point"}
}