{
  "type": "Feature",
  "properties": {
    "addr:full":"4420 Cleburne Blvd Dublin VA 24126",
    "addr:housenumber":"4420",
    "addr:postcode":"24126",
    "addr:street":"Cleburne Blvd",
    "iso:country":"US",
    "sg:address":"4420 Cleburne Blvd",
    "sg:city":"Dublin",
    "sg:classifiers":[
        {
            "category":"Travel",
            "subcategory":"Hotels & Motels",
            "type":"Entertainment"
        }
    ],
    "sg:phone":"+1 540 674 5700",
    "sg:postcode":"24126",
    "sg:province":"VA",
    "sg:website":"www.hamptoninn.com",
    "wof:name":"Hampton Inn",
    "wof:placetype":"venue"
},
  "geometry": {"coordinates":[-80.697146,37.07163],"type":"Point"}
}