{
  "type": "Feature",
  "properties": {
    "addr:full":"6515 Midlothian Tpke Richmond VA 23225",
    "addr:housenumber":"6515",
    "addr:postcode":"23225",
    "addr:street":"Midlothian Tpke",
    "iso:country":"US",
    "sg:address":"6515 Midlothian Tpke",
    "sg:city":"Richmond",
    "sg:classifiers":[
        {
            "category":"Travel",
            "subcategory":"Hotels & Motels",
            "type":"Entertainment"
        }
    ],
    "sg:phone":"+1 804 745 5200",
    "sg:postcode":"23225",
    "sg:province":"VA",
    "sg:tags":[
        "operation"
    ],
    "wof:name":"Eagle Inn",
    "wof:placetype":"venue"
},
  "geometry": {"coordinates":[-77.516502,37.503048],"type":"Point"}
}