{
  "type": "Feature",
  "properties": {
    "addr:full":"334 Sand Mine Rd Gore VA 22637",
    "addr:housenumber":"334",
    "addr:postcode":"22637",
    "addr:street":"Sand Mine Rd",
    "iso:country":"US",
    "sg:address":"334 Sand Mine Rd",
    "sg:city":"Gore",
    "sg:classifiers":[
        {
            "category":"Mining & Drilling",
            "type":"Manufacturing & Wholesale Goods"
        }
    ],
    "sg:phone":"+1 540 858 3444",
    "sg:postcode":"22637",
    "sg:province":"VA",
    "sg:tags":[
        "sand",
        "industrial"
    ],
    "wof:name":"Unimin Corp",
    "wof:placetype":"venue"
},
  "geometry": {"coordinates":[-78.334549,39.256477],"type":"Point"}
}