{
  "type": "Feature",
  "properties": {
    "addr:full":"2201 E Main St Richmond VA 23223",
    "addr:housenumber":"2201",
    "addr:postcode":"23223",
    "addr:street":"E Main St",
    "iso:country":"US",
    "sg:address":"2201 E Main St",
    "sg:city":"Richmond",
    "sg:classifiers":[
        {
            "category":"Health Services",
            "subcategory":"Doctor",
            "type":"Services"
        }
    ],
    "sg:phone":"+1 804 643 3061",
    "sg:postcode":"23223",
    "sg:province":"VA",
    "sg:tags":[
        "physician",
        "surgeon"
    ],
    "wof:name":"Mid-Atlantic Nephrology",
    "wof:placetype":"venue"
},
  "geometry": {"coordinates":[-77.423103,37.530145],"type":"Point"}
}