{
  "type": "Feature",
  "properties": {
    "addr:full":"4705 Buckingham Ct Chester VA 23831",
    "addr:housenumber":"4705",
    "addr:postcode":"23831",
    "addr:street":"Buckingham Ct",
    "iso:country":"US",
    "sg:address":"4705 Buckingham Ct",
    "sg:city":"Chester",
    "sg:classifiers":[
        {
            "category":"Professional",
            "subcategory":"Employment Agencies",
            "type":"Services"
        }
    ],
    "sg:phone":"+1 804 768 0144",
    "sg:postcode":"23831",
    "sg:province":"VA",
    "wof:name":"Pomerntz Staffing Alternatives",
    "wof:placetype":"venue"
},
  "geometry": {"coordinates":[-77.452746,37.352064],"type":"Point"}
}