{
  "type": "Feature",
  "properties": {
    "addr:full":"521 E Custis Ave Alexandria VA 22301",
    "addr:housenumber":"521",
    "addr:postcode":"22301",
    "addr:street":"E Custis Ave",
    "iso:country":"US",
    "sg:address":"521 E Custis Ave",
    "sg:city":"Alexandria",
    "sg:classifiers":[
        {
            "category":"Professional",
            "type":"Services"
        }
    ],
    "sg:phone":"+1 703 299 1709",
    "sg:postcode":"22301",
    "sg:province":"VA",
    "wof:name":"Dinosource Music Inc",
    "wof:placetype":"venue"
},
  "geometry": {"coordinates":[-77.05045200000001,38.825998],"type":"Point"}
}