{
  "type": "Feature",
  "properties": {
    "iso:country":"US",
    "sg:address":"380 Toytown Rd",
    "sg:city":"Amherst",
    "sg:classifiers":[
        {
            "category":"Manufacturing",
            "subcategory":"Retail Goods",
            "type":"Manufacturing & Wholesale Goods"
        }
    ],
    "sg:phone":"+1 434 946 5345",
    "sg:postcode":"24521",
    "sg:province":"VA",
    "sg:tags":[
        "product",
        "mfg"
    ],
    "wof:name":"Charles Royer",
    "wof:placetype":"venue"
},
  "geometry": {"coordinates":[-79.008982,37.616099],"type":"Point"}
}