{
  "type": "Feature",
  "properties": {
    "addr:full":"5911 W Broad St Richmond VA 23230",
    "addr:housenumber":"5911",
    "addr:postcode":"23230",
    "addr:street":"W Broad St",
    "iso:country":"US",
    "sg:address":"5911 W Broad St",
    "sg:city":"Richmond",
    "sg:classifiers":[
        {
            "category":"Professional",
            "subcategory":"Accounting & Tax Preparation",
            "type":"Services"
        }
    ],
    "sg:phone":"+1 804 855 1200",
    "sg:postcode":"23230",
    "sg:province":"VA",
    "sg:tags":[
        "bookkeeping",
        "return"
    ],
    "sg:website":"http://www.biegler.net",
    "wof:name":"Biegler & Associates CPA's PC",
    "wof:placetype":"venue"
},
  "geometry": {"coordinates":[-77.506221,37.592006],"type":"Point"}
}