{
  "type": "Feature",
  "properties": {
    "addr:full":"241 W Main St Covington VA 24426",
    "addr:housenumber":"241",
    "addr:postcode":"24426",
    "addr:street":"W Main St",
    "iso:country":"US",
    "sg:address":"241 W Main St",
    "sg:city":"Covington",
    "sg:classifiers":[
        {
            "category":"Organizations",
            "subcategory":"Professional Association",
            "type":"Services"
        }
    ],
    "sg:phone":"+1 540 962 2178",
    "sg:postcode":"24426",
    "sg:province":"VA",
    "sg:tags":[
        "chambers",
        "business",
        "commerce"
    ],
    "wof:name":"Alleghany Highlands Cham Comm",
    "wof:placetype":"venue"
},
  "geometry": {"coordinates":[-79.994822,37.792806],"type":"Point"}
}