{
  "type": "Feature",
  "properties": {
    "iso:country":"US",
    "sg:address":"621 N Commerce Ave",
    "sg:city":"Front Royal",
    "sg:classifiers":[
        {
            "category":"Social Services",
            "subcategory":"Child Care",
            "type":"Services"
        }
    ],
    "sg:phone":"+1 540 635 2214",
    "sg:postcode":"22630",
    "sg:province":"VA",
    "wof:name":"Angel's Korner",
    "wof:placetype":"venue"
},
  "geometry": {"coordinates":[-78.191328,38.926599],"type":"Point"}
}