{
  "type": "Feature",
  "properties": {
    "iso:country":"US",
    "sg:address":"356 Waddy Dr",
    "sg:city":"Weems",
    "sg:classifiers":[
        {
            "category":"Professional",
            "subcategory":"Management & Consulting",
            "type":"Services"
        }
    ],
    "sg:phone":"+1 804 435 0054",
    "sg:postcode":"22576",
    "sg:province":"VA",
    "sg:tags":[
        "consultant"
    ],
    "wof:name":"Bruce Bevan",
    "wof:placetype":"venue"
},
  "geometry": {"coordinates":[-76.445629,37.711313],"type":"Point"}
}