{
  "type": "Feature",
  "properties": {
    "addr:full":"4844 Shannon Hill Rd Columbia VA 23038",
    "addr:housenumber":"4844",
    "addr:postcode":"23038",
    "addr:street":"Shannon Hill Rd",
    "iso:country":"US",
    "sg:address":"4844 Shannon Hill Rd",
    "sg:city":"Columbia",
    "sg:classifiers":[
        {
            "category":"Building & Trades",
            "subcategory":"Plumbing",
            "type":"Services"
        }
    ],
    "sg:phone":"+1 804 457 2525",
    "sg:postcode":"23038",
    "sg:province":"VA",
    "sg:tags":[
        "sheet",
        "work",
        "metal",
        "contractor"
    ],
    "wof:name":"J E Fifer Sheet Metal Fbrctrs",
    "wof:placetype":"venue"
},
  "geometry": {"coordinates":[-78.06043699999999,37.864486],"type":"Point"}
}