{
  "type": "Feature",
  "properties": {
    "addr:full":"2095 Langhorne Rd Lynchburg VA 24501",
    "addr:housenumber":"2095",
    "addr:postcode":"24501",
    "addr:street":"Langhorne Rd",
    "iso:country":"US",
    "sg:address":"2095 Langhorne Rd",
    "sg:city":"Lynchburg",
    "sg:classifiers":[
        {
            "category":"Arts & Performance",
            "subcategory":"Theater",
            "type":"Entertainment"
        }
    ],
    "sg:phone":"+1 434 384 8573",
    "sg:postcode":"24501",
    "sg:province":"VA",
    "sg:tags":[
        "group"
    ],
    "wof:name":"Michael Ramsey",
    "wof:placetype":"venue"
},
  "geometry": {"coordinates":[-79.18302199999999,37.413477],"type":"Point"}
}