{
  "type": "Feature",
  "properties": {
    "addr:full":"16869 Moneta Rd Moneta VA 24121",
    "addr:postcode":"16869;24121",
    "addr:street":"Moneta Rd",
    "iso:country":"US",
    "sg:address":"16869 Moneta Rd",
    "sg:city":"Moneta",
    "sg:classifiers":[
        {
            "category":"Insurance",
            "subcategory":"Insurance Agent",
            "type":"Services"
        }
    ],
    "sg:phone":"+1 540 297 7765",
    "sg:postcode":"24121",
    "sg:province":"VA",
    "wof:name":"Virginia Insurance",
    "wof:placetype":"venue"
},
  "geometry": {"coordinates":[-79.664002,37.146867],"type":"Point"}
}