{
  "type": "Feature",
  "properties": {
    "addr:full":"7305 Burroughs Ln Falls Church VA 22043",
    "addr:housenumber":"7305",
    "addr:postcode":"22043",
    "addr:street":"Burroughs Ln",
    "iso:country":"US",
    "sg:address":"7305 Burroughs Ln",
    "sg:city":"Falls Church",
    "sg:classifiers":[
        {
            "category":"Professional",
            "subcategory":"Management & Consulting",
            "type":"Services"
        }
    ],
    "sg:phone":"+1 703 821 8953",
    "sg:postcode":"22043",
    "sg:province":"VA",
    "sg:tags":[
        "consultant",
        "business"
    ],
    "wof:name":"Kenosis Group Inc",
    "wof:placetype":"venue"
},
  "geometry": {"coordinates":[-77.196792,38.903306],"type":"Point"}
}