{
  "type": "Feature",
  "properties": {
    "iso:country":"US",
    "sg:address":"6125 Boydton Plank Rd",
    "sg:city":"Petersburg",
    "sg:classifiers":[
        {
            "category":"Recreation",
            "type":"Entertainment"
        }
    ],
    "sg:phone":"+1 804 861 2408",
    "sg:postcode":"23803",
    "sg:province":"VA",
    "sg:tags":[
        "site",
        "historical"
    ],
    "wof:name":"Pamplin Historical Park",
    "wof:placetype":"venue"
},
  "geometry": {"coordinates":[-77.478233,37.188127],"type":"Point"}
}