{
  "type": "Feature",
  "properties": {
    "addr:full":"1504 Crowell Rd Vienna VA 22182",
    "addr:housenumber":"1504",
    "addr:postcode":"22182",
    "addr:street":"Crowell Rd",
    "iso:country":"US",
    "sg:address":"1504 Crowell Rd",
    "sg:city":"Vienna",
    "sg:classifiers":[
        {
            "category":"Home & Garden",
            "subcategory":"Garden Supply",
            "type":"Retail Goods"
        }
    ],
    "sg:phone":"+1 703 759 5399",
    "sg:postcode":"22182",
    "sg:province":"VA",
    "wof:name":"Great Falls Outdoor Power",
    "wof:placetype":"venue"
},
  "geometry": {"coordinates":[-77.301368,38.955833],"type":"Point"}
}