{
  "type": "Feature",
  "properties": {
    "iso:country":"US",
    "sg:address":"1100 Sunset Ln",
    "sg:city":"Culpeper",
    "sg:classifiers":[
        {
            "category":"Health Services",
            "subcategory":"Doctor",
            "type":"Services"
        }
    ],
    "sg:phone":"+1 540 825 6064",
    "sg:postcode":"22701",
    "sg:province":"VA",
    "sg:tags":[
        "dentist"
    ],
    "wof:name":"Miller Orthodontics",
    "wof:placetype":"venue"
},
  "geometry": {"coordinates":[-78.014443,38.459517],"type":"Point"}
}