{
  "type": "Feature",
  "properties": {
    "addr:full":"43379 Fullerton St Ashburn VA 20147",
    "addr:housenumber":"43379",
    "addr:postcode":"20147",
    "addr:street":"Fullerton St",
    "iso:country":"US",
    "sg:address":"43379 Fullerton St",
    "sg:city":"Ashburn",
    "sg:classifiers":[
        {
            "category":"Professional",
            "subcategory":"Computer Services",
            "type":"Services"
        }
    ],
    "sg:phone":"+1 703 867 5918",
    "sg:postcode":"20147",
    "sg:province":"VA",
    "sg:tags":[
        "info",
        "database"
    ],
    "wof:name":"Joseph G Clark",
    "wof:placetype":"venue"
},
  "geometry": {"coordinates":[-77.50091,39.021169],"type":"Point"}
}