{
  "type": "Feature",
  "properties": {
    "iso:country":"US",
    "sg:address":"10771 Old Washington Hwy",
    "sg:city":"Glen Allen",
    "sg:classifiers":[
        {
            "category":"Government",
            "subcategory":"Fire Station",
            "type":"Public Place"
        }
    ],
    "sg:phone":"+1 804 266 0361",
    "sg:postcode":"23060",
    "sg:province":"VA",
    "sg:tags":[
        "protection"
    ],
    "wof:name":"Training and Logistics Center",
    "wof:placetype":"venue"
},
  "geometry": {"coordinates":[-77.50232800000001,37.665886],"type":"Point"}
}