{
  "type": "Feature",
  "properties": {
    "addr:full":"501 Denver Ave Shenandoah VA 22849",
    "addr:housenumber":"501",
    "addr:postcode":"22849",
    "addr:street":"Denver Ave",
    "iso:country":"US",
    "sg:address":"501 Denver Ave",
    "sg:city":"Shenandoah",
    "sg:classifiers":[
        {
            "category":"Building & Trades",
            "subcategory":"Cleaning & Sanitation",
            "type":"Services"
        }
    ],
    "sg:phone":"+1 540 652 1296",
    "sg:postcode":"22849",
    "sg:province":"VA",
    "sg:tags":[
        "commercial",
        "janitorial"
    ],
    "wof:name":"Dth Cleaning Service",
    "wof:placetype":"venue"
},
  "geometry": {"coordinates":[-78.623176,38.489075],"type":"Point"}
}