{
  "type": "Feature",
  "properties": {
    "iso:country":"US",
    "sg:address":"699 N Laburnum Ave",
    "sg:city":"Richmond",
    "sg:classifiers":[
        {
            "category":"Professional",
            "type":"Services"
        }
    ],
    "sg:phone":"+1 804 236 2870",
    "sg:postcode":"23223",
    "sg:province":"VA",
    "wof:name":"Alvin Watkins Rev",
    "wof:placetype":"venue"
},
  "geometry": {"coordinates":[-77.373592,37.558273],"type":"Point"}
}