{
  "type": "Feature",
  "properties": {
    "iso:country":"US",
    "sg:address":"5549 James Madison Hwy",
    "sg:city":"The Plains",
    "sg:classifiers":[
        {
            "category":"Building & Trades",
            "subcategory":"Construction",
            "type":"Services"
        }
    ],
    "sg:phone":"+1 540 253 5376",
    "sg:postcode":"20198",
    "sg:province":"VA",
    "sg:tags":[
        "excavating",
        "contractor"
    ],
    "wof:name":"Shelton Davis Inc",
    "wof:placetype":"venue"
},
  "geometry": {"coordinates":[-77.812758,38.809377],"type":"Point"}
}