{
  "type": "Feature",
  "properties": {
    "addr:full":"1411 Devils Reach Rd Woodbridge VA 22192",
    "addr:housenumber":"1411",
    "addr:postcode":"22192",
    "addr:street":"Devils Reach Rd",
    "iso:country":"US",
    "sg:address":"1411 Devils Reach Rd",
    "sg:city":"Woodbridge",
    "sg:classifiers":[
        {
            "category":"Real Estate",
            "subcategory":"Real Estate Operator",
            "type":"Services"
        }
    ],
    "sg:phone":"+1 703 497 9701",
    "sg:postcode":"22192",
    "sg:province":"VA",
    "sg:tags":[
        "building",
        "nonresidential"
    ],
    "wof:name":"Outer Banks Properties LLC",
    "wof:placetype":"venue"
},
  "geometry": {"coordinates":[-77.258067,38.67104],"type":"Point"}
}