{
  "type": "Feature",
  "properties": {
    "iso:country":"US",
    "sg:address":"181 S Main St",
    "sg:city":"Danville",
    "sg:classifiers":[
        {
            "category":"Health Services",
            "subcategory":"Doctor",
            "type":"Services"
        }
    ],
    "sg:phone":"+1 434 793 1231",
    "sg:postcode":"24541",
    "sg:province":"VA",
    "sg:tags":[
        "physician",
        "surgeon"
    ],
    "wof:name":"Danville Pediatrics",
    "wof:placetype":"venue"
},
  "geometry": {"coordinates":[-79.404563,36.577469],"type":"Point"}
}