{
  "type": "Feature",
  "properties": {
    "iso:country":"US",
    "sg:address":"6319 Georgetown Pike",
    "sg:city":"Mclean",
    "sg:classifiers":[
        {
            "category":"Recreation",
            "subcategory":"Playground",
            "type":"Entertainment"
        }
    ],
    "sg:postcode":"22107",
    "sg:province":"VA",
    "sg:website":"www.fairfaxcounty.gov/parks/clem...",
    "wof:name":"Clemyjontri Park",
    "wof:placetype":"venue"
},
  "geometry": {"coordinates":[-77.156505,38.943457],"type":"Point"}
}