{
  "type": "Feature",
  "properties": {
    "addr:full":"414 N Main St Culpeper VA 22701",
    "addr:housenumber":"414",
    "addr:postcode":"22701",
    "addr:street":"N Main St",
    "iso:country":"US",
    "sg:address":"414 N Main St",
    "sg:city":"Culpeper",
    "sg:classifiers":[
        {
            "category":"Autos & Motor Vehicles",
            "subcategory":"Automobile Sales",
            "type":"Retail Goods"
        }
    ],
    "sg:phone":"+1 540 825 7643",
    "sg:postcode":"22701",
    "sg:province":"VA",
    "sg:tags":[
        "car",
        "used",
        "dealer"
    ],
    "wof:name":"M & M Auto Sales",
    "wof:placetype":"venue"
},
  "geometry": {"coordinates":[-77.99525199999999,38.475843],"type":"Point"}
}