{
  "type": "Feature",
  "properties": {
    "iso:country":"US",
    "sg:address":"2050 Roanoke St",
    "sg:city":"Christiansburg",
    "sg:classifiers":[
        {
            "category":"Autos & Motor Vehicles",
            "subcategory":"Automobile Sales",
            "type":"Retail Goods"
        },
        {
            "category":"Retail",
            "subcategory":"Auto Repair",
            "type":"Services"
        }
    ],
    "sg:phone":"+1 540 382 2100",
    "sg:postcode":"24073",
    "sg:province":"VA",
    "sg:tags":[
        "dealers-used",
        "new",
        "used",
        "cars-wholesale",
        "car"
    ],
    "sg:website":"http://www.duncanhyundai.com",
    "wof:name":"Duncan Hyundai",
    "wof:placetype":"venue"
},
  "geometry": {"coordinates":[-80.37019600000001,37.135239],"type":"Point"}
}