{
  "type": "Feature",
  "properties": {
    "addr:full":"10083 Kings Hwy King George VA 22485",
    "addr:housenumber":"10083",
    "addr:postcode":"22485",
    "addr:street":"Kings Hwy",
    "iso:country":"US",
    "sg:address":"10083 Kings Hwy",
    "sg:city":"King George",
    "sg:classifiers":[
        {
            "category":"Personal",
            "subcategory":"Barber",
            "type":"Services"
        }
    ],
    "sg:phone":"+1 540 775 9912",
    "sg:postcode":"22485",
    "sg:province":"VA",
    "sg:tags":[
        "shop"
    ],
    "wof:name":"Elite Barber Shop",
    "wof:placetype":"venue"
},
  "geometry": {"coordinates":[-77.171154,38.26384],"type":"Point"}
}