{
  "type": "Feature",
  "properties": {
    "iso:country":"US",
    "sg:address":"6228 Rolling Rd",
    "sg:city":"Springfield",
    "sg:classifiers":[
        {
            "category":"Shopping",
            "subcategory":"Bicycles & Sporting Goods",
            "type":"Retail Goods"
        }
    ],
    "sg:phone":"+1 703 916 9696",
    "sg:postcode":"22152",
    "sg:province":"VA",
    "wof:name":"Rivera's Shop",
    "wof:placetype":"venue"
},
  "geometry": {"coordinates":[-77.2345,38.781272],"type":"Point"}
}