{
  "type": "Feature",
  "properties": {
    "addr:full":"294 River Rd Farmville VA 23901",
    "addr:housenumber":"294",
    "addr:postcode":"23901",
    "addr:street":"River Rd",
    "iso:country":"US",
    "sg:address":"294 River Rd",
    "sg:city":"Farmville",
    "sg:classifiers":[
        {
            "category":"Food & Beverages",
            "subcategory":"Bakery",
            "type":"Retail Goods"
        }
    ],
    "sg:phone":"+1 434 392 8476",
    "sg:postcode":"23901",
    "sg:province":"VA",
    "sg:tags":[
        "baker"
    ],
    "wof:name":"Cake Kitchen",
    "wof:placetype":"venue"
},
  "geometry": {"coordinates":[-78.375266,37.309813],"type":"Point"}
}