{
  "type": "Feature",
  "properties": {
    "iso:country":"US",
    "sg:address":"1731 Maxwell Ct",
    "sg:city":"Mc Lean",
    "sg:classifiers":[
        {
            "category":"Professional",
            "subcategory":"Accounting & Tax Preparation",
            "type":"Services"
        }
    ],
    "sg:phone":"+1 703 734 6884",
    "sg:postcode":"22101",
    "sg:province":"VA",
    "wof:name":"Chris Sorrels",
    "wof:placetype":"venue"
},
  "geometry": {"coordinates":[-77.18146299999999,38.919346],"type":"Point"}
}