{
  "type": "Feature",
  "properties": {
    "addr:full":"453 W Washington St Suffolk VA 23434",
    "addr:housenumber":"453",
    "addr:postcode":"23434",
    "addr:street":"W Washington St",
    "iso:country":"US",
    "sg:address":"453 W Washington St",
    "sg:city":"Suffolk",
    "sg:classifiers":[
        {
            "category":"Insurance",
            "subcategory":"Hazard Insurance",
            "type":"Services"
        }
    ],
    "sg:phone":"+1 757 539 3421",
    "sg:postcode":"23434",
    "sg:province":"VA",
    "sg:tags":[
        "fidelity",
        "bond"
    ],
    "wof:name":"Nansemond Insurance Inc",
    "wof:placetype":"venue"
},
  "geometry": {"coordinates":[-76.589913,36.729629],"type":"Point"}
}