{
  "type": "Feature",
  "properties": {
    "iso:country":"US",
    "sg:address":"14862 Warwick Blvd",
    "sg:city":"Newport News",
    "sg:classifiers":[
        {
            "category":"Wholesale",
            "subcategory":"Stationery",
            "type":"Manufacturing & Wholesale Goods"
        },
        {
            "category":"Shopping",
            "subcategory":"Computers & Home Electronics",
            "type":"Retail Goods"
        }
    ],
    "sg:phone":"+1 757 874 3163",
    "sg:postcode":"23608",
    "sg:province":"VA",
    "sg:tags":[
        "compute",
        "business",
        "form",
        "prepackaged",
        "system",
        "software"
    ],
    "wof:name":"Turnkey Small Business Systems",
    "wof:placetype":"venue"
},
  "geometry": {"coordinates":[-76.544343,37.134609],"type":"Point"}
}