{
  "type": "Feature",
  "properties": {
    "addr:full":"616 Virginia Beach Blvd Virginia Beach VA 23451",
    "addr:housenumber":"616",
    "addr:postcode":"23451",
    "addr:street":"Virginia Beach Blvd",
    "iso:country":"US",
    "sg:address":"616 Virginia Beach Blvd",
    "sg:city":"Virginia Beach",
    "sg:classifiers":[
        {
            "category":"Restaurant",
            "type":"Food & Drink"
        }
    ],
    "sg:phone":"+1 757 428 1355",
    "sg:postcode":"23451",
    "sg:province":"VA",
    "sg:tags":[
        "eating"
    ],
    "wof:name":"Marys Food Lc",
    "wof:placetype":"venue"
},
  "geometry": {"coordinates":[-75.982727,36.84381],"type":"Point"}
}