{
  "type": "Feature",
  "properties": {
    "addr:full":"2175 Clearview Rd Exmore VA 23350",
    "addr:housenumber":"2175",
    "addr:postcode":"23350",
    "addr:street":"Clearview Rd",
    "iso:country":"US",
    "sg:address":"2175 Clearview Rd",
    "sg:city":"Exmore",
    "sg:classifiers":[
        {
            "category":"Personal",
            "type":"Services"
        }
    ],
    "sg:phone":"+1 757 442 3191",
    "sg:postcode":"23350",
    "sg:province":"VA",
    "wof:name":"Therapeutic Bodywork LLC",
    "wof:placetype":"venue"
},
  "geometry": {"coordinates":[-75.9042,37.549112],"type":"Point"}
}