{
  "type": "Feature",
  "properties": {
    "iso:country":"US",
    "sg:address":"6872 Chelsea Rd",
    "sg:city":"Mc Lean",
    "sg:classifiers":[
        {
            "category":"Communications",
            "subcategory":"Film & Video Production",
            "type":"Services"
        }
    ],
    "sg:phone":"+1 703 556 8840",
    "sg:postcode":"22101",
    "sg:province":"VA",
    "sg:tags":[
        "motion",
        "taping"
    ],
    "wof:name":"Frank Frost Production Inc",
    "wof:placetype":"venue"
},
  "geometry": {"coordinates":[-77.179619,38.940644],"type":"Point"}
}