{
  "type": "Feature",
  "properties": {
    "addr:full":"351 Archer St Crewe VA 23930",
    "addr:housenumber":"351",
    "addr:postcode":"23930",
    "addr:street":"Archer St",
    "iso:country":"US",
    "sg:address":"351 Archer St",
    "sg:city":"Crewe",
    "sg:classifiers":[
        {
            "category":"Professional",
            "subcategory":"Business Services",
            "type":"Services"
        }
    ],
    "sg:phone":"+1 434 645 0391",
    "sg:postcode":"23930",
    "sg:province":"VA",
    "sg:tags":[
        "drafting"
    ],
    "wof:name":"Southside Virginia Auto Cad",
    "wof:placetype":"venue"
},
  "geometry": {"coordinates":[-78.141488,37.189849],"type":"Point"}
}