{
  "type": "Feature",
  "properties": {
    "addr:full":"11051 Lee Hwy Fairfax VA 22030",
    "addr:housenumber":"11051",
    "addr:postcode":"22030",
    "addr:street":"Lee Hwy",
    "iso:country":"US",
    "sg:address":"11051 Lee Hwy",
    "sg:city":"Fairfax",
    "sg:classifiers":[
        {
            "category":"Professional",
            "subcategory":"Management & Consulting",
            "type":"Services"
        }
    ],
    "sg:phone":"+1 703 359 4193",
    "sg:postcode":"22030",
    "sg:province":"VA",
    "wof:name":"Racanelli Construction Corp",
    "wof:placetype":"venue"
},
  "geometry": {"coordinates":[-77.324513,38.852592],"type":"Point"}
}