{
  "type": "Feature",
  "properties": {
    "addr:full":"1210 W 3rd St Farmville VA 23901",
    "addr:housenumber":"1210",
    "addr:postcode":"23901",
    "addr:street":"W 3Rd St",
    "iso:country":"US",
    "sg:address":"1210 W 3rd St",
    "sg:city":"Farmville",
    "sg:classifiers":[
        {
            "category":"Retail",
            "subcategory":"Auto Repair",
            "type":"Services"
        }
    ],
    "sg:phone":"+1 434 315 5939",
    "sg:postcode":"23901",
    "sg:province":"VA",
    "sg:tags":[
        "repairing",
        "automobile"
    ],
    "wof:name":"Auto WORX Plus",
    "wof:placetype":"venue"
},
  "geometry": {"coordinates":[-78.413909,37.305097],"type":"Point"}
}