{
  "type": "Feature",
  "properties": {
    "iso:country":"US",
    "sg:address":"110 E 22nd St",
    "sg:city":"Norfolk",
    "sg:classifiers":[
        {
            "category":"Freight",
            "type":"Transportation"
        }
    ],
    "sg:phone":"+1 757 460 4077",
    "sg:postcode":"23517",
    "sg:province":"VA",
    "sg:tags":[
        "courier"
    ],
    "wof:name":"Beavex",
    "wof:placetype":"venue"
},
  "geometry": {"coordinates":[-76.283986,36.868035],"type":"Point"}
}