{
  "type": "Feature",
  "properties": {
    "addr:full":"202 Harrison St SE Leesburg VA 20175",
    "addr:housenumber":"202",
    "addr:postcode":"20175",
    "addr:street":"Harrison St Se",
    "iso:country":"US",
    "sg:address":"202 Harrison St SE",
    "sg:city":"Leesburg",
    "sg:classifiers":[
        {
            "category":"Home & Garden",
            "subcategory":"Furniture",
            "type":"Retail Goods"
        }
    ],
    "sg:phone":"+1 703 777 5480",
    "sg:postcode":"20175",
    "sg:province":"VA",
    "sg:tags":[
        "cabinet"
    ],
    "wof:name":"Macdowell Custom Kitchens",
    "wof:placetype":"venue"
},
  "geometry": {"coordinates":[-77.56249200000001,39.112755],"type":"Point"}
}