{
  "type": "Feature",
  "properties": {
    "addr:full":"27497 Main St Hallwood VA 23359",
    "addr:housenumber":"27497",
    "addr:postcode":"23359",
    "addr:street":"Main St",
    "iso:country":"US",
    "sg:address":"27497 Main St",
    "sg:city":"Hallwood",
    "sg:classifiers":[
        {
            "category":"Government",
            "subcategory":"Post Office",
            "type":"Public Place"
        }
    ],
    "sg:phone":"+1 757 824 4800",
    "sg:postcode":"23359",
    "sg:province":"VA",
    "wof:name":"US Post Office",
    "wof:placetype":"venue"
},
  "geometry": {"coordinates":[-75.58916600000001,37.877468],"type":"Point"}
}