{
  "type": "Feature",
  "properties": {
    "addr:full":"48 Main St Warrenton VA 20186",
    "addr:housenumber":"48",
    "addr:postcode":"20186",
    "addr:street":"Main St",
    "iso:country":"US",
    "sg:address":"48 Main St",
    "sg:city":"Warrenton",
    "sg:classifiers":[
        {
            "category":"Organizations",
            "subcategory":"Religious Organization",
            "type":"Services"
        }
    ],
    "sg:phone":"+1 540 349 1424",
    "sg:postcode":"20186",
    "sg:province":"VA",
    "sg:tags":[
        "church"
    ],
    "wof:name":"Christian Science Reading Room",
    "wof:placetype":"venue"
},
  "geometry": {"coordinates":[-77.79438399999999,38.713131],"type":"Point"}
}