{
  "type": "Feature",
  "properties": {
    "addr:full":"10 E Chapman St Alexandria VA 22301",
    "addr:housenumber":"10",
    "addr:postcode":"22301",
    "addr:street":"E Chapman St",
    "iso:country":"US",
    "sg:address":"10 E Chapman St",
    "sg:city":"Alexandria",
    "sg:classifiers":[
        {
            "category":"Health Services",
            "subcategory":"Clinic",
            "type":"Services"
        }
    ],
    "sg:phone":"+1 703 549 4058",
    "sg:postcode":"22301",
    "sg:province":"VA",
    "wof:name":"Runton Associates",
    "wof:placetype":"venue"
},
  "geometry": {"coordinates":[-77.05959199999999,38.813826],"type":"Point"}
}