{
  "type": "Feature",
  "properties": {
    "addr:full":"210 Evergreen Ave Richmond VA 23223",
    "addr:housenumber":"210",
    "addr:postcode":"23223",
    "addr:street":"Evergreen Ave",
    "iso:country":"US",
    "sg:address":"210 Evergreen Ave",
    "sg:city":"Richmond",
    "sg:classifiers":[
        {
            "category":"Building & Trades",
            "subcategory":"Construction",
            "type":"Services"
        }
    ],
    "sg:phone":"+1 804 737 8719",
    "sg:postcode":"23223",
    "sg:province":"VA",
    "sg:tags":[
        "excavating",
        "contractor",
        "grading"
    ],
    "wof:name":"Willie Cosby III Contracting",
    "wof:placetype":"venue"
},
  "geometry": {"coordinates":[-77.346587,37.558959],"type":"Point"}
}