{
  "type": "Feature",
  "properties": {
    "iso:country":"US",
    "sg:address":"1248 Orchard Dr",
    "sg:city":"Crozet",
    "sg:classifiers":[
        {
            "category":"Home & Garden",
            "subcategory":"Carpets & Floor Coverings",
            "type":"Retail Goods"
        }
    ],
    "sg:phone":"+1 434 823 2066",
    "sg:postcode":"22932",
    "sg:province":"VA",
    "sg:tags":[
        "laying",
        "contractor"
    ],
    "wof:name":"Aquafit USA",
    "wof:placetype":"venue"
},
  "geometry": {"coordinates":[-78.711354,38.071233],"type":"Point"}
}