{
  "type": "Feature",
  "properties": {
    "iso:country":"US",
    "sg:address":"5501 Williamson Rd NW",
    "sg:city":"Roanoke",
    "sg:classifiers":[
        {
            "category":"Health Services",
            "subcategory":"Doctor",
            "type":"Services"
        }
    ],
    "sg:phone":"+1 540 362 1616",
    "sg:postcode":"24012",
    "sg:province":"VA",
    "sg:tags":[
        "general"
    ],
    "wof:name":"Boxley Hill Clinic Inc",
    "wof:placetype":"venue"
},
  "geometry": {"coordinates":[-79.95362900000001,37.323975],"type":"Point"}
}