{
  "type": "Feature",
  "properties": {
    "iso:country":"US",
    "sg:address":"3761 Shore Dr",
    "sg:city":"Virginia Beach",
    "sg:classifiers":[
        {
            "category":"Shopping",
            "subcategory":"Bicycles & Sporting Goods",
            "type":"Retail Goods"
        }
    ],
    "sg:phone":"+1 757 318 7470",
    "sg:postcode":"23455",
    "sg:province":"VA",
    "sg:tags":[
        "bait",
        "fishing"
    ],
    "wof:name":"Long Point Bay Bait & Tackle",
    "wof:placetype":"venue"
},
  "geometry": {"coordinates":[-76.103161,36.907723],"type":"Point"}
}