{
  "type": "Feature",
  "properties": {
    "addr:full":"5193 Shore Dr Virginia Beach VA 23455",
    "addr:housenumber":"5193",
    "addr:postcode":"23455",
    "addr:street":"Shore Dr",
    "iso:country":"US",
    "sg:address":"5193 Shore Dr",
    "sg:city":"Virginia Beach",
    "sg:classifiers":[
        {
            "category":"Personal",
            "subcategory":"Beauty Salon",
            "type":"Services"
        }
    ],
    "sg:phone":"+1 757 460 6101",
    "sg:postcode":"23455",
    "sg:province":"VA",
    "sg:tags":[
        "shop",
        "manicuring"
    ],
    "wof:name":"Nancy Nails",
    "wof:placetype":"venue"
},
  "geometry": {"coordinates":[-76.150622,36.906369],"type":"Point"}
}