{
  "type": "Feature",
  "properties": {
    "iso:country":"US",
    "sg:address":"15111 Washington St Ste 113",
    "sg:city":"Haymarket",
    "sg:classifiers":[
        {
            "category":"Food & Beverages",
            "subcategory":"Bakery",
            "type":"Retail Goods"
        },
        {
            "category":"Ice Cream",
            "type":"Food & Drink"
        },
        {
            "category":"Food & Beverages",
            "subcategory":"Meat & Fish",
            "type":"Retail Goods"
        }
    ],
    "sg:phone":"+1 703 743 9730",
    "sg:postcode":"20169",
    "sg:province":"VA",
    "sg:tags":[
        "frozen",
        "yogurt",
        "hot",
        "sandwich",
        "dog"
    ],
    "wof:name":"Haymarket Delights",
    "wof:placetype":"venue"
},
  "geometry": {"coordinates":[-77.638392,38.813133],"type":"Point"}
}