{
  "type": "Feature",
  "properties": {
    "addr:full":"741 E Little Creek Rd Norfolk VA 23518",
    "addr:housenumber":"741",
    "addr:postcode":"23518",
    "addr:street":"E Little Creek Rd",
    "iso:country":"US",
    "sg:address":"741 E Little Creek Rd",
    "sg:city":"Norfolk",
    "sg:classifiers":[
        {
            "category":"Restaurant",
            "type":"Food & Drink"
        }
    ],
    "sg:menulink":"http://www.allmenus.com/va/norfolk/86102-little-caesars-pizza/menu/",
    "sg:phone":"+1 757 583 2964",
    "sg:postcode":"23518",
    "sg:province":"VA",
    "sg:tags":[
        "american",
        "pizza"
    ],
    "wof:name":"Little Caesar's Pizza",
    "wof:placetype":"venue"
},
  "geometry": {"coordinates":[-76.25240100000001,36.915688],"type":"Point"}
}