{
  "type": "Feature",
  "properties": {
    "addr:full":"2183 Park Blvd Marion VA 24354",
    "addr:housenumber":"2183",
    "addr:postcode":"24354",
    "addr:street":"Park Blvd",
    "iso:country":"US",
    "sg:address":"2183 Park Blvd",
    "sg:city":"Marion",
    "sg:classifiers":[
        {
            "category":"Farming",
            "subcategory":"Nursery",
            "type":"Manufacturing & Wholesale Goods"
        }
    ],
    "sg:phone":"+1 276 783 5420",
    "sg:postcode":"24354",
    "sg:province":"VA",
    "sg:tags":[
        "greenhouse"
    ],
    "wof:name":"Campbell's Garden Ctr",
    "wof:placetype":"venue"
},
  "geometry": {"coordinates":[-81.52750899999999,36.866806],"type":"Point"}
}