{
  "type": "Feature",
  "properties": {
    "iso:country":"US",
    "sg:address":"8100 Old Dominion Dr",
    "sg:city":"Mc Lean",
    "sg:classifiers":[
        {
            "category":"Real Estate",
            "subcategory":"Real Estate Agent",
            "type":"Services"
        }
    ],
    "sg:phone":"+1 703 821 1871",
    "sg:postcode":"22102",
    "sg:province":"VA",
    "sg:tags":[
        "consultant"
    ],
    "sg:website":"www.yerks.com",
    "wof:name":"Weichert Realtors",
    "wof:placetype":"venue"
},
  "geometry": {"coordinates":[-77.223741,38.951351],"type":"Point"}
}