{
  "type": "Feature",
  "properties": {
    "iso:country":"US",
    "sg:address":"1718 Ashby Station Rd",
    "sg:city":"Front Royal",
    "sg:classifiers":[
        {
            "category":"Farming",
            "subcategory":"Livestock Farm",
            "type":"Manufacturing & Wholesale Goods"
        }
    ],
    "sg:phone":"+1 540 636 9716",
    "sg:postcode":"22630",
    "sg:province":"VA",
    "sg:tags":[
        "beef",
        "feedlot",
        "cattle"
    ],
    "wof:name":"William S Royston",
    "wof:placetype":"venue"
},
  "geometry": {"coordinates":[-78.139099,39.010324],"type":"Point"}
}