{
  "type": "Feature",
  "properties": {
    "iso:country":"US",
    "sg:address":"1811 Huguenot Rd",
    "sg:city":"Richmond",
    "sg:classifiers":[
        {
            "category":"Wholesale",
            "subcategory":"Office Equipment",
            "type":"Manufacturing & Wholesale Goods"
        },
        {
            "category":"Shopping",
            "subcategory":"Stationery & Office Supplies",
            "type":"Retail Goods"
        }
    ],
    "sg:phone":"+1 804 794 4944",
    "sg:postcode":"23235",
    "sg:province":"VA",
    "sg:tags":[
        "register",
        "autographic"
    ],
    "wof:name":"Orlando Business Systems Inc",
    "wof:placetype":"venue"
},
  "geometry": {"coordinates":[-77.612118,37.52187],"type":"Point"}
}