{
  "type": "Feature",
  "properties": {
    "addr:full":"3833 Pickett Rd Fairfax VA 22031",
    "addr:housenumber":"3833",
    "addr:postcode":"22031",
    "addr:street":"Pickett Rd",
    "iso:country":"US",
    "sg:address":"3833 Pickett Rd",
    "sg:city":"Fairfax",
    "sg:classifiers":[
        {
            "category":"Wholesale",
            "subcategory":"Apparel",
            "type":"Manufacturing & Wholesale Goods"
        },
        {
            "category":"Manufacturing",
            "subcategory":"Printing",
            "type":"Manufacturing & Wholesale Goods"
        }
    ],
    "sg:phone":"+1 703 250 2556",
    "sg:postcode":"22031",
    "sg:province":"VA",
    "sg:tags":[
        "screen",
        "wear",
        "leisure"
    ],
    "sg:website":"www.eastlandscreenprints.com",
    "wof:name":"Eastland Screen Prints Inc",
    "wof:placetype":"venue"
},
  "geometry": {"coordinates":[-77.27206099999999,38.845686],"type":"Point"}
}