{
  "type": "Feature",
  "properties": {
    "addr:full":"6005 Leesburg Pike Falls Church VA 22041",
    "addr:housenumber":"6005",
    "addr:postcode":"22041",
    "addr:street":"Leesburg Pike",
    "iso:country":"US",
    "sg:address":"6005 Leesburg Pike",
    "sg:city":"Falls Church",
    "sg:classifiers":[
        {
            "category":"Shopping",
            "subcategory":"Florist",
            "type":"Retail Goods"
        }
    ],
    "sg:phone":"+1 703 820 2018",
    "sg:postcode":"22041",
    "sg:province":"VA",
    "wof:name":"Flowers For All",
    "wof:placetype":"venue"
},
  "geometry": {"coordinates":[-77.139777,38.855987],"type":"Point"}
}