{
  "type": "Feature",
  "properties": {
    "iso:country":"US",
    "sg:address":"815 Culpeper St",
    "sg:city":"Fredericksburg",
    "sg:classifiers":[
        {
            "category":"Wholesale",
            "subcategory":"Non-durable Goods",
            "type":"Manufacturing & Wholesale Goods"
        }
    ],
    "sg:phone":"+1 540 371 3516",
    "sg:postcode":"22405",
    "sg:province":"VA",
    "wof:name":"Birds of Plenty of Frdick",
    "wof:placetype":"venue"
},
  "geometry": {"coordinates":[-77.433138,38.328254],"type":"Point"}
}