{
  "type": "Feature",
  "properties": {
    "addr:full":"2274 Suggetts Point Rd Warsaw VA 22572",
    "addr:housenumber":"2274",
    "addr:postcode":"22572",
    "addr:street":"Suggetts Point Rd",
    "iso:country":"US",
    "sg:address":"2274 Suggetts Point Rd",
    "sg:city":"Warsaw",
    "sg:classifiers":[
        {
            "category":"Food & Beverages",
            "subcategory":"Bakery",
            "type":"Retail Goods"
        }
    ],
    "sg:phone":"+1 804 394 2404",
    "sg:postcode":"22572",
    "sg:province":"VA",
    "wof:name":"Lewis Family Ltd Partners",
    "wof:placetype":"venue"
},
  "geometry": {"coordinates":[-76.725729,37.836609],"type":"Point"}
}