{
  "type": "Feature",
  "properties": {
    "addr:full":"4901 Virginia Beach Blvd Virginia Beach VA 23462",
    "addr:housenumber":"4901",
    "addr:postcode":"23462",
    "addr:street":"Virginia Beach Blvd",
    "iso:country":"US",
    "sg:address":"4901 Virginia Beach Blvd",
    "sg:city":"Virginia Beach",
    "sg:classifiers":[
        {
            "category":"Manufacturing",
            "subcategory":"Food",
            "type":"Manufacturing & Wholesale Goods"
        },
        {
            "category":"Bakery",
            "type":"Food & Drink"
        }
    ],
    "sg:menulink":"http://www.allmenus.com/va/virginia-beach/121425-krispy-kreme/menu/",
    "sg:phone":"+1 757 497 4878",
    "sg:postcode":"23462",
    "sg:province":"VA",
    "sg:tags":[
        "american",
        "bakery",
        "pastry"
    ],
    "wof:name":"Krispy Kreme",
    "wof:placetype":"venue"
},
  "geometry": {"coordinates":[-76.14619,36.843238],"type":"Point"}
}