{
  "type": "Feature",
  "properties": {
    "iso:country":"US",
    "sg:address":"1220 Mendelssohn Ct",
    "sg:city":"Virginia Beach",
    "sg:classifiers":[
        {
            "category":"Professional",
            "subcategory":"Computer Services",
            "type":"Services"
        }
    ],
    "sg:phone":"+1 757 368 3166",
    "sg:postcode":"23454",
    "sg:province":"VA",
    "sg:tags":[
        "programming"
    ],
    "wof:name":"Proicere Inc",
    "wof:placetype":"venue"
},
  "geometry": {"coordinates":[-75.999071,36.77272],"type":"Point"}
}