{
  "type": "Feature",
  "properties": {
    "addr:full":"5613 Stone Rd Centreville VA 20120",
    "addr:housenumber":"5613",
    "addr:postcode":"20120",
    "addr:street":"Stone Rd",
    "iso:country":"US",
    "sg:address":"5613 Stone Rd",
    "sg:city":"Centreville",
    "sg:classifiers":[
        {
            "category":"Banks & Credit Unions",
            "subcategory":"Bank",
            "type":"Services"
        }
    ],
    "sg:phone":"+1 703 802 4774",
    "sg:postcode":"20120",
    "sg:province":"VA",
    "sg:tags":[
        "saving",
        "commercial"
    ],
    "sg:website":"http://www.chevychasebank.com",
    "wof:name":"Chevy Chase Bank, F.S.B.",
    "wof:placetype":"venue"
},
  "geometry": {"coordinates":[-77.450722,38.854389],"type":"Point"}
}