{
  "type": "Feature",
  "properties": {
    "iso:country":"US",
    "sg:address":"8825 Jacks Summit Ln",
    "sg:city":"Fredericksburg",
    "sg:classifiers":[
        {
            "category":"Wholesale",
            "subcategory":"Vending Machines",
            "type":"Manufacturing & Wholesale Goods"
        }
    ],
    "sg:phone":"+1 540 429 0160",
    "sg:postcode":"22408",
    "sg:province":"VA",
    "wof:name":"Rocnsyd Vending",
    "wof:placetype":"venue"
},
  "geometry": {"coordinates":[-77.44685200000001,38.200956],"type":"Point"}
}