{
  "type": "Feature",
  "properties": {
    "addr:full":"3118 Allen Rd Jarratt VA 23867",
    "addr:housenumber":"3118",
    "addr:postcode":"23867",
    "addr:street":"Allen Rd",
    "iso:country":"US",
    "sg:address":"3118 Allen Rd",
    "sg:city":"Jarratt",
    "sg:phone":"+1 434 535 8673",
    "sg:postcode":"23867",
    "sg:province":"VA",
    "sg:tags":[
        "farm",
        "field",
        "crop",
        "soybean"
    ],
    "wof:name":"Charles Tyler",
    "wof:placetype":"venue"
},
  "geometry": {"coordinates":[-77.50942999999999,36.80437],"type":"Point"}
}