{
  "type": "Feature",
  "properties": {
    "addr:full":"5315 Hampton Forest Way Fairfax VA 22030",
    "addr:housenumber":"5315",
    "addr:postcode":"22030",
    "addr:street":"Hampton Forest Way",
    "iso:country":"US",
    "sg:address":"5315 Hampton Forest Way",
    "sg:city":"Fairfax",
    "sg:classifiers":[
        {
            "category":"Retail",
            "subcategory":"Repair Shop",
            "type":"Services"
        }
    ],
    "sg:phone":"+1 703 830 9282",
    "sg:postcode":"22030",
    "sg:province":"VA",
    "sg:tags":[
        "machinery",
        "cleaning"
    ],
    "wof:name":"A B C Service",
    "wof:placetype":"venue"
},
  "geometry": {"coordinates":[-77.393141,38.839596],"type":"Point"}
}