{
  "type": "Feature",
  "properties": {
    "addr:full":"158 Front Royal Pike Winchester VA 22602",
    "addr:housenumber":"158",
    "addr:postcode":"22602",
    "addr:street":"Front Royal Pike",
    "iso:country":"US",
    "sg:address":"158 Front Royal Pike",
    "sg:city":"Winchester",
    "sg:classifiers":[
        {
            "category":"Professional",
            "subcategory":"Business Services",
            "type":"Services"
        }
    ],
    "sg:phone":"+1 540 450 2285",
    "sg:postcode":"22602",
    "sg:province":"VA",
    "sg:tags":[
        "auctioneer"
    ],
    "wof:name":"Auction Svc Group",
    "wof:placetype":"venue"
},
  "geometry": {"coordinates":[-78.156448,39.1597],"type":"Point"}
}