{
  "type": "Feature",
  "properties": {
    "iso:country":"US",
    "sg:address":"25255 Pleasant Valley Dr",
    "sg:city":"Chantilly",
    "sg:classifiers":[
        {
            "category":"Building & Trades",
            "subcategory":"Landscaping Services",
            "type":"Services"
        }
    ],
    "sg:phone":"+1 703 471 4018",
    "sg:postcode":"20152",
    "sg:province":"VA",
    "sg:tags":[
        "tree"
    ],
    "sg:website":"www.daveytree.com",
    "wof:name":"Davey Tree & Lawn Care",
    "wof:placetype":"venue"
},
  "geometry": {"coordinates":[-77.471243,38.917612],"type":"Point"}
}