{
  "type": "Feature",
  "properties": {
    "addr:full":"11306 Eastcliff Dr Richmond VA 23236",
    "addr:housenumber":"11306",
    "addr:postcode":"23236",
    "addr:street":"Eastcliff Dr",
    "iso:country":"US",
    "sg:address":"11306 Eastcliff Dr",
    "sg:city":"Richmond",
    "sg:classifiers":[
        {
            "category":"Shopping",
            "subcategory":"Shoes",
            "type":"Retail Goods"
        }
    ],
    "sg:phone":"+1 804 379 6226",
    "sg:postcode":"23236",
    "sg:province":"VA",
    "wof:name":"Campbell Tracy",
    "wof:placetype":"venue"
},
  "geometry": {"coordinates":[-77.604783,37.476329],"type":"Point"}
}