{
  "type": "Feature",
  "properties": {
    "addr:full":"105 High St Charlottesville VA 22902",
    "addr:housenumber":"105",
    "addr:postcode":"22902",
    "addr:street":"High St",
    "iso:country":"US",
    "sg:address":"105 High St",
    "sg:city":"Charlottesville",
    "sg:classifiers":[
        {
            "category":"Professional",
            "subcategory":"Lawyer & Legal Services",
            "type":"Services"
        }
    ],
    "sg:phone":"+1 434 977 4455",
    "sg:postcode":"22902",
    "sg:province":"VA",
    "sg:tags":[
        "attorney"
    ],
    "wof:name":"Tremblay & Smith",
    "wof:placetype":"venue"
},
  "geometry": {"coordinates":[-78.481208,38.033301],"type":"Point"}
}