{
  "type": "Feature",
  "properties": {
    "addr:full":"1818 Library St Ste 500 Reston VA 20190",
    "addr:housenumber":"1818",
    "addr:postcode":"20190",
    "addr:street":"Library St Ste 500",
    "iso:country":"US",
    "sg:address":"1818 Library St Ste 500",
    "sg:city":"Reston",
    "sg:classifiers":[
        {
            "category":"Professional",
            "subcategory":"Business Services",
            "type":"Services"
        }
    ],
    "sg:phone":"+1 703 599 1438",
    "sg:postcode":"20190",
    "sg:province":"VA",
    "sg:tags":[
        "consultant",
        "coach"
    ],
    "sg:website":"http://www.renique.com",
    "wof:name":"Renique Consulting",
    "wof:placetype":"venue"
},
  "geometry": {"coordinates":[-77.358597,38.958199],"type":"Point"}
}