{
  "type": "Feature",
  "properties": {
    "addr:full":"15507 Woodman Hall Rd Montpelier VA 23192",
    "addr:housenumber":"15507",
    "addr:postcode":"23192",
    "addr:street":"Woodman Hall Rd",
    "iso:country":"US",
    "sg:address":"15507 Woodman Hall Rd",
    "sg:city":"Montpelier",
    "sg:classifiers":[
        {
            "category":"Building & Trades",
            "subcategory":"Construction",
            "type":"Services"
        }
    ],
    "sg:phone":"+1 804 883 7805",
    "sg:postcode":"23192",
    "sg:province":"VA",
    "sg:tags":[
        "home"
    ],
    "wof:name":"Piedmont Builders Inc",
    "wof:placetype":"venue"
},
  "geometry": {"coordinates":[-77.674978,37.832897],"type":"Point"}
}