{
  "type": "Feature",
  "properties": {
    "addr:full":"567 Splitrail Ln Rustburg VA 24588",
    "addr:housenumber":"567",
    "addr:postcode":"24588",
    "addr:street":"Splitrail Ln",
    "iso:country":"US",
    "sg:address":"567 Splitrail Ln",
    "sg:city":"Rustburg",
    "sg:classifiers":[
        {
            "category":"Retail",
            "subcategory":"Animal Services",
            "type":"Services"
        }
    ],
    "sg:phone":"+1 434 660 7387",
    "sg:postcode":"24588",
    "sg:province":"VA",
    "sg:tags":[
        "pet",
        "boarding",
        "sitting"
    ],
    "wof:name":"Shade Tree Pet Care",
    "wof:placetype":"venue"
},
  "geometry": {"coordinates":[-79.08739199999999,37.314594],"type":"Point"}
}