{
  "type": "Feature",
  "properties": {
    "iso:country":"US",
    "sg:address":"105 Reading Rd S",
    "sg:city":"Weber City",
    "sg:classifiers":[
        {
            "category":"Banks & Credit Unions",
            "subcategory":"Bank",
            "type":"Services"
        }
    ],
    "sg:phone":"+1 276 386 6768",
    "sg:postcode":"24290",
    "sg:province":"VA",
    "sg:tags":[
        "depository",
        "banking",
        "check",
        "cashing"
    ],
    "wof:name":"P D Q Cash Advance Inc",
    "wof:placetype":"venue"
},
  "geometry": {"coordinates":[-82.553417,36.628164],"type":"Point"}
}