{
  "type": "Feature",
  "properties": {
    "addr:full":"5446 W Broad St Richmond VA 23230",
    "addr:housenumber":"5446",
    "addr:postcode":"23230",
    "addr:street":"W Broad St",
    "iso:country":"US",
    "sg:address":"5446 W Broad St",
    "sg:city":"Richmond",
    "sg:classifiers":[
        {
            "category":"Shopping",
            "subcategory":"Used Merchandise",
            "type":"Retail Goods"
        }
    ],
    "sg:phone":"+1 804 288 6301",
    "sg:postcode":"23230",
    "sg:province":"VA",
    "sg:tags":[
        "antique"
    ],
    "wof:name":"Willow Place Antiques Gallery",
    "wof:placetype":"venue"
},
  "geometry": {"coordinates":[-77.500755,37.587659],"type":"Point"}
}