{
  "type": "Feature",
  "properties": {
    "addr:full":"1428 Southern Blvd Virginia Beach VA 23454",
    "addr:housenumber":"1428",
    "addr:postcode":"23454",
    "addr:street":"Southern Blvd",
    "iso:country":"US",
    "sg:address":"1428 Southern Blvd",
    "sg:city":"Virginia Beach",
    "sg:classifiers":[
        {
            "category":"Travel",
            "subcategory":"Hotels & Motels",
            "type":"Entertainment"
        }
    ],
    "sg:phone":"+1 757 313 0330",
    "sg:postcode":"23454",
    "sg:province":"VA",
    "sg:tags":[
        "resort"
    ],
    "wof:name":"Pioneer Lodge 1412",
    "wof:placetype":"venue"
},
  "geometry": {"coordinates":[-76.01114800000001,36.838389],"type":"Point"}
}