{
  "type": "Feature",
  "properties": {
    "iso:country":"US",
    "sg:address":"10 Franklin Rd SE",
    "sg:city":"Roanoke",
    "sg:classifiers":[
        {
            "category":"Banks & Credit Unions",
            "subcategory":"Bank",
            "type":"Services"
        }
    ],
    "sg:phone":"+1 540 982 3262",
    "sg:postcode":"24011",
    "sg:province":"VA",
    "sg:tags":[
        "state",
        "commercial"
    ],
    "wof:name":"Crestar Bldg Ops Dept",
    "wof:placetype":"venue"
},
  "geometry": {"coordinates":[-79.939131,37.269529],"type":"Point"}
}