{
  "type": "Feature",
  "properties": {
    "iso:country":"US",
    "sg:address":"3320 Bus Center Dr",
    "sg:city":"Chesapeake",
    "sg:classifiers":[
        {
            "category":"Retail",
            "subcategory":"Auto Repair",
            "type":"Services"
        }
    ],
    "sg:phone":"+1 757 558 2404",
    "sg:postcode":"23323",
    "sg:province":"VA",
    "sg:tags":[
        "trailer"
    ],
    "sg:website":"www.virginiatrailer.com",
    "wof:name":"Virginia Trailer & Truck Body",
    "wof:placetype":"venue"
},
  "geometry": {"coordinates":[-76.35292699999999,36.787891],"type":"Point"}
}