{
  "type": "Feature",
  "properties": {
    "addr:full":"223 Little Falls St Falls Church VA 22046",
    "addr:housenumber":"223",
    "addr:postcode":"22046",
    "addr:street":"Little Falls St",
    "iso:country":"US",
    "sg:address":"223 Little Falls St",
    "sg:city":"Falls Church",
    "sg:classifiers":[
        {
            "category":"Government",
            "subcategory":"Office",
            "type":"Public Place"
        }
    ],
    "sg:phone":"+1 703 248 5077",
    "sg:postcode":"22046",
    "sg:province":"VA",
    "sg:tags":[
        "recreation",
        "park"
    ],
    "wof:name":"Falls Church Recreation Parks",
    "wof:placetype":"venue"
},
  "geometry": {"coordinates":[-77.171539,38.885837],"type":"Point"}
}