{
  "type": "Feature",
  "properties": {
    "addr:full":"3804 Mechanicsville Pike Richmond VA 23223",
    "addr:postcode":"3804;23223",
    "addr:street":"Mechanicsville Pike",
    "iso:country":"US",
    "sg:address":"3804 Mechanicsville Pike",
    "sg:city":"Richmond",
    "sg:classifiers":[
        {
            "category":"Retail",
            "subcategory":"Laundry & Dry Cleaning",
            "type":"Services"
        }
    ],
    "sg:phone":"+1 804 321 2306",
    "sg:postcode":"23223",
    "sg:province":"VA",
    "sg:tags":[
        "cleaners"
    ],
    "wof:name":"Prince Cleaners",
    "wof:placetype":"venue"
},
  "geometry": {"coordinates":[-77.395364,37.578249],"type":"Point"}
}