{
  "type": "Feature",
  "properties": {
    "iso:country":"US",
    "sg:address":"711 Hillcrest Dr SW",
    "sg:city":"Vienna",
    "sg:classifiers":[
        {
            "category":"Building & Trades",
            "subcategory":"Cleaning & Sanitation",
            "type":"Services"
        }
    ],
    "sg:phone":"+1 703 319 0712",
    "sg:postcode":"22180",
    "sg:province":"VA",
    "sg:tags":[
        "maintenance"
    ],
    "wof:name":"Afterhours Building Services",
    "wof:placetype":"venue"
},
  "geometry": {"coordinates":[-77.26119799999999,38.890524],"type":"Point"}
}