{
  "type": "Feature",
  "properties": {
    "addr:full":"1301 Buckingham Station Dr Midlothian VA 23113",
    "addr:housenumber":"1301",
    "addr:postcode":"23113",
    "addr:street":"Buckingham Station Dr",
    "iso:country":"US",
    "sg:address":"1301 Buckingham Station Dr",
    "sg:city":"Midlothian",
    "sg:classifiers":[
        {
            "category":"Real Estate",
            "subcategory":"Real Estate Operator",
            "type":"Services"
        }
    ],
    "sg:phone":"+1 804 379 9777",
    "sg:postcode":"23113",
    "sg:province":"VA",
    "sg:tags":[
        "management"
    ],
    "wof:name":"Windsor At Old Buckingham Stn",
    "wof:placetype":"venue"
},
  "geometry": {"coordinates":[-77.64415,37.503634],"type":"Point"}
}