{
  "type": "Feature",
  "properties": {
    "addr:full":"401 Draper Rd SW Blacksburg VA 24060",
    "addr:housenumber":"401",
    "addr:postcode":"24060",
    "addr:street":"Draper Rd Sw",
    "iso:country":"US",
    "sg:address":"401 Draper Rd SW",
    "sg:city":"Blacksburg",
    "sg:classifiers":[
        {
            "category":"Restaurant",
            "type":"Food & Drink"
        }
    ],
    "sg:phone":"+1 540 552 0871",
    "sg:postcode":"24060",
    "sg:province":"VA",
    "sg:tags":[
        "asian",
        "chinese",
        "pan"
    ],
    "sg:website":"http://www.chinainn.info",
    "wof:name":"China Inn",
    "wof:placetype":"venue"
},
  "geometry": {"coordinates":[-80.412491,37.22673],"type":"Point"}
}