{
  "type": "Feature",
  "properties": {
    "addr:full":"1400 Armory Dr Franklin VA 23851",
    "addr:housenumber":"1400",
    "addr:postcode":"23851",
    "addr:street":"Armory Dr",
    "iso:country":"US",
    "sg:address":"1400 Armory Dr",
    "sg:city":"Franklin",
    "sg:classifiers":[
        {
            "category":"Autos & Motor Vehicles",
            "subcategory":"Auto Supplies",
            "type":"Retail Goods"
        }
    ],
    "sg:phone":"+1 757 516 8782",
    "sg:postcode":"23851",
    "sg:province":"VA",
    "sg:tags":[
        "tire"
    ],
    "wof:name":"Pungo Off Road",
    "wof:placetype":"venue"
},
  "geometry": {"coordinates":[-76.94727899999999,36.669799],"type":"Point"}
}