{
  "type": "Feature",
  "properties": {
    "addr:full":"13985 Raised Antler Cir Midlothian VA 23112",
    "addr:housenumber":"13985",
    "addr:postcode":"23112",
    "addr:street":"Raised Antler Cir",
    "iso:country":"US",
    "sg:address":"13985 Raised Antler Cir",
    "sg:city":"Midlothian",
    "sg:classifiers":[
        {
            "category":"Personal",
            "subcategory":"Beauty Salon",
            "type":"Services"
        }
    ],
    "sg:phone":"+1 804 639 7410",
    "sg:postcode":"23112",
    "sg:province":"VA",
    "sg:tags":[
        "shop"
    ],
    "wof:name":"Shear Image Inc",
    "wof:placetype":"venue"
},
  "geometry": {"coordinates":[-77.66199899999999,37.40339],"type":"Point"}
}