{
  "type": "Feature",
  "properties": {
    "addr:full":"832 Santmyer Dr SE Leesburg VA 20175",
    "addr:housenumber":"832",
    "addr:postcode":"20175",
    "addr:street":"Santmyer Dr Se",
    "iso:country":"US",
    "sg:address":"832 Santmyer Dr SE",
    "sg:city":"Leesburg",
    "sg:classifiers":[
        {
            "category":"Professional",
            "subcategory":"Computer Services",
            "type":"Services"
        }
    ],
    "sg:phone":"+1 703 669 3779",
    "sg:postcode":"20175",
    "sg:province":"VA",
    "sg:tags":[
        "consulting"
    ],
    "wof:name":"Alliance Resource Technology",
    "wof:placetype":"venue"
},
  "geometry": {"coordinates":[-77.54665,39.083946],"type":"Point"}
}