{
  "type": "Feature",
  "properties": {
    "addr:full":"10 Bridge St N Martinsville VA 24112",
    "addr:housenumber":"10",
    "addr:postcode":"24112",
    "addr:street":"Bridge St N",
    "iso:country":"US",
    "sg:address":"10 Bridge St N",
    "sg:city":"Martinsville",
    "sg:classifiers":[
        {
            "category":"Professional",
            "subcategory":"Employment Agencies",
            "type":"Services"
        }
    ],
    "sg:phone":"+1 276 666 9122",
    "sg:postcode":"24112",
    "sg:province":"VA",
    "wof:name":"Work Force Inc",
    "wof:placetype":"venue"
},
  "geometry": {"coordinates":[-79.872941,36.691637],"type":"Point"}
}