{
  "type": "Feature",
  "properties": {
    "addr:full":"12229 Jefferson Ave Newport News VA 23602",
    "addr:housenumber":"12229",
    "addr:postcode":"23602",
    "addr:street":"Jefferson Ave",
    "iso:country":"US",
    "sg:address":"12229 Jefferson Ave",
    "sg:city":"Newport News",
    "sg:classifiers":[
        {
            "category":"Insurance",
            "subcategory":"Insurance Agent",
            "type":"Services"
        }
    ],
    "sg:phone":"+1 757 249 2800",
    "sg:postcode":"23602",
    "sg:province":"VA",
    "wof:name":"Allstate Insurance",
    "wof:placetype":"venue"
},
  "geometry": {"coordinates":[-76.500102,37.112998],"type":"Point"}
}