{
  "type": "Feature",
  "properties": {
    "iso:country":"US",
    "sg:address":"3277 Dutch Mill Ct",
    "sg:city":"Oakton",
    "sg:classifiers":[
        {
            "category":"Professional",
            "type":"Services"
        }
    ],
    "sg:phone":"+1 703 631 9777",
    "sg:postcode":"22124",
    "sg:province":"VA",
    "wof:name":"Kao Da-Tung",
    "wof:placetype":"venue"
},
  "geometry": {"coordinates":[-77.34804099999999,38.877868],"type":"Point"}
}