{
  "type": "Feature",
  "properties": {
    "addr:full":"Highway 621 Catawba VA 24070",
    "addr:postcode":"24070",
    "addr:street":"Highway 621",
    "iso:country":"US",
    "sg:address":"Highway 621",
    "sg:city":"Catawba",
    "sg:classifiers":[
        {
            "category":"Building & Trades",
            "subcategory":"Construction",
            "type":"Services"
        }
    ],
    "sg:phone":"+1 540 864 7852",
    "sg:postcode":"24070",
    "sg:province":"VA",
    "sg:tags":[
        "contractor"
    ],
    "wof:name":"Catawba Builders",
    "wof:placetype":"venue"
},
  "geometry": {"coordinates":[-80.163399,37.357399],"type":"Point"}
}