{
  "type": "Feature",
  "properties": {
    "addr:full":"728 Etheridge Rd Chesapeake VA 23322",
    "addr:housenumber":"728",
    "addr:postcode":"23322",
    "addr:street":"Etheridge Rd",
    "iso:country":"US",
    "sg:address":"728 Etheridge Rd",
    "sg:city":"Chesapeake",
    "sg:classifiers":[
        {
            "category":"Wholesale",
            "subcategory":"Electrical",
            "type":"Manufacturing & Wholesale Goods"
        }
    ],
    "sg:phone":"+1 757 482 8636",
    "sg:postcode":"23322",
    "sg:province":"VA",
    "sg:tags":[
        "lighting"
    ],
    "wof:name":"Moonlight & Sound Inc",
    "wof:placetype":"venue"
},
  "geometry": {"coordinates":[-76.210928,36.703837],"type":"Point"}
}