{
  "type": "Feature",
  "properties": {
    "addr:full":"4032 Old Virginia Rd Chesapeake VA 23323",
    "addr:housenumber":"4032",
    "addr:postcode":"23323",
    "addr:street":"Old Virginia Rd",
    "iso:country":"US",
    "sg:address":"4032 Old Virginia Rd",
    "sg:city":"Chesapeake",
    "sg:classifiers":[
        {
            "category":"Arena",
            "subcategory":"Horse Racetrack",
            "type":"Entertainment"
        }
    ],
    "sg:phone":"+1 757 488 7245",
    "sg:postcode":"23323",
    "sg:province":"VA",
    "sg:tags":[
        "twine",
        "cordage"
    ],
    "wof:name":"Twine Sr Melvin",
    "wof:placetype":"venue"
},
  "geometry": {"coordinates":[-76.38044600000001,36.785839],"type":"Point"}
}