{
  "type": "Feature",
  "properties": {
    "addr:full":"695 Church St Norfolk VA 23510",
    "addr:housenumber":"695",
    "addr:postcode":"23510",
    "addr:street":"Church St",
    "iso:country":"US",
    "sg:address":"695 Church St",
    "sg:city":"Norfolk",
    "sg:classifiers":[
        {
            "category":"Professional",
            "subcategory":"Business Services",
            "type":"Services"
        }
    ],
    "sg:phone":"+1 757 226 9075",
    "sg:postcode":"23510",
    "sg:province":"VA",
    "wof:name":"Business Infinity Group Inc",
    "wof:placetype":"venue"
},
  "geometry": {"coordinates":[-76.280536,36.853169],"type":"Point"}
}