{
  "type": "Feature",
  "properties": {
    "addr:full":"5197 Worley Rich Rd Sugar Grove VA 24375",
    "addr:housenumber":"5197",
    "addr:postcode":"24375",
    "addr:street":"Worley Rich Rd",
    "iso:country":"US",
    "sg:address":"5197 Worley Rich Rd",
    "sg:city":"Sugar Grove",
    "sg:classifiers":[
        {
            "category":"Building & Trades",
            "subcategory":"Construction",
            "type":"Services"
        }
    ],
    "sg:phone":"+1 276 677 3702",
    "sg:postcode":"24375",
    "sg:province":"VA",
    "sg:tags":[
        "masonry",
        "contractor"
    ],
    "wof:name":"Vaught Masonry Contractor Inc",
    "wof:placetype":"venue"
},
  "geometry": {"coordinates":[-81.40428300000001,36.7809],"type":"Point"}
}