{
  "type": "Feature",
  "properties": {
    "addr:full":"318 Allegheny St Richlands VA 24641",
    "addr:housenumber":"318",
    "addr:postcode":"24641",
    "addr:street":"Allegheny St",
    "iso:country":"US",
    "sg:address":"318 Allegheny St",
    "sg:city":"Richlands",
    "sg:classifiers":[
        {
            "category":"Personal",
            "subcategory":"Beauty Salon",
            "type":"Services"
        }
    ],
    "sg:phone":"+1 276 963 2263",
    "sg:postcode":"24641",
    "sg:province":"VA",
    "sg:tags":[
        "shop"
    ],
    "wof:name":"Susie's Beauty Shop",
    "wof:placetype":"venue"
},
  "geometry": {"coordinates":[-81.80062,37.099274],"type":"Point"}
}