{
  "type": "Feature",
  "properties": {
    "iso:country":"US",
    "sg:address":"1708 E Main St",
    "sg:city":"Richmond",
    "sg:classifiers":[
        {
            "category":"Restaurant",
            "type":"Food & Drink"
        }
    ],
    "sg:phone":"+1 804 780 2344",
    "sg:postcode":"23223",
    "sg:province":"VA",
    "wof:name":"After 6",
    "wof:placetype":"venue"
},
  "geometry": {"coordinates":[-77.427651,37.533011],"type":"Point"}
}