{
  "type": "Feature",
  "properties": {
    "iso:country":"US",
    "sg:address":"7304 Warwick Blvd",
    "sg:city":"Newport News",
    "sg:classifiers":[
        {
            "category":"Autos & Motor Vehicles",
            "subcategory":"Automobile Sales",
            "type":"Retail Goods"
        }
    ],
    "sg:phone":"+1 757 244 6531",
    "sg:postcode":"23607",
    "sg:province":"VA",
    "wof:name":"Hrbr Buick/Amc/Jeep/Rnlt",
    "wof:placetype":"venue"
},
  "geometry": {"coordinates":[-76.44785400000001,37.013968],"type":"Point"}
}