{
  "type": "Feature",
  "properties": {
    "iso:country":"US",
    "sg:address":"1521 Goodyear Blvd",
    "sg:city":"Danville",
    "sg:classifiers":[
        {
            "category":"Restaurant",
            "type":"Food & Drink"
        }
    ],
    "sg:phone":"+1 434 791 0320",
    "sg:postcode":"24541",
    "sg:province":"VA",
    "sg:tags":[
        "eating"
    ],
    "wof:name":"Boulevard Restaurant & Lounge",
    "wof:placetype":"venue"
},
  "geometry": {"coordinates":[-79.37621,36.563486],"type":"Point"}
}