{
  "type": "Feature",
  "properties": {
    "addr:full":"801 Church St Lynchburg VA 24504",
    "addr:housenumber":"801",
    "addr:postcode":"24504",
    "addr:street":"Church St",
    "iso:country":"US",
    "sg:address":"801 Church St",
    "sg:city":"Lynchburg",
    "sg:classifiers":[
        {
            "category":"Professional",
            "subcategory":"Lawyer & Legal Services",
            "type":"Services"
        }
    ],
    "sg:phone":"+1 434 847 3225",
    "sg:postcode":"24504",
    "sg:province":"VA",
    "sg:tags":[
        "attorney"
    ],
    "wof:name":"De Bruin & Layne",
    "wof:placetype":"venue"
},
  "geometry": {"coordinates":[-79.143193,37.414351],"type":"Point"}
}