{
  "type": "Feature",
  "properties": {
    "addr:full":"2151 Richmond Rd Charlottesville VA 22911",
    "addr:housenumber":"2151",
    "addr:postcode":"22911",
    "addr:street":"Richmond Rd",
    "iso:country":"US",
    "sg:address":"2151 Richmond Rd",
    "sg:city":"Charlottesville",
    "sg:classifiers":[
        {
            "category":"Banks & Credit Unions",
            "subcategory":"Bank",
            "type":"Services"
        }
    ],
    "sg:phone":"+1 434 977 0203",
    "sg:postcode":"22911",
    "sg:province":"VA",
    "sg:website":"statefarm.com",
    "wof:name":"Bartleski Ted",
    "wof:placetype":"venue"
},
  "geometry": {"coordinates":[-78.4254,38.0163],"type":"Point"}
}