{
  "type": "Feature",
  "properties": {
    "iso:country":"US",
    "sg:address":"150 S Pickett St",
    "sg:city":"Alexandria",
    "sg:classifiers":[
        {
            "category":"Autos & Motor Vehicles",
            "subcategory":"Automobile Sales",
            "type":"Retail Goods"
        }
    ],
    "sg:phone":"+1 703 461 5292",
    "sg:postcode":"22304",
    "sg:province":"VA",
    "sg:tags":[
        "car",
        "used",
        "truck",
        "dealership",
        "new"
    ],
    "sg:website":"http://www.passportnissanva.com/",
    "wof:name":"Passport Nissan Of Alexandria",
    "wof:placetype":"venue"
},
  "geometry": {"coordinates":[-77.122557,38.809803],"type":"Point"}
}