{
  "type": "Feature",
  "properties": {
    "addr:full":"12175 Rock Point Rd Newburg MD 20664",
    "addr:housenumber":"12175",
    "addr:postcode":"20664",
    "addr:street":"Rock Point Rd",
    "iso:country":"US",
    "sg:address":"12175 Rock Point Rd",
    "sg:city":"Newburg",
    "sg:classifiers":[
        {
            "category":"Food & Beverages",
            "subcategory":"Groceries & Convenience Stores",
            "type":"Retail Goods"
        }
    ],
    "sg:phone":"+1 301 259 2314",
    "sg:postcode":"20664",
    "sg:province":"MD",
    "sg:tags":[
        "grocer"
    ],
    "wof:name":"Dan's Store Inc",
    "wof:placetype":"venue"
},
  "geometry": {"coordinates":[-76.952347,38.376485],"type":"Point"}
}