{
  "type": "Feature",
  "properties": {
    "addr:full":"910 E Rock Rd Radford VA 24141",
    "addr:housenumber":"910",
    "addr:postcode":"24141",
    "addr:street":"E Rock Rd",
    "iso:country":"US",
    "sg:address":"910 E Rock Rd",
    "sg:city":"Radford",
    "sg:classifiers":[
        {
            "category":"Organizations",
            "subcategory":"Religious Organization",
            "type":"Services"
        }
    ],
    "sg:phone":"+1 540 639 6773",
    "sg:postcode":"24141",
    "sg:province":"VA",
    "sg:tags":[
        "church"
    ],
    "wof:name":"Zion Hill Baptist Church",
    "wof:placetype":"venue"
},
  "geometry": {"coordinates":[-80.529569,37.120419],"type":"Point"}
}