{
  "type": "Feature",
  "properties": {
    "iso:country":"US",
    "sg:address":"1316 Portland Ct",
    "sg:city":"Norfolk",
    "sg:classifiers":[
        {
            "category":"Wholesale",
            "subcategory":"Medical Equipment & Supplies",
            "type":"Manufacturing & Wholesale Goods"
        }
    ],
    "sg:phone":"+1 757 318 7601",
    "sg:postcode":"23521",
    "sg:province":"VA",
    "wof:name":"Extremedocs",
    "wof:placetype":"venue"
},
  "geometry": {"coordinates":[-76.14051499999999,36.914116],"type":"Point"}
}