{
  "type": "Feature",
  "properties": {
    "iso:country":"US",
    "sg:address":"13311 Gordon Blvd",
    "sg:city":"Woodbridge",
    "sg:classifiers":[
        {
            "category":"Restaurant",
            "type":"Food & Drink"
        }
    ],
    "sg:menulink":"http://www.allmenus.com/va/woodbridge/205633-taco-bell/menu/",
    "sg:phone":"+1 703 491 1906",
    "sg:postcode":"22191",
    "sg:province":"VA",
    "sg:tags":[
        "mexican"
    ],
    "wof:name":"Taco Bell",
    "wof:placetype":"venue"
},
  "geometry": {"coordinates":[-77.248976,38.663355],"type":"Point"}
}