{
  "type": "Feature",
  "properties": {
    "iso:country":"US",
    "sg:address":"1301 Rivermont Ave",
    "sg:city":"Lynchburg",
    "sg:classifiers":[
        {
            "category":"Organizations",
            "subcategory":"Religious Organization",
            "type":"Services"
        }
    ],
    "sg:phone":"+1 434 845 6023",
    "sg:postcode":"24504",
    "sg:province":"VA",
    "wof:name":"Rivermont Avenue Baptst Church",
    "wof:placetype":"venue"
},
  "geometry": {"coordinates":[-79.15409699999999,37.429417],"type":"Point"}
}