{
  "type": "Feature",
  "properties": {
    "addr:full":"101 N Irving St Arlington VA 22201",
    "addr:housenumber":"101",
    "addr:postcode":"22201",
    "addr:street":"N Irving St",
    "iso:country":"US",
    "sg:address":"101 N Irving St",
    "sg:city":"Arlington",
    "sg:classifiers":[
        {
            "category":"Building & Trades",
            "subcategory":"Construction",
            "type":"Services"
        }
    ],
    "sg:phone":"+1 703 525 7971",
    "sg:postcode":"22201",
    "sg:province":"VA",
    "sg:tags":[
        "contractor",
        "painter",
        "hanging"
    ],
    "wof:name":"Lyon Custom Painting",
    "wof:placetype":"venue"
},
  "geometry": {"coordinates":[-77.094398,38.874298],"type":"Point"}
}