{
  "type": "Feature",
  "properties": {
    "addr:full":"2501 Williamson Rd NE Roanoke VA 24012",
    "addr:housenumber":"2501",
    "addr:postcode":"24012",
    "addr:street":"Williamson Rd Ne",
    "iso:country":"US",
    "sg:address":"2501 Williamson Rd NE",
    "sg:city":"Roanoke",
    "sg:classifiers":[
        {
            "category":"Professional",
            "subcategory":"Accounting & Tax Preparation",
            "type":"Services"
        }
    ],
    "sg:phone":"+1 540 265 8618",
    "sg:postcode":"24012",
    "sg:province":"VA",
    "sg:tags":[
        "return"
    ],
    "wof:name":"Taxmax",
    "wof:placetype":"venue"
},
  "geometry": {"coordinates":[-79.93642699999999,37.295263],"type":"Point"}
}