{
  "type": "Feature",
  "properties": {
    "addr:full":"11240 Waples Mill Rd Fairfax VA 22030",
    "addr:housenumber":"11240",
    "addr:postcode":"22030",
    "addr:street":"Waples Mill Rd",
    "iso:country":"US",
    "sg:address":"11240 Waples Mill Rd",
    "sg:city":"Fairfax",
    "sg:classifiers":[
        {
            "category":"Insurance",
            "subcategory":"Insurance Agent",
            "type":"Services"
        }
    ],
    "sg:phone":"+1 703 293 6000",
    "sg:postcode":"22030",
    "sg:province":"VA",
    "sg:tags":[
        "broker"
    ],
    "wof:name":"Waterfield Insurance Agency",
    "wof:placetype":"venue"
},
  "geometry": {"coordinates":[-77.33632799999999,38.862278],"type":"Point"}
}