{
  "type": "Feature",
  "properties": {
    "iso:country":"US",
    "sg:address":"6663 Old Dominion Dr",
    "sg:city":"Mc Lean",
    "sg:classifiers":[
        {
            "category":"Shopping",
            "subcategory":"Used Merchandise",
            "type":"Retail Goods"
        }
    ],
    "sg:phone":"+1 703 760 0808",
    "sg:postcode":"22101",
    "sg:province":"VA",
    "sg:tags":[
        "shop",
        "clothing",
        "consignment",
        "secondhand",
        "accessory"
    ],
    "sg:website":"www.shopfashionexchange.com",
    "wof:name":"Fashion Exchange Consignment",
    "wof:placetype":"venue"
},
  "geometry": {"coordinates":[-77.174301,38.9319],"type":"Point"}
}