{
  "type": "Feature",
  "properties": {
    "iso:country":"US",
    "sg:address":"800 10th St",
    "sg:city":"Shenandoah",
    "sg:classifiers":[
        {
            "category":"Building & Trades",
            "subcategory":"Construction",
            "type":"Services"
        }
    ],
    "sg:phone":"+1 540 652 6127",
    "sg:postcode":"22849",
    "sg:province":"VA",
    "sg:tags":[
        "excavation",
        "contractor"
    ],
    "wof:name":"Charlies Backhoe & Cnstr Svc",
    "wof:placetype":"venue"
},
  "geometry": {"coordinates":[-78.613545,38.488581],"type":"Point"}
}