{
  "type": "Feature",
  "properties": {
    "addr:full":"7293 Hanover Green Dr Mechanicsville VA 23111",
    "addr:housenumber":"7293",
    "addr:postcode":"23111",
    "addr:street":"Hanover Green Dr",
    "iso:country":"US",
    "sg:address":"7293 Hanover Green Dr",
    "sg:city":"Mechanicsville",
    "sg:classifiers":[
        {
            "category":"Professional",
            "subcategory":"Employment Agencies",
            "type":"Services"
        }
    ],
    "sg:phone":"+1 804 283 1328",
    "sg:postcode":"23111",
    "sg:province":"VA",
    "sg:tags":[
        "nurse",
        "staffing"
    ],
    "wof:name":"Neighborhood Nurse",
    "wof:placetype":"venue"
},
  "geometry": {"coordinates":[-77.37573399999999,37.603981],"type":"Point"}
}