{
  "type": "Feature",
  "properties": {
    "addr:full":"13187 Summit Dr Meadowview VA 24361",
    "addr:housenumber":"13187",
    "addr:postcode":"24361",
    "addr:street":"Summit Dr",
    "iso:country":"US",
    "sg:address":"13187 Summit Dr",
    "sg:city":"Meadowview",
    "sg:classifiers":[
        {
            "category":"Utilities",
            "subcategory":"Telephone",
            "type":"Services"
        }
    ],
    "sg:phone":"+1 276 944 4761",
    "sg:postcode":"24361",
    "sg:province":"VA",
    "sg:tags":[
        "telecommunication"
    ],
    "wof:name":"American Tower Northeast",
    "wof:placetype":"venue"
},
  "geometry": {"coordinates":[-81.87103399999999,36.760183],"type":"Point"}
}