{
  "type": "Feature",
  "properties": {
    "addr:full":"6313 Eppard St Falls Church VA 22044",
    "addr:housenumber":"6313",
    "addr:postcode":"22044",
    "addr:street":"Eppard St",
    "iso:country":"US",
    "sg:address":"6313 Eppard St",
    "sg:city":"Falls Church",
    "sg:classifiers":[
        {
            "category":"Professional",
            "type":"Services"
        }
    ],
    "sg:phone":"+1 703 532 5139",
    "sg:postcode":"22044",
    "sg:province":"VA",
    "sg:tags":[
        "establishment"
    ],
    "wof:name":"A K & M Corp",
    "wof:placetype":"venue"
},
  "geometry": {"coordinates":[-77.160535,38.862466],"type":"Point"}
}