{
  "type": "Feature",
  "properties": {
    "iso:country":"US",
    "sg:address":"7350 Robert Ln",
    "sg:city":"Falls Church",
    "sg:classifiers":[
        {
            "category":"Building & Trades",
            "subcategory":"Construction",
            "type":"Services"
        }
    ],
    "sg:phone":"+1 703 560 2338",
    "sg:postcode":"22042",
    "sg:province":"VA",
    "sg:tags":[
        "house"
    ],
    "wof:name":"Pacific Home Improve",
    "wof:placetype":"venue"
},
  "geometry": {"coordinates":[-77.196583,38.868972],"type":"Point"}
}