{
  "type": "Feature",
  "properties": {
    "addr:full":"1012 Michaelwood Dr Virginia Beach VA 23452",
    "addr:housenumber":"1012",
    "addr:postcode":"23452",
    "addr:street":"Michaelwood Dr",
    "iso:country":"US",
    "sg:address":"1012 Michaelwood Dr",
    "sg:city":"Virginia Beach",
    "sg:classifiers":[
        {
            "category":"Shopping",
            "subcategory":"Clothing, Apparel, & Fashions",
            "type":"Retail Goods"
        }
    ],
    "sg:phone":"+1 757 486 8881",
    "sg:postcode":"23452",
    "sg:province":"VA",
    "wof:name":"Sexy Point Inc",
    "wof:placetype":"venue"
},
  "geometry": {"coordinates":[-76.098725,36.871201],"type":"Point"}
}