{
  "type": "Feature",
  "properties": {
    "iso:country":"US",
    "sg:address":"2020 14th St N",
    "sg:city":"Arlington",
    "sg:classifiers":[
        {
            "category":"Communications",
            "subcategory":"Film & Video Production",
            "type":"Services"
        },
        {
            "category":"Communications",
            "type":"Services"
        }
    ],
    "sg:phone":"+1 703 525 7000",
    "sg:postcode":"22201",
    "sg:province":"VA",
    "sg:tags":[
        "motion",
        "to",
        "picture",
        "allied",
        "communication"
    ],
    "wof:name":"Post Op Media",
    "wof:placetype":"venue"
},
  "geometry": {"coordinates":[-77.08338999999999,38.889549],"type":"Point"}
}