{
  "type": "Feature",
  "properties": {
    "addr:full":"2400 Aluminum Ave Hampton VA 23661",
    "addr:postcode":"2400;23661",
    "addr:street":"Aluminum Ave",
    "iso:country":"US",
    "sg:address":"2400 Aluminum Ave",
    "sg:city":"Hampton",
    "sg:classifiers":[
        {
            "category":"Freight",
            "type":"Transportation"
        }
    ],
    "sg:phone":"+1 757 827 9900",
    "sg:postcode":"23661",
    "sg:province":"VA",
    "sg:tags":[
        "arrangement",
        "general"
    ],
    "wof:name":"Chrysler Freight Line",
    "wof:placetype":"venue"
},
  "geometry": {"coordinates":[-76.40554899999999,37.006163],"type":"Point"}
}