{
  "type": "Feature",
  "properties": {
    "addr:full":"112 Starling Ave Martinsville VA 24112",
    "addr:housenumber":"112",
    "addr:postcode":"24112",
    "addr:street":"Starling Ave",
    "iso:country":"US",
    "sg:address":"112 Starling Ave",
    "sg:city":"Martinsville",
    "sg:classifiers":[
        {
            "category":"Health Services",
            "subcategory":"Doctor",
            "type":"Services"
        }
    ],
    "sg:phone":"+1 276 632 8445",
    "sg:postcode":"24112",
    "sg:province":"VA",
    "sg:tags":[
        "physician",
        "surgeon"
    ],
    "wof:name":"David W Roycroft Inc",
    "wof:placetype":"venue"
},
  "geometry": {"coordinates":[-79.86507400000001,36.686395],"type":"Point"}
}