{
  "type": "Feature",
  "properties": {
    "addr:full":"1901 S Main St Blacksburg VA 24060",
    "addr:housenumber":"1901",
    "addr:postcode":"24060",
    "addr:street":"S Main St",
    "iso:country":"US",
    "sg:address":"1901 S Main St",
    "sg:city":"Blacksburg",
    "sg:classifiers":[
        {
            "category":"Banks & Credit Unions",
            "subcategory":"Bank",
            "type":"Services"
        }
    ],
    "sg:phone":"+1 540 953 0456",
    "sg:postcode":"24060",
    "sg:province":"VA",
    "sg:tags":[
        "banking",
        "mortgage"
    ],
    "wof:name":"Chase Manhattan",
    "wof:placetype":"venue"
},
  "geometry": {"coordinates":[-80.398815,37.206469],"type":"Point"}
}