{
  "type": "Feature",
  "properties": {
    "addr:full":"2730 Fort Ave Lynchburg VA 24501",
    "addr:housenumber":"2730",
    "addr:postcode":"24501",
    "addr:street":"Fort Ave",
    "iso:country":"US",
    "sg:address":"2730 Fort Ave",
    "sg:city":"Lynchburg",
    "sg:classifiers":[
        {
            "category":"Manufacturing",
            "subcategory":"Tools & Machinery",
            "type":"Manufacturing & Wholesale Goods"
        }
    ],
    "sg:phone":"+1 434 845 6677",
    "sg:postcode":"24501",
    "sg:province":"VA",
    "sg:tags":[
        "machine",
        "shop"
    ],
    "wof:name":"IMC Corp",
    "wof:placetype":"venue"
},
  "geometry": {"coordinates":[-79.163963,37.398014],"type":"Point"}
}