{
  "type": "Feature",
  "properties": {
    "addr:full":"7129 Suncrest Dr Lynchburg VA 24502",
    "addr:housenumber":"7129",
    "addr:postcode":"24502",
    "addr:street":"Suncrest Dr",
    "iso:country":"US",
    "sg:address":"7129 Suncrest Dr",
    "sg:city":"Lynchburg",
    "sg:classifiers":[
        {
            "category":"Professional",
            "subcategory":"Management & Consulting",
            "type":"Services"
        }
    ],
    "sg:phone":"+1 434 239 1129",
    "sg:postcode":"24502",
    "sg:province":"VA",
    "sg:tags":[
        "business"
    ],
    "wof:name":"Tummond Aviation",
    "wof:placetype":"venue"
},
  "geometry": {"coordinates":[-79.220412,37.366203],"type":"Point"}
}