{
  "type": "Feature",
  "properties": {
    "iso:country":"US",
    "sg:address":"11250 Roger Bacon Dr",
    "sg:city":"Reston",
    "sg:classifiers":[
        {
            "category":"Professional",
            "subcategory":"Management & Consulting",
            "type":"Services"
        }
    ],
    "sg:phone":"+1 703 464 7009",
    "sg:postcode":"20190",
    "sg:province":"VA",
    "sg:tags":[
        "fuel"
    ],
    "wof:name":"Wellburn Management Co",
    "wof:placetype":"venue"
},
  "geometry": {"coordinates":[-77.334795,38.951522],"type":"Point"}
}