{
  "type": "Feature",
  "properties": {
    "addr:full":"299 Commerce Dr Abingdon VA 24211",
    "addr:housenumber":"299",
    "addr:postcode":"24211",
    "addr:street":"Commerce Dr",
    "iso:country":"US",
    "sg:address":"299 Commerce Dr",
    "sg:city":"Abingdon",
    "sg:classifiers":[
        {
            "category":"Social Services",
            "subcategory":"Child Care",
            "type":"Services"
        }
    ],
    "sg:phone":"+1 276 739 0048",
    "sg:postcode":"24211",
    "sg:province":"VA",
    "sg:tags":[
        "day"
    ],
    "wof:name":"Candyland",
    "wof:placetype":"venue"
},
  "geometry": {"coordinates":[-81.976591,36.699098],"type":"Point"}
}