{
  "type": "Feature",
  "properties": {
    "iso:country":"US",
    "sg:address":"7021 Haycock Rd",
    "sg:city":"Falls Church",
    "sg:classifiers":[
        {
            "category":"Professional",
            "subcategory":"Engineering",
            "type":"Services"
        }
    ],
    "sg:phone":"+1 703 538 5001",
    "sg:postcode":"22043",
    "sg:province":"VA",
    "sg:tags":[
        "govt",
        "consulting"
    ],
    "wof:name":"Geoff Thompson Consulting",
    "wof:placetype":"venue"
},
  "geometry": {"coordinates":[-77.18764,38.89716],"type":"Point"}
}