{
  "type": "Feature",
  "properties": {
    "addr:full":"2 Cardinal Park Dr SE Leesburg VA 20175",
    "addr:housenumber":"2",
    "addr:postcode":"20175",
    "addr:street":"Cardinal Park Dr Se",
    "iso:country":"US",
    "sg:address":"2 Cardinal Park Dr SE",
    "sg:city":"Leesburg",
    "sg:classifiers":[
        {
            "category":"Personal",
            "subcategory":"Beauty Salon",
            "type":"Services"
        }
    ],
    "sg:phone":"+1 703 777 1260",
    "sg:postcode":"20175",
    "sg:province":"VA",
    "sg:tags":[
        "shop"
    ],
    "wof:name":"Electrologist Associates",
    "wof:placetype":"venue"
},
  "geometry": {"coordinates":[-77.541675,39.098188],"type":"Point"}
}