{
  "type": "Feature",
  "properties": {
    "addr:full":"19 S Market St Staunton VA 24401",
    "addr:housenumber":"19",
    "addr:postcode":"24401",
    "addr:street":"S Market St",
    "iso:country":"US",
    "sg:address":"19 S Market St",
    "sg:city":"Staunton",
    "sg:classifiers":[
        {
            "category":"Education",
            "subcategory":"School",
            "type":"Public Place"
        }
    ],
    "sg:phone":"+1 540 886 9109",
    "sg:postcode":"24401",
    "sg:province":"VA",
    "sg:website":"www.gcswarriors.org",
    "wof:name":"Grace Christian School",
    "wof:placetype":"venue"
},
  "geometry": {"coordinates":[-79.070379,38.149377],"type":"Point"}
}