{
  "type": "Feature",
  "properties": {
    "addr:full":"7627 Vicksburg Ct Norfolk VA 23518",
    "addr:housenumber":"7627",
    "addr:postcode":"23518",
    "addr:street":"Vicksburg Ct",
    "iso:country":"US",
    "sg:address":"7627 Vicksburg Ct",
    "sg:city":"Norfolk",
    "sg:classifiers":[
        {
            "category":"Health Services",
            "subcategory":"Doctor",
            "type":"Services"
        }
    ],
    "sg:phone":"+1 757 583 1652",
    "sg:postcode":"23518",
    "sg:province":"VA",
    "sg:tags":[
        "physician",
        "surgeon"
    ],
    "wof:name":"Samuel L Shapiro MD",
    "wof:placetype":"venue"
},
  "geometry": {"coordinates":[-76.202549,36.912325],"type":"Point"}
}