{
  "type": "Feature",
  "properties": {
    "addr:full":"1900 E Cary St Richmond VA 23223",
    "addr:housenumber":"1900",
    "addr:postcode":"23223",
    "addr:street":"E Cary St",
    "iso:country":"US",
    "sg:address":"1900 E Cary St",
    "sg:city":"Richmond",
    "sg:classifiers":[
        {
            "category":"Building & Trades",
            "subcategory":"Construction",
            "type":"Services"
        }
    ],
    "sg:phone":"+1 804 521 6192",
    "sg:postcode":"23223",
    "sg:province":"VA",
    "sg:tags":[
        "renovation"
    ],
    "wof:name":"Environ LLC",
    "wof:placetype":"venue"
},
  "geometry": {"coordinates":[-77.426637,37.530964],"type":"Point"}
}