{
  "type": "Feature",
  "properties": {
    "addr:full":"1509 Ballsville Rd Powhatan VA 23139",
    "addr:housenumber":"1509",
    "addr:postcode":"23139",
    "addr:street":"Ballsville Rd",
    "iso:country":"US",
    "sg:address":"1509 Ballsville Rd",
    "sg:city":"Powhatan",
    "sg:classifiers":[
        {
            "category":"Building & Trades",
            "subcategory":"Construction",
            "type":"Services"
        }
    ],
    "sg:phone":"+1 804 492 9221",
    "sg:postcode":"23139",
    "sg:province":"VA",
    "sg:tags":[
        "general",
        "contractor"
    ],
    "wof:name":"Mathews George K Builder",
    "wof:placetype":"venue"
},
  "geometry": {"coordinates":[-78.078666,37.508052],"type":"Point"}
}