{
  "type": "Feature",
  "properties": {
    "iso:country":"US",
    "sg:address":"126 Fairfax Pike",
    "sg:city":"Stephens City",
    "sg:classifiers":[
        {
            "category":"Banks & Credit Unions",
            "subcategory":"Bank",
            "type":"Services"
        }
    ],
    "sg:phone":"+1 540 868 1828",
    "sg:postcode":"22655",
    "sg:province":"VA",
    "wof:name":"B B & T",
    "wof:placetype":"venue"
},
  "geometry": {"coordinates":[-78.21324300000001,39.080716],"type":"Point"}
}