{
  "type": "Feature",
  "properties": {
    "addr:full":"200 Westgate Pkwy Richmond VA 23233",
    "addr:housenumber":"200",
    "addr:postcode":"23233",
    "addr:street":"Westgate Pkwy",
    "iso:country":"US",
    "sg:address":"200 Westgate Pkwy",
    "sg:city":"Richmond",
    "sg:classifiers":[
        {
            "category":"Insurance",
            "subcategory":"Hazard Insurance",
            "type":"Services"
        }
    ],
    "sg:phone":"+1 804 364 6600",
    "sg:postcode":"23233",
    "sg:province":"VA",
    "sg:tags":[
        "auto"
    ],
    "wof:name":"Progressive Insurance",
    "wof:placetype":"venue"
},
  "geometry": {"coordinates":[-77.62028599999999,37.651917],"type":"Point"}
}