{
  "type": "Feature",
  "properties": {
    "addr:full":"6501 Amelia Springs Rd Jetersville VA 23083",
    "addr:housenumber":"6501",
    "addr:postcode":"23083",
    "addr:street":"Amelia Springs Rd",
    "iso:country":"US",
    "sg:address":"6501 Amelia Springs Rd",
    "sg:city":"Jetersville",
    "sg:classifiers":[
        {
            "category":"Building & Trades",
            "subcategory":"Construction",
            "type":"Services"
        }
    ],
    "sg:phone":"+1 804 561 4637",
    "sg:postcode":"23083",
    "sg:province":"VA",
    "sg:tags":[
        "contractor"
    ],
    "wof:name":"Bandy Brothers Partnership",
    "wof:placetype":"venue"
},
  "geometry": {"coordinates":[-78.100137,37.296243],"type":"Point"}
}