{
  "type": "Feature",
  "properties": {
    "addr:full":"1034 Rivermont Dr Front Royal VA 22630",
    "addr:housenumber":"1034",
    "addr:postcode":"22630",
    "addr:street":"Rivermont Dr",
    "iso:country":"US",
    "sg:address":"1034 Rivermont Dr",
    "sg:city":"Front Royal",
    "sg:classifiers":[
        {
            "category":"Retail",
            "subcategory":"Auto Repair",
            "type":"Services"
        }
    ],
    "sg:phone":"+1 540 622 5080",
    "sg:postcode":"22630",
    "sg:province":"VA",
    "sg:tags":[
        "repairing",
        "automobile"
    ],
    "wof:name":"Mark's Automotive",
    "wof:placetype":"venue"
},
  "geometry": {"coordinates":[-78.264196,38.906618],"type":"Point"}
}