{
  "type": "Feature",
  "properties": {
    "addr:full":"9622 Main St Fairfax VA 22031",
    "addr:housenumber":"9622",
    "addr:postcode":"22031",
    "addr:street":"Main St",
    "iso:country":"US",
    "sg:address":"9622 Main St",
    "sg:city":"Fairfax",
    "sg:classifiers":[
        {
            "category":"Food & Beverages",
            "subcategory":"Supermarket",
            "type":"Retail Goods"
        },
        {
            "category":"Shopping",
            "subcategory":"Pharmacy",
            "type":"Retail Goods"
        },
        {
            "category":"Food & Beverages",
            "subcategory":"Groceries & Convenience Stores",
            "type":"Retail Goods"
        }
    ],
    "sg:phone":"+1 703 978 7188",
    "sg:postcode":"22031",
    "sg:province":"VA",
    "sg:tags":[
        "super"
    ],
    "sg:website":"http://www.shoppersfood.com/",
    "wof:name":"Shoppers Food & Pharmacy",
    "wof:placetype":"venue"
},
  "geometry": {"coordinates":[-77.276494,38.841865],"type":"Point"}
}