{
  "type": "Feature",
  "properties": {
    "addr:full":"2111 Tuckaway Ln Richmond VA 23229",
    "addr:housenumber":"2111",
    "addr:postcode":"23229",
    "addr:street":"Tuckaway Ln",
    "iso:country":"US",
    "sg:address":"2111 Tuckaway Ln",
    "sg:city":"Richmond",
    "sg:classifiers":[
        {
            "category":"Building & Trades",
            "subcategory":"Construction",
            "type":"Services"
        }
    ],
    "sg:phone":"+1 804 747 8112",
    "sg:postcode":"23229",
    "sg:province":"VA",
    "sg:tags":[
        "home",
        "improvement"
    ],
    "wof:name":"Home Solutions",
    "wof:placetype":"venue"
},
  "geometry": {"coordinates":[-77.566564,37.611565],"type":"Point"}
}