{
  "type": "Feature",
  "properties": {
    "addr:full":"106 Westwick Ct Sterling VA 20165",
    "addr:housenumber":"106",
    "addr:postcode":"20165",
    "addr:street":"Westwick Ct",
    "iso:country":"US",
    "sg:address":"106 Westwick Ct",
    "sg:city":"Sterling",
    "sg:classifiers":[
        {
            "category":"Freight",
            "type":"Transportation"
        }
    ],
    "sg:phone":"+1 703 421 4025",
    "sg:postcode":"20165",
    "sg:province":"VA",
    "sg:tags":[
        "operator",
        "local",
        "trucking"
    ],
    "wof:name":"Applegate Truck",
    "wof:placetype":"venue"
},
  "geometry": {"coordinates":[-77.40862199999999,39.039823],"type":"Point"}
}