{
  "type": "Feature",
  "properties": {
    "iso:country":"US",
    "sg:address":"5155 Snead Rd",
    "sg:city":"Richmond",
    "sg:classifiers":[
        {
            "category":"Insurance",
            "subcategory":"Title Insurance",
            "type":"Services"
        }
    ],
    "sg:phone":"+1 804 675 2379",
    "sg:postcode":"23224",
    "sg:province":"VA",
    "sg:tags":[
        "abstract",
        "carrier"
    ],
    "wof:name":"New Drction Ttle Sttlment Srvi",
    "wof:placetype":"venue"
},
  "geometry": {"coordinates":[-77.487835,37.47593],"type":"Point"}
}