{
  "type": "Feature",
  "properties": {
    "addr:full":"1812 Clearfield St Richmond VA 23224",
    "addr:housenumber":"1812",
    "addr:postcode":"23224",
    "addr:street":"Clearfield St",
    "iso:country":"US",
    "sg:address":"1812 Clearfield St",
    "sg:city":"Richmond",
    "sg:classifiers":[
        {
            "category":"Building & Trades",
            "subcategory":"Construction",
            "type":"Services"
        }
    ],
    "sg:phone":"+1 804 231 4265",
    "sg:postcode":"23224",
    "sg:province":"VA",
    "sg:tags":[
        "floor",
        "laying",
        "contractor"
    ],
    "wof:name":"Stone Rejuvenators",
    "wof:placetype":"venue"
},
  "geometry": {"coordinates":[-77.49271299999999,37.486655],"type":"Point"}
}