{
  "type": "Feature",
  "properties": {
    "iso:country":"US",
    "sg:address":"304 Laural Ln",
    "sg:city":"Ophelia",
    "sg:classifiers":[
        {
            "category":"Professional",
            "subcategory":"Management & Consulting",
            "type":"Services"
        }
    ],
    "sg:phone":"+1 804 453 3200",
    "sg:postcode":"22473",
    "sg:province":"VA",
    "sg:tags":[
        "consultant",
        "business"
    ],
    "wof:name":"Butler Greene & Assoc Inc",
    "wof:placetype":"venue"
},
  "geometry": {"coordinates":[-76.27852300000001,37.894466],"type":"Point"}
}