{
  "type": "Feature",
  "properties": {
    "iso:country":"US",
    "sg:address":"1500 N Wilson Blvd",
    "sg:city":"Arlington",
    "sg:classifiers":[
        {
            "category":"Organizations",
            "subcategory":"Community Association",
            "type":"Services"
        }
    ],
    "sg:phone":"+1 703 522 0200",
    "sg:postcode":"22209",
    "sg:province":"VA",
    "sg:tags":[
        "environmental",
        "org"
    ],
    "sg:website":"www.troutunlimited.net",
    "wof:name":"Trout Unlimited National",
    "wof:placetype":"venue"
},
  "geometry": {"coordinates":[-77.076731,38.894387],"type":"Point"}
}