{
  "type": "Feature",
  "properties": {
    "addr:full":"9812 Thunderhill Ct Great Falls VA 22066",
    "addr:housenumber":"9812",
    "addr:postcode":"22066",
    "addr:street":"Thunderhill Ct",
    "iso:country":"US",
    "sg:address":"9812 Thunderhill Ct",
    "sg:city":"Great Falls",
    "sg:classifiers":[
        {
            "category":"Professional",
            "subcategory":"Management & Consulting",
            "type":"Services"
        }
    ],
    "sg:phone":"+1 703 757 1360",
    "sg:postcode":"22066",
    "sg:province":"VA",
    "wof:name":"Kirk Boyd",
    "wof:placetype":"venue"
},
  "geometry": {"coordinates":[-77.28785000000001,38.99393],"type":"Point"}
}