{
  "type": "Feature",
  "properties": {
    "addr:full":"13979 Jefferson Davis Hwy Woodbridge VA 22191",
    "addr:housenumber":"13979",
    "addr:postcode":"22191",
    "addr:street":"Jefferson Davis Hwy",
    "iso:country":"US",
    "sg:address":"13979 Jefferson Davis Hwy",
    "sg:city":"Woodbridge",
    "sg:classifiers":[
        {
            "category":"Shopping",
            "type":"Retail Goods"
        }
    ],
    "sg:phone":"+1 703 491 4867",
    "sg:postcode":"22191",
    "sg:province":"VA",
    "sg:tags":[
        "shooting",
        "range",
        "indoor",
        "police",
        "supply"
    ],
    "wof:name":"Straighter Shooting Inc",
    "wof:placetype":"venue"
},
  "geometry": {"coordinates":[-77.26008,38.649912],"type":"Point"}
}