{
  "type": "Feature",
  "properties": {
    "addr:full":"10390 Lee Hwy Fairfax VA 22030",
    "addr:housenumber":"10390",
    "addr:postcode":"22030",
    "addr:street":"Lee Hwy",
    "iso:country":"US",
    "sg:address":"10390 Lee Hwy",
    "sg:city":"Fairfax",
    "sg:classifiers":[
        {
            "category":"Home & Garden",
            "subcategory":"Furniture",
            "type":"Retail Goods"
        }
    ],
    "sg:phone":"+1 703 359 9299",
    "sg:postcode":"22030",
    "sg:province":"VA",
    "wof:name":"Parvisian Furniture and Rug",
    "wof:placetype":"venue"
},
  "geometry": {"coordinates":[-77.30189,38.860302],"type":"Point"}
}