{
  "type": "Feature",
  "properties": {
    "addr:full":"12 Cardinal Park Dr SE Suite 107 Leesburg VA 20175",
    "addr:housenumber":"12",
    "addr:postcode":"20175",
    "addr:street":"Cardinal Park Dr Se Suite 107",
    "iso:country":"US",
    "sg:address":"12 Cardinal Park Dr SE Suite 107",
    "sg:city":"Leesburg",
    "sg:classifiers":[
        {
            "category":"Building & Trades",
            "subcategory":"Cleaning & Sanitation",
            "type":"Services"
        },
        {
            "category":"Building & Trades",
            "subcategory":"Construction",
            "type":"Services"
        }
    ],
    "sg:phone":"+1 866 201 0975",
    "sg:postcode":"20175",
    "sg:province":"VA",
    "sg:tags":[
        "repair",
        "systems-repairing",
        "system",
        "specialty",
        "equipment",
        "furnaces-repairing",
        "heating",
        "contractor",
        "air conditioning"
    ],
    "sg:website":"http://local.ingenio.com/Listings/Details.aspx?NUM=a%3a10077200%3a13%3a4859924%3a14%3a0%3a7",
    "wof:name":"M. E. Flow Incorporated",
    "wof:placetype":"venue"
},
  "geometry": {"coordinates":[-77.541145,39.098775],"type":"Point"}
}