{
  "type": "Feature",
  "properties": {
    "addr:full":"208 Taylor St Fredericksburg VA 22405",
    "addr:housenumber":"208",
    "addr:postcode":"22405",
    "addr:street":"Taylor St",
    "iso:country":"US",
    "sg:address":"208 Taylor St",
    "sg:city":"Fredericksburg",
    "sg:classifiers":[
        {
            "category":"Building & Trades",
            "subcategory":"Electrical",
            "type":"Services"
        }
    ],
    "sg:phone":"+1 540 371 1030",
    "sg:postcode":"22405",
    "sg:province":"VA",
    "sg:tags":[
        "electrical",
        "contractor"
    ],
    "wof:name":"CUC Electric",
    "wof:placetype":"venue"
},
  "geometry": {"coordinates":[-77.441197,38.29914],"type":"Point"}
}