{
  "type": "Feature",
  "properties": {
    "iso:country":"US",
    "sg:address":"2000 N Daniel St",
    "sg:city":"Arlington",
    "sg:classifiers":[
        {
            "category":"Real Estate",
            "subcategory":"Real Estate Agent",
            "type":"Services"
        }
    ],
    "sg:phone":"+1 703 469 2272",
    "sg:postcode":"22201",
    "sg:province":"VA",
    "wof:name":"Washington Select Properties",
    "wof:placetype":"venue"
},
  "geometry": {"coordinates":[-77.093355,38.895284],"type":"Point"}
}