{
  "type": "Feature",
  "properties": {
    "addr:full":"135 S Saratoga St Suffolk VA 23434",
    "addr:housenumber":"135",
    "addr:postcode":"23434",
    "addr:street":"S Saratoga St",
    "iso:country":"US",
    "sg:address":"135 S Saratoga St",
    "sg:city":"Suffolk",
    "sg:classifiers":[
        {
            "category":"Manufacturing",
            "subcategory":"Printing",
            "type":"Manufacturing & Wholesale Goods"
        }
    ],
    "sg:phone":"+1 757 925 2222",
    "sg:postcode":"23434",
    "sg:province":"VA",
    "sg:tags":[
        "lithographic",
        "job",
        "commercial",
        "s"
    ],
    "wof:name":"Elevare Inc",
    "wof:placetype":"venue"
},
  "geometry": {"coordinates":[-76.584718,36.728636],"type":"Point"}
}