{
  "type": "Feature",
  "properties": {
    "addr:full":"120 Atlantic St Norfolk VA 23510",
    "addr:housenumber":"120",
    "addr:postcode":"23510",
    "addr:street":"Atlantic St",
    "iso:country":"US",
    "sg:address":"120 Atlantic St",
    "sg:city":"Norfolk",
    "sg:classifiers":[
        {
            "category":"Real Estate",
            "subcategory":"Architect",
            "type":"Services"
        }
    ],
    "sg:phone":"+1 757 321 9600",
    "sg:postcode":"23510",
    "sg:province":"VA",
    "sg:website":"www.hewv.com",
    "wof:name":"Hanbury Evans Wright Vlattas",
    "wof:placetype":"venue"
},
  "geometry": {"coordinates":[-76.29004,36.846174],"type":"Point"}
}