{
  "type": "Feature",
  "properties": {
    "addr:full":"4160 Leake Ave Richmond VA 23224",
    "addr:housenumber":"4160",
    "addr:postcode":"23224",
    "addr:street":"Leake Ave",
    "iso:country":"US",
    "sg:address":"4160 Leake Ave",
    "sg:city":"Richmond",
    "sg:classifiers":[
        {
            "category":"Wholesale",
            "subcategory":"Machinery & Supplies",
            "type":"Manufacturing & Wholesale Goods"
        }
    ],
    "sg:phone":"+1 804 249 3530",
    "sg:postcode":"23224",
    "sg:province":"VA",
    "sg:tags":[
        "equipment"
    ],
    "wof:name":"B & R A1 Contractors",
    "wof:placetype":"venue"
},
  "geometry": {"coordinates":[-77.470383,37.487429],"type":"Point"}
}