{
  "type": "Feature",
  "properties": {
    "addr:full":"2255 Maiden Ln SW Roanoke VA 24015",
    "addr:housenumber":"2255",
    "addr:postcode":"24015",
    "addr:street":"Maiden Ln Sw",
    "iso:country":"US",
    "sg:address":"2255 Maiden Ln SW",
    "sg:city":"Roanoke",
    "sg:classifiers":[
        {
            "category":"Professional",
            "subcategory":"Business Services",
            "type":"Services"
        }
    ],
    "sg:phone":"+1 540 982 3946",
    "sg:postcode":"24015",
    "sg:province":"VA",
    "wof:name":"Lori Brody Associates",
    "wof:placetype":"venue"
},
  "geometry": {"coordinates":[-79.984177,37.264735],"type":"Point"}
}