{
  "type": "Feature",
  "properties": {
    "addr:full":"1165 Sunlight Dr Chesapeake VA 23322",
    "addr:housenumber":"1165",
    "addr:postcode":"23322",
    "addr:street":"Sunlight Dr",
    "iso:country":"US",
    "sg:address":"1165 Sunlight Dr",
    "sg:city":"Chesapeake",
    "sg:classifiers":[
        {
            "category":"Professional",
            "type":"Services"
        }
    ],
    "sg:phone":"+1 757 548 3819",
    "sg:postcode":"23322",
    "sg:province":"VA",
    "wof:name":"Motivational Moments",
    "wof:placetype":"venue"
},
  "geometry": {"coordinates":[-76.285375,36.728848],"type":"Point"}
}