{
  "type": "Feature",
  "properties": {
    "addr:full":"826 Wesley St Petersburg VA 23803",
    "addr:housenumber":"826",
    "addr:postcode":"23803",
    "addr:street":"Wesley St",
    "iso:country":"US",
    "sg:address":"826 Wesley St",
    "sg:city":"Petersburg",
    "sg:classifiers":[
        {
            "category":"Building & Trades",
            "subcategory":"Landscaping Services",
            "type":"Services"
        }
    ],
    "sg:phone":"+1 804 733 7079",
    "sg:postcode":"23803",
    "sg:province":"VA",
    "wof:name":"E B Washington Masonary Inc",
    "wof:placetype":"venue"
},
  "geometry": {"coordinates":[-77.41273,37.216396],"type":"Point"}
}