{
  "type": "Feature",
  "properties": {
    "addr:full":"6869 Springfield Blvd Springfield VA 22150",
    "addr:housenumber":"6869",
    "addr:postcode":"22150",
    "addr:street":"Springfield Blvd",
    "iso:country":"US",
    "sg:address":"6869 Springfield Blvd",
    "sg:city":"Springfield",
    "sg:classifiers":[
        {
            "category":"Real Estate",
            "subcategory":"Real Estate Agent",
            "type":"Services"
        }
    ],
    "sg:phone":"+1 703 912 4800",
    "sg:postcode":"22150",
    "sg:province":"VA",
    "wof:name":"Angelmar Real Estate",
    "wof:placetype":"venue"
},
  "geometry": {"coordinates":[-77.18364200000001,38.778005],"type":"Point"}
}