{
  "type": "Feature",
  "properties": {
    "iso:country":"US",
    "sg:address":"509 Crestwood Dr",
    "sg:city":"Alexandria",
    "sg:classifiers":[
        {
            "category":"Building & Trades",
            "subcategory":"Locksmith",
            "type":"Services"
        }
    ],
    "sg:phone":"+1 571 431 1492",
    "sg:postcode":"22302",
    "sg:province":"VA",
    "sg:tags":[
        "key"
    ],
    "wof:name":"Crestwood Drive 24 Hour Locksmith Service",
    "wof:placetype":"venue"
},
  "geometry": {"coordinates":[-77.07144,38.831834],"type":"Point"}
}