{
  "type": "Feature",
  "properties": {
    "addr:full":"1841 Jeter Rd Powhatan VA 23139",
    "addr:housenumber":"1841",
    "addr:postcode":"23139",
    "addr:street":"Jeter Rd",
    "iso:country":"US",
    "sg:address":"1841 Jeter Rd",
    "sg:city":"Powhatan",
    "sg:classifiers":[
        {
            "category":"Building & Trades",
            "subcategory":"Construction",
            "type":"Services"
        }
    ],
    "sg:phone":"+1 804 598 5553",
    "sg:postcode":"23139",
    "sg:province":"VA",
    "sg:tags":[
        "house"
    ],
    "wof:name":"A & B Builders",
    "wof:placetype":"venue"
},
  "geometry": {"coordinates":[-77.96915,37.521447],"type":"Point"}
}