{
  "type": "Feature",
  "properties": {
    "addr:full":"21571 Beaumeade Cir Ashburn VA 20147",
    "addr:postcode":"21571;20147",
    "addr:street":"Beaumeade Cir",
    "iso:country":"US",
    "sg:address":"21571 Beaumeade Cir",
    "sg:city":"Ashburn",
    "sg:classifiers":[
        {
            "category":"Wholesale",
            "subcategory":"Machinery & Supplies",
            "type":"Manufacturing & Wholesale Goods"
        }
    ],
    "sg:phone":"+1 703 726 0542",
    "sg:postcode":"20147",
    "sg:province":"VA",
    "sg:tags":[
        "equipment",
        "industrial"
    ],
    "wof:name":"Gsi Equipment",
    "wof:placetype":"venue"
},
  "geometry": {"coordinates":[-77.45510299999999,39.02102],"type":"Point"}
}