{
  "type": "Feature",
  "properties": {
    "iso:country":"US",
    "sg:address":"8706 Berwickshire Dr",
    "sg:city":"Richmond",
    "sg:classifiers":[
        {
            "category":"Professional",
            "subcategory":"Business Services",
            "type":"Services"
        }
    ],
    "sg:phone":"+1 804 873 1543",
    "sg:postcode":"23229",
    "sg:province":"VA",
    "wof:name":"Bacon & Eggheads LLC",
    "wof:placetype":"venue"
},
  "geometry": {"coordinates":[-77.57045100000001,37.576113],"type":"Point"}
}