{
  "type": "Feature",
  "properties": {
    "iso:country":"US",
    "sg:address":"19200 Swan Ct",
    "sg:city":"Purcellville",
    "sg:classifiers":[
        {
            "category":"Professional",
            "subcategory":"Management & Consulting",
            "type":"Services"
        }
    ],
    "sg:phone":"+1 540 338 0044",
    "sg:postcode":"20132",
    "sg:province":"VA",
    "wof:name":"C S P Associates",
    "wof:placetype":"venue"
},
  "geometry": {"coordinates":[-77.741714,39.087719],"type":"Point"}
}