{
  "type": "Feature",
  "properties": {
    "iso:country":"US",
    "sg:address":"1016 Grove Ave",
    "sg:city":"Lawrenceville",
    "sg:classifiers":[
        {
            "category":"Organizations",
            "subcategory":"Community Association",
            "type":"Services"
        }
    ],
    "sg:phone":"+1 434 848 2722",
    "sg:postcode":"23868",
    "sg:province":"VA",
    "wof:name":"Veterans of Foreign Wars of US",
    "wof:placetype":"venue"
},
  "geometry": {"coordinates":[-77.859525,36.761881],"type":"Point"}
}