{
  "type": "Feature",
  "properties": {
    "addr:full":"8794 Sacramento Dr Alexandria VA 22309",
    "addr:housenumber":"8794",
    "addr:postcode":"22309",
    "addr:street":"Sacramento Dr",
    "iso:country":"US",
    "sg:address":"8794 Sacramento Dr",
    "sg:city":"Alexandria",
    "sg:classifiers":[
        {
            "category":"Building & Trades",
            "subcategory":"Equipment Rental",
            "type":"Services"
        }
    ],
    "sg:phone":"+1 703 360 5545",
    "sg:postcode":"22309",
    "sg:province":"VA",
    "sg:tags":[
        "leasing",
        "furniture"
    ],
    "wof:name":"Aarons Sales & Lease Ownership",
    "wof:placetype":"venue"
},
  "geometry": {"coordinates":[-77.12655599999999,38.721632],"type":"Point"}
}