{
  "type": "Feature",
  "properties": {
    "iso:country":"US",
    "sg:address":"4200 Cary Street Rd",
    "sg:city":"Richmond",
    "sg:classifiers":[
        {
            "category":"Organizations",
            "subcategory":"Religious Organization",
            "type":"Services"
        }
    ],
    "sg:phone":"+1 804 359 6041",
    "sg:postcode":"23221",
    "sg:province":"VA",
    "sg:tags":[
        "church"
    ],
    "sg:website":"www.reveilleumc.org",
    "wof:name":"Reveille United Methodist Chr",
    "wof:placetype":"venue"
},
  "geometry": {"coordinates":[-77.49596099999999,37.559453],"type":"Point"}
}