{
  "type": "Feature",
  "properties": {
    "iso:country":"US",
    "sg:address":"13451 Dodsworth Dr",
    "sg:city":"Bristow",
    "sg:classifiers":[
        {
            "category":"Communications",
            "type":"Services"
        },
        {
            "category":"Building & Trades",
            "subcategory":"Electrical",
            "type":"Services"
        }
    ],
    "sg:phone":"+1 703 753 3948",
    "sg:postcode":"20136",
    "sg:province":"VA",
    "sg:tags":[
        "television",
        "systems-repair",
        "cable",
        "telephone",
        "contractor",
        "equipment"
    ],
    "wof:name":"Jamie Brand",
    "wof:placetype":"venue"
},
  "geometry": {"coordinates":[-77.593412,38.76189],"type":"Point"}
}