{
  "type": "Feature",
  "properties": {
    "addr:full":"1612 Kecoughtan Rd Hampton VA 23661",
    "addr:housenumber":"1612",
    "addr:postcode":"23661",
    "addr:street":"Kecoughtan Rd",
    "iso:country":"US",
    "sg:address":"1612 Kecoughtan Rd",
    "sg:city":"Hampton",
    "sg:classifiers":[
        {
            "category":"Organizations",
            "subcategory":"Religious Organization",
            "type":"Services"
        }
    ],
    "sg:phone":"+1 757 246 9693",
    "sg:postcode":"23661",
    "sg:province":"VA",
    "sg:tags":[
        "church"
    ],
    "wof:name":"Living Water Tabernacle Baptis",
    "wof:placetype":"venue"
},
  "geometry": {"coordinates":[-76.385102,36.999306],"type":"Point"}
}