{
  "type": "Feature",
  "properties": {
    "addr:full":"775 Gateway Dr SE Leesburg VA 20175",
    "addr:housenumber":"775",
    "addr:postcode":"20175",
    "addr:street":"Gateway Dr Se",
    "iso:country":"US",
    "sg:address":"775 Gateway Dr SE",
    "sg:city":"Leesburg",
    "sg:classifiers":[
        {
            "category":"Utilities",
            "subcategory":"Mobile Phone",
            "type":"Services"
        }
    ],
    "sg:phone":"+1 703 669 6339",
    "sg:postcode":"20175",
    "sg:province":"VA",
    "sg:tags":[
        "communication",
        "radiotelephone"
    ],
    "wof:name":"Net Velocity Wireless",
    "wof:placetype":"venue"
},
  "geometry": {"coordinates":[-77.55907500000001,39.101386],"type":"Point"}
}