{
  "type": "Feature",
  "properties": {
    "addr:full":"27 9th St Lynchburg VA 24504",
    "addr:housenumber":"27",
    "addr:postcode":"24504",
    "addr:street":"9Th St",
    "iso:country":"US",
    "sg:address":"27 9th St",
    "sg:city":"Lynchburg",
    "sg:classifiers":[
        {
            "category":"Museum",
            "type":"Entertainment"
        }
    ],
    "sg:phone":"+1 434 845 1888",
    "sg:postcode":"24504",
    "sg:province":"VA",
    "sg:website":"www.amazementsquare.com",
    "wof:name":"Amazement Square Inc",
    "wof:placetype":"venue"
},
  "geometry": {"coordinates":[-79.140102,37.416185],"type":"Point"}
}