{
  "type": "Feature",
  "properties": {
    "addr:full":"2310 Cunningham Dr Hampton VA 23666",
    "addr:housenumber":"2310",
    "addr:postcode":"23666",
    "addr:street":"Cunningham Dr",
    "iso:country":"US",
    "sg:address":"2310 Cunningham Dr",
    "sg:city":"Hampton",
    "sg:classifiers":[
        {
            "category":"Shopping",
            "subcategory":"Optical Goods",
            "type":"Retail Goods"
        }
    ],
    "sg:phone":"+1 757 838 5933",
    "sg:postcode":"23666",
    "sg:province":"VA",
    "wof:name":"Pearl Vision",
    "wof:placetype":"venue"
},
  "geometry": {"coordinates":[-76.39472499999999,37.046476],"type":"Point"}
}