{
  "type": "Feature",
  "properties": {
    "addr:full":"122 W Main St Orange VA 22960",
    "addr:housenumber":"122",
    "addr:postcode":"22960",
    "addr:street":"W Main St",
    "iso:country":"US",
    "sg:address":"122 W Main St",
    "sg:city":"Orange",
    "sg:classifiers":[
        {
            "category":"Shopping",
            "subcategory":"Clothing, Apparel, & Fashions",
            "type":"Retail Goods"
        }
    ],
    "sg:phone":"+1 540 672 0000",
    "sg:postcode":"22960",
    "sg:province":"VA",
    "wof:name":"Rosebuds Dance N Things",
    "wof:placetype":"venue"
},
  "geometry": {"coordinates":[-78.112227,38.244702],"type":"Point"}
}