{
  "type": "Feature",
  "properties": {
    "iso:country":"US",
    "sg:address":"12720 Directors Loop",
    "sg:city":"Woodbridge",
    "sg:classifiers":[
        {
            "category":"Real Estate",
            "subcategory":"Real Estate Agent",
            "type":"Services"
        }
    ],
    "sg:phone":"+1 703 492 1888",
    "sg:postcode":"22192",
    "sg:province":"VA",
    "sg:tags":[
        "management"
    ],
    "wof:name":"Superior Property Management",
    "wof:placetype":"venue"
},
  "geometry": {"coordinates":[-77.26563,38.6768],"type":"Point"}
}