{
  "type": "Feature",
  "properties": {
    "addr:full":"1107 Westbriar Dr Richmond VA 23238",
    "addr:housenumber":"1107",
    "addr:postcode":"23238",
    "addr:street":"Westbriar Dr",
    "iso:country":"US",
    "sg:address":"1107 Westbriar Dr",
    "sg:city":"Richmond",
    "sg:classifiers":[
        {
            "category":"Health Services",
            "subcategory":"Doctor",
            "type":"Services"
        }
    ],
    "sg:phone":"+1 804 741 2812",
    "sg:postcode":"23238",
    "sg:province":"VA",
    "sg:tags":[
        "dentist"
    ],
    "wof:name":"Stephen S Young DDS",
    "wof:placetype":"venue"
},
  "geometry": {"coordinates":[-77.62285900000001,37.599553],"type":"Point"}
}