{
  "type": "Feature",
  "properties": {
    "addr:full":"3756 Back Rd Woodstock VA 22664",
    "addr:housenumber":"3756",
    "addr:postcode":"22664",
    "addr:street":"Back Rd",
    "iso:country":"US",
    "sg:address":"3756 Back Rd",
    "sg:city":"Woodstock",
    "sg:classifiers":[
        {
            "category":"Building & Trades",
            "subcategory":"Landscaping Services",
            "type":"Services"
        }
    ],
    "sg:phone":"+1 540 459 3998",
    "sg:postcode":"22664",
    "sg:province":"VA",
    "wof:name":"Shenandoah Lawn & Landscape",
    "wof:placetype":"venue"
},
  "geometry": {"coordinates":[-78.574461,38.906575],"type":"Point"}
}