{
  "type": "Feature",
  "properties": {
    "addr:full":"1110 Sparrow Rd Chesapeake VA 23325",
    "addr:housenumber":"1110",
    "addr:postcode":"23325",
    "addr:street":"Sparrow Rd",
    "iso:country":"US",
    "sg:address":"1110 Sparrow Rd",
    "sg:city":"Chesapeake",
    "sg:classifiers":[
        {
            "category":"Personal",
            "subcategory":"Barber",
            "type":"Services"
        }
    ],
    "sg:phone":"+1 757 420 0197",
    "sg:postcode":"23325",
    "sg:province":"VA",
    "wof:name":"Mel's Barber Shop",
    "wof:placetype":"venue"
},
  "geometry": {"coordinates":[-76.22693,36.819924],"type":"Point"}
}