{
  "type": "Feature",
  "properties": {
    "iso:country":"US",
    "sg:address":"1377 Towne Sq Blvd NW",
    "sg:city":"Roanoke",
    "sg:classifiers":[
        {
            "category":"Retail",
            "subcategory":"Portrait Studio",
            "type":"Services"
        }
    ],
    "sg:phone":"+1 540 362 0331",
    "sg:postcode":"24012",
    "sg:province":"VA",
    "sg:tags":[
        "photographer"
    ],
    "wof:name":"Olan Mills Portrait Studio",
    "wof:placetype":"venue"
},
  "geometry": {"coordinates":[-79.962356,37.31875],"type":"Point"}
}