{
  "type": "Feature",
  "properties": {
    "iso:country":"US",
    "sg:address":"15700 River Rd",
    "sg:city":"Germantown",
    "sg:classifiers":[
        {
            "category":"Recreation",
            "type":"Entertainment"
        }
    ],
    "sg:phone":"+1 301 948 5405",
    "sg:postcode":"20874",
    "sg:province":"MD",
    "sg:tags":[
        "instruction",
        "golf"
    ],
    "wof:name":"Golf Pro Shop",
    "wof:placetype":"venue"
},
  "geometry": {"coordinates":[-77.340517,39.078974],"type":"Point"}
}