{
  "type": "Feature",
  "properties": {
    "addr:full":"12918 Livia Dr Catharpin VA 20143",
    "addr:postcode":"12918;20143",
    "addr:street":"Livia Dr",
    "iso:country":"US",
    "sg:address":"12918 Livia Dr",
    "sg:city":"Catharpin",
    "sg:classifiers":[
        {
            "category":"Wholesale",
            "subcategory":"Electrical",
            "type":"Manufacturing & Wholesale Goods"
        }
    ],
    "sg:phone":"+1 703 753 1953",
    "sg:postcode":"20143",
    "sg:province":"VA",
    "sg:tags":[
        "equipment"
    ],
    "wof:name":"Dominion Electric Supply Co",
    "wof:placetype":"venue"
},
  "geometry": {"coordinates":[-77.579244,38.851057],"type":"Point"}
}