{
  "type": "Feature",
  "properties": {
    "addr:full":"4869 Catterton Rd Free Union VA 22940",
    "addr:housenumber":"4869",
    "addr:postcode":"22940",
    "addr:street":"Catterton Rd",
    "iso:country":"US",
    "sg:address":"4869 Catterton Rd",
    "sg:city":"Free Union",
    "sg:classifiers":[
        {
            "category":"Farming",
            "subcategory":"Livestock Farm",
            "type":"Manufacturing & Wholesale Goods"
        }
    ],
    "sg:phone":"+1 434 978 1066",
    "sg:postcode":"22940",
    "sg:province":"VA",
    "sg:tags":[
        "equine"
    ],
    "wof:name":"Dam Ltd",
    "wof:placetype":"venue"
},
  "geometry": {"coordinates":[-78.55923,38.183406],"type":"Point"}
}