{
  "type": "Feature",
  "properties": {
    "addr:full":"1009 Chalbourne Dr Chesapeake VA 23322",
    "addr:housenumber":"1009",
    "addr:postcode":"23322",
    "addr:street":"Chalbourne Dr",
    "iso:country":"US",
    "sg:address":"1009 Chalbourne Dr",
    "sg:city":"Chesapeake",
    "sg:classifiers":[
        {
            "category":"Arts & Performance",
            "subcategory":"Theater",
            "type":"Entertainment"
        }
    ],
    "sg:phone":"+1 757 482 8772",
    "sg:postcode":"23322",
    "sg:province":"VA",
    "sg:tags":[
        "group"
    ],
    "wof:name":"Sound Ex MBL Dj Karaoke Entrmt",
    "wof:placetype":"venue"
},
  "geometry": {"coordinates":[-76.202111,36.686467],"type":"Point"}
}