{
  "type": "Feature",
  "properties": {
    "iso:country":"US",
    "sg:address":"10415 Midlothian Tpke",
    "sg:city":"Richmond",
    "sg:classifiers":[
        {
            "category":"Insurance",
            "subcategory":"Hazard Insurance",
            "type":"Services"
        }
    ],
    "sg:phone":"+1 804 320 2886",
    "sg:postcode":"23235",
    "sg:province":"VA",
    "sg:tags":[
        "commercial",
        "business"
    ],
    "wof:name":"Nationwide Mutual Insurance Companies Agents R",
    "wof:placetype":"venue"
},
  "geometry": {"coordinates":[-77.588641,37.506855],"type":"Point"}
}