{
  "type": "Feature",
  "properties": {
    "addr:full":"388 Pantops Ctr Charlottesville VA 22911",
    "addr:housenumber":"388",
    "addr:postcode":"22911",
    "addr:street":"Pantops Ctr",
    "iso:country":"US",
    "sg:address":"388 Pantops Ctr",
    "sg:city":"Charlottesville",
    "sg:classifiers":[
        {
            "category":"Retail",
            "subcategory":"Veterinary Services",
            "type":"Services"
        }
    ],
    "sg:phone":"+1 434 295 8757",
    "sg:postcode":"22911",
    "sg:province":"VA",
    "sg:tags":[
        "veterinarian"
    ],
    "wof:name":"Animal Medical Center of Charlottesville",
    "wof:placetype":"venue"
},
  "geometry": {"coordinates":[-78.4571,38.031601],"type":"Point"}
}