{
  "type": "Feature",
  "properties": {
    "addr:full":"10350 Launch Cir Apt 101 Manassas VA 20109",
    "addr:housenumber":"10350;101",
    "addr:postcode":"20109",
    "addr:street":"Launch Cir Apt",
    "iso:country":"US",
    "sg:address":"10350 Launch Cir Apt 101",
    "sg:city":"Manassas",
    "sg:classifiers":[
        {
            "category":"Real Estate",
            "subcategory":"Real Estate Services",
            "type":"Services"
        },
        {
            "category":"Building & Trades",
            "subcategory":"Cleaning & Sanitation",
            "type":"Services"
        }
    ],
    "sg:phone":"+1 703 477 5987",
    "sg:postcode":"20109",
    "sg:province":"VA",
    "sg:tags":[
        "maintenance",
        "cleaners-interior"
    ],
    "wof:name":"Mrs. Clean",
    "wof:placetype":"venue"
},
  "geometry": {"coordinates":[-77.504161,38.761413],"type":"Point"}
}