{
  "type": "Feature",
  "properties": {
    "iso:country":"US",
    "sg:address":"225 Bowman Rd",
    "sg:city":"Dayton",
    "sg:classifiers":[
        {
            "category":"Utilities",
            "subcategory":"Telephone",
            "type":"Services"
        }
    ],
    "sg:phone":"+1 540 879 9996",
    "sg:postcode":"22821",
    "sg:province":"VA",
    "sg:tags":[
        "communications"
    ],
    "wof:name":"React Corp",
    "wof:placetype":"venue"
},
  "geometry": {"coordinates":[-78.94070000000001,38.420075],"type":"Point"}
}