{
  "type": "Feature",
  "properties": {
    "addr:full":"5417 Cary Street Rd Richmond VA 23226",
    "addr:housenumber":"5417",
    "addr:postcode":"23226",
    "addr:street":"Cary Street Rd",
    "iso:country":"US",
    "sg:address":"5417 Cary Street Rd",
    "sg:city":"Richmond",
    "sg:classifiers":[
        {
            "category":"Real Estate",
            "subcategory":"Real Estate Agent",
            "type":"Services"
        }
    ],
    "sg:phone":"+1 804 288 0322",
    "sg:postcode":"23226",
    "sg:province":"VA",
    "wof:name":"Drakes Island Properties LLC",
    "wof:placetype":"venue"
},
  "geometry": {"coordinates":[-77.51863299999999,37.568657],"type":"Point"}
}