{
  "type": "Feature",
  "properties": {
    "addr:full":"1100 Cherokee Ct Martinsville VA 24112",
    "addr:housenumber":"1100",
    "addr:postcode":"24112",
    "addr:street":"Cherokee Ct",
    "iso:country":"US",
    "sg:address":"1100 Cherokee Ct",
    "sg:city":"Martinsville",
    "sg:classifiers":[
        {
            "category":"Professional",
            "subcategory":"Management & Consulting",
            "type":"Services"
        }
    ],
    "sg:phone":"+1 276 656 6719",
    "sg:postcode":"24112",
    "sg:province":"VA",
    "sg:tags":[
        "business"
    ],
    "wof:name":"J W R Associates",
    "wof:placetype":"venue"
},
  "geometry": {"coordinates":[-79.853596,36.66413],"type":"Point"}
}