{
  "type": "Feature",
  "properties": {
    "iso:country":"US",
    "sg:address":"408 N Main St",
    "sg:city":"Danville",
    "sg:classifiers":[
        {
            "category":"Building & Trades",
            "subcategory":"Construction",
            "type":"Services"
        }
    ],
    "sg:phone":"+1 434 792 1422",
    "sg:postcode":"24540",
    "sg:province":"VA",
    "sg:tags":[
        "roofing",
        "contractor"
    ],
    "wof:name":"A S Pugh Roofing Co",
    "wof:placetype":"venue"
},
  "geometry": {"coordinates":[-79.385524,36.59475],"type":"Point"}
}