{
  "type": "Feature",
  "properties": {
    "iso:country":"US",
    "sg:address":"609 E Lynn Shores Cir",
    "sg:city":"Virginia Beach",
    "sg:classifiers":[
        {
            "category":"Health Services",
            "subcategory":"Doctor",
            "type":"Services"
        }
    ],
    "sg:phone":"+1 757 486 8079",
    "sg:postcode":"23452",
    "sg:province":"VA",
    "sg:tags":[
        "medical"
    ],
    "wof:name":"Convenient Care Medical Center",
    "wof:placetype":"venue"
},
  "geometry": {"coordinates":[-76.11252399999999,36.856367],"type":"Point"}
}