{
  "type": "Feature",
  "properties": {
    "addr:full":"11175 Ridgefield Pkwy Richmond VA 23233",
    "addr:housenumber":"11175",
    "addr:postcode":"23233",
    "addr:street":"Ridgefield Pkwy",
    "iso:country":"US",
    "sg:address":"11175 Ridgefield Pkwy",
    "sg:city":"Richmond",
    "sg:classifiers":[
        {
            "category":"Real Estate",
            "subcategory":"Real Estate Services",
            "type":"Services"
        }
    ],
    "sg:phone":"+1 804 741 5522",
    "sg:postcode":"23233",
    "sg:province":"VA",
    "sg:tags":[
        "company",
        "title"
    ],
    "wof:name":"Capital City Title & Escrow",
    "wof:placetype":"venue"
},
  "geometry": {"coordinates":[-77.638018,37.623929],"type":"Point"}
}