{
  "type": "Feature",
  "properties": {
    "addr:full":"5604 Shannon Ct Woodbridge VA 22193",
    "addr:housenumber":"5604",
    "addr:postcode":"22193",
    "addr:street":"Shannon Ct",
    "iso:country":"US",
    "sg:address":"5604 Shannon Ct",
    "sg:city":"Woodbridge",
    "sg:classifiers":[
        {
            "category":"Professional",
            "type":"Services"
        }
    ],
    "sg:phone":"+1 703 730 0510",
    "sg:postcode":"22193",
    "sg:province":"VA",
    "wof:name":"Salvador Escobar",
    "wof:placetype":"venue"
},
  "geometry": {"coordinates":[-77.375951,38.639175],"type":"Point"}
}