{
  "type": "Feature",
  "properties": {
    "addr:full":"6818 Roanoke Rd Shawsville VA 24162",
    "addr:housenumber":"6818",
    "addr:postcode":"24162",
    "addr:street":"Roanoke Rd",
    "iso:country":"US",
    "sg:address":"6818 Roanoke Rd",
    "sg:city":"Shawsville",
    "sg:classifiers":[
        {
            "category":"Home & Garden",
            "subcategory":"Mobile Homes",
            "type":"Retail Goods"
        }
    ],
    "sg:phone":"+1 540 268 5000",
    "sg:postcode":"24162",
    "sg:province":"VA",
    "wof:name":"Heritage Homes",
    "wof:placetype":"venue"
},
  "geometry": {"coordinates":[-80.259474,37.168469],"type":"Point"}
}