{
  "type": "Feature",
  "properties": {
    "iso:country":"US",
    "sg:address":"492 E Main St",
    "sg:city":"Abingdon",
    "sg:classifiers":[
        {
            "category":"Real Estate",
            "subcategory":"Real Estate Agent",
            "type":"Services"
        }
    ],
    "sg:phone":"+1 276 628 8131",
    "sg:postcode":"24210",
    "sg:province":"VA",
    "sg:website":"www.century21shamrock.com",
    "wof:name":"Shamrock Realty",
    "wof:placetype":"venue"
},
  "geometry": {"coordinates":[-81.96181799999999,36.714773],"type":"Point"}
}