{
  "type": "Feature",
  "properties": {
    "addr:full":"15844 Kings Hwy King George VA 22485",
    "addr:housenumber":"15844",
    "addr:postcode":"22485",
    "addr:street":"Kings Hwy",
    "iso:country":"US",
    "sg:address":"15844 Kings Hwy",
    "sg:city":"King George",
    "sg:classifiers":[
        {
            "category":"Building & Trades",
            "subcategory":"Electrical",
            "type":"Services"
        }
    ],
    "sg:phone":"+1 540 775 7866",
    "sg:postcode":"22485",
    "sg:province":"VA",
    "sg:tags":[
        "electrical",
        "electric",
        "contractor"
    ],
    "wof:name":"King George Electric Supply Co",
    "wof:placetype":"venue"
},
  "geometry": {"coordinates":[-77.073747,38.191406],"type":"Point"}
}