{
  "type": "Feature",
  "properties": {
    "addr:full":"9820 Flagler Rd Fort Belvoir VA 22060",
    "addr:housenumber":"9820",
    "addr:postcode":"22060",
    "addr:street":"Flagler Rd",
    "iso:country":"US",
    "sg:address":"9820 Flagler Rd",
    "sg:city":"Fort Belvoir",
    "sg:classifiers":[
        {
            "category":"Government",
            "subcategory":"Office",
            "type":"Public Place"
        }
    ],
    "sg:phone":"+1 703 805 2052",
    "sg:postcode":"22060",
    "sg:province":"VA",
    "sg:tags":[
        "national",
        "security"
    ],
    "wof:name":"United States Dept of Army",
    "wof:placetype":"venue"
},
  "geometry": {"coordinates":[-77.132349,38.690217],"type":"Point"}
}