{
  "type": "Feature",
  "properties": {
    "addr:full":"1507 Hershberger Rd NW Roanoke VA 24012",
    "addr:housenumber":"1507",
    "addr:postcode":"24012",
    "addr:street":"Hershberger Rd Nw",
    "iso:country":"US",
    "sg:address":"1507 Hershberger Rd NW",
    "sg:city":"Roanoke",
    "sg:classifiers":[
        {
            "category":"Personal",
            "subcategory":"Beauty Salon",
            "type":"Services"
        }
    ],
    "sg:phone":"+1 540 265 7877",
    "sg:postcode":"24012",
    "sg:province":"VA",
    "sg:tags":[
        "shop"
    ],
    "wof:name":"Wonder Nails",
    "wof:placetype":"venue"
},
  "geometry": {"coordinates":[-79.96114799999999,37.314645],"type":"Point"}
}