{
  "type": "Feature",
  "properties": {
    "iso:country":"US",
    "sg:address":"7293 Jay Way",
    "sg:city":"Mechanicsville",
    "sg:classifiers":[
        {
            "category":"Professional",
            "subcategory":"Business Services",
            "type":"Services"
        }
    ],
    "sg:phone":"+1 804 730 4991",
    "sg:postcode":"23111",
    "sg:province":"VA",
    "sg:tags":[
        "organizing"
    ],
    "wof:name":"Simply Organized",
    "wof:placetype":"venue"
},
  "geometry": {"coordinates":[-77.33247900000001,37.604441],"type":"Point"}
}