{
  "type": "Feature",
  "properties": {
    "iso:country":"US",
    "sg:address":"3828 Farr Oak Cir",
    "sg:city":"Fairfax",
    "sg:classifiers":[
        {
            "category":"Professional",
            "subcategory":"Management & Consulting",
            "type":"Services"
        }
    ],
    "sg:phone":"+1 703 934 4218",
    "sg:postcode":"22030",
    "sg:province":"VA",
    "wof:name":"Logvalu",
    "wof:placetype":"venue"
},
  "geometry": {"coordinates":[-77.29573000000001,38.849119],"type":"Point"}
}