{
  "type": "Feature",
  "properties": {
    "addr:full":"1018 Millwood Pike Winchester VA 22602",
    "addr:housenumber":"1018",
    "addr:postcode":"22602",
    "addr:street":"Millwood Pike",
    "iso:country":"US",
    "sg:address":"1018 Millwood Pike",
    "sg:city":"Winchester",
    "sg:classifiers":[
        {
            "category":"Building & Trades",
            "subcategory":"Construction",
            "type":"Services"
        }
    ],
    "sg:phone":"+1 540 535 2244",
    "sg:postcode":"22602",
    "sg:province":"VA",
    "sg:tags":[
        "concrete",
        "contractor"
    ],
    "wof:name":"Novacon Inc",
    "wof:placetype":"venue"
},
  "geometry": {"coordinates":[-78.15375,39.160347],"type":"Point"}
}