{
  "type": "Feature",
  "properties": {
    "iso:country":"US",
    "sg:address":"310 S Franklin St",
    "sg:city":"Christiansburg",
    "sg:classifiers":[
        {
            "category":"Organizations",
            "subcategory":"Religious Organization",
            "type":"Services"
        }
    ],
    "sg:phone":"+1 540 382 2221",
    "sg:postcode":"24073",
    "sg:province":"VA",
    "sg:tags":[
        "church"
    ],
    "wof:name":"Church Of The Brethren",
    "wof:placetype":"venue"
},
  "geometry": {"coordinates":[-80.40448000000001,37.126509],"type":"Point"}
}