{
  "type": "Feature",
  "properties": {
    "addr:full":"1700 Huguenot Rd Midlothian VA 23113",
    "addr:housenumber":"1700",
    "addr:postcode":"23113",
    "addr:street":"Huguenot Rd",
    "iso:country":"US",
    "sg:address":"1700 Huguenot Rd",
    "sg:city":"Midlothian",
    "sg:classifiers":[
        {
            "category":"Real Estate",
            "subcategory":"Real Estate Services",
            "type":"Services"
        }
    ],
    "sg:phone":"+1 804 594 2771",
    "sg:postcode":"23113",
    "sg:province":"VA",
    "sg:tags":[
        "abstract",
        "title"
    ],
    "wof:name":"Frontier Title",
    "wof:placetype":"venue"
},
  "geometry": {"coordinates":[-77.615855,37.517112],"type":"Point"}
}