{
  "type": "Feature",
  "properties": {
    "addr:full":"216 E Main St Richmond VA 23219",
    "addr:housenumber":"216",
    "addr:postcode":"23219",
    "addr:street":"E Main St",
    "iso:country":"US",
    "sg:address":"216 E Main St",
    "sg:city":"Richmond",
    "sg:classifiers":[
        {
            "category":"Professional",
            "subcategory":"Advertising",
            "type":"Services"
        }
    ],
    "sg:phone":"+1 804 643 4003",
    "sg:postcode":"23219",
    "sg:province":"VA",
    "sg:tags":[
        "designer",
        "display",
        "producer"
    ],
    "wof:name":"R T Sunday Co",
    "wof:placetype":"venue"
},
  "geometry": {"coordinates":[-77.441765,37.541584],"type":"Point"}
}