{
  "type": "Feature",
  "properties": {
    "iso:country":"US",
    "sg:address":"2412 10th St NW",
    "sg:city":"Roanoke",
    "sg:classifiers":[
        {
            "category":"Building & Trades",
            "subcategory":"Electrical",
            "type":"Services"
        }
    ],
    "sg:phone":"+1 540 366 1796",
    "sg:postcode":"24012",
    "sg:province":"VA",
    "sg:tags":[
        "electrician",
        "contractor"
    ],
    "wof:name":"M & M Electrical Contracting Inc",
    "wof:placetype":"venue"
},
  "geometry": {"coordinates":[-79.946797,37.29667],"type":"Point"}
}