{
  "type": "Feature",
  "properties": {
    "iso:country":"US",
    "sg:address":"400 Sugar Maple Ln",
    "sg:city":"Harrisonburg",
    "sg:classifiers":[
        {
            "category":"Farming",
            "subcategory":"Poultry Farm",
            "type":"Manufacturing & Wholesale Goods"
        }
    ],
    "sg:phone":"+1 540 434 6650",
    "sg:postcode":"22801",
    "sg:province":"VA",
    "sg:tags":[
        "chicken"
    ],
    "wof:name":"W Heatwole",
    "wof:placetype":"venue"
},
  "geometry": {"coordinates":[-78.917574,38.447373],"type":"Point"}
}