{
  "type": "Feature",
  "properties": {
    "addr:full":"1700 W Pembroke Ave Hampton VA 23661",
    "addr:housenumber":"1700",
    "addr:postcode":"23661",
    "addr:street":"W Pembroke Ave",
    "iso:country":"US",
    "sg:address":"1700 W Pembroke Ave",
    "sg:city":"Hampton",
    "sg:classifiers":[
        {
            "category":"Retail",
            "subcategory":"Auto Repair",
            "type":"Services"
        }
    ],
    "sg:phone":"+1 757 723 6356",
    "sg:postcode":"23661",
    "sg:province":"VA",
    "sg:tags":[
        "repairing",
        "automobile"
    ],
    "wof:name":"German Motor Svc",
    "wof:placetype":"venue"
},
  "geometry": {"coordinates":[-76.381379,37.015519],"type":"Point"}
}