{
  "type": "Feature",
  "properties": {
    "addr:full":"417 Old York-Hampton Hwy Yorktown VA 23692",
    "addr:housenumber":"417",
    "addr:postcode":"23692",
    "addr:street":"Old York-Hampton Hwy",
    "iso:country":"US",
    "sg:address":"417 Old York-Hampton Hwy",
    "sg:city":"Yorktown",
    "sg:classifiers":[
        {
            "category":"Building & Trades",
            "subcategory":"Plumbing",
            "type":"Services"
        }
    ],
    "sg:phone":"+1 757 890 2600",
    "sg:postcode":"23692",
    "sg:province":"VA",
    "sg:tags":[
        "contractor"
    ],
    "wof:name":"Buds Heating & AC",
    "wof:placetype":"venue"
},
  "geometry": {"coordinates":[-76.48037100000001,37.18149],"type":"Point"}
}