{
  "type": "Feature",
  "properties": {
    "iso:country":"US",
    "sg:address":"35 Robinson Ln",
    "sg:city":"Emporia",
    "sg:classifiers":[
        {
            "category":"Building & Trades",
            "subcategory":"Construction",
            "type":"Services"
        }
    ],
    "sg:phone":"+1 434 634 4407",
    "sg:postcode":"23847",
    "sg:province":"VA",
    "sg:tags":[
        "installs",
        "layer",
        "carpet",
        "floor",
        "covering"
    ],
    "wof:name":"Jordans Carpet & Floor Service",
    "wof:placetype":"venue"
},
  "geometry": {"coordinates":[-77.532929,36.717031],"type":"Point"}
}