{
  "type": "Feature",
  "properties": {
    "iso:country":"US",
    "sg:address":"143 Fox Meadow Ln",
    "sg:city":"Winchester",
    "sg:classifiers":[
        {
            "category":"Home & Garden",
            "subcategory":"Building Materials",
            "type":"Retail Goods"
        },
        {
            "category":"Professional",
            "subcategory":"Business Services",
            "type":"Services"
        }
    ],
    "sg:phone":"+1 540 662 6265",
    "sg:postcode":"22602",
    "sg:province":"VA",
    "sg:tags":[
        "interior",
        "consultant",
        "design",
        "decorator"
    ],
    "wof:name":"Ponn Design Group Inc",
    "wof:placetype":"venue"
},
  "geometry": {"coordinates":[-78.220024,39.164595],"type":"Point"}
}