{
  "type": "Feature",
  "properties": {
    "addr:full":"305 W Morgan Ave Pennington Gap VA 24277",
    "addr:housenumber":"305",
    "addr:postcode":"24277",
    "addr:street":"W Morgan Ave",
    "iso:country":"US",
    "sg:address":"305 W Morgan Ave",
    "sg:city":"Pennington Gap",
    "sg:classifiers":[
        {
            "category":"Home & Garden",
            "subcategory":"Household Appliances",
            "type":"Retail Goods"
        }
    ],
    "sg:phone":"+1 276 546 5121",
    "sg:postcode":"24277",
    "sg:province":"VA",
    "sg:tags":[
        "cleaners",
        "vacuum"
    ],
    "sg:website":"www.vacuum-outlet.com",
    "wof:name":"Vacuum Outlet",
    "wof:placetype":"venue"
},
  "geometry": {"coordinates":[-83.029533,36.757139],"type":"Point"}
}