{
  "type": "Feature",
  "properties": {
    "iso:country":"US",
    "sg:address":"7461 Mums Dr",
    "sg:city":"Alexandria",
    "sg:classifiers":[
        {
            "category":"Professional",
            "type":"Services"
        }
    ],
    "sg:phone":"+1 703 660 8533",
    "sg:postcode":"22306",
    "sg:province":"VA",
    "wof:name":"Alvarez Brothers Co Inc",
    "wof:placetype":"venue"
},
  "geometry": {"coordinates":[-77.081013,38.757526],"type":"Point"}
}