{
  "type": "Feature",
  "properties": {
    "addr:full":"10321 Grendel Ct Mechanicsville VA 23116",
    "addr:postcode":"10321;23116",
    "addr:street":"Grendel Ct",
    "iso:country":"US",
    "sg:address":"10321 Grendel Ct",
    "sg:city":"Mechanicsville",
    "sg:classifiers":[
        {
            "category":"Professional",
            "subcategory":"Computer Services",
            "type":"Services"
        }
    ],
    "sg:phone":"+1 804 550 7125",
    "sg:postcode":"23116",
    "sg:province":"VA",
    "sg:tags":[
        "consultant",
        "designer"
    ],
    "wof:name":"Jdt Consulting",
    "wof:placetype":"venue"
},
  "geometry": {"coordinates":[-77.412994,37.689853],"type":"Point"}
}