{
  "type": "Feature",
  "properties": {
    "addr:full":"5840 Kingstowne Ctr # 110 Alexandria VA 22315",
    "addr:housenumber":"5840",
    "addr:postcode":"22315",
    "addr:street":"Kingstowne Ctr # 110",
    "iso:country":"US",
    "sg:address":"5840 Kingstowne Ctr # 110",
    "sg:city":"Alexandria",
    "sg:classifiers":[
        {
            "category":"Personal",
            "subcategory":"Nail Salon",
            "type":"Services"
        }
    ],
    "sg:phone":"+1 703 313 9050",
    "sg:postcode":"22315",
    "sg:province":"VA",
    "wof:name":"Nails Club 2",
    "wof:placetype":"venue"
},
  "geometry": {"coordinates":[-77.136977,38.770826],"type":"Point"}
}