{
  "type": "Feature",
  "properties": {
    "iso:country":"US",
    "sg:address":"2203 Orange Ave NE",
    "sg:city":"Roanoke",
    "sg:classifiers":[
        {
            "category":"Restaurant",
            "type":"Food & Drink"
        }
    ],
    "sg:phone":"+1 540 344 1688",
    "sg:postcode":"24012",
    "sg:province":"VA",
    "wof:name":"Rally's Hamburgers Inc",
    "wof:placetype":"venue"
},
  "geometry": {"coordinates":[-79.909735,37.290373],"type":"Point"}
}