{
  "type": "Feature",
  "properties": {
    "addr:full":"550 N Main St Blacksburg VA 24060",
    "addr:housenumber":"550",
    "addr:postcode":"24060",
    "addr:street":"N Main St",
    "iso:country":"US",
    "sg:address":"550 N Main St",
    "sg:city":"Blacksburg",
    "sg:classifiers":[
        {
            "category":"Organizations",
            "subcategory":"Religious Organization",
            "type":"Services"
        }
    ],
    "sg:phone":"+1 434 316 9178",
    "sg:postcode":"24060",
    "sg:province":"VA",
    "sg:tags":[
        "church"
    ],
    "wof:name":"Music School-Blacksburg Baptst",
    "wof:placetype":"venue"
},
  "geometry": {"coordinates":[-80.417203,37.232536],"type":"Point"}
}