{
  "type": "Feature",
  "properties": {
    "iso:country":"US",
    "sg:address":"924 S Oriole Dr",
    "sg:city":"Virginia Beach",
    "sg:classifiers":[
        {
            "category":"Building & Trades",
            "subcategory":"Landscaping Services",
            "type":"Services"
        }
    ],
    "sg:phone":"+1 757 422 2450",
    "sg:postcode":"23451",
    "sg:province":"VA",
    "wof:name":"Yard Man LLC",
    "wof:placetype":"venue"
},
  "geometry": {"coordinates":[-75.990073,36.854882],"type":"Point"}
}