{
  "type": "Feature",
  "properties": {
    "addr:full":"13004 New Austin Ct Herndon VA 20171",
    "addr:housenumber":"13004",
    "addr:postcode":"20171",
    "addr:street":"New Austin Ct",
    "iso:country":"US",
    "sg:address":"13004 New Austin Ct",
    "sg:city":"Herndon",
    "sg:classifiers":[
        {
            "category":"Insurance",
            "subcategory":"Insurance Agent",
            "type":"Services"
        }
    ],
    "sg:phone":"+1 703 471 7528",
    "sg:postcode":"20171",
    "sg:province":"VA",
    "wof:name":"RGI Ltd",
    "wof:placetype":"venue"
},
  "geometry": {"coordinates":[-77.39613900000001,38.934112],"type":"Point"}
}