{
  "type": "Feature",
  "properties": {
    "addr:full":"4540 Plank Rd Fredericksburg VA 22407",
    "addr:housenumber":"4540",
    "addr:postcode":"22407",
    "addr:street":"Plank Rd",
    "iso:country":"US",
    "sg:address":"4540 Plank Rd",
    "sg:city":"Fredericksburg",
    "sg:classifiers":[
        {
            "category":"Building & Trades",
            "subcategory":"Construction",
            "type":"Services"
        }
    ],
    "sg:phone":"+1 540 548 2900",
    "sg:postcode":"22407",
    "sg:province":"VA",
    "sg:tags":[
        "house"
    ],
    "wof:name":"Cantrell Builders",
    "wof:placetype":"venue"
},
  "geometry": {"coordinates":[-77.539131,38.288887],"type":"Point"}
}