{
  "type": "Feature",
  "properties": {
    "iso:country":"US",
    "sg:address":"1113 Rose Ln",
    "sg:city":"Virginia Beach",
    "sg:classifiers":[
        {
            "category":"Real Estate",
            "subcategory":"Real Estate Agent",
            "type":"Services"
        }
    ],
    "sg:phone":"+1 757 428 3509",
    "sg:postcode":"23451",
    "sg:province":"VA",
    "wof:name":"Molloy Realty Associates Inc",
    "wof:placetype":"venue"
},
  "geometry": {"coordinates":[-75.99816300000001,36.871598],"type":"Point"}
}