{
  "type": "Feature",
  "properties": {
    "iso:country":"US",
    "sg:address":"1110 Moles Farm Rd",
    "sg:city":"Vinton",
    "sg:classifiers":[
        {
            "category":"Recreation",
            "type":"Entertainment"
        }
    ],
    "sg:phone":"+1 540 593 2441",
    "sg:postcode":"24179",
    "sg:province":"VA",
    "sg:tags":[
        "stable"
    ],
    "wof:name":"Earl Moles Stables",
    "wof:placetype":"venue"
},
  "geometry": {"coordinates":[-79.74389600000001,37.260326],"type":"Point"}
}