{
  "type": "Feature",
  "properties": {
    "iso:country":"US",
    "sg:address":"405 Lynnfield Rd",
    "sg:city":"Chesapeake",
    "sg:classifiers":[
        {
            "category":"Building & Trades",
            "subcategory":"Landscaping Services",
            "type":"Services"
        }
    ],
    "sg:phone":"+1 757 487 7383",
    "sg:postcode":"23323",
    "sg:province":"VA",
    "wof:name":"Hamilton Lawn & Garden Service",
    "wof:placetype":"venue"
},
  "geometry": {"coordinates":[-76.325947,36.725833],"type":"Point"}
}