{
  "type": "Feature",
  "properties": {
    "addr:full":"13921 Tall Timber Ct Gainesville VA 20155",
    "addr:housenumber":"13921",
    "addr:postcode":"20155",
    "addr:street":"Tall Timber Ct",
    "iso:country":"US",
    "sg:address":"13921 Tall Timber Ct",
    "sg:city":"Gainesville",
    "sg:classifiers":[
        {
            "category":"Organizations",
            "subcategory":"Community Association",
            "type":"Services"
        }
    ],
    "sg:phone":"+1 703 754 7639",
    "sg:postcode":"20155",
    "sg:province":"VA",
    "wof:name":"Prince Wlliam Cnty Yuth Ftball",
    "wof:placetype":"venue"
},
  "geometry": {"coordinates":[-77.603407,38.775193],"type":"Point"}
}