{
  "type": "Feature",
  "properties": {
    "addr:full":"8000 Jefferson Davis Hwy Richmond VA 23237",
    "addr:housenumber":"8000",
    "addr:postcode":"23237",
    "addr:street":"Jefferson Davis Hwy",
    "iso:country":"US",
    "sg:address":"8000 Jefferson Davis Hwy",
    "sg:city":"Richmond",
    "sg:classifiers":[
        {
            "category":"Travel",
            "subcategory":"Travel Agent",
            "type":"Entertainment"
        }
    ],
    "sg:phone":"+1 804 271 3850",
    "sg:postcode":"23237",
    "sg:province":"VA",
    "sg:tags":[
        "agency",
        "bureau"
    ],
    "wof:name":"Omega World Travel",
    "wof:placetype":"venue"
},
  "geometry": {"coordinates":[-77.436345,37.416357],"type":"Point"}
}