{
  "type": "Feature",
  "properties": {
    "addr:full":"205 Summit Ct Hampton VA 23666",
    "addr:housenumber":"205",
    "addr:postcode":"23666",
    "addr:street":"Summit Ct",
    "iso:country":"US",
    "sg:address":"205 Summit Ct",
    "sg:city":"Hampton",
    "sg:classifiers":[
        {
            "category":"Organizations",
            "subcategory":"Community Association",
            "type":"Services"
        }
    ],
    "sg:phone":"+1 757 827 0237",
    "sg:postcode":"23666",
    "sg:province":"VA",
    "wof:name":"Harbor View Owners Association",
    "wof:placetype":"venue"
},
  "geometry": {"coordinates":[-76.43393,37.050084],"type":"Point"}
}