{
  "type": "Feature",
  "properties": {
    "addr:full":"6360 Chestnut Hill Rd Virginia Beach VA 23464",
    "addr:housenumber":"6360",
    "addr:postcode":"23464",
    "addr:street":"Chestnut Hill Rd",
    "iso:country":"US",
    "sg:address":"6360 Chestnut Hill Rd",
    "sg:city":"Virginia Beach",
    "sg:classifiers":[
        {
            "category":"Professional",
            "subcategory":"Management & Consulting",
            "type":"Services"
        }
    ],
    "sg:phone":"+1 757 366 3118",
    "sg:postcode":"23464",
    "sg:province":"VA",
    "sg:tags":[
        "consultant",
        "training"
    ],
    "wof:name":"R M Swindell",
    "wof:placetype":"venue"
},
  "geometry": {"coordinates":[-76.21224599999999,36.79872],"type":"Point"}
}