{
  "type": "Feature",
  "properties": {
    "addr:full":"9800 Winchester Rd Front Royal VA 22630",
    "addr:housenumber":"9800",
    "addr:postcode":"22630",
    "addr:street":"Winchester Rd",
    "iso:country":"US",
    "sg:address":"9800 Winchester Rd",
    "sg:city":"Front Royal",
    "sg:classifiers":[
        {
            "category":"Travel",
            "subcategory":"Hotels & Motels",
            "type":"Entertainment"
        }
    ],
    "sg:phone":"+1 540 635 1882",
    "sg:postcode":"22630",
    "sg:province":"VA",
    "wof:name":"Hampton Inn",
    "wof:placetype":"venue"
},
  "geometry": {"coordinates":[-78.194102,38.959536],"type":"Point"}
}