{
  "type": "Feature",
  "properties": {
    "iso:country":"US",
    "sg:address":"1632 Jolliff Rd",
    "sg:city":"Chesapeake",
    "sg:classifiers":[
        {
            "category":"Building & Trades",
            "subcategory":"Construction",
            "type":"Services"
        }
    ],
    "sg:phone":"+1 757 488 6369",
    "sg:postcode":"23321",
    "sg:province":"VA",
    "sg:tags":[
        "house",
        "general",
        "contractor"
    ],
    "wof:name":"First Class Builders",
    "wof:placetype":"venue"
},
  "geometry": {"coordinates":[-76.4387,36.803717],"type":"Point"}
}