{
  "type": "Feature",
  "properties": {
    "iso:country":"US",
    "sg:address":"160 N Massanutten St",
    "sg:city":"Strasburg",
    "sg:classifiers":[
        {
            "category":"Shopping",
            "subcategory":"Used Merchandise",
            "type":"Retail Goods"
        },
        {
            "category":"Professional",
            "subcategory":"Business Services",
            "type":"Services"
        }
    ],
    "sg:phone":"+1 540 465 3550",
    "sg:postcode":"22657",
    "sg:province":"VA",
    "sg:tags":[
        "flea",
        "market"
    ],
    "wof:name":"Strassburg Flea Market",
    "wof:placetype":"venue"
},
  "geometry": {"coordinates":[-78.358559,38.98891],"type":"Point"}
}