{
  "type": "Feature",
  "properties": {
    "addr:full":"111 N Pitt St Alexandria VA 22314",
    "addr:housenumber":"111",
    "addr:postcode":"22314",
    "addr:street":"N Pitt St",
    "iso:country":"US",
    "sg:address":"111 N Pitt St",
    "sg:city":"Alexandria",
    "sg:classifiers":[
        {
            "category":"Restaurant",
            "type":"Food & Drink"
        }
    ],
    "sg:phone":"+1 703 549 4535",
    "sg:postcode":"22314",
    "sg:province":"VA",
    "sg:tags":[
        "eating"
    ],
    "wof:name":"Pat Troy's Restaurant & Pub",
    "wof:placetype":"venue"
},
  "geometry": {"coordinates":[-77.044527,38.805412],"type":"Point"}
}