{
  "type": "Feature",
  "properties": {
    "iso:country":"US",
    "sg:address":"9780 Centerville Rd",
    "sg:city":"Bridgewater",
    "sg:classifiers":[
        {
            "category":"Wholesale",
            "subcategory":"Hardware",
            "type":"Manufacturing & Wholesale Goods"
        }
    ],
    "sg:phone":"+1 540 828 6369",
    "sg:postcode":"22812",
    "sg:province":"VA",
    "sg:tags":[
        "refrigerating"
    ],
    "wof:name":"Byrds Refrigeration",
    "wof:placetype":"venue"
},
  "geometry": {"coordinates":[-78.992786,38.354571],"type":"Point"}
}