{
  "type": "Feature",
  "properties": {
    "addr:full":"1248 Kegman Rd Chesapeake VA 23322",
    "addr:housenumber":"1248",
    "addr:postcode":"23322",
    "addr:street":"Kegman Rd",
    "iso:country":"US",
    "sg:address":"1248 Kegman Rd",
    "sg:city":"Chesapeake",
    "sg:classifiers":[
        {
            "category":"Building & Trades",
            "subcategory":"Cleaning & Sanitation",
            "type":"Services"
        },
        {
            "category":"Building & Trades",
            "subcategory":"Construction",
            "type":"Services"
        }
    ],
    "sg:phone":"+1 757 482 8028",
    "sg:postcode":"23322",
    "sg:province":"VA",
    "sg:tags":[
        "ceiling",
        "washing",
        "deck",
        "acoustical",
        "pressure",
        "restoration",
        "patio"
    ],
    "wof:name":"Best Under Pressure Inc",
    "wof:placetype":"venue"
},
  "geometry": {"coordinates":[-76.22903599999999,36.683654],"type":"Point"}
}