{
  "type": "Feature",
  "properties": {
    "addr:full":"46440 Benedict Dr Sterling VA 20164",
    "addr:postcode":"46440;20164",
    "addr:street":"Benedict Dr",
    "iso:country":"US",
    "sg:address":"46440 Benedict Dr",
    "sg:city":"Sterling",
    "sg:classifiers":[
        {
            "category":"Health Services",
            "subcategory":"Health Practitioner",
            "type":"Services"
        }
    ],
    "sg:phone":"+1 703 450 7114",
    "sg:postcode":"20164",
    "sg:province":"VA",
    "wof:name":"Andrew E Dmds Bluhm",
    "wof:placetype":"venue"
},
  "geometry": {"coordinates":[-77.39437700000001,39.024643],"type":"Point"}
}