{
  "type": "Feature",
  "properties": {
    "addr:full":"2 Loudoun St SE Leesburg VA 20175",
    "addr:housenumber":"2",
    "addr:postcode":"20175",
    "addr:street":"Loudoun St Se",
    "iso:country":"US",
    "sg:address":"2 Loudoun St SE",
    "sg:city":"Leesburg",
    "sg:classifiers":[
        {
            "category":"Shopping",
            "type":"Retail Goods"
        }
    ],
    "sg:phone":"+1 703 771 8696",
    "sg:postcode":"20175",
    "sg:province":"VA",
    "sg:tags":[
        "merchandise"
    ],
    "wof:name":"Art Medlin Ltd",
    "wof:placetype":"venue"
},
  "geometry": {"coordinates":[-77.56509200000001,39.114246],"type":"Point"}
}