{
  "type": "Feature",
  "properties": {
    "iso:country":"US",
    "sg:address":"6319 Telegraph Rd",
    "sg:city":"Alexandria",
    "sg:classifiers":[
        {
            "category":"Professional",
            "subcategory":"Accounting & Tax Preparation",
            "type":"Services"
        }
    ],
    "sg:phone":"+1 703 960 3253",
    "sg:postcode":"22310",
    "sg:province":"VA",
    "wof:name":"Baltodanos Bookkeeping",
    "wof:placetype":"venue"
},
  "geometry": {"coordinates":[-77.10277600000001,38.782355],"type":"Point"}
}