{
  "type": "Feature",
  "properties": {
    "addr:full":"3993 Hales Point Rd Farnham VA 22460",
    "addr:housenumber":"3993",
    "addr:postcode":"22460",
    "addr:street":"Hales Point Rd",
    "iso:country":"US",
    "sg:address":"3993 Hales Point Rd",
    "sg:city":"Farnham",
    "sg:classifiers":[
        {
            "category":"Autos & Motor Vehicles",
            "subcategory":"Boat Sales",
            "type":"Retail Goods"
        },
        {
            "category":"Freight",
            "type":"Transportation"
        }
    ],
    "sg:phone":"+1 804 394 9500",
    "sg:postcode":"22460",
    "sg:province":"VA",
    "sg:tags":[
        "marina",
        "campground",
        "dealer",
        "sales"
    ],
    "sg:website":"www.whelansmarina.com",
    "wof:name":"Whelan's Marina & Camp Ground",
    "wof:placetype":"venue"
},
  "geometry": {"coordinates":[-76.65233600000001,37.800171],"type":"Point"}
}