{
  "type": "Feature",
  "properties": {
    "addr:full":"8409 Brook Rd Glen Allen VA 23060",
    "addr:housenumber":"8409",
    "addr:postcode":"23060",
    "addr:street":"Brook Rd",
    "iso:country":"US",
    "sg:address":"8409 Brook Rd",
    "sg:city":"Glen Allen",
    "sg:classifiers":[
        {
            "category":"Shopping",
            "subcategory":"Bicycles & Sporting Goods",
            "type":"Retail Goods"
        }
    ],
    "sg:phone":"+1 804 266 7119",
    "sg:postcode":"23060",
    "sg:province":"VA",
    "sg:tags":[
        "repair"
    ],
    "wof:name":"Clubs Fore You",
    "wof:placetype":"venue"
},
  "geometry": {"coordinates":[-77.459397,37.638367],"type":"Point"}
}