{
  "type": "Feature",
  "properties": {
    "addr:full":"2600 S Fort Scott Dr Arlington VA 22202",
    "addr:housenumber":"2600",
    "addr:postcode":"22202",
    "addr:street":"S Fort Scott Dr",
    "iso:country":"US",
    "sg:address":"2600 S Fort Scott Dr",
    "sg:city":"Arlington",
    "sg:classifiers":[
        {
            "category":"Professional",
            "type":"Services"
        }
    ],
    "sg:phone":"+1 703 894 9494",
    "sg:postcode":"22202",
    "sg:province":"VA",
    "wof:name":"Global Expand",
    "wof:placetype":"venue"
},
  "geometry": {"coordinates":[-77.063925,38.850327],"type":"Point"}
}