{
  "type": "Feature",
  "properties": {
    "addr:full":"2443 Centreville Rd Herndon VA 20171",
    "addr:housenumber":"2443",
    "addr:postcode":"20171",
    "addr:street":"Centreville Rd",
    "iso:country":"US",
    "sg:address":"2443 Centreville Rd",
    "sg:city":"Herndon",
    "sg:classifiers":[
        {
            "category":"Personal",
            "subcategory":"Beauty Salon",
            "type":"Services"
        }
    ],
    "sg:phone":"+1 703 318 0888",
    "sg:postcode":"20171",
    "sg:province":"VA",
    "sg:tags":[
        "shop"
    ],
    "wof:name":"Quick Coupe",
    "wof:placetype":"venue"
},
  "geometry": {"coordinates":[-77.41214600000001,38.949684],"type":"Point"}
}