{
  "type": "Feature",
  "properties": {
    "iso:country":"US",
    "sg:address":"5230 Johnson Ave",
    "sg:city":"Portsmouth",
    "sg:classifiers":[
        {
            "category":"Freight",
            "type":"Transportation"
        }
    ],
    "sg:phone":"+1 757 488 6362",
    "sg:postcode":"23701",
    "sg:province":"VA",
    "sg:tags":[
        "distance",
        "long",
        "trucking"
    ],
    "wof:name":"APE Inc",
    "wof:placetype":"venue"
},
  "geometry": {"coordinates":[-76.37509,36.825826],"type":"Point"}
}