{
  "type": "Feature",
  "properties": {
    "addr:full":"8045 Leesburg Pike Vienna VA 22182",
    "addr:housenumber":"8045",
    "addr:postcode":"22182",
    "addr:street":"Leesburg Pike",
    "iso:country":"US",
    "sg:address":"8045 Leesburg Pike",
    "sg:city":"Vienna",
    "sg:classifiers":[
        {
            "category":"Professional",
            "type":"Services"
        }
    ],
    "sg:phone":"+1 703 506 3528",
    "sg:postcode":"22182",
    "sg:province":"VA",
    "wof:name":"Los Padres Fdtn",
    "wof:placetype":"venue"
},
  "geometry": {"coordinates":[-77.223198,38.913266],"type":"Point"}
}