{
  "type": "Feature",
  "properties": {
    "addr:full":"1105 Greenville Ave Staunton VA 24401",
    "addr:housenumber":"1105",
    "addr:postcode":"24401",
    "addr:street":"Greenville Ave",
    "iso:country":"US",
    "sg:address":"1105 Greenville Ave",
    "sg:city":"Staunton",
    "sg:classifiers":[
        {
            "category":"Shopping",
            "type":"Retail Goods"
        }
    ],
    "sg:phone":"+1 540 886 4490",
    "sg:postcode":"24401",
    "sg:province":"VA",
    "sg:tags":[
        "merchandise"
    ],
    "wof:name":"Miracle-Ear",
    "wof:placetype":"venue"
},
  "geometry": {"coordinates":[-79.06280700000001,38.131816],"type":"Point"}
}