{
  "type": "Feature",
  "properties": {
    "iso:country":"US",
    "sg:address":"46161 Westlake Dr Ste 130",
    "sg:city":"Sterling",
    "sg:classifiers":[
        {
            "category":"Insurance",
            "subcategory":"Title Insurance",
            "type":"Services"
        }
    ],
    "sg:phone":"+1 703 444 4100",
    "sg:postcode":"20165",
    "sg:province":"VA",
    "wof:name":"Champion Title & Settlements, Inc.",
    "wof:placetype":"venue"
},
  "geometry": {"coordinates":[-77.40217,39.035001],"type":"Point"}
}