{
  "type": "Feature",
  "properties": {
    "addr:full":"247 E Cawson St Hopewell VA 23860",
    "addr:housenumber":"247",
    "addr:postcode":"23860",
    "addr:street":"E Cawson St",
    "iso:country":"US",
    "sg:address":"247 E Cawson St",
    "sg:city":"Hopewell",
    "sg:classifiers":[
        {
            "category":"Social Services",
            "type":"Services"
        }
    ],
    "sg:phone":"+1 804 541 8660",
    "sg:postcode":"23860",
    "sg:province":"VA",
    "sg:tags":[
        "counseling"
    ],
    "wof:name":"District 19 Community Svc",
    "wof:placetype":"venue"
},
  "geometry": {"coordinates":[-77.28589599999999,37.305265],"type":"Point"}
}