{
  "type": "Feature",
  "properties": {
    "addr:full":"1101 S Joyce St Ste B7 Arlington VA 22202",
    "addr:housenumber":"1101",
    "addr:postcode":"22202",
    "addr:street":"S Joyce St Ste B7",
    "iso:country":"US",
    "sg:address":"1101 S Joyce St Ste B7",
    "sg:city":"Arlington",
    "sg:classifiers":[
        {
            "category":"Health Services",
            "subcategory":"Optometrist",
            "type":"Services"
        }
    ],
    "sg:phone":"+1 703 418 2020",
    "sg:postcode":"22202",
    "sg:province":"VA",
    "wof:name":"A Visual Affair",
    "wof:placetype":"venue"
},
  "geometry": {"coordinates":[-77.0569,38.8564],"type":"Point"}
}