{
  "type": "Feature",
  "properties": {
    "iso:country":"US",
    "sg:address":"31 Main St",
    "sg:city":"Chatham",
    "sg:classifiers":[
        {
            "category":"Government",
            "subcategory":"Post Office",
            "type":"Public Place"
        }
    ],
    "sg:phone":"+1 434 432 4321",
    "sg:postcode":"24531",
    "sg:province":"VA",
    "sg:tags":[
        "postal",
        "us"
    ],
    "wof:name":"US Post Office",
    "wof:placetype":"venue"
},
  "geometry": {"coordinates":[-79.398166,36.827125],"type":"Point"}
}