{
  "type": "Feature",
  "properties": {
    "addr:full":"111 Harrison St Radford VA 24141",
    "addr:housenumber":"111",
    "addr:postcode":"24141",
    "addr:street":"Harrison St",
    "iso:country":"US",
    "sg:address":"111 Harrison St",
    "sg:city":"Radford",
    "sg:classifiers":[
        {
            "category":"Utilities",
            "subcategory":"Natural Gas",
            "type":"Services"
        }
    ],
    "sg:phone":"+1 540 639 1611",
    "sg:postcode":"24141",
    "sg:province":"VA",
    "sg:tags":[
        "liquefied",
        "petroleum"
    ],
    "sg:website":"www.swvagasservice.com",
    "wof:name":"Southwestern Virginia Gas Svc",
    "wof:placetype":"venue"
},
  "geometry": {"coordinates":[-80.55894499999999,37.141118],"type":"Point"}
}