{
  "type": "Feature",
  "properties": {
    "addr:full":"5626 Princess Anne Rd Virginia Beach VA 23462",
    "addr:housenumber":"5626",
    "addr:postcode":"23462",
    "addr:street":"Princess Anne Rd",
    "iso:country":"US",
    "sg:address":"5626 Princess Anne Rd",
    "sg:city":"Virginia Beach",
    "sg:classifiers":[
        {
            "category":"Manufacturing",
            "subcategory":"Food",
            "type":"Manufacturing & Wholesale Goods"
        },
        {
            "category":"Building & Trades",
            "subcategory":"Pest Control",
            "type":"Services"
        }
    ],
    "sg:phone":"+1 757 485 5832",
    "sg:postcode":"23462",
    "sg:province":"VA",
    "sg:tags":[
        "dehydrating",
        "disinfecting"
    ],
    "wof:name":"Superior Termite & Pest Cntrl",
    "wof:placetype":"venue"
},
  "geometry": {"coordinates":[-76.182137,36.839892],"type":"Point"}
}