{
  "type": "Feature",
  "properties": {
    "addr:full":"221 Ruthers Rd Richmond VA 23235",
    "addr:housenumber":"221",
    "addr:postcode":"23235",
    "addr:street":"Ruthers Rd",
    "iso:country":"US",
    "sg:address":"221 Ruthers Rd",
    "sg:city":"Richmond",
    "sg:classifiers":[
        {
            "category":"Wholesale",
            "subcategory":"Durable Goods & Equipment",
            "type":"Manufacturing & Wholesale Goods"
        },
        {
            "category":"Wholesale",
            "subcategory":"Electrical",
            "type":"Manufacturing & Wholesale Goods"
        }
    ],
    "sg:phone":"+1 804 320 8970",
    "sg:postcode":"23235",
    "sg:province":"VA",
    "sg:tags":[
        "mfg",
        "representative",
        "manufacturer"
    ],
    "sg:website":"www.atlsou.com",
    "wof:name":"Atlantic Southern Associates",
    "wof:placetype":"venue"
},
  "geometry": {"coordinates":[-77.54017899999999,37.497514],"type":"Point"}
}