{
  "type": "Feature",
  "properties": {
    "addr:full":"9008 Kerrydale Ct Springfield VA 22152",
    "addr:housenumber":"9008",
    "addr:postcode":"22152",
    "addr:street":"Kerrydale Ct",
    "iso:country":"US",
    "sg:address":"9008 Kerrydale Ct",
    "sg:city":"Springfield",
    "sg:classifiers":[
        {
            "category":"Shopping",
            "subcategory":"Crafts & Fabrics",
            "type":"Retail Goods"
        }
    ],
    "sg:phone":"+1 703 569 7072",
    "sg:postcode":"22152",
    "sg:province":"VA",
    "sg:tags":[
        "shop"
    ],
    "sg:website":"http://www.dollmakersjourney.com",
    "wof:name":"Dollmakers Journey",
    "wof:placetype":"venue"
},
  "geometry": {"coordinates":[-77.254499,38.77963],"type":"Point"}
}