{
  "type": "Feature",
  "properties": {
    "iso:country":"US",
    "sg:address":"7012 Aspen Ln",
    "sg:city":"Spotsylvania",
    "sg:classifiers":[
        {
            "category":"Professional",
            "subcategory":"Management & Consulting",
            "type":"Services"
        }
    ],
    "sg:phone":"+1 540 582 9719",
    "sg:postcode":"22551",
    "sg:province":"VA",
    "sg:tags":[
        "telecommunication"
    ],
    "wof:name":"Dominion Telcom Services LLC",
    "wof:placetype":"venue"
},
  "geometry": {"coordinates":[-77.57437,38.152179],"type":"Point"}
}