{
  "type": "Feature",
  "properties": {
    "addr:full":"2221 S Kenmore St Arlington VA 22206",
    "addr:housenumber":"2221",
    "addr:postcode":"22206",
    "addr:street":"S Kenmore St",
    "iso:country":"US",
    "sg:address":"2221 S Kenmore St",
    "sg:city":"Arlington",
    "sg:classifiers":[
        {
            "category":"Autos & Motor Vehicles",
            "subcategory":"Automobile Sales",
            "type":"Retail Goods"
        }
    ],
    "sg:phone":"+1 703 892 3110",
    "sg:postcode":"22206",
    "sg:province":"VA",
    "sg:tags":[
        "used"
    ],
    "wof:name":"Cars Market",
    "wof:placetype":"venue"
},
  "geometry": {"coordinates":[-77.085221,38.849332],"type":"Point"}
}