{
  "type": "Feature",
  "properties": {
    "addr:full":"2025 Browns Gap Tpke Charlottesville VA 22901",
    "addr:housenumber":"2025",
    "addr:postcode":"22901",
    "addr:street":"Browns Gap",
    "iso:country":"US",
    "sg:address":"2025 Browns Gap Tpke",
    "sg:city":"Charlottesville",
    "sg:classifiers":[
        {
            "category":"Professional",
            "subcategory":"Business Services",
            "type":"Services"
        }
    ],
    "sg:phone":"+1 434 823 2061",
    "sg:postcode":"22901",
    "sg:province":"VA",
    "wof:name":"Obsequy Associates LLC",
    "wof:placetype":"venue"
},
  "geometry": {"coordinates":[-78.65840799999999,38.08926],"type":"Point"}
}