{
  "type": "Feature",
  "properties": {
    "addr:full":"105 Gaddy Rd Lynchburg VA 24502",
    "addr:housenumber":"105",
    "addr:postcode":"24502",
    "addr:street":"Gaddy Rd",
    "iso:country":"US",
    "sg:address":"105 Gaddy Rd",
    "sg:city":"Lynchburg",
    "sg:classifiers":[
        {
            "category":"Professional",
            "type":"Services"
        }
    ],
    "sg:phone":"+1 434 239 7050",
    "sg:postcode":"24502",
    "sg:province":"VA",
    "wof:name":"Central Vrgnia Irrgtion Ldscpg",
    "wof:placetype":"venue"
},
  "geometry": {"coordinates":[-79.23554799999999,37.385965],"type":"Point"}
}