{
  "type": "Feature",
  "properties": {
    "addr:full":"300 Majestic Ct Newport News VA 23606",
    "addr:housenumber":"300",
    "addr:postcode":"23606",
    "addr:street":"Majestic Ct",
    "iso:country":"US",
    "sg:address":"300 Majestic Ct",
    "sg:city":"Newport News",
    "sg:classifiers":[
        {
            "category":"Freight",
            "type":"Transportation"
        }
    ],
    "sg:phone":"+1 757 369 9652",
    "sg:postcode":"23606",
    "sg:province":"VA",
    "wof:name":"Jordan's Transportation Inc",
    "wof:placetype":"venue"
},
  "geometry": {"coordinates":[-76.502377,37.075171],"type":"Point"}
}