{
  "type": "Feature",
  "properties": {
    "addr:full":"1800 N Oak St Arlington VA 22209",
    "addr:housenumber":"1800",
    "addr:postcode":"22209",
    "addr:street":"N Oak St",
    "iso:country":"US",
    "sg:address":"1800 N Oak St",
    "sg:city":"Arlington",
    "sg:classifiers":[
        {
            "category":"Professional",
            "subcategory":"Management & Consulting",
            "type":"Services"
        }
    ],
    "sg:phone":"+1 703 528 5285",
    "sg:postcode":"22209",
    "sg:province":"VA",
    "wof:name":"Viraj V Gandhi",
    "wof:placetype":"venue"
},
  "geometry": {"coordinates":[-77.074022,38.89637],"type":"Point"}
}