{
  "type": "Feature",
  "properties": {
    "addr:full":"4510 Jefferson Davis Hwy Richmond VA 23234",
    "addr:housenumber":"4510",
    "addr:postcode":"23234",
    "addr:street":"Jefferson Davis Hwy",
    "iso:country":"US",
    "sg:address":"4510 Jefferson Davis Hwy",
    "sg:city":"Richmond",
    "sg:classifiers":[
        {
            "category":"Organizations",
            "subcategory":"Professional Association",
            "type":"Services"
        }
    ],
    "sg:phone":"+1 804 275 5542",
    "sg:postcode":"23234",
    "sg:province":"VA",
    "sg:tags":[
        "taxi",
        "bus",
        "business",
        "facility"
    ],
    "wof:name":"Veterans Cab Association",
    "wof:placetype":"venue"
},
  "geometry": {"coordinates":[-77.443034,37.465336],"type":"Point"}
}