{
  "type": "Feature",
  "properties": {
    "addr:full":"1317 Jamestown Rd Ste 102 Williamsburg VA 23185",
    "addr:housenumber":"1317",
    "addr:postcode":"23185",
    "addr:street":"Jamestown Rd Ste 102",
    "iso:country":"US",
    "sg:address":"1317 Jamestown Rd Ste 102",
    "sg:city":"Williamsburg",
    "sg:classifiers":[
        {
            "category":"Health Services",
            "subcategory":"Doctor",
            "type":"Services"
        },
        {
            "category":"Health Services",
            "subcategory":"Clinic",
            "type":"Services"
        }
    ],
    "sg:phone":"+1 757 220 2700",
    "sg:postcode":"23185",
    "sg:province":"VA",
    "sg:tags":[
        "psychological",
        "psychologist"
    ],
    "wof:name":"Frances E Reinker",
    "wof:placetype":"venue"
},
  "geometry": {"coordinates":[-76.734055,37.251731],"type":"Point"}
}