{
  "type": "Feature",
  "properties": {
    "iso:country":"US",
    "sg:address":"25 S Kent St",
    "sg:city":"Winchester",
    "sg:classifiers":[
        {
            "category":"Government",
            "subcategory":"Office",
            "type":"Public Place"
        }
    ],
    "sg:phone":"+1 540 667 8208",
    "sg:postcode":"22601",
    "sg:province":"VA",
    "sg:tags":[
        "agency"
    ],
    "wof:name":"Concern Hotline Inc",
    "wof:placetype":"venue"
},
  "geometry": {"coordinates":[-78.162864,39.183158],"type":"Point"}
}