{
  "type": "Feature",
  "properties": {
    "addr:full":"2111 Stoneheather Rd Richmond VA 23238",
    "addr:housenumber":"2111",
    "addr:postcode":"23238",
    "addr:street":"Stoneheather Rd",
    "iso:country":"US",
    "sg:address":"2111 Stoneheather Rd",
    "sg:city":"Richmond",
    "sg:classifiers":[
        {
            "category":"Building & Trades",
            "subcategory":"Construction",
            "type":"Services"
        }
    ],
    "sg:phone":"+1 804 740 8331",
    "sg:postcode":"23238",
    "sg:province":"VA",
    "sg:tags":[
        "house"
    ],
    "wof:name":"L&A Builders",
    "wof:placetype":"venue"
},
  "geometry": {"coordinates":[-77.626935,37.620258],"type":"Point"}
}