{
  "type": "Feature",
  "properties": {
    "iso:country":"US",
    "sg:address":"424 S Washington St",
    "sg:city":"Alexandria",
    "sg:classifiers":[
        {
            "category":"Health Services",
            "subcategory":"Health Practitioner",
            "type":"Services"
        },
        {
            "category":"Health Services",
            "subcategory":"Doctor",
            "type":"Services"
        }
    ],
    "sg:phone":"+1 703 683 5084",
    "sg:postcode":"22314",
    "sg:province":"VA",
    "sg:tags":[
        "medical",
        "psychologist"
    ],
    "wof:name":"Psychatric Assoc of Alexandria",
    "wof:placetype":"venue"
},
  "geometry": {"coordinates":[-77.047821,38.800772],"type":"Point"}
}