{
  "type": "Feature",
  "properties": {
    "iso:country":"US",
    "sg:address":"1672 Dee's Rd",
    "sg:city":"Axton",
    "sg:classifiers":[
        {
            "category":"Shopping",
            "subcategory":"Florist",
            "type":"Retail Goods"
        }
    ],
    "sg:phone":"+1 276 650 2323",
    "sg:postcode":"24054",
    "sg:province":"VA",
    "wof:name":"Flowers & Creations",
    "wof:placetype":"venue"
},
  "geometry": {"coordinates":[-79.68123,36.686278],"type":"Point"}
}