{
  "type": "Feature",
  "properties": {
    "addr:full":"13539 Port Republic Rd Grottoes VA 24441",
    "addr:housenumber":"13539",
    "addr:postcode":"24441",
    "addr:street":"Port Republic Rd",
    "iso:country":"US",
    "sg:address":"13539 Port Republic Rd",
    "sg:city":"Grottoes",
    "sg:classifiers":[
        {
            "category":"Home & Garden",
            "subcategory":"Building Materials",
            "type":"Retail Goods"
        },
        {
            "category":"Manufacturing",
            "subcategory":"Lumber",
            "type":"Manufacturing & Wholesale Goods"
        }
    ],
    "sg:phone":"+1 540 249 4458",
    "sg:postcode":"24441",
    "sg:province":"VA",
    "sg:tags":[
        "mill"
    ],
    "wof:name":"Mace Lumber Mill",
    "wof:placetype":"venue"
},
  "geometry": {"coordinates":[-78.78206400000001,38.260646],"type":"Point"}
}