{
  "type": "Feature",
  "properties": {
    "addr:full":"612 E Main St Luray VA 22835",
    "addr:housenumber":"612",
    "addr:postcode":"22835",
    "addr:street":"E Main St",
    "iso:country":"US",
    "sg:address":"612 E Main St",
    "sg:city":"Luray",
    "sg:classifiers":[
        {
            "category":"Banks & Credit Unions",
            "subcategory":"Bank",
            "type":"Services"
        }
    ],
    "sg:phone":"+1 540 743 6521",
    "sg:postcode":"22835",
    "sg:province":"VA",
    "wof:name":"Page Valley Bank",
    "wof:placetype":"venue"
},
  "geometry": {"coordinates":[-78.44942899999999,38.665446],"type":"Point"}
}