{
  "type": "Feature",
  "properties": {
    "addr:full":"112 S 2nd St Richmond VA 23219",
    "addr:housenumber":"112",
    "addr:postcode":"23219",
    "addr:street":"S 2Nd St",
    "iso:country":"US",
    "sg:address":"112 S 2nd St",
    "sg:city":"Richmond",
    "sg:classifiers":[
        {
            "category":"Restaurant",
            "type":"Food & Drink"
        }
    ],
    "sg:phone":"+1 804 643 1000",
    "sg:postcode":"23219",
    "sg:province":"VA",
    "sg:tags":[
        "caterer"
    ],
    "sg:website":"www.cateraide.com",
    "wof:name":"Cateraide",
    "wof:placetype":"venue"
},
  "geometry": {"coordinates":[-77.444202,37.540401],"type":"Point"}
}