{
  "type": "Feature",
  "properties": {
    "addr:full":"77 W Lee St #201 Warrenton VA 20186",
    "addr:housenumber":"77;201",
    "addr:postcode":"20186",
    "addr:street":"W Lee St #",
    "iso:country":"US",
    "sg:address":"77 W Lee St #201",
    "sg:city":"Warrenton",
    "sg:classifiers":[
        {
            "category":"Insurance",
            "subcategory":"Hazard Insurance",
            "type":"Services"
        }
    ],
    "sg:phone":"+1 540 349 9100",
    "sg:postcode":"20186",
    "sg:province":"VA",
    "sg:tags":[
        "motorcycle"
    ],
    "sg:website":"http://clickserve.dartsearch.net/link/click?lid=43000000142099008",
    "wof:name":"William M. King - Allstate Insurance Company",
    "wof:placetype":"venue"
},
  "geometry": {"coordinates":[-77.79850399999999,38.713211],"type":"Point"}
}