{
  "type": "Feature",
  "properties": {
    "addr:full":"3007 Fairhill Rd Fairfax VA 22031",
    "addr:housenumber":"3007",
    "addr:postcode":"22031",
    "addr:street":"Fairhill Rd",
    "iso:country":"US",
    "sg:address":"3007 Fairhill Rd",
    "sg:city":"Fairfax",
    "sg:classifiers":[
        {
            "category":"Building & Trades",
            "subcategory":"Locksmith",
            "type":"Services"
        }
    ],
    "sg:phone":"+1 703 560 2616",
    "sg:postcode":"22031",
    "sg:province":"VA",
    "sg:tags":[
        "lock",
        "industrial",
        "key",
        "locksmiths-commercial"
    ],
    "wof:name":"Bears Lock & Key",
    "wof:placetype":"venue"
},
  "geometry": {"coordinates":[-77.244606,38.869835],"type":"Point"}
}