{
  "type": "Feature",
  "properties": {
    "addr:full":"3963 Persimmon Dr Fairfax VA 22031",
    "addr:housenumber":"3963",
    "addr:postcode":"22031",
    "addr:street":"Persimmon Dr",
    "iso:country":"US",
    "sg:address":"3963 Persimmon Dr",
    "sg:city":"Fairfax",
    "sg:classifiers":[
        {
            "category":"Real Estate",
            "subcategory":"Real Estate Operator",
            "type":"Services"
        }
    ],
    "sg:phone":"+1 703 323 0465",
    "sg:postcode":"22031",
    "sg:province":"VA",
    "sg:tags":[
        "building",
        "apartment"
    ],
    "wof:name":"Pinewood Plaza Apartments",
    "wof:placetype":"venue"
},
  "geometry": {"coordinates":[-77.268338,38.841075],"type":"Point"}
}