{
  "type": "Feature",
  "properties": {
    "addr:full":"1360 E Washington St Petersburg VA 23803",
    "addr:housenumber":"1360",
    "addr:postcode":"23803",
    "addr:street":"E Washington",
    "iso:country":"US",
    "sg:address":"1360 E Washington St",
    "sg:city":"Petersburg",
    "sg:classifiers":[
        {
            "category":"Health Services",
            "subcategory":"Doctor",
            "type":"Services"
        }
    ],
    "sg:phone":"+1 804 861 5433",
    "sg:postcode":"23803",
    "sg:province":"VA",
    "sg:tags":[
        "medical"
    ],
    "wof:name":"Tri Cties Crisis Pregnancy Ctr",
    "wof:placetype":"venue"
},
  "geometry": {"coordinates":[-77.37878499999999,37.237355],"type":"Point"}
}