{
  "type": "Feature",
  "properties": {
    "addr:full":"607 W Washington St Suffolk VA 23434",
    "addr:housenumber":"607",
    "addr:postcode":"23434",
    "addr:street":"W Washington St",
    "iso:country":"US",
    "sg:address":"607 W Washington St",
    "sg:city":"Suffolk",
    "sg:classifiers":[
        {
            "category":"Insurance",
            "subcategory":"Insurance Agent",
            "type":"Services"
        }
    ],
    "sg:phone":"+1 757 934 2321",
    "sg:postcode":"23434",
    "sg:province":"VA",
    "wof:name":"Farm Bureau Insurance",
    "wof:placetype":"venue"
},
  "geometry": {"coordinates":[-76.593497,36.730061],"type":"Point"}
}