{
  "type": "Feature",
  "properties": {
    "addr:full":"1395 W Main Street Charlottesville VA 22903",
    "addr:housenumber":"1395",
    "addr:postcode":"22903",
    "addr:street":"W Main Street",
    "iso:country":"US",
    "sg:address":"1395 W Main Street",
    "sg:city":"Charlottesville",
    "sg:classifiers":[
        {
            "category":"Restaurant",
            "type":"Food & Drink"
        }
    ],
    "sg:phone":"+1 434 977 8000",
    "sg:postcode":"22903",
    "sg:province":"VA",
    "wof:name":"Lee's Grill",
    "wof:placetype":"venue"
},
  "geometry": {"coordinates":[-78.499211,38.034072],"type":"Point"}
}