{
  "type": "Feature",
  "properties": {
    "addr:full":"900 Church St Lynchburg VA 24504",
    "addr:housenumber":"900",
    "addr:postcode":"24504",
    "addr:street":"Church St",
    "iso:country":"US",
    "sg:address":"900 Church St",
    "sg:city":"Lynchburg",
    "sg:classifiers":[
        {
            "category":"Government",
            "subcategory":"Office",
            "type":"Public Place"
        }
    ],
    "sg:phone":"+1 434 847 1470",
    "sg:postcode":"24504",
    "sg:province":"VA",
    "sg:tags":[
        "village"
    ],
    "wof:name":"City Of Lynchburg Collections",
    "wof:placetype":"venue"
},
  "geometry": {"coordinates":[-79.142448,37.413515],"type":"Point"}
}