{
  "type": "Feature",
  "properties": {
    "iso:country":"US",
    "sg:address":"301 Mill Stream Way",
    "sg:city":"Williamsburg",
    "sg:classifiers":[
        {
            "category":"Professional",
            "subcategory":"Accounting & Tax Preparation",
            "type":"Services"
        }
    ],
    "sg:phone":"+1 757 565 7219",
    "sg:postcode":"23185",
    "sg:province":"VA",
    "wof:name":"Joan S Morrow PA",
    "wof:placetype":"venue"
},
  "geometry": {"coordinates":[-76.755833,37.243838],"type":"Point"}
}