{
  "type": "Feature",
  "properties": {
    "iso:country":"US",
    "sg:address":"1407 N Main St",
    "sg:city":"Suffolk",
    "sg:classifiers":[
        {
            "category":"Shopping",
            "subcategory":"Shoes",
            "type":"Retail Goods"
        }
    ],
    "sg:phone":"+1 757 539 9405",
    "sg:postcode":"23434",
    "sg:province":"VA",
    "wof:name":"Payless Shoesource",
    "wof:placetype":"venue"
},
  "geometry": {"coordinates":[-76.58339599999999,36.750252],"type":"Point"}
}