{
  "type": "Feature",
  "properties": {
    "iso:country":"US",
    "sg:address":"649 Newtown Rd",
    "sg:city":"Virginia Beach",
    "sg:classifiers":[
        {
            "category":"Shopping",
            "subcategory":"Clothing, Apparel, & Fashions",
            "type":"Retail Goods"
        }
    ],
    "sg:phone":"+1 757 456 2440",
    "sg:postcode":"23462",
    "sg:province":"VA",
    "sg:tags":[
        "made"
    ],
    "wof:name":"E Outfitters",
    "wof:placetype":"venue"
},
  "geometry": {"coordinates":[-76.174497,36.860657],"type":"Point"}
}