{
  "type": "Feature",
  "properties": {
    "addr:full":"10614 Patterson Ave Richmond VA 23238",
    "addr:housenumber":"10614",
    "addr:postcode":"23238",
    "addr:street":"Patterson Ave",
    "iso:country":"US",
    "sg:address":"10614 Patterson Ave",
    "sg:city":"Richmond",
    "sg:classifiers":[
        {
            "category":"Restaurant",
            "type":"Food & Drink"
        }
    ],
    "sg:phone":"+1 804 740 0033",
    "sg:postcode":"23238",
    "sg:province":"VA",
    "sg:tags":[
        "eating"
    ],
    "wof:name":"Domino's Pizza",
    "wof:placetype":"venue"
},
  "geometry": {"coordinates":[-77.60841499999999,37.597095],"type":"Point"}
}