{
  "type": "Feature",
  "properties": {
    "iso:country":"US",
    "sg:address":"2901 S Lynnhaven Rd",
    "sg:city":"Virginia Beach",
    "sg:classifiers":[
        {
            "category":"Banks & Credit Unions",
            "subcategory":"Investment Brokerage",
            "type":"Services"
        },
        {
            "category":"Banks & Credit Unions",
            "subcategory":"Financial Services",
            "type":"Services"
        }
    ],
    "sg:phone":"+1 757 463 2265",
    "sg:postcode":"23452",
    "sg:province":"VA",
    "wof:name":"Dominion Investments Group",
    "wof:placetype":"venue"
},
  "geometry": {"coordinates":[-76.072852,36.832499],"type":"Point"}
}