{
  "type": "Feature",
  "properties": {
    "iso:country":"US",
    "sg:address":"128 N Washington St",
    "sg:city":"Falls Church",
    "sg:classifiers":[
        {
            "category":"Personal",
            "subcategory":"Beauty Salon",
            "type":"Services"
        }
    ],
    "sg:phone":"+1 703 237 8387",
    "sg:postcode":"22046",
    "sg:province":"VA",
    "sg:tags":[
        "shop"
    ],
    "wof:name":"Fringes Hair Place",
    "wof:placetype":"venue"
},
  "geometry": {"coordinates":[-77.170823,38.882396],"type":"Point"}
}