{
  "type": "Feature",
  "properties": {
    "addr:full":"175 London Company Way Williamsburg VA 23185",
    "addr:housenumber":"175",
    "addr:postcode":"23185",
    "addr:street":"London Company Way",
    "iso:country":"US",
    "sg:address":"175 London Company Way",
    "sg:city":"Williamsburg",
    "sg:classifiers":[
        {
            "category":"Professional",
            "type":"Services"
        }
    ],
    "sg:phone":"+1 757 229 7688",
    "sg:postcode":"23185",
    "sg:province":"VA",
    "wof:name":"Dively Inc Robert C",
    "wof:placetype":"venue"
},
  "geometry": {"coordinates":[-76.77371599999999,37.234539],"type":"Point"}
}