{
  "type": "Feature",
  "properties": {
    "iso:country":"US",
    "sg:address":"8045 Leesburg Pike Ste 200",
    "sg:city":"Vienna",
    "sg:classifiers":[
        {
            "category":"Professional",
            "subcategory":"Employment Agencies",
            "type":"Services"
        }
    ],
    "sg:phone":"+1 703 342 3100",
    "sg:postcode":"22182",
    "sg:province":"VA",
    "wof:name":"Kforce Professional Staffing",
    "wof:placetype":"venue"
},
  "geometry": {"coordinates":[-77.221397,38.912399],"type":"Point"}
}