{
  "type": "Feature",
  "properties": {
    "addr:full":"3248 Davis Ave Roanoke VA 24015",
    "addr:housenumber":"3248",
    "addr:postcode":"24015",
    "addr:street":"Davis Ave",
    "iso:country":"US",
    "sg:address":"3248 Davis Ave",
    "sg:city":"Roanoke",
    "sg:classifiers":[
        {
            "category":"Professional",
            "subcategory":"Management & Consulting",
            "type":"Services"
        }
    ],
    "sg:phone":"+1 540 774 3570",
    "sg:postcode":"24015",
    "sg:province":"VA",
    "wof:name":"Coleman Marketing",
    "wof:placetype":"venue"
},
  "geometry": {"coordinates":[-79.99704800000001,37.241761],"type":"Point"}
}