{
  "type": "Feature",
  "properties": {
    "addr:full":"713 Avalon Ave Virginia Beach VA 23464",
    "addr:housenumber":"713",
    "addr:postcode":"23464",
    "addr:street":"Avalon Ave",
    "iso:country":"US",
    "sg:address":"713 Avalon Ave",
    "sg:city":"Virginia Beach",
    "sg:classifiers":[
        {
            "category":"Building & Trades",
            "subcategory":"Construction",
            "type":"Services"
        }
    ],
    "sg:phone":"+1 757 424 3260",
    "sg:postcode":"23464",
    "sg:province":"VA",
    "sg:tags":[
        "commercial",
        "contractor"
    ],
    "wof:name":"Smart",
    "wof:placetype":"venue"
},
  "geometry": {"coordinates":[-76.188802,36.818784],"type":"Point"}
}