{
  "type": "Feature",
  "properties": {
    "addr:full":"75 Hampton Blvd NE Christiansburg VA 24073",
    "addr:housenumber":"75",
    "addr:postcode":"24073",
    "addr:street":"Hampton Blvd Ne",
    "iso:country":"US",
    "sg:address":"75 Hampton Blvd NE",
    "sg:city":"Christiansburg",
    "sg:classifiers":[
        {
            "category":"Government",
            "subcategory":"Office",
            "type":"Public Place"
        }
    ],
    "sg:phone":"+1 540 382 3961",
    "sg:postcode":"24073",
    "sg:province":"VA",
    "sg:tags":[
        "farm",
        "agency"
    ],
    "wof:name":"Farm Service Agency",
    "wof:placetype":"venue"
},
  "geometry": {"coordinates":[-80.35230199999999,37.139293],"type":"Point"}
}