{
  "type": "Feature",
  "properties": {
    "addr:full":"12735 Shoppes Ln Fairfax VA 22033",
    "addr:housenumber":"12735",
    "addr:postcode":"22033",
    "addr:street":"Shoppes Ln",
    "iso:country":"US",
    "sg:address":"12735 Shoppes Ln",
    "sg:city":"Fairfax",
    "sg:classifiers":[
        {
            "category":"Banks & Credit Unions",
            "subcategory":"Bank",
            "type":"Services"
        }
    ],
    "sg:phone":"+1 703 631 6411",
    "sg:postcode":"22033",
    "sg:province":"VA",
    "sg:website":"www.alliancehomefunding.com",
    "wof:name":"Alliance Bank Corp",
    "wof:placetype":"venue"
},
  "geometry": {"coordinates":[-77.387455,38.861437],"type":"Point"}
}