{
  "type": "Feature",
  "properties": {
    "iso:country":"US",
    "sg:address":"1216 Mary Ellen Ave",
    "sg:city":"Chesapeake",
    "sg:classifiers":[
        {
            "category":"Health Services",
            "subcategory":"Doctor",
            "type":"Services"
        }
    ],
    "sg:phone":"+1 757 361 5824",
    "sg:postcode":"23324",
    "sg:province":"VA",
    "sg:tags":[
        "medical"
    ],
    "wof:name":"Khan Khalid",
    "wof:placetype":"venue"
},
  "geometry": {"coordinates":[-76.278493,36.781465],"type":"Point"}
}