{
  "type": "Feature",
  "properties": {
    "addr:full":"1313 Barterbrook Rd Staunton VA 24401",
    "addr:housenumber":"1313",
    "addr:postcode":"24401",
    "addr:street":"Barterbrook Rd",
    "iso:country":"US",
    "sg:address":"1313 Barterbrook Rd",
    "sg:city":"Staunton",
    "sg:classifiers":[
        {
            "category":"Autos & Motor Vehicles",
            "subcategory":"Automobile Sales",
            "type":"Retail Goods"
        }
    ],
    "sg:phone":"+1 540 885 0875",
    "sg:postcode":"24401",
    "sg:province":"VA",
    "sg:tags":[
        "car",
        "dealer"
    ],
    "wof:name":"Augusta Dodge Jeep",
    "wof:placetype":"venue"
},
  "geometry": {"coordinates":[-79.06248100000001,38.12908],"type":"Point"}
}