{
  "type": "Feature",
  "properties": {
    "addr:full":"707 E Franklin St Richmond VA 23219",
    "addr:housenumber":"707",
    "addr:postcode":"23219",
    "addr:street":"E Franklin St",
    "iso:country":"US",
    "sg:address":"707 E Franklin St",
    "sg:city":"Richmond",
    "sg:classifiers":[
        {
            "category":"Professional",
            "subcategory":"Management & Consulting",
            "type":"Services"
        }
    ],
    "sg:phone":"+1 804 644 4424",
    "sg:postcode":"23219",
    "sg:province":"VA",
    "sg:tags":[
        "consultant",
        "business"
    ],
    "wof:name":"Whitehead Consulting",
    "wof:placetype":"venue"
},
  "geometry": {"coordinates":[-77.436476,37.539584],"type":"Point"}
}