{
  "type": "Feature",
  "properties": {
    "addr:full":"8801 Park Central Dr Richmond VA 23227",
    "addr:housenumber":"8801",
    "addr:postcode":"23227",
    "addr:street":"Park Central Dr",
    "iso:country":"US",
    "sg:address":"8801 Park Central Dr",
    "sg:city":"Richmond",
    "sg:classifiers":[
        {
            "category":"Building & Trades",
            "subcategory":"Construction",
            "type":"Services"
        }
    ],
    "sg:phone":"+1 804 266 1027",
    "sg:postcode":"23227",
    "sg:province":"VA",
    "sg:tags":[
        "elevator"
    ],
    "wof:name":"Schindler Elevator Corp",
    "wof:placetype":"venue"
},
  "geometry": {"coordinates":[-77.441728,37.645646],"type":"Point"}
}