{
  "type": "Feature",
  "properties": {
    "iso:country":"US",
    "sg:address":"10713 Ridgerun Rd",
    "sg:city":"Chesterfield",
    "sg:classifiers":[
        {
            "category":"Education",
            "subcategory":"School",
            "type":"Public Place"
        }
    ],
    "sg:phone":"+1 804 379 6580",
    "sg:postcode":"23832",
    "sg:province":"VA",
    "sg:tags":[
        "special"
    ],
    "wof:name":"Richmond Adult Services",
    "wof:placetype":"venue"
},
  "geometry": {"coordinates":[-77.59200300000001,37.423579],"type":"Point"}
}