{
  "type": "Feature",
  "properties": {
    "iso:country":"US",
    "sg:address":"156 Carlton Rd Ste 201",
    "sg:city":"Charlottesville",
    "sg:classifiers":[
        {
            "category":"Professional",
            "subcategory":"Computer Services",
            "type":"Services"
        }
    ],
    "sg:phone":"+1 434 296 7419",
    "sg:postcode":"22902",
    "sg:province":"VA",
    "sg:tags":[
        "repair"
    ],
    "wof:name":"Charlottesville Office Machine Co",
    "wof:placetype":"venue"
},
  "geometry": {"coordinates":[-78.46844900000001,38.025309],"type":"Point"}
}