{
  "type": "Feature",
  "properties": {
    "iso:country":"US",
    "sg:address":"1242 Easy St",
    "sg:city":"Woodbridge",
    "sg:classifiers":[
        {
            "category":"Retail",
            "subcategory":"Funeral Services",
            "type":"Services"
        }
    ],
    "sg:phone":"+1 703 490 1212",
    "sg:postcode":"22191",
    "sg:province":"VA",
    "sg:tags":[
        "director",
        "embalmer",
        "supply"
    ],
    "wof:name":"Aden Muslim Funeral Services",
    "wof:placetype":"venue"
},
  "geometry": {"coordinates":[-77.253657,38.655757],"type":"Point"}
}