{
  "type": "Feature",
  "properties": {
    "addr:full":"1117 Greenbrook Ct Forest VA 24551",
    "addr:housenumber":"1117",
    "addr:postcode":"24551",
    "addr:street":"Greenbrook Ct",
    "iso:country":"US",
    "sg:address":"1117 Greenbrook Ct",
    "sg:city":"Forest",
    "sg:classifiers":[
        {
            "category":"Health Services",
            "subcategory":"Optometrist",
            "type":"Services"
        }
    ],
    "sg:phone":"+1 434 525 5458",
    "sg:postcode":"24551",
    "sg:province":"VA",
    "wof:name":"Visions In Sonlight",
    "wof:placetype":"venue"
},
  "geometry": {"coordinates":[-79.299716,37.381401],"type":"Point"}
}