{
  "type": "Feature",
  "properties": {
    "iso:country":"US",
    "sg:address":"91 Garrett St",
    "sg:city":"Warrenton",
    "sg:classifiers":[
        {
            "category":"Building & Trades",
            "subcategory":"Electrical",
            "type":"Services"
        }
    ],
    "sg:phone":"+1 540 347 0849",
    "sg:postcode":"20186",
    "sg:province":"VA",
    "sg:tags":[
        "electrician"
    ],
    "wof:name":"M S Minor Electrical Service",
    "wof:placetype":"venue"
},
  "geometry": {"coordinates":[-77.80661000000001,38.714561],"type":"Point"}
}