{
  "type": "Feature",
  "properties": {
    "iso:country":"US",
    "sg:address":"445 Mill Pointe Rd",
    "sg:city":"Blacksburg",
    "sg:classifiers":[
        {
            "category":"Professional",
            "subcategory":"Engineering",
            "type":"Services"
        }
    ],
    "sg:phone":"+1 540 552 1471",
    "sg:postcode":"24060",
    "sg:province":"VA",
    "sg:tags":[
        "consulting"
    ],
    "wof:name":"Brush Mountain Tech LLC",
    "wof:placetype":"venue"
},
  "geometry": {"coordinates":[-80.375235,37.245353],"type":"Point"}
}