{
  "type": "Feature",
  "properties": {
    "iso:country":"US",
    "sg:address":"615 Cheadle Loop Rd",
    "sg:city":"Seaford",
    "sg:classifiers":[
        {
            "category":"Wholesale",
            "subcategory":"Machinery & Supplies",
            "type":"Manufacturing & Wholesale Goods"
        },
        {
            "category":"Building & Trades",
            "subcategory":"Construction",
            "type":"Services"
        }
    ],
    "sg:phone":"+1 757 898 3080",
    "sg:postcode":"23696",
    "sg:province":"VA",
    "sg:tags":[
        "concrete",
        "equipment",
        "cutting",
        "breaking",
        "sawing"
    ],
    "wof:name":"J T M Concrete Sawing",
    "wof:placetype":"venue"
},
  "geometry": {"coordinates":[-76.430413,37.188613],"type":"Point"}
}