{
  "type": "Feature",
  "properties": {
    "iso:country":"US",
    "sg:address":"8004 Alban Rd Ste E",
    "sg:city":"Springfield",
    "sg:classifiers":[
        {
            "category":"Restaurant",
            "type":"Food & Drink"
        }
    ],
    "sg:phone":"+1 703 451 2798",
    "sg:postcode":"22150",
    "sg:province":"VA",
    "sg:tags":[
        "mexican"
    ],
    "wof:name":"R & R Catering",
    "wof:placetype":"venue"
},
  "geometry": {"coordinates":[-77.193138,38.739361],"type":"Point"}
}