{
  "type": "Feature",
  "properties": {
    "addr:full":"5243 Duke St Alexandria VA 22304",
    "addr:housenumber":"5243",
    "addr:postcode":"22304",
    "addr:street":"Duke St",
    "iso:country":"US",
    "sg:address":"5243 Duke St",
    "sg:city":"Alexandria",
    "sg:classifiers":[
        {
            "category":"Shopping",
            "subcategory":"Clothing, Apparel, & Fashions",
            "type":"Retail Goods"
        }
    ],
    "sg:phone":"+1 301 984 3339",
    "sg:postcode":"22304",
    "sg:province":"VA",
    "sg:tags":[
        "tailor"
    ],
    "wof:name":"Hong Kong Tailors",
    "wof:placetype":"venue"
},
  "geometry": {"coordinates":[-77.122552,38.812635],"type":"Point"}
}