{
  "type": "Feature",
  "properties": {
    "addr:full":"1209 Independence Blvd Virginia Beach VA 23455",
    "addr:housenumber":"1209",
    "addr:postcode":"23455",
    "addr:street":"Independence Blvd",
    "iso:country":"US",
    "sg:address":"1209 Independence Blvd",
    "sg:city":"Virginia Beach",
    "sg:classifiers":[
        {
            "category":"Health Services",
            "subcategory":"Doctor",
            "type":"Services"
        }
    ],
    "sg:phone":"+1 757 436 6546",
    "sg:postcode":"23455",
    "sg:province":"VA",
    "sg:tags":[
        "medical"
    ],
    "wof:name":"Dr Tang & Associates Od",
    "wof:placetype":"venue"
},
  "geometry": {"coordinates":[-76.13346799999999,36.878949],"type":"Point"}
}