{
  "type": "Feature",
  "properties": {
    "iso:country":"US",
    "sg:address":"602 E Laburnum Ave",
    "sg:city":"Richmond",
    "sg:classifiers":[
        {
            "category":"Communications",
            "type":"Services"
        }
    ],
    "sg:phone":"+1 804 228 0069",
    "sg:postcode":"23222",
    "sg:province":"VA",
    "wof:name":"Sports Communications",
    "wof:placetype":"venue"
},
  "geometry": {"coordinates":[-77.420849,37.585656],"type":"Point"}
}