{
  "type": "Feature",
  "properties": {
    "iso:country":"US",
    "sg:address":"14504 Highgate Hill Ct",
    "sg:city":"Chesterfield",
    "sg:classifiers":[
        {
            "category":"Professional",
            "type":"Services"
        }
    ],
    "sg:phone":"+1 804 639 3864",
    "sg:postcode":"23832",
    "sg:province":"VA",
    "sg:tags":[
        "establishment"
    ],
    "wof:name":"Siemens Pl&D DAD Ap",
    "wof:placetype":"venue"
},
  "geometry": {"coordinates":[-77.670402,37.381823],"type":"Point"}
}