{
  "type": "Feature",
  "properties": {
    "addr:full":"1109 Rockingham St Norfolk VA 23523",
    "addr:housenumber":"1109",
    "addr:postcode":"23523",
    "addr:street":"Rockingham St",
    "iso:country":"US",
    "sg:address":"1109 Rockingham St",
    "sg:city":"Norfolk",
    "sg:classifiers":[
        {
            "category":"Bus Charters",
            "type":"Transportation"
        }
    ],
    "sg:phone":"+1 757 545 3329",
    "sg:postcode":"23523",
    "sg:province":"VA",
    "wof:name":"Faithway Express",
    "wof:placetype":"venue"
},
  "geometry": {"coordinates":[-76.28379099999999,36.827712],"type":"Point"}
}