{
  "type": "Feature",
  "properties": {
    "iso:country":"US",
    "sg:address":"6229 Osborne Tpke",
    "sg:city":"Richmond",
    "sg:classifiers":[
        {
            "category":"Organizations",
            "subcategory":"Religious Organization",
            "type":"Services"
        }
    ],
    "sg:phone":"+1 804 226 2665",
    "sg:postcode":"23231",
    "sg:province":"VA",
    "wof:name":"New Life Baptist Church",
    "wof:placetype":"venue"
},
  "geometry": {"coordinates":[-77.404658,37.494573],"type":"Point"}
}