{
  "type": "Feature",
  "properties": {
    "iso:country":"US",
    "sg:address":"7400 Token Valley Rd",
    "sg:city":"Manassas",
    "sg:classifiers":[
        {
            "category":"Building & Trades",
            "subcategory":"Construction",
            "type":"Services"
        }
    ],
    "sg:phone":"+1 703 791 2885",
    "sg:postcode":"20112",
    "sg:province":"VA",
    "sg:tags":[
        "house",
        "contractor"
    ],
    "sg:website":"www.classicconceptbuilders.com",
    "wof:name":"Classic Concept Builders Inc",
    "wof:placetype":"venue"
},
  "geometry": {"coordinates":[-77.424379,38.658319],"type":"Point"}
}