{
  "type": "Feature",
  "properties": {
    "addr:full":"5000 W Norfolk Rd Portsmouth VA 23703",
    "addr:housenumber":"5000",
    "addr:postcode":"23703",
    "addr:street":"W Norfolk Rd",
    "iso:country":"US",
    "sg:address":"5000 W Norfolk Rd",
    "sg:city":"Portsmouth",
    "sg:classifiers":[
        {
            "category":"Organizations",
            "subcategory":"Religious Organization",
            "type":"Services"
        }
    ],
    "sg:phone":"+1 757 484 4067",
    "sg:postcode":"23703",
    "sg:province":"VA",
    "sg:tags":[
        "church",
        "school",
        "center",
        "day",
        "care"
    ],
    "wof:name":"Sweet Haven Christian Day Care",
    "wof:placetype":"venue"
},
  "geometry": {"coordinates":[-76.381372,36.867154],"type":"Point"}
}