{
  "type": "Feature",
  "properties": {
    "iso:country":"US",
    "sg:address":"240 Watson Ave",
    "sg:city":"Blacksburg",
    "sg:classifiers":[
        {
            "category":"Social Services",
            "subcategory":"Child Care",
            "type":"Services"
        }
    ],
    "sg:phone":"+1 540 552 4810",
    "sg:postcode":"24060",
    "sg:province":"VA",
    "sg:tags":[
        "organization",
        "religious",
        "day"
    ],
    "wof:name":"Blacksburg Christian Church",
    "wof:placetype":"venue"
},
  "geometry": {"coordinates":[-80.42568,37.237838],"type":"Point"}
}