{
  "type": "Feature",
  "properties": {
    "iso:country":"US",
    "sg:address":"1300 Chain Bridge Rd",
    "sg:city":"McLean",
    "sg:classifiers":[
        {
            "category":"Health Services",
            "subcategory":"Doctor",
            "type":"Services"
        }
    ],
    "sg:phone":"+1 703 790 5455",
    "sg:postcode":"22101",
    "sg:province":"VA",
    "wof:name":"Magassy Csaba L MD Facs",
    "wof:placetype":"venue"
},
  "geometry": {"coordinates":[-77.17483300000001,38.940583],"type":"Point"}
}