{
  "type": "Feature",
  "properties": {
    "addr:full":"3407 Cedar Creek Grade Winchester VA 22602",
    "addr:housenumber":"3407",
    "addr:postcode":"22602",
    "addr:street":"Cedar Creek Grade",
    "iso:country":"US",
    "sg:address":"3407 Cedar Creek Grade",
    "sg:city":"Winchester",
    "sg:classifiers":[
        {
            "category":"Professional",
            "type":"Services"
        }
    ],
    "sg:phone":"+1 540 667 9150",
    "sg:postcode":"22602",
    "sg:province":"VA",
    "wof:name":"Home Net",
    "wof:placetype":"venue"
},
  "geometry": {"coordinates":[-78.275841,39.140583],"type":"Point"}
}