{
  "type": "Feature",
  "properties": {
    "iso:country":"US",
    "sg:address":"3234 Holly Berry Ct",
    "sg:city":"Falls Church",
    "sg:classifiers":[
        {
            "category":"Professional",
            "subcategory":"Business Services",
            "type":"Services"
        }
    ],
    "sg:phone":"+1 703 560 1653",
    "sg:postcode":"22042",
    "sg:province":"VA",
    "wof:name":"Itsc Group",
    "wof:placetype":"venue"
},
  "geometry": {"coordinates":[-77.213204,38.857108],"type":"Point"}
}