{
  "type": "Feature",
  "properties": {
    "iso:country":"US",
    "sg:address":"13717 Lynn St",
    "sg:city":"Woodbridge",
    "sg:classifiers":[
        {
            "category":"Professional",
            "type":"Services"
        }
    ],
    "sg:phone":"+1 703 498 2741",
    "sg:postcode":"22191",
    "sg:province":"VA",
    "sg:tags":[
        "establishment"
    ],
    "wof:name":"Mosley L",
    "wof:placetype":"venue"
},
  "geometry": {"coordinates":[-77.26549199999999,38.653318],"type":"Point"}
}