{
  "type": "Feature",
  "properties": {
    "iso:country":"US",
    "sg:address":"400 Surrey Dr",
    "sg:city":"Huddleston",
    "sg:classifiers":[
        {
            "category":"Building & Trades",
            "subcategory":"Landscaping Services",
            "type":"Services"
        }
    ],
    "sg:phone":"+1 540 297 7753",
    "sg:postcode":"24104",
    "sg:province":"VA",
    "wof:name":"Smith Mountain Landscapes",
    "wof:placetype":"venue"
},
  "geometry": {"coordinates":[-79.579469,37.093256],"type":"Point"}
}