{
  "type": "Feature",
  "properties": {
    "iso:country":"US",
    "sg:address":"8703 Digges Rd",
    "sg:city":"Manassas",
    "sg:classifiers":[
        {
            "category":"Health Services",
            "subcategory":"Doctor",
            "type":"Services"
        }
    ],
    "sg:phone":"+1 703 393 8187",
    "sg:postcode":"20110",
    "sg:province":"VA",
    "sg:tags":[
        "medical"
    ],
    "wof:name":"Anu Ralapati Dr",
    "wof:placetype":"venue"
},
  "geometry": {"coordinates":[-77.486378,38.766093],"type":"Point"}
}