{
  "type": "Feature",
  "properties": {
    "iso:country":"US",
    "sg:address":"17 Middlesex Rd",
    "sg:city":"Newport News",
    "sg:classifiers":[
        {
            "category":"Real Estate",
            "subcategory":"Real Estate Operator",
            "type":"Services"
        }
    ],
    "sg:phone":"+1 757 595 5373",
    "sg:postcode":"23606",
    "sg:province":"VA",
    "sg:tags":[
        "apartment"
    ],
    "wof:name":"Hiddenwood North Apartments",
    "wof:placetype":"venue"
},
  "geometry": {"coordinates":[-76.493326,37.075987],"type":"Point"}
}