{
  "type": "Feature",
  "properties": {
    "addr:full":"411 E Liberty St Norfolk VA 23523",
    "addr:housenumber":"411",
    "addr:postcode":"23523",
    "addr:street":"E Liberty St",
    "iso:country":"US",
    "sg:address":"411 E Liberty St",
    "sg:city":"Norfolk",
    "sg:classifiers":[
        {
            "category":"Organizations",
            "subcategory":"Religious Organization",
            "type":"Services"
        }
    ],
    "sg:phone":"+1 757 545 9222",
    "sg:postcode":"23523",
    "sg:province":"VA",
    "sg:tags":[
        "church"
    ],
    "wof:name":"Church Of The Lord Jesus",
    "wof:placetype":"venue"
},
  "geometry": {"coordinates":[-76.281131,36.829419],"type":"Point"}
}