{
  "type": "Feature",
  "properties": {
    "addr:full":"101 E Belt Blvd Richmond VA 23224",
    "addr:housenumber":"101",
    "addr:postcode":"23224",
    "addr:street":"E Belt Blvd",
    "iso:country":"US",
    "sg:address":"101 E Belt Blvd",
    "sg:city":"Richmond",
    "sg:classifiers":[
        {
            "category":"Autos & Motor Vehicles",
            "subcategory":"Automobile Sales",
            "type":"Retail Goods"
        }
    ],
    "sg:phone":"+1 804 232 0055",
    "sg:postcode":"23224",
    "sg:province":"VA",
    "sg:tags":[
        "car",
        "dealer"
    ],
    "wof:name":"Crown Motors Inc",
    "wof:placetype":"venue"
},
  "geometry": {"coordinates":[-77.486619,37.508499],"type":"Point"}
}