{
  "type": "Feature",
  "properties": {
    "iso:country":"US",
    "sg:address":"2154 Evans Ct",
    "sg:city":"Falls Church",
    "sg:classifiers":[
        {
            "category":"Real Estate",
            "subcategory":"Real Estate Operator",
            "type":"Services"
        }
    ],
    "sg:phone":"+1 703 893 1212",
    "sg:postcode":"22043",
    "sg:province":"VA",
    "sg:tags":[
        "apartment"
    ],
    "wof:name":"West Falls Station Apts",
    "wof:placetype":"venue"
},
  "geometry": {"coordinates":[-77.206382,38.903977],"type":"Point"}
}