{
  "type": "Feature",
  "properties": {
    "iso:country":"US",
    "sg:address":"20547 Birchfield Pl",
    "sg:city":"Sterling",
    "sg:classifiers":[
        {
            "category":"Wholesale",
            "subcategory":"Non-durable Goods",
            "type":"Manufacturing & Wholesale Goods"
        }
    ],
    "sg:phone":"+1 703 444 9100",
    "sg:postcode":"20165",
    "sg:province":"VA",
    "sg:tags":[
        "advertising"
    ],
    "wof:name":"Promotions Kartel",
    "wof:placetype":"venue"
},
  "geometry": {"coordinates":[-77.39283500000001,39.046475],"type":"Point"}
}