{
  "type": "Feature",
  "properties": {
    "addr:full":"809 Main St Altavista VA 24517",
    "addr:housenumber":"809",
    "addr:postcode":"24517",
    "addr:street":"Main St",
    "iso:country":"US",
    "sg:address":"809 Main St",
    "sg:city":"Altavista",
    "sg:classifiers":[
        {
            "category":"Retail",
            "subcategory":"Funeral Services",
            "type":"Services"
        }
    ],
    "sg:phone":"+1 434 369 5621",
    "sg:postcode":"24517",
    "sg:province":"VA",
    "sg:tags":[
        "director"
    ],
    "wof:name":"Finch & Finch Funeral Home Inc",
    "wof:placetype":"venue"
},
  "geometry": {"coordinates":[-79.285487,37.111714],"type":"Point"}
}