{
  "type": "Feature",
  "properties": {
    "iso:country":"US",
    "sg:address":"5249 Duke St",
    "sg:city":"Alexandria",
    "sg:classifiers":[
        {
            "category":"Professional",
            "type":"Services"
        }
    ],
    "sg:phone":"+1 703 751 7773",
    "sg:postcode":"22304",
    "sg:province":"VA",
    "sg:tags":[
        "establishment"
    ],
    "wof:name":"Bryce W Phillips Psy D",
    "wof:placetype":"venue"
},
  "geometry": {"coordinates":[-77.123834,38.812643],"type":"Point"}
}