{
  "type": "Feature",
  "properties": {
    "addr:full":"2260 Hunters Woods Plz Reston VA 20191",
    "addr:housenumber":"2260",
    "addr:postcode":"20191",
    "addr:street":"Hunters Woods Plz",
    "iso:country":"US",
    "sg:address":"2260 Hunters Woods Plz",
    "sg:city":"Reston",
    "sg:classifiers":[
        {
            "category":"Restaurant",
            "type":"Food & Drink"
        }
    ],
    "sg:phone":"+1 703 390 9015",
    "sg:postcode":"20191",
    "sg:province":"VA",
    "sg:tags":[
        "drinking",
        "eating"
    ],
    "wof:name":"Buffalo Wing Factory & Pub",
    "wof:placetype":"venue"
},
  "geometry": {"coordinates":[-77.361977,38.938244],"type":"Point"}
}