{
  "type": "Feature",
  "properties": {
    "addr:full":"8009 Hankins Industrial Park Toano VA 23168",
    "addr:housenumber":"8009",
    "addr:postcode":"23168",
    "addr:street":"Hankins Industrial Park",
    "iso:country":"US",
    "sg:address":"8009 Hankins Industrial Park",
    "sg:city":"Toano",
    "sg:classifiers":[
        {
            "category":"Autos & Motor Vehicles",
            "subcategory":"Auto Supplies",
            "type":"Retail Goods"
        }
    ],
    "sg:phone":"+1 757 566 2699",
    "sg:postcode":"23168",
    "sg:province":"VA",
    "sg:tags":[
        "automobile",
        "parts"
    ],
    "wof:name":"NAPA Auto Parts",
    "wof:placetype":"venue"
},
  "geometry": {"coordinates":[-76.803543,37.385306],"type":"Point"}
}