{
  "type": "Feature",
  "properties": {
    "addr:full":"850 Gangplank Rd Moneta VA 24121",
    "addr:housenumber":"850",
    "addr:postcode":"24121",
    "addr:street":"Gangplank Rd",
    "iso:country":"US",
    "sg:address":"850 Gangplank Rd",
    "sg:city":"Moneta",
    "sg:classifiers":[
        {
            "category":"Professional",
            "subcategory":"Management & Consulting",
            "type":"Services"
        }
    ],
    "sg:phone":"+1 540 721 5658",
    "sg:postcode":"24121",
    "sg:province":"VA",
    "wof:name":"Naturals Unlimited",
    "wof:placetype":"venue"
},
  "geometry": {"coordinates":[-79.64915499999999,37.109817],"type":"Point"}
}