{
  "type": "Feature",
  "properties": {
    "iso:country":"US",
    "sg:address":"1212 Loudon Ave NW",
    "sg:city":"Roanoke",
    "sg:phone":"+1 540 342 9235",
    "sg:postcode":"24017",
    "sg:province":"VA",
    "sg:tags":[
        "oil"
    ],
    "wof:name":"Petroleum Marketers Inc",
    "wof:placetype":"venue"
},
  "geometry": {"coordinates":[-79.96136300000001,37.28006],"type":"Point"}
}