{
  "type": "Feature",
  "properties": {
    "iso:country":"US",
    "sg:address":"2924 N Lynnhaven Rd",
    "sg:city":"Virginia Beach",
    "sg:classifiers":[
        {
            "category":"Insurance",
            "subcategory":"Insurance Agent",
            "type":"Services"
        }
    ],
    "sg:phone":"+1 757 340 6322",
    "sg:postcode":"23452",
    "sg:province":"VA",
    "wof:name":"State Farm Insurance",
    "wof:placetype":"venue"
},
  "geometry": {"coordinates":[-76.07264499999999,36.844646],"type":"Point"}
}