{
  "type": "Feature",
  "properties": {
    "iso:country":"US",
    "sg:address":"5502 Alson Dr",
    "sg:city":"Norfolk",
    "sg:classifiers":[
        {
            "category":"Shopping",
            "subcategory":"Florist",
            "type":"Retail Goods"
        }
    ],
    "sg:phone":"+1 757 423 2728",
    "sg:postcode":"23508",
    "sg:province":"VA",
    "wof:name":"D Flowers",
    "wof:placetype":"venue"
},
  "geometry": {"coordinates":[-76.30058099999999,36.89156],"type":"Point"}
}