{
  "type": "Feature",
  "properties": {
    "addr:full":"420 Zelkova Rd Williamsburg VA 23185",
    "addr:housenumber":"420",
    "addr:postcode":"23185",
    "addr:street":"Zelkova Rd",
    "iso:country":"US",
    "sg:address":"420 Zelkova Rd",
    "sg:city":"Williamsburg",
    "sg:classifiers":[
        {
            "category":"Professional",
            "type":"Services"
        }
    ],
    "sg:phone":"+1 757 645 3445",
    "sg:postcode":"23185",
    "sg:province":"VA",
    "wof:name":"Kapp John",
    "wof:placetype":"venue"
},
  "geometry": {"coordinates":[-76.68358499999999,37.279984],"type":"Point"}
}