{
  "type": "Feature",
  "properties": {
    "iso:country":"US",
    "sg:address":"150 E 11th St",
    "sg:city":"Buena Vista",
    "sg:classifiers":[
        {
            "category":"Organizations",
            "subcategory":"Religious Organization",
            "type":"Services"
        }
    ],
    "sg:phone":"+1 540 261 2005",
    "sg:postcode":"24416",
    "sg:province":"VA",
    "sg:tags":[
        "church"
    ],
    "wof:name":"Blue Ridge Baptist Church",
    "wof:placetype":"venue"
},
  "geometry": {"coordinates":[-79.359358,37.722471],"type":"Point"}
}