{
  "type": "Feature",
  "properties": {
    "iso:country":"US",
    "sg:address":"11 Canal Center Plz",
    "sg:city":"Alexandria",
    "sg:classifiers":[
        {
            "category":"Professional",
            "subcategory":"Lawyer & Legal Services",
            "type":"Services"
        },
        {
            "category":"Building & Trades",
            "subcategory":"Construction",
            "type":"Services"
        }
    ],
    "sg:phone":"+1 703 549 6100",
    "sg:postcode":"22314",
    "sg:province":"VA",
    "sg:tags":[
        "painter"
    ],
    "wof:name":"Robertson B Mayo Atty",
    "wof:placetype":"venue"
},
  "geometry": {"coordinates":[-77.037997,38.814814],"type":"Point"}
}