{
  "type": "Feature",
  "properties": {
    "iso:country":"US",
    "sg:address":"328 Virginia Ave",
    "sg:city":"Clarksville",
    "sg:classifiers":[
        {
            "category":"Professional",
            "subcategory":"Lawyer & Legal Services",
            "type":"Services"
        }
    ],
    "sg:phone":"+1 434 374 3600",
    "sg:postcode":"23927",
    "sg:province":"VA",
    "sg:tags":[
        "attorney"
    ],
    "wof:name":"Jonathan Green Attorney At Law",
    "wof:placetype":"venue"
},
  "geometry": {"coordinates":[-78.555515,36.625365],"type":"Point"}
}