{
  "type": "Feature",
  "properties": {
    "addr:full":"12178 Cheshire Ct Bristow VA 20136",
    "addr:housenumber":"12178",
    "addr:postcode":"20136",
    "addr:street":"Cheshire Ct",
    "iso:country":"US",
    "sg:address":"12178 Cheshire Ct",
    "sg:city":"Bristow",
    "sg:classifiers":[
        {
            "category":"Building & Trades",
            "subcategory":"Cleaning & Sanitation",
            "type":"Services"
        }
    ],
    "sg:phone":"+1 703 257 1701",
    "sg:postcode":"20136",
    "sg:province":"VA",
    "sg:tags":[
        "maintenance"
    ],
    "wof:name":"James Holmes Home Maintenance",
    "wof:placetype":"venue"
},
  "geometry": {"coordinates":[-77.553365,38.74222],"type":"Point"}
}