{
  "type": "Feature",
  "properties": {
    "addr:full":"111 Springvale Dr Lynchburg VA 24502",
    "addr:housenumber":"111",
    "addr:postcode":"24502",
    "addr:street":"Springvale Dr",
    "iso:country":"US",
    "sg:address":"111 Springvale Dr",
    "sg:city":"Lynchburg",
    "sg:classifiers":[
        {
            "category":"Freight",
            "type":"Transportation"
        }
    ],
    "sg:phone":"+1 434 239 9990",
    "sg:postcode":"24502",
    "sg:province":"VA",
    "wof:name":"Homeward Bound Removal Trnspt",
    "wof:placetype":"venue"
},
  "geometry": {"coordinates":[-79.233481,37.363662],"type":"Point"}
}