{
  "type": "Feature",
  "properties": {
    "addr:full":"412 S Maple Ave Falls Church VA 22046",
    "addr:housenumber":"412",
    "addr:postcode":"22046",
    "addr:street":"S Maple Ave",
    "iso:country":"US",
    "sg:address":"412 S Maple Ave",
    "sg:city":"Falls Church",
    "sg:phone":"+1 703 532 2673",
    "sg:postcode":"22046",
    "sg:province":"VA",
    "sg:tags":[
        "communications",
        "telegraph"
    ],
    "wof:name":"Ms Enterprises",
    "wof:placetype":"venue"
},
  "geometry": {"coordinates":[-77.177442,38.880316],"type":"Point"}
}