{
  "type": "Feature",
  "properties": {
    "addr:full":"4320 Cogbill Rd Richmond VA 23234",
    "addr:housenumber":"4320",
    "addr:postcode":"23234",
    "addr:street":"Cogbill Rd",
    "iso:country":"US",
    "sg:address":"4320 Cogbill Rd",
    "sg:city":"Richmond",
    "sg:classifiers":[
        {
            "category":"Professional",
            "type":"Services"
        }
    ],
    "sg:phone":"+1 804 743 7891",
    "sg:postcode":"23234",
    "sg:province":"VA",
    "wof:name":"William Worden",
    "wof:placetype":"venue"
},
  "geometry": {"coordinates":[-77.47573300000001,37.440615],"type":"Point"}
}