{
  "type": "Feature",
  "properties": {
    "addr:full":"126 Chatham Ct Danville VA 24540",
    "addr:housenumber":"126",
    "addr:postcode":"24540",
    "addr:street":"Chatham Ct",
    "iso:country":"US",
    "sg:address":"126 Chatham Ct",
    "sg:city":"Danville",
    "sg:classifiers":[
        {
            "category":"Professional",
            "subcategory":"Business Services",
            "type":"Services"
        }
    ],
    "sg:phone":"+1 434 836 5167",
    "sg:postcode":"24540",
    "sg:province":"VA",
    "wof:name":"Informatica",
    "wof:placetype":"venue"
},
  "geometry": {"coordinates":[-79.386101,36.626725],"type":"Point"}
}