{
  "type": "Feature",
  "properties": {
    "addr:full":"169 Wards Gap Rd Cana VA 24317",
    "addr:housenumber":"169",
    "addr:postcode":"24317",
    "addr:street":"Wards Gap Rd",
    "iso:country":"US",
    "sg:address":"169 Wards Gap Rd",
    "sg:city":"Cana",
    "sg:classifiers":[
        {
            "category":"Wholesale",
            "subcategory":"Fruits & Vegetables",
            "type":"Manufacturing & Wholesale Goods"
        }
    ],
    "sg:phone":"+1 276 755 4343",
    "sg:postcode":"24317",
    "sg:province":"VA",
    "wof:name":"Virginia Carolina Produce Co",
    "wof:placetype":"venue"
},
  "geometry": {"coordinates":[-80.61188300000001,36.56273],"type":"Point"}
}