{
  "type": "Feature",
  "properties": {
    "addr:full":"3464 Colonial Ave Roanoke VA 24018",
    "addr:housenumber":"3464",
    "addr:postcode":"24018",
    "addr:street":"Colonial Ave",
    "iso:country":"US",
    "sg:address":"3464 Colonial Ave",
    "sg:city":"Roanoke",
    "sg:classifiers":[
        {
            "category":"Real Estate",
            "subcategory":"Real Estate Operator",
            "type":"Services"
        }
    ],
    "sg:phone":"+1 540 774 7373",
    "sg:postcode":"24018",
    "sg:province":"VA",
    "sg:tags":[
        "building",
        "apartment"
    ],
    "wof:name":"Bent Tree Apartments",
    "wof:placetype":"venue"
},
  "geometry": {"coordinates":[-79.990431,37.233765],"type":"Point"}
}