{
  "type": "Feature",
  "properties": {
    "iso:country":"US",
    "sg:address":"911 Randolph Ave",
    "sg:city":"Pulaski",
    "sg:classifiers":[
        {
            "category":"Government",
            "subcategory":"Office",
            "type":"Public Place"
        }
    ],
    "sg:phone":"+1 540 994 8620",
    "sg:postcode":"24301",
    "sg:province":"VA",
    "sg:tags":[
        "village"
    ],
    "wof:name":"Pulaski Water Filtration Plant",
    "wof:placetype":"venue"
},
  "geometry": {"coordinates":[-80.783805,37.05652],"type":"Point"}
}