{
  "type": "Feature",
  "properties": {
    "iso:country":"US",
    "sg:address":"1005 Lindsay Ct",
    "sg:city":"Fredericksburg",
    "sg:classifiers":[
        {
            "category":"Professional",
            "subcategory":"Business Services",
            "type":"Services"
        }
    ],
    "sg:phone":"+1 540 372 3354",
    "sg:postcode":"22401",
    "sg:province":"VA",
    "sg:tags":[
        "lobbying",
        "development"
    ],
    "wof:name":"Edward C Olivares Jr",
    "wof:placetype":"venue"
},
  "geometry": {"coordinates":[-77.491427,38.30885],"type":"Point"}
}