{
  "type": "Feature",
  "properties": {
    "addr:full":"8601 Claypool Rd Richmond VA 23236",
    "addr:housenumber":"8601",
    "addr:postcode":"23236",
    "addr:street":"Claypool Rd",
    "iso:country":"US",
    "sg:address":"8601 Claypool Rd",
    "sg:city":"Richmond",
    "sg:classifiers":[
        {
            "category":"Professional",
            "subcategory":"Computer Services",
            "type":"Services"
        }
    ],
    "sg:phone":"+1 804 674 4934",
    "sg:postcode":"23236",
    "sg:province":"VA",
    "sg:tags":[
        "publisher",
        "developer",
        "software"
    ],
    "wof:name":"Tam Enterprises",
    "wof:placetype":"venue"
},
  "geometry": {"coordinates":[-77.557457,37.486092],"type":"Point"}
}