{
  "type": "Feature",
  "properties": {
    "iso:country":"US",
    "sg:address":"2912 Center St",
    "sg:city":"Lynchburg",
    "sg:classifiers":[
        {
            "category":"Building & Trades",
            "subcategory":"Construction",
            "type":"Services"
        }
    ],
    "sg:phone":"+1 434 528 4380",
    "sg:postcode":"24501",
    "sg:province":"VA",
    "sg:tags":[
        "house"
    ],
    "wof:name":"H L Pitman",
    "wof:placetype":"venue"
},
  "geometry": {"coordinates":[-79.19183099999999,37.411882],"type":"Point"}
}