{
  "type": "Feature",
  "properties": {
    "addr:full":"7232 Williamson Rd Roanoke VA 24019",
    "addr:housenumber":"7232",
    "addr:postcode":"24019",
    "addr:street":"Williamson Rd",
    "iso:country":"US",
    "sg:address":"7232 Williamson Rd",
    "sg:city":"Roanoke",
    "sg:classifiers":[
        {
            "category":"Restaurant",
            "type":"Food & Drink"
        }
    ],
    "sg:phone":"+1 540 265 0393",
    "sg:postcode":"24019",
    "sg:province":"VA",
    "sg:tags":[
        "eating"
    ],
    "wof:name":"Double Dragon",
    "wof:placetype":"venue"
},
  "geometry": {"coordinates":[-79.954791,37.346801],"type":"Point"}
}