{
  "type": "Feature",
  "properties": {
    "iso:country":"US",
    "sg:address":"2635 Greensboro Rd",
    "sg:city":"Martinsville",
    "sg:classifiers":[
        {
            "category":"Restaurant",
            "type":"Food & Drink"
        }
    ],
    "sg:phone":"+1 276 638 3990",
    "sg:postcode":"24112",
    "sg:province":"VA",
    "sg:tags":[
        "eating",
        "pizza"
    ],
    "wof:name":"Jerry's Pizza",
    "wof:placetype":"venue"
},
  "geometry": {"coordinates":[-79.87444000000001,36.653152],"type":"Point"}
}