{
  "type": "Feature",
  "properties": {
    "addr:full":"1801 Hillenwood Dr Powhatan VA 23139",
    "addr:housenumber":"1801",
    "addr:postcode":"23139",
    "addr:street":"Hillenwood Dr",
    "iso:country":"US",
    "sg:address":"1801 Hillenwood Dr",
    "sg:city":"Powhatan",
    "sg:classifiers":[
        {
            "category":"Professional",
            "type":"Services"
        }
    ],
    "sg:phone":"+1 804 379 6906",
    "sg:postcode":"23139",
    "sg:province":"VA",
    "wof:name":"Softsung Inc",
    "wof:placetype":"venue"
},
  "geometry": {"coordinates":[-77.745392,37.519931],"type":"Point"}
}