{
  "type": "Feature",
  "properties": {
    "addr:full":"501 E Brambleton Ave Norfolk VA 23510",
    "addr:housenumber":"501",
    "addr:postcode":"23510",
    "addr:street":"E Brambleton Ave",
    "iso:country":"US",
    "sg:address":"501 E Brambleton Ave",
    "sg:city":"Norfolk",
    "sg:classifiers":[
        {
            "category":"Insurance",
            "subcategory":"Insurance Agent",
            "type":"Services"
        }
    ],
    "sg:phone":"+1 757 623 2755",
    "sg:postcode":"23510",
    "sg:province":"VA",
    "sg:tags":[
        "auto"
    ],
    "wof:name":"Allstate Insurance Company - Frank & Manouchka Mercer",
    "wof:placetype":"venue"
},
  "geometry": {"coordinates":[-76.283081,36.853691],"type":"Point"}
}