{
  "type": "Feature",
  "properties": {
    "addr:full":"2320 W Hundred Rd Chester VA 23831",
    "addr:housenumber":"2320",
    "addr:postcode":"23831",
    "addr:street":"W Hundred Rd",
    "iso:country":"US",
    "sg:address":"2320 W Hundred Rd",
    "sg:city":"Chester",
    "sg:classifiers":[
        {
            "category":"Banks & Credit Unions",
            "subcategory":"Bank",
            "type":"Services"
        }
    ],
    "sg:phone":"+1 804 706 6184",
    "sg:postcode":"23831",
    "sg:province":"VA",
    "wof:name":"B B & T",
    "wof:placetype":"venue"
},
  "geometry": {"coordinates":[-77.408298,37.354868],"type":"Point"}
}