{
  "type": "Feature",
  "properties": {
    "iso:country":"US",
    "sg:address":"235 Idlewood Ave",
    "sg:city":"Portsmouth",
    "sg:classifiers":[
        {
            "category":"Building & Trades",
            "subcategory":"Construction",
            "type":"Services"
        }
    ],
    "sg:phone":"+1 757 399 4295",
    "sg:postcode":"23704",
    "sg:province":"VA",
    "sg:tags":[
        "residential",
        "wallpapering",
        "commercial",
        "painting"
    ],
    "wof:name":"Two Sisters Painting",
    "wof:placetype":"venue"
},
  "geometry": {"coordinates":[-76.32581500000001,36.83992],"type":"Point"}
}