{
  "type": "Feature",
  "properties": {
    "iso:country":"US",
    "sg:address":"2810 Glade Vale Way",
    "sg:city":"Vienna",
    "sg:classifiers":[
        {
            "category":"Professional",
            "subcategory":"Management & Consulting",
            "type":"Services"
        }
    ],
    "sg:phone":"+1 703 255 3133",
    "sg:postcode":"22181",
    "sg:province":"VA",
    "sg:tags":[
        "consultant",
        "business"
    ],
    "sg:website":"www.arnoldsanow.com",
    "wof:name":"Business Source",
    "wof:placetype":"venue"
},
  "geometry": {"coordinates":[-77.293993,38.885836],"type":"Point"}
}