{
  "type": "Feature",
  "properties": {
    "addr:full":"125 Industrial Dr Elizabethton VA 37620",
    "addr:housenumber":"125",
    "addr:postcode":"37620",
    "addr:street":"Industrial Dr",
    "iso:country":"US",
    "sg:address":"125 Industrial Dr",
    "sg:city":"Elizabethton",
    "sg:classifiers":[
        {
            "category":"Professional",
            "subcategory":"Business Services",
            "type":"Services"
        }
    ],
    "sg:phone":"+1 423 542 1550",
    "sg:postcode":"37620",
    "sg:province":"VA",
    "sg:tags":[
        "repossessing"
    ],
    "wof:name":"Recovery Specialists",
    "wof:placetype":"venue"
},
  "geometry": {"coordinates":[-82.174702,36.560449],"type":"Point"}
}