{
  "type": "Feature",
  "properties": {
    "addr:full":"1519 Summit Ave Richmond VA 23230",
    "addr:housenumber":"1519",
    "addr:postcode":"23230",
    "addr:street":"Summit Ave",
    "iso:country":"US",
    "sg:address":"1519 Summit Ave",
    "sg:city":"Richmond",
    "sg:classifiers":[
        {
            "category":"Professional",
            "subcategory":"Research",
            "type":"Services"
        }
    ],
    "sg:phone":"+1 804 281 3509",
    "sg:postcode":"23230",
    "sg:province":"VA",
    "sg:tags":[
        "nonphysical",
        "commercial"
    ],
    "wof:name":"Reynolds Metals Company",
    "wof:placetype":"venue"
},
  "geometry": {"coordinates":[-77.47018199999999,37.567819],"type":"Point"}
}