{
  "type": "Feature",
  "properties": {
    "addr:full":"7500 Whitepine Rd Richmond VA 23237",
    "addr:postcode":"7500;23237",
    "addr:street":"Whitepine Rd",
    "iso:country":"US",
    "sg:address":"7500 Whitepine Rd",
    "sg:city":"Richmond",
    "sg:classifiers":[
        {
            "category":"Wholesale",
            "subcategory":"Machinery & Supplies",
            "type":"Manufacturing & Wholesale Goods"
        }
    ],
    "sg:phone":"+1 804 275 5930",
    "sg:postcode":"23237",
    "sg:province":"VA",
    "sg:tags":[
        "industrial"
    ],
    "wof:name":"Tricorbraun",
    "wof:placetype":"venue"
},
  "geometry": {"coordinates":[-77.52270799999999,37.399093],"type":"Point"}
}