{
  "type": "Feature",
  "properties": {
    "addr:full":"1355 Beverly Rd Mc Lean VA 22101",
    "addr:housenumber":"1355",
    "addr:postcode":"22101",
    "addr:street":"Beverly Rd",
    "iso:country":"US",
    "sg:address":"1355 Beverly Rd",
    "sg:city":"Mc Lean",
    "sg:classifiers":[
        {
            "category":"Real Estate",
            "subcategory":"Architect",
            "type":"Services"
        }
    ],
    "sg:phone":"+1 703 903 9100",
    "sg:postcode":"22101",
    "sg:province":"VA",
    "sg:website":"www.grimmandparker.com",
    "wof:name":"Grimm and Parker Architects",
    "wof:placetype":"venue"
},
  "geometry": {"coordinates":[-77.1772,38.938499],"type":"Point"}
}