{
  "type": "Feature",
  "properties": {
    "iso:country":"US",
    "sg:address":"18500 Perdido Bay Ter",
    "sg:city":"Leesburg",
    "sg:classifiers":[
        {
            "category":"Professional",
            "subcategory":"Management & Consulting",
            "type":"Services"
        }
    ],
    "sg:phone":"+1 703 669 5896",
    "sg:postcode":"20176",
    "sg:province":"VA",
    "sg:tags":[
        "enforcement",
        "medium",
        "law"
    ],
    "wof:name":"John W Warner Jr",
    "wof:placetype":"venue"
},
  "geometry": {"coordinates":[-77.483886,39.104024],"type":"Point"}
}