{
  "type": "Feature",
  "properties": {
    "iso:country":"US",
    "sg:address":"2807 N Parham Rd",
    "sg:city":"Richmond",
    "sg:classifiers":[
        {
            "category":"Professional",
            "subcategory":"Lawyer & Legal Services",
            "type":"Services"
        }
    ],
    "sg:phone":"+1 804 967 9090",
    "sg:postcode":"23294",
    "sg:province":"VA",
    "sg:tags":[
        "attorney"
    ],
    "wof:name":"Williams & Lynch",
    "wof:placetype":"venue"
},
  "geometry": {"coordinates":[-77.545562,37.628418],"type":"Point"}
}