{
  "type": "Feature",
  "properties": {
    "addr:full":"612 Industrial Park Dr Newport News VA 23608",
    "addr:housenumber":"612",
    "addr:postcode":"23608",
    "addr:street":"Industrial Park Dr",
    "iso:country":"US",
    "sg:address":"612 Industrial Park Dr",
    "sg:city":"Newport News",
    "sg:classifiers":[
        {
            "category":"Wholesale",
            "subcategory":"Beer",
            "type":"Manufacturing & Wholesale Goods"
        }
    ],
    "sg:phone":"+1 757 874 6600",
    "sg:postcode":"23608",
    "sg:province":"VA",
    "sg:tags":[
        "beverage"
    ],
    "wof:name":"Tri-Cities Beverage Corp",
    "wof:placetype":"venue"
},
  "geometry": {"coordinates":[-76.538228,37.165983],"type":"Point"}
}