{
  "type": "Feature",
  "properties": {
    "addr:full":"1600 Carolyn Rd Salem VA 24153",
    "addr:housenumber":"1600",
    "addr:postcode":"24153",
    "addr:street":"Carolyn Rd",
    "iso:country":"US",
    "sg:address":"1600 Carolyn Rd",
    "sg:city":"Salem",
    "sg:classifiers":[
        {
            "category":"Education",
            "subcategory":"School",
            "type":"Public Place"
        }
    ],
    "sg:phone":"+1 540 387 2478",
    "sg:postcode":"24153",
    "sg:province":"VA",
    "sg:tags":[
        "executive"
    ],
    "wof:name":"South Salem Elementary School",
    "wof:placetype":"venue"
},
  "geometry": {"coordinates":[-80.081602,37.277829],"type":"Point"}
}