{
  "type": "Feature",
  "properties": {
    "iso:country":"US",
    "sg:address":"8801 Newell Ct",
    "sg:city":"Springfield",
    "sg:classifiers":[
        {
            "category":"Manufacturing",
            "subcategory":"Paper Products",
            "type":"Manufacturing & Wholesale Goods"
        }
    ],
    "sg:phone":"+1 703 644 1186",
    "sg:postcode":"22153",
    "sg:province":"VA",
    "sg:tags":[
        "stationery",
        "store",
        "mfg"
    ],
    "wof:name":"Cordially Yours",
    "wof:placetype":"venue"
},
  "geometry": {"coordinates":[-77.251007,38.761051],"type":"Point"}
}