{
  "type": "Feature",
  "properties": {
    "iso:country":"US",
    "sg:address":"3900 Bonney Rd",
    "sg:city":"Virginia Beach",
    "sg:classifiers":[
        {
            "category":"Retail",
            "subcategory":"Auto Rental",
            "type":"Services"
        }
    ],
    "sg:phone":"+1 757 486 6535",
    "sg:postcode":"23452",
    "sg:province":"VA",
    "sg:tags":[
        "renting",
        "truck",
        "leasing"
    ],
    "wof:name":"Budget Truck Rental",
    "wof:placetype":"venue"
},
  "geometry": {"coordinates":[-76.11077299999999,36.838744],"type":"Point"}
}