{
  "type": "Feature",
  "properties": {
    "addr:full":"22135 Davis Dr Ste 116 Sterling VA 20164",
    "addr:housenumber":"22135",
    "addr:postcode":"20164",
    "addr:street":"Davis Dr Ste 116",
    "iso:country":"US",
    "sg:address":"22135 Davis Dr Ste 116",
    "sg:city":"Sterling",
    "sg:classifiers":[
        {
            "category":"Professional",
            "subcategory":"Detective & Security Services",
            "type":"Services"
        }
    ],
    "sg:phone":"+1 703 860 3686",
    "sg:postcode":"20164",
    "sg:province":"VA",
    "sg:tags":[
        "information",
        "bureau"
    ],
    "wof:name":"Apertures Inc",
    "wof:placetype":"venue"
},
  "geometry": {"coordinates":[-77.428629,39.00357],"type":"Point"}
}