{
  "type": "Feature",
  "properties": {
    "iso:country":"US",
    "sg:address":"4605 Valley Forge Ln",
    "sg:city":"Virginia Beach",
    "sg:classifiers":[
        {
            "category":"Building & Trades",
            "subcategory":"Construction",
            "type":"Services"
        }
    ],
    "sg:phone":"+1 757 490 5444",
    "sg:postcode":"23462",
    "sg:province":"VA",
    "sg:tags":[
        "on",
        "site",
        "welding"
    ],
    "wof:name":"D&G Mobile Welding",
    "wof:placetype":"venue"
},
  "geometry": {"coordinates":[-76.140614,36.849195],"type":"Point"}
}