{
  "type": "Feature",
  "properties": {
    "iso:country":"US",
    "sg:address":"3076 Kline Dr",
    "sg:city":"Virginia Beach",
    "sg:classifiers":[
        {
            "category":"Retail",
            "subcategory":"Animal Services",
            "type":"Services"
        }
    ],
    "sg:phone":"+1 757 340 6818",
    "sg:postcode":"23452",
    "sg:province":"VA",
    "wof:name":"Annie Sandler Ltd",
    "wof:placetype":"venue"
},
  "geometry": {"coordinates":[-76.078838,36.880337],"type":"Point"}
}