{
  "type": "Feature",
  "properties": {
    "addr:full":"112 Fardale St SE Vienna VA 22180",
    "addr:housenumber":"112",
    "addr:postcode":"22180",
    "addr:street":"Fardale St Se",
    "iso:country":"US",
    "sg:address":"112 Fardale St SE",
    "sg:city":"Vienna",
    "sg:classifiers":[
        {
            "category":"Professional",
            "subcategory":"Management & Consulting",
            "type":"Services"
        }
    ],
    "sg:phone":"+1 703 698 7652",
    "sg:postcode":"22180",
    "sg:province":"VA",
    "sg:tags":[
        "business"
    ],
    "wof:name":"Joseph Raible",
    "wof:placetype":"venue"
},
  "geometry": {"coordinates":[-77.24717800000001,38.88956],"type":"Point"}
}