{
  "type": "Feature",
  "properties": {
    "addr:full":"5801 Bremo Rd Richmond VA 23226",
    "addr:housenumber":"5801",
    "addr:postcode":"23226",
    "addr:street":"Bremo Rd",
    "iso:country":"US",
    "sg:address":"5801 Bremo Rd",
    "sg:city":"Richmond",
    "sg:classifiers":[
        {
            "category":"Health Services",
            "subcategory":"Medical Lab",
            "type":"Services"
        }
    ],
    "sg:phone":"+1 804 281 8100",
    "sg:postcode":"23226",
    "sg:province":"VA",
    "sg:tags":[
        "laboratory"
    ],
    "wof:name":"Healthpartners Labs",
    "wof:placetype":"venue"
},
  "geometry": {"coordinates":[-77.515458,37.583292],"type":"Point"}
}