{
  "type": "Feature",
  "properties": {
    "iso:country":"US",
    "sg:address":"4851 Fort Ave",
    "sg:city":"Lynchburg",
    "sg:classifiers":[
        {
            "category":"Organizations",
            "subcategory":"Non-profit Organization",
            "type":"Services"
        },
        {
            "category":"Social Services",
            "type":"Services"
        }
    ],
    "sg:phone":"+1 434 832 7030",
    "sg:postcode":"24502",
    "sg:province":"VA",
    "sg:tags":[
        "human"
    ],
    "wof:name":"Creative Family Solutions Inc",
    "wof:placetype":"venue"
},
  "geometry": {"coordinates":[-79.18176099999999,37.381239],"type":"Point"}
}