{
  "type": "Feature",
  "properties": {
    "iso:country":"US",
    "sg:address":"8313 Gaylord Rd",
    "sg:city":"Richmond",
    "sg:phone":"+1 804 270 0804",
    "sg:postcode":"23229",
    "sg:province":"VA",
    "sg:tags":[
        "product",
        "petroleum"
    ],
    "wof:name":"Shirley Tuck Amsoil Dealer",
    "wof:placetype":"venue"
},
  "geometry": {"coordinates":[-77.556938,37.613755],"type":"Point"}
}