{
  "type": "Feature",
  "properties": {
    "addr:full":"2114 Thoroughgood Rd Virginia Beach VA 23455",
    "addr:housenumber":"2114",
    "addr:postcode":"23455",
    "addr:street":"Thoroughgood Rd",
    "iso:country":"US",
    "sg:address":"2114 Thoroughgood Rd",
    "sg:city":"Virginia Beach",
    "sg:classifiers":[
        {
            "category":"Retail",
            "subcategory":"Auto Repair",
            "type":"Services"
        }
    ],
    "sg:phone":"+1 757 363 8243",
    "sg:postcode":"23455",
    "sg:province":"VA",
    "sg:tags":[
        "repairing",
        "automobile",
        "general"
    ],
    "wof:name":"Automotive Remedies Inc",
    "wof:placetype":"venue"
},
  "geometry": {"coordinates":[-76.141453,36.8958],"type":"Point"}
}