{
  "type": "Feature",
  "properties": {
    "addr:full":"16130 Forest Rd Forest VA 24551",
    "addr:housenumber":"16130",
    "addr:postcode":"24551",
    "addr:street":"Forest Rd",
    "iso:country":"US",
    "sg:address":"16130 Forest Rd",
    "sg:city":"Forest",
    "sg:classifiers":[
        {
            "category":"Farming",
            "subcategory":"Dairy Farm",
            "type":"Manufacturing & Wholesale Goods"
        }
    ],
    "sg:phone":"+1 434 525 6081",
    "sg:postcode":"24551",
    "sg:province":"VA",
    "wof:name":"R P & D J White",
    "wof:placetype":"venue"
},
  "geometry": {"coordinates":[-79.27839299999999,37.365783],"type":"Point"}
}