{
  "type": "Feature",
  "properties": {
    "addr:full":"127 W Broad St Falls Church VA 22046",
    "addr:housenumber":"127",
    "addr:postcode":"22046",
    "addr:street":"W Broad St",
    "iso:country":"US",
    "sg:address":"127 W Broad St",
    "sg:city":"Falls Church",
    "sg:classifiers":[
        {
            "category":"Restaurant",
            "type":"Food & Drink"
        }
    ],
    "sg:menulink":"http://www.allmenus.com/va/falls-church/24480-applebees/menu/",
    "sg:phone":"+1 703 532 5380",
    "sg:postcode":"22046",
    "sg:province":"VA",
    "sg:tags":[
        "burger",
        "american",
        "sandwich",
        "soup"
    ],
    "wof:name":"Applebee's",
    "wof:placetype":"venue"
},
  "geometry": {"coordinates":[-77.17148,38.882412],"type":"Point"}
}