{
  "type": "Feature",
  "properties": {
    "addr:full":"17260 Vannes Ct Hamilton VA 20158",
    "addr:postcode":"17260;20158",
    "addr:street":"Ct",
    "iso:country":"US",
    "sg:address":"17260 Vannes Ct",
    "sg:city":"Hamilton",
    "sg:classifiers":[
        {
            "category":"Professional",
            "subcategory":"Management & Consulting",
            "type":"Services"
        }
    ],
    "sg:phone":"+1 540 751 2093",
    "sg:postcode":"20158",
    "sg:province":"VA",
    "wof:name":"Hunt Management Svc",
    "wof:placetype":"venue"
},
  "geometry": {"coordinates":[-77.648836,39.139492],"type":"Point"}
}