{
  "type": "Feature",
  "properties": {
    "iso:country":"US",
    "sg:address":"11759 Fair Oaks Mall",
    "sg:city":"Fairfax",
    "sg:classifiers":[
        {
            "category":"Shopping",
            "subcategory":"Clothing, Apparel, & Fashions",
            "type":"Retail Goods"
        }
    ],
    "sg:phone":"+1 703 359 2943",
    "sg:postcode":"22033",
    "sg:province":"VA",
    "sg:tags":[
        "swimwear",
        "accessory"
    ],
    "wof:name":"Water Water Everywhere Inc",
    "wof:placetype":"venue"
},
  "geometry": {"coordinates":[-77.355783,38.861223],"type":"Point"}
}