{
  "type": "Feature",
  "properties": {
    "addr:full":"110 Hardwood Dr Newport News VA 23603",
    "addr:housenumber":"110",
    "addr:postcode":"23603",
    "addr:street":"Hardwood Dr",
    "iso:country":"US",
    "sg:address":"110 Hardwood Dr",
    "sg:city":"Newport News",
    "sg:classifiers":[
        {
            "category":"Building & Trades",
            "subcategory":"Electrical",
            "type":"Services"
        }
    ],
    "sg:phone":"+1 757 886 0100",
    "sg:postcode":"23603",
    "sg:province":"VA",
    "sg:tags":[
        "electric",
        "contractor"
    ],
    "wof:name":"Advanced Electrical Svc",
    "wof:placetype":"venue"
},
  "geometry": {"coordinates":[-76.58986899999999,37.176595],"type":"Point"}
}