{
  "type": "Feature",
  "properties": {
    "iso:country":"US",
    "sg:address":"23008 Browning Rd",
    "sg:city":"Abingdon",
    "sg:classifiers":[
        {
            "category":"Building & Trades",
            "subcategory":"Construction",
            "type":"Services"
        }
    ],
    "sg:phone":"+1 276 628 7545",
    "sg:postcode":"24211",
    "sg:province":"VA",
    "wof:name":"Bartley Construction",
    "wof:placetype":"venue"
},
  "geometry": {"coordinates":[-81.96093,36.647094],"type":"Point"}
}