{
  "type": "Feature",
  "properties": {
    "iso:country":"US",
    "sg:address":"326 Park St NE",
    "sg:city":"Vienna",
    "sg:classifiers":[
        {
            "category":"Professional",
            "subcategory":"Lawyer & Legal Services",
            "type":"Services"
        }
    ],
    "sg:phone":"+1 703 255 4800",
    "sg:postcode":"22180",
    "sg:province":"VA",
    "sg:tags":[
        "attorney"
    ],
    "wof:name":"Wilson James Law Offices",
    "wof:placetype":"venue"
},
  "geometry": {"coordinates":[-77.267371,38.906824],"type":"Point"}
}