{
  "type": "Feature",
  "properties": {
    "addr:full":"1607 Maddux Ln Mc Lean VA 22101",
    "addr:housenumber":"1607",
    "addr:postcode":"22101",
    "addr:street":"Maddux Ln Mc Lean",
    "iso:country":"US",
    "sg:address":"1607 Maddux Ln",
    "sg:city":"Mc Lean",
    "sg:classifiers":[
        {
            "category":"Professional",
            "subcategory":"Management & Consulting",
            "type":"Services"
        }
    ],
    "sg:phone":"+1 703 734 4145",
    "sg:postcode":"22101",
    "sg:province":"VA",
    "sg:tags":[
        "business"
    ],
    "wof:name":"Fornaro Consulting LLC",
    "wof:placetype":"venue"
},
  "geometry": {"coordinates":[-77.143655,38.926089],"type":"Point"}
}