{
  "type": "Feature",
  "properties": {
    "iso:country":"US",
    "sg:address":"Seminole Square Shopping Center 139 Zan Rd",
    "sg:city":"Charlottesville",
    "sg:classifiers":[
        {
            "category":"Restaurant",
            "type":"Food & Drink"
        }
    ],
    "sg:phone":"+1 434 973 0440",
    "sg:postcode":"22901",
    "sg:province":"VA",
    "sg:tags":[
        "indian"
    ],
    "sg:website":"www.maharaja-indian-restaurant.com/",
    "wof:name":"Maharaja Fine Indian Cuisine",
    "wof:placetype":"venue"
},
  "geometry": {"coordinates":[-78.48904899999999,38.063699],"type":"Point"}
}