{
  "type": "Feature",
  "properties": {
    "iso:country":"US",
    "sg:address":"5514 Alma Ln",
    "sg:city":"Springfield",
    "sg:classifiers":[
        {
            "category":"Health Services",
            "subcategory":"Doctor",
            "type":"Services"
        }
    ],
    "sg:phone":"+1 703 813 1242",
    "sg:postcode":"22151",
    "sg:province":"VA",
    "sg:tags":[
        "physician",
        "surgeon"
    ],
    "wof:name":"Heart Specialists-Northern Va",
    "wof:placetype":"venue"
},
  "geometry": {"coordinates":[-77.185813,38.800249],"type":"Point"}
}