{
  "type": "Feature",
  "properties": {
    "addr:full":"205 N Bridge St Bedford VA 24523",
    "addr:housenumber":"205",
    "addr:postcode":"24523",
    "addr:street":"N Bridge St",
    "iso:country":"US",
    "sg:address":"205 N Bridge St",
    "sg:city":"Bedford",
    "sg:classifiers":[
        {
            "category":"Shopping",
            "subcategory":"Gifts & Souvenirs",
            "type":"Retail Goods"
        }
    ],
    "sg:phone":"+1 540 587 8660",
    "sg:postcode":"24523",
    "sg:province":"VA",
    "wof:name":"Ser Arts",
    "wof:placetype":"venue"
},
  "geometry": {"coordinates":[-79.523096,37.33568],"type":"Point"}
}