{
  "type": "Feature",
  "properties": {
    "addr:full":"7336 Old Mountain Rd Roanoke VA 24019",
    "addr:housenumber":"7336",
    "addr:postcode":"24019",
    "addr:street":"Old Mountain Rd",
    "iso:country":"US",
    "sg:address":"7336 Old Mountain Rd",
    "sg:city":"Roanoke",
    "sg:classifiers":[
        {
            "category":"Retail",
            "subcategory":"Laundry & Dry Cleaning",
            "type":"Services"
        }
    ],
    "sg:phone":"+1 540 362 1479",
    "sg:postcode":"24019",
    "sg:province":"VA",
    "sg:tags":[
        "cleaners",
        "rug",
        "carpet"
    ],
    "wof:name":"Robert's Carpet Cleaning",
    "wof:placetype":"venue"
},
  "geometry": {"coordinates":[-79.914857,37.348427],"type":"Point"}
}