{
  "type": "Feature",
  "properties": {
    "iso:country":"US",
    "sg:address":"3810 Smith Mountain Rd",
    "sg:city":"Penhook",
    "sg:classifiers":[
        {
            "category":"Manufacturing",
            "subcategory":"Buildings",
            "type":"Manufacturing & Wholesale Goods"
        },
        {
            "category":"Building & Trades",
            "subcategory":"Construction",
            "type":"Services"
        }
    ],
    "sg:phone":"+1 434 927 5004",
    "sg:postcode":"24137",
    "sg:province":"VA",
    "sg:tags":[
        "home",
        "builder",
        "contractor"
    ],
    "wof:name":"Home Maint Rep Svc",
    "wof:placetype":"venue"
},
  "geometry": {"coordinates":[-79.590478,37.007773],"type":"Point"}
}