{
  "type": "Feature",
  "properties": {
    "addr:full":"11242 Waples Mill Rd Fairfax VA 22030",
    "addr:housenumber":"11242",
    "addr:postcode":"22030",
    "addr:street":"Waples Mill Rd",
    "iso:country":"US",
    "sg:address":"11242 Waples Mill Rd",
    "sg:city":"Fairfax",
    "sg:classifiers":[
        {
            "category":"Professional",
            "subcategory":"Engineering",
            "type":"Services"
        }
    ],
    "sg:phone":"+1 703 385 0393",
    "sg:postcode":"22030",
    "sg:province":"VA",
    "wof:name":"Tri-M Technologies Inc",
    "wof:placetype":"venue"
},
  "geometry": {"coordinates":[-77.33589499999999,38.861022],"type":"Point"}
}