{
  "type": "Feature",
  "properties": {
    "iso:country":"US",
    "sg:address":"407 Mill St",
    "sg:city":"Occoquan",
    "sg:classifiers":[
        {
            "category":"Shopping",
            "subcategory":"Used Merchandise",
            "type":"Retail Goods"
        }
    ],
    "sg:phone":"+1 703 490 1750",
    "sg:postcode":"22125",
    "sg:province":"VA",
    "sg:tags":[
        "antique"
    ],
    "wof:name":"Sloan's Antique Office",
    "wof:placetype":"venue"
},
  "geometry": {"coordinates":[-77.261667,38.68492],"type":"Point"}
}