{
  "type": "Feature",
  "properties": {
    "addr:full":"206 Greenville Ave Staunton VA 24401",
    "addr:housenumber":"206",
    "addr:postcode":"24401",
    "addr:street":"Greenville Ave",
    "iso:country":"US",
    "sg:address":"206 Greenville Ave",
    "sg:city":"Staunton",
    "sg:classifiers":[
        {
            "category":"Home & Garden",
            "subcategory":"Home Furnishings",
            "type":"Retail Goods"
        }
    ],
    "sg:phone":"+1 540 887 1201",
    "sg:postcode":"24401",
    "sg:province":"VA",
    "sg:tags":[
        "lighting"
    ],
    "wof:name":"South River Lighting Inc",
    "wof:placetype":"venue"
},
  "geometry": {"coordinates":[-79.06893599999999,38.146532],"type":"Point"}
}