{
  "type": "Feature",
  "properties": {
    "iso:country":"US",
    "sg:address":"5707 Edsall Rd",
    "sg:city":"Alexandria",
    "sg:classifiers":[
        {
            "category":"Building & Trades",
            "subcategory":"Plumbing",
            "type":"Services"
        }
    ],
    "sg:phone":"+1 703 751 7500",
    "sg:postcode":"22304",
    "sg:province":"VA",
    "sg:tags":[
        "repair",
        "installation",
        "system",
        "air",
        "heating",
        "conditioning",
        "contractor",
        "unit"
    ],
    "wof:name":"Krafft Service Corporation",
    "wof:placetype":"venue"
},
  "geometry": {"coordinates":[-77.132986,38.807701],"type":"Point"}
}