{
  "type": "Feature",
  "properties": {
    "addr:full":"1958 Evelyn Byrd Ave Harrisonburg VA 22801",
    "addr:housenumber":"1958",
    "addr:postcode":"22801",
    "addr:street":"Evelyn Byrd Ave",
    "iso:country":"US",
    "sg:address":"1958 Evelyn Byrd Ave",
    "sg:city":"Harrisonburg",
    "sg:classifiers":[
        {
            "category":"Banks & Credit Unions",
            "subcategory":"Investment Brokerage",
            "type":"Services"
        }
    ],
    "sg:phone":"+1 540 434 2505",
    "sg:postcode":"22801",
    "sg:province":"VA",
    "sg:tags":[
        "security"
    ],
    "wof:name":"Rbc Dain Rauscher Corporation",
    "wof:placetype":"venue"
},
  "geometry": {"coordinates":[-78.847741,38.428075],"type":"Point"}
}