{
  "type": "Feature",
  "properties": {
    "addr:full":"6700 Bleight Dr Haymarket VA 20169",
    "addr:housenumber":"6700",
    "addr:postcode":"20169",
    "addr:street":"Bleight Dr",
    "iso:country":"US",
    "sg:address":"6700 Bleight Dr",
    "sg:city":"Haymarket",
    "sg:classifiers":[
        {
            "category":"Building & Trades",
            "subcategory":"Construction",
            "type":"Services"
        }
    ],
    "sg:phone":"+1 703 754 7202",
    "sg:postcode":"20169",
    "sg:province":"VA",
    "sg:tags":[
        "contractor"
    ],
    "wof:name":"Crouch Sam & Son Contr",
    "wof:placetype":"venue"
},
  "geometry": {"coordinates":[-77.628601,38.811798],"type":"Point"}
}