{
  "type": "Feature",
  "properties": {
    "iso:country":"US",
    "sg:address":"1101 E Main St",
    "sg:city":"Richmond",
    "sg:classifiers":[
        {
            "category":"Professional",
            "subcategory":"Printing & Photocopies",
            "type":"Services"
        }
    ],
    "sg:phone":"+1 804 343 6985",
    "sg:postcode":"23219",
    "sg:province":"VA",
    "sg:tags":[
        "photocopying"
    ],
    "wof:name":"Kinkos",
    "wof:placetype":"venue"
},
  "geometry": {"coordinates":[-77.434641,37.537149],"type":"Point"}
}