{
  "type": "Feature",
  "properties": {
    "addr:full":"929 Brookdale St Martinsville VA 24112",
    "addr:housenumber":"929",
    "addr:postcode":"24112",
    "addr:street":"Brookdale St",
    "iso:country":"US",
    "sg:address":"929 Brookdale St",
    "sg:city":"Martinsville",
    "sg:classifiers":[
        {
            "category":"Organizations",
            "subcategory":"Religious Organization",
            "type":"Services"
        }
    ],
    "sg:phone":"+1 276 632 7935",
    "sg:postcode":"24112",
    "sg:province":"VA",
    "sg:tags":[
        "church"
    ],
    "wof:name":"Mt Bethel Pentecostal Church",
    "wof:placetype":"venue"
},
  "geometry": {"coordinates":[-79.851934,36.685063],"type":"Point"}
}