{
  "type": "Feature",
  "properties": {
    "addr:full":"3252 Indian River Rd Virginia Beach VA 23456",
    "addr:housenumber":"3252",
    "addr:postcode":"23456",
    "addr:street":"Indian River Rd",
    "iso:country":"US",
    "sg:address":"3252 Indian River Rd",
    "sg:city":"Virginia Beach",
    "sg:classifiers":[
        {
            "category":"Organizations",
            "subcategory":"Religious Organization",
            "type":"Services"
        }
    ],
    "sg:phone":"+1 757 721 3987",
    "sg:postcode":"23456",
    "sg:province":"VA",
    "sg:tags":[
        "church"
    ],
    "wof:name":"Campbell's Chapel Church",
    "wof:placetype":"venue"
},
  "geometry": {"coordinates":[-76.098483,36.734122],"type":"Point"}
}