{
  "type": "Feature",
  "properties": {
    "addr:full":"45075 Old Ox Rd Sterling VA 20166",
    "addr:housenumber":"45075",
    "addr:postcode":"20166",
    "addr:street":"Old Ox Rd",
    "iso:country":"US",
    "sg:address":"45075 Old Ox Rd",
    "sg:city":"Sterling",
    "sg:classifiers":[
        {
            "category":"Wholesale",
            "subcategory":"Electrical",
            "type":"Manufacturing & Wholesale Goods"
        }
    ],
    "sg:phone":"+1 703 318 2300",
    "sg:postcode":"20166",
    "sg:province":"VA",
    "sg:tags":[
        "equipment"
    ],
    "wof:name":"Anixter",
    "wof:placetype":"venue"
},
  "geometry": {"coordinates":[-77.441171,38.979059],"type":"Point"}
}