{
  "type": "Feature",
  "properties": {
    "iso:country":"US",
    "sg:address":"6633 Blackwater Rd",
    "sg:city":"Virginia Beach",
    "sg:classifiers":[
        {
            "category":"Building & Trades",
            "subcategory":"Construction",
            "type":"Services"
        }
    ],
    "sg:phone":"+1 757 498 4169",
    "sg:postcode":"23457",
    "sg:province":"VA",
    "sg:tags":[
        "roofing",
        "contractor"
    ],
    "wof:name":"Professional Roofing",
    "wof:placetype":"venue"
},
  "geometry": {"coordinates":[-76.072647,36.553377],"type":"Point"}
}