{
  "type": "Feature",
  "properties": {
    "iso:country":"US",
    "sg:address":"109 Channel Cove",
    "sg:city":"Stafford",
    "sg:classifiers":[
        {
            "category":"Cinema",
            "subcategory":"Movie Rental",
            "type":"Entertainment"
        }
    ],
    "sg:phone":"+1 540 659 5977",
    "sg:postcode":"22554",
    "sg:province":"VA",
    "sg:tags":[
        "contracting",
        "video",
        "tape",
        "general"
    ],
    "wof:name":"Docs Video",
    "wof:placetype":"venue"
},
  "geometry": {"coordinates":[-77.386736,38.453673],"type":"Point"}
}