{
  "type": "Feature",
  "properties": {
    "iso:country":"US",
    "sg:address":"2573 Gunstock Creek Rd",
    "sg:city":"Bedford",
    "sg:classifiers":[
        {
            "category":"Shopping",
            "subcategory":"Gifts & Souvenirs",
            "type":"Retail Goods"
        }
    ],
    "sg:phone":"+1 540 586 1271",
    "sg:postcode":"24523",
    "sg:province":"VA",
    "sg:tags":[
        "merchandise"
    ],
    "wof:name":"A Village Store",
    "wof:placetype":"venue"
},
  "geometry": {"coordinates":[-79.467394,37.492686],"type":"Point"}
}