{
  "type": "Feature",
  "properties": {
    "addr:full":"30 Lagrange St Pulaski VA 24301",
    "addr:housenumber":"30",
    "addr:postcode":"24301",
    "addr:street":"Lagrange St",
    "iso:country":"US",
    "sg:address":"30 Lagrange St",
    "sg:city":"Pulaski",
    "sg:phone":"+1 540 980 1011",
    "sg:postcode":"24301",
    "sg:province":"VA",
    "sg:tags":[
        "oil"
    ],
    "wof:name":"Huff Petroleum Co",
    "wof:placetype":"venue"
},
  "geometry": {"coordinates":[-80.785888,37.045614],"type":"Point"}
}