{
  "type": "Feature",
  "properties": {
    "iso:country":"US",
    "sg:address":"3635 Low Gap Rd",
    "sg:city":"Trout Dale",
    "sg:classifiers":[
        {
            "category":"Building & Trades",
            "subcategory":"Construction",
            "type":"Services"
        }
    ],
    "sg:phone":"+1 276 579 2023",
    "sg:postcode":"24378",
    "sg:province":"VA",
    "sg:tags":[
        "contractor"
    ],
    "wof:name":"Weaver Contracting",
    "wof:placetype":"venue"
},
  "geometry": {"coordinates":[-81.420976,36.645546],"type":"Point"}
}