{
  "type": "Feature",
  "properties": {
    "addr:full":"1903 Lafayette Blvd Norfolk VA 23509",
    "addr:housenumber":"1903",
    "addr:postcode":"23509",
    "addr:street":"Lafayette Blvd",
    "iso:country":"US",
    "sg:address":"1903 Lafayette Blvd",
    "sg:city":"Norfolk",
    "sg:classifiers":[
        {
            "category":"Shopping",
            "subcategory":"Hobbies, Toys, & Games",
            "type":"Retail Goods"
        }
    ],
    "sg:phone":"+1 757 627 9929",
    "sg:postcode":"23509",
    "sg:province":"VA",
    "wof:name":"Our World",
    "wof:placetype":"venue"
},
  "geometry": {"coordinates":[-76.262677,36.877373],"type":"Point"}
}