{
  "type": "Feature",
  "properties": {
    "addr:full":"13325 Coverly Rd Amelia Court House VA 23002",
    "addr:housenumber":"13325",
    "addr:postcode":"23002",
    "addr:street":"Coverly Rd",
    "iso:country":"US",
    "sg:address":"13325 Coverly Rd",
    "sg:city":"Amelia Court House",
    "sg:classifiers":[
        {
            "category":"Home & Garden",
            "subcategory":"Garden Supply",
            "type":"Retail Goods"
        }
    ],
    "sg:phone":"+1 804 561 3359",
    "sg:postcode":"23002",
    "sg:province":"VA",
    "wof:name":"Greener Landscape Nursery",
    "wof:placetype":"venue"
},
  "geometry": {"coordinates":[-77.88342900000001,37.409704],"type":"Point"}
}