{
  "type": "Feature",
  "properties": {
    "addr:full":"3000 Ogden Rd Roanoke VA 24018",
    "addr:housenumber":"3000",
    "addr:postcode":"24018",
    "addr:street":"Ogden Rd",
    "iso:country":"US",
    "sg:address":"3000 Ogden Rd",
    "sg:city":"Roanoke",
    "sg:classifiers":[
        {
            "category":"Manufacturing",
            "subcategory":"Food",
            "type":"Manufacturing & Wholesale Goods"
        },
        {
            "category":"Food & Beverages",
            "subcategory":"Groceries & Convenience Stores",
            "type":"Retail Goods"
        }
    ],
    "sg:phone":"+1 540 343 7397",
    "sg:postcode":"24018",
    "sg:province":"VA",
    "sg:tags":[
        "product"
    ],
    "wof:name":"Stop In Food Stores",
    "wof:placetype":"venue"
},
  "geometry": {"coordinates":[-79.981499,37.230061],"type":"Point"}
}