{
  "type": "Feature",
  "properties": {
    "addr:full":"1631 Bruce Ave Charlottesville VA 22903",
    "addr:housenumber":"1631",
    "addr:postcode":"22903",
    "addr:street":"Bruce Ave",
    "iso:country":"US",
    "sg:address":"1631 Bruce Ave",
    "sg:city":"Charlottesville",
    "sg:classifiers":[
        {
            "category":"Professional",
            "type":"Services"
        }
    ],
    "sg:phone":"+1 434 984 0376",
    "sg:postcode":"22903",
    "sg:province":"VA",
    "wof:name":"Lisa Goff",
    "wof:placetype":"venue"
},
  "geometry": {"coordinates":[-78.487044,38.050476],"type":"Point"}
}