{
  "type": "Feature",
  "properties": {
    "iso:country":"US",
    "sg:address":"12111 W Broad St",
    "sg:city":"Richmond",
    "sg:classifiers":[
        {
            "category":"Shopping",
            "subcategory":"Florist",
            "type":"Retail Goods"
        }
    ],
    "sg:phone":"+1 804 360 2800",
    "sg:postcode":"23233",
    "sg:province":"VA",
    "sg:website":"www.stanges.com",
    "wof:name":"Strange's Florists Greenhouse",
    "wof:placetype":"venue"
},
  "geometry": {"coordinates":[-77.637923,37.660242],"type":"Point"}
}