{
  "type": "Feature",
  "properties": {
    "iso:country":"US",
    "sg:address":"1736 Independence Blvd",
    "sg:city":"Virginia Beach",
    "sg:classifiers":[
        {
            "category":"Retail",
            "subcategory":"Auto Repair",
            "type":"Services"
        }
    ],
    "sg:phone":"+1 757 460 1018",
    "sg:postcode":"23455",
    "sg:province":"VA",
    "sg:tags":[
        "automotive"
    ],
    "wof:name":"Brownngs Altrntor Starter Exch",
    "wof:placetype":"venue"
},
  "geometry": {"coordinates":[-76.143789,36.895355],"type":"Point"}
}