{
  "type": "Feature",
  "properties": {
    "addr:full":"432 Crosman Ct Purcellville VA 20132",
    "addr:housenumber":"432",
    "addr:postcode":"20132",
    "addr:street":"Crosman Ct",
    "iso:country":"US",
    "sg:address":"432 Crosman Ct",
    "sg:city":"Purcellville",
    "sg:classifiers":[
        {
            "category":"Professional",
            "subcategory":"Computer Services",
            "type":"Services"
        }
    ],
    "sg:phone":"+1 540 338 8599",
    "sg:postcode":"20132",
    "sg:province":"VA",
    "sg:tags":[
        "information",
        "technology",
        "solution",
        "provider"
    ],
    "wof:name":"Accountspro Bus Tech Solutions",
    "wof:placetype":"venue"
},
  "geometry": {"coordinates":[-77.70948199999999,39.125561],"type":"Point"}
}