{
  "type": "Feature",
  "properties": {
    "addr:full":"4042 Welcome Valley Rd SE Roanoke VA 24014",
    "addr:housenumber":"4042",
    "addr:postcode":"24014",
    "addr:street":"Welcome Valley Rd Se",
    "iso:country":"US",
    "sg:address":"4042 Welcome Valley Rd SE",
    "sg:city":"Roanoke",
    "sg:classifiers":[
        {
            "category":"Building & Trades",
            "subcategory":"Landscaping Services",
            "type":"Services"
        }
    ],
    "sg:phone":"+1 540 725 8720",
    "sg:postcode":"24014",
    "sg:province":"VA",
    "wof:name":"Lucas Landscaping",
    "wof:placetype":"venue"
},
  "geometry": {"coordinates":[-79.94585600000001,37.22269],"type":"Point"}
}