{
  "type": "Feature",
  "properties": {
    "addr:full":"7953 Twist Ln Springfield VA 22153",
    "addr:housenumber":"7953",
    "addr:postcode":"22153",
    "addr:street":"Twist Ln",
    "iso:country":"US",
    "sg:address":"7953 Twist Ln",
    "sg:city":"Springfield",
    "sg:classifiers":[
        {
            "category":"Wholesale",
            "subcategory":"Machinery & Supplies",
            "type":"Manufacturing & Wholesale Goods"
        },
        {
            "category":"Home & Garden",
            "subcategory":"Garden Supply",
            "type":"Retail Goods"
        }
    ],
    "sg:phone":"+1 703 440 0900",
    "sg:postcode":"22153",
    "sg:province":"VA",
    "sg:tags":[
        "sprinkler"
    ],
    "wof:name":"John Deere Landscapes Inc",
    "wof:placetype":"venue"
},
  "geometry": {"coordinates":[-77.20859799999999,38.741834],"type":"Point"}
}