{
  "type": "Feature",
  "properties": {
    "iso:country":"US",
    "sg:address":"14301 Sullyfield Cir",
    "sg:city":"Chantilly",
    "sg:classifiers":[
        {
            "category":"Retail",
            "subcategory":"Repair Shop",
            "type":"Services"
        }
    ],
    "sg:phone":"+1 703 818 8007",
    "sg:postcode":"20151",
    "sg:province":"VA",
    "sg:tags":[
        "watch"
    ],
    "wof:name":"Anytime Watch Repair Inc",
    "wof:placetype":"venue"
},
  "geometry": {"coordinates":[-77.439053,38.893656],"type":"Point"}
}