{
  "type": "Feature",
  "properties": {
    "iso:country":"US",
    "sg:address":"20920 Furr Rd",
    "sg:city":"Round Hill",
    "sg:classifiers":[
        {
            "category":"Freight",
            "type":"Transportation"
        },
        {
            "category":"Building & Trades",
            "subcategory":"Construction",
            "type":"Services"
        }
    ],
    "sg:phone":"+1 540 554 8563",
    "sg:postcode":"20141",
    "sg:province":"VA",
    "sg:tags":[
        "excavating",
        "dump",
        "excavation",
        "hauling",
        "contractor",
        "truck"
    ],
    "wof:name":"Monroe Trucking & Excavation",
    "wof:placetype":"venue"
},
  "geometry": {"coordinates":[-77.79456500000001,39.041226],"type":"Point"}
}