{
  "type": "Feature",
  "properties": {
    "addr:full":"12680 Dulcinea Pl Woodbridge VA 22192",
    "addr:housenumber":"12680",
    "addr:postcode":"22192",
    "addr:street":"Dulcinea Pl",
    "iso:country":"US",
    "sg:address":"12680 Dulcinea Pl",
    "sg:city":"Woodbridge",
    "sg:classifiers":[
        {
            "category":"Food & Beverages",
            "subcategory":"Specialty",
            "type":"Retail Goods"
        }
    ],
    "sg:phone":"+1 703 491 2405",
    "sg:postcode":"22192",
    "sg:province":"VA",
    "wof:name":"Keja International Market",
    "wof:placetype":"venue"
},
  "geometry": {"coordinates":[-77.294319,38.677966],"type":"Point"}
}