{
  "type": "Feature",
  "properties": {
    "iso:country":"US",
    "sg:address":"9400 Charter Xing",
    "sg:city":"Mechanicsville",
    "sg:classifiers":[
        {
            "category":"Insurance",
            "subcategory":"Insurance Agent",
            "type":"Services"
        }
    ],
    "sg:phone":"+1 804 550 7900",
    "sg:postcode":"23116",
    "sg:province":"VA",
    "wof:name":"Woodman of World Lf Insur Soc",
    "wof:placetype":"venue"
},
  "geometry": {"coordinates":[-77.43136199999999,37.687546],"type":"Point"}
}