{
  "type": "Feature",
  "properties": {
    "addr:full":"300 S Main St Kilmarnock VA 22482",
    "addr:housenumber":"300",
    "addr:postcode":"22482",
    "addr:street":"S Main St",
    "iso:country":"US",
    "sg:address":"300 S Main St",
    "sg:city":"Kilmarnock",
    "sg:classifiers":[
        {
            "category":"Professional",
            "type":"Services"
        }
    ],
    "sg:phone":"+1 804 435 0880",
    "sg:postcode":"22482",
    "sg:province":"VA",
    "wof:name":"Dr Ed Blake",
    "wof:placetype":"venue"
},
  "geometry": {"coordinates":[-76.378991,37.706752],"type":"Point"}
}