{
  "type": "Feature",
  "properties": {
    "addr:full":"8005 Creighton Pkwy Mechanicsville VA 23111",
    "addr:housenumber":"8005",
    "addr:postcode":"23111",
    "addr:street":"Creighton Pkwy",
    "iso:country":"US",
    "sg:address":"8005 Creighton Pkwy",
    "sg:city":"Mechanicsville",
    "sg:classifiers":[
        {
            "category":"Wholesale",
            "subcategory":"Toys & Hobbies",
            "type":"Manufacturing & Wholesale Goods"
        }
    ],
    "sg:phone":"+1 804 569 9335",
    "sg:postcode":"23111",
    "sg:province":"VA",
    "sg:tags":[
        "wholesaler"
    ],
    "wof:name":"Engineering Products",
    "wof:placetype":"venue"
},
  "geometry": {"coordinates":[-77.31848599999999,37.616179],"type":"Point"}
}