{
  "type": "Feature",
  "properties": {
    "iso:country":"US",
    "sg:address":"8953 Falling Creek Ct",
    "sg:city":"Annandale",
    "sg:classifiers":[
        {
            "category":"Recreation",
            "type":"Entertainment"
        }
    ],
    "sg:phone":"+1 703 978 3269",
    "sg:postcode":"22003",
    "sg:province":"VA",
    "sg:tags":[
        "club",
        "membership"
    ],
    "wof:name":"Jaguar Club",
    "wof:placetype":"venue"
},
  "geometry": {"coordinates":[-77.254586,38.813654],"type":"Point"}
}