{
  "type": "Feature",
  "properties": {
    "addr:full":"12780 Bradwell Rd Herndon VA 20171",
    "addr:housenumber":"12780",
    "addr:postcode":"20171",
    "addr:street":"Bradwell Rd",
    "iso:country":"US",
    "sg:address":"12780 Bradwell Rd",
    "sg:city":"Herndon",
    "sg:classifiers":[
        {
            "category":"Education",
            "subcategory":"Dance Studio",
            "type":"Public Place"
        }
    ],
    "sg:phone":"+1 703 860 5289",
    "sg:postcode":"20171",
    "sg:province":"VA",
    "wof:name":"Adrenaline Dance Inc",
    "wof:placetype":"venue"
},
  "geometry": {"coordinates":[-77.385024,38.925962],"type":"Point"}
}