{
  "type": "Feature",
  "properties": {
    "addr:full":"5206 Rolling Rd Burke VA 22015",
    "addr:housenumber":"5206",
    "addr:postcode":"22015",
    "addr:street":"Rolling Rd",
    "iso:country":"US",
    "sg:address":"5206 Rolling Rd",
    "sg:city":"Burke",
    "sg:classifiers":[
        {
            "category":"Health Services",
            "subcategory":"Clinic",
            "type":"Services"
        }
    ],
    "sg:phone":"+1 703 978 8330",
    "sg:postcode":"22015",
    "sg:province":"VA",
    "sg:tags":[
        "specialty",
        "outpatient"
    ],
    "wof:name":"Burke Fmly Counseling & Cnsltn",
    "wof:placetype":"venue"
},
  "geometry": {"coordinates":[-77.256547,38.810408],"type":"Point"}
}