{
  "type": "Feature",
  "properties": {
    "iso:country":"US",
    "sg:address":"7501 Brook Rd",
    "sg:city":"Richmond",
    "sg:classifiers":[
        {
            "category":"Food & Beverages",
            "subcategory":"Groceries & Convenience Stores",
            "type":"Retail Goods"
        }
    ],
    "sg:phone":"+1 804 266 2616",
    "sg:postcode":"23227",
    "sg:province":"VA",
    "wof:name":"7-Eleven",
    "wof:placetype":"venue"
},
  "geometry": {"coordinates":[-77.458259,37.627002],"type":"Point"}
}