{
  "type": "Feature",
  "properties": {
    "iso:country":"US",
    "sg:address":"2008 Kenley Ct",
    "sg:city":"Alexandria",
    "sg:classifiers":[
        {
            "category":"Wholesale",
            "subcategory":"Durable Goods & Equipment",
            "type":"Manufacturing & Wholesale Goods"
        }
    ],
    "sg:phone":"+1 703 780 4460",
    "sg:postcode":"22308",
    "sg:province":"VA",
    "sg:tags":[
        "representative",
        "manufacturer"
    ],
    "wof:name":"Clean Answer",
    "wof:placetype":"venue"
},
  "geometry": {"coordinates":[-77.065702,38.731213],"type":"Point"}
}