{
  "type": "Feature",
  "properties": {
    "addr:full":"400 Beal Ave Luray VA 22835",
    "addr:housenumber":"400",
    "addr:postcode":"22835",
    "addr:street":"Beal Ave",
    "iso:country":"US",
    "sg:address":"400 Beal Ave",
    "sg:city":"Luray",
    "sg:classifiers":[
        {
            "category":"Insurance",
            "subcategory":"Insurance Agent",
            "type":"Services"
        }
    ],
    "sg:phone":"+1 540 743 1458",
    "sg:postcode":"22835",
    "sg:province":"VA",
    "wof:name":"Dotson Insurance Agency",
    "wof:placetype":"venue"
},
  "geometry": {"coordinates":[-78.515119,38.671321],"type":"Point"}
}