{
  "type": "Feature",
  "properties": {
    "addr:full":"2804 Prince William Pkwy Woodbridge VA 22192",
    "addr:housenumber":"2804",
    "addr:postcode":"22192",
    "addr:street":"Prince William Pkwy",
    "iso:country":"US",
    "sg:address":"2804 Prince William Pkwy",
    "sg:city":"Woodbridge",
    "sg:classifiers":[
        {
            "category":"Restaurant",
            "type":"Food & Drink"
        }
    ],
    "sg:phone":"+1 703 490 0668",
    "sg:postcode":"22192",
    "sg:province":"VA",
    "wof:name":"Panera Bread",
    "wof:placetype":"venue"
},
  "geometry": {"coordinates":[-77.28509200000001,38.656008],"type":"Point"}
}