{
  "type": "Feature",
  "properties": {
    "addr:full":"3094 Breckinridge Mill Rd Fincastle VA 24090",
    "addr:housenumber":"3094",
    "addr:postcode":"24090",
    "addr:street":"Breckinridge Mill Rd",
    "iso:country":"US",
    "sg:address":"3094 Breckinridge Mill Rd",
    "sg:city":"Fincastle",
    "sg:classifiers":[
        {
            "category":"Farming",
            "subcategory":"Farm",
            "type":"Manufacturing & Wholesale Goods"
        }
    ],
    "sg:phone":"+1 540 473 2357",
    "sg:postcode":"24090",
    "sg:province":"VA",
    "sg:tags":[
        "crop",
        "general"
    ],
    "wof:name":"Triple M Farm",
    "wof:placetype":"venue"
},
  "geometry": {"coordinates":[-79.94182000000001,37.500749],"type":"Point"}
}