{
  "type": "Feature",
  "properties": {
    "iso:country":"US",
    "sg:address":"6058 Woolen Mill Ct",
    "sg:city":"Haymarket",
    "sg:classifiers":[
        {
            "category":"Building & Trades",
            "subcategory":"Construction",
            "type":"Services"
        }
    ],
    "sg:phone":"+1 703 753 3413",
    "sg:postcode":"20169",
    "sg:province":"VA",
    "sg:tags":[
        "contractor"
    ],
    "sg:website":"www.beazer.com",
    "wof:name":"Beazer Homes",
    "wof:placetype":"venue"
},
  "geometry": {"coordinates":[-77.62575099999999,38.826762],"type":"Point"}
}