{
  "type": "Feature",
  "properties": {
    "addr:full":"2 Millard Ct Sterling VA 20165",
    "addr:housenumber":"2",
    "addr:postcode":"20165",
    "addr:street":"Millard Ct",
    "iso:country":"US",
    "sg:address":"2 Millard Ct",
    "sg:city":"Sterling",
    "sg:classifiers":[
        {
            "category":"Social Services",
            "subcategory":"Child Care",
            "type":"Services"
        }
    ],
    "sg:phone":"+1 703 430 2592",
    "sg:postcode":"20165",
    "sg:province":"VA",
    "wof:name":"Massik Inc",
    "wof:placetype":"venue"
},
  "geometry": {"coordinates":[-77.412593,39.057808],"type":"Point"}
}