{
  "type": "Feature",
  "properties": {
    "addr:full":"7884 Red House Rd Gladys VA 24554",
    "addr:housenumber":"7884",
    "addr:postcode":"24554",
    "addr:street":"Red House Rd",
    "iso:country":"US",
    "sg:address":"7884 Red House Rd",
    "sg:city":"Gladys",
    "sg:classifiers":[
        {
            "category":"Farming",
            "subcategory":"Livestock Farm",
            "type":"Manufacturing & Wholesale Goods"
        }
    ],
    "sg:phone":"+1 434 283 1487",
    "sg:postcode":"24554",
    "sg:province":"VA",
    "sg:tags":[
        "dairy",
        "beef",
        "feedlot",
        "cattle"
    ],
    "wof:name":"Gravel Ridge Farm",
    "wof:placetype":"venue"
},
  "geometry": {"coordinates":[-79.001229,37.20526],"type":"Point"}
}