{
  "type": "Feature",
  "properties": {
    "addr:full":"5716 Courthouse Rd Prince George VA 23875",
    "addr:housenumber":"5716",
    "addr:postcode":"23875",
    "addr:street":"Courthouse Rd",
    "iso:country":"US",
    "sg:address":"5716 Courthouse Rd",
    "sg:city":"Prince George",
    "sg:classifiers":[
        {
            "category":"Food & Beverages",
            "subcategory":"Specialty",
            "type":"Retail Goods"
        }
    ],
    "sg:phone":"+1 804 862 4372",
    "sg:postcode":"23875",
    "sg:province":"VA",
    "wof:name":"Herb Basket",
    "wof:placetype":"venue"
},
  "geometry": {"coordinates":[-77.301063,37.222872],"type":"Point"}
}