{
  "type": "Feature",
  "properties": {
    "addr:full":"318 Maple Rd Yorktown VA 23690",
    "addr:housenumber":"318",
    "addr:postcode":"23690",
    "addr:street":"Maple Rd",
    "iso:country":"US",
    "sg:address":"318 Maple Rd",
    "sg:city":"Yorktown",
    "sg:classifiers":[
        {
            "category":"Retail",
            "subcategory":"Auto Repair",
            "type":"Services"
        }
    ],
    "sg:phone":"+1 757 888 0837",
    "sg:postcode":"23690",
    "sg:province":"VA",
    "sg:tags":[
        "automotive"
    ],
    "wof:name":"Johnsons Towing",
    "wof:placetype":"venue"
},
  "geometry": {"coordinates":[-76.55219200000001,37.227259],"type":"Point"}
}