{
  "type": "Feature",
  "properties": {
    "addr:full":"3340 Woodburn Rd Annandale VA 22003",
    "addr:housenumber":"3340",
    "addr:postcode":"22003",
    "addr:street":"Woodburn Rd",
    "iso:country":"US",
    "sg:address":"3340 Woodburn Rd",
    "sg:city":"Annandale",
    "sg:classifiers":[
        {
            "category":"Health Services",
            "subcategory":"Hospital",
            "type":"Services"
        }
    ],
    "sg:phone":"+1 703 207 7737",
    "sg:postcode":"22003",
    "sg:province":"VA",
    "sg:tags":[
        "mental"
    ],
    "wof:name":"Fairfax-Falls Church Community",
    "wof:placetype":"venue"
},
  "geometry": {"coordinates":[-77.22613200000001,38.854544],"type":"Point"}
}