{
  "type": "Feature",
  "properties": {
    "addr:full":"9 N College Ave Salem VA 24153",
    "addr:housenumber":"9",
    "addr:postcode":"24153",
    "addr:street":"N College Ave",
    "iso:country":"US",
    "sg:address":"9 N College Ave",
    "sg:city":"Salem",
    "sg:classifiers":[
        {
            "category":"Health Services",
            "subcategory":"Doctor",
            "type":"Services"
        }
    ],
    "sg:phone":"+1 540 389 3555",
    "sg:postcode":"24153",
    "sg:province":"VA",
    "sg:tags":[
        "medical"
    ],
    "wof:name":"TLC Books",
    "wof:placetype":"venue"
},
  "geometry": {"coordinates":[-80.054987,37.294119],"type":"Point"}
}