{
  "type": "Feature",
  "properties": {
    "iso:country":"US",
    "sg:address":"6509 N Stevens Hollow Dr",
    "sg:city":"Chesterfield",
    "sg:classifiers":[
        {
            "category":"Building & Trades",
            "subcategory":"Cleaning & Sanitation",
            "type":"Services"
        }
    ],
    "sg:phone":"+1 804 276 0055",
    "sg:postcode":"23832",
    "sg:province":"VA",
    "sg:tags":[
        "janitor"
    ],
    "wof:name":"L B Cleaning Svc",
    "wof:placetype":"venue"
},
  "geometry": {"coordinates":[-77.51414800000001,37.464244],"type":"Point"}
}