{
  "type": "Feature",
  "properties": {
    "addr:full":"1185 N Main St Marion VA 24354",
    "addr:housenumber":"1185",
    "addr:postcode":"24354",
    "addr:street":"N Main St",
    "iso:country":"US",
    "sg:address":"1185 N Main St",
    "sg:city":"Marion",
    "sg:classifiers":[
        {
            "category":"Food & Beverages",
            "subcategory":"Groceries & Convenience Stores",
            "type":"Retail Goods"
        }
    ],
    "sg:phone":"+1 276 783 5461",
    "sg:postcode":"24354",
    "sg:province":"VA",
    "sg:tags":[
        "grocer"
    ],
    "wof:name":"Ingles",
    "wof:placetype":"venue"
},
  "geometry": {"coordinates":[-81.49926000000001,36.844873],"type":"Point"}
}