{
  "type": "Feature",
  "properties": {
    "addr:full":"409 Church St Clifton Forge VA 24422",
    "addr:housenumber":"409",
    "addr:postcode":"24422",
    "addr:street":"Church St",
    "iso:country":"US",
    "sg:address":"409 Church St",
    "sg:city":"Clifton Forge",
    "sg:classifiers":[
        {
            "category":"Social Services",
            "type":"Services"
        }
    ],
    "sg:phone":"+1 540 863 1630",
    "sg:postcode":"24422",
    "sg:province":"VA",
    "sg:tags":[
        "organization",
        "welfare"
    ],
    "wof:name":"Alleghany House Day Program",
    "wof:placetype":"venue"
},
  "geometry": {"coordinates":[-79.82689499999999,37.817331],"type":"Point"}
}