{
  "type": "Feature",
  "properties": {
    "addr:full":"4655 Monticello Ave Williamsburg VA 23188",
    "addr:housenumber":"4655",
    "addr:postcode":"23188",
    "addr:street":"Monticello Ave",
    "iso:country":"US",
    "sg:address":"4655 Monticello Ave",
    "sg:city":"Williamsburg",
    "sg:classifiers":[
        {
            "category":"Shopping",
            "subcategory":"Luggage & Leather Goods",
            "type":"Retail Goods"
        }
    ],
    "sg:phone":"+1 757 565 7030",
    "sg:postcode":"23188",
    "sg:province":"VA",
    "wof:name":"Rountrees Luggage Co Inc H W",
    "wof:placetype":"venue"
},
  "geometry": {"coordinates":[-76.755978,37.27068],"type":"Point"}
}