{
  "type": "Feature",
  "properties": {
    "iso:country":"US",
    "sg:address":"709 Industrial Ave",
    "sg:city":"Danville",
    "sg:classifiers":[
        {
            "category":"Building & Trades",
            "subcategory":"Construction",
            "type":"Services"
        }
    ],
    "sg:phone":"+1 434 791 3223",
    "sg:postcode":"24541",
    "sg:province":"VA",
    "sg:tags":[
        "general",
        "contractor"
    ],
    "wof:name":"Harley Enterprise Gen Contr",
    "wof:placetype":"venue"
},
  "geometry": {"coordinates":[-79.389939,36.573619],"type":"Point"}
}