{
  "type": "Feature",
  "properties": {
    "addr:full":"16028 Macedonia Dr Woodbridge VA 22191",
    "addr:postcode":"16028;22191",
    "addr:street":"Macedonia Dr",
    "iso:country":"US",
    "sg:address":"16028 Macedonia Dr",
    "sg:city":"Woodbridge",
    "sg:classifiers":[
        {
            "category":"Shopping",
            "subcategory":"Beauty & Cosmetics",
            "type":"Retail Goods"
        }
    ],
    "sg:phone":"+1 703 670 7023",
    "sg:postcode":"22191",
    "sg:province":"VA",
    "sg:tags":[
        "merchandise"
    ],
    "wof:name":"Jean R Beall",
    "wof:placetype":"venue"
},
  "geometry": {"coordinates":[-77.28102800000001,38.602157],"type":"Point"}
}