{
  "type": "Feature",
  "properties": {
    "addr:full":"21 N Main St Halifax VA 24558",
    "addr:housenumber":"21",
    "addr:postcode":"24558",
    "addr:street":"N Main St",
    "iso:country":"US",
    "sg:address":"21 N Main St",
    "sg:city":"Halifax",
    "sg:classifiers":[
        {
            "category":"Shopping",
            "subcategory":"Jewelry",
            "type":"Retail Goods"
        }
    ],
    "sg:phone":"+1 434 476 6646",
    "sg:postcode":"24558",
    "sg:province":"VA",
    "sg:tags":[
        "jeweler"
    ],
    "wof:name":"Garland's Jewelry",
    "wof:placetype":"venue"
},
  "geometry": {"coordinates":[-78.927651,36.76755],"type":"Point"}
}