{
  "type": "Feature",
  "properties": {
    "iso:country":"US",
    "sg:address":"9542 Whiteceder Ct",
    "sg:city":"Vienna",
    "sg:classifiers":[
        {
            "category":"Professional",
            "type":"Services"
        }
    ],
    "sg:phone":"+1 703 255 6506",
    "sg:postcode":"22181",
    "sg:province":"VA",
    "sg:tags":[
        "establishment"
    ],
    "wof:name":"White Cedar Corp",
    "wof:placetype":"venue"
},
  "geometry": {"coordinates":[-77.276529,38.889064],"type":"Point"}
}