{
  "type": "Feature",
  "properties": {
    "addr:full":"144 Damaris Ln Cross Junction VA 22625",
    "addr:housenumber":"144",
    "addr:postcode":"22625",
    "addr:street":"Damaris Ln",
    "iso:country":"US",
    "sg:address":"144 Damaris Ln",
    "sg:city":"Cross Junction",
    "sg:classifiers":[
        {
            "category":"Real Estate",
            "subcategory":"Real Estate Operator",
            "type":"Services"
        }
    ],
    "sg:phone":"+1 540 888 4872",
    "sg:postcode":"22625",
    "sg:province":"VA",
    "sg:tags":[
        "building",
        "nonresidential"
    ],
    "wof:name":"Mountain View Properties LLC",
    "wof:placetype":"venue"
},
  "geometry": {"coordinates":[-78.316828,39.325202],"type":"Point"}
}