{
  "type": "Feature",
  "properties": {
    "addr:full":"2401 Columbia Pike Arlington VA 22204",
    "addr:housenumber":"2401",
    "addr:postcode":"22204",
    "addr:street":"Columbia Pike",
    "iso:country":"US",
    "sg:address":"2401 Columbia Pike",
    "sg:city":"Arlington",
    "sg:classifiers":[
        {
            "category":"Shopping",
            "subcategory":"Party Supplies",
            "type":"Retail Goods"
        },
        {
            "category":"Shopping",
            "subcategory":"Gifts & Souvenirs",
            "type":"Retail Goods"
        }
    ],
    "sg:phone":"+1 703 892 8115",
    "sg:postcode":"22204",
    "sg:province":"VA",
    "sg:tags":[
        "shop"
    ],
    "wof:name":"Party Favors & Gifts Shop",
    "wof:placetype":"venue"
},
  "geometry": {"coordinates":[-77.083298,38.863499],"type":"Point"}
}