{
  "type": "Feature",
  "properties": {
    "iso:country":"US",
    "sg:address":"1343 Moneta Rd",
    "sg:city":"Bedford",
    "sg:classifiers":[
        {
            "category":"Retail",
            "subcategory":"Veterinary Services",
            "type":"Services"
        }
    ],
    "sg:phone":"+1 540 586 4290",
    "sg:postcode":"24523",
    "sg:province":"VA",
    "sg:tags":[
        "hospital",
        "veterinarian",
        "animal"
    ],
    "wof:name":"Blue Ridge Animal Hospital",
    "wof:placetype":"venue"
},
  "geometry": {"coordinates":[-79.53785000000001,37.311884],"type":"Point"}
}