{
  "type": "Feature",
  "properties": {
    "addr:full":"1135 Dove St Richmond VA 23222",
    "addr:housenumber":"1135",
    "addr:postcode":"23222",
    "addr:street":"Dove St",
    "iso:country":"US",
    "sg:address":"1135 Dove St",
    "sg:city":"Richmond",
    "sg:classifiers":[
        {
            "category":"Real Estate",
            "subcategory":"Real Estate Operator",
            "type":"Services"
        }
    ],
    "sg:phone":"+1 804 329 7021",
    "sg:postcode":"23222",
    "sg:province":"VA",
    "sg:tags":[
        "building",
        "apartment"
    ],
    "wof:name":"Carrington Gardens",
    "wof:placetype":"venue"
},
  "geometry": {"coordinates":[-77.42524899999999,37.562861],"type":"Point"}
}