{
  "type": "Feature",
  "properties": {
    "addr:full":"Tysons Corner Ctr Falls Church VA 22041",
    "addr:postcode":"22041",
    "addr:street":"Ctr",
    "iso:country":"US",
    "sg:address":"Tysons Corner Ctr",
    "sg:city":"Falls Church",
    "sg:classifiers":[
        {
            "category":"Shopping",
            "subcategory":"Jewelry",
            "type":"Retail Goods"
        }
    ],
    "sg:phone":"+1 703 506 6712",
    "sg:postcode":"22041",
    "sg:province":"VA",
    "sg:tags":[
        "watch"
    ],
    "wof:name":"Lenkersdorfer Fine Jewelers",
    "wof:placetype":"venue"
},
  "geometry": {"coordinates":[-77.131699,38.844601],"type":"Point"}
}