{
  "type": "Feature",
  "properties": {
    "iso:country":"US",
    "sg:address":"100 N 9th St",
    "sg:city":"Richmond",
    "sg:classifiers":[
        {
            "category":"Government",
            "subcategory":"Office",
            "type":"Public Place"
        }
    ],
    "sg:phone":"+1 804 786 6636",
    "sg:postcode":"23219",
    "sg:province":"VA",
    "wof:name":"Judicial Inquiry & Review Comm",
    "wof:placetype":"venue"
},
  "geometry": {"coordinates":[-77.43466600000001,37.53993],"type":"Point"}
}