{
  "type": "Feature",
  "properties": {
    "addr:full":"13515 Minnieville Rd Woodbridge VA 22192",
    "addr:housenumber":"13515",
    "addr:postcode":"22192",
    "addr:street":"Minnieville Rd",
    "iso:country":"US",
    "sg:address":"13515 Minnieville Rd",
    "sg:city":"Woodbridge",
    "sg:classifiers":[
        {
            "category":"Restaurant",
            "type":"Food & Drink"
        }
    ],
    "sg:menulink":"http://www.allmenus.com/va/neabsco/165870-arbys/menu/",
    "sg:phone":"+1 703 897 0292",
    "sg:postcode":"22192",
    "sg:province":"VA",
    "sg:tags":[
        "burger",
        "american"
    ],
    "wof:name":"Arby's",
    "wof:placetype":"venue"
},
  "geometry": {"coordinates":[-77.308426,38.6545],"type":"Point"}
}