{
  "type": "Feature",
  "properties": {
    "iso:country":"US",
    "sg:address":"125 W Shirley Ave",
    "sg:city":"Warrenton",
    "sg:classifiers":[
        {
            "category":"Communications",
            "subcategory":"Newspaper",
            "type":"Services"
        }
    ],
    "sg:phone":"+1 540 349 8060",
    "sg:postcode":"20186",
    "sg:province":"VA",
    "sg:tags":[
        "print",
        "medium"
    ],
    "wof:name":"Discovery Publication Inc",
    "wof:placetype":"venue"
},
  "geometry": {"coordinates":[-77.802673,38.711282],"type":"Point"}
}