{
  "type": "Feature",
  "properties": {
    "iso:country":"US",
    "sg:address":"9704 Clark Pl",
    "sg:city":"Manassas",
    "sg:classifiers":[
        {
            "category":"Real Estate",
            "subcategory":"Real Estate Operator",
            "type":"Services"
        }
    ],
    "sg:phone":"+1 703 368 6734",
    "sg:postcode":"20110",
    "sg:province":"VA",
    "sg:tags":[
        "building",
        "apartment"
    ],
    "wof:name":"Colonial Village",
    "wof:placetype":"venue"
},
  "geometry": {"coordinates":[-77.466578,38.743108],"type":"Point"}
}