{
  "type": "Feature",
  "properties": {
    "addr:full":"313 Park Ave Falls Church VA 22046",
    "addr:housenumber":"313",
    "addr:postcode":"22046",
    "addr:street":"Park Ave",
    "iso:country":"US",
    "sg:address":"313 Park Ave",
    "sg:city":"Falls Church",
    "sg:classifiers":[
        {
            "category":"Professional",
            "type":"Services"
        }
    ],
    "sg:phone":"+1 703 536 5593",
    "sg:postcode":"22046",
    "sg:province":"VA",
    "sg:tags":[
        "establishment"
    ],
    "wof:name":"Mathews Professional Bldg",
    "wof:placetype":"venue"
},
  "geometry": {"coordinates":[-77.174533,38.88595],"type":"Point"}
}