{
  "type": "Feature",
  "properties": {
    "addr:full":"2000 N Beauregard St Ste 548 Alexandria VA 22311",
    "addr:housenumber":"2000",
    "addr:postcode":"22311",
    "addr:street":"N Beauregard St Ste 548",
    "iso:country":"US",
    "sg:address":"2000 N Beauregard St Ste 548",
    "sg:city":"Alexandria",
    "sg:classifiers":[
        {
            "category":"Banks & Credit Unions",
            "subcategory":"Investment Brokerage",
            "type":"Services"
        },
        {
            "category":"Banks & Credit Unions",
            "subcategory":"Financial Services",
            "type":"Services"
        }
    ],
    "sg:phone":"+1 703 399 7480",
    "sg:postcode":"22311",
    "sg:province":"VA",
    "sg:tags":[
        "investing",
        "advising"
    ],
    "sg:website":"www.ameripriseadvisors.com",
    "wof:name":"Ameriprise Financial Advisors",
    "wof:placetype":"venue"
},
  "geometry": {"coordinates":[-77.119174,38.834342],"type":"Point"}
}