{
  "type": "Feature",
  "properties": {
    "iso:country":"US",
    "sg:address":"512 Central Dr",
    "sg:city":"Virginia Beach",
    "sg:classifiers":[
        {
            "category":"Professional",
            "subcategory":"Employment Agencies",
            "type":"Services"
        }
    ],
    "sg:phone":"+1 757 463 7309",
    "sg:postcode":"23454",
    "sg:province":"VA",
    "sg:tags":[
        "staff"
    ],
    "wof:name":"Ces",
    "wof:placetype":"venue"
},
  "geometry": {"coordinates":[-76.05389599999999,36.824184],"type":"Point"}
}