{
  "type": "Feature",
  "properties": {
    "addr:full":"1767 King St Alexandria VA 22314",
    "addr:housenumber":"1767",
    "addr:postcode":"22314",
    "addr:street":"King St",
    "iso:country":"US",
    "sg:address":"1767 King St",
    "sg:city":"Alexandria",
    "sg:classifiers":[
        {
            "category":"Restaurant",
            "type":"Food & Drink"
        }
    ],
    "sg:menulink":"http://www.allmenus.com/va/alexandria/267445-seagars-restaurant/menu/",
    "sg:phone":"+1 703 647 2000",
    "sg:postcode":"22314",
    "sg:province":"VA",
    "sg:tags":[
        "american"
    ],
    "wof:name":"Seagar's Restaurant",
    "wof:placetype":"venue"
},
  "geometry": {"coordinates":[-77.05957600000001,38.806829],"type":"Point"}
}