{
  "type": "Feature",
  "properties": {
    "addr:full":"3326 St James Pl Falls Church VA 22042",
    "addr:housenumber":"3326",
    "addr:postcode":"22042",
    "addr:street":"St James Pl",
    "iso:country":"US",
    "sg:address":"3326 St James Pl",
    "sg:city":"Falls Church",
    "sg:classifiers":[
        {
            "category":"Professional",
            "subcategory":"Management & Consulting",
            "type":"Services"
        }
    ],
    "sg:phone":"+1 703 204 9140",
    "sg:postcode":"22042",
    "sg:province":"VA",
    "wof:name":"D S K Solutions Inc",
    "wof:placetype":"venue"
},
  "geometry": {"coordinates":[-77.196202,38.855428],"type":"Point"}
}