{
  "type": "Feature",
  "properties": {
    "addr:full":"26 W Beverley St Staunton VA 24401",
    "addr:housenumber":"26",
    "addr:postcode":"24401",
    "addr:street":"W Beverley St",
    "iso:country":"US",
    "sg:address":"26 W Beverley St",
    "sg:city":"Staunton",
    "sg:classifiers":[
        {
            "category":"Autos & Motor Vehicles",
            "subcategory":"Fuel & Gas Station",
            "type":"Retail Goods"
        }
    ],
    "sg:phone":"+1 540 885 0891",
    "sg:postcode":"24401",
    "sg:province":"VA",
    "sg:tags":[
        "hardware",
        "antique",
        "gasoline"
    ],
    "wof:name":"Independent Gas",
    "wof:placetype":"venue"
},
  "geometry": {"coordinates":[-79.071758,38.149485],"type":"Point"}
}