{
  "type": "Feature",
  "properties": {
    "iso:country":"US",
    "sg:address":"1418 Mayflower Dr",
    "sg:city":"Mc Lean",
    "sg:classifiers":[
        {
            "category":"Professional",
            "type":"Services"
        }
    ],
    "sg:phone":"+1 703 790 4667",
    "sg:postcode":"22101",
    "sg:province":"VA",
    "wof:name":"Stellagraphica",
    "wof:placetype":"venue"
},
  "geometry": {"coordinates":[-77.19153,38.933883],"type":"Point"}
}