{
  "type": "Feature",
  "properties": {
    "iso:country":"US",
    "sg:address":"311 Alleghany Ave",
    "sg:city":"Lynchburg",
    "sg:classifiers":[
        {
            "category":"Retail",
            "subcategory":"Auto Repair",
            "type":"Services"
        }
    ],
    "sg:phone":"+1 434 846 0555",
    "sg:postcode":"24501",
    "sg:province":"VA",
    "sg:tags":[
        "general"
    ],
    "wof:name":"Jones Brothers Garage",
    "wof:placetype":"venue"
},
  "geometry": {"coordinates":[-79.173404,37.403455],"type":"Point"}
}