{
  "type": "Feature",
  "properties": {
    "addr:full":"2703 Horner Rd Woodbridge VA 22192",
    "addr:housenumber":"2703",
    "addr:postcode":"22192",
    "addr:street":"Horner Rd",
    "iso:country":"US",
    "sg:address":"2703 Horner Rd",
    "sg:city":"Woodbridge",
    "sg:classifiers":[
        {
            "category":"Utilities",
            "subcategory":"Fuel Oil & Lpg",
            "type":"Services"
        }
    ],
    "sg:phone":"+1 703 643 1819",
    "sg:postcode":"22192",
    "sg:province":"VA",
    "sg:tags":[
        "liquefied",
        "gas",
        "petroleum"
    ],
    "wof:name":"Ferrellgas L P",
    "wof:placetype":"venue"
},
  "geometry": {"coordinates":[-77.29431,38.657944],"type":"Point"}
}