{
  "type": "Feature",
  "properties": {
    "addr:full":"35 E Linden St Alexandria VA 22301",
    "addr:housenumber":"35",
    "addr:postcode":"22301",
    "addr:street":"E Linden St",
    "iso:country":"US",
    "sg:address":"35 E Linden St",
    "sg:city":"Alexandria",
    "sg:classifiers":[
        {
            "category":"Building & Trades",
            "subcategory":"Construction",
            "type":"Services"
        }
    ],
    "sg:phone":"+1 703 519 3623",
    "sg:postcode":"22301",
    "sg:province":"VA",
    "sg:tags":[
        "residential"
    ],
    "wof:name":"Macphail Construction Corp",
    "wof:placetype":"venue"
},
  "geometry": {"coordinates":[-77.059094,38.810757],"type":"Point"}
}