{
  "type": "Feature",
  "properties": {
    "addr:full":"4554 Virginia Beach Blvd Virginia Beach VA 23462",
    "addr:housenumber":"4554",
    "addr:postcode":"23462",
    "addr:street":"Virginia Beach Blvd",
    "iso:country":"US",
    "sg:address":"4554 Virginia Beach Blvd",
    "sg:city":"Virginia Beach",
    "sg:classifiers":[
        {
            "category":"Home & Garden",
            "subcategory":"Furniture",
            "type":"Retail Goods"
        }
    ],
    "sg:phone":"+1 757 490 4509",
    "sg:postcode":"23462",
    "sg:province":"VA",
    "sg:tags":[
        "builder",
        "custom"
    ],
    "wof:name":"Joys Tar Trade Corp",
    "wof:placetype":"venue"
},
  "geometry": {"coordinates":[-76.13240999999999,36.84368],"type":"Point"}
}