{
  "type": "Feature",
  "properties": {
    "iso:country":"US",
    "sg:address":"2317 Westwood Ave",
    "sg:city":"Richmond",
    "sg:classifiers":[
        {
            "category":"Local Transit",
            "type":"Transportation"
        }
    ],
    "sg:phone":"+1 804 355 7556",
    "sg:postcode":"23230",
    "sg:province":"VA",
    "sg:tags":[
        "passenger"
    ],
    "wof:name":"M&G Transport",
    "wof:placetype":"venue"
},
  "geometry": {"coordinates":[-77.477844,37.576216],"type":"Point"}
}