{
  "type": "Feature",
  "properties": {
    "iso:country":"US",
    "sg:address":"6417 Loisdale Rd",
    "sg:city":"Springfield",
    "sg:classifiers":[
        {
            "category":"Real Estate",
            "subcategory":"Developer",
            "type":"Services"
        },
        {
            "category":"Real Estate",
            "subcategory":"Real Estate Agent",
            "type":"Services"
        }
    ],
    "sg:phone":"+1 703 313 9045",
    "sg:postcode":"22150",
    "sg:province":"VA",
    "sg:tags":[
        "management"
    ],
    "wof:name":"Modcon Inc",
    "wof:placetype":"venue"
},
  "geometry": {"coordinates":[-77.177824,38.77451],"type":"Point"}
}