{
  "type": "Feature",
  "properties": {
    "addr:full":"3805 Old Farm Rd Portsmouth VA 23703",
    "addr:housenumber":"3805",
    "addr:postcode":"23703",
    "addr:street":"Old Farm Rd",
    "iso:country":"US",
    "sg:address":"3805 Old Farm Rd",
    "sg:city":"Portsmouth",
    "sg:classifiers":[
        {
            "category":"Health Services",
            "subcategory":"Hospital",
            "type":"Services"
        }
    ],
    "sg:phone":"+1 757 686 8990",
    "sg:postcode":"23703",
    "sg:province":"VA",
    "sg:tags":[
        "mental"
    ],
    "wof:name":"Unique Friends",
    "wof:placetype":"venue"
},
  "geometry": {"coordinates":[-76.405158,36.870101],"type":"Point"}
}