{
  "type": "Feature",
  "properties": {
    "iso:country":"US",
    "sg:address":"510 Spring St",
    "sg:city":"Herndon",
    "sg:classifiers":[
        {
            "category":"Building & Trades",
            "subcategory":"Equipment Rental",
            "type":"Services"
        }
    ],
    "sg:phone":"+1 703 435 0543",
    "sg:postcode":"20170",
    "sg:province":"VA",
    "wof:name":"Wiltel Communications",
    "wof:placetype":"venue"
},
  "geometry": {"coordinates":[-77.382333,38.963357],"type":"Point"}
}