{
  "type": "Feature",
  "properties": {
    "addr:full":"1609 White Cedar Ln Richmond VA 23235",
    "addr:housenumber":"1609",
    "addr:postcode":"23235",
    "addr:street":"White Cedar Ln",
    "iso:country":"US",
    "sg:address":"1609 White Cedar Ln",
    "sg:city":"Richmond",
    "sg:classifiers":[
        {
            "category":"Shopping",
            "subcategory":"Gifts & Souvenirs",
            "type":"Retail Goods"
        }
    ],
    "sg:phone":"+1 804 276 7871",
    "sg:postcode":"23235",
    "sg:province":"VA",
    "sg:tags":[
        "shop"
    ],
    "wof:name":"Gifts From Lynn",
    "wof:placetype":"venue"
},
  "geometry": {"coordinates":[-77.55479,37.473376],"type":"Point"}
}