{
  "type": "Feature",
  "properties": {
    "addr:full":"803 Douglas St Fredericksburg VA 22407",
    "addr:housenumber":"803",
    "addr:postcode":"22407",
    "addr:street":"Douglas St",
    "iso:country":"US",
    "sg:address":"803 Douglas St",
    "sg:city":"Fredericksburg",
    "sg:classifiers":[
        {
            "category":"Building & Trades",
            "subcategory":"Cleaning & Sanitation",
            "type":"Services"
        }
    ],
    "sg:phone":"+1 540 786 7300",
    "sg:postcode":"22407",
    "sg:province":"VA",
    "sg:tags":[
        "house"
    ],
    "wof:name":"Alex's Cleaning Svc",
    "wof:placetype":"venue"
},
  "geometry": {"coordinates":[-77.527744,38.28612],"type":"Point"}
}