{
  "type": "Feature",
  "properties": {
    "iso:country":"US",
    "sg:address":"420 Hudgins Rd",
    "sg:city":"Fredericksburg",
    "sg:classifiers":[
        {
            "category":"Professional",
            "subcategory":"Management & Consulting",
            "type":"Services"
        }
    ],
    "sg:phone":"+1 540 891 2500",
    "sg:postcode":"22408",
    "sg:province":"VA",
    "sg:tags":[
        "consultant"
    ],
    "wof:name":"C & D Consultants",
    "wof:placetype":"venue"
},
  "geometry": {"coordinates":[-77.496387,38.273599],"type":"Point"}
}