{
  "type": "Feature",
  "properties": {
    "addr:full":"2213 W Great Neck Rd Virginia Beach VA 23451",
    "addr:housenumber":"2213",
    "addr:postcode":"23451",
    "addr:street":"W Great Neck Rd",
    "iso:country":"US",
    "sg:address":"2213 W Great Neck Rd",
    "sg:city":"Virginia Beach",
    "sg:classifiers":[
        {
            "category":"Professional",
            "subcategory":"Management & Consulting",
            "type":"Services"
        }
    ],
    "sg:phone":"+1 757 496 4060",
    "sg:postcode":"23451",
    "sg:province":"VA",
    "sg:tags":[
        "party",
        "planning"
    ],
    "wof:name":"Rains Associates LLC",
    "wof:placetype":"venue"
},
  "geometry": {"coordinates":[-76.070965,36.909709],"type":"Point"}
}