{
  "type": "Feature",
  "properties": {
    "iso:country":"US",
    "sg:address":"7010 Little River Tpke",
    "sg:city":"Annandale",
    "sg:classifiers":[
        {
            "category":"Professional",
            "subcategory":"Computer Services",
            "type":"Services"
        }
    ],
    "sg:phone":"+1 703 916 0777",
    "sg:postcode":"22003",
    "sg:province":"VA",
    "sg:tags":[
        "design",
        "system",
        "network"
    ],
    "wof:name":"Keyware Solutions",
    "wof:placetype":"venue"
},
  "geometry": {"coordinates":[-77.18694499999999,38.82897],"type":"Point"}
}