{
  "type": "Feature",
  "properties": {
    "addr:full":"7252 Lipscomb Rd Woodford VA 22580",
    "addr:housenumber":"7252",
    "addr:postcode":"22580",
    "addr:street":"Lipscomb Rd",
    "iso:country":"US",
    "sg:address":"7252 Lipscomb Rd",
    "sg:city":"Woodford",
    "sg:classifiers":[
        {
            "category":"Professional",
            "type":"Services"
        }
    ],
    "sg:phone":"+1 804 448 4859",
    "sg:postcode":"22580",
    "sg:province":"VA",
    "wof:name":"Lipman Services",
    "wof:placetype":"venue"
},
  "geometry": {"coordinates":[-77.520724,38.050098],"type":"Point"}
}