{
  "type": "Feature",
  "properties": {
    "addr:full":"2986 Kings Hwy Colonial Beach VA 22443",
    "addr:housenumber":"2986",
    "addr:postcode":"beach;22443",
    "addr:street":"Kings Hwy Colonial",
    "iso:country":"US",
    "sg:address":"2986 Kings Hwy",
    "sg:city":"Colonial Beach",
    "sg:classifiers":[
        {
            "category":"Utilities",
            "subcategory":"Cable",
            "type":"Services"
        },
        {
            "category":"Travel",
            "subcategory":"Travel Agent",
            "type":"Entertainment"
        }
    ],
    "sg:phone":"+1 804 224 9711",
    "sg:postcode":"22443",
    "sg:province":"VA",
    "sg:tags":[
        "real",
        "satellite",
        "est",
        "for",
        "industry",
        "agency",
        "television"
    ],
    "wof:name":"Mid Atlantic Video Satellite",
    "wof:placetype":"venue"
},
  "geometry": {"coordinates":[-76.996331,38.181309],"type":"Point"}
}