{
  "type": "Feature",
  "properties": {
    "addr:full":"4270 Free Union Rd Free Union VA 22940",
    "addr:housenumber":"4270",
    "addr:postcode":"22940",
    "addr:street":"Free Union Rd",
    "iso:country":"US",
    "sg:address":"4270 Free Union Rd",
    "sg:city":"Free Union",
    "sg:classifiers":[
        {
            "category":"Government",
            "subcategory":"Post Office",
            "type":"Public Place"
        }
    ],
    "sg:phone":"+1 434 973 6710",
    "sg:postcode":"22940",
    "sg:province":"VA",
    "wof:name":"US Post Office",
    "wof:placetype":"venue"
},
  "geometry": {"coordinates":[-78.561914,38.153193],"type":"Point"}
}