{
  "type": "Feature",
  "properties": {
    "iso:country":"US",
    "sg:address":"704 W Brookland Park Blvd",
    "sg:city":"Richmond",
    "sg:classifiers":[
        {
            "category":"Real Estate",
            "subcategory":"Real Estate Agent",
            "type":"Services"
        }
    ],
    "sg:phone":"+1 804 321 6580",
    "sg:postcode":"23222",
    "sg:province":"VA",
    "wof:name":"Betty Jones Realty",
    "wof:placetype":"venue"
},
  "geometry": {"coordinates":[-77.43899999999999,37.571862],"type":"Point"}
}