{
  "type": "Feature",
  "properties": {
    "addr:full":"511 Monroe St Danville VA 24541",
    "addr:housenumber":"511",
    "addr:postcode":"24541",
    "addr:street":"Monroe St",
    "iso:country":"US",
    "sg:address":"511 Monroe St",
    "sg:city":"Danville",
    "sg:classifiers":[
        {
            "category":"Retail",
            "subcategory":"Auto Repair",
            "type":"Services"
        }
    ],
    "sg:phone":"+1 434 799 4099",
    "sg:postcode":"24541",
    "sg:province":"VA",
    "sg:tags":[
        "repairing",
        "automobile"
    ],
    "wof:name":"Harrington's Auto Repair & Svc",
    "wof:placetype":"venue"
},
  "geometry": {"coordinates":[-79.395837,36.590835],"type":"Point"}
}