{
  "type": "Feature",
  "properties": {
    "addr:full":"21 Weems St Colonial Beach VA 22443",
    "addr:housenumber":"21",
    "addr:postcode":"22443",
    "addr:street":"Weems St",
    "iso:country":"US",
    "sg:address":"21 Weems St",
    "sg:city":"Colonial Beach",
    "sg:classifiers":[
        {
            "category":"Travel",
            "subcategory":"Hotels & Motels",
            "type":"Entertainment"
        }
    ],
    "sg:phone":"+1 804 224 1101",
    "sg:postcode":"22443",
    "sg:province":"VA",
    "sg:tags":[
        "operation"
    ],
    "wof:name":"Plaza Bed & Breakfast The",
    "wof:placetype":"venue"
},
  "geometry": {"coordinates":[-76.95964600000001,38.247068],"type":"Point"}
}