{
  "type": "Feature",
  "properties": {
    "iso:country":"US",
    "sg:address":"499 Export Cir",
    "sg:city":"Newport News",
    "sg:classifiers":[
        {
            "category":"Freight",
            "type":"Transportation"
        }
    ],
    "sg:phone":"+1 757 595 0541",
    "sg:postcode":"23601",
    "sg:province":"VA",
    "sg:tags":[
        "packing",
        "crating"
    ],
    "wof:name":"Chick Packaging Of Virginia",
    "wof:placetype":"venue"
},
  "geometry": {"coordinates":[-76.46659699999999,37.038654],"type":"Point"}
}