{
  "type": "Feature",
  "properties": {
    "addr:full":"1001 Douglas Ave Martinsville VA 24112",
    "addr:housenumber":"1001",
    "addr:postcode":"24112",
    "addr:street":"Douglas Ave",
    "iso:country":"US",
    "sg:address":"1001 Douglas Ave",
    "sg:city":"Martinsville",
    "sg:classifiers":[
        {
            "category":"Museum",
            "type":"Entertainment"
        }
    ],
    "sg:phone":"+1 276 666 8600",
    "sg:postcode":"24112",
    "sg:province":"VA",
    "wof:name":"Museum of Natural History VA",
    "wof:placetype":"venue"
},
  "geometry": {"coordinates":[-79.87561599999999,36.677694],"type":"Point"}
}