{
  "type": "Feature",
  "properties": {
    "iso:country":"US",
    "sg:address":"43904 Loganwood Ct",
    "sg:city":"Ashburn",
    "sg:classifiers":[
        {
            "category":"Health Services",
            "subcategory":"Clinic",
            "type":"Services"
        }
    ],
    "sg:phone":"+1 301 529 2936",
    "sg:postcode":"20147",
    "sg:province":"VA",
    "sg:tags":[
        "welfare"
    ],
    "wof:name":"Katherine Ann Kany",
    "wof:placetype":"venue"
},
  "geometry": {"coordinates":[-77.48203100000001,39.013277],"type":"Point"}
}