{
  "type": "Feature",
  "properties": {
    "addr:full":"12848 Harbor Dr Woodbridge VA 22192",
    "addr:housenumber":"12848",
    "addr:postcode":"22192",
    "addr:street":"Harbor Dr",
    "iso:country":"US",
    "sg:address":"12848 Harbor Dr",
    "sg:city":"Woodbridge",
    "sg:classifiers":[
        {
            "category":"Organizations",
            "subcategory":"Religious Organization",
            "type":"Services"
        }
    ],
    "sg:phone":"+1 703 492 9719",
    "sg:postcode":"22192",
    "sg:province":"VA",
    "sg:tags":[
        "church"
    ],
    "sg:website":"www.obc.org",
    "wof:name":"Occoquan Bible Church",
    "wof:placetype":"venue"
},
  "geometry": {"coordinates":[-77.280079,38.673784],"type":"Point"}
}