{
  "type": "Feature",
  "properties": {
    "addr:full":"350 Littletown Quarter Williamsburg VA 23185",
    "addr:housenumber":"350",
    "addr:postcode":"23185",
    "addr:street":"Littletown Quarter",
    "iso:country":"US",
    "sg:address":"350 Littletown Quarter",
    "sg:city":"Williamsburg",
    "sg:classifiers":[
        {
            "category":"Professional",
            "type":"Services"
        }
    ],
    "sg:phone":"+1 757 220 8951",
    "sg:postcode":"23185",
    "sg:province":"VA",
    "wof:name":"Breva International",
    "wof:placetype":"venue"
},
  "geometry": {"coordinates":[-76.665138,37.22972],"type":"Point"}
}