{
  "type": "Feature",
  "properties": {
    "iso:country":"US",
    "sg:address":"119 Rudolph St",
    "sg:city":"Ruckersville",
    "sg:classifiers":[
        {
            "category":"Professional",
            "subcategory":"Business Services",
            "type":"Services"
        }
    ],
    "sg:phone":"+1 434 990 1152",
    "sg:postcode":"22968",
    "sg:province":"VA",
    "wof:name":"Pro Sound Productions",
    "wof:placetype":"venue"
},
  "geometry": {"coordinates":[-78.393714,38.220798],"type":"Point"}
}