{
  "type": "Feature",
  "properties": {
    "iso:country":"US",
    "sg:address":"320 Hull St",
    "sg:city":"Richmond",
    "sg:classifiers":[
        {
            "category":"Professional",
            "subcategory":"Accounting & Tax Preparation",
            "type":"Services"
        }
    ],
    "sg:phone":"+1 804 291 1100",
    "sg:postcode":"23224",
    "sg:province":"VA",
    "sg:tags":[
        "return",
        "filing"
    ],
    "wof:name":"Tax Shack",
    "wof:placetype":"venue"
},
  "geometry": {"coordinates":[-77.43750900000001,37.525036],"type":"Point"}
}