{
  "type": "Feature",
  "properties": {
    "iso:country":"US",
    "sg:address":"1434 Wilson Rd",
    "sg:city":"Norfolk",
    "sg:classifiers":[
        {
            "category":"Organizations",
            "subcategory":"Religious Organization",
            "type":"Services"
        }
    ],
    "sg:phone":"+1 757 543 0458",
    "sg:postcode":"23523",
    "sg:province":"VA",
    "sg:tags":[
        "church"
    ],
    "sg:website":"www.firstpentecostaluhc.org",
    "wof:name":"First United Holy Church",
    "wof:placetype":"venue"
},
  "geometry": {"coordinates":[-76.265699,36.829262],"type":"Point"}
}