{
  "type": "Feature",
  "properties": {
    "addr:full":"1030 Warrenton Rd Fredericksburg VA 22406",
    "addr:housenumber":"1030",
    "addr:postcode":"22406",
    "addr:street":"Warrenton Rd",
    "iso:country":"US",
    "sg:address":"1030 Warrenton Rd",
    "sg:city":"Fredericksburg",
    "sg:classifiers":[
        {
            "category":"Sports & Exercise",
            "subcategory":"Gym",
            "type":"Entertainment"
        }
    ],
    "sg:phone":"+1 540 286 0600",
    "sg:postcode":"22406",
    "sg:province":"VA",
    "sg:tags":[
        "club",
        "health",
        "studio",
        "gymnasium"
    ],
    "wof:name":"Gold's Gym",
    "wof:placetype":"venue"
},
  "geometry": {"coordinates":[-77.52041,38.361661],"type":"Point"}
}