{
  "type": "Feature",
  "properties": {
    "iso:country":"US",
    "sg:address":"1152 Bill Tuck Hwy",
    "sg:city":"South Boston",
    "sg:classifiers":[
        {
            "category":"Home & Garden",
            "subcategory":"Mobile Homes",
            "type":"Retail Goods"
        }
    ],
    "sg:phone":"+1 434 575 7931",
    "sg:postcode":"24592",
    "sg:province":"NC",
    "sg:tags":[
        "house",
        "construction"
    ],
    "wof:name":"Colonial Homes Center",
    "wof:placetype":"venue"
},
  "geometry": {"coordinates":[-78.88985,36.6884],"type":"Point"}
}