{
  "type": "Feature",
  "properties": {
    "addr:full":"6400 Hull Street Rd Richmond VA 23224",
    "addr:housenumber":"6400",
    "addr:postcode":"23224",
    "addr:street":"Hull Street Rd",
    "iso:country":"US",
    "sg:address":"6400 Hull Street Rd",
    "sg:city":"Richmond",
    "sg:classifiers":[
        {
            "category":"Autos & Motor Vehicles",
            "subcategory":"Fuel & Gas Station",
            "type":"Retail Goods"
        }
    ],
    "sg:phone":"+1 804 276 5013",
    "sg:postcode":"23224",
    "sg:province":"VA",
    "wof:name":"Chippenham Amoco",
    "wof:placetype":"venue"
},
  "geometry": {"coordinates":[-77.510559,37.480099],"type":"Point"}
}