{
  "type": "Feature",
  "properties": {
    "addr:full":"139 Richards Ferry Rd Fredericksburg VA 22406",
    "addr:housenumber":"139",
    "addr:postcode":"22406",
    "addr:street":"Richards Ferry Rd",
    "iso:country":"US",
    "sg:address":"139 Richards Ferry Rd",
    "sg:city":"Fredericksburg",
    "sg:classifiers":[
        {
            "category":"Education",
            "subcategory":"Vocational School",
            "type":"Public Place"
        }
    ],
    "sg:phone":"+1 540 286 2492",
    "sg:postcode":"22406",
    "sg:province":"VA",
    "sg:tags":[
        "training",
        "computer"
    ],
    "wof:name":"Business Infocus Group Inc",
    "wof:placetype":"venue"
},
  "geometry": {"coordinates":[-77.57800899999999,38.39801],"type":"Point"}
}