{
  "type": "Feature",
  "properties": {
    "iso:country":"US",
    "sg:address":"3310 Rosedale Ave",
    "sg:city":"Richmond",
    "sg:classifiers":[
        {
            "category":"Wholesale",
            "subcategory":"Furniture",
            "type":"Manufacturing & Wholesale Goods"
        }
    ],
    "sg:phone":"+1 804 359 1011",
    "sg:postcode":"23230",
    "sg:province":"VA",
    "wof:name":"Ennis Business Systems",
    "wof:placetype":"venue"
},
  "geometry": {"coordinates":[-77.469746,37.575898],"type":"Point"}
}