{
  "type": "Feature",
  "properties": {
    "iso:country":"US",
    "sg:address":"208 Little Florida Rd",
    "sg:city":"Poquoson",
    "sg:classifiers":[
        {
            "category":"Home & Garden",
            "subcategory":"Household Appliances",
            "type":"Retail Goods"
        }
    ],
    "sg:phone":"+1 757 868 9136",
    "sg:postcode":"23662",
    "sg:province":"VA",
    "wof:name":"Vacu Flo Sales Service",
    "wof:placetype":"venue"
},
  "geometry": {"coordinates":[-76.376469,37.125068],"type":"Point"}
}