{
  "type": "Feature",
  "properties": {
    "addr:full":"506 N Main St Danville VA 24540",
    "addr:housenumber":"506",
    "addr:postcode":"24540",
    "addr:street":"N Main St",
    "iso:country":"US",
    "sg:address":"506 N Main St",
    "sg:city":"Danville",
    "sg:classifiers":[
        {
            "category":"Taxi",
            "type":"Transportation"
        }
    ],
    "sg:phone":"+1 434 791 1666",
    "sg:postcode":"24540",
    "sg:province":"VA",
    "sg:tags":[
        "taxicab"
    ],
    "wof:name":"Yellow Cab Co",
    "wof:placetype":"venue"
},
  "geometry": {"coordinates":[-79.38592,36.593664],"type":"Point"}
}