{
  "type": "Feature",
  "properties": {
    "iso:country":"US",
    "sg:address":"10026 Colvin Run Rd",
    "sg:city":"Great Falls",
    "sg:classifiers":[
        {
            "category":"Real Estate",
            "subcategory":"Real Estate Agent",
            "type":"Services"
        }
    ],
    "sg:phone":"+1 703 759 5227",
    "sg:postcode":"22066",
    "sg:province":"VA",
    "wof:name":"Richardson Group",
    "wof:placetype":"venue"
},
  "geometry": {"coordinates":[-77.292922,38.969377],"type":"Point"}
}