{
  "type": "Feature",
  "properties": {
    "addr:full":"716 Spruce Rd Newport News VA 23601",
    "addr:housenumber":"716",
    "addr:postcode":"23601",
    "addr:street":"Spruce Rd",
    "iso:country":"US",
    "sg:address":"716 Spruce Rd",
    "sg:city":"Newport News",
    "sg:classifiers":[
        {
            "category":"Building & Trades",
            "subcategory":"Construction",
            "type":"Services"
        }
    ],
    "sg:phone":"+1 757 596 2360",
    "sg:postcode":"23601",
    "sg:province":"VA",
    "sg:tags":[
        "handyman"
    ],
    "wof:name":"Johnston & Sons Svc",
    "wof:placetype":"venue"
},
  "geometry": {"coordinates":[-76.451564,37.043955],"type":"Point"}
}