{
  "type": "Feature",
  "properties": {
    "addr:full":"16538 Machodoc Lndg King George VA 22485",
    "addr:housenumber":"16538",
    "addr:postcode":"22485",
    "addr:street":"Machodoc Lndg",
    "iso:country":"US",
    "sg:address":"16538 Machodoc Lndg",
    "sg:city":"King George",
    "sg:classifiers":[
        {
            "category":"Building & Trades",
            "subcategory":"Landscaping Services",
            "type":"Services"
        }
    ],
    "sg:phone":"+1 540 775 7669",
    "sg:postcode":"22485",
    "sg:province":"VA",
    "sg:tags":[
        "landscape",
        "contractor"
    ],
    "wof:name":"Snow's Turf & Grounds Mgmt",
    "wof:placetype":"venue"
},
  "geometry": {"coordinates":[-77.053466,38.28858],"type":"Point"}
}