{
  "type": "Feature",
  "properties": {
    "addr:full":"9137 Courthouse Rd Ste 200 Spotsylvania VA 22553",
    "addr:housenumber":"9137",
    "addr:postcode":"22553",
    "addr:street":"Courthouse Rd Ste 200",
    "iso:country":"US",
    "sg:address":"9137 Courthouse Rd Ste 200",
    "sg:city":"Spotsylvania",
    "sg:classifiers":[
        {
            "category":"Professional",
            "subcategory":"Lawyer & Legal Services",
            "type":"Services"
        }
    ],
    "sg:phone":"+1 540 582 8300",
    "sg:postcode":"22553",
    "sg:province":"VA",
    "sg:tags":[
        "attorney",
        "injury",
        "estate",
        "family",
        "personal",
        "divorce",
        "practice",
        "planning",
        "law"
    ],
    "wof:name":"Beverley Mc Namara Liposky",
    "wof:placetype":"venue"
},
  "geometry": {"coordinates":[-77.526966,38.24408],"type":"Point"}
}