{
  "type": "Feature",
  "properties": {
    "addr:full":"2509 Maymont Ct Virginia Beach VA 23454",
    "addr:housenumber":"2509",
    "addr:postcode":"23454",
    "addr:street":"Maymont Ct",
    "iso:country":"US",
    "sg:address":"2509 Maymont Ct",
    "sg:city":"Virginia Beach",
    "sg:classifiers":[
        {
            "category":"Building & Trades",
            "subcategory":"Landscaping Services",
            "type":"Services"
        }
    ],
    "sg:phone":"+1 757 426 5344",
    "sg:postcode":"23454",
    "sg:province":"VA",
    "sg:tags":[
        "landscape",
        "contractor"
    ],
    "wof:name":"Premier Earthshaping Inc",
    "wof:placetype":"venue"
},
  "geometry": {"coordinates":[-76.00358,36.757893],"type":"Point"}
}