{
  "type": "Feature",
  "properties": {
    "iso:country":"US",
    "sg:address":"705 W Washington St",
    "sg:city":"Suffolk",
    "sg:classifiers":[
        {
            "category":"Professional",
            "subcategory":"Lawyer & Legal Services",
            "type":"Services"
        }
    ],
    "sg:phone":"+1 757 934 1313",
    "sg:postcode":"23434",
    "sg:province":"VA",
    "wof:name":"Bb & C Mfg Homes Inc",
    "wof:placetype":"venue"
},
  "geometry": {"coordinates":[-76.595232,36.730354],"type":"Point"}
}