{
  "type": "Feature",
  "properties": {
    "addr:full":"114 Ridgebourne Ct Goodview VA 24095",
    "addr:housenumber":"114",
    "addr:postcode":"24095",
    "addr:street":"Ridgebourne Ct",
    "iso:country":"US",
    "sg:address":"114 Ridgebourne Ct",
    "sg:city":"Goodview",
    "sg:classifiers":[
        {
            "category":"Building & Trades",
            "subcategory":"Construction",
            "type":"Services"
        }
    ],
    "sg:phone":"+1 540 890 5156",
    "sg:postcode":"24095",
    "sg:province":"VA",
    "sg:tags":[
        "industrial"
    ],
    "wof:name":"Chisom RR Bldg & Elec Contr",
    "wof:placetype":"venue"
},
  "geometry": {"coordinates":[-79.74063200000001,37.242914],"type":"Point"}
}