{
  "type": "Feature",
  "properties": {
    "addr:full":"4475 Cheshire Station Plz Woodbridge VA 22193",
    "addr:housenumber":"4475",
    "addr:postcode":"22193",
    "addr:street":"Cheshire Station Plz",
    "iso:country":"US",
    "sg:address":"4475 Cheshire Station Plz",
    "sg:city":"Woodbridge",
    "sg:classifiers":[
        {
            "category":"Restaurant",
            "type":"Food & Drink"
        }
    ],
    "sg:menulink":"http://www.allmenus.com/va/neabsco/71413-ledo-pizza/menu/",
    "sg:phone":"+1 703 590 1717",
    "sg:postcode":"22193",
    "sg:province":"VA",
    "sg:tags":[
        "american",
        "pizza"
    ],
    "wof:name":"Ledo Pizza",
    "wof:placetype":"venue"
},
  "geometry": {"coordinates":[-77.33430300000001,38.646307],"type":"Point"}
}