{
  "type": "Feature",
  "properties": {
    "iso:country":"US",
    "sg:address":"605 William St",
    "sg:city":"Fredericksburg",
    "sg:classifiers":[
        {
            "category":"Professional",
            "subcategory":"Advertising",
            "type":"Services"
        }
    ],
    "sg:phone":"+1 540 368 5055",
    "sg:postcode":"22401",
    "sg:province":"VA",
    "wof:name":"Freelance Star",
    "wof:placetype":"venue"
},
  "geometry": {"coordinates":[-77.464054,38.30204],"type":"Point"}
}