{
  "type": "Feature",
  "properties": {
    "addr:full":"7919 Provincetown Dr Richmond VA 23235",
    "addr:housenumber":"7919",
    "addr:postcode":"23235",
    "addr:street":"Provincetown Dr",
    "iso:country":"US",
    "sg:address":"7919 Provincetown Dr",
    "sg:city":"Richmond",
    "sg:classifiers":[
        {
            "category":"Professional",
            "subcategory":"Computer Services",
            "type":"Services"
        }
    ],
    "sg:phone":"+1 804 320 8810",
    "sg:postcode":"23235",
    "sg:province":"VA",
    "sg:tags":[
        "related"
    ],
    "wof:name":"Sam Hastings Macintosh Cons",
    "wof:placetype":"venue"
},
  "geometry": {"coordinates":[-77.542185,37.494717],"type":"Point"}
}