{
  "type": "Feature",
  "properties": {
    "addr:full":"8910 Granby St Norfolk VA 23503",
    "addr:housenumber":"8910",
    "addr:postcode":"23503",
    "addr:street":"Granby St",
    "iso:country":"US",
    "sg:address":"8910 Granby St",
    "sg:city":"Norfolk",
    "sg:classifiers":[
        {
            "category":"Building & Trades",
            "subcategory":"Plumbing",
            "type":"Services"
        }
    ],
    "sg:phone":"+1 757 494 3777",
    "sg:postcode":"23503",
    "sg:province":"VA",
    "sg:tags":[
        "conditioning",
        "air",
        "system",
        "contractor"
    ],
    "wof:name":"Air Specialty Corp",
    "wof:placetype":"venue"
},
  "geometry": {"coordinates":[-76.261239,36.939651],"type":"Point"}
}