{
  "type": "Feature",
  "properties": {
    "addr:full":"1309 Jamestown Rd Ste 202 Williamsburg VA 23185",
    "addr:housenumber":"1309",
    "addr:postcode":"23185",
    "addr:street":"Jamestown Rd Ste 202",
    "iso:country":"US",
    "sg:address":"1309 Jamestown Rd Ste 202",
    "sg:city":"Williamsburg",
    "sg:classifiers":[
        {
            "category":"Education",
            "subcategory":"University",
            "type":"Public Place"
        }
    ],
    "sg:phone":"+1 757 253 6933",
    "sg:postcode":"23185",
    "sg:province":"VA",
    "sg:tags":[
        "college"
    ],
    "wof:name":"Peace Operations Training Institute, Inc.",
    "wof:placetype":"venue"
},
  "geometry": {"coordinates":[-76.733368,37.252449],"type":"Point"}
}