{
  "type": "Feature",
  "properties": {
    "addr:full":"10201 Iron Bridge Rd Chesterfield VA 23832",
    "addr:housenumber":"10201",
    "addr:postcode":"23832",
    "addr:street":"Iron Bridge Rd",
    "iso:country":"US",
    "sg:address":"10201 Iron Bridge Rd",
    "sg:city":"Chesterfield",
    "sg:classifiers":[
        {
            "category":"Professional",
            "subcategory":"Research",
            "type":"Services"
        }
    ],
    "sg:phone":"+1 804 777 9663",
    "sg:postcode":"23832",
    "sg:province":"VA",
    "sg:tags":[
        "historical"
    ],
    "wof:name":"Chesterfield County Historical",
    "wof:placetype":"venue"
},
  "geometry": {"coordinates":[-77.504744,37.375163],"type":"Point"}
}