{
  "type": "Feature",
  "properties": {
    "addr:full":"2236 Scottsburg Rd Scottsburg VA 24589",
    "addr:housenumber":"2236",
    "addr:postcode":"24589",
    "addr:street":"Scottsburg Rd",
    "iso:country":"US",
    "sg:address":"2236 Scottsburg Rd",
    "sg:city":"Scottsburg",
    "sg:classifiers":[
        {
            "category":"Professional",
            "type":"Services"
        }
    ],
    "sg:phone":"+1 434 454 6414",
    "sg:postcode":"24589",
    "sg:province":"VA",
    "sg:tags":[
        "establishment"
    ],
    "wof:name":"A B Guthrie",
    "wof:placetype":"venue"
},
  "geometry": {"coordinates":[-78.794945,36.759319],"type":"Point"}
}