{
  "type": "Feature",
  "properties": {
    "iso:country":"US",
    "sg:address":"2231 William And Mary Dr",
    "sg:city":"Alexandria",
    "sg:classifiers":[
        {
            "category":"Manufacturing",
            "subcategory":"Aerospace",
            "type":"Manufacturing & Wholesale Goods"
        },
        {
            "category":"Manufacturing",
            "subcategory":"Musical Instruments",
            "type":"Manufacturing & Wholesale Goods"
        }
    ],
    "sg:phone":"+1 703 417 9677",
    "sg:postcode":"22308",
    "sg:province":"VA",
    "sg:tags":[
        "aircraft",
        "avionics",
        "nautical"
    ],
    "sg:website":"http://www.shasolutions.com",
    "wof:name":"Sha Solutions",
    "wof:placetype":"venue"
},
  "geometry": {"coordinates":[-77.069608,38.73473],"type":"Point"}
}