{
  "type": "Feature",
  "properties": {
    "addr:full":"1520 Bridle Creek Blvd Virginia Beach VA 23464",
    "addr:housenumber":"1520",
    "addr:postcode":"23464",
    "addr:street":"Bridle Creek Blvd",
    "iso:country":"US",
    "sg:address":"1520 Bridle Creek Blvd",
    "sg:city":"Virginia Beach",
    "sg:classifiers":[
        {
            "category":"Professional",
            "subcategory":"Business Services",
            "type":"Services"
        }
    ],
    "sg:phone":"+1 757 718 1788",
    "sg:postcode":"23464",
    "sg:province":"VA",
    "wof:name":"Grasshopper Recording Studio",
    "wof:placetype":"venue"
},
  "geometry": {"coordinates":[-76.15747500000001,36.787695],"type":"Point"}
}