{
  "type": "Feature",
  "properties": {
    "addr:full":"1429 Riverside Rd Chilhowie VA 24319",
    "addr:housenumber":"1429",
    "addr:postcode":"24319",
    "addr:street":"Riverside Rd",
    "iso:country":"US",
    "sg:address":"1429 Riverside Rd",
    "sg:city":"Chilhowie",
    "sg:phone":"+1 276 783 2273",
    "sg:postcode":"24319",
    "sg:province":"VA",
    "sg:tags":[
        "tobacco",
        "beef",
        "farm",
        "crop",
        "field",
        "cattle",
        "feedlot"
    ],
    "wof:name":"James Sturgill",
    "wof:placetype":"venue"
},
  "geometry": {"coordinates":[-81.615499,36.769996],"type":"Point"}
}