{
  "type": "Feature",
  "properties": {
    "addr:full":"10621 Oliver St Fairfax VA 22030",
    "addr:housenumber":"10621",
    "addr:postcode":"22030",
    "addr:street":"Oliver St",
    "iso:country":"US",
    "sg:address":"10621 Oliver St",
    "sg:city":"Fairfax",
    "sg:classifiers":[
        {
            "category":"Building & Trades",
            "subcategory":"Construction",
            "type":"Services"
        }
    ],
    "sg:phone":"+1 703 534 3069",
    "sg:postcode":"22030",
    "sg:province":"VA",
    "sg:tags":[
        "home",
        "remodeling",
        "family",
        "general"
    ],
    "wof:name":"A & L Construction Inc",
    "wof:placetype":"venue"
},
  "geometry": {"coordinates":[-77.314094,38.851361],"type":"Point"}
}