{
  "type": "Feature",
  "properties": {
    "iso:country":"US",
    "sg:address":"3133 Magic Hollow Blvd",
    "sg:city":"Virginia Beach",
    "sg:classifiers":[
        {
            "category":"Professional",
            "subcategory":"Lawyer & Legal Services",
            "type":"Services"
        }
    ],
    "sg:phone":"+1 757 368 6929",
    "sg:postcode":"23453",
    "sg:province":"VA",
    "wof:name":"Law Offices Jennifer Lacey PC",
    "wof:placetype":"venue"
},
  "geometry": {"coordinates":[-76.07908399999999,36.806256],"type":"Point"}
}