{
  "type": "Feature",
  "properties": {
    "addr:full":"2803 N Garden Ln North Garden VA 22959",
    "addr:housenumber":"2803",
    "addr:postcode":"22959",
    "addr:street":"N Garden Ln North",
    "iso:country":"US",
    "sg:address":"2803 N Garden Ln",
    "sg:city":"North Garden",
    "sg:classifiers":[
        {
            "category":"Building & Trades",
            "subcategory":"Construction",
            "type":"Services"
        }
    ],
    "sg:phone":"+1 434 293 8780",
    "sg:postcode":"22959",
    "sg:province":"VA",
    "sg:tags":[
        "residential"
    ],
    "wof:name":"R&T Construction",
    "wof:placetype":"venue"
},
  "geometry": {"coordinates":[-78.644486,37.959044],"type":"Point"}
}