{
  "type": "Feature",
  "properties": {
    "addr:full":"729 Pecan Point Rd Norfolk VA 23502",
    "addr:housenumber":"729",
    "addr:postcode":"23502",
    "addr:street":"Pecan Point Rd",
    "iso:country":"US",
    "sg:address":"729 Pecan Point Rd",
    "sg:city":"Norfolk",
    "sg:classifiers":[
        {
            "category":"Wholesale",
            "subcategory":"Groceries",
            "type":"Manufacturing & Wholesale Goods"
        }
    ],
    "sg:phone":"+1 757 461 2731",
    "sg:postcode":"23502",
    "sg:province":"VA",
    "sg:tags":[
        "genus",
        "packaged"
    ],
    "wof:name":"Woodbine Farm",
    "wof:placetype":"venue"
},
  "geometry": {"coordinates":[-76.222728,36.853042],"type":"Point"}
}