{
  "type": "Feature",
  "properties": {
    "addr:full":"591 Alleghany Spring Rd Shawsville VA 24162",
    "addr:housenumber":"591",
    "addr:postcode":"24162",
    "addr:street":"Alleghany Spring Rd",
    "iso:country":"US",
    "sg:address":"591 Alleghany Spring Rd",
    "sg:city":"Shawsville",
    "sg:classifiers":[
        {
            "category":"Professional",
            "subcategory":"Management & Consulting",
            "type":"Services"
        }
    ],
    "sg:phone":"+1 540 268 2300",
    "sg:postcode":"24162",
    "sg:province":"VA",
    "wof:name":"Business Edge",
    "wof:placetype":"venue"
},
  "geometry": {"coordinates":[-80.253665,37.159604],"type":"Point"}
}