{
  "type": "Feature",
  "properties": {
    "iso:country":"US",
    "sg:address":"5679 Saffron Ln",
    "sg:city":"Woodbridge",
    "sg:classifiers":[
        {
            "category":"Professional",
            "subcategory":"Management & Consulting",
            "type":"Services"
        }
    ],
    "sg:phone":"+1 703 680 3564",
    "sg:postcode":"22193",
    "sg:province":"VA",
    "sg:tags":[
        "business"
    ],
    "wof:name":"Robert Wildberger Jr",
    "wof:placetype":"venue"
},
  "geometry": {"coordinates":[-77.377,38.637898],"type":"Point"}
}