{
  "type": "Feature",
  "properties": {
    "iso:country":"US",
    "sg:address":"3471 Anderson Hwy",
    "sg:city":"Powhatan",
    "sg:classifiers":[
        {
            "category":"Retail",
            "subcategory":"Auto Repair",
            "type":"Services"
        }
    ],
    "sg:phone":"+1 804 598 0071",
    "sg:postcode":"23139",
    "sg:province":"VA",
    "sg:tags":[
        "repairing",
        "automobile",
        "general"
    ],
    "wof:name":"Pete S Auto Repair",
    "wof:placetype":"venue"
},
  "geometry": {"coordinates":[-77.89783799999999,37.541595],"type":"Point"}
}