{
  "type": "Feature",
  "properties": {
    "addr:full":"4 Walnut St Martinsville VA 24112",
    "addr:housenumber":"4",
    "addr:postcode":"24112",
    "addr:street":"Walnut St",
    "iso:country":"US",
    "sg:address":"4 Walnut St",
    "sg:city":"Martinsville",
    "sg:classifiers":[
        {
            "category":"Professional",
            "subcategory":"Computer Services",
            "type":"Services"
        }
    ],
    "sg:phone":"+1 276 618 0141",
    "sg:postcode":"24112",
    "sg:province":"VA",
    "sg:tags":[
        "internet"
    ],
    "wof:name":"Ntelos",
    "wof:placetype":"venue"
},
  "geometry": {"coordinates":[-79.872641,36.690996],"type":"Point"}
}