{
  "type": "Feature",
  "properties": {
    "addr:full":"1229 Cedar Rd Chesapeake VA 23322",
    "addr:housenumber":"1229",
    "addr:postcode":"23322",
    "addr:street":"Cedar Rd",
    "iso:country":"US",
    "sg:address":"1229 Cedar Rd",
    "sg:city":"Chesapeake",
    "sg:classifiers":[
        {
            "category":"Food & Beverages",
            "subcategory":"Groceries & Convenience Stores",
            "type":"Retail Goods"
        }
    ],
    "sg:phone":"+1 757 548 3680",
    "sg:postcode":"23322",
    "sg:province":"VA",
    "wof:name":"Miller Mart",
    "wof:placetype":"venue"
},
  "geometry": {"coordinates":[-76.28260299999999,36.715787],"type":"Point"}
}