{
  "type": "Feature",
  "properties": {
    "addr:full":"105 Keystone Pl Charlottesville VA 22902",
    "addr:housenumber":"105",
    "addr:postcode":"22902",
    "addr:street":"Keystone Pl",
    "iso:country":"US",
    "sg:address":"105 Keystone Pl",
    "sg:city":"Charlottesville",
    "sg:classifiers":[
        {
            "category":"Professional",
            "type":"Services"
        }
    ],
    "sg:phone":"+1 434 963 9700",
    "sg:postcode":"22902",
    "sg:province":"VA",
    "sg:tags":[
        "establishment"
    ],
    "wof:name":"Lightstyles Limited",
    "wof:placetype":"venue"
},
  "geometry": {"coordinates":[-78.47123000000001,38.014416],"type":"Point"}
}