{
  "type": "Feature",
  "properties": {
    "iso:country":"US",
    "sg:address":"940 Professional Pl",
    "sg:city":"Chesapeake",
    "sg:classifiers":[
        {
            "category":"Retail",
            "subcategory":"Auto Rental",
            "type":"Services"
        }
    ],
    "sg:phone":"+1 757 547 4632",
    "sg:postcode":"23320",
    "sg:province":"VA",
    "sg:tags":[
        "renting",
        "truck",
        "leasing"
    ],
    "wof:name":"Budget Truck Rental",
    "wof:placetype":"venue"
},
  "geometry": {"coordinates":[-76.230864,36.763368],"type":"Point"}
}