{
  "type": "Feature",
  "properties": {
    "iso:country":"US",
    "sg:address":"801 Volvo Pkwy",
    "sg:city":"Chesapeake",
    "sg:classifiers":[
        {
            "category":"Professional",
            "subcategory":"Printing & Photocopies",
            "type":"Services"
        }
    ],
    "sg:phone":"+1 757 547 4200",
    "sg:postcode":"23320",
    "sg:province":"VA",
    "sg:tags":[
        "photocopying"
    ],
    "wof:name":"Kinkos",
    "wof:placetype":"venue"
},
  "geometry": {"coordinates":[-76.229328,36.768726],"type":"Point"}
}