{
  "type": "Feature",
  "properties": {
    "addr:full":"17802 Madison St Hamilton VA 20158",
    "addr:housenumber":"17802",
    "addr:postcode":"20158",
    "addr:street":"Madison St",
    "iso:country":"US",
    "sg:address":"17802 Madison St",
    "sg:city":"Hamilton",
    "sg:classifiers":[
        {
            "category":"Utilities",
            "subcategory":"Telephone",
            "type":"Services"
        }
    ],
    "sg:phone":"+1 540 338 2797",
    "sg:postcode":"20158",
    "sg:province":"VA",
    "sg:tags":[
        "communications"
    ],
    "wof:name":"Telco Electronics",
    "wof:placetype":"venue"
},
  "geometry": {"coordinates":[-77.674143,39.134095],"type":"Point"}
}