{
  "type": "Feature",
  "properties": {
    "addr:full":"317 Updike Pl Danville VA 24541",
    "addr:housenumber":"317",
    "addr:postcode":"24541",
    "addr:street":"Updike Pl",
    "iso:country":"US",
    "sg:address":"317 Updike Pl",
    "sg:city":"Danville",
    "sg:classifiers":[
        {
            "category":"Real Estate",
            "subcategory":"Real Estate Agent",
            "type":"Services"
        }
    ],
    "sg:phone":"+1 434 792 3424",
    "sg:postcode":"24541",
    "sg:province":"VA",
    "wof:name":"Shields Appraisal Service",
    "wof:placetype":"venue"
},
  "geometry": {"coordinates":[-79.395448,36.556154],"type":"Point"}
}