{
  "type": "Feature",
  "properties": {
    "addr:full":"1600 Wilson Blvd Ste 902 Arlington VA 22209",
    "addr:housenumber":"1600",
    "addr:postcode":"22209",
    "addr:street":"Wilson Blvd Ste 902",
    "iso:country":"US",
    "sg:address":"1600 Wilson Blvd Ste 902",
    "sg:city":"Arlington",
    "sg:classifiers":[
        {
            "category":"Arts & Performance",
            "subcategory":"Arts Center",
            "type":"Entertainment"
        }
    ],
    "sg:phone":"+1 703 908 9700",
    "sg:postcode":"22209",
    "sg:province":"VA",
    "sg:tags":[
        "information"
    ],
    "sg:website":"http://www.statehumanities.org",
    "wof:name":"Federation Of State Humanities Councils",
    "wof:placetype":"venue"
},
  "geometry": {"coordinates":[-77.07759799999999,38.894278],"type":"Point"}
}