{
  "type": "Feature",
  "properties": {
    "iso:country":"US",
    "sg:address":"5418 Broadmoor St",
    "sg:city":"Alexandria",
    "sg:classifiers":[
        {
            "category":"Communications",
            "type":"Services"
        }
    ],
    "sg:phone":"+1 703 971 9023",
    "sg:postcode":"22315",
    "sg:province":"VA",
    "sg:tags":[
        "communication"
    ],
    "wof:name":"Velvet Hammer Communication",
    "wof:placetype":"venue"
},
  "geometry": {"coordinates":[-77.14141600000001,38.748192],"type":"Point"}
}