{
  "type": "Feature",
  "properties": {
    "addr:full":"5508 Hamlet Hill Ct Fairfax VA 22030",
    "addr:housenumber":"5508",
    "addr:postcode":"22030",
    "addr:street":"Hamlet Hill Ct",
    "iso:country":"US",
    "sg:address":"5508 Hamlet Hill Ct",
    "sg:city":"Fairfax",
    "sg:classifiers":[
        {
            "category":"Professional",
            "type":"Services"
        }
    ],
    "sg:phone":"+1 703 385 2904",
    "sg:postcode":"22030",
    "sg:province":"VA",
    "sg:tags":[
        "establishment"
    ],
    "wof:name":"Networkore",
    "wof:placetype":"venue"
},
  "geometry": {"coordinates":[-77.390241,38.832501],"type":"Point"}
}