{
  "type": "Feature",
  "properties": {
    "addr:full":"110 Whitewood Rd Charlottesville VA 22901",
    "addr:housenumber":"110",
    "addr:postcode":"22901",
    "addr:street":"Whitewood Rd",
    "iso:country":"US",
    "sg:address":"110 Whitewood Rd",
    "sg:city":"Charlottesville",
    "sg:classifiers":[
        {
            "category":"Health Services",
            "subcategory":"Optometrist",
            "type":"Services"
        }
    ],
    "sg:phone":"+1 434 978 4090",
    "sg:postcode":"22901",
    "sg:province":"VA",
    "wof:name":"Record Carol Dr",
    "wof:placetype":"venue"
},
  "geometry": {"coordinates":[-78.49214499999999,38.074293],"type":"Point"}
}