{
  "type": "Feature",
  "properties": {
    "addr:full":"1274 Swan Lake Dr Charlottesville VA 22902",
    "addr:housenumber":"1274",
    "addr:postcode":"22902",
    "addr:street":"Swan Lake Dr",
    "iso:country":"US",
    "sg:address":"1274 Swan Lake Dr",
    "sg:city":"Charlottesville",
    "sg:classifiers":[
        {
            "category":"Banks & Credit Unions",
            "subcategory":"Financial Services",
            "type":"Services"
        }
    ],
    "sg:phone":"+1 434 974 6178",
    "sg:postcode":"22902",
    "sg:province":"VA",
    "sg:tags":[
        "company",
        "holding"
    ],
    "wof:name":"Valovuosi LLC",
    "wof:placetype":"venue"
},
  "geometry": {"coordinates":[-78.49400799999999,38.00388],"type":"Point"}
}