{
  "type": "Feature",
  "properties": {
    "addr:full":"15142 Mountain Rd South Boston VA 24592",
    "addr:housenumber":"15142",
    "addr:postcode":"24592",
    "addr:street":"Mountain Rd",
    "iso:country":"US",
    "sg:address":"15142 Mountain Rd",
    "sg:city":"South Boston",
    "sg:classifiers":[
        {
            "category":"Food & Beverages",
            "subcategory":"Groceries & Convenience Stores",
            "type":"Retail Goods"
        }
    ],
    "sg:phone":"+1 434 476 7717",
    "sg:postcode":"24592",
    "sg:province":"VA",
    "wof:name":"Tot's Place",
    "wof:placetype":"venue"
},
  "geometry": {"coordinates":[-79.168685,36.736624],"type":"Point"}
}