{
  "type": "Feature",
  "properties": {
    "iso:country":"US",
    "sg:address":"5018 Mercury Blvd",
    "sg:city":"Newport News",
    "sg:classifiers":[
        {
            "category":"Autos & Motor Vehicles",
            "subcategory":"Fuel & Gas Station",
            "type":"Retail Goods"
        }
    ],
    "sg:phone":"+1 757 827 5070",
    "sg:postcode":"23605",
    "sg:province":"VA",
    "sg:tags":[
        "oil"
    ],
    "wof:name":"Donkey Enterprises",
    "wof:placetype":"venue"
},
  "geometry": {"coordinates":[-76.44297299999999,37.020391],"type":"Point"}
}