{
  "type": "Feature",
  "properties": {
    "iso:country":"US",
    "sg:address":"2200 Maple St",
    "sg:city":"Virginia Beach",
    "sg:classifiers":[
        {
            "category":"Professional",
            "subcategory":"Secretarial Services",
            "type":"Services"
        }
    ],
    "sg:phone":"+1 757 496 2473",
    "sg:postcode":"23451",
    "sg:province":"VA",
    "sg:tags":[
        "editing",
        "reading",
        "proof",
        "writing"
    ],
    "wof:name":"Edit Services LLC",
    "wof:placetype":"venue"
},
  "geometry": {"coordinates":[-76.06268300000001,36.909582],"type":"Point"}
}