{
  "type": "Feature",
  "properties": {
    "addr:full":"21 E Queens Way Hampton VA 23669",
    "addr:housenumber":"21",
    "addr:postcode":"23669",
    "addr:street":"E Queens Way",
    "iso:country":"US",
    "sg:address":"21 E Queens Way",
    "sg:city":"Hampton",
    "sg:classifiers":[
        {
            "category":"Restaurant",
            "type":"Food & Drink"
        }
    ],
    "sg:phone":"+1 757 726 2614",
    "sg:postcode":"23669",
    "sg:province":"VA",
    "sg:tags":[
        "eating"
    ],
    "wof:name":"Rooneys Downtown Cafe",
    "wof:placetype":"venue"
},
  "geometry": {"coordinates":[-76.34316,37.025889],"type":"Point"}
}