{
  "type": "Feature",
  "properties": {
    "addr:full":"2201 Commerce Rd Richmond VA 23234",
    "addr:housenumber":"2201",
    "addr:postcode":"23234",
    "addr:street":"Commerce Rd",
    "iso:country":"US",
    "sg:address":"2201 Commerce Rd",
    "sg:city":"Richmond",
    "sg:classifiers":[
        {
            "category":"Retail",
            "subcategory":"Auto Repair",
            "type":"Services"
        }
    ],
    "sg:phone":"+1 804 230 4000",
    "sg:postcode":"23234",
    "sg:province":"VA",
    "sg:tags":[
        "fleet",
        "parts",
        "truck",
        "maintenance"
    ],
    "wof:name":"Southeastern Truck and Trlr Co",
    "wof:placetype":"venue"
},
  "geometry": {"coordinates":[-77.43335399999999,37.492024],"type":"Point"}
}