{
  "type": "Feature",
  "properties": {
    "iso:country":"US",
    "sg:address":"1053 Cedar Valley Dr",
    "sg:city":"Cedar Bluff",
    "sg:classifiers":[
        {
            "category":"Building & Trades",
            "subcategory":"Construction",
            "type":"Services"
        }
    ],
    "sg:phone":"+1 276 963 8946",
    "sg:postcode":"24609",
    "sg:province":"VA",
    "sg:tags":[
        "general",
        "contractor"
    ],
    "wof:name":"Twin Enterprises",
    "wof:placetype":"venue"
},
  "geometry": {"coordinates":[-81.761977,37.087459],"type":"Point"}
}