{
  "type": "Feature",
  "properties": {
    "addr:full":"5900 Fort Dr Suite 110 Centreville VA 20121",
    "addr:housenumber":"5900",
    "addr:postcode":"20121",
    "addr:street":"Fort Dr Suite 110",
    "iso:country":"US",
    "sg:address":"5900 Fort Dr Suite 110",
    "sg:city":"Centreville",
    "sg:classifiers":[
        {
            "category":"Banks & Credit Unions",
            "subcategory":"Bank",
            "type":"Services"
        },
        {
            "category":"Organizations",
            "subcategory":"Membership Organization",
            "type":"Services"
        }
    ],
    "sg:phone":"+1 888 842 6328",
    "sg:postcode":"20121",
    "sg:province":"VA",
    "sg:tags":[
        "military",
        "veteran"
    ],
    "sg:website":"http://navyfederal.org",
    "wof:name":"Navy Federal Credit Union",
    "wof:placetype":"venue"
},
  "geometry": {"coordinates":[-77.433145,38.83461],"type":"Point"}
}