{
  "type": "Feature",
  "properties": {
    "addr:full":"3508 Rochelle Ct Chesapeake VA 23321",
    "addr:housenumber":"3508",
    "addr:postcode":"23321",
    "addr:street":"Rochelle Ct",
    "iso:country":"US",
    "sg:address":"3508 Rochelle Ct",
    "sg:city":"Chesapeake",
    "sg:classifiers":[
        {
            "category":"Professional",
            "type":"Services"
        }
    ],
    "sg:phone":"+1 757 686 4492",
    "sg:postcode":"23321",
    "sg:province":"VA",
    "wof:name":"John Boss",
    "wof:placetype":"venue"
},
  "geometry": {"coordinates":[-76.42791800000001,36.852975],"type":"Point"}
}