{
  "type": "Feature",
  "properties": {
    "addr:full":"13 Carriage House Cir Alexandria VA 22304",
    "addr:housenumber":"13",
    "addr:postcode":"22304",
    "addr:street":"Carriage House Cir",
    "iso:country":"US",
    "sg:address":"13 Carriage House Cir",
    "sg:city":"Alexandria",
    "sg:classifiers":[
        {
            "category":"Professional",
            "type":"Services"
        }
    ],
    "sg:phone":"+1 703 644 8887",
    "sg:postcode":"22304",
    "sg:province":"VA",
    "sg:tags":[
        "establishment"
    ],
    "sg:website":"www.allegianceassociations.com",
    "wof:name":"Allegiance",
    "wof:placetype":"venue"
},
  "geometry": {"coordinates":[-77.09313400000001,38.809357],"type":"Point"}
}