{
  "type": "Feature",
  "properties": {
    "addr:full":"8371 Greensboro Dr Mc Lean VA 22102",
    "addr:housenumber":"8371",
    "addr:postcode":"22102",
    "addr:street":"Greensboro Dr",
    "iso:country":"US",
    "sg:address":"8371 Greensboro Dr",
    "sg:city":"Mc Lean",
    "sg:classifiers":[
        {
            "category":"Health Services",
            "subcategory":"Doctor",
            "type":"Services"
        }
    ],
    "sg:phone":"+1 703 821 0882",
    "sg:postcode":"22102",
    "sg:province":"VA",
    "sg:tags":[
        "dentist"
    ],
    "wof:name":"Rouben A Yedigarian DDS",
    "wof:placetype":"venue"
},
  "geometry": {"coordinates":[-77.234797,38.926886],"type":"Point"}
}