{
  "type": "Feature",
  "properties": {
    "addr:full":"3968 Blue Ridge Blvd Blue Ridge VA 24064",
    "addr:housenumber":"3968",
    "addr:postcode":"24064",
    "addr:street":"Blue Ridge Blvd",
    "iso:country":"US",
    "sg:address":"3968 Blue Ridge Blvd",
    "sg:city":"Blue Ridge",
    "sg:classifiers":[
        {
            "category":"Building & Trades",
            "subcategory":"Construction",
            "type":"Services"
        }
    ],
    "sg:phone":"+1 540 977 1403",
    "sg:postcode":"24064",
    "sg:province":"VA",
    "sg:tags":[
        "excavating",
        "contractor"
    ],
    "wof:name":"Ricky Cook Hauling & Excavtg",
    "wof:placetype":"venue"
},
  "geometry": {"coordinates":[-79.814649,37.368377],"type":"Point"}
}