{
  "type": "Feature",
  "properties": {
    "addr:full":"5080 Halycon Dr Crozet VA 22932",
    "addr:housenumber":"5080",
    "addr:postcode":"22932",
    "addr:street":"Halycon Dr",
    "iso:country":"US",
    "sg:address":"5080 Halycon Dr",
    "sg:city":"Crozet",
    "sg:classifiers":[
        {
            "category":"Retail",
            "subcategory":"Veterinary Services",
            "type":"Services"
        }
    ],
    "sg:phone":"+1 434 823 1550",
    "sg:postcode":"22932",
    "sg:province":"VA",
    "wof:name":"Afton Equine Clinic",
    "wof:placetype":"venue"
},
  "geometry": {"coordinates":[-78.678785,38.076104],"type":"Point"}
}