{
  "type": "Feature",
  "properties": {
    "addr:full":"10404 Johnson Dr Manassas VA 20110",
    "addr:housenumber":"10404",
    "addr:postcode":"20110",
    "addr:street":"Johnson Dr",
    "iso:country":"US",
    "sg:address":"10404 Johnson Dr",
    "sg:city":"Manassas",
    "sg:classifiers":[
        {
            "category":"Real Estate",
            "subcategory":"Real Estate Agent",
            "type":"Services"
        }
    ],
    "sg:phone":"+1 703 368 0891",
    "sg:postcode":"20110",
    "sg:province":"VA",
    "wof:name":"MEG Enterprises Inc",
    "wof:placetype":"venue"
},
  "geometry": {"coordinates":[-77.491074,38.72544],"type":"Point"}
}