{
  "type": "Feature",
  "properties": {
    "addr:full":"1403 Admiral Dr Woodbridge VA 22192",
    "addr:housenumber":"1403",
    "addr:postcode":"22192",
    "addr:street":"Admiral Dr",
    "iso:country":"US",
    "sg:address":"1403 Admiral Dr",
    "sg:city":"Woodbridge",
    "sg:classifiers":[
        {
            "category":"Personal",
            "subcategory":"Beauty Salon",
            "type":"Services"
        }
    ],
    "sg:phone":"+1 703 491 5292",
    "sg:postcode":"22192",
    "sg:province":"VA",
    "sg:tags":[
        "make",
        "studio"
    ],
    "wof:name":"Avon",
    "wof:placetype":"venue"
},
  "geometry": {"coordinates":[-77.256545,38.676997],"type":"Point"}
}