{
  "type": "Feature",
  "properties": {
    "addr:full":"9015 Pole Green Park Ln Mechanicsville VA 23116",
    "addr:postcode":"9015;23116",
    "addr:street":"Pole Green Park Ln",
    "iso:country":"US",
    "sg:address":"9015 Pole Green Park Ln",
    "sg:city":"Mechanicsville",
    "sg:classifiers":[
        {
            "category":"Professional",
            "subcategory":"Management & Consulting",
            "type":"Services"
        }
    ],
    "sg:phone":"+1 804 779 7718",
    "sg:postcode":"23116",
    "sg:province":"VA",
    "sg:tags":[
        "construction"
    ],
    "wof:name":"CRSS/Sverdrup",
    "wof:placetype":"venue"
},
  "geometry": {"coordinates":[-77.309442,37.650162],"type":"Point"}
}