{
  "type": "Feature",
  "properties": {
    "iso:country":"US",
    "sg:address":"10368 Festival Ln",
    "sg:city":"Manassas",
    "sg:classifiers":[
        {
            "category":"Shopping",
            "subcategory":"Crafts & Fabrics",
            "type":"Retail Goods"
        }
    ],
    "sg:phone":"+1 703 335 1219",
    "sg:postcode":"20109",
    "sg:province":"VA",
    "sg:tags":[
        "store"
    ],
    "sg:website":"www.joann.com",
    "wof:name":"Jo-Ann Fabrics & Crafts",
    "wof:placetype":"venue"
},
  "geometry": {"coordinates":[-77.49900100000001,38.7761],"type":"Point"}
}