{
  "type": "Feature",
  "properties": {
    "iso:country":"US",
    "sg:address":"7634 Knightshayes Dr",
    "sg:city":"Manassas",
    "sg:classifiers":[
        {
            "category":"Professional",
            "subcategory":"Computer Services",
            "type":"Services"
        }
    ],
    "sg:phone":"+1 703 369 6366",
    "sg:postcode":"20111",
    "sg:province":"VA",
    "sg:tags":[
        "telecommunication",
        "related"
    ],
    "wof:name":"Jk Zcom Inc",
    "wof:placetype":"venue"
},
  "geometry": {"coordinates":[-77.434573,38.708556],"type":"Point"}
}