{
  "type": "Feature",
  "properties": {
    "addr:full":"6617 Holland Rd Suffolk VA 23437",
    "addr:housenumber":"6617",
    "addr:postcode":"23437",
    "addr:street":"Holland Rd",
    "iso:country":"US",
    "sg:address":"6617 Holland Rd",
    "sg:city":"Suffolk",
    "sg:classifiers":[
        {
            "category":"Banks & Credit Unions",
            "subcategory":"Bank",
            "type":"Services"
        }
    ],
    "sg:phone":"+1 757 657 6421",
    "sg:postcode":"23437",
    "sg:province":"VA",
    "wof:name":"Bb & T Atlantic",
    "wof:placetype":"venue"
},
  "geometry": {"coordinates":[-76.780637,36.681075],"type":"Point"}
}