{
  "type": "Feature",
  "properties": {
    "addr:full":"25 Wade Ct Fredericksburg VA 22405",
    "addr:housenumber":"25",
    "addr:postcode":"22405",
    "addr:street":"Wade Ct",
    "iso:country":"US",
    "sg:address":"25 Wade Ct",
    "sg:city":"Fredericksburg",
    "sg:classifiers":[
        {
            "category":"Communications",
            "type":"Services"
        }
    ],
    "sg:phone":"+1 703 856 2707",
    "sg:postcode":"22405",
    "sg:province":"VA",
    "sg:tags":[
        "communication"
    ],
    "wof:name":"Pcg Communications",
    "wof:placetype":"venue"
},
  "geometry": {"coordinates":[-77.422194,38.313036],"type":"Point"}
}