{
  "type": "Feature",
  "properties": {
    "addr:full":"11543 Hickory Cluster Reston VA 20190",
    "addr:housenumber":"11543",
    "addr:postcode":"20190",
    "addr:street":"Hickory Cluster",
    "iso:country":"US",
    "sg:address":"11543 Hickory Cluster",
    "sg:city":"Reston",
    "sg:classifiers":[
        {
            "category":"Professional",
            "type":"Services"
        }
    ],
    "sg:phone":"+1 703 481 9115",
    "sg:postcode":"20190",
    "sg:province":"VA",
    "sg:tags":[
        "establishment"
    ],
    "wof:name":"Crevits & Crevits",
    "wof:placetype":"venue"
},
  "geometry": {"coordinates":[-77.343322,38.966557],"type":"Point"}
}