{
  "type": "Feature",
  "properties": {
    "addr:full":"12723 Jefferson Ave Newport News VA 23602",
    "addr:housenumber":"12723",
    "addr:postcode":"23602",
    "addr:street":"Jefferson Ave",
    "iso:country":"US",
    "sg:address":"12723 Jefferson Ave",
    "sg:city":"Newport News",
    "sg:classifiers":[
        {
            "category":"Home & Garden",
            "subcategory":"Furniture",
            "type":"Retail Goods"
        },
        {
            "category":"Professional",
            "subcategory":"Computer Services",
            "type":"Services"
        }
    ],
    "sg:phone":"+1 757 877 4400",
    "sg:postcode":"23602",
    "sg:province":"VA",
    "sg:tags":[
        "co"
    ],
    "wof:name":"Freedom Furniture & Electronic",
    "wof:placetype":"venue"
},
  "geometry": {"coordinates":[-76.51333099999999,37.129585],"type":"Point"}
}