{
  "type": "Feature",
  "properties": {
    "addr:full":"1857 Varsity Dr Chesapeake VA 23324",
    "addr:housenumber":"1857",
    "addr:postcode":"23324",
    "addr:street":"Varsity Dr",
    "iso:country":"US",
    "sg:address":"1857 Varsity Dr",
    "sg:city":"Chesapeake",
    "sg:classifiers":[
        {
            "category":"Education",
            "subcategory":"School",
            "type":"Public Place"
        }
    ],
    "sg:phone":"+1 757 494 7555",
    "sg:postcode":"23324",
    "sg:province":"VA",
    "wof:name":"Portlock Elementary School",
    "wof:placetype":"venue"
},
  "geometry": {"coordinates":[-76.271607,36.788629],"type":"Point"}
}