{
  "type": "Feature",
  "properties": {
    "iso:country":"US",
    "sg:address":"6603 Holland Rd",
    "sg:city":"Suffolk",
    "sg:classifiers":[
        {
            "category":"Organizations",
            "subcategory":"Professional Association",
            "type":"Services"
        }
    ],
    "sg:phone":"+1 757 657 6300",
    "sg:postcode":"23437",
    "sg:province":"VA",
    "wof:name":"Virginia Auctioneers Assn",
    "wof:placetype":"venue"
},
  "geometry": {"coordinates":[-76.778919,36.681813],"type":"Point"}
}