{
  "type": "Feature",
  "properties": {
    "iso:country":"US",
    "sg:address":"830 Dolley Madison Blvd",
    "sg:city":"McLean",
    "sg:classifiers":[
        {
            "category":"Sports & Exercise",
            "subcategory":"Stables",
            "type":"Entertainment"
        }
    ],
    "sg:phone":"+1 571 259 2321",
    "sg:postcode":"22101",
    "sg:province":"VA",
    "sg:tags":[
        "riding",
        "horseback"
    ],
    "sg:website":"www.somersetfarm411.com",
    "wof:name":"Somerset Farm",
    "wof:placetype":"venue"
},
  "geometry": {"coordinates":[-77.13751999999999,38.941462],"type":"Point"}
}