{
  "type": "Feature",
  "properties": {
    "addr:full":"200 Thompson Ave Fredericksburg VA 22405",
    "addr:housenumber":"200",
    "addr:postcode":"22405",
    "addr:street":"Thompson Ave",
    "iso:country":"US",
    "sg:address":"200 Thompson Ave",
    "sg:city":"Fredericksburg",
    "sg:classifiers":[
        {
            "category":"Building & Trades",
            "subcategory":"Construction",
            "type":"Services"
        }
    ],
    "sg:phone":"+1 540 373 2463",
    "sg:postcode":"22405",
    "sg:province":"VA",
    "sg:tags":[
        "roofing",
        "contractor"
    ],
    "wof:name":"Kevin Parker Roofing",
    "wof:placetype":"venue"
},
  "geometry": {"coordinates":[-77.44957599999999,38.31361],"type":"Point"}
}