{
  "type": "Feature",
  "properties": {
    "addr:full":"5832 Mapledale Plz Woodbridge VA 22193",
    "addr:housenumber":"5832",
    "addr:postcode":"22193",
    "addr:street":"Mapledale Plz",
    "iso:country":"US",
    "sg:address":"5832 Mapledale Plz",
    "sg:city":"Woodbridge",
    "sg:classifiers":[
        {
            "category":"Restaurant",
            "type":"Food & Drink"
        }
    ],
    "sg:phone":"+1 703 583 1818",
    "sg:postcode":"22193",
    "sg:province":"VA",
    "sg:tags":[
        "eating"
    ],
    "wof:name":"I Like It Black Ent LLC",
    "wof:placetype":"venue"
},
  "geometry": {"coordinates":[-77.367806,38.660292],"type":"Point"}
}