{
  "type": "Feature",
  "properties": {
    "addr:full":"5131 10th Rd N Arlington VA 22205",
    "addr:housenumber":"5131",
    "addr:postcode":"22205",
    "addr:street":"10Th Rd N",
    "iso:country":"US",
    "sg:address":"5131 10th Rd N",
    "sg:city":"Arlington",
    "sg:classifiers":[
        {
            "category":"Real Estate",
            "subcategory":"Real Estate Operator",
            "type":"Services"
        }
    ],
    "sg:phone":"+1 703 527 3377",
    "sg:postcode":"22205",
    "sg:province":"VA",
    "sg:tags":[
        "apartment"
    ],
    "wof:name":"Manor Court Apartments",
    "wof:placetype":"venue"
},
  "geometry": {"coordinates":[-77.12554799999999,38.882481],"type":"Point"}
}