{
  "type": "Feature",
  "properties": {
    "addr:full":"7425 Bell Creek Rd Mechanicsville VA 23111",
    "addr:housenumber":"7425",
    "addr:postcode":"23111",
    "addr:street":"Bell Creek Rd",
    "iso:country":"US",
    "sg:address":"7425 Bell Creek Rd",
    "sg:city":"Mechanicsville",
    "sg:classifiers":[
        {
            "category":"Restaurant",
            "type":"Food & Drink"
        }
    ],
    "sg:menulink":"http://www.allmenus.com/va/mechanicsville/32654-ruby-tuesdays/menu/",
    "sg:phone":"+1 804 559 3050",
    "sg:postcode":"23111",
    "sg:province":"VA",
    "sg:tags":[
        "burger",
        "american"
    ],
    "wof:name":"Ruby Tuesdays",
    "wof:placetype":"venue"
},
  "geometry": {"coordinates":[-77.354657,37.611501],"type":"Point"}
}