{
  "type": "Feature",
  "properties": {
    "addr:full":"19255 Pleasant View Dr Abingdon VA 24211",
    "addr:housenumber":"19255",
    "addr:postcode":"24211",
    "addr:street":"Pleasant View Dr",
    "iso:country":"US",
    "sg:address":"19255 Pleasant View Dr",
    "sg:city":"Abingdon",
    "sg:classifiers":[
        {
            "category":"Building & Trades",
            "subcategory":"Construction",
            "type":"Services"
        }
    ],
    "sg:phone":"+1 276 628 6865",
    "sg:postcode":"24211",
    "sg:province":"VA",
    "sg:tags":[
        "house"
    ],
    "wof:name":"Beverly Builders Inc",
    "wof:placetype":"venue"
},
  "geometry": {"coordinates":[-82.021647,36.680591],"type":"Point"}
}