{
  "type": "Feature",
  "properties": {
    "iso:country":"US",
    "sg:address":"1931 S Langley St",
    "sg:city":"Arlington",
    "sg:classifiers":[
        {
            "category":"Manufacturing",
            "subcategory":"Buildings",
            "type":"Manufacturing & Wholesale Goods"
        },
        {
            "category":"Building & Trades",
            "subcategory":"Construction",
            "type":"Services"
        }
    ],
    "sg:phone":"+1 703 892 1363",
    "sg:postcode":"22204",
    "sg:province":"VA",
    "sg:tags":[
        "home",
        "builder",
        "estimate",
        "contractor"
    ],
    "wof:name":"Gl Construction Inc",
    "wof:placetype":"venue"
},
  "geometry": {"coordinates":[-77.088632,38.853076],"type":"Point"}
}