{
  "type": "Feature",
  "properties": {
    "addr:full":"8318 Halesworth Rd Richmond VA 23235",
    "addr:housenumber":"8318",
    "addr:postcode":"23235",
    "addr:street":"Halesworth Rd",
    "iso:country":"US",
    "sg:address":"8318 Halesworth Rd",
    "sg:city":"Richmond",
    "sg:classifiers":[
        {
            "category":"Personal",
            "type":"Services"
        }
    ],
    "sg:phone":"+1 804 320 8367",
    "sg:postcode":"23235",
    "sg:province":"VA",
    "sg:tags":[
        "miscellaneous"
    ],
    "wof:name":"Mutual Endeavors Of Richmond",
    "wof:placetype":"venue"
},
  "geometry": {"coordinates":[-77.548192,37.551803],"type":"Point"}
}