{
  "type": "Feature",
  "properties": {
    "iso:country":"US",
    "sg:address":"7123 Richland Dr",
    "sg:city":"Lynchburg",
    "sg:classifiers":[
        {
            "category":"Professional",
            "type":"Services"
        }
    ],
    "sg:phone":"+1 434 237 3887",
    "sg:postcode":"24502",
    "sg:province":"VA",
    "wof:name":"Tweedy Mentoring Services LLC",
    "wof:placetype":"venue"
},
  "geometry": {"coordinates":[-79.21914599999999,37.363484],"type":"Point"}
}