{
  "type": "Feature",
  "properties": {
    "addr:full":"5720 Sellger Dr Norfolk VA 23502",
    "addr:housenumber":"5720",
    "addr:postcode":"23502",
    "addr:street":"Sellger Dr",
    "iso:country":"US",
    "sg:address":"5720 Sellger Dr",
    "sg:city":"Norfolk",
    "sg:classifiers":[
        {
            "category":"Restaurant",
            "type":"Food & Drink"
        }
    ],
    "sg:phone":"+1 757 466 7647",
    "sg:postcode":"23502",
    "sg:province":"VA",
    "sg:tags":[
        "eating"
    ],
    "wof:name":"Lunch Box",
    "wof:placetype":"venue"
},
  "geometry": {"coordinates":[-76.207325,36.838749],"type":"Point"}
}