{
  "type": "Feature",
  "properties": {
    "iso:country":"US",
    "sg:address":"1028 Richmond Ave",
    "sg:city":"Staunton",
    "sg:classifiers":[
        {
            "category":"Restaurant",
            "type":"Food & Drink"
        }
    ],
    "sg:menulink":"http://www.allmenus.com/va/staunton/187895-mcdonalds/menu/",
    "sg:postcode":"24401",
    "sg:province":"VA",
    "sg:tags":[
        "burger",
        "american"
    ],
    "wof:name":"McDonald's",
    "wof:placetype":"venue"
},
  "geometry": {"coordinates":[-79.04616300000001,38.137171],"type":"Point"}
}