{
  "type": "Feature",
  "properties": {
    "iso:country":"US",
    "sg:address":"4655 Sir Gilbert Loop",
    "sg:city":"Williamsburg",
    "sg:classifiers":[
        {
            "category":"Professional",
            "subcategory":"Computer Services",
            "type":"Services"
        }
    ],
    "sg:phone":"+1 757 345 0088",
    "sg:postcode":"23185",
    "sg:province":"VA",
    "sg:tags":[
        "consultant",
        "designer",
        "system"
    ],
    "wof:name":"Camcor Technical Services Inc.",
    "wof:placetype":"venue"
},
  "geometry": {"coordinates":[-76.776994,37.238084],"type":"Point"}
}