{
  "type": "Feature",
  "properties": {
    "addr:full":"1110 Davis Ln Halifax VA 24558",
    "addr:housenumber":"1110",
    "addr:postcode":"24558",
    "addr:street":"Davis Ln",
    "iso:country":"US",
    "sg:address":"1110 Davis Ln",
    "sg:city":"Halifax",
    "sg:classifiers":[
        {
            "category":"Wholesale",
            "subcategory":"Electrical",
            "type":"Manufacturing & Wholesale Goods"
        }
    ],
    "sg:phone":"+1 434 572 4899",
    "sg:postcode":"24558",
    "sg:province":"VA",
    "sg:tags":[
        "alarm",
        "burglar",
        "system"
    ],
    "wof:name":"Southside Security Systems",
    "wof:placetype":"venue"
},
  "geometry": {"coordinates":[-78.943781,36.807229],"type":"Point"}
}