{
  "type": "Feature",
  "properties": {
    "iso:country":"US",
    "sg:address":"664 Phoenix Dr",
    "sg:city":"Virginia Beach",
    "sg:classifiers":[
        {
            "category":"Shopping",
            "subcategory":"Shoes",
            "type":"Retail Goods"
        }
    ],
    "sg:phone":"+1 757 340 4838",
    "sg:postcode":"23452",
    "sg:province":"VA",
    "wof:name":"Off Broadway",
    "wof:placetype":"venue"
},
  "geometry": {"coordinates":[-76.068442,36.826922],"type":"Point"}
}