{
  "type": "Feature",
  "properties": {
    "addr:full":"4328 Taney Ave Alexandria VA 22304",
    "addr:housenumber":"4328",
    "addr:postcode":"22304",
    "addr:street":"Taney Ave",
    "iso:country":"US",
    "sg:address":"4328 Taney Ave",
    "sg:city":"Alexandria",
    "sg:classifiers":[
        {
            "category":"Building & Trades",
            "subcategory":"Cleaning & Sanitation",
            "type":"Services"
        }
    ],
    "sg:phone":"+1 703 212 0613",
    "sg:postcode":"22304",
    "sg:province":"VA",
    "sg:tags":[
        "house"
    ],
    "wof:name":"Marshalls Maid Svc",
    "wof:placetype":"venue"
},
  "geometry": {"coordinates":[-77.10574200000001,38.814875],"type":"Point"}
}