{
  "type": "Feature",
  "properties": {
    "addr:full":"1420 George Washington Hwy N Chesapeake VA 23323",
    "addr:housenumber":"1420",
    "addr:postcode":"23323",
    "addr:street":"George Washington Hwy N",
    "iso:country":"US",
    "sg:address":"1420 George Washington Hwy N",
    "sg:city":"Chesapeake",
    "sg:classifiers":[
        {
            "category":"Restaurant",
            "type":"Food & Drink"
        }
    ],
    "sg:phone":"+1 757 487 8565",
    "sg:postcode":"23323",
    "sg:province":"VA",
    "wof:name":"Victory Snack Bar",
    "wof:placetype":"venue"
},
  "geometry": {"coordinates":[-76.329928,36.791469],"type":"Point"}
}