{
  "type": "Feature",
  "properties": {
    "addr:full":"500 Le Gordon Dr Midlothian VA 23114",
    "addr:housenumber":"500",
    "addr:postcode":"23114",
    "addr:street":"Le Gordon Dr",
    "iso:country":"US",
    "sg:address":"500 Le Gordon Dr",
    "sg:city":"Midlothian",
    "sg:classifiers":[
        {
            "category":"Organizations",
            "subcategory":"Religious Organization",
            "type":"Services"
        }
    ],
    "sg:phone":"+1 804 379 2551",
    "sg:postcode":"23114",
    "sg:province":"VA",
    "sg:tags":[
        "church"
    ],
    "sg:website":"www.kingsway.cc",
    "wof:name":"Kings Way Community Church",
    "wof:placetype":"venue"
},
  "geometry": {"coordinates":[-77.662598,37.503448],"type":"Point"}
}