{
  "type": "Feature",
  "properties": {
    "addr:full":"1803 W 3rd St Farmville VA 23901",
    "addr:housenumber":"1803",
    "addr:postcode":"23901",
    "addr:street":"W 3Rd St",
    "iso:country":"US",
    "sg:address":"1803 W 3rd St",
    "sg:city":"Farmville",
    "sg:classifiers":[
        {
            "category":"Wholesale",
            "subcategory":"Machinery & Supplies",
            "type":"Manufacturing & Wholesale Goods"
        }
    ],
    "sg:phone":"+1 434 392 3141",
    "sg:postcode":"23901",
    "sg:province":"VA",
    "sg:tags":[
        "equipment",
        "irrigation",
        "system"
    ],
    "sg:website":"www.irrigationparts.com",
    "wof:name":"Mid-Atlantic Irrigation",
    "wof:placetype":"venue"
},
  "geometry": {"coordinates":[-78.416797,37.307809],"type":"Point"}
}