{
  "type": "Feature",
  "properties": {
    "addr:full":"4807 Kempair Dr Woodbridge VA 22193",
    "addr:housenumber":"4807",
    "addr:postcode":"22193",
    "addr:street":"Kempair Dr",
    "iso:country":"US",
    "sg:address":"4807 Kempair Dr",
    "sg:city":"Woodbridge",
    "sg:classifiers":[
        {
            "category":"Shopping",
            "subcategory":"Hobbies, Toys, & Games",
            "type":"Retail Goods"
        }
    ],
    "sg:phone":"+1 703 680 4532",
    "sg:postcode":"22193",
    "sg:province":"VA",
    "sg:tags":[
        "craft"
    ],
    "wof:name":"Katherine Kollection",
    "wof:placetype":"venue"
},
  "geometry": {"coordinates":[-77.34764199999999,38.658924],"type":"Point"}
}