{
  "type": "Feature",
  "properties": {
    "addr:full":"7997 Wellingford Dr Manassas VA 20109",
    "addr:housenumber":"7997",
    "addr:postcode":"20109",
    "addr:street":"Wellingford Dr",
    "iso:country":"US",
    "sg:address":"7997 Wellingford Dr",
    "sg:city":"Manassas",
    "sg:classifiers":[
        {
            "category":"Manufacturing",
            "subcategory":"Signs",
            "type":"Manufacturing & Wholesale Goods"
        }
    ],
    "sg:phone":"+1 703 368 5578",
    "sg:postcode":"20109",
    "sg:province":"VA",
    "sg:tags":[
        "manufacture",
        "art",
        "design",
        "commercial"
    ],
    "sg:website":"www.graphicservicesinc.com",
    "wof:name":"Graphics Services Inc",
    "wof:placetype":"venue"
},
  "geometry": {"coordinates":[-77.555542,38.784135],"type":"Point"}
}