{
  "type": "Feature",
  "properties": {
    "iso:country":"US",
    "sg:address":"3441 Brandon Ave SW",
    "sg:city":"Roanoke",
    "sg:classifiers":[
        {
            "category":"Wholesale",
            "subcategory":"Plants",
            "type":"Manufacturing & Wholesale Goods"
        }
    ],
    "sg:phone":"+1 540 343 4461",
    "sg:postcode":"24018",
    "sg:province":"VA",
    "sg:tags":[
        "florist"
    ],
    "wof:name":"TFS Roanoke Inc",
    "wof:placetype":"venue"
},
  "geometry": {"coordinates":[-80.004215,37.264017],"type":"Point"}
}