{
  "type": "Feature",
  "properties": {
    "addr:full":"1518 Longview Dr Bassett VA 24055",
    "addr:housenumber":"1518",
    "addr:postcode":"24055",
    "addr:street":"Longview Dr",
    "iso:country":"US",
    "sg:address":"1518 Longview Dr",
    "sg:city":"Bassett",
    "sg:classifiers":[
        {
            "category":"Banks & Credit Unions",
            "subcategory":"Investment Brokerage",
            "type":"Services"
        }
    ],
    "sg:phone":"+1 276 629 5048",
    "sg:postcode":"24055",
    "sg:province":"VA",
    "wof:name":"Southern Investments LLC",
    "wof:placetype":"venue"
},
  "geometry": {"coordinates":[-80.042992,36.751597],"type":"Point"}
}