{
  "type": "Feature",
  "properties": {
    "addr:full":"6117 Dorchester St Springfield VA 22150",
    "addr:housenumber":"6117",
    "addr:postcode":"22150",
    "addr:street":"Dorchester St",
    "iso:country":"US",
    "sg:address":"6117 Dorchester St",
    "sg:city":"Springfield",
    "sg:classifiers":[
        {
            "category":"Manufacturing",
            "subcategory":"Motor Vehicles & Parts",
            "type":"Manufacturing & Wholesale Goods"
        }
    ],
    "sg:phone":"+1 703 451 5582",
    "sg:postcode":"22150",
    "sg:province":"VA",
    "sg:tags":[
        "repair",
        "mfg"
    ],
    "sg:website":"www.filzbuilt.com",
    "wof:name":"Filz Built Bicycles",
    "wof:placetype":"venue"
},
  "geometry": {"coordinates":[-77.18335500000001,38.784975],"type":"Point"}
}