{
  "type": "Feature",
  "properties": {
    "iso:country":"US",
    "sg:address":"5220 Germain Rd",
    "sg:city":"Richmond",
    "sg:classifiers":[
        {
            "category":"Manufacturing",
            "subcategory":"Printing",
            "type":"Manufacturing & Wholesale Goods"
        }
    ],
    "sg:phone":"+1 804 232 6999",
    "sg:postcode":"23224",
    "sg:province":"VA",
    "sg:tags":[
        "publishing"
    ],
    "wof:name":"Jireh Press",
    "wof:placetype":"venue"
},
  "geometry": {"coordinates":[-77.487717,37.482977],"type":"Point"}
}