{
  "type": "Feature",
  "properties": {
    "addr:full":"4614 Linmar Ct Alexandria VA 22312",
    "addr:housenumber":"4614",
    "addr:postcode":"22312",
    "addr:street":"Linmar Ct",
    "iso:country":"US",
    "sg:address":"4614 Linmar Ct",
    "sg:city":"Alexandria",
    "sg:classifiers":[
        {
            "category":"Retail",
            "subcategory":"Portrait Studio",
            "type":"Services"
        },
        {
            "category":"Professional",
            "subcategory":"Art Services",
            "type":"Services"
        }
    ],
    "sg:phone":"+1 703 941 8270",
    "sg:postcode":"22312",
    "sg:province":"VA",
    "sg:tags":[
        "rental",
        "photographers-portrait",
        "photographic",
        "darkroom"
    ],
    "wof:name":"Tessmer Of Fairfax",
    "wof:placetype":"venue"
},
  "geometry": {"coordinates":[-77.14583,38.824668],"type":"Point"}
}