{
  "type": "Feature",
  "properties": {
    "addr:full":"3434 Buck Mountain Rd Roanoke VA 24018",
    "addr:housenumber":"3434",
    "addr:postcode":"24018",
    "addr:street":"Buck Mountain Rd",
    "iso:country":"US",
    "sg:address":"3434 Buck Mountain Rd",
    "sg:city":"Roanoke",
    "sg:classifiers":[
        {
            "category":"Wholesale",
            "subcategory":"Sporting Goods",
            "type":"Manufacturing & Wholesale Goods"
        }
    ],
    "sg:phone":"+1 540 774 8890",
    "sg:postcode":"24018",
    "sg:province":"VA",
    "sg:tags":[
        "b",
        "merchandise"
    ],
    "wof:name":"Hot Tub Heaven Inc",
    "wof:placetype":"venue"
},
  "geometry": {"coordinates":[-79.95489000000001,37.205329],"type":"Point"}
}