{
  "type": "Feature",
  "properties": {
    "iso:country":"US",
    "sg:address":"238 Post Rd",
    "sg:city":"Roanoke",
    "sg:classifiers":[
        {
            "category":"Building & Trades",
            "subcategory":"Construction",
            "type":"Services"
        }
    ],
    "sg:phone":"+1 540 366 4310",
    "sg:postcode":"24019",
    "sg:province":"VA",
    "sg:tags":[
        "painter"
    ],
    "wof:name":"John D Benois",
    "wof:placetype":"venue"
},
  "geometry": {"coordinates":[-79.95838000000001,37.347355],"type":"Point"}
}