{
  "type": "Feature",
  "properties": {
    "addr:full":"99 Joy Ranch Rd Woodlawn VA 24381",
    "addr:housenumber":"99",
    "addr:postcode":"24381",
    "addr:street":"Joy Ranch Rd",
    "iso:country":"US",
    "sg:address":"99 Joy Ranch Rd",
    "sg:city":"Woodlawn",
    "sg:classifiers":[
        {
            "category":"Organizations",
            "subcategory":"Religious Organization",
            "type":"Services"
        }
    ],
    "sg:phone":"+1 276 236 7814",
    "sg:postcode":"24381",
    "sg:province":"VA",
    "sg:tags":[
        "church"
    ],
    "wof:name":"St Joseph's Catholic Church",
    "wof:placetype":"venue"
},
  "geometry": {"coordinates":[-80.79869600000001,36.73224],"type":"Point"}
}