{
  "type": "Feature",
  "properties": {
    "addr:full":"2020 Regatta Cir Virginia Beach VA 23454",
    "addr:housenumber":"2020",
    "addr:postcode":"23454",
    "addr:street":"Regatta Cir",
    "iso:country":"US",
    "sg:address":"2020 Regatta Cir",
    "sg:city":"Virginia Beach",
    "sg:classifiers":[
        {
            "category":"Professional",
            "type":"Services"
        }
    ],
    "sg:phone":"+1 757 481 3277",
    "sg:postcode":"23454",
    "sg:province":"VA",
    "sg:tags":[
        "establishment"
    ],
    "wof:name":"Jacque Duncan Inc",
    "wof:placetype":"venue"
},
  "geometry": {"coordinates":[-76.035881,36.863155],"type":"Point"}
}