{
  "type": "Feature",
  "properties": {
    "iso:country":"US",
    "sg:address":"11400 W Huguenot Rd",
    "sg:city":"Midlothian",
    "sg:classifiers":[
        {
            "category":"Food & Beverages",
            "subcategory":"Groceries & Convenience Stores",
            "type":"Retail Goods"
        }
    ],
    "sg:phone":"+1 804 379 2496",
    "sg:postcode":"23113",
    "sg:province":"VA",
    "sg:tags":[
        "drug"
    ],
    "wof:name":"Hannaford Bros Co",
    "wof:placetype":"venue"
},
  "geometry": {"coordinates":[-77.60713699999999,37.523913],"type":"Point"}
}