{
  "type": "Feature",
  "properties": {
    "addr:full":"592 Craddock Ln Stuart VA 24171",
    "addr:housenumber":"592",
    "addr:postcode":"24171",
    "addr:street":"Craddock Ln",
    "iso:country":"US",
    "sg:address":"592 Craddock Ln",
    "sg:city":"Stuart",
    "sg:classifiers":[
        {
            "category":"Farming",
            "subcategory":"Livestock Farm",
            "type":"Manufacturing & Wholesale Goods"
        }
    ],
    "sg:phone":"+1 276 694 7359",
    "sg:postcode":"24171",
    "sg:province":"VA",
    "sg:tags":[
        "beef",
        "feedlot",
        "cattle"
    ],
    "wof:name":"Lincoln Craddock Farm",
    "wof:placetype":"venue"
},
  "geometry": {"coordinates":[-80.198301,36.550304],"type":"Point"}
}