{
  "type": "Feature",
  "properties": {
    "addr:full":"1515 Forest Meadow Ln Manakin Sabot VA 23103",
    "addr:housenumber":"1515",
    "addr:postcode":"23103",
    "addr:street":"Forest Meadow Ln",
    "iso:country":"US",
    "sg:address":"1515 Forest Meadow Ln",
    "sg:city":"Manakin Sabot",
    "sg:classifiers":[
        {
            "category":"Building & Trades",
            "subcategory":"Construction",
            "type":"Services"
        }
    ],
    "sg:phone":"+1 804 784 4158",
    "sg:postcode":"23103",
    "sg:province":"VA",
    "sg:tags":[
        "residential",
        "contractor"
    ],
    "wof:name":"Quality Builders of Virginia",
    "wof:placetype":"venue"
},
  "geometry": {"coordinates":[-77.69245100000001,37.663752],"type":"Point"}
}