{
  "type": "Feature",
  "properties": {
    "addr:full":"1080 Piney Forest Rd Danville VA 24540",
    "addr:housenumber":"1080",
    "addr:postcode":"24540",
    "addr:street":"Piney Forest Rd",
    "iso:country":"US",
    "sg:address":"1080 Piney Forest Rd",
    "sg:city":"Danville",
    "sg:classifiers":[
        {
            "category":"Shopping",
            "subcategory":"Jewelry",
            "type":"Retail Goods"
        }
    ],
    "sg:phone":"+1 434 799 9510",
    "sg:postcode":"24540",
    "sg:province":"VA",
    "wof:name":"Forest Piney Jewelry Inc",
    "wof:placetype":"venue"
},
  "geometry": {"coordinates":[-79.404568,36.62209],"type":"Point"}
}