{
  "type": "Feature",
  "properties": {
    "addr:full":"7315 Golden Iris Ct Springfield VA 22153",
    "addr:housenumber":"7315",
    "addr:postcode":"22153",
    "addr:street":"Golden Iris Ct",
    "iso:country":"US",
    "sg:address":"7315 Golden Iris Ct",
    "sg:city":"Springfield",
    "sg:classifiers":[
        {
            "category":"Professional",
            "subcategory":"Management & Consulting",
            "type":"Services"
        }
    ],
    "sg:phone":"+1 703 644 0886",
    "sg:postcode":"22153",
    "sg:province":"VA",
    "sg:tags":[
        "general"
    ],
    "wof:name":"Gary N Easton",
    "wof:placetype":"venue"
},
  "geometry": {"coordinates":[-77.255168,38.757548],"type":"Point"}
}