{
  "type": "Feature",
  "properties": {
    "addr:full":"22473 Tally Ho Dr Carrollton VA 23314",
    "addr:housenumber":"22473",
    "addr:postcode":"23314",
    "addr:street":"Tally Ho Dr",
    "iso:country":"US",
    "sg:address":"22473 Tally Ho Dr",
    "sg:city":"Carrollton",
    "sg:classifiers":[
        {
            "category":"Building & Trades",
            "subcategory":"Construction",
            "type":"Services"
        }
    ],
    "sg:phone":"+1 757 357 3042",
    "sg:postcode":"23314",
    "sg:province":"VA",
    "sg:tags":[
        "contracting",
        "general"
    ],
    "wof:name":"Ashett Construction LLC",
    "wof:placetype":"venue"
},
  "geometry": {"coordinates":[-76.544428,36.989155],"type":"Point"}
}