{
  "type": "Feature",
  "properties": {
    "iso:country":"US",
    "sg:address":"310 E Virginia Ave",
    "sg:city":"Vinton",
    "sg:classifiers":[
        {
            "category":"Shopping",
            "subcategory":"Used Merchandise",
            "type":"Retail Goods"
        }
    ],
    "sg:phone":"+1 540 345 7818",
    "sg:postcode":"24179",
    "sg:province":"VA",
    "sg:tags":[
        "pawnbroker"
    ],
    "wof:name":"Vinton Pawn Shop Inc",
    "wof:placetype":"venue"
},
  "geometry": {"coordinates":[-79.896141,37.275113],"type":"Point"}
}