{
  "type": "Feature",
  "properties": {
    "iso:country":"US",
    "sg:address":"1710 Maxwell Ct",
    "sg:city":"McLean",
    "sg:classifiers":[
        {
            "category":"Building & Trades",
            "subcategory":"Locksmith",
            "type":"Services"
        }
    ],
    "sg:phone":"+1 202 621 2256",
    "sg:postcode":"22101",
    "sg:province":"VA",
    "sg:tags":[
        "key"
    ],
    "wof:name":"Associate Locksmith",
    "wof:placetype":"venue"
},
  "geometry": {"coordinates":[-77.182956,38.919876],"type":"Point"}
}