{
  "type": "Feature",
  "properties": {
    "iso:country":"US",
    "sg:address":"2060 River Pearl Way",
    "sg:city":"Chesapeake",
    "sg:classifiers":[
        {
            "category":"Shopping",
            "subcategory":"Luggage & Leather Goods",
            "type":"Retail Goods"
        }
    ],
    "sg:phone":"+1 757 465 6215",
    "sg:postcode":"23321",
    "sg:province":"VA",
    "wof:name":"Bound 2 Please",
    "wof:placetype":"venue"
},
  "geometry": {"coordinates":[-76.42667899999999,36.815042],"type":"Point"}
}