{
  "type": "Feature",
  "properties": {
    "addr:full":"1800 E Main St Waynesboro VA 22980",
    "addr:housenumber":"1800",
    "addr:postcode":"22980",
    "addr:street":"E Main St",
    "iso:country":"US",
    "sg:address":"1800 E Main St",
    "sg:city":"Waynesboro",
    "sg:classifiers":[
        {
            "category":"Autos & Motor Vehicles",
            "subcategory":"Automobile Sales",
            "type":"Retail Goods"
        }
    ],
    "sg:phone":"+1 540 941 8408",
    "sg:postcode":"22980",
    "sg:province":"VA",
    "sg:tags":[
        "car",
        "used",
        "dealer"
    ],
    "wof:name":"Bradley's Used Cars",
    "wof:placetype":"venue"
},
  "geometry": {"coordinates":[-78.86900799999999,38.053178],"type":"Point"}
}