{
  "type": "Feature",
  "properties": {
    "addr:full":"1427 University Avenue Charlottesville VA 22903",
    "addr:housenumber":"1427",
    "addr:postcode":"22903",
    "addr:street":"University Avenue",
    "iso:country":"US",
    "sg:address":"1427 University Avenue",
    "sg:city":"Charlottesville",
    "sg:classifiers":[
        {
            "category":"Bars & Pubs",
            "type":"Food & Drink"
        },
        {
            "category":"Restaurant",
            "type":"Food & Drink"
        }
    ],
    "sg:phone":"+1 434 977 3697",
    "sg:postcode":"22903",
    "sg:province":"VA",
    "sg:tags":[
        "traditional",
        "american"
    ],
    "wof:name":"Michael's Bistro and Tap House",
    "wof:placetype":"venue"
},
  "geometry": {"coordinates":[-78.49960299999999,38.034199],"type":"Point"}
}