{
  "type": "Feature",
  "properties": {
    "addr:full":"3317 Greenwood Dr Hampton VA 23666",
    "addr:housenumber":"3317",
    "addr:postcode":"23666",
    "addr:street":"Greenwood Dr",
    "iso:country":"US",
    "sg:address":"3317 Greenwood Dr",
    "sg:city":"Hampton",
    "sg:classifiers":[
        {
            "category":"Building & Trades",
            "subcategory":"Landscaping Services",
            "type":"Services"
        }
    ],
    "sg:phone":"+1 757 838 0429",
    "sg:postcode":"23666",
    "sg:province":"VA",
    "sg:tags":[
        "landscape"
    ],
    "wof:name":"Jakes Services Inc",
    "wof:placetype":"venue"
},
  "geometry": {"coordinates":[-76.416877,37.03075],"type":"Point"}
}