{
  "type": "Feature",
  "properties": {
    "iso:country":"US",
    "sg:address":"19848 James River Dr",
    "sg:city":"Spring Grove",
    "sg:classifiers":[
        {
            "category":"Building & Trades",
            "subcategory":"Construction",
            "type":"Services"
        }
    ],
    "sg:phone":"+1 804 943 3443",
    "sg:postcode":"23881",
    "sg:province":"VA",
    "sg:tags":[
        "home",
        "improvement"
    ],
    "wof:name":"C & T Contractors Inc",
    "wof:placetype":"venue"
},
  "geometry": {"coordinates":[-77.055841,37.20519],"type":"Point"}
}