{
  "type": "Feature",
  "properties": {
    "iso:country":"US",
    "sg:address":"1075 W Broad St",
    "sg:city":"Falls Church",
    "sg:classifiers":[
        {
            "category":"Building & Trades",
            "subcategory":"Construction",
            "type":"Services"
        }
    ],
    "sg:phone":"+1 703 532 0225",
    "sg:postcode":"22046",
    "sg:province":"VA",
    "sg:tags":[
        "flooring",
        "contractor"
    ],
    "wof:name":"M & M Floors Inc",
    "wof:placetype":"venue"
},
  "geometry": {"coordinates":[-77.185968,38.891812],"type":"Point"}
}