{
  "type": "Feature",
  "properties": {
    "addr:full":"209 Washburn Dr Danville VA 24541",
    "addr:housenumber":"209",
    "addr:postcode":"24541",
    "addr:street":"Washburn Dr",
    "iso:country":"US",
    "sg:address":"209 Washburn Dr",
    "sg:city":"Danville",
    "sg:classifiers":[
        {
            "category":"Retail",
            "subcategory":"Veterinary Services",
            "type":"Services"
        }
    ],
    "sg:phone":"+1 434 822 0020",
    "sg:postcode":"24541",
    "sg:province":"VA",
    "sg:tags":[
        "veterinarian"
    ],
    "wof:name":"Town & Country Veterinary Clnc",
    "wof:placetype":"venue"
},
  "geometry": {"coordinates":[-79.505031,36.573386],"type":"Point"}
}