{
  "type": "Feature",
  "properties": {
    "addr:full":"1241 Volunteer Pkwy Bristol VA 37620",
    "addr:housenumber":"1241",
    "addr:postcode":"37620",
    "addr:street":"Volunteer Pkwy",
    "iso:country":"US",
    "sg:address":"1241 Volunteer Pkwy",
    "sg:city":"Bristol",
    "sg:classifiers":[
        {
            "category":"Health Services",
            "subcategory":"Clinic",
            "type":"Services"
        }
    ],
    "sg:phone":"+1 423 968 2004",
    "sg:postcode":"37620",
    "sg:province":"VA",
    "sg:tags":[
        "home",
        "care"
    ],
    "wof:name":"Amedisys Inc",
    "wof:placetype":"venue"
},
  "geometry": {"coordinates":[-82.202225,36.566136],"type":"Point"}
}