{
  "type": "Feature",
  "properties": {
    "addr:full":"1433 Battlefield Blvd N Chesapeake VA 23320",
    "addr:housenumber":"1433",
    "addr:postcode":"23320",
    "addr:street":"Battlefield Blvd N",
    "iso:country":"US",
    "sg:address":"1433 Battlefield Blvd N",
    "sg:city":"Chesapeake",
    "sg:classifiers":[
        {
            "category":"Travel",
            "subcategory":"Hotels & Motels",
            "type":"Entertainment"
        }
    ],
    "sg:phone":"+1 757 547 9262",
    "sg:postcode":"23320",
    "sg:province":"VA",
    "sg:tags":[
        "a",
        "operates"
    ],
    "sg:website":"www.daysinn.com",
    "wof:name":"Days Inn",
    "wof:placetype":"venue"
},
  "geometry": {"coordinates":[-76.25205,36.768225],"type":"Point"}
}