{
  "type": "Feature",
  "properties": {
    "iso:country":"US",
    "sg:address":"3409 Deep Creek Blvd",
    "sg:city":"Portsmouth",
    "sg:classifiers":[
        {
            "category":"Professional",
            "subcategory":"Business Services",
            "type":"Services"
        }
    ],
    "sg:phone":"+1 757 397 2010",
    "sg:postcode":"23702",
    "sg:province":"VA",
    "sg:tags":[
        "repossessing"
    ],
    "wof:name":"Wes Frye Auto & Van Repair",
    "wof:placetype":"venue"
},
  "geometry": {"coordinates":[-76.3288,36.813782],"type":"Point"}
}