{
  "type": "Feature",
  "properties": {
    "iso:country":"US",
    "sg:address":"1635 N George Mason Dr",
    "sg:city":"Arlington",
    "sg:classifiers":[
        {
            "category":"Professional",
            "subcategory":"Lawyer & Legal Services",
            "type":"Services"
        }
    ],
    "sg:phone":"+1 703 243 9000",
    "sg:postcode":"22205",
    "sg:province":"VA",
    "sg:tags":[
        "attorney"
    ],
    "wof:name":"Bruce Don Burtoff MD",
    "wof:placetype":"venue"
},
  "geometry": {"coordinates":[-77.128934,38.889955],"type":"Point"}
}