{
  "type": "Feature",
  "properties": {
    "addr:full":"14801 Willard Rd Chantilly VA 20151",
    "addr:housenumber":"14801",
    "addr:postcode":"20151",
    "addr:street":"Willard Rd",
    "iso:country":"US",
    "sg:address":"14801 Willard Rd",
    "sg:city":"Chantilly",
    "sg:classifiers":[
        {
            "category":"Building & Trades",
            "subcategory":"Construction",
            "type":"Services"
        }
    ],
    "sg:phone":"+1 703 263 1335",
    "sg:postcode":"20151",
    "sg:province":"VA",
    "sg:tags":[
        "house"
    ],
    "wof:name":"Stanley Martin Design Studio",
    "wof:placetype":"venue"
},
  "geometry": {"coordinates":[-77.463646,38.891194],"type":"Point"}
}