{
  "type": "Feature",
  "properties": {
    "addr:full":"1918 Sheppard Town Rd Crozier VA 23039",
    "addr:housenumber":"1918",
    "addr:postcode":"23039",
    "addr:street":"Sheppard Town Rd",
    "iso:country":"US",
    "sg:address":"1918 Sheppard Town Rd",
    "sg:city":"Crozier",
    "sg:classifiers":[
        {
            "category":"Utilities",
            "subcategory":"Telephone",
            "type":"Services"
        }
    ],
    "sg:phone":"+1 804 784 3707",
    "sg:postcode":"23039",
    "sg:province":"VA",
    "sg:tags":[
        "communications"
    ],
    "wof:name":"Indoff",
    "wof:placetype":"venue"
},
  "geometry": {"coordinates":[-77.81107799999999,37.684444],"type":"Point"}
}