{
  "type": "Feature",
  "properties": {
    "addr:full":"10649 Jacksons Way Port Republic VA 24471",
    "addr:housenumber":"10649",
    "addr:postcode":"24471",
    "addr:street":"Jacksons Way",
    "iso:country":"US",
    "sg:address":"10649 Jacksons Way",
    "sg:city":"Port Republic",
    "sg:classifiers":[
        {
            "category":"Wholesale",
            "subcategory":"Machinery & Supplies",
            "type":"Manufacturing & Wholesale Goods"
        },
        {
            "category":"Home & Garden",
            "subcategory":"Garden Supply",
            "type":"Retail Goods"
        }
    ],
    "sg:phone":"+1 540 249 4749",
    "sg:postcode":"24471",
    "sg:province":"VA",
    "sg:tags":[
        "equipment",
        "lawn",
        "industrial",
        "mower"
    ],
    "wof:name":"Sonny's Small Engine Repair",
    "wof:placetype":"venue"
},
  "geometry": {"coordinates":[-78.77831,38.296777],"type":"Point"}
}