{
  "type": "Feature",
  "properties": {
    "iso:country":"US",
    "sg:address":"7612 Rustle Ridge Ct",
    "sg:city":"Fairfax Station",
    "sg:classifiers":[
        {
            "category":"Food & Beverages",
            "subcategory":"Groceries & Convenience Stores",
            "type":"Retail Goods"
        }
    ],
    "sg:phone":"+1 703 912 9372",
    "sg:postcode":"22039",
    "sg:province":"VA",
    "wof:name":"Italian Deli 2 LLC",
    "wof:placetype":"venue"
},
  "geometry": {"coordinates":[-77.28211,38.750107],"type":"Point"}
}