{
  "type": "Feature",
  "properties": {
    "addr:full":"401 Albemarle Ave Roanoke VA 24013",
    "addr:housenumber":"401",
    "addr:postcode":"24013",
    "addr:street":"Albemarle Ave",
    "iso:country":"US",
    "sg:address":"401 Albemarle Ave",
    "sg:city":"Roanoke",
    "sg:classifiers":[
        {
            "category":"Manufacturing",
            "subcategory":"Tools & Machinery",
            "type":"Manufacturing & Wholesale Goods"
        }
    ],
    "sg:phone":"+1 540 777 7002",
    "sg:postcode":"24013",
    "sg:province":"VA",
    "sg:tags":[
        "machine",
        "shop"
    ],
    "wof:name":"S V Solutions",
    "wof:placetype":"venue"
},
  "geometry": {"coordinates":[-79.93729,37.262928],"type":"Point"}
}