{
  "type": "Feature",
  "properties": {
    "iso:country":"US",
    "sg:address":"11201 Old Washington Hwy",
    "sg:city":"Glen Allen",
    "sg:classifiers":[
        {
            "category":"Building & Trades",
            "subcategory":"Construction",
            "type":"Services"
        }
    ],
    "sg:phone":"+1 804 262 4910",
    "sg:postcode":"23059",
    "sg:province":"VA",
    "sg:tags":[
        "general",
        "contractor"
    ],
    "wof:name":"KODY Custom Builders",
    "wof:placetype":"venue"
},
  "geometry": {"coordinates":[-77.502686,37.677617],"type":"Point"}
}