{
  "type": "Feature",
  "properties": {
    "addr:full":"201 Gumwood Dr Hampton VA 23666",
    "addr:housenumber":"201",
    "addr:postcode":"23666",
    "addr:street":"Gumwood Dr",
    "iso:country":"US",
    "sg:address":"201 Gumwood Dr",
    "sg:city":"Hampton",
    "sg:classifiers":[
        {
            "category":"Health Services",
            "subcategory":"Doctor",
            "type":"Services"
        }
    ],
    "sg:phone":"+1 757 356 9228",
    "sg:postcode":"23666",
    "sg:province":"VA",
    "sg:tags":[
        "physician",
        "surgeon"
    ],
    "wof:name":"Family Medical Care-Smthfld",
    "wof:placetype":"venue"
},
  "geometry": {"coordinates":[-76.409824,37.028583],"type":"Point"}
}