{
  "type": "Feature",
  "properties": {
    "addr:full":"36 Catoctin Cir SE Leesburg VA 20175",
    "addr:housenumber":"36",
    "addr:postcode":"20175",
    "addr:street":"Catoctin Cir Se",
    "iso:country":"US",
    "sg:address":"36 Catoctin Cir SE",
    "sg:city":"Leesburg",
    "sg:classifiers":[
        {
            "category":"Health Services",
            "subcategory":"Doctor",
            "type":"Services"
        },
        {
            "category":"Health Services",
            "subcategory":"Chiropractor",
            "type":"Services"
        }
    ],
    "sg:phone":"+1 703 777 4840",
    "sg:postcode":"20175",
    "sg:province":"VA",
    "sg:tags":[
        "physician",
        "surgeon",
        "chiropractic"
    ],
    "wof:name":"Sampson Joshua M DR",
    "wof:placetype":"venue"
},
  "geometry": {"coordinates":[-77.56493399999999,39.106768],"type":"Point"}
}