{
  "type": "Feature",
  "properties": {
    "addr:full":"7488 US Hwy 15 Clarksville VA 23927",
    "addr:housenumber":"7488",
    "addr:postcode":"23927",
    "addr:street":"Us Hwy 15",
    "iso:country":"US",
    "sg:address":"7488 US Hwy 15",
    "sg:city":"Clarksville",
    "sg:classifiers":[
        {
            "category":"Organizations",
            "subcategory":"Community Association",
            "type":"Services"
        }
    ],
    "sg:phone":"+1 434 374 2666",
    "sg:postcode":"23927",
    "sg:province":"VA",
    "sg:tags":[
        "military"
    ],
    "wof:name":"Veterans Of Foreign Wars",
    "wof:placetype":"venue"
},
  "geometry": {"coordinates":[-78.547375,36.643792],"type":"Point"}
}