{
  "type": "Feature",
  "properties": {
    "addr:full":"3134 Harris St SW Roanoke VA 24015",
    "addr:housenumber":"3134",
    "addr:postcode":"24015",
    "addr:street":"Harris St Sw",
    "iso:country":"US",
    "sg:address":"3134 Harris St SW",
    "sg:city":"Roanoke",
    "sg:classifiers":[
        {
            "category":"Recreation",
            "type":"Entertainment"
        }
    ],
    "sg:phone":"+1 540 774 9990",
    "sg:postcode":"24015",
    "sg:province":"VA",
    "sg:tags":[
        "pool",
        "swimming"
    ],
    "wof:name":"Olympic Park Pool",
    "wof:placetype":"venue"
},
  "geometry": {"coordinates":[-79.996393,37.241448],"type":"Point"}
}