{
  "type": "Feature",
  "properties": {
    "addr:full":"16300 Mount Cross Rd Dry Fork VA 24549",
    "addr:housenumber":"16300",
    "addr:postcode":"24549",
    "addr:street":"Mount Cross Rd",
    "iso:country":"US",
    "sg:address":"16300 Mount Cross Rd",
    "sg:city":"Dry Fork",
    "sg:classifiers":[
        {
            "category":"Organizations",
            "subcategory":"Religious Organization",
            "type":"Services"
        }
    ],
    "sg:phone":"+1 434 724 6500",
    "sg:postcode":"24549",
    "sg:province":"VA",
    "sg:tags":[
        "church"
    ],
    "wof:name":"Swansonville Pentecostal Holin",
    "wof:placetype":"venue"
},
  "geometry": {"coordinates":[-79.573087,36.7025],"type":"Point"}
}