{
  "type": "Feature",
  "properties": {
    "iso:country":"US",
    "sg:address":"408 Park St",
    "sg:city":"Charlottesville",
    "sg:classifiers":[
        {
            "category":"Professional",
            "subcategory":"Lawyer & Legal Services",
            "type":"Services"
        }
    ],
    "sg:phone":"+1 434 979 0077",
    "sg:postcode":"22902",
    "sg:province":"VA",
    "wof:name":"Wagoner David C Atty",
    "wof:placetype":"venue"
},
  "geometry": {"coordinates":[-78.476744,38.03196],"type":"Point"}
}