{
  "type": "Feature",
  "properties": {
    "iso:country":"US",
    "sg:address":"9205 Alyssum Way",
    "sg:city":"Annandale",
    "sg:classifiers":[
        {
            "category":"Communications",
            "subcategory":"Film & Video Production",
            "type":"Services"
        }
    ],
    "sg:phone":"+1 703 978 6887",
    "sg:postcode":"22003",
    "sg:province":"VA",
    "sg:tags":[
        "audio"
    ],
    "wof:name":"RHL Web Page Design",
    "wof:placetype":"venue"
},
  "geometry": {"coordinates":[-77.26220499999999,38.815505],"type":"Point"}
}