{
  "type": "Feature",
  "properties": {
    "addr:full":"5289 Halifax Rd Halifax VA 24558",
    "addr:housenumber":"5289",
    "addr:postcode":"24558",
    "addr:street":"Halifax Rd",
    "iso:country":"US",
    "sg:address":"5289 Halifax Rd",
    "sg:city":"Halifax",
    "sg:classifiers":[
        {
            "category":"Building & Trades",
            "subcategory":"Landscaping Services",
            "type":"Services"
        }
    ],
    "sg:phone":"+1 434 476 1200",
    "sg:postcode":"24558",
    "sg:province":"VA",
    "sg:tags":[
        "landscape",
        "contractor"
    ],
    "wof:name":"Moore Farm Landscaping",
    "wof:placetype":"venue"
},
  "geometry": {"coordinates":[-78.926838,36.758342],"type":"Point"}
}