{
  "type": "Feature",
  "properties": {
    "addr:full":"3823 Plaza Dr Fairfax VA 22030",
    "addr:housenumber":"3823",
    "addr:postcode":"22030",
    "addr:street":"Plaza Dr",
    "iso:country":"US",
    "sg:address":"3823 Plaza Dr",
    "sg:city":"Fairfax",
    "sg:classifiers":[
        {
            "category":"Real Estate",
            "subcategory":"Real Estate Services",
            "type":"Services"
        }
    ],
    "sg:phone":"+1 703 383 0605",
    "sg:postcode":"22030",
    "sg:province":"VA",
    "sg:tags":[
        "company",
        "title"
    ],
    "wof:name":"Independence Title Inc",
    "wof:placetype":"venue"
},
  "geometry": {"coordinates":[-77.301366,38.848154],"type":"Point"}
}