{
  "type": "Feature",
  "properties": {
    "addr:full":"1705 Parkview Dr Chesapeake VA 23320",
    "addr:housenumber":"1705",
    "addr:postcode":"23320",
    "addr:street":"Parkview Dr",
    "iso:country":"US",
    "sg:address":"1705 Parkview Dr",
    "sg:city":"Chesapeake",
    "sg:classifiers":[
        {
            "category":"Banks & Credit Unions",
            "subcategory":"Bank",
            "type":"Services"
        }
    ],
    "sg:phone":"+1 757 523 9105",
    "sg:postcode":"23320",
    "sg:province":"VA",
    "sg:tags":[
        "financing"
    ],
    "wof:name":"Wells Fargo Financial Accptnce",
    "wof:placetype":"venue"
},
  "geometry": {"coordinates":[-76.238131,36.793522],"type":"Point"}
}