{
  "type": "Feature",
  "properties": {
    "iso:country":"US",
    "sg:address":"601 Bottino Ln",
    "sg:city":"Virginia Beach",
    "sg:classifiers":[
        {
            "category":"Retail",
            "subcategory":"Laundry & Dry Cleaning",
            "type":"Services"
        }
    ],
    "sg:phone":"+1 757 497 4580",
    "sg:postcode":"23455",
    "sg:province":"VA",
    "sg:tags":[
        "tailoring"
    ],
    "wof:name":"Brickhouse Tailoring",
    "wof:placetype":"venue"
},
  "geometry": {"coordinates":[-76.155444,36.857738],"type":"Point"}
}