{
  "type": "Feature",
  "properties": {
    "addr:full":"191 Johnson St NE Abingdon VA 24210",
    "addr:housenumber":"191",
    "addr:postcode":"24210",
    "addr:street":"Johnson St Ne",
    "iso:country":"US",
    "sg:address":"191 Johnson St NE",
    "sg:city":"Abingdon",
    "sg:classifiers":[
        {
            "category":"Health Services",
            "subcategory":"Doctor",
            "type":"Services"
        }
    ],
    "sg:phone":"+1 276 623 0038",
    "sg:postcode":"24210",
    "sg:province":"VA",
    "sg:tags":[
        "medical"
    ],
    "wof:name":"Internal Medicine Assn PC",
    "wof:placetype":"venue"
},
  "geometry": {"coordinates":[-81.972624,36.714592],"type":"Point"}
}