{
  "type": "Feature",
  "properties": {
    "addr:full":"1110 Drake St SW Vienna VA 22180",
    "addr:housenumber":"1110",
    "addr:postcode":"22180",
    "addr:street":"Drake St Sw",
    "iso:country":"US",
    "sg:address":"1110 Drake St SW",
    "sg:city":"Vienna",
    "sg:classifiers":[
        {
            "category":"Professional",
            "subcategory":"Computer Services",
            "type":"Services"
        }
    ],
    "sg:phone":"+1 703 938 3687",
    "sg:postcode":"22180",
    "sg:province":"VA",
    "sg:tags":[
        "related"
    ],
    "wof:name":"James L Delahoussayo Conslt",
    "wof:placetype":"venue"
},
  "geometry": {"coordinates":[-77.253946,38.881032],"type":"Point"}
}