{
  "type": "Feature",
  "properties": {
    "iso:country":"US",
    "sg:address":"2031 Jennie Scher Rd",
    "sg:city":"Richmond",
    "sg:classifiers":[
        {
            "category":"Wholesale",
            "subcategory":"Auto Parts",
            "type":"Manufacturing & Wholesale Goods"
        }
    ],
    "sg:phone":"+1 804 226 4917",
    "sg:postcode":"23231",
    "sg:province":"VA",
    "sg:tags":[
        "automobile",
        "rebuilt",
        "supplies-used"
    ],
    "wof:name":"Jb Used Auto Parts",
    "wof:placetype":"venue"
},
  "geometry": {"coordinates":[-77.394689,37.525904],"type":"Point"}
}