{
  "type": "Feature",
  "properties": {
    "addr:full":"2121 Columbia Pike Arlington VA 22204",
    "addr:housenumber":"2121",
    "addr:postcode":"22204",
    "addr:street":"Columbia Pike",
    "iso:country":"US",
    "sg:address":"2121 Columbia Pike",
    "sg:city":"Arlington",
    "sg:classifiers":[
        {
            "category":"Health Services",
            "subcategory":"Dentist",
            "type":"Services"
        }
    ],
    "sg:phone":"+1 703 521 8843",
    "sg:postcode":"22204",
    "sg:province":"VA",
    "wof:name":"Rubin Michael F DMD",
    "wof:placetype":"venue"
},
  "geometry": {"coordinates":[-77.08049800000001,38.864201],"type":"Point"}
}