{
  "type": "Feature",
  "properties": {
    "addr:full":"24048 Lenah Rd Aldie VA 20105",
    "addr:postcode":"24048;20105",
    "addr:street":"Lenah Rd",
    "iso:country":"US",
    "sg:address":"24048 Lenah Rd",
    "sg:city":"Aldie",
    "sg:classifiers":[
        {
            "category":"Organizations",
            "subcategory":"Religious Organization",
            "type":"Services"
        }
    ],
    "sg:phone":"+1 703 327 4392",
    "sg:postcode":"20105",
    "sg:province":"VA",
    "wof:name":"National Episcopal Cursillo",
    "wof:placetype":"venue"
},
  "geometry": {"coordinates":[-77.580422,38.950549],"type":"Point"}
}