{
  "type": "Feature",
  "properties": {
    "addr:full":"1320 Central Park Blvd Fredericksburg VA 22401",
    "addr:housenumber":"1320",
    "addr:postcode":"22401",
    "addr:street":"Central Park Blvd",
    "iso:country":"US",
    "sg:address":"1320 Central Park Blvd",
    "sg:city":"Fredericksburg",
    "sg:classifiers":[
        {
            "category":"Professional",
            "subcategory":"Lawyer & Legal Services",
            "type":"Services"
        }
    ],
    "sg:phone":"+1 540 548 3363",
    "sg:postcode":"22401",
    "sg:province":"VA",
    "sg:tags":[
        "attorney"
    ],
    "wof:name":"Cynthia B Malament Atty Of Law",
    "wof:placetype":"venue"
},
  "geometry": {"coordinates":[-77.513623,38.301644],"type":"Point"}
}