{
  "type": "Feature",
  "properties": {
    "iso:country":"US",
    "sg:address":"1 E Main St",
    "sg:city":"Salem",
    "sg:classifiers":[
        {
            "category":"Professional",
            "subcategory":"Management & Consulting",
            "type":"Services"
        }
    ],
    "sg:phone":"+1 540 375 8826",
    "sg:postcode":"24153",
    "sg:province":"VA",
    "sg:tags":[
        "consultant",
        "business"
    ],
    "wof:name":"Registrations By Design Inc",
    "wof:placetype":"venue"
},
  "geometry": {"coordinates":[-80.057727,37.292829],"type":"Point"}
}