{
  "type": "Feature",
  "properties": {
    "addr:full":"134 Nelson Dr Newport News VA 23601",
    "addr:housenumber":"134",
    "addr:postcode":"23601",
    "addr:street":"Nelson Dr",
    "iso:country":"US",
    "sg:address":"134 Nelson Dr",
    "sg:city":"Newport News",
    "sg:classifiers":[
        {
            "category":"Building & Trades",
            "subcategory":"Construction",
            "type":"Services"
        }
    ],
    "sg:phone":"+1 804 695 2888",
    "sg:postcode":"23601",
    "sg:province":"VA",
    "sg:tags":[
        "general",
        "contractor"
    ],
    "wof:name":"Daniels Construction",
    "wof:placetype":"venue"
},
  "geometry": {"coordinates":[-76.475692,37.046012],"type":"Point"}
}