{
  "type": "Feature",
  "properties": {
    "addr:full":"263 Millwood Ave Winchester VA 22601",
    "addr:housenumber":"263",
    "addr:postcode":"22601",
    "addr:street":"Millwood Ave",
    "iso:country":"US",
    "sg:address":"263 Millwood Ave",
    "sg:city":"Winchester",
    "sg:classifiers":[
        {
            "category":"Autos & Motor Vehicles",
            "subcategory":"Auto Supplies",
            "type":"Retail Goods"
        }
    ],
    "sg:phone":"+1 540 662 1724",
    "sg:postcode":"22601",
    "sg:province":"VA",
    "sg:tags":[
        "automobile",
        "stereo",
        "radio"
    ],
    "sg:website":"www.wincautoradio.com",
    "wof:name":"Winchester Auto Radio",
    "wof:placetype":"venue"
},
  "geometry": {"coordinates":[-78.165167,39.1737],"type":"Point"}
}