{
  "type": "Feature",
  "properties": {
    "addr:full":"2101 Parks Ave Virginia Beach VA 23451",
    "addr:housenumber":"2101",
    "addr:postcode":"23451",
    "addr:street":"Parks Ave",
    "iso:country":"US",
    "sg:address":"2101 Parks Ave",
    "sg:city":"Virginia Beach",
    "sg:classifiers":[
        {
            "category":"Professional",
            "subcategory":"Lawyer & Legal Services",
            "type":"Services"
        }
    ],
    "sg:phone":"+1 757 491 4045",
    "sg:postcode":"23451",
    "sg:province":"VA",
    "sg:tags":[
        "attorney"
    ],
    "wof:name":"Jeffrey L Marks",
    "wof:placetype":"venue"
},
  "geometry": {"coordinates":[-75.985923,36.847411],"type":"Point"}
}