{
  "type": "Feature",
  "properties": {
    "iso:country":"US",
    "sg:address":"616 Old Dominion Rd",
    "sg:city":"Yorktown",
    "sg:classifiers":[
        {
            "category":"Professional",
            "subcategory":"Engineering",
            "type":"Services"
        }
    ],
    "sg:phone":"+1 757 898 4679",
    "sg:postcode":"23692",
    "sg:province":"VA",
    "wof:name":"James E Wirkner",
    "wof:placetype":"venue"
},
  "geometry": {"coordinates":[-76.50201300000001,37.186551],"type":"Point"}
}