{
  "type": "Feature",
  "properties": {
    "addr:full":"251 W Lee Hwy Warrenton VA 20186",
    "addr:housenumber":"251",
    "addr:postcode":"20186",
    "addr:street":"W Lee Hwy",
    "iso:country":"US",
    "sg:address":"251 W Lee Hwy",
    "sg:city":"Warrenton",
    "sg:classifiers":[
        {
            "category":"Banks & Credit Unions",
            "subcategory":"Financial Services",
            "type":"Services"
        }
    ],
    "sg:phone":"+1 540 349 8936",
    "sg:postcode":"20186",
    "sg:province":"VA",
    "sg:tags":[
        "broker",
        "mortgage"
    ],
    "sg:website":"www.citifinancial.com",
    "wof:name":"Citifinancial",
    "wof:placetype":"venue"
},
  "geometry": {"coordinates":[-77.798598,38.728825],"type":"Point"}
}