{
  "type": "Feature",
  "properties": {
    "iso:country":"US",
    "sg:address":"1430 Anderson Hwy",
    "sg:city":"Powhatan",
    "sg:classifiers":[
        {
            "category":"Building & Trades",
            "subcategory":"Construction",
            "type":"Services"
        }
    ],
    "sg:phone":"+1 804 794 3419",
    "sg:postcode":"23139",
    "sg:province":"VA",
    "sg:tags":[
        "wallpaper",
        "painting",
        "contractor"
    ],
    "wof:name":"M P Barden & Sons Inc",
    "wof:placetype":"venue"
},
  "geometry": {"coordinates":[-77.745394,37.507932],"type":"Point"}
}