{
  "type": "Feature",
  "properties": {
    "addr:full":"1529 Apperson Dr Salem VA 24153",
    "addr:housenumber":"1529",
    "addr:postcode":"24153",
    "addr:street":"Apperson Dr",
    "iso:country":"US",
    "sg:address":"1529 Apperson Dr",
    "sg:city":"Salem",
    "sg:classifiers":[
        {
            "category":"Professional",
            "type":"Services"
        }
    ],
    "sg:phone":"+1 540 389 5990",
    "sg:postcode":"24153",
    "sg:province":"VA",
    "sg:tags":[
        "establishment"
    ],
    "wof:name":"Apperson Village",
    "wof:placetype":"venue"
},
  "geometry": {"coordinates":[-80.03608699999999,37.271518],"type":"Point"}
}