{
  "type": "Feature",
  "properties": {
    "iso:country":"US",
    "sg:address":"4000 W Mercury Blvd",
    "sg:city":"Hampton",
    "sg:classifiers":[
        {
            "category":"Health Services",
            "subcategory":"Doctor",
            "type":"Services"
        }
    ],
    "sg:phone":"+1 757 826 7372",
    "sg:postcode":"23666",
    "sg:province":"VA",
    "wof:name":"Steven L Perlman DDS",
    "wof:placetype":"venue"
},
  "geometry": {"coordinates":[-76.422996,37.030197],"type":"Point"}
}