{
  "type": "Feature",
  "properties": {
    "addr:full":"420 Rorer Ave SW Roanoke VA 24016",
    "addr:housenumber":"420",
    "addr:postcode":"24016",
    "addr:street":"Rorer Ave Sw",
    "iso:country":"US",
    "sg:address":"420 Rorer Ave SW",
    "sg:city":"Roanoke",
    "sg:classifiers":[
        {
            "category":"Retail",
            "subcategory":"Auto Repair",
            "type":"Services"
        }
    ],
    "sg:phone":"+1 540 343 1332",
    "sg:postcode":"24016",
    "sg:province":"VA",
    "sg:tags":[
        "automotive",
        "general"
    ],
    "wof:name":"Z Doctor",
    "wof:placetype":"venue"
},
  "geometry": {"coordinates":[-79.94971700000001,37.271735],"type":"Point"}
}