{
  "type": "Feature",
  "properties": {
    "addr:full":"4703 Autumn Glory Way Chantilly VA 20151",
    "addr:housenumber":"4703",
    "addr:postcode":"20151",
    "addr:street":"Autumn Glory Way",
    "iso:country":"US",
    "sg:address":"4703 Autumn Glory Way",
    "sg:city":"Chantilly",
    "sg:classifiers":[
        {
            "category":"Professional",
            "subcategory":"Management & Consulting",
            "type":"Services"
        }
    ],
    "sg:phone":"+1 703 626 1353",
    "sg:postcode":"20151",
    "sg:province":"VA",
    "wof:name":"Quest Benefits Inc",
    "wof:placetype":"venue"
},
  "geometry": {"coordinates":[-77.422899,38.870681],"type":"Point"}
}