{
  "type": "Feature",
  "properties": {
    "addr:full":"316 Spurlane Cir Chesapeake VA 23322",
    "addr:housenumber":"316",
    "addr:postcode":"23322",
    "addr:street":"Spurlane Cir",
    "iso:country":"US",
    "sg:address":"316 Spurlane Cir",
    "sg:city":"Chesapeake",
    "sg:classifiers":[
        {
            "category":"Building & Trades",
            "subcategory":"Cleaning & Sanitation",
            "type":"Services"
        }
    ],
    "sg:phone":"+1 757 546 1453",
    "sg:postcode":"23322",
    "sg:province":"VA",
    "sg:tags":[
        "maintenance"
    ],
    "wof:name":"Southeastern Cleaning Service",
    "wof:placetype":"venue"
},
  "geometry": {"coordinates":[-76.240407,36.695623],"type":"Point"}
}