{
  "type": "Feature",
  "properties": {
    "iso:country":"US",
    "sg:address":"8412 Sudley Rd",
    "sg:city":"Manassas",
    "sg:classifiers":[
        {
            "category":"Restaurant",
            "type":"Food & Drink"
        }
    ],
    "sg:phone":"+1 703 257 7293",
    "sg:postcode":"20109",
    "sg:province":"VA",
    "sg:tags":[
        "mexican"
    ],
    "wof:name":"La Tolteca Mexican Family",
    "wof:placetype":"venue"
},
  "geometry": {"coordinates":[-77.499264,38.772698],"type":"Point"}
}