{
  "type": "Feature",
  "properties": {
    "addr:full":"63 E Williamsburg Rd Sandston VA 23150",
    "addr:housenumber":"63",
    "addr:postcode":"23150",
    "addr:street":"E Williamsburg Rd",
    "iso:country":"US",
    "sg:address":"63 E Williamsburg Rd",
    "sg:city":"Sandston",
    "sg:classifiers":[
        {
            "category":"Professional",
            "subcategory":"Accounting & Tax Preparation",
            "type":"Services"
        }
    ],
    "sg:phone":"+1 804 737 8846",
    "sg:postcode":"23150",
    "sg:province":"VA",
    "sg:tags":[
        "return",
        "preparation-business"
    ],
    "wof:name":"Computax of VA",
    "wof:placetype":"venue"
},
  "geometry": {"coordinates":[-77.311415,37.522491],"type":"Point"}
}