{
  "type": "Feature",
  "properties": {
    "addr:full":"748 Oriole Dr Virginia Beach VA 23451",
    "addr:housenumber":"748",
    "addr:postcode":"23451",
    "addr:street":"Oriole Dr",
    "iso:country":"US",
    "sg:address":"748 Oriole Dr",
    "sg:city":"Virginia Beach",
    "sg:classifiers":[
        {
            "category":"Real Estate",
            "subcategory":"Real Estate Agent",
            "type":"Services"
        }
    ],
    "sg:phone":"+1 757 428 9276",
    "sg:postcode":"23451",
    "sg:province":"VA",
    "wof:name":"Cole-Ash Inc",
    "wof:placetype":"venue"
},
  "geometry": {"coordinates":[-75.994304,36.859326],"type":"Point"}
}