{
  "type": "Feature",
  "properties": {
    "iso:country":"US",
    "sg:address":"5304 1st Pl N",
    "sg:city":"Arlington",
    "sg:classifiers":[
        {
            "category":"Professional",
            "subcategory":"Management & Consulting",
            "type":"Services"
        }
    ],
    "sg:phone":"+1 703 312 4464",
    "sg:postcode":"22203",
    "sg:province":"VA",
    "sg:tags":[
        "business"
    ],
    "wof:name":"Intcontrol",
    "wof:placetype":"venue"
},
  "geometry": {"coordinates":[-77.126623,38.869222],"type":"Point"}
}