{
  "type": "Feature",
  "properties": {
    "addr:full":"2807 Skipwith Rd Richmond VA 23294",
    "addr:housenumber":"2807",
    "addr:postcode":"23294",
    "addr:street":"Skipwith Rd",
    "iso:country":"US",
    "sg:address":"2807 Skipwith Rd",
    "sg:city":"Richmond",
    "sg:classifiers":[
        {
            "category":"Real Estate",
            "subcategory":"Real Estate Agent",
            "type":"Services"
        }
    ],
    "sg:phone":"+1 804 270 4851",
    "sg:postcode":"23294",
    "sg:province":"VA",
    "wof:name":"Tates Estates Inc",
    "wof:placetype":"venue"
},
  "geometry": {"coordinates":[-77.53849099999999,37.626056],"type":"Point"}
}