{
  "type": "Feature",
  "properties": {
    "addr:full":"416 Ashlawn Dr Norfolk VA 23505",
    "addr:housenumber":"416",
    "addr:postcode":"23505",
    "addr:street":"Ashlawn Dr",
    "iso:country":"US",
    "sg:address":"416 Ashlawn Dr",
    "sg:city":"Norfolk",
    "sg:classifiers":[
        {
            "category":"Manufacturing",
            "subcategory":"Tools & Machinery",
            "type":"Manufacturing & Wholesale Goods"
        }
    ],
    "sg:phone":"+1 757 480 8888",
    "sg:postcode":"23505",
    "sg:province":"VA",
    "sg:tags":[
        "protection",
        "system",
        "power"
    ],
    "wof:name":"Advanced Systems Integration",
    "wof:placetype":"venue"
},
  "geometry": {"coordinates":[-76.26173199999999,36.919013],"type":"Point"}
}