{
  "type": "Feature",
  "properties": {
    "addr:full":"34 Joynes Rd Hampton VA 23666",
    "addr:housenumber":"34",
    "addr:postcode":"23666",
    "addr:street":"Joynes Rd",
    "iso:country":"US",
    "sg:address":"34 Joynes Rd",
    "sg:city":"Hampton",
    "sg:classifiers":[
        {
            "category":"Education",
            "subcategory":"Special Training",
            "type":"Public Place"
        }
    ],
    "sg:phone":"+1 757 826 8810",
    "sg:postcode":"23666",
    "sg:province":"VA",
    "wof:name":"Committee of Management",
    "wof:placetype":"venue"
},
  "geometry": {"coordinates":[-76.408838,37.025729],"type":"Point"}
}