{
  "type": "Feature",
  "properties": {
    "addr:full":"9841 S Clark Pl Manassas VA 20110",
    "addr:housenumber":"9841",
    "addr:postcode":"20110",
    "addr:street":"S Clark Pl",
    "iso:country":"US",
    "sg:address":"9841 S Clark Pl",
    "sg:city":"Manassas",
    "sg:classifiers":[
        {
            "category":"Building & Trades",
            "subcategory":"Construction",
            "type":"Services"
        }
    ],
    "sg:phone":"+1 703 330 1311",
    "sg:postcode":"20110",
    "sg:province":"VA",
    "sg:tags":[
        "roofing",
        "contractor"
    ],
    "wof:name":"Reyes Roofing LLC",
    "wof:placetype":"venue"
},
  "geometry": {"coordinates":[-77.465683,38.741848],"type":"Point"}
}