{
  "type": "Feature",
  "properties": {
    "addr:full":"3624 E Stratford Rd Virginia Beach VA 23455",
    "addr:housenumber":"3624",
    "addr:postcode":"23455",
    "addr:street":"E Stratford Rd",
    "iso:country":"US",
    "sg:address":"3624 E Stratford Rd",
    "sg:city":"Virginia Beach",
    "sg:classifiers":[
        {
            "category":"Shopping",
            "subcategory":"Catalog Store",
            "type":"Retail Goods"
        }
    ],
    "sg:phone":"+1 757 460 8549",
    "sg:postcode":"23455",
    "sg:province":"VA",
    "sg:tags":[
        "collectible"
    ],
    "wof:name":"Tayloes Treasures",
    "wof:placetype":"venue"
},
  "geometry": {"coordinates":[-76.097611,36.906512],"type":"Point"}
}