{
  "type": "Feature",
  "properties": {
    "addr:full":"9658 Thackery Sq Fairfax VA 22032",
    "addr:housenumber":"9658",
    "addr:postcode":"22032",
    "addr:street":"Thackery Sq",
    "iso:country":"US",
    "sg:address":"9658 Thackery Sq",
    "sg:city":"Fairfax",
    "sg:classifiers":[
        {
            "category":"Home & Garden",
            "subcategory":"Home Furnishings",
            "type":"Retail Goods"
        }
    ],
    "sg:phone":"+1 703 425 6705",
    "sg:postcode":"22032",
    "sg:province":"VA",
    "sg:tags":[
        "installation",
        "drapery"
    ],
    "wof:name":"S & W Installation Inc",
    "wof:placetype":"venue"
},
  "geometry": {"coordinates":[-77.27759399999999,38.815782],"type":"Point"}
}