{
  "type": "Feature",
  "properties": {
    "addr:full":"4298 Childress Rd Christiansburg VA 24073",
    "addr:housenumber":"4298",
    "addr:postcode":"24073",
    "addr:street":"Childress Rd",
    "iso:country":"US",
    "sg:address":"4298 Childress Rd",
    "sg:city":"Christiansburg",
    "sg:classifiers":[
        {
            "category":"Building & Trades",
            "subcategory":"Construction",
            "type":"Services"
        }
    ],
    "sg:phone":"+1 540 382 7711",
    "sg:postcode":"24073",
    "sg:province":"VA",
    "sg:tags":[
        "concrete",
        "contractor"
    ],
    "wof:name":"Linkous Paving Inc",
    "wof:placetype":"venue"
},
  "geometry": {"coordinates":[-80.511871,37.051481],"type":"Point"}
}