{
  "type": "Feature",
  "properties": {
    "addr:full":"3714 Moody Ave Richmond VA 23225",
    "addr:housenumber":"3714",
    "addr:postcode":"23225",
    "addr:street":"Moody Ave",
    "iso:country":"US",
    "sg:address":"3714 Moody Ave",
    "sg:city":"Richmond",
    "sg:classifiers":[
        {
            "category":"Communications",
            "subcategory":"Film & Video Production",
            "type":"Services"
        }
    ],
    "sg:phone":"+1 804 283 7300",
    "sg:postcode":"23225",
    "sg:province":"VA",
    "wof:name":"Tycoon Production",
    "wof:placetype":"venue"
},
  "geometry": {"coordinates":[-77.472781,37.51155],"type":"Point"}
}