{
  "type": "Feature",
  "properties": {
    "addr:full":"507 Miami Dr Chesapeake VA 23323",
    "addr:housenumber":"507",
    "addr:postcode":"23323",
    "addr:street":"Miami Dr",
    "iso:country":"US",
    "sg:address":"507 Miami Dr",
    "sg:city":"Chesapeake",
    "sg:classifiers":[
        {
            "category":"Banks & Credit Unions",
            "subcategory":"Financial Services",
            "type":"Services"
        }
    ],
    "sg:phone":"+1 757 436 2410",
    "sg:postcode":"23323",
    "sg:province":"VA",
    "sg:tags":[
        "real estate"
    ],
    "wof:name":"Chesapeake Property Services",
    "wof:placetype":"venue"
},
  "geometry": {"coordinates":[-76.312714,36.724759],"type":"Point"}
}