{
  "type": "Feature",
  "properties": {
    "addr:full":"125 Turner Rd Richmond VA 23225",
    "addr:housenumber":"125",
    "addr:postcode":"23225",
    "addr:street":"Turner Rd",
    "iso:country":"US",
    "sg:address":"125 Turner Rd",
    "sg:city":"Richmond",
    "sg:classifiers":[
        {
            "category":"Personal",
            "subcategory":"Beauty Salon",
            "type":"Services"
        }
    ],
    "sg:phone":"+1 804 276 1331",
    "sg:postcode":"23225",
    "sg:province":"VA",
    "sg:tags":[
        "shop"
    ],
    "wof:name":"Trend Setters",
    "wof:placetype":"venue"
},
  "geometry": {"coordinates":[-77.536597,37.49756],"type":"Point"}
}