{
  "type": "Feature",
  "properties": {
    "addr:full":"301 Wingfield Orchard Rd Martinsville VA 24112",
    "addr:housenumber":"301",
    "addr:postcode":"24112",
    "addr:street":"Wingfield Orchard Rd",
    "iso:country":"US",
    "sg:address":"301 Wingfield Orchard Rd",
    "sg:city":"Martinsville",
    "sg:classifiers":[
        {
            "category":"Wholesale",
            "subcategory":"Home Furnishings",
            "type":"Manufacturing & Wholesale Goods"
        }
    ],
    "sg:phone":"+1 276 681 6178",
    "sg:postcode":"24112",
    "sg:province":"VA",
    "sg:tags":[
        "furniture",
        "specify",
        "furnish",
        "accessory"
    ],
    "wof:name":"Estep & Associates",
    "wof:placetype":"venue"
},
  "geometry": {"coordinates":[-80.006552,36.687864],"type":"Point"}
}