{
  "type": "Feature",
  "properties": {
    "addr:full":"507 23rd St S Arlington VA 22202",
    "addr:housenumber":"507",
    "addr:postcode":"22202",
    "addr:street":"23Rd St S",
    "iso:country":"US",
    "sg:address":"507 23rd St S",
    "sg:city":"Arlington",
    "sg:classifiers":[
        {
            "category":"Shopping",
            "subcategory":"Musical Instruments",
            "type":"Retail Goods"
        }
    ],
    "sg:phone":"+1 703 979 7060",
    "sg:postcode":"22202",
    "sg:province":"VA",
    "sg:tags":[
        "music",
        "dealer"
    ],
    "wof:name":"Zavarella's Music",
    "wof:placetype":"venue"
},
  "geometry": {"coordinates":[-77.05519099999999,38.853415],"type":"Point"}
}