{
  "type": "Feature",
  "properties": {
    "iso:country":"US",
    "sg:address":"303 S Saratoga St",
    "sg:city":"Suffolk",
    "sg:classifiers":[
        {
            "category":"Wholesale",
            "subcategory":"Farm Supplies",
            "type":"Manufacturing & Wholesale Goods"
        }
    ],
    "sg:phone":"+1 757 934 6700",
    "sg:postcode":"23434",
    "sg:province":"VA",
    "sg:tags":[
        "peanut",
        "product"
    ],
    "sg:website":"www.goldenpeanut.com",
    "wof:name":"Golden Peanut Co",
    "wof:placetype":"venue"
},
  "geometry": {"coordinates":[-76.590356,36.72301],"type":"Point"}
}