{
  "type": "Feature",
  "properties": {
    "addr:full":"400 N Main St Gordonsville VA 22942",
    "addr:housenumber":"400",
    "addr:postcode":"22942",
    "addr:street":"N Main St",
    "iso:country":"US",
    "sg:address":"400 N Main St",
    "sg:city":"Gordonsville",
    "sg:classifiers":[
        {
            "category":"Professional",
            "subcategory":"Lawyer & Legal Services",
            "type":"Services"
        }
    ],
    "sg:phone":"+1 540 832 2711",
    "sg:postcode":"22942",
    "sg:province":"VA",
    "sg:tags":[
        "attorney"
    ],
    "wof:name":"Charles R Jaeger",
    "wof:placetype":"venue"
},
  "geometry": {"coordinates":[-78.188755,38.140497],"type":"Point"}
}