{
  "type": "Feature",
  "properties": {
    "addr:full":"400 Elden St Herndon VA 20170",
    "addr:housenumber":"400",
    "addr:postcode":"20170",
    "addr:street":"Elden St",
    "iso:country":"US",
    "sg:address":"400 Elden St",
    "sg:city":"Herndon",
    "sg:classifiers":[
        {
            "category":"Taxi",
            "type":"Transportation"
        },
        {
            "category":"Airport",
            "type":"Transportation"
        }
    ],
    "sg:phone":"+1 703 437 9100",
    "sg:postcode":"20170",
    "sg:province":"VA",
    "wof:name":"Yellow Cab",
    "wof:placetype":"venue"
},
  "geometry": {"coordinates":[-77.375137,38.967758],"type":"Point"}
}