{
  "type": "Feature",
  "properties": {
    "addr:full":"13901 Jefferson Davis Hwy Woodbridge VA 22191",
    "addr:housenumber":"13901",
    "addr:postcode":"22191",
    "addr:street":"Jefferson Davis Hwy",
    "iso:country":"US",
    "sg:address":"13901 Jefferson Davis Hwy",
    "sg:city":"Woodbridge",
    "sg:classifiers":[
        {
            "category":"Social Services",
            "subcategory":"Job Training",
            "type":"Services"
        },
        {
            "category":"Health Services",
            "subcategory":"Health Practitioner",
            "type":"Services"
        }
    ],
    "sg:phone":"+1 703 490 6726",
    "sg:postcode":"22191",
    "sg:province":"VA",
    "sg:tags":[
        "rehabilitation",
        "outpatient",
        "specialty"
    ],
    "wof:name":"HealthSouth",
    "wof:placetype":"venue"
},
  "geometry": {"coordinates":[-77.25753,38.651505],"type":"Point"}
}