{
  "type": "Feature",
  "properties": {
    "addr:full":"555 Settlers Landing Rd Hampton VA 23669",
    "addr:housenumber":"555",
    "addr:postcode":"23669",
    "addr:street":"Settlers Landing Rd",
    "iso:country":"US",
    "sg:address":"555 Settlers Landing Rd",
    "sg:city":"Hampton",
    "sg:classifiers":[
        {
            "category":"Manufacturing",
            "subcategory":"Printing",
            "type":"Manufacturing & Wholesale Goods"
        },
        {
            "category":"Shopping",
            "subcategory":"Clothing, Apparel, & Fashions",
            "type":"Retail Goods"
        }
    ],
    "sg:phone":"+1 757 728 3678",
    "sg:postcode":"23669",
    "sg:province":"VA",
    "sg:tags":[
        "screen",
        "beach",
        "wear",
        "family",
        "casual"
    ],
    "wof:name":"Seals Custom Screen Printing",
    "wof:placetype":"venue"
},
  "geometry": {"coordinates":[-76.347849,37.02436],"type":"Point"}
}