{
  "type": "Feature",
  "properties": {
    "addr:full":"1218 Ox Rd Woodstock VA 22664",
    "addr:housenumber":"1218",
    "addr:postcode":"22664",
    "addr:street":"Ox Rd",
    "iso:country":"US",
    "sg:address":"1218 Ox Rd",
    "sg:city":"Woodstock",
    "sg:classifiers":[
        {
            "category":"Government",
            "subcategory":"Office",
            "type":"Public Place"
        }
    ],
    "sg:phone":"+1 540 459 5514",
    "sg:postcode":"22664",
    "sg:province":"VA",
    "sg:tags":[
        "village"
    ],
    "wof:name":"Woodstock Water Tower",
    "wof:placetype":"venue"
},
  "geometry": {"coordinates":[-78.52706000000001,38.866182],"type":"Point"}
}