{
  "type": "Feature",
  "properties": {
    "addr:full":"804 Professional Pl Chesapeake VA 23320",
    "addr:housenumber":"804",
    "addr:postcode":"23320",
    "addr:street":"Professional Pl",
    "iso:country":"US",
    "sg:address":"804 Professional Pl",
    "sg:city":"Chesapeake",
    "sg:classifiers":[
        {
            "category":"Professional",
            "subcategory":"Computer Services",
            "type":"Services"
        }
    ],
    "sg:phone":"+1 757 547 5555",
    "sg:postcode":"23320",
    "sg:province":"VA",
    "sg:website":"www.metrocomva.com",
    "wof:name":"Metrocom Corp",
    "wof:placetype":"venue"
},
  "geometry": {"coordinates":[-76.234655,36.760198],"type":"Point"}
}