{
  "type": "Feature",
  "properties": {
    "addr:full":"1733 Virginia Beach Blvd Virginia Beach VA 23454",
    "addr:housenumber":"1733",
    "addr:postcode":"23454",
    "addr:street":"Virginia Beach Blvd",
    "iso:country":"US",
    "sg:address":"1733 Virginia Beach Blvd",
    "sg:city":"Virginia Beach",
    "sg:classifiers":[
        {
            "category":"Retail",
            "subcategory":"Auto Repair",
            "type":"Services"
        }
    ],
    "sg:phone":"+1 757 422 6959",
    "sg:postcode":"23454",
    "sg:province":"VA",
    "sg:tags":[
        "repairing",
        "automobile",
        "general"
    ],
    "wof:name":"Beach Auto World",
    "wof:placetype":"venue"
},
  "geometry": {"coordinates":[-76.025047,36.842907],"type":"Point"}
}