{
  "type": "Feature",
  "properties": {
    "addr:full":"2453 Long Island Rd Gladys VA 24554",
    "addr:housenumber":"2453",
    "addr:postcode":"24554",
    "addr:street":"Long Island Rd",
    "iso:country":"US",
    "sg:address":"2453 Long Island Rd",
    "sg:city":"Gladys",
    "sg:classifiers":[
        {
            "category":"Personal",
            "subcategory":"Beauty Salon",
            "type":"Services"
        }
    ],
    "sg:phone":"+1 434 283 4935",
    "sg:postcode":"24554",
    "sg:province":"VA",
    "wof:name":"Fannie's Beauty Salon",
    "wof:placetype":"venue"
},
  "geometry": {"coordinates":[-79.09089299999999,37.138956],"type":"Point"}
}