{
  "type": "Feature",
  "properties": {
    "iso:country":"US",
    "sg:address":"5945 Three Notch Rd",
    "sg:city":"Louisa",
    "sg:classifiers":[
        {
            "category":"Wholesale",
            "subcategory":"Scrap",
            "type":"Manufacturing & Wholesale Goods"
        }
    ],
    "sg:phone":"+1 434 589 5770",
    "sg:postcode":"23093",
    "sg:province":"VA",
    "sg:tags":[
        "recycling",
        "center"
    ],
    "wof:name":"250 East Auto Recycling",
    "wof:placetype":"venue"
},
  "geometry": {"coordinates":[-78.155083,37.948857],"type":"Point"}
}