{
  "type": "Feature",
  "properties": {
    "iso:country":"US",
    "sg:address":"300 Garrisonville Rd",
    "sg:city":"Stafford",
    "sg:classifiers":[
        {
            "category":"Education",
            "subcategory":"Vocational School",
            "type":"Public Place"
        }
    ],
    "sg:phone":"+1 540 657 1300",
    "sg:postcode":"22554",
    "sg:province":"VA",
    "wof:name":"Eagle Education Inc",
    "wof:placetype":"venue"
},
  "geometry": {"coordinates":[-77.425551,38.475625],"type":"Point"}
}