{
  "type": "Feature",
  "properties": {
    "addr:full":"105 Battleground Ave Saltville VA 24370",
    "addr:housenumber":"105",
    "addr:postcode":"24370",
    "addr:street":"Battleground Ave",
    "iso:country":"US",
    "sg:address":"105 Battleground Ave",
    "sg:city":"Saltville",
    "sg:classifiers":[
        {
            "category":"Real Estate",
            "subcategory":"Real Estate Operator",
            "type":"Services"
        }
    ],
    "sg:phone":"+1 276 496 3399",
    "sg:postcode":"24370",
    "sg:province":"VA",
    "sg:tags":[
        "building",
        "apartment"
    ],
    "wof:name":"Battleground Apartments",
    "wof:placetype":"venue"
},
  "geometry": {"coordinates":[-81.749132,36.893526],"type":"Point"}
}