{
  "type": "Feature",
  "properties": {
    "addr:full":"1916 Coliseum Dr Hampton VA 23666",
    "addr:housenumber":"1916",
    "addr:postcode":"23666",
    "addr:street":"Coliseum Dr",
    "iso:country":"US",
    "sg:address":"1916 Coliseum Dr",
    "sg:city":"Hampton",
    "sg:classifiers":[
        {
            "category":"Travel",
            "subcategory":"Hotels & Motels",
            "type":"Entertainment"
        }
    ],
    "sg:phone":"+1 757 827 5052",
    "sg:postcode":"23666",
    "sg:province":"VA",
    "wof:name":"Comfort Inn",
    "wof:placetype":"venue"
},
  "geometry": {"coordinates":[-76.38650699999999,37.038579],"type":"Point"}
}