{
  "type": "Feature",
  "properties": {
    "addr:full":"1522 Hillview Ave SE Roanoke VA 24014",
    "addr:housenumber":"1522",
    "addr:postcode":"24014",
    "addr:street":"Hillview Ave Se",
    "iso:country":"US",
    "sg:address":"1522 Hillview Ave SE",
    "sg:city":"Roanoke",
    "sg:classifiers":[
        {
            "category":"Building & Trades",
            "subcategory":"Plumbing",
            "type":"Services"
        }
    ],
    "sg:phone":"+1 540 427 2478",
    "sg:postcode":"24014",
    "sg:province":"VA",
    "sg:tags":[
        "contractor"
    ],
    "wof:name":"Minute Plumbing",
    "wof:placetype":"venue"
},
  "geometry": {"coordinates":[-79.925336,37.229546],"type":"Point"}
}