{
  "type": "Feature",
  "properties": {
    "iso:country":"US",
    "sg:address":"132 Falcon Dr",
    "sg:city":"Fredericksburg",
    "sg:classifiers":[
        {
            "category":"Education",
            "subcategory":"School",
            "type":"Public Place"
        }
    ],
    "sg:phone":"+1 540 898 0020",
    "sg:postcode":"22408",
    "sg:province":"VA",
    "sg:tags":[
        "private"
    ],
    "sg:website":"www.fredericksburgacademy.org",
    "wof:name":"Fredericksburg Academy",
    "wof:placetype":"venue"
},
  "geometry": {"coordinates":[-77.49280299999999,38.256209],"type":"Point"}
}