{
  "type": "Feature",
  "properties": {
    "iso:country":"US",
    "sg:address":"10340 Main St",
    "sg:city":"Fairfax",
    "sg:classifiers":[
        {
            "category":"Restaurant",
            "type":"Food & Drink"
        }
    ],
    "sg:phone":"+1 703 929 6959",
    "sg:postcode":"22030",
    "sg:province":"VA",
    "sg:tags":[
        "eating"
    ],
    "wof:name":"Farrzo Inc",
    "wof:placetype":"venue"
},
  "geometry": {"coordinates":[-77.30152099999999,38.845152],"type":"Point"}
}