{
  "type": "Feature",
  "properties": {
    "addr:full":"821 Mount View Rd Danville VA 24540",
    "addr:housenumber":"821",
    "addr:postcode":"24540",
    "addr:street":"Mount View Rd",
    "iso:country":"US",
    "sg:address":"821 Mount View Rd",
    "sg:city":"Danville",
    "sg:classifiers":[
        {
            "category":"Retail",
            "subcategory":"Auto Repair",
            "type":"Services"
        }
    ],
    "sg:phone":"+1 434 836 1955",
    "sg:postcode":"24540",
    "sg:province":"VA",
    "sg:tags":[
        "repairing",
        "automobile",
        "general"
    ],
    "wof:name":"Mtn View Garage",
    "wof:placetype":"venue"
},
  "geometry": {"coordinates":[-79.393818,36.701667],"type":"Point"}
}