{
  "type": "Feature",
  "properties": {
    "addr:full":"11359 Berry Ave King George VA 22485",
    "addr:housenumber":"11359",
    "addr:postcode":"22485",
    "addr:street":"Berry Ave",
    "iso:country":"US",
    "sg:address":"11359 Berry Ave",
    "sg:city":"King George",
    "sg:classifiers":[
        {
            "category":"Retail",
            "subcategory":"Repair Shop",
            "type":"Services"
        }
    ],
    "sg:phone":"+1 540 775 0954",
    "sg:postcode":"22485",
    "sg:province":"VA",
    "wof:name":"Atlas Communication Networks",
    "wof:placetype":"venue"
},
  "geometry": {"coordinates":[-77.145487,38.304833],"type":"Point"}
}