{
  "type": "Feature",
  "properties": {
    "addr:full":"716 Liberty St Martinsville VA 24112",
    "addr:housenumber":"716",
    "addr:postcode":"24112",
    "addr:street":"Liberty St",
    "iso:country":"US",
    "sg:address":"716 Liberty St",
    "sg:city":"Martinsville",
    "sg:classifiers":[
        {
            "category":"Home & Garden",
            "subcategory":"Furniture",
            "type":"Retail Goods"
        }
    ],
    "sg:phone":"+1 276 632 1592",
    "sg:postcode":"24112",
    "sg:province":"VA",
    "wof:name":"Parcat Enterprises",
    "wof:placetype":"venue"
},
  "geometry": {"coordinates":[-79.876482,36.705294],"type":"Point"}
}