{
  "type": "Feature",
  "properties": {
    "addr:full":"1073 E Stuart Dr Galax VA 24333",
    "addr:housenumber":"1073",
    "addr:postcode":"24333",
    "addr:street":"E Stuart Dr",
    "iso:country":"US",
    "sg:address":"1073 E Stuart Dr",
    "sg:city":"Galax",
    "sg:classifiers":[
        {
            "category":"Banks & Credit Unions",
            "subcategory":"Bank",
            "type":"Services"
        }
    ],
    "sg:phone":"+1 276 236 0322",
    "sg:postcode":"24333",
    "sg:province":"VA",
    "sg:tags":[
        "personal",
        "institution"
    ],
    "wof:name":"Advance America",
    "wof:placetype":"venue"
},
  "geometry": {"coordinates":[-80.89299699999999,36.681919],"type":"Point"}
}