{
  "type": "Feature",
  "properties": {
    "iso:country":"US",
    "sg:address":"707 Liberty St",
    "sg:city":"Chesapeake",
    "sg:classifiers":[
        {
            "category":"Insurance",
            "subcategory":"Insurance Agent",
            "type":"Services"
        }
    ],
    "sg:phone":"+1 757 545 2450",
    "sg:postcode":"23324",
    "sg:province":"VA",
    "wof:name":"Divers Dawley Savage Lassiter",
    "wof:placetype":"venue"
},
  "geometry": {"coordinates":[-76.272659,36.820664],"type":"Point"}
}