{
  "type": "Feature",
  "properties": {
    "iso:country":"US",
    "sg:address":"4620 N Lee Hwy",
    "sg:city":"Arlington",
    "sg:classifiers":[
        {
            "category":"Professional",
            "subcategory":"Business Services",
            "type":"Services"
        }
    ],
    "sg:phone":"+1 703 248 8860",
    "sg:postcode":"22207",
    "sg:province":"VA",
    "wof:name":"Mid Atlantic Human Resources A",
    "wof:placetype":"venue"
},
  "geometry": {"coordinates":[-77.120413,38.898462],"type":"Point"}
}