{
  "type": "Feature",
  "properties": {
    "iso:country":"US",
    "sg:address":"4210 Franklin Rd SW",
    "sg:city":"Roanoke",
    "sg:classifiers":[
        {
            "category":"Shopping",
            "subcategory":"Department Store",
            "type":"Retail Goods"
        }
    ],
    "sg:phone":"+1 540 772 3892",
    "sg:postcode":"24014",
    "sg:province":"VA",
    "sg:tags":[
        "discount"
    ],
    "wof:name":"Wal-Mart",
    "wof:placetype":"venue"
},
  "geometry": {"coordinates":[-79.96816,37.223161],"type":"Point"}
}