{
  "type": "Feature",
  "properties": {
    "addr:full":"10379 Democracy Ln Fairfax VA 22030",
    "addr:housenumber":"10379",
    "addr:postcode":"22030",
    "addr:street":"Democracy Ln",
    "iso:country":"US",
    "sg:address":"10379 Democracy Ln",
    "sg:city":"Fairfax",
    "sg:classifiers":[
        {
            "category":"Banks & Credit Unions",
            "subcategory":"Bank",
            "type":"Services"
        }
    ],
    "sg:phone":"+1 571 432 5671",
    "sg:postcode":"22030",
    "sg:province":"VA",
    "sg:tags":[
        "financing"
    ],
    "wof:name":"Financial Development Svc Inc",
    "wof:placetype":"venue"
},
  "geometry": {"coordinates":[-77.300634,38.849743],"type":"Point"}
}