{
  "type": "Feature",
  "properties": {
    "addr:full":"4456 Corporation Ln Virginia Beach VA 23462",
    "addr:housenumber":"4456",
    "addr:postcode":"23462",
    "addr:street":"Corporation Ln",
    "iso:country":"US",
    "sg:address":"4456 Corporation Ln",
    "sg:city":"Virginia Beach",
    "sg:classifiers":[
        {
            "category":"Personal",
            "type":"Services"
        }
    ],
    "sg:phone":"+1 757 497 8899",
    "sg:postcode":"23462",
    "sg:province":"VA",
    "sg:tags":[
        "control",
        "weight"
    ],
    "sg:website":"www.weightlossforever.net",
    "wof:name":"Weight Loss Forever",
    "wof:placetype":"venue"
},
  "geometry": {"coordinates":[-76.128112,36.847967],"type":"Point"}
}