{
  "type": "Feature",
  "properties": {
    "addr:full":"189 Barron Dr Troutville VA 24175",
    "addr:housenumber":"189",
    "addr:postcode":"24175",
    "addr:street":"Barron Dr",
    "iso:country":"US",
    "sg:address":"189 Barron Dr",
    "sg:city":"Troutville",
    "sg:classifiers":[
        {
            "category":"Retail",
            "subcategory":"Repair Shop",
            "type":"Services"
        }
    ],
    "sg:phone":"+1 540 777 5561",
    "sg:postcode":"24175",
    "sg:province":"VA",
    "sg:tags":[
        "tool",
        "power"
    ],
    "wof:name":"Tool Doctor",
    "wof:placetype":"venue"
},
  "geometry": {"coordinates":[-79.84655600000001,37.440852],"type":"Point"}
}