{
  "type": "Feature",
  "properties": {
    "addr:full":"27327 Perkins Rd Petersburg VA 23805",
    "addr:housenumber":"27327",
    "addr:postcode":"23805",
    "addr:street":"Perkins Rd",
    "iso:country":"US",
    "sg:address":"27327 Perkins Rd",
    "sg:city":"Petersburg",
    "sg:classifiers":[
        {
            "category":"Professional",
            "subcategory":"Computer Services",
            "type":"Services"
        }
    ],
    "sg:phone":"+1 804 863 4276",
    "sg:postcode":"23805",
    "sg:province":"VA",
    "sg:tags":[
        "installation",
        "childcare",
        "network"
    ],
    "wof:name":"Chraomai Enterprises Inc",
    "wof:placetype":"venue"
},
  "geometry": {"coordinates":[-77.442729,37.071808],"type":"Point"}
}