{
  "type": "Feature",
  "properties": {
    "addr:full":"1018 Clarence St Norfolk VA 23502",
    "addr:housenumber":"1018",
    "addr:postcode":"23502",
    "addr:street":"Clarence St",
    "iso:country":"US",
    "sg:address":"1018 Clarence St",
    "sg:city":"Norfolk",
    "sg:classifiers":[
        {
            "category":"Personal",
            "subcategory":"Beauty Salon",
            "type":"Services"
        }
    ],
    "sg:phone":"+1 757 459 2289",
    "sg:postcode":"23502",
    "sg:province":"VA",
    "wof:name":"Hollywood Hairstyles",
    "wof:placetype":"venue"
},
  "geometry": {"coordinates":[-76.18341100000001,36.855872],"type":"Point"}
}