{
  "type": "Feature",
  "properties": {
    "iso:country":"US",
    "sg:address":"2190 Pimmit Dr Ste 212",
    "sg:city":"Falls Church",
    "sg:classifiers":[
        {
            "category":"Wholesale",
            "subcategory":"Computers",
            "type":"Manufacturing & Wholesale Goods"
        },
        {
            "category":"Professional",
            "subcategory":"Computer Services",
            "type":"Services"
        }
    ],
    "sg:phone":"+1 703 893 0034",
    "sg:postcode":"22043",
    "sg:province":"VA",
    "sg:tags":[
        "repair"
    ],
    "sg:website":"www.myrxpc.com",
    "wof:name":"Rx PC",
    "wof:placetype":"venue"
},
  "geometry": {"coordinates":[-77.202685,38.902924],"type":"Point"}
}