{
  "type": "Feature",
  "properties": {
    "iso:country":"US",
    "sg:address":"15548 Lee Hwy",
    "sg:city":"Bristol",
    "sg:classifiers":[
        {
            "category":"Shopping",
            "subcategory":"Jewelry",
            "type":"Retail Goods"
        }
    ],
    "sg:phone":"+1 276 669 4212",
    "sg:postcode":"24202",
    "sg:province":"VA",
    "sg:tags":[
        "coin",
        "jeweler"
    ],
    "wof:name":"Skyland Coin & Jewelry Inc",
    "wof:placetype":"venue"
},
  "geometry": {"coordinates":[-82.07999599999999,36.656172],"type":"Point"}
}