{
  "type": "Feature",
  "properties": {
    "iso:country":"US",
    "sg:address":"10360 Courthouse Rd",
    "sg:city":"Chesterfield",
    "sg:classifiers":[
        {
            "category":"Retail",
            "subcategory":"Auto Repair",
            "type":"Services"
        }
    ],
    "sg:phone":"+1 804 748 8740",
    "sg:postcode":"23832",
    "sg:province":"VA",
    "sg:tags":[
        "automotive"
    ],
    "wof:name":"Progressive Towing",
    "wof:placetype":"venue"
},
  "geometry": {"coordinates":[-77.582745,37.42536],"type":"Point"}
}