{
  "type": "Feature",
  "properties": {
    "iso:country":"US",
    "sg:address":"11301 Sunset Hills Rd",
    "sg:city":"Reston",
    "sg:classifiers":[
        {
            "category":"Manufacturing",
            "subcategory":"Printing",
            "type":"Manufacturing & Wholesale Goods"
        }
    ],
    "sg:phone":"+1 703 787 6506",
    "sg:postcode":"20190",
    "sg:province":"VA",
    "sg:tags":[
        "printer"
    ],
    "wof:name":"Minuteman Press",
    "wof:placetype":"venue"
},
  "geometry": {"coordinates":[-77.33772999999999,38.950551],"type":"Point"}
}