{
  "type": "Feature",
  "properties": {
    "iso:country":"US",
    "sg:address":"7170 Gary Rd",
    "sg:city":"Manassas",
    "sg:classifiers":[
        {
            "category":"Manufacturing",
            "subcategory":"Electronics",
            "type":"Manufacturing & Wholesale Goods"
        }
    ],
    "sg:phone":"+1 703 631 7476",
    "sg:postcode":"20109",
    "sg:province":"VA",
    "sg:tags":[
        "fire",
        "alarm",
        "system"
    ],
    "sg:website":"www.tlglss.com",
    "wof:name":"Life Safety Systems",
    "wof:placetype":"venue"
},
  "geometry": {"coordinates":[-77.50360000000001,38.802807],"type":"Point"}
}