{
  "type": "Feature",
  "properties": {
    "addr:full":"5541 Olde West Ct Richmond VA 23228",
    "addr:housenumber":"5541",
    "addr:postcode":"23228",
    "addr:street":"Olde West Ct",
    "iso:country":"US",
    "sg:address":"5541 Olde West Ct",
    "sg:city":"Richmond",
    "sg:classifiers":[
        {
            "category":"Real Estate",
            "subcategory":"Real Estate Operator",
            "type":"Services"
        }
    ],
    "sg:phone":"+1 804 672 3633",
    "sg:postcode":"23228",
    "sg:province":"VA",
    "sg:tags":[
        "apartment"
    ],
    "wof:name":"Dominion Olde West Apartments",
    "wof:placetype":"venue"
},
  "geometry": {"coordinates":[-77.52391799999999,37.635536],"type":"Point"}
}