{
  "type": "Feature",
  "properties": {
    "addr:full":"7740 Whitepine Rd Richmond VA 23237",
    "addr:postcode":"7740;23237",
    "addr:street":"Whitepine Rd",
    "iso:country":"US",
    "sg:address":"7740 Whitepine Rd",
    "sg:city":"Richmond",
    "sg:classifiers":[
        {
            "category":"Manufacturing",
            "subcategory":"Tools & Machinery",
            "type":"Manufacturing & Wholesale Goods"
        }
    ],
    "sg:phone":"+1 804 275 5555",
    "sg:postcode":"23237",
    "sg:province":"VA",
    "sg:tags":[
        "shop",
        "machine",
        "metalworking",
        "industrial",
        "mfg"
    ],
    "sg:website":"www.marcomachine.com",
    "wof:name":"Marco Machine & Design Inc",
    "wof:placetype":"venue"
},
  "geometry": {"coordinates":[-77.525847,37.402153],"type":"Point"}
}