{
  "type": "Feature",
  "properties": {
    "iso:country":"US",
    "sg:address":"18039 Birmingham Rd",
    "sg:city":"Culpeper",
    "sg:classifiers":[
        {
            "category":"Real Estate",
            "subcategory":"Developer",
            "type":"Services"
        }
    ],
    "sg:phone":"+1 540 547 2263",
    "sg:postcode":"22701",
    "sg:province":"VA",
    "wof:name":"Birmingham Farms",
    "wof:placetype":"venue"
},
  "geometry": {"coordinates":[-78.09448500000001,38.458068],"type":"Point"}
}