{
  "type": "Feature",
  "properties": {
    "addr:full":"10633 Crestwood Dr Manassas VA 20109",
    "addr:housenumber":"10633",
    "addr:postcode":"20109",
    "addr:street":"Crestwood Dr",
    "iso:country":"US",
    "sg:address":"10633 Crestwood Dr",
    "sg:city":"Manassas",
    "sg:classifiers":[
        {
            "category":"Health Services",
            "subcategory":"Chiropractor",
            "type":"Services"
        }
    ],
    "sg:phone":"+1 703 368 9887",
    "sg:postcode":"20109",
    "sg:province":"VA",
    "sg:website":"www.spinecareofmanassas.com",
    "wof:name":"Leavitt Catherine",
    "wof:placetype":"venue"
},
  "geometry": {"coordinates":[-77.513397,38.7789],"type":"Point"}
}