{
  "type": "Feature",
  "properties": {
    "addr:full":"6300 River Rd Richmond VA 23226",
    "addr:housenumber":"6300",
    "addr:postcode":"23226",
    "addr:street":"River Rd",
    "iso:country":"US",
    "sg:address":"6300 River Rd",
    "sg:city":"Richmond",
    "sg:classifiers":[
        {
            "category":"Education",
            "subcategory":"Library",
            "type":"Public Place"
        },
        {
            "category":"Education",
            "subcategory":"University",
            "type":"Public Place"
        }
    ],
    "sg:phone":"+1 804 289 8261",
    "sg:postcode":"23226",
    "sg:province":"VA",
    "sg:tags":[
        "college"
    ],
    "wof:name":"University of Richmond Library",
    "wof:placetype":"venue"
},
  "geometry": {"coordinates":[-77.53494999999999,37.568041],"type":"Point"}
}