{
  "type": "Feature",
  "properties": {
    "iso:country":"US",
    "sg:address":"2220 Winterfield Rd",
    "sg:city":"Midlothian",
    "sg:classifiers":[
        {
            "category":"Building & Trades",
            "subcategory":"Construction",
            "type":"Services"
        }
    ],
    "sg:phone":"+1 804 794 5174",
    "sg:postcode":"23113",
    "sg:province":"VA",
    "sg:tags":[
        "house"
    ],
    "wof:name":"Joseph S Weakley General Contr",
    "wof:placetype":"venue"
},
  "geometry": {"coordinates":[-77.66344100000001,37.519546],"type":"Point"}
}