{
  "type": "Feature",
  "properties": {
    "iso:country":"US",
    "sg:address":"14106 Shallowford Landing Rd",
    "sg:city":"Midlothian",
    "sg:classifiers":[
        {
            "category":"Social Services",
            "type":"Services"
        }
    ],
    "sg:phone":"+1 804 763 4772",
    "sg:postcode":"23112",
    "sg:province":"VA",
    "sg:tags":[
        "instruction",
        "health",
        "care"
    ],
    "wof:name":"Health Care & Rehabilitation",
    "wof:placetype":"venue"
},
  "geometry": {"coordinates":[-77.66761200000001,37.44082],"type":"Point"}
}