{
  "type": "Feature",
  "properties": {
    "iso:country":"US",
    "sg:address":"485 S Independence Blvd",
    "sg:city":"Virginia Beach",
    "sg:classifiers":[
        {
            "category":"Organizations",
            "subcategory":"Religious Organization",
            "type":"Services"
        }
    ],
    "sg:phone":"+1 757 499 7990",
    "sg:postcode":"23452",
    "sg:province":"VA",
    "sg:tags":[
        "church"
    ],
    "wof:name":"Faith House Of Refuge",
    "wof:placetype":"venue"
},
  "geometry": {"coordinates":[-76.133171,36.827764],"type":"Point"}
}