{
  "type": "Feature",
  "properties": {
    "addr:full":"8063 Gracie Dr Manassas VA 20112",
    "addr:housenumber":"8063",
    "addr:postcode":"20112",
    "addr:street":"Gracie Dr",
    "iso:country":"US",
    "sg:address":"8063 Gracie Dr",
    "sg:city":"Manassas",
    "sg:classifiers":[
        {
            "category":"Professional",
            "subcategory":"Management & Consulting",
            "type":"Services"
        }
    ],
    "sg:phone":"+1 703 791 2237",
    "sg:postcode":"20112",
    "sg:province":"VA",
    "sg:tags":[
        "consultant",
        "business"
    ],
    "wof:name":"Rjd Consulting",
    "wof:placetype":"venue"
},
  "geometry": {"coordinates":[-77.45350000000001,38.656751],"type":"Point"}
}