{
  "type": "Feature",
  "properties": {
    "iso:country":"US",
    "sg:address":"9059 Aldingham Pl",
    "sg:city":"Mechanicsville",
    "sg:classifiers":[
        {
            "category":"Shopping",
            "subcategory":"Bicycles & Sporting Goods",
            "type":"Retail Goods"
        }
    ],
    "sg:phone":"+1 804 550 0632",
    "sg:postcode":"23116",
    "sg:province":"VA",
    "sg:tags":[
        "equipment",
        "golf",
        "supply"
    ],
    "sg:website":"www.customizedgolf.com",
    "wof:name":"Customized Golf Inc",
    "wof:placetype":"venue"
},
  "geometry": {"coordinates":[-77.40856100000001,37.69572],"type":"Point"}
}