{
  "type": "Feature",
  "properties": {
    "iso:country":"US",
    "sg:address":"120 Swain Ln",
    "sg:city":"Yorktown",
    "sg:classifiers":[
        {
            "category":"Organizations",
            "subcategory":"Religious Organization",
            "type":"Services"
        }
    ],
    "sg:phone":"+1 757 865 8942",
    "sg:postcode":"23693",
    "sg:province":"VA",
    "sg:tags":[
        "clergy"
    ],
    "wof:name":"W P Coleman",
    "wof:placetype":"venue"
},
  "geometry": {"coordinates":[-76.431074,37.10728],"type":"Point"}
}