{
  "type": "Feature",
  "properties": {
    "addr:full":"11801 Chase Wellesley Dr Richmond VA 23233",
    "addr:housenumber":"11801",
    "addr:postcode":"23233",
    "addr:street":"Chase Wellesley Dr",
    "iso:country":"US",
    "sg:address":"11801 Chase Wellesley Dr",
    "sg:city":"Richmond",
    "sg:classifiers":[
        {
            "category":"Social Services",
            "subcategory":"Child Care",
            "type":"Services"
        }
    ],
    "sg:phone":"+1 804 364 3053",
    "sg:postcode":"23233",
    "sg:province":"VA",
    "wof:name":"Loving Care Cottage",
    "wof:placetype":"venue"
},
  "geometry": {"coordinates":[-77.62159699999999,37.648609],"type":"Point"}
}