{
  "type": "Feature",
  "properties": {
    "addr:full":"102 Collingswood Ct Forest VA 24551",
    "addr:housenumber":"102",
    "addr:postcode":"24551",
    "addr:street":"Collingswood Ct",
    "iso:country":"US",
    "sg:address":"102 Collingswood Ct",
    "sg:city":"Forest",
    "sg:classifiers":[
        {
            "category":"Professional",
            "subcategory":"Business Services",
            "type":"Services"
        }
    ],
    "sg:phone":"+1 434 385 8856",
    "sg:postcode":"24551",
    "sg:province":"VA",
    "sg:tags":[
        "engraving"
    ],
    "wof:name":"Rossers Engraving",
    "wof:placetype":"venue"
},
  "geometry": {"coordinates":[-79.258836,37.364567],"type":"Point"}
}