{
  "type": "Feature",
  "properties": {
    "addr:full":"6901 Apamatica Ln Chesterfield VA 23838",
    "addr:housenumber":"6901",
    "addr:postcode":"23838",
    "addr:street":"Apamatica Ln",
    "iso:country":"US",
    "sg:address":"6901 Apamatica Ln",
    "sg:city":"Chesterfield",
    "sg:classifiers":[
        {
            "category":"Retail",
            "subcategory":"Auto Rental",
            "type":"Services"
        }
    ],
    "sg:phone":"+1 804 748 7397",
    "sg:postcode":"23838",
    "sg:province":"VA",
    "sg:tags":[
        "automobile",
        "leasing"
    ],
    "wof:name":"Consolidated Service Corp",
    "wof:placetype":"venue"
},
  "geometry": {"coordinates":[-77.491648,37.327603],"type":"Point"}
}