{
  "type": "Feature",
  "properties": {
    "iso:country":"US",
    "sg:address":"623 Virginia Beach Blvd",
    "sg:city":"Virginia Beach",
    "sg:classifiers":[
        {
            "category":"Autos & Motor Vehicles",
            "subcategory":"Automobile Sales",
            "type":"Retail Goods"
        }
    ],
    "sg:phone":"+1 757 428 8623",
    "sg:postcode":"23451",
    "sg:province":"VA",
    "sg:tags":[
        "used"
    ],
    "wof:name":"Howard T Nixon",
    "wof:placetype":"venue"
},
  "geometry": {"coordinates":[-75.982668,36.843976],"type":"Point"}
}