{
  "type": "Feature",
  "properties": {
    "iso:country":"US",
    "sg:address":"219 Apperson Dr",
    "sg:city":"Salem",
    "sg:classifiers":[
        {
            "category":"Restaurant",
            "type":"Food & Drink"
        }
    ],
    "sg:phone":"+1 540 387 2555",
    "sg:postcode":"24153",
    "sg:province":"VA",
    "sg:tags":[
        "eating"
    ],
    "wof:name":"Pepper's Pizza & Subs",
    "wof:placetype":"venue"
},
  "geometry": {"coordinates":[-80.05329500000001,37.274284],"type":"Point"}
}