{
  "type": "Feature",
  "properties": {
    "addr:full":"1700 Charles St Fredericksburg VA 22401",
    "addr:housenumber":"1700",
    "addr:postcode":"22401",
    "addr:street":"Charles St",
    "iso:country":"US",
    "sg:address":"1700 Charles St",
    "sg:city":"Fredericksburg",
    "sg:classifiers":[
        {
            "category":"Building & Trades",
            "subcategory":"Construction",
            "type":"Services"
        }
    ],
    "sg:phone":"+1 540 374 1843",
    "sg:postcode":"22401",
    "sg:province":"VA",
    "sg:tags":[
        "interior",
        "residential",
        "painting",
        "contractor"
    ],
    "wof:name":"Premium Plus Painters",
    "wof:placetype":"venue"
},
  "geometry": {"coordinates":[-77.466269,38.310229],"type":"Point"}
}