{
  "type": "Feature",
  "properties": {
    "iso:country":"US",
    "sg:address":"494 N Pickett St",
    "sg:city":"Alexandria",
    "sg:classifiers":[
        {
            "category":"Professional",
            "type":"Services"
        }
    ],
    "sg:phone":"+1 703 823 0544",
    "sg:postcode":"22304",
    "sg:province":"VA",
    "sg:tags":[
        "establishment"
    ],
    "wof:name":"Backyard Aerospace",
    "wof:placetype":"venue"
},
  "geometry": {"coordinates":[-77.118393,38.816658],"type":"Point"}
}