{
  "type": "Feature",
  "properties": {
    "addr:full":"2000 15th St N Arlington VA 22201",
    "addr:housenumber":"2000",
    "addr:postcode":"22201",
    "addr:street":"15Th St N",
    "iso:country":"US",
    "sg:address":"2000 15th St N",
    "sg:city":"Arlington",
    "sg:classifiers":[
        {
            "category":"Communications",
            "subcategory":"Film & Video Production",
            "type":"Services"
        }
    ],
    "sg:phone":"+1 703 465 8804",
    "sg:postcode":"22201",
    "sg:province":"VA",
    "sg:tags":[
        "taping"
    ],
    "wof:name":"TRF Productions",
    "wof:placetype":"venue"
},
  "geometry": {"coordinates":[-77.08294600000001,38.890895],"type":"Point"}
}