{
  "type": "Feature",
  "properties": {
    "iso:country":"US",
    "sg:address":"1415 N Pickett St",
    "sg:city":"Alexandria",
    "sg:classifiers":[
        {
            "category":"Education",
            "subcategory":"Special Training",
            "type":"Public Place"
        }
    ],
    "sg:phone":"+1 703 370 2189",
    "sg:postcode":"22304",
    "sg:province":"VA",
    "sg:tags":[
        "teacher"
    ],
    "wof:name":"Eginli Ilknur",
    "wof:placetype":"venue"
},
  "geometry": {"coordinates":[-77.10942799999999,38.825459],"type":"Point"}
}