{
  "type": "Feature",
  "properties": {
    "iso:country":"US",
    "sg:address":"203 Fayette St",
    "sg:city":"Farmville",
    "sg:classifiers":[
        {
            "category":"Communications",
            "subcategory":"Radio Station",
            "type":"Services"
        }
    ],
    "sg:phone":"+1 434 391 7337",
    "sg:postcode":"23901",
    "sg:province":"VA",
    "sg:tags":[
        "program",
        "outreach"
    ],
    "wof:name":"Postpartum Virginia",
    "wof:placetype":"venue"
},
  "geometry": {"coordinates":[-78.40654000000001,37.297571],"type":"Point"}
}