{
  "type": "Feature",
  "properties": {
    "addr:full":"131 Great Falls St Falls Church VA 22046",
    "addr:housenumber":"131",
    "addr:postcode":"22046",
    "addr:street":"Great Falls St",
    "iso:country":"US",
    "sg:address":"131 Great Falls St",
    "sg:city":"Falls Church",
    "sg:classifiers":[
        {
            "category":"Insurance",
            "subcategory":"Insurance Agent",
            "type":"Services"
        }
    ],
    "sg:phone":"+1 703 532 7261",
    "sg:postcode":"22046",
    "sg:province":"VA",
    "wof:name":"Integon Insurance Claims",
    "wof:placetype":"venue"
},
  "geometry": {"coordinates":[-77.169049,38.884264],"type":"Point"}
}