{
  "type": "Feature",
  "properties": {
    "addr:full":"3533 Kecoughtan Rd Hampton VA 23661",
    "addr:housenumber":"3533",
    "addr:postcode":"23661",
    "addr:street":"Kecoughtan Rd",
    "iso:country":"US",
    "sg:address":"3533 Kecoughtan Rd",
    "sg:city":"Hampton",
    "sg:classifiers":[
        {
            "category":"Restaurant",
            "type":"Food & Drink"
        }
    ],
    "sg:phone":"+1 757 723 7707",
    "sg:postcode":"23661",
    "sg:province":"VA",
    "wof:name":"White Oak Lodge",
    "wof:placetype":"venue"
},
  "geometry": {"coordinates":[-76.36184900000001,37.008134],"type":"Point"}
}