{
  "type": "Feature",
  "properties": {
    "addr:full":"9401 Peabody St Manassas VA 20110",
    "addr:housenumber":"9401",
    "addr:postcode":"20110",
    "addr:street":"Peabody St",
    "iso:country":"US",
    "sg:address":"9401 Peabody St",
    "sg:city":"Manassas",
    "sg:classifiers":[
        {
            "category":"Professional",
            "subcategory":"Research",
            "type":"Services"
        }
    ],
    "sg:phone":"+1 703 369 5552",
    "sg:postcode":"20110",
    "sg:province":"VA",
    "sg:website":"www.utroninc.com",
    "wof:name":"Utron Inc",
    "wof:placetype":"venue"
},
  "geometry": {"coordinates":[-77.477183,38.751158],"type":"Point"}
}