{
  "type": "Feature",
  "properties": {
    "iso:country":"US",
    "sg:address":"188 S Mason St",
    "sg:city":"Harrisonburg",
    "sg:classifiers":[
        {
            "category":"Personal",
            "subcategory":"Beauty Salon",
            "type":"Services"
        }
    ],
    "sg:phone":"+1 540 433 7376",
    "sg:postcode":"22801",
    "sg:province":"VA",
    "sg:tags":[
        "shop"
    ],
    "wof:name":"Hair Fashions By Michael",
    "wof:placetype":"venue"
},
  "geometry": {"coordinates":[-78.867087,38.447102],"type":"Point"}
}