{
  "type": "Feature",
  "properties": {
    "addr:full":"170 Hedgefield Terrace Ln Wytheville VA 24382",
    "addr:housenumber":"170",
    "addr:postcode":"24382",
    "addr:street":"Hedgefield Terrace Ln",
    "iso:country":"US",
    "sg:address":"170 Hedgefield Terrace Ln",
    "sg:city":"Wytheville",
    "sg:classifiers":[
        {
            "category":"Real Estate",
            "subcategory":"Real Estate Agent",
            "type":"Services"
        }
    ],
    "sg:phone":"+1 276 228 6515",
    "sg:postcode":"24382",
    "sg:province":"VA",
    "sg:tags":[
        "authorities",
        "housing"
    ],
    "wof:name":"Wytheville Redevelopment",
    "wof:placetype":"venue"
},
  "geometry": {"coordinates":[-81.074449,36.956678],"type":"Point"}
}