{
  "type": "Feature",
  "properties": {
    "iso:country":"US",
    "sg:address":"890 N McKinley Rd",
    "sg:city":"Arlington",
    "sg:classifiers":[
        {
            "category":"Organizations",
            "subcategory":"Religious Organization",
            "type":"Services"
        }
    ],
    "sg:phone":"+1 703 534 0020",
    "sg:postcode":"22205",
    "sg:province":"VA",
    "wof:name":"First Church Christ Scientists",
    "wof:placetype":"venue"
},
  "geometry": {"coordinates":[-77.147206,38.873812],"type":"Point"}
}