{
  "type": "Feature",
  "properties": {
    "iso:country":"US",
    "sg:address":"7211 Danny Ln",
    "sg:city":"Manassas",
    "sg:classifiers":[
        {
            "category":"Professional",
            "type":"Services"
        }
    ],
    "sg:phone":"+1 703 791 2912",
    "sg:postcode":"20112",
    "sg:province":"VA",
    "wof:name":"Opticom Corp",
    "wof:placetype":"venue"
},
  "geometry": {"coordinates":[-77.420462,38.673389],"type":"Point"}
}