{
  "type": "Feature",
  "properties": {
    "iso:country":"US",
    "sg:address":"297 Herndon Pkwy",
    "sg:city":"Herndon",
    "sg:classifiers":[
        {
            "category":"Social Services",
            "type":"Services"
        }
    ],
    "sg:phone":"+1 703 689 4880",
    "sg:postcode":"20170",
    "sg:province":"VA",
    "wof:name":"Fox Judith B Lcsw",
    "wof:placetype":"venue"
},
  "geometry": {"coordinates":[-77.371916,38.967057],"type":"Point"}
}