{
  "type": "Feature",
  "properties": {
    "addr:full":"9701 Main St Fairfax VA 22031",
    "addr:housenumber":"9701",
    "addr:postcode":"22031",
    "addr:street":"Main St",
    "iso:country":"US",
    "sg:address":"9701 Main St",
    "sg:city":"Fairfax",
    "sg:classifiers":[
        {
            "category":"Banks & Credit Unions",
            "subcategory":"Bank",
            "type":"Services"
        }
    ],
    "sg:phone":"+1 703 679 1209",
    "sg:postcode":"22031",
    "sg:province":"VA",
    "sg:tags":[
        "federal"
    ],
    "sg:website":"www.applefcu.org",
    "wof:name":"Apple Federal Credit Union",
    "wof:placetype":"venue"
},
  "geometry": {"coordinates":[-77.27822,38.842079],"type":"Point"}
}