{
  "type": "Feature",
  "properties": {
    "addr:full":"3194 Black Creek Dr Mechanicsville VA 23111",
    "addr:housenumber":"3194",
    "addr:postcode":"23111",
    "addr:street":"Black Creek Dr",
    "iso:country":"US",
    "sg:address":"3194 Black Creek Dr",
    "sg:city":"Mechanicsville",
    "sg:classifiers":[
        {
            "category":"Retail",
            "subcategory":"Repair Shop",
            "type":"Services"
        }
    ],
    "sg:phone":"+1 804 781 0230",
    "sg:postcode":"23111",
    "sg:province":"VA",
    "wof:name":"Townsend Upholstery",
    "wof:placetype":"venue"
},
  "geometry": {"coordinates":[-77.211737,37.57169],"type":"Point"}
}