{
  "type": "Feature",
  "properties": {
    "iso:country":"US",
    "sg:address":"243 Ocean Hills Rd",
    "sg:city":"Virginia Beach",
    "sg:classifiers":[
        {
            "category":"Professional",
            "subcategory":"Computer Services",
            "type":"Services"
        }
    ],
    "sg:phone":"+1 757 431 0452",
    "sg:postcode":"23451",
    "sg:province":"VA",
    "sg:tags":[
        "related"
    ],
    "wof:name":"Lynnhaven Group Ltd",
    "wof:placetype":"venue"
},
  "geometry": {"coordinates":[-75.983688,36.867809],"type":"Point"}
}