{
  "type": "Feature",
  "properties": {
    "addr:full":"6003 Forest Hollow Ln Springfield VA 22152",
    "addr:housenumber":"6003",
    "addr:postcode":"22152",
    "addr:street":"Forest Hollow Ln",
    "iso:country":"US",
    "sg:address":"6003 Forest Hollow Ln",
    "sg:city":"Springfield",
    "sg:classifiers":[
        {
            "category":"Professional",
            "subcategory":"Management & Consulting",
            "type":"Services"
        }
    ],
    "sg:phone":"+1 703 866 9970",
    "sg:postcode":"22152",
    "sg:province":"VA",
    "sg:tags":[
        "consultant",
        "training"
    ],
    "wof:name":"Swath Leadership Inc",
    "wof:placetype":"venue"
},
  "geometry": {"coordinates":[-77.24583,38.787406],"type":"Point"}
}