{
  "type": "Feature",
  "properties": {
    "addr:full":"112 Bruce Dr Winchester VA 22601",
    "addr:housenumber":"112",
    "addr:postcode":"22601",
    "addr:street":"Bruce Dr",
    "iso:country":"US",
    "sg:address":"112 Bruce Dr",
    "sg:city":"Winchester",
    "sg:phone":"+1 540 665 9495",
    "sg:postcode":"22601",
    "sg:province":"VA",
    "sg:tags":[
        "equipment",
        "commercial"
    ],
    "wof:name":"Toledo Scales & Systems",
    "wof:placetype":"venue"
},
  "geometry": {"coordinates":[-78.17680799999999,39.150791],"type":"Point"}
}