{
  "type": "Feature",
  "properties": {
    "addr:full":"4221 Pleasant Valley Rd Virginia Beach VA 23464",
    "addr:housenumber":"4221",
    "addr:postcode":"23464",
    "addr:street":"Pleasant Valley Rd",
    "iso:country":"US",
    "sg:address":"4221 Pleasant Valley Rd",
    "sg:city":"Virginia Beach",
    "sg:classifiers":[
        {
            "category":"Personal",
            "subcategory":"Barber",
            "type":"Services"
        }
    ],
    "sg:phone":"+1 757 495 3260",
    "sg:postcode":"23464",
    "sg:province":"VA",
    "sg:tags":[
        "shop"
    ],
    "wof:name":"Millenium Quality Cuts",
    "wof:placetype":"venue"
},
  "geometry": {"coordinates":[-76.149812,36.786764],"type":"Point"}
}