{
  "type": "Feature",
  "properties": {
    "iso:country":"US",
    "sg:address":"3416 N Military Hwy",
    "sg:city":"Norfolk",
    "sg:classifiers":[
        {
            "category":"Shopping",
            "subcategory":"Gifts & Souvenirs",
            "type":"Retail Goods"
        }
    ],
    "sg:phone":"+1 757 855 3280",
    "sg:postcode":"23518",
    "sg:province":"VA",
    "sg:website":"www.mysticmoon.cc",
    "wof:name":"Mystic Moon",
    "wof:placetype":"venue"
},
  "geometry": {"coordinates":[-76.219702,36.889621],"type":"Point"}
}