{
  "type": "Feature",
  "properties": {
    "iso:country":"US",
    "sg:address":"107 Liberty Dr",
    "sg:city":"Yorktown",
    "sg:classifiers":[
        {
            "category":"Health Services",
            "subcategory":"Health Practitioner",
            "type":"Services"
        }
    ],
    "sg:phone":"+1 757 867 6437",
    "sg:postcode":"23693",
    "sg:province":"VA",
    "sg:tags":[
        "nurse",
        "manager"
    ],
    "wof:name":"Anne Grinnell",
    "wof:placetype":"venue"
},
  "geometry": {"coordinates":[-76.43328099999999,37.104589],"type":"Point"}
}