{
  "type": "Feature",
  "properties": {
    "iso:country":"US",
    "sg:address":"5256 Lake Victoria Arch",
    "sg:city":"Virginia Beach",
    "sg:classifiers":[
        {
            "category":"Retail",
            "subcategory":"Portrait Studio",
            "type":"Services"
        }
    ],
    "sg:phone":"+1 757 200 8065",
    "sg:postcode":"23464",
    "sg:province":"VA",
    "sg:tags":[
        "photo"
    ],
    "wof:name":"Photographic Treasures",
    "wof:placetype":"venue"
},
  "geometry": {"coordinates":[-76.162139,36.793933],"type":"Point"}
}