{
  "type": "Feature",
  "properties": {
    "addr:full":"16269 Washington Hwy Doswell VA 23047",
    "addr:housenumber":"16269",
    "addr:postcode":"23047",
    "addr:street":"Washington Hwy",
    "iso:country":"US",
    "sg:address":"16269 Washington Hwy",
    "sg:city":"Doswell",
    "sg:classifiers":[
        {
            "category":"Retail",
            "subcategory":"Auto Repair",
            "type":"Services"
        }
    ],
    "sg:phone":"+1 804 876 3630",
    "sg:postcode":"23047",
    "sg:province":"VA",
    "sg:tags":[
        "wrecker"
    ],
    "wof:name":"Number One Towing Co",
    "wof:placetype":"venue"
},
  "geometry": {"coordinates":[-77.46433,37.850436],"type":"Point"}
}