{
  "type": "Feature",
  "properties": {
    "addr:full":"9208 Venture Ct Manassas VA 20111",
    "addr:housenumber":"9208",
    "addr:postcode":"20111",
    "addr:street":"Venture Ct",
    "iso:country":"US",
    "sg:address":"9208 Venture Ct",
    "sg:city":"Manassas",
    "sg:classifiers":[
        {
            "category":"Building & Trades",
            "subcategory":"Construction",
            "type":"Services"
        }
    ],
    "sg:phone":"+1 703 330 9209",
    "sg:postcode":"20111",
    "sg:province":"VA",
    "sg:tags":[
        "general",
        "commercial",
        "contractor"
    ],
    "wof:name":"Interior Cnstr Svcs Group",
    "wof:placetype":"venue"
},
  "geometry": {"coordinates":[-77.438699,38.77027],"type":"Point"}
}