{
  "type": "Feature",
  "properties": {
    "iso:country":"US",
    "sg:address":"47081 Glenaire Ct",
    "sg:city":"Sterling",
    "sg:classifiers":[
        {
            "category":"Professional",
            "subcategory":"Accounting & Tax Preparation",
            "type":"Services"
        }
    ],
    "sg:phone":"+1 703 450 6984",
    "sg:postcode":"20165",
    "sg:province":"VA",
    "sg:tags":[
        "accountant"
    ],
    "wof:name":"Professional Accounting Svc",
    "wof:placetype":"venue"
},
  "geometry": {"coordinates":[-77.36986899999999,39.047903],"type":"Point"}
}