{
  "type": "Feature",
  "properties": {
    "addr:full":"24843 Serpentine Pl Aldie VA 20152",
    "addr:housenumber":"24843",
    "addr:postcode":"20152",
    "addr:street":"Serpentine Pl",
    "iso:country":"US",
    "sg:address":"24843 Serpentine Pl",
    "sg:city":"Aldie",
    "sg:classifiers":[
        {
            "category":"Communications",
            "type":"Services"
        },
        {
            "category":"Professional",
            "subcategory":"Business Services",
            "type":"Services"
        }
    ],
    "sg:phone":"+1 703 542 6199",
    "sg:postcode":"20152",
    "sg:province":"VA",
    "wof:name":"RJR Communications Solutions",
    "wof:placetype":"venue"
},
  "geometry": {"coordinates":[-77.552832,38.930491],"type":"Point"}
}