{
  "type": "Feature",
  "properties": {
    "addr:full":"709 E Broad St Richmond VA 23219",
    "addr:housenumber":"709",
    "addr:postcode":"23219",
    "addr:street":"E Broad St",
    "iso:country":"US",
    "sg:address":"709 E Broad St",
    "sg:city":"Richmond",
    "sg:classifiers":[
        {
            "category":"Restaurant",
            "type":"Food & Drink"
        }
    ],
    "sg:phone":"+1 804 782 0970",
    "sg:postcode":"23219",
    "sg:province":"VA",
    "sg:tags":[
        "eating"
    ],
    "wof:name":"McDonalds",
    "wof:placetype":"venue"
},
  "geometry": {"coordinates":[-77.434904,37.541262],"type":"Point"}
}