{
  "type": "Feature",
  "properties": {
    "addr:full":"1757 Galleria at Tysons II Mc Lean VA 22102",
    "addr:housenumber":"1757",
    "addr:postcode":"22102",
    "addr:street":"Galleria At Tysons Ii Mc Lean",
    "iso:country":"US",
    "sg:address":"1757 Galleria at Tysons II",
    "sg:city":"Mc Lean",
    "sg:classifiers":[
        {
            "category":"Shopping",
            "subcategory":"Clothing, Apparel, & Fashions",
            "type":"Retail Goods"
        }
    ],
    "sg:phone":"+1 571 633 0241",
    "sg:postcode":"22102",
    "sg:province":"VA",
    "wof:name":"Lacoste",
    "wof:placetype":"venue"
},
  "geometry": {"coordinates":[-77.22521,38.925463],"type":"Point"}
}