{
  "type": "Feature",
  "properties": {
    "iso:country":"US",
    "sg:address":"2839 Maple Ln",
    "sg:city":"Fairfax",
    "sg:classifiers":[
        {
            "category":"Professional",
            "subcategory":"Management & Consulting",
            "type":"Services"
        }
    ],
    "sg:phone":"+1 703 560 1334",
    "sg:postcode":"22031",
    "sg:province":"VA",
    "sg:tags":[
        "business"
    ],
    "wof:name":"Midstream Farm LLC",
    "wof:placetype":"venue"
},
  "geometry": {"coordinates":[-77.248525,38.876723],"type":"Point"}
}