{
  "type": "Feature",
  "properties": {
    "addr:full":"9502 Chamberlayne Rd Mechanicsville VA 23116",
    "addr:housenumber":"9502",
    "addr:postcode":"23116",
    "addr:street":"Chamberlayne Rd",
    "iso:country":"US",
    "sg:address":"9502 Chamberlayne Rd",
    "sg:city":"Mechanicsville",
    "sg:classifiers":[
        {
            "category":"Fast Food",
            "type":"Food & Drink"
        },
        {
            "category":"Restaurant",
            "type":"Food & Drink"
        },
        {
            "category":"Food & Beverages",
            "subcategory":"Groceries & Convenience Stores",
            "type":"Retail Goods"
        }
    ],
    "sg:phone":"+1 804 559 7546",
    "sg:postcode":"23116",
    "sg:province":"VA",
    "sg:tags":[
        "shop",
        "american",
        "sandwich",
        "take"
    ],
    "sg:website":"http://www.subway.com",
    "wof:name":"Subway",
    "wof:placetype":"venue"
},
  "geometry": {"coordinates":[-77.384922,37.66058],"type":"Point"}
}