{
  "type": "Feature",
  "properties": {
    "iso:country":"US",
    "sg:address":"513 Kindig Rd",
    "sg:city":"Waynesboro",
    "sg:classifiers":[
        {
            "category":"Farming",
            "subcategory":"Livestock Farm",
            "type":"Manufacturing & Wholesale Goods"
        }
    ],
    "sg:phone":"+1 540 943 2234",
    "sg:postcode":"22980",
    "sg:province":"VA",
    "sg:tags":[
        "beef",
        "feedlot",
        "cattle"
    ],
    "wof:name":"Gerald Stump",
    "wof:placetype":"venue"
},
  "geometry": {"coordinates":[-78.988541,38.050211],"type":"Point"}
}