{
  "type": "Feature",
  "properties": {
    "addr:full":"2809 Decatur St Richmond VA 23224",
    "addr:housenumber":"2809",
    "addr:postcode":"23224",
    "addr:street":"Decatur St",
    "iso:country":"US",
    "sg:address":"2809 Decatur St",
    "sg:city":"Richmond",
    "sg:classifiers":[
        {
            "category":"Building & Trades",
            "subcategory":"Landscaping Services",
            "type":"Services"
        }
    ],
    "sg:phone":"+1 804 230 6607",
    "sg:postcode":"23224",
    "sg:province":"VA",
    "wof:name":"Batemans Heating and AC In",
    "wof:placetype":"venue"
},
  "geometry": {"coordinates":[-77.45862700000001,37.510425],"type":"Point"}
}