{
  "type": "Feature",
  "properties": {
    "addr:full":"13912 James River Dr Hopewell VA 23860",
    "addr:housenumber":"13912",
    "addr:postcode":"23860",
    "addr:street":"James River Dr",
    "iso:country":"US",
    "sg:address":"13912 James River Dr",
    "sg:city":"Hopewell",
    "sg:classifiers":[
        {
            "category":"Retail",
            "subcategory":"Auto Repair",
            "type":"Services"
        }
    ],
    "sg:phone":"+1 804 452 3522",
    "sg:postcode":"23860",
    "sg:province":"VA",
    "sg:tags":[
        "automotive"
    ],
    "wof:name":"Franks Towing & Repair",
    "wof:placetype":"venue"
},
  "geometry": {"coordinates":[-77.15897099999999,37.249758],"type":"Point"}
}