{
  "type": "Feature",
  "properties": {
    "addr:full":"20571 Quarterpath Trace Cir Sterling VA 20165",
    "addr:postcode":"20571;20165",
    "addr:street":"Quarterpath Trace Cir",
    "iso:country":"US",
    "sg:address":"20571 Quarterpath Trace Cir",
    "sg:city":"Sterling",
    "sg:classifiers":[
        {
            "category":"Professional",
            "subcategory":"Business Services",
            "type":"Services"
        }
    ],
    "sg:phone":"+1 703 444 9423",
    "sg:postcode":"20165",
    "sg:province":"VA",
    "wof:name":"18 Karat Interiors",
    "wof:placetype":"venue"
},
  "geometry": {"coordinates":[-77.368279,39.048044],"type":"Point"}
}