{
  "type": "Feature",
  "properties": {
    "iso:country":"US",
    "sg:address":"1012 Main St",
    "sg:city":"Danville",
    "sg:classifiers":[
        {
            "category":"Professional",
            "subcategory":"Computer Services",
            "type":"Services"
        }
    ],
    "sg:phone":"+1 434 799 4611",
    "sg:postcode":"24541",
    "sg:province":"VA",
    "sg:tags":[
        "internet"
    ],
    "sg:website":"www.gamewood.net",
    "wof:name":"Gamewood Data Systems",
    "wof:placetype":"venue"
},
  "geometry": {"coordinates":[-79.402613,36.580006],"type":"Point"}
}