{
  "type": "Feature",
  "properties": {
    "addr:full":"230 Charwood Dr Abingdon VA 24210",
    "addr:housenumber":"230",
    "addr:postcode":"24210",
    "addr:street":"Charwood Dr",
    "iso:country":"US",
    "sg:address":"230 Charwood Dr",
    "sg:city":"Abingdon",
    "sg:classifiers":[
        {
            "category":"Professional",
            "subcategory":"Management & Consulting",
            "type":"Services"
        }
    ],
    "sg:phone":"+1 276 676 2200",
    "sg:postcode":"24210",
    "sg:province":"VA",
    "sg:tags":[
        "consultant",
        "rehabilitation"
    ],
    "wof:name":"Roi",
    "wof:placetype":"venue"
},
  "geometry": {"coordinates":[-82.005072,36.702182],"type":"Point"}
}