{
  "type": "Feature",
  "properties": {
    "addr:full":"2711 Verily Ct Oakton VA 22124",
    "addr:housenumber":"2711",
    "addr:postcode":"22124",
    "addr:street":"Verily Ct",
    "iso:country":"US",
    "sg:address":"2711 Verily Ct",
    "sg:city":"Oakton",
    "sg:classifiers":[
        {
            "category":"Professional",
            "subcategory":"Accounting & Tax Preparation",
            "type":"Services"
        }
    ],
    "sg:phone":"+1 703 648 3186",
    "sg:postcode":"22124",
    "sg:province":"VA",
    "wof:name":"Mary Ellen Bagley",
    "wof:placetype":"venue"
},
  "geometry": {"coordinates":[-77.328772,38.901985],"type":"Point"}
}