{
  "type": "Feature",
  "properties": {
    "iso:country":"US",
    "sg:address":"19 E Market St",
    "sg:city":"Leesburg",
    "sg:classifiers":[
        {
            "category":"Professional",
            "subcategory":"Lawyer & Legal Services",
            "type":"Services"
        }
    ],
    "sg:phone":"+1 703 779 0881",
    "sg:postcode":"20176",
    "sg:province":"VA",
    "wof:name":"Otto C Fiala",
    "wof:placetype":"venue"
},
  "geometry": {"coordinates":[-77.564342,39.115298],"type":"Point"}
}