{
  "type": "Feature",
  "properties": {
    "addr:full":"3901 Guest Ln Alexandria VA 22312",
    "addr:housenumber":"3901",
    "addr:postcode":"22312",
    "addr:street":"Guest Ln",
    "iso:country":"US",
    "sg:address":"3901 Guest Ln",
    "sg:city":"Alexandria",
    "sg:classifiers":[
        {
            "category":"Building & Trades",
            "subcategory":"Construction",
            "type":"Services"
        }
    ],
    "sg:phone":"+1 703 930 9532",
    "sg:postcode":"22312",
    "sg:province":"VA",
    "sg:tags":[
        "roofing",
        "industrial",
        "contractors-commercial",
        "contractor"
    ],
    "wof:name":"Fsr Roofing Contractor Inc",
    "wof:placetype":"venue"
},
  "geometry": {"coordinates":[-77.149384,38.839729],"type":"Point"}
}