{
  "type": "Feature",
  "properties": {
    "addr:full":"1656 Flammarion Dr Virginia Beach VA 23454",
    "addr:housenumber":"1656",
    "addr:postcode":"23454",
    "addr:street":"Flammarion Dr",
    "iso:country":"US",
    "sg:address":"1656 Flammarion Dr",
    "sg:city":"Virginia Beach",
    "sg:classifiers":[
        {
            "category":"Wholesale",
            "subcategory":"Medical Equipment & Supplies",
            "type":"Manufacturing & Wholesale Goods"
        }
    ],
    "sg:phone":"+1 757 425 2624",
    "sg:postcode":"23454",
    "sg:province":"VA",
    "sg:tags":[
        "hospital"
    ],
    "wof:name":"Radman Radiological Corp",
    "wof:placetype":"venue"
},
  "geometry": {"coordinates":[-75.986266,36.778353],"type":"Point"}
}