{
  "type": "Feature",
  "properties": {
    "addr:full":"207 W Shirley Ave Warrenton VA 20186",
    "addr:housenumber":"207",
    "addr:postcode":"20186",
    "addr:street":"W Shirley Ave",
    "iso:country":"US",
    "sg:address":"207 W Shirley Ave",
    "sg:city":"Warrenton",
    "sg:classifiers":[
        {
            "category":"Food & Beverages",
            "subcategory":"Groceries & Convenience Stores",
            "type":"Retail Goods"
        }
    ],
    "sg:phone":"+1 540 347 9350",
    "sg:postcode":"20186",
    "sg:province":"VA",
    "sg:website":"www.7-eleven.com",
    "wof:name":"7-Eleven Stores",
    "wof:placetype":"venue"
},
  "geometry": {"coordinates":[-77.804872,38.712481],"type":"Point"}
}