{
  "type": "Feature",
  "properties": {
    "addr:full":"416 S Jefferson St Roanoke VA 24011",
    "addr:housenumber":"416",
    "addr:postcode":"24011",
    "addr:street":"S Jefferson St",
    "iso:country":"US",
    "sg:address":"416 S Jefferson St",
    "sg:city":"Roanoke",
    "sg:classifiers":[
        {
            "category":"Real Estate",
            "subcategory":"Real Estate Agent",
            "type":"Services"
        }
    ],
    "sg:phone":"+1 540 344 6481",
    "sg:postcode":"24011",
    "sg:province":"VA",
    "sg:tags":[
        "desk",
        "space"
    ],
    "wof:name":"Boxley Building Trust",
    "wof:placetype":"venue"
},
  "geometry": {"coordinates":[-79.940523,37.269972],"type":"Point"}
}