{
  "type": "Feature",
  "properties": {
    "iso:country":"US",
    "sg:address":"464 S Union St",
    "sg:city":"Alexandria",
    "sg:classifiers":[
        {
            "category":"Professional",
            "subcategory":"Lawyer & Legal Services",
            "type":"Services"
        }
    ],
    "sg:phone":"+1 703 548 2272",
    "sg:postcode":"22314",
    "sg:province":"VA",
    "wof:name":"Kilcullen Law LLC",
    "wof:placetype":"venue"
},
  "geometry": {"coordinates":[-77.041161,38.799702],"type":"Point"}
}