{
  "type": "Feature",
  "properties": {
    "iso:country":"US",
    "sg:address":"224 S Alfred St",
    "sg:city":"Alexandria",
    "sg:classifiers":[
        {
            "category":"Utilities",
            "subcategory":"Telephone",
            "type":"Services"
        }
    ],
    "sg:phone":"+1 703 739 3444",
    "sg:postcode":"22314",
    "sg:province":"VA",
    "sg:tags":[
        "telecommunication"
    ],
    "wof:name":"Invertix",
    "wof:placetype":"venue"
},
  "geometry": {"coordinates":[-77.04956300000001,38.803338],"type":"Point"}
}