{
  "type": "Feature",
  "properties": {
    "addr:full":"14439 Jefferson Davis Hwy Woodbridge VA 22191",
    "addr:housenumber":"14439",
    "addr:postcode":"22191",
    "addr:street":"Jefferson Davis Hwy",
    "iso:country":"US",
    "sg:address":"14439 Jefferson Davis Hwy",
    "sg:city":"Woodbridge",
    "sg:classifiers":[
        {
            "category":"Home & Garden",
            "subcategory":"Furniture",
            "type":"Retail Goods"
        }
    ],
    "sg:phone":"+1 703 490 2277",
    "sg:postcode":"22191",
    "sg:province":"VA",
    "sg:tags":[
        "mattress"
    ],
    "wof:name":"Mattress For You Inc",
    "wof:placetype":"venue"
},
  "geometry": {"coordinates":[-77.267945,38.638578],"type":"Point"}
}