{
  "type": "Feature",
  "properties": {
    "iso:country":"US",
    "sg:address":"116 N Columbus St",
    "sg:city":"Arlington",
    "sg:classifiers":[
        {
            "category":"Building & Trades",
            "subcategory":"Plumbing",
            "type":"Services"
        }
    ],
    "sg:phone":"+1 703 351 9677",
    "sg:postcode":"22203",
    "sg:province":"VA",
    "sg:tags":[
        "contractor"
    ],
    "wof:name":"Potomac Climate Systems Inc",
    "wof:placetype":"venue"
},
  "geometry": {"coordinates":[-77.117665,38.868339],"type":"Point"}
}