{
  "type": "Feature",
  "properties": {
    "iso:country":"US",
    "sg:address":"4036 Lee Hwy",
    "sg:city":"Arlington",
    "sg:classifiers":[
        {
            "category":"Retail",
            "subcategory":"Laundry & Dry Cleaning",
            "type":"Services"
        }
    ],
    "sg:phone":"+1 703 525 8112",
    "sg:postcode":"22207",
    "sg:province":"VA",
    "wof:name":"Old Dominion Cleaners & Shirt Finishers",
    "wof:placetype":"venue"
},
  "geometry": {"coordinates":[-77.10880299999999,38.896999],"type":"Point"}
}