{
  "type": "Feature",
  "properties": {
    "iso:country":"US",
    "sg:address":"4100 Lafayette Center Dr",
    "sg:city":"Chantilly",
    "sg:classifiers":[
        {
            "category":"Wholesale",
            "subcategory":"Computers",
            "type":"Manufacturing & Wholesale Goods"
        }
    ],
    "sg:phone":"+1 703 961 1401",
    "sg:postcode":"20151",
    "sg:province":"VA",
    "sg:tags":[
        "software",
        "provider"
    ],
    "wof:name":"Guru Network Inc",
    "wof:placetype":"venue"
},
  "geometry": {"coordinates":[-77.471549,38.905],"type":"Point"}
}