{
  "type": "Feature",
  "properties": {
    "addr:full":"1474 V F W Rd West Point VA 23181",
    "addr:housenumber":"1474",
    "addr:postcode":"23181",
    "addr:street":"V F W Rd",
    "iso:country":"US",
    "sg:address":"1474 V F W Rd",
    "sg:city":"West Point",
    "sg:classifiers":[
        {
            "category":"Building & Trades",
            "subcategory":"Construction",
            "type":"Services"
        }
    ],
    "sg:phone":"+1 804 843 3832",
    "sg:postcode":"23181",
    "sg:province":"VA",
    "sg:tags":[
        "general",
        "contractor"
    ],
    "wof:name":"R & W Contractors",
    "wof:placetype":"venue"
},
  "geometry": {"coordinates":[-76.79943,37.543299],"type":"Point"}
}