{
  "type": "Feature",
  "properties": {
    "addr:full":"21492 Vances Mill Rd Abingdon VA 24211",
    "addr:housenumber":"21492",
    "addr:postcode":"24211",
    "addr:street":"Vances Mill Rd",
    "iso:country":"US",
    "sg:address":"21492 Vances Mill Rd",
    "sg:city":"Abingdon",
    "sg:classifiers":[
        {
            "category":"Retail",
            "subcategory":"Veterinary Services",
            "type":"Services"
        }
    ],
    "sg:phone":"+1 276 676 3401",
    "sg:postcode":"24211",
    "sg:province":"VA",
    "sg:tags":[
        "veterinarian"
    ],
    "wof:name":"Farm Success",
    "wof:placetype":"venue"
},
  "geometry": {"coordinates":[-81.980423,36.688024],"type":"Point"}
}