{
  "type": "Feature",
  "properties": {
    "addr:full":"255 Granby St Norfolk VA 23510",
    "addr:housenumber":"255",
    "addr:postcode":"23510",
    "addr:street":"Granby St",
    "iso:country":"US",
    "sg:address":"255 Granby St",
    "sg:city":"Norfolk",
    "sg:classifiers":[
        {
            "category":"Restaurant",
            "type":"Food & Drink"
        }
    ],
    "sg:phone":"+1 757 627 5800",
    "sg:postcode":"23510",
    "sg:province":"VA",
    "sg:tags":[
        "eating"
    ],
    "wof:name":"Havana",
    "wof:placetype":"venue"
},
  "geometry": {"coordinates":[-76.29055700000001,36.84992],"type":"Point"}
}