{
  "type": "Feature",
  "properties": {
    "addr:full":"711 W 21st St Norfolk VA 23517",
    "addr:housenumber":"711",
    "addr:postcode":"23517",
    "addr:street":"W 21St St",
    "iso:country":"US",
    "sg:address":"711 W 21st St",
    "sg:city":"Norfolk",
    "sg:classifiers":[
        {
            "category":"Real Estate",
            "subcategory":"Real Estate Agent",
            "type":"Services"
        }
    ],
    "sg:phone":"+1 757 623 3003",
    "sg:postcode":"23517",
    "sg:province":"VA",
    "sg:tags":[
        "management"
    ],
    "sg:website":"www.nancychandler.com",
    "wof:name":"Nancy Chandler Assoc",
    "wof:placetype":"venue"
},
  "geometry": {"coordinates":[-76.293965,36.869714],"type":"Point"}
}