{
  "type": "Feature",
  "properties": {
    "addr:full":"1138 Emmet St N Charlottesville VA 22903",
    "addr:housenumber":"1138",
    "addr:postcode":"22903",
    "addr:street":"Emmet St N",
    "iso:country":"US",
    "sg:address":"1138 Emmet St N",
    "sg:city":"Charlottesville",
    "sg:classifiers":[
        {
            "category":"Restaurant",
            "type":"Food & Drink"
        }
    ],
    "sg:menulink":"http://www.allmenus.com/va/charlottesville/256526-superstars-pizza/menu/",
    "sg:phone":"+1 434 923 3663",
    "sg:postcode":"22903",
    "sg:province":"VA",
    "sg:tags":[
        "american",
        "sandwich",
        "salad",
        "pizza"
    ],
    "wof:name":"Superstars Pizza",
    "wof:placetype":"venue"
},
  "geometry": {"coordinates":[-78.49979,38.051794],"type":"Point"}
}