{
  "type": "Feature",
  "properties": {
    "iso:country":"US",
    "sg:address":"9215 Midlothian Tpke",
    "sg:city":"Richmond",
    "sg:classifiers":[
        {
            "category":"Personal",
            "subcategory":"Beauty Salon",
            "type":"Services"
        }
    ],
    "sg:phone":"+1 804 320 7705",
    "sg:postcode":"23235",
    "sg:province":"VA",
    "sg:tags":[
        "shop"
    ],
    "wof:name":"Kats Hair Studio",
    "wof:placetype":"venue"
},
  "geometry": {"coordinates":[-77.56760199999999,37.497613],"type":"Point"}
}