{
  "type": "Feature",
  "properties": {
    "iso:country":"US",
    "sg:address":"118 W Bute St",
    "sg:city":"Norfolk",
    "sg:classifiers":[
        {
            "category":"Building & Trades",
            "subcategory":"Cleaning & Sanitation",
            "type":"Services"
        }
    ],
    "sg:phone":"+1 757 463 3434",
    "sg:postcode":"23510",
    "sg:province":"VA",
    "sg:tags":[
        "janitor"
    ],
    "wof:name":"Swif Tees Janitorial",
    "wof:placetype":"venue"
},
  "geometry": {"coordinates":[-76.289305,36.853066],"type":"Point"}
}