{
  "type": "Feature",
  "properties": {
    "iso:country":"US",
    "sg:address":"3113 W Marshall St",
    "sg:city":"Richmond",
    "sg:classifiers":[
        {
            "category":"Real Estate",
            "subcategory":"Real Estate Agent",
            "type":"Services"
        }
    ],
    "sg:phone":"+1 804 213 0011",
    "sg:postcode":"23230",
    "sg:province":"VA",
    "wof:name":"Sam Nelson Realtor",
    "wof:placetype":"venue"
},
  "geometry": {"coordinates":[-77.473783,37.56655],"type":"Point"}
}