{
  "type": "Feature",
  "properties": {
    "iso:country":"US",
    "sg:address":"3686 King St",
    "sg:city":"Alexandria",
    "sg:classifiers":[
        {
            "category":"Banks & Credit Unions",
            "subcategory":"Financial Services",
            "type":"Services"
        }
    ],
    "sg:phone":"+1 703 927 7356",
    "sg:postcode":"22302",
    "sg:province":"VA",
    "sg:tags":[
        "investor"
    ],
    "wof:name":"Sherman Ventures International",
    "wof:placetype":"venue"
},
  "geometry": {"coordinates":[-77.091859,38.830201],"type":"Point"}
}