{
  "type": "Feature",
  "properties": {
    "addr:full":"411 S Hicks St Lawrenceville VA 23868",
    "addr:housenumber":"411",
    "addr:postcode":"23868",
    "addr:street":"S Hicks St",
    "iso:country":"US",
    "sg:address":"411 S Hicks St",
    "sg:city":"Lawrenceville",
    "sg:classifiers":[
        {
            "category":"Banks & Credit Unions",
            "subcategory":"Bank",
            "type":"Services"
        }
    ],
    "sg:phone":"+1 434 848 8644",
    "sg:postcode":"23868",
    "sg:province":"VA",
    "sg:tags":[
        "loan",
        "real estate"
    ],
    "wof:name":"SLM Financial Corp",
    "wof:placetype":"venue"
},
  "geometry": {"coordinates":[-77.850622,36.754565],"type":"Point"}
}