{
  "type": "Feature",
  "properties": {
    "addr:full":"800 Elden St Herndon VA 20170",
    "addr:housenumber":"800",
    "addr:postcode":"20170",
    "addr:street":"Elden St",
    "iso:country":"US",
    "sg:address":"800 Elden St",
    "sg:city":"Herndon",
    "sg:classifiers":[
        {
            "category":"Organizations",
            "subcategory":"Religious Organization",
            "type":"Services"
        }
    ],
    "sg:phone":"+1 703 707 8433",
    "sg:postcode":"20170",
    "sg:province":"VA",
    "wof:name":"Corporation of President of Th",
    "wof:placetype":"venue"
},
  "geometry": {"coordinates":[-77.38946799999999,38.969471],"type":"Point"}
}