{
  "type": "Feature",
  "properties": {
    "iso:country":"US",
    "sg:address":"225 Century Pl",
    "sg:city":"Alexandria",
    "sg:classifiers":[
        {
            "category":"Building & Trades",
            "subcategory":"Construction",
            "type":"Services"
        }
    ],
    "sg:phone":"+1 703 461 0600",
    "sg:postcode":"22304",
    "sg:province":"VA",
    "sg:tags":[
        "painter"
    ],
    "wof:name":"WEB Painting",
    "wof:placetype":"venue"
},
  "geometry": {"coordinates":[-77.127387,38.816489],"type":"Point"}
}