{
  "type": "Feature",
  "properties": {
    "addr:full":"20364 Hartwell St Ashburn VA 20147",
    "addr:postcode":"20364;20147",
    "addr:street":"Hartwell St",
    "iso:country":"US",
    "sg:address":"20364 Hartwell St",
    "sg:city":"Ashburn",
    "sg:classifiers":[
        {
            "category":"Wholesale",
            "subcategory":"Machinery & Supplies",
            "type":"Manufacturing & Wholesale Goods"
        }
    ],
    "sg:phone":"+1 703 505 8409",
    "sg:postcode":"20147",
    "sg:province":"VA",
    "sg:tags":[
        "equipment",
        "industrial"
    ],
    "wof:name":"Dominion Handling Inc",
    "wof:placetype":"venue"
},
  "geometry": {"coordinates":[-77.516914,39.052741],"type":"Point"}
}