{
  "type": "Feature",
  "properties": {
    "iso:country":"US",
    "sg:address":"3943 Lawyer Rd",
    "sg:city":"Mc Gaheysville",
    "sg:classifiers":[
        {
            "category":"Farming",
            "subcategory":"Dairy Farm",
            "type":"Manufacturing & Wholesale Goods"
        }
    ],
    "sg:phone":"+1 540 289 9832",
    "sg:postcode":"22840",
    "sg:province":"VA",
    "wof:name":"Cub Run Dairy",
    "wof:placetype":"venue"
},
  "geometry": {"coordinates":[-78.76877899999999,38.335094],"type":"Point"}
}