{
  "type": "Feature",
  "properties": {
    "addr:full":"3590 Towne Point Rd Portsmouth VA 23703",
    "addr:housenumber":"3590",
    "addr:postcode":"23703",
    "addr:street":"Towne Point Rd",
    "iso:country":"US",
    "sg:address":"3590 Towne Point Rd",
    "sg:city":"Portsmouth",
    "sg:classifiers":[
        {
            "category":"Government",
            "subcategory":"Post Office",
            "type":"Public Place"
        }
    ],
    "sg:phone":"+1 757 484 8249",
    "sg:postcode":"23703",
    "sg:province":"VA",
    "sg:tags":[
        "postal",
        "us"
    ],
    "wof:name":"US Post Office",
    "wof:placetype":"venue"
},
  "geometry": {"coordinates":[-76.400289,36.866762],"type":"Point"}
}