{
  "type": "Feature",
  "properties": {
    "iso:country":"US",
    "sg:address":"6354 Walker Ln Ste 104",
    "sg:city":"Alexandria",
    "sg:classifiers":[
        {
            "category":"Deli",
            "type":"Food & Drink"
        }
    ],
    "sg:phone":"+1 703 924 3700",
    "sg:postcode":"22310",
    "sg:province":"VA",
    "sg:tags":[
        "delicatessen"
    ],
    "wof:name":"Metro Park Deli",
    "wof:placetype":"venue"
},
  "geometry": {"coordinates":[-77.159644,38.768996],"type":"Point"}
}