{
  "type": "Feature",
  "properties": {
    "addr:full":"12269 Livingston Rd Manassas VA 20109",
    "addr:housenumber":"12269",
    "addr:postcode":"20109",
    "addr:street":"Livingston Rd",
    "iso:country":"US",
    "sg:address":"12269 Livingston Rd",
    "sg:city":"Manassas",
    "sg:classifiers":[
        {
            "category":"Wholesale",
            "subcategory":"Machinery & Supplies",
            "type":"Manufacturing & Wholesale Goods"
        }
    ],
    "sg:phone":"+1 703 368 6808",
    "sg:postcode":"20109",
    "sg:province":"VA",
    "sg:tags":[
        "equipment",
        "establishment"
    ],
    "wof:name":"Kitchen Equipment Contractors",
    "wof:placetype":"venue"
},
  "geometry": {"coordinates":[-77.55506800000001,38.781785],"type":"Point"}
}