{
  "type": "Feature",
  "properties": {
    "addr:full":"936 Colleen Dr Newport News VA 23608",
    "addr:housenumber":"936",
    "addr:postcode":"23608",
    "addr:street":"Colleen Dr",
    "iso:country":"US",
    "sg:address":"936 Colleen Dr",
    "sg:city":"Newport News",
    "sg:classifiers":[
        {
            "category":"Retail",
            "subcategory":"Car Wash",
            "type":"Services"
        }
    ],
    "sg:phone":"+1 757 369 1386",
    "sg:postcode":"23608",
    "sg:province":"VA",
    "sg:tags":[
        "carwash"
    ],
    "wof:name":"A & G Detailing",
    "wof:placetype":"venue"
},
  "geometry": {"coordinates":[-76.557024,37.138039],"type":"Point"}
}