{
  "type": "Feature",
  "properties": {
    "addr:full":"1019 Shirley Ave Norfolk VA 23507",
    "addr:housenumber":"1019",
    "addr:postcode":"23507",
    "addr:street":"Shirley Ave",
    "iso:country":"US",
    "sg:address":"1019 Shirley Ave",
    "sg:city":"Norfolk",
    "sg:classifiers":[
        {
            "category":"Recreation",
            "type":"Entertainment"
        }
    ],
    "sg:phone":"+1 757 624 1348",
    "sg:postcode":"23507",
    "sg:province":"VA",
    "wof:name":"My Yoga Spirit",
    "wof:placetype":"venue"
},
  "geometry": {"coordinates":[-76.302246,36.868928],"type":"Point"}
}