{
  "type": "Feature",
  "properties": {
    "iso:country":"US",
    "sg:address":"1036 Jubal Early Dr",
    "sg:city":"Forest",
    "sg:classifiers":[
        {
            "category":"Professional",
            "type":"Services"
        }
    ],
    "sg:phone":"+1 434 534 6091",
    "sg:postcode":"24551",
    "sg:province":"VA",
    "wof:name":"Growers Nursery",
    "wof:placetype":"venue"
},
  "geometry": {"coordinates":[-79.30117300000001,37.305126],"type":"Point"}
}