{
  "type": "Feature",
  "properties": {
    "addr:full":"15274 Cloverdale Rd Woodbridge VA 22193",
    "addr:housenumber":"15274",
    "addr:postcode":"22193",
    "addr:street":"Cloverdale Rd",
    "iso:country":"US",
    "sg:address":"15274 Cloverdale Rd",
    "sg:city":"Woodbridge",
    "sg:classifiers":[
        {
            "category":"Food & Beverages",
            "subcategory":"Groceries & Convenience Stores",
            "type":"Retail Goods"
        }
    ],
    "sg:phone":"+1 703 670 0478",
    "sg:postcode":"22193",
    "sg:province":"VA",
    "wof:name":"Carolinas Food & Bread Distrs",
    "wof:placetype":"venue"
},
  "geometry": {"coordinates":[-77.314545,38.625872],"type":"Point"}
}