{
  "type": "Feature",
  "properties": {
    "addr:full":"12198 Crest Hill Rd Hume VA 22639",
    "addr:housenumber":"12198",
    "addr:postcode":"22639",
    "addr:street":"Crest Hill Rd",
    "iso:country":"US",
    "sg:address":"12198 Crest Hill Rd",
    "sg:city":"Hume",
    "sg:classifiers":[
        {
            "category":"Building & Trades",
            "subcategory":"Construction",
            "type":"Services"
        }
    ],
    "sg:phone":"+1 540 364 2054",
    "sg:postcode":"22639",
    "sg:province":"VA",
    "sg:tags":[
        "preparation",
        "residential",
        "market",
        "crop",
        "for"
    ],
    "wof:name":"Colonial Builders",
    "wof:placetype":"venue"
},
  "geometry": {"coordinates":[-78.008358,38.767624],"type":"Point"}
}