{
  "type": "Feature",
  "properties": {
    "addr:full":"3331 Lavender Rd Pulaski VA 24301",
    "addr:housenumber":"3331",
    "addr:postcode":"24301",
    "addr:street":"Lavender Rd",
    "iso:country":"US",
    "sg:address":"3331 Lavender Rd",
    "sg:city":"Pulaski",
    "sg:classifiers":[
        {
            "category":"Building & Trades",
            "subcategory":"Construction",
            "type":"Services"
        }
    ],
    "sg:phone":"+1 540 980 4663",
    "sg:postcode":"24301",
    "sg:province":"VA",
    "sg:tags":[
        "tank",
        "excavating",
        "installation",
        "septic",
        "grading"
    ],
    "wof:name":"Alfred L Hughett Cnstr Co",
    "wof:placetype":"venue"
},
  "geometry": {"coordinates":[-80.78746599999999,37.108501],"type":"Point"}
}