{
  "type": "Feature",
  "properties": {
    "addr:full":"12009 Corral Dr Fairfax Station VA 22039",
    "addr:housenumber":"12009",
    "addr:postcode":"22039",
    "addr:street":"Corral Dr",
    "iso:country":"US",
    "sg:address":"12009 Corral Dr",
    "sg:city":"Fairfax Station",
    "sg:classifiers":[
        {
            "category":"Professional",
            "subcategory":"Computer Services",
            "type":"Services"
        }
    ],
    "sg:phone":"+1 703 449 9795",
    "sg:postcode":"22039",
    "sg:province":"VA",
    "sg:tags":[
        "consulting",
        "technology"
    ],
    "wof:name":"Technlogy Design Resources LLC",
    "wof:placetype":"venue"
},
  "geometry": {"coordinates":[-77.362303,38.768497],"type":"Point"}
}