{
  "type": "Feature",
  "properties": {
    "addr:full":"15393 Mountain Spring Rd Abingdon VA 24210",
    "addr:housenumber":"15393",
    "addr:postcode":"24210",
    "addr:street":"Mountain Spring Rd",
    "iso:country":"US",
    "sg:address":"15393 Mountain Spring Rd",
    "sg:city":"Abingdon",
    "sg:classifiers":[
        {
            "category":"Building & Trades",
            "subcategory":"Construction",
            "type":"Services"
        }
    ],
    "sg:phone":"+1 276 676 2234",
    "sg:postcode":"24210",
    "sg:province":"VA",
    "sg:tags":[
        "house"
    ],
    "wof:name":"Russel Street",
    "wof:placetype":"venue"
},
  "geometry": {"coordinates":[-82.10409300000001,36.721128],"type":"Point"}
}