{
  "type": "Feature",
  "properties": {
    "addr:full":"605 Industrial Park Dr Newport News VA 23608",
    "addr:housenumber":"605",
    "addr:postcode":"23608",
    "addr:street":"Industrial Park Dr",
    "iso:country":"US",
    "sg:address":"605 Industrial Park Dr",
    "sg:city":"Newport News",
    "sg:classifiers":[
        {
            "category":"Retail",
            "subcategory":"Repair Shop",
            "type":"Services"
        }
    ],
    "sg:phone":"+1 757 874 7977",
    "sg:postcode":"23608",
    "sg:province":"VA",
    "sg:tags":[
        "upholstery",
        "refinishing",
        "restoration",
        "furniture"
    ],
    "wof:name":"Furniture By Lowell",
    "wof:placetype":"venue"
},
  "geometry": {"coordinates":[-76.541247,37.164676],"type":"Point"}
}