{
  "type": "Feature",
  "properties": {
    "addr:full":"6 E Nelson Ave Apt 208 Alexandria VA 22301",
    "addr:housenumber":"6;208",
    "addr:postcode":"22301",
    "addr:street":"E Nelson Ave Apt",
    "iso:country":"US",
    "sg:address":"6 E Nelson Ave Apt 208",
    "sg:city":"Alexandria",
    "sg:classifiers":[
        {
            "category":"Professional",
            "subcategory":"Advertising",
            "type":"Services"
        }
    ],
    "sg:phone":"+1 703 548 4745",
    "sg:postcode":"22301",
    "sg:province":"VA",
    "sg:tags":[
        "mail",
        "direct"
    ],
    "wof:name":"Congressional Communications Company",
    "wof:placetype":"venue"
},
  "geometry": {"coordinates":[-77.062836,38.819203],"type":"Point"}
}