{
  "type": "Feature",
  "properties": {
    "iso:country":"US",
    "sg:address":"508 Marston Dr",
    "sg:city":"Chesapeake",
    "sg:classifiers":[
        {
            "category":"Organizations",
            "subcategory":"Religious Organization",
            "type":"Services"
        }
    ],
    "sg:phone":"+1 757 482 6355",
    "sg:postcode":"23322",
    "sg:province":"VA",
    "wof:name":"Powerhouse Inc",
    "wof:placetype":"venue"
},
  "geometry": {"coordinates":[-76.209948,36.687202],"type":"Point"}
}