{
  "type": "Feature",
  "properties": {
    "iso:country":"US",
    "sg:address":"18504 Triangle St",
    "sg:city":"Triangle",
    "sg:classifiers":[
        {
            "category":"Building & Trades",
            "subcategory":"Construction",
            "type":"Services"
        }
    ],
    "sg:phone":"+1 703 221 9014",
    "sg:postcode":"22172",
    "sg:province":"VA",
    "sg:tags":[
        "house"
    ],
    "wof:name":"R & R Renovations",
    "wof:placetype":"venue"
},
  "geometry": {"coordinates":[-77.332883,38.550724],"type":"Point"}
}