{
  "type": "Feature",
  "properties": {
    "iso:country":"US",
    "sg:address":"4944 Ruth Rd",
    "sg:city":"Virginia Beach",
    "sg:classifiers":[
        {
            "category":"Building & Trades",
            "subcategory":"Construction",
            "type":"Services"
        }
    ],
    "sg:phone":"+1 757 495 4190",
    "sg:postcode":"23464",
    "sg:province":"VA",
    "sg:tags":[
        "hanging",
        "contractor"
    ],
    "wof:name":"Cr Designs",
    "wof:placetype":"venue"
},
  "geometry": {"coordinates":[-76.155961,36.800613],"type":"Point"}
}