{
  "type": "Feature",
  "properties": {
    "iso:country":"US",
    "sg:address":"619 W Cary St",
    "sg:city":"Richmond",
    "sg:classifiers":[
        {
            "category":"Real Estate",
            "subcategory":"Real Estate Agent",
            "type":"Services"
        }
    ],
    "sg:phone":"+1 804 644 4244",
    "sg:postcode":"23220",
    "sg:province":"VA",
    "sg:tags":[
        "housing",
        "low",
        "rent"
    ],
    "wof:name":"Oregon Hill Home Improvement",
    "wof:placetype":"venue"
},
  "geometry": {"coordinates":[-77.450307,37.544411],"type":"Point"}
}