{
  "type": "Feature",
  "properties": {
    "addr:full":"210 1st St SW Roanoke VA 24011",
    "addr:housenumber":"210",
    "addr:postcode":"24011",
    "addr:street":"1St St Sw",
    "iso:country":"US",
    "sg:address":"210 1st St SW",
    "sg:city":"Roanoke",
    "sg:classifiers":[
        {
            "category":"Government",
            "subcategory":"Court House",
            "type":"Public Place"
        }
    ],
    "sg:phone":"+1 540 857 6337",
    "sg:postcode":"24011",
    "sg:province":"VA",
    "sg:tags":[
        "legal"
    ],
    "wof:name":"Attorney General Office",
    "wof:placetype":"venue"
},
  "geometry": {"coordinates":[-79.942331,37.27126],"type":"Point"}
}