{
  "type": "Feature",
  "properties": {
    "iso:country":"US",
    "sg:address":"6207 Portsmouth Blvd",
    "sg:city":"Portsmouth",
    "sg:classifiers":[
        {
            "category":"Building & Trades",
            "subcategory":"Construction",
            "type":"Services"
        }
    ],
    "sg:phone":"+1 757 488 6022",
    "sg:postcode":"23701",
    "sg:province":"VA",
    "sg:tags":[
        "general",
        "contractor"
    ],
    "wof:name":"G R Bailey & Co Inc",
    "wof:placetype":"venue"
},
  "geometry": {"coordinates":[-76.389951,36.821173],"type":"Point"}
}