{
  "type": "Feature",
  "properties": {
    "addr:full":"43102 Kimberley Ct Leesburg VA 20176",
    "addr:postcode":"43102;20176",
    "addr:street":"Kimberley Ct",
    "iso:country":"US",
    "sg:address":"43102 Kimberley Ct",
    "sg:city":"Leesburg",
    "sg:classifiers":[
        {
            "category":"Professional",
            "subcategory":"Business Services",
            "type":"Services"
        }
    ],
    "sg:phone":"+1 703 771 0250",
    "sg:postcode":"20176",
    "sg:province":"VA",
    "wof:name":"Spradling Interior Design LLC",
    "wof:placetype":"venue"
},
  "geometry": {"coordinates":[-77.508663,39.090202],"type":"Point"}
}