{
  "type": "Feature",
  "properties": {
    "iso:country":"US",
    "sg:address":"14508 Telegraph Rd",
    "sg:city":"Woodbridge",
    "sg:classifiers":[
        {
            "category":"Organizations",
            "subcategory":"Religious Organization",
            "type":"Services"
        }
    ],
    "sg:phone":"+1 703 492 7172",
    "sg:postcode":"22192",
    "sg:province":"VA",
    "sg:tags":[
        "church"
    ],
    "wof:name":"Ebenezer Presbyterian Church",
    "wof:placetype":"venue"
},
  "geometry": {"coordinates":[-77.290479,38.640319],"type":"Point"}
}