{
  "type": "Feature",
  "properties": {
    "addr:full":"3515 N Washington Blvd Arlington VA 22201",
    "addr:housenumber":"3515",
    "addr:postcode":"22201",
    "addr:street":"N Washington Blvd",
    "iso:country":"US",
    "sg:address":"3515 N Washington Blvd",
    "sg:city":"Arlington",
    "sg:classifiers":[
        {
            "category":"Real Estate",
            "subcategory":"Real Estate Agent",
            "type":"Services"
        },
        {
            "category":"Real Estate",
            "subcategory":"Real Estate Operator",
            "type":"Services"
        }
    ],
    "sg:phone":"+1 703 525 6096",
    "sg:postcode":"22201",
    "sg:province":"VA",
    "sg:tags":[
        "condominium"
    ],
    "wof:name":"Wentworth Place Condominiums",
    "wof:placetype":"venue"
},
  "geometry": {"coordinates":[-77.1046,38.886174],"type":"Point"}
}