{
  "type": "Feature",
  "properties": {
    "addr:full":"10200 Kings Hwy King George VA 22485",
    "addr:housenumber":"10200",
    "addr:postcode":"22485",
    "addr:street":"Kings Hwy",
    "iso:country":"US",
    "sg:address":"10200 Kings Hwy",
    "sg:city":"King George",
    "sg:classifiers":[
        {
            "category":"Shopping",
            "subcategory":"Used Merchandise",
            "type":"Retail Goods"
        }
    ],
    "sg:phone":"+1 540 775 2111",
    "sg:postcode":"22485",
    "sg:province":"VA",
    "wof:name":"C & C Variety",
    "wof:placetype":"venue"
},
  "geometry": {"coordinates":[-77.16963800000001,38.26274],"type":"Point"}
}