{
  "type": "Feature",
  "properties": {
    "addr:full":"1025 Seneca Rd Great Falls VA 22066",
    "addr:housenumber":"1025",
    "addr:postcode":"22066",
    "addr:street":"Seneca Rd",
    "iso:country":"US",
    "sg:address":"1025 Seneca Rd",
    "sg:city":"Great Falls",
    "sg:classifiers":[
        {
            "category":"Professional",
            "subcategory":"Management & Consulting",
            "type":"Services"
        },
        {
            "category":"Shopping",
            "subcategory":"Bicycles & Sporting Goods",
            "type":"Retail Goods"
        }
    ],
    "sg:phone":"+1 703 404 2800",
    "sg:postcode":"22066",
    "sg:province":"VA",
    "sg:tags":[
        "repair"
    ],
    "wof:name":"Pedal -N- Spoke Inc",
    "wof:placetype":"venue"
},
  "geometry": {"coordinates":[-77.34413499999999,39.00106],"type":"Point"}
}