{
  "type": "Feature",
  "properties": {
    "addr:full":"3219 Fall Hill Ave Fredericksburg VA 22401",
    "addr:housenumber":"3219",
    "addr:postcode":"22401",
    "addr:street":"Fall Hill Ave",
    "iso:country":"US",
    "sg:address":"3219 Fall Hill Ave",
    "sg:city":"Fredericksburg",
    "sg:classifiers":[
        {
            "category":"Recreation",
            "type":"Entertainment"
        }
    ],
    "sg:phone":"+1 540 373 1030",
    "sg:postcode":"22401",
    "sg:province":"VA",
    "sg:tags":[
        "sporting"
    ],
    "wof:name":"Scuba Shack",
    "wof:placetype":"venue"
},
  "geometry": {"coordinates":[-77.483012,38.316481],"type":"Point"}
}