{
  "type": "Feature",
  "properties": {
    "iso:country":"US",
    "sg:address":"1068 Riverside Dr",
    "sg:city":"Danville",
    "sg:classifiers":[
        {
            "category":"Recreation",
            "type":"Entertainment"
        }
    ],
    "sg:phone":"+1 434 792 0120",
    "sg:postcode":"24540",
    "sg:province":"VA",
    "sg:tags":[
        "instruction",
        "gymnastic"
    ],
    "wof:name":"Blue Ridge Gynmastics Academy",
    "wof:placetype":"venue"
},
  "geometry": {"coordinates":[-79.402305,36.596412],"type":"Point"}
}