{
  "type": "Feature",
  "properties": {
    "iso:country":"US",
    "sg:address":"1810 Melbourne Dr",
    "sg:city":"Mc Lean",
    "sg:classifiers":[
        {
            "category":"Professional",
            "subcategory":"Management & Consulting",
            "type":"Services"
        }
    ],
    "sg:phone":"+1 703 356 8881",
    "sg:postcode":"22101",
    "sg:province":"VA",
    "sg:tags":[
        "business"
    ],
    "wof:name":"Frank M Mc Dermott Ltd",
    "wof:placetype":"venue"
},
  "geometry": {"coordinates":[-77.177369,38.917225],"type":"Point"}
}