{
  "type": "Feature",
  "properties": {
    "addr:full":"9202 Venture Ct Manassas Park VA 20111",
    "addr:housenumber":"9202",
    "addr:postcode":"20111",
    "addr:street":"Venture Ct;Park",
    "iso:country":"US",
    "sg:address":"9202 Venture Ct",
    "sg:city":"Manassas Park",
    "sg:classifiers":[
        {
            "category":"Freight",
            "type":"Transportation"
        }
    ],
    "sg:phone":"+1 703 257 2255",
    "sg:postcode":"20111",
    "sg:province":"VA",
    "sg:tags":[
        "delivery"
    ],
    "wof:name":"Alma International",
    "wof:placetype":"venue"
},
  "geometry": {"coordinates":[-77.43864600000001,38.77021],"type":"Point"}
}