{
  "type": "Feature",
  "properties": {
    "addr:full":"2453 Mineral Springs Rd Boydton VA 23917",
    "addr:housenumber":"2453",
    "addr:postcode":"23917",
    "addr:street":"Mineral Springs Rd",
    "iso:country":"US",
    "sg:address":"2453 Mineral Springs Rd",
    "sg:city":"Boydton",
    "sg:classifiers":[
        {
            "category":"Professional",
            "subcategory":"Management & Consulting",
            "type":"Services"
        }
    ],
    "sg:phone":"+1 434 689 2299",
    "sg:postcode":"23917",
    "sg:province":"VA",
    "wof:name":"Harts Transportation",
    "wof:placetype":"venue"
},
  "geometry": {"coordinates":[-78.220591,36.586362],"type":"Point"}
}