{
  "type": "Feature",
  "properties": {
    "addr:full":"4725 W Ox Rd Fairfax VA 22030",
    "addr:housenumber":"4725",
    "addr:postcode":"22030",
    "addr:street":"W Ox Rd",
    "iso:country":"US",
    "sg:address":"4725 W Ox Rd",
    "sg:city":"Fairfax",
    "sg:classifiers":[
        {
            "category":"Health Services",
            "subcategory":"Optometrist",
            "type":"Services"
        }
    ],
    "sg:phone":"+1 703 266 8245",
    "sg:postcode":"22030",
    "sg:province":"VA",
    "wof:name":"Premier Optometric Svc",
    "wof:placetype":"venue"
},
  "geometry": {"coordinates":[-77.373396,38.847771],"type":"Point"}
}