{
  "type": "Feature",
  "properties": {
    "iso:country":"US",
    "sg:address":"5116 Donovan Dr",
    "sg:city":"Alexandria",
    "sg:classifiers":[
        {
            "category":"Professional",
            "subcategory":"Business Services",
            "type":"Services"
        }
    ],
    "sg:phone":"+1 703 370 5253",
    "sg:postcode":"22304",
    "sg:province":"VA",
    "sg:tags":[
        "interior",
        "decorator"
    ],
    "wof:name":"Paula Klein Design",
    "wof:placetype":"venue"
},
  "geometry": {"coordinates":[-77.12041000000001,38.809502],"type":"Point"}
}