{
  "type": "Feature",
  "properties": {
    "addr:full":"6333 Covered Bridge Rd Gladys VA 24554",
    "addr:housenumber":"6333",
    "addr:postcode":"24554",
    "addr:street":"Covered Bridge Rd",
    "iso:country":"US",
    "sg:address":"6333 Covered Bridge Rd",
    "sg:city":"Gladys",
    "sg:classifiers":[
        {
            "category":"Building & Trades",
            "subcategory":"Landscaping Services",
            "type":"Services"
        }
    ],
    "sg:phone":"+1 434 283 5296",
    "sg:postcode":"24554",
    "sg:province":"VA",
    "sg:tags":[
        "lawn"
    ],
    "wof:name":"Altavista Lawn Care",
    "wof:placetype":"venue"
},
  "geometry": {"coordinates":[-79.173149,37.091991],"type":"Point"}
}