{
  "type": "Feature",
  "properties": {
    "iso:country":"US",
    "sg:address":"1236 Carpers Pike",
    "sg:city":"Gore",
    "sg:classifiers":[
        {
            "category":"Building & Trades",
            "subcategory":"Construction",
            "type":"Services"
        }
    ],
    "sg:phone":"+1 540 858 2768",
    "sg:postcode":"22637",
    "sg:province":"VA",
    "sg:tags":[
        "carpentry",
        "contractor"
    ],
    "wof:name":"J Coots Carpentry",
    "wof:placetype":"venue"
},
  "geometry": {"coordinates":[-78.374155,39.245952],"type":"Point"}
}