{
  "type": "Feature",
  "properties": {
    "iso:country":"US",
    "sg:address":"1961 Chain Bridge Rd",
    "sg:city":"Mc Lean",
    "sg:classifiers":[
        {
            "category":"Shopping",
            "subcategory":"Department Store",
            "type":"Retail Goods"
        }
    ],
    "sg:phone":"+1 703 556 4600",
    "sg:postcode":"22102",
    "sg:province":"VA",
    "wof:name":"Bloomingdale's",
    "wof:placetype":"venue"
},
  "geometry": {"coordinates":[-77.226226,38.919716],"type":"Point"}
}