{
  "type": "Feature",
  "properties": {
    "addr:full":"24385 Rogers Clark Blvd Ruther Glen VA 22546",
    "addr:housenumber":"24385",
    "addr:postcode":"22546",
    "addr:street":"Rogers Clark Blvd",
    "iso:country":"US",
    "sg:address":"24385 Rogers Clark Blvd",
    "sg:city":"Ruther Glen",
    "sg:classifiers":[
        {
            "category":"Shopping",
            "subcategory":"Used Merchandise",
            "type":"Retail Goods"
        }
    ],
    "sg:phone":"+1 804 448 8547",
    "sg:postcode":"22546",
    "sg:province":"VA",
    "sg:tags":[
        "flea",
        "market"
    ],
    "wof:name":"Carmel Church Flea Market",
    "wof:placetype":"venue"
},
  "geometry": {"coordinates":[-77.477953,37.932029],"type":"Point"}
}