{
  "type": "Feature",
  "properties": {
    "addr:full":"17957 Rinker Rd Broadway VA 22815",
    "addr:postcode":"17957;22815",
    "addr:street":"Rinker Rd",
    "iso:country":"US",
    "sg:address":"17957 Rinker Rd",
    "sg:city":"Broadway",
    "sg:classifiers":[
        {
            "category":"Building & Trades",
            "subcategory":"Construction",
            "type":"Services"
        }
    ],
    "sg:phone":"+1 540 896 1412",
    "sg:postcode":"22815",
    "sg:province":"VA",
    "sg:tags":[
        "contractor"
    ],
    "wof:name":"Baer Tile Contractor",
    "wof:placetype":"venue"
},
  "geometry": {"coordinates":[-78.830032,38.692898],"type":"Point"}
}