{
  "type": "Feature",
  "properties": {
    "iso:country":"US",
    "sg:address":"148 Heritage Pointe",
    "sg:city":"Williamsburg",
    "sg:classifiers":[
        {
            "category":"Professional",
            "subcategory":"Lawyer & Legal Services",
            "type":"Services"
        }
    ],
    "sg:phone":"+1 757 253 7626",
    "sg:postcode":"23188",
    "sg:province":"VA",
    "wof:name":"James N McCune",
    "wof:placetype":"venue"
},
  "geometry": {"coordinates":[-76.757368,37.28491],"type":"Point"}
}