{
  "type": "Feature",
  "properties": {
    "addr:full":"4435 Waterfront Dr Glen Allen VA 23060",
    "addr:housenumber":"4435",
    "addr:postcode":"23060",
    "addr:street":"Waterfront Dr",
    "iso:country":"US",
    "sg:address":"4435 Waterfront Dr",
    "sg:city":"Glen Allen",
    "sg:classifiers":[
        {
            "category":"Professional",
            "type":"Services"
        }
    ],
    "sg:phone":"+1 804 747 9698",
    "sg:postcode":"23060",
    "sg:province":"VA",
    "sg:tags":[
        "establishment"
    ],
    "sg:website":"www.aamcn.org",
    "wof:name":"American Assn Of Managed Care",
    "wof:placetype":"venue"
},
  "geometry": {"coordinates":[-77.579798,37.657993],"type":"Point"}
}