{
  "type": "Feature",
  "properties": {
    "addr:full":"14094 Rixeyville Rd Culpeper VA 22701",
    "addr:housenumber":"14094",
    "addr:postcode":"22701",
    "addr:street":"Rixeyville Rd",
    "iso:country":"US",
    "sg:address":"14094 Rixeyville Rd",
    "sg:city":"Culpeper",
    "sg:classifiers":[
        {
            "category":"Professional",
            "type":"Services"
        }
    ],
    "sg:phone":"+1 540 825 6386",
    "sg:postcode":"22701",
    "sg:province":"VA",
    "sg:tags":[
        "establishment"
    ],
    "wof:name":"G T & B Inc",
    "wof:placetype":"venue"
},
  "geometry": {"coordinates":[-77.987972,38.509629],"type":"Point"}
}