{
  "type": "Feature",
  "properties": {
    "addr:full":"10175 Glebe Rd Orange VA 22960",
    "addr:housenumber":"10175",
    "addr:postcode":"22960",
    "addr:street":"Glebe Rd",
    "iso:country":"US",
    "sg:address":"10175 Glebe Rd",
    "sg:city":"Orange",
    "sg:classifiers":[
        {
            "category":"Professional",
            "subcategory":"Engineering",
            "type":"Services"
        }
    ],
    "sg:phone":"+1 540 672 0675",
    "sg:postcode":"22960",
    "sg:province":"VA",
    "wof:name":"Cmw LLC",
    "wof:placetype":"venue"
},
  "geometry": {"coordinates":[-78.11941899999999,38.266323],"type":"Point"}
}