{
  "type": "Feature",
  "properties": {
    "addr:full":"3122 W Marshall St Ste 1 Richmond VA 23230",
    "addr:housenumber":"3122",
    "addr:postcode":"23230",
    "addr:street":"W Marshall St Ste 1",
    "iso:country":"US",
    "sg:address":"3122 W Marshall St Ste 1",
    "sg:city":"Richmond",
    "sg:classifiers":[
        {
            "category":"Retail",
            "subcategory":"Driving School",
            "type":"Services"
        }
    ],
    "sg:phone":"+1 804 342 8080",
    "sg:postcode":"23230",
    "sg:province":"VA",
    "sg:tags":[
        "instruction",
        "traffic"
    ],
    "wof:name":"B & M Driving Improvement",
    "wof:placetype":"venue"
},
  "geometry": {"coordinates":[-77.47307499999999,37.566079],"type":"Point"}
}