{
  "type": "Feature",
  "properties": {
    "iso:country":"US",
    "sg:address":"631 W Main St",
    "sg:city":"Purcellville",
    "sg:classifiers":[
        {
            "category":"Food & Beverages",
            "subcategory":"Specialty",
            "type":"Retail Goods"
        }
    ],
    "sg:phone":"+1 540 338 7156",
    "sg:postcode":"20132",
    "sg:province":"VA",
    "sg:tags":[
        "water",
        "bulk",
        "company"
    ],
    "wof:name":"Loudoun Milk Transportation",
    "wof:placetype":"venue"
},
  "geometry": {"coordinates":[-77.724963,39.137368],"type":"Point"}
}