{
  "type": "Feature",
  "properties": {
    "addr:full":"408 Cheadle Loop Rd Seaford VA 23696",
    "addr:housenumber":"408",
    "addr:postcode":"23696",
    "addr:street":"Cheadle Loop Rd",
    "iso:country":"US",
    "sg:address":"408 Cheadle Loop Rd",
    "sg:city":"Seaford",
    "sg:classifiers":[
        {
            "category":"Building & Trades",
            "subcategory":"Cleaning & Sanitation",
            "type":"Services"
        }
    ],
    "sg:phone":"+1 757 898 4481",
    "sg:postcode":"23696",
    "sg:province":"VA",
    "sg:tags":[
        "fireplace",
        "chimney"
    ],
    "wof:name":"Olde Virginia Chimney Sweeps",
    "wof:placetype":"venue"
},
  "geometry": {"coordinates":[-76.42921,37.185948],"type":"Point"}
}