{
  "type": "Feature",
  "properties": {
    "iso:country":"US",
    "sg:address":"12702 Jefferson Davis Hwy",
    "sg:city":"Chester",
    "sg:classifiers":[
        {
            "category":"Recreation",
            "type":"Entertainment"
        }
    ],
    "sg:phone":"+1 804 777 9700",
    "sg:postcode":"23831",
    "sg:province":"VA",
    "sg:tags":[
        "karate",
        "judo",
        "instr"
    ],
    "wof:name":"U S Taekwondo College",
    "wof:placetype":"venue"
},
  "geometry": {"coordinates":[-77.412496,37.352683],"type":"Point"}
}