{
  "type": "Feature",
  "properties": {
    "iso:country":"US",
    "sg:address":"17 Michaels Woods Dr",
    "sg:city":"Hampton",
    "sg:classifiers":[
        {
            "category":"Banks & Credit Unions",
            "subcategory":"Financial Services",
            "type":"Services"
        }
    ],
    "sg:phone":"+1 757 896 0788",
    "sg:postcode":"23666",
    "sg:province":"VA",
    "sg:tags":[
        "company",
        "holding"
    ],
    "wof:name":"W M D & Associates Inc",
    "wof:placetype":"venue"
},
  "geometry": {"coordinates":[-76.44058200000001,37.057024],"type":"Point"}
}