{
  "type": "Feature",
  "properties": {
    "addr:full":"508 W Main St Appalachia VA 24216",
    "addr:housenumber":"508",
    "addr:postcode":"24216",
    "addr:street":"W Main St",
    "iso:country":"US",
    "sg:address":"508 W Main St",
    "sg:city":"Appalachia",
    "sg:classifiers":[
        {
            "category":"Health Services",
            "subcategory":"Doctor",
            "type":"Services"
        }
    ],
    "sg:phone":"+1 276 565 2203",
    "sg:postcode":"24216",
    "sg:province":"VA",
    "sg:tags":[
        "physician",
        "surgeon"
    ],
    "wof:name":"Center For Pain Control",
    "wof:placetype":"venue"
},
  "geometry": {"coordinates":[-82.783929,36.904222],"type":"Point"}
}