{
  "type": "Feature",
  "properties": {
    "addr:full":"4310 Old Nottingham Rd Quinton VA 23141",
    "addr:housenumber":"4310",
    "addr:postcode":"23141",
    "addr:street":"Old Nottingham Rd",
    "iso:country":"US",
    "sg:address":"4310 Old Nottingham Rd",
    "sg:city":"Quinton",
    "sg:classifiers":[
        {
            "category":"Professional",
            "subcategory":"Business Services",
            "type":"Services"
        }
    ],
    "sg:phone":"+1 804 932 5257",
    "sg:postcode":"23141",
    "sg:province":"VA",
    "wof:name":"Idea Design Group Inc",
    "wof:placetype":"venue"
},
  "geometry": {"coordinates":[-77.14729,37.516402],"type":"Point"}
}