{
  "type": "Feature",
  "properties": {
    "addr:full":"8811 Weir St Manassas VA 20110",
    "addr:housenumber":"8811",
    "addr:postcode":"20110",
    "addr:street":"Weir St",
    "iso:country":"US",
    "sg:address":"8811 Weir St",
    "sg:city":"Manassas",
    "sg:classifiers":[
        {
            "category":"Health Services",
            "subcategory":"Health Practitioner",
            "type":"Services"
        }
    ],
    "sg:phone":"+1 703 368 7357",
    "sg:postcode":"20110",
    "sg:province":"VA",
    "sg:tags":[
        "pathologist",
        "speech"
    ],
    "wof:name":"Speech Pathology Conslnt Svc",
    "wof:placetype":"venue"
},
  "geometry": {"coordinates":[-77.474215,38.763926],"type":"Point"}
}