{
  "type": "Feature",
  "properties": {
    "addr:full":"14000 Post Oak Rd Spotsylvania VA 22553",
    "addr:housenumber":"14000",
    "addr:postcode":"22553",
    "addr:street":"Post Oak Rd",
    "iso:country":"US",
    "sg:address":"14000 Post Oak Rd",
    "sg:city":"Spotsylvania",
    "sg:classifiers":[
        {
            "category":"Retail",
            "subcategory":"Repair Shop",
            "type":"Services"
        }
    ],
    "sg:phone":"+1 540 854 6537",
    "sg:postcode":"22553",
    "sg:province":"VA",
    "sg:tags":[
        "upholsterer"
    ],
    "wof:name":"Harding's Upholstery",
    "wof:placetype":"venue"
},
  "geometry": {"coordinates":[-77.817415,38.217103],"type":"Point"}
}