{
  "type": "Feature",
  "properties": {
    "addr:full":"105 Perrymont Ave Lynchburg VA 24502",
    "addr:housenumber":"105",
    "addr:postcode":"24502",
    "addr:street":"Perrymont Ave",
    "iso:country":"US",
    "sg:address":"105 Perrymont Ave",
    "sg:city":"Lynchburg",
    "sg:classifiers":[
        {
            "category":"Retail",
            "subcategory":"Car Wash",
            "type":"Services"
        }
    ],
    "sg:phone":"+1 434 444 1016",
    "sg:postcode":"24502",
    "sg:province":"VA",
    "sg:tags":[
        "carwash"
    ],
    "wof:name":"Diamond Mobile Car Wash",
    "wof:placetype":"venue"
},
  "geometry": {"coordinates":[-79.189013,37.391513],"type":"Point"}
}