{
  "type": "Feature",
  "properties": {
    "addr:full":"7608 Amherst Dr Manassas VA 20111",
    "addr:housenumber":"7608",
    "addr:postcode":"20111",
    "addr:street":"Amherst Dr",
    "iso:country":"US",
    "sg:address":"7608 Amherst Dr",
    "sg:city":"Manassas",
    "sg:classifiers":[
        {
            "category":"Retail",
            "subcategory":"Pet Boarding",
            "type":"Services"
        }
    ],
    "sg:phone":"+1 703 361 6865",
    "sg:postcode":"20111",
    "sg:province":"VA",
    "sg:tags":[
        "boarding/pet",
        "sitting"
    ],
    "wof:name":"K N K Pet Sitting",
    "wof:placetype":"venue"
},
  "geometry": {"coordinates":[-77.474197,38.791],"type":"Point"}
}