{
  "type": "Feature",
  "properties": {
    "iso:country":"US",
    "sg:address":"10937 Lee Hwy",
    "sg:city":"Fairfax",
    "sg:classifiers":[
        {
            "category":"Home & Garden",
            "subcategory":"Home Furnishings",
            "type":"Retail Goods"
        },
        {
            "category":"Insurance",
            "subcategory":"Health Insurance",
            "type":"Services"
        }
    ],
    "sg:phone":"+1 703 279 1000",
    "sg:postcode":"22030",
    "sg:province":"VA",
    "sg:tags":[
        "kitchen",
        "plan",
        "accessory"
    ],
    "wof:name":"Kitchen & Bath Gallery Inc",
    "wof:placetype":"venue"
},
  "geometry": {"coordinates":[-77.322982,38.852776],"type":"Point"}
}