{
  "type": "Feature",
  "properties": {
    "addr:full":"601 Shenandoah Village Dr Waynesboro VA 22980",
    "addr:housenumber":"601",
    "addr:postcode":"22980",
    "addr:street":"Shenandoah Village Dr",
    "iso:country":"US",
    "sg:address":"601 Shenandoah Village Dr",
    "sg:city":"Waynesboro",
    "sg:classifiers":[
        {
            "category":"Home & Garden",
            "subcategory":"Building Materials",
            "type":"Retail Goods"
        }
    ],
    "sg:phone":"+1 540 949 8453",
    "sg:postcode":"22980",
    "sg:province":"VA",
    "sg:tags":[
        "merchandise"
    ],
    "wof:name":"Tile Vision",
    "wof:placetype":"venue"
},
  "geometry": {"coordinates":[-78.942624,38.058859],"type":"Point"}
}