{
  "type": "Feature",
  "properties": {
    "iso:country":"US",
    "sg:address":"4 Bickel Ct",
    "sg:city":"Sterling",
    "sg:classifiers":[
        {
            "category":"Professional",
            "type":"Services"
        }
    ],
    "sg:phone":"+1 703 421 9511",
    "sg:postcode":"20165",
    "sg:province":"VA",
    "wof:name":"Nora Fitzgerald",
    "wof:placetype":"venue"
},
  "geometry": {"coordinates":[-77.422196,39.050403],"type":"Point"}
}