{
  "type": "Feature",
  "properties": {
    "iso:country":"US",
    "sg:address":"182 Ireson St",
    "sg:city":"Danville",
    "sg:classifiers":[
        {
            "category":"Retail",
            "subcategory":"Repair Shop",
            "type":"Services"
        }
    ],
    "sg:phone":"+1 434 791 3021",
    "sg:postcode":"24541",
    "sg:province":"VA",
    "wof:name":"Precision Duct Cleaning",
    "wof:placetype":"venue"
},
  "geometry": {"coordinates":[-79.466391,36.563913],"type":"Point"}
}