{
  "type": "Feature",
  "properties": {
    "iso:country":"US",
    "sg:address":"2250 Clarendon Blvd",
    "sg:city":"Arlington",
    "sg:classifiers":[
        {
            "category":"Real Estate",
            "subcategory":"Real Estate Services",
            "type":"Services"
        },
        {
            "category":"Real Estate",
            "subcategory":"Real Estate Operator",
            "type":"Services"
        }
    ],
    "sg:phone":"+1 866 512 2913",
    "sg:postcode":"22201",
    "sg:province":"VA",
    "sg:tags":[
        "apartment",
        "property",
        "management"
    ],
    "sg:website":"www.CourthousePlaza.com",
    "wof:name":"Archstone Courthouse Plaza",
    "wof:placetype":"venue"
},
  "geometry": {"coordinates":[-77.086709,38.890298],"type":"Point"}
}