{
  "type": "Feature",
  "properties": {
    "addr:full":"5509 Luxford Ct Glen Allen VA 23059",
    "addr:housenumber":"5509",
    "addr:postcode":"23059",
    "addr:street":"Luxford Ct",
    "iso:country":"US",
    "sg:address":"5509 Luxford Ct",
    "sg:city":"Glen Allen",
    "sg:classifiers":[
        {
            "category":"Retail",
            "subcategory":"Auto Repair",
            "type":"Services"
        }
    ],
    "sg:phone":"+1 804 937 2981",
    "sg:postcode":"23059",
    "sg:province":"VA",
    "sg:tags":[
        "general"
    ],
    "wof:name":"Bender Auto Service",
    "wof:placetype":"venue"
},
  "geometry": {"coordinates":[-77.61515799999999,37.685387],"type":"Point"}
}