{
  "type": "Feature",
  "properties": {
    "addr:full":"1680 Huguenot Rd Midlothian VA 23113",
    "addr:housenumber":"1680",
    "addr:postcode":"23113",
    "addr:street":"Huguenot Rd",
    "iso:country":"US",
    "sg:address":"1680 Huguenot Rd",
    "sg:city":"Midlothian",
    "sg:classifiers":[
        {
            "category":"Health Services",
            "subcategory":"Doctor",
            "type":"Services"
        }
    ],
    "sg:phone":"+1 804 379 7120",
    "sg:postcode":"23113",
    "sg:province":"VA",
    "sg:tags":[
        "dentist"
    ],
    "sg:website":"www.rocs.net",
    "wof:name":"Richmond Oral & Cosmetic Srgns",
    "wof:placetype":"venue"
},
  "geometry": {"coordinates":[-77.61506799999999,37.513962],"type":"Point"}
}