{
  "type": "Feature",
  "properties": {
    "addr:full":"550 N Commerce Ave Waynesboro VA 22980",
    "addr:housenumber":"550",
    "addr:postcode":"22980",
    "addr:street":"N Commerce Ave",
    "iso:country":"US",
    "sg:address":"550 N Commerce Ave",
    "sg:city":"Waynesboro",
    "sg:classifiers":[
        {
            "category":"Professional",
            "subcategory":"Art Services",
            "type":"Services"
        }
    ],
    "sg:phone":"+1 540 949 8139",
    "sg:postcode":"22980",
    "sg:province":"VA",
    "sg:tags":[
        "graphic",
        "designer"
    ],
    "sg:website":"www.mcclungco.com",
    "wof:name":"Mc Clung Co",
    "wof:placetype":"venue"
},
  "geometry": {"coordinates":[-78.873468,38.072694],"type":"Point"}
}