{
  "type": "Feature",
  "properties": {
    "iso:country":"US",
    "sg:address":"4254 Hungry Run Rd",
    "sg:city":"The Plains",
    "sg:classifiers":[
        {
            "category":"Professional",
            "subcategory":"Management & Consulting",
            "type":"Services"
        }
    ],
    "sg:phone":"+1 703 754 8690",
    "sg:postcode":"20198",
    "sg:province":"VA",
    "wof:name":"Coral Seas Inc",
    "wof:placetype":"venue"
},
  "geometry": {"coordinates":[-77.684138,38.907717],"type":"Point"}
}