{
  "type": "Feature",
  "properties": {
    "addr:full":"12000 Winfree St Chester VA 23831",
    "addr:postcode":"12000;23831",
    "addr:street":"Winfree St",
    "iso:country":"US",
    "sg:address":"12000 Winfree St",
    "sg:city":"Chester",
    "sg:classifiers":[
        {
            "category":"Home & Garden",
            "subcategory":"Home Furnishings",
            "type":"Retail Goods"
        }
    ],
    "sg:phone":"+1 804 748 8392",
    "sg:postcode":"23831",
    "sg:province":"VA",
    "sg:tags":[
        "curtain",
        "made",
        "drapery"
    ],
    "wof:name":"Country Store",
    "wof:placetype":"venue"
},
  "geometry": {"coordinates":[-77.441604,37.35691],"type":"Point"}
}