{
  "type": "Feature",
  "properties": {
    "iso:country":"US",
    "sg:address":"2914 Old Glory Rd",
    "sg:city":"Virginia Beach",
    "sg:classifiers":[
        {
            "category":"Freight",
            "type":"Transportation"
        }
    ],
    "sg:phone":"+1 757 468 2153",
    "sg:postcode":"23453",
    "sg:province":"VA",
    "sg:tags":[
        "operator",
        "local",
        "trucking"
    ],
    "wof:name":"R & E Trucking Inc",
    "wof:placetype":"venue"
},
  "geometry": {"coordinates":[-76.07047900000001,36.803227],"type":"Point"}
}