{
  "type": "Feature",
  "properties": {
    "addr:full":"3696 US Hwy 29 Bus Danville VA 24540",
    "addr:housenumber":"3696",
    "addr:postcode":"24540",
    "addr:street":"Us Hwy 29 Bus",
    "iso:country":"US",
    "sg:address":"3696 US Hwy 29 Bus",
    "sg:city":"Danville",
    "sg:classifiers":[
        {
            "category":"Insurance",
            "subcategory":"Insurance Agent",
            "type":"Services"
        }
    ],
    "sg:phone":"+1 434 836 0431",
    "sg:postcode":"24540",
    "sg:province":"VA",
    "wof:name":"National Agents Alliance",
    "wof:placetype":"venue"
},
  "geometry": {"coordinates":[-79.37609399999999,36.657367],"type":"Point"}
}