{
  "type": "Feature",
  "properties": {
    "iso:country":"US",
    "sg:address":"4347 Rock Creek Rd",
    "sg:city":"Alexandria",
    "sg:classifiers":[
        {
            "category":"Retail",
            "subcategory":"Portrait Studio",
            "type":"Services"
        }
    ],
    "sg:phone":"+1 703 768 2157",
    "sg:postcode":"22306",
    "sg:province":"VA",
    "sg:tags":[
        "photographer"
    ],
    "wof:name":"A Focus By Hopkins",
    "wof:placetype":"venue"
},
  "geometry": {"coordinates":[-77.108673,38.768028],"type":"Point"}
}