{
  "type": "Feature",
  "properties": {
    "iso:country":"US",
    "sg:address":"4711 24th Rd N",
    "sg:city":"Arlington",
    "sg:classifiers":[
        {
            "category":"Real Estate",
            "subcategory":"Architect",
            "type":"Services"
        }
    ],
    "sg:phone":"+1 703 243 8283",
    "sg:postcode":"22207",
    "sg:province":"VA",
    "wof:name":"Gregory D Torchio",
    "wof:placetype":"venue"
},
  "geometry": {"coordinates":[-77.123554,38.901823],"type":"Point"}
}