{
  "type": "Feature",
  "properties": {
    "addr:full":"2000 Maidens Rd Maidens VA 23102",
    "addr:housenumber":"2000",
    "addr:postcode":"23102",
    "addr:street":"Maidens Rd",
    "iso:country":"US",
    "sg:address":"2000 Maidens Rd",
    "sg:city":"Maidens",
    "sg:classifiers":[
        {
            "category":"Retail",
            "subcategory":"Veterinary Services",
            "type":"Services"
        }
    ],
    "sg:phone":"+1 804 556 5566",
    "sg:postcode":"23102",
    "sg:province":"VA",
    "wof:name":"Goochland Animal Clinic",
    "wof:placetype":"venue"
},
  "geometry": {"coordinates":[-77.860699,37.702111],"type":"Point"}
}