{
  "type": "Feature",
  "properties": {
    "addr:full":"9323 Midlothian Tpke Richmond VA 23235",
    "addr:housenumber":"9323",
    "addr:postcode":"23235",
    "addr:street":"Midlothian Tpke",
    "iso:country":"US",
    "sg:address":"9323 Midlothian Tpke",
    "sg:city":"Richmond",
    "sg:classifiers":[
        {
            "category":"Organizations",
            "subcategory":"Non-profit Organization",
            "type":"Services"
        },
        {
            "category":"Health Services",
            "subcategory":"Hospital",
            "type":"Services"
        }
    ],
    "sg:phone":"+1 804 560 5400",
    "sg:postcode":"23235",
    "sg:province":"VA",
    "sg:tags":[
        "information",
        "treatment",
        "alcoholism",
        "specialty"
    ],
    "wof:name":"Recovery Center of Richmond",
    "wof:placetype":"venue"
},
  "geometry": {"coordinates":[-77.569374,37.498854],"type":"Point"}
}