{
  "type": "Feature",
  "properties": {
    "iso:country":"US",
    "sg:address":"217 E Luray Ave",
    "sg:city":"Alexandria",
    "sg:classifiers":[
        {
            "category":"Shopping",
            "type":"Retail Goods"
        }
    ],
    "sg:phone":"+1 703 549 7939",
    "sg:postcode":"22301",
    "sg:province":"VA",
    "sg:tags":[
        "merchandise"
    ],
    "wof:name":"Spa Solutions",
    "wof:placetype":"venue"
},
  "geometry": {"coordinates":[-77.058498,38.817715],"type":"Point"}
}