{
  "type": "Feature",
  "properties": {
    "addr:full":"947 Jouett Dr Newport News VA 23608",
    "addr:housenumber":"947",
    "addr:postcode":"23608",
    "addr:street":"Jouett Dr",
    "iso:country":"US",
    "sg:address":"947 Jouett Dr",
    "sg:city":"Newport News",
    "sg:classifiers":[
        {
            "category":"Insurance",
            "subcategory":"Hazard Insurance",
            "type":"Services"
        }
    ],
    "sg:phone":"+1 757 234 4536",
    "sg:postcode":"23608",
    "sg:province":"VA",
    "sg:tags":[
        "bond"
    ],
    "wof:name":"Michael's Bail Bond Co",
    "wof:placetype":"venue"
},
  "geometry": {"coordinates":[-76.50944200000001,37.155251],"type":"Point"}
}