{
  "type": "Feature",
  "properties": {
    "addr:full":"814 E Main St Richmond VA 23219",
    "addr:housenumber":"814",
    "addr:postcode":"23219",
    "addr:street":"E Main St",
    "iso:country":"US",
    "sg:address":"814 E Main St",
    "sg:city":"Richmond",
    "sg:classifiers":[
        {
            "category":"Travel",
            "subcategory":"Hotels & Motels",
            "type":"Entertainment"
        }
    ],
    "sg:phone":"+1 804 344 8121",
    "sg:postcode":"23219",
    "sg:province":"VA",
    "sg:website":"www.applehospitality.com",
    "wof:name":"Apple Suites",
    "wof:placetype":"venue"
},
  "geometry": {"coordinates":[-77.436364,37.538352],"type":"Point"}
}