{
  "type": "Feature",
  "properties": {
    "iso:country":"US",
    "sg:address":"120 Wyck St",
    "sg:city":"Richmond",
    "sg:classifiers":[
        {
            "category":"Local Transit",
            "type":"Transportation"
        }
    ],
    "sg:phone":"+1 804 276 4310",
    "sg:postcode":"23225",
    "sg:province":"VA",
    "sg:tags":[
        "passenger"
    ],
    "wof:name":"City Link Inc",
    "wof:placetype":"venue"
},
  "geometry": {"coordinates":[-77.523465,37.503545],"type":"Point"}
}