{
  "type": "Feature",
  "properties": {
    "addr:full":"2882 Chevoit Hill Ct Woodbridge VA 22191",
    "addr:housenumber":"2882",
    "addr:postcode":"22191",
    "addr:street":"Chevoit Hill Ct",
    "iso:country":"US",
    "sg:address":"2882 Chevoit Hill Ct",
    "sg:city":"Woodbridge",
    "sg:classifiers":[
        {
            "category":"Professional",
            "type":"Services"
        }
    ],
    "sg:phone":"+1 703 445 9446",
    "sg:postcode":"22191",
    "sg:province":"VA",
    "wof:name":"Faram LLC",
    "wof:placetype":"venue"
},
  "geometry": {"coordinates":[-77.300291,38.585101],"type":"Point"}
}