{
  "type": "Feature",
  "properties": {
    "addr:full":"8985 Hersand Dr Burke VA 22015",
    "addr:housenumber":"8985",
    "addr:postcode":"22015",
    "addr:street":"Hersand Dr",
    "iso:country":"US",
    "sg:address":"8985 Hersand Dr",
    "sg:city":"Burke",
    "sg:classifiers":[
        {
            "category":"Wholesale",
            "subcategory":"Office Equipment",
            "type":"Manufacturing & Wholesale Goods"
        }
    ],
    "sg:phone":"+1 703 534 0969",
    "sg:postcode":"22015",
    "sg:province":"VA",
    "sg:tags":[
        "register",
        "cash",
        "supply"
    ],
    "wof:name":"Datasyst",
    "wof:placetype":"venue"
},
  "geometry": {"coordinates":[-77.256467,38.809005],"type":"Point"}
}