{
  "type": "Feature",
  "properties": {
    "addr:full":"913 Grove Rd Midlothian VA 23114",
    "addr:housenumber":"913",
    "addr:postcode":"23114",
    "addr:street":"Grove Rd",
    "iso:country":"US",
    "sg:address":"913 Grove Rd",
    "sg:city":"Midlothian",
    "sg:classifiers":[
        {
            "category":"Food & Beverages",
            "subcategory":"Specialty",
            "type":"Retail Goods"
        }
    ],
    "sg:phone":"+1 804 794 7900",
    "sg:postcode":"23114",
    "sg:province":"VA",
    "wof:name":"Natures Nutrition Center",
    "wof:placetype":"venue"
},
  "geometry": {"coordinates":[-77.614985,37.502248],"type":"Point"}
}