{
  "type": "Feature",
  "properties": {
    "iso:country":"US",
    "sg:address":"5601 Seminary Rd",
    "sg:city":"Falls Church",
    "sg:classifiers":[
        {
            "category":"Organizations",
            "subcategory":"Religious Organization",
            "type":"Services"
        }
    ],
    "sg:phone":"+1 703 824 3673",
    "sg:postcode":"22041",
    "sg:province":"VA",
    "wof:name":"Dove of Life Ministries Inc",
    "wof:placetype":"venue"
},
  "geometry": {"coordinates":[-77.12451799999999,38.846019],"type":"Point"}
}