{
  "type": "Feature",
  "properties": {
    "addr:full":"6923 N Hairpin Dr Quinton VA 23141",
    "addr:housenumber":"6923",
    "addr:postcode":"23141",
    "addr:street":"N Hairpin Dr",
    "iso:country":"US",
    "sg:address":"6923 N Hairpin Dr",
    "sg:city":"Quinton",
    "sg:classifiers":[
        {
            "category":"Real Estate",
            "subcategory":"Real Estate Services",
            "type":"Services"
        }
    ],
    "sg:phone":"+1 804 932 5402",
    "sg:postcode":"23141",
    "sg:province":"VA",
    "sg:tags":[
        "company",
        "title"
    ],
    "wof:name":"Cool Settlement & Title Svc",
    "wof:placetype":"venue"
},
  "geometry": {"coordinates":[-77.166111,37.50099],"type":"Point"}
}