{
  "type": "Feature",
  "properties": {
    "addr:full":"120 Aero Dr Waynesboro VA 22980",
    "addr:housenumber":"120",
    "addr:postcode":"22980",
    "addr:street":"Aero Dr",
    "iso:country":"US",
    "sg:address":"120 Aero Dr",
    "sg:city":"Waynesboro",
    "sg:classifiers":[
        {
            "category":"Organizations",
            "subcategory":"Religious Organization",
            "type":"Services"
        }
    ],
    "sg:phone":"+1 540 942 9594",
    "sg:postcode":"22980",
    "sg:province":"VA",
    "sg:tags":[
        "clergy"
    ],
    "wof:name":"D W Hines",
    "wof:placetype":"venue"
},
  "geometry": {"coordinates":[-78.935733,38.082123],"type":"Point"}
}