{
  "type": "Feature",
  "properties": {
    "addr:full":"10426 Knotty Pine Ln Glen Allen VA 23059",
    "addr:housenumber":"10426",
    "addr:postcode":"23059",
    "addr:street":"Knotty Pine Ln",
    "iso:country":"US",
    "sg:address":"10426 Knotty Pine Ln",
    "sg:city":"Glen Allen",
    "sg:classifiers":[
        {
            "category":"Building & Trades",
            "subcategory":"Plumbing",
            "type":"Services"
        }
    ],
    "sg:phone":"+1 804 798 0561",
    "sg:postcode":"23059",
    "sg:province":"VA",
    "sg:tags":[
        "heat",
        "pump"
    ],
    "wof:name":"Cimco Inc",
    "wof:placetype":"venue"
},
  "geometry": {"coordinates":[-77.46866900000001,37.703085],"type":"Point"}
}