{
  "type": "Feature",
  "properties": {
    "addr:full":"4940 Rutherford Dr Virginia Beach VA 23455",
    "addr:housenumber":"4940",
    "addr:postcode":"23455",
    "addr:street":"Rutherford Dr",
    "iso:country":"US",
    "sg:address":"4940 Rutherford Dr",
    "sg:city":"Virginia Beach",
    "sg:classifiers":[
        {
            "category":"Building & Trades",
            "subcategory":"Construction",
            "type":"Services"
        }
    ],
    "sg:phone":"+1 757 460 3224",
    "sg:postcode":"23455",
    "sg:province":"VA",
    "sg:tags":[
        "painter"
    ],
    "wof:name":"Wrenn Painting Svc",
    "wof:placetype":"venue"
},
  "geometry": {"coordinates":[-76.143441,36.893613],"type":"Point"}
}