{
  "type": "Feature",
  "properties": {
    "iso:country":"US",
    "sg:address":"160 Park St SE",
    "sg:city":"Abingdon",
    "sg:classifiers":[
        {
            "category":"Sports & Exercise",
            "subcategory":"Gym",
            "type":"Entertainment"
        }
    ],
    "sg:phone":"+1 276 623 5239",
    "sg:postcode":"24210",
    "sg:province":"VA",
    "sg:tags":[
        "fitness",
        "physical",
        "facility"
    ],
    "wof:name":"Maximum Health & Fitness",
    "wof:placetype":"venue"
},
  "geometry": {"coordinates":[-81.97095899999999,36.710641],"type":"Point"}
}