{
  "type": "Feature",
  "properties": {
    "iso:country":"US",
    "sg:address":"2511 Jefferson Davis Hwy",
    "sg:city":"Arlington",
    "sg:classifiers":[
        {
            "category":"Deli",
            "type":"Food & Drink"
        },
        {
            "category":"Restaurant",
            "type":"Food & Drink"
        }
    ],
    "sg:phone":"+1 703 418 1002",
    "sg:postcode":"22202",
    "sg:province":"VA",
    "sg:tags":[
        "delicatessen"
    ],
    "wof:name":"Opportunities For The Blind",
    "wof:placetype":"venue"
},
  "geometry": {"coordinates":[-77.052667,38.852573],"type":"Point"}
}