{
  "type": "Feature",
  "properties": {
    "addr:full":"4507 Exeter St Annandale VA 22003",
    "addr:housenumber":"4507",
    "addr:postcode":"22003",
    "addr:street":"Exeter St",
    "iso:country":"US",
    "sg:address":"4507 Exeter St",
    "sg:city":"Annandale",
    "sg:classifiers":[
        {
            "category":"Building & Trades",
            "subcategory":"Construction",
            "type":"Services"
        }
    ],
    "sg:phone":"+1 703 941 0580",
    "sg:postcode":"22003",
    "sg:province":"VA",
    "sg:tags":[
        "general",
        "contractor"
    ],
    "wof:name":"A V C Construction",
    "wof:placetype":"venue"
},
  "geometry": {"coordinates":[-77.18951300000001,38.825863],"type":"Point"}
}