{
  "type": "Feature",
  "properties": {
    "addr:full":"12356 Lima Ln Reston VA 20191",
    "addr:housenumber":"12356",
    "addr:postcode":"20191",
    "addr:street":"Lima Ln",
    "iso:country":"US",
    "sg:address":"12356 Lima Ln",
    "sg:city":"Reston",
    "sg:classifiers":[
        {
            "category":"Professional",
            "type":"Services"
        }
    ],
    "sg:phone":"+1 703 295 0941",
    "sg:postcode":"20191",
    "sg:province":"VA",
    "wof:name":"John Fliegel",
    "wof:placetype":"venue"
},
  "geometry": {"coordinates":[-77.371865,38.932007],"type":"Point"}
}