{
  "type": "Feature",
  "properties": {
    "iso:country":"US",
    "sg:address":"21 E Washington St",
    "sg:city":"Middleburg",
    "sg:classifiers":[
        {
            "category":"Shopping",
            "subcategory":"Clothing, Apparel, & Fashions",
            "type":"Retail Goods"
        }
    ],
    "sg:phone":"+1 540 687 3686",
    "sg:postcode":"20117",
    "sg:province":"VA",
    "sg:tags":[
        "furnishing"
    ],
    "wof:name":"English Country Classic",
    "wof:placetype":"venue"
},
  "geometry": {"coordinates":[-77.734386,38.969328],"type":"Point"}
}