{
  "type": "Feature",
  "properties": {
    "addr:full":"1023 Virginia Ave Portsmouth VA 23707",
    "addr:housenumber":"1023",
    "addr:postcode":"23707",
    "addr:street":"Virginia Ave",
    "iso:country":"US",
    "sg:address":"1023 Virginia Ave",
    "sg:city":"Portsmouth",
    "sg:classifiers":[
        {
            "category":"Building & Trades",
            "subcategory":"Construction",
            "type":"Services"
        }
    ],
    "sg:phone":"+1 757 399 3340",
    "sg:postcode":"23707",
    "sg:province":"VA",
    "sg:tags":[
        "sheet",
        "metal",
        "contractor"
    ],
    "wof:name":"United Sheet Metal",
    "wof:placetype":"venue"
},
  "geometry": {"coordinates":[-76.33079499999999,36.837739],"type":"Point"}
}