{
  "type": "Feature",
  "properties": {
    "iso:country":"US",
    "sg:address":"866 Vine St",
    "sg:city":"Herndon",
    "sg:classifiers":[
        {
            "category":"Real Estate",
            "subcategory":"Real Estate Agent",
            "type":"Services"
        }
    ],
    "sg:phone":"+1 703 810 8490",
    "sg:postcode":"20170",
    "sg:province":"VA",
    "wof:name":"Nachman Real Estate Services",
    "wof:placetype":"venue"
},
  "geometry": {"coordinates":[-77.391216,38.970687],"type":"Point"}
}