{
  "type": "Feature",
  "properties": {
    "iso:country":"US",
    "sg:address":"105 Pipe Kiln Ct",
    "sg:city":"Williamsburg",
    "sg:classifiers":[
        {
            "category":"Shopping",
            "subcategory":"Catalog Store",
            "type":"Retail Goods"
        }
    ],
    "sg:phone":"+1 757 229 4096",
    "sg:postcode":"23185",
    "sg:province":"VA",
    "sg:tags":[
        "electronic",
        "an",
        "through",
        "mail",
        "marine",
        "order"
    ],
    "wof:name":"Indigo Electronics Inc",
    "wof:placetype":"venue"
},
  "geometry": {"coordinates":[-76.720392,37.259318],"type":"Point"}
}