{
  "type": "Feature",
  "properties": {
    "iso:country":"US",
    "sg:address":"610 Pedigo Ridge Rd",
    "sg:city":"Claudville",
    "sg:classifiers":[
        {
            "category":"Home & Garden",
            "subcategory":"Building Materials",
            "type":"Retail Goods"
        }
    ],
    "sg:phone":"+1 276 251 5186",
    "sg:postcode":"24053",
    "sg:province":"VA",
    "wof:name":"Slates Logging & Lumber",
    "wof:placetype":"venue"
},
  "geometry": {"coordinates":[-80.531435,36.56733],"type":"Point"}
}