{
  "type": "Feature",
  "properties": {
    "addr:full":"5417 19th St N Arlington VA 22205",
    "addr:housenumber":"5417",
    "addr:postcode":"22205",
    "addr:street":"19Th St N",
    "iso:country":"US",
    "sg:address":"5417 19th St N",
    "sg:city":"Arlington",
    "sg:classifiers":[
        {
            "category":"Professional",
            "subcategory":"Management & Consulting",
            "type":"Services"
        }
    ],
    "sg:phone":"+1 703 536 3091",
    "sg:postcode":"22205",
    "sg:province":"VA",
    "sg:tags":[
        "marketing",
        "social"
    ],
    "wof:name":"Lynne Doner",
    "wof:placetype":"venue"
},
  "geometry": {"coordinates":[-77.13326000000001,38.890581],"type":"Point"}
}