{
  "type": "Feature",
  "properties": {
    "addr:full":"1281 Good Luck Rd Lancaster VA 22503",
    "addr:housenumber":"1281",
    "addr:postcode":"22503",
    "addr:street":"Good Luck Rd",
    "iso:country":"US",
    "sg:address":"1281 Good Luck Rd",
    "sg:city":"Lancaster",
    "sg:classifiers":[
        {
            "category":"Wholesale",
            "subcategory":"Construction Materials",
            "type":"Manufacturing & Wholesale Goods"
        }
    ],
    "sg:phone":"+1 804 435 6486",
    "sg:postcode":"22503",
    "sg:province":"VA",
    "sg:tags":[
        "tank",
        "system",
        "septic"
    ],
    "wof:name":"Delmarva Septic Solutions In",
    "wof:placetype":"venue"
},
  "geometry": {"coordinates":[-76.37157500000001,37.742383],"type":"Point"}
}