{
  "type": "Feature",
  "properties": {
    "addr:full":"402 W Main St Louisa VA 23093",
    "addr:housenumber":"402",
    "addr:postcode":"23093",
    "addr:street":"W Main St",
    "iso:country":"US",
    "sg:address":"402 W Main St",
    "sg:city":"Louisa",
    "sg:classifiers":[
        {
            "category":"Shopping",
            "subcategory":"Gifts & Souvenirs",
            "type":"Retail Goods"
        }
    ],
    "sg:phone":"+1 540 967 5009",
    "sg:postcode":"23093",
    "sg:province":"VA",
    "sg:tags":[
        "shop"
    ],
    "wof:name":"Memories On Main",
    "wof:placetype":"venue"
},
  "geometry": {"coordinates":[-78.014146,38.028292],"type":"Point"}
}