{
  "type": "Feature",
  "properties": {
    "addr:full":"2401 Lee Hwy Pulaski VA 24301",
    "addr:housenumber":"2401",
    "addr:postcode":"24301",
    "addr:street":"Lee Hwy",
    "iso:country":"US",
    "sg:address":"2401 Lee Hwy",
    "sg:city":"Pulaski",
    "sg:classifiers":[
        {
            "category":"Health Services",
            "subcategory":"Nursing And Care Facility",
            "type":"Services"
        }
    ],
    "sg:phone":"+1 540 980 8535",
    "sg:postcode":"24301",
    "sg:province":"VA",
    "sg:tags":[
        "home",
        "retirement",
        "community"
    ],
    "wof:name":"Pulaski Retirement Community",
    "wof:placetype":"venue"
},
  "geometry": {"coordinates":[-80.757228,37.070079],"type":"Point"}
}