{
  "type": "Feature",
  "properties": {
    "addr:full":"905 Quarry Rd Berryville VA 22611",
    "addr:housenumber":"905",
    "addr:postcode":"22611",
    "addr:street":"Quarry Rd",
    "iso:country":"US",
    "sg:address":"905 Quarry Rd",
    "sg:city":"Berryville",
    "sg:classifiers":[
        {
            "category":"Wholesale",
            "subcategory":"Wine & Distilled Alcoholic Beverages",
            "type":"Manufacturing & Wholesale Goods"
        }
    ],
    "sg:phone":"+1 540 955 5510",
    "sg:postcode":"22611",
    "sg:province":"VA",
    "wof:name":"Veramar Vineyard",
    "wof:placetype":"venue"
},
  "geometry": {"coordinates":[-77.91089100000001,39.129357],"type":"Point"}
}