{
  "type": "Feature",
  "properties": {
    "addr:full":"1933 Daniel Stuart Sq Woodbridge VA 22191",
    "addr:housenumber":"1933",
    "addr:postcode":"22191",
    "addr:street":"Daniel Stuart Sq",
    "iso:country":"US",
    "sg:address":"1933 Daniel Stuart Sq",
    "sg:city":"Woodbridge",
    "sg:classifiers":[
        {
            "category":"Restaurant",
            "type":"Food & Drink"
        }
    ],
    "sg:phone":"+1 703 491 1172",
    "sg:postcode":"22191",
    "sg:province":"VA",
    "sg:tags":[
        "eating"
    ],
    "wof:name":"Carry Ginas Out",
    "wof:placetype":"venue"
},
  "geometry": {"coordinates":[-77.273752,38.631677],"type":"Point"}
}