{
  "type": "Feature",
  "properties": {
    "iso:country":"US",
    "sg:address":"1108 High St E",
    "sg:city":"Charlottesville",
    "sg:classifiers":[
        {
            "category":"Professional",
            "subcategory":"Art Services",
            "type":"Services"
        }
    ],
    "sg:phone":"+1 434 977 3903",
    "sg:postcode":"22902",
    "sg:province":"VA",
    "sg:tags":[
        "graphic",
        "designer"
    ],
    "sg:website":"www.birchstudio.com",
    "wof:name":"Birch Studio Graphics",
    "wof:placetype":"venue"
},
  "geometry": {"coordinates":[-78.46844299999999,38.031847],"type":"Point"}
}