{
  "type": "Feature",
  "properties": {
    "iso:country":"US",
    "sg:address":"500 Lafayette Blvd",
    "sg:city":"Fredericksburg",
    "sg:classifiers":[
        {
            "category":"Insurance",
            "subcategory":"Insurance Agent",
            "type":"Services"
        }
    ],
    "sg:phone":"+1 540 371 4488",
    "sg:postcode":"22401",
    "sg:province":"VA",
    "sg:tags":[
        "processing"
    ],
    "sg:website":"www.samedical.com",
    "wof:name":"S A Medical Reimbursement",
    "wof:placetype":"venue"
},
  "geometry": {"coordinates":[-77.459569,38.297472],"type":"Point"}
}