{
  "type": "Feature",
  "properties": {
    "addr:full":"120 Wagner Rd Petersburg VA 23805",
    "addr:housenumber":"120",
    "addr:postcode":"23805",
    "addr:street":"Wagner Rd",
    "iso:country":"US",
    "sg:address":"120 Wagner Rd",
    "sg:city":"Petersburg",
    "sg:classifiers":[
        {
            "category":"Government",
            "subcategory":"Office",
            "type":"Public Place"
        }
    ],
    "sg:phone":"+1 804 732 6493",
    "sg:postcode":"23805",
    "sg:province":"VA",
    "sg:tags":[
        "state",
        "program"
    ],
    "wof:name":"Motor Vehicle Dept",
    "wof:placetype":"venue"
},
  "geometry": {"coordinates":[-77.36603100000001,37.189501],"type":"Point"}
}