{
  "type": "Feature",
  "properties": {
    "iso:country":"US",
    "sg:address":"8350 Plum Grove Dr",
    "sg:city":"Mechanicsville",
    "sg:classifiers":[
        {
            "category":"Professional",
            "subcategory":"Business Services",
            "type":"Services"
        }
    ],
    "sg:phone":"+1 804 559 4379",
    "sg:postcode":"23111",
    "sg:province":"VA",
    "sg:tags":[
        "lumber",
        "broker"
    ],
    "wof:name":"Richmond Lumber Co Inc",
    "wof:placetype":"venue"
},
  "geometry": {"coordinates":[-77.34695499999999,37.635901],"type":"Point"}
}