{
  "type": "Feature",
  "properties": {
    "addr:full":"17851 General Puller Hwy Deltaville VA 23043",
    "addr:housenumber":"17851",
    "addr:postcode":"23043",
    "addr:street":"General Puller Hwy",
    "iso:country":"US",
    "sg:address":"17851 General Puller Hwy",
    "sg:city":"Deltaville",
    "sg:classifiers":[
        {
            "category":"Autos & Motor Vehicles",
            "subcategory":"Auto Supplies",
            "type":"Retail Goods"
        }
    ],
    "sg:phone":"+1 804 776 6781",
    "sg:postcode":"23043",
    "sg:province":"VA",
    "sg:tags":[
        "automobile",
        "parts"
    ],
    "wof:name":"A & N Svc Ctr Inc",
    "wof:placetype":"venue"
},
  "geometry": {"coordinates":[-76.328352,37.555066],"type":"Point"}
}