{
  "type": "Feature",
  "properties": {
    "addr:full":"8065 Fancy Gap Hwy Fancy Gap VA 24328",
    "addr:housenumber":"8065",
    "addr:postcode":"24328",
    "addr:street":"Fancy Gap Hwy",
    "iso:country":"US",
    "sg:address":"8065 Fancy Gap Hwy",
    "sg:city":"Fancy Gap",
    "sg:classifiers":[
        {
            "category":"Shopping",
            "subcategory":"Used Merchandise",
            "type":"Retail Goods"
        },
        {
            "category":"Wholesale",
            "subcategory":"Non-durable Goods",
            "type":"Manufacturing & Wholesale Goods"
        }
    ],
    "sg:phone":"+1 276 728 0556",
    "sg:postcode":"24328",
    "sg:province":"VA",
    "sg:tags":[
        "antique"
    ],
    "wof:name":"Susan S Trading Post",
    "wof:placetype":"venue"
},
  "geometry": {"coordinates":[-80.693079,36.659878],"type":"Point"}
}