{
  "type": "Feature",
  "properties": {
    "iso:country":"US",
    "sg:address":"600 N Main St",
    "sg:city":"Woodstock",
    "sg:classifiers":[
        {
            "category":"Government",
            "subcategory":"Office",
            "type":"Public Place"
        }
    ],
    "sg:phone":"+1 540 459 6226",
    "sg:postcode":"22664",
    "sg:province":"VA",
    "sg:tags":[
        "county",
        "resource"
    ],
    "wof:name":"Shenandoah County Social Svc",
    "wof:placetype":"venue"
},
  "geometry": {"coordinates":[-78.499937,38.888573],"type":"Point"}
}