{
  "type": "Feature",
  "properties": {
    "addr:full":"1603 White Cedar Ln Richmond VA 23235",
    "addr:housenumber":"1603",
    "addr:postcode":"23235",
    "addr:street":"White Cedar Ln",
    "iso:country":"US",
    "sg:address":"1603 White Cedar Ln",
    "sg:city":"Richmond",
    "sg:classifiers":[
        {
            "category":"Shopping",
            "subcategory":"Computers & Home Electronics",
            "type":"Retail Goods"
        }
    ],
    "sg:phone":"+1 804 276 6489",
    "sg:postcode":"23235",
    "sg:province":"VA",
    "sg:tags":[
        "software"
    ],
    "wof:name":"Ahef Software Design",
    "wof:placetype":"venue"
},
  "geometry": {"coordinates":[-77.55493199999999,37.473379],"type":"Point"}
}