{
  "type": "Feature",
  "properties": {
    "iso:country":"US",
    "sg:address":"86 Luray Ave",
    "sg:city":"Front Royal",
    "sg:classifiers":[
        {
            "category":"Professional",
            "subcategory":"Computer Services",
            "type":"Services"
        }
    ],
    "sg:phone":"+1 650 295 5000",
    "sg:postcode":"22630",
    "sg:province":"VA",
    "sg:tags":[
        "prepackaged",
        "software"
    ],
    "wof:name":"Siebel Systems",
    "wof:placetype":"venue"
},
  "geometry": {"coordinates":[-78.195685,38.917217],"type":"Point"}
}