{
  "type": "Feature",
  "properties": {
    "iso:country":"US",
    "sg:address":"5852 Washington Blvd # 7",
    "sg:city":"Arlington",
    "sg:classifiers":[
        {
            "category":"Education",
            "subcategory":"Music School",
            "type":"Public Place"
        },
        {
            "category":"Education",
            "subcategory":"Special Training",
            "type":"Public Place"
        }
    ],
    "sg:phone":"+1 703 536 8200",
    "sg:postcode":"22205",
    "sg:province":"VA",
    "sg:tags":[
        "educational",
        "instruction-instrumental"
    ],
    "wof:name":"Alexander School",
    "wof:placetype":"venue"
},
  "geometry": {"coordinates":[-77.140773,38.885198],"type":"Point"}
}