{
  "type": "Feature",
  "properties": {
    "addr:full":"1341 Long St Charlottesville VA 22901",
    "addr:housenumber":"1341",
    "addr:postcode":"22901",
    "addr:street":"Long St",
    "iso:country":"US",
    "sg:address":"1341 Long St",
    "sg:city":"Charlottesville",
    "sg:classifiers":[
        {
            "category":"Building & Trades",
            "subcategory":"Construction",
            "type":"Services"
        }
    ],
    "sg:phone":"+1 434 245 7055",
    "sg:postcode":"22901",
    "sg:province":"VA",
    "sg:tags":[
        "company"
    ],
    "wof:name":"John S Clark Construction",
    "wof:placetype":"venue"
},
  "geometry": {"coordinates":[-78.460019,38.035403],"type":"Point"}
}