{
  "type": "Feature",
  "properties": {
    "iso:country":"US",
    "sg:address":"1936 S Sycamore St",
    "sg:city":"Petersburg",
    "sg:classifiers":[
        {
            "category":"Manufacturing",
            "subcategory":"Food",
            "type":"Manufacturing & Wholesale Goods"
        }
    ],
    "sg:phone":"+1 804 861 8424",
    "sg:postcode":"23805",
    "sg:province":"VA",
    "sg:tags":[
        "distiller"
    ],
    "wof:name":"Durastill",
    "wof:placetype":"venue"
},
  "geometry": {"coordinates":[-77.38349100000001,37.203145],"type":"Point"}
}