{
  "type": "Feature",
  "properties": {
    "addr:full":"14565 Church St Eagle Rock VA 24085",
    "addr:housenumber":"14565",
    "addr:postcode":"24085",
    "addr:street":"Church St",
    "iso:country":"US",
    "sg:address":"14565 Church St",
    "sg:city":"Eagle Rock",
    "sg:classifiers":[
        {
            "category":"Organizations",
            "subcategory":"Religious Organization",
            "type":"Services"
        }
    ],
    "sg:phone":"+1 540 884 2031",
    "sg:postcode":"24085",
    "sg:province":"VA",
    "sg:tags":[
        "church"
    ],
    "wof:name":"Eagle Rock Methodist Church",
    "wof:placetype":"venue"
},
  "geometry": {"coordinates":[-79.800127,37.639703],"type":"Point"}
}