{
  "type": "Feature",
  "properties": {
    "iso:country":"US",
    "sg:address":"5627 Haney Ln",
    "sg:city":"Fredericksburg",
    "sg:classifiers":[
        {
            "category":"Real Estate",
            "subcategory":"Real Estate Agent",
            "type":"Services"
        }
    ],
    "sg:phone":"+1 540 582 8600",
    "sg:postcode":"22407",
    "sg:province":"VA",
    "wof:name":"Snow Realty",
    "wof:placetype":"venue"
},
  "geometry": {"coordinates":[-77.562309,38.291159],"type":"Point"}
}