{
  "type": "Feature",
  "properties": {
    "addr:full":"4001 Williamsburg Ct Fairfax VA 22032",
    "addr:housenumber":"4001",
    "addr:postcode":"22032",
    "addr:street":"Williamsburg Ct",
    "iso:country":"US",
    "sg:address":"4001 Williamsburg Ct",
    "sg:city":"Fairfax",
    "sg:classifiers":[
        {
            "category":"Professional",
            "subcategory":"Computer Services",
            "type":"Services"
        }
    ],
    "sg:phone":"+1 703 591 0911",
    "sg:postcode":"22032",
    "sg:province":"VA",
    "sg:tags":[
        "programming",
        "custom"
    ],
    "sg:website":"www.bmsi.com",
    "wof:name":"Business Management Systems",
    "wof:placetype":"venue"
},
  "geometry": {"coordinates":[-77.28199499999999,38.841432],"type":"Point"}
}