{
  "type": "Feature",
  "properties": {
    "addr:full":"14279 Deertrack Trl Culpeper VA 22701",
    "addr:housenumber":"14279",
    "addr:postcode":"22701",
    "addr:street":"Deertrack Trl",
    "iso:country":"US",
    "sg:address":"14279 Deertrack Trl",
    "sg:city":"Culpeper",
    "sg:classifiers":[
        {
            "category":"Building & Trades",
            "subcategory":"Construction",
            "type":"Services"
        }
    ],
    "sg:phone":"+1 540 937 6630",
    "sg:postcode":"22701",
    "sg:province":"VA",
    "sg:tags":[
        "dry wall",
        "contractor"
    ],
    "wof:name":"N V Drywall",
    "wof:placetype":"venue"
},
  "geometry": {"coordinates":[-77.984763,38.560406],"type":"Point"}
}