{
  "type": "Feature",
  "properties": {
    "iso:country":"US",
    "sg:address":"4001 9th St N",
    "sg:city":"Arlington",
    "sg:classifiers":[
        {
            "category":"Personal",
            "subcategory":"Beauty Salon",
            "type":"Services"
        }
    ],
    "sg:phone":"+1 703 525 6444",
    "sg:postcode":"22203",
    "sg:province":"VA",
    "wof:name":"Magic Scissors Inc",
    "wof:placetype":"venue"
},
  "geometry": {"coordinates":[-77.10921399999999,38.881025],"type":"Point"}
}