{
  "type": "Feature",
  "properties": {
    "iso:country":"US",
    "sg:address":"4501 Bexwood Dr",
    "sg:city":"Chesterfield",
    "sg:classifiers":[
        {
            "category":"Building & Trades",
            "subcategory":"Construction",
            "type":"Services"
        }
    ],
    "sg:phone":"+1 804 763 1114",
    "sg:postcode":"23832",
    "sg:province":"VA",
    "sg:tags":[
        "house"
    ],
    "wof:name":"J&J Home Repairs",
    "wof:placetype":"venue"
},
  "geometry": {"coordinates":[-77.59280099999999,37.429095],"type":"Point"}
}