{
  "type": "Feature",
  "properties": {
    "iso:country":"US",
    "sg:address":"1733 N Queens Ln",
    "sg:city":"Arlington",
    "sg:classifiers":[
        {
            "category":"Professional",
            "type":"Services"
        }
    ],
    "sg:phone":"+1 202 460 5102",
    "sg:postcode":"22201",
    "sg:province":"VA",
    "wof:name":"Elizabeth Callender",
    "wof:placetype":"venue"
},
  "geometry": {"coordinates":[-77.08009800000001,38.894335],"type":"Point"}
}