{
  "type": "Feature",
  "properties": {
    "addr:full":"1875 Avon Street Ext Charlottesville VA 22902",
    "addr:housenumber":"1875",
    "addr:postcode":"22902",
    "addr:street":"Avon Street Ext",
    "iso:country":"US",
    "sg:address":"1875 Avon Street Ext",
    "sg:city":"Charlottesville",
    "sg:classifiers":[
        {
            "category":"Home & Garden",
            "subcategory":"Garden Supply",
            "type":"Retail Goods"
        },
        {
            "category":"Food & Beverages",
            "subcategory":"Farmers Market",
            "type":"Retail Goods"
        }
    ],
    "sg:phone":"+1 434 295 2159",
    "sg:postcode":"22902",
    "sg:province":"VA",
    "sg:tags":[
        "nursery",
        "gardening"
    ],
    "sg:website":"www.snowknows.com",
    "wof:name":"Snow's Garden Center",
    "wof:placetype":"venue"
},
  "geometry": {"coordinates":[-78.5047,37.9897],"type":"Point"}
}