{
  "type": "Feature",
  "properties": {
    "addr:full":"5011 Columbia Pike Arlington VA 22204",
    "addr:housenumber":"5011",
    "addr:postcode":"22204",
    "addr:street":"Columbia Pike",
    "iso:country":"US",
    "sg:address":"5011 Columbia Pike",
    "sg:city":"Arlington",
    "sg:classifiers":[
        {
            "category":"Professional",
            "subcategory":"Accounting & Tax Preparation",
            "type":"Services"
        }
    ],
    "sg:phone":"+1 866 871 1040",
    "sg:postcode":"22204",
    "sg:province":"VA",
    "sg:tags":[
        "return",
        "preparation-business"
    ],
    "sg:website":"http://www.libertytax.com/",
    "wof:name":"Liberty Tax Service",
    "wof:placetype":"venue"
},
  "geometry": {"coordinates":[-77.112515,38.855802],"type":"Point"}
}