{
  "type": "Feature",
  "properties": {
    "addr:full":"1040 N Quincy St Arlington VA 22201",
    "addr:housenumber":"1040",
    "addr:postcode":"22201",
    "addr:street":"N Quincy St",
    "iso:country":"US",
    "sg:address":"1040 N Quincy St",
    "sg:city":"Arlington",
    "sg:classifiers":[
        {
            "category":"Professional",
            "subcategory":"Management & Consulting",
            "type":"Services"
        }
    ],
    "sg:phone":"+1 703 627 0192",
    "sg:postcode":"22201",
    "sg:province":"VA",
    "sg:tags":[
        "operations",
        "networking",
        "it",
        "tech",
        "are",
        "staffing"
    ],
    "wof:name":"Smart Tier Group Inc",
    "wof:placetype":"venue"
},
  "geometry": {"coordinates":[-77.108019,38.883987],"type":"Point"}
}