{
  "type": "Feature",
  "properties": {
    "addr:full":"1401 Poindexter St Chesapeake VA 23324",
    "addr:housenumber":"1401",
    "addr:postcode":"23324",
    "addr:street":"Poindexter St",
    "iso:country":"US",
    "sg:address":"1401 Poindexter St",
    "sg:city":"Chesapeake",
    "sg:classifiers":[
        {
            "category":"Shopping",
            "subcategory":"Used Merchandise",
            "type":"Retail Goods"
        }
    ],
    "sg:phone":"+1 757 545 7296",
    "sg:postcode":"23324",
    "sg:province":"VA",
    "sg:tags":[
        "pawnbroker"
    ],
    "wof:name":"Mr T's Pawn",
    "wof:placetype":"venue"
},
  "geometry": {"coordinates":[-76.271957,36.819936],"type":"Point"}
}