{
  "type": "Feature",
  "properties": {
    "iso:country":"US",
    "sg:address":"2501 20th Rd N",
    "sg:city":"Arlington",
    "sg:classifiers":[
        {
            "category":"Real Estate",
            "subcategory":"Real Estate Operator",
            "type":"Services"
        }
    ],
    "sg:phone":"+1 703 560 8164",
    "sg:postcode":"22201",
    "sg:province":"VA",
    "sg:tags":[
        "building",
        "apartment"
    ],
    "wof:name":"S & S Properties",
    "wof:placetype":"venue"
},
  "geometry": {"coordinates":[-77.091872,38.896782],"type":"Point"}
}