{
  "type": "Feature",
  "properties": {
    "addr:full":"242 Hillcrest Dr Fredericksburg VA 22401",
    "addr:housenumber":"242",
    "addr:postcode":"22401",
    "addr:street":"Hillcrest Dr",
    "iso:country":"US",
    "sg:address":"242 Hillcrest Dr",
    "sg:city":"Fredericksburg",
    "sg:classifiers":[
        {
            "category":"Real Estate",
            "subcategory":"Real Estate Agent",
            "type":"Services"
        }
    ],
    "sg:phone":"+1 540 898 0851",
    "sg:postcode":"22401",
    "sg:province":"VA",
    "wof:name":"A Wing & A Prayer LLC",
    "wof:placetype":"venue"
},
  "geometry": {"coordinates":[-77.475894,38.273533],"type":"Point"}
}