{
  "type": "Feature",
  "properties": {
    "iso:country":"US",
    "sg:address":"6352 Rolling Mill Pl",
    "sg:city":"Springfield",
    "sg:classifiers":[
        {
            "category":"Professional",
            "subcategory":"Management & Consulting",
            "type":"Services"
        }
    ],
    "sg:phone":"+1 703 455 2822",
    "sg:postcode":"22152",
    "sg:province":"VA",
    "sg:tags":[
        "defense",
        "contractor"
    ],
    "wof:name":"Command Technologies Inc",
    "wof:placetype":"venue"
},
  "geometry": {"coordinates":[-77.23811000000001,38.778476],"type":"Point"}
}