{
  "type": "Feature",
  "properties": {
    "iso:country":"US",
    "sg:address":"2920 Gray St",
    "sg:city":"Oakton",
    "sg:classifiers":[
        {
            "category":"Wholesale",
            "subcategory":"Furniture",
            "type":"Manufacturing & Wholesale Goods"
        }
    ],
    "sg:phone":"+1 703 938 7909",
    "sg:postcode":"22124",
    "sg:province":"VA",
    "sg:tags":[
        "modular"
    ],
    "sg:website":"www.mosfurniture.com",
    "wof:name":"Modular Office Systems",
    "wof:placetype":"venue"
},
  "geometry": {"coordinates":[-77.297495,38.879858],"type":"Point"}
}