{
  "type": "Feature",
  "properties": {
    "addr:full":"8002 Revenna Ln Springfield VA 22153",
    "addr:housenumber":"8002",
    "addr:postcode":"22153",
    "addr:street":"Revenna Ln",
    "iso:country":"US",
    "sg:address":"8002 Revenna Ln",
    "sg:city":"Springfield",
    "sg:classifiers":[
        {
            "category":"Real Estate",
            "subcategory":"Real Estate Operator",
            "type":"Services"
        }
    ],
    "sg:phone":"+1 703 455 5573",
    "sg:postcode":"22153",
    "sg:province":"VA",
    "sg:tags":[
        "building",
        "nonresidential"
    ],
    "wof:name":"Mkf Properties LLC",
    "wof:placetype":"venue"
},
  "geometry": {"coordinates":[-77.215029,38.740961],"type":"Point"}
}