{
  "type": "Feature",
  "properties": {
    "iso:country":"US",
    "sg:address":"901 Preston Ave Ste 102",
    "sg:city":"Charlottesville",
    "sg:classifiers":[
        {
            "category":"Health Services",
            "subcategory":"Clinic",
            "type":"Services"
        }
    ],
    "sg:phone":"+1 434 984 4627",
    "sg:postcode":"22903",
    "sg:province":"VA",
    "sg:tags":[
        "welfare"
    ],
    "wof:name":"Imbs",
    "wof:placetype":"venue"
},
  "geometry": {"coordinates":[-78.48965200000001,38.037991],"type":"Point"}
}