{
  "type": "Feature",
  "properties": {
    "addr:full":"401 Azalea Ave Richmond VA 23227",
    "addr:housenumber":"401",
    "addr:postcode":"23227",
    "addr:street":"Azalea Ave",
    "iso:country":"US",
    "sg:address":"401 Azalea Ave",
    "sg:city":"Richmond",
    "sg:classifiers":[
        {
            "category":"Professional",
            "subcategory":"Management & Consulting",
            "type":"Services"
        }
    ],
    "sg:phone":"+1 804 264 3771",
    "sg:postcode":"23227",
    "sg:province":"VA",
    "sg:tags":[
        "food"
    ],
    "wof:name":"ABL Management Inc",
    "wof:placetype":"venue"
},
  "geometry": {"coordinates":[-77.439258,37.602458],"type":"Point"}
}