{
  "type": "Feature",
  "properties": {
    "addr:full":"870 N Liberty St Harrisonburg VA 22802",
    "addr:housenumber":"870",
    "addr:postcode":"22802",
    "addr:street":"N Liberty St",
    "iso:country":"US",
    "sg:address":"870 N Liberty St",
    "sg:city":"Harrisonburg",
    "sg:classifiers":[
        {
            "category":"Wholesale",
            "subcategory":"Electrical",
            "type":"Manufacturing & Wholesale Goods"
        }
    ],
    "sg:phone":"+1 540 433 5335",
    "sg:postcode":"22802",
    "sg:province":"VA",
    "sg:tags":[
        "electric",
        "motor"
    ],
    "wof:name":"Lloyd Electric Co",
    "wof:placetype":"venue"
},
  "geometry": {"coordinates":[-78.86563099999999,38.462323],"type":"Point"}
}