{
  "type": "Feature",
  "properties": {
    "addr:full":"466 Brockwell Ave Norfolk VA 23502",
    "addr:housenumber":"466",
    "addr:postcode":"23502",
    "addr:street":"Brockwell Ave",
    "iso:country":"US",
    "sg:address":"466 Brockwell Ave",
    "sg:city":"Norfolk",
    "sg:classifiers":[
        {
            "category":"Retail",
            "subcategory":"Car Wash",
            "type":"Services"
        }
    ],
    "sg:phone":"+1 757 466 3333",
    "sg:postcode":"23502",
    "sg:province":"VA",
    "sg:tags":[
        "carwash"
    ],
    "wof:name":"L & E Auto Detailing & Window",
    "wof:placetype":"venue"
},
  "geometry": {"coordinates":[-76.202348,36.848912],"type":"Point"}
}