{
  "type": "Feature",
  "properties": {
    "iso:country":"US",
    "sg:address":"14750 Conference Center Dr",
    "sg:city":"Chantilly",
    "sg:classifiers":[
        {
            "category":"Restaurant",
            "type":"Food & Drink"
        }
    ],
    "sg:menulink":"http://www.allmenus.com/va/sully/267424-palm-court-restaurant/menu/",
    "sg:phone":"+1 703 818 3520",
    "sg:postcode":"20151",
    "sg:province":"VA",
    "sg:tags":[
        "american"
    ],
    "wof:name":"Palm Court Restaurant",
    "wof:placetype":"venue"
},
  "geometry": {"coordinates":[-77.456264,38.874544],"type":"Point"}
}