{
  "type": "Feature",
  "properties": {
    "addr:full":"357 Chautauqua Ave Portsmouth VA 23707",
    "addr:housenumber":"357",
    "addr:postcode":"23707",
    "addr:street":"Chautauqua Ave",
    "iso:country":"US",
    "sg:address":"357 Chautauqua Ave",
    "sg:city":"Portsmouth",
    "sg:classifiers":[
        {
            "category":"Building & Trades",
            "subcategory":"Construction",
            "type":"Services"
        }
    ],
    "sg:phone":"+1 757 399 8327",
    "sg:postcode":"23707",
    "sg:province":"VA",
    "sg:tags":[
        "caulking",
        "contractor"
    ],
    "wof:name":"Herrin Sealant Co",
    "wof:placetype":"venue"
},
  "geometry": {"coordinates":[-76.332911,36.849464],"type":"Point"}
}