{
  "type": "Feature",
  "properties": {
    "addr:full":"26414 Old Saltworks Rd Meadowview VA 24361",
    "addr:housenumber":"26414",
    "addr:postcode":"24361",
    "addr:street":"Old Saltworks Rd",
    "iso:country":"US",
    "sg:address":"26414 Old Saltworks Rd",
    "sg:city":"Meadowview",
    "sg:classifiers":[
        {
            "category":"Building & Trades",
            "subcategory":"Landscaping Services",
            "type":"Services"
        }
    ],
    "sg:phone":"+1 276 944 4453",
    "sg:postcode":"24361",
    "sg:province":"VA",
    "sg:tags":[
        "tree"
    ],
    "wof:name":"Powers Tree & Lawn Serving",
    "wof:placetype":"venue"
},
  "geometry": {"coordinates":[-81.91126300000001,36.761209],"type":"Point"}
}