{
  "type": "Feature",
  "properties": {
    "addr:full":"848 W Main St Salem VA 24153",
    "addr:housenumber":"848",
    "addr:postcode":"24153",
    "addr:street":"W Main St",
    "iso:country":"US",
    "sg:address":"848 W Main St",
    "sg:city":"Salem",
    "sg:classifiers":[
        {
            "category":"Personal",
            "subcategory":"Barber",
            "type":"Services"
        }
    ],
    "sg:phone":"+1 540 444 2888",
    "sg:postcode":"24153",
    "sg:province":"VA",
    "sg:tags":[
        "shop"
    ],
    "wof:name":"Salem Barber",
    "wof:placetype":"venue"
},
  "geometry": {"coordinates":[-80.07198,37.290496],"type":"Point"}
}