{
  "type": "Feature",
  "properties": {
    "addr:full":"11403 Waples Mill Rd Oakton VA 22124",
    "addr:housenumber":"11403",
    "addr:postcode":"22124",
    "addr:street":"Waples Mill Rd",
    "iso:country":"US",
    "sg:address":"11403 Waples Mill Rd",
    "sg:city":"Oakton",
    "sg:classifiers":[
        {
            "category":"Utilities",
            "subcategory":"Telephone",
            "type":"Services"
        }
    ],
    "sg:phone":"+1 703 758 2552",
    "sg:postcode":"22124",
    "sg:province":"VA",
    "sg:tags":[
        "mail",
        "paging",
        "voice"
    ],
    "wof:name":"Ace Communications",
    "wof:placetype":"venue"
},
  "geometry": {"coordinates":[-77.342535,38.877825],"type":"Point"}
}