{
  "type": "Feature",
  "properties": {
    "addr:full":"9833 Poindexter Rd Louisa VA 23093",
    "addr:housenumber":"9833",
    "addr:postcode":"23093",
    "addr:street":"Poindexter Rd",
    "iso:country":"US",
    "sg:address":"9833 Poindexter Rd",
    "sg:city":"Louisa",
    "sg:classifiers":[
        {
            "category":"Organizations",
            "subcategory":"Religious Organization",
            "type":"Services"
        }
    ],
    "sg:phone":"+1 540 967 3502",
    "sg:postcode":"23093",
    "sg:province":"VA",
    "sg:tags":[
        "church"
    ],
    "wof:name":"Bright Hope Baptist Church",
    "wof:placetype":"venue"
},
  "geometry": {"coordinates":[-78.08553999999999,38.048798],"type":"Point"}
}