{
  "type": "Feature",
  "properties": {
    "iso:country":"US",
    "sg:address":"4600 Cox Rd",
    "sg:city":"Glen Allen",
    "sg:classifiers":[
        {
            "category":"Professional",
            "type":"Services"
        }
    ],
    "sg:phone":"+1 804 217 8801",
    "sg:postcode":"23060",
    "sg:province":"VA",
    "sg:tags":[
        "establishment"
    ],
    "wof:name":"Innsbrook Owners Asociation",
    "wof:placetype":"venue"
},
  "geometry": {"coordinates":[-77.574985,37.661051],"type":"Point"}
}