{
  "type": "Feature",
  "properties": {
    "addr:full":"2315 Patterson Ave SW Roanoke VA 24016",
    "addr:housenumber":"2315",
    "addr:postcode":"24016",
    "addr:street":"Patterson Ave Sw",
    "iso:country":"US",
    "sg:address":"2315 Patterson Ave SW",
    "sg:city":"Roanoke",
    "sg:classifiers":[
        {
            "category":"Autos & Motor Vehicles",
            "subcategory":"Automobile Sales",
            "type":"Retail Goods"
        }
    ],
    "sg:phone":"+1 540 982 0005",
    "sg:postcode":"24016",
    "sg:province":"VA",
    "sg:tags":[
        "heavy",
        "equipment",
        "rental",
        "sales"
    ],
    "wof:name":"Hertz",
    "wof:placetype":"venue"
},
  "geometry": {"coordinates":[-79.97806199999999,37.275648],"type":"Point"}
}