{
  "type": "Feature",
  "properties": {
    "iso:country":"US",
    "sg:address":"1470 Pantops Mountain Pl",
    "sg:city":"Charlottesville",
    "sg:classifiers":[
        {
            "category":"Health Services",
            "subcategory":"Dentist",
            "type":"Services"
        }
    ],
    "sg:phone":"+1 434 817 1817",
    "sg:postcode":"22911",
    "sg:province":"VA",
    "sg:tags":[
        "pediatric"
    ],
    "sg:website":"www.childrensdentistryofcharlott...",
    "wof:name":"Children's Dentistry of Charlottesville",
    "wof:placetype":"venue"
},
  "geometry": {"coordinates":[-78.43814500000001,38.027153],"type":"Point"}
}