{
  "type": "Feature",
  "properties": {
    "addr:full":"10407 Samaga Dr Oakton VA 22124",
    "addr:housenumber":"10407",
    "addr:postcode":"22124",
    "addr:street":"Samaga Dr",
    "iso:country":"US",
    "sg:address":"10407 Samaga Dr",
    "sg:city":"Oakton",
    "sg:classifiers":[
        {
            "category":"Building & Trades",
            "subcategory":"Construction",
            "type":"Services"
        }
    ],
    "sg:phone":"+1 703 560 2405",
    "sg:postcode":"22124",
    "sg:province":"VA",
    "sg:tags":[
        "hanging",
        "co",
        "painter",
        "contractor"
    ],
    "wof:name":"Lillard Painting Inc",
    "wof:placetype":"venue"
},
  "geometry": {"coordinates":[-77.30401999999999,38.893409],"type":"Point"}
}