{
  "type": "Feature",
  "properties": {
    "addr:full":"3 Hope Springs Ln Stafford VA 22554",
    "addr:housenumber":"3",
    "addr:postcode":"22554",
    "addr:street":"Hope Springs Ln",
    "iso:country":"US",
    "sg:address":"3 Hope Springs Ln",
    "sg:city":"Stafford",
    "sg:classifiers":[
        {
            "category":"Recreation",
            "subcategory":"Marina",
            "type":"Entertainment"
        }
    ],
    "sg:phone":"+1 540 659 4768",
    "sg:postcode":"22554",
    "sg:province":"VA",
    "sg:tags":[
        "operation"
    ],
    "wof:name":"Aquia Beach Marina",
    "wof:placetype":"venue"
},
  "geometry": {"coordinates":[-77.359635,38.422615],"type":"Point"}
}