{
  "type": "Feature",
  "properties": {
    "addr:full":"5708 Sellger Dr Norfolk VA 23502",
    "addr:housenumber":"5708",
    "addr:postcode":"23502",
    "addr:street":"Sellger Dr",
    "iso:country":"US",
    "sg:address":"5708 Sellger Dr",
    "sg:city":"Norfolk",
    "sg:classifiers":[
        {
            "category":"Building & Trades",
            "subcategory":"Plumbing",
            "type":"Services"
        }
    ],
    "sg:phone":"+1 757 466 8345",
    "sg:postcode":"23502",
    "sg:province":"VA",
    "sg:tags":[
        "plumbing"
    ],
    "wof:name":"Norfolk Pulmbing Inc",
    "wof:placetype":"venue"
},
  "geometry": {"coordinates":[-76.20671299999999,36.838738],"type":"Point"}
}