{
  "type": "Feature",
  "properties": {
    "addr:full":"610 S Carlin Springs Rd A Arlington VA 22204",
    "addr:housenumber":"610",
    "addr:postcode":"22204",
    "addr:street":"S Carlin Springs Rd A",
    "iso:country":"US",
    "sg:address":"610 S Carlin Springs Rd A",
    "sg:city":"Arlington",
    "sg:classifiers":[
        {
            "category":"Health Services",
            "subcategory":"Nursing And Care Facility",
            "type":"Services"
        },
        {
            "category":"Social Services",
            "subcategory":"Retirement Home",
            "type":"Services"
        },
        {
            "category":"Social Services",
            "subcategory":"Adult Care",
            "type":"Services"
        }
    ],
    "sg:phone":"+1 703 845 1443",
    "sg:postcode":"22204",
    "sg:province":"VA",
    "sg:tags":[
        "living",
        "assisted",
        "rest",
        "elder",
        "homes-intermediate"
    ],
    "wof:name":"Aea Retirement Housing",
    "wof:placetype":"venue"
},
  "geometry": {"coordinates":[-77.12770399999999,38.860125],"type":"Point"}
}