{
  "type": "Feature",
  "properties": {
    "addr:full":"2154 Newton Rd Hampton VA 23663",
    "addr:housenumber":"2154",
    "addr:postcode":"23663",
    "addr:street":"Newton Rd",
    "iso:country":"US",
    "sg:address":"2154 Newton Rd",
    "sg:city":"Hampton",
    "sg:classifiers":[
        {
            "category":"Building & Trades",
            "subcategory":"Cleaning & Sanitation",
            "type":"Services"
        }
    ],
    "sg:phone":"+1 757 334 3382",
    "sg:postcode":"23663",
    "sg:province":"VA",
    "sg:tags":[
        "construction",
        "maintenance"
    ],
    "wof:name":"G & L Quality Construction",
    "wof:placetype":"venue"
},
  "geometry": {"coordinates":[-76.30855099999999,37.050385],"type":"Point"}
}