{
  "type": "Feature",
  "properties": {
    "iso:country":"US",
    "sg:address":"216 S Military Hwy",
    "sg:city":"Norfolk",
    "sg:classifiers":[
        {
            "category":"Wholesale",
            "subcategory":"Office Equipment",
            "type":"Manufacturing & Wholesale Goods"
        }
    ],
    "sg:phone":"+1 757 455 0747",
    "sg:postcode":"23502",
    "sg:province":"VA",
    "sg:tags":[
        "machine",
        "duplicating",
        "copying"
    ],
    "wof:name":"Xerox It Local",
    "wof:placetype":"venue"
},
  "geometry": {"coordinates":[-76.210227,36.837627],"type":"Point"}
}