{
  "type": "Feature",
  "properties": {
    "iso:country":"US",
    "sg:address":"3208 Academy Ave",
    "sg:city":"Portsmouth",
    "sg:classifiers":[
        {
            "category":"Restaurant",
            "type":"Food & Drink"
        }
    ],
    "sg:phone":"+1 757 686 1588",
    "sg:postcode":"23703",
    "sg:province":"VA",
    "sg:tags":[
        "eating"
    ],
    "wof:name":"Himalaya Chinese Restaurant",
    "wof:placetype":"venue"
},
  "geometry": {"coordinates":[-76.397161,36.863608],"type":"Point"}
}