{
  "type": "Feature",
  "properties": {
    "iso:country":"US",
    "sg:address":"5350 White Pickett Ln",
    "sg:city":"Richmond",
    "sg:classifiers":[
        {
            "category":"Shopping",
            "subcategory":"Beauty & Cosmetics",
            "type":"Retail Goods"
        }
    ],
    "sg:phone":"+1 804 275 9353",
    "sg:postcode":"23237",
    "sg:province":"VA",
    "sg:tags":[
        "merchandise"
    ],
    "wof:name":"Anita Ruffin",
    "wof:placetype":"venue"
},
  "geometry": {"coordinates":[-77.482957,37.395795],"type":"Point"}
}