{
  "type": "Feature",
  "properties": {
    "addr:full":"2530 Lakefield Mews Ct Richmond VA 23231",
    "addr:housenumber":"2530",
    "addr:postcode":"23231",
    "addr:street":"Lakefield Mews Ct",
    "iso:country":"US",
    "sg:address":"2530 Lakefield Mews Ct",
    "sg:city":"Richmond",
    "sg:classifiers":[
        {
            "category":"Retail",
            "subcategory":"Auto Repair",
            "type":"Services"
        }
    ],
    "sg:phone":"+1 804 746 1010",
    "sg:postcode":"23231",
    "sg:province":"VA",
    "sg:tags":[
        "general"
    ],
    "wof:name":"Rods N Riders",
    "wof:placetype":"venue"
},
  "geometry": {"coordinates":[-77.36950899999999,37.52866],"type":"Point"}
}