{
  "type": "Feature",
  "properties": {
    "addr:full":"5826 Hoffmans Ln Falls Church VA 22041",
    "addr:housenumber":"5826",
    "addr:postcode":"22041",
    "addr:street":"Hoffmans Ln",
    "iso:country":"US",
    "sg:address":"5826 Hoffmans Ln",
    "sg:city":"Falls Church",
    "sg:classifiers":[
        {
            "category":"Building & Trades",
            "subcategory":"Construction",
            "type":"Services"
        }
    ],
    "sg:phone":"+1 703 820 8212",
    "sg:postcode":"22041",
    "sg:province":"VA",
    "sg:tags":[
        "contractor"
    ],
    "wof:name":"Hall Masonry Contracting",
    "wof:placetype":"venue"
},
  "geometry": {"coordinates":[-77.134004,38.845535],"type":"Point"}
}