{
  "type": "Feature",
  "properties": {
    "iso:country":"US",
    "sg:address":"1218 Kerns Ave SW",
    "sg:city":"Roanoke",
    "sg:classifiers":[
        {
            "category":"Freight",
            "type":"Transportation"
        }
    ],
    "sg:phone":"+1 540 342 5010",
    "sg:postcode":"24015",
    "sg:province":"VA",
    "wof:name":"Chaser Logistics Inc",
    "wof:placetype":"venue"
},
  "geometry": {"coordinates":[-79.96458699999999,37.261749],"type":"Point"}
}