{
  "type": "Feature",
  "properties": {
    "addr:full":"11521 Sunrise Valley Dr Reston VA 20191",
    "addr:housenumber":"11521",
    "addr:postcode":"20191",
    "addr:street":"Sunrise Valley Dr",
    "iso:country":"US",
    "sg:address":"11521 Sunrise Valley Dr",
    "sg:city":"Reston",
    "sg:classifiers":[
        {
            "category":"Retail",
            "subcategory":"Laundry & Dry Cleaning",
            "type":"Services"
        }
    ],
    "sg:phone":"+1 703 620 4400",
    "sg:postcode":"20191",
    "sg:province":"VA",
    "sg:tags":[
        "drycleaning",
        "plant"
    ],
    "wof:name":"Village Square Cleaners",
    "wof:placetype":"venue"
},
  "geometry": {"coordinates":[-77.34673600000001,38.945421],"type":"Point"}
}