{
  "type": "Feature",
  "properties": {
    "addr:full":"10182 Ponderosa Pine Ct Manassas VA 20110",
    "addr:housenumber":"10182",
    "addr:postcode":"20110",
    "addr:street":"Ponderosa Pine Ct",
    "iso:country":"US",
    "sg:address":"10182 Ponderosa Pine Ct",
    "sg:city":"Manassas",
    "sg:classifiers":[
        {
            "category":"Banks & Credit Unions",
            "subcategory":"Financial Services",
            "type":"Services"
        }
    ],
    "sg:phone":"+1 703 368 1060",
    "sg:postcode":"20110",
    "sg:province":"VA",
    "sg:tags":[
        "card-merchant"
    ],
    "wof:name":"Heartland Payment Systems Inc",
    "wof:placetype":"venue"
},
  "geometry": {"coordinates":[-77.480322,38.733146],"type":"Point"}
}