{
  "type": "Feature",
  "properties": {
    "addr:full":"1000 Wilson Blvd Ste 1825 Arlington VA 22209",
    "addr:housenumber":"1000",
    "addr:postcode":"22209",
    "addr:street":"Wilson Blvd Ste 1825",
    "iso:country":"US",
    "sg:address":"1000 Wilson Blvd Ste 1825",
    "sg:city":"Arlington",
    "sg:classifiers":[
        {
            "category":"Health Services",
            "subcategory":"Doctor",
            "type":"Services"
        }
    ],
    "sg:phone":"+1 703 907 7856",
    "sg:postcode":"22209",
    "sg:province":"VA",
    "sg:tags":[
        "physician",
        "surgeon",
        "surgeons",
        "psychiatry"
    ],
    "wof:name":"Journal Of Neuropsychiatry And Clinical Neurosciences",
    "wof:placetype":"venue"
},
  "geometry": {"coordinates":[-77.06841300000001,38.893951],"type":"Point"}
}