{
  "type": "Feature",
  "properties": {
    "addr:full":"800 S Lynnhaven Rd Virginia Beach VA 23452",
    "addr:housenumber":"800",
    "addr:postcode":"23452",
    "addr:street":"S Lynnhaven Rd",
    "iso:country":"US",
    "sg:address":"800 S Lynnhaven Rd",
    "sg:city":"Virginia Beach",
    "sg:classifiers":[
        {
            "category":"Restaurant",
            "type":"Food & Drink"
        }
    ],
    "sg:menulink":"http://www.allmenus.com/va/virginia-beach/97681-zeros-subs/menu/",
    "sg:phone":"+1 757 431 9145",
    "sg:postcode":"23452",
    "sg:province":"VA",
    "sg:tags":[
        "wrap",
        "american",
        "sandwich",
        "steakhouse"
    ],
    "wof:name":"Zero's Subs",
    "wof:placetype":"venue"
},
  "geometry": {"coordinates":[-76.073144,36.813179],"type":"Point"}
}