{
  "type": "Feature",
  "properties": {
    "iso:country":"US",
    "sg:address":"5500 Holmes Run Pkwy",
    "sg:city":"Alexandria",
    "sg:classifiers":[
        {
            "category":"Food & Beverages",
            "subcategory":"Groceries & Convenience Stores",
            "type":"Retail Goods"
        }
    ],
    "sg:phone":"+1 703 823 0700",
    "sg:postcode":"22304",
    "sg:province":"VA",
    "sg:tags":[
        "market"
    ],
    "wof:name":"Global Market & Deli",
    "wof:placetype":"venue"
},
  "geometry": {"coordinates":[-77.12832299999999,38.81912],"type":"Point"}
}