{
  "type": "Feature",
  "properties": {
    "addr:full":"304 Springwood Ct NE Vienna VA 22180",
    "addr:housenumber":"304",
    "addr:postcode":"22180",
    "addr:street":"Springwood Ct Ne",
    "iso:country":"US",
    "sg:address":"304 Springwood Ct NE",
    "sg:city":"Vienna",
    "sg:classifiers":[
        {
            "category":"Professional",
            "subcategory":"Management & Consulting",
            "type":"Services"
        }
    ],
    "sg:phone":"+1 703 319 3161",
    "sg:postcode":"22180",
    "sg:province":"VA",
    "wof:name":"Chiba International LLC",
    "wof:placetype":"venue"
},
  "geometry": {"coordinates":[-77.268293,38.911072],"type":"Point"}
}