{
  "type": "Feature",
  "properties": {
    "addr:full":"17337 Pickwick Dr Purcellville VA 20132",
    "addr:housenumber":"17337",
    "addr:postcode":"20132",
    "addr:street":"Pickwick Dr",
    "iso:country":"US",
    "sg:address":"17337 Pickwick Dr",
    "sg:city":"Purcellville",
    "sg:classifiers":[
        {
            "category":"Building & Trades",
            "subcategory":"Construction",
            "type":"Services"
        }
    ],
    "sg:phone":"+1 540 751 0383",
    "sg:postcode":"20132",
    "sg:province":"VA",
    "sg:tags":[
        "general",
        "contractor"
    ],
    "wof:name":"Residential Construction",
    "wof:placetype":"venue"
},
  "geometry": {"coordinates":[-77.69695299999999,39.140462],"type":"Point"}
}