{
  "type": "Feature",
  "properties": {
    "iso:country":"US",
    "sg:address":"645 Berryville Ave",
    "sg:city":"Winchester",
    "sg:classifiers":[
        {
            "category":"Organizations",
            "subcategory":"Religious Organization",
            "type":"Services"
        }
    ],
    "sg:phone":"+1 540 542 1776",
    "sg:postcode":"22601",
    "sg:province":"VA",
    "wof:name":"Good Shepherd Church",
    "wof:placetype":"venue"
},
  "geometry": {"coordinates":[-78.151934,39.185005],"type":"Point"}
}