{
  "type": "Feature",
  "properties": {
    "addr:full":"14305 Climbing Rose Way Centreville VA 20121",
    "addr:postcode":"14305;20121",
    "addr:street":"Rose Way",
    "iso:country":"US",
    "sg:address":"14305 Climbing Rose Way",
    "sg:city":"Centreville",
    "sg:classifiers":[
        {
            "category":"Building & Trades",
            "subcategory":"Landscaping Services",
            "type":"Services"
        }
    ],
    "sg:phone":"+1 703 393 8861",
    "sg:postcode":"20121",
    "sg:province":"VA",
    "sg:tags":[
        "tree"
    ],
    "wof:name":"Brennans Tree Service LLC",
    "wof:placetype":"venue"
},
  "geometry": {"coordinates":[-77.441017,38.834959],"type":"Point"}
}