{
  "type": "Feature",
  "properties": {
    "iso:country":"US",
    "sg:address":"2100 Steppingstone Sq",
    "sg:city":"Chesapeake",
    "sg:classifiers":[
        {
            "category":"Government",
            "subcategory":"Office",
            "type":"Public Place"
        }
    ],
    "sg:phone":"+1 757 424 8240",
    "sg:postcode":"23320",
    "sg:province":"VA",
    "wof:name":"Southeastern Virginia Training",
    "wof:placetype":"venue"
},
  "geometry": {"coordinates":[-76.22678999999999,36.792455],"type":"Point"}
}