{
  "type": "Feature",
  "properties": {
    "addr:full":"58 Raleigh Rd Newport News VA 23601",
    "addr:housenumber":"58",
    "addr:postcode":"23601",
    "addr:street":"Raleigh Rd",
    "iso:country":"US",
    "sg:address":"58 Raleigh Rd",
    "sg:city":"Newport News",
    "sg:classifiers":[
        {
            "category":"Health Services",
            "subcategory":"Doctor",
            "type":"Services"
        }
    ],
    "sg:phone":"+1 757 596 2118",
    "sg:postcode":"23601",
    "sg:province":"VA",
    "sg:tags":[
        "osteopathic"
    ],
    "wof:name":"Honey Do Helpers Inc",
    "wof:placetype":"venue"
},
  "geometry": {"coordinates":[-76.46097899999999,37.02659],"type":"Point"}
}