{
  "type": "Feature",
  "properties": {
    "addr:full":"13083 Chinn Park Dr Woodbridge VA 22192",
    "addr:postcode":"13083;22192",
    "addr:street":"Chinn Park Dr",
    "iso:country":"US",
    "sg:address":"13083 Chinn Park Dr",
    "sg:city":"Woodbridge",
    "sg:classifiers":[
        {
            "category":"Education",
            "subcategory":"Library",
            "type":"Public Place"
        }
    ],
    "sg:phone":"+1 703 792 6100",
    "sg:postcode":"22192",
    "sg:province":"VA",
    "sg:website":"www.pwcgov.org",
    "wof:name":"Prince William Pblc Lbry Systm",
    "wof:placetype":"venue"
},
  "geometry": {"coordinates":[-77.33476,38.671274],"type":"Point"}
}