{
  "type": "Feature",
  "properties": {
    "iso:country":"US",
    "sg:address":"1600 S Joyce St",
    "sg:city":"Arlington",
    "sg:classifiers":[
        {
            "category":"Retail",
            "subcategory":"Laundry & Dry Cleaning",
            "type":"Services"
        }
    ],
    "sg:phone":"+1 703 521 3270",
    "sg:postcode":"22202",
    "sg:province":"VA",
    "sg:tags":[
        "cleaners"
    ],
    "wof:name":"South Washington Valet",
    "wof:placetype":"venue"
},
  "geometry": {"coordinates":[-77.063338,38.859227],"type":"Point"}
}