{
  "type": "Feature",
  "properties": {
    "addr:full":"95 Laurel Ln Hurt VA 24502",
    "addr:housenumber":"95",
    "addr:postcode":"24502",
    "addr:street":"Laurel Ln",
    "iso:country":"US",
    "sg:address":"95 Laurel Ln",
    "sg:city":"Hurt",
    "sg:classifiers":[
        {
            "category":"Farming",
            "subcategory":"Nursery",
            "type":"Manufacturing & Wholesale Goods"
        }
    ],
    "sg:phone":"+1 434 656 6724",
    "sg:postcode":"24502",
    "sg:province":"VA",
    "wof:name":"Burkhardts Nursery Inc",
    "wof:placetype":"venue"
},
  "geometry": {"coordinates":[-79.246115,37.345893],"type":"Point"}
}