{
  "type": "Feature",
  "properties": {
    "iso:country":"US",
    "sg:address":"1500 Amherst St",
    "sg:city":"Charlottesville",
    "sg:classifiers":[
        {
            "category":"Health Services",
            "subcategory":"Doctor",
            "type":"Services"
        }
    ],
    "sg:phone":"+1 434 977 4422",
    "sg:postcode":"22903",
    "sg:province":"VA",
    "wof:name":"Alexander F Stephen PHD",
    "wof:placetype":"venue"
},
  "geometry": {"coordinates":[-78.48400100000001,38.042599],"type":"Point"}
}