{
  "type": "Feature",
  "properties": {
    "addr:full":"Realtor-Real Estate Agent 10432 Balls Ford Road Suite 120 Manassas VA 20109",
    "addr:housenumber":"10432",
    "addr:postcode":"20109",
    "addr:street":"Balls Ford Road Suite 120",
    "iso:country":"US",
    "sg:address":"Realtor-Real Estate Agent 10432 Balls Ford Road Suite 120",
    "sg:city":"Manassas",
    "sg:classifiers":[
        {
            "category":"Real Estate",
            "subcategory":"Real Estate Agent",
            "type":"Services"
        }
    ],
    "sg:phone":"+1 703 629 0297",
    "sg:postcode":"20109",
    "sg:province":"VA",
    "wof:name":"Fred Marcellus-Realtor-Manassas, VA- Coldwell Banker",
    "wof:placetype":"venue"
},
  "geometry": {"coordinates":[-77.510036,38.80083],"type":"Point"}
}