{
  "type": "Feature",
  "properties": {
    "addr:full":"601 E Randolph Rd Hopewell VA 23860",
    "addr:housenumber":"601",
    "addr:postcode":"23860",
    "addr:street":"E Randolph Rd",
    "iso:country":"US",
    "sg:address":"601 E Randolph Rd",
    "sg:city":"Hopewell",
    "sg:classifiers":[
        {
            "category":"Restaurant",
            "type":"Food & Drink"
        }
    ],
    "sg:phone":"+1 804 541 8253",
    "sg:postcode":"23860",
    "sg:province":"VA",
    "sg:tags":[
        "eating"
    ],
    "wof:name":"Subway",
    "wof:placetype":"venue"
},
  "geometry": {"coordinates":[-77.28019399999999,37.300706],"type":"Point"}
}