{
  "type": "Feature",
  "properties": {
    "iso:country":"US",
    "sg:address":"2362 Fleeton Rd",
    "sg:city":"Reedville",
    "sg:classifiers":[
        {
            "category":"Professional",
            "subcategory":"Business Services",
            "type":"Services"
        }
    ],
    "sg:phone":"+1 804 453 7323",
    "sg:postcode":"22539",
    "sg:province":"VA",
    "wof:name":"Manuel G Haynie Auctioneer",
    "wof:placetype":"venue"
},
  "geometry": {"coordinates":[-76.27051400000001,37.820807],"type":"Point"}
}