{
  "type": "Feature",
  "properties": {
    "addr:full":"5009 Wilson Blvd Arlington VA 22203",
    "addr:housenumber":"5009",
    "addr:postcode":"22203",
    "addr:street":"Wilson Blvd",
    "iso:country":"US",
    "sg:address":"5009 Wilson Blvd",
    "sg:city":"Arlington",
    "sg:classifiers":[
        {
            "category":"Fast Food",
            "type":"Food & Drink"
        }
    ],
    "sg:phone":"+1 703 525 0522",
    "sg:postcode":"22203",
    "sg:province":"VA",
    "sg:website":"www.mcdonalds.com/",
    "wof:name":"McDonald's",
    "wof:placetype":"venue"
},
  "geometry": {"coordinates":[-77.12130000000001,38.877998],"type":"Point"}
}