{
  "type": "Feature",
  "properties": {
    "addr:full":"5725 Arrowhead Dr Virginia Beach VA 23462",
    "addr:housenumber":"5725",
    "addr:postcode":"23462",
    "addr:street":"Arrowhead Dr",
    "iso:country":"US",
    "sg:address":"5725 Arrowhead Dr",
    "sg:city":"Virginia Beach",
    "sg:classifiers":[
        {
            "category":"Manufacturing",
            "subcategory":"Tools & Machinery",
            "type":"Manufacturing & Wholesale Goods"
        }
    ],
    "sg:phone":"+1 757 518 1222",
    "sg:postcode":"23462",
    "sg:province":"VA",
    "sg:tags":[
        "repair",
        "industrial",
        "sheet",
        "mfg",
        "metal",
        "welding"
    ],
    "wof:name":"A M T",
    "wof:placetype":"venue"
},
  "geometry": {"coordinates":[-76.18422,36.840513],"type":"Point"}
}