{
  "type": "Feature",
  "properties": {
    "addr:full":"U Va Digestive Healt Charlottesville VA 22903",
    "addr:postcode":"22903",
    "iso:country":"US",
    "sg:address":"U Va Digestive Healt",
    "sg:city":"Charlottesville",
    "sg:classifiers":[
        {
            "category":"Health Services",
            "subcategory":"Doctor",
            "type":"Services"
        }
    ],
    "sg:phone":"+1 434 243 2718",
    "sg:postcode":"22903",
    "sg:province":"VA",
    "wof:name":"Cohn Steven M MD PHD",
    "wof:placetype":"venue"
},
  "geometry": {"coordinates":[-78.5205,38.025002],"type":"Point"}
}