{
  "type": "Feature",
  "properties": {
    "iso:country":"US",
    "sg:address":"5445 Colfax Ave",
    "sg:city":"Alexandria",
    "sg:classifiers":[
        {
            "category":"Professional",
            "subcategory":"Lawyer & Legal Services",
            "type":"Services"
        }
    ],
    "sg:phone":"+1 703 820 4999",
    "sg:postcode":"22311",
    "sg:province":"VA",
    "sg:tags":[
        "attorney"
    ],
    "wof:name":"Hadley & Mc Kenna",
    "wof:placetype":"venue"
},
  "geometry": {"coordinates":[-77.122863,38.839788],"type":"Point"}
}