{
  "type": "Feature",
  "properties": {
    "iso:country":"US",
    "sg:address":"7710 Georgetown Pike",
    "sg:city":"Mc Lean",
    "sg:classifiers":[
        {
            "category":"Professional",
            "subcategory":"Lawyer & Legal Services",
            "type":"Services"
        }
    ],
    "sg:phone":"+1 703 356 9593",
    "sg:postcode":"22102",
    "sg:province":"VA",
    "wof:name":"Moses Alfred H Lwyr",
    "wof:placetype":"venue"
},
  "geometry": {"coordinates":[-77.212502,38.9599],"type":"Point"}
}