{
  "type": "Feature",
  "properties": {
    "addr:full":"4207 W Hundred Rd Chester VA 23831",
    "addr:housenumber":"4207",
    "addr:postcode":"23831",
    "addr:street":"W Hundred Rd",
    "iso:country":"US",
    "sg:address":"4207 W Hundred Rd",
    "sg:city":"Chester",
    "sg:classifiers":[
        {
            "category":"Insurance",
            "subcategory":"Insurance Agent",
            "type":"Services"
        }
    ],
    "sg:phone":"+1 804 748 6262",
    "sg:postcode":"23831",
    "sg:province":"VA",
    "wof:name":"Allstate Insurance",
    "wof:placetype":"venue"
},
  "geometry": {"coordinates":[-77.44368799999999,37.357045],"type":"Point"}
}