{
  "type": "Feature",
  "properties": {
    "addr:full":"8 Highland Ave Staunton VA 24401",
    "addr:housenumber":"8",
    "addr:postcode":"24401",
    "addr:street":"Highland Ave",
    "iso:country":"US",
    "sg:address":"8 Highland Ave",
    "sg:city":"Staunton",
    "sg:classifiers":[
        {
            "category":"Home & Garden",
            "subcategory":"Building Materials",
            "type":"Retail Goods"
        }
    ],
    "sg:phone":"+1 540 885 5094",
    "sg:postcode":"24401",
    "sg:province":"VA",
    "sg:tags":[
        "auto",
        "window",
        "glass",
        "plate",
        "replacement"
    ],
    "wof:name":"Augusta Glass & Mirror Inc",
    "wof:placetype":"venue"
},
  "geometry": {"coordinates":[-79.092209,38.154487],"type":"Point"}
}