{
  "type": "Feature",
  "properties": {
    "addr:full":"814 S Loudoun St Winchester VA 22601",
    "addr:housenumber":"814",
    "addr:postcode":"22601",
    "addr:street":"S Loudoun St",
    "iso:country":"US",
    "sg:address":"814 S Loudoun St",
    "sg:city":"Winchester",
    "sg:classifiers":[
        {
            "category":"Home & Garden",
            "subcategory":"Building Materials",
            "type":"Retail Goods"
        }
    ],
    "sg:phone":"+1 540 662 7501",
    "sg:postcode":"22601",
    "sg:province":"VA",
    "sg:tags":[
        "paint",
        "floor",
        "covering"
    ],
    "wof:name":"Sherwin-Williams Paints",
    "wof:placetype":"venue"
},
  "geometry": {"coordinates":[-78.168121,39.177331],"type":"Point"}
}