{
  "type": "Feature",
  "properties": {
    "iso:country":"US",
    "sg:address":"2306 S Eads St",
    "sg:city":"Arlington",
    "sg:classifiers":[
        {
            "category":"Professional",
            "subcategory":"Lawyer & Legal Services",
            "type":"Services"
        }
    ],
    "sg:phone":"+1 703 979 3242",
    "sg:postcode":"22202",
    "sg:province":"VA",
    "sg:tags":[
        "attorney"
    ],
    "wof:name":"Albright Penrose Lucas",
    "wof:placetype":"venue"
},
  "geometry": {"coordinates":[-77.05361000000001,38.852454],"type":"Point"}
}