{
  "type": "Feature",
  "properties": {
    "iso:country":"US",
    "sg:address":"218 N Braddock St",
    "sg:city":"Winchester",
    "sg:classifiers":[
        {
            "category":"Shopping",
            "subcategory":"Used Merchandise",
            "type":"Retail Goods"
        }
    ],
    "sg:phone":"+1 540 722 4792",
    "sg:postcode":"22601",
    "sg:province":"VA",
    "sg:tags":[
        "antique"
    ],
    "wof:name":"Baldwin's Alley Antiques",
    "wof:placetype":"venue"
},
  "geometry": {"coordinates":[-78.16594499999999,39.187265],"type":"Point"}
}