{
  "type": "Feature",
  "properties": {
    "addr:full":"313 Meadow Creek Dr Chesapeake VA 23323",
    "addr:housenumber":"313",
    "addr:postcode":"23323",
    "addr:street":"Meadow Creek Dr",
    "iso:country":"US",
    "sg:address":"313 Meadow Creek Dr",
    "sg:city":"Chesapeake",
    "sg:classifiers":[
        {
            "category":"Building & Trades",
            "subcategory":"Construction",
            "type":"Services"
        }
    ],
    "sg:phone":"+1 757 558 2987",
    "sg:postcode":"23323",
    "sg:province":"VA",
    "sg:tags":[
        "downspouts",
        "gutter"
    ],
    "wof:name":"A Gutter Cleaning & Repair",
    "wof:placetype":"venue"
},
  "geometry": {"coordinates":[-76.33798400000001,36.752542],"type":"Point"}
}