{
  "type": "Feature",
  "properties": {
    "addr:full":"451 Carlisle Dr Herndon VA 20170",
    "addr:housenumber":"451",
    "addr:postcode":"20170",
    "addr:street":"Carlisle Dr",
    "iso:country":"US",
    "sg:address":"451 Carlisle Dr",
    "sg:city":"Herndon",
    "sg:classifiers":[
        {
            "category":"Real Estate",
            "subcategory":"Real Estate Agent",
            "type":"Services"
        },
        {
            "category":"Professional",
            "subcategory":"Business Services",
            "type":"Services"
        }
    ],
    "sg:phone":"+1 703 450 5900",
    "sg:postcode":"20170",
    "sg:province":"VA",
    "sg:tags":[
        "appraiser"
    ],
    "wof:name":"Advanced Appraisal Services",
    "wof:placetype":"venue"
},
  "geometry": {"coordinates":[-77.369063,38.966116],"type":"Point"}
}