{
  "type": "Feature",
  "properties": {
    "iso:country":"US",
    "sg:address":"202 Turkeysag Trl",
    "sg:city":"Palmyra",
    "sg:classifiers":[
        {
            "category":"Home & Garden",
            "subcategory":"Household Appliances",
            "type":"Retail Goods"
        },
        {
            "category":"Retail",
            "subcategory":"Repair Shop",
            "type":"Services"
        }
    ],
    "sg:phone":"+1 434 589 8988",
    "sg:postcode":"22963",
    "sg:province":"VA",
    "sg:tags":[
        "small",
        "major",
        "refinishing",
        "refrigerator",
        "freezers-repair"
    ],
    "wof:name":"Kraft Appliance Service",
    "wof:placetype":"venue"
},
  "geometry": {"coordinates":[-78.342136,37.904328],"type":"Point"}
}