{
  "type": "Feature",
  "properties": {
    "iso:country":"US",
    "sg:address":"11028 Leadbetter Rd Ste 1",
    "sg:city":"Ashland",
    "sg:classifiers":[
        {
            "category":"Autos & Motor Vehicles",
            "subcategory":"Boat Sales",
            "type":"Retail Goods"
        },
        {
            "category":"Manufacturing",
            "subcategory":"Glass & Minerals",
            "type":"Manufacturing & Wholesale Goods"
        }
    ],
    "sg:phone":"+1 804 798 4840",
    "sg:postcode":"23005",
    "sg:province":"VA",
    "sg:tags":[
        "fiberglass",
        "repair",
        "maintenance",
        "fabricator"
    ],
    "sg:website":"http://AWWRIGHTBOATREPAIRSHOP.NET",
    "wof:name":"A.W. Wright & Company",
    "wof:placetype":"venue"
},
  "geometry": {"coordinates":[-77.44368799999999,37.698618],"type":"Point"}
}