{
  "type": "Feature",
  "properties": {
    "addr:full":"3160 Holloway Rd Falls Church VA 22042",
    "addr:housenumber":"3160",
    "addr:postcode":"22042",
    "addr:street":"Holloway Rd",
    "iso:country":"US",
    "sg:address":"3160 Holloway Rd",
    "sg:city":"Falls Church",
    "sg:classifiers":[
        {
            "category":"Shopping",
            "subcategory":"Books",
            "type":"Retail Goods"
        }
    ],
    "sg:phone":"+1 703 532 3661",
    "sg:postcode":"22042",
    "sg:province":"VA",
    "sg:tags":[
        "dealer"
    ],
    "wof:name":"Create-A-Book At Bryan's Trdng",
    "wof:placetype":"venue"
},
  "geometry": {"coordinates":[-77.17317300000001,38.862397],"type":"Point"}
}