{
  "type": "Feature",
  "properties": {
    "addr:full":"6332 Allmondsville Rd Gloucester VA 23061",
    "addr:housenumber":"6332",
    "addr:postcode":"23061",
    "addr:street":"Allmondsville Rd",
    "iso:country":"US",
    "sg:address":"6332 Allmondsville Rd",
    "sg:city":"Gloucester",
    "sg:classifiers":[
        {
            "category":"Building & Trades",
            "subcategory":"Construction",
            "type":"Services"
        }
    ],
    "sg:phone":"+1 804 694 5138",
    "sg:postcode":"23061",
    "sg:province":"VA",
    "sg:tags":[
        "residential",
        "contractor"
    ],
    "wof:name":"LAD Builders Inc",
    "wof:placetype":"venue"
},
  "geometry": {"coordinates":[-76.64116799999999,37.385794],"type":"Point"}
}