{
  "type": "Feature",
  "properties": {
    "addr:full":"404 Norwood Rd Gladstone VA 24553",
    "addr:housenumber":"404",
    "addr:postcode":"24553",
    "addr:street":"Norwood Rd",
    "iso:country":"US",
    "sg:address":"404 Norwood Rd",
    "sg:city":"Gladstone",
    "sg:classifiers":[
        {
            "category":"Organizations",
            "subcategory":"Religious Organization",
            "type":"Services"
        }
    ],
    "sg:phone":"+1 434 933 8129",
    "sg:postcode":"24553",
    "sg:province":"VA",
    "wof:name":"Second Mineral Baptist Church",
    "wof:placetype":"venue"
},
  "geometry": {"coordinates":[-78.86312700000001,37.577592],"type":"Point"}
}