{
  "type": "Feature",
  "properties": {
    "iso:country":"US",
    "sg:address":"533 Jefferson Davis Hwy",
    "sg:city":"Fredericksburg",
    "sg:classifiers":[
        {
            "category":"Professional",
            "subcategory":"Employment Agencies",
            "type":"Services"
        }
    ],
    "sg:phone":"+1 540 371 7001",
    "sg:postcode":"22401",
    "sg:province":"VA",
    "sg:tags":[
        "opportunity"
    ],
    "sg:website":"www.laborready.com",
    "wof:name":"Labor Ready Inc",
    "wof:placetype":"venue"
},
  "geometry": {"coordinates":[-77.475399,38.313334],"type":"Point"}
}