{
  "type": "Feature",
  "properties": {
    "iso:country":"US",
    "sg:address":"908 E Randolph Rd",
    "sg:city":"Hopewell",
    "sg:classifiers":[
        {
            "category":"Retail",
            "subcategory":"Repair Shop",
            "type":"Services"
        }
    ],
    "sg:phone":"+1 804 541 5288",
    "sg:postcode":"23860",
    "sg:province":"VA",
    "wof:name":"Rescar Inc 403",
    "wof:placetype":"venue"
},
  "geometry": {"coordinates":[-77.278301,37.297805],"type":"Point"}
}