{
  "type": "Feature",
  "properties": {
    "addr:full":"19364 Beaver Dam Rd Beaverdam VA 23015",
    "addr:housenumber":"19364",
    "addr:postcode":"23015",
    "addr:street":"Beaver Dam Rd",
    "iso:country":"US",
    "sg:address":"19364 Beaver Dam Rd",
    "sg:city":"Beaverdam",
    "sg:classifiers":[
        {
            "category":"Retail",
            "subcategory":"Auto Repair",
            "type":"Services"
        }
    ],
    "sg:phone":"+1 804 449 6341",
    "sg:postcode":"23015",
    "sg:province":"VA",
    "sg:tags":[
        "body",
        "automobile",
        "painting"
    ],
    "wof:name":"Gayle's Automotive Svc",
    "wof:placetype":"venue"
},
  "geometry": {"coordinates":[-77.654926,37.940883],"type":"Point"}
}