{
  "type": "Feature",
  "properties": {
    "iso:country":"US",
    "sg:address":"1645 Lola Dr",
    "sg:city":"Virginia Beach",
    "sg:classifiers":[
        {
            "category":"Organizations",
            "subcategory":"Religious Organization",
            "type":"Services"
        }
    ],
    "sg:phone":"+1 757 479 0328",
    "sg:postcode":"23464",
    "sg:province":"VA",
    "sg:tags":[
        "clergy"
    ],
    "wof:name":"J L Jackson Rev",
    "wof:placetype":"venue"
},
  "geometry": {"coordinates":[-76.171605,36.778732],"type":"Point"}
}