{
  "type": "Feature",
  "properties": {
    "iso:country":"US",
    "sg:address":"2341 Schenley Dr",
    "sg:city":"Richmond",
    "sg:classifiers":[
        {
            "category":"Professional",
            "subcategory":"Detective & Security Services",
            "type":"Services"
        }
    ],
    "sg:phone":"+1 804 272 4775",
    "sg:postcode":"23235",
    "sg:province":"VA",
    "sg:tags":[
        "information",
        "bureau"
    ],
    "wof:name":"Power Generation Service Of V",
    "wof:placetype":"venue"
},
  "geometry": {"coordinates":[-77.591294,37.526328],"type":"Point"}
}