{
  "type": "Feature",
  "properties": {
    "addr:full":"1015 Ohio St Salem VA 24153",
    "addr:housenumber":"1015",
    "addr:postcode":"24153",
    "addr:street":"Ohio St",
    "iso:country":"US",
    "sg:address":"1015 Ohio St",
    "sg:city":"Salem",
    "sg:classifiers":[
        {
            "category":"Manufacturing",
            "subcategory":"Tools & Machinery",
            "type":"Manufacturing & Wholesale Goods"
        }
    ],
    "sg:phone":"+1 540 389 5100",
    "sg:postcode":"24153",
    "sg:province":"VA",
    "sg:tags":[
        "machine",
        "shop"
    ],
    "wof:name":"Salem Precision Machine",
    "wof:placetype":"venue"
},
  "geometry": {"coordinates":[-80.04245299999999,37.280784],"type":"Point"}
}