{
  "type": "Feature",
  "properties": {
    "iso:country":"US",
    "sg:address":"4803 Valley St",
    "sg:city":"Alexandria",
    "sg:classifiers":[
        {
            "category":"Organizations",
            "subcategory":"Religious Organization",
            "type":"Services"
        }
    ],
    "sg:phone":"+1 703 256 8622",
    "sg:postcode":"22312",
    "sg:province":"VA",
    "wof:name":"Idara Dawat Oirshad USA I",
    "wof:placetype":"venue"
},
  "geometry": {"coordinates":[-77.15764799999999,38.820667],"type":"Point"}
}