{
  "type": "Feature",
  "properties": {
    "addr:full":"11708 Lucasville Rd Manassas VA 20112",
    "addr:housenumber":"11708",
    "addr:postcode":"20112",
    "addr:street":"Lucasville Rd",
    "iso:country":"US",
    "sg:address":"11708 Lucasville Rd",
    "sg:city":"Manassas",
    "sg:classifiers":[
        {
            "category":"Building & Trades",
            "subcategory":"Construction",
            "type":"Services"
        }
    ],
    "sg:phone":"+1 703 330 7001",
    "sg:postcode":"20112",
    "sg:province":"VA",
    "sg:tags":[
        "home",
        "builder"
    ],
    "wof:name":"NV Homes",
    "wof:placetype":"venue"
},
  "geometry": {"coordinates":[-77.491894,38.704178],"type":"Point"}
}