{
  "type": "Feature",
  "properties": {
    "addr:full":"3504 Vimy Ridge Ave Norfolk VA 23509",
    "addr:housenumber":"3504",
    "addr:postcode":"23509",
    "addr:street":"Vimy Ridge Ave",
    "iso:country":"US",
    "sg:address":"3504 Vimy Ridge Ave",
    "sg:city":"Norfolk",
    "sg:classifiers":[
        {
            "category":"Manufacturing",
            "subcategory":"Printing",
            "type":"Manufacturing & Wholesale Goods"
        }
    ],
    "sg:phone":"+1 757 853 2435",
    "sg:postcode":"23509",
    "sg:province":"VA",
    "sg:tags":[
        "printer",
        "commercial"
    ],
    "wof:name":"H & J Printer",
    "wof:placetype":"venue"
},
  "geometry": {"coordinates":[-76.2591,36.884104],"type":"Point"}
}