{
  "type": "Feature",
  "properties": {
    "addr:full":"3789 Benson Ct Dumfries VA 22025",
    "addr:housenumber":"3789",
    "addr:postcode":"22025",
    "addr:street":"Benson Ct",
    "iso:country":"US",
    "sg:address":"3789 Benson Ct",
    "sg:city":"Dumfries",
    "sg:classifiers":[
        {
            "category":"Food & Beverages",
            "subcategory":"Groceries & Convenience Stores",
            "type":"Retail Goods"
        }
    ],
    "sg:phone":"+1 703 221 8648",
    "sg:postcode":"22025",
    "sg:province":"VA",
    "wof:name":"Seven-Express Food Store",
    "wof:placetype":"venue"
},
  "geometry": {"coordinates":[-77.32559999999999,38.607685],"type":"Point"}
}