{
  "type": "Feature",
  "properties": {
    "iso:country":"US",
    "sg:address":"6021 Frederick St",
    "sg:city":"Springfield",
    "sg:classifiers":[
        {
            "category":"Insurance",
            "subcategory":"Hazard Insurance",
            "type":"Services"
        }
    ],
    "sg:phone":"+1 703 569 7133",
    "sg:postcode":"22150",
    "sg:province":"VA",
    "wof:name":"Organisation I Dhammasala",
    "wof:placetype":"venue"
},
  "geometry": {"coordinates":[-77.192339,38.788204],"type":"Point"}
}