{
  "type": "Feature",
  "properties": {
    "addr:full":"10465 Dow Gil Rd Ashland VA 23005",
    "addr:housenumber":"10465",
    "addr:postcode":"23005",
    "addr:street":"Dow Gil Rd",
    "iso:country":"US",
    "sg:address":"10465 Dow Gil Rd",
    "sg:city":"Ashland",
    "sg:classifiers":[
        {
            "category":"Wholesale",
            "subcategory":"Non-durable Goods",
            "type":"Manufacturing & Wholesale Goods"
        },
        {
            "category":"Shopping",
            "subcategory":"Department Store",
            "type":"Retail Goods"
        },
        {
            "category":"Building & Trades",
            "subcategory":"Cleaning & Sanitation",
            "type":"Services"
        },
        {
            "category":"Home & Garden",
            "subcategory":"Hardware",
            "type":"Retail Goods"
        }
    ],
    "sg:phone":"+1 804 798 5857",
    "sg:postcode":"23005",
    "sg:province":"VA",
    "sg:tags":[
        "cleaner",
        "supply",
        "supplies-wholesale",
        "equipment",
        "house",
        "janitor",
        "manufacturer"
    ],
    "sg:website":"http://www.cebcoinc.com",
    "wof:name":"Cebco, Inc",
    "wof:placetype":"venue"
},
  "geometry": {"coordinates":[-77.469077,37.741216],"type":"Point"}
}