{
  "type": "Feature",
  "properties": {
    "addr:full":"241 E Jackson St Gate City VA 24251",
    "addr:housenumber":"241",
    "addr:postcode":"24251",
    "addr:street":"E Jackson St Gate",
    "iso:country":"US",
    "sg:address":"241 E Jackson St",
    "sg:city":"Gate City",
    "sg:classifiers":[
        {
            "category":"Banks & Credit Unions",
            "subcategory":"Bank",
            "type":"Services"
        }
    ],
    "sg:phone":"+1 276 386 6551",
    "sg:postcode":"24251",
    "sg:province":"VA",
    "sg:tags":[
        "loan"
    ],
    "wof:name":"Farm Credit Svc",
    "wof:placetype":"venue"
},
  "geometry": {"coordinates":[-82.577894,36.640039],"type":"Point"}
}