{
  "type": "Feature",
  "properties": {
    "iso:country":"US",
    "sg:address":"8180 Silverbrook Rd",
    "sg:city":"Lorton",
    "sg:classifiers":[
        {
            "category":"Government",
            "subcategory":"Office",
            "type":"Public Place"
        }
    ],
    "sg:phone":"+1 703 550 2450",
    "sg:postcode":"22079",
    "sg:province":"VA",
    "wof:name":"Fairfax County Visitors Ctr",
    "wof:placetype":"venue"
},
  "geometry": {"coordinates":[-77.22848999999999,38.70641],"type":"Point"}
}