{
  "type": "Feature",
  "properties": {
    "addr:full":"1486 Golden View Rd Glade Hill VA 24092",
    "addr:housenumber":"1486",
    "addr:postcode":"24092",
    "addr:street":"Golden View Rd Glade Hill",
    "iso:country":"US",
    "sg:address":"1486 Golden View Rd",
    "sg:city":"Glade Hill",
    "sg:classifiers":[
        {
            "category":"Building & Trades",
            "subcategory":"Construction",
            "type":"Services"
        }
    ],
    "sg:phone":"+1 540 483 0337",
    "sg:postcode":"24092",
    "sg:province":"VA",
    "sg:tags":[
        "house",
        "contractor"
    ],
    "wof:name":"Wendell J Perdue Builder Inc",
    "wof:placetype":"venue"
},
  "geometry": {"coordinates":[-79.80726799999999,37.02766],"type":"Point"}
}