{
  "type": "Feature",
  "properties": {
    "addr:full":"4410 Christiansburg Pike NE Pilot VA 24138",
    "addr:housenumber":"4410",
    "addr:postcode":"24138",
    "addr:street":"Christiansburg Pike Ne",
    "iso:country":"US",
    "sg:address":"4410 Christiansburg Pike NE",
    "sg:city":"Pilot",
    "sg:classifiers":[
        {
            "category":"Social Services",
            "subcategory":"Adult Care",
            "type":"Services"
        }
    ],
    "sg:phone":"+1 540 745 3887",
    "sg:postcode":"24138",
    "sg:province":"VA",
    "sg:tags":[
        "home",
        "group"
    ],
    "wof:name":"Tekoa Inc",
    "wof:placetype":"venue"
},
  "geometry": {"coordinates":[-80.338106,37.018221],"type":"Point"}
}