{
  "type": "Feature",
  "properties": {
    "addr:full":"3290 Rolling Rd Scottsville VA 24590",
    "addr:housenumber":"3290",
    "addr:postcode":"24590",
    "addr:street":"Rolling Rd",
    "iso:country":"US",
    "sg:address":"3290 Rolling Rd",
    "sg:city":"Scottsville",
    "sg:classifiers":[
        {
            "category":"Recreation",
            "type":"Entertainment"
        }
    ],
    "sg:phone":"+1 434 979 2761",
    "sg:postcode":"24590",
    "sg:province":"VA",
    "sg:tags":[
        "amusement"
    ],
    "wof:name":"Truesports Network",
    "wof:placetype":"venue"
},
  "geometry": {"coordinates":[-78.457086,37.945441],"type":"Point"}
}