{
  "type": "Feature",
  "properties": {
    "iso:country":"US",
    "sg:address":"15867 Pebblewood St",
    "sg:city":"Dumfries",
    "sg:classifiers":[
        {
            "category":"Building & Trades",
            "subcategory":"Landscaping Services",
            "type":"Services"
        },
        {
            "category":"Home & Garden",
            "subcategory":"Garden Supply",
            "type":"Retail Goods"
        }
    ],
    "sg:phone":"+1 703 638 2545",
    "sg:postcode":"22025",
    "sg:province":"VA",
    "sg:tags":[
        "consultant",
        "designer",
        "landscape",
        "equipment"
    ],
    "sg:website":"http://www.meadowsfarms.com",
    "wof:name":"Meadows Farms Landscape Design/Build Services",
    "wof:placetype":"venue"
},
  "geometry": {"coordinates":[-77.355752,38.608246],"type":"Point"}
}