{
  "type": "Feature",
  "properties": {
    "addr:full":"13022 Torchlight Dr Woodbridge VA 22193",
    "addr:housenumber":"13022",
    "addr:postcode":"22193",
    "addr:street":"Torchlight Dr",
    "iso:country":"US",
    "sg:address":"13022 Torchlight Dr",
    "sg:city":"Woodbridge",
    "sg:classifiers":[
        {
            "category":"Wholesale",
            "subcategory":"Computers",
            "type":"Manufacturing & Wholesale Goods"
        }
    ],
    "sg:phone":"+1 703 590 2779",
    "sg:postcode":"22193",
    "sg:province":"VA",
    "sg:tags":[
        "repair"
    ],
    "wof:name":"Papa Sharps Computer Repr Svc",
    "wof:placetype":"venue"
},
  "geometry": {"coordinates":[-77.383803,38.670828],"type":"Point"}
}