{
  "type": "Feature",
  "properties": {
    "iso:country":"US",
    "sg:address":"15206 Horseshoe Bridge Rd",
    "sg:city":"Doswell",
    "sg:classifiers":[
        {
            "category":"Personal",
            "type":"Services"
        }
    ],
    "sg:phone":"+1 804 883 7180",
    "sg:postcode":"23047",
    "sg:province":"VA",
    "wof:name":"Fleet Auto Tag & Title Inc",
    "wof:placetype":"venue"
},
  "geometry": {"coordinates":[-77.552511,37.822067],"type":"Point"}
}