{
  "type": "Feature",
  "properties": {
    "iso:country":"US",
    "sg:address":"4231 Dale Blvd",
    "sg:city":"Woodbridge",
    "sg:classifiers":[
        {
            "category":"Insurance",
            "subcategory":"Insurance Agent",
            "type":"Services"
        },
        {
            "category":"Insurance",
            "subcategory":"Hazard Insurance",
            "type":"Services"
        }
    ],
    "sg:phone":"+1 703 680 5700",
    "sg:postcode":"22193",
    "sg:province":"VA",
    "sg:tags":[
        "auto",
        "recreational",
        "motorcycle",
        "vehicle",
        "marine",
        "boat"
    ],
    "wof:name":"Simply Auto Insurance Agency",
    "wof:placetype":"venue"
},
  "geometry": {"coordinates":[-77.336906,38.644055],"type":"Point"}
}