{
  "type": "Feature",
  "properties": {
    "iso:country":"US",
    "sg:address":"5216 Rolling Rd",
    "sg:city":"Burke",
    "sg:classifiers":[
        {
            "category":"Health Services",
            "subcategory":"Chiropractor",
            "type":"Services"
        }
    ],
    "sg:phone":"+1 703 323 8500",
    "sg:postcode":"22015",
    "sg:province":"VA",
    "wof:name":"Commonwealth Family Healthcare",
    "wof:placetype":"venue"
},
  "geometry": {"coordinates":[-77.254981,38.807927],"type":"Point"}
}