{
  "type": "Feature",
  "properties": {
    "addr:full":"1209 Benns Church Blvd Smithfield VA 23430",
    "addr:housenumber":"1209",
    "addr:postcode":"23430",
    "addr:street":"Benns Church Blvd",
    "iso:country":"US",
    "sg:address":"1209 Benns Church Blvd",
    "sg:city":"Smithfield",
    "sg:classifiers":[
        {
            "category":"Sports & Exercise",
            "subcategory":"Gym",
            "type":"Entertainment"
        }
    ],
    "sg:phone":"+1 757 356 9944",
    "sg:postcode":"23430",
    "sg:province":"VA",
    "sg:tags":[
        "club",
        "health",
        "studio",
        "gymnasium"
    ],
    "wof:name":"Contours Express",
    "wof:placetype":"venue"
},
  "geometry": {"coordinates":[-76.60314700000001,36.958438],"type":"Point"}
}