{
  "type": "Feature",
  "properties": {
    "addr:full":"2056 Kenlake Pl Norfolk VA 23518",
    "addr:housenumber":"2056",
    "addr:postcode":"va 23518",
    "addr:street":"Kenlake Pl",
    "iso:country":"US",
    "sg:address":"2056 Kenlake Pl",
    "sg:city":"Norfolk",
    "sg:classifiers":[
        {
            "category":"Building & Trades",
            "subcategory":"Landscaping Services",
            "type":"Services"
        }
    ],
    "sg:phone":"+1 757 857 0371",
    "sg:postcode":"23518",
    "sg:province":"VA",
    "sg:tags":[
        "landscape",
        "contractor"
    ],
    "wof:name":"Terrell's Lawn & Landscape",
    "wof:placetype":"venue"
},
  "geometry": {"coordinates":[-76.216814,36.903962],"type":"Point"}
}