{
  "type": "Feature",
  "properties": {
    "addr:full":"17 Bondurant St Martinsville VA 24112",
    "addr:housenumber":"17",
    "addr:postcode":"24112",
    "addr:street":"Bondurant St",
    "iso:country":"US",
    "sg:address":"17 Bondurant St",
    "sg:city":"Martinsville",
    "sg:classifiers":[
        {
            "category":"Manufacturing",
            "subcategory":"Retail Goods",
            "type":"Manufacturing & Wholesale Goods"
        }
    ],
    "sg:phone":"+1 276 632 5875",
    "sg:postcode":"24112",
    "sg:province":"VA",
    "sg:tags":[
        "lead",
        "mfg"
    ],
    "wof:name":"Art Show",
    "wof:placetype":"venue"
},
  "geometry": {"coordinates":[-79.858875,36.68823],"type":"Point"}
}