{
  "type": "Feature",
  "properties": {
    "iso:country":"US",
    "sg:address":"501 S Washington St",
    "sg:city":"Alexandria",
    "sg:classifiers":[
        {
            "category":"Autos & Motor Vehicles",
            "subcategory":"Fuel & Gas Station",
            "type":"Retail Goods"
        }
    ],
    "sg:phone":"+1 703 549 6631",
    "sg:postcode":"22314",
    "sg:province":"VA",
    "sg:tags":[
        "oil"
    ],
    "wof:name":"Alexandria Exxon",
    "wof:placetype":"venue"
},
  "geometry": {"coordinates":[-77.04818299999999,38.799372],"type":"Point"}
}