{
  "type": "Feature",
  "properties": {
    "addr:full":"11 W 4th St Salem VA 24153",
    "addr:housenumber":"11",
    "addr:postcode":"24153",
    "addr:street":"W 4Th St",
    "iso:country":"US",
    "sg:address":"11 W 4th St",
    "sg:city":"Salem",
    "sg:classifiers":[
        {
            "category":"Communications",
            "subcategory":"Film & Video Production",
            "type":"Services"
        }
    ],
    "sg:phone":"+1 540 375 0070",
    "sg:postcode":"24153",
    "sg:province":"VA",
    "sg:tags":[
        "taping"
    ],
    "wof:name":"Video Ventures",
    "wof:placetype":"venue"
},
  "geometry": {"coordinates":[-80.058019,37.286177],"type":"Point"}
}