{
  "type": "Feature",
  "properties": {
    "iso:country":"US",
    "sg:address":"14352 Wrangler Ln",
    "sg:city":"Woodbridge",
    "sg:classifiers":[
        {
            "category":"Real Estate",
            "subcategory":"Real Estate Operator",
            "type":"Services"
        }
    ],
    "sg:phone":"+1 703 878 3005",
    "sg:postcode":"22193",
    "sg:province":"VA",
    "sg:tags":[
        "building",
        "apartment"
    ],
    "wof:name":"Coombs",
    "wof:placetype":"venue"
},
  "geometry": {"coordinates":[-77.340216,38.640391],"type":"Point"}
}