{
  "type": "Feature",
  "properties": {
    "iso:country":"US",
    "sg:address":"6704 Braddock Rd",
    "sg:city":"Annandale",
    "sg:classifiers":[
        {
            "category":"Organizations",
            "subcategory":"Religious Organization",
            "type":"Services"
        }
    ],
    "sg:phone":"+1 703 256 5590",
    "sg:postcode":"22003",
    "sg:province":"VA",
    "wof:name":"Trinity Community",
    "wof:placetype":"venue"
},
  "geometry": {"coordinates":[-77.177897,38.811965],"type":"Point"}
}