{
  "type": "Feature",
  "properties": {
    "iso:country":"US",
    "sg:address":"83 Lincoln St",
    "sg:city":"Hampton",
    "sg:classifiers":[
        {
            "category":"Wholesale",
            "subcategory":"Machinery & Supplies",
            "type":"Manufacturing & Wholesale Goods"
        }
    ],
    "sg:phone":"+1 757 722 6855",
    "sg:postcode":"23669",
    "sg:province":"VA",
    "sg:tags":[
        "equipment",
        "establishment"
    ],
    "wof:name":"Beauty World Discount Supply",
    "wof:placetype":"venue"
},
  "geometry": {"coordinates":[-76.34777699999999,37.027635],"type":"Point"}
}