{
  "type": "Feature",
  "properties": {
    "addr:full":"30285 Bobtown Rd Pungoteague VA 23422",
    "addr:postcode":"30285;23422",
    "addr:street":"Bobtown Rd",
    "iso:country":"US",
    "sg:address":"30285 Bobtown Rd",
    "sg:city":"Pungoteague",
    "sg:classifiers":[
        {
            "category":"Food & Beverages",
            "subcategory":"Groceries & Convenience Stores",
            "type":"Retail Goods"
        }
    ],
    "sg:phone":"+1 757 442 2124",
    "sg:postcode":"23422",
    "sg:province":"VA",
    "sg:tags":[
        "grocer"
    ],
    "wof:name":"Village General Store",
    "wof:placetype":"venue"
},
  "geometry": {"coordinates":[-75.815763,37.629686],"type":"Point"}
}