{
  "type": "Feature",
  "properties": {
    "iso:country":"US",
    "sg:address":"409 Slate St",
    "sg:city":"Chesapeake",
    "sg:classifiers":[
        {
            "category":"Real Estate",
            "subcategory":"Real Estate Agent",
            "type":"Services"
        }
    ],
    "sg:phone":"+1 757 482 0171",
    "sg:postcode":"23322",
    "sg:province":"VA",
    "wof:name":"Alan M Keffer & Associates",
    "wof:placetype":"venue"
},
  "geometry": {"coordinates":[-76.182174,36.713031],"type":"Point"}
}