{
  "type": "Feature",
  "properties": {
    "addr:full":"3440 Londonderry Ct Roanoke VA 24018",
    "addr:housenumber":"3440",
    "addr:postcode":"24018",
    "addr:street":"Londonderry Ct",
    "iso:country":"US",
    "sg:address":"3440 Londonderry Ct",
    "sg:city":"Roanoke",
    "sg:classifiers":[
        {
            "category":"Professional",
            "type":"Services"
        }
    ],
    "sg:phone":"+1 540 989 7002",
    "sg:postcode":"24018",
    "sg:province":"VA",
    "wof:name":"GA White & Co Inc",
    "wof:placetype":"venue"
},
  "geometry": {"coordinates":[-79.98949,37.219481],"type":"Point"}
}