{
  "type": "Feature",
  "properties": {
    "addr:full":"1344 Meade Dr Suffolk VA 23434",
    "addr:housenumber":"1344",
    "addr:postcode":"23434",
    "addr:street":"Meade Dr",
    "iso:country":"US",
    "sg:address":"1344 Meade Dr",
    "sg:city":"Suffolk",
    "sg:classifiers":[
        {
            "category":"Organizations",
            "subcategory":"Professional Association",
            "type":"Services"
        }
    ],
    "sg:phone":"+1 757 539 8601",
    "sg:postcode":"23434",
    "sg:province":"VA",
    "wof:name":"International Reading Assoc",
    "wof:placetype":"venue"
},
  "geometry": {"coordinates":[-76.616302,36.749994],"type":"Point"}
}