{
  "type": "Feature",
  "properties": {
    "addr:full":"802 Seminole Dr Suffolk VA 23434",
    "addr:housenumber":"802",
    "addr:postcode":"23434",
    "addr:street":"Seminole Dr",
    "iso:country":"US",
    "sg:address":"802 Seminole Dr",
    "sg:city":"Suffolk",
    "sg:classifiers":[
        {
            "category":"Organizations",
            "subcategory":"Professional Association",
            "type":"Services"
        }
    ],
    "sg:phone":"+1 757 539 3780",
    "sg:postcode":"23434",
    "sg:province":"VA",
    "sg:tags":[
        "business"
    ],
    "wof:name":"Economy Builders Association",
    "wof:placetype":"venue"
},
  "geometry": {"coordinates":[-76.570973,36.713009],"type":"Point"}
}