{
  "type": "Feature",
  "properties": {
    "addr:full":"5205 Watercrest Rd Midlothian VA 23112",
    "addr:housenumber":"5205",
    "addr:postcode":"23112",
    "addr:street":"Watercrest Rd",
    "iso:country":"US",
    "sg:address":"5205 Watercrest Rd",
    "sg:city":"Midlothian",
    "sg:classifiers":[
        {
            "category":"Professional",
            "subcategory":"Business Services",
            "type":"Services"
        }
    ],
    "sg:phone":"+1 804 744 3583",
    "sg:postcode":"23112",
    "sg:province":"VA",
    "wof:name":"D & M Enterprises",
    "wof:placetype":"venue"
},
  "geometry": {"coordinates":[-77.669129,37.428383],"type":"Point"}
}