{
  "type": "Feature",
  "properties": {
    "addr:full":"536 Rosemary Ln Danville VA 24541",
    "addr:housenumber":"536",
    "addr:postcode":"24541",
    "addr:street":"Rosemary Ln",
    "iso:country":"US",
    "sg:address":"536 Rosemary Ln",
    "sg:city":"Danville",
    "sg:classifiers":[
        {
            "category":"Building & Trades",
            "subcategory":"Electrical",
            "type":"Services"
        }
    ],
    "sg:phone":"+1 434 799 6206",
    "sg:postcode":"24541",
    "sg:province":"VA",
    "sg:tags":[
        "electrical",
        "contractor"
    ],
    "wof:name":"Jordan Electric Comp",
    "wof:placetype":"venue"
},
  "geometry": {"coordinates":[-79.441823,36.590849],"type":"Point"}
}