{
  "type": "Feature",
  "properties": {
    "iso:country":"US",
    "sg:address":"6435 Lee Hwy",
    "sg:city":"Warrenton",
    "sg:classifiers":[
        {
            "category":"Coffee & Tea",
            "type":"Food & Drink"
        }
    ],
    "sg:phone":"+1 540 347 6475",
    "sg:postcode":"20187",
    "sg:province":"VA",
    "sg:website":"www.starbucks.com",
    "wof:name":"Starbucks Coffee",
    "wof:placetype":"venue"
},
  "geometry": {"coordinates":[-77.77129499999999,38.734013],"type":"Point"}
}