{
  "type": "Feature",
  "properties": {
    "addr:full":"555 N Franklin St Christiansburg VA 24073",
    "addr:housenumber":"555",
    "addr:postcode":"24073",
    "addr:street":"N Franklin St",
    "iso:country":"US",
    "sg:address":"555 N Franklin St",
    "sg:city":"Christiansburg",
    "sg:classifiers":[
        {
            "category":"Food & Beverages",
            "subcategory":"Groceries & Convenience Stores",
            "type":"Retail Goods"
        }
    ],
    "sg:phone":"+1 540 381 8713",
    "sg:postcode":"24073",
    "sg:province":"VA",
    "sg:tags":[
        "grocer"
    ],
    "wof:name":"Kroger",
    "wof:placetype":"venue"
},
  "geometry": {"coordinates":[-80.413746,37.136147],"type":"Point"}
}