{
  "type": "Feature",
  "properties": {
    "addr:full":"18960 Boydton Plank Rd Warfield VA 23889",
    "addr:postcode":"18960;23889",
    "addr:street":"Plank Rd",
    "iso:country":"US",
    "sg:address":"18960 Boydton Plank Rd",
    "sg:city":"Warfield",
    "sg:classifiers":[
        {
            "category":"Autos & Motor Vehicles",
            "subcategory":"Auto Supplies",
            "type":"Retail Goods"
        }
    ],
    "sg:phone":"+1 804 478 4920",
    "sg:postcode":"23889",
    "sg:province":"VA",
    "wof:name":"H&H Used Auto & Truck Parts",
    "wof:placetype":"venue"
},
  "geometry": {"coordinates":[-77.757999,36.93001],"type":"Point"}
}