{
  "type": "Feature",
  "properties": {
    "iso:country":"US",
    "sg:address":"301 Cleveland Pl",
    "sg:city":"Virginia Beach",
    "sg:classifiers":[
        {
            "category":"Health Services",
            "subcategory":"Clinic",
            "type":"Services"
        }
    ],
    "sg:phone":"+1 757 671 1802",
    "sg:postcode":"23462",
    "sg:province":"VA",
    "sg:tags":[
        "home",
        "care"
    ],
    "wof:name":"Lincare Inc",
    "wof:placetype":"venue"
},
  "geometry": {"coordinates":[-76.16164499999999,36.844181],"type":"Point"}
}