{
  "type": "Feature",
  "properties": {
    "addr:full":"915 King St Alexandria VA 22314",
    "addr:housenumber":"915",
    "addr:postcode":"22314",
    "addr:street":"King St",
    "iso:country":"US",
    "sg:address":"915 King St",
    "sg:city":"Alexandria",
    "sg:classifiers":[
        {
            "category":"Shopping",
            "subcategory":"Clothing, Apparel, & Fashions",
            "type":"Retail Goods"
        }
    ],
    "sg:phone":"+1 703 684 0080",
    "sg:postcode":"22314",
    "sg:province":"VA",
    "sg:tags":[
        "home",
        "an",
        "furnishing",
        "wear",
        "furniture"
    ],
    "wof:name":"Nantucket Moon LLC",
    "wof:placetype":"venue"
},
  "geometry": {"coordinates":[-77.050155,38.805537],"type":"Point"}
}