{
  "type": "Feature",
  "properties": {
    "iso:country":"US",
    "sg:address":"3710 John Tyler Memorial Hwy",
    "sg:city":"Charles City",
    "sg:classifiers":[
        {
            "category":"Food & Beverages",
            "subcategory":"Groceries & Convenience Stores",
            "type":"Retail Goods"
        }
    ],
    "sg:phone":"+1 804 829 9463",
    "sg:postcode":"23030",
    "sg:province":"VA",
    "sg:tags":[
        "grocer"
    ],
    "wof:name":"Ghee's Grocery",
    "wof:placetype":"venue"
},
  "geometry": {"coordinates":[-77.20580099999999,37.338886],"type":"Point"}
}