{
  "type": "Feature",
  "properties": {
    "iso:country":"US",
    "sg:address":"111 Legrande Ave",
    "sg:city":"Charlotte Ct Hse",
    "sg:classifiers":[
        {
            "category":"Government",
            "subcategory":"Court House",
            "type":"Public Place"
        }
    ],
    "sg:phone":"+1 434 542 5600",
    "sg:postcode":"23923",
    "sg:province":"VA",
    "sg:tags":[
        "county"
    ],
    "wof:name":"Charlotte District Court",
    "wof:placetype":"venue"
},
  "geometry": {"coordinates":[-78.637933,37.056198],"type":"Point"}
}