{
  "type": "Feature",
  "properties": {
    "addr:full":"65 Lee Jackson Hwy Staunton VA 24401",
    "addr:housenumber":"65",
    "addr:postcode":"24401",
    "addr:street":"Lee Jackson Hwy",
    "iso:country":"US",
    "sg:address":"65 Lee Jackson Hwy",
    "sg:city":"Staunton",
    "sg:classifiers":[
        {
            "category":"Restaurant",
            "type":"Food & Drink"
        }
    ],
    "sg:phone":"+1 540 886 0786",
    "sg:postcode":"24401",
    "sg:province":"VA",
    "wof:name":"Sam's Hot Dogs",
    "wof:placetype":"venue"
},
  "geometry": {"coordinates":[-79.101478,38.073419],"type":"Point"}
}