{
  "type": "Feature",
  "properties": {
    "addr:full":"2343 Dale Dr Falls Church VA 22043",
    "addr:housenumber":"2343",
    "addr:postcode":"22043",
    "addr:street":"Dale Dr",
    "iso:country":"US",
    "sg:address":"2343 Dale Dr",
    "sg:city":"Falls Church",
    "sg:classifiers":[
        {
            "category":"Wholesale",
            "subcategory":"Machinery & Supplies",
            "type":"Manufacturing & Wholesale Goods"
        }
    ],
    "sg:phone":"+1 703 641 9480",
    "sg:postcode":"22043",
    "sg:province":"VA",
    "sg:tags":[
        "equipment",
        "welding"
    ],
    "wof:name":"Airgas",
    "wof:placetype":"venue"
},
  "geometry": {"coordinates":[-77.196388,38.893754],"type":"Point"}
}