{
  "type": "Feature",
  "properties": {
    "addr:full":"1409 Moore Pl SW Leesburg VA 20175",
    "addr:housenumber":"1409",
    "addr:postcode":"20175",
    "addr:street":"Moore Pl Sw",
    "iso:country":"US",
    "sg:address":"1409 Moore Pl SW",
    "sg:city":"Leesburg",
    "sg:classifiers":[
        {
            "category":"Professional",
            "type":"Services"
        }
    ],
    "sg:phone":"+1 703 737 0137",
    "sg:postcode":"20175",
    "sg:province":"VA",
    "wof:name":"Kushlaw Inc",
    "wof:placetype":"venue"
},
  "geometry": {"coordinates":[-77.591375,39.093022],"type":"Point"}
}