{
  "type": "Feature",
  "properties": {
    "addr:full":"4019 Main St Chincoteague VA 23336",
    "addr:housenumber":"4019",
    "addr:postcode":"23336",
    "addr:street":"Main St",
    "iso:country":"US",
    "sg:address":"4019 Main St",
    "sg:city":"Chincoteague",
    "sg:classifiers":[
        {
            "category":"Shopping",
            "subcategory":"Bicycles & Sporting Goods",
            "type":"Retail Goods"
        }
    ],
    "sg:phone":"+1 757 336 5188",
    "sg:postcode":"23336",
    "sg:province":"VA",
    "wof:name":"Barnacle Bills Bait & Tackle",
    "wof:placetype":"venue"
},
  "geometry": {"coordinates":[-75.37868,37.933052],"type":"Point"}
}