{
  "type": "Feature",
  "properties": {
    "iso:country":"US",
    "sg:address":"9706 Lee Hwy",
    "sg:city":"Weyers Cave",
    "sg:classifiers":[
        {
            "category":"Autos & Motor Vehicles",
            "subcategory":"Automobile Sales",
            "type":"Retail Goods"
        }
    ],
    "sg:phone":"+1 540 234 6003",
    "sg:postcode":"24486",
    "sg:province":"VA",
    "sg:tags":[
        "used"
    ],
    "wof:name":"EDS Auto Mart",
    "wof:placetype":"venue"
},
  "geometry": {"coordinates":[-78.93704099999999,38.321294],"type":"Point"}
}