{
  "type": "Feature",
  "properties": {
    "addr:full":"11868 Breton Ct Reston VA 20191",
    "addr:housenumber":"11868",
    "addr:postcode":"20191",
    "addr:street":"Breton Ct",
    "iso:country":"US",
    "sg:address":"11868 Breton Ct",
    "sg:city":"Reston",
    "sg:classifiers":[
        {
            "category":"Professional",
            "subcategory":"Business Services",
            "type":"Services"
        }
    ],
    "sg:phone":"+1 703 453 9171",
    "sg:postcode":"20191",
    "sg:province":"VA",
    "sg:tags":[
        "translation"
    ],
    "wof:name":"Mario A Montenegro",
    "wof:placetype":"venue"
},
  "geometry": {"coordinates":[-77.36032899999999,38.935188],"type":"Point"}
}