{
  "type": "Feature",
  "properties": {
    "addr:full":"234 Old Main St Brookneal VA 24528",
    "addr:housenumber":"234",
    "addr:postcode":"24528",
    "addr:street":"Old Main St",
    "iso:country":"US",
    "sg:address":"234 Old Main St",
    "sg:city":"Brookneal",
    "sg:classifiers":[
        {
            "category":"Manufacturing",
            "subcategory":"Pet Food",
            "type":"Manufacturing & Wholesale Goods"
        }
    ],
    "sg:phone":"+1 434 376 2939",
    "sg:postcode":"24528",
    "sg:province":"VA",
    "sg:tags":[
        "dog",
        "cat"
    ],
    "wof:name":"Brookneal Milling Co Inc",
    "wof:placetype":"venue"
},
  "geometry": {"coordinates":[-78.942126,37.043417],"type":"Point"}
}