{
  "type": "Feature",
  "properties": {
    "addr:full":"3505 Howard Rd Richmond VA 23223",
    "addr:housenumber":"3505",
    "addr:postcode":"23223",
    "addr:street":"Howard Rd",
    "iso:country":"US",
    "sg:address":"3505 Howard Rd",
    "sg:city":"Richmond",
    "sg:classifiers":[
        {
            "category":"Retail",
            "subcategory":"Car Wash",
            "type":"Services"
        }
    ],
    "sg:phone":"+1 804 644 1444",
    "sg:postcode":"23223",
    "sg:province":"VA",
    "sg:tags":[
        "carwash"
    ],
    "wof:name":"Www Walters Wash & Wax",
    "wof:placetype":"venue"
},
  "geometry": {"coordinates":[-77.389916,37.572786],"type":"Point"}
}