{
  "type": "Feature",
  "properties": {
    "addr:full":"170 Southgate Sq Colonial Heights VA 23834",
    "addr:housenumber":"170",
    "addr:postcode":"23834",
    "addr:street":"Southgate Sq",
    "iso:country":"US",
    "sg:address":"170 Southgate Sq",
    "sg:city":"Colonial Heights",
    "sg:classifiers":[
        {
            "category":"Restaurant",
            "type":"Food & Drink"
        }
    ],
    "sg:phone":"+1 804 504 0678",
    "sg:postcode":"23834",
    "sg:province":"VA",
    "wof:name":"Anthony's Pizza Subs & Pasta",
    "wof:placetype":"venue"
},
  "geometry": {"coordinates":[-77.39086,37.248126],"type":"Point"}
}