{
  "type": "Feature",
  "properties": {
    "iso:country":"US",
    "sg:address":"6265 Snowfox Ln",
    "sg:city":"Broad Run",
    "sg:classifiers":[
        {
            "category":"Retail",
            "subcategory":"Auto Repair",
            "type":"Services"
        }
    ],
    "sg:phone":"+1 703 467 0437",
    "sg:postcode":"20137",
    "sg:province":"VA",
    "sg:tags":[
        "repairing",
        "automobile"
    ],
    "wof:name":"T & J Automotive",
    "wof:placetype":"venue"
},
  "geometry": {"coordinates":[-77.75134,38.777153],"type":"Point"}
}