{
  "type": "Feature",
  "properties": {
    "addr:full":"4029 E Little Creek Rd Norfolk VA 23518",
    "addr:housenumber":"4029",
    "addr:postcode":"23518",
    "addr:street":"E Little Creek Rd",
    "iso:country":"US",
    "sg:address":"4029 E Little Creek Rd",
    "sg:city":"Norfolk",
    "sg:classifiers":[
        {
            "category":"Shopping",
            "subcategory":"Jewelry",
            "type":"Retail Goods"
        }
    ],
    "sg:phone":"+1 757 587 1757",
    "sg:postcode":"23518",
    "sg:province":"VA",
    "sg:tags":[
        "jeweler"
    ],
    "wof:name":"H C Barker & Son Inc",
    "wof:placetype":"venue"
},
  "geometry": {"coordinates":[-76.195863,36.917884],"type":"Point"}
}