{
  "type": "Feature",
  "properties": {
    "iso:country":"US",
    "sg:address":"316 Atlantic Ave",
    "sg:city":"Hampton",
    "sg:classifiers":[
        {
            "category":"Real Estate",
            "subcategory":"Real Estate Agent",
            "type":"Services"
        }
    ],
    "sg:phone":"+1 757 851 8758",
    "sg:postcode":"23664",
    "sg:province":"VA",
    "wof:name":"Tri Man Enterprises Inc",
    "wof:placetype":"venue"
},
  "geometry": {"coordinates":[-76.297445,37.0398],"type":"Point"}
}