{
  "type": "Feature",
  "properties": {
    "iso:country":"US",
    "sg:address":"511 Germanna Hwy",
    "sg:city":"Culpeper",
    "sg:classifiers":[
        {
            "category":"Retail",
            "subcategory":"Repair Shop",
            "type":"Services"
        }
    ],
    "sg:phone":"+1 540 825 6191",
    "sg:postcode":"22701",
    "sg:province":"VA",
    "wof:name":"Ferguson Taxidermy",
    "wof:placetype":"venue"
},
  "geometry": {"coordinates":[-77.995107,38.46151],"type":"Point"}
}