{
  "type": "Feature",
  "properties": {
    "addr:full":"66 Rocky Ln Strasburg VA 22657",
    "addr:housenumber":"66",
    "addr:postcode":"22657",
    "addr:street":"Rocky Ln",
    "iso:country":"US",
    "sg:address":"66 Rocky Ln",
    "sg:city":"Strasburg",
    "sg:classifiers":[
        {
            "category":"Building & Trades",
            "subcategory":"Plumbing",
            "type":"Services"
        }
    ],
    "sg:phone":"+1 540 465 4079",
    "sg:postcode":"22657",
    "sg:province":"VA",
    "sg:tags":[
        "septic"
    ],
    "wof:name":"Tevault Septic Svc",
    "wof:placetype":"venue"
},
  "geometry": {"coordinates":[-78.394581,38.98252],"type":"Point"}
}