{
  "type": "Feature",
  "properties": {
    "addr:full":"43110 Weatherwood Dr Ashburn VA 20147",
    "addr:housenumber":"43110",
    "addr:postcode":"20147",
    "addr:street":"Weatherwood Dr",
    "iso:country":"US",
    "sg:address":"43110 Weatherwood Dr",
    "sg:city":"Ashburn",
    "sg:classifiers":[
        {
            "category":"Professional",
            "type":"Services"
        }
    ],
    "sg:phone":"+1 703 723 8142",
    "sg:postcode":"20147",
    "sg:province":"VA",
    "sg:tags":[
        "establishment"
    ],
    "wof:name":"Csc-K Pack Isdn",
    "wof:placetype":"venue"
},
  "geometry": {"coordinates":[-77.51209299999999,39.045278],"type":"Point"}
}