{
  "type": "Feature",
  "properties": {
    "addr:full":"410 Patton St Danville VA 24541",
    "addr:housenumber":"410",
    "addr:postcode":"24541",
    "addr:street":"Patton St",
    "iso:country":"US",
    "sg:address":"410 Patton St",
    "sg:city":"Danville",
    "sg:classifiers":[
        {
            "category":"Professional",
            "subcategory":"Secretarial Services",
            "type":"Services"
        }
    ],
    "sg:phone":"+1 434 792 5408",
    "sg:postcode":"24541",
    "sg:province":"VA",
    "sg:tags":[
        "reporting",
        "court"
    ],
    "wof:name":"Secretarial Services Dvrsfd",
    "wof:placetype":"venue"
},
  "geometry": {"coordinates":[-79.391227,36.587118],"type":"Point"}
}