{
  "type": "Feature",
  "properties": {
    "addr:full":"9816 Winchester Rd Front Royal VA 22630",
    "addr:housenumber":"9816",
    "addr:postcode":"22630",
    "addr:street":"Winchester Rd",
    "iso:country":"US",
    "sg:address":"9816 Winchester Rd",
    "sg:city":"Front Royal",
    "sg:classifiers":[
        {
            "category":"Personal",
            "type":"Services"
        }
    ],
    "sg:phone":"+1 540 631 0900",
    "sg:postcode":"22630",
    "sg:province":"VA",
    "sg:tags":[
        "control",
        "weight"
    ],
    "wof:name":"Healthy Inspirations",
    "wof:placetype":"venue"
},
  "geometry": {"coordinates":[-78.19449299999999,38.959181],"type":"Point"}
}