{
  "type": "Feature",
  "properties": {
    "iso:country":"US",
    "sg:address":"213 Greenland Dr",
    "sg:city":"Yorktown",
    "sg:classifiers":[
        {
            "category":"Professional",
            "subcategory":"Computer Services",
            "type":"Services"
        }
    ],
    "sg:phone":"+1 757 303 3578",
    "sg:postcode":"23693",
    "sg:province":"VA",
    "sg:tags":[
        "related"
    ],
    "wof:name":"Three Computeers",
    "wof:placetype":"venue"
},
  "geometry": {"coordinates":[-76.44798299999999,37.124384],"type":"Point"}
}