{
  "type": "Feature",
  "properties": {
    "addr:full":"112 Campbell Ave SE Roanoke VA 24011",
    "addr:housenumber":"112",
    "addr:postcode":"24011",
    "addr:street":"Campbell Ave Se",
    "iso:country":"US",
    "sg:address":"112 Campbell Ave SE",
    "sg:city":"Roanoke",
    "sg:classifiers":[
        {
            "category":"Restaurant",
            "type":"Food & Drink"
        }
    ],
    "sg:phone":"+1 540 342 9404",
    "sg:postcode":"24011",
    "sg:province":"VA",
    "sg:tags":[
        "eating"
    ],
    "wof:name":"Johnson & Elich Roasters Ltd",
    "wof:placetype":"venue"
},
  "geometry": {"coordinates":[-79.938541,37.271866],"type":"Point"}
}