{
  "type": "Feature",
  "properties": {
    "iso:country":"US",
    "sg:address":"2049 Mayfair McLean Ct",
    "sg:city":"Falls Church",
    "sg:classifiers":[
        {
            "category":"Professional",
            "subcategory":"Business Services",
            "type":"Services"
        }
    ],
    "sg:phone":"+1 703 533 5500",
    "sg:postcode":"22043",
    "sg:province":"VA",
    "wof:name":"Philadelphia Convention",
    "wof:placetype":"venue"
},
  "geometry": {"coordinates":[-77.17226599999999,38.910699],"type":"Point"}
}