{
  "type": "Feature",
  "properties": {
    "addr:full":"10300 Richmond Rd Warsaw VA 22572",
    "addr:housenumber":"10300",
    "addr:postcode":"22572",
    "addr:street":"Richmond Rd",
    "iso:country":"US",
    "sg:address":"10300 Richmond Rd",
    "sg:city":"Warsaw",
    "sg:classifiers":[
        {
            "category":"Retail",
            "subcategory":"Funeral Services",
            "type":"Services"
        }
    ],
    "sg:phone":"+1 804 333 3770",
    "sg:postcode":"22572",
    "sg:province":"VA",
    "sg:tags":[
        "director"
    ],
    "wof:name":"Welch Marks Funeral Homes",
    "wof:placetype":"venue"
},
  "geometry": {"coordinates":[-76.69830899999999,37.94916],"type":"Point"}
}