{
  "type": "Feature",
  "properties": {
    "addr:full":"417 Washington St Altavista VA 24517",
    "addr:housenumber":"417",
    "addr:postcode":"24517",
    "addr:street":"Washington St",
    "iso:country":"US",
    "sg:address":"417 Washington St",
    "sg:city":"Altavista",
    "sg:classifiers":[
        {
            "category":"Organizations",
            "subcategory":"Non-profit Organization",
            "type":"Services"
        }
    ],
    "sg:phone":"+1 434 369 6920",
    "sg:postcode":"24517",
    "sg:province":"VA",
    "wof:name":"Sheltered Workshop",
    "wof:placetype":"venue"
},
  "geometry": {"coordinates":[-79.29221200000001,37.108907],"type":"Point"}
}