{
  "type": "Feature",
  "properties": {
    "addr:full":"356 S Main St Harrisonburg VA 22801",
    "addr:housenumber":"356",
    "addr:postcode":"22801",
    "addr:street":"S Main St",
    "iso:country":"US",
    "sg:address":"356 S Main St",
    "sg:city":"Harrisonburg",
    "sg:classifiers":[
        {
            "category":"Social Services",
            "type":"Services"
        }
    ],
    "sg:phone":"+1 540 801 8400",
    "sg:postcode":"22801",
    "sg:province":"VA",
    "sg:tags":[
        "counseling"
    ],
    "wof:name":"Craig E Abrahamson",
    "wof:placetype":"venue"
},
  "geometry": {"coordinates":[-78.86944,38.445806],"type":"Point"}
}