{
  "type": "Feature",
  "properties": {
    "addr:full":"8014 Midlothian Tpke Richmond VA 23235",
    "addr:housenumber":"8014",
    "addr:postcode":"23235",
    "addr:street":"Midlothian Tpke",
    "iso:country":"US",
    "sg:address":"8014 Midlothian Tpke",
    "sg:city":"Richmond",
    "sg:classifiers":[
        {
            "category":"Professional",
            "subcategory":"Detective & Security Services",
            "type":"Services"
        }
    ],
    "sg:phone":"+1 804 344 0820",
    "sg:postcode":"23235",
    "sg:province":"VA",
    "sg:tags":[
        "car"
    ],
    "wof:name":"Guardsmark Llc",
    "wof:placetype":"venue"
},
  "geometry": {"coordinates":[-77.543211,37.49798],"type":"Point"}
}