{
  "type": "Feature",
  "properties": {
    "addr:full":"23310 Cox Rd Petersburg VA 23803",
    "addr:housenumber":"23310",
    "addr:postcode":"23803",
    "addr:street":"Cox Rd",
    "iso:country":"US",
    "sg:address":"23310 Cox Rd",
    "sg:city":"Petersburg",
    "sg:classifiers":[
        {
            "category":"Freight",
            "type":"Transportation"
        }
    ],
    "sg:phone":"+1 804 861 2425",
    "sg:postcode":"23803",
    "sg:province":"VA",
    "sg:tags":[
        "trucking"
    ],
    "wof:name":"Britt Trucking Co",
    "wof:placetype":"venue"
},
  "geometry": {"coordinates":[-77.50481600000001,37.196546],"type":"Point"}
}