{
  "type": "Feature",
  "properties": {
    "iso:country":"US",
    "sg:address":"82 Saint Roberts Dr",
    "sg:city":"Stafford",
    "sg:classifiers":[
        {
            "category":"Building & Trades",
            "subcategory":"Construction",
            "type":"Services"
        },
        {
            "category":"Manufacturing",
            "subcategory":"Building Materials",
            "type":"Manufacturing & Wholesale Goods"
        }
    ],
    "sg:phone":"+1 757 435 1281",
    "sg:postcode":"22556",
    "sg:province":"VA",
    "sg:tags":[
        "roofing",
        "sheet",
        "work",
        "metal",
        "contractor",
        "siding"
    ],
    "wof:name":"Noel Phinney",
    "wof:placetype":"venue"
},
  "geometry": {"coordinates":[-77.48443899999999,38.470786],"type":"Point"}
}