{
  "type": "Feature",
  "properties": {
    "addr:full":"5753 Mount Clinton Pike Harrisonburg VA 22802",
    "addr:housenumber":"5753",
    "addr:postcode":"22802",
    "addr:street":"Mount Clinton Pike",
    "iso:country":"US",
    "sg:address":"5753 Mount Clinton Pike",
    "sg:city":"Harrisonburg",
    "sg:classifiers":[
        {
            "category":"Shopping",
            "subcategory":"Hobbies, Toys, & Games",
            "type":"Retail Goods"
        }
    ],
    "sg:phone":"+1 540 867 5858",
    "sg:postcode":"22802",
    "sg:province":"VA",
    "sg:tags":[
        "equipment",
        "ceramic",
        "supply"
    ],
    "wof:name":"Ceramic Brush",
    "wof:placetype":"venue"
},
  "geometry": {"coordinates":[-78.930639,38.473546],"type":"Point"}
}