{
  "type": "Feature",
  "properties": {
    "addr:full":"1334 Lawson Cir Suffolk VA 23434",
    "addr:housenumber":"1334",
    "addr:postcode":"23434",
    "addr:street":"Lawson Cir",
    "iso:country":"US",
    "sg:address":"1334 Lawson Cir",
    "sg:city":"Suffolk",
    "sg:classifiers":[
        {
            "category":"Building & Trades",
            "subcategory":"Electrical",
            "type":"Services"
        }
    ],
    "sg:phone":"+1 757 539 7498",
    "sg:postcode":"23434",
    "sg:province":"VA",
    "sg:tags":[
        "electrical",
        "contractor"
    ],
    "wof:name":"Stallings Electric",
    "wof:placetype":"venue"
},
  "geometry": {"coordinates":[-76.61913699999999,36.702384],"type":"Point"}
}