{
  "type": "Feature",
  "properties": {
    "iso:country":"US",
    "sg:address":"7305 W Franklin St",
    "sg:city":"Richmond",
    "sg:classifiers":[
        {
            "category":"Organizations",
            "subcategory":"Membership Organization",
            "type":"Services"
        }
    ],
    "sg:phone":"+1 804 285 7122",
    "sg:postcode":"23226",
    "sg:province":"VA",
    "sg:tags":[
        "meditation",
        "instruction"
    ],
    "wof:name":"Transcendental Meditation",
    "wof:placetype":"venue"
},
  "geometry": {"coordinates":[-77.53243399999999,37.595766],"type":"Point"}
}