{
  "type": "Feature",
  "properties": {
    "addr:full":"1655 Crystal Square Arc Arlington VA 22202",
    "addr:housenumber":"1655",
    "addr:postcode":"22202",
    "addr:street":"Crystal Square Arc",
    "iso:country":"US",
    "sg:address":"1655 Crystal Square Arc",
    "sg:city":"Arlington",
    "sg:classifiers":[
        {
            "category":"Shopping",
            "subcategory":"Clothing, Apparel, & Fashions",
            "type":"Retail Goods"
        }
    ],
    "sg:phone":"+1 703 413 3400",
    "sg:postcode":"22202",
    "sg:province":"VA",
    "sg:tags":[
        "tailor",
        "clothing",
        "boys'"
    ],
    "wof:name":"Kelly's Mens Wear",
    "wof:placetype":"venue"
},
  "geometry": {"coordinates":[-77.049858,38.860294],"type":"Point"}
}