{
  "type": "Feature",
  "properties": {
    "iso:country":"US",
    "sg:address":"154 Madison Cir",
    "sg:city":"Madison Heights",
    "sg:classifiers":[
        {
            "category":"Manufacturing",
            "subcategory":"Printing",
            "type":"Manufacturing & Wholesale Goods"
        }
    ],
    "sg:phone":"+1 434 929 7876",
    "sg:postcode":"24572",
    "sg:province":"VA",
    "sg:tags":[
        "commercial"
    ],
    "wof:name":"Forruss Creations",
    "wof:placetype":"venue"
},
  "geometry": {"coordinates":[-79.132496,37.424428],"type":"Point"}
}