{
  "type": "Feature",
  "properties": {
    "iso:country":"US",
    "sg:address":"10721 Main St",
    "sg:city":"Fairfax",
    "sg:classifiers":[
        {
            "category":"Health Services",
            "subcategory":"Chiropractor",
            "type":"Services"
        }
    ],
    "sg:phone":"+1 703 383 9212",
    "sg:postcode":"22030",
    "sg:province":"VA",
    "wof:name":"Jewel Family Chiropractic PC",
    "wof:placetype":"venue"
},
  "geometry": {"coordinates":[-77.316315,38.849443],"type":"Point"}
}