{
  "type": "Feature",
  "properties": {
    "addr:full":"820 Chatsworth Dr Newport News VA 23601",
    "addr:housenumber":"820",
    "addr:postcode":"23601",
    "addr:street":"Chatsworth Dr",
    "iso:country":"US",
    "sg:address":"820 Chatsworth Dr",
    "sg:city":"Newport News",
    "sg:classifiers":[
        {
            "category":"Building & Trades",
            "subcategory":"Construction",
            "type":"Services"
        }
    ],
    "sg:phone":"+1 757 229 6738",
    "sg:postcode":"23601",
    "sg:province":"VA",
    "sg:tags":[
        "concrete",
        "contractor"
    ],
    "wof:name":"A & B Concrete",
    "wof:placetype":"venue"
},
  "geometry": {"coordinates":[-76.451137,37.083126],"type":"Point"}
}