{
  "type": "Feature",
  "properties": {
    "addr:full":"5545 Lee Hwy Arlington VA 22207",
    "addr:housenumber":"5545",
    "addr:postcode":"22207",
    "addr:street":"Lee Hwy",
    "iso:country":"US",
    "sg:address":"5545 Lee Hwy",
    "sg:city":"Arlington",
    "sg:classifiers":[
        {
            "category":"Building & Trades",
            "subcategory":"Construction",
            "type":"Services"
        }
    ],
    "sg:phone":"+1 703 536 7666",
    "sg:postcode":"22207",
    "sg:province":"VA",
    "sg:tags":[
        "interior",
        "design"
    ],
    "sg:website":"www.innospace.com",
    "wof:name":"Innospace Inc",
    "wof:placetype":"venue"
},
  "geometry": {"coordinates":[-77.14009900000001,38.895699],"type":"Point"}
}