{
  "type": "Feature",
  "properties": {
    "addr:full":"13551 Midlothian Tpke Midlothian VA 23113",
    "addr:housenumber":"13551",
    "addr:postcode":"23113",
    "addr:street":"Midlothian Tpke",
    "iso:country":"US",
    "sg:address":"13551 Midlothian Tpke",
    "sg:city":"Midlothian",
    "sg:classifiers":[
        {
            "category":"Personal",
            "subcategory":"Beauty Salon",
            "type":"Services"
        }
    ],
    "sg:phone":"+1 804 594 3726",
    "sg:postcode":"23113",
    "sg:province":"VA",
    "sg:tags":[
        "hair"
    ],
    "wof:name":"Glitz A Salon LLC",
    "wof:placetype":"venue"
},
  "geometry": {"coordinates":[-77.65017400000001,37.503073],"type":"Point"}
}