{
  "type": "Feature",
  "properties": {
    "addr:full":"206 N Lexington Ave Covington VA 24426",
    "addr:housenumber":"206",
    "addr:postcode":"24426",
    "addr:street":"N Lexington Ave",
    "iso:country":"US",
    "sg:address":"206 N Lexington Ave",
    "sg:city":"Covington",
    "sg:classifiers":[
        {
            "category":"Building & Trades",
            "subcategory":"Construction",
            "type":"Services"
        }
    ],
    "sg:phone":"+1 540 962 3963",
    "sg:postcode":"24426",
    "sg:province":"VA",
    "sg:tags":[
        "home",
        "improvement"
    ],
    "wof:name":"Huston Construction",
    "wof:placetype":"venue"
},
  "geometry": {"coordinates":[-79.99828100000001,37.790385],"type":"Point"}
}