{
  "type": "Feature",
  "properties": {
    "addr:full":"19 Oakland Dr Newport News VA 23601",
    "addr:housenumber":"19",
    "addr:postcode":"23601",
    "addr:street":"Oakland Dr",
    "iso:country":"US",
    "sg:address":"19 Oakland Dr",
    "sg:city":"Newport News",
    "sg:classifiers":[
        {
            "category":"Freight",
            "type":"Transportation"
        }
    ],
    "sg:phone":"+1 757 599 0154",
    "sg:postcode":"23601",
    "sg:province":"VA",
    "sg:tags":[
        "refrigeration"
    ],
    "wof:name":"Atlantic Cold Storage Concepts",
    "wof:placetype":"venue"
},
  "geometry": {"coordinates":[-76.47619400000001,37.037053],"type":"Point"}
}