{
  "type": "Feature",
  "properties": {
    "addr:full":"2318 E Laburnum Ave Richmond VA 23223",
    "addr:housenumber":"2318",
    "addr:postcode":"23223",
    "addr:street":"E Laburnum Ave",
    "iso:country":"US",
    "sg:address":"2318 E Laburnum Ave",
    "sg:city":"Richmond",
    "sg:classifiers":[
        {
            "category":"Fast Food",
            "type":"Food & Drink"
        },
        {
            "category":"Restaurant",
            "type":"Food & Drink"
        }
    ],
    "sg:phone":"+1 804 321 2221",
    "sg:postcode":"23223",
    "sg:province":"VA",
    "sg:tags":[
        "american",
        "take",
        "chicken"
    ],
    "sg:website":"http://www.popeyes.com",
    "wof:name":"Popeyes Chicken & Biscuits",
    "wof:placetype":"venue"
},
  "geometry": {"coordinates":[-77.395464,37.577376],"type":"Point"}
}