{
  "type": "Feature",
  "properties": {
    "addr:full":"7482 Lee Davis Rd Mechanicsville VA 23111",
    "addr:housenumber":"7482",
    "addr:postcode":"23111",
    "addr:street":"Lee Davis Rd",
    "iso:country":"US",
    "sg:address":"7482 Lee Davis Rd",
    "sg:city":"Mechanicsville",
    "sg:classifiers":[
        {
            "category":"Banks & Credit Unions",
            "subcategory":"Bank",
            "type":"Services"
        }
    ],
    "sg:phone":"+1 804 730 4100",
    "sg:postcode":"23111",
    "sg:province":"VA",
    "wof:name":"River City Bank",
    "wof:placetype":"venue"
},
  "geometry": {"coordinates":[-77.339309,37.613024],"type":"Point"}
}