{
  "type": "Feature",
  "properties": {
    "addr:full":"4807 1st St N Arlington VA 22203",
    "addr:housenumber":"4807",
    "addr:postcode":"22203",
    "addr:street":"1St St N",
    "iso:country":"US",
    "sg:address":"4807 1st St N",
    "sg:city":"Arlington",
    "sg:classifiers":[
        {
            "category":"Restaurant",
            "type":"Food & Drink"
        }
    ],
    "sg:phone":"+1 703 528 3194",
    "sg:postcode":"22203",
    "sg:province":"VA",
    "sg:tags":[
        "filipino"
    ],
    "wof:name":"Little Quiapo Restaurant",
    "wof:placetype":"venue"
},
  "geometry": {"coordinates":[-77.116501,38.867298],"type":"Point"}
}