{
  "type": "Feature",
  "properties": {
    "iso:country":"US",
    "sg:address":"470 Broadview Ave",
    "sg:city":"Warrenton",
    "sg:classifiers":[
        {
            "category":"Home & Garden",
            "subcategory":"Household Appliances",
            "type":"Retail Goods"
        }
    ],
    "sg:phone":"+1 540 347 3030",
    "sg:postcode":"20186",
    "sg:province":"VA",
    "sg:website":"www.tolsons.com",
    "wof:name":"Tolson Appliance Center Inc",
    "wof:placetype":"venue"
},
  "geometry": {"coordinates":[-77.80529799999999,38.728401],"type":"Point"}
}