{
  "type": "Feature",
  "properties": {
    "addr:full":"12308 Lynwood Dr Glen Allen VA 23059",
    "addr:housenumber":"12308",
    "addr:postcode":"23059",
    "addr:street":"Lynwood Dr",
    "iso:country":"US",
    "sg:address":"12308 Lynwood Dr",
    "sg:city":"Glen Allen",
    "sg:classifiers":[
        {
            "category":"Building & Trades",
            "subcategory":"Equipment Rental",
            "type":"Services"
        }
    ],
    "sg:phone":"+1 804 364 1652",
    "sg:postcode":"23059",
    "sg:province":"VA",
    "sg:tags":[
        "medical"
    ],
    "wof:name":"Edwards Lifesciences",
    "wof:placetype":"venue"
},
  "geometry": {"coordinates":[-77.62709099999999,37.700959],"type":"Point"}
}