{
  "type": "Feature",
  "properties": {
    "addr:full":"13190 Parcher Ave Herndon VA 20170",
    "addr:postcode":"13190;20170",
    "addr:street":"Parcher Ave",
    "iso:country":"US",
    "sg:address":"13190 Parcher Ave",
    "sg:city":"Herndon",
    "sg:classifiers":[
        {
            "category":"Food & Beverages",
            "subcategory":"Groceries & Convenience Stores",
            "type":"Retail Goods"
        }
    ],
    "sg:phone":"+1 703 689 3602",
    "sg:postcode":"20170",
    "sg:province":"VA",
    "wof:name":"7-Eleven",
    "wof:placetype":"venue"
},
  "geometry": {"coordinates":[-77.402113,38.959337],"type":"Point"}
}