{
  "type": "Feature",
  "properties": {
    "iso:country":"US",
    "sg:address":"1900 Beechwood Rd",
    "sg:city":"Chesapeake",
    "sg:classifiers":[
        {
            "category":"Organizations",
            "subcategory":"Religious Organization",
            "type":"Services"
        }
    ],
    "sg:phone":"+1 757 487 1493",
    "sg:postcode":"23323",
    "sg:province":"VA",
    "sg:tags":[
        "church"
    ],
    "wof:name":"St Mary's Holiness Church",
    "wof:placetype":"venue"
},
  "geometry": {"coordinates":[-76.312792,36.741594],"type":"Point"}
}