{
  "type": "Feature",
  "properties": {
    "addr:full":"6829 Atmore Dr Richmond VA 23225",
    "addr:housenumber":"6829",
    "addr:postcode":"23225",
    "addr:street":"Atmore Dr",
    "iso:country":"US",
    "sg:address":"6829 Atmore Dr",
    "sg:city":"Richmond",
    "sg:classifiers":[
        {
            "category":"Professional",
            "subcategory":"Detective & Security Services",
            "type":"Services"
        },
        {
            "category":"Manufacturing",
            "subcategory":"Electronics",
            "type":"Manufacturing & Wholesale Goods"
        },
        {
            "category":"Manufacturing",
            "subcategory":"Building Materials",
            "type":"Manufacturing & Wholesale Goods"
        }
    ],
    "sg:phone":"+1 804 767 7382",
    "sg:postcode":"23225",
    "sg:province":"VA",
    "sg:tags":[
        "control",
        "monitoring",
        "fire",
        "equipment-wholesale",
        "consultant",
        "alarm",
        "system",
        "systems-wholesale",
        "equipment",
        "guard",
        "patrol",
        "manufacturer"
    ],
    "sg:website":"http://richmond.citysearch.com/profile/external/10556664/richmond_va/richmond_alarm_company.html?publisher=yellowpages&reference_id=1&placement=ypwebsitemip",
    "wof:name":"Richmond Alarm Company",
    "wof:placetype":"venue"
},
  "geometry": {"coordinates":[-77.521439,37.504142],"type":"Point"}
}