{
  "type": "Feature",
  "properties": {
    "iso:country":"US",
    "sg:address":"8300 Sudley Rd",
    "sg:city":"Manassas",
    "sg:classifiers":[
        {
            "category":"Food & Beverages",
            "subcategory":"Specialty",
            "type":"Retail Goods"
        }
    ],
    "sg:phone":"+1 703 361 7277",
    "sg:postcode":"20109",
    "sg:province":"VA",
    "wof:name":"Hickory Farms",
    "wof:placetype":"venue"
},
  "geometry": {"coordinates":[-77.501817,38.774311],"type":"Point"}
}