{
  "type": "Feature",
  "properties": {
    "iso:country":"US",
    "sg:address":"6595 Main St",
    "sg:city":"Zanoni",
    "sg:classifiers":[
        {
            "category":"Government",
            "subcategory":"Fire Station",
            "type":"Public Place"
        }
    ],
    "sg:phone":"+1 804 693 2148",
    "sg:postcode":"23061",
    "sg:province":"VA",
    "sg:tags":[
        "department"
    ],
    "wof:name":"Gloucester Fire & Rescue Sta",
    "wof:placetype":"venue"
},
  "geometry": {"coordinates":[-76.532522,37.415703],"type":"Point"}
}