{
  "type": "Feature",
  "properties": {
    "iso:country":"US",
    "sg:address":"6205 Manor Park Ct",
    "sg:city":"Glen Allen",
    "sg:classifiers":[
        {
            "category":"Travel",
            "subcategory":"Travel Agent",
            "type":"Entertainment"
        }
    ],
    "sg:phone":"+1 804 360 1622",
    "sg:postcode":"23059",
    "sg:province":"VA",
    "sg:tags":[
        "agency"
    ],
    "wof:name":"Contemporary Travel Inc",
    "wof:placetype":"venue"
},
  "geometry": {"coordinates":[-77.61003700000001,37.706863],"type":"Point"}
}