{
  "type": "Feature",
  "properties": {
    "addr:full":"1553 Rio Road East Charlottesville VA 22901",
    "addr:housenumber":"1553",
    "addr:postcode":"22901",
    "addr:street":"Rio Road East",
    "iso:country":"US",
    "sg:address":"1553 Rio Road East",
    "sg:city":"Charlottesville",
    "sg:classifiers":[
        {
            "category":"Shopping",
            "subcategory":"Mobile Phones",
            "type":"Retail Goods"
        }
    ],
    "sg:phone":"+1 434 973 6664",
    "sg:postcode":"22901",
    "sg:province":"VA",
    "sg:website":"www.radioshack.com",
    "wof:name":"Radioshack",
    "wof:placetype":"venue"
},
  "geometry": {"coordinates":[-78.47102099999999,38.078054],"type":"Point"}
}