{
  "type": "Feature",
  "properties": {
    "addr:full":"307 Potomac Ave Quantico VA 22134",
    "addr:housenumber":"307",
    "addr:postcode":"22134",
    "addr:street":"Potomac Ave",
    "iso:country":"US",
    "sg:address":"307 Potomac Ave",
    "sg:city":"Quantico",
    "sg:classifiers":[
        {
            "category":"Personal",
            "subcategory":"Barber",
            "type":"Services"
        }
    ],
    "sg:phone":"+1 703 640 0539",
    "sg:postcode":"22134",
    "sg:province":"VA",
    "wof:name":"Yung's Hair Cut",
    "wof:placetype":"venue"
},
  "geometry": {"coordinates":[-77.29231900000001,38.522367],"type":"Point"}
}