{
  "type": "Feature",
  "properties": {
    "iso:country":"US",
    "sg:address":"10304 Eaton Pl",
    "sg:city":"Fairfax",
    "sg:classifiers":[
        {
            "category":"Government",
            "subcategory":"Office",
            "type":"Public Place"
        }
    ],
    "sg:phone":"+1 703 306 6444",
    "sg:postcode":"22030",
    "sg:province":"VA",
    "sg:tags":[
        "agency"
    ],
    "wof:name":"Federal Tech Service",
    "wof:placetype":"venue"
},
  "geometry": {"coordinates":[-77.30126199999999,38.860774],"type":"Point"}
}