{
  "type": "Feature",
  "properties": {
    "iso:country":"US",
    "sg:address":"8721 Parliament Dr",
    "sg:city":"Springfield",
    "sg:classifiers":[
        {
            "category":"Restaurant",
            "type":"Food & Drink"
        }
    ],
    "sg:phone":"+1 703 764 2011",
    "sg:postcode":"22151",
    "sg:province":"VA",
    "sg:tags":[
        "caterer"
    ],
    "wof:name":"Movable Feast",
    "wof:placetype":"venue"
},
  "geometry": {"coordinates":[-77.245835,38.806166],"type":"Point"}
}