{
  "type": "Feature",
  "properties": {
    "addr:full":"244 Wythe Creek Rd Poquoson VA 23662",
    "addr:housenumber":"244",
    "addr:postcode":"23662",
    "addr:street":"Wythe Creek Rd",
    "iso:country":"US",
    "sg:address":"244 Wythe Creek Rd",
    "sg:city":"Poquoson",
    "sg:classifiers":[
        {
            "category":"Retail",
            "subcategory":"Auto Repair",
            "type":"Services"
        }
    ],
    "sg:phone":"+1 757 868 4714",
    "sg:postcode":"23662",
    "sg:province":"VA",
    "sg:tags":[
        "glass",
        "replacement"
    ],
    "wof:name":"Corbett Auto Glass Inc",
    "wof:placetype":"venue"
},
  "geometry": {"coordinates":[-76.39311600000001,37.111334],"type":"Point"}
}