{
  "type": "Feature",
  "properties": {
    "addr:full":"5121 Concordia St Fairfax VA 22032",
    "addr:housenumber":"5121",
    "addr:postcode":"22032",
    "addr:street":"Concordia St",
    "iso:country":"US",
    "sg:address":"5121 Concordia St",
    "sg:city":"Fairfax",
    "sg:classifiers":[
        {
            "category":"Arena",
            "subcategory":"Sports Club",
            "type":"Entertainment"
        }
    ],
    "sg:phone":"+1 703 978 4348",
    "sg:postcode":"22032",
    "sg:province":"VA",
    "sg:tags":[
        "camp"
    ],
    "wof:name":"R G H Inc",
    "wof:placetype":"venue"
},
  "geometry": {"coordinates":[-77.310035,38.815904],"type":"Point"}
}