{
  "type": "Feature",
  "properties": {
    "addr:full":"400 N Meadow St Richmond VA 23220",
    "addr:housenumber":"400",
    "addr:postcode":"23220",
    "addr:street":"N Meadow St",
    "iso:country":"US",
    "sg:address":"400 N Meadow St",
    "sg:city":"Richmond",
    "sg:classifiers":[
        {
            "category":"Wholesale",
            "subcategory":"Groceries",
            "type":"Manufacturing & Wholesale Goods"
        }
    ],
    "sg:phone":"+1 804 353 6719",
    "sg:postcode":"23220",
    "sg:province":"VA",
    "wof:name":"Aunt Emilys Foods of South",
    "wof:placetype":"venue"
},
  "geometry": {"coordinates":[-77.463088,37.554189],"type":"Point"}
}