{
  "type": "Feature",
  "properties": {
    "addr:full":"229 N Henry St Alexandria VA 22314",
    "addr:housenumber":"229",
    "addr:postcode":"22314",
    "addr:street":"N Henry St",
    "iso:country":"US",
    "sg:address":"229 N Henry St",
    "sg:city":"Alexandria",
    "sg:classifiers":[
        {
            "category":"Shopping",
            "subcategory":"Computers & Home Electronics",
            "type":"Retail Goods"
        }
    ],
    "sg:phone":"+1 703 549 4949",
    "sg:postcode":"22314",
    "sg:province":"VA",
    "sg:tags":[
        "audio"
    ],
    "wof:name":"Communicaids Inc",
    "wof:placetype":"venue"
},
  "geometry": {"coordinates":[-77.050864,38.80756],"type":"Point"}
}