{
  "type": "Feature",
  "properties": {
    "iso:country":"US",
    "sg:address":"900 N Stafford St Apt 1403",
    "sg:city":"Arlington",
    "sg:classifiers":[
        {
            "category":"Health Services",
            "subcategory":"Doctor",
            "type":"Services"
        }
    ],
    "sg:phone":"+1 703 525 4037",
    "sg:postcode":"22203",
    "sg:province":"VA",
    "sg:tags":[
        "surgeon",
        "oral"
    ],
    "wof:name":"Halla Paul E DDS",
    "wof:placetype":"venue"
},
  "geometry": {"coordinates":[-77.110497,38.881599],"type":"Point"}
}