{
  "type": "Feature",
  "properties": {
    "addr:full":"7108 Midlothian Tpke Richmond VA 23225",
    "addr:housenumber":"7108",
    "addr:postcode":"23225",
    "addr:street":"Midlothian Tpke",
    "iso:country":"US",
    "sg:address":"7108 Midlothian Tpke",
    "sg:city":"Richmond",
    "sg:classifiers":[
        {
            "category":"Shopping",
            "subcategory":"Clothing, Apparel, & Fashions",
            "type":"Retail Goods"
        },
        {
            "category":"Shopping",
            "subcategory":"Shoes",
            "type":"Retail Goods"
        }
    ],
    "sg:phone":"+1 804 565 5574",
    "sg:postcode":"23225",
    "sg:province":"VA",
    "sg:tags":[
        "sportswear",
        "store"
    ],
    "wof:name":"A & N Stores",
    "wof:placetype":"venue"
},
  "geometry": {"coordinates":[-77.52875,37.500911],"type":"Point"}
}