{
  "type": "Feature",
  "properties": {
    "addr:full":"523 Rutherford Ave NE Roanoke VA 24016",
    "addr:housenumber":"523",
    "addr:postcode":"24016",
    "addr:street":"Rutherford Ave Ne",
    "iso:country":"US",
    "sg:address":"523 Rutherford Ave NE",
    "sg:city":"Roanoke",
    "sg:classifiers":[
        {
            "category":"Home & Garden",
            "subcategory":"Building Materials",
            "type":"Retail Goods"
        }
    ],
    "sg:phone":"+1 540 982 2366",
    "sg:postcode":"24016",
    "sg:province":"VA",
    "sg:tags":[
        "mixed",
        "concrete"
    ],
    "wof:name":"Asphalt Ready Mix Inc",
    "wof:placetype":"venue"
},
  "geometry": {"coordinates":[-79.931231,37.27842],"type":"Point"}
}