{
  "type": "Feature",
  "properties": {
    "addr:full":"3482 Lumber Mill Rd Dayton VA 22821",
    "addr:postcode":"3482;22821",
    "addr:street":"Lumber Mill Rd",
    "iso:country":"US",
    "sg:address":"3482 Lumber Mill Rd",
    "sg:city":"Dayton",
    "sg:classifiers":[
        {
            "category":"Farming",
            "subcategory":"Poultry Farm",
            "type":"Manufacturing & Wholesale Goods"
        }
    ],
    "sg:phone":"+1 540 879 2185",
    "sg:postcode":"22821",
    "sg:province":"VA",
    "sg:tags":[
        "hatchery"
    ],
    "wof:name":"Willis Good",
    "wof:placetype":"venue"
},
  "geometry": {"coordinates":[-79.009934,38.436337],"type":"Point"}
}