{
  "type": "Feature",
  "properties": {
    "addr:full":"850 W 40th St Norfolk VA 23508",
    "addr:housenumber":"850",
    "addr:postcode":"23508",
    "addr:street":"W 40Th St",
    "iso:country":"US",
    "sg:address":"850 W 40th St",
    "sg:city":"Norfolk",
    "sg:classifiers":[
        {
            "category":"Autos & Motor Vehicles",
            "subcategory":"Boat Sales",
            "type":"Retail Goods"
        }
    ],
    "sg:phone":"+1 757 423 1111",
    "sg:postcode":"23508",
    "sg:province":"VA",
    "sg:tags":[
        "equipment",
        "marine",
        "supply"
    ],
    "wof:name":"Marine Transport New Jersey",
    "wof:placetype":"venue"
},
  "geometry": {"coordinates":[-76.29653399999999,36.881528],"type":"Point"}
}