{
  "type": "Feature",
  "properties": {
    "addr:full":"3209 Cedar Ln Portsmouth VA 23703",
    "addr:housenumber":"3209",
    "addr:postcode":"23703",
    "addr:street":"Cedar Ln",
    "iso:country":"US",
    "sg:address":"3209 Cedar Ln",
    "sg:city":"Portsmouth",
    "sg:classifiers":[
        {
            "category":"Banks & Credit Unions",
            "subcategory":"Bank",
            "type":"Services"
        }
    ],
    "sg:phone":"+1 757 686 3051",
    "sg:postcode":"23703",
    "sg:province":"VA",
    "wof:name":"Portsmouth Fire Dept CU",
    "wof:placetype":"venue"
},
  "geometry": {"coordinates":[-76.378992,36.852225],"type":"Point"}
}