{
  "type": "Feature",
  "properties": {
    "addr:full":"1560 N Wilson Blvd Arlington VA 22209",
    "addr:housenumber":"1560",
    "addr:postcode":"22209",
    "addr:street":"N Wilson Blvd",
    "iso:country":"US",
    "sg:address":"1560 N Wilson Blvd",
    "sg:city":"Arlington",
    "sg:classifiers":[
        {
            "category":"Professional",
            "type":"Services"
        }
    ],
    "sg:phone":"+1 703 525 3000",
    "sg:postcode":"22209",
    "sg:province":"VA",
    "sg:tags":[
        "establishment"
    ],
    "wof:name":"Accrediting Council-Continuing",
    "wof:placetype":"venue"
},
  "geometry": {"coordinates":[-77.07522,38.894569],"type":"Point"}
}