{
  "type": "Feature",
  "properties": {
    "addr:full":"9039 W Broad St Richmond VA 23294",
    "addr:housenumber":"9039",
    "addr:postcode":"23294",
    "addr:street":"W Broad St",
    "iso:country":"US",
    "sg:address":"9039 W Broad St",
    "sg:city":"Richmond",
    "sg:classifiers":[
        {
            "category":"Personal",
            "subcategory":"Beauty Salon",
            "type":"Services"
        }
    ],
    "sg:phone":"+1 804 967 0340",
    "sg:postcode":"23294",
    "sg:province":"VA",
    "sg:tags":[
        "manicuring"
    ],
    "wof:name":"Hollywood Nails",
    "wof:placetype":"venue"
},
  "geometry": {"coordinates":[-77.54993,37.636371],"type":"Point"}
}