{
  "type": "Feature",
  "properties": {
    "addr:full":"1108 E Main St Richmond VA 23219",
    "addr:housenumber":"1108",
    "addr:postcode":"23219",
    "addr:street":"E Main St",
    "iso:country":"US",
    "sg:address":"1108 E Main St",
    "sg:city":"Richmond",
    "sg:classifiers":[
        {
            "category":"Wholesale",
            "subcategory":"Non-durable Goods",
            "type":"Manufacturing & Wholesale Goods"
        }
    ],
    "sg:phone":"+1 804 225 8690",
    "sg:postcode":"23219",
    "sg:province":"VA",
    "wof:name":"Office Talk",
    "wof:placetype":"venue"
},
  "geometry": {"coordinates":[-77.434603,37.537308],"type":"Point"}
}