{
  "type": "Feature",
  "properties": {
    "addr:full":"3640 S Main St Harrisonburg VA 22801",
    "addr:housenumber":"3640",
    "addr:postcode":"22801",
    "addr:street":"S Main St",
    "iso:country":"US",
    "sg:address":"3640 S Main St",
    "sg:city":"Harrisonburg",
    "sg:classifiers":[
        {
            "category":"Retail",
            "subcategory":"Auto Repair",
            "type":"Services"
        }
    ],
    "sg:phone":"+1 540 434 7004",
    "sg:postcode":"22801",
    "sg:province":"VA",
    "sg:tags":[
        "trailer"
    ],
    "wof:name":"Thermo King",
    "wof:placetype":"venue"
},
  "geometry": {"coordinates":[-78.912677,38.399901],"type":"Point"}
}