{
  "type": "Feature",
  "properties": {
    "addr:full":"8654 Staples Mill Rd Richmond VA 23228",
    "addr:housenumber":"8654",
    "addr:postcode":"23228",
    "addr:street":"Staples Mill Rd",
    "iso:country":"US",
    "sg:address":"8654 Staples Mill Rd",
    "sg:city":"Richmond",
    "sg:classifiers":[
        {
            "category":"Restaurant",
            "type":"Food & Drink"
        }
    ],
    "sg:menulink":"http://www.allmenus.com/va/brookland/228944-jersey-mikes/menu/",
    "sg:phone":"+1 804 627 0507",
    "sg:postcode":"23228",
    "sg:province":"VA",
    "sg:tags":[
        "american",
        "sandwich"
    ],
    "wof:name":"Jersey Mike's",
    "wof:placetype":"venue"
},
  "geometry": {"coordinates":[-77.507858,37.631644],"type":"Point"}
}