{
  "type": "Feature",
  "properties": {
    "addr:full":"2351 Oak Level Rd Bassett VA 24055",
    "addr:housenumber":"2351",
    "addr:postcode":"24055",
    "addr:street":"Oak Level Rd",
    "iso:country":"US",
    "sg:address":"2351 Oak Level Rd",
    "sg:city":"Bassett",
    "sg:classifiers":[
        {
            "category":"Personal",
            "subcategory":"Beauty Salon",
            "type":"Services"
        }
    ],
    "sg:phone":"+1 276 629 2499",
    "sg:postcode":"24055",
    "sg:province":"VA",
    "wof:name":"E Dale Hair & Tanning Salon",
    "wof:placetype":"venue"
},
  "geometry": {"coordinates":[-79.956018,36.752893],"type":"Point"}
}