{
  "type": "Feature",
  "properties": {
    "iso:country":"US",
    "sg:address":"630 Notabene Dr",
    "sg:city":"Alexandria",
    "sg:classifiers":[
        {
            "category":"Building & Trades",
            "subcategory":"Construction",
            "type":"Services"
        }
    ],
    "sg:phone":"+1 703 622 6948",
    "sg:postcode":"22305",
    "sg:province":"VA",
    "sg:tags":[
        "repair",
        "handyman",
        "maintenance",
        "home"
    ],
    "wof:name":"Golden Hands Handyman Service",
    "wof:placetype":"venue"
},
  "geometry": {"coordinates":[-77.06743899999999,38.841184],"type":"Point"}
}