{
  "type": "Feature",
  "properties": {
    "addr:full":"14735 Dumfries Rd Manassas VA 20112",
    "addr:housenumber":"14735",
    "addr:postcode":"20112",
    "addr:street":"Dumfries Rd",
    "iso:country":"US",
    "sg:address":"14735 Dumfries Rd",
    "sg:city":"Manassas",
    "sg:classifiers":[
        {
            "category":"Restaurant",
            "type":"Food & Drink"
        }
    ],
    "sg:phone":"+1 703 791 2300",
    "sg:postcode":"20112",
    "sg:province":"VA",
    "sg:tags":[
        "eating"
    ],
    "wof:name":"Shrimp Connection",
    "wof:placetype":"venue"
},
  "geometry": {"coordinates":[-77.426165,38.633216],"type":"Point"}
}