{
  "type": "Feature",
  "properties": {
    "addr:full":"203 9th St Lynchburg VA 24504",
    "addr:housenumber":"203",
    "addr:postcode":"24504",
    "addr:street":"9Th St",
    "iso:country":"US",
    "sg:address":"203 9th St",
    "sg:city":"Lynchburg",
    "sg:classifiers":[
        {
            "category":"Banks & Credit Unions",
            "subcategory":"Investment Brokerage",
            "type":"Services"
        }
    ],
    "sg:phone":"+1 434 385 1881",
    "sg:postcode":"24504",
    "sg:province":"VA",
    "sg:tags":[
        "advisory",
        "financial"
    ],
    "wof:name":"Gerhardt Advisors Inc",
    "wof:placetype":"venue"
},
  "geometry": {"coordinates":[-79.14322199999999,37.414423],"type":"Point"}
}