{
  "type": "Feature",
  "properties": {
    "addr:full":"2101 Wilson Blvd Ste 402 Arlington VA 22201",
    "addr:housenumber":"2101",
    "addr:postcode":"22201",
    "addr:street":"Wilson Blvd Ste 402",
    "iso:country":"US",
    "sg:address":"2101 Wilson Blvd Ste 402",
    "sg:city":"Arlington",
    "sg:classifiers":[
        {
            "category":"Communications",
            "subcategory":"Film & Video Production",
            "type":"Services"
        }
    ],
    "sg:phone":"+1 703 351 9130",
    "sg:postcode":"22201",
    "sg:province":"VA",
    "sg:tags":[
        "video/film"
    ],
    "sg:website":"www.greenerandhook.com/",
    "wof:name":"Greener and Hook",
    "wof:placetype":"venue"
},
  "geometry": {"coordinates":[-77.084203,38.892685],"type":"Point"}
}