{
  "type": "Feature",
  "properties": {
    "addr:full":"305 Bataan Rd Fort Lee VA 23801",
    "addr:housenumber":"305",
    "addr:postcode":"23801",
    "addr:street":"Bataan Rd",
    "iso:country":"US",
    "sg:address":"305 Bataan Rd",
    "sg:city":"Fort Lee",
    "sg:classifiers":[
        {
            "category":"Organizations",
            "subcategory":"Religious Organization",
            "type":"Services"
        }
    ],
    "sg:phone":"+1 804 732 0219",
    "sg:postcode":"23801",
    "sg:province":"VA",
    "wof:name":"First Things Church",
    "wof:placetype":"venue"
},
  "geometry": {"coordinates":[-77.321848,37.227135],"type":"Point"}
}