{
  "type": "Feature",
  "properties": {
    "iso:country":"US",
    "sg:address":"8702 Greeley Ct",
    "sg:city":"Springfield",
    "sg:classifiers":[
        {
            "category":"Health Services",
            "subcategory":"Doctor",
            "type":"Services"
        }
    ],
    "sg:phone":"+1 703 451 2084",
    "sg:postcode":"22152",
    "sg:province":"VA",
    "sg:tags":[
        "physician",
        "surgeon"
    ],
    "wof:name":"Lee A Blakely Jr Md Ltd",
    "wof:placetype":"venue"
},
  "geometry": {"coordinates":[-77.24126699999999,38.7761],"type":"Point"}
}