{
  "type": "Feature",
  "properties": {
    "iso:country":"US",
    "sg:address":"669 Cedar Rd",
    "sg:city":"Chesapeake",
    "sg:classifiers":[
        {
            "category":"Home & Garden",
            "subcategory":"Carpets & Floor Coverings",
            "type":"Retail Goods"
        }
    ],
    "sg:phone":"+1 757 436 1393",
    "sg:postcode":"23322",
    "sg:province":"VA",
    "wof:name":"Carpet City Inc",
    "wof:placetype":"venue"
},
  "geometry": {"coordinates":[-76.26167,36.710584],"type":"Point"}
}