{
  "type": "Feature",
  "properties": {
    "addr:full":"2425 Shenandoah St Vienna VA 22180",
    "addr:housenumber":"2425",
    "addr:postcode":"22180",
    "addr:street":"Shenandoah St",
    "iso:country":"US",
    "sg:address":"2425 Shenandoah St",
    "sg:city":"Vienna",
    "sg:classifiers":[
        {
            "category":"Professional",
            "subcategory":"Management & Consulting",
            "type":"Services"
        }
    ],
    "sg:phone":"+1 703 207 0581",
    "sg:postcode":"22180",
    "sg:province":"VA",
    "sg:tags":[
        "consultant",
        "economic"
    ],
    "wof:name":"Enviro-Latina Associates",
    "wof:placetype":"venue"
},
  "geometry": {"coordinates":[-77.237441,38.891889],"type":"Point"}
}