{
  "type": "Feature",
  "properties": {
    "addr:full":"14733 Jarnigan St Centreville VA 20120",
    "addr:postcode":"14733;20120",
    "addr:street":"Jarnigan St",
    "iso:country":"US",
    "sg:address":"14733 Jarnigan St",
    "sg:city":"Centreville",
    "sg:classifiers":[
        {
            "category":"Social Services",
            "subcategory":"Job Training",
            "type":"Services"
        }
    ],
    "sg:phone":"+1 703 815 1497",
    "sg:postcode":"20120",
    "sg:province":"VA",
    "wof:name":"Inpursuit",
    "wof:placetype":"venue"
},
  "geometry": {"coordinates":[-77.458451,38.856227],"type":"Point"}
}