{
  "type": "Feature",
  "properties": {
    "iso:country":"US",
    "sg:address":"107 5th St SE",
    "sg:city":"Charlottesville",
    "sg:classifiers":[
        {
            "category":"Sports & Exercise",
            "subcategory":"Gym",
            "type":"Entertainment"
        }
    ],
    "sg:phone":"+1 434 220 1415",
    "sg:postcode":"22902",
    "sg:province":"VA",
    "sg:tags":[
        "yoga"
    ],
    "wof:name":"Bikram Yoga Charlottesville",
    "wof:placetype":"venue"
},
  "geometry": {"coordinates":[-78.4785,38.0298],"type":"Point"}
}