{
  "type": "Feature",
  "properties": {
    "addr:full":"1427 N Augusta St Staunton VA 24401",
    "addr:housenumber":"1427",
    "addr:postcode":"24401",
    "addr:street":"N Augusta St",
    "iso:country":"US",
    "sg:address":"1427 N Augusta St",
    "sg:city":"Staunton",
    "sg:classifiers":[
        {
            "category":"Real Estate",
            "subcategory":"Real Estate Agent",
            "type":"Services"
        }
    ],
    "sg:phone":"+1 540 886 0301",
    "sg:postcode":"24401",
    "sg:province":"VA",
    "wof:name":"Crowne Realty",
    "wof:placetype":"venue"
},
  "geometry": {"coordinates":[-79.066766,38.162755],"type":"Point"}
}