{
  "type": "Feature",
  "properties": {
    "addr:full":"4512 Village Park Dr E Williamsburg VA 23185",
    "addr:housenumber":"4512",
    "addr:postcode":"23185",
    "addr:street":"Village Park Dr E",
    "iso:country":"US",
    "sg:address":"4512 Village Park Dr E",
    "sg:city":"Williamsburg",
    "sg:classifiers":[
        {
            "category":"Professional",
            "type":"Services"
        }
    ],
    "sg:phone":"+1 757 221 8366",
    "sg:postcode":"23185",
    "sg:province":"VA",
    "wof:name":"Grant BJ Ltd",
    "wof:placetype":"venue"
},
  "geometry": {"coordinates":[-76.76244699999999,37.24903],"type":"Point"}
}