{
  "type": "Feature",
  "properties": {
    "addr:full":"10229 Cedar Pond Dr Vienna VA 22182",
    "addr:housenumber":"10229",
    "addr:postcode":"22182",
    "addr:street":"Cedar Pond Dr",
    "iso:country":"US",
    "sg:address":"10229 Cedar Pond Dr",
    "sg:city":"Vienna",
    "sg:classifiers":[
        {
            "category":"Professional",
            "subcategory":"Management & Consulting",
            "type":"Services"
        }
    ],
    "sg:phone":"+1 703 472 5911",
    "sg:postcode":"22182",
    "sg:province":"VA",
    "sg:tags":[
        "business"
    ],
    "wof:name":"Foundation3 Ventures LLC",
    "wof:placetype":"venue"
},
  "geometry": {"coordinates":[-77.303994,38.927199],"type":"Point"}
}