{
  "type": "Feature",
  "properties": {
    "addr:full":"325 Redbrick Dr Chesapeake VA 23325",
    "addr:housenumber":"325",
    "addr:postcode":"23325",
    "addr:street":"Redbrick Dr",
    "iso:country":"US",
    "sg:address":"325 Redbrick Dr",
    "sg:city":"Chesapeake",
    "sg:classifiers":[
        {
            "category":"Travel",
            "subcategory":"Travel Agent",
            "type":"Entertainment"
        }
    ],
    "sg:phone":"+1 757 523 0784",
    "sg:postcode":"23325",
    "sg:province":"VA",
    "sg:tags":[
        "agency"
    ],
    "wof:name":"Personal Touch Travel Inc",
    "wof:placetype":"venue"
},
  "geometry": {"coordinates":[-76.24731,36.799217],"type":"Point"}
}