{
  "type": "Feature",
  "properties": {
    "addr:full":"2190 Pimmit Dr. Falls Church VA 22043",
    "addr:housenumber":"2190",
    "addr:postcode":"22043",
    "addr:street":"Pimmit Dr.",
    "iso:country":"US",
    "sg:address":"2190 Pimmit Dr.",
    "sg:city":"Falls Church",
    "sg:classifiers":[
        {
            "category":"Restaurant",
            "type":"Food & Drink"
        },
        {
            "category":"Bars & Pubs",
            "subcategory":"Wine Bar",
            "type":"Food & Drink"
        }
    ],
    "sg:phone":"+1 703 992 0915",
    "sg:postcode":"22043",
    "sg:province":"VA",
    "sg:website":"www.idylwoodgrill.com/",
    "wof:name":"Idylwood Grill & Wine Bar",
    "wof:placetype":"venue"
},
  "geometry": {"coordinates":[-77.203728,38.902222],"type":"Point"}
}