{
  "type": "Feature",
  "properties": {
    "iso:country":"US",
    "sg:address":"4301 Longdale Furnace Rd",
    "sg:city":"Clifton Forge",
    "sg:classifiers":[
        {
            "category":"Professional",
            "subcategory":"Research",
            "type":"Services"
        }
    ],
    "sg:phone":"+1 540 862 9171",
    "sg:postcode":"24422",
    "sg:province":"VA",
    "sg:tags":[
        "environmental",
        "ecological"
    ],
    "wof:name":"Environmental Pipe Bursting Co",
    "wof:placetype":"venue"
},
  "geometry": {"coordinates":[-79.735494,37.80012],"type":"Point"}
}