{
  "type": "Feature",
  "properties": {
    "iso:country":"US",
    "sg:address":"9426 Dogwood Garth Ln",
    "sg:city":"Mechanicsville",
    "sg:classifiers":[
        {
            "category":"Professional",
            "subcategory":"Computer Services",
            "type":"Services"
        }
    ],
    "sg:phone":"+1 804 550 1551",
    "sg:postcode":"23116",
    "sg:province":"VA",
    "sg:tags":[
        "consulting",
        "related"
    ],
    "wof:name":"Tech Knowledge Inc",
    "wof:placetype":"venue"
},
  "geometry": {"coordinates":[-77.433499,37.689701],"type":"Point"}
}