{
  "type": "Feature",
  "properties": {
    "iso:country":"US",
    "sg:address":"190 Cross Harbor Dr",
    "sg:city":"Penhook",
    "sg:classifiers":[
        {
            "category":"Wholesale",
            "subcategory":"Machinery & Supplies",
            "type":"Manufacturing & Wholesale Goods"
        }
    ],
    "sg:phone":"+1 540 576 9969",
    "sg:postcode":"24137",
    "sg:province":"VA",
    "wof:name":"Prestige Irrigation",
    "wof:placetype":"venue"
},
  "geometry": {"coordinates":[-79.61630100000001,37.017469],"type":"Point"}
}