{
  "type": "Feature",
  "properties": {
    "iso:country":"US",
    "sg:address":"315 N Maple Ave",
    "sg:city":"Falls Church",
    "sg:classifiers":[
        {
            "category":"Professional",
            "subcategory":"Management & Consulting",
            "type":"Services"
        }
    ],
    "sg:phone":"+1 703 538 3512",
    "sg:postcode":"22046",
    "sg:province":"VA",
    "sg:tags":[
        "consultant",
        "training"
    ],
    "wof:name":"Michael Snyder",
    "wof:placetype":"venue"
},
  "geometry": {"coordinates":[-77.16851,38.885682],"type":"Point"}
}