{
  "type": "Feature",
  "properties": {
    "addr:full":"410 Glenfield Ct Harrisonburg VA 22802",
    "addr:housenumber":"410",
    "addr:postcode":"22802",
    "addr:street":"Glenfield Ct",
    "iso:country":"US",
    "sg:address":"410 Glenfield Ct",
    "sg:city":"Harrisonburg",
    "sg:classifiers":[
        {
            "category":"Professional",
            "subcategory":"Business Services",
            "type":"Services"
        }
    ],
    "sg:phone":"+1 540 820 9142",
    "sg:postcode":"22802",
    "sg:province":"VA",
    "sg:tags":[
        "drafting"
    ],
    "wof:name":"Designer Home Plans",
    "wof:placetype":"venue"
},
  "geometry": {"coordinates":[-78.853838,38.4567],"type":"Point"}
}