{
  "type": "Feature",
  "properties": {
    "iso:country":"US",
    "sg:address":"101 Enterprise St",
    "sg:city":"Sterling",
    "sg:phone":"+1 703 444 8602",
    "sg:postcode":"20164",
    "sg:province":"VA",
    "sg:website":"http://www.firstvirginia.com",
    "wof:name":"Cardinal Bank",
    "wof:placetype":"venue"
},
  "geometry": {"coordinates":[-77.40315200000001,38.999477],"type":"Point"}
}