{
  "type": "Feature",
  "properties": {
    "addr:full":"110 Kirk Ave SW Roanoke VA 24011",
    "addr:housenumber":"110",
    "addr:postcode":"24011",
    "addr:street":"Kirk Ave Sw",
    "iso:country":"US",
    "sg:address":"110 Kirk Ave SW",
    "sg:city":"Roanoke",
    "sg:classifiers":[
        {
            "category":"Real Estate",
            "subcategory":"Architect",
            "type":"Services"
        }
    ],
    "sg:phone":"+1 540 527 1233",
    "sg:postcode":"24011",
    "sg:province":"VA",
    "sg:tags":[
        "architectural"
    ],
    "wof:name":"Mark McConnel & Associates",
    "wof:placetype":"venue"
},
  "geometry": {"coordinates":[-79.94409400000001,37.271167],"type":"Point"}
}