{
  "type": "Feature",
  "properties": {
    "addr:full":"320 Jefferson Davis Hwy Fredericksburg VA 22401",
    "addr:housenumber":"320",
    "addr:postcode":"22401",
    "addr:street":"Jefferson Davis Hwy",
    "iso:country":"US",
    "sg:address":"320 Jefferson Davis Hwy",
    "sg:city":"Fredericksburg",
    "sg:classifiers":[
        {
            "category":"Shopping",
            "subcategory":"Pharmacy",
            "type":"Retail Goods"
        }
    ],
    "sg:phone":"+1 540 373 2424",
    "sg:postcode":"22401",
    "sg:province":"VA",
    "wof:name":"Metro Drug Store",
    "wof:placetype":"venue"
},
  "geometry": {"coordinates":[-77.47245700000001,38.317901],"type":"Point"}
}