{
  "type": "Feature",
  "properties": {
    "addr:full":"118 Madison Cir Madison Heights VA 24572",
    "addr:housenumber":"118",
    "addr:postcode":"24572",
    "addr:street":"Madison Cir",
    "iso:country":"US",
    "sg:address":"118 Madison Cir",
    "sg:city":"Madison Heights",
    "sg:classifiers":[
        {
            "category":"Wholesale",
            "subcategory":"Groceries",
            "type":"Manufacturing & Wholesale Goods"
        }
    ],
    "sg:phone":"+1 434 929 6515",
    "sg:postcode":"24572",
    "sg:province":"VA",
    "sg:tags":[
        "grocer"
    ],
    "wof:name":"Quality Foods Co-Operative Inc",
    "wof:placetype":"venue"
},
  "geometry": {"coordinates":[-79.134141,37.42304],"type":"Point"}
}