{
  "type": "Feature",
  "properties": {
    "iso:country":"US",
    "sg:address":"9119 Church St",
    "sg:city":"Manassas",
    "sg:classifiers":[
        {
            "category":"Professional",
            "subcategory":"Lawyer & Legal Services",
            "type":"Services"
        }
    ],
    "sg:phone":"+1 703 365 9900",
    "sg:postcode":"20110",
    "sg:province":"VA",
    "sg:tags":[
        "attorney"
    ],
    "wof:name":"Chris Kachouroff Atty At Law",
    "wof:placetype":"venue"
},
  "geometry": {"coordinates":[-77.473427,38.751569],"type":"Point"}
}