{
  "type": "Feature",
  "properties": {
    "addr:full":"1002 Rocky Ford Rd Thaxton VA 24174",
    "addr:housenumber":"1002",
    "addr:postcode":"24174",
    "addr:street":"Rocky Ford Rd",
    "iso:country":"US",
    "sg:address":"1002 Rocky Ford Rd",
    "sg:city":"Thaxton",
    "sg:classifiers":[
        {
            "category":"Wholesale",
            "subcategory":"Construction Materials",
            "type":"Manufacturing & Wholesale Goods"
        }
    ],
    "sg:phone":"+1 540 586 3549",
    "sg:postcode":"24174",
    "sg:province":"VA",
    "sg:tags":[
        "windows",
        "siding",
        "replacement",
        "vinyl",
        "ins"
    ],
    "wof:name":"Aair Tite Exteriors",
    "wof:placetype":"venue"
},
  "geometry": {"coordinates":[-79.618604,37.350239],"type":"Point"}
}