{
  "type": "Feature",
  "properties": {
    "addr:full":"111 Virginia Ln Yorktown VA 23692",
    "addr:housenumber":"111",
    "addr:postcode":"23692",
    "addr:street":"Virginia Ln",
    "iso:country":"US",
    "sg:address":"111 Virginia Ln",
    "sg:city":"Yorktown",
    "sg:classifiers":[
        {
            "category":"Home & Garden",
            "subcategory":"Building Materials",
            "type":"Retail Goods"
        }
    ],
    "sg:phone":"+1 757 898 3020",
    "sg:postcode":"23692",
    "sg:province":"VA",
    "sg:tags":[
        "modular"
    ],
    "wof:name":"Jab Inc",
    "wof:placetype":"venue"
},
  "geometry": {"coordinates":[-76.463565,37.151919],"type":"Point"}
}