{
  "type": "Feature",
  "properties": {
    "addr:full":"100 W Strasburg Rd Front Royal VA 22630",
    "addr:housenumber":"100",
    "addr:postcode":"22630",
    "addr:street":"W Strasburg Rd",
    "iso:country":"US",
    "sg:address":"100 W Strasburg Rd",
    "sg:city":"Front Royal",
    "sg:classifiers":[
        {
            "category":"Building & Trades",
            "subcategory":"Construction",
            "type":"Services"
        }
    ],
    "sg:phone":"+1 540 636 6017",
    "sg:postcode":"22630",
    "sg:province":"VA",
    "sg:tags":[
        "hanging",
        "contractor"
    ],
    "wof:name":"Massey Painting",
    "wof:placetype":"venue"
},
  "geometry": {"coordinates":[-78.20364600000001,38.947628],"type":"Point"}
}