{
  "type": "Feature",
  "properties": {
    "addr:full":"128 Briarwood Ct Sterling VA 20164",
    "addr:housenumber":"128",
    "addr:postcode":"20164",
    "addr:street":"Briarwood Ct",
    "iso:country":"US",
    "sg:address":"128 Briarwood Ct",
    "sg:city":"Sterling",
    "sg:classifiers":[
        {
            "category":"Organizations",
            "subcategory":"Professional Association",
            "type":"Services"
        }
    ],
    "sg:phone":"+1 703 481 0283",
    "sg:postcode":"20164",
    "sg:province":"VA",
    "sg:tags":[
        "business"
    ],
    "wof:name":"Forest Ridge Home Owners Assoc",
    "wof:placetype":"venue"
},
  "geometry": {"coordinates":[-77.402704,38.984349],"type":"Point"}
}