{
  "type": "Feature",
  "properties": {
    "iso:country":"US",
    "sg:address":"919 Canal Dr",
    "sg:city":"Chesapeake",
    "sg:classifiers":[
        {
            "category":"Retail",
            "subcategory":"Repair Shop",
            "type":"Services"
        }
    ],
    "sg:phone":"+1 757 543 4002",
    "sg:postcode":"23323",
    "sg:province":"VA",
    "wof:name":"Macks Lock & Key",
    "wof:placetype":"venue"
},
  "geometry": {"coordinates":[-76.325633,36.776438],"type":"Point"}
}