{
  "type": "Feature",
  "properties": {
    "addr:full":"7708 Castlebury Ct Warrenton VA 20186",
    "addr:housenumber":"7708",
    "addr:postcode":"20186",
    "addr:street":"Castlebury Ct",
    "iso:country":"US",
    "sg:address":"7708 Castlebury Ct",
    "sg:city":"Warrenton",
    "sg:classifiers":[
        {
            "category":"Professional",
            "subcategory":"Management & Consulting",
            "type":"Services"
        }
    ],
    "sg:phone":"+1 540 347 3660",
    "sg:postcode":"20186",
    "sg:province":"VA",
    "sg:tags":[
        "business"
    ],
    "wof:name":"Government Bus Solutions LLC",
    "wof:placetype":"venue"
},
  "geometry": {"coordinates":[-77.821645,38.629411],"type":"Point"}
}