{
  "type": "Feature",
  "properties": {
    "iso:country":"US",
    "sg:address":"13817 Foulger Sq",
    "sg:city":"Woodbridge",
    "sg:classifiers":[
        {
            "category":"Professional",
            "subcategory":"Business Services",
            "type":"Services"
        }
    ],
    "sg:phone":"+1 703 583 0130",
    "sg:postcode":"22192",
    "sg:province":"VA",
    "wof:name":"Foulger Pratt Management",
    "wof:placetype":"venue"
},
  "geometry": {"coordinates":[-77.30392000000001,38.654964],"type":"Point"}
}