{
  "type": "Feature",
  "properties": {
    "addr:full":"4907 Brambleton Ave Roanoke VA 24018",
    "addr:housenumber":"4907",
    "addr:postcode":"24018",
    "addr:street":"Brambleton Ave",
    "iso:country":"US",
    "sg:address":"4907 Brambleton Ave",
    "sg:city":"Roanoke",
    "sg:classifiers":[
        {
            "category":"Health Services",
            "subcategory":"Doctor",
            "type":"Services"
        }
    ],
    "sg:phone":"+1 540 774 3143",
    "sg:postcode":"24018",
    "sg:province":"VA",
    "sg:tags":[
        "dentist"
    ],
    "wof:name":"John Carter DDS",
    "wof:placetype":"venue"
},
  "geometry": {"coordinates":[-80.019526,37.214335],"type":"Point"}
}