{
  "type": "Feature",
  "properties": {
    "addr:full":"201 Kings Hwy Fredericksburg VA 22405",
    "addr:housenumber":"201",
    "addr:postcode":"22405",
    "addr:street":"Kings Hwy",
    "iso:country":"US",
    "sg:address":"201 Kings Hwy",
    "sg:city":"Fredericksburg",
    "sg:classifiers":[
        {
            "category":"Restaurant",
            "type":"Food & Drink"
        }
    ],
    "sg:phone":"+1 540 371 1970",
    "sg:postcode":"22405",
    "sg:province":"VA",
    "sg:tags":[
        "eating"
    ],
    "wof:name":"Moonstar",
    "wof:placetype":"venue"
},
  "geometry": {"coordinates":[-77.447334,38.297072],"type":"Point"}
}