{
  "type": "Feature",
  "properties": {
    "iso:country":"US",
    "sg:address":"3917 Terry Pl",
    "sg:city":"Alexandria",
    "sg:classifiers":[
        {
            "category":"Retail",
            "subcategory":"Auto Repair",
            "type":"Services"
        }
    ],
    "sg:phone":"+1 703 370 9286",
    "sg:postcode":"22304",
    "sg:province":"VA",
    "sg:tags":[
        "glass",
        "replacement"
    ],
    "wof:name":"Preferred Auto Glass Inc",
    "wof:placetype":"venue"
},
  "geometry": {"coordinates":[-77.098567,38.81823],"type":"Point"}
}