{
  "type": "Feature",
  "properties": {
    "addr:full":"1382 Carl D Silver Pkwy Fredericksburg VA 22401",
    "addr:housenumber":"1382",
    "addr:postcode":"22401",
    "addr:street":"Carl D Silver Pkwy",
    "iso:country":"US",
    "sg:address":"1382 Carl D Silver Pkwy",
    "sg:city":"Fredericksburg",
    "sg:classifiers":[
        {
            "category":"Shopping",
            "subcategory":"Clothing, Apparel, & Fashions",
            "type":"Retail Goods"
        }
    ],
    "sg:phone":"+1 540 548 0006",
    "sg:postcode":"22401",
    "sg:province":"VA",
    "wof:name":"Catherines",
    "wof:placetype":"venue"
},
  "geometry": {"coordinates":[-77.507949,38.301418],"type":"Point"}
}