{
  "type": "Feature",
  "properties": {
    "addr:full":"841 W Main St Smithfield VA 23430",
    "addr:housenumber":"841",
    "addr:postcode":"23430",
    "addr:street":"W Main St",
    "iso:country":"US",
    "sg:address":"841 W Main St",
    "sg:city":"Smithfield",
    "sg:classifiers":[
        {
            "category":"Food & Beverages",
            "subcategory":"Groceries & Convenience Stores",
            "type":"Retail Goods"
        }
    ],
    "sg:phone":"+1 757 357 7164",
    "sg:postcode":"23430",
    "sg:province":"VA",
    "wof:name":"Hearn's Bait Barn & Gen Store",
    "wof:placetype":"venue"
},
  "geometry": {"coordinates":[-76.64883500000001,36.974147],"type":"Point"}
}