{
  "type": "Feature",
  "properties": {
    "addr:full":"2700 Potomac Mills Cir Woodbridge VA 22192",
    "addr:housenumber":"2700",
    "addr:postcode":"22192",
    "addr:street":"Potomac Mills Cir",
    "iso:country":"US",
    "sg:address":"2700 Potomac Mills Cir",
    "sg:city":"Woodbridge",
    "sg:classifiers":[
        {
            "category":"Restaurant",
            "type":"Food & Drink"
        }
    ],
    "sg:menulink":"http://www.allmenus.com/va/occoquan/199999-long-john-silvers/menu/",
    "sg:phone":"+1 703 490 4343",
    "sg:postcode":"22192",
    "sg:province":"VA",
    "sg:tags":[
        "seafood",
        "american"
    ],
    "wof:name":"Long John Silver's",
    "wof:placetype":"venue"
},
  "geometry": {"coordinates":[-77.29899,38.645707],"type":"Point"}
}