{
  "type": "Feature",
  "properties": {
    "addr:full":"8498 Richmond Hwy Alexandria VA 22309",
    "addr:housenumber":"8498",
    "addr:postcode":"22309",
    "addr:street":"Richmond Hwy",
    "iso:country":"US",
    "sg:address":"8498 Richmond Hwy",
    "sg:city":"Alexandria",
    "sg:classifiers":[
        {
            "category":"Personal",
            "subcategory":"Beauty Salon",
            "type":"Services"
        }
    ],
    "sg:phone":"+1 703 780 3451",
    "sg:postcode":"22309",
    "sg:province":"VA",
    "wof:name":"Mimi Of Alexandria Beauty Sln",
    "wof:placetype":"venue"
},
  "geometry": {"coordinates":[-77.11039100000001,38.727878],"type":"Point"}
}