{
  "type": "Feature",
  "properties": {
    "iso:country":"US",
    "sg:address":"2706 E Main St",
    "sg:city":"Richmond",
    "sg:classifiers":[
        {
            "category":"Restaurant",
            "type":"Food & Drink"
        }
    ],
    "sg:phone":"+1 804 648 2120",
    "sg:postcode":"23223",
    "sg:province":"VA",
    "sg:website":"http://www.poespub.com",
    "wof:name":"Poe's Pub",
    "wof:placetype":"venue"
},
  "geometry": {"coordinates":[-77.41900099999999,37.527591],"type":"Point"}
}