{
  "type": "Feature",
  "properties": {
    "addr:full":"400 Kramer Dr Highland Springs VA 23075",
    "addr:housenumber":"400",
    "addr:postcode":"23075",
    "addr:street":"Kramer Dr",
    "iso:country":"US",
    "sg:address":"400 Kramer Dr",
    "sg:city":"Highland Springs",
    "sg:classifiers":[
        {
            "category":"Retail",
            "subcategory":"Laundry & Dry Cleaning",
            "type":"Services"
        }
    ],
    "sg:phone":"+1 804 737 9704",
    "sg:postcode":"23075",
    "sg:province":"VA",
    "sg:tags":[
        "cleaners",
        "rug",
        "carpet"
    ],
    "wof:name":"Mr Green Carpet Cleaning",
    "wof:placetype":"venue"
},
  "geometry": {"coordinates":[-77.32289299999999,37.554905],"type":"Point"}
}