{
  "type": "Feature",
  "properties": {
    "iso:country":"US",
    "sg:address":"118 Buckingham Cir",
    "sg:city":"Charlottesville",
    "sg:classifiers":[
        {
            "category":"Professional",
            "type":"Services"
        }
    ],
    "sg:phone":"+1 434 923 0987",
    "sg:postcode":"22903",
    "sg:province":"VA",
    "sg:tags":[
        "consulting",
        "geological"
    ],
    "wof:name":"True North Consulting",
    "wof:placetype":"venue"
},
  "geometry": {"coordinates":[-78.530332,38.027653],"type":"Point"}
}