{
  "type": "Feature",
  "properties": {
    "iso:country":"US",
    "sg:address":"1888 Grinnell Ct",
    "sg:city":"Virginia Beach",
    "sg:classifiers":[
        {
            "category":"Professional",
            "subcategory":"Computer Services",
            "type":"Services"
        }
    ],
    "sg:phone":"+1 757 427 6737",
    "sg:postcode":"23454",
    "sg:province":"VA",
    "sg:tags":[
        "datum"
    ],
    "wof:name":"Cybersites",
    "wof:placetype":"venue"
},
  "geometry": {"coordinates":[-75.995107,36.772989],"type":"Point"}
}