{
  "type": "Feature",
  "properties": {
    "addr:full":"21192 Yellow Bottom Rd Lignum VA 22726",
    "addr:housenumber":"21192",
    "addr:postcode":"22726",
    "addr:street":"Yellow Bottom Rd",
    "iso:country":"US",
    "sg:address":"21192 Yellow Bottom Rd",
    "sg:city":"Lignum",
    "sg:classifiers":[
        {
            "category":"Building & Trades",
            "subcategory":"Construction",
            "type":"Services"
        }
    ],
    "sg:phone":"+1 540 842 4000",
    "sg:postcode":"22726",
    "sg:province":"VA",
    "sg:tags":[
        "home",
        "improvement"
    ],
    "wof:name":"Grace Windows & Siding",
    "wof:placetype":"venue"
},
  "geometry": {"coordinates":[-77.799049,38.410122],"type":"Point"}
}