{
  "type": "Feature",
  "properties": {
    "iso:country":"US",
    "sg:address":"2307 Freetown Ct",
    "sg:city":"Reston",
    "sg:classifiers":[
        {
            "category":"Professional",
            "subcategory":"Management & Consulting",
            "type":"Services"
        }
    ],
    "sg:phone":"+1 703 716 0077",
    "sg:postcode":"20191",
    "sg:province":"VA",
    "wof:name":"Turning Point",
    "wof:placetype":"venue"
},
  "geometry": {"coordinates":[-77.367507,38.936042],"type":"Point"}
}