{
  "type": "Feature",
  "properties": {
    "iso:country":"US",
    "sg:address":"7423 Shreve Rd",
    "sg:city":"Falls Church",
    "sg:classifiers":[
        {
            "category":"Real Estate",
            "subcategory":"Real Estate Agent",
            "type":"Services"
        }
    ],
    "sg:phone":"+1 703 573 3157",
    "sg:postcode":"22043",
    "sg:province":"VA",
    "sg:tags":[
        "management"
    ],
    "wof:name":"Shrevewood Estates",
    "wof:placetype":"venue"
},
  "geometry": {"coordinates":[-77.206856,38.889309],"type":"Point"}
}