{
  "type": "Feature",
  "properties": {
    "addr:full":"4160 Rectortown Rd Marshall VA 20115",
    "addr:housenumber":"4160",
    "addr:postcode":"20115",
    "addr:street":"Rectortown Rd",
    "iso:country":"US",
    "sg:address":"4160 Rectortown Rd",
    "sg:city":"Marshall",
    "sg:classifiers":[
        {
            "category":"Organizations",
            "subcategory":"Non-profit Organization",
            "type":"Services"
        }
    ],
    "sg:phone":"+1 540 364 2047",
    "sg:postcode":"20115",
    "sg:province":"VA",
    "wof:name":"Marshall Volunteer Fire Dept",
    "wof:placetype":"venue"
},
  "geometry": {"coordinates":[-77.85548300000001,38.867258],"type":"Point"}
}