{
  "type": "Feature",
  "properties": {
    "addr:full":"1948 Thomson Dr Lynchburg VA 24501",
    "addr:housenumber":"1948",
    "addr:postcode":"24501",
    "addr:street":"Thomson Dr",
    "iso:country":"US",
    "sg:address":"1948 Thomson Dr",
    "sg:city":"Lynchburg",
    "sg:classifiers":[
        {
            "category":"Health Services",
            "subcategory":"Health Practitioner",
            "type":"Services"
        }
    ],
    "sg:phone":"+1 434 845 8765",
    "sg:postcode":"24501",
    "sg:province":"VA",
    "wof:name":"Blue Ridge Therapy Associates",
    "wof:placetype":"venue"
},
  "geometry": {"coordinates":[-79.176558,37.41921],"type":"Point"}
}