{
  "type": "Feature",
  "properties": {
    "iso:country":"US",
    "sg:address":"6150 Deer Ridge Trl",
    "sg:city":"Springfield",
    "sg:classifiers":[
        {
            "category":"Professional",
            "subcategory":"Engineering",
            "type":"Services"
        },
        {
            "category":"Manufacturing",
            "subcategory":"Electronics",
            "type":"Manufacturing & Wholesale Goods"
        }
    ],
    "sg:phone":"+1 703 461 0629",
    "sg:postcode":"22150",
    "sg:province":"VA",
    "sg:tags":[
        "control",
        "system",
        "automation",
        "electronic",
        "controls-manufacturers",
        "engineer"
    ],
    "wof:name":"12 120 Installations",
    "wof:placetype":"venue"
},
  "geometry": {"coordinates":[-77.157093,38.784678],"type":"Point"}
}