{
  "type": "Feature",
  "properties": {
    "iso:country":"US",
    "sg:address":"1320 Gust Ln",
    "sg:city":"Chesapeake",
    "sg:classifiers":[
        {
            "category":"Professional",
            "type":"Services"
        }
    ],
    "sg:phone":"+1 757 487 5441",
    "sg:postcode":"23323",
    "sg:province":"VA",
    "wof:name":"Spirit of Verona H Thomas",
    "wof:placetype":"venue"
},
  "geometry": {"coordinates":[-76.34194599999999,36.786685],"type":"Point"}
}