{
  "type": "Feature",
  "properties": {
    "iso:country":"US",
    "sg:address":"29 Hollaway Rd",
    "sg:city":"Poquoson",
    "sg:classifiers":[
        {
            "category":"Real Estate",
            "subcategory":"Real Estate Agent",
            "type":"Services"
        }
    ],
    "sg:phone":"+1 757 868 4663",
    "sg:postcode":"23662",
    "sg:province":"VA",
    "sg:tags":[
        "book"
    ],
    "wof:name":"All Star Comics",
    "wof:placetype":"venue"
},
  "geometry": {"coordinates":[-76.372129,37.136455],"type":"Point"}
}