{
  "type": "Feature",
  "properties": {
    "iso:country":"US",
    "sg:address":"6001 Duke St",
    "sg:city":"Alexandria",
    "sg:classifiers":[
        {
            "category":"Retail",
            "subcategory":"Auto Repair",
            "type":"Services"
        }
    ],
    "sg:phone":"+1 703 914 2228",
    "sg:postcode":"22304",
    "sg:province":"VA",
    "sg:website":"auto.sears.com",
    "wof:name":"Sears Auto Center",
    "wof:placetype":"venue"
},
  "geometry": {"coordinates":[-77.13475800000001,38.815206],"type":"Point"}
}