{
  "type": "Feature",
  "properties": {
    "addr:full":"120 N Hatcher Ave Purcellville VA 20132",
    "addr:housenumber":"120",
    "addr:postcode":"20132",
    "addr:street":"N Hatcher Ave",
    "iso:country":"US",
    "sg:address":"120 N Hatcher Ave",
    "sg:city":"Purcellville",
    "sg:classifiers":[
        {
            "category":"Banks & Credit Unions",
            "subcategory":"Investment Brokerage",
            "type":"Services"
        }
    ],
    "sg:phone":"+1 540 751 1733",
    "sg:postcode":"20132",
    "sg:province":"VA",
    "sg:tags":[
        "advisory",
        "financial"
    ],
    "wof:name":"Black Elk Management Inc",
    "wof:placetype":"venue"
},
  "geometry": {"coordinates":[-77.713031,39.138167],"type":"Point"}
}