{
  "type": "Feature",
  "properties": {
    "iso:country":"US",
    "sg:address":"1101 Madison Plz",
    "sg:city":"Chesapeake",
    "sg:classifiers":[
        {
            "category":"Health Services",
            "subcategory":"Clinic",
            "type":"Services"
        },
        {
            "category":"Social Services",
            "type":"Services"
        }
    ],
    "sg:phone":"+1 757 436 2444",
    "sg:postcode":"23320",
    "sg:province":"VA",
    "sg:tags":[
        "worker"
    ],
    "wof:name":"King Jones & Assoc",
    "wof:placetype":"venue"
},
  "geometry": {"coordinates":[-76.251997,36.760881],"type":"Point"}
}