{
  "type": "Feature",
  "properties": {
    "iso:country":"US",
    "sg:address":"725 N Henry St",
    "sg:city":"Alexandria",
    "sg:classifiers":[
        {
            "category":"Autos & Motor Vehicles",
            "subcategory":"Automobile Sales",
            "type":"Retail Goods"
        }
    ],
    "sg:phone":"+1 703 739 0004",
    "sg:postcode":"22314",
    "sg:province":"VA",
    "sg:tags":[
        "car",
        "used",
        "sales"
    ],
    "wof:name":"Euro Imports",
    "wof:placetype":"venue"
},
  "geometry": {"coordinates":[-77.049634,38.81329],"type":"Point"}
}