{
  "type": "Feature",
  "properties": {
    "addr:full":"14300 Midlothian Tpke Midlothian VA 23113",
    "addr:housenumber":"14300",
    "addr:postcode":"23113",
    "addr:street":"Midlothian Tpke",
    "iso:country":"US",
    "sg:address":"14300 Midlothian Tpke",
    "sg:city":"Midlothian",
    "sg:classifiers":[
        {
            "category":"Professional",
            "subcategory":"Printing & Photocopies",
            "type":"Services"
        }
    ],
    "sg:phone":"+1 804 379 2075",
    "sg:postcode":"23113",
    "sg:province":"VA",
    "sg:tags":[
        "duplicating",
        "copying"
    ],
    "wof:name":"Midlothian Quickprint",
    "wof:placetype":"venue"
},
  "geometry": {"coordinates":[-77.67068399999999,37.506663],"type":"Point"}
}