{
  "type": "Feature",
  "properties": {
    "addr:full":"10005 Brandon Way Manassas VA 20109",
    "addr:housenumber":"10005",
    "addr:postcode":"20109",
    "addr:street":"Brandon Way",
    "iso:country":"US",
    "sg:address":"10005 Brandon Way",
    "sg:city":"Manassas",
    "sg:classifiers":[
        {
            "category":"Professional",
            "subcategory":"Business Services",
            "type":"Services"
        }
    ],
    "sg:phone":"+1 703 361 2868",
    "sg:postcode":"20109",
    "sg:province":"VA",
    "sg:tags":[
        "interior",
        "consultant",
        "design",
        "decorator"
    ],
    "wof:name":"Barbara Bateman Interior Decor",
    "wof:placetype":"venue"
},
  "geometry": {"coordinates":[-77.49678,38.793113],"type":"Point"}
}