{
  "type": "Feature",
  "properties": {
    "iso:country":"US",
    "sg:address":"10604 Judicial Dr",
    "sg:city":"Fairfax",
    "sg:classifiers":[
        {
            "category":"Professional",
            "type":"Services"
        }
    ],
    "sg:phone":"+1 703 246 2697",
    "sg:postcode":"22030",
    "sg:province":"VA",
    "wof:name":"Volunteer Services",
    "wof:placetype":"venue"
},
  "geometry": {"coordinates":[-77.31194600000001,38.84384],"type":"Point"}
}