{
  "type": "Feature",
  "properties": {
    "iso:country":"US",
    "sg:address":"9501 Gayton Rd",
    "sg:city":"Richmond",
    "sg:classifiers":[
        {
            "category":"Education",
            "subcategory":"School",
            "type":"Public Place"
        }
    ],
    "sg:phone":"+1 804 740 1048",
    "sg:postcode":"23229",
    "sg:province":"VA",
    "wof:name":"Saint Marys School",
    "wof:placetype":"venue"
},
  "geometry": {"coordinates":[-77.58868099999999,37.602827],"type":"Point"}
}