{
  "type": "Feature",
  "properties": {
    "addr:full":"2118 Clover Rd Richmond VA 23230",
    "addr:housenumber":"2118",
    "addr:postcode":"23230",
    "addr:street":"Clover Rd",
    "iso:country":"US",
    "sg:address":"2118 Clover Rd",
    "sg:city":"Richmond",
    "sg:classifiers":[
        {
            "category":"Building & Trades",
            "subcategory":"Construction",
            "type":"Services"
        }
    ],
    "sg:phone":"+1 804 355 9130",
    "sg:postcode":"23230",
    "sg:province":"VA",
    "sg:tags":[
        "repairing",
        "remodeling",
        "contractor"
    ],
    "wof:name":"O'Berry Home Remodeling",
    "wof:placetype":"venue"
},
  "geometry": {"coordinates":[-77.49499,37.587718],"type":"Point"}
}