{
  "type": "Feature",
  "properties": {
    "addr:full":"519 Branchway Rd Richmond VA 23236",
    "addr:housenumber":"519",
    "addr:postcode":"23236",
    "addr:street":"Branchway Rd",
    "iso:country":"US",
    "sg:address":"519 Branchway Rd",
    "sg:city":"Richmond",
    "sg:classifiers":[
        {
            "category":"Banks & Credit Unions",
            "subcategory":"Financial Services",
            "type":"Services"
        }
    ],
    "sg:phone":"+1 804 594 2522",
    "sg:postcode":"23236",
    "sg:province":"VA",
    "sg:tags":[
        "investor"
    ],
    "wof:name":"CFD Investments",
    "wof:placetype":"venue"
},
  "geometry": {"coordinates":[-77.60638,37.498127],"type":"Point"}
}