{
  "type": "Feature",
  "properties": {
    "addr:full":"7553 Gary Rd Manassas VA 20109",
    "addr:housenumber":"7553",
    "addr:postcode":"20109",
    "addr:street":"Gary Rd",
    "iso:country":"US",
    "sg:address":"7553 Gary Rd",
    "sg:city":"Manassas",
    "sg:classifiers":[
        {
            "category":"Manufacturing",
            "subcategory":"Retail Goods",
            "type":"Manufacturing & Wholesale Goods"
        }
    ],
    "sg:phone":"+1 703 361 9663",
    "sg:postcode":"20109",
    "sg:province":"VA",
    "sg:tags":[
        "manufacturer"
    ],
    "sg:website":"www.cmore.com",
    "wof:name":"C-More Systems",
    "wof:placetype":"venue"
},
  "geometry": {"coordinates":[-77.501437,38.801202],"type":"Point"}
}