{
  "type": "Feature",
  "properties": {
    "addr:full":"825 Windmill Rd Galax VA 24333",
    "addr:housenumber":"825",
    "addr:postcode":"24333",
    "addr:street":"Windmill Rd",
    "iso:country":"US",
    "sg:address":"825 Windmill Rd",
    "sg:city":"Galax",
    "sg:classifiers":[
        {
            "category":"Professional",
            "type":"Services"
        }
    ],
    "sg:phone":"+1 276 238 1824",
    "sg:postcode":"24333",
    "sg:province":"VA",
    "wof:name":"Larry D Mays",
    "wof:placetype":"venue"
},
  "geometry": {"coordinates":[-80.95308199999999,36.687274],"type":"Point"}
}