{
  "type": "Feature",
  "properties": {
    "addr:full":"4023 26th St N Arlington VA 22207",
    "addr:housenumber":"4023",
    "addr:postcode":"22207",
    "addr:street":"26Th St N",
    "iso:country":"US",
    "sg:address":"4023 26th St N",
    "sg:city":"Arlington",
    "sg:classifiers":[
        {
            "category":"Professional",
            "type":"Services"
        }
    ],
    "sg:phone":"+1 703 276 3597",
    "sg:postcode":"22207",
    "sg:province":"VA",
    "wof:name":"14640 Flint Lee Rd LLC",
    "wof:placetype":"venue"
},
  "geometry": {"coordinates":[-77.10888300000001,38.906797],"type":"Point"}
}