{
  "type": "Feature",
  "properties": {
    "iso:country":"US",
    "sg:address":"5536 Glen View Dr",
    "sg:city":"Virginia Beach",
    "sg:classifiers":[
        {
            "category":"Building & Trades",
            "subcategory":"Plumbing",
            "type":"Services"
        }
    ],
    "sg:phone":"+1 757 461 0111",
    "sg:postcode":"23464",
    "sg:province":"VA",
    "sg:tags":[
        "plumbing",
        "contractor"
    ],
    "wof:name":"Plumbing Man Inc",
    "wof:placetype":"venue"
},
  "geometry": {"coordinates":[-76.192121,36.772472],"type":"Point"}
}