{
  "type": "Feature",
  "properties": {
    "iso:country":"US",
    "sg:address":"403 N Main St",
    "sg:city":"Emporia",
    "sg:classifiers":[
        {
            "category":"Retail",
            "subcategory":"Auto Repair",
            "type":"Services"
        }
    ],
    "sg:phone":"+1 434 634 0299",
    "sg:postcode":"23847",
    "sg:province":"VA",
    "sg:tags":[
        "glass",
        "replacement"
    ],
    "wof:name":"Jons Auto Glass Inc",
    "wof:placetype":"venue"
},
  "geometry": {"coordinates":[-77.538494,36.694629],"type":"Point"}
}