{
  "type": "Feature",
  "properties": {
    "iso:country":"US",
    "sg:address":"7293 Hanover Green Dr",
    "sg:city":"Mechanicsville",
    "sg:classifiers":[
        {
            "category":"Education",
            "subcategory":"Special Training",
            "type":"Public Place"
        }
    ],
    "sg:phone":"+1 804 559 7293",
    "sg:postcode":"23111",
    "sg:province":"VA",
    "sg:tags":[
        "center"
    ],
    "wof:name":"Learning Specialists Of Va Inc",
    "wof:placetype":"venue"
},
  "geometry": {"coordinates":[-77.37573399999999,37.603981],"type":"Point"}
}