{
  "type": "Feature",
  "properties": {
    "addr:full":"9232 Portner Ave Manassas VA 20110",
    "addr:postcode":"9232;20110",
    "addr:street":"Portner Ave",
    "iso:country":"US",
    "sg:address":"9232 Portner Ave",
    "sg:city":"Manassas",
    "sg:classifiers":[
        {
            "category":"Building & Trades",
            "subcategory":"Landscaping Services",
            "type":"Services"
        }
    ],
    "sg:phone":"+1 703 368 6223",
    "sg:postcode":"20110",
    "sg:province":"VA",
    "sg:tags":[
        "landscape"
    ],
    "wof:name":"Brent E Neal",
    "wof:placetype":"venue"
},
  "geometry": {"coordinates":[-77.474853,38.754482],"type":"Point"}
}