{
  "type": "Feature",
  "properties": {
    "iso:country":"US",
    "sg:address":"4905 W Leigh St",
    "sg:city":"Richmond",
    "sg:classifiers":[
        {
            "category":"Wholesale",
            "subcategory":"Machinery & Supplies",
            "type":"Manufacturing & Wholesale Goods"
        },
        {
            "category":"Wholesale",
            "subcategory":"Groceries",
            "type":"Manufacturing & Wholesale Goods"
        }
    ],
    "sg:phone":"+1 804 354 9895",
    "sg:postcode":"23230",
    "sg:province":"VA",
    "sg:tags":[
        "grocer"
    ],
    "wof:name":"Flushing Fairy Inc",
    "wof:placetype":"venue"
},
  "geometry": {"coordinates":[-77.494716,37.586238],"type":"Point"}
}