{
  "type": "Feature",
  "properties": {
    "addr:full":"4217 Kincaid Ct Chantilly VA 20151",
    "addr:housenumber":"4217",
    "addr:postcode":"20151",
    "addr:street":"Kincaid Ct",
    "iso:country":"US",
    "sg:address":"4217 Kincaid Ct",
    "sg:city":"Chantilly",
    "sg:classifiers":[
        {
            "category":"Professional",
            "subcategory":"Computer Services",
            "type":"Services"
        }
    ],
    "sg:phone":"+1 703 623 9943",
    "sg:postcode":"20151",
    "sg:province":"VA",
    "sg:tags":[
        "technology"
    ],
    "wof:name":"Toucan Technologies LLC",
    "wof:placetype":"venue"
},
  "geometry": {"coordinates":[-77.41612499999999,38.879475],"type":"Point"}
}