{
  "type": "Feature",
  "properties": {
    "iso:country":"US",
    "sg:address":"3613 Prince William Dr",
    "sg:city":"Fairfax",
    "sg:classifiers":[
        {
            "category":"Professional",
            "subcategory":"Lawyer & Legal Services",
            "type":"Services"
        }
    ],
    "sg:phone":"+1 703 383 3991",
    "sg:postcode":"22031",
    "sg:province":"VA",
    "wof:name":"Jay Schiffries",
    "wof:placetype":"venue"
},
  "geometry": {"coordinates":[-77.266036,38.849447],"type":"Point"}
}