{
  "type": "Feature",
  "properties": {
    "iso:country":"US",
    "sg:address":"114 Court St",
    "sg:city":"Hillsville",
    "sg:classifiers":[
        {
            "category":"Professional",
            "subcategory":"Business Services",
            "type":"Services"
        }
    ],
    "sg:phone":"+1 276 728 0991",
    "sg:postcode":"24343",
    "sg:province":"VA",
    "sg:tags":[
        "appraiser"
    ],
    "wof:name":"Yonce Real Estate & Appraisal",
    "wof:placetype":"venue"
},
  "geometry": {"coordinates":[-80.73695499999999,36.766768],"type":"Point"}
}