{
  "type": "Feature",
  "properties": {
    "addr:full":"1243 Spring Ave SW Norton VA 24273",
    "addr:housenumber":"1243",
    "addr:postcode":"24273",
    "addr:street":"Spring Ave Sw",
    "iso:country":"US",
    "sg:address":"1243 Spring Ave SW",
    "sg:city":"Norton",
    "sg:classifiers":[
        {
            "category":"Organizations",
            "subcategory":"Religious Organization",
            "type":"Services"
        }
    ],
    "sg:phone":"+1 276 679 6008",
    "sg:postcode":"24273",
    "sg:province":"VA",
    "wof:name":"Grace Bible Church",
    "wof:placetype":"venue"
},
  "geometry": {"coordinates":[-82.635306,36.92925],"type":"Point"}
}