{
  "type": "Feature",
  "properties": {
    "iso:country":"US",
    "sg:address":"2010 Old Greenbrier Rd",
    "sg:city":"Chesapeake",
    "sg:classifiers":[
        {
            "category":"Building & Trades",
            "subcategory":"Construction",
            "type":"Services"
        }
    ],
    "sg:phone":"+1 757 523 2569",
    "sg:postcode":"23320",
    "sg:province":"VA",
    "sg:tags":[
        "home",
        "speculative",
        "builder",
        "family",
        "contractor"
    ],
    "wof:name":"Hearndon Construction Corp",
    "wof:placetype":"venue"
},
  "geometry": {"coordinates":[-76.234582,36.793955],"type":"Point"}
}