{
  "type": "Feature",
  "properties": {
    "addr:full":"843 Orville Ave Chesapeake VA 23324",
    "addr:housenumber":"843",
    "addr:postcode":"23324",
    "addr:street":"Orville Ave",
    "iso:country":"US",
    "sg:address":"843 Orville Ave",
    "sg:city":"Chesapeake",
    "sg:classifiers":[
        {
            "category":"Manufacturing",
            "subcategory":"Retail Goods",
            "type":"Manufacturing & Wholesale Goods"
        }
    ],
    "sg:phone":"+1 757 228 7963",
    "sg:postcode":"23324",
    "sg:province":"VA",
    "sg:tags":[
        "product",
        "mfg"
    ],
    "wof:name":"Fourstar Industries",
    "wof:placetype":"venue"
},
  "geometry": {"coordinates":[-76.275177,36.807707],"type":"Point"}
}