{
  "type": "Feature",
  "properties": {
    "iso:country":"US",
    "sg:address":"518 Stoney Creek Blvd",
    "sg:city":"Edinburg",
    "sg:classifiers":[
        {
            "category":"Building & Trades",
            "subcategory":"Construction",
            "type":"Services"
        }
    ],
    "sg:phone":"+1 540 984 3440",
    "sg:postcode":"22824",
    "sg:province":"VA",
    "sg:tags":[
        "hanging",
        "painter",
        "contractor"
    ],
    "wof:name":"Action Custom Painting Contrac",
    "wof:placetype":"venue"
},
  "geometry": {"coordinates":[-78.570442,38.826982],"type":"Point"}
}