{
  "type": "Feature",
  "properties": {
    "addr:full":"719 Galloway Dr SE Leesburg VA 20175",
    "addr:housenumber":"719",
    "addr:postcode":"20175",
    "addr:street":"Galloway Dr Se",
    "iso:country":"US",
    "sg:address":"719 Galloway Dr SE",
    "sg:city":"Leesburg",
    "sg:classifiers":[
        {
            "category":"Retail",
            "subcategory":"Auto Repair",
            "type":"Services"
        }
    ],
    "sg:phone":"+1 703 771 1980",
    "sg:postcode":"20175",
    "sg:province":"VA",
    "sg:tags":[
        "body"
    ],
    "wof:name":"Loudoun Collision",
    "wof:placetype":"venue"
},
  "geometry": {"coordinates":[-77.549705,39.085561],"type":"Point"}
}