{
  "type": "Feature",
  "properties": {
    "addr:full":"9058 Edgewater Cir Mechanicsville VA 23116",
    "addr:housenumber":"9058",
    "addr:postcode":"23116",
    "addr:street":"Edgewater Cir",
    "iso:country":"US",
    "sg:address":"9058 Edgewater Cir",
    "sg:city":"Mechanicsville",
    "sg:classifiers":[
        {
            "category":"Professional",
            "subcategory":"Accounting & Tax Preparation",
            "type":"Services"
        }
    ],
    "sg:phone":"+1 804 550 3439",
    "sg:postcode":"23116",
    "sg:province":"VA",
    "sg:tags":[
        "return"
    ],
    "wof:name":"Taxman Dussell",
    "wof:placetype":"venue"
},
  "geometry": {"coordinates":[-77.409209,37.702496],"type":"Point"}
}