{
  "type": "Feature",
  "properties": {
    "addr:full":"11731 Dry River Ct Reston VA 20191",
    "addr:housenumber":"11731",
    "addr:postcode":"20191",
    "addr:street":"Dry River Ct",
    "iso:country":"US",
    "sg:address":"11731 Dry River Ct",
    "sg:city":"Reston",
    "sg:classifiers":[
        {
            "category":"Wholesale",
            "subcategory":"Non-durable Goods",
            "type":"Manufacturing & Wholesale Goods"
        }
    ],
    "sg:phone":"+1 703 400 4460",
    "sg:postcode":"20191",
    "sg:province":"VA",
    "sg:tags":[
        "social"
    ],
    "wof:name":"Restondogs Inc",
    "wof:placetype":"venue"
},
  "geometry": {"coordinates":[-77.351292,38.931683],"type":"Point"}
}