{
  "type": "Feature",
  "properties": {
    "iso:country":"US",
    "sg:address":"3100 Warwick Blvd",
    "sg:city":"Newport News",
    "sg:classifiers":[
        {
            "category":"Manufacturing",
            "subcategory":"Tools & Machinery",
            "type":"Manufacturing & Wholesale Goods"
        }
    ],
    "sg:phone":"+1 757 247 0614",
    "sg:postcode":"23607",
    "sg:province":"VA",
    "sg:tags":[
        "machine",
        "shop"
    ],
    "wof:name":"American General Fabrication",
    "wof:placetype":"venue"
},
  "geometry": {"coordinates":[-76.428878,36.983154],"type":"Point"}
}