{
  "type": "Feature",
  "properties": {
    "addr:full":"35538 Belle Haven Rd Belle Haven VA 23306",
    "addr:housenumber":"35538",
    "addr:postcode":"23306",
    "addr:street":"Belle Haven Rd",
    "iso:country":"US",
    "sg:address":"35538 Belle Haven Rd",
    "sg:city":"Belle Haven",
    "sg:classifiers":[
        {
            "category":"Autos & Motor Vehicles",
            "subcategory":"Fuel & Gas Station",
            "type":"Retail Goods"
        }
    ],
    "sg:phone":"+1 757 442 4575",
    "sg:postcode":"23306",
    "sg:province":"VA",
    "sg:tags":[
        "oil"
    ],
    "wof:name":"Phillips Of Bellhaven",
    "wof:placetype":"venue"
},
  "geometry": {"coordinates":[-75.821568,37.551066],"type":"Point"}
}