{
  "type": "Feature",
  "properties": {
    "iso:country":"US",
    "sg:address":"19021 Stoney Point Rd",
    "sg:city":"King George",
    "sg:classifiers":[
        {
            "category":"Building & Trades",
            "subcategory":"Plumbing",
            "type":"Services"
        }
    ],
    "sg:phone":"+1 540 775 3041",
    "sg:postcode":"22485",
    "sg:province":"VA",
    "sg:tags":[
        "plumbing",
        "contractor"
    ],
    "wof:name":"Deckson Corporation",
    "wof:placetype":"venue"
},
  "geometry": {"coordinates":[-77.018333,38.278404],"type":"Point"}
}