{
  "type": "Feature",
  "properties": {
    "addr:full":"1220 Alverser Plz Midlothian VA 23113",
    "addr:housenumber":"1220",
    "addr:postcode":"23113",
    "addr:street":"Alverser Plz",
    "iso:country":"US",
    "sg:address":"1220 Alverser Plz",
    "sg:city":"Midlothian",
    "sg:classifiers":[
        {
            "category":"Ice Cream",
            "type":"Food & Drink"
        }
    ],
    "sg:menulink":"http://www.allmenus.com/va/midlothian/184444-cold-stone-creamery/menu/",
    "sg:phone":"+1 804 423 2653",
    "sg:postcode":"23113",
    "sg:province":"VA",
    "sg:tags":[
        "smoothy",
        "juice",
        "american"
    ],
    "wof:name":"Cold Stone Creamery",
    "wof:placetype":"venue"
},
  "geometry": {"coordinates":[-77.61700399999999,37.508555],"type":"Point"}
}