{
  "type": "Feature",
  "properties": {
    "addr:full":"1666 S Crystal Dr Arlington VA 22202",
    "addr:housenumber":"1666",
    "addr:postcode":"22202",
    "addr:street":"S Crystal Dr",
    "iso:country":"US",
    "sg:address":"1666 S Crystal Dr",
    "sg:city":"Arlington",
    "sg:classifiers":[
        {
            "category":"Shopping",
            "subcategory":"Gifts & Souvenirs",
            "type":"Retail Goods"
        }
    ],
    "sg:phone":"+1 703 416 0582",
    "sg:postcode":"22202",
    "sg:province":"VA",
    "wof:name":"Mad About Bears",
    "wof:placetype":"venue"
},
  "geometry": {"coordinates":[-77.04910700000001,38.858427],"type":"Point"}
}