{
  "type": "Feature",
  "properties": {
    "addr:full":"9224 Wrights Hollow Ln Lorton VA 22079",
    "addr:housenumber":"9224",
    "addr:postcode":"22079",
    "addr:street":"Wrights Hollow Ln",
    "iso:country":"US",
    "sg:address":"9224 Wrights Hollow Ln",
    "sg:city":"Lorton",
    "sg:classifiers":[
        {
            "category":"Building & Trades",
            "subcategory":"Construction",
            "type":"Services"
        }
    ],
    "sg:phone":"+1 703 690 8906",
    "sg:postcode":"22079",
    "sg:province":"VA",
    "sg:tags":[
        "painter"
    ],
    "wof:name":"Olde World Painting",
    "wof:placetype":"venue"
},
  "geometry": {"coordinates":[-77.266755,38.707358],"type":"Point"}
}