{
  "type": "Feature",
  "properties": {
    "addr:full":"5233 Pumphrey Dr Fairfax VA 22032",
    "addr:housenumber":"5233",
    "addr:postcode":"22032",
    "addr:street":"Pumphrey Dr",
    "iso:country":"US",
    "sg:address":"5233 Pumphrey Dr",
    "sg:city":"Fairfax",
    "sg:classifiers":[
        {
            "category":"Organizations",
            "subcategory":"Religious Organization",
            "type":"Services"
        }
    ],
    "sg:phone":"+1 703 978 7983",
    "sg:postcode":"22032",
    "sg:province":"VA",
    "wof:name":"Jerry W Turner",
    "wof:placetype":"venue"
},
  "geometry": {"coordinates":[-77.300639,38.814721],"type":"Point"}
}