{
  "type": "Feature",
  "properties": {
    "addr:full":"4650 Latrobe Pl Alexandria VA 22311",
    "addr:housenumber":"4650",
    "addr:postcode":"22311",
    "addr:street":"Latrobe Pl",
    "iso:country":"US",
    "sg:address":"4650 Latrobe Pl",
    "sg:city":"Alexandria",
    "sg:classifiers":[
        {
            "category":"Retail",
            "subcategory":"Laundry & Dry Cleaning",
            "type":"Services"
        }
    ],
    "sg:phone":"+1 703 575 9569",
    "sg:postcode":"22311",
    "sg:province":"VA",
    "wof:name":"Met Carpet Cleaners Inc",
    "wof:placetype":"venue"
},
  "geometry": {"coordinates":[-77.11058800000001,38.832982],"type":"Point"}
}