{
  "type": "Feature",
  "properties": {
    "addr:full":"3232 Carrollton Pike Woodlawn VA 24381",
    "addr:housenumber":"3232",
    "addr:postcode":"24381",
    "addr:street":"Carrollton Pike",
    "iso:country":"US",
    "sg:address":"3232 Carrollton Pike",
    "sg:city":"Woodlawn",
    "sg:classifiers":[
        {
            "category":"Food & Beverages",
            "subcategory":"Fruits & Vegetables",
            "type":"Retail Goods"
        }
    ],
    "sg:phone":"+1 276 238 8077",
    "sg:postcode":"24381",
    "sg:province":"VA",
    "sg:tags":[
        "produce"
    ],
    "wof:name":"Yoder's Farm Market",
    "wof:placetype":"venue"
},
  "geometry": {"coordinates":[-80.798492,36.735346],"type":"Point"}
}