{
  "type": "Feature",
  "properties": {
    "addr:full":"18005 Dumfries Shopping Plz Dumfries VA 22026",
    "addr:housenumber":"18005",
    "addr:postcode":"22026",
    "addr:street":"Dumfries Shopping Plz",
    "iso:country":"US",
    "sg:address":"18005 Dumfries Shopping Plz",
    "sg:city":"Dumfries",
    "sg:classifiers":[
        {
            "category":"Real Estate",
            "subcategory":"Real Estate Agent",
            "type":"Services"
        }
    ],
    "sg:phone":"+1 703 221 8890",
    "sg:postcode":"22026",
    "sg:province":"VA",
    "sg:tags":[
        "management"
    ],
    "wof:name":"Cavalier Management Inc",
    "wof:placetype":"venue"
},
  "geometry": {"coordinates":[-77.32925,38.56042],"type":"Point"}
}