{
  "type": "Feature",
  "properties": {
    "iso:country":"US",
    "sg:address":"6812 Bland St",
    "sg:city":"Springfield",
    "sg:classifiers":[
        {
            "category":"Shopping",
            "subcategory":"Musical Instruments",
            "type":"Retail Goods"
        }
    ],
    "sg:phone":"+1 703 451 0875",
    "sg:postcode":"22150",
    "sg:province":"VA",
    "wof:name":"Music & Arts Ctr",
    "wof:placetype":"venue"
},
  "geometry": {"coordinates":[-77.183256,38.780645],"type":"Point"}
}