{
  "type": "Feature",
  "properties": {
    "addr:full":"6360 Chatham Rd Martinsville VA 24112",
    "addr:housenumber":"6360",
    "addr:postcode":"24112",
    "addr:street":"Chatham Rd",
    "iso:country":"US",
    "sg:address":"6360 Chatham Rd",
    "sg:city":"Martinsville",
    "sg:classifiers":[
        {
            "category":"Food & Beverages",
            "subcategory":"Groceries & Convenience Stores",
            "type":"Retail Goods"
        }
    ],
    "sg:phone":"+1 276 650 8641",
    "sg:postcode":"24112",
    "sg:province":"VA",
    "wof:name":"Leatherwood Grocery",
    "wof:placetype":"venue"
},
  "geometry": {"coordinates":[-79.747105,36.738271],"type":"Point"}
}