{
  "type": "Feature",
  "properties": {
    "addr:full":"611 Fairview Cir Woodstock VA 22664",
    "addr:housenumber":"611",
    "addr:postcode":"22664",
    "addr:street":"Fairview Cir",
    "iso:country":"US",
    "sg:address":"611 Fairview Cir",
    "sg:city":"Woodstock",
    "sg:classifiers":[
        {
            "category":"Professional",
            "subcategory":"Business Services",
            "type":"Services"
        }
    ],
    "sg:phone":"+1 540 459 2087",
    "sg:postcode":"22664",
    "sg:province":"VA",
    "wof:name":"Advisory Home Inspections LLC",
    "wof:placetype":"venue"
},
  "geometry": {"coordinates":[-78.550673,38.927254],"type":"Point"}
}