{
  "type": "Feature",
  "properties": {
    "iso:country":"US",
    "sg:address":"200 Davis Dr",
    "sg:city":"Sterling",
    "sg:classifiers":[
        {
            "category":"Autos & Motor Vehicles",
            "subcategory":"Auto Supplies",
            "type":"Retail Goods"
        }
    ],
    "sg:phone":"+1 703 433 1394",
    "sg:postcode":"20164",
    "sg:province":"VA",
    "sg:tags":[
        "tire"
    ],
    "sg:website":"www.craventire.com",
    "wof:name":"Craven Tire & Auto",
    "wof:placetype":"venue"
},
  "geometry": {"coordinates":[-77.42003200000001,38.992441],"type":"Point"}
}