{
  "type": "Feature",
  "properties": {
    "addr:full":"14714 Keelers Mill Rd Dewitt VA 23840",
    "addr:housenumber":"14714",
    "addr:postcode":"23840",
    "addr:street":"Keelers Mill Rd",
    "iso:country":"US",
    "sg:address":"14714 Keelers Mill Rd",
    "sg:city":"Dewitt",
    "sg:classifiers":[
        {
            "category":"Farming",
            "subcategory":"Dairy Farm",
            "type":"Manufacturing & Wholesale Goods"
        }
    ],
    "sg:phone":"+1 804 469 3670",
    "sg:postcode":"23840",
    "sg:province":"VA",
    "wof:name":"Leesmere Farm",
    "wof:placetype":"venue"
},
  "geometry": {"coordinates":[-77.637265,37.069113],"type":"Point"}
}