{
  "type": "Feature",
  "properties": {
    "iso:country":"US",
    "sg:address":"6867 Elm St",
    "sg:city":"Mc Lean",
    "sg:classifiers":[
        {
            "category":"Organizations",
            "subcategory":"Membership Organization",
            "type":"Services"
        }
    ],
    "sg:phone":"+1 703 448 8323",
    "sg:postcode":"22101",
    "sg:province":"VA",
    "sg:tags":[
        "laboratory",
        "photofinishing"
    ],
    "wof:name":"Verhalen & Associates",
    "wof:placetype":"venue"
},
  "geometry": {"coordinates":[-77.18154199999999,38.937005],"type":"Point"}
}