{
  "type": "Feature",
  "properties": {
    "addr:full":"2670 Bumpass Rd Bumpass VA 23015",
    "addr:postcode":"2670;23015",
    "addr:street":"Bumpass Rd",
    "iso:country":"US",
    "sg:address":"2670 Bumpass Rd",
    "sg:city":"Bumpass",
    "sg:classifiers":[
        {
            "category":"Wholesale",
            "subcategory":"Medical Equipment & Supplies",
            "type":"Manufacturing & Wholesale Goods"
        },
        {
            "category":"Wholesale",
            "subcategory":"Durable Goods & Equipment",
            "type":"Manufacturing & Wholesale Goods"
        }
    ],
    "sg:phone":"+1 540 872 3464",
    "sg:postcode":"23015",
    "sg:province":"VA",
    "sg:tags":[
        "microscope",
        "balance",
        "sales",
        "for"
    ],
    "wof:name":"Dominion Microscope Inc of VA",
    "wof:placetype":"venue"
},
  "geometry": {"coordinates":[-77.71777299999999,37.97506],"type":"Point"}
}