{
  "type": "Feature",
  "properties": {
    "iso:country":"US",
    "sg:address":"1908 Whittles Wood Rd",
    "sg:city":"Williamsburg",
    "sg:classifiers":[
        {
            "category":"Professional",
            "subcategory":"Business Services",
            "type":"Services"
        }
    ],
    "sg:phone":"+1 757 258 9128",
    "sg:postcode":"23185",
    "sg:province":"VA",
    "wof:name":"Steger & Associates Inc",
    "wof:placetype":"venue"
},
  "geometry": {"coordinates":[-76.855079,37.248235],"type":"Point"}
}