{
  "type": "Feature",
  "properties": {
    "iso:country":"US",
    "sg:address":"521 Singhass Rd",
    "sg:city":"Winchester",
    "sg:classifiers":[
        {
            "category":"Professional",
            "subcategory":"Management & Consulting",
            "type":"Services"
        }
    ],
    "sg:phone":"+1 540 877 2980",
    "sg:postcode":"22602",
    "sg:province":"VA",
    "sg:tags":[
        "business"
    ],
    "wof:name":"Hartwix & Associates",
    "wof:placetype":"venue"
},
  "geometry": {"coordinates":[-78.24973799999999,39.182965],"type":"Point"}
}