{
  "type": "Feature",
  "properties": {
    "addr:full":"165 Camp Creek Pkwy Gordonsville VA 22942",
    "addr:housenumber":"165",
    "addr:postcode":"22942",
    "addr:street":"Camp Creek Pkwy",
    "iso:country":"US",
    "sg:address":"165 Camp Creek Pkwy",
    "sg:city":"Gordonsville",
    "sg:classifiers":[
        {
            "category":"Home & Garden",
            "subcategory":"Household Appliances",
            "type":"Retail Goods"
        },
        {
            "category":"Home & Garden",
            "subcategory":"Building Materials",
            "type":"Retail Goods"
        },
        {
            "category":"Building & Trades",
            "subcategory":"Construction",
            "type":"Services"
        }
    ],
    "sg:phone":"+1 877 471 9739",
    "sg:postcode":"22942",
    "sg:province":"VA",
    "sg:tags":[
        "repair",
        "major",
        "heater",
        "improvement",
        "water",
        "maintenance"
    ],
    "sg:website":"http://www.lowes.com",
    "wof:name":"Lowe's? Home Improvement",
    "wof:placetype":"venue"
},
  "geometry": {"coordinates":[-78.20807499999999,37.979157],"type":"Point"}
}