{
  "type": "Feature",
  "properties": {
    "addr:full":"124 E Laurel Ave Damascus VA 24236",
    "addr:housenumber":"124",
    "addr:postcode":"24236",
    "addr:street":"E Laurel Ave",
    "iso:country":"US",
    "sg:address":"124 E Laurel Ave",
    "sg:city":"Damascus",
    "sg:classifiers":[
        {
            "category":"Shopping",
            "type":"Retail Goods"
        }
    ],
    "sg:phone":"+1 276 475 3530",
    "sg:postcode":"24236",
    "sg:province":"VA",
    "sg:tags":[
        "art",
        "gallery",
        "dealer"
    ],
    "wof:name":"Grapevine Gallery",
    "wof:placetype":"venue"
},
  "geometry": {"coordinates":[-81.788387,36.634757],"type":"Point"}
}