{
  "type": "Feature",
  "properties": {
    "addr:full":"3013 Hickory Grove Ct Fairfax VA 22031",
    "addr:housenumber":"3013",
    "addr:postcode":"22031",
    "addr:street":"Hickory Grove Ct",
    "iso:country":"US",
    "sg:address":"3013 Hickory Grove Ct",
    "sg:city":"Fairfax",
    "sg:classifiers":[
        {
            "category":"Shopping",
            "subcategory":"Jewelry",
            "type":"Retail Goods"
        }
    ],
    "sg:phone":"+1 703 861 6151",
    "sg:postcode":"22031",
    "sg:province":"VA",
    "sg:tags":[
        "designer"
    ],
    "wof:name":"Dmitry Samoylin Models",
    "wof:placetype":"venue"
},
  "geometry": {"coordinates":[-77.27127,38.871451],"type":"Point"}
}