{
  "type": "Feature",
  "properties": {
    "iso:country":"US",
    "sg:address":"6700 Newman Rd",
    "sg:city":"Clifton",
    "sg:classifiers":[
        {
            "category":"Building & Trades",
            "subcategory":"Landscaping Services",
            "type":"Services"
        }
    ],
    "sg:phone":"+1 703 830 8147",
    "sg:postcode":"20124",
    "sg:province":"VA",
    "sg:tags":[
        "landscape"
    ],
    "wof:name":"Hanan Landscaping",
    "wof:placetype":"venue"
},
  "geometry": {"coordinates":[-77.37836299999999,38.79101],"type":"Point"}
}