{
  "type": "Feature",
  "properties": {
    "addr:full":"44 Kingston Dr Daleville VA 24083",
    "addr:housenumber":"44",
    "addr:postcode":"24083",
    "addr:street":"Kingston Dr",
    "iso:country":"US",
    "sg:address":"44 Kingston Dr",
    "sg:city":"Daleville",
    "sg:classifiers":[
        {
            "category":"Wholesale",
            "subcategory":"Home Furnishings",
            "type":"Manufacturing & Wholesale Goods"
        }
    ],
    "sg:phone":"+1 540 797 5023",
    "sg:postcode":"24083",
    "sg:province":"VA",
    "wof:name":"Custom Metal Creations",
    "wof:placetype":"venue"
},
  "geometry": {"coordinates":[-79.909916,37.396259],"type":"Point"}
}