{
  "type": "Feature",
  "properties": {
    "iso:country":"US",
    "sg:address":"4401 Ford Ave",
    "sg:city":"Alexandria",
    "sg:classifiers":[
        {
            "category":"Professional",
            "subcategory":"Engineering",
            "type":"Services"
        }
    ],
    "sg:phone":"+1 703 312 2319",
    "sg:postcode":"22302",
    "sg:province":"VA",
    "sg:tags":[
        "engineer"
    ],
    "wof:name":"PRC Inc",
    "wof:placetype":"venue"
},
  "geometry": {"coordinates":[-77.10521799999999,38.83685],"type":"Point"}
}