{
  "type": "Feature",
  "properties": {
    "iso:country":"US",
    "sg:address":"4720 Business Dr",
    "sg:city":"Fredericksburg",
    "sg:classifiers":[
        {
            "category":"Freight",
            "type":"Transportation"
        }
    ],
    "sg:phone":"+1 540 898 8288",
    "sg:postcode":"22408",
    "sg:province":"VA",
    "sg:tags":[
        "commercial",
        "storage",
        "special"
    ],
    "wof:name":"Storage 2000 Spotsylvania",
    "wof:placetype":"venue"
},
  "geometry": {"coordinates":[-77.49881600000001,38.247689],"type":"Point"}
}