{
  "type": "Feature",
  "properties": {
    "iso:country":"US",
    "sg:address":"12528 Dillingham Sq",
    "sg:city":"Woodbridge",
    "sg:classifiers":[
        {
            "category":"Restaurant",
            "type":"Food & Drink"
        }
    ],
    "sg:menulink":"http://www.allmenus.com/va/occoquan/116343-quiznos-sub/menu/",
    "sg:phone":"+1 703 590 7940",
    "sg:postcode":"22192",
    "sg:province":"VA",
    "sg:tags":[
        "wrap",
        "american",
        "sandwich"
    ],
    "wof:name":"Quiznos Sub",
    "wof:placetype":"venue"
},
  "geometry": {"coordinates":[-77.319436,38.682975],"type":"Point"}
}