{
  "type": "Feature",
  "properties": {
    "addr:full":"280 Sky Chalet Ln Basye VA 22810",
    "addr:housenumber":"280",
    "addr:postcode":"22810",
    "addr:street":"Sky Chalet Ln",
    "iso:country":"US",
    "sg:address":"280 Sky Chalet Ln",
    "sg:city":"Basye",
    "sg:classifiers":[
        {
            "category":"Travel",
            "subcategory":"Hotels & Motels",
            "type":"Entertainment"
        }
    ],
    "sg:phone":"+1 540 856 2147",
    "sg:postcode":"22810",
    "sg:province":"VA",
    "sg:tags":[
        "breakfast",
        "accommodation",
        "bed"
    ],
    "wof:name":"Sky Chalet Mountain Lodges",
    "wof:placetype":"venue"
},
  "geometry": {"coordinates":[-78.77341199999999,38.805515],"type":"Point"}
}