{
  "type": "Feature",
  "properties": {
    "iso:country":"US",
    "sg:address":"11790 Jefferson Ave",
    "sg:city":"Newport News",
    "sg:classifiers":[
        {
            "category":"Health Services",
            "subcategory":"Health Practitioner",
            "type":"Services"
        }
    ],
    "sg:phone":"+1 757 873 8701",
    "sg:postcode":"23606",
    "sg:province":"VA",
    "wof:name":"Acupunctr-Cute Pain Specialist",
    "wof:placetype":"venue"
},
  "geometry": {"coordinates":[-76.479738,37.082058],"type":"Point"}
}