{
  "type": "Feature",
  "properties": {
    "addr:full":"3704 Old Forest Rd Lynchburg VA 24501",
    "addr:housenumber":"3704",
    "addr:postcode":"24501",
    "addr:street":"Old Forest Rd",
    "iso:country":"US",
    "sg:address":"3704 Old Forest Rd",
    "sg:city":"Lynchburg",
    "sg:classifiers":[
        {
            "category":"Health Services",
            "subcategory":"Medical Lab",
            "type":"Services"
        }
    ],
    "sg:phone":"+1 434 385 0115",
    "sg:postcode":"24501",
    "sg:province":"VA",
    "sg:tags":[
        "laboratory",
        "dental"
    ],
    "wof:name":"Paradigm Dental Lab",
    "wof:placetype":"venue"
},
  "geometry": {"coordinates":[-79.220124,37.405962],"type":"Point"}
}