{
  "type": "Feature",
  "properties": {
    "addr:full":"9705 Rolling Ridge Dr Fairfax Station VA 22039",
    "addr:housenumber":"9705",
    "addr:postcode":"22039",
    "addr:street":"Rolling Ridge Dr",
    "iso:country":"US",
    "sg:address":"9705 Rolling Ridge Dr",
    "sg:city":"Fairfax Station",
    "sg:classifiers":[
        {
            "category":"Professional",
            "subcategory":"Computer Services",
            "type":"Services"
        }
    ],
    "sg:phone":"+1 703 455 4952",
    "sg:postcode":"22039",
    "sg:province":"VA",
    "sg:tags":[
        "management",
        "technology"
    ],
    "wof:name":"Brinson Technologies Inc",
    "wof:placetype":"venue"
},
  "geometry": {"coordinates":[-77.28227,38.757307],"type":"Point"}
}