{
  "type": "Feature",
  "properties": {
    "addr:full":"15095 Little Dry River Rd Fulks Run VA 22830",
    "addr:housenumber":"15095",
    "addr:postcode":"22830",
    "addr:street":"Little Dry River Rd",
    "iso:country":"US",
    "sg:address":"15095 Little Dry River Rd",
    "sg:city":"Fulks Run",
    "sg:classifiers":[
        {
            "category":"Retail",
            "subcategory":"Animal Services",
            "type":"Services"
        }
    ],
    "sg:phone":"+1 540 289 7020",
    "sg:postcode":"22830",
    "sg:province":"VA",
    "wof:name":"Happy Tails Boutique",
    "wof:placetype":"venue"
},
  "geometry": {"coordinates":[-78.953643,38.653733],"type":"Point"}
}