{
  "type": "Feature",
  "properties": {
    "addr:full":"1148 Poor Farm Rd SE Floyd VA 24091",
    "addr:housenumber":"1148",
    "addr:postcode":"24091",
    "addr:street":"Poor Farm Rd Se",
    "iso:country":"US",
    "sg:address":"1148 Poor Farm Rd SE",
    "sg:city":"Floyd",
    "sg:classifiers":[
        {
            "category":"Organizations",
            "subcategory":"Religious Organization",
            "type":"Services"
        }
    ],
    "sg:phone":"+1 540 745 3172",
    "sg:postcode":"24091",
    "sg:province":"VA",
    "sg:tags":[
        "church"
    ],
    "wof:name":"Little River Missionary",
    "wof:placetype":"venue"
},
  "geometry": {"coordinates":[-80.225194,36.947145],"type":"Point"}
}