{
  "type": "Feature",
  "properties": {
    "addr:full":"200 W Mercury Blvd Hampton VA 23669",
    "addr:housenumber":"200",
    "addr:postcode":"23669",
    "addr:street":"W Mercury Blvd",
    "iso:country":"US",
    "sg:address":"200 W Mercury Blvd",
    "sg:city":"Hampton",
    "sg:classifiers":[
        {
            "category":"Manufacturing",
            "subcategory":"Soap",
            "type":"Manufacturing & Wholesale Goods"
        }
    ],
    "sg:phone":"+1 757 722 3250",
    "sg:postcode":"23669",
    "sg:province":"VA",
    "sg:tags":[
        "detergent"
    ],
    "wof:name":"Soap N Suds",
    "wof:placetype":"venue"
},
  "geometry": {"coordinates":[-76.358549,37.043814],"type":"Point"}
}