{
  "type": "Feature",
  "properties": {
    "addr:full":"3619 Tallwood Ter Falls Church VA 22041",
    "addr:housenumber":"3619",
    "addr:postcode":"22041",
    "addr:street":"Tallwood Ter",
    "iso:country":"US",
    "sg:address":"3619 Tallwood Ter",
    "sg:city":"Falls Church",
    "sg:classifiers":[
        {
            "category":"Professional",
            "type":"Services"
        }
    ],
    "sg:phone":"+1 703 354 4002",
    "sg:postcode":"22041",
    "sg:province":"VA",
    "wof:name":"Family Watch",
    "wof:placetype":"venue"
},
  "geometry": {"coordinates":[-77.16459,38.843788],"type":"Point"}
}