{
  "type": "Feature",
  "properties": {
    "addr:full":"324 E Main St Independence VA 24348",
    "addr:housenumber":"324",
    "addr:postcode":"24348",
    "addr:street":"E Main St",
    "iso:country":"US",
    "sg:address":"324 E Main St",
    "sg:city":"Independence",
    "sg:classifiers":[
        {
            "category":"Real Estate",
            "subcategory":"Real Estate Agent",
            "type":"Services"
        }
    ],
    "sg:phone":"+1 276 773 3333",
    "sg:postcode":"24348",
    "sg:province":"VA",
    "wof:name":"Morton Realty & Auction Co",
    "wof:placetype":"venue"
},
  "geometry": {"coordinates":[-81.14961099999999,36.622428],"type":"Point"}
}