{
  "type": "Feature",
  "properties": {
    "addr:full":"19 Dula St Danville VA 24541",
    "addr:housenumber":"19",
    "addr:postcode":"24541",
    "addr:street":"Dula St",
    "iso:country":"US",
    "sg:address":"19 Dula St",
    "sg:city":"Danville",
    "sg:classifiers":[
        {
            "category":"Organizations",
            "subcategory":"Religious Organization",
            "type":"Services"
        }
    ],
    "sg:phone":"+1 434 797 5214",
    "sg:postcode":"24541",
    "sg:province":"VA",
    "sg:tags":[
        "church"
    ],
    "wof:name":"Trinity Wesleyan Church",
    "wof:placetype":"venue"
},
  "geometry": {"coordinates":[-79.437534,36.56271],"type":"Point"}
}