{
  "type": "Feature",
  "properties": {
    "addr:full":"7903 Tysons Corner Center McLean VA 22101",
    "addr:housenumber":"7903",
    "addr:postcode":"22101",
    "addr:street":"Tysons",
    "iso:country":"US",
    "sg:address":"7903 Tysons Corner Center",
    "sg:city":"McLean",
    "sg:classifiers":[
        {
            "category":"Professional",
            "type":"Services"
        },
        {
            "category":"Shopping",
            "subcategory":"Computers & Home Electronics",
            "type":"Retail Goods"
        }
    ],
    "sg:phone":"+1 703 883 9166",
    "sg:postcode":"22101",
    "sg:province":"VA",
    "sg:website":"www.sprint.com",
    "wof:name":"Sprint Store",
    "wof:placetype":"venue"
},
  "geometry": {"coordinates":[-77.218531,38.915738],"type":"Point"}
}