{
  "type": "Feature",
  "properties": {
    "iso:country":"US",
    "sg:address":"143 Labrook Dr",
    "sg:city":"Richmond",
    "sg:classifiers":[
        {
            "category":"Taxi",
            "type":"Transportation"
        }
    ],
    "sg:phone":"+1 804 218 2642",
    "sg:postcode":"23225",
    "sg:province":"VA",
    "sg:tags":[
        "taxicab"
    ],
    "wof:name":"Unity Cab",
    "wof:placetype":"venue"
},
  "geometry": {"coordinates":[-77.508216,37.506593],"type":"Point"}
}