{
  "type": "Feature",
  "properties": {
    "addr:full":"5416 Mechanicsville Tpke Mechanicsville VA 23111",
    "addr:postcode":"5416;23111",
    "addr:street":"Tpke",
    "iso:country":"US",
    "sg:address":"5416 Mechanicsville Tpke",
    "sg:city":"Mechanicsville",
    "sg:classifiers":[
        {
            "category":"Shopping",
            "type":"Retail Goods"
        }
    ],
    "sg:phone":"+1 804 779 0336",
    "sg:postcode":"23111",
    "sg:province":"VA",
    "sg:tags":[
        "merchandise"
    ],
    "wof:name":"Country Store Of Virginia",
    "wof:placetype":"venue"
},
  "geometry": {"coordinates":[-77.29289,37.630072],"type":"Point"}
}