{
  "type": "Feature",
  "properties": {
    "iso:country":"US",
    "sg:address":"7600 Allman Dr",
    "sg:city":"Annandale",
    "sg:classifiers":[
        {
            "category":"Shopping",
            "subcategory":"Pharmacy",
            "type":"Retail Goods"
        }
    ],
    "sg:phone":"+1 703 750 3095",
    "sg:postcode":"22003",
    "sg:province":"VA",
    "wof:name":"Maria Rozenfeld",
    "wof:placetype":"venue"
},
  "geometry": {"coordinates":[-77.209098,38.829533],"type":"Point"}
}