{
  "type": "Feature",
  "properties": {
    "iso:country":"US",
    "sg:address":"10523 Brevity Dr",
    "sg:city":"Great Falls",
    "sg:classifiers":[
        {
            "category":"Professional",
            "subcategory":"Business Services",
            "type":"Services"
        }
    ],
    "sg:phone":"+1 804 436 9727",
    "sg:postcode":"22066",
    "sg:province":"VA",
    "wof:name":"LCB",
    "wof:placetype":"venue"
},
  "geometry": {"coordinates":[-77.30981800000001,38.983985],"type":"Point"}
}