{
  "type": "Feature",
  "properties": {
    "addr:full":"520 Shoppers World Ct Charlottesville VA 22901",
    "addr:housenumber":"520",
    "addr:postcode":"22901",
    "addr:street":"World Ct",
    "iso:country":"US",
    "sg:address":"520 Shoppers World Ct",
    "sg:city":"Charlottesville",
    "sg:classifiers":[
        {
            "category":"Personal",
            "subcategory":"Massage",
            "type":"Services"
        }
    ],
    "sg:phone":"+1 434 977 3689",
    "sg:postcode":"22901",
    "sg:province":"VA",
    "wof:name":"Massage Envy Charlottesville",
    "wof:placetype":"venue"
},
  "geometry": {"coordinates":[-78.47995299999999,38.0777],"type":"Point"}
}