{
  "type": "Feature",
  "properties": {
    "addr:full":"1986 Lawrenceville Plank Rd Lawrenceville VA 23868",
    "addr:housenumber":"1986",
    "addr:postcode":"23868",
    "addr:street":"Lawrenceville Plank Rd",
    "iso:country":"US",
    "sg:address":"1986 Lawrenceville Plank Rd",
    "sg:city":"Lawrenceville",
    "sg:classifiers":[
        {
            "category":"Professional",
            "subcategory":"Accounting & Tax Preparation",
            "type":"Services"
        }
    ],
    "sg:phone":"+1 434 848 4140",
    "sg:postcode":"23868",
    "sg:province":"VA",
    "sg:tags":[
        "accountant"
    ],
    "wof:name":"A & A Accounting & Tax Svc",
    "wof:placetype":"venue"
},
  "geometry": {"coordinates":[-77.83246200000001,36.766419],"type":"Point"}
}