{
  "type": "Feature",
  "properties": {
    "iso:country":"US",
    "sg:address":"618 Gibson Dr SW",
    "sg:city":"Vienna",
    "sg:classifiers":[
        {
            "category":"Building & Trades",
            "subcategory":"Construction",
            "type":"Services"
        }
    ],
    "sg:phone":"+1 703 938 2901",
    "sg:postcode":"22180",
    "sg:province":"VA",
    "sg:tags":[
        "painter"
    ],
    "wof:name":"M C Painting Contracor's LLC",
    "wof:placetype":"venue"
},
  "geometry": {"coordinates":[-77.268535,38.889141],"type":"Point"}
}