{
  "type": "Feature",
  "properties": {
    "addr:full":"15 Winter Harbor Rd Colonial Beach VA 22443",
    "addr:housenumber":"15",
    "addr:postcode":"22443",
    "addr:street":"Winter Harbor Rd",
    "iso:country":"US",
    "sg:address":"15 Winter Harbor Rd",
    "sg:city":"Colonial Beach",
    "sg:classifiers":[
        {
            "category":"Government",
            "subcategory":"Office",
            "type":"Public Place"
        }
    ],
    "sg:phone":"+1 804 224 9150",
    "sg:postcode":"22443",
    "sg:province":"VA",
    "sg:tags":[
        "state",
        "program"
    ],
    "wof:name":"Transportation Dept",
    "wof:placetype":"venue"
},
  "geometry": {"coordinates":[-76.941712,38.16258],"type":"Point"}
}