{
  "type": "Feature",
  "properties": {
    "addr:full":"6325 Richmond Hwy Alexandria VA 22306",
    "addr:housenumber":"6325",
    "addr:postcode":"22306",
    "addr:street":"Richmond Hwy",
    "iso:country":"US",
    "sg:address":"6325 Richmond Hwy",
    "sg:city":"Alexandria",
    "sg:classifiers":[
        {
            "category":"Restaurant",
            "type":"Food & Drink"
        }
    ],
    "sg:phone":"+1 703 765 2785",
    "sg:postcode":"22306",
    "sg:province":"VA",
    "sg:tags":[
        "family"
    ],
    "wof:name":"Ranch House Restaurant",
    "wof:placetype":"venue"
},
  "geometry": {"coordinates":[-77.079494,38.779443],"type":"Point"}
}