{
  "type": "Feature",
  "properties": {
    "addr:full":"1315 Euclid Ave Bristol VA 24201",
    "addr:housenumber":"1315",
    "addr:postcode":"24201",
    "addr:street":"Euclid Ave",
    "iso:country":"US",
    "sg:address":"1315 Euclid Ave",
    "sg:city":"Bristol",
    "sg:classifiers":[
        {
            "category":"Banks & Credit Unions",
            "subcategory":"Bank",
            "type":"Services"
        }
    ],
    "sg:phone":"+1 276 466 4673",
    "sg:postcode":"24201",
    "sg:province":"VA",
    "sg:tags":[
        "cashing",
        "check"
    ],
    "wof:name":"Check Into Cash",
    "wof:placetype":"venue"
},
  "geometry": {"coordinates":[-82.192279,36.602738],"type":"Point"}
}