{
  "type": "Feature",
  "properties": {
    "addr:full":"1755 Virginia Ave Martinsville VA 24078",
    "addr:housenumber":"1755",
    "addr:postcode":"24078",
    "addr:street":"Virginia Ave",
    "iso:country":"US",
    "sg:address":"1755 Virginia Ave",
    "sg:city":"Martinsville",
    "sg:classifiers":[
        {
            "category":"Restaurant",
            "type":"Food & Drink"
        }
    ],
    "sg:phone":"+1 276 638 5411",
    "sg:postcode":"24078",
    "sg:province":"VA",
    "wof:name":"Macarena's Seafood Bar & Grill",
    "wof:placetype":"venue"
},
  "geometry": {"coordinates":[-79.907214,36.703505],"type":"Point"}
}