{
  "type": "Feature",
  "properties": {
    "addr:full":"415 Turlington Rd Newport News VA 23606",
    "addr:housenumber":"415",
    "addr:postcode":"23606",
    "addr:street":"Turlington Rd",
    "iso:country":"US",
    "sg:address":"415 Turlington Rd",
    "sg:city":"Newport News",
    "sg:classifiers":[
        {
            "category":"Building & Trades",
            "subcategory":"Landscaping Services",
            "type":"Services"
        }
    ],
    "sg:phone":"+1 757 930 0204",
    "sg:postcode":"23606",
    "sg:province":"VA",
    "sg:tags":[
        "landscape",
        "contractor"
    ],
    "wof:name":"Lonegran Lawns & Gardens",
    "wof:placetype":"venue"
},
  "geometry": {"coordinates":[-76.49793699999999,37.083151],"type":"Point"}
}