{
  "type": "Feature",
  "properties": {
    "addr:full":"21219 Edgewood Ct Sterling VA 20165",
    "addr:housenumber":"21219",
    "addr:postcode":"20165",
    "addr:street":"Edgewood Ct",
    "iso:country":"US",
    "sg:address":"21219 Edgewood Ct",
    "sg:city":"Sterling",
    "sg:classifiers":[
        {
            "category":"Professional",
            "subcategory":"Computer Services",
            "type":"Services"
        }
    ],
    "sg:phone":"+1 703 421 7652",
    "sg:postcode":"20165",
    "sg:province":"VA",
    "sg:tags":[
        "engineering"
    ],
    "wof:name":"Signal Science LLC",
    "wof:placetype":"venue"
},
  "geometry": {"coordinates":[-77.364194,39.028061],"type":"Point"}
}