{
  "type": "Feature",
  "properties": {
    "iso:country":"US",
    "sg:address":"3226 Graham Rd",
    "sg:city":"Falls Church",
    "sg:classifiers":[
        {
            "category":"Social Services",
            "type":"Services"
        }
    ],
    "sg:phone":"+1 703 208 1932",
    "sg:postcode":"22042",
    "sg:province":"VA",
    "wof:name":"Volunteers of America Inc",
    "wof:placetype":"venue"
},
  "geometry": {"coordinates":[-77.192269,38.859146],"type":"Point"}
}