{
  "type": "Feature",
  "properties": {
    "addr:full":"5500 Wise Norton Rd Wise VA 24293",
    "addr:housenumber":"5500",
    "addr:postcode":"24293",
    "addr:street":"Wise Norton Rd",
    "iso:country":"US",
    "sg:address":"5500 Wise Norton Rd",
    "sg:city":"Wise",
    "sg:classifiers":[
        {
            "category":"Mining & Drilling",
            "type":"Manufacturing & Wholesale Goods"
        }
    ],
    "sg:phone":"+1 276 679 2628",
    "sg:postcode":"24293",
    "sg:province":"VA",
    "sg:tags":[
        "coal",
        "shipping"
    ],
    "sg:website":"www.barnettecontractors.com",
    "wof:name":"Barnette Contractors",
    "wof:placetype":"venue"
},
  "geometry": {"coordinates":[-82.59905500000001,36.961256],"type":"Point"}
}