{
  "type": "Feature",
  "properties": {
    "addr:full":"14275 Uniform Dr Centreville VA 20121",
    "addr:postcode":"14275;20121",
    "addr:street":"Uniform Dr",
    "iso:country":"US",
    "sg:address":"14275 Uniform Dr",
    "sg:city":"Centreville",
    "sg:classifiers":[
        {
            "category":"Recreation",
            "type":"Entertainment"
        }
    ],
    "sg:phone":"+1 703 968 7505",
    "sg:postcode":"20121",
    "sg:province":"VA",
    "wof:name":"Center Ridge Recreation Center",
    "wof:placetype":"venue"
},
  "geometry": {"coordinates":[-77.441728,38.827197],"type":"Point"}
}