{
  "type": "Feature",
  "properties": {
    "addr:full":"300 Oyster Point Rd Newport News VA 23602",
    "addr:housenumber":"300",
    "addr:postcode":"23602",
    "addr:street":"Oyster Point Rd",
    "iso:country":"US",
    "sg:address":"300 Oyster Point Rd",
    "sg:city":"Newport News",
    "sg:classifiers":[
        {
            "category":"Cinema",
            "subcategory":"Movie Rental",
            "type":"Entertainment"
        }
    ],
    "sg:phone":"+1 757 249 9010",
    "sg:postcode":"23602",
    "sg:province":"VA",
    "sg:tags":[
        "leasing",
        "video",
        "disc",
        "tape"
    ],
    "wof:name":"Blockbuster Video",
    "wof:placetype":"venue"
},
  "geometry": {"coordinates":[-76.506074,37.106018],"type":"Point"}
}