{
  "type": "Feature",
  "properties": {
    "addr:full":"2203 Portlock Rd Chesapeake VA 23324",
    "addr:housenumber":"2203",
    "addr:postcode":"23324",
    "addr:street":"Portlock Rd",
    "iso:country":"US",
    "sg:address":"2203 Portlock Rd",
    "sg:city":"Chesapeake",
    "sg:classifiers":[
        {
            "category":"Personal",
            "subcategory":"Barber",
            "type":"Services"
        }
    ],
    "sg:phone":"+1 757 494 5941",
    "sg:postcode":"23324",
    "sg:province":"VA",
    "wof:name":"Perfect Cut Barber Shop",
    "wof:placetype":"venue"
},
  "geometry": {"coordinates":[-76.26624,36.7857],"type":"Point"}
}