{
  "type": "Feature",
  "properties": {
    "addr:full":"156 Cherry Hill Dr Stafford VA 22556",
    "addr:housenumber":"156",
    "addr:postcode":"22556",
    "addr:street":"Cherry Hill Dr",
    "iso:country":"US",
    "sg:address":"156 Cherry Hill Dr",
    "sg:city":"Stafford",
    "sg:classifiers":[
        {
            "category":"Professional",
            "subcategory":"Management & Consulting",
            "type":"Services"
        }
    ],
    "sg:phone":"+1 540 429 2215",
    "sg:postcode":"22556",
    "sg:province":"VA",
    "sg:tags":[
        "consultant"
    ],
    "wof:name":"Windsor Consulting & Professional Services",
    "wof:placetype":"venue"
},
  "geometry": {"coordinates":[-77.495921,38.484589],"type":"Point"}
}