{
  "type": "Feature",
  "properties": {
    "iso:country":"US",
    "sg:address":"8453 Tyco Rd Ste A",
    "sg:city":"Vienna",
    "sg:classifiers":[
        {
            "category":"Retail",
            "subcategory":"Laundry & Dry Cleaning",
            "type":"Services"
        }
    ],
    "sg:phone":"+1 703 448 0007",
    "sg:postcode":"22182",
    "sg:province":"VA",
    "wof:name":"Tyco Cleaners",
    "wof:placetype":"venue"
},
  "geometry": {"coordinates":[-77.238102,38.930862],"type":"Point"}
}