{
  "type": "Feature",
  "properties": {
    "addr:full":"5671 Derby Ct Alexandria VA 22311",
    "addr:housenumber":"5671",
    "addr:postcode":"22311",
    "addr:street":"Derby Ct",
    "iso:country":"US",
    "sg:address":"5671 Derby Ct",
    "sg:city":"Alexandria",
    "sg:classifiers":[
        {
            "category":"Building & Trades",
            "subcategory":"Construction",
            "type":"Services"
        }
    ],
    "sg:phone":"+1 703 309 4232",
    "sg:postcode":"22311",
    "sg:province":"VA",
    "sg:tags":[
        "house"
    ],
    "wof:name":"Kalev Kruuk",
    "wof:placetype":"venue"
},
  "geometry": {"coordinates":[-77.12997,38.828198],"type":"Point"}
}