{
  "type": "Feature",
  "properties": {
    "iso:country":"US",
    "sg:address":"600 Massie Rd",
    "sg:city":"Charlottesville",
    "sg:classifiers":[
        {
            "category":"Manufacturing",
            "subcategory":"Printing",
            "type":"Manufacturing & Wholesale Goods"
        }
    ],
    "sg:phone":"+1 877 327 7226",
    "sg:postcode":"22903",
    "sg:province":"VA",
    "wof:name":"Document Automation & Prod Svc",
    "wof:placetype":"venue"
},
  "geometry": {"coordinates":[-78.508134,38.052251],"type":"Point"}
}