{
  "type": "Feature",
  "properties": {
    "addr:full":"6304 Leesburg Pike Falls Church VA 22044",
    "addr:housenumber":"6304",
    "addr:postcode":"22044",
    "addr:street":"Leesburg Pike",
    "iso:country":"US",
    "sg:address":"6304 Leesburg Pike",
    "sg:city":"Falls Church",
    "sg:classifiers":[
        {
            "category":"Restaurant",
            "type":"Food & Drink"
        }
    ],
    "sg:phone":"+1 703 533 9555",
    "sg:postcode":"22044",
    "sg:province":"VA",
    "wof:name":"Golden Diner",
    "wof:placetype":"venue"
},
  "geometry": {"coordinates":[-77.15492500000001,38.871109],"type":"Point"}
}