{
  "type": "Feature",
  "properties": {
    "addr:full":"4501 Arlington Blvd Apt 120 Arlington VA 22203",
    "addr:housenumber":"4501;120",
    "addr:postcode":"22203",
    "addr:street":"Arlington Blvd Apt",
    "iso:country":"US",
    "sg:address":"4501 Arlington Blvd Apt 120",
    "sg:city":"Arlington",
    "sg:classifiers":[
        {
            "category":"Health Services",
            "subcategory":"Doctor",
            "type":"Services"
        }
    ],
    "sg:phone":"+1 703 841 1133",
    "sg:postcode":"22203",
    "sg:province":"VA",
    "sg:tags":[
        "medicine",
        "internal"
    ],
    "wof:name":"Hunt Lillian B MD PC",
    "wof:placetype":"venue"
},
  "geometry": {"coordinates":[-77.107803,38.869099],"type":"Point"}
}