{
  "type": "Feature",
  "properties": {
    "addr:full":"485 Red Bud Rd Strasburg VA 22657",
    "addr:housenumber":"485",
    "addr:postcode":"22657",
    "addr:street":"Red Bud Rd",
    "iso:country":"US",
    "sg:address":"485 Red Bud Rd",
    "sg:city":"Strasburg",
    "sg:phone":"+1 540 465 8649",
    "sg:postcode":"22657",
    "sg:province":"VA",
    "sg:tags":[
        "farm",
        "field",
        "corn",
        "crop"
    ],
    "wof:name":"Gerald Kidwell",
    "wof:placetype":"venue"
},
  "geometry": {"coordinates":[-78.36853499999999,39.013781],"type":"Point"}
}