{
  "type": "Feature",
  "properties": {
    "addr:full":"7325 Beaufont Spring Dr Richmond VA 23225",
    "addr:housenumber":"7325",
    "addr:postcode":"23225",
    "addr:street":"Beaufont Spring Dr",
    "iso:country":"US",
    "sg:address":"7325 Beaufont Spring Dr",
    "sg:city":"Richmond",
    "sg:classifiers":[
        {
            "category":"Professional",
            "subcategory":"Employment Agencies",
            "type":"Services"
        }
    ],
    "sg:phone":"+1 804 323 0800",
    "sg:postcode":"23225",
    "sg:province":"VA",
    "sg:tags":[
        "datum",
        "help",
        "supply"
    ],
    "wof:name":"Broughton Systems",
    "wof:placetype":"venue"
},
  "geometry": {"coordinates":[-77.529579,37.509437],"type":"Point"}
}