{
  "type": "Feature",
  "properties": {
    "addr:full":"22169 Tidewater Trl Rappahannock Academy VA 22538",
    "addr:housenumber":"22169",
    "addr:postcode":"22538",
    "addr:street":"Tidewater Trl;Academy",
    "iso:country":"US",
    "sg:address":"22169 Tidewater Trl",
    "sg:city":"Rappahannock Academy",
    "sg:classifiers":[
        {
            "category":"Shopping",
            "subcategory":"Discount & Variety Stores",
            "type":"Retail Goods"
        }
    ],
    "sg:phone":"+1 804 742 5210",
    "sg:postcode":"22538",
    "sg:province":"VA",
    "sg:tags":[
        "merchandise",
        "general"
    ],
    "wof:name":"Bettys Inn",
    "wof:placetype":"venue"
},
  "geometry": {"coordinates":[-77.259714,38.172544],"type":"Point"}
}