{
  "type": "Feature",
  "properties": {
    "addr:full":"512 S Braddock St Winchester VA 22601",
    "addr:housenumber":"512",
    "addr:postcode":"22601",
    "addr:street":"S Braddock St",
    "iso:country":"US",
    "sg:address":"512 S Braddock St",
    "sg:city":"Winchester",
    "sg:classifiers":[
        {
            "category":"Social Services",
            "subcategory":"Adult Care",
            "type":"Services"
        }
    ],
    "sg:phone":"+1 540 662 8877",
    "sg:postcode":"22601",
    "sg:province":"VA",
    "sg:tags":[
        "home",
        "group"
    ],
    "wof:name":"Lord Fairfax House",
    "wof:placetype":"venue"
},
  "geometry": {"coordinates":[-78.16876999999999,39.180012],"type":"Point"}
}