{
  "type": "Feature",
  "properties": {
    "iso:country":"US",
    "sg:address":"1823 N Hamilton St",
    "sg:city":"Richmond",
    "sg:classifiers":[
        {
            "category":"Wholesale",
            "subcategory":"Machinery & Supplies",
            "type":"Manufacturing & Wholesale Goods"
        }
    ],
    "sg:phone":"+1 888 729 2334",
    "sg:postcode":"23230",
    "sg:province":"VA",
    "wof:name":"A E B I-North America Inc",
    "wof:placetype":"venue"
},
  "geometry": {"coordinates":[-77.478888,37.570509],"type":"Point"}
}