{
  "type": "Feature",
  "properties": {
    "addr:full":"3157 Adam Keeling Rd Virginia Beach VA 23454",
    "addr:housenumber":"3157",
    "addr:postcode":"23454",
    "addr:street":"Adam Keeling Rd",
    "iso:country":"US",
    "sg:address":"3157 Adam Keeling Rd",
    "sg:city":"Virginia Beach",
    "sg:classifiers":[
        {
            "category":"Health Services",
            "subcategory":"Doctor",
            "type":"Services"
        }
    ],
    "sg:phone":"+1 757 496 3960",
    "sg:postcode":"23454",
    "sg:province":"VA",
    "sg:tags":[
        "physician",
        "surgeon"
    ],
    "wof:name":"Glenn R Carwell MD",
    "wof:placetype":"venue"
},
  "geometry": {"coordinates":[-76.076764,36.902514],"type":"Point"}
}