{
  "type": "Feature",
  "properties": {
    "addr:full":"8249 Backlick Rd Ste D Lorton VA 22079",
    "addr:housenumber":"8249",
    "addr:postcode":"22079",
    "addr:street":"Backlick Rd Ste D",
    "iso:country":"US",
    "sg:address":"8249 Backlick Rd Ste D",
    "sg:city":"Lorton",
    "sg:classifiers":[
        {
            "category":"Retail",
            "subcategory":"Auto Repair",
            "type":"Services"
        }
    ],
    "sg:phone":"+1 703 550 8818",
    "sg:postcode":"22079",
    "sg:province":"VA",
    "sg:tags":[
        "body",
        "automobile",
        "painting",
        "repairing"
    ],
    "sg:website":"http://eurosportautobody.com",
    "wof:name":"Euro Sport Auto Body",
    "wof:placetype":"venue"
},
  "geometry": {"coordinates":[-77.188671,38.730623],"type":"Point"}
}