{
  "type": "Feature",
  "properties": {
    "addr:full":"1011 Middle School Cir Halifax VA 24592",
    "addr:housenumber":"1011",
    "addr:postcode":"24592",
    "addr:street":"Middle School Cir",
    "iso:country":"US",
    "sg:address":"1011 Middle School Cir",
    "sg:city":"Halifax",
    "sg:classifiers":[
        {
            "category":"Government",
            "subcategory":"Office",
            "type":"Public Place"
        }
    ],
    "sg:phone":"+1 434 572 4154",
    "sg:postcode":"24592",
    "sg:province":"VA",
    "wof:name":"Halifax County Project Idea",
    "wof:placetype":"venue"
},
  "geometry": {"coordinates":[-78.915818,36.723818],"type":"Point"}
}