{
  "type": "Feature",
  "properties": {
    "addr:full":"2304 Kenstock Dr Virginia Beach VA 23454",
    "addr:housenumber":"2304",
    "addr:postcode":"23454",
    "addr:street":"Kenstock Dr",
    "iso:country":"US",
    "sg:address":"2304 Kenstock Dr",
    "sg:city":"Virginia Beach",
    "sg:classifiers":[
        {
            "category":"Organizations",
            "subcategory":"Membership Organization",
            "type":"Services"
        }
    ],
    "sg:phone":"+1 757 463 6312",
    "sg:postcode":"23454",
    "sg:province":"VA",
    "wof:name":"Young Life of Virginia Beach",
    "wof:placetype":"venue"
},
  "geometry": {"coordinates":[-76.049735,36.849637],"type":"Point"}
}