{
  "type": "Feature",
  "properties": {
    "iso:country":"US",
    "sg:address":"944 Alma Dr",
    "sg:city":"Norfolk",
    "sg:classifiers":[
        {
            "category":"Building & Trades",
            "subcategory":"Construction",
            "type":"Services"
        }
    ],
    "sg:phone":"+1 757 588 6092",
    "sg:postcode":"23518",
    "sg:province":"VA",
    "sg:tags":[
        "house"
    ],
    "wof:name":"Jim Allen Home Improvements",
    "wof:placetype":"venue"
},
  "geometry": {"coordinates":[-76.242299,36.918934],"type":"Point"}
}