{
  "type": "Feature",
  "properties": {
    "addr:full":"2904 13th St S Arlington VA 22204",
    "addr:housenumber":"2904",
    "addr:postcode":"22204",
    "addr:street":"13Th St S",
    "iso:country":"US",
    "sg:address":"2904 13th St S",
    "sg:city":"Arlington",
    "sg:classifiers":[
        {
            "category":"Social Services",
            "type":"Services"
        }
    ],
    "sg:phone":"+1 703 685 2273",
    "sg:postcode":"22204",
    "sg:province":"VA",
    "wof:name":"Agape",
    "wof:placetype":"venue"
},
  "geometry": {"coordinates":[-77.08644200000001,38.860041],"type":"Point"}
}