{
  "type": "Feature",
  "properties": {
    "iso:country":"US",
    "sg:address":"185 Reservoir Dr",
    "sg:city":"Stanardsville",
    "sg:classifiers":[
        {
            "category":"Mining & Drilling",
            "type":"Manufacturing & Wholesale Goods"
        }
    ],
    "sg:phone":"+1 434 990 9150",
    "sg:postcode":"22973",
    "sg:province":"VA",
    "sg:tags":[
        "stone"
    ],
    "wof:name":"Luck Stone",
    "wof:placetype":"venue"
},
  "geometry": {"coordinates":[-78.447406,38.296731],"type":"Point"}
}