{
  "type": "Feature",
  "properties": {
    "addr:full":"847 Whann Ave Mc Lean VA 22101",
    "addr:housenumber":"847",
    "addr:postcode":"22101",
    "addr:street":"Whann Ave Mc Lean",
    "iso:country":"US",
    "sg:address":"847 Whann Ave",
    "sg:city":"Mc Lean",
    "sg:classifiers":[
        {
            "category":"Communications",
            "type":"Services"
        }
    ],
    "sg:phone":"+1 703 821 0079",
    "sg:postcode":"22101",
    "sg:province":"VA",
    "sg:tags":[
        "communication"
    ],
    "wof:name":"Globalsat Communications",
    "wof:placetype":"venue"
},
  "geometry": {"coordinates":[-77.17587399999999,38.95782],"type":"Point"}
}