{
  "type": "Feature",
  "properties": {
    "addr:full":"2225 Rosson Rd Powhatan VA 23139",
    "addr:housenumber":"2225",
    "addr:postcode":"23139",
    "addr:street":"Rosson Rd",
    "iso:country":"US",
    "sg:address":"2225 Rosson Rd",
    "sg:city":"Powhatan",
    "sg:classifiers":[
        {
            "category":"Home & Garden",
            "subcategory":"Garden Supply",
            "type":"Retail Goods"
        }
    ],
    "sg:phone":"+1 804 794 7324",
    "sg:postcode":"23139",
    "sg:province":"VA",
    "sg:tags":[
        "sprinkler"
    ],
    "wof:name":"Flatrock Irrigation Systems",
    "wof:placetype":"venue"
},
  "geometry": {"coordinates":[-77.923242,37.544909],"type":"Point"}
}