{
  "type": "Feature",
  "properties": {
    "addr:full":"21863 Engleside Pl Ashburn VA 20148",
    "addr:postcode":"21863;20148",
    "addr:street":"Engleside Pl",
    "iso:country":"US",
    "sg:address":"21863 Engleside Pl",
    "sg:city":"Ashburn",
    "sg:classifiers":[
        {
            "category":"Wholesale",
            "subcategory":"Non-durable Goods",
            "type":"Manufacturing & Wholesale Goods"
        }
    ],
    "sg:phone":"+1 571 223 1126",
    "sg:postcode":"20148",
    "sg:province":"VA",
    "sg:tags":[
        "item",
        "gift"
    ],
    "wof:name":"Vild",
    "wof:placetype":"venue"
},
  "geometry": {"coordinates":[-77.520169,39.011955],"type":"Point"}
}