{
  "type": "Feature",
  "properties": {
    "addr:full":"12479 Dillingham Sq Woodbridge VA 22192",
    "addr:housenumber":"12479",
    "addr:postcode":"22192",
    "addr:street":"Dillingham Sq",
    "iso:country":"US",
    "sg:address":"12479 Dillingham Sq",
    "sg:city":"Woodbridge",
    "sg:classifiers":[
        {
            "category":"Real Estate",
            "subcategory":"Real Estate Agent",
            "type":"Services"
        }
    ],
    "sg:phone":"+1 703 897 4777",
    "sg:postcode":"22192",
    "sg:province":"VA",
    "wof:name":"Weichert Realtors",
    "wof:placetype":"venue"
},
  "geometry": {"coordinates":[-77.319068,38.683241],"type":"Point"}
}