{
  "type": "Feature",
  "properties": {
    "iso:country":"US",
    "sg:address":"1008 Main St",
    "sg:city":"Altavista",
    "sg:classifiers":[
        {
            "category":"Autos & Motor Vehicles",
            "subcategory":"Automobile Sales",
            "type":"Retail Goods"
        }
    ],
    "sg:phone":"+1 434 369 4880",
    "sg:postcode":"24517",
    "sg:province":"VA",
    "wof:name":"Main Street Motors",
    "wof:placetype":"venue"
},
  "geometry": {"coordinates":[-79.28054299999999,37.115384],"type":"Point"}
}