{
  "type": "Feature",
  "properties": {
    "iso:country":"US",
    "sg:address":"4300 Ben Gunn Rd",
    "sg:city":"Virginia Beach",
    "sg:classifiers":[
        {
            "category":"Professional",
            "type":"Services"
        }
    ],
    "sg:phone":"+1 757 464 4832",
    "sg:postcode":"23455",
    "sg:province":"VA",
    "wof:name":"Ryan Td Inc",
    "wof:placetype":"venue"
},
  "geometry": {"coordinates":[-76.12200799999999,36.910483],"type":"Point"}
}