{
  "type": "Feature",
  "properties": {
    "addr:full":"1420 King St Alexandria VA 22314",
    "addr:housenumber":"1420",
    "addr:postcode":"22314",
    "addr:street":"King St",
    "iso:country":"US",
    "sg:address":"1420 King St",
    "sg:city":"Alexandria",
    "sg:classifiers":[
        {
            "category":"Organizations",
            "subcategory":"Professional Association",
            "type":"Services"
        }
    ],
    "sg:phone":"+1 703 838 9580",
    "sg:postcode":"22314",
    "sg:province":"VA",
    "wof:name":"Open Door Foundation",
    "wof:placetype":"venue"
},
  "geometry": {"coordinates":[-77.055543,38.806077],"type":"Point"}
}