{
  "type": "Feature",
  "properties": {
    "addr:full":"315 Wendell Scott Dr Danville VA 24540",
    "addr:housenumber":"315",
    "addr:postcode":"24540",
    "addr:street":"Wendell Scott Dr",
    "iso:country":"US",
    "sg:address":"315 Wendell Scott Dr",
    "sg:city":"Danville",
    "sg:classifiers":[
        {
            "category":"Organizations",
            "subcategory":"Religious Organization",
            "type":"Services"
        }
    ],
    "sg:phone":"+1 434 792 2001",
    "sg:postcode":"24540",
    "sg:province":"VA",
    "wof:name":"Glorious Church Of God",
    "wof:placetype":"venue"
},
  "geometry": {"coordinates":[-79.401163,36.614681],"type":"Point"}
}