{
  "type": "Feature",
  "properties": {
    "iso:country":"US",
    "sg:address":"3092 John Wayland Hwy",
    "sg:city":"Dayton",
    "sg:classifiers":[
        {
            "category":"Personal",
            "type":"Services"
        },
        {
            "category":"Sports & Exercise",
            "subcategory":"Gym",
            "type":"Entertainment"
        },
        {
            "category":"Health Services",
            "subcategory":"Health Practitioner",
            "type":"Services"
        },
        {
            "category":"Arena",
            "subcategory":"Sports Club",
            "type":"Entertainment"
        }
    ],
    "sg:phone":"+1 800 615 7352",
    "sg:postcode":"22821",
    "sg:province":"VA",
    "sg:tags":[
        "trainer",
        "control",
        "weight",
        "consultant",
        "program",
        "fitness",
        "physical"
    ],
    "sg:website":"http://national.citysearch.com/profile/external/34807683/timberville_va/curves.html?publisher=yellowpages&reference_id=1&placement=ypwebsitemip",
    "wof:name":"Curves",
    "wof:placetype":"venue"
},
  "geometry": {"coordinates":[-78.936317,38.415298],"type":"Point"}
}