{
  "type": "Feature",
  "properties": {
    "iso:country":"US",
    "sg:address":"980 J Clyde Morris Blvd",
    "sg:city":"Newport News",
    "sg:classifiers":[
        {
            "category":"Shopping",
            "type":"Retail Goods"
        }
    ],
    "sg:phone":"+1 757 594 6100",
    "sg:postcode":"23601",
    "sg:province":"VA",
    "sg:tags":[
        "album",
        "photo",
        "frame"
    ],
    "wof:name":"Totally Scrapbooks",
    "wof:placetype":"venue"
},
  "geometry": {"coordinates":[-76.45889099999999,37.095895],"type":"Point"}
}