{
  "type": "Feature",
  "properties": {
    "iso:country":"US",
    "sg:address":"1404 Avondale Ave",
    "sg:city":"Richmond",
    "sg:classifiers":[
        {
            "category":"Education",
            "subcategory":"Special Training",
            "type":"Public Place"
        }
    ],
    "sg:phone":"+1 804 266 4399",
    "sg:postcode":"23227",
    "sg:province":"VA",
    "sg:tags":[
        "consulting",
        "research"
    ],
    "wof:name":"Glasser Group The",
    "wof:placetype":"venue"
},
  "geometry": {"coordinates":[-77.457975,37.585324],"type":"Point"}
}