{
  "type": "Feature",
  "properties": {
    "iso:country":"US",
    "sg:address":"400 Madison St",
    "sg:city":"Alexandria",
    "sg:classifiers":[
        {
            "category":"Real Estate",
            "subcategory":"Real Estate Operator",
            "type":"Services"
        },
        {
            "category":"Organizations",
            "subcategory":"Community Association",
            "type":"Services"
        }
    ],
    "sg:phone":"+1 703 548 5002",
    "sg:postcode":"22314",
    "sg:province":"VA",
    "sg:tags":[
        "condo",
        "condominium"
    ],
    "wof:name":"Alexandria House Condominiums",
    "wof:placetype":"venue"
},
  "geometry": {"coordinates":[-77.04303299999999,38.812733],"type":"Point"}
}