{
  "type": "Feature",
  "properties": {
    "iso:country":"US",
    "sg:address":"3033 Gentry Rd",
    "sg:city":"Virginia Beach",
    "sg:classifiers":[
        {
            "category":"Building & Trades",
            "subcategory":"Plumbing",
            "type":"Services"
        }
    ],
    "sg:phone":"+1 757 486 4242",
    "sg:postcode":"23452",
    "sg:province":"VA",
    "sg:tags":[
        "conditioning",
        "contractor",
        "refrigeration",
        "system",
        "air"
    ],
    "wof:name":"Dolphin Heating and Cooling",
    "wof:placetype":"venue"
},
  "geometry": {"coordinates":[-76.077253,36.815169],"type":"Point"}
}