{
  "type": "Feature",
  "properties": {
    "iso:country":"US",
    "sg:address":"6711 Peters Creek Rd NW",
    "sg:city":"Roanoke",
    "sg:classifiers":[
        {
            "category":"Building & Trades",
            "subcategory":"Construction",
            "type":"Services"
        }
    ],
    "sg:phone":"+1 540 362 5173",
    "sg:postcode":"24019",
    "sg:province":"VA",
    "sg:tags":[
        "general",
        "contractor"
    ],
    "wof:name":"Erie Construction",
    "wof:placetype":"venue"
},
  "geometry": {"coordinates":[-79.95854,37.345543],"type":"Point"}
}