{
  "type": "Feature",
  "properties": {
    "addr:full":"3987 Buck Island Rd Charlottesville VA 22902",
    "addr:housenumber":"3987",
    "addr:postcode":"22902",
    "addr:street":"Buck Island Rd",
    "iso:country":"US",
    "sg:address":"3987 Buck Island Rd",
    "sg:city":"Charlottesville",
    "sg:classifiers":[
        {
            "category":"Shopping",
            "subcategory":"Jewelry",
            "type":"Retail Goods"
        }
    ],
    "sg:phone":"+1 434 293 8711",
    "sg:postcode":"22902",
    "sg:province":"VA",
    "wof:name":"Griffin Dove Designs",
    "wof:placetype":"venue"
},
  "geometry": {"coordinates":[-78.405698,37.926022],"type":"Point"}
}