{
  "type": "Feature",
  "properties": {
    "addr:full":"1814 Westmoreland St Mc Lean VA 22101",
    "addr:housenumber":"1814",
    "addr:postcode":"22101",
    "addr:street":"Westmoreland St Mc Lean",
    "iso:country":"US",
    "sg:address":"1814 Westmoreland St",
    "sg:city":"Mc Lean",
    "sg:classifiers":[
        {
            "category":"Professional",
            "subcategory":"Management & Consulting",
            "type":"Services"
        }
    ],
    "sg:phone":"+1 703 760 0844",
    "sg:postcode":"22101",
    "sg:province":"VA",
    "sg:tags":[
        "consultant",
        "business"
    ],
    "wof:name":"J & J Consulting Group LLC",
    "wof:placetype":"venue"
},
  "geometry": {"coordinates":[-77.178212,38.9162],"type":"Point"}
}