{
  "type": "Feature",
  "properties": {
    "iso:country":"US",
    "sg:address":"8100 Angel Ln",
    "sg:city":"Roanoke",
    "sg:classifiers":[
        {
            "category":"Organizations",
            "subcategory":"Religious Organization",
            "type":"Services"
        }
    ],
    "sg:phone":"+1 540 362 8041",
    "sg:postcode":"24019",
    "sg:province":"VA",
    "sg:tags":[
        "church"
    ],
    "sg:website":"www.cathedralofpraise.com",
    "wof:name":"Church Of God",
    "wof:placetype":"venue"
},
  "geometry": {"coordinates":[-79.969273,37.360874],"type":"Point"}
}