{
  "type": "Feature",
  "properties": {
    "addr:full":"5391 Three Notched Rd Crozet VA 22932",
    "addr:housenumber":"5391",
    "addr:postcode":"22932",
    "addr:street":"Three Notched Rd",
    "iso:country":"US",
    "sg:address":"5391 Three Notched Rd",
    "sg:city":"Crozet",
    "sg:classifiers":[
        {
            "category":"Food & Beverages",
            "subcategory":"Liquor & Beverages",
            "type":"Retail Goods"
        }
    ],
    "sg:phone":"+1 434 823 5671",
    "sg:postcode":"22932",
    "sg:province":"VA",
    "sg:tags":[
        "beer",
        "ale"
    ],
    "wof:name":"Star Hill Brewing Co",
    "wof:placetype":"venue"
},
  "geometry": {"coordinates":[-78.68719900000001,38.06935],"type":"Point"}
}