{
  "type": "Feature",
  "properties": {
    "iso:country":"US",
    "sg:address":"7120 Stanchion Ln",
    "sg:city":"Burke",
    "sg:classifiers":[
        {
            "category":"Professional",
            "subcategory":"Management & Consulting",
            "type":"Services"
        }
    ],
    "sg:phone":"+1 703 866 1516",
    "sg:postcode":"22015",
    "sg:province":"VA",
    "sg:tags":[
        "business"
    ],
    "wof:name":"Sjk Associates",
    "wof:placetype":"venue"
},
  "geometry": {"coordinates":[-77.272223,38.760084],"type":"Point"}
}