{
  "type": "Feature",
  "properties": {
    "addr:full":"5938 Veranda Dr Springfield VA 22152",
    "addr:housenumber":"5938",
    "addr:postcode":"22152",
    "addr:street":"Veranda Dr",
    "iso:country":"US",
    "sg:address":"5938 Veranda Dr",
    "sg:city":"Springfield",
    "sg:classifiers":[
        {
            "category":"Organizations",
            "subcategory":"Community Association",
            "type":"Services"
        }
    ],
    "sg:phone":"+1 703 569 5370",
    "sg:postcode":"22152",
    "sg:province":"VA",
    "wof:name":"World Lthnian Youth Assocation",
    "wof:placetype":"venue"
},
  "geometry": {"coordinates":[-77.24660900000001,38.788435],"type":"Point"}
}