{
  "type": "Feature",
  "properties": {
    "iso:country":"US",
    "sg:address":"904 N Liberty St",
    "sg:city":"Harrisonburg",
    "sg:classifiers":[
        {
            "category":"Shopping",
            "subcategory":"Computers & Home Electronics",
            "type":"Retail Goods"
        }
    ],
    "sg:phone":"+1 540 434 6693",
    "sg:postcode":"22802",
    "sg:province":"VA",
    "sg:tags":[
        "radio"
    ],
    "wof:name":"Biller 2-Way Radio Svc",
    "wof:placetype":"venue"
},
  "geometry": {"coordinates":[-78.865031,38.463053],"type":"Point"}
}