{
  "type": "Feature",
  "properties": {
    "addr:full":"3027 N John Marshall Dr Arlington VA 22207",
    "addr:housenumber":"3027",
    "addr:postcode":"22207",
    "addr:street":"N John Marshall Dr",
    "iso:country":"US",
    "sg:address":"3027 N John Marshall Dr",
    "sg:city":"Arlington",
    "sg:classifiers":[
        {
            "category":"Manufacturing",
            "subcategory":"Printing",
            "type":"Manufacturing & Wholesale Goods"
        }
    ],
    "sg:phone":"+1 703 237 2625",
    "sg:postcode":"22207",
    "sg:province":"VA",
    "sg:tags":[
        "newsletter"
    ],
    "wof:name":"Micro Learning",
    "wof:placetype":"venue"
},
  "geometry": {"coordinates":[-77.150929,38.905072],"type":"Point"}
}