{
  "type": "Feature",
  "properties": {
    "addr:full":"115 Oakwood Dr Bridgewater VA 22812",
    "addr:housenumber":"115",
    "addr:postcode":"22812",
    "addr:street":"Oakwood Dr",
    "iso:country":"US",
    "sg:address":"115 Oakwood Dr",
    "sg:city":"Bridgewater",
    "sg:classifiers":[
        {
            "category":"Health Services",
            "subcategory":"Doctor",
            "type":"Services"
        }
    ],
    "sg:phone":"+1 540 828 2312",
    "sg:postcode":"22812",
    "sg:province":"VA",
    "sg:tags":[
        "dentist"
    ],
    "sg:website":"www.bwaterdental.com",
    "wof:name":"Bridgewater Family Dentistry",
    "wof:placetype":"venue"
},
  "geometry": {"coordinates":[-78.963425,38.391735],"type":"Point"}
}