{
  "type": "Feature",
  "properties": {
    "iso:country":"US",
    "sg:address":"1520 Kennon Ave",
    "sg:city":"Norfolk",
    "sg:classifiers":[
        {
            "category":"Organizations",
            "subcategory":"Religious Organization",
            "type":"Services"
        }
    ],
    "sg:phone":"+1 757 858 2162",
    "sg:postcode":"23502",
    "sg:province":"VA",
    "sg:tags":[
        "church"
    ],
    "wof:name":"Friendship Independent Baptist",
    "wof:placetype":"venue"
},
  "geometry": {"coordinates":[-76.237527,36.867437],"type":"Point"}
}