{
  "type": "Feature",
  "properties": {
    "iso:country":"US",
    "sg:address":"612 S Pickett St Ste B",
    "sg:city":"Alexandria",
    "sg:classifiers":[
        {
            "category":"Manufacturing",
            "subcategory":"Metals",
            "type":"Manufacturing & Wholesale Goods"
        },
        {
            "category":"Manufacturing",
            "subcategory":"Building Materials",
            "type":"Manufacturing & Wholesale Goods"
        }
    ],
    "sg:phone":"+1 703 370 5050",
    "sg:postcode":"22304",
    "sg:province":"VA",
    "sg:tags":[
        "work-manufacturers",
        "work",
        "sheet",
        "fabricator"
    ],
    "sg:website":"http://www.jettmech.com",
    "wof:name":"Swing M E Co Inc",
    "wof:placetype":"venue"
},
  "geometry": {"coordinates":[-77.131612,38.804648],"type":"Point"}
}