{
  "type": "Feature",
  "properties": {
    "iso:country":"US",
    "sg:address":"11871 Mandy Ln",
    "sg:city":"Manassas",
    "sg:classifiers":[
        {
            "category":"Building & Trades",
            "subcategory":"Construction",
            "type":"Services"
        }
    ],
    "sg:phone":"+1 703 369 4555",
    "sg:postcode":"20112",
    "sg:province":"VA",
    "sg:tags":[
        "carpentry",
        "contractor"
    ],
    "wof:name":"Custom Carpentry & Design",
    "wof:placetype":"venue"
},
  "geometry": {"coordinates":[-77.457532,38.698665],"type":"Point"}
}