{
  "type": "Feature",
  "properties": {
    "addr:full":"870 Falcon Dr NE Abingdon VA 24210",
    "addr:housenumber":"870",
    "addr:postcode":"24210",
    "addr:street":"Falcon Dr Ne",
    "iso:country":"US",
    "sg:address":"870 Falcon Dr NE",
    "sg:city":"Abingdon",
    "sg:classifiers":[
        {
            "category":"Professional",
            "type":"Services"
        }
    ],
    "sg:phone":"+1 276 628 7717",
    "sg:postcode":"24210",
    "sg:province":"VA",
    "wof:name":"Turf Tech Inc",
    "wof:placetype":"venue"
},
  "geometry": {"coordinates":[-81.943614,36.722986],"type":"Point"}
}