{
  "type": "Feature",
  "properties": {
    "addr:full":"1400 Best Plz Richmond VA 23227",
    "addr:housenumber":"1400",
    "addr:postcode":"23227",
    "addr:street":"Best Plz",
    "iso:country":"US",
    "sg:address":"1400 Best Plz",
    "sg:city":"Richmond",
    "sg:classifiers":[
        {
            "category":"Restaurant",
            "type":"Food & Drink"
        }
    ],
    "sg:phone":"+1 804 627 7069",
    "sg:postcode":"23227",
    "sg:province":"VA",
    "sg:tags":[
        "eating"
    ],
    "wof:name":"Compass Eurest Dining Services",
    "wof:placetype":"venue"
},
  "geometry": {"coordinates":[-77.448391,37.638878],"type":"Point"}
}