{
  "type": "Feature",
  "properties": {
    "addr:full":"47745 League Ct Sterling VA 20165",
    "addr:housenumber":"47745",
    "addr:postcode":"20165",
    "addr:street":"League Ct",
    "iso:country":"US",
    "sg:address":"47745 League Ct",
    "sg:city":"Sterling",
    "sg:classifiers":[
        {
            "category":"Wholesale",
            "subcategory":"Durable Goods & Equipment",
            "type":"Manufacturing & Wholesale Goods"
        }
    ],
    "sg:phone":"+1 703 406 2497",
    "sg:postcode":"20165",
    "sg:province":"VA",
    "wof:name":"League Technologies Inc",
    "wof:placetype":"venue"
},
  "geometry": {"coordinates":[-77.346616,39.04043],"type":"Point"}
}