{
  "type": "Feature",
  "properties": {
    "addr:full":"7221 Pullen Dr Fredericksburg VA 22407",
    "addr:housenumber":"7221",
    "addr:postcode":"22407",
    "addr:street":"Pullen Dr",
    "iso:country":"US",
    "sg:address":"7221 Pullen Dr",
    "sg:city":"Fredericksburg",
    "sg:classifiers":[
        {
            "category":"Building & Trades",
            "subcategory":"Cleaning & Sanitation",
            "type":"Services"
        }
    ],
    "sg:phone":"+1 540 785 4524",
    "sg:postcode":"22407",
    "sg:province":"VA",
    "sg:tags":[
        "co",
        "maintenance",
        "hanging"
    ],
    "wof:name":"E & T Contractors & Jantr Svcs",
    "wof:placetype":"venue"
},
  "geometry": {"coordinates":[-77.592764,38.28316],"type":"Point"}
}