{
  "type": "Feature",
  "properties": {
    "iso:country":"US",
    "sg:address":"1059 J Clyde Morris Blvd",
    "sg:city":"Newport News",
    "sg:classifiers":[
        {
            "category":"Personal",
            "type":"Services"
        }
    ],
    "sg:phone":"+1 757 873 8267",
    "sg:postcode":"23602",
    "sg:province":"VA",
    "wof:name":"Tan-Your-Hide",
    "wof:placetype":"venue"
},
  "geometry": {"coordinates":[-76.458617,37.100559],"type":"Point"}
}