{
  "type": "Feature",
  "properties": {
    "addr:full":"427 Durham St Hampton VA 23669",
    "addr:housenumber":"427",
    "addr:postcode":"23669",
    "addr:street":"Durham St",
    "iso:country":"US",
    "sg:address":"427 Durham St",
    "sg:city":"Hampton",
    "sg:classifiers":[
        {
            "category":"Organizations",
            "subcategory":"Community Association",
            "type":"Services"
        }
    ],
    "sg:phone":"+1 757 851 8016",
    "sg:postcode":"23669",
    "sg:province":"VA",
    "sg:tags":[
        "veteran",
        "fraternal"
    ],
    "wof:name":"Air Force Sergeants Assn",
    "wof:placetype":"venue"
},
  "geometry": {"coordinates":[-76.313335,37.063643],"type":"Point"}
}