{
  "type": "Feature",
  "properties": {
    "addr:full":"511 Cedar Grove Rd Farnham VA 22460",
    "addr:housenumber":"511",
    "addr:postcode":"22460",
    "addr:street":"Cedar Grove Rd",
    "iso:country":"US",
    "sg:address":"511 Cedar Grove Rd",
    "sg:city":"Farnham",
    "sg:classifiers":[
        {
            "category":"Health Services",
            "subcategory":"Nursing And Care Facility",
            "type":"Services"
        }
    ],
    "sg:phone":"+1 804 394 2102",
    "sg:postcode":"22460",
    "sg:province":"VA",
    "sg:tags":[
        "home",
        "retirement",
        "community"
    ],
    "wof:name":"Farnham Manor",
    "wof:placetype":"venue"
},
  "geometry": {"coordinates":[-76.622726,37.884974],"type":"Point"}
}