{
  "type": "Feature",
  "properties": {
    "iso:country":"US",
    "sg:address":"14160 Newbrook Dr",
    "sg:city":"Chantilly",
    "sg:classifiers":[
        {
            "category":"Health Services",
            "subcategory":"Hospital",
            "type":"Services"
        }
    ],
    "sg:phone":"+1 703 841 7768",
    "sg:postcode":"20151",
    "sg:province":"VA",
    "sg:tags":[
        "mental"
    ],
    "sg:website":"www.comres.org",
    "wof:name":"Community Residences",
    "wof:placetype":"venue"
},
  "geometry": {"coordinates":[-77.434453,38.872811],"type":"Point"}
}