{
  "type": "Feature",
  "properties": {
    "iso:country":"US",
    "sg:address":"600 Granby St",
    "sg:city":"Norfolk",
    "sg:classifiers":[
        {
            "category":"Government",
            "subcategory":"Office",
            "type":"Public Place"
        }
    ],
    "sg:phone":"+1 757 222 7470",
    "sg:postcode":"23510",
    "sg:province":"VA",
    "wof:name":"Honorable David H Adams",
    "wof:placetype":"venue"
},
  "geometry": {"coordinates":[-76.28880100000001,36.853595],"type":"Point"}
}