{
  "type": "Feature",
  "properties": {
    "addr:full":"12885 Carriage Ford Rd Nokesville VA 20181",
    "addr:housenumber":"12885",
    "addr:postcode":"20181",
    "addr:street":"Carriage Ford Rd",
    "iso:country":"US",
    "sg:address":"12885 Carriage Ford Rd",
    "sg:city":"Nokesville",
    "sg:classifiers":[
        {
            "category":"Wholesale",
            "subcategory":"Vending Machines",
            "type":"Manufacturing & Wholesale Goods"
        }
    ],
    "sg:phone":"+1 703 593 5693",
    "sg:postcode":"20181",
    "sg:province":"VA",
    "sg:tags":[
        "operator"
    ],
    "wof:name":"W & B Vending Inc",
    "wof:placetype":"venue"
},
  "geometry": {"coordinates":[-77.57993999999999,38.674517],"type":"Point"}
}