{
  "type": "Feature",
  "properties": {
    "addr:full":"8619 Westwood Center Dr Vienna VA 22182",
    "addr:housenumber":"8619",
    "addr:postcode":"22182",
    "addr:street":"Westwood Center Dr",
    "iso:country":"US",
    "sg:address":"8619 Westwood Center Dr",
    "sg:city":"Vienna",
    "sg:classifiers":[
        {
            "category":"Banks & Credit Unions",
            "subcategory":"Investment Brokerage",
            "type":"Services"
        }
    ],
    "sg:phone":"+1 703 448 4830",
    "sg:postcode":"22182",
    "sg:province":"VA",
    "sg:tags":[
        "advisory",
        "financial"
    ],
    "sg:website":"www.dfcinc.com",
    "wof:name":"Woodbury Financial Svc",
    "wof:placetype":"venue"
},
  "geometry": {"coordinates":[-77.24808899999999,38.92876],"type":"Point"}
}