{
  "type": "Feature",
  "properties": {
    "iso:country":"US",
    "sg:address":"121 Mercedes Ct",
    "sg:city":"Winchester",
    "sg:classifiers":[
        {
            "category":"Retail",
            "subcategory":"Auto Repair",
            "type":"Services"
        }
    ],
    "sg:phone":"+1 540 662 5202",
    "sg:postcode":"22603",
    "sg:province":"VA",
    "sg:tags":[
        "body",
        "automobile",
        "painting"
    ],
    "sg:website":"www.jrsautobody.com",
    "wof:name":"J R's Auto Body",
    "wof:placetype":"venue"
},
  "geometry": {"coordinates":[-78.140717,39.218486],"type":"Point"}
}