{
  "type": "Feature",
  "properties": {
    "addr:full":"13998 Parkeast Cir Chantilly VA 20151",
    "addr:housenumber":"13998",
    "addr:postcode":"20151",
    "addr:street":"Parkeast Cir",
    "iso:country":"US",
    "sg:address":"13998 Parkeast Cir",
    "sg:city":"Chantilly",
    "sg:classifiers":[
        {
            "category":"Building & Trades",
            "subcategory":"Construction",
            "type":"Services"
        }
    ],
    "sg:phone":"+1 703 803 9641",
    "sg:postcode":"20151",
    "sg:province":"VA",
    "sg:tags":[
        "land",
        "gen"
    ],
    "wof:name":"Preston Street Communities",
    "wof:placetype":"venue"
},
  "geometry": {"coordinates":[-77.432664,38.872409],"type":"Point"}
}