{
  "type": "Feature",
  "properties": {
    "addr:full":"522 Front Royal Pike Winchester VA 22602",
    "addr:housenumber":"522",
    "addr:postcode":"22602",
    "addr:street":"Front Royal Pike",
    "iso:country":"US",
    "sg:address":"522 Front Royal Pike",
    "sg:city":"Winchester",
    "sg:classifiers":[
        {
            "category":"Professional",
            "subcategory":"Employment Agencies",
            "type":"Services"
        }
    ],
    "sg:phone":"+1 540 722 0333",
    "sg:postcode":"22602",
    "sg:province":"VA",
    "wof:name":"Integrity Staffing Services",
    "wof:placetype":"venue"
},
  "geometry": {"coordinates":[-78.160545,39.151048],"type":"Point"}
}