{
  "type": "Feature",
  "properties": {
    "addr:full":"15262 Goshen Rd Montpelier VA 23192",
    "addr:housenumber":"15262",
    "addr:postcode":"23192",
    "addr:street":"Goshen Rd",
    "iso:country":"US",
    "sg:address":"15262 Goshen Rd",
    "sg:city":"Montpelier",
    "sg:classifiers":[
        {
            "category":"Manufacturing",
            "subcategory":"Lumber",
            "type":"Manufacturing & Wholesale Goods"
        }
    ],
    "sg:phone":"+1 804 883 7296",
    "sg:postcode":"23192",
    "sg:province":"VA",
    "sg:tags":[
        "operation",
        "timber",
        "tract"
    ],
    "wof:name":"Hawkwood Farm",
    "wof:placetype":"venue"
},
  "geometry": {"coordinates":[-77.645031,37.826467],"type":"Point"}
}