{
  "type": "Feature",
  "properties": {
    "addr:full":"103 Cheyenne Trl Winchester VA 22602",
    "addr:housenumber":"103",
    "addr:postcode":"22602",
    "addr:street":"Cheyenne Trl",
    "iso:country":"US",
    "sg:address":"103 Cheyenne Trl",
    "sg:city":"Winchester",
    "sg:classifiers":[
        {
            "category":"Professional",
            "subcategory":"Art Services",
            "type":"Services"
        }
    ],
    "sg:phone":"+1 540 877 9770",
    "sg:postcode":"22602",
    "sg:province":"VA",
    "wof:name":"Cheyenne Consulting",
    "wof:placetype":"venue"
},
  "geometry": {"coordinates":[-78.34321300000001,39.190455],"type":"Point"}
}