{
  "type": "Feature",
  "properties": {
    "iso:country":"US",
    "sg:address":"1221 N Hudson St",
    "sg:city":"Arlington",
    "sg:classifiers":[
        {
            "category":"Real Estate",
            "subcategory":"Real Estate Agent",
            "type":"Services"
        }
    ],
    "sg:phone":"+1 703 807 5582",
    "sg:postcode":"22201",
    "sg:province":"VA",
    "wof:name":"Clark Realty Builder",
    "wof:placetype":"venue"
},
  "geometry": {"coordinates":[-77.09662400000001,38.887133],"type":"Point"}
}