{
  "type": "Feature",
  "properties": {
    "addr:full":"162 Normandy Hill Dr Alexandria VA 22304",
    "addr:housenumber":"162",
    "addr:postcode":"22304",
    "addr:street":"Normandy Hill Dr",
    "iso:country":"US",
    "sg:address":"162 Normandy Hill Dr",
    "sg:city":"Alexandria",
    "sg:classifiers":[
        {
            "category":"Professional",
            "subcategory":"Computer Services",
            "type":"Services"
        }
    ],
    "sg:phone":"+1 703 751 3757",
    "sg:postcode":"22304",
    "sg:province":"VA",
    "sg:tags":[
        "consultant",
        "designer"
    ],
    "wof:name":"Something To REMEMBER-Cs",
    "wof:placetype":"venue"
},
  "geometry": {"coordinates":[-77.093658,38.80852],"type":"Point"}
}