{
  "type": "Feature",
  "properties": {
    "addr:full":"34 Bittersweet Ln Hardy VA 24101",
    "addr:housenumber":"34",
    "addr:postcode":"24101",
    "addr:street":"Bittersweet Ln",
    "iso:country":"US",
    "sg:address":"34 Bittersweet Ln",
    "sg:city":"Hardy",
    "sg:classifiers":[
        {
            "category":"Insurance",
            "subcategory":"Insurance Agent",
            "type":"Services"
        }
    ],
    "sg:phone":"+1 540 427 1368",
    "sg:postcode":"24101",
    "sg:province":"VA",
    "wof:name":"Nationwide Insurance",
    "wof:placetype":"venue"
},
  "geometry": {"coordinates":[-79.881891,37.188598],"type":"Point"}
}