{
  "type": "Feature",
  "properties": {
    "iso:country":"US",
    "sg:address":"1709 Colley Ave",
    "sg:city":"Norfolk",
    "sg:classifiers":[
        {
            "category":"Health Services",
            "subcategory":"Doctor",
            "type":"Services"
        }
    ],
    "sg:phone":"+1 757 627 8303",
    "sg:postcode":"23517",
    "sg:province":"VA",
    "wof:name":"Frederick E Martin III DDS",
    "wof:placetype":"venue"
},
  "geometry": {"coordinates":[-76.29689399999999,36.869727],"type":"Point"}
}