{
  "type": "Feature",
  "properties": {
    "addr:full":"501 Rison St Danville VA 24541",
    "addr:housenumber":"501",
    "addr:postcode":"24541",
    "addr:street":"Rison St",
    "iso:country":"US",
    "sg:address":"501 Rison St",
    "sg:city":"Danville",
    "sg:classifiers":[
        {
            "category":"Health Services",
            "subcategory":"Doctor",
            "type":"Services"
        }
    ],
    "sg:phone":"+1 434 792 5134",
    "sg:postcode":"24541",
    "sg:province":"VA",
    "sg:tags":[
        "surgeon",
        "oral"
    ],
    "wof:name":"Wentz & Manry DDS PC",
    "wof:placetype":"venue"
},
  "geometry": {"coordinates":[-79.40178,36.578947],"type":"Point"}
}