{
  "type": "Feature",
  "properties": {
    "addr:full":"1032 Saw Pen Point Trl Virginia Beach VA 23455",
    "addr:housenumber":"1032",
    "addr:postcode":"23455",
    "addr:street":"Saw Pen Point Trl",
    "iso:country":"US",
    "sg:address":"1032 Saw Pen Point Trl",
    "sg:city":"Virginia Beach",
    "sg:classifiers":[
        {
            "category":"Building & Trades",
            "subcategory":"Construction",
            "type":"Services"
        }
    ],
    "sg:phone":"+1 757 460 2353",
    "sg:postcode":"23455",
    "sg:province":"VA",
    "sg:tags":[
        "home",
        "family"
    ],
    "wof:name":"Vern Howerin Builders Inc",
    "wof:placetype":"venue"
},
  "geometry": {"coordinates":[-76.11798899999999,36.869071],"type":"Point"}
}