{
  "type": "Feature",
  "properties": {
    "addr:full":"2518 S Fort Scott Dr Arlington VA 22202",
    "addr:housenumber":"2518",
    "addr:postcode":"22202",
    "addr:street":"S Fort Scott Dr",
    "iso:country":"US",
    "sg:address":"2518 S Fort Scott Dr",
    "sg:city":"Arlington",
    "sg:classifiers":[
        {
            "category":"Professional",
            "subcategory":"Business Services",
            "type":"Services"
        }
    ],
    "sg:phone":"+1 703 683 6295",
    "sg:postcode":"22202",
    "sg:province":"VA",
    "wof:name":"Daphne Hammond Assoc Ltd",
    "wof:placetype":"venue"
},
  "geometry": {"coordinates":[-77.064381,38.850708],"type":"Point"}
}