{
  "type": "Feature",
  "properties": {
    "addr:full":"418 Brewers Creek Ln Carrollton VA 23314",
    "addr:housenumber":"418",
    "addr:postcode":"23314",
    "addr:street":"Brewers Creek Ln",
    "iso:country":"US",
    "sg:address":"418 Brewers Creek Ln",
    "sg:city":"Carrollton",
    "sg:classifiers":[
        {
            "category":"Building & Trades",
            "subcategory":"Cleaning & Sanitation",
            "type":"Services"
        }
    ],
    "sg:phone":"+1 757 238 2395",
    "sg:postcode":"23314",
    "sg:province":"VA",
    "sg:tags":[
        "maintenance"
    ],
    "wof:name":"Joyner Maintenance & Service",
    "wof:placetype":"venue"
},
  "geometry": {"coordinates":[-76.523189,36.912035],"type":"Point"}
}