{
  "type": "Feature",
  "properties": {
    "iso:country":"US",
    "sg:address":"7723 Harwood Pl",
    "sg:city":"Springfield",
    "sg:classifiers":[
        {
            "category":"Communications",
            "subcategory":"News Services",
            "type":"Services"
        }
    ],
    "sg:phone":"+1 703 866 4708",
    "sg:postcode":"22152",
    "sg:province":"VA",
    "sg:tags":[
        "organization",
        "editorial"
    ],
    "wof:name":"Targeted News Service LLC",
    "wof:placetype":"venue"
},
  "geometry": {"coordinates":[-77.21410299999999,38.776274],"type":"Point"}
}