{
  "type": "Feature",
  "properties": {
    "iso:country":"US",
    "sg:address":"278 Stones Dairy Rd",
    "sg:city":"Martinsville",
    "sg:classifiers":[
        {
            "category":"Personal",
            "subcategory":"Beauty Salon",
            "type":"Services"
        }
    ],
    "sg:phone":"+1 276 673 1150",
    "sg:postcode":"24112",
    "sg:province":"VA",
    "wof:name":"Pleasant Grove Salon",
    "wof:placetype":"venue"
},
  "geometry": {"coordinates":[-80.00428700000001,36.689859],"type":"Point"}
}