{
  "type": "Feature",
  "properties": {
    "addr:full":"1222 2nd St Richlands VA 24641",
    "addr:housenumber":"1222",
    "addr:postcode":"24641",
    "addr:street":"2Nd St",
    "iso:country":"US",
    "sg:address":"1222 2nd St",
    "sg:city":"Richlands",
    "sg:classifiers":[
        {
            "category":"Wholesale",
            "subcategory":"Chemicals & Plastics",
            "type":"Manufacturing & Wholesale Goods"
        }
    ],
    "sg:phone":"+1 276 963 1106",
    "sg:postcode":"24641",
    "sg:province":"VA",
    "sg:tags":[
        "mining",
        "ore"
    ],
    "wof:name":"Reiss Viking",
    "wof:placetype":"venue"
},
  "geometry": {"coordinates":[-81.796746,37.093655],"type":"Point"}
}