{
  "type": "Feature",
  "properties": {
    "iso:country":"US",
    "sg:address":"3103 9th Rd N",
    "sg:city":"Arlington",
    "sg:classifiers":[
        {
            "category":"Organizations",
            "subcategory":"Religious Organization",
            "type":"Services"
        }
    ],
    "sg:phone":"+1 703 525 7177",
    "sg:postcode":"22201",
    "sg:province":"VA",
    "sg:tags":[
        "mission"
    ],
    "sg:website":"http://www.aachhomeless.org",
    "wof:name":"Aach",
    "wof:placetype":"venue"
},
  "geometry": {"coordinates":[-77.094627,38.883628],"type":"Point"}
}