{
  "type": "Feature",
  "properties": {
    "addr:full":"116 Industrial Park Rd Chilhowie VA 24319",
    "addr:housenumber":"116",
    "addr:postcode":"24319",
    "addr:street":"Industrial Park Rd",
    "iso:country":"US",
    "sg:address":"116 Industrial Park Rd",
    "sg:city":"Chilhowie",
    "sg:classifiers":[
        {
            "category":"Recreation",
            "type":"Entertainment"
        }
    ],
    "sg:phone":"+1 276 646 3916",
    "sg:postcode":"24319",
    "sg:province":"VA",
    "sg:tags":[
        "club",
        "membership"
    ],
    "wof:name":"Chilhowie Lions Club",
    "wof:placetype":"venue"
},
  "geometry": {"coordinates":[-81.697289,36.789697],"type":"Point"}
}