{
  "type": "Feature",
  "properties": {
    "addr:full":"196 Van Buren St Herndon VA 20170",
    "addr:housenumber":"196",
    "addr:postcode":"20170",
    "addr:street":"Van Buren St",
    "iso:country":"US",
    "sg:address":"196 Van Buren St",
    "sg:city":"Herndon",
    "sg:classifiers":[
        {
            "category":"Utilities",
            "subcategory":"Telephone",
            "type":"Services"
        }
    ],
    "sg:phone":"+1 703 464 0292",
    "sg:postcode":"20170",
    "sg:province":"VA",
    "sg:tags":[
        "video",
        "internet"
    ],
    "wof:name":"Connect Live",
    "wof:placetype":"venue"
},
  "geometry": {"coordinates":[-77.388375,38.956373],"type":"Point"}
}