{
  "type": "Feature",
  "properties": {
    "iso:country":"US",
    "sg:address":"16905 Cass Brook Ln",
    "sg:city":"Woodbridge",
    "sg:classifiers":[
        {
            "category":"Professional",
            "subcategory":"Management & Consulting",
            "type":"Services"
        }
    ],
    "sg:phone":"+1 703 221 4960",
    "sg:postcode":"22191",
    "sg:province":"VA",
    "sg:tags":[
        "business"
    ],
    "wof:name":"Alliance Technology",
    "wof:placetype":"venue"
},
  "geometry": {"coordinates":[-77.29859500000001,38.585135],"type":"Point"}
}