{
  "type": "Feature",
  "properties": {
    "addr:full":"2637 Glenridge Dr Powhatan VA 23139",
    "addr:housenumber":"2637",
    "addr:postcode":"23139",
    "addr:street":"Glenridge Dr",
    "iso:country":"US",
    "sg:address":"2637 Glenridge Dr",
    "sg:city":"Powhatan",
    "sg:classifiers":[
        {
            "category":"Building & Trades",
            "subcategory":"Construction",
            "type":"Services"
        }
    ],
    "sg:phone":"+1 804 598 1164",
    "sg:postcode":"23139",
    "sg:province":"VA",
    "sg:tags":[
        "concrete",
        "work"
    ],
    "wof:name":"Concrete Formations",
    "wof:placetype":"venue"
},
  "geometry": {"coordinates":[-77.832686,37.55963],"type":"Point"}
}