{
  "type": "Feature",
  "properties": {
    "iso:country":"US",
    "sg:address":"2011 S Crystal Dr",
    "sg:city":"Arlington",
    "sg:classifiers":[
        {
            "category":"Professional",
            "subcategory":"Computer Services",
            "type":"Services"
        }
    ],
    "sg:phone":"+1 703 486 2282",
    "sg:postcode":"22202",
    "sg:province":"VA",
    "sg:tags":[
        "integrated",
        "system"
    ],
    "wof:name":"Titan Corporation",
    "wof:placetype":"venue"
},
  "geometry": {"coordinates":[-77.049601,38.853399],"type":"Point"}
}