{
  "type": "Feature",
  "properties": {
    "addr:full":"4505 Madison Ave Newport News VA 23607",
    "addr:housenumber":"4505",
    "addr:postcode":"23607",
    "addr:street":"Madison Ave",
    "iso:country":"US",
    "sg:address":"4505 Madison Ave",
    "sg:city":"Newport News",
    "sg:classifiers":[
        {
            "category":"Professional",
            "subcategory":"Business Services",
            "type":"Services"
        }
    ],
    "sg:phone":"+1 757 926 2829",
    "sg:postcode":"23607",
    "sg:province":"VA",
    "wof:name":"Java Enterprises",
    "wof:placetype":"venue"
},
  "geometry": {"coordinates":[-76.426393,36.995304],"type":"Point"}
}