{
  "type": "Feature",
  "properties": {
    "addr:full":"5110 Bradfield Ct Annandale VA 22003",
    "addr:housenumber":"5110",
    "addr:postcode":"22003",
    "addr:street":"Bradfield Ct",
    "iso:country":"US",
    "sg:address":"5110 Bradfield Ct",
    "sg:city":"Annandale",
    "sg:classifiers":[
        {
            "category":"Professional",
            "subcategory":"Management & Consulting",
            "type":"Services"
        }
    ],
    "sg:phone":"+1 703 426 5611",
    "sg:postcode":"22003",
    "sg:province":"VA",
    "wof:name":"Medical Management Consulting",
    "wof:placetype":"venue"
},
  "geometry": {"coordinates":[-77.264448,38.813456],"type":"Point"}
}