{
  "type": "Feature",
  "properties": {
    "addr:full":"289 Laurel Ln Laurel Fork VA 24348",
    "addr:housenumber":"289",
    "addr:postcode":"24348",
    "addr:street":"Laurel Ln",
    "iso:country":"US",
    "sg:address":"289 Laurel Ln",
    "sg:city":"Laurel Fork",
    "sg:classifiers":[
        {
            "category":"Building & Trades",
            "subcategory":"Construction",
            "type":"Services"
        }
    ],
    "sg:phone":"+1 276 398 4284",
    "sg:postcode":"24348",
    "sg:province":"VA",
    "sg:tags":[
        "painter"
    ],
    "wof:name":"DEP Enterprises",
    "wof:placetype":"venue"
},
  "geometry": {"coordinates":[-81.15607900000001,36.605423],"type":"Point"}
}