{
  "type": "Feature",
  "properties": {
    "iso:country":"US",
    "sg:address":"2132 Lake Surrey Dr",
    "sg:city":"Richmond",
    "sg:classifiers":[
        {
            "category":"Professional",
            "subcategory":"Lawyer & Legal Services",
            "type":"Services"
        }
    ],
    "sg:phone":"+1 804 745 4230",
    "sg:postcode":"23235",
    "sg:province":"VA",
    "wof:name":"Jerome L Lonnes",
    "wof:placetype":"venue"
},
  "geometry": {"coordinates":[-77.545973,37.470995],"type":"Point"}
}