{
  "type": "Feature",
  "properties": {
    "addr:full":"3459 Chapel Dr Richmond VA 23224",
    "addr:housenumber":"3459",
    "addr:postcode":"23224",
    "addr:street":"Chapel Dr",
    "iso:country":"US",
    "sg:address":"3459 Chapel Dr",
    "sg:city":"Richmond",
    "sg:classifiers":[
        {
            "category":"Organizations",
            "subcategory":"Religious Organization",
            "type":"Services"
        }
    ],
    "sg:phone":"+1 804 233 8901",
    "sg:postcode":"23224",
    "sg:province":"VA",
    "wof:name":"New Canaan Pentecostal Church",
    "wof:placetype":"venue"
},
  "geometry": {"coordinates":[-77.463078,37.500486],"type":"Point"}
}