{
  "type": "Feature",
  "properties": {
    "iso:country":"US",
    "sg:address":"474 Gidbrown Hollow Rd",
    "sg:city":"Washington",
    "sg:classifiers":[
        {
            "category":"Professional",
            "subcategory":"Lawyer & Legal Services",
            "type":"Services"
        }
    ],
    "sg:phone":"+1 540 987 8484",
    "sg:postcode":"22747",
    "sg:province":"VA",
    "wof:name":"Paul Arneson",
    "wof:placetype":"venue"
},
  "geometry": {"coordinates":[-78.22366,38.711138],"type":"Point"}
}