{
  "type": "Feature",
  "properties": {
    "addr:full":"5101 Cleveland St Virginia Beach VA 23462",
    "addr:housenumber":"5101",
    "addr:postcode":"23462",
    "addr:street":"Cleveland St",
    "iso:country":"US",
    "sg:address":"5101 Cleveland St",
    "sg:city":"Virginia Beach",
    "sg:classifiers":[
        {
            "category":"Professional",
            "subcategory":"Accounting & Tax Preparation",
            "type":"Services"
        }
    ],
    "sg:phone":"+1 757 499 1122",
    "sg:postcode":"23462",
    "sg:province":"VA",
    "sg:tags":[
        "accountant"
    ],
    "sg:website":"www.bakerandmcniff.com",
    "wof:name":"Baker & Mc Niff PC",
    "wof:placetype":"venue"
},
  "geometry": {"coordinates":[-76.159313,36.842054],"type":"Point"}
}