{
  "type": "Feature",
  "properties": {
    "addr:full":"701 Fort Chiswell Rd Max Meadows VA 24360",
    "addr:housenumber":"701",
    "addr:postcode":"24360",
    "addr:street":"Fort Chiswell Rd;Meadows",
    "iso:country":"US",
    "sg:address":"701 Fort Chiswell Rd",
    "sg:city":"Max Meadows",
    "sg:classifiers":[
        {
            "category":"Restaurant",
            "type":"Food & Drink"
        }
    ],
    "sg:phone":"+1 276 637 6285",
    "sg:postcode":"24360",
    "sg:province":"VA",
    "sg:tags":[
        "eating"
    ],
    "wof:name":"Burger Express Inc",
    "wof:placetype":"venue"
},
  "geometry": {"coordinates":[-80.94389700000001,36.938119],"type":"Point"}
}