{
  "type": "Feature",
  "properties": {
    "addr:full":"1118 W Mercury Blvd Hampton VA 23666",
    "addr:housenumber":"1118",
    "addr:postcode":"23666",
    "addr:street":"W Mercury Blvd",
    "iso:country":"US",
    "sg:address":"1118 W Mercury Blvd",
    "sg:city":"Hampton",
    "sg:classifiers":[
        {
            "category":"Restaurant",
            "type":"Food & Drink"
        }
    ],
    "sg:menulink":"http://www.allmenus.com/va/hampton/50499-pho-79/menu/",
    "sg:phone":"+1 757 827 4679",
    "sg:postcode":"23666",
    "sg:province":"VA",
    "sg:tags":[
        "asian",
        "vietnamese"
    ],
    "wof:name":"Pho 79",
    "wof:placetype":"venue"
},
  "geometry": {"coordinates":[-76.38663699999999,37.042227],"type":"Point"}
}