{
  "type": "Feature",
  "properties": {
    "addr:full":"1978 Patton Ave Fort Eustis VA 23604",
    "addr:housenumber":"1978",
    "addr:postcode":"23604",
    "addr:street":"Patton Ave Fort",
    "iso:country":"US",
    "sg:address":"1978 Patton Ave",
    "sg:city":"Fort Eustis",
    "sg:classifiers":[
        {
            "category":"Professional",
            "type":"Services"
        }
    ],
    "sg:phone":"+1 757 888 6540",
    "sg:postcode":"23604",
    "sg:province":"VA",
    "wof:name":"Lori Vanwychen",
    "wof:placetype":"venue"
},
  "geometry": {"coordinates":[-76.57235799999999,37.147606],"type":"Point"}
}