{
  "type": "Feature",
  "properties": {
    "addr:full":"502 5th St SW Roanoke VA 24016",
    "addr:housenumber":"502",
    "addr:postcode":"24016",
    "addr:street":"5Th St Sw",
    "iso:country":"US",
    "sg:address":"502 5th St SW",
    "sg:city":"Roanoke",
    "sg:classifiers":[
        {
            "category":"Manufacturing",
            "subcategory":"Chemicals & Compounds",
            "type":"Manufacturing & Wholesale Goods"
        }
    ],
    "sg:phone":"+1 540 344 3247",
    "sg:postcode":"24016",
    "sg:province":"VA",
    "sg:tags":[
        "plasma",
        "center"
    ],
    "wof:name":"Roanoke Plasma Co",
    "wof:placetype":"venue"
},
  "geometry": {"coordinates":[-79.950136,37.269207],"type":"Point"}
}