{
  "type": "Feature",
  "properties": {
    "iso:country":"US",
    "sg:address":"3601 Pruden Blvd",
    "sg:city":"Suffolk",
    "sg:classifiers":[
        {
            "category":"Wholesale",
            "subcategory":"Machinery & Supplies",
            "type":"Manufacturing & Wholesale Goods"
        }
    ],
    "sg:phone":"+1 757 934 2395",
    "sg:postcode":"23434",
    "sg:province":"VA",
    "sg:tags":[
        "equipment",
        "welding"
    ],
    "wof:name":"Arcet",
    "wof:placetype":"venue"
},
  "geometry": {"coordinates":[-76.62555399999999,36.780525],"type":"Point"}
}