{
  "type": "Feature",
  "properties": {
    "iso:country":"US",
    "sg:address":"125 William Richmond",
    "sg:city":"Williamsburg",
    "sg:classifiers":[
        {
            "category":"Health Services",
            "subcategory":"Clinic",
            "type":"Services"
        }
    ],
    "sg:phone":"+1 757 565 5595",
    "sg:postcode":"23185",
    "sg:province":"VA",
    "wof:name":"Healthcare Enterprises",
    "wof:placetype":"venue"
},
  "geometry": {"coordinates":[-76.694233,37.232857],"type":"Point"}
}