{
  "type": "Feature",
  "properties": {
    "addr:full":"7605 Compton Rd Richmond VA 23228",
    "addr:housenumber":"7605",
    "addr:postcode":"23228",
    "addr:street":"Compton Rd",
    "iso:country":"US",
    "sg:address":"7605 Compton Rd",
    "sg:city":"Richmond",
    "sg:classifiers":[
        {
            "category":"Home & Garden",
            "subcategory":"Building Materials",
            "type":"Retail Goods"
        }
    ],
    "sg:phone":"+1 804 515 8866",
    "sg:postcode":"23228",
    "sg:province":"VA",
    "sg:tags":[
        "screen",
        "window"
    ],
    "wof:name":"Listing Screen & Graphics Inc",
    "wof:placetype":"venue"
},
  "geometry": {"coordinates":[-77.49802099999999,37.619013],"type":"Point"}
}