{
  "type": "Feature",
  "properties": {
    "iso:country":"US",
    "sg:address":"7785 Ballston Dr",
    "sg:city":"Springfield",
    "sg:classifiers":[
        {
            "category":"Social Services",
            "subcategory":"Child Care",
            "type":"Services"
        }
    ],
    "sg:phone":"+1 703 451 5602",
    "sg:postcode":"22153",
    "sg:province":"VA",
    "sg:tags":[
        "day"
    ],
    "wof:name":"Sekandary Najmia",
    "wof:placetype":"venue"
},
  "geometry": {"coordinates":[-77.21343,38.747313],"type":"Point"}
}