{
  "type": "Feature",
  "properties": {
    "addr:full":"915 S Washington St Alexandria VA 22314",
    "addr:housenumber":"915",
    "addr:postcode":"22314",
    "addr:street":"S Washington St",
    "iso:country":"US",
    "sg:address":"915 S Washington St",
    "sg:city":"Alexandria",
    "sg:classifiers":[
        {
            "category":"Professional",
            "subcategory":"Art Services",
            "type":"Services"
        }
    ],
    "sg:phone":"+1 703 838 5714",
    "sg:postcode":"22314",
    "sg:province":"VA",
    "sg:tags":[
        "commercial",
        "design"
    ],
    "wof:name":"RE Studios",
    "wof:placetype":"venue"
},
  "geometry": {"coordinates":[-77.04922500000001,38.794922],"type":"Point"}
}