{
  "type": "Feature",
  "properties": {
    "addr:full":"8220 Meadowbridge Rd Mechanicsville VA 23116",
    "addr:housenumber":"8220",
    "addr:postcode":"23116",
    "addr:street":"Meadowbridge Rd",
    "iso:country":"US",
    "sg:address":"8220 Meadowbridge Rd",
    "sg:city":"Mechanicsville",
    "sg:classifiers":[
        {
            "category":"Health Services",
            "subcategory":"Doctor",
            "type":"Services"
        }
    ],
    "sg:phone":"+1 804 746 8020",
    "sg:postcode":"23116",
    "sg:province":"VA",
    "sg:tags":[
        "physician",
        "surgeon",
        "medical"
    ],
    "wof:name":"Hanover Endocrinology Assoc",
    "wof:placetype":"venue"
},
  "geometry": {"coordinates":[-77.385617,37.626661],"type":"Point"}
}