{
  "type": "Feature",
  "properties": {
    "iso:country":"US",
    "sg:address":"517 S Washington St",
    "sg:city":"Alexandria",
    "sg:classifiers":[
        {
            "category":"Professional",
            "subcategory":"Lawyer & Legal Services",
            "type":"Services"
        }
    ],
    "sg:phone":"+1 703 683 3044",
    "sg:postcode":"22314",
    "sg:province":"VA",
    "sg:tags":[
        "firm",
        "law"
    ],
    "wof:name":"Pierson & Burnett",
    "wof:placetype":"venue"
},
  "geometry": {"coordinates":[-77.048226,38.79957],"type":"Point"}
}