{
  "type": "Feature",
  "properties": {
    "addr:full":"6166 Leesburg Pike Falls Church VA 22044",
    "addr:housenumber":"6166",
    "addr:postcode":"22044",
    "addr:street":"Leesburg Pike",
    "iso:country":"US",
    "sg:address":"6166 Leesburg Pike",
    "sg:city":"Falls Church",
    "sg:classifiers":[
        {
            "category":"Professional",
            "subcategory":"Business Services",
            "type":"Services"
        }
    ],
    "sg:phone":"+1 703 534 7380",
    "sg:postcode":"22044",
    "sg:province":"VA",
    "sg:tags":[
        "telecom"
    ],
    "wof:name":"Fastone",
    "wof:placetype":"venue"
},
  "geometry": {"coordinates":[-77.148786,38.863113],"type":"Point"}
}