{
  "type": "Feature",
  "properties": {
    "addr:full":"10911 Main St Fairfax VA 22030",
    "addr:housenumber":"10911",
    "addr:postcode":"22030",
    "addr:street":"Main St",
    "iso:country":"US",
    "sg:address":"10911 Main St",
    "sg:city":"Fairfax",
    "sg:classifiers":[
        {
            "category":"Food & Beverages",
            "subcategory":"Groceries & Convenience Stores",
            "type":"Retail Goods"
        }
    ],
    "sg:phone":"+1 703 359 3559",
    "sg:postcode":"22030",
    "sg:province":"VA",
    "wof:name":"7-Eleven",
    "wof:placetype":"venue"
},
  "geometry": {"coordinates":[-77.322722,38.852247],"type":"Point"}
}