{
  "type": "Feature",
  "properties": {
    "addr:full":"2157 N Pollard St Arlington VA 22207",
    "addr:housenumber":"2157",
    "addr:postcode":"22207",
    "addr:street":"N Pollard St",
    "iso:country":"US",
    "sg:address":"2157 N Pollard St",
    "sg:city":"Arlington",
    "sg:classifiers":[
        {
            "category":"Shopping",
            "subcategory":"Pets & Pet Supplies",
            "type":"Retail Goods"
        }
    ],
    "sg:phone":"+1 703 465 4481",
    "sg:postcode":"22207",
    "sg:province":"VA",
    "sg:tags":[
        "food"
    ],
    "sg:website":"http://maxandruffys.com",
    "wof:name":"Max & Ruffy's",
    "wof:placetype":"venue"
},
  "geometry": {"coordinates":[-77.106449,38.898758],"type":"Point"}
}