{
  "type": "Feature",
  "properties": {
    "addr:full":"111 Commerce Park Rd Franklin VA 23851",
    "addr:housenumber":"111",
    "addr:postcode":"23851",
    "addr:street":"Commerce Park Rd",
    "iso:country":"US",
    "sg:address":"111 Commerce Park Rd",
    "sg:city":"Franklin",
    "sg:classifiers":[
        {
            "category":"Home & Garden",
            "subcategory":"Garden Supply",
            "type":"Retail Goods"
        }
    ],
    "sg:phone":"+1 757 562 0186",
    "sg:postcode":"23851",
    "sg:province":"VA",
    "sg:tags":[
        "center"
    ],
    "wof:name":"Franklin Garden Ctr",
    "wof:placetype":"venue"
},
  "geometry": {"coordinates":[-76.94658800000001,36.669104],"type":"Point"}
}