{
  "type": "Feature",
  "properties": {
    "iso:country":"US",
    "sg:address":"28 Bridgehampton Pl",
    "sg:city":"Richmond",
    "sg:classifiers":[
        {
            "category":"Social Services",
            "type":"Services"
        }
    ],
    "sg:phone":"+1 804 740 2600",
    "sg:postcode":"23229",
    "sg:province":"VA",
    "wof:name":"Youre About To Lose It",
    "wof:placetype":"venue"
},
  "geometry": {"coordinates":[-77.569041,37.582673],"type":"Point"}
}