{
  "type": "Feature",
  "properties": {
    "addr:full":"20250 Rustic Ln Abingdon VA 24210",
    "addr:housenumber":"20250",
    "addr:postcode":"24210",
    "addr:street":"Rustic Ln",
    "iso:country":"US",
    "sg:address":"20250 Rustic Ln",
    "sg:city":"Abingdon",
    "sg:classifiers":[
        {
            "category":"Building & Trades",
            "subcategory":"Construction",
            "type":"Services"
        }
    ],
    "sg:phone":"+1 276 628 1402",
    "sg:postcode":"24210",
    "sg:province":"VA",
    "sg:tags":[
        "paving",
        "contractor"
    ],
    "wof:name":"W-L Construction Paving Inc",
    "wof:placetype":"venue"
},
  "geometry": {"coordinates":[-82.00826000000001,36.71937],"type":"Point"}
}