{
  "type": "Feature",
  "properties": {
    "iso:country":"US",
    "sg:address":"4637 Denpat Ct",
    "sg:city":"Annandale",
    "sg:classifiers":[
        {
            "category":"Professional",
            "subcategory":"Business Services",
            "type":"Services"
        }
    ],
    "sg:phone":"+1 703 425 5271",
    "sg:postcode":"22003",
    "sg:province":"VA",
    "wof:name":"Smithson Interiors",
    "wof:placetype":"venue"
},
  "geometry": {"coordinates":[-77.241119,38.82302],"type":"Point"}
}