{
  "type": "Feature",
  "properties": {
    "addr:full":"2819 N Parham Rd Richmond VA 23294",
    "addr:housenumber":"2819",
    "addr:postcode":"23294",
    "addr:street":"N Parham Rd",
    "iso:country":"US",
    "sg:address":"2819 N Parham Rd",
    "sg:city":"Richmond",
    "sg:classifiers":[
        {
            "category":"Professional",
            "subcategory":"Lawyer & Legal Services",
            "type":"Services"
        }
    ],
    "sg:phone":"+1 804 747 4547",
    "sg:postcode":"23294",
    "sg:province":"VA",
    "wof:name":"Hunton Eppa",
    "wof:placetype":"venue"
},
  "geometry": {"coordinates":[-77.546159,37.628157],"type":"Point"}
}