{
  "type": "Feature",
  "properties": {
    "iso:country":"US",
    "sg:address":"4317 Cromwell Ct",
    "sg:city":"Chesapeake",
    "sg:classifiers":[
        {
            "category":"Building & Trades",
            "subcategory":"Construction",
            "type":"Services"
        }
    ],
    "sg:phone":"+1 757 361 0290",
    "sg:postcode":"23325",
    "sg:province":"VA",
    "wof:name":"Indian River Aqua Source",
    "wof:placetype":"venue"
},
  "geometry": {"coordinates":[-76.224993,36.815908],"type":"Point"}
}