{
  "type": "Feature",
  "properties": {
    "addr:full":"5531 N Lee Hwy Arlington VA 22207",
    "addr:housenumber":"5531",
    "addr:postcode":"22207",
    "addr:street":"N Lee Hwy",
    "iso:country":"US",
    "sg:address":"5531 N Lee Hwy",
    "sg:city":"Arlington",
    "sg:classifiers":[
        {
            "category":"Building & Trades",
            "subcategory":"Construction",
            "type":"Services"
        }
    ],
    "sg:phone":"+1 703 534 3036",
    "sg:postcode":"22207",
    "sg:province":"VA",
    "sg:tags":[
        "home",
        "house",
        "improvement"
    ],
    "wof:name":"Innovative Management & Maint",
    "wof:placetype":"venue"
},
  "geometry": {"coordinates":[-77.140062,38.895877],"type":"Point"}
}