{
  "type": "Feature",
  "properties": {
    "iso:country":"US",
    "sg:address":"6011 York Rd",
    "sg:city":"Richmond",
    "sg:classifiers":[
        {
            "category":"Education",
            "subcategory":"School",
            "type":"Public Place"
        }
    ],
    "sg:phone":"+1 804 288 1994",
    "sg:postcode":"23226",
    "sg:province":"VA",
    "sg:website":"www.saintbridget.org",
    "wof:name":"St Bridgets School",
    "wof:placetype":"venue"
},
  "geometry": {"coordinates":[-77.524068,37.57427],"type":"Point"}
}