{
  "type": "Feature",
  "properties": {
    "addr:full":"130 Ron Springs Dr Williamsburg VA 23185",
    "addr:housenumber":"130",
    "addr:postcode":"23185",
    "addr:street":"Ron Springs Dr",
    "iso:country":"US",
    "sg:address":"130 Ron Springs Dr",
    "sg:city":"Williamsburg",
    "sg:classifiers":[
        {
            "category":"Utilities",
            "subcategory":"Refuse",
            "type":"Services"
        }
    ],
    "sg:phone":"+1 757 253 0519",
    "sg:postcode":"23185",
    "sg:province":"VA",
    "sg:tags":[
        "garbage",
        "system",
        "collection"
    ],
    "wof:name":"Suburban Disposal Company Inc",
    "wof:placetype":"venue"
},
  "geometry": {"coordinates":[-76.627653,37.214541],"type":"Point"}
}