{
  "type": "Feature",
  "properties": {
    "iso:country":"US",
    "sg:address":"301 N Allen Ave",
    "sg:city":"Richmond",
    "sg:classifiers":[
        {
            "category":"Insurance",
            "subcategory":"Insurance Agent",
            "type":"Services"
        }
    ],
    "sg:phone":"+1 804 359 6525",
    "sg:postcode":"23220",
    "sg:province":"VA",
    "wof:name":"Kenneth Fortee",
    "wof:placetype":"venue"
},
  "geometry": {"coordinates":[-77.46091699999999,37.552755],"type":"Point"}
}