{
  "type": "Feature",
  "properties": {
    "iso:country":"US",
    "sg:address":"174 Garber Ln",
    "sg:city":"Winchester",
    "sg:classifiers":[
        {
            "category":"Education",
            "subcategory":"Special Training",
            "type":"Public Place"
        }
    ],
    "sg:phone":"+1 540 450 0139",
    "sg:postcode":"22602",
    "sg:province":"VA",
    "sg:tags":[
        "program"
    ],
    "wof:name":"Wilsons Safety Training",
    "wof:placetype":"venue"
},
  "geometry": {"coordinates":[-78.160263,39.158811],"type":"Point"}
}