{
  "type": "Feature",
  "properties": {
    "iso:country":"US",
    "sg:address":"2144 Aquia Dr",
    "sg:city":"Stafford",
    "sg:classifiers":[
        {
            "category":"Social Services",
            "type":"Services"
        }
    ],
    "sg:phone":"+1 540 659 6845",
    "sg:postcode":"22554",
    "sg:province":"VA",
    "wof:name":"Assistant Stork",
    "wof:placetype":"venue"
},
  "geometry": {"coordinates":[-77.379392,38.465803],"type":"Point"}
}