{
  "type": "Feature",
  "properties": {
    "iso:country":"US",
    "sg:address":"913 Lynchburg Ave",
    "sg:city":"Brookneal",
    "sg:phone":"+1 434 376 2418",
    "sg:postcode":"24528",
    "sg:province":"VA",
    "sg:tags":[
        "gas"
    ],
    "wof:name":"Francis Oil Co",
    "wof:placetype":"venue"
},
  "geometry": {"coordinates":[-78.948841,37.056384],"type":"Point"}
}