{
  "type": "Feature",
  "properties": {
    "iso:country":"US",
    "sg:address":"400 11th St S",
    "sg:city":"Arlington",
    "sg:classifiers":[
        {
            "category":"Real Estate",
            "subcategory":"Real Estate Operator",
            "type":"Services"
        }
    ],
    "sg:phone":"+1 703 414 0001",
    "sg:postcode":"22202",
    "sg:province":"VA",
    "sg:tags":[
        "apartment"
    ],
    "wof:name":"Ksi Servces Inc",
    "wof:placetype":"venue"
},
  "geometry": {"coordinates":[-77.053417,38.863664],"type":"Point"}
}