{
  "type": "Feature",
  "properties": {
    "addr:full":"429 Woodlawn Dr Danville VA 24541",
    "addr:housenumber":"429",
    "addr:postcode":"24541",
    "addr:street":"Woodlawn Dr",
    "iso:country":"US",
    "sg:address":"429 Woodlawn Dr",
    "sg:city":"Danville",
    "sg:classifiers":[
        {
            "category":"Building & Trades",
            "subcategory":"Construction",
            "type":"Services"
        }
    ],
    "sg:phone":"+1 434 822 0127",
    "sg:postcode":"24541",
    "sg:province":"VA",
    "sg:tags":[
        "contractor",
        "painting",
        "hanging"
    ],
    "wof:name":"Keen Painting & Papering",
    "wof:placetype":"venue"
},
  "geometry": {"coordinates":[-79.459228,36.600322],"type":"Point"}
}