{
  "type": "Feature",
  "properties": {
    "iso:country":"US",
    "sg:address":"4106 Wheeler Ave",
    "sg:city":"Alexandria",
    "sg:classifiers":[
        {
            "category":"Restaurant",
            "type":"Food & Drink"
        },
        {
            "category":"Food & Beverages",
            "subcategory":"Groceries & Convenience Stores",
            "type":"Retail Goods"
        }
    ],
    "sg:phone":"+1 703 751 8600",
    "sg:postcode":"22304",
    "sg:province":"VA",
    "wof:name":"Cuisine Solutions Culinary Div",
    "wof:placetype":"venue"
},
  "geometry": {"coordinates":[-77.10133,38.808349],"type":"Point"}
}