{
  "type": "Feature",
  "properties": {
    "addr:full":"27 Hollis Wood Dr Hampton VA 23666",
    "addr:housenumber":"27",
    "addr:postcode":"23666",
    "addr:street":"Hollis Wood Dr",
    "iso:country":"US",
    "sg:address":"27 Hollis Wood Dr",
    "sg:city":"Hampton",
    "sg:classifiers":[
        {
            "category":"Wholesale",
            "subcategory":"Non-durable Goods",
            "type":"Manufacturing & Wholesale Goods"
        }
    ],
    "sg:phone":"+1 757 838 4927",
    "sg:postcode":"23666",
    "sg:province":"VA",
    "sg:tags":[
        "mail",
        "house"
    ],
    "wof:name":"BP",
    "wof:placetype":"venue"
},
  "geometry": {"coordinates":[-76.430267,37.057759],"type":"Point"}
}