{
  "type": "Feature",
  "properties": {
    "iso:country":"US",
    "sg:address":"639 N Coalter St",
    "sg:city":"Staunton",
    "sg:classifiers":[
        {
            "category":"Health Services",
            "subcategory":"Chiropractor",
            "type":"Services"
        }
    ],
    "sg:phone":"+1 540 885 8877",
    "sg:postcode":"24401",
    "sg:province":"VA",
    "wof:name":"Mask Chiropractic Clinic",
    "wof:placetype":"venue"
},
  "geometry": {"coordinates":[-79.062178,38.159243],"type":"Point"}
}