{
  "type": "Feature",
  "properties": {
    "addr:full":"6115 Fort Ave Lynchburg VA 24502",
    "addr:housenumber":"6115",
    "addr:postcode":"24502",
    "addr:street":"Fort Ave",
    "iso:country":"US",
    "sg:address":"6115 Fort Ave",
    "sg:city":"Lynchburg",
    "sg:classifiers":[
        {
            "category":"Shopping",
            "subcategory":"Used Merchandise",
            "type":"Retail Goods"
        }
    ],
    "sg:phone":"+1 434 845 7296",
    "sg:postcode":"24502",
    "sg:province":"VA",
    "sg:tags":[
        "pawnbroker"
    ],
    "wof:name":"Lynchburg Pawn Inc",
    "wof:placetype":"venue"
},
  "geometry": {"coordinates":[-79.197547,37.369959],"type":"Point"}
}