{
  "type": "Feature",
  "properties": {
    "addr:full":"2687 Ridge Rd Callao VA 22435",
    "addr:housenumber":"2687",
    "addr:postcode":"22435",
    "addr:street":"Ridge Rd",
    "iso:country":"US",
    "sg:address":"2687 Ridge Rd",
    "sg:city":"Callao",
    "sg:classifiers":[
        {
            "category":"Professional",
            "type":"Services"
        }
    ],
    "sg:phone":"+1 804 529 6272",
    "sg:postcode":"22435",
    "sg:province":"VA",
    "wof:name":"Material Girl",
    "wof:placetype":"venue"
},
  "geometry": {"coordinates":[-76.55099800000001,37.92149],"type":"Point"}
}