{
  "type": "Feature",
  "properties": {
    "addr:full":"1816 Rio Hill Ctr Charlottesville VA 22901",
    "addr:housenumber":"1816",
    "addr:postcode":"22901",
    "addr:street":"Rio Hill",
    "iso:country":"US",
    "sg:address":"1816 Rio Hill Ctr",
    "sg:city":"Charlottesville",
    "sg:classifiers":[
        {
            "category":"Education",
            "subcategory":"Music School",
            "type":"Public Place"
        }
    ],
    "sg:phone":"+1 434 974 1555",
    "sg:postcode":"22901",
    "sg:province":"VA",
    "sg:tags":[
        "instrument",
        "teacher",
        "musical"
    ],
    "wof:name":"Stacy's Music Shop",
    "wof:placetype":"venue"
},
  "geometry": {"coordinates":[-78.47110000000001,38.087601],"type":"Point"}
}