{
  "type": "Feature",
  "properties": {
    "addr:full":"1197 Blue Rock Trl Vernon Hill VA 24597",
    "addr:housenumber":"1197",
    "addr:postcode":"24597",
    "addr:street":"Blue Rock Trl",
    "iso:country":"US",
    "sg:address":"1197 Blue Rock Trl",
    "sg:city":"Vernon Hill",
    "sg:classifiers":[
        {
            "category":"Organizations",
            "subcategory":"Religious Organization",
            "type":"Services"
        }
    ],
    "sg:phone":"+1 434 476 4260",
    "sg:postcode":"24597",
    "sg:province":"VA",
    "sg:tags":[
        "church"
    ],
    "wof:name":"Christ Temple Holiness Church",
    "wof:placetype":"venue"
},
  "geometry": {"coordinates":[-79.047175,36.817293],"type":"Point"}
}