{
  "type": "Feature",
  "properties": {
    "iso:country":"US",
    "sg:address":"4992 Euclid Rd",
    "sg:city":"Virginia Beach",
    "sg:classifiers":[
        {
            "category":"Organizations",
            "subcategory":"Religious Organization",
            "type":"Services"
        }
    ],
    "sg:phone":"+1 757 499 8449",
    "sg:postcode":"23462",
    "sg:province":"VA",
    "sg:tags":[
        "church"
    ],
    "wof:name":"New Beginning Deliverance",
    "wof:placetype":"venue"
},
  "geometry": {"coordinates":[-76.151472,36.841702],"type":"Point"}
}