{
  "type": "Feature",
  "properties": {
    "addr:full":"613 Gladesdale Dr Chesapeake VA 23322",
    "addr:housenumber":"613",
    "addr:postcode":"23322",
    "addr:street":"Gladesdale Dr",
    "iso:country":"US",
    "sg:address":"613 Gladesdale Dr",
    "sg:city":"Chesapeake",
    "sg:classifiers":[
        {
            "category":"Freight",
            "type":"Transportation"
        }
    ],
    "sg:phone":"+1 757 482 4753",
    "sg:postcode":"23322",
    "sg:province":"VA",
    "sg:tags":[
        "operator",
        "local",
        "trucking"
    ],
    "wof:name":"J Brugger Trucking",
    "wof:placetype":"venue"
},
  "geometry": {"coordinates":[-76.20942100000001,36.69166],"type":"Point"}
}