{
  "type": "Feature",
  "properties": {
    "addr:full":"14510 Spriggs Rd Dale City VA 22193",
    "addr:postcode":"14510;22193",
    "addr:street":"Spriggs Rd Dale",
    "iso:country":"US",
    "sg:address":"14510 Spriggs Rd",
    "sg:city":"Dale City",
    "sg:classifiers":[
        {
            "category":"Organizations",
            "subcategory":"Religious Organization",
            "type":"Services"
        }
    ],
    "sg:phone":"+1 703 680 6629",
    "sg:postcode":"22193",
    "sg:province":"VA",
    "sg:tags":[
        "church"
    ],
    "sg:website":"www.hbchcs.org",
    "wof:name":"Heritage Baptist Church",
    "wof:placetype":"venue"
},
  "geometry": {"coordinates":[-77.38096299999999,38.640245],"type":"Point"}
}