{
  "type": "Feature",
  "properties": {
    "iso:country":"US",
    "sg:address":"1775 Duke St C",
    "sg:city":"Alexandria",
    "sg:classifiers":[
        {
            "category":"Transit Center",
            "subcategory":"Passenger",
            "type":"Transportation"
        },
        {
            "category":"Local Transit",
            "type":"Transportation"
        }
    ],
    "sg:phone":"+1 703 299 6227",
    "sg:postcode":"22314",
    "sg:province":"VA",
    "sg:tags":[
        "line",
        "public"
    ],
    "wof:name":"Old Town Transit Shop",
    "wof:placetype":"venue"
},
  "geometry": {"coordinates":[-77.060819,38.804458],"type":"Point"}
}