{
  "type": "Feature",
  "properties": {
    "addr:full":"13530 Wilt Store Rd Leesburg VA 20176",
    "addr:housenumber":"13530",
    "addr:postcode":"20176",
    "addr:street":"Wilt Store Rd",
    "iso:country":"US",
    "sg:address":"13530 Wilt Store Rd",
    "sg:city":"Leesburg",
    "sg:classifiers":[
        {
            "category":"Professional",
            "subcategory":"Management & Consulting",
            "type":"Services"
        }
    ],
    "sg:phone":"+1 703 777 2771",
    "sg:postcode":"20176",
    "sg:province":"VA",
    "sg:tags":[
        "consultant",
        "computer"
    ],
    "wof:name":"S S C Inc",
    "wof:placetype":"venue"
},
  "geometry": {"coordinates":[-77.556037,39.237298],"type":"Point"}
}