{
  "type": "Feature",
  "properties": {
    "iso:country":"US",
    "sg:address":"3022 Sylvan Dr",
    "sg:city":"Falls Church",
    "sg:classifiers":[
        {
            "category":"Professional",
            "subcategory":"Management & Consulting",
            "type":"Services"
        }
    ],
    "sg:phone":"+1 703 536 7078",
    "sg:postcode":"22042",
    "sg:province":"VA",
    "sg:tags":[
        "business"
    ],
    "wof:name":"Bjorklund Communications",
    "wof:placetype":"venue"
},
  "geometry": {"coordinates":[-77.171395,38.867163],"type":"Point"}
}