{
  "type": "Feature",
  "properties": {
    "addr:full":"222 Dry Rd Wytheville VA 24374",
    "addr:housenumber":"222",
    "addr:postcode":"24374",
    "addr:street":"Dry Rd",
    "iso:country":"US",
    "sg:address":"222 Dry Rd",
    "sg:city":"Wytheville",
    "sg:classifiers":[
        {
            "category":"Professional",
            "subcategory":"Management & Consulting",
            "type":"Services"
        }
    ],
    "sg:phone":"+1 276 228 5689",
    "sg:postcode":"24374",
    "sg:province":"VA",
    "sg:tags":[
        "specialist",
        "industry",
        "consultant"
    ],
    "wof:name":"Polymer Development LLC",
    "wof:placetype":"venue"
},
  "geometry": {"coordinates":[-81.202039,36.810801],"type":"Point"}
}