{
  "type": "Feature",
  "properties": {
    "addr:full":"1322 W Broad St Richmond VA 23220",
    "addr:housenumber":"1322",
    "addr:postcode":"23220",
    "addr:street":"W Broad St",
    "iso:country":"US",
    "sg:address":"1322 W Broad St",
    "sg:city":"Richmond",
    "sg:classifiers":[
        {
            "category":"Professional",
            "subcategory":"Art Services",
            "type":"Services"
        }
    ],
    "sg:phone":"+1 804 359 0506",
    "sg:postcode":"23220",
    "sg:province":"VA",
    "sg:tags":[
        "photography",
        "commercial"
    ],
    "wof:name":"Samardge Photographics",
    "wof:placetype":"venue"
},
  "geometry": {"coordinates":[-77.454596,37.55314],"type":"Point"}
}