{
  "type": "Feature",
  "properties": {
    "addr:full":"6164 Mitch Ln Smithfield VA 23430",
    "addr:housenumber":"6164",
    "addr:postcode":"23430",
    "addr:street":"Mitch Ln",
    "iso:country":"US",
    "sg:address":"6164 Mitch Ln",
    "sg:city":"Smithfield",
    "sg:classifiers":[
        {
            "category":"Retail",
            "subcategory":"Auto Repair",
            "type":"Services"
        }
    ],
    "sg:phone":"+1 757 357 6849",
    "sg:postcode":"23430",
    "sg:province":"VA",
    "sg:tags":[
        "repairing",
        "automobile"
    ],
    "wof:name":"Joe's Alignment & Exhaust",
    "wof:placetype":"venue"
},
  "geometry": {"coordinates":[-76.67586300000001,37.056155],"type":"Point"}
}