{
  "type": "Feature",
  "properties": {
    "addr:full":"9555 Kings Charter Dr Ashland VA 23005",
    "addr:housenumber":"9555",
    "addr:postcode":"23005",
    "addr:street":"Kings Charter Dr",
    "iso:country":"US",
    "sg:address":"9555 Kings Charter Dr",
    "sg:city":"Ashland",
    "sg:classifiers":[
        {
            "category":"Shopping",
            "subcategory":"Musical Instruments",
            "type":"Retail Goods"
        }
    ],
    "sg:phone":"+1 804 550 1233",
    "sg:postcode":"23005",
    "sg:province":"VA",
    "wof:name":"Atlee Music Ctr",
    "wof:placetype":"venue"
},
  "geometry": {"coordinates":[-77.436245,37.692731],"type":"Point"}
}