{
  "type": "Feature",
  "properties": {
    "addr:full":"110 W Washington St Petersburg VA 23803",
    "addr:housenumber":"110",
    "addr:postcode":"23803",
    "addr:street":"W Washington",
    "iso:country":"US",
    "sg:address":"110 W Washington St",
    "sg:city":"Petersburg",
    "sg:classifiers":[
        {
            "category":"Food & Beverages",
            "subcategory":"Groceries & Convenience Stores",
            "type":"Retail Goods"
        }
    ],
    "sg:phone":"+1 804 861 4466",
    "sg:postcode":"23803",
    "sg:province":"VA",
    "wof:name":"Market Place Convenient Store",
    "wof:placetype":"venue"
},
  "geometry": {"coordinates":[-77.406536,37.227146],"type":"Point"}
}