{
  "type": "Feature",
  "properties": {
    "addr:full":"19568 Franklin Tpke Chatham VA 24531",
    "addr:housenumber":"19568",
    "addr:postcode":"24531",
    "addr:street":"Franklin Tpke",
    "iso:country":"US",
    "sg:address":"19568 Franklin Tpke",
    "sg:city":"Chatham",
    "sg:classifiers":[
        {
            "category":"Wholesale",
            "subcategory":"Chemicals & Plastics",
            "type":"Manufacturing & Wholesale Goods"
        }
    ],
    "sg:phone":"+1 434 724 7534",
    "sg:postcode":"24531",
    "sg:province":"VA",
    "wof:name":"Rey-Chem Co",
    "wof:placetype":"venue"
},
  "geometry": {"coordinates":[-79.581675,36.788652],"type":"Point"}
}