{
  "type": "Feature",
  "properties": {
    "addr:full":"10702 Fairfax Blvd Fairfax VA 22030",
    "addr:housenumber":"10702",
    "addr:postcode":"22030",
    "addr:street":"Fairfax Blvd",
    "iso:country":"US",
    "sg:address":"10702 Fairfax Blvd",
    "sg:city":"Fairfax",
    "sg:classifiers":[
        {
            "category":"Fast Food",
            "type":"Food & Drink"
        },
        {
            "category":"Coffee & Tea",
            "type":"Food & Drink"
        },
        {
            "category":"Restaurant",
            "type":"Food & Drink"
        },
        {
            "category":"Bakery",
            "type":"Food & Drink"
        },
        {
            "category":"Food & Beverages",
            "subcategory":"Groceries & Convenience Stores",
            "type":"Retail Goods"
        }
    ],
    "sg:phone":"+1 703 934 1470",
    "sg:postcode":"22030",
    "sg:province":"VA",
    "sg:tags":[
        "shop",
        "sandwich",
        "espresso",
        "take"
    ],
    "sg:website":"http://www.panerabread.com",
    "wof:name":"Panera Bread",
    "wof:placetype":"venue"
},
  "geometry": {"coordinates":[-77.31407,38.855884],"type":"Point"}
}