{
  "type": "Feature",
  "properties": {
    "addr:full":"406 E Main St Charlottesville VA 22902",
    "addr:housenumber":"406",
    "addr:postcode":"22902",
    "addr:street":"E Main St",
    "iso:country":"US",
    "sg:address":"406 E Main St",
    "sg:city":"Charlottesville",
    "sg:classifiers":[
        {
            "category":"Home & Garden",
            "subcategory":"Home Furnishings",
            "type":"Retail Goods"
        }
    ],
    "sg:phone":"+1 434 293 3368",
    "sg:postcode":"22902",
    "sg:province":"VA",
    "sg:tags":[
        "curtain",
        "made",
        "drapery"
    ],
    "wof:name":"Simin Tailoring",
    "wof:placetype":"venue"
},
  "geometry": {"coordinates":[-78.478531,38.029767],"type":"Point"}
}