{
  "type": "Feature",
  "properties": {
    "iso:country":"US",
    "sg:address":"8300 Sudley Rd",
    "sg:city":"Manassas",
    "sg:classifiers":[
        {
            "category":"Shopping",
            "subcategory":"Shoes",
            "type":"Retail Goods"
        }
    ],
    "sg:phone":"+1 703 330 0682",
    "sg:postcode":"20109",
    "sg:province":"VA",
    "sg:tags":[
        "store"
    ],
    "wof:name":"Journey's",
    "wof:placetype":"venue"
},
  "geometry": {"coordinates":[-77.503303,38.775071],"type":"Point"}
}