{
  "type": "Feature",
  "properties": {
    "iso:country":"US",
    "sg:address":"2527 Franklin Tpke",
    "sg:city":"Danville",
    "sg:classifiers":[
        {
            "category":"Shopping",
            "subcategory":"Gifts & Souvenirs",
            "type":"Retail Goods"
        }
    ],
    "sg:phone":"+1 434 836 8900",
    "sg:postcode":"24540",
    "sg:province":"VA",
    "sg:tags":[
        "basket",
        "parcel"
    ],
    "wof:name":"All Wrapped Up",
    "wof:placetype":"venue"
},
  "geometry": {"coordinates":[-79.41067700000001,36.656858],"type":"Point"}
}