{
  "type": "Feature",
  "properties": {
    "addr:full":"6008 Margate Ave Virginia Beach VA 23462",
    "addr:housenumber":"6008",
    "addr:postcode":"23462",
    "addr:street":"Margate Ave",
    "iso:country":"US",
    "sg:address":"6008 Margate Ave",
    "sg:city":"Virginia Beach",
    "sg:classifiers":[
        {
            "category":"Freight",
            "type":"Transportation"
        }
    ],
    "sg:phone":"+1 757 552 0157",
    "sg:postcode":"23462",
    "sg:province":"VA",
    "sg:tags":[
        "operator",
        "local",
        "trucking"
    ],
    "wof:name":"M&A Movers & Helpers Inc",
    "wof:placetype":"venue"
},
  "geometry": {"coordinates":[-76.18486900000001,36.861286],"type":"Point"}
}