{
  "type": "Feature",
  "properties": {
    "addr:full":"107 Foxworth Cir Suffolk VA 23434",
    "addr:housenumber":"107",
    "addr:postcode":"23434",
    "addr:street":"Foxworth Cir",
    "iso:country":"US",
    "sg:address":"107 Foxworth Cir",
    "sg:city":"Suffolk",
    "sg:classifiers":[
        {
            "category":"Building & Trades",
            "subcategory":"Construction",
            "type":"Services"
        }
    ],
    "sg:phone":"+1 757 925 0597",
    "sg:postcode":"23434",
    "sg:province":"VA",
    "sg:tags":[
        "contractor"
    ],
    "wof:name":"Cheeks Roofing & Home",
    "wof:placetype":"venue"
},
  "geometry": {"coordinates":[-76.587097,36.772852],"type":"Point"}
}