{
  "type": "Feature",
  "properties": {
    "addr:full":"5590 Leeds Manor Rd Hume VA 22639",
    "addr:housenumber":"5590",
    "addr:postcode":"22639",
    "addr:street":"Leeds Manor Rd",
    "iso:country":"US",
    "sg:address":"5590 Leeds Manor Rd",
    "sg:city":"Hume",
    "sg:classifiers":[
        {
            "category":"Health Services",
            "subcategory":"Doctor",
            "type":"Services"
        }
    ],
    "sg:phone":"+1 540 364 0370",
    "sg:postcode":"22639",
    "sg:province":"VA",
    "sg:tags":[
        "dentist"
    ],
    "wof:name":"Jackson Professional Svc Inc",
    "wof:placetype":"venue"
},
  "geometry": {"coordinates":[-77.995788,38.803446],"type":"Point"}
}