{
  "type": "Feature",
  "properties": {
    "iso:country":"US",
    "sg:address":"3525 Iron Bridge Rd",
    "sg:city":"Richmond",
    "sg:classifiers":[
        {
            "category":"Health Services",
            "subcategory":"Doctor",
            "type":"Services"
        }
    ],
    "sg:phone":"+1 804 275 7477",
    "sg:postcode":"23234",
    "sg:province":"VA",
    "sg:tags":[
        "dentist"
    ],
    "wof:name":"Gregory K Kontopanios DDS/ASC",
    "wof:placetype":"venue"
},
  "geometry": {"coordinates":[-77.487568,37.467645],"type":"Point"}
}