{
  "type": "Feature",
  "properties": {
    "addr:full":"7503 Brook Rd Richmond VA 23227",
    "addr:housenumber":"7503",
    "addr:postcode":"23227",
    "addr:street":"Brook Rd",
    "iso:country":"US",
    "sg:address":"7503 Brook Rd",
    "sg:city":"Richmond",
    "sg:classifiers":[
        {
            "category":"Health Services",
            "subcategory":"Chiropractor",
            "type":"Services"
        }
    ],
    "sg:phone":"+1 804 261 6685",
    "sg:postcode":"23227",
    "sg:province":"VA",
    "wof:name":"Rulli Chiropractic Clinic",
    "wof:placetype":"venue"
},
  "geometry": {"coordinates":[-77.45818199999999,37.626968],"type":"Point"}
}