{
  "type": "Feature",
  "properties": {
    "addr:full":"228 N Main St Farmville VA 23901",
    "addr:housenumber":"228",
    "addr:postcode":"23901",
    "addr:street":"N Main St",
    "iso:country":"US",
    "sg:address":"228 N Main St",
    "sg:city":"Farmville",
    "sg:classifiers":[
        {
            "category":"Shopping",
            "subcategory":"Hobbies, Toys, & Games",
            "type":"Retail Goods"
        }
    ],
    "sg:phone":"+1 434 392 6723",
    "sg:postcode":"23901",
    "sg:province":"VA",
    "wof:name":"Country Nook",
    "wof:placetype":"venue"
},
  "geometry": {"coordinates":[-78.391547,37.303395],"type":"Point"}
}