{
  "type": "Feature",
  "properties": {
    "addr:full":"6052 Burke Commons Rd Burke VA 22015",
    "addr:housenumber":"6052",
    "addr:postcode":"22015",
    "addr:street":"Burke Commons Rd",
    "iso:country":"US",
    "sg:address":"6052 Burke Commons Rd",
    "sg:city":"Burke",
    "sg:classifiers":[
        {
            "category":"Banks & Credit Unions",
            "subcategory":"Bank",
            "type":"Services"
        }
    ],
    "sg:phone":"+1 703 838 3540",
    "sg:postcode":"22015",
    "sg:province":"VA",
    "wof:name":"Sun Trust Bank",
    "wof:placetype":"venue"
},
  "geometry": {"coordinates":[-77.29915800000001,38.78751],"type":"Point"}
}