{
  "type": "Feature",
  "properties": {
    "iso:country":"US",
    "sg:address":"4 E Virginia Beach Blvd",
    "sg:city":"Norfolk",
    "sg:classifiers":[
        {
            "category":"Building & Trades",
            "subcategory":"Construction",
            "type":"Services"
        }
    ],
    "sg:phone":"+1 757 313 7400",
    "sg:postcode":"23504",
    "sg:province":"VA",
    "sg:tags":[
        "heating",
        "specialty",
        "contractor"
    ],
    "wof:name":"National Air Filtration Assoc",
    "wof:placetype":"venue"
},
  "geometry": {"coordinates":[-76.276802,36.855289],"type":"Point"}
}