{
  "type": "Feature",
  "properties": {
    "addr:full":"8021 Hampton Blvd Norfolk VA 23505",
    "addr:housenumber":"8021",
    "addr:postcode":"23505",
    "addr:street":"Hampton Blvd",
    "iso:country":"US",
    "sg:address":"8021 Hampton Blvd",
    "sg:city":"Norfolk",
    "sg:classifiers":[
        {
            "category":"Banks & Credit Unions",
            "subcategory":"Bank",
            "type":"Services"
        }
    ],
    "sg:phone":"+1 757 624 2813",
    "sg:postcode":"23505",
    "sg:province":"VA",
    "sg:tags":[
        "national",
        "commercial"
    ],
    "wof:name":"Bank Of America",
    "wof:placetype":"venue"
},
  "geometry": {"coordinates":[-76.317629,36.926163],"type":"Point"}
}