{
  "type": "Feature",
  "properties": {
    "addr:full":"43118 Lake Ridge Pl Leesburg VA 20176",
    "addr:housenumber":"43118",
    "addr:postcode":"20176",
    "addr:street":"Lake Ridge Pl",
    "iso:country":"US",
    "sg:address":"43118 Lake Ridge Pl",
    "sg:city":"Leesburg",
    "sg:classifiers":[
        {
            "category":"Recreation",
            "type":"Entertainment"
        }
    ],
    "sg:phone":"+1 703 443 1809",
    "sg:postcode":"20176",
    "sg:province":"VA",
    "wof:name":"Life For Kid Inc",
    "wof:placetype":"venue"
},
  "geometry": {"coordinates":[-77.508494,39.109921],"type":"Point"}
}