{
  "type": "Feature",
  "properties": {
    "iso:country":"US",
    "sg:address":"3170 Draper Dr",
    "sg:city":"Fairfax",
    "sg:classifiers":[
        {
            "category":"Building & Trades",
            "subcategory":"Construction",
            "type":"Services"
        },
        {
            "category":"Retail",
            "subcategory":"Auto Repair",
            "type":"Services"
        }
    ],
    "sg:phone":"+1 703 591 4500",
    "sg:postcode":"22031",
    "sg:province":"VA",
    "sg:tags":[
        "glass",
        "window",
        "coating",
        "tinting"
    ],
    "sg:website":"www.ziebart.com",
    "wof:name":"Sunrise Glass Tinting",
    "wof:placetype":"venue"
},
  "geometry": {"coordinates":[-77.281452,38.864972],"type":"Point"}
}