{
  "type": "Feature",
  "properties": {
    "iso:country":"US",
    "sg:address":"2720 Arlington Dr",
    "sg:city":"Alexandria",
    "sg:classifiers":[
        {
            "category":"Social Services",
            "subcategory":"Child Care",
            "type":"Services"
        }
    ],
    "sg:phone":"+1 703 765 1050",
    "sg:postcode":"22306",
    "sg:province":"VA",
    "sg:website":"www.littlepeoplesplace.com",
    "wof:name":"Little People's Place",
    "wof:placetype":"venue"
},
  "geometry": {"coordinates":[-77.07817799999999,38.75579],"type":"Point"}
}