{
  "type": "Feature",
  "properties": {
    "iso:country":"US",
    "sg:address":"845 N Howard St",
    "sg:city":"Alexandria",
    "sg:classifiers":[
        {
            "category":"Social Services",
            "subcategory":"Child Care",
            "type":"Services"
        }
    ],
    "sg:phone":"+1 703 751 3388",
    "sg:postcode":"22304",
    "sg:province":"VA",
    "sg:tags":[
        "day"
    ],
    "wof:name":"Creative Play School",
    "wof:placetype":"venue"
},
  "geometry": {"coordinates":[-77.105442,38.818551],"type":"Point"}
}