{
  "type": "Feature",
  "properties": {
    "addr:full":"2857 Dark Hollow Rd Roseland VA 22967",
    "addr:housenumber":"2857",
    "addr:postcode":"22967",
    "addr:street":"Dark Hollow Rd",
    "iso:country":"US",
    "sg:address":"2857 Dark Hollow Rd",
    "sg:city":"Roseland",
    "sg:classifiers":[
        {
            "category":"Professional",
            "subcategory":"Business Services",
            "type":"Services"
        }
    ],
    "sg:phone":"+1 434 361 1478",
    "sg:postcode":"22967",
    "sg:province":"VA",
    "sg:tags":[
        "interior",
        "consultant",
        "design",
        "decorator"
    ],
    "wof:name":"Window Fashions Of Virginia",
    "wof:placetype":"venue"
},
  "geometry": {"coordinates":[-78.951695,37.770467],"type":"Point"}
}