{
  "type": "Feature",
  "properties": {
    "iso:country":"US",
    "sg:address":"7100 Woodglen Ct",
    "sg:city":"Fairfax Station",
    "sg:classifiers":[
        {
            "category":"Professional",
            "type":"Services"
        }
    ],
    "sg:phone":"+1 703 250 3345",
    "sg:postcode":"22039",
    "sg:province":"VA",
    "wof:name":"MTL Svc Intl",
    "wof:placetype":"venue"
},
  "geometry": {"coordinates":[-77.34345999999999,38.765346],"type":"Point"}
}