{
  "type": "Feature",
  "properties": {
    "iso:country":"US",
    "sg:address":"11866 Folly Ln",
    "sg:city":"Lovettsville",
    "sg:classifiers":[
        {
            "category":"Professional",
            "subcategory":"Computer Services",
            "type":"Services"
        }
    ],
    "sg:phone":"+1 540 822 4687",
    "sg:postcode":"20180",
    "sg:province":"VA",
    "sg:tags":[
        "website",
        "design"
    ],
    "wof:name":"Downey Mill Group",
    "wof:placetype":"venue"
},
  "geometry": {"coordinates":[-77.59016099999999,39.280177],"type":"Point"}
}