{
  "type": "Feature",
  "properties": {
    "iso:country":"US",
    "sg:address":"3431 W Leigh St",
    "sg:city":"Richmond",
    "sg:classifiers":[
        {
            "category":"Wholesale",
            "subcategory":"Stationery",
            "type":"Manufacturing & Wholesale Goods"
        }
    ],
    "sg:phone":"+1 804 355 8628",
    "sg:postcode":"23230",
    "sg:province":"VA",
    "sg:tags":[
        "food",
        "product",
        "paper"
    ],
    "wof:name":"Old Dominion Paper Co",
    "wof:placetype":"venue"
},
  "geometry": {"coordinates":[-77.475149,37.570656],"type":"Point"}
}