{
  "type": "Feature",
  "properties": {
    "iso:country":"US",
    "sg:address":"4350 Fairfax Dr",
    "sg:city":"Arlington",
    "sg:classifiers":[
        {
            "category":"Organizations",
            "subcategory":"Professional Association",
            "type":"Services"
        },
        {
            "category":"Social Services",
            "type":"Services"
        }
    ],
    "sg:phone":"+1 703 812 4600",
    "sg:postcode":"22203",
    "sg:province":"VA",
    "wof:name":"National Emergency Number Assn",
    "wof:placetype":"venue"
},
  "geometry": {"coordinates":[-77.113287,38.882068],"type":"Point"}
}