{
  "type": "Feature",
  "properties": {
    "addr:full":"9600 Main St Fairfax VA 22031",
    "addr:housenumber":"9600",
    "addr:postcode":"22031",
    "addr:street":"Main St",
    "iso:country":"US",
    "sg:address":"9600 Main St",
    "sg:city":"Fairfax",
    "sg:classifiers":[
        {
            "category":"Shopping",
            "subcategory":"Clothing, Apparel, & Fashions",
            "type":"Retail Goods"
        }
    ],
    "sg:phone":"+1 703 764 0480",
    "sg:postcode":"22031",
    "sg:province":"VA",
    "sg:tags":[
        "store"
    ],
    "wof:name":"Dress Barn",
    "wof:placetype":"venue"
},
  "geometry": {"coordinates":[-77.276837,38.841828],"type":"Point"}
}