{
  "type": "Feature",
  "properties": {
    "addr:full":"2750 Electric Rd Roanoke VA 24018",
    "addr:housenumber":"2750",
    "addr:postcode":"24018",
    "addr:street":"Electric Rd",
    "iso:country":"US",
    "sg:address":"2750 Electric Rd",
    "sg:city":"Roanoke",
    "sg:classifiers":[
        {
            "category":"Retail",
            "subcategory":"Veterinary Services",
            "type":"Services"
        }
    ],
    "sg:phone":"+1 540 989 1400",
    "sg:postcode":"24018",
    "sg:province":"VA",
    "sg:tags":[
        "veterinarian",
        "specialty"
    ],
    "wof:name":"Jessup Kimberly DVM",
    "wof:placetype":"venue"
},
  "geometry": {"coordinates":[-79.978561,37.22765],"type":"Point"}
}