{
  "type": "Feature",
  "properties": {
    "addr:full":"2905 Maplewood Pl Alexandria VA 22302",
    "addr:housenumber":"2905",
    "addr:postcode":"22302",
    "addr:street":"Maplewood Pl",
    "iso:country":"US",
    "sg:address":"2905 Maplewood Pl",
    "sg:city":"Alexandria",
    "sg:classifiers":[
        {
            "category":"Arts & Performance",
            "subcategory":"Theater",
            "type":"Entertainment"
        }
    ],
    "sg:phone":"+1 703 836 6773",
    "sg:postcode":"22302",
    "sg:province":"VA",
    "sg:tags":[
        "group"
    ],
    "wof:name":"Alexandria Guitar Studio",
    "wof:placetype":"venue"
},
  "geometry": {"coordinates":[-77.07880299999999,38.831281],"type":"Point"}
}