{
  "type": "Feature",
  "properties": {
    "iso:country":"US",
    "sg:address":"308 Caroline St",
    "sg:city":"Fredericksburg",
    "sg:classifiers":[
        {
            "category":"Professional",
            "subcategory":"Business Services",
            "type":"Services"
        }
    ],
    "sg:phone":"+1 540 373 8644",
    "sg:postcode":"22401",
    "sg:province":"VA",
    "wof:name":"Coker Enterprises LP",
    "wof:placetype":"venue"
},
  "geometry": {"coordinates":[-77.455933,38.297733],"type":"Point"}
}