{
  "type": "Feature",
  "properties": {
    "addr:full":"7234 Arlington Blvd Falls Church VA 22042",
    "addr:housenumber":"7234",
    "addr:postcode":"22042",
    "addr:street":"Arlington Blvd",
    "iso:country":"US",
    "sg:address":"7234 Arlington Blvd",
    "sg:city":"Falls Church",
    "sg:classifiers":[
        {
            "category":"Wholesale",
            "subcategory":"Machinery & Supplies",
            "type":"Manufacturing & Wholesale Goods"
        }
    ],
    "sg:phone":"+1 703 849 8887",
    "sg:postcode":"22042",
    "sg:province":"VA",
    "sg:tags":[
        "beauty"
    ],
    "wof:name":"Skyline Beauty Supply Corp",
    "wof:placetype":"venue"
},
  "geometry": {"coordinates":[-77.196428,38.866254],"type":"Point"}
}