{
  "type": "Feature",
  "properties": {
    "addr:full":"3833 N Fairfax Dr Ste 200 Arlington VA 22203",
    "addr:housenumber":"3833",
    "addr:postcode":"22203",
    "addr:street":"N Fairfax Dr Ste 200",
    "iso:country":"US",
    "sg:address":"3833 N Fairfax Dr Ste 200",
    "sg:city":"Arlington",
    "sg:classifiers":[
        {
            "category":"Health Services",
            "subcategory":"Doctor",
            "type":"Services"
        }
    ],
    "sg:phone":"+1 703 525 8863",
    "sg:postcode":"22203",
    "sg:province":"VA",
    "sg:tags":[
        "medicine",
        "internal"
    ],
    "sg:website":"www.gimg.com",
    "wof:name":"General Internal Medicine Group",
    "wof:placetype":"venue"
},
  "geometry": {"coordinates":[-77.105486,38.882639],"type":"Point"}
}