{
  "type": "Feature",
  "properties": {
    "addr:full":"315 Charlotte Dr Portsmouth VA 23701",
    "addr:housenumber":"315",
    "addr:postcode":"23701",
    "addr:street":"Charlotte Dr",
    "iso:country":"US",
    "sg:address":"315 Charlotte Dr",
    "sg:city":"Portsmouth",
    "sg:classifiers":[
        {
            "category":"Building & Trades",
            "subcategory":"Construction",
            "type":"Services"
        }
    ],
    "sg:phone":"+1 757 488 7383",
    "sg:postcode":"23701",
    "sg:province":"VA",
    "sg:tags":[
        "water",
        "excavating",
        "sewer",
        "contractor"
    ],
    "wof:name":"Pearce Corporation",
    "wof:placetype":"venue"
},
  "geometry": {"coordinates":[-76.39049,36.825366],"type":"Point"}
}