{
  "type": "Feature",
  "properties": {
    "addr:full":"549 Mariners Way Norfolk VA 23503",
    "addr:housenumber":"549",
    "addr:postcode":"23503",
    "addr:street":"Mariners Way",
    "iso:country":"US",
    "sg:address":"549 Mariners Way",
    "sg:city":"Norfolk",
    "sg:classifiers":[
        {
            "category":"Health Services",
            "subcategory":"Health Practitioner",
            "type":"Services"
        }
    ],
    "sg:phone":"+1 757 692 8001",
    "sg:postcode":"23503",
    "sg:province":"VA",
    "sg:tags":[
        "dental",
        "hygienist"
    ],
    "wof:name":"Daniels Latashia",
    "wof:placetype":"venue"
},
  "geometry": {"coordinates":[-76.24924799999999,36.939219],"type":"Point"}
}