{
  "type": "Feature",
  "properties": {
    "addr:full":"3807 W Hundred Rd Chester VA 23831",
    "addr:housenumber":"3807",
    "addr:postcode":"23831",
    "addr:street":"W Hundred Rd",
    "iso:country":"US",
    "sg:address":"3807 W Hundred Rd",
    "sg:city":"Chester",
    "sg:classifiers":[
        {
            "category":"Retail",
            "subcategory":"Laundry & Dry Cleaning",
            "type":"Services"
        }
    ],
    "sg:phone":"+1 804 737 8525",
    "sg:postcode":"23831",
    "sg:province":"VA",
    "sg:tags":[
        "cleaners",
        "rug",
        "carpet"
    ],
    "wof:name":"Better Carpet & Upholstery",
    "wof:placetype":"venue"
},
  "geometry": {"coordinates":[-77.43879,37.359147],"type":"Point"}
}