{
  "type": "Feature",
  "properties": {
    "iso:country":"US",
    "sg:address":"85 Peachtree Valley Dr",
    "sg:city":"Roanoke",
    "sg:classifiers":[
        {
            "category":"Retail",
            "subcategory":"Laundry & Dry Cleaning",
            "type":"Services"
        }
    ],
    "sg:phone":"+1 540 977 0806",
    "sg:postcode":"24012",
    "sg:province":"VA",
    "sg:tags":[
        "cleaner"
    ],
    "wof:name":"Asset Cleaning & Protective",
    "wof:placetype":"venue"
},
  "geometry": {"coordinates":[-79.85997500000001,37.337071],"type":"Point"}
}