{
  "type": "Feature",
  "properties": {
    "iso:country":"US",
    "sg:address":"3202 Chamberlayne Ave",
    "sg:city":"Richmond",
    "sg:classifiers":[
        {
            "category":"Social Services",
            "subcategory":"Child Care",
            "type":"Services"
        }
    ],
    "sg:phone":"+1 804 359 3376",
    "sg:postcode":"23227",
    "sg:province":"VA",
    "sg:tags":[
        "day"
    ],
    "wof:name":"Creative Center For Early Lrng",
    "wof:placetype":"venue"
},
  "geometry": {"coordinates":[-77.446201,37.578066],"type":"Point"}
}