{
  "type": "Feature",
  "properties": {
    "iso:country":"US",
    "sg:address":"7651 Happy Creek Rd",
    "sg:city":"Gordonsville",
    "sg:classifiers":[
        {
            "category":"Farming",
            "subcategory":"Farm",
            "type":"Manufacturing & Wholesale Goods"
        }
    ],
    "sg:phone":"+1 540 832 0806",
    "sg:postcode":"22942",
    "sg:province":"VA",
    "wof:name":"Chance Farm",
    "wof:placetype":"venue"
},
  "geometry": {"coordinates":[-78.23146699999999,38.130935],"type":"Point"}
}