{
  "type": "Feature",
  "properties": {
    "iso:country":"US",
    "sg:address":"1017 Todds Ln",
    "sg:city":"Hampton",
    "sg:classifiers":[
        {
            "category":"Social Services",
            "type":"Services"
        }
    ],
    "sg:phone":"+1 757 825 2591",
    "sg:postcode":"23666",
    "sg:province":"VA",
    "wof:name":"Rape Crsis Cunseling-Peninsula",
    "wof:placetype":"venue"
},
  "geometry": {"coordinates":[-76.439204,37.043099],"type":"Point"}
}