{
  "type": "Feature",
  "properties": {
    "addr:full":"153 W Main St Abingdon VA 24210",
    "addr:housenumber":"153",
    "addr:postcode":"24210",
    "addr:street":"W Main St",
    "iso:country":"US",
    "sg:address":"153 W Main St",
    "sg:city":"Abingdon",
    "sg:classifiers":[
        {
            "category":"Shopping",
            "subcategory":"Gifts & Souvenirs",
            "type":"Retail Goods"
        }
    ],
    "sg:phone":"+1 276 628 2420",
    "sg:postcode":"24210",
    "sg:province":"VA",
    "sg:tags":[
        "shop"
    ],
    "wof:name":"Plumb Alley Beads & Gifts",
    "wof:placetype":"venue"
},
  "geometry": {"coordinates":[-81.975965,36.710285],"type":"Point"}
}