{
  "type": "Feature",
  "properties": {
    "iso:country":"US",
    "sg:address":"365 Tanyard Rd",
    "sg:city":"Rocky Mount",
    "sg:classifiers":[
        {
            "category":"Health Services",
            "subcategory":"Optometrist",
            "type":"Services"
        }
    ],
    "sg:phone":"+1 540 483 5256",
    "sg:postcode":"24151",
    "sg:province":"VA",
    "wof:name":"Drs Newman & Blackstock",
    "wof:placetype":"venue"
},
  "geometry": {"coordinates":[-79.882648,37.001596],"type":"Point"}
}