{
  "type": "Feature",
  "properties": {
    "iso:country":"US",
    "sg:address":"3100 Elmhurst Ln",
    "sg:city":"Portsmouth",
    "sg:classifiers":[
        {
            "category":"Manufacturing",
            "subcategory":"Lumber",
            "type":"Manufacturing & Wholesale Goods"
        }
    ],
    "sg:phone":"+1 757 488 2402",
    "sg:postcode":"23701",
    "sg:province":"VA",
    "sg:tags":[
        "forester"
    ],
    "wof:name":"Buie Forest Products",
    "wof:placetype":"venue"
},
  "geometry": {"coordinates":[-76.36927900000001,36.804057],"type":"Point"}
}