{
  "type": "Feature",
  "properties": {
    "addr:full":"9218 Timberwood Ct Manassas VA 20110",
    "addr:housenumber":"9218",
    "addr:postcode":"20110",
    "addr:street":"Timberwood Ct",
    "iso:country":"US",
    "sg:address":"9218 Timberwood Ct",
    "sg:city":"Manassas",
    "sg:classifiers":[
        {
            "category":"Organizations",
            "subcategory":"Religious Organization",
            "type":"Services"
        }
    ],
    "sg:phone":"+1 703 257 5005",
    "sg:postcode":"20110",
    "sg:province":"VA",
    "wof:name":"Copenhaver Rev Gene & Marty",
    "wof:placetype":"venue"
},
  "geometry": {"coordinates":[-77.47500100000001,38.771606],"type":"Point"}
}