{
  "type": "Feature",
  "properties": {
    "addr:full":"6126 Redwood Ln Alexandria VA 22310",
    "addr:housenumber":"6126",
    "addr:postcode":"22310",
    "addr:street":"Redwood Ln",
    "iso:country":"US",
    "sg:address":"6126 Redwood Ln",
    "sg:city":"Alexandria",
    "sg:classifiers":[
        {
            "category":"Retail",
            "subcategory":"Car Wash",
            "type":"Services"
        }
    ],
    "sg:phone":"+1 703 768 4318",
    "sg:postcode":"22310",
    "sg:province":"VA",
    "sg:tags":[
        "carwash",
        "station",
        "gasoline"
    ],
    "wof:name":"Groveton Car Wash & Detail",
    "wof:placetype":"venue"
},
  "geometry": {"coordinates":[-77.10596700000001,38.78467],"type":"Point"}
}