{
  "type": "Feature",
  "properties": {
    "iso:country":"US",
    "sg:address":"6139 Blacksburg Rd",
    "sg:city":"Troutville",
    "sg:classifiers":[
        {
            "category":"Building & Trades",
            "subcategory":"Plumbing",
            "type":"Services"
        }
    ],
    "sg:phone":"+1 540 992 6343",
    "sg:postcode":"24175",
    "sg:province":"VA",
    "sg:tags":[
        "conditioning",
        "air",
        "system",
        "contractor"
    ],
    "wof:name":"TROY'S Hvac Systems",
    "wof:placetype":"venue"
},
  "geometry": {"coordinates":[-79.96413099999999,37.450846],"type":"Point"}
}