{
  "type": "Feature",
  "properties": {
    "addr:full":"14005 Wards Rd Lynchburg VA 24501",
    "addr:housenumber":"14005",
    "addr:postcode":"24501",
    "addr:street":"Wards Rd",
    "iso:country":"US",
    "sg:address":"14005 Wards Rd",
    "sg:city":"Lynchburg",
    "sg:classifiers":[
        {
            "category":"Cinema",
            "subcategory":"Movie Rental",
            "type":"Entertainment"
        }
    ],
    "sg:phone":"+1 434 237 8220",
    "sg:postcode":"24501",
    "sg:province":"VA",
    "sg:tags":[
        "leasing",
        "video",
        "disc",
        "tape"
    ],
    "wof:name":"Movie Gallery",
    "wof:placetype":"venue"
},
  "geometry": {"coordinates":[-79.18831900000001,37.317708],"type":"Point"}
}