{
  "type": "Feature",
  "properties": {
    "addr:full":"101 Kenneth Dr Seaford VA 23696",
    "addr:housenumber":"101",
    "addr:postcode":"23696",
    "addr:street":"Kenneth Dr",
    "iso:country":"US",
    "sg:address":"101 Kenneth Dr",
    "sg:city":"Seaford",
    "sg:classifiers":[
        {
            "category":"Personal",
            "subcategory":"Beauty Salon",
            "type":"Services"
        }
    ],
    "sg:phone":"+1 757 898 7839",
    "sg:postcode":"23696",
    "sg:province":"VA",
    "sg:tags":[
        "shop"
    ],
    "wof:name":"Creative Images",
    "wof:placetype":"venue"
},
  "geometry": {"coordinates":[-76.42354899999999,37.193287],"type":"Point"}
}