{
  "type": "Feature",
  "properties": {
    "addr:full":"7439 Whitepine Rd Richmond VA 23237",
    "addr:housenumber":"7439",
    "addr:postcode":"23237",
    "addr:street":"Whitepine Rd",
    "iso:country":"US",
    "sg:address":"7439 Whitepine Rd",
    "sg:city":"Richmond",
    "sg:classifiers":[
        {
            "category":"Building & Trades",
            "subcategory":"Construction",
            "type":"Services"
        }
    ],
    "sg:phone":"+1 804 271 7000",
    "sg:postcode":"23237",
    "sg:province":"VA",
    "sg:tags":[
        "home",
        "builder"
    ],
    "wof:name":"Jim Walter Homes Inc",
    "wof:placetype":"venue"
},
  "geometry": {"coordinates":[-77.519915,37.396747],"type":"Point"}
}