{
  "type": "Feature",
  "properties": {
    "iso:country":"US",
    "sg:address":"7245 Arlington Blvd",
    "sg:city":"Falls Church",
    "sg:classifiers":[
        {
            "category":"Building & Trades",
            "subcategory":"Construction",
            "type":"Services"
        }
    ],
    "sg:phone":"+1 703 849 9274",
    "sg:postcode":"22042",
    "sg:province":"VA",
    "sg:tags":[
        "maintenance",
        "contractor"
    ],
    "wof:name":"Loehmanns Plaza Maintenance",
    "wof:placetype":"venue"
},
  "geometry": {"coordinates":[-77.195713,38.866156],"type":"Point"}
}