{
  "type": "Feature",
  "properties": {
    "addr:full":"2017 Walnut Ave Buena Vista VA 24416",
    "addr:housenumber":"2017",
    "addr:postcode":"24416",
    "addr:street":"Walnut Ave",
    "iso:country":"US",
    "sg:address":"2017 Walnut Ave",
    "sg:city":"Buena Vista",
    "sg:classifiers":[
        {
            "category":"Recreation",
            "type":"Entertainment"
        }
    ],
    "sg:phone":"+1 540 261 1620",
    "sg:postcode":"24416",
    "sg:province":"VA",
    "wof:name":"Kokoro Dojo",
    "wof:placetype":"venue"
},
  "geometry": {"coordinates":[-79.351128,37.733386],"type":"Point"}
}