{
  "type": "Feature",
  "properties": {
    "addr:full":"12456 Gayton Station Blvd Richmond VA 23233",
    "addr:housenumber":"12456",
    "addr:postcode":"23233",
    "addr:street":"Gayton Station Blvd",
    "iso:country":"US",
    "sg:address":"12456 Gayton Station Blvd",
    "sg:city":"Richmond",
    "sg:classifiers":[
        {
            "category":"Building & Trades",
            "subcategory":"Construction",
            "type":"Services"
        }
    ],
    "sg:phone":"+1 804 360 7880",
    "sg:postcode":"23233",
    "sg:province":"VA",
    "sg:tags":[
        "house"
    ],
    "wof:name":"Continental Home Improvement",
    "wof:placetype":"venue"
},
  "geometry": {"coordinates":[-77.64568300000001,37.65636],"type":"Point"}
}