{
  "type": "Feature",
  "properties": {
    "iso:country":"US",
    "sg:address":"2013 Cunningham Dr",
    "sg:city":"Hampton",
    "sg:classifiers":[
        {
            "category":"Real Estate",
            "subcategory":"Real Estate Agent",
            "type":"Services"
        }
    ],
    "sg:phone":"+1 757 838 9780",
    "sg:postcode":"23666",
    "sg:province":"VA",
    "wof:name":"Selective Association Mgt",
    "wof:placetype":"venue"
},
  "geometry": {"coordinates":[-76.38150899999999,37.04436],"type":"Point"}
}