{
  "type": "Feature",
  "properties": {
    "iso:country":"US",
    "sg:address":"277 Calais Rd",
    "sg:city":"Hague",
    "sg:classifiers":[
        {
            "category":"Freight",
            "type":"Transportation"
        }
    ],
    "sg:phone":"+1 804 472 5656",
    "sg:postcode":"22469",
    "sg:province":"VA",
    "sg:tags":[
        "trucking"
    ],
    "wof:name":"Blueboy Trucking Co",
    "wof:placetype":"venue"
},
  "geometry": {"coordinates":[-76.664384,38.089375],"type":"Point"}
}