{
  "type": "Feature",
  "properties": {
    "addr:full":"15430 Rowlett Rd Chesterfield VA 23838",
    "addr:housenumber":"15430",
    "addr:postcode":"23838",
    "addr:street":"Rowlett Rd",
    "iso:country":"US",
    "sg:address":"15430 Rowlett Rd",
    "sg:city":"Chesterfield",
    "sg:classifiers":[
        {
            "category":"Food & Beverages",
            "subcategory":"Groceries & Convenience Stores",
            "type":"Retail Goods"
        }
    ],
    "sg:phone":"+1 804 590 3671",
    "sg:postcode":"23838",
    "sg:province":"VA",
    "sg:tags":[
        "grocer"
    ],
    "wof:name":"Seven Springs Deli & Market",
    "wof:placetype":"venue"
},
  "geometry": {"coordinates":[-77.54605100000001,37.287193],"type":"Point"}
}