{
  "type": "Feature",
  "properties": {
    "addr:full":"2111 Mill Rd Alexandria VA 22314",
    "addr:housenumber":"2111",
    "addr:postcode":"22314",
    "addr:street":"Mill Rd",
    "iso:country":"US",
    "sg:address":"2111 Mill Rd",
    "sg:city":"Alexandria",
    "sg:classifiers":[
        {
            "category":"Retail",
            "subcategory":"Animal Services",
            "type":"Services"
        }
    ],
    "sg:phone":"+1 703 535 3355",
    "sg:postcode":"22314",
    "sg:province":"VA",
    "wof:name":"Walking & Wagging In Old Town",
    "wof:placetype":"venue"
},
  "geometry": {"coordinates":[-77.074596,38.804052],"type":"Point"}
}