{
  "type": "Feature",
  "properties": {
    "iso:country":"US",
    "sg:address":"3550 Poplar Dr",
    "sg:city":"Roanoke",
    "sg:classifiers":[
        {
            "category":"Organizations",
            "subcategory":"Religious Organization",
            "type":"Services"
        }
    ],
    "sg:phone":"+1 540 774 2706",
    "sg:postcode":"24018",
    "sg:province":"VA",
    "sg:website":"www.colonialpres.org",
    "wof:name":"Colonial Presbyterian Church",
    "wof:placetype":"venue"
},
  "geometry": {"coordinates":[-79.99509399999999,37.23218],"type":"Point"}
}