{
  "type": "Feature",
  "properties": {
    "addr:full":"102 Fern Ct Winchester VA 22602",
    "addr:housenumber":"102",
    "addr:postcode":"22602",
    "addr:street":"Fern Ct",
    "iso:country":"US",
    "sg:address":"102 Fern Ct",
    "sg:city":"Winchester",
    "sg:classifiers":[
        {
            "category":"Shopping",
            "type":"Retail Goods"
        }
    ],
    "sg:phone":"+1 540 665 3810",
    "sg:postcode":"22602",
    "sg:province":"VA",
    "sg:tags":[
        "merchandise"
    ],
    "wof:name":"All Star Awards & Trophies",
    "wof:placetype":"venue"
},
  "geometry": {"coordinates":[-78.097718,39.163745],"type":"Point"}
}