{
  "type": "Feature",
  "properties": {
    "addr:full":"6715 Lowell Ave Mc Lean VA 22101",
    "addr:housenumber":"6715",
    "addr:postcode":"22101",
    "addr:street":"Lowell Ave Mc Lean",
    "iso:country":"US",
    "sg:address":"6715 Lowell Ave",
    "sg:city":"Mc Lean",
    "sg:classifiers":[
        {
            "category":"Restaurant",
            "type":"Food & Drink"
        }
    ],
    "sg:phone":"+1 703 821 3779",
    "sg:postcode":"22101",
    "sg:province":"VA",
    "sg:tags":[
        "taiwanese",
        "chinese"
    ],
    "wof:name":"House of Fortune",
    "wof:placetype":"venue"
},
  "geometry": {"coordinates":[-77.176804,38.931301],"type":"Point"}
}