{
  "type": "Feature",
  "properties": {
    "addr:full":"4103 S Laburnum Ave Richmond VA 23231",
    "addr:housenumber":"4103",
    "addr:postcode":"23231",
    "addr:street":"S Laburnum Ave",
    "iso:country":"US",
    "sg:address":"4103 S Laburnum Ave",
    "sg:city":"Richmond",
    "sg:classifiers":[
        {
            "category":"Retail",
            "subcategory":"Auto Rental",
            "type":"Services"
        }
    ],
    "sg:phone":"+1 804 226 8376",
    "sg:postcode":"23231",
    "sg:province":"VA",
    "sg:tags":[
        "renting",
        "truck",
        "leasing"
    ],
    "wof:name":"Budget Truck Rental",
    "wof:placetype":"venue"
},
  "geometry": {"coordinates":[-77.36244600000001,37.533253],"type":"Point"}
}