{
  "type": "Feature",
  "properties": {
    "iso:country":"US",
    "sg:address":"6945 Commons Plz",
    "sg:city":"Chesterfield",
    "sg:classifiers":[
        {
            "category":"Restaurant",
            "type":"Food & Drink"
        }
    ],
    "sg:menulink":"http://www.allmenus.com/va/dale/228948-jersey-mikes/menu/",
    "sg:phone":"+1 804 706 1970",
    "sg:postcode":"23832",
    "sg:province":"VA",
    "sg:tags":[
        "american",
        "sandwich"
    ],
    "wof:name":"Jersey Mike's",
    "wof:placetype":"venue"
},
  "geometry": {"coordinates":[-77.511557,37.375408],"type":"Point"}
}