{
  "type": "Feature",
  "properties": {
    "iso:country":"US",
    "sg:address":"647 Williamson Rd",
    "sg:city":"Crewe",
    "sg:phone":"+1 434 645 9180",
    "sg:postcode":"23930",
    "sg:province":"VA",
    "sg:tags":[
        "farm",
        "field",
        "crop"
    ],
    "wof:name":"L E Williamson and Son",
    "wof:placetype":"venue"
},
  "geometry": {"coordinates":[-78.088881,37.107202],"type":"Point"}
}