{
  "type": "Feature",
  "properties": {
    "iso:country":"US",
    "sg:address":"44632 Guilford Dr",
    "sg:city":"Ashburn",
    "sg:classifiers":[
        {
            "category":"Building & Trades",
            "subcategory":"Construction",
            "type":"Services"
        }
    ],
    "sg:phone":"+1 703 589 1077",
    "sg:postcode":"20147",
    "sg:province":"VA",
    "sg:tags":[
        "house",
        "general",
        "contractor"
    ],
    "wof:name":"Select Construction Co Inc",
    "wof:placetype":"venue"
},
  "geometry": {"coordinates":[-77.460021,39.02539],"type":"Point"}
}