{
  "type": "Feature",
  "properties": {
    "iso:country":"US",
    "sg:address":"252 Potomac Ave",
    "sg:city":"Quantico",
    "sg:classifiers":[
        {
            "category":"Building & Trades",
            "subcategory":"Plumbing",
            "type":"Services"
        }
    ],
    "sg:phone":"+1 703 640 7800",
    "sg:postcode":"22134",
    "sg:province":"VA",
    "sg:tags":[
        "plumbing",
        "heating",
        "air"
    ],
    "wof:name":"B C T Contractors Inc",
    "wof:placetype":"venue"
},
  "geometry": {"coordinates":[-77.291237,38.521847],"type":"Point"}
}