{
  "type": "Feature",
  "properties": {
    "iso:country":"US",
    "sg:address":"351 E Mercury Blvd",
    "sg:city":"Hampton",
    "sg:classifiers":[
        {
            "category":"Organizations",
            "subcategory":"Religious Organization",
            "type":"Services"
        }
    ],
    "sg:phone":"+1 757 722 1182",
    "sg:postcode":"23663",
    "sg:province":"VA",
    "sg:tags":[
        "church"
    ],
    "wof:name":"Harborpointe Community Church",
    "wof:placetype":"venue"
},
  "geometry": {"coordinates":[-76.324133,37.029091],"type":"Point"}
}