{
  "type": "Feature",
  "properties": {
    "addr:full":"690 Berkmar Cir Charlottesville VA 22901",
    "addr:housenumber":"690",
    "addr:postcode":"22901",
    "addr:street":"Berkmar Cir",
    "iso:country":"US",
    "sg:address":"690 Berkmar Cir",
    "sg:city":"Charlottesville",
    "sg:classifiers":[
        {
            "category":"Shopping",
            "subcategory":"Computers & Home Electronics",
            "type":"Retail Goods"
        }
    ],
    "sg:phone":"+1 434 817 2470",
    "sg:postcode":"22901",
    "sg:province":"VA",
    "sg:tags":[
        "parts",
        "supply"
    ],
    "wof:name":"24-7 Computer Svc",
    "wof:placetype":"venue"
},
  "geometry": {"coordinates":[-78.47852,38.084931],"type":"Point"}
}