{
  "type": "Feature",
  "properties": {
    "iso:country":"US",
    "sg:address":"14 Cardinal Park Dr SE",
    "sg:city":"Leesburg",
    "sg:classifiers":[
        {
            "category":"Shopping",
            "type":"Retail Goods"
        }
    ],
    "sg:phone":"+1 703 669 3180",
    "sg:postcode":"20175",
    "sg:province":"VA",
    "sg:tags":[
        "contracting",
        "system",
        "integration"
    ],
    "wof:name":"Wavecrest Systems",
    "wof:placetype":"venue"
},
  "geometry": {"coordinates":[-77.541561,39.098221],"type":"Point"}
}