{
  "type": "Feature",
  "properties": {
    "addr:full":"4343 Plank Rd Fredericksburg VA 22407",
    "addr:housenumber":"4343",
    "addr:postcode":"22407",
    "addr:street":"Plank Rd",
    "iso:country":"US",
    "sg:address":"4343 Plank Rd",
    "sg:city":"Fredericksburg",
    "sg:classifiers":[
        {
            "category":"Real Estate",
            "subcategory":"Real Estate Services",
            "type":"Services"
        }
    ],
    "sg:phone":"+1 540 786 1126",
    "sg:postcode":"22407",
    "sg:province":"VA",
    "sg:tags":[
        "company",
        "issue",
        "insurance",
        "title"
    ],
    "sg:website":"www.closefred.net",
    "wof:name":"Chancellor Title & Settlement",
    "wof:placetype":"venue"
},
  "geometry": {"coordinates":[-77.53483300000001,38.289095],"type":"Point"}
}