{
  "type": "Feature",
  "properties": {
    "iso:country":"US",
    "sg:address":"4444 38th St N",
    "sg:city":"Arlington",
    "sg:classifiers":[
        {
            "category":"Professional",
            "subcategory":"Management & Consulting",
            "type":"Services"
        }
    ],
    "sg:phone":"+1 703 536 2575",
    "sg:postcode":"22207",
    "sg:province":"VA",
    "sg:tags":[
        "application",
        "training",
        "computer"
    ],
    "wof:name":"Joann Levine",
    "wof:placetype":"venue"
},
  "geometry": {"coordinates":[-77.129981,38.918879],"type":"Point"}
}