{
  "type": "Feature",
  "properties": {
    "addr:full":"400 Natchez Rd Richmond VA 23223",
    "addr:housenumber":"400",
    "addr:postcode":"23223",
    "addr:street":"Natchez Rd",
    "iso:country":"US",
    "sg:address":"400 Natchez Rd",
    "sg:city":"Richmond",
    "sg:classifiers":[
        {
            "category":"Building & Trades",
            "subcategory":"Landscaping Services",
            "type":"Services"
        }
    ],
    "sg:phone":"+1 804 737 1279",
    "sg:postcode":"23223",
    "sg:province":"VA",
    "wof:name":"A1 Lawn Care Inc",
    "wof:placetype":"venue"
},
  "geometry": {"coordinates":[-77.358487,37.554901],"type":"Point"}
}