{
  "type": "Feature",
  "properties": {
    "addr:full":"6532 Gildar St Alexandria VA 22310",
    "addr:housenumber":"6532",
    "addr:postcode":"22310",
    "addr:street":"Gildar St",
    "iso:country":"US",
    "sg:address":"6532 Gildar St",
    "sg:city":"Alexandria",
    "sg:classifiers":[
        {
            "category":"Professional",
            "subcategory":"Business Services",
            "type":"Services"
        }
    ],
    "sg:phone":"+1 703 971 6614",
    "sg:postcode":"22310",
    "sg:province":"VA",
    "sg:tags":[
        "interior",
        "consultant",
        "design",
        "decorator"
    ],
    "wof:name":"Designers Consortium LTD",
    "wof:placetype":"venue"
},
  "geometry": {"coordinates":[-77.149326,38.777052],"type":"Point"}
}