{
  "type": "Feature",
  "properties": {
    "addr:full":"109 S Fairfax St Alexandria VA 22314",
    "addr:housenumber":"109",
    "addr:postcode":"22314",
    "addr:street":"S Fairfax St",
    "iso:country":"US",
    "sg:address":"109 S Fairfax St",
    "sg:city":"Alexandria",
    "sg:classifiers":[
        {
            "category":"Professional",
            "subcategory":"Lawyer & Legal Services",
            "type":"Services"
        }
    ],
    "sg:phone":"+1 703 548 1700",
    "sg:postcode":"22314",
    "sg:province":"VA",
    "sg:tags":[
        "attorney"
    ],
    "wof:name":"Herman W Lutz Law Office",
    "wof:placetype":"venue"
},
  "geometry": {"coordinates":[-77.04266699999999,38.80432],"type":"Point"}
}