{
  "type": "Feature",
  "properties": {
    "iso:country":"US",
    "sg:address":"6507 Coachleigh Way",
    "sg:city":"Alexandria",
    "sg:classifiers":[
        {
            "category":"Professional",
            "subcategory":"Management & Consulting",
            "type":"Services"
        }
    ],
    "sg:phone":"+1 703 924 9297",
    "sg:postcode":"22315",
    "sg:province":"VA",
    "sg:tags":[
        "business"
    ],
    "wof:name":"Win Win Business Solutions",
    "wof:placetype":"venue"
},
  "geometry": {"coordinates":[-77.16993100000001,38.755745],"type":"Point"}
}