{
  "type": "Feature",
  "properties": {
    "addr:full":"108 Martin Dr Manassas VA 20111",
    "addr:housenumber":"108",
    "addr:postcode":"20111",
    "addr:street":"Martin Dr",
    "iso:country":"US",
    "sg:address":"108 Martin Dr",
    "sg:city":"Manassas",
    "sg:classifiers":[
        {
            "category":"Professional",
            "type":"Services"
        }
    ],
    "sg:phone":"+1 703 330 6150",
    "sg:postcode":"20111",
    "sg:province":"VA",
    "wof:name":"Robert F Frye Jr",
    "wof:placetype":"venue"
},
  "geometry": {"coordinates":[-77.464213,38.779877],"type":"Point"}
}