{
  "type": "Feature",
  "properties": {
    "addr:full":"209 Lorac Rd Williamsburg VA 23185",
    "addr:housenumber":"209",
    "addr:postcode":"23185",
    "addr:street":"Lorac Rd",
    "iso:country":"US",
    "sg:address":"209 Lorac Rd",
    "sg:city":"Williamsburg",
    "sg:classifiers":[
        {
            "category":"Arts & Performance",
            "subcategory":"Theater",
            "type":"Entertainment"
        }
    ],
    "sg:phone":"+1 757 253 0855",
    "sg:postcode":"23185",
    "sg:province":"VA",
    "sg:tags":[
        "group"
    ],
    "wof:name":"Rh Entertainment Ventures Inc",
    "wof:placetype":"venue"
},
  "geometry": {"coordinates":[-76.71051799999999,37.288661],"type":"Point"}
}