{
  "type": "Feature",
  "properties": {
    "addr:full":"4457 Revere Dr Virginia Beach VA 23456",
    "addr:housenumber":"4457",
    "addr:postcode":"23456",
    "addr:street":"Revere Dr",
    "iso:country":"US",
    "sg:address":"4457 Revere Dr",
    "sg:city":"Virginia Beach",
    "sg:classifiers":[
        {
            "category":"Real Estate",
            "subcategory":"Real Estate Operator",
            "type":"Services"
        }
    ],
    "sg:phone":"+1 757 474 0474",
    "sg:postcode":"23456",
    "sg:province":"VA",
    "sg:tags":[
        "property",
        "commercial",
        "lessor"
    ],
    "wof:name":"Musolino & Sons Inc",
    "wof:placetype":"venue"
},
  "geometry": {"coordinates":[-76.134637,36.795056],"type":"Point"}
}