{
  "type": "Feature",
  "properties": {
    "addr:full":"12384 Richmond Hwy Concord VA 24538",
    "addr:housenumber":"12384",
    "addr:postcode":"24538",
    "addr:street":"Richmond Hwy",
    "iso:country":"US",
    "sg:address":"12384 Richmond Hwy",
    "sg:city":"Concord",
    "sg:classifiers":[
        {
            "category":"Autos & Motor Vehicles",
            "subcategory":"Auto Supplies",
            "type":"Retail Goods"
        }
    ],
    "sg:phone":"+1 434 993 2224",
    "sg:postcode":"24538",
    "sg:province":"VA",
    "sg:tags":[
        "automobile",
        "parts"
    ],
    "wof:name":"National Auto Parts Inc",
    "wof:placetype":"venue"
},
  "geometry": {"coordinates":[-78.983756,37.351684],"type":"Point"}
}