{
  "type": "Feature",
  "properties": {
    "addr:full":"385 Garrisonville Rd Stafford VA 22554",
    "addr:housenumber":"385",
    "addr:postcode":"22554",
    "addr:street":"Garrisonville Rd",
    "iso:country":"US",
    "sg:address":"385 Garrisonville Rd",
    "sg:city":"Stafford",
    "sg:classifiers":[
        {
            "category":"Professional",
            "subcategory":"Computer Services",
            "type":"Services"
        }
    ],
    "sg:phone":"+1 540 657 4466",
    "sg:postcode":"22554",
    "sg:province":"VA",
    "sg:tags":[
        "design",
        "school",
        "processing",
        "datum",
        "system"
    ],
    "wof:name":"Ocean Systems Engineering",
    "wof:placetype":"venue"
},
  "geometry": {"coordinates":[-77.427942,38.474956],"type":"Point"}
}