{
  "type": "Feature",
  "properties": {
    "addr:full":"14270 Wards Rd Lynchburg VA 24502",
    "addr:housenumber":"14270",
    "addr:postcode":"24502",
    "addr:street":"Wards Rd",
    "iso:country":"US",
    "sg:address":"14270 Wards Rd",
    "sg:city":"Lynchburg",
    "sg:classifiers":[
        {
            "category":"Home & Garden",
            "subcategory":"Mobile Homes",
            "type":"Retail Goods"
        }
    ],
    "sg:phone":"+1 434 239 2619",
    "sg:postcode":"24502",
    "sg:province":"VA",
    "wof:name":"Clayton Homes Inc",
    "wof:placetype":"venue"
},
  "geometry": {"coordinates":[-79.189853,37.322749],"type":"Point"}
}