{
  "type": "Feature",
  "properties": {
    "iso:country":"US",
    "sg:address":"36 King St",
    "sg:city":"Bristol",
    "sg:classifiers":[
        {
            "category":"Social Services",
            "subcategory":"Adult Care",
            "type":"Services"
        }
    ],
    "sg:phone":"+1 276 466 2286",
    "sg:postcode":"24201",
    "sg:province":"VA",
    "sg:tags":[
        "home",
        "group"
    ],
    "wof:name":"Sunhouse",
    "wof:placetype":"venue"
},
  "geometry": {"coordinates":[-82.18644500000001,36.596134],"type":"Point"}
}