{
  "type": "Feature",
  "properties": {
    "addr:full":"209 Sheffey Dr Forest VA 24551",
    "addr:housenumber":"209",
    "addr:postcode":"24551",
    "addr:street":"Sheffey Dr",
    "iso:country":"US",
    "sg:address":"209 Sheffey Dr",
    "sg:city":"Forest",
    "sg:classifiers":[
        {
            "category":"Real Estate",
            "subcategory":"Real Estate Services",
            "type":"Services"
        }
    ],
    "sg:phone":"+1 434 525 2428",
    "sg:postcode":"24551",
    "sg:province":"VA",
    "sg:tags":[
        "abstract",
        "title"
    ],
    "wof:name":"Central SW Virginia Title Exam",
    "wof:placetype":"venue"
},
  "geometry": {"coordinates":[-79.305155,37.31843],"type":"Point"}
}