{
  "type": "Feature",
  "properties": {
    "iso:country":"US",
    "sg:address":"2232 Mill Race Ln Apt C",
    "sg:city":"Reston",
    "sg:classifiers":[
        {
            "category":"Taxi",
            "type":"Transportation"
        }
    ],
    "sg:phone":"+1 703 860 0562",
    "sg:postcode":"20191",
    "sg:province":"VA",
    "wof:name":"Loudon General Taxi Sedan",
    "wof:placetype":"venue"
},
  "geometry": {"coordinates":[-77.36476500000001,38.939792],"type":"Point"}
}