{
  "type": "Feature",
  "properties": {
    "addr:full":"107 Essex Dr Staunton VA 24401",
    "addr:housenumber":"107",
    "addr:postcode":"24401",
    "addr:street":"Essex Dr",
    "iso:country":"US",
    "sg:address":"107 Essex Dr",
    "sg:city":"Staunton",
    "sg:classifiers":[
        {
            "category":"Professional",
            "subcategory":"Business Services",
            "type":"Services"
        }
    ],
    "sg:phone":"+1 540 932 7557",
    "sg:postcode":"24401",
    "sg:province":"VA",
    "wof:name":"Inspector Homes Inc",
    "wof:placetype":"venue"
},
  "geometry": {"coordinates":[-79.10337199999999,38.163462],"type":"Point"}
}