{
  "type": "Feature",
  "properties": {
    "addr:full":"742 E 25th St Norfolk VA 23504",
    "addr:housenumber":"742",
    "addr:postcode":"23504",
    "addr:street":"E 25Th St",
    "iso:country":"US",
    "sg:address":"742 E 25th St",
    "sg:city":"Norfolk",
    "sg:classifiers":[
        {
            "category":"Building & Trades",
            "subcategory":"Construction",
            "type":"Services"
        }
    ],
    "sg:phone":"+1 757 623 2229",
    "sg:postcode":"23504",
    "sg:province":"VA",
    "sg:tags":[
        "commercial",
        "cabinetry"
    ],
    "wof:name":"Innovative Interior Inc",
    "wof:placetype":"venue"
},
  "geometry": {"coordinates":[-76.27766099999999,36.869593],"type":"Point"}
}