{
  "type": "Feature",
  "properties": {
    "iso:country":"US",
    "sg:address":"13785 Warwick Blvd",
    "sg:city":"Newport News",
    "sg:classifiers":[
        {
            "category":"Utilities",
            "subcategory":"Telephone",
            "type":"Services"
        }
    ],
    "sg:phone":"+1 757 989 2000",
    "sg:postcode":"23602",
    "sg:province":"VA",
    "sg:tags":[
        "telecommunication"
    ],
    "wof:name":"MCI",
    "wof:placetype":"venue"
},
  "geometry": {"coordinates":[-76.530708,37.123835],"type":"Point"}
}