{
  "type": "Feature",
  "properties": {
    "addr:full":"1841 Beulah Rd Vienna VA 22182",
    "addr:housenumber":"1841",
    "addr:postcode":"22182",
    "addr:street":"Beulah Rd",
    "iso:country":"US",
    "sg:address":"1841 Beulah Rd",
    "sg:city":"Vienna",
    "sg:classifiers":[
        {
            "category":"Building & Trades",
            "subcategory":"Landscaping Services",
            "type":"Services"
        }
    ],
    "sg:phone":"+1 703 281 7249",
    "sg:postcode":"22182",
    "sg:province":"VA",
    "sg:tags":[
        "lawn"
    ],
    "wof:name":"Vienna Landscape & Garden Lc",
    "wof:placetype":"venue"
},
  "geometry": {"coordinates":[-77.271951,38.924167],"type":"Point"}
}