{
  "type": "Feature",
  "properties": {
    "addr:full":"118 S Main St Galax VA 24333",
    "addr:housenumber":"118",
    "addr:postcode":"24333",
    "addr:street":"S Main St",
    "iso:country":"US",
    "sg:address":"118 S Main St",
    "sg:city":"Galax",
    "sg:classifiers":[
        {
            "category":"Shopping",
            "subcategory":"Used Merchandise",
            "type":"Retail Goods"
        }
    ],
    "sg:phone":"+1 276 236 8068",
    "sg:postcode":"24333",
    "sg:province":"VA",
    "sg:tags":[
        "shop",
        "consignment"
    ],
    "wof:name":"Carol's Consignment",
    "wof:placetype":"venue"
},
  "geometry": {"coordinates":[-80.924806,36.661776],"type":"Point"}
}