{
  "type": "Feature",
  "properties": {
    "addr:full":"4632 Priscilla Ln Virginia Beach VA 23455",
    "addr:housenumber":"4632",
    "addr:postcode":"23455",
    "addr:street":"Priscilla Ln",
    "iso:country":"US",
    "sg:address":"4632 Priscilla Ln",
    "sg:city":"Virginia Beach",
    "sg:classifiers":[
        {
            "category":"Professional",
            "type":"Services"
        }
    ],
    "sg:phone":"+1 757 497 5926",
    "sg:postcode":"23455",
    "sg:province":"VA",
    "wof:name":"Horst Incorporated C J",
    "wof:placetype":"venue"
},
  "geometry": {"coordinates":[-76.138479,36.877458],"type":"Point"}
}