{
  "type": "Feature",
  "properties": {
    "addr:full":"952 W Main St Abingdon VA 24210",
    "addr:housenumber":"952",
    "addr:postcode":"24210",
    "addr:street":"W Main St",
    "iso:country":"US",
    "sg:address":"952 W Main St",
    "sg:city":"Abingdon",
    "sg:classifiers":[
        {
            "category":"Personal",
            "type":"Services"
        }
    ],
    "sg:phone":"+1 276 623 2345",
    "sg:postcode":"24210",
    "sg:province":"VA",
    "wof:name":"Crazy Daizy Tattoos",
    "wof:placetype":"venue"
},
  "geometry": {"coordinates":[-82.00503999999999,36.701027],"type":"Point"}
}