{
  "type": "Feature",
  "properties": {
    "iso:country":"US",
    "sg:address":"4001 Eisenhower Ave",
    "sg:city":"Alexandria",
    "sg:classifiers":[
        {
            "category":"Recreation",
            "subcategory":"Miniature Golf",
            "type":"Entertainment"
        },
        {
            "category":"Landmark",
            "subcategory":"Tourist Information",
            "type":"Public Place"
        }
    ],
    "sg:phone":"+1 703 960 8719",
    "sg:postcode":"22304",
    "sg:province":"VA",
    "sg:tags":[
        "attraction"
    ],
    "wof:name":"Northern Virginia Regional Park Authority",
    "wof:placetype":"venue"
},
  "geometry": {"coordinates":[-77.098681,38.804109],"type":"Point"}
}