{
  "type": "Feature",
  "properties": {
    "addr:full":"6141 Main St Mt Jackson VA 22842",
    "addr:housenumber":"6141",
    "addr:postcode":"22842",
    "addr:street":"Main St",
    "iso:country":"US",
    "sg:address":"6141 Main St",
    "sg:city":"Mt Jackson",
    "sg:classifiers":[
        {
            "category":"Food & Beverages",
            "subcategory":"Groceries & Convenience Stores",
            "type":"Retail Goods"
        }
    ],
    "sg:phone":"+1 540 477 3911",
    "sg:postcode":"22842",
    "sg:province":"VA",
    "sg:tags":[
        "grocer"
    ],
    "wof:name":"South End Grocery & Fruit Mkt",
    "wof:placetype":"venue"
},
  "geometry": {"coordinates":[-78.64397099999999,38.734656],"type":"Point"}
}