{
  "type": "Feature",
  "properties": {
    "addr:full":"12206 Golden Sands Ln Reston VA 20191",
    "addr:housenumber":"12206",
    "addr:postcode":"20191",
    "addr:street":"Golden Sands Ln",
    "iso:country":"US",
    "sg:address":"12206 Golden Sands Ln",
    "sg:city":"Reston",
    "sg:classifiers":[
        {
            "category":"Building & Trades",
            "subcategory":"Construction",
            "type":"Services"
        }
    ],
    "sg:phone":"+1 703 715 0910",
    "sg:postcode":"20191",
    "sg:province":"VA",
    "sg:tags":[
        "floor",
        "laying",
        "contractor"
    ],
    "wof:name":"Delao Floors Inc",
    "wof:placetype":"venue"
},
  "geometry": {"coordinates":[-77.36959,38.944521],"type":"Point"}
}