{
  "type": "Feature",
  "properties": {
    "addr:full":"822 Cabell Rd Wingina VA 24599",
    "addr:housenumber":"822",
    "addr:postcode":"24599",
    "addr:street":"Cabell Rd",
    "iso:country":"US",
    "sg:address":"822 Cabell Rd",
    "sg:city":"Wingina",
    "sg:classifiers":[
        {
            "category":"Building & Trades",
            "subcategory":"Construction",
            "type":"Services"
        }
    ],
    "sg:phone":"+1 434 263 5184",
    "sg:postcode":"24599",
    "sg:province":"VA",
    "wof:name":"Londerees Construction",
    "wof:placetype":"venue"
},
  "geometry": {"coordinates":[-78.732313,37.672155],"type":"Point"}
}