{
  "type": "Feature",
  "properties": {
    "addr:full":"5229 Back Rd Woodstock VA 22664",
    "addr:housenumber":"5229",
    "addr:postcode":"22664",
    "addr:street":"Back Rd",
    "iso:country":"US",
    "sg:address":"5229 Back Rd",
    "sg:city":"Woodstock",
    "sg:classifiers":[
        {
            "category":"Place Of Worship",
            "subcategory":"Church",
            "type":"Public Place"
        },
        {
            "category":"Place Of Worship",
            "type":"Public Place"
        }
    ],
    "sg:phone":"+1 540 459 4239",
    "sg:postcode":"22664",
    "sg:province":"VA",
    "sg:tags":[
        "churches-non-denominational"
    ],
    "wof:name":"Emmanuel Evangel Church",
    "wof:placetype":"venue"
},
  "geometry": {"coordinates":[-78.554084,38.91866],"type":"Point"}
}