{
  "type": "Feature",
  "properties": {
    "iso:country":"US",
    "sg:address":"5043 Plank Rd",
    "sg:city":"Fredericksburg",
    "sg:classifiers":[
        {
            "category":"Home & Garden",
            "subcategory":"Garden Supply",
            "type":"Retail Goods"
        }
    ],
    "sg:phone":"+1 540 786 8171",
    "sg:postcode":"22407",
    "sg:province":"VA",
    "wof:name":"Meadows Farms Inc",
    "wof:placetype":"venue"
},
  "geometry": {"coordinates":[-77.549087,38.28975],"type":"Point"}
}