{
  "type": "Feature",
  "properties": {
    "iso:country":"US",
    "sg:address":"431 Cloudbreak Rd",
    "sg:city":"Meadows Of Dan",
    "sg:classifiers":[
        {
            "category":"Farming",
            "subcategory":"Farm",
            "type":"Manufacturing & Wholesale Goods"
        }
    ],
    "sg:phone":"+1 276 952 2371",
    "sg:postcode":"24120",
    "sg:province":"VA",
    "sg:tags":[
        "crop",
        "general"
    ],
    "wof:name":"Hall Esmond",
    "wof:placetype":"venue"
},
  "geometry": {"coordinates":[-80.348702,36.726686],"type":"Point"}
}