{
  "type": "Feature",
  "properties": {
    "addr:full":"2072 Iberis Rd Lancaster VA 22503",
    "addr:housenumber":"2072",
    "addr:postcode":"22503",
    "addr:street":"Iberis Rd",
    "iso:country":"US",
    "sg:address":"2072 Iberis Rd",
    "sg:city":"Lancaster",
    "sg:classifiers":[
        {
            "category":"Manufacturing",
            "subcategory":"Watercraft",
            "type":"Manufacturing & Wholesale Goods"
        }
    ],
    "sg:phone":"+1 804 462 9943",
    "sg:postcode":"22503",
    "sg:province":"VA",
    "wof:name":"Ackerly Marine Co Inc",
    "wof:placetype":"venue"
},
  "geometry": {"coordinates":[-76.45320700000001,37.729343],"type":"Point"}
}