{
  "type": "Feature",
  "properties": {
    "addr:full":"12450 Fairview Way Pungoteague VA 23422",
    "addr:housenumber":"12450",
    "addr:postcode":"23422",
    "addr:street":"Fairview Way",
    "iso:country":"US",
    "sg:address":"12450 Fairview Way",
    "sg:city":"Pungoteague",
    "sg:classifiers":[
        {
            "category":"Mining & Drilling",
            "type":"Manufacturing & Wholesale Goods"
        }
    ],
    "sg:phone":"+1 757 442 7688",
    "sg:postcode":"23422",
    "sg:province":"VA",
    "sg:tags":[
        "stone"
    ],
    "wof:name":"Kestral Marine Construction",
    "wof:placetype":"venue"
},
  "geometry": {"coordinates":[-75.86169,37.614714],"type":"Point"}
}