{
  "type": "Feature",
  "properties": {
    "iso:country":"US",
    "sg:address":"433 Fleming Cir",
    "sg:city":"Chesapeake",
    "sg:classifiers":[
        {
            "category":"Freight",
            "type":"Transportation"
        }
    ],
    "sg:phone":"+1 757 487 2690",
    "sg:postcode":"23323",
    "sg:province":"VA",
    "sg:tags":[
        "operator",
        "local",
        "trucking"
    ],
    "wof:name":"Mother Load",
    "wof:placetype":"venue"
},
  "geometry": {"coordinates":[-76.332615,36.728843],"type":"Point"}
}