{
  "type": "Feature",
  "properties": {
    "addr:full":"6272 Edsall Rd Alexandria VA 22312",
    "addr:housenumber":"6272",
    "addr:postcode":"22312",
    "addr:street":"Edsall Rd",
    "iso:country":"US",
    "sg:address":"6272 Edsall Rd",
    "sg:city":"Alexandria",
    "sg:classifiers":[
        {
            "category":"Education",
            "subcategory":"Special Training",
            "type":"Public Place"
        }
    ],
    "sg:phone":"+1 703 823 2367",
    "sg:postcode":"22312",
    "sg:province":"VA",
    "sg:tags":[
        "educational",
        "curriculum",
        "tutoring"
    ],
    "wof:name":"SMR Reading Resource",
    "wof:placetype":"venue"
},
  "geometry": {"coordinates":[-77.143754,38.804776],"type":"Point"}
}