{
  "type": "Feature",
  "properties": {
    "iso:country":"US",
    "sg:address":"9204 Enterprise Ct",
    "sg:city":"Manassas Park",
    "sg:classifiers":[
        {
            "category":"Retail",
            "subcategory":"Auto Repair",
            "type":"Services"
        }
    ],
    "sg:phone":"+1 703 335 0080",
    "sg:postcode":"20111",
    "sg:province":"VA",
    "sg:tags":[
        "body",
        "automobile",
        "painting"
    ],
    "wof:name":"Precision Auto Body",
    "wof:placetype":"venue"
},
  "geometry": {"coordinates":[-77.43674799999999,38.77491],"type":"Point"}
}