{
  "type": "Feature",
  "properties": {
    "addr:full":"610 Mansion Cir Hopewell VA 23860",
    "addr:housenumber":"610",
    "addr:postcode":"23860",
    "addr:street":"Mansion Cir",
    "iso:country":"US",
    "sg:address":"610 Mansion Cir",
    "sg:city":"Hopewell",
    "sg:classifiers":[
        {
            "category":"Professional",
            "subcategory":"Management & Consulting",
            "type":"Services"
        }
    ],
    "sg:phone":"+1 804 452 0186",
    "sg:postcode":"23860",
    "sg:province":"VA",
    "sg:tags":[
        "educational",
        "testing"
    ],
    "wof:name":"Valerie Rafey",
    "wof:placetype":"venue"
},
  "geometry": {"coordinates":[-77.30967800000001,37.307126],"type":"Point"}
}