{
  "type": "Feature",
  "properties": {
    "addr:full":"420 Starlight Dr Christiansburg VA 24073",
    "addr:housenumber":"420",
    "addr:postcode":"24073",
    "addr:street":"Starlight Dr",
    "iso:country":"US",
    "sg:address":"420 Starlight Dr",
    "sg:city":"Christiansburg",
    "sg:classifiers":[
        {
            "category":"Social Services",
            "subcategory":"Child Care",
            "type":"Services"
        }
    ],
    "sg:phone":"+1 540 382 1138",
    "sg:postcode":"24073",
    "sg:province":"VA",
    "sg:tags":[
        "day"
    ],
    "wof:name":"New Beginnings Child Dev Ctr",
    "wof:placetype":"venue"
},
  "geometry": {"coordinates":[-80.380152,37.129171],"type":"Point"}
}