{
  "type": "Feature",
  "properties": {
    "iso:country":"US",
    "sg:address":"1427 Baker Rd",
    "sg:city":"Virginia Beach",
    "sg:classifiers":[
        {
            "category":"Manufacturing",
            "subcategory":"Chemicals & Compounds",
            "type":"Manufacturing & Wholesale Goods"
        }
    ],
    "sg:phone":"+1 757 460 2401",
    "sg:postcode":"23455",
    "sg:province":"VA",
    "sg:website":"www.sanitize.com",
    "wof:name":"Edwards-Councilor Co",
    "wof:placetype":"venue"
},
  "geometry": {"coordinates":[-76.185022,36.896545],"type":"Point"}
}