{
  "type": "Feature",
  "properties": {
    "addr:full":"117 Mason Ave Cape Charles VA 23310",
    "addr:housenumber":"117",
    "addr:postcode":"charles;23310",
    "addr:street":"Mason Ave",
    "iso:country":"US",
    "sg:address":"117 Mason Ave",
    "sg:city":"Cape Charles",
    "sg:classifiers":[
        {
            "category":"Professional",
            "subcategory":"Management & Consulting",
            "type":"Services"
        }
    ],
    "sg:phone":"+1 757 331 2233",
    "sg:postcode":"23310",
    "sg:province":"VA",
    "wof:name":"John W Burdiss",
    "wof:placetype":"venue"
},
  "geometry": {"coordinates":[-76.01998500000001,37.267148],"type":"Point"}
}