{
  "type": "Feature",
  "properties": {
    "iso:country":"US",
    "sg:address":"15699 Back Rd",
    "sg:city":"Strasburg",
    "sg:classifiers":[
        {
            "category":"Health Services",
            "subcategory":"Medical Lab",
            "type":"Services"
        }
    ],
    "sg:phone":"+1 540 465 2926",
    "sg:postcode":"22657",
    "sg:province":"VA",
    "sg:tags":[
        "laboratory"
    ],
    "wof:name":"Blue Ridge Orthodontic Lab",
    "wof:placetype":"venue"
},
  "geometry": {"coordinates":[-78.41370999999999,39.015332],"type":"Point"}
}