{
  "type": "Feature",
  "properties": {
    "addr:full":"7080 Brooks Farm Rd Mechanicsville VA 23111",
    "addr:housenumber":"7080",
    "addr:postcode":"23111",
    "addr:street":"Brooks Farm Rd",
    "iso:country":"US",
    "sg:address":"7080 Brooks Farm Rd",
    "sg:city":"Mechanicsville",
    "sg:classifiers":[
        {
            "category":"Social Services",
            "subcategory":"Job Training",
            "type":"Services"
        }
    ],
    "sg:phone":"+1 804 559 4970",
    "sg:postcode":"23111",
    "sg:province":"VA",
    "sg:tags":[
        "rehabilitation"
    ],
    "wof:name":"Rehab Mgmt Inc",
    "wof:placetype":"venue"
},
  "geometry": {"coordinates":[-77.34205300000001,37.623467],"type":"Point"}
}