{
  "type": "Feature",
  "properties": {
    "addr:full":"9225 Wards Rd Rustburg VA 24588",
    "addr:housenumber":"9225",
    "addr:postcode":"24588",
    "addr:street":"Wards Rd",
    "iso:country":"US",
    "sg:address":"9225 Wards Rd",
    "sg:city":"Rustburg",
    "sg:classifiers":[
        {
            "category":"Freight",
            "type":"Transportation"
        }
    ],
    "sg:phone":"+1 434 821 5959",
    "sg:postcode":"24588",
    "sg:province":"VA",
    "sg:tags":[
        "operator",
        "repair",
        "local",
        "trucking"
    ],
    "wof:name":"Harveys Homes",
    "wof:placetype":"venue"
},
  "geometry": {"coordinates":[-79.18330899999999,37.2578],"type":"Point"}
}