{
  "type": "Feature",
  "properties": {
    "addr:full":"10367 New Britton Rd Mechanicsville VA 23116",
    "addr:housenumber":"10367",
    "addr:postcode":"23116",
    "addr:street":"New Britton Rd",
    "iso:country":"US",
    "sg:address":"10367 New Britton Rd",
    "sg:city":"Mechanicsville",
    "sg:classifiers":[
        {
            "category":"Building & Trades",
            "subcategory":"Construction",
            "type":"Services"
        }
    ],
    "sg:phone":"+1 804 746 2182",
    "sg:postcode":"23116",
    "sg:province":"VA",
    "sg:tags":[
        "house"
    ],
    "wof:name":"Paul H Connors",
    "wof:placetype":"venue"
},
  "geometry": {"coordinates":[-77.399754,37.690897],"type":"Point"}
}