{
  "type": "Feature",
  "properties": {
    "addr:full":"13409 Spriggs Rd Manassas VA 20112",
    "addr:postcode":"13409;20112",
    "addr:street":"Spriggs Rd",
    "iso:country":"US",
    "sg:address":"13409 Spriggs Rd",
    "sg:city":"Manassas",
    "sg:classifiers":[
        {
            "category":"Local Transit",
            "type":"Transportation"
        }
    ],
    "sg:phone":"+1 703 794 8595",
    "sg:postcode":"20112",
    "sg:province":"VA",
    "sg:tags":[
        "passenger"
    ],
    "wof:name":"Genesis Limousine",
    "wof:placetype":"venue"
},
  "geometry": {"coordinates":[-77.39933499999999,38.661941],"type":"Point"}
}