{
  "type": "Feature",
  "properties": {
    "addr:full":"151 Pullen Rd Lexington VA 24450",
    "addr:housenumber":"151",
    "addr:postcode":"24450",
    "addr:street":"Pullen Rd",
    "iso:country":"US",
    "sg:address":"151 Pullen Rd",
    "sg:city":"Lexington",
    "sg:classifiers":[
        {
            "category":"Wholesale",
            "subcategory":"Non-durable Goods",
            "type":"Manufacturing & Wholesale Goods"
        }
    ],
    "sg:phone":"+1 540 463 9556",
    "sg:postcode":"24450",
    "sg:province":"VA",
    "sg:tags":[
        "pet",
        "supply"
    ],
    "wof:name":"Chinook & Co",
    "wof:placetype":"venue"
},
  "geometry": {"coordinates":[-79.642415,37.716762],"type":"Point"}
}