{
  "type": "Feature",
  "properties": {
    "addr:full":"4520 King St Alexandria VA 22302",
    "addr:housenumber":"4520",
    "addr:postcode":"22302",
    "addr:street":"King St",
    "iso:country":"US",
    "sg:address":"4520 King St",
    "sg:city":"Alexandria",
    "sg:classifiers":[
        {
            "category":"Real Estate",
            "subcategory":"Real Estate Agent",
            "type":"Services"
        }
    ],
    "sg:phone":"+1 703 671 3254",
    "sg:postcode":"22302",
    "sg:province":"VA",
    "sg:tags":[
        "broker"
    ],
    "wof:name":"Brick Front Properties LLC",
    "wof:placetype":"venue"
},
  "geometry": {"coordinates":[-77.10593299999999,38.839927],"type":"Point"}
}