{
  "type": "Feature",
  "properties": {
    "addr:full":"8404 Finlay Ct Springfield VA 22153",
    "addr:housenumber":"8404",
    "addr:postcode":"22153",
    "addr:street":"Finlay Ct",
    "iso:country":"US",
    "sg:address":"8404 Finlay Ct",
    "sg:city":"Springfield",
    "sg:classifiers":[
        {
            "category":"Personal",
            "type":"Services"
        },
        {
            "category":"Arts & Performance",
            "subcategory":"Music",
            "type":"Entertainment"
        },
        {
            "category":"Retail",
            "subcategory":"Event Space",
            "type":"Services"
        }
    ],
    "sg:phone":"+1 703 455 1950",
    "sg:postcode":"22153",
    "sg:province":"VA",
    "sg:tags":[
        "party",
        "planning",
        "meeting",
        "wedding"
    ],
    "sg:website":"http://www.celestialsinging.com",
    "wof:name":"Celestial Singing",
    "wof:placetype":"venue"
},
  "geometry": {"coordinates":[-77.216382,38.729331],"type":"Point"}
}