{
  "type": "Feature",
  "properties": {
    "iso:country":"US",
    "sg:address":"7190 Charlie Town Rd",
    "sg:city":"Port Republic",
    "sg:classifiers":[
        {
            "category":"Retail",
            "subcategory":"Auto Repair",
            "type":"Services"
        }
    ],
    "sg:phone":"+1 540 289 5079",
    "sg:postcode":"24471",
    "sg:province":"VA",
    "sg:tags":[
        "general"
    ],
    "wof:name":"Dalmatian Hill Engneering",
    "wof:placetype":"venue"
},
  "geometry": {"coordinates":[-78.812985,38.341438],"type":"Point"}
}