{
  "type": "Feature",
  "properties": {
    "iso:country":"US",
    "sg:address":"128 Church St",
    "sg:city":"Poquoson",
    "sg:classifiers":[
        {
            "category":"Manufacturing",
            "subcategory":"Signs",
            "type":"Manufacturing & Wholesale Goods"
        }
    ],
    "sg:phone":"+1 757 868 6526",
    "sg:postcode":"23662",
    "sg:province":"VA",
    "sg:tags":[
        "specialty",
        "mfg"
    ],
    "wof:name":"Joeys Sign & Letter Inc",
    "wof:placetype":"venue"
},
  "geometry": {"coordinates":[-76.355125,37.121606],"type":"Point"}
}