{
  "type": "Feature",
  "properties": {
    "iso:country":"US",
    "sg:address":"4803 Lockgreen Cir",
    "sg:city":"Richmond",
    "sg:classifiers":[
        {
            "category":"Real Estate",
            "subcategory":"Real Estate Agent",
            "type":"Services"
        }
    ],
    "sg:phone":"+1 804 358 1094",
    "sg:postcode":"23226",
    "sg:province":"VA",
    "wof:name":"Allen Family Ltd Partnership",
    "wof:placetype":"venue"
},
  "geometry": {"coordinates":[-77.512361,37.559636],"type":"Point"}
}