{
  "type": "Feature",
  "properties": {
    "addr:full":"5310 Kimanna Dr Centreville VA 20120",
    "addr:housenumber":"5310",
    "addr:postcode":"20120",
    "addr:street":"Kimanna Dr",
    "iso:country":"US",
    "sg:address":"5310 Kimanna Dr",
    "sg:city":"Centreville",
    "sg:classifiers":[
        {
            "category":"Building & Trades",
            "subcategory":"Construction",
            "type":"Services"
        }
    ],
    "sg:phone":"+1 703 830 9582",
    "sg:postcode":"20120",
    "sg:province":"VA",
    "sg:tags":[
        "hanging",
        "contractor"
    ],
    "wof:name":"Seymours Paintings",
    "wof:placetype":"venue"
},
  "geometry": {"coordinates":[-77.45634099999999,38.86349],"type":"Point"}
}