{
  "type": "Feature",
  "properties": {
    "addr:full":"302 S Main St Blackstone VA 23824",
    "addr:housenumber":"302",
    "addr:postcode":"23824",
    "addr:street":"S Main St",
    "iso:country":"US",
    "sg:address":"302 S Main St",
    "sg:city":"Blackstone",
    "sg:classifiers":[
        {
            "category":"Retail",
            "subcategory":"Laundry & Dry Cleaning",
            "type":"Services"
        }
    ],
    "sg:phone":"+1 434 292 7127",
    "sg:postcode":"23824",
    "sg:province":"VA",
    "sg:tags":[
        "cleaners",
        "agent",
        "garment"
    ],
    "wof:name":"Blackstone's Cavalier Cleaners",
    "wof:placetype":"venue"
},
  "geometry": {"coordinates":[-77.99849,37.078697],"type":"Point"}
}