{
  "type": "Feature",
  "properties": {
    "iso:country":"US",
    "sg:address":"1725 Duke St",
    "sg:city":"Alexandria",
    "sg:classifiers":[
        {
            "category":"Freight",
            "type":"Transportation"
        }
    ],
    "sg:phone":"+1 703 299 4770",
    "sg:postcode":"22314",
    "sg:province":"VA",
    "wof:name":"Traffic Tech Intl USA LLC",
    "wof:placetype":"venue"
},
  "geometry": {"coordinates":[-77.061418,38.804566],"type":"Point"}
}