{
  "type": "Feature",
  "properties": {
    "iso:country":"US",
    "sg:address":"13037 Lee Jackson Memorial Hwy",
    "sg:city":"Fairfax",
    "sg:classifiers":[
        {
            "category":"Personal",
            "subcategory":"Beauty Salon",
            "type":"Services"
        }
    ],
    "sg:phone":"+1 703 968 9112",
    "sg:postcode":"22033",
    "sg:province":"VA",
    "sg:tags":[
        "shop"
    ],
    "wof:name":"Fancy Nails",
    "wof:placetype":"venue"
},
  "geometry": {"coordinates":[-77.400069,38.881914],"type":"Point"}
}