{
  "type": "Feature",
  "properties": {
    "addr:full":"30363 Marcus Dr Glade Spring VA 24361",
    "addr:postcode":"30363;24361",
    "addr:street":"Marcus Dr",
    "iso:country":"US",
    "sg:address":"30363 Marcus Dr",
    "sg:city":"Glade Spring",
    "sg:classifiers":[
        {
            "category":"Autos & Motor Vehicles",
            "subcategory":"Automobile Sales",
            "type":"Retail Goods"
        }
    ],
    "sg:phone":"+1 276 944 4772",
    "sg:postcode":"24361",
    "sg:province":"VA",
    "sg:tags":[
        "car",
        "used",
        "dealer"
    ],
    "wof:name":"Broadwine Auto Sales",
    "wof:placetype":"venue"
},
  "geometry": {"coordinates":[-81.832852,36.757482],"type":"Point"}
}