{
  "type": "Feature",
  "properties": {
    "addr:full":"529 J Clyde Morris Blvd Newport News VA 23601",
    "addr:housenumber":"529",
    "addr:postcode":"23601",
    "addr:street":"J Clyde Morris Blvd",
    "iso:country":"US",
    "sg:address":"529 J Clyde Morris Blvd",
    "sg:city":"Newport News",
    "sg:classifiers":[
        {
            "category":"Wholesale",
            "subcategory":"Metals & Minerals",
            "type":"Manufacturing & Wholesale Goods"
        }
    ],
    "sg:phone":"+1 757 596 1606",
    "sg:postcode":"23601",
    "sg:province":"VA",
    "sg:tags":[
        "steel",
        "warehouse"
    ],
    "sg:website":"www.richmansteel.com",
    "wof:name":"Richman Steel & Fabrication",
    "wof:placetype":"venue"
},
  "geometry": {"coordinates":[-76.476664,37.073238],"type":"Point"}
}