{
  "type": "Feature",
  "properties": {
    "addr:full":"13041 Greenwood Rd Glen Allen VA 23059",
    "addr:housenumber":"13041",
    "addr:postcode":"23059",
    "addr:street":"Greenwood Rd",
    "iso:country":"US",
    "sg:address":"13041 Greenwood Rd",
    "sg:city":"Glen Allen",
    "sg:classifiers":[
        {
            "category":"Building & Trades",
            "subcategory":"Equipment Rental",
            "type":"Services"
        }
    ],
    "sg:phone":"+1 804 798 8131",
    "sg:postcode":"23059",
    "sg:province":"VA",
    "sg:tags":[
        "heavy",
        "concrete",
        "construction",
        "contractor"
    ],
    "wof:name":"Janclar Eqp Rentals & Mtls",
    "wof:placetype":"venue"
},
  "geometry": {"coordinates":[-77.54608,37.714089],"type":"Point"}
}