{
  "type": "Feature",
  "properties": {
    "iso:country":"US",
    "sg:address":"633 S Washington St",
    "sg:city":"Alexandria",
    "sg:classifiers":[
        {
            "category":"Organizations",
            "subcategory":"Professional Association",
            "type":"Services"
        }
    ],
    "sg:phone":"+1 703 836 0850",
    "sg:postcode":"22314",
    "sg:province":"VA",
    "sg:tags":[
        "membership"
    ],
    "wof:name":"N R A",
    "wof:placetype":"venue"
},
  "geometry": {"coordinates":[-77.048445,38.798588],"type":"Point"}
}