{
  "type": "Feature",
  "properties": {
    "addr:full":"3301 Jefferson Davis Hwy Fredericksburg VA 22401",
    "addr:housenumber":"3301",
    "addr:postcode":"22401",
    "addr:street":"Jefferson Davis Hwy",
    "iso:country":"US",
    "sg:address":"3301 Jefferson Davis Hwy",
    "sg:city":"Fredericksburg",
    "sg:classifiers":[
        {
            "category":"Real Estate",
            "subcategory":"Real Estate Agent",
            "type":"Services"
        }
    ],
    "sg:phone":"+1 540 899 0995",
    "sg:postcode":"22401",
    "sg:province":"VA",
    "sg:tags":[
        "business"
    ],
    "wof:name":"AP Appraisal Services",
    "wof:placetype":"venue"
},
  "geometry": {"coordinates":[-77.49065,38.277502],"type":"Point"}
}