{
  "type": "Feature",
  "properties": {
    "addr:full":"8049 Ormesby Ln Woodford VA 22580",
    "addr:housenumber":"8049",
    "addr:postcode":"22580",
    "addr:street":"Ormesby Ln",
    "iso:country":"US",
    "sg:address":"8049 Ormesby Ln",
    "sg:city":"Woodford",
    "sg:classifiers":[
        {
            "category":"Travel",
            "subcategory":"Travel Agent",
            "type":"Entertainment"
        }
    ],
    "sg:phone":"+1 804 633 6752",
    "sg:postcode":"22580",
    "sg:province":"VA",
    "sg:tags":[
        "agency",
        "bureau"
    ],
    "sg:website":"www.wcduke.com",
    "wof:name":"W C Duke & Assoc Inc",
    "wof:placetype":"venue"
},
  "geometry": {"coordinates":[-77.43997400000001,38.155168],"type":"Point"}
}