{
  "type": "Feature",
  "properties": {
    "addr:full":"13873 Park Center Rd Herndon VA 20171",
    "addr:housenumber":"13873",
    "addr:postcode":"20171",
    "addr:street":"Park Center Rd",
    "iso:country":"US",
    "sg:address":"13873 Park Center Rd",
    "sg:city":"Herndon",
    "sg:classifiers":[
        {
            "category":"Real Estate",
            "subcategory":"Real Estate Agent",
            "type":"Services"
        }
    ],
    "sg:phone":"+1 703 481 3104",
    "sg:postcode":"20171",
    "sg:province":"VA",
    "sg:tags":[
        "broker"
    ],
    "wof:name":"Trusa Realty Inc",
    "wof:placetype":"venue"
},
  "geometry": {"coordinates":[-77.42601000000001,38.933122],"type":"Point"}
}