{
  "type": "Feature",
  "properties": {
    "iso:country":"US",
    "sg:address":"320 W 5th Ave",
    "sg:city":"Lawrenceville",
    "sg:classifiers":[
        {
            "category":"Manufacturing",
            "subcategory":"Tools & Machinery",
            "type":"Manufacturing & Wholesale Goods"
        }
    ],
    "sg:phone":"+1 434 848 3460",
    "sg:postcode":"23868",
    "sg:province":"VA",
    "sg:tags":[
        "machine",
        "shop"
    ],
    "wof:name":"Lawrenceville Machine Shop",
    "wof:placetype":"venue"
},
  "geometry": {"coordinates":[-77.852884,36.754606],"type":"Point"}
}