{
  "type": "Feature",
  "properties": {
    "addr:full":"15100 Enterprise Ct Chantilly VA 20151",
    "addr:housenumber":"15100",
    "addr:postcode":"20151",
    "addr:street":"Enterprise Ct",
    "iso:country":"US",
    "sg:address":"15100 Enterprise Ct",
    "sg:city":"Chantilly",
    "sg:classifiers":[
        {
            "category":"Professional",
            "subcategory":"Engineering",
            "type":"Services"
        }
    ],
    "sg:phone":"+1 703 961 8700",
    "sg:postcode":"20151",
    "sg:province":"VA",
    "sg:tags":[
        "engineer"
    ],
    "sg:website":"www.phytotech.com",
    "wof:name":"Edenspace Systems Corp",
    "wof:placetype":"venue"
},
  "geometry": {"coordinates":[-77.46928699999999,38.906889],"type":"Point"}
}