{
  "type": "Feature",
  "properties": {
    "iso:country":"US",
    "sg:address":"780 Lynnhaven Pkwy",
    "sg:city":"Virginia Beach",
    "sg:classifiers":[
        {
            "category":"Professional",
            "subcategory":"Lawyer & Legal Services",
            "type":"Services"
        }
    ],
    "sg:phone":"+1 757 468 1345",
    "sg:postcode":"23452",
    "sg:province":"VA",
    "wof:name":"Richard Conrod Atty At Law",
    "wof:placetype":"venue"
},
  "geometry": {"coordinates":[-76.066762,36.81621],"type":"Point"}
}