{
  "type": "Feature",
  "properties": {
    "addr:full":"23746 Rogers Clark Blvd Ruther Glen VA 22546",
    "addr:housenumber":"23746",
    "addr:postcode":"22546",
    "addr:street":"Rogers Clark Blvd",
    "iso:country":"US",
    "sg:address":"23746 Rogers Clark Blvd",
    "sg:city":"Ruther Glen",
    "sg:classifiers":[
        {
            "category":"Autos & Motor Vehicles",
            "subcategory":"Fuel & Gas Station",
            "type":"Retail Goods"
        }
    ],
    "sg:phone":"+1 804 448 4031",
    "sg:postcode":"22546",
    "sg:province":"VA",
    "sg:tags":[
        "oil"
    ],
    "wof:name":"Chevron",
    "wof:placetype":"venue"
},
  "geometry": {"coordinates":[-77.462153,37.940853],"type":"Point"}
}