{
  "type": "Feature",
  "properties": {
    "iso:country":"US",
    "sg:address":"5614 Hollins Rd",
    "sg:city":"Roanoke",
    "sg:classifiers":[
        {
            "category":"Manufacturing",
            "subcategory":"Electronics",
            "type":"Manufacturing & Wholesale Goods"
        }
    ],
    "sg:phone":"+1 540 427 2400",
    "sg:postcode":"24019",
    "sg:province":"VA",
    "sg:tags":[
        "sound",
        "equipment",
        "mfg",
        "telephone",
        "p",
        "including"
    ],
    "wof:name":"Valcom Services LLC",
    "wof:placetype":"venue"
},
  "geometry": {"coordinates":[-79.92599300000001,37.339792],"type":"Point"}
}