{
  "type": "Feature",
  "properties": {
    "addr:full":"3830 Jefferson Davis Hwy Fredericksburg VA 22408",
    "addr:housenumber":"3830",
    "addr:postcode":"22408",
    "addr:street":"Jefferson Davis Hwy",
    "iso:country":"US",
    "sg:address":"3830 Jefferson Davis Hwy",
    "sg:city":"Fredericksburg",
    "sg:classifiers":[
        {
            "category":"Food & Beverages",
            "subcategory":"Groceries & Convenience Stores",
            "type":"Retail Goods"
        }
    ],
    "sg:phone":"+1 540 898 7241",
    "sg:postcode":"22408",
    "sg:province":"VA",
    "wof:name":"Snellings Food & Convenience",
    "wof:placetype":"venue"
},
  "geometry": {"coordinates":[-77.49337800000001,38.268903],"type":"Point"}
}