{
  "type": "Feature",
  "properties": {
    "addr:full":"517 Washington St Portsmouth VA 23704",
    "addr:housenumber":"517",
    "addr:postcode":"23704",
    "addr:street":"Washington St",
    "iso:country":"US",
    "sg:address":"517 Washington St",
    "sg:city":"Portsmouth",
    "sg:classifiers":[
        {
            "category":"Real Estate",
            "subcategory":"Real Estate Agent",
            "type":"Services"
        }
    ],
    "sg:phone":"+1 757 397 4430",
    "sg:postcode":"23704",
    "sg:province":"VA",
    "wof:name":"Exantus Investment Group LLC",
    "wof:placetype":"venue"
},
  "geometry": {"coordinates":[-76.303763,36.834606],"type":"Point"}
}