{
  "type": "Feature",
  "properties": {
    "iso:country":"US",
    "sg:address":"27 E Main St",
    "sg:city":"Salem",
    "sg:classifiers":[
        {
            "category":"Building & Trades",
            "subcategory":"Construction",
            "type":"Services"
        }
    ],
    "sg:phone":"+1 540 375 8828",
    "sg:postcode":"24153",
    "sg:province":"VA",
    "sg:tags":[
        "tile",
        "dealer"
    ],
    "wof:name":"Southwest Va Tile & Stone",
    "wof:placetype":"venue"
},
  "geometry": {"coordinates":[-80.056769,37.293074],"type":"Point"}
}