{
  "type": "Feature",
  "properties": {
    "iso:country":"US",
    "sg:address":"20477 Market St",
    "sg:city":"Onancock",
    "sg:classifiers":[
        {
            "category":"Real Estate",
            "subcategory":"Real Estate Agent",
            "type":"Services"
        }
    ],
    "sg:phone":"+1 757 787 7603",
    "sg:postcode":"23417",
    "sg:province":"VA",
    "sg:website":"www.southernshoreshomes.com",
    "wof:name":"Southern Shores Realty",
    "wof:placetype":"venue"
},
  "geometry": {"coordinates":[-75.72202,37.700583],"type":"Point"}
}