{
  "type": "Feature",
  "properties": {
    "iso:country":"US",
    "sg:address":"8718 W Broad St",
    "sg:city":"Richmond",
    "sg:classifiers":[
        {
            "category":"Wholesale",
            "subcategory":"Farm Supplies",
            "type":"Manufacturing & Wholesale Goods"
        }
    ],
    "sg:phone":"+1 804 747 9315",
    "sg:postcode":"23294",
    "sg:province":"VA",
    "sg:tags":[
        "feed"
    ],
    "sg:website":"www.southernstates.com",
    "wof:name":"Southern States Cooperative",
    "wof:placetype":"venue"
},
  "geometry": {"coordinates":[-77.54263,37.633601],"type":"Point"}
}