{
  "type": "Feature",
  "properties": {
    "addr:full":"320 W 21st St Norfolk VA 23517",
    "addr:housenumber":"320",
    "addr:postcode":"23517",
    "addr:street":"W 21St St",
    "iso:country":"US",
    "sg:address":"320 W 21st St",
    "sg:city":"Norfolk",
    "sg:classifiers":[
        {
            "category":"Home & Garden",
            "subcategory":"Carpets & Floor Coverings",
            "type":"Retail Goods"
        }
    ],
    "sg:phone":"+1 804 358 1711",
    "sg:postcode":"23517",
    "sg:province":"VA",
    "sg:tags":[
        "dealer",
        "rug"
    ],
    "wof:name":"Amir Rug Exchange",
    "wof:placetype":"venue"
},
  "geometry": {"coordinates":[-76.289562,36.868663],"type":"Point"}
}