{
  "type": "Feature",
  "properties": {
    "iso:country":"US",
    "sg:address":"3810 Meredith Dr",
    "sg:city":"Fairfax",
    "sg:classifiers":[
        {
            "category":"Organizations",
            "subcategory":"Religious Organization",
            "type":"Services"
        }
    ],
    "sg:phone":"+1 703 425 9075",
    "sg:postcode":"22030",
    "sg:province":"VA",
    "sg:tags":[
        "church"
    ],
    "wof:name":"Central Presby Ch Of Virginia",
    "wof:placetype":"venue"
},
  "geometry": {"coordinates":[-77.317549,38.856505],"type":"Point"}
}