{
  "type": "Feature",
  "properties": {
    "iso:country":"US",
    "sg:address":"100 Culpepper Rd",
    "sg:city":"Portsmouth",
    "sg:classifiers":[
        {
            "category":"Shopping",
            "subcategory":"Gifts & Souvenirs",
            "type":"Retail Goods"
        }
    ],
    "sg:phone":"+1 757 397 6043",
    "sg:postcode":"23704",
    "sg:province":"VA",
    "sg:tags":[
        "eating"
    ],
    "wof:name":"Pfeiffers Books & Cards Inc",
    "wof:placetype":"venue"
},
  "geometry": {"coordinates":[-76.326978,36.843211],"type":"Point"}
}