{
  "type": "Feature",
  "properties": {
    "addr:full":"5267 Hull Street Rd Richmond VA 23224",
    "addr:housenumber":"5267",
    "addr:postcode":"23224",
    "addr:street":"Hull Street Rd",
    "iso:country":"US",
    "sg:address":"5267 Hull Street Rd",
    "sg:city":"Richmond",
    "sg:classifiers":[
        {
            "category":"Restaurant",
            "type":"Food & Drink"
        }
    ],
    "sg:phone":"+1 804 232 4051",
    "sg:postcode":"23224",
    "sg:province":"VA",
    "wof:name":"Hideaway Restaurant",
    "wof:placetype":"venue"
},
  "geometry": {"coordinates":[-77.489907,37.491583],"type":"Point"}
}