{
  "type": "Feature",
  "properties": {
    "iso:country":"US",
    "sg:address":"730 Marshall Rd SW",
    "sg:city":"Vienna",
    "sg:classifiers":[
        {
            "category":"Education",
            "subcategory":"School",
            "type":"Public Place"
        }
    ],
    "sg:phone":"+1 703 937 1500",
    "sg:postcode":"22180",
    "sg:province":"VA",
    "sg:website":"www.fcps.edu",
    "wof:name":"Marshall Road Elementary Schl",
    "wof:placetype":"venue"
},
  "geometry": {"coordinates":[-77.26718,38.882947],"type":"Point"}
}