{
  "type": "Feature",
  "properties": {
    "addr:full":"1324 Penniman Rd Williamsburg VA 23185",
    "addr:housenumber":"1324",
    "addr:postcode":"23185",
    "addr:street":"Penniman Rd",
    "iso:country":"US",
    "sg:address":"1324 Penniman Rd",
    "sg:city":"Williamsburg",
    "sg:classifiers":[
        {
            "category":"Freight",
            "type":"Transportation"
        }
    ],
    "sg:phone":"+1 757 220 4999",
    "sg:postcode":"23185",
    "sg:province":"VA",
    "sg:tags":[
        "warehouse"
    ],
    "sg:website":"www.libertywarehousing.com",
    "wof:name":"Liberty Warehousing Inc",
    "wof:placetype":"venue"
},
  "geometry": {"coordinates":[-76.658204,37.259288],"type":"Point"}
}