{
  "type": "Feature",
  "properties": {
    "iso:country":"US",
    "sg:address":"11681 Fox Glen Dr",
    "sg:city":"Oakton",
    "sg:classifiers":[
        {
            "category":"Health Services",
            "subcategory":"Chiropractor",
            "type":"Services"
        }
    ],
    "sg:phone":"+1 703 352 4357",
    "sg:postcode":"22124",
    "sg:province":"VA",
    "wof:name":"Chiroprctic Physcl Therapy Ctr",
    "wof:placetype":"venue"
},
  "geometry": {"coordinates":[-77.349059,38.88415],"type":"Point"}
}