{
  "type": "Feature",
  "properties": {
    "addr:full":"1081 19th St Virginia Beach VA 23451",
    "addr:housenumber":"1081",
    "addr:postcode":"23451",
    "addr:street":"19Th St",
    "iso:country":"US",
    "sg:address":"1081 19th St",
    "sg:city":"Virginia Beach",
    "sg:classifiers":[
        {
            "category":"Travel",
            "subcategory":"Hotels & Motels",
            "type":"Entertainment"
        }
    ],
    "sg:phone":"+1 757 437 0164",
    "sg:postcode":"23451",
    "sg:province":"VA",
    "sg:website":"www.goldkeyresorts.com",
    "wof:name":"Gold Key Welcome Ctr",
    "wof:placetype":"venue"
},
  "geometry": {"coordinates":[-75.99126699999999,36.844495],"type":"Point"}
}