{
  "type": "Feature",
  "properties": {
    "addr:full":"13039 Fair Lakes Shopping Ctr Fairfax VA 22033",
    "addr:housenumber":"13039",
    "addr:postcode":"22033",
    "addr:street":"Fair Lakes Shopping Ctr",
    "iso:country":"US",
    "sg:address":"13039 Fair Lakes Shopping Ctr",
    "sg:city":"Fairfax",
    "sg:classifiers":[
        {
            "category":"Restaurant",
            "type":"Food & Drink"
        }
    ],
    "sg:menulink":"http://www.allmenus.com/va/sully/24804-tsunami/menu/",
    "sg:phone":"+1 703 449 8404",
    "sg:postcode":"22033",
    "sg:province":"VA",
    "sg:tags":[
        "japanese",
        "asian"
    ],
    "wof:name":"Tsunami",
    "wof:placetype":"venue"
},
  "geometry": {"coordinates":[-77.39345400000001,38.857063],"type":"Point"}
}