{
  "type": "Feature",
  "properties": {
    "addr:full":"7230 Lockport Pl Lorton VA 22079",
    "addr:housenumber":"7230",
    "addr:postcode":"22079",
    "addr:street":"Lockport Pl",
    "iso:country":"US",
    "sg:address":"7230 Lockport Pl",
    "sg:city":"Lorton",
    "sg:classifiers":[
        {
            "category":"Restaurant",
            "type":"Food & Drink"
        }
    ],
    "sg:phone":"+1 703 550 9792",
    "sg:postcode":"22079",
    "sg:province":"VA",
    "sg:tags":[
        "eating"
    ],
    "wof:name":"Hearts Delight",
    "wof:placetype":"venue"
},
  "geometry": {"coordinates":[-77.193241,38.715486],"type":"Point"}
}