{
  "type": "Feature",
  "properties": {
    "addr:full":"705 E Washington St Suffolk VA 23434",
    "addr:housenumber":"705",
    "addr:postcode":"23434",
    "addr:street":"E Washington St",
    "iso:country":"US",
    "sg:address":"705 E Washington St",
    "sg:city":"Suffolk",
    "sg:classifiers":[
        {
            "category":"Professional",
            "subcategory":"Accounting & Tax Preparation",
            "type":"Services"
        }
    ],
    "sg:phone":"+1 757 539 9123",
    "sg:postcode":"23434",
    "sg:province":"VA",
    "sg:tags":[
        "bookkeeping",
        "return",
        "general"
    ],
    "wof:name":"Nicholson Tax Service Inc",
    "wof:placetype":"venue"
},
  "geometry": {"coordinates":[-76.572602,36.724819],"type":"Point"}
}