{
  "type": "Feature",
  "properties": {
    "iso:country":"US",
    "sg:address":"382 S Pickett St",
    "sg:city":"Alexandria",
    "sg:classifiers":[
        {
            "category":"Home & Garden",
            "subcategory":"Furniture",
            "type":"Retail Goods"
        }
    ],
    "sg:phone":"+1 703 212 9040",
    "sg:postcode":"22304",
    "sg:province":"VA",
    "wof:name":"Mattress Warehouse",
    "wof:placetype":"venue"
},
  "geometry": {"coordinates":[-77.128745,38.807339],"type":"Point"}
}