{
  "type": "Feature",
  "properties": {
    "iso:country":"US",
    "sg:address":"400 Madison St Apt 1306",
    "sg:city":"Alexandria",
    "sg:classifiers":[
        {
            "category":"Shopping",
            "subcategory":"Stationery & Office Supplies",
            "type":"Retail Goods"
        }
    ],
    "sg:phone":"+1 703 684 5560",
    "sg:postcode":"22314",
    "sg:province":"VA",
    "sg:tags":[
        "envelope",
        "store"
    ],
    "wof:name":"Always Write Ltd",
    "wof:placetype":"venue"
},
  "geometry": {"coordinates":[-77.041939,38.81258],"type":"Point"}
}