{
  "type": "Feature",
  "properties": {
    "addr:full":"9273 Sprucewood Rd Burke VA 22015",
    "addr:housenumber":"9273",
    "addr:postcode":"22015",
    "addr:street":"Sprucewood Rd",
    "iso:country":"US",
    "sg:address":"9273 Sprucewood Rd",
    "sg:city":"Burke",
    "sg:classifiers":[
        {
            "category":"Professional",
            "subcategory":"Management & Consulting",
            "type":"Services"
        }
    ],
    "sg:phone":"+1 703 455 1281",
    "sg:postcode":"22015",
    "sg:province":"VA",
    "sg:tags":[
        "business"
    ],
    "wof:name":"Kern Communications",
    "wof:placetype":"venue"
},
  "geometry": {"coordinates":[-77.26228500000001,38.779816],"type":"Point"}
}