{
  "type": "Feature",
  "properties": {
    "addr:full":"1604 Jamestown Dr Charlottesville VA 22901",
    "addr:housenumber":"1604",
    "addr:postcode":"22901",
    "addr:street":"Jamestown Dr",
    "iso:country":"US",
    "sg:address":"1604 Jamestown Dr",
    "sg:city":"Charlottesville",
    "sg:classifiers":[
        {
            "category":"Social Services",
            "type":"Services"
        }
    ],
    "sg:phone":"+1 434 971 8406",
    "sg:postcode":"22901",
    "sg:province":"VA",
    "wof:name":"Patricia A Cheeks",
    "wof:placetype":"venue"
},
  "geometry": {"coordinates":[-78.473845,38.061865],"type":"Point"}
}