{
  "type": "Feature",
  "properties": {
    "iso:country":"US",
    "sg:address":"5589 Greenwich Rd",
    "sg:city":"Virginia Beach",
    "sg:classifiers":[
        {
            "category":"Communications",
            "subcategory":"Radio Station",
            "type":"Services"
        }
    ],
    "sg:phone":"+1 757 671 1000",
    "sg:postcode":"23462",
    "sg:province":"VA",
    "sg:tags":[
        "broadcasting"
    ],
    "wof:name":"Wgh Eagle",
    "wof:placetype":"venue"
},
  "geometry": {"coordinates":[-76.180368,36.844587],"type":"Point"}
}