{
  "type": "Feature",
  "properties": {
    "iso:country":"US",
    "sg:address":"650 Meadow St NE",
    "sg:city":"Coeburn",
    "sg:classifiers":[
        {
            "category":"Arts & Performance",
            "subcategory":"Theater",
            "type":"Entertainment"
        }
    ],
    "sg:phone":"+1 276 395 8196",
    "sg:postcode":"24230",
    "sg:province":"VA",
    "sg:tags":[
        "group"
    ],
    "wof:name":"Virginia Cross Ties",
    "wof:placetype":"venue"
},
  "geometry": {"coordinates":[-82.461567,36.94529],"type":"Point"}
}