{
  "type": "Feature",
  "properties": {
    "iso:country":"US",
    "sg:address":"2615 Orange Ave NE",
    "sg:city":"Roanoke",
    "sg:classifiers":[
        {
            "category":"Organizations",
            "subcategory":"Community Association",
            "type":"Services"
        }
    ],
    "sg:phone":"+1 540 344 6197",
    "sg:postcode":"24012",
    "sg:province":"VA",
    "wof:name":"Independent Order Odd Fellows",
    "wof:placetype":"venue"
},
  "geometry": {"coordinates":[-79.90450800000001,37.293326],"type":"Point"}
}