{
  "type": "Feature",
  "properties": {
    "iso:country":"US",
    "sg:address":"909 Grantham Ln",
    "sg:city":"Chesapeake",
    "sg:classifiers":[
        {
            "category":"Banks & Credit Unions",
            "subcategory":"Financial Services",
            "type":"Services"
        }
    ],
    "sg:phone":"+1 757 546 7700",
    "sg:postcode":"23322",
    "sg:province":"VA",
    "sg:tags":[
        "investor"
    ],
    "wof:name":"Joshua Investments Inc",
    "wof:placetype":"venue"
},
  "geometry": {"coordinates":[-76.201674,36.690113],"type":"Point"}
}