{
  "type": "Feature",
  "properties": {
    "addr:full":"1920 Fairmount Ave Richmond VA 23223",
    "addr:housenumber":"1920",
    "addr:postcode":"23223",
    "addr:street":"Fairmount Ave",
    "iso:country":"US",
    "sg:address":"1920 Fairmount Ave",
    "sg:city":"Richmond",
    "sg:classifiers":[
        {
            "category":"Social Services",
            "subcategory":"Child Care",
            "type":"Services"
        }
    ],
    "sg:phone":"+1 804 648 0039",
    "sg:postcode":"23223",
    "sg:province":"VA",
    "wof:name":"Bethlehem Baptist Day Care",
    "wof:placetype":"venue"
},
  "geometry": {"coordinates":[-77.415188,37.543263],"type":"Point"}
}