{
  "type": "Feature",
  "properties": {
    "addr:full":"445 Battlefield Blvd N Chesapeake VA 23320",
    "addr:housenumber":"445",
    "addr:postcode":"23320",
    "addr:street":"Battlefield Blvd N",
    "iso:country":"US",
    "sg:address":"445 Battlefield Blvd N",
    "sg:city":"Chesapeake",
    "sg:classifiers":[
        {
            "category":"Professional",
            "subcategory":"Business Services",
            "type":"Services"
        }
    ],
    "sg:phone":"+1 757 549 1076",
    "sg:postcode":"23320",
    "sg:province":"VA",
    "sg:tags":[
        "recording",
        "studio"
    ],
    "wof:name":"Steveland Recording Studios",
    "wof:placetype":"venue"
},
  "geometry": {"coordinates":[-76.240127,36.731529],"type":"Point"}
}