{
  "type": "Feature",
  "properties": {
    "addr:full":"1210 Tatum Dr Alexandria VA 22307",
    "addr:housenumber":"1210",
    "addr:postcode":"22307",
    "addr:street":"Tatum Dr",
    "iso:country":"US",
    "sg:address":"1210 Tatum Dr",
    "sg:city":"Alexandria",
    "sg:classifiers":[
        {
            "category":"Professional",
            "type":"Services"
        }
    ],
    "sg:phone":"+1 703 660 6556",
    "sg:postcode":"22307",
    "sg:province":"VA",
    "wof:name":"Carmen Berger",
    "wof:placetype":"venue"
},
  "geometry": {"coordinates":[-77.052897,38.76133],"type":"Point"}
}