{
  "type": "Feature",
  "properties": {
    "addr:full":"4301 Cedar Ln Portsmouth VA 23703",
    "addr:housenumber":"4301",
    "addr:postcode":"23703",
    "addr:street":"Cedar Ln",
    "iso:country":"US",
    "sg:address":"4301 Cedar Ln",
    "sg:city":"Portsmouth",
    "sg:classifiers":[
        {
            "category":"Organizations",
            "subcategory":"Religious Organization",
            "type":"Services"
        }
    ],
    "sg:phone":"+1 757 484 0624",
    "sg:postcode":"23703",
    "sg:province":"VA",
    "sg:tags":[
        "church"
    ],
    "sg:website":"www.nlm.cc",
    "wof:name":"New Life Ministries",
    "wof:placetype":"venue"
},
  "geometry": {"coordinates":[-76.37455300000001,36.882599],"type":"Point"}
}