{
  "type": "Feature",
  "properties": {
    "iso:country":"US",
    "sg:address":"11488 Waterhaven Ct",
    "sg:city":"Reston",
    "sg:classifiers":[
        {
            "category":"Building & Trades",
            "subcategory":"Construction",
            "type":"Services"
        }
    ],
    "sg:phone":"+1 703 435 1655",
    "sg:postcode":"20190",
    "sg:province":"VA",
    "sg:tags":[
        "floor",
        "laying",
        "contractor"
    ],
    "wof:name":"Jack Mecca Flooring",
    "wof:placetype":"venue"
},
  "geometry": {"coordinates":[-77.34269399999999,38.964248],"type":"Point"}
}