{
  "type": "Feature",
  "properties": {
    "iso:country":"US",
    "sg:address":"794 Shopping Center Rd",
    "sg:city":"Strasburg",
    "sg:classifiers":[
        {
            "category":"Food & Beverages",
            "subcategory":"Groceries & Convenience Stores",
            "type":"Retail Goods"
        }
    ],
    "sg:phone":"+1 540 465 5335",
    "sg:postcode":"22657",
    "sg:province":"VA",
    "sg:tags":[
        "supermarket",
        "chain"
    ],
    "wof:name":"Food Lion Store 550",
    "wof:placetype":"venue"
},
  "geometry": {"coordinates":[-78.35215599999999,38.997062],"type":"Point"}
}