{
  "type": "Feature",
  "properties": {
    "addr:full":"3608 12th St S Arlington VA 22204",
    "addr:housenumber":"3608",
    "addr:postcode":"22204",
    "addr:street":"12Th St S",
    "iso:country":"US",
    "sg:address":"3608 12th St S",
    "sg:city":"Arlington",
    "sg:classifiers":[
        {
            "category":"Professional",
            "subcategory":"Management & Consulting",
            "type":"Services"
        }
    ],
    "sg:phone":"+1 703 920 0874",
    "sg:postcode":"22204",
    "sg:province":"VA",
    "sg:tags":[
        "construction"
    ],
    "wof:name":"Project Management Svc Bureau",
    "wof:placetype":"venue"
},
  "geometry": {"coordinates":[-77.098146,38.857807],"type":"Point"}
}