{
  "type": "Feature",
  "properties": {
    "addr:full":"15161 Washington St Haymarket VA 20169",
    "addr:housenumber":"15161",
    "addr:postcode":"20169",
    "addr:street":"Washington St",
    "iso:country":"US",
    "sg:address":"15161 Washington St",
    "sg:city":"Haymarket",
    "sg:classifiers":[
        {
            "category":"Autos & Motor Vehicles",
            "subcategory":"Automobile Sales",
            "type":"Retail Goods"
        }
    ],
    "sg:phone":"+1 703 754 4884",
    "sg:postcode":"20169",
    "sg:province":"VA",
    "sg:tags":[
        "car",
        "dealer"
    ],
    "wof:name":"Town & Country Auto",
    "wof:placetype":"venue"
},
  "geometry": {"coordinates":[-77.638666,38.813067],"type":"Point"}
}