{
  "type": "Feature",
  "properties": {
    "addr:full":"2119 Ivy Rd Charlottesville VA 22903",
    "addr:housenumber":"2119",
    "addr:postcode":"22903",
    "addr:street":"Ivy Rd",
    "iso:country":"US",
    "sg:address":"2119 Ivy Rd",
    "sg:city":"Charlottesville",
    "sg:classifiers":[
        {
            "category":"Restaurant",
            "type":"Food & Drink"
        }
    ],
    "sg:phone":"+1 434 979 9292",
    "sg:postcode":"22903",
    "sg:province":"VA",
    "sg:tags":[
        "eating",
        "chinese"
    ],
    "wof:name":"Dragon Lady Restaurant",
    "wof:placetype":"venue"
},
  "geometry": {"coordinates":[-78.512199,38.0429],"type":"Point"}
}