{
  "type": "Feature",
  "properties": {
    "addr:full":"5573 E Virginia Beach Blvd Norfolk VA 23502",
    "addr:housenumber":"5573",
    "addr:postcode":"23502",
    "addr:street":"E Virginia Beach Blvd",
    "iso:country":"US",
    "sg:address":"5573 E Virginia Beach Blvd",
    "sg:city":"Norfolk",
    "sg:classifiers":[
        {
            "category":"Autos & Motor Vehicles",
            "subcategory":"Automobile Sales",
            "type":"Retail Goods"
        }
    ],
    "sg:phone":"+1 757 461 7575",
    "sg:postcode":"23502",
    "sg:province":"VA",
    "sg:tags":[
        "car",
        "dealer"
    ],
    "wof:name":"Uptown Auto Sales Inc",
    "wof:placetype":"venue"
},
  "geometry": {"coordinates":[-76.214794,36.85586],"type":"Point"}
}