{
  "type": "Feature",
  "properties": {
    "addr:full":"353 Maple Ave E Vienna VA 22180",
    "addr:housenumber":"353",
    "addr:postcode":"22180",
    "addr:street":"Maple Ave E",
    "iso:country":"US",
    "sg:address":"353 Maple Ave E",
    "sg:city":"Vienna",
    "sg:classifiers":[
        {
            "category":"Banks & Credit Unions",
            "subcategory":"Bank",
            "type":"Services"
        }
    ],
    "sg:phone":"+1 703 319 2641",
    "sg:postcode":"22180",
    "sg:province":"VA",
    "sg:website":"http://www.pnc.com",
    "wof:name":"PNC",
    "wof:placetype":"venue"
},
  "geometry": {"coordinates":[-77.25976900000001,38.905896],"type":"Point"}
}