{
  "type": "Feature",
  "properties": {
    "iso:country":"US",
    "sg:address":"2485 Rivermont Ave",
    "sg:city":"Lynchburg",
    "sg:classifiers":[
        {
            "category":"Government",
            "subcategory":"Post Office",
            "type":"Public Place"
        }
    ],
    "sg:phone":"+1 434 528 8966",
    "sg:postcode":"24503",
    "sg:province":"VA",
    "wof:name":"US Post Office",
    "wof:placetype":"venue"
},
  "geometry": {"coordinates":[-79.16995199999999,37.434923],"type":"Point"}
}