{
  "type": "Feature",
  "properties": {
    "addr:full":"3526 Goodview Ct Fairfax VA 22031",
    "addr:housenumber":"3526",
    "addr:postcode":"22031",
    "addr:street":"Goodview Ct",
    "iso:country":"US",
    "sg:address":"3526 Goodview Ct",
    "sg:city":"Fairfax",
    "sg:classifiers":[
        {
            "category":"Professional",
            "subcategory":"Management & Consulting",
            "type":"Services"
        }
    ],
    "sg:phone":"+1 703 608 2263",
    "sg:postcode":"22031",
    "sg:province":"VA",
    "wof:name":"Schachinger Group The",
    "wof:placetype":"venue"
},
  "geometry": {"coordinates":[-77.250362,38.850749],"type":"Point"}
}