{
  "type": "Feature",
  "properties": {
    "addr:full":"110 82nd St Virginia Beach VA 23451",
    "addr:housenumber":"110",
    "addr:postcode":"23451",
    "addr:street":"82Nd St",
    "iso:country":"US",
    "sg:address":"110 82nd St",
    "sg:city":"Virginia Beach",
    "sg:classifiers":[
        {
            "category":"Manufacturing",
            "subcategory":"Glass & Minerals",
            "type":"Manufacturing & Wholesale Goods"
        }
    ],
    "sg:phone":"+1 757 417 8181",
    "sg:postcode":"23451",
    "sg:province":"VA",
    "sg:tags":[
        "repair",
        "product",
        "mfg"
    ],
    "wof:name":"A Ray Gregory",
    "wof:placetype":"venue"
},
  "geometry": {"coordinates":[-75.99304100000001,36.906927],"type":"Point"}
}