{
  "type": "Feature",
  "properties": {
    "addr:full":"1100 Coolbrook Rd Bedford VA 24523",
    "addr:housenumber":"1100",
    "addr:postcode":"24523",
    "addr:street":"Coolbrook Rd",
    "iso:country":"US",
    "sg:address":"1100 Coolbrook Rd",
    "sg:city":"Bedford",
    "sg:classifiers":[
        {
            "category":"Building & Trades",
            "subcategory":"Construction",
            "type":"Services"
        }
    ],
    "sg:phone":"+1 540 586 6612",
    "sg:postcode":"24523",
    "sg:province":"VA",
    "sg:tags":[
        "contractor"
    ],
    "wof:name":"Puckett Joey Allen Masonry",
    "wof:placetype":"venue"
},
  "geometry": {"coordinates":[-79.542795,37.326474],"type":"Point"}
}