{
  "type": "Feature",
  "properties": {
    "addr:full":"699 State Rte 699 Leesburg VA 20175",
    "addr:housenumber":"699",
    "addr:postcode":"20175",
    "addr:street":"State Rte 699",
    "iso:country":"US",
    "sg:address":"699 State Rte 699",
    "sg:city":"Leesburg",
    "sg:classifiers":[
        {
            "category":"Recreation",
            "type":"Entertainment"
        }
    ],
    "sg:phone":"+1 703 777 3835",
    "sg:postcode":"20175",
    "sg:province":"VA",
    "sg:tags":[
        "fairground"
    ],
    "wof:name":"Loudoun 4H Fairgrounds",
    "wof:placetype":"venue"
},
  "geometry": {"coordinates":[-77.58377900000001,39.108475],"type":"Point"}
}