{
  "type": "Feature",
  "properties": {
    "addr:full":"2407 Kensington Ave Richmond VA 23220",
    "addr:housenumber":"2407",
    "addr:postcode":"23220",
    "addr:street":"Kensington Ave",
    "iso:country":"US",
    "sg:address":"2407 Kensington Ave",
    "sg:city":"Richmond",
    "sg:classifiers":[
        {
            "category":"Building & Trades",
            "subcategory":"Landscaping Services",
            "type":"Services"
        }
    ],
    "sg:phone":"+1 804 355 3352",
    "sg:postcode":"23220",
    "sg:province":"VA",
    "sg:tags":[
        "tree",
        "stump",
        "grinding",
        "removal"
    ],
    "wof:name":"Affordable Tree Removal",
    "wof:placetype":"venue"
},
  "geometry": {"coordinates":[-77.467855,37.556447],"type":"Point"}
}