{
  "type": "Feature",
  "properties": {
    "addr:full":"7040 Hull Street Rd Richmond VA 23224",
    "addr:housenumber":"7040",
    "addr:postcode":"23224",
    "addr:street":"Hull Street Rd",
    "iso:country":"US",
    "sg:address":"7040 Hull Street Rd",
    "sg:city":"Richmond",
    "sg:classifiers":[
        {
            "category":"Food & Beverages",
            "subcategory":"Groceries & Convenience Stores",
            "type":"Retail Goods"
        }
    ],
    "sg:phone":"+1 804 276 8921",
    "sg:postcode":"23224",
    "sg:province":"VA",
    "wof:name":"7-Eleven",
    "wof:placetype":"venue"
},
  "geometry": {"coordinates":[-77.522431,37.474949],"type":"Point"}
}