{
  "type": "Feature",
  "properties": {
    "iso:country":"US",
    "sg:address":"12144 Morgansburg Rd",
    "sg:city":"Bealeton",
    "sg:classifiers":[
        {
            "category":"Organizations",
            "subcategory":"Non-profit Organization",
            "type":"Services"
        }
    ],
    "sg:phone":"+1 540 439 4396",
    "sg:postcode":"22712",
    "sg:province":"VA",
    "wof:name":"Stronghold Ministries",
    "wof:placetype":"venue"
},
  "geometry": {"coordinates":[-77.749876,38.534718],"type":"Point"}
}