{
  "type": "Feature",
  "properties": {
    "addr:full":"2842 Annandale Rd Falls Church VA 22042",
    "addr:housenumber":"2842",
    "addr:postcode":"22042",
    "addr:street":"Annandale Rd",
    "iso:country":"US",
    "sg:address":"2842 Annandale Rd",
    "sg:city":"Falls Church",
    "sg:classifiers":[
        {
            "category":"Airline",
            "type":"Transportation"
        }
    ],
    "sg:phone":"+1 703 538 3868",
    "sg:postcode":"22042",
    "sg:province":"VA",
    "sg:tags":[
        "courier",
        "air"
    ],
    "wof:name":"Saudi Arabian Embassy",
    "wof:placetype":"venue"
},
  "geometry": {"coordinates":[-77.174528,38.874985],"type":"Point"}
}