{
  "type": "Feature",
  "properties": {
    "addr:full":"42990 Elk Pl Chantilly VA 20152",
    "addr:housenumber":"42990",
    "addr:postcode":"20152",
    "addr:street":"Elk Pl",
    "iso:country":"US",
    "sg:address":"42990 Elk Pl",
    "sg:city":"Chantilly",
    "sg:classifiers":[
        {
            "category":"Building & Trades",
            "subcategory":"Plumbing",
            "type":"Services"
        }
    ],
    "sg:phone":"+1 703 327 1895",
    "sg:postcode":"20152",
    "sg:province":"VA",
    "sg:tags":[
        "contractor"
    ],
    "wof:name":"A&T Heating & Air Conditioning",
    "wof:placetype":"venue"
},
  "geometry": {"coordinates":[-77.515624,38.92226],"type":"Point"}
}