{
  "type": "Feature",
  "properties": {
    "iso:country":"US",
    "sg:address":"8000 Jefferson Davis Hwy",
    "sg:city":"Richmond",
    "sg:classifiers":[
        {
            "category":"Farming",
            "subcategory":"Farm",
            "type":"Manufacturing & Wholesale Goods"
        }
    ],
    "sg:phone":"+1 804 279 3049",
    "sg:postcode":"23237",
    "sg:province":"VA",
    "sg:tags":[
        "crop",
        "general"
    ],
    "wof:name":"McCormick Farms LP",
    "wof:placetype":"venue"
},
  "geometry": {"coordinates":[-77.436345,37.416357],"type":"Point"}
}