{
  "type": "Feature",
  "properties": {
    "addr:full":"10113 Falconbridge Dr Richmond VA 23238",
    "addr:housenumber":"10113",
    "addr:postcode":"23238",
    "addr:street":"Falconbridge Dr",
    "iso:country":"US",
    "sg:address":"10113 Falconbridge Dr",
    "sg:city":"Richmond",
    "sg:classifiers":[
        {
            "category":"Building & Trades",
            "subcategory":"Construction",
            "type":"Services"
        }
    ],
    "sg:phone":"+1 804 740 1784",
    "sg:postcode":"23238",
    "sg:province":"VA",
    "sg:tags":[
        "hanging",
        "contractor"
    ],
    "wof:name":"All About Painting",
    "wof:placetype":"venue"
},
  "geometry": {"coordinates":[-77.59008,37.619662],"type":"Point"}
}