{
  "type": "Feature",
  "properties": {
    "iso:country":"US",
    "sg:address":"117 Old Aberdeen Rd",
    "sg:city":"Hampton",
    "sg:classifiers":[
        {
            "category":"Building & Trades",
            "subcategory":"Plumbing",
            "type":"Services"
        }
    ],
    "sg:phone":"+1 757 244 4100",
    "sg:postcode":"23661",
    "sg:province":"VA",
    "sg:tags":[
        "heating",
        "contractor"
    ],
    "wof:name":"Indoor Air Systems Inc",
    "wof:placetype":"venue"
},
  "geometry": {"coordinates":[-76.40155,37.003465],"type":"Point"}
}