{
  "type": "Feature",
  "properties": {
    "addr:full":"5922 Cascade Dr Fredericksburg VA 22407",
    "addr:housenumber":"5922",
    "addr:postcode":"22407",
    "addr:street":"Cascade Dr",
    "iso:country":"US",
    "sg:address":"5922 Cascade Dr",
    "sg:city":"Fredericksburg",
    "sg:classifiers":[
        {
            "category":"Professional",
            "subcategory":"Management & Consulting",
            "type":"Services"
        }
    ],
    "sg:phone":"+1 540 710 1216",
    "sg:postcode":"22407",
    "sg:province":"VA",
    "sg:tags":[
        "business"
    ],
    "wof:name":"Cnr Consulting Services Inc",
    "wof:placetype":"venue"
},
  "geometry": {"coordinates":[-77.537814,38.23224],"type":"Point"}
}