{
  "type": "Feature",
  "properties": {
    "iso:country":"US",
    "sg:address":"4343 Ridgewood Center Dr",
    "sg:city":"Woodbridge",
    "sg:classifiers":[
        {
            "category":"Wholesale",
            "subcategory":"Electrical",
            "type":"Manufacturing & Wholesale Goods"
        }
    ],
    "sg:phone":"+1 703 897 1655",
    "sg:postcode":"22192",
    "sg:province":"VA",
    "sg:tags":[
        "control"
    ],
    "sg:website":"www.magyarandassociates.com",
    "wof:name":"Magyar & Assoc",
    "wof:placetype":"venue"
},
  "geometry": {"coordinates":[-77.341008,38.674662],"type":"Point"}
}