{
  "type": "Feature",
  "properties": {
    "addr:full":"1300 Warrington Pl Alexandria VA 22307",
    "addr:housenumber":"1300",
    "addr:postcode":"22307",
    "addr:street":"Warrington Pl",
    "iso:country":"US",
    "sg:address":"1300 Warrington Pl",
    "sg:city":"Alexandria",
    "sg:classifiers":[
        {
            "category":"Manufacturing",
            "subcategory":"Tools & Machinery",
            "type":"Manufacturing & Wholesale Goods"
        }
    ],
    "sg:phone":"+1 703 768 0144",
    "sg:postcode":"22307",
    "sg:province":"VA",
    "sg:tags":[
        "distributor",
        "fixture",
        "commercial",
        "lighting"
    ],
    "wof:name":"Lighting Resources",
    "wof:placetype":"venue"
},
  "geometry": {"coordinates":[-77.057343,38.762868],"type":"Point"}
}