{
  "type": "Feature",
  "properties": {
    "iso:country":"US",
    "sg:address":"7942 Cluny Ct",
    "sg:city":"Springfield",
    "sg:classifiers":[
        {
            "category":"Building & Trades",
            "subcategory":"Construction",
            "type":"Services"
        }
    ],
    "sg:phone":"+1 703 644 3000",
    "sg:postcode":"22153",
    "sg:province":"VA",
    "sg:tags":[
        "roofing",
        "contractor"
    ],
    "wof:name":"Commonwealth Aluminum Supply",
    "wof:placetype":"venue"
},
  "geometry": {"coordinates":[-77.208287,38.742977],"type":"Point"}
}