{
  "type": "Feature",
  "properties": {
    "addr:full":"3009 North Ct Williamsburg VA 23185",
    "addr:housenumber":"3009",
    "addr:postcode":"23185",
    "addr:street":"North Ct",
    "iso:country":"US",
    "sg:address":"3009 North Ct",
    "sg:city":"Williamsburg",
    "sg:classifiers":[
        {
            "category":"Building & Trades",
            "subcategory":"Construction",
            "type":"Services"
        }
    ],
    "sg:phone":"+1 757 259 0490",
    "sg:postcode":"23185",
    "sg:province":"VA",
    "sg:tags":[
        "hanging",
        "contractor"
    ],
    "wof:name":"Four Seasons Custom Painting",
    "wof:placetype":"venue"
},
  "geometry": {"coordinates":[-76.735338,37.247602],"type":"Point"}
}