{
  "type": "Feature",
  "properties": {
    "addr:full":"121 Lilburne Way Yorktown VA 23693",
    "addr:housenumber":"121",
    "addr:postcode":"23693",
    "addr:street":"Lilburne Way",
    "iso:country":"US",
    "sg:address":"121 Lilburne Way",
    "sg:city":"Yorktown",
    "sg:classifiers":[
        {
            "category":"Manufacturing",
            "subcategory":"Buildings",
            "type":"Manufacturing & Wholesale Goods"
        },
        {
            "category":"Building & Trades",
            "subcategory":"Construction",
            "type":"Services"
        }
    ],
    "sg:phone":"+1 757 715 0758",
    "sg:postcode":"23693",
    "sg:province":"VA",
    "sg:tags":[
        "home",
        "consultant",
        "builder",
        "contractor"
    ],
    "wof:name":"New Life Painting & Repairs",
    "wof:placetype":"venue"
},
  "geometry": {"coordinates":[-76.446737,37.101978],"type":"Point"}
}