{
  "type": "Feature",
  "properties": {
    "iso:country":"US",
    "sg:address":"1219 Memorial Blvd S",
    "sg:city":"Martinsville",
    "sg:classifiers":[
        {
            "category":"Professional",
            "subcategory":"Accounting & Tax Preparation",
            "type":"Services"
        }
    ],
    "sg:phone":"+1 276 666 7900",
    "sg:postcode":"24112",
    "sg:province":"VA",
    "wof:name":"Akers Bookkeeping & Tax Svc",
    "wof:placetype":"venue"
},
  "geometry": {"coordinates":[-79.87808,36.673705],"type":"Point"}
}