{
  "type": "Feature",
  "properties": {
    "iso:country":"US",
    "sg:address":"7000 Aronow Dr",
    "sg:city":"Falls Church",
    "sg:phone":"+1 703 532 8768",
    "sg:postcode":"22042",
    "sg:province":"VA",
    "sg:tags":[
        "vending"
    ],
    "wof:name":"Women On The Vend Inc",
    "wof:placetype":"venue"
},
  "geometry": {"coordinates":[-77.186566,38.869166],"type":"Point"}
}