{
  "type": "Feature",
  "properties": {
    "iso:country":"US",
    "sg:address":"1600 Duke St",
    "sg:city":"Alexandria",
    "sg:classifiers":[
        {
            "category":"Professional",
            "subcategory":"Business Services",
            "type":"Services"
        }
    ],
    "sg:phone":"+1 703 647 6880",
    "sg:postcode":"22314",
    "sg:province":"VA",
    "sg:tags":[
        "convention",
        "meeting",
        "facility"
    ],
    "wof:name":"San Diego Convention",
    "wof:placetype":"venue"
},
  "geometry": {"coordinates":[-77.05951,38.80432],"type":"Point"}
}