{
  "type": "Feature",
  "properties": {
    "addr:full":"2108 W Laburnum Ave # 300 Richmond VA 23227",
    "addr:housenumber":"2108;300",
    "addr:postcode":"23227",
    "addr:street":"W Laburnum Ave #",
    "iso:country":"US",
    "sg:address":"2108 W Laburnum Ave # 300",
    "sg:city":"Richmond",
    "sg:classifiers":[
        {
            "category":"Organizations",
            "subcategory":"Community Association",
            "type":"Services"
        }
    ],
    "sg:phone":"+1 804 249 2500",
    "sg:postcode":"23227",
    "sg:province":"VA",
    "wof:name":"Construction Financial Management Association Of Central Virginia",
    "wof:placetype":"venue"
},
  "geometry": {"coordinates":[-77.472672,37.583921],"type":"Point"}
}