{
  "type": "Feature",
  "properties": {
    "addr:full":"8294 Liberia Ave Manassas VA 20110",
    "addr:postcode":"8294;20110",
    "addr:street":"Liberia Ave",
    "iso:country":"US",
    "sg:address":"8294 Liberia Ave",
    "sg:city":"Manassas",
    "sg:classifiers":[
        {
            "category":"Building & Trades",
            "subcategory":"Plumbing",
            "type":"Services"
        }
    ],
    "sg:phone":"+1 703 690 0710",
    "sg:postcode":"20110",
    "sg:province":"VA",
    "sg:tags":[
        "plumbing",
        "contractor"
    ],
    "wof:name":"Todd's Plumbing Svc",
    "wof:placetype":"venue"
},
  "geometry": {"coordinates":[-77.47593999999999,38.776223],"type":"Point"}
}