{
  "type": "Feature",
  "properties": {
    "addr:full":"1025 W Glebe Rd Alexandria VA 22305",
    "addr:housenumber":"1025",
    "addr:postcode":"22305",
    "addr:street":"W Glebe Rd",
    "iso:country":"US",
    "sg:address":"1025 W Glebe Rd",
    "sg:city":"Alexandria",
    "sg:classifiers":[
        {
            "category":"Food & Beverages",
            "subcategory":"Groceries & Convenience Stores",
            "type":"Retail Goods"
        }
    ],
    "sg:phone":"+1 703 519 7168",
    "sg:postcode":"22305",
    "sg:province":"VA",
    "sg:website":"www.7-eleven.com",
    "wof:name":"7-Eleven",
    "wof:placetype":"venue"
},
  "geometry": {"coordinates":[-77.075298,38.842766],"type":"Point"}
}