{
  "type": "Feature",
  "properties": {
    "iso:country":"US",
    "sg:address":"3401 Four Year Trl",
    "sg:city":"Dumfries",
    "sg:classifiers":[
        {
            "category":"Education",
            "subcategory":"School",
            "type":"Public Place"
        }
    ],
    "sg:phone":"+1 703 441 4200",
    "sg:postcode":"22026",
    "sg:province":"VA",
    "sg:tags":[
        "consulting",
        "business"
    ],
    "wof:name":"Potomac High School",
    "wof:placetype":"venue"
},
  "geometry": {"coordinates":[-77.306866,38.591599],"type":"Point"}
}