{
  "type": "Feature",
  "properties": {
    "iso:country":"US",
    "sg:address":"850 Church St",
    "sg:city":"Norfolk",
    "sg:classifiers":[
        {
            "category":"Personal",
            "subcategory":"Beauty Salon",
            "type":"Services"
        }
    ],
    "sg:phone":"+1 757 625 4247",
    "sg:postcode":"23510",
    "sg:province":"VA",
    "wof:name":"Xtreme Salon",
    "wof:placetype":"venue"
},
  "geometry": {"coordinates":[-76.27978899999999,36.854881],"type":"Point"}
}