{
  "type": "Feature",
  "properties": {
    "addr:full":"2008 Libbie Ave Richmond VA 23226",
    "addr:housenumber":"2008",
    "addr:postcode":"23226",
    "addr:street":"Libbie Ave",
    "iso:country":"US",
    "sg:address":"2008 Libbie Ave",
    "sg:city":"Richmond",
    "sg:classifiers":[
        {
            "category":"Insurance",
            "subcategory":"Life Insurance",
            "type":"Services"
        }
    ],
    "sg:phone":"+1 804 288 4151",
    "sg:postcode":"23226",
    "sg:province":"VA",
    "sg:tags":[
        "security",
        "carrier"
    ],
    "wof:name":"Nationwide",
    "wof:placetype":"venue"
},
  "geometry": {"coordinates":[-77.503975,37.590097],"type":"Point"}
}