{
  "type": "Feature",
  "properties": {
    "addr:full":"15403 Merry Cat Ln Belle Haven VA 23306",
    "addr:housenumber":"15403",
    "addr:postcode":"23306",
    "addr:street":"Merry Cat Ln",
    "iso:country":"US",
    "sg:address":"15403 Merry Cat Ln",
    "sg:city":"Belle Haven",
    "sg:classifiers":[
        {
            "category":"Government",
            "subcategory":"Office",
            "type":"Public Place"
        }
    ],
    "sg:phone":"+1 757 787 5992",
    "sg:postcode":"23306",
    "sg:province":"VA",
    "sg:tags":[
        "state",
        "program"
    ],
    "wof:name":"Rehabilitative Services Dept",
    "wof:placetype":"venue"
},
  "geometry": {"coordinates":[-75.815586,37.545727],"type":"Point"}
}