{
  "type": "Feature",
  "properties": {
    "addr:full":"7508 Diplomat Dr Manassas VA 20109",
    "addr:housenumber":"7508",
    "addr:postcode":"20109",
    "addr:street":"Diplomat Dr",
    "iso:country":"US",
    "sg:address":"7508 Diplomat Dr",
    "sg:city":"Manassas",
    "sg:classifiers":[
        {
            "category":"Real Estate",
            "subcategory":"Real Estate Agent",
            "type":"Services"
        }
    ],
    "sg:phone":"+1 703 335 8000",
    "sg:postcode":"20109",
    "sg:province":"VA",
    "wof:name":"Keller Williams Virginia",
    "wof:placetype":"venue"
},
  "geometry": {"coordinates":[-77.518085,38.794026],"type":"Point"}
}