{
  "type": "Feature",
  "properties": {
    "iso:country":"US",
    "sg:address":"557 Richmond Ave",
    "sg:city":"Staunton",
    "sg:classifiers":[
        {
            "category":"Retail",
            "subcategory":"Car Wash",
            "type":"Services"
        }
    ],
    "sg:phone":"+1 540 886 9550",
    "sg:postcode":"24401",
    "sg:province":"VA",
    "sg:tags":[
        "polishing",
        "washing"
    ],
    "wof:name":"Auto Washland",
    "wof:placetype":"venue"
},
  "geometry": {"coordinates":[-79.064458,38.145961],"type":"Point"}
}