{
  "type": "Feature",
  "properties": {
    "addr:full":"107 S Bridge St Bedford VA 24523",
    "addr:housenumber":"107",
    "addr:postcode":"24523",
    "addr:street":"S Bridge St",
    "iso:country":"US",
    "sg:address":"107 S Bridge St",
    "sg:city":"Bedford",
    "sg:classifiers":[
        {
            "category":"Insurance",
            "subcategory":"Insurance Agent",
            "type":"Services"
        }
    ],
    "sg:phone":"+1 540 586 3025",
    "sg:postcode":"24523",
    "sg:province":"VA",
    "wof:name":"Nationwide Insurance",
    "wof:placetype":"venue"
},
  "geometry": {"coordinates":[-79.523478,37.334373],"type":"Point"}
}