{
  "type": "Feature",
  "properties": {
    "addr:full":"4244 Marlin Ave Suffolk VA 23435",
    "addr:housenumber":"4244",
    "addr:postcode":"23435",
    "addr:street":"Marlin Ave",
    "iso:country":"US",
    "sg:address":"4244 Marlin Ave",
    "sg:city":"Suffolk",
    "sg:classifiers":[
        {
            "category":"Organizations",
            "subcategory":"Religious Organization",
            "type":"Services"
        }
    ],
    "sg:phone":"+1 757 484 6661",
    "sg:postcode":"23435",
    "sg:province":"VA",
    "wof:name":"Otto Williams Pastor",
    "wof:placetype":"venue"
},
  "geometry": {"coordinates":[-76.445367,36.850798],"type":"Point"}
}