{
  "type": "Feature",
  "properties": {
    "addr:full":"1213 Mall Dr Richmond VA 23235",
    "addr:housenumber":"1213",
    "addr:postcode":"23235",
    "addr:street":"Mall Dr",
    "iso:country":"US",
    "sg:address":"1213 Mall Dr",
    "sg:city":"Richmond",
    "sg:classifiers":[
        {
            "category":"Building & Trades",
            "subcategory":"Construction",
            "type":"Services"
        }
    ],
    "sg:phone":"+1 804 423 5841",
    "sg:postcode":"23235",
    "sg:province":"VA",
    "sg:tags":[
        "residential"
    ],
    "wof:name":"Enterprise Bldrs & Developers",
    "wof:placetype":"venue"
},
  "geometry": {"coordinates":[-77.606539,37.507998],"type":"Point"}
}