{
  "type": "Feature",
  "properties": {
    "iso:country":"US",
    "sg:address":"192 Beech Ave",
    "sg:city":"Danville",
    "sg:classifiers":[
        {
            "category":"Building & Trades",
            "subcategory":"Plumbing",
            "type":"Services"
        }
    ],
    "sg:phone":"+1 434 822 2251",
    "sg:postcode":"24541",
    "sg:province":"VA",
    "sg:tags":[
        "heating",
        "contractor"
    ],
    "wof:name":"Shumate's Service",
    "wof:placetype":"venue"
},
  "geometry": {"coordinates":[-79.47555699999999,36.603246],"type":"Point"}
}