{
  "type": "Feature",
  "properties": {
    "addr:full":"570 N High St Christiansburg VA 24073",
    "addr:housenumber":"570",
    "addr:postcode":"24073",
    "addr:street":"N High St",
    "iso:country":"US",
    "sg:address":"570 N High St",
    "sg:city":"Christiansburg",
    "sg:classifiers":[
        {
            "category":"Organizations",
            "subcategory":"Professional Association",
            "type":"Services"
        }
    ],
    "sg:phone":"+1 540 382 6751",
    "sg:postcode":"24073",
    "sg:province":"VA",
    "sg:tags":[
        "business"
    ],
    "wof:name":"N A A C P-Mntgomery-Radford BR",
    "wof:placetype":"venue"
},
  "geometry": {"coordinates":[-80.40647300000001,37.139184],"type":"Point"}
}