{
  "type": "Feature",
  "properties": {
    "addr:full":"4600 John Marr Dr Annandale VA 22003",
    "addr:housenumber":"4600",
    "addr:postcode":"22003",
    "addr:street":"John Marr Dr",
    "iso:country":"US",
    "sg:address":"4600 John Marr Dr",
    "sg:city":"Annandale",
    "sg:classifiers":[
        {
            "category":"Health Services",
            "subcategory":"Doctor",
            "type":"Services"
        }
    ],
    "sg:phone":"+1 703 916 0005",
    "sg:postcode":"22003",
    "sg:province":"VA",
    "sg:tags":[
        "physician",
        "surgeon"
    ],
    "wof:name":"Internal Medicine Ctr Of Va",
    "wof:placetype":"venue"
},
  "geometry": {"coordinates":[-77.196344,38.828559],"type":"Point"}
}