{
  "type": "Feature",
  "properties": {
    "iso:country":"US",
    "sg:address":"4074 Pearman Rd",
    "sg:city":"Blacksburg",
    "sg:classifiers":[
        {
            "category":"Professional",
            "type":"Services"
        }
    ],
    "sg:phone":"+1 540 552 6552",
    "sg:postcode":"24060",
    "sg:province":"VA",
    "wof:name":"Architectural Structures Ltd",
    "wof:placetype":"venue"
},
  "geometry": {"coordinates":[-80.414159,37.277911],"type":"Point"}
}