{
  "type": "Feature",
  "properties": {
    "addr:full":"521 Maple Ave W Vienna VA 22180",
    "addr:housenumber":"521",
    "addr:postcode":"22180",
    "addr:street":"Maple Ave W",
    "iso:country":"US",
    "sg:address":"521 Maple Ave W",
    "sg:city":"Vienna",
    "sg:classifiers":[
        {
            "category":"Health Services",
            "subcategory":"Health Practitioner",
            "type":"Services"
        }
    ],
    "sg:phone":"+1 703 319 3200",
    "sg:postcode":"22180",
    "sg:province":"VA",
    "wof:name":"N P Acupuncture",
    "wof:placetype":"venue"
},
  "geometry": {"coordinates":[-77.27465599999999,38.894217],"type":"Point"}
}