{
  "type": "Feature",
  "properties": {
    "addr:full":"4751 N Lee Hwy Arlington VA 22207",
    "addr:housenumber":"4751",
    "addr:postcode":"22207",
    "addr:street":"N Lee Hwy",
    "iso:country":"US",
    "sg:address":"4751 N Lee Hwy",
    "sg:city":"Arlington",
    "sg:classifiers":[
        {
            "category":"Personal",
            "subcategory":"Beauty Salon",
            "type":"Services"
        }
    ],
    "sg:phone":"+1 703 294 4959",
    "sg:postcode":"22207",
    "sg:province":"VA",
    "sg:tags":[
        "shop"
    ],
    "wof:name":"Copacabana Hair Salon",
    "wof:placetype":"venue"
},
  "geometry": {"coordinates":[-77.124438,38.897364],"type":"Point"}
}