{
  "type": "Feature",
  "properties": {
    "iso:country":"US",
    "sg:address":"257 Tyson Dr",
    "sg:city":"Winchester",
    "sg:classifiers":[
        {
            "category":"Freight",
            "type":"Transportation"
        }
    ],
    "sg:phone":"+1 540 662 8140",
    "sg:postcode":"22603",
    "sg:province":"VA",
    "sg:tags":[
        "broker",
        "trucking"
    ],
    "wof:name":"Trans-Marketing Resources Inc",
    "wof:placetype":"venue"
},
  "geometry": {"coordinates":[-78.150121,39.22254],"type":"Point"}
}