{
  "type": "Feature",
  "properties": {
    "addr:full":"21730 Towncenter Plz Sterling VA 20164",
    "addr:housenumber":"21730",
    "addr:postcode":"20164",
    "addr:street":"Towncenter Plz",
    "iso:country":"US",
    "sg:address":"21730 Towncenter Plz",
    "sg:city":"Sterling",
    "sg:classifiers":[
        {
            "category":"Restaurant",
            "type":"Food & Drink"
        }
    ],
    "sg:menulink":"http://www.allmenus.com/va/sterling/187988-mcdonalds/menu/",
    "sg:postcode":"20164",
    "sg:province":"VA",
    "sg:tags":[
        "burger",
        "american"
    ],
    "wof:name":"McDonald's",
    "wof:placetype":"venue"
},
  "geometry": {"coordinates":[-77.372709,39.013664],"type":"Point"}
}