{
  "type": "Feature",
  "properties": {
    "iso:country":"US",
    "sg:address":"7209 Madison Ave",
    "sg:city":"Newport News",
    "sg:classifiers":[
        {
            "category":"Travel",
            "subcategory":"Travel Agent",
            "type":"Entertainment"
        }
    ],
    "sg:phone":"+1 757 313 0879",
    "sg:postcode":"23605",
    "sg:province":"VA",
    "sg:tags":[
        "agency"
    ],
    "wof:name":"Caribbean Queen Tours",
    "wof:placetype":"venue"
},
  "geometry": {"coordinates":[-76.43884300000001,37.012839],"type":"Point"}
}