{
  "type": "Feature",
  "properties": {
    "addr:full":"320 Masters Dr Cross Junction VA 22625",
    "addr:housenumber":"320",
    "addr:postcode":"22625",
    "addr:street":"Masters Dr",
    "iso:country":"US",
    "sg:address":"320 Masters Dr",
    "sg:city":"Cross Junction",
    "sg:classifiers":[
        {
            "category":"Wholesale",
            "subcategory":"Groceries",
            "type":"Manufacturing & Wholesale Goods"
        }
    ],
    "sg:phone":"+1 540 888 4018",
    "sg:postcode":"22625",
    "sg:province":"VA",
    "wof:name":"Ideal Co",
    "wof:placetype":"venue"
},
  "geometry": {"coordinates":[-78.31302599999999,39.31675],"type":"Point"}
}