{
  "type": "Feature",
  "properties": {
    "addr:full":"2040 Wingfield Rd Charlottesville VA 22901",
    "addr:housenumber":"2040",
    "addr:postcode":"22901",
    "addr:street":"Wingfield Rd",
    "iso:country":"US",
    "sg:address":"2040 Wingfield Rd",
    "sg:city":"Charlottesville",
    "sg:classifiers":[
        {
            "category":"Professional",
            "type":"Services"
        }
    ],
    "sg:phone":"+1 434 293 8672",
    "sg:postcode":"22901",
    "sg:province":"VA",
    "wof:name":"Studio Rabun",
    "wof:placetype":"venue"
},
  "geometry": {"coordinates":[-78.513699,38.091596],"type":"Point"}
}