{
  "type": "Feature",
  "properties": {
    "addr:full":"3615 Maryland Ave Richmond VA 23222",
    "addr:housenumber":"3615",
    "addr:postcode":"23222",
    "addr:street":"Maryland Ave",
    "iso:country":"US",
    "sg:address":"3615 Maryland Ave",
    "sg:city":"Richmond",
    "sg:classifiers":[
        {
            "category":"Building & Trades",
            "subcategory":"Plumbing",
            "type":"Services"
        }
    ],
    "sg:phone":"+1 804 321 1884",
    "sg:postcode":"23222",
    "sg:province":"VA",
    "sg:tags":[
        "contractor"
    ],
    "wof:name":"M&J Heating & Air Conditionig",
    "wof:placetype":"venue"
},
  "geometry": {"coordinates":[-77.416082,37.580159],"type":"Point"}
}