{
  "type": "Feature",
  "properties": {
    "addr:full":"1704 Shelby St Bristol VA 37620",
    "addr:housenumber":"1704",
    "addr:postcode":"37620",
    "addr:street":"Shelby St",
    "iso:country":"US",
    "sg:address":"1704 Shelby St",
    "sg:city":"Bristol",
    "sg:classifiers":[
        {
            "category":"Shopping",
            "subcategory":"Hobbies, Toys, & Games",
            "type":"Retail Goods"
        }
    ],
    "sg:phone":"+1 423 764 0438",
    "sg:postcode":"37620",
    "sg:province":"VA",
    "sg:tags":[
        "shop"
    ],
    "wof:name":"All-Pro Sports",
    "wof:placetype":"venue"
},
  "geometry": {"coordinates":[-82.201813,36.594386],"type":"Point"}
}