{
  "type": "Feature",
  "properties": {
    "addr:full":"8629 Mathis Ave Manassas VA 20110",
    "addr:housenumber":"8629",
    "addr:postcode":"20110",
    "addr:street":"Mathis Ave",
    "iso:country":"US",
    "sg:address":"8629 Mathis Ave",
    "sg:city":"Manassas",
    "sg:classifiers":[
        {
            "category":"Building & Trades",
            "subcategory":"Construction",
            "type":"Services"
        }
    ],
    "sg:phone":"+1 703 368 1010",
    "sg:postcode":"20110",
    "sg:province":"VA",
    "sg:tags":[
        "house"
    ],
    "wof:name":"Hadden Group of Virginia Inc",
    "wof:placetype":"venue"
},
  "geometry": {"coordinates":[-77.456248,38.768075],"type":"Point"}
}