{
  "type": "Feature",
  "properties": {
    "addr:full":"117 Roanoke Ave Colonial Heights VA 23834",
    "addr:housenumber":"117",
    "addr:postcode":"23834",
    "addr:street":"Roanoke Ave",
    "iso:country":"US",
    "sg:address":"117 Roanoke Ave",
    "sg:city":"Colonial Heights",
    "sg:classifiers":[
        {
            "category":"Building & Trades",
            "subcategory":"Construction",
            "type":"Services"
        }
    ],
    "sg:phone":"+1 804 526 0012",
    "sg:postcode":"23834",
    "sg:province":"VA",
    "sg:tags":[
        "contractor",
        "general"
    ],
    "wof:name":"Gilbert C Martin Company",
    "wof:placetype":"venue"
},
  "geometry": {"coordinates":[-77.41582,37.248577],"type":"Point"}
}