{
  "type": "Feature",
  "properties": {
    "iso:country":"US",
    "sg:address":"13 Granite Spring Rd",
    "sg:city":"Richmond",
    "sg:classifiers":[
        {
            "category":"Personal",
            "subcategory":"Beauty Salon",
            "type":"Services"
        }
    ],
    "sg:phone":"+1 804 745 7944",
    "sg:postcode":"23225",
    "sg:province":"VA",
    "sg:tags":[
        "shop"
    ],
    "wof:name":"Basher & Sylvia Beauty Salon",
    "wof:placetype":"venue"
},
  "geometry": {"coordinates":[-77.531122,37.496572],"type":"Point"}
}