{
  "type": "Feature",
  "properties": {
    "addr:full":"4627 Kayhoe Rd Glen Allen VA 23060",
    "addr:housenumber":"4627",
    "addr:postcode":"23060",
    "addr:street":"Kayhoe Rd",
    "iso:country":"US",
    "sg:address":"4627 Kayhoe Rd",
    "sg:city":"Glen Allen",
    "sg:classifiers":[
        {
            "category":"Professional",
            "subcategory":"Management & Consulting",
            "type":"Services"
        }
    ],
    "sg:phone":"+1 804 747 6928",
    "sg:postcode":"23060",
    "sg:province":"VA",
    "sg:tags":[
        "organizational",
        "development"
    ],
    "wof:name":"O E Solutions",
    "wof:placetype":"venue"
},
  "geometry": {"coordinates":[-77.549305,37.651706],"type":"Point"}
}