{
  "type": "Feature",
  "properties": {
    "iso:country":"US",
    "sg:address":"621 J Clyde Morris Blvd",
    "sg:city":"Newport News",
    "sg:classifiers":[
        {
            "category":"Restaurant",
            "type":"Food & Drink"
        }
    ],
    "sg:menulink":"http://www.allmenus.com/va/newport-news/42367-yukon-steak-co/menu/",
    "sg:phone":"+1 757 643 5846",
    "sg:postcode":"23601",
    "sg:province":"VA",
    "sg:tags":[
        "american"
    ],
    "wof:name":"Yukon Steak Co.",
    "wof:placetype":"venue"
},
  "geometry": {"coordinates":[-76.472195,37.075165],"type":"Point"}
}