{
  "type": "Feature",
  "properties": {
    "iso:country":"US",
    "sg:address":"43330 Junction Plz",
    "sg:city":"Ashburn",
    "sg:classifiers":[
        {
            "category":"Restaurant",
            "type":"Food & Drink"
        }
    ],
    "sg:phone":"+1 703 729 6100",
    "sg:postcode":"20147",
    "sg:province":"VA",
    "wof:name":"Domino's Pizza",
    "wof:placetype":"venue"
},
  "geometry": {"coordinates":[-77.502594,39.036511],"type":"Point"}
}