{
  "type": "Feature",
  "properties": {
    "iso:country":"US",
    "sg:address":"12283 Old Mill Rd",
    "sg:city":"Midland",
    "sg:classifiers":[
        {
            "category":"Building & Trades",
            "subcategory":"Landscaping Services",
            "type":"Services"
        }
    ],
    "sg:phone":"+1 540 788 3632",
    "sg:postcode":"22728",
    "sg:province":"VA",
    "wof:name":"O and W Lawn Care",
    "wof:placetype":"venue"
},
  "geometry": {"coordinates":[-77.686289,38.530894],"type":"Point"}
}