{
  "type": "Feature",
  "properties": {
    "addr:full":"6711 N Lee Hwy Arlington VA 22205",
    "addr:housenumber":"6711",
    "addr:postcode":"22205",
    "addr:street":"N Lee Hwy",
    "iso:country":"US",
    "sg:address":"6711 N Lee Hwy",
    "sg:city":"Arlington",
    "sg:classifiers":[
        {
            "category":"Professional",
            "subcategory":"Art Services",
            "type":"Services"
        }
    ],
    "sg:phone":"+1 703 533 3345",
    "sg:postcode":"22205",
    "sg:province":"VA",
    "sg:tags":[
        "graphic",
        "design"
    ],
    "wof:name":"F & S Graphic Design",
    "wof:placetype":"venue"
},
  "geometry": {"coordinates":[-77.159542,38.889083],"type":"Point"}
}