{
  "type": "Feature",
  "properties": {
    "addr:full":"2045 Wilson Blvd Arlington VA 22201",
    "addr:housenumber":"2045",
    "addr:postcode":"22201",
    "addr:street":"Wilson Blvd",
    "iso:country":"US",
    "sg:address":"2045 Wilson Blvd",
    "sg:city":"Arlington",
    "sg:classifiers":[
        {
            "category":"Restaurant",
            "type":"Food & Drink"
        }
    ],
    "sg:phone":"+1 703 875 0480",
    "sg:postcode":"22201",
    "sg:province":"VA",
    "sg:tags":[
        "italian"
    ],
    "sg:website":"www.courthousebistro.com/caterin...",
    "wof:name":"Court House Bistro",
    "wof:placetype":"venue"
},
  "geometry": {"coordinates":[-77.083918,38.891901],"type":"Point"}
}