{
  "type": "Feature",
  "properties": {
    "iso:country":"US",
    "sg:address":"2224 N Harrison St",
    "sg:city":"Arlington",
    "sg:classifiers":[
        {
            "category":"Professional",
            "type":"Services"
        }
    ],
    "sg:phone":"+1 703 237 2764",
    "sg:postcode":"22205",
    "sg:province":"VA",
    "wof:name":"P & R Decorators",
    "wof:placetype":"venue"
},
  "geometry": {"coordinates":[-77.135991,38.895132],"type":"Point"}
}