{
  "type": "Feature",
  "properties": {
    "iso:country":"US",
    "sg:address":"75 W Ridge Ct",
    "sg:city":"Fredericksburg",
    "sg:classifiers":[
        {
            "category":"Building & Trades",
            "subcategory":"Construction",
            "type":"Services"
        }
    ],
    "sg:phone":"+1 540 361 4596",
    "sg:postcode":"22405",
    "sg:province":"VA",
    "sg:tags":[
        "contractor"
    ],
    "wof:name":"Thomas J Worman Building Inc",
    "wof:placetype":"venue"
},
  "geometry": {"coordinates":[-77.452225,38.345928],"type":"Point"}
}