{
  "type": "Feature",
  "properties": {
    "addr:full":"12512 Crystal Downs Ln Chester VA 23836",
    "addr:housenumber":"12512",
    "addr:postcode":"23836",
    "addr:street":"Crystal Downs Ln",
    "iso:country":"US",
    "sg:address":"12512 Crystal Downs Ln",
    "sg:city":"Chester",
    "sg:classifiers":[
        {
            "category":"Education",
            "subcategory":"Special Training",
            "type":"Public Place"
        },
        {
            "category":"Shopping",
            "subcategory":"Crafts & Fabrics",
            "type":"Retail Goods"
        }
    ],
    "sg:phone":"+1 804 530 0624",
    "sg:postcode":"23836",
    "sg:province":"VA",
    "sg:tags":[
        "school",
        "instruction",
        "art"
    ],
    "wof:name":"Curley, Lorrie A Creative Memories Consultant",
    "wof:placetype":"venue"
},
  "geometry": {"coordinates":[-77.35730100000001,37.359377],"type":"Point"}
}