{
  "type": "Feature",
  "properties": {
    "iso:country":"US",
    "sg:address":"401 Main St",
    "sg:city":"South Boston",
    "sg:classifiers":[
        {
            "category":"Professional",
            "subcategory":"Lawyer & Legal Services",
            "type":"Services"
        }
    ],
    "sg:phone":"+1 434 572 4952",
    "sg:postcode":"24592",
    "sg:province":"NC",
    "sg:tags":[
        "attorney"
    ],
    "wof:name":"Tuck Dillard Nelson & Dillard",
    "wof:placetype":"venue"
},
  "geometry": {"coordinates":[-78.901667,36.698616],"type":"Point"}
}