{
  "type": "Feature",
  "properties": {
    "iso:country":"US",
    "sg:address":"10601 Jennings Ln",
    "sg:city":"Amelia Court House",
    "sg:classifiers":[
        {
            "category":"Building & Trades",
            "subcategory":"Construction",
            "type":"Services"
        }
    ],
    "sg:phone":"+1 804 561 5521",
    "sg:postcode":"23002",
    "sg:province":"VA",
    "sg:tags":[
        "house"
    ],
    "wof:name":"Country Club Homebuilders",
    "wof:placetype":"venue"
},
  "geometry": {"coordinates":[-77.852851,37.242853],"type":"Point"}
}