{
  "type": "Feature",
  "properties": {
    "iso:country":"US",
    "sg:address":"3601 Dam Neck Rd",
    "sg:city":"Virginia Beach",
    "sg:classifiers":[
        {
            "category":"Manufacturing",
            "subcategory":"Glass & Minerals",
            "type":"Manufacturing & Wholesale Goods"
        },
        {
            "category":"Home & Garden",
            "subcategory":"Garden Supply",
            "type":"Retail Goods"
        }
    ],
    "sg:phone":"+1 757 427 6226",
    "sg:postcode":"23453",
    "sg:province":"VA",
    "sg:tags":[
        "concrete",
        "stone",
        "statuary",
        "statue",
        "mfg"
    ],
    "wof:name":"Concrete Creations Inc",
    "wof:placetype":"venue"
},
  "geometry": {"coordinates":[-76.08856,36.776925],"type":"Point"}
}