{
  "type": "Feature",
  "properties": {
    "addr:full":"289 W Main St Abingdon VA 24210",
    "addr:housenumber":"289",
    "addr:postcode":"24210",
    "addr:street":"W Main St",
    "iso:country":"US",
    "sg:address":"289 W Main St",
    "sg:city":"Abingdon",
    "sg:classifiers":[
        {
            "category":"Professional",
            "subcategory":"Accounting & Tax Preparation",
            "type":"Services"
        }
    ],
    "sg:phone":"+1 276 739 0093",
    "sg:postcode":"24210",
    "sg:province":"VA",
    "sg:tags":[
        "return",
        "filing"
    ],
    "wof:name":"Jackson Hewitt Tax Svc",
    "wof:placetype":"venue"
},
  "geometry": {"coordinates":[-81.97971699999999,36.708992],"type":"Point"}
}