{
  "type": "Feature",
  "properties": {
    "addr:full":"4238 Wilson Blvd Ste 3094 Arlington VA 22203",
    "addr:housenumber":"4238",
    "addr:postcode":"22203",
    "addr:street":"Wilson Blvd Ste 3094",
    "iso:country":"US",
    "sg:address":"4238 Wilson Blvd Ste 3094",
    "sg:city":"Arlington",
    "sg:classifiers":[
        {
            "category":"Food & Beverages",
            "subcategory":"Candy",
            "type":"Retail Goods"
        }
    ],
    "sg:phone":"+1 703 525 6867",
    "sg:postcode":"22203",
    "sg:province":"VA",
    "sg:tags":[
        "store"
    ],
    "wof:name":"Tropik Sun Fruit & Nut",
    "wof:placetype":"venue"
},
  "geometry": {"coordinates":[-77.111504,38.880001],"type":"Point"}
}