{
  "type": "Feature",
  "properties": {
    "addr:full":"3535 Ellwood Ave Richmond VA 23221",
    "addr:housenumber":"3535",
    "addr:postcode":"23221",
    "addr:street":"Ellwood Ave",
    "iso:country":"US",
    "sg:address":"3535 Ellwood Ave",
    "sg:city":"Richmond",
    "sg:classifiers":[
        {
            "category":"Retail",
            "subcategory":"Photofinishing",
            "type":"Services"
        }
    ],
    "sg:phone":"+1 804 355 7103",
    "sg:postcode":"23221",
    "sg:province":"VA",
    "sg:tags":[
        "laboratory",
        "finishing",
        "photo"
    ],
    "wof:name":"Action Photo Company",
    "wof:placetype":"venue"
},
  "geometry": {"coordinates":[-77.487573,37.556821],"type":"Point"}
}