{
  "type": "Feature",
  "properties": {
    "addr:full":"7148 Mechanicsville Tpke Mechanicsville VA 23111",
    "addr:housenumber":"7148",
    "addr:postcode":"23111",
    "addr:street":"Mechanicsville Tpke",
    "iso:country":"US",
    "sg:address":"7148 Mechanicsville Tpke",
    "sg:city":"Mechanicsville",
    "sg:classifiers":[
        {
            "category":"Shopping",
            "subcategory":"Computers & Home Electronics",
            "type":"Retail Goods"
        }
    ],
    "sg:phone":"+1 804 730 9697",
    "sg:postcode":"23111",
    "sg:province":"VA",
    "sg:tags":[
        "equipment",
        "dealer"
    ],
    "wof:name":"Sharp's Computer Ctr",
    "wof:placetype":"venue"
},
  "geometry": {"coordinates":[-77.346322,37.611071],"type":"Point"}
}