{
  "type": "Feature",
  "properties": {
    "addr:full":"12104 Waterford Way Pl Richmond VA 23233",
    "addr:housenumber":"12104",
    "addr:postcode":"23233",
    "addr:street":"Waterford Way Pl",
    "iso:country":"US",
    "sg:address":"12104 Waterford Way Pl",
    "sg:city":"Richmond",
    "sg:classifiers":[
        {
            "category":"Professional",
            "type":"Services"
        }
    ],
    "sg:phone":"+1 804 360 4275",
    "sg:postcode":"23233",
    "sg:province":"VA",
    "wof:name":"Vmikedyetscom",
    "wof:placetype":"venue"
},
  "geometry": {"coordinates":[-77.623053,37.638217],"type":"Point"}
}