{
  "type": "Feature",
  "properties": {
    "iso:country":"US",
    "sg:address":"1675 Richmond Rd",
    "sg:city":"Williamsburg",
    "sg:classifiers":[
        {
            "category":"Shopping",
            "subcategory":"Gifts & Souvenirs",
            "type":"Retail Goods"
        }
    ],
    "sg:phone":"+1 757 564 6101",
    "sg:postcode":"23185",
    "sg:province":"VA",
    "wof:name":"Trading Post",
    "wof:placetype":"venue"
},
  "geometry": {"coordinates":[-76.72408900000001,37.292539],"type":"Point"}
}