{
  "type": "Feature",
  "properties": {
    "addr:full":"2053 Memorial Ave SW Roanoke VA 24015",
    "addr:housenumber":"2053",
    "addr:postcode":"24015",
    "addr:street":"Memorial Ave Sw",
    "iso:country":"US",
    "sg:address":"2053 Memorial Ave SW",
    "sg:city":"Roanoke",
    "sg:classifiers":[
        {
            "category":"Building & Trades",
            "subcategory":"Construction",
            "type":"Services"
        }
    ],
    "sg:phone":"+1 540 344 6283",
    "sg:postcode":"24015",
    "sg:province":"VA",
    "sg:tags":[
        "house"
    ],
    "wof:name":"Snowden",
    "wof:placetype":"venue"
},
  "geometry": {"coordinates":[-79.97930700000001,37.266206],"type":"Point"}
}