{
  "type": "Feature",
  "properties": {
    "addr:full":"6324 Old Plank Rd Fredericksburg VA 22407",
    "addr:housenumber":"6324",
    "addr:postcode":"22407",
    "addr:street":"Old Plank Rd",
    "iso:country":"US",
    "sg:address":"6324 Old Plank Rd",
    "sg:city":"Fredericksburg",
    "sg:classifiers":[
        {
            "category":"Wholesale",
            "subcategory":"Auto Parts",
            "type":"Manufacturing & Wholesale Goods"
        }
    ],
    "sg:phone":"+1 540 786 2008",
    "sg:postcode":"22407",
    "sg:province":"VA",
    "wof:name":"Discount Auto Parts Inc",
    "wof:placetype":"venue"
},
  "geometry": {"coordinates":[-77.554166,38.289623],"type":"Point"}
}