{
  "type": "Feature",
  "properties": {
    "addr:full":"16060 Kings Mountain Rd Woodbridge VA 22191",
    "addr:housenumber":"16060",
    "addr:postcode":"22191",
    "addr:street":"Kings Mountain Rd",
    "iso:country":"US",
    "sg:address":"16060 Kings Mountain Rd",
    "sg:city":"Woodbridge",
    "sg:classifiers":[
        {
            "category":"Professional",
            "subcategory":"Computer Services",
            "type":"Services"
        }
    ],
    "sg:phone":"+1 703 878 3410",
    "sg:postcode":"22191",
    "sg:province":"VA",
    "sg:tags":[
        "programing",
        "custom"
    ],
    "wof:name":"Universal Group Inc",
    "wof:placetype":"venue"
},
  "geometry": {"coordinates":[-77.269042,38.600418],"type":"Point"}
}