{
  "type": "Feature",
  "properties": {
    "addr:full":"185 Wesley Rd Daleville VA 24083",
    "addr:housenumber":"185",
    "addr:postcode":"24083",
    "addr:street":"Wesley Rd",
    "iso:country":"US",
    "sg:address":"185 Wesley Rd",
    "sg:city":"Daleville",
    "sg:classifiers":[
        {
            "category":"Building & Trades",
            "subcategory":"Construction",
            "type":"Services"
        }
    ],
    "sg:phone":"+1 540 992 4266",
    "sg:postcode":"24083",
    "sg:province":"VA",
    "sg:tags":[
        "house"
    ],
    "wof:name":"William J Conner Construction",
    "wof:placetype":"venue"
},
  "geometry": {"coordinates":[-79.902579,37.398025],"type":"Point"}
}