{
  "type": "Feature",
  "properties": {
    "addr:full":"5301 Lakeside Ave Richmond VA 23228",
    "addr:housenumber":"5301",
    "addr:postcode":"23228",
    "addr:street":"Lakeside Ave",
    "iso:country":"US",
    "sg:address":"5301 Lakeside Ave",
    "sg:city":"Richmond",
    "sg:classifiers":[
        {
            "category":"Food & Beverages",
            "subcategory":"Groceries & Convenience Stores",
            "type":"Retail Goods"
        }
    ],
    "sg:phone":"+1 804 262 2181",
    "sg:postcode":"23228",
    "sg:province":"VA",
    "wof:name":"East Coast Oil Corp",
    "wof:placetype":"venue"
},
  "geometry": {"coordinates":[-77.46704,37.601439],"type":"Point"}
}