{
  "type": "Feature",
  "properties": {
    "iso:country":"US",
    "sg:address":"9760 Center St",
    "sg:city":"Manassas",
    "sg:classifiers":[
        {
            "category":"Shopping",
            "type":"Retail Goods"
        }
    ],
    "sg:phone":"+1 703 368 3949",
    "sg:postcode":"20110",
    "sg:province":"VA",
    "sg:tags":[
        "enforcement",
        "law",
        "supply"
    ],
    "wof:name":"Virginia Arms Co Inc",
    "wof:placetype":"venue"
},
  "geometry": {"coordinates":[-77.48926400000001,38.753478],"type":"Point"}
}