{
  "type": "Feature",
  "properties": {
    "iso:country":"US",
    "sg:address":"2312 Plank Rd",
    "sg:city":"Fredericksburg",
    "sg:classifiers":[
        {
            "category":"Communications",
            "type":"Services"
        }
    ],
    "sg:phone":"+1 540 371 2617",
    "sg:postcode":"22401",
    "sg:province":"VA",
    "wof:name":"Quantum Communications",
    "wof:placetype":"venue"
},
  "geometry": {"coordinates":[-77.498811,38.296275],"type":"Point"}
}