{
  "type": "Feature",
  "properties": {
    "addr:full":"2612 Three Willows Ct Richmond VA 23294",
    "addr:housenumber":"2612",
    "addr:postcode":"23294",
    "addr:street":"Three Willows Ct",
    "iso:country":"US",
    "sg:address":"2612 Three Willows Ct",
    "sg:city":"Richmond",
    "sg:classifiers":[
        {
            "category":"Wholesale",
            "subcategory":"Stationery",
            "type":"Manufacturing & Wholesale Goods"
        }
    ],
    "sg:phone":"+1 804 273 6081",
    "sg:postcode":"23294",
    "sg:province":"VA",
    "sg:tags":[
        "supply"
    ],
    "wof:name":"Magnolia Graphics",
    "wof:placetype":"venue"
},
  "geometry": {"coordinates":[-77.53311600000001,37.624845],"type":"Point"}
}