{
  "type": "Feature",
  "properties": {
    "addr:full":"29442 Three Bees Rd Newsoms VA 23874",
    "addr:housenumber":"29442",
    "addr:postcode":"23874",
    "addr:street":"Three Bees Rd",
    "iso:country":"US",
    "sg:address":"29442 Three Bees Rd",
    "sg:city":"Newsoms",
    "sg:classifiers":[
        {
            "category":"Building & Trades",
            "subcategory":"Construction",
            "type":"Services"
        }
    ],
    "sg:phone":"+1 757 654 0599",
    "sg:postcode":"23874",
    "sg:province":"VA",
    "sg:tags":[
        "concrete",
        "contractor"
    ],
    "wof:name":"Keyser & Sons Home Improvement",
    "wof:placetype":"venue"
},
  "geometry": {"coordinates":[-77.15989999999999,36.620358],"type":"Point"}
}