{
  "type": "Feature",
  "properties": {
    "addr:full":"1300 Commerce St Lynchburg VA 24504",
    "addr:housenumber":"1300",
    "addr:postcode":"24504",
    "addr:street":"Commerce St",
    "iso:country":"US",
    "sg:address":"1300 Commerce St",
    "sg:city":"Lynchburg",
    "sg:classifiers":[
        {
            "category":"Real Estate",
            "subcategory":"Real Estate Agent",
            "type":"Services"
        }
    ],
    "sg:phone":"+1 434 846 3875",
    "sg:postcode":"24504",
    "sg:province":"VA",
    "sg:tags":[
        "management"
    ],
    "wof:name":"Hammer Enterprises",
    "wof:placetype":"venue"
},
  "geometry": {"coordinates":[-79.138729,37.410863],"type":"Point"}
}