{
  "type": "Feature",
  "properties": {
    "iso:country":"US",
    "sg:address":"3515 Dublin Ct",
    "sg:city":"Virginia Beach",
    "sg:classifiers":[
        {
            "category":"Building & Trades",
            "subcategory":"Construction",
            "type":"Services"
        }
    ],
    "sg:phone":"+1 757 721 6947",
    "sg:postcode":"23453",
    "sg:province":"VA",
    "sg:tags":[
        "water",
        "well",
        "drilling"
    ],
    "wof:name":"Bay Side Well & Pump Svc",
    "wof:placetype":"venue"
},
  "geometry": {"coordinates":[-76.107074,36.792142],"type":"Point"}
}