{
  "type": "Feature",
  "properties": {
    "addr:full":"289 Orchard Dr Bassett VA 24055",
    "addr:housenumber":"289",
    "addr:postcode":"24055",
    "addr:street":"Orchard Dr",
    "iso:country":"US",
    "sg:address":"289 Orchard Dr",
    "sg:city":"Bassett",
    "sg:classifiers":[
        {
            "category":"Organizations",
            "subcategory":"Religious Organization",
            "type":"Services"
        }
    ],
    "sg:phone":"+1 276 629 5722",
    "sg:postcode":"24055",
    "sg:province":"VA",
    "wof:name":"Charity Free Will Bptst Church",
    "wof:placetype":"venue"
},
  "geometry": {"coordinates":[-80.07962999999999,36.726693],"type":"Point"}
}