{
  "type": "Feature",
  "properties": {
    "iso:country":"US",
    "sg:address":"2403 Fall Hill Ave",
    "sg:city":"Fredericksburg",
    "sg:classifiers":[
        {
            "category":"Professional",
            "type":"Services"
        }
    ],
    "sg:phone":"+1 540 370 0300",
    "sg:postcode":"22401",
    "sg:province":"VA",
    "sg:tags":[
        "establishment"
    ],
    "wof:name":"Rotary International Dist 7610",
    "wof:placetype":"venue"
},
  "geometry": {"coordinates":[-77.473253,38.31365],"type":"Point"}
}