{
  "type": "Feature",
  "properties": {
    "addr:full":"255 W Lee Hwy Wytheville VA 24382",
    "addr:housenumber":"255",
    "addr:postcode":"24382",
    "addr:street":"W Lee Hwy",
    "iso:country":"US",
    "sg:address":"255 W Lee Hwy",
    "sg:city":"Wytheville",
    "sg:classifiers":[
        {
            "category":"Restaurant",
            "type":"Food & Drink"
        }
    ],
    "sg:menulink":"http://www.allmenus.com/va/west-wytheville/71931-pizza-hut/menu/",
    "sg:phone":"+1 276 228 7127",
    "sg:postcode":"24382",
    "sg:province":"VA",
    "sg:tags":[
        "american",
        "pizza"
    ],
    "wof:name":"Pizza Hut",
    "wof:placetype":"venue"
},
  "geometry": {"coordinates":[-81.090688,36.946481],"type":"Point"}
}