{
  "type": "Feature",
  "properties": {
    "addr:full":"11013 Lance Ln Oakton VA 22124",
    "addr:housenumber":"11013",
    "addr:postcode":"22124",
    "addr:street":"Lance Ln",
    "iso:country":"US",
    "sg:address":"11013 Lance Ln",
    "sg:city":"Oakton",
    "sg:classifiers":[
        {
            "category":"Home & Garden",
            "subcategory":"Mobile Homes",
            "type":"Retail Goods"
        }
    ],
    "sg:phone":"+1 703 558 0660",
    "sg:postcode":"22124",
    "sg:province":"VA",
    "wof:name":"Brian Cooney",
    "wof:placetype":"venue"
},
  "geometry": {"coordinates":[-77.327009,38.871978],"type":"Point"}
}