{
  "type": "Feature",
  "properties": {
    "addr:full":"3175 Azalea Garden Rd Norfolk VA 23513",
    "addr:housenumber":"3175",
    "addr:postcode":"23513",
    "addr:street":"Azalea Garden Rd",
    "iso:country":"US",
    "sg:address":"3175 Azalea Garden Rd",
    "sg:city":"Norfolk",
    "sg:classifiers":[
        {
            "category":"Food & Beverages",
            "subcategory":"Groceries & Convenience Stores",
            "type":"Retail Goods"
        }
    ],
    "sg:phone":"+1 757 852 2322",
    "sg:postcode":"23513",
    "sg:province":"VA",
    "sg:tags":[
        "grocer"
    ],
    "wof:name":"Azalea Food Mart",
    "wof:placetype":"venue"
},
  "geometry": {"coordinates":[-76.224006,36.883682],"type":"Point"}
}