{
  "type": "Feature",
  "properties": {
    "iso:country":"US",
    "sg:address":"2706 Border Rd",
    "sg:city":"Chesapeake",
    "sg:classifiers":[
        {
            "category":"Education",
            "subcategory":"School",
            "type":"Public Place"
        }
    ],
    "sg:phone":"+1 757 494 7515",
    "sg:postcode":"23324",
    "sg:province":"VA",
    "sg:tags":[
        "elementary"
    ],
    "sg:website":"http://www.cps.k12.va.us",
    "wof:name":"Thurgood Marshall Elementary School",
    "wof:placetype":"venue"
},
  "geometry": {"coordinates":[-76.25404399999999,36.816891],"type":"Point"}
}