{
  "type": "Feature",
  "properties": {
    "addr:full":"10658 Stegara Rd Barboursville VA 22923",
    "addr:housenumber":"10658",
    "addr:postcode":"22923",
    "addr:street":"Stegara Rd",
    "iso:country":"US",
    "sg:address":"10658 Stegara Rd",
    "sg:city":"Barboursville",
    "sg:classifiers":[
        {
            "category":"Museum",
            "type":"Entertainment"
        }
    ],
    "sg:phone":"+1 540 672 2473",
    "sg:postcode":"22923",
    "sg:province":"VA",
    "sg:tags":[
        "gallery"
    ],
    "wof:name":"Peter Payette",
    "wof:placetype":"venue"
},
  "geometry": {"coordinates":[-78.28074100000001,38.260359],"type":"Point"}
}