{
  "type": "Feature",
  "properties": {
    "addr:full":"227 28th St Newport News VA 23607",
    "addr:housenumber":"227",
    "addr:postcode":"23607",
    "addr:street":"28Th St",
    "iso:country":"US",
    "sg:address":"227 28th St",
    "sg:city":"Newport News",
    "sg:classifiers":[
        {
            "category":"Professional",
            "subcategory":"Lawyer & Legal Services",
            "type":"Services"
        }
    ],
    "sg:phone":"+1 757 245 1516",
    "sg:postcode":"23607",
    "sg:province":"VA",
    "sg:tags":[
        "attorney"
    ],
    "wof:name":"Louise J Richman Jr",
    "wof:placetype":"venue"
},
  "geometry": {"coordinates":[-76.430188,36.98025],"type":"Point"}
}