{
  "type": "Feature",
  "properties": {
    "addr:full":"1117 Moore House Rd Yorktown VA 23690",
    "addr:housenumber":"1117",
    "addr:postcode":"23690",
    "addr:street":"Moore House Rd",
    "iso:country":"US",
    "sg:address":"1117 Moore House Rd",
    "sg:city":"Yorktown",
    "sg:classifiers":[
        {
            "category":"Professional",
            "subcategory":"Engineering",
            "type":"Services"
        }
    ],
    "sg:phone":"+1 757 898 6585",
    "sg:postcode":"23690",
    "sg:province":"VA",
    "wof:name":"Jordan Kendall Inc",
    "wof:placetype":"venue"
},
  "geometry": {"coordinates":[-76.489468,37.22304],"type":"Point"}
}