{
  "type": "Feature",
  "properties": {
    "iso:country":"US",
    "sg:address":"235 Overhill Rd",
    "sg:city":"Christiansburg",
    "sg:classifiers":[
        {
            "category":"Professional",
            "subcategory":"Business Services",
            "type":"Services"
        }
    ],
    "sg:phone":"+1 540 381 5400",
    "sg:postcode":"24073",
    "sg:province":"VA",
    "wof:name":"Marie Raulfs Interior Design",
    "wof:placetype":"venue"
},
  "geometry": {"coordinates":[-80.394971,37.128959],"type":"Point"}
}