{
  "type": "Feature",
  "properties": {
    "addr:full":"14252 Glade Spring Dr Centreville VA 20121",
    "addr:housenumber":"14252",
    "addr:postcode":"20121",
    "addr:street":"Glade Spring Dr",
    "iso:country":"US",
    "sg:address":"14252 Glade Spring Dr",
    "sg:city":"Centreville",
    "sg:classifiers":[
        {
            "category":"Arena",
            "subcategory":"Sports Club",
            "type":"Entertainment"
        }
    ],
    "sg:phone":"+1 703 587 6619",
    "sg:postcode":"20121",
    "sg:province":"VA",
    "sg:tags":[
        "health"
    ],
    "wof:name":"Evolve Fitness",
    "wof:placetype":"venue"
},
  "geometry": {"coordinates":[-77.44564099999999,38.829739],"type":"Point"}
}