{
  "type": "Feature",
  "properties": {
    "addr:full":"11 Riverside Dr Charlottesville VA 22969",
    "addr:housenumber":"11",
    "addr:postcode":"22969",
    "addr:street":"Riverside Dr",
    "iso:country":"US",
    "sg:address":"11 Riverside Dr",
    "sg:city":"Charlottesville",
    "sg:classifiers":[
        {
            "category":"Building & Trades",
            "subcategory":"Construction",
            "type":"Services"
        }
    ],
    "sg:phone":"+1 434 977 3444",
    "sg:postcode":"22969",
    "sg:province":"VA",
    "sg:tags":[
        "house"
    ],
    "wof:name":"Decks By Dak",
    "wof:placetype":"venue"
},
  "geometry": {"coordinates":[-78.704489,37.792146],"type":"Point"}
}