{
  "type": "Feature",
  "properties": {
    "addr:full":"3613 Bridge Rd Suffolk VA 23435",
    "addr:housenumber":"3613",
    "addr:postcode":"23435",
    "addr:street":"Bridge Rd",
    "iso:country":"US",
    "sg:address":"3613 Bridge Rd",
    "sg:city":"Suffolk",
    "sg:classifiers":[
        {
            "category":"Farming",
            "subcategory":"Nursery",
            "type":"Manufacturing & Wholesale Goods"
        }
    ],
    "sg:phone":"+1 757 483 1425",
    "sg:postcode":"23435",
    "sg:province":"VA",
    "sg:tags":[
        "grows",
        "stock"
    ],
    "wof:name":"Bennetts Creek Wholesale Nurs",
    "wof:placetype":"venue"
},
  "geometry": {"coordinates":[-76.465548,36.86209],"type":"Point"}
}