{
  "type": "Feature",
  "properties": {
    "iso:country":"US",
    "sg:address":"800 N Wayne St",
    "sg:city":"Arlington",
    "sg:classifiers":[
        {
            "category":"Professional",
            "type":"Services"
        }
    ],
    "sg:phone":"+1 703 836 6390",
    "sg:postcode":"22201",
    "sg:province":"VA",
    "wof:name":"Caudill Dodd Inc",
    "wof:placetype":"venue"
},
  "geometry": {"coordinates":[-77.085995,38.882444],"type":"Point"}
}