{
  "type": "Feature",
  "properties": {
    "addr:full":"177 Madison Cir Madison Heights VA 24572",
    "addr:housenumber":"177",
    "addr:postcode":"24572",
    "addr:street":"Madison Cir",
    "iso:country":"US",
    "sg:address":"177 Madison Cir",
    "sg:city":"Madison Heights",
    "sg:classifiers":[
        {
            "category":"Shopping",
            "subcategory":"Jewelry",
            "type":"Retail Goods"
        }
    ],
    "sg:phone":"+1 434 846 1339",
    "sg:postcode":"24572",
    "sg:province":"VA",
    "sg:tags":[
        "jeweler"
    ],
    "wof:name":"Friedman's",
    "wof:placetype":"venue"
},
  "geometry": {"coordinates":[-79.133441,37.423621],"type":"Point"}
}