{
  "type": "Feature",
  "properties": {
    "addr:full":"225 S Hill Ave South Hill VA 23970",
    "addr:housenumber":"225",
    "addr:postcode":"23970",
    "addr:street":"S Hill Ave",
    "iso:country":"US",
    "sg:address":"225 S Hill Ave",
    "sg:city":"South Hill",
    "sg:classifiers":[
        {
            "category":"Retail",
            "subcategory":"Repair Shop",
            "type":"Services"
        }
    ],
    "sg:phone":"+1 434 447 4991",
    "sg:postcode":"23970",
    "sg:province":"VA",
    "sg:tags":[
        "upholsterer"
    ],
    "wof:name":"Wright's Upholstery",
    "wof:placetype":"venue"
},
  "geometry": {"coordinates":[-78.13083,36.724284],"type":"Point"}
}