{
  "type": "Feature",
  "properties": {
    "addr:full":"7524 Linton Hall Rd Gainesville VA 20155",
    "addr:housenumber":"7524",
    "addr:postcode":"20155",
    "addr:street":"Linton Hall Rd",
    "iso:country":"US",
    "sg:address":"7524 Linton Hall Rd",
    "sg:city":"Gainesville",
    "sg:classifiers":[
        {
            "category":"Health Services",
            "subcategory":"Doctor",
            "type":"Services"
        },
        {
            "category":"Arena",
            "subcategory":"Sports Club",
            "type":"Entertainment"
        }
    ],
    "sg:phone":"+1 703 753 9595",
    "sg:postcode":"20155",
    "sg:province":"VA",
    "sg:tags":[
        "martial art"
    ],
    "wof:name":"Mountain Kim Tae Kwon DO",
    "wof:placetype":"venue"
},
  "geometry": {"coordinates":[-77.62159699999999,38.804901],"type":"Point"}
}