{
  "type": "Feature",
  "properties": {
    "addr:full":"46314 Summerhill Pl Sterling VA 20165",
    "addr:housenumber":"46314",
    "addr:postcode":"20165",
    "addr:street":"Summerhill Pl",
    "iso:country":"US",
    "sg:address":"46314 Summerhill Pl",
    "sg:city":"Sterling",
    "sg:classifiers":[
        {
            "category":"Professional",
            "subcategory":"Computer Services",
            "type":"Services"
        }
    ],
    "sg:phone":"+1 703 450 0054",
    "sg:postcode":"20165",
    "sg:province":"VA",
    "sg:tags":[
        "related"
    ],
    "wof:name":"Singh Computer Consulting",
    "wof:placetype":"venue"
},
  "geometry": {"coordinates":[-77.397034,39.03704],"type":"Point"}
}