{
  "type": "Feature",
  "properties": {
    "iso:country":"US",
    "sg:address":"13507 Star Flower Ct",
    "sg:city":"Chantilly",
    "sg:classifiers":[
        {
            "category":"Professional",
            "subcategory":"Computer Services",
            "type":"Services"
        }
    ],
    "sg:phone":"+1 703 263 2653",
    "sg:postcode":"20151",
    "sg:province":"VA",
    "wof:name":"Gamut Systems",
    "wof:placetype":"venue"
},
  "geometry": {"coordinates":[-77.417765,38.868067],"type":"Point"}
}