{
  "type": "Feature",
  "properties": {
    "iso:country":"US",
    "sg:address":"1352 Peach Grove Ave",
    "sg:city":"Harrisonburg",
    "sg:classifiers":[
        {
            "category":"Home & Garden",
            "subcategory":"Carpets & Floor Coverings",
            "type":"Retail Goods"
        }
    ],
    "sg:phone":"+1 540 434 1818",
    "sg:postcode":"22801",
    "sg:province":"VA",
    "sg:tags":[
        "dealer",
        "rug"
    ],
    "wof:name":"Eagle Carpet Inc",
    "wof:placetype":"venue"
},
  "geometry": {"coordinates":[-78.87155199999999,38.416935],"type":"Point"}
}