{
  "type": "Feature",
  "properties": {
    "addr:full":"1781 Shelbourn Ln Keswick VA 22947",
    "addr:housenumber":"1781",
    "addr:postcode":"22947",
    "addr:street":"Shelbourn Ln",
    "iso:country":"US",
    "sg:address":"1781 Shelbourn Ln",
    "sg:city":"Keswick",
    "sg:classifiers":[
        {
            "category":"Professional",
            "subcategory":"Business Services",
            "type":"Services"
        }
    ],
    "sg:phone":"+1 434 296 8775",
    "sg:postcode":"22947",
    "sg:province":"VA",
    "wof:name":"Robert J Roberts Foundati",
    "wof:placetype":"venue"
},
  "geometry": {"coordinates":[-78.379693,37.985826],"type":"Point"}
}