{
  "type": "Feature",
  "properties": {
    "iso:country":"US",
    "sg:address":"400 N Robinson St",
    "sg:city":"Richmond",
    "sg:classifiers":[
        {
            "category":"Personal",
            "subcategory":"Tanning Parlor",
            "type":"Services"
        }
    ],
    "sg:phone":"+1 804 726 6056",
    "sg:postcode":"23220",
    "sg:province":"VA",
    "sg:tags":[
        "salon"
    ],
    "wof:name":"Absolute Tan",
    "wof:placetype":"venue"
},
  "geometry": {"coordinates":[-77.47011999999999,37.557441],"type":"Point"}
}