{
  "type": "Feature",
  "properties": {
    "addr:full":"11119 White Marsh Rd Elberon VA 23846",
    "addr:housenumber":"11119",
    "addr:postcode":"23846",
    "addr:street":"White Marsh Rd",
    "iso:country":"US",
    "sg:address":"11119 White Marsh Rd",
    "sg:city":"Elberon",
    "sg:classifiers":[
        {
            "category":"Farming",
            "subcategory":"Farm",
            "type":"Manufacturing & Wholesale Goods"
        }
    ],
    "sg:phone":"+1 757 294 3888",
    "sg:postcode":"23846",
    "sg:province":"VA",
    "sg:tags":[
        "crop",
        "general"
    ],
    "wof:name":"C Pittman",
    "wof:placetype":"venue"
},
  "geometry": {"coordinates":[-76.802734,37.038467],"type":"Point"}
}