{
  "type": "Feature",
  "properties": {
    "iso:country":"US",
    "sg:address":"6200 N Military Hwy",
    "sg:city":"Norfolk",
    "sg:classifiers":[
        {
            "category":"Restaurant",
            "type":"Food & Drink"
        }
    ],
    "sg:phone":"+1 757 853 8111",
    "sg:postcode":"23518",
    "sg:province":"VA",
    "sg:tags":[
        "eating"
    ],
    "wof:name":"New China Restaurant Inc",
    "wof:placetype":"venue"
},
  "geometry": {"coordinates":[-76.224958,36.896859],"type":"Point"}
}