{
  "type": "Feature",
  "properties": {
    "addr:full":"801 Tazewell Ave SE Roanoke VA 24013",
    "addr:housenumber":"801",
    "addr:postcode":"24013",
    "addr:street":"Tazewell Ave Se",
    "iso:country":"US",
    "sg:address":"801 Tazewell Ave SE",
    "sg:city":"Roanoke",
    "sg:classifiers":[
        {
            "category":"Autos & Motor Vehicles",
            "subcategory":"Automobile Sales",
            "type":"Retail Goods"
        }
    ],
    "sg:phone":"+1 540 982 2330",
    "sg:postcode":"24013",
    "sg:province":"VA",
    "sg:tags":[
        "used"
    ],
    "wof:name":"Bill Smith Motors Inc",
    "wof:placetype":"venue"
},
  "geometry": {"coordinates":[-79.930196,37.271609],"type":"Point"}
}