{
  "type": "Feature",
  "properties": {
    "addr:full":"7016 Leewood Forest Dr Springfield VA 22151",
    "addr:housenumber":"7016",
    "addr:postcode":"22151",
    "addr:street":"Leewood Forest Dr",
    "iso:country":"US",
    "sg:address":"7016 Leewood Forest Dr",
    "sg:city":"Springfield",
    "sg:classifiers":[
        {
            "category":"Professional",
            "subcategory":"Management & Consulting",
            "type":"Services"
        }
    ],
    "sg:phone":"+1 703 256 4938",
    "sg:postcode":"22151",
    "sg:province":"VA",
    "sg:tags":[
        "consultant"
    ],
    "wof:name":"Jay C Shaffer",
    "wof:placetype":"venue"
},
  "geometry": {"coordinates":[-77.186331,38.803568],"type":"Point"}
}