{
  "type": "Feature",
  "properties": {
    "iso:country":"US",
    "sg:address":"4537 Picasso Dr",
    "sg:city":"Virginia Beach",
    "sg:classifiers":[
        {
            "category":"Building & Trades",
            "subcategory":"Construction",
            "type":"Services"
        }
    ],
    "sg:phone":"+1 757 474 2724",
    "sg:postcode":"23456",
    "sg:province":"VA",
    "sg:tags":[
        "carpentry",
        "contractor"
    ],
    "wof:name":"Central Builders of Virginia",
    "wof:placetype":"venue"
},
  "geometry": {"coordinates":[-76.13639499999999,36.790169],"type":"Point"}
}