{
  "type": "Feature",
  "properties": {
    "iso:country":"US",
    "sg:address":"767 Madison Rd",
    "sg:city":"Culpeper",
    "sg:classifiers":[
        {
            "category":"Government",
            "subcategory":"Office",
            "type":"Public Place"
        }
    ],
    "sg:phone":"+1 540 829 0048",
    "sg:postcode":"22701",
    "sg:province":"VA",
    "sg:tags":[
        "armed",
        "force",
        "recruiting"
    ],
    "wof:name":"Navy Recruiting",
    "wof:placetype":"venue"
},
  "geometry": {"coordinates":[-78.018252,38.456579],"type":"Point"}
}