{
  "type": "Feature",
  "properties": {
    "addr:full":"400 15th St S Arlington VA 22202",
    "addr:housenumber":"400",
    "addr:postcode":"22202",
    "addr:street":"15Th St S",
    "iso:country":"US",
    "sg:address":"400 15th St S",
    "sg:city":"Arlington",
    "sg:classifiers":[
        {
            "category":"Retail",
            "subcategory":"Auto Rental",
            "type":"Services"
        }
    ],
    "sg:phone":"+1 703 892 1578",
    "sg:postcode":"22202",
    "sg:province":"VA",
    "sg:tags":[
        "car",
        "truck"
    ],
    "sg:website":"http://www.enterprise.com",
    "wof:name":"Enterprise Rent-A-Car",
    "wof:placetype":"venue"
},
  "geometry": {"coordinates":[-77.052933,38.85981],"type":"Point"}
}