{
  "type": "Feature",
  "properties": {
    "iso:country":"US",
    "sg:address":"7292 Thompson Rd",
    "sg:city":"Harrisonburg",
    "sg:classifiers":[
        {
            "category":"Building & Trades",
            "subcategory":"Landscaping Services",
            "type":"Services"
        }
    ],
    "sg:phone":"+1 540 833 4300",
    "sg:postcode":"22834",
    "sg:province":"VA",
    "sg:tags":[
        "tree"
    ],
    "wof:name":"American Tree Removal & Ldscp",
    "wof:placetype":"venue"
},
  "geometry": {"coordinates":[-78.920672,38.510169],"type":"Point"}
}