{
  "type": "Feature",
  "properties": {
    "addr:full":"2603 Warm Hearth Dr Blacksburg VA 24060",
    "addr:housenumber":"2603",
    "addr:postcode":"24060",
    "addr:street":"Warm Hearth Dr",
    "iso:country":"US",
    "sg:address":"2603 Warm Hearth Dr",
    "sg:city":"Blacksburg",
    "sg:classifiers":[
        {
            "category":"Health Services",
            "subcategory":"Nursing And Care Facility",
            "type":"Services"
        }
    ],
    "sg:phone":"+1 540 552 1498",
    "sg:postcode":"24060",
    "sg:province":"VA",
    "sg:tags":[
        "intermediate",
        "insurance"
    ],
    "wof:name":"Warm Heart Village",
    "wof:placetype":"venue"
},
  "geometry": {"coordinates":[-80.419251,37.199819],"type":"Point"}
}