{
  "type": "Feature",
  "properties": {
    "addr:full":"4741 Jefferson Davis Hwy Richmond VA 23234",
    "addr:housenumber":"4741",
    "addr:postcode":"23234",
    "addr:street":"Jefferson Davis Hwy",
    "iso:country":"US",
    "sg:address":"4741 Jefferson Davis Hwy",
    "sg:city":"Richmond",
    "sg:classifiers":[
        {
            "category":"Professional",
            "subcategory":"Lawyer & Legal Services",
            "type":"Services"
        }
    ],
    "sg:phone":"+1 804 743 8003",
    "sg:postcode":"23234",
    "sg:province":"VA",
    "wof:name":"William Orr Smith  Esquire  PC",
    "wof:placetype":"venue"
},
  "geometry": {"coordinates":[-77.442403,37.46173],"type":"Point"}
}