{
  "type": "Feature",
  "properties": {
    "iso:country":"US",
    "sg:address":"1608 Commerce Rd",
    "sg:city":"Richmond",
    "sg:classifiers":[
        {
            "category":"Professional",
            "type":"Services"
        }
    ],
    "sg:phone":"+1 804 675 1904",
    "sg:postcode":"23224",
    "sg:province":"VA",
    "wof:name":"Custom Storage Trailer LLC",
    "wof:placetype":"venue"
},
  "geometry": {"coordinates":[-77.430567,37.501856],"type":"Point"}
}