{
  "type": "Feature",
  "properties": {
    "iso:country":"US",
    "sg:address":"8535 Sudley Rd",
    "sg:city":"Manassas",
    "sg:classifiers":[
        {
            "category":"Real Estate",
            "subcategory":"Developer",
            "type":"Services"
        }
    ],
    "sg:phone":"+1 703 369 0070",
    "sg:postcode":"20109",
    "sg:province":"VA",
    "sg:tags":[
        "heavy",
        "house",
        "con"
    ],
    "wof:name":"Sunnybrook Golf",
    "wof:placetype":"venue"
},
  "geometry": {"coordinates":[-77.49577600000001,38.770883],"type":"Point"}
}