{
  "type": "Feature",
  "properties": {
    "addr:full":"2325 Virginia Beach Blvd Virginia Beach VA 23454",
    "addr:housenumber":"2325",
    "addr:postcode":"23454",
    "addr:street":"Virginia Beach Blvd",
    "iso:country":"US",
    "sg:address":"2325 Virginia Beach Blvd",
    "sg:city":"Virginia Beach",
    "sg:classifiers":[
        {
            "category":"Home & Garden",
            "subcategory":"Garden Supply",
            "type":"Retail Goods"
        }
    ],
    "sg:phone":"+1 757 340 8262",
    "sg:postcode":"23454",
    "sg:province":"VA",
    "sg:tags":[
        "repair",
        "lawn",
        "mower"
    ],
    "wof:name":"Aldridge & Chambers",
    "wof:placetype":"venue"
},
  "geometry": {"coordinates":[-76.04934299999999,36.84145],"type":"Point"}
}