{
  "type": "Feature",
  "properties": {
    "iso:country":"US",
    "sg:address":"997 Hardy Rd",
    "sg:city":"Vinton",
    "sg:classifiers":[
        {
            "category":"Personal",
            "subcategory":"Tanning Parlor",
            "type":"Services"
        },
        {
            "category":"Personal",
            "type":"Services"
        }
    ],
    "sg:phone":"+1 540 342 0183",
    "sg:postcode":"24179",
    "sg:province":"VA",
    "sg:tags":[
        "salon"
    ],
    "wof:name":"Nails N Rays Tanning Salon",
    "wof:placetype":"venue"
},
  "geometry": {"coordinates":[-79.885639,37.272885],"type":"Point"}
}