{
  "type": "Feature",
  "properties": {
    "iso:country":"US",
    "sg:address":"12543 Browns Ferry Rd",
    "sg:city":"Herndon",
    "sg:classifiers":[
        {
            "category":"Professional",
            "subcategory":"Computer Services",
            "type":"Services"
        }
    ],
    "sg:phone":"+1 703 406 9498",
    "sg:postcode":"20170",
    "sg:province":"VA",
    "sg:tags":[
        "related"
    ],
    "wof:name":"Walker Brynn Consulting",
    "wof:placetype":"venue"
},
  "geometry": {"coordinates":[-77.379515,38.998639],"type":"Point"}
}