{
  "type": "Feature",
  "properties": {
    "addr:full":"655 Fork Mountain Ln Montebello VA 24464",
    "addr:housenumber":"655",
    "addr:postcode":"24464",
    "addr:street":"Fork Mountain Ln",
    "iso:country":"US",
    "sg:address":"655 Fork Mountain Ln",
    "sg:city":"Montebello",
    "sg:classifiers":[
        {
            "category":"Professional",
            "subcategory":"Accounting & Tax Preparation",
            "type":"Services"
        }
    ],
    "sg:phone":"+1 540 377 6646",
    "sg:postcode":"24464",
    "sg:province":"VA",
    "sg:tags":[
        "accountant"
    ],
    "wof:name":"Earl Arnold CPA",
    "wof:placetype":"venue"
},
  "geometry": {"coordinates":[-79.08462299999999,37.875552],"type":"Point"}
}