{
  "type": "Feature",
  "properties": {
    "addr:full":"1400 S Main St Blacksburg VA 24060",
    "addr:housenumber":"1400",
    "addr:postcode":"24060",
    "addr:street":"S Main St",
    "iso:country":"US",
    "sg:address":"1400 S Main St",
    "sg:city":"Blacksburg",
    "sg:classifiers":[
        {
            "category":"Home & Garden",
            "subcategory":"Building Materials",
            "type":"Retail Goods"
        }
    ],
    "sg:phone":"+1 540 951 1556",
    "sg:postcode":"24060",
    "sg:province":"VA",
    "wof:name":"Timber Truss Housing Systems",
    "wof:placetype":"venue"
},
  "geometry": {"coordinates":[-80.40104700000001,37.215843],"type":"Point"}
}