{
  "type": "Feature",
  "properties": {
    "addr:full":"5145 Dickerson Rd Charlottesville VA 22911",
    "addr:housenumber":"5145",
    "addr:postcode":"22911",
    "addr:street":"Dickerson Rd",
    "iso:country":"US",
    "sg:address":"5145 Dickerson Rd",
    "sg:city":"Charlottesville",
    "sg:classifiers":[
        {
            "category":"Social Services",
            "subcategory":"Child Care",
            "type":"Services"
        }
    ],
    "sg:phone":"+1 434 973 9077",
    "sg:postcode":"22911",
    "sg:province":"VA",
    "sg:tags":[
        "kindergarten",
        "academic",
        "school"
    ],
    "wof:name":"Paran Preschool",
    "wof:placetype":"venue"
},
  "geometry": {"coordinates":[-78.41126800000001,38.171323],"type":"Point"}
}