{
  "type": "Feature",
  "properties": {
    "iso:country":"US",
    "sg:address":"6610 Commons Dr",
    "sg:city":"Prince George",
    "sg:classifiers":[
        {
            "category":"Social Services",
            "type":"Services"
        }
    ],
    "sg:phone":"+1 804 861 0393",
    "sg:postcode":"23875",
    "sg:province":"VA",
    "sg:tags":[
        "counseling"
    ],
    "wof:name":"District 19 Community Svc",
    "wof:placetype":"venue"
},
  "geometry": {"coordinates":[-77.29067499999999,37.221941],"type":"Point"}
}