{
  "type": "Feature",
  "properties": {
    "iso:country":"US",
    "sg:address":"440 Arrow Ln",
    "sg:city":"Wytheville",
    "sg:classifiers":[
        {
            "category":"Food & Beverages",
            "subcategory":"Groceries & Convenience Stores",
            "type":"Retail Goods"
        }
    ],
    "sg:phone":"+1 276 228 6889",
    "sg:postcode":"24382",
    "sg:province":"VA",
    "wof:name":"Agape Food Pantry",
    "wof:placetype":"venue"
},
  "geometry": {"coordinates":[-81.11344699999999,36.93369],"type":"Point"}
}