{
  "type": "Feature",
  "properties": {
    "addr:full":"2561 Jude's Ferry Rd Powhatan VA 23139",
    "addr:housenumber":"2561",
    "addr:postcode":"23139",
    "addr:street":"Jude'S Ferry Rd",
    "iso:country":"US",
    "sg:address":"2561 Jude's Ferry Rd",
    "sg:city":"Powhatan",
    "sg:classifiers":[
        {
            "category":"Building & Trades",
            "subcategory":"Construction",
            "type":"Services"
        }
    ],
    "sg:phone":"+1 804 598 2689",
    "sg:postcode":"23139",
    "sg:province":"VA",
    "sg:tags":[
        "hanging",
        "contractor"
    ],
    "wof:name":"Sam Lawson Painting",
    "wof:placetype":"venue"
},
  "geometry": {"coordinates":[-77.79979899999999,37.561195],"type":"Point"}
}