{
  "type": "Feature",
  "properties": {
    "iso:country":"US",
    "sg:address":"2028 Powhatan St",
    "sg:city":"Falls Church",
    "sg:classifiers":[
        {
            "category":"Professional",
            "subcategory":"Management & Consulting",
            "type":"Services"
        }
    ],
    "sg:phone":"+1 703 998 7772",
    "sg:postcode":"22043",
    "sg:province":"VA",
    "wof:name":"Taramex Inc",
    "wof:placetype":"venue"
},
  "geometry": {"coordinates":[-77.163144,38.906614],"type":"Point"}
}