{
  "type": "Feature",
  "properties": {
    "addr:full":"5945 Wellington Rd Gainesville VA 20155",
    "addr:housenumber":"5945",
    "addr:postcode":"20155",
    "addr:street":"Wellington Rd",
    "iso:country":"US",
    "sg:address":"5945 Wellington Rd",
    "sg:city":"Gainesville",
    "sg:classifiers":[
        {
            "category":"Autos & Motor Vehicles",
            "subcategory":"Automobile Sales",
            "type":"Retail Goods"
        }
    ],
    "sg:phone":"+1 703 754 5000",
    "sg:postcode":"20155",
    "sg:province":"VA",
    "sg:tags":[
        "equipment",
        "electrical"
    ],
    "sg:website":"http://www.atlanticresearchcorp.com",
    "wof:name":"Atlantic Research Corporation",
    "wof:placetype":"venue"
},
  "geometry": {"coordinates":[-77.60517900000001,38.791592],"type":"Point"}
}