{
  "type": "Feature",
  "properties": {
    "addr:full":"5894 Lee Hwy Atkins VA 24311",
    "addr:housenumber":"5894",
    "addr:postcode":"24311",
    "addr:street":"Lee Hwy",
    "iso:country":"US",
    "sg:address":"5894 Lee Hwy",
    "sg:city":"Atkins",
    "sg:classifiers":[
        {
            "category":"Banks & Credit Unions",
            "subcategory":"Bank",
            "type":"Services"
        }
    ],
    "sg:phone":"+1 276 783 3911",
    "sg:postcode":"24311",
    "sg:province":"VA",
    "wof:name":"B B & T",
    "wof:placetype":"venue"
},
  "geometry": {"coordinates":[-81.417569,36.867771],"type":"Point"}
}