{
  "type": "Feature",
  "properties": {
    "addr:full":"800 Orrix Creek Rd Evington VA 24550",
    "addr:housenumber":"800",
    "addr:postcode":"24550",
    "addr:street":"Orrix Creek Rd",
    "iso:country":"US",
    "sg:address":"800 Orrix Creek Rd",
    "sg:city":"Evington",
    "sg:classifiers":[
        {
            "category":"Shopping",
            "subcategory":"Antiques",
            "type":"Retail Goods"
        }
    ],
    "sg:phone":"+1 434 309 1132",
    "sg:postcode":"24550",
    "sg:province":"VA",
    "wof:name":"The Yorkshireman Antiques",
    "wof:placetype":"venue"
},
  "geometry": {"coordinates":[-79.330421,37.225788],"type":"Point"}
}