{
  "type": "Feature",
  "properties": {
    "addr:full":"4112 Meadowdale Blvd Richmond VA 23234",
    "addr:housenumber":"4112",
    "addr:postcode":"23234",
    "addr:street":"Meadowdale Blvd",
    "iso:country":"US",
    "sg:address":"4112 Meadowdale Blvd",
    "sg:city":"Richmond",
    "sg:phone":"+1 804 275 0568",
    "sg:postcode":"23234",
    "sg:province":"VA",
    "sg:website":"http://www.pinospizzarichmond.com",
    "wof:name":"Pino's Pizza Italian Family Restaurant",
    "wof:placetype":"venue"
},
  "geometry": {"coordinates":[-77.471001,37.438019],"type":"Point"}
}