{
  "type": "Feature",
  "properties": {
    "addr:full":"1405 S Fern St Arlington VA 22202",
    "addr:housenumber":"1405",
    "addr:postcode":"22202",
    "addr:street":"S Fern St",
    "iso:country":"US",
    "sg:address":"1405 S Fern St",
    "sg:city":"Arlington",
    "sg:classifiers":[
        {
            "category":"Building & Trades",
            "subcategory":"Locksmith",
            "type":"Services"
        }
    ],
    "sg:phone":"+1 571 431 1914",
    "sg:postcode":"22202",
    "sg:province":"VA",
    "sg:tags":[
        "key"
    ],
    "wof:name":"A 1 Emergency Locksmith",
    "wof:placetype":"venue"
},
  "geometry": {"coordinates":[-77.05609800000001,38.860637],"type":"Point"}
}