{
  "type": "Feature",
  "properties": {
    "addr:full":"327 Payne St Gretna VA 24557",
    "addr:housenumber":"327",
    "addr:postcode":"24557",
    "addr:street":"Payne St",
    "iso:country":"US",
    "sg:address":"327 Payne St",
    "sg:city":"Gretna",
    "sg:classifiers":[
        {
            "category":"Real Estate",
            "subcategory":"Real Estate Operator",
            "type":"Services"
        }
    ],
    "sg:phone":"+1 434 656 6529",
    "sg:postcode":"24557",
    "sg:province":"VA",
    "sg:tags":[
        "apartment"
    ],
    "wof:name":"Gretna Village Apartments",
    "wof:placetype":"venue"
},
  "geometry": {"coordinates":[-79.356533,36.951038],"type":"Point"}
}