{
  "type": "Feature",
  "properties": {
    "addr:full":"2003 S Main St Farmville VA 23901",
    "addr:housenumber":"2003",
    "addr:postcode":"23901",
    "addr:street":"S Main St",
    "iso:country":"US",
    "sg:address":"2003 S Main St",
    "sg:city":"Farmville",
    "sg:classifiers":[
        {
            "category":"Autos & Motor Vehicles",
            "subcategory":"Fuel & Gas Station",
            "type":"Retail Goods"
        }
    ],
    "sg:phone":"+1 434 315 0222",
    "sg:postcode":"23901",
    "sg:province":"VA",
    "sg:tags":[
        "oil"
    ],
    "wof:name":"Shell",
    "wof:placetype":"venue"
},
  "geometry": {"coordinates":[-78.40115299999999,37.27444],"type":"Point"}
}