{
  "type": "Feature",
  "properties": {
    "iso:country":"US",
    "sg:address":"802 W Broad St",
    "sg:city":"Falls Church",
    "sg:classifiers":[
        {
            "category":"Professional",
            "subcategory":"Business Services",
            "type":"Services"
        }
    ],
    "sg:phone":"+1 703 237 2080",
    "sg:postcode":"22046",
    "sg:province":"VA",
    "sg:tags":[
        "interior",
        "consultant",
        "design",
        "decorator"
    ],
    "wof:name":"Creations By Carrol",
    "wof:placetype":"venue"
},
  "geometry": {"coordinates":[-77.181798,38.889217],"type":"Point"}
}