{
  "type": "Feature",
  "properties": {
    "iso:country":"US",
    "sg:address":"2111 W Main St",
    "sg:city":"Richmond",
    "sg:classifiers":[
        {
            "category":"Building & Trades",
            "subcategory":"Cleaning & Sanitation",
            "type":"Services"
        }
    ],
    "sg:phone":"+1 804 355 1710",
    "sg:postcode":"23220",
    "sg:province":"VA",
    "sg:tags":[
        "house"
    ],
    "wof:name":"Maid Brigade",
    "wof:placetype":"venue"
},
  "geometry": {"coordinates":[-77.468253,37.549979],"type":"Point"}
}