{
  "type": "Feature",
  "properties": {
    "addr:full":"3511 Maple Ct Falls Church VA 22041",
    "addr:housenumber":"3511",
    "addr:postcode":"22041",
    "addr:street":"Maple Ct",
    "iso:country":"US",
    "sg:address":"3511 Maple Ct",
    "sg:city":"Falls Church",
    "sg:classifiers":[
        {
            "category":"Professional",
            "type":"Services"
        }
    ],
    "sg:phone":"+1 703 820 1457",
    "sg:postcode":"22041",
    "sg:province":"VA",
    "wof:name":"Gary Wingard",
    "wof:placetype":"venue"
},
  "geometry": {"coordinates":[-77.13619799999999,38.847641],"type":"Point"}
}