{
  "type": "Feature",
  "properties": {
    "iso:country":"US",
    "sg:address":"125 N Quarter",
    "sg:city":"Williamsburg",
    "sg:classifiers":[
        {
            "category":"Professional",
            "subcategory":"Management & Consulting",
            "type":"Services"
        }
    ],
    "sg:phone":"+1 757 253 1371",
    "sg:postcode":"23185",
    "sg:province":"VA",
    "sg:tags":[
        "construction"
    ],
    "wof:name":"Teck Corp",
    "wof:placetype":"venue"
},
  "geometry": {"coordinates":[-76.681703,37.243077],"type":"Point"}
}