{
  "type": "Feature",
  "properties": {
    "iso:country":"US",
    "sg:address":"9485 Silver King Ct",
    "sg:city":"Fairfax",
    "sg:classifiers":[
        {
            "category":"Wholesale",
            "subcategory":"Seafood",
            "type":"Manufacturing & Wholesale Goods"
        }
    ],
    "sg:phone":"+1 703 359 1000",
    "sg:postcode":"22031",
    "sg:province":"VA",
    "wof:name":"Blue Ocean Seafood Corp",
    "wof:placetype":"venue"
},
  "geometry": {"coordinates":[-77.270521,38.85898],"type":"Point"}
}