{
  "type": "Feature",
  "properties": {
    "addr:full":"2153 Old Greenbrier Rd Chesapeake VA 23320",
    "addr:housenumber":"2153",
    "addr:postcode":"23320",
    "addr:street":"Old Greenbrier Rd",
    "iso:country":"US",
    "sg:address":"2153 Old Greenbrier Rd",
    "sg:city":"Chesapeake",
    "sg:classifiers":[
        {
            "category":"Retail",
            "subcategory":"Auto Rental",
            "type":"Services"
        }
    ],
    "sg:phone":"+1 757 420 9295",
    "sg:postcode":"23320",
    "sg:province":"VA",
    "sg:tags":[
        "automobile",
        "lease",
        "used",
        "truck",
        "car"
    ],
    "wof:name":"Car-Truck Leasing Corp",
    "wof:placetype":"venue"
},
  "geometry": {"coordinates":[-76.234515,36.795834],"type":"Point"}
}