{
  "type": "Feature",
  "properties": {
    "iso:country":"US",
    "sg:address":"11128 Henderson Rd",
    "sg:city":"Fairfax Station",
    "sg:classifiers":[
        {
            "category":"Wholesale",
            "subcategory":"Seafood",
            "type":"Manufacturing & Wholesale Goods"
        }
    ],
    "sg:phone":"+1 703 323 5366",
    "sg:postcode":"22039",
    "sg:province":"VA",
    "wof:name":"Sealand Food Inc",
    "wof:placetype":"venue"
},
  "geometry": {"coordinates":[-77.331671,38.742457],"type":"Point"}
}