{
  "type": "Feature",
  "properties": {
    "addr:full":"302 22nd St Virginia Beach VA 23451",
    "addr:housenumber":"302",
    "addr:postcode":"23451",
    "addr:street":"22Nd St",
    "iso:country":"US",
    "sg:address":"302 22nd St",
    "sg:city":"Virginia Beach",
    "sg:classifiers":[
        {
            "category":"Arts & Performance",
            "subcategory":"Theater",
            "type":"Entertainment"
        }
    ],
    "sg:phone":"+1 757 425 3111",
    "sg:postcode":"23451",
    "sg:province":"VA",
    "sg:tags":[
        "theatrical",
        "bureau"
    ],
    "wof:name":"Cellar Door Productions",
    "wof:placetype":"venue"
},
  "geometry": {"coordinates":[-75.977947,36.849737],"type":"Point"}
}