{
  "type": "Feature",
  "properties": {
    "iso:country":"US",
    "sg:address":"3035 W Cary St",
    "sg:city":"Richmond",
    "sg:classifiers":[
        {
            "category":"Building & Trades",
            "subcategory":"Equipment Rental",
            "type":"Services"
        }
    ],
    "sg:phone":"+1 804 750 1142",
    "sg:postcode":"23221",
    "sg:province":"VA",
    "sg:tags":[
        "party",
        "supply"
    ],
    "wof:name":"Party Rental Discounters",
    "wof:placetype":"venue"
},
  "geometry": {"coordinates":[-77.48035900000001,37.553043],"type":"Point"}
}