{
  "type": "Feature",
  "properties": {
    "addr:full":"2608 Valley Ave Winchester VA 22601",
    "addr:housenumber":"2608",
    "addr:postcode":"22601",
    "addr:street":"Valley Ave",
    "iso:country":"US",
    "sg:address":"2608 Valley Ave",
    "sg:city":"Winchester",
    "sg:classifiers":[
        {
            "category":"Banks & Credit Unions",
            "subcategory":"Bank",
            "type":"Services"
        }
    ],
    "sg:phone":"+1 540 665 2384",
    "sg:postcode":"22601",
    "sg:province":"VA",
    "sg:tags":[
        "national"
    ],
    "wof:name":"Wachovia Bank National Assn",
    "wof:placetype":"venue"
},
  "geometry": {"coordinates":[-78.18644399999999,39.156204],"type":"Point"}
}