{
  "type": "Feature",
  "properties": {
    "addr:full":"3809 Keith Ave Fairfax VA 22030",
    "addr:housenumber":"3809",
    "addr:postcode":"22030",
    "addr:street":"Keith Ave",
    "iso:country":"US",
    "sg:address":"3809 Keith Ave",
    "sg:city":"Fairfax",
    "sg:classifiers":[
        {
            "category":"Manufacturing",
            "subcategory":"Tools & Machinery",
            "type":"Manufacturing & Wholesale Goods"
        }
    ],
    "sg:phone":"+1 703 385 9181",
    "sg:postcode":"22030",
    "sg:province":"VA",
    "sg:tags":[
        "repair",
        "industry",
        "mfg"
    ],
    "wof:name":"Car Wash Care Inc",
    "wof:placetype":"venue"
},
  "geometry": {"coordinates":[-77.313225,38.853089],"type":"Point"}
}