{
  "type": "Feature",
  "properties": {
    "iso:country":"US",
    "sg:address":"3745 Holland Rd",
    "sg:city":"Virginia Beach",
    "sg:classifiers":[
        {
            "category":"Health Services",
            "subcategory":"Doctor",
            "type":"Services"
        }
    ],
    "sg:phone":"+1 757 463 0922",
    "sg:postcode":"23452",
    "sg:province":"VA",
    "wof:name":"Tisdale Bradford",
    "wof:placetype":"venue"
},
  "geometry": {"coordinates":[-76.100953,36.81389],"type":"Point"}
}