{
  "type": "Feature",
  "properties": {
    "iso:country":"US",
    "sg:address":"21 Biscayne Pl",
    "sg:city":"Sterling",
    "sg:classifiers":[
        {
            "category":"Utilities",
            "subcategory":"Telephone",
            "type":"Services"
        }
    ],
    "sg:phone":"+1 703 450 4574",
    "sg:postcode":"20164",
    "sg:province":"VA",
    "sg:tags":[
        "internet"
    ],
    "wof:name":"Rp Products Corporation",
    "wof:placetype":"venue"
},
  "geometry": {"coordinates":[-77.36597999999999,39.03516],"type":"Point"}
}