{
  "type": "Feature",
  "properties": {
    "iso:country":"US",
    "sg:address":"3059 S Abingdon St",
    "sg:city":"Arlington",
    "sg:classifiers":[
        {
            "category":"Professional",
            "subcategory":"Art Services",
            "type":"Services"
        }
    ],
    "sg:phone":"+1 703 379 6342",
    "sg:postcode":"22206",
    "sg:province":"VA",
    "sg:tags":[
        "graphic",
        "designer"
    ],
    "wof:name":"V W Design",
    "wof:placetype":"venue"
},
  "geometry": {"coordinates":[-77.095787,38.837562],"type":"Point"}
}