{
  "type": "Feature",
  "properties": {
    "addr:full":"1620 Burson Dr Chesapeake VA 23323",
    "addr:housenumber":"1620",
    "addr:postcode":"23323",
    "addr:street":"Burson Dr",
    "iso:country":"US",
    "sg:address":"1620 Burson Dr",
    "sg:city":"Chesapeake",
    "sg:classifiers":[
        {
            "category":"Building & Trades",
            "subcategory":"Construction",
            "type":"Services"
        }
    ],
    "sg:phone":"+1 757 485 3678",
    "sg:postcode":"23323",
    "sg:province":"VA",
    "sg:tags":[
        "painter"
    ],
    "wof:name":"Ken Hill Sign & Mural Painting",
    "wof:placetype":"venue"
},
  "geometry": {"coordinates":[-76.30586700000001,36.740086],"type":"Point"}
}