{
  "type": "Feature",
  "properties": {
    "addr:full":"3884 Long Meadow Ave NW Roanoke VA 24017",
    "addr:housenumber":"3884",
    "addr:postcode":"24017",
    "addr:street":"Long Meadow Ave Nw",
    "iso:country":"US",
    "sg:address":"3884 Long Meadow Ave NW",
    "sg:city":"Roanoke",
    "sg:classifiers":[
        {
            "category":"Education",
            "subcategory":"Vocational School",
            "type":"Public Place"
        }
    ],
    "sg:phone":"+1 540 345 0105",
    "sg:postcode":"24017",
    "sg:province":"VA",
    "sg:tags":[
        "processing",
        "datum"
    ],
    "wof:name":"Computer Training & Publishing",
    "wof:placetype":"venue"
},
  "geometry": {"coordinates":[-80.006311,37.285331],"type":"Point"}
}