{
  "type": "Feature",
  "properties": {
    "addr:full":"7651 Whispering Pines Trl Windsor VA 23487",
    "addr:housenumber":"7651",
    "addr:postcode":"23487",
    "addr:street":"Whispering Pines Trl",
    "iso:country":"US",
    "sg:address":"7651 Whispering Pines Trl",
    "sg:city":"Windsor",
    "sg:classifiers":[
        {
            "category":"Travel",
            "subcategory":"Campground",
            "type":"Entertainment"
        }
    ],
    "sg:phone":"+1 757 357 7211",
    "sg:postcode":"23487",
    "sg:province":"VA",
    "sg:tags":[
        "grocery",
        "trailer"
    ],
    "wof:name":"Black Water Campground",
    "wof:placetype":"venue"
},
  "geometry": {"coordinates":[-76.793933,36.901816],"type":"Point"}
}