{
  "type": "Feature",
  "properties": {
    "addr:full":"10299 Millbank Rd King George VA 22485",
    "addr:housenumber":"10299",
    "addr:postcode":"22485",
    "addr:street":"Millbank Rd",
    "iso:country":"US",
    "sg:address":"10299 Millbank Rd",
    "sg:city":"King George",
    "sg:classifiers":[
        {
            "category":"Organizations",
            "subcategory":"Religious Organization",
            "type":"Services"
        }
    ],
    "sg:phone":"+1 540 775 7381",
    "sg:postcode":"22485",
    "sg:province":"VA",
    "sg:tags":[
        "church"
    ],
    "wof:name":"St Anthony's Catholic Church",
    "wof:placetype":"venue"
},
  "geometry": {"coordinates":[-77.189869,38.269276],"type":"Point"}
}