{
  "type": "Feature",
  "properties": {
    "addr:full":"64 Semple Farm Rd Hampton VA 23666",
    "addr:housenumber":"64",
    "addr:postcode":"23666",
    "addr:street":"Semple Farm Rd",
    "iso:country":"US",
    "sg:address":"64 Semple Farm Rd",
    "sg:city":"Hampton",
    "sg:classifiers":[
        {
            "category":"Home & Garden",
            "subcategory":"Carpets & Floor Coverings",
            "type":"Retail Goods"
        }
    ],
    "sg:phone":"+1 757 766 1230",
    "sg:postcode":"23666",
    "sg:province":"VA",
    "wof:name":"Edgar Burwell",
    "wof:placetype":"venue"
},
  "geometry": {"coordinates":[-76.39857000000001,37.091821],"type":"Point"}
}