{
  "type": "Feature",
  "properties": {
    "addr:full":"3502 Corum Dr Richmond VA 23294",
    "addr:housenumber":"3502",
    "addr:postcode":"23294",
    "addr:street":"Corum Dr",
    "iso:country":"US",
    "sg:address":"3502 Corum Dr",
    "sg:city":"Richmond",
    "sg:classifiers":[
        {
            "category":"Building & Trades",
            "subcategory":"Construction",
            "type":"Services"
        }
    ],
    "sg:phone":"+1 804 346 5497",
    "sg:postcode":"23294",
    "sg:province":"VA",
    "sg:tags":[
        "floor",
        "laying",
        "contractor"
    ],
    "wof:name":"Francisco Eber Flooring",
    "wof:placetype":"venue"
},
  "geometry": {"coordinates":[-77.557233,37.638943],"type":"Point"}
}