{
  "type": "Feature",
  "properties": {
    "addr:full":"104 N Hawksbill St Luray VA 22835",
    "addr:housenumber":"104",
    "addr:postcode":"22835",
    "addr:street":"N Hawksbill St",
    "iso:country":"US",
    "sg:address":"104 N Hawksbill St",
    "sg:city":"Luray",
    "sg:classifiers":[
        {
            "category":"Manufacturing",
            "subcategory":"Printing",
            "type":"Manufacturing & Wholesale Goods"
        }
    ],
    "sg:phone":"+1 540 743 7343",
    "sg:postcode":"22835",
    "sg:province":"VA",
    "sg:tags":[
        "screen"
    ],
    "wof:name":"Showalter Signs & Silk Screen",
    "wof:placetype":"venue"
},
  "geometry": {"coordinates":[-78.46219600000001,38.666537],"type":"Point"}
}