{
  "type": "Feature",
  "properties": {
    "iso:country":"US",
    "sg:address":"10816 Harley Rd",
    "sg:city":"Lorton",
    "sg:classifiers":[
        {
            "category":"Food & Beverages",
            "subcategory":"Fruits & Vegetables",
            "type":"Retail Goods"
        }
    ],
    "sg:phone":"+1 703 339 6315",
    "sg:postcode":"22079",
    "sg:province":"VA",
    "sg:tags":[
        "farm",
        "antique",
        "market"
    ],
    "wof:name":"Marshas Country Store",
    "wof:placetype":"venue"
},
  "geometry": {"coordinates":[-77.18216099999999,38.662665],"type":"Point"}
}