{
  "type": "Feature",
  "properties": {
    "addr:full":"11618 Foxclove Rd Reston VA 20191",
    "addr:housenumber":"11618",
    "addr:postcode":"20191",
    "addr:street":"Foxclove Rd",
    "iso:country":"US",
    "sg:address":"11618 Foxclove Rd",
    "sg:city":"Reston",
    "sg:classifiers":[
        {
            "category":"Organizations",
            "subcategory":"Professional Association",
            "type":"Services"
        }
    ],
    "sg:phone":"+1 703 860 0962",
    "sg:postcode":"20191",
    "sg:province":"VA",
    "wof:name":"Rrp Assoc",
    "wof:placetype":"venue"
},
  "geometry": {"coordinates":[-77.348703,38.916799],"type":"Point"}
}