{
  "type": "Feature",
  "properties": {
    "addr:full":"6612 E Virginia Beach Blvd Norfolk VA 23502",
    "addr:housenumber":"6612",
    "addr:postcode":"23502",
    "addr:street":"E Virginia Beach Blvd",
    "iso:country":"US",
    "sg:address":"6612 E Virginia Beach Blvd",
    "sg:city":"Norfolk",
    "sg:classifiers":[
        {
            "category":"Personal",
            "subcategory":"Beauty Salon",
            "type":"Services"
        }
    ],
    "sg:phone":"+1 757 461 5570",
    "sg:postcode":"23502",
    "sg:province":"VA",
    "sg:tags":[
        "shop"
    ],
    "wof:name":"Bintu's African Hair Braiding",
    "wof:placetype":"venue"
},
  "geometry": {"coordinates":[-76.180708,36.854758],"type":"Point"}
}