{
  "type": "Feature",
  "properties": {
    "addr:full":"801 Bizzarre St Farmville VA 23901",
    "addr:housenumber":"801",
    "addr:postcode":"23901",
    "addr:street":"Bizzarre St",
    "iso:country":"US",
    "sg:address":"801 Bizzarre St",
    "sg:city":"Farmville",
    "sg:classifiers":[
        {
            "category":"Social Services",
            "type":"Services"
        }
    ],
    "sg:phone":"+1 434 392 8061",
    "sg:postcode":"23901",
    "sg:province":"VA",
    "wof:name":"Inge Diann Byrd MA Ms",
    "wof:placetype":"venue"
},
  "geometry": {"coordinates":[-78.38927099999999,37.310702],"type":"Point"}
}