{
  "type": "Feature",
  "properties": {
    "iso:country":"US",
    "sg:address":"8815 Side Saddle Rd",
    "sg:city":"Springfield",
    "sg:classifiers":[
        {
            "category":"Real Estate",
            "subcategory":"Real Estate Agent",
            "type":"Services"
        }
    ],
    "sg:phone":"+1 703 455 1125",
    "sg:postcode":"22152",
    "sg:province":"VA",
    "wof:name":"A I Inc",
    "wof:placetype":"venue"
},
  "geometry": {"coordinates":[-77.249177,38.766704],"type":"Point"}
}