{
  "type": "Feature",
  "properties": {
    "addr:full":"8133 Forest Hill Ave Richmond VA 23235",
    "addr:housenumber":"8133",
    "addr:postcode":"23235",
    "addr:street":"Forest Hill Ave",
    "iso:country":"US",
    "sg:address":"8133 Forest Hill Ave",
    "sg:city":"Richmond",
    "sg:classifiers":[
        {
            "category":"Professional",
            "subcategory":"Lawyer & Legal Services",
            "type":"Services"
        }
    ],
    "sg:phone":"+1 804 330 0213",
    "sg:postcode":"23235",
    "sg:province":"VA",
    "wof:name":"Isaacs Stphen A Attrney At Law",
    "wof:placetype":"venue"
},
  "geometry": {"coordinates":[-77.54794,37.531678],"type":"Point"}
}