{
  "type": "Feature",
  "properties": {
    "addr:full":"221 W Main St Marion VA 24354",
    "addr:housenumber":"221",
    "addr:postcode":"24354",
    "addr:street":"W Main St",
    "iso:country":"US",
    "sg:address":"221 W Main St",
    "sg:city":"Marion",
    "sg:classifiers":[
        {
            "category":"Health Services",
            "subcategory":"Nursing And Care Facility",
            "type":"Services"
        }
    ],
    "sg:phone":"+1 276 782 1819",
    "sg:postcode":"24354",
    "sg:province":"VA",
    "wof:name":"Rejuvination C Retirement",
    "wof:placetype":"venue"
},
  "geometry": {"coordinates":[-81.522279,36.831723],"type":"Point"}
}