{
  "type": "Feature",
  "properties": {
    "addr:full":"743 Welsh Run Rd Ruckersville VA 22968",
    "addr:housenumber":"743",
    "addr:postcode":"22968",
    "addr:street":"Welsh Run Rd",
    "iso:country":"US",
    "sg:address":"743 Welsh Run Rd",
    "sg:city":"Ruckersville",
    "sg:classifiers":[
        {
            "category":"Real Estate",
            "subcategory":"Real Estate Agent",
            "type":"Services"
        }
    ],
    "sg:phone":"+1 434 245 8445",
    "sg:postcode":"22968",
    "sg:province":"VA",
    "sg:website":"www.dominionrealty.com",
    "wof:name":"Dominion Realty Group",
    "wof:placetype":"venue"
},
  "geometry": {"coordinates":[-78.440848,38.218662],"type":"Point"}
}