{
  "type": "Feature",
  "properties": {
    "iso:country":"US",
    "sg:address":"118 Production Dr",
    "sg:city":"Yorktown",
    "sg:classifiers":[
        {
            "category":"Home & Garden",
            "subcategory":"Building Materials",
            "type":"Retail Goods"
        }
    ],
    "sg:phone":"+1 757 594 9078",
    "sg:postcode":"23693",
    "sg:province":"VA",
    "sg:tags":[
        "house"
    ],
    "wof:name":"Ace Handyman & Remodeling LLC",
    "wof:placetype":"venue"
},
  "geometry": {"coordinates":[-76.458074,37.111252],"type":"Point"}
}