{
  "type": "Feature",
  "properties": {
    "addr:full":"7923 Freehollow Dr Falls Church VA 22042",
    "addr:housenumber":"7923",
    "addr:postcode":"22042",
    "addr:street":"Freehollow Dr",
    "iso:country":"US",
    "sg:address":"7923 Freehollow Dr",
    "sg:city":"Falls Church",
    "sg:classifiers":[
        {
            "category":"Professional",
            "type":"Services"
        }
    ],
    "sg:phone":"+1 703 698 1747",
    "sg:postcode":"22042",
    "sg:province":"VA",
    "wof:name":"Quang Vinh",
    "wof:placetype":"venue"
},
  "geometry": {"coordinates":[-77.21794199999999,38.856936],"type":"Point"}
}