{
  "type": "Feature",
  "properties": {
    "addr:full":"6023 Creek Stone Ln Centreville VA 20120",
    "addr:housenumber":"6023",
    "addr:postcode":"20120",
    "addr:street":"Creek Stone Ln",
    "iso:country":"US",
    "sg:address":"6023 Creek Stone Ln",
    "sg:city":"Centreville",
    "sg:classifiers":[
        {
            "category":"Building & Trades",
            "subcategory":"Construction",
            "type":"Services"
        }
    ],
    "sg:phone":"+1 703 815 6474",
    "sg:postcode":"20120",
    "sg:province":"VA",
    "sg:tags":[
        "resurfacing",
        "laying",
        "refinishing",
        "floor"
    ],
    "wof:name":"Sunny's Flooring",
    "wof:placetype":"venue"
},
  "geometry": {"coordinates":[-77.454539,38.840579],"type":"Point"}
}