{
  "type": "Feature",
  "properties": {
    "addr:full":"8901 Swift Creek Rd Fairfax Station VA 22039",
    "addr:housenumber":"8901",
    "addr:postcode":"22039",
    "addr:street":"Swift Creek Rd",
    "iso:country":"US",
    "sg:address":"8901 Swift Creek Rd",
    "sg:city":"Fairfax Station",
    "sg:classifiers":[
        {
            "category":"Home & Garden",
            "subcategory":"Building Materials",
            "type":"Retail Goods"
        }
    ],
    "sg:phone":"+1 703 690 6575",
    "sg:postcode":"22039",
    "sg:province":"VA",
    "wof:name":"Kellys Unique Glass",
    "wof:placetype":"venue"
},
  "geometry": {"coordinates":[-77.289056,38.713705],"type":"Point"}
}