{
  "type": "Feature",
  "properties": {
    "addr:full":"4399 Ironbound Rd Williamsburg VA 23188",
    "addr:housenumber":"4399",
    "addr:postcode":"23188",
    "addr:street":"Ironbound Rd",
    "iso:country":"US",
    "sg:address":"4399 Ironbound Rd",
    "sg:city":"Williamsburg",
    "sg:classifiers":[
        {
            "category":"Manufacturing",
            "subcategory":"Printing",
            "type":"Manufacturing & Wholesale Goods"
        }
    ],
    "sg:phone":"+1 757 220 3299",
    "sg:postcode":"23188",
    "sg:province":"VA",
    "sg:tags":[
        "print",
        "lithographic",
        "typesetting"
    ],
    "wof:name":"KWIK KOPY Printing",
    "wof:placetype":"venue"
},
  "geometry": {"coordinates":[-76.73616800000001,37.282993],"type":"Point"}
}