{
  "type": "Feature",
  "properties": {
    "addr:full":"8240 Treherneville Dr Birdsnest VA 23307",
    "addr:housenumber":"8240",
    "addr:postcode":"23307",
    "addr:street":"Treherneville Dr",
    "iso:country":"US",
    "sg:address":"8240 Treherneville Dr",
    "sg:city":"Birdsnest",
    "sg:classifiers":[
        {
            "category":"Organizations",
            "subcategory":"Religious Organization",
            "type":"Services"
        }
    ],
    "sg:phone":"+1 757 678 7600",
    "sg:postcode":"23307",
    "sg:province":"VA",
    "sg:tags":[
        "church"
    ],
    "wof:name":"New Mission United Meth Chr",
    "wof:placetype":"venue"
},
  "geometry": {"coordinates":[-75.89187800000001,37.427531],"type":"Point"}
}