{
  "type": "Feature",
  "properties": {
    "addr:full":"316 N Great Neck Rd Virginia Beach VA 23454",
    "addr:housenumber":"316",
    "addr:postcode":"23454",
    "addr:street":"N Great Neck Rd",
    "iso:country":"US",
    "sg:address":"316 N Great Neck Rd",
    "sg:city":"Virginia Beach",
    "sg:classifiers":[
        {
            "category":"Restaurant",
            "type":"Food & Drink"
        }
    ],
    "sg:phone":"+1 757 486 0345",
    "sg:postcode":"23454",
    "sg:province":"VA",
    "wof:name":"Hardee's",
    "wof:placetype":"venue"
},
  "geometry": {"coordinates":[-76.04773400000001,36.843146],"type":"Point"}
}