{
  "type": "Feature",
  "properties": {
    "addr:full":"8829 Lake Hill Dr Lorton VA 22079",
    "addr:housenumber":"8829",
    "addr:postcode":"22079",
    "addr:street":"Lake Hill Dr",
    "iso:country":"US",
    "sg:address":"8829 Lake Hill Dr",
    "sg:city":"Lorton",
    "sg:classifiers":[
        {
            "category":"Restaurant",
            "type":"Food & Drink"
        },
        {
            "category":"Retail",
            "subcategory":"Repair Shop",
            "type":"Services"
        },
        {
            "category":"Wholesale",
            "subcategory":"Machinery & Supplies",
            "type":"Manufacturing & Wholesale Goods"
        },
        {
            "category":"Building & Trades",
            "subcategory":"Construction",
            "type":"Services"
        }
    ],
    "sg:phone":"+1 703 690 1021",
    "sg:postcode":"22079",
    "sg:province":"VA",
    "sg:tags":[
        "equipment-commercial",
        "specialty",
        "equipment",
        "heating",
        "system",
        "supplies-refrigeration",
        "industrial",
        "refrigeration",
        "air conditioning",
        "contractor",
        "freezers-repair",
        "refrigerator"
    ],
    "wof:name":"Landers Airconditioning & Heating, Inc",
    "wof:placetype":"venue"
},
  "geometry": {"coordinates":[-77.27288799999999,38.715],"type":"Point"}
}