{
  "type": "Feature",
  "properties": {
    "addr:full":"999 Aylor Rd Stephens City VA 22655",
    "addr:housenumber":"999",
    "addr:postcode":"22655",
    "addr:street":"Aylor Rd",
    "iso:country":"US",
    "sg:address":"999 Aylor Rd",
    "sg:city":"Stephens City",
    "sg:classifiers":[
        {
            "category":"Food & Beverages",
            "subcategory":"Groceries & Convenience Stores",
            "type":"Retail Goods"
        }
    ],
    "sg:phone":"+1 540 869 6170",
    "sg:postcode":"22655",
    "sg:province":"VA",
    "wof:name":"7-Eleven",
    "wof:placetype":"venue"
},
  "geometry": {"coordinates":[-78.211073,39.085482],"type":"Point"}
}