{
  "type": "Feature",
  "properties": {
    "iso:country":"US",
    "sg:address":"25 White Pine St",
    "sg:city":"Scottsville",
    "sg:classifiers":[
        {
            "category":"Utilities",
            "subcategory":"Water",
            "type":"Services"
        }
    ],
    "sg:phone":"+1 434 286 4957",
    "sg:postcode":"24590",
    "sg:province":"VA",
    "sg:tags":[
        "supply"
    ],
    "wof:name":"Gadient Enterprises",
    "wof:placetype":"venue"
},
  "geometry": {"coordinates":[-78.499521,37.80932],"type":"Point"}
}