{
  "type": "Feature",
  "properties": {
    "addr:full":"150 W Main St Norfolk VA 23510",
    "addr:housenumber":"150",
    "addr:postcode":"23510",
    "addr:street":"W Main St",
    "iso:country":"US",
    "sg:address":"150 W Main St",
    "sg:city":"Norfolk",
    "sg:classifiers":[
        {
            "category":"Real Estate",
            "subcategory":"Developer",
            "type":"Services"
        }
    ],
    "sg:phone":"+1 757 490 3300",
    "sg:postcode":"23510",
    "sg:province":"VA",
    "sg:tags":[
        "leasing",
        "management",
        "co",
        "sales"
    ],
    "wof:name":"CB Richard Ellis Building Svcs",
    "wof:placetype":"venue"
},
  "geometry": {"coordinates":[-76.293667,36.846862],"type":"Point"}
}