{
  "type": "Feature",
  "properties": {
    "addr:full":"10530 Rosehaven St Fairfax VA 22030",
    "addr:housenumber":"10530",
    "addr:postcode":"22030",
    "addr:street":"Rosehaven St",
    "iso:country":"US",
    "sg:address":"10530 Rosehaven St",
    "sg:city":"Fairfax",
    "sg:classifiers":[
        {
            "category":"Professional",
            "subcategory":"Management & Consulting",
            "type":"Services"
        }
    ],
    "sg:phone":"+1 703 383 1550",
    "sg:postcode":"22030",
    "sg:province":"VA",
    "wof:name":"Bdr",
    "wof:placetype":"venue"
},
  "geometry": {"coordinates":[-77.309563,38.872355],"type":"Point"}
}