{
  "type": "Feature",
  "properties": {
    "addr:full":"6637 Belfield Rd La Crosse VA 23950",
    "addr:housenumber":"6637",
    "addr:postcode":"23950",
    "addr:street":"Belfield Rd",
    "iso:country":"US",
    "sg:address":"6637 Belfield Rd",
    "sg:city":"La Crosse",
    "sg:classifiers":[
        {
            "category":"Professional",
            "type":"Services"
        }
    ],
    "sg:phone":"+1 434 636 5220",
    "sg:postcode":"23950",
    "sg:province":"VA",
    "sg:tags":[
        "establishment"
    ],
    "wof:name":"Divers Processing Co Inc",
    "wof:placetype":"venue"
},
  "geometry": {"coordinates":[-78.122028,36.668101],"type":"Point"}
}