{
  "type": "Feature",
  "properties": {
    "iso:country":"US",
    "sg:address":"501 College St",
    "sg:city":"Narrows",
    "sg:classifiers":[
        {
            "category":"Organizations",
            "subcategory":"Religious Organization",
            "type":"Services"
        }
    ],
    "sg:phone":"+1 540 726 2399",
    "sg:postcode":"24124",
    "sg:province":"VA",
    "sg:tags":[
        "clergy"
    ],
    "wof:name":"Don Keith Clements",
    "wof:placetype":"venue"
},
  "geometry": {"coordinates":[-80.810198,37.325756],"type":"Point"}
}