{
  "type": "Feature",
  "properties": {
    "addr:full":"2205 Hunters Wood Way Virginia Beach VA 23454",
    "addr:housenumber":"2205",
    "addr:postcode":"23454",
    "addr:street":"Hunters Wood Way",
    "iso:country":"US",
    "sg:address":"2205 Hunters Wood Way",
    "sg:city":"Virginia Beach",
    "sg:classifiers":[
        {
            "category":"Professional",
            "type":"Services"
        }
    ],
    "sg:phone":"+1 757 496 3698",
    "sg:postcode":"23454",
    "sg:province":"VA",
    "wof:name":"Kim & Seo Corp",
    "wof:placetype":"venue"
},
  "geometry": {"coordinates":[-76.04384400000001,36.869571],"type":"Point"}
}