{
  "type": "Feature",
  "properties": {
    "addr:full":"1809 Hollindale Dr Alexandria VA 22306",
    "addr:housenumber":"1809",
    "addr:postcode":"22306",
    "addr:street":"Hollindale Dr",
    "iso:country":"US",
    "sg:address":"1809 Hollindale Dr",
    "sg:city":"Alexandria",
    "sg:classifiers":[
        {
            "category":"Professional",
            "type":"Services"
        },
        {
            "category":"Professional",
            "subcategory":"Management & Consulting",
            "type":"Services"
        }
    ],
    "sg:phone":"+1 703 765 8458",
    "sg:postcode":"22306",
    "sg:province":"VA",
    "sg:tags":[
        "establishment",
        "business"
    ],
    "wof:name":"Vaughan Associate Inc",
    "wof:placetype":"venue"
},
  "geometry": {"coordinates":[-77.062381,38.752147],"type":"Point"}
}