{
  "type": "Feature",
  "properties": {
    "addr:full":"3908 Laro Ct Fairfax VA 22031",
    "addr:housenumber":"3908",
    "addr:postcode":"22031",
    "addr:street":"Laro Ct",
    "iso:country":"US",
    "sg:address":"3908 Laro Ct",
    "sg:city":"Fairfax",
    "sg:classifiers":[
        {
            "category":"Organizations",
            "subcategory":"Religious Organization",
            "type":"Services"
        }
    ],
    "sg:phone":"+1 703 425 3494",
    "sg:postcode":"22031",
    "sg:province":"VA",
    "wof:name":"Le LLC Cong Van",
    "wof:placetype":"venue"
},
  "geometry": {"coordinates":[-77.25039099999999,38.840784],"type":"Point"}
}