{
  "type": "Feature",
  "properties": {
    "iso:country":"US",
    "sg:address":"2206 Mountain Rd",
    "sg:city":"Glen Allen",
    "sg:classifiers":[
        {
            "category":"Education",
            "subcategory":"School",
            "type":"Public Place"
        }
    ],
    "sg:phone":"+1 804 261 5090",
    "sg:postcode":"23060",
    "sg:province":"VA",
    "wof:name":"Virginia Randolph Special Ed",
    "wof:placetype":"venue"
},
  "geometry": {"coordinates":[-77.483462,37.661732],"type":"Point"}
}