{
  "type": "Feature",
  "properties": {
    "addr:full":"2965 Colonnade Drive, SW Colonnade Corporate Center, Suite 200 Roanoke VA 24018",
    "addr:housenumber":"2965;suite 200",
    "addr:postcode":"24018",
    "addr:street":"Colonnade Drive Sw",
    "iso:country":"US",
    "sg:address":"2965 Colonnade Drive, SW Colonnade Corporate Center, Suite 200",
    "sg:city":"Roanoke",
    "sg:classifiers":[
        {
            "category":"Professional",
            "subcategory":"Computer Services",
            "type":"Services"
        }
    ],
    "sg:phone":"+1 540 345 1716",
    "sg:postcode":"24018",
    "sg:province":"VA",
    "wof:name":"ProVox Technologies",
    "wof:placetype":"venue"
},
  "geometry": {"coordinates":[-80.01671899999999,37.233839],"type":"Point"}
}