{
  "type": "Feature",
  "properties": {
    "addr:full":"1616 Enoch Creek Rd Moneta VA 24121",
    "addr:housenumber":"1616",
    "addr:postcode":"24121",
    "addr:street":"Enoch Creek Rd",
    "iso:country":"US",
    "sg:address":"1616 Enoch Creek Rd",
    "sg:city":"Moneta",
    "sg:classifiers":[
        {
            "category":"Health Services",
            "subcategory":"Doctor",
            "type":"Services"
        }
    ],
    "sg:phone":"+1 540 297 1102",
    "sg:postcode":"24121",
    "sg:province":"VA",
    "sg:tags":[
        "physician",
        "surgeon"
    ],
    "wof:name":"Robert Chri Barksdale MD",
    "wof:placetype":"venue"
},
  "geometry": {"coordinates":[-79.6464,37.278681],"type":"Point"}
}