{
  "type": "Feature",
  "properties": {
    "iso:country":"US",
    "sg:address":"593 Madison Rd",
    "sg:city":"Culpeper",
    "sg:classifiers":[
        {
            "category":"Retail",
            "subcategory":"Laundry & Dry Cleaning",
            "type":"Services"
        }
    ],
    "sg:phone":"+1 540 825 2892",
    "sg:postcode":"22701",
    "sg:province":"VA",
    "sg:tags":[
        "drycleaning",
        "plant",
        "power",
        "cleaners"
    ],
    "wof:name":"Culpeper Cleaners Inc",
    "wof:placetype":"venue"
},
  "geometry": {"coordinates":[-78.013246,38.458971],"type":"Point"}
}