{
  "type": "Feature",
  "properties": {
    "iso:country":"US",
    "sg:address":"13346 Rollingwood Ln",
    "sg:city":"Montpelier",
    "sg:classifiers":[
        {
            "category":"Wholesale",
            "subcategory":"Groceries",
            "type":"Manufacturing & Wholesale Goods"
        }
    ],
    "sg:phone":"+1 804 883 7514",
    "sg:postcode":"23192",
    "sg:province":"VA",
    "wof:name":"Van Dusen Distributing Inc",
    "wof:placetype":"venue"
},
  "geometry": {"coordinates":[-77.677296,37.775658],"type":"Point"}
}