{
  "type": "Feature",
  "properties": {
    "addr:full":"4716 Valencia Pl Chesterfield VA 23832",
    "addr:housenumber":"4716",
    "addr:postcode":"23832",
    "addr:street":"Valencia Pl",
    "iso:country":"US",
    "sg:address":"4716 Valencia Pl",
    "sg:city":"Chesterfield",
    "sg:classifiers":[
        {
            "category":"Building & Trades",
            "subcategory":"Construction",
            "type":"Services"
        }
    ],
    "sg:phone":"+1 804 744 0045",
    "sg:postcode":"23832",
    "sg:province":"VA",
    "sg:tags":[
        "hanging",
        "contractor"
    ],
    "wof:name":"Gardner Painting Inc",
    "wof:placetype":"venue"
},
  "geometry": {"coordinates":[-77.537384,37.443027],"type":"Point"}
}