{
  "type": "Feature",
  "properties": {
    "iso:country":"US",
    "sg:address":"1300 Wilson Blvd Ste 400",
    "sg:city":"Arlington",
    "sg:classifiers":[
        {
            "category":"Real Estate",
            "subcategory":"Real Estate Services",
            "type":"Services"
        }
    ],
    "sg:phone":"+1 703 526 5000",
    "sg:postcode":"22209",
    "sg:province":"VA",
    "sg:tags":[
        "management",
        "property"
    ],
    "wof:name":"Mills Corporation",
    "wof:placetype":"venue"
},
  "geometry": {"coordinates":[-77.073097,38.894798],"type":"Point"}
}