{
  "type": "Feature",
  "properties": {
    "addr:full":"15 W Washington St Middleburg VA 20117",
    "addr:housenumber":"15",
    "addr:postcode":"20117",
    "addr:street":"W Washington St",
    "iso:country":"US",
    "sg:address":"15 W Washington St",
    "sg:city":"Middleburg",
    "sg:classifiers":[
        {
            "category":"Social Services",
            "subcategory":"Child Care",
            "type":"Services"
        }
    ],
    "sg:phone":"+1 540 687 5622",
    "sg:postcode":"20117",
    "sg:province":"VA",
    "sg:tags":[
        "kindergarten",
        "academic",
        "school"
    ],
    "wof:name":"Friends At Parrish House Nrsry",
    "wof:placetype":"venue"
},
  "geometry": {"coordinates":[-77.73654000000001,38.968523],"type":"Point"}
}