{
  "type": "Feature",
  "properties": {
    "addr:full":"408 Marion St Winchester VA 22601",
    "addr:housenumber":"408",
    "addr:postcode":"22601",
    "addr:street":"Marion St",
    "iso:country":"US",
    "sg:address":"408 Marion St",
    "sg:city":"Winchester",
    "sg:classifiers":[
        {
            "category":"Professional",
            "subcategory":"Business Services",
            "type":"Services"
        }
    ],
    "sg:phone":"+1 540 667 0761",
    "sg:postcode":"22601",
    "sg:province":"VA",
    "wof:name":"Lawrence Design",
    "wof:placetype":"venue"
},
  "geometry": {"coordinates":[-78.177402,39.195903],"type":"Point"}
}