{
  "type": "Feature",
  "properties": {
    "addr:full":"1865 Bob White Blvd Pulaski VA 24301",
    "addr:housenumber":"1865",
    "addr:postcode":"24301",
    "addr:street":"Bob White Blvd",
    "iso:country":"US",
    "sg:address":"1865 Bob White Blvd",
    "sg:city":"Pulaski",
    "sg:classifiers":[
        {
            "category":"Retail",
            "subcategory":"Car Wash",
            "type":"Services"
        },
        {
            "category":"Building & Trades",
            "subcategory":"Construction",
            "type":"Services"
        }
    ],
    "sg:phone":"+1 540 980 0246",
    "sg:postcode":"24301",
    "sg:province":"VA",
    "sg:tags":[
        "carwash",
        "restoration",
        "cleaning",
        "patio",
        "deck"
    ],
    "wof:name":"D M's Laser Wash",
    "wof:placetype":"venue"
},
  "geometry": {"coordinates":[-80.74386800000001,37.059159],"type":"Point"}
}