{
  "type": "Feature",
  "properties": {
    "addr:full":"4700 Monument Ave Richmond VA 23230",
    "addr:housenumber":"4700",
    "addr:postcode":"23230",
    "addr:street":"Monument Ave",
    "iso:country":"US",
    "sg:address":"4700 Monument Ave",
    "sg:city":"Richmond",
    "sg:classifiers":[
        {
            "category":"Organizations",
            "subcategory":"Religious Organization",
            "type":"Services"
        }
    ],
    "sg:phone":"+1 804 358 6393",
    "sg:postcode":"23230",
    "sg:province":"VA",
    "wof:name":"James E Temple Dr",
    "wof:placetype":"venue"
},
  "geometry": {"coordinates":[-77.49636099999999,37.575604],"type":"Point"}
}