{
  "type": "Feature",
  "properties": {
    "iso:country":"US",
    "sg:address":"4846 Virginia Beach Blvd",
    "sg:city":"Virginia Beach",
    "sg:classifiers":[
        {
            "category":"Professional",
            "subcategory":"Computer Services",
            "type":"Services"
        }
    ],
    "sg:phone":"+1 757 499 4070",
    "sg:postcode":"23462",
    "sg:province":"VA",
    "sg:tags":[
        "home",
        "consulting",
        "page",
        "dev",
        "internet"
    ],
    "wof:name":"Y2k Web Technologies LLC",
    "wof:placetype":"venue"
},
  "geometry": {"coordinates":[-76.143969,36.843855],"type":"Point"}
}