{
  "type": "Feature",
  "properties": {
    "iso:country":"US",
    "sg:address":"324 N Fairfax St",
    "sg:city":"Alexandria",
    "sg:classifiers":[
        {
            "category":"Personal",
            "type":"Services"
        }
    ],
    "sg:phone":"+1 703 299 4422",
    "sg:postcode":"22314",
    "sg:province":"VA",
    "sg:tags":[
        "bureau"
    ],
    "sg:website":"www.vipdesk.com",
    "wof:name":"VIPDESK.COM",
    "wof:placetype":"venue"
},
  "geometry": {"coordinates":[-77.042045,38.807127],"type":"Point"}
}