{
  "type": "Feature",
  "properties": {
    "addr:full":"1100 S Hayes St Arlington VA 22202",
    "addr:housenumber":"1100",
    "addr:postcode":"22202",
    "addr:street":"S Hayes St",
    "iso:country":"US",
    "sg:address":"1100 S Hayes St",
    "sg:city":"Arlington",
    "sg:classifiers":[
        {
            "category":"Personal",
            "subcategory":"Barber",
            "type":"Services"
        }
    ],
    "sg:phone":"+1 703 415 2040",
    "sg:postcode":"22202",
    "sg:province":"VA",
    "wof:name":"Creative Hairdressers",
    "wof:placetype":"venue"
},
  "geometry": {"coordinates":[-77.0596,38.863547],"type":"Point"}
}