{
  "type": "Feature",
  "properties": {
    "addr:full":"3893 Jefferson Davis Hwy Stafford VA 22554",
    "addr:housenumber":"3893",
    "addr:postcode":"22554",
    "addr:street":"Jefferson Davis Hwy",
    "iso:country":"US",
    "sg:address":"3893 Jefferson Davis Hwy",
    "sg:city":"Stafford",
    "sg:classifiers":[
        {
            "category":"Autos & Motor Vehicles",
            "subcategory":"Automobile Sales",
            "type":"Retail Goods"
        }
    ],
    "sg:phone":"+1 703 445 1100",
    "sg:postcode":"22554",
    "sg:province":"VA",
    "sg:tags":[
        "used"
    ],
    "wof:name":"Guarantee Automaxx Inc",
    "wof:placetype":"venue"
},
  "geometry": {"coordinates":[-77.371353,38.508215],"type":"Point"}
}