{
  "type": "Feature",
  "properties": {
    "iso:country":"US",
    "sg:address":"442 Rutherford Ave NE",
    "sg:city":"Roanoke",
    "sg:classifiers":[
        {
            "category":"Professional",
            "type":"Services"
        }
    ],
    "sg:phone":"+1 540 981 9055",
    "sg:postcode":"24016",
    "sg:province":"VA",
    "sg:tags":[
        "establishment"
    ],
    "wof:name":"CES",
    "wof:placetype":"venue"
},
  "geometry": {"coordinates":[-79.933345,37.278606],"type":"Point"}
}