{
  "type": "Feature",
  "properties": {
    "addr:full":"1124 First Colonial Rd Virginia Beach VA 23454",
    "addr:housenumber":"1124",
    "addr:postcode":"23454",
    "addr:street":"First Colonial Rd",
    "iso:country":"US",
    "sg:address":"1124 First Colonial Rd",
    "sg:city":"Virginia Beach",
    "sg:classifiers":[
        {
            "category":"Banks & Credit Unions",
            "subcategory":"Bank",
            "type":"Services"
        }
    ],
    "sg:phone":"+1 757 446 6940",
    "sg:postcode":"23454",
    "sg:province":"VA",
    "sg:tags":[
        "state",
        "commercial"
    ],
    "wof:name":"Bank of Commonwealth",
    "wof:placetype":"venue"
},
  "geometry": {"coordinates":[-76.029231,36.866191],"type":"Point"}
}