{
  "type": "Feature",
  "properties": {
    "iso:country":"US",
    "sg:address":"1655 Jefferson Hwy",
    "sg:city":"Fishersville",
    "sg:classifiers":[
        {
            "category":"Banks & Credit Unions",
            "subcategory":"Investment Brokerage",
            "type":"Services"
        }
    ],
    "sg:phone":"+1 540 932 2332",
    "sg:postcode":"22939",
    "sg:province":"VA",
    "sg:tags":[
        "consultant",
        "planning",
        "financial"
    ],
    "wof:name":"American Express Financial Adv",
    "wof:placetype":"venue"
},
  "geometry": {"coordinates":[-78.983996,38.106656],"type":"Point"}
}