{
  "type": "Feature",
  "properties": {
    "addr:full":"1125 Alverser Dr Midlothian VA 23113",
    "addr:housenumber":"1125",
    "addr:postcode":"23113",
    "addr:street":"Alverser Dr",
    "iso:country":"US",
    "sg:address":"1125 Alverser Dr",
    "sg:city":"Midlothian",
    "sg:classifiers":[
        {
            "category":"Shopping",
            "subcategory":"Musical Instruments",
            "type":"Retail Goods"
        }
    ],
    "sg:phone":"+1 804 378 3761",
    "sg:postcode":"23113",
    "sg:province":"VA",
    "wof:name":"Virginia Harp Ctr",
    "wof:placetype":"venue"
},
  "geometry": {"coordinates":[-77.617771,37.50667],"type":"Point"}
}