{
  "type": "Feature",
  "properties": {
    "addr:full":"219 Water St E Charlottesville VA 22902",
    "addr:housenumber":"219",
    "addr:postcode":"22902",
    "addr:street":"Water St E",
    "iso:country":"US",
    "sg:address":"219 Water St E",
    "sg:city":"Charlottesville",
    "sg:classifiers":[
        {
            "category":"Recreation",
            "type":"Entertainment"
        }
    ],
    "sg:phone":"+1 434 817 2400",
    "sg:postcode":"22902",
    "sg:province":"VA",
    "sg:tags":[
        "skating",
        "rink"
    ],
    "sg:website":"www.icepark.com",
    "wof:name":"Water Street Terrace",
    "wof:placetype":"venue"
},
  "geometry": {"coordinates":[-78.48043800000001,38.029679],"type":"Point"}
}