{
  "type": "Feature",
  "properties": {
    "addr:full":"44269 Ginghamsburg Pl Ashburn VA 20147",
    "addr:postcode":"44269;20147",
    "addr:street":"Ginghamsburg Pl",
    "iso:country":"US",
    "sg:address":"44269 Ginghamsburg Pl",
    "sg:city":"Ashburn",
    "sg:classifiers":[
        {
            "category":"Food & Beverages",
            "subcategory":"Candy",
            "type":"Retail Goods"
        }
    ],
    "sg:phone":"+1 703 481 3465",
    "sg:postcode":"20147",
    "sg:province":"VA",
    "sg:tags":[
        "confectionery"
    ],
    "wof:name":"Eads",
    "wof:placetype":"venue"
},
  "geometry": {"coordinates":[-77.469655,39.041983],"type":"Point"}
}