{
  "type": "Feature",
  "properties": {
    "addr:full":"1302 Tanner Town Rd Brodnax VA 23920",
    "addr:housenumber":"1302",
    "addr:postcode":"23920",
    "addr:street":"Tanner Town Rd",
    "iso:country":"US",
    "sg:address":"1302 Tanner Town Rd",
    "sg:city":"Brodnax",
    "sg:classifiers":[
        {
            "category":"Professional",
            "subcategory":"Management & Consulting",
            "type":"Services"
        }
    ],
    "sg:phone":"+1 434 729 2523",
    "sg:postcode":"23920",
    "sg:province":"VA",
    "wof:name":"Harris Construcktion",
    "wof:placetype":"venue"
},
  "geometry": {"coordinates":[-78.015693,36.723895],"type":"Point"}
}