{
  "type": "Feature",
  "properties": {
    "iso:country":"US",
    "sg:address":"8130 Boone Blvd",
    "sg:city":"Vienna",
    "sg:classifiers":[
        {
            "category":"Utilities",
            "subcategory":"Mobile Phone",
            "type":"Services"
        }
    ],
    "sg:phone":"+1 703 848 3588",
    "sg:postcode":"22182",
    "sg:province":"VA",
    "sg:tags":[
        "wireless",
        "location",
        "provider"
    ],
    "wof:name":"Trueposition Inc",
    "wof:placetype":"venue"
},
  "geometry": {"coordinates":[-77.225719,38.913074],"type":"Point"}
}