{
  "type": "Feature",
  "properties": {
    "addr:full":"8803 Sudley Rd Manassas VA 20110",
    "addr:housenumber":"8803",
    "addr:postcode":"20110",
    "addr:street":"Sudley Rd",
    "iso:country":"US",
    "sg:address":"8803 Sudley Rd",
    "sg:city":"Manassas",
    "sg:classifiers":[
        {
            "category":"Banks & Credit Unions",
            "subcategory":"Bank",
            "type":"Services"
        }
    ],
    "sg:phone":"+1 703 497 1860",
    "sg:postcode":"20110",
    "sg:province":"VA",
    "sg:tags":[
        "federal",
        "savings",
        "institution"
    ],
    "wof:name":"Washington Mutual Bank",
    "wof:placetype":"venue"
},
  "geometry": {"coordinates":[-77.48185599999999,38.765535],"type":"Point"}
}