{
  "type": "Feature",
  "properties": {
    "iso:country":"US",
    "sg:address":"208 Hemlock Rd",
    "sg:city":"Bristol",
    "sg:classifiers":[
        {
            "category":"Real Estate",
            "subcategory":"Real Estate Agent",
            "type":"Services"
        }
    ],
    "sg:phone":"+1 423 968 3246",
    "sg:postcode":"37620",
    "sg:province":"VA",
    "wof:name":"Gott Rental Properties LLP",
    "wof:placetype":"venue"
},
  "geometry": {"coordinates":[-82.21873600000001,36.555325],"type":"Point"}
}