{
  "type": "Feature",
  "properties": {
    "addr:full":"128 Reedy Creek Rd Abingdon VA 24210",
    "addr:housenumber":"128",
    "addr:postcode":"24210",
    "addr:street":"Reedy Creek Rd",
    "iso:country":"US",
    "sg:address":"128 Reedy Creek Rd",
    "sg:city":"Abingdon",
    "sg:classifiers":[
        {
            "category":"Professional",
            "subcategory":"Art Services",
            "type":"Services"
        }
    ],
    "sg:phone":"+1 276 628 7127",
    "sg:postcode":"24210",
    "sg:province":"VA",
    "sg:tags":[
        "graphic",
        "designer"
    ],
    "wof:name":"Graphix Solutions",
    "wof:placetype":"venue"
},
  "geometry": {"coordinates":[-81.999088,36.705456],"type":"Point"}
}