{
  "type": "Feature",
  "properties": {
    "iso:country":"US",
    "sg:address":"12310 Washington Hwy",
    "sg:city":"Ashland",
    "sg:classifiers":[
        {
            "category":"Government",
            "subcategory":"Office",
            "type":"Public Place"
        }
    ],
    "sg:phone":"+1 804 752 4300",
    "sg:postcode":"23005",
    "sg:province":"VA",
    "wof:name":"Hanover County Community Rsrcs",
    "wof:placetype":"venue"
},
  "geometry": {"coordinates":[-77.471174,37.743672],"type":"Point"}
}