{
  "type": "Feature",
  "properties": {
    "iso:country":"US",
    "sg:address":"1600 International Dr",
    "sg:city":"Mc Lean",
    "sg:classifiers":[
        {
            "category":"Professional",
            "subcategory":"Management & Consulting",
            "type":"Services"
        }
    ],
    "sg:phone":"+1 703 827 5422",
    "sg:postcode":"22102",
    "sg:province":"VA",
    "sg:tags":[
        "fuel"
    ],
    "wof:name":"Quadrangle Management",
    "wof:placetype":"venue"
},
  "geometry": {"coordinates":[-77.22815199999999,38.924737],"type":"Point"}
}