{
  "type": "Feature",
  "properties": {
    "addr:full":"1305 Todds Ln Hampton VA 23666",
    "addr:housenumber":"1305",
    "addr:postcode":"23666",
    "addr:street":"Todds Ln",
    "iso:country":"US",
    "sg:address":"1305 Todds Ln",
    "sg:city":"Hampton",
    "sg:classifiers":[
        {
            "category":"Food & Beverages",
            "subcategory":"Groceries & Convenience Stores",
            "type":"Retail Goods"
        }
    ],
    "sg:phone":"+1 757 826 9040",
    "sg:postcode":"23666",
    "sg:province":"VA",
    "wof:name":"7-Eleven",
    "wof:placetype":"venue"
},
  "geometry": {"coordinates":[-76.427272,37.042313],"type":"Point"}
}