{
  "type": "Feature",
  "properties": {
    "addr:full":"205 Research Dr Chesapeake VA 23320",
    "addr:housenumber":"205",
    "addr:postcode":"23320",
    "addr:street":"Research Dr",
    "iso:country":"US",
    "sg:address":"205 Research Dr",
    "sg:city":"Chesapeake",
    "sg:classifiers":[
        {
            "category":"Travel",
            "subcategory":"Travel Agent",
            "type":"Entertainment"
        }
    ],
    "sg:phone":"+1 757 547 8600",
    "sg:postcode":"23320",
    "sg:province":"VA",
    "sg:tags":[
        "agency"
    ],
    "wof:name":"Design Temperature",
    "wof:placetype":"venue"
},
  "geometry": {"coordinates":[-76.25891,36.772462],"type":"Point"}
}