{
  "type": "Feature",
  "properties": {
    "addr:full":"215 E Main St Bedford VA 24523",
    "addr:housenumber":"215",
    "addr:postcode":"24523",
    "addr:street":"E Main St",
    "iso:country":"US",
    "sg:address":"215 E Main St",
    "sg:city":"Bedford",
    "sg:classifiers":[
        {
            "category":"Government",
            "subcategory":"Office",
            "type":"Public Place"
        }
    ],
    "sg:phone":"+1 540 587 6005",
    "sg:postcode":"24523",
    "sg:province":"VA",
    "sg:tags":[
        "city"
    ],
    "wof:name":"Bedford Mayor",
    "wof:placetype":"venue"
},
  "geometry": {"coordinates":[-79.522065,37.334119],"type":"Point"}
}