{
  "type": "Feature",
  "properties": {
    "addr:full":"1940 Cobblestone Ln Charlottesville VA 22901",
    "addr:housenumber":"1940",
    "addr:postcode":"22901",
    "addr:street":"Cobblestone Ln",
    "iso:country":"US",
    "sg:address":"1940 Cobblestone Ln",
    "sg:city":"Charlottesville",
    "sg:classifiers":[
        {
            "category":"Wholesale",
            "subcategory":"Machinery & Supplies",
            "type":"Manufacturing & Wholesale Goods"
        }
    ],
    "sg:phone":"+1 434 977 3333",
    "sg:postcode":"22901",
    "sg:province":"VA",
    "sg:tags":[
        "durable",
        "trade"
    ],
    "wof:name":"Seacurity Products Div Hmdc",
    "wof:placetype":"venue"
},
  "geometry": {"coordinates":[-78.5694,38.071573],"type":"Point"}
}