{
  "type": "Feature",
  "properties": {
    "iso:country":"US",
    "sg:address":"9112 Leesburg Pike",
    "sg:city":"Vienna",
    "sg:classifiers":[
        {
            "category":"Professional",
            "subcategory":"Business Services",
            "type":"Services"
        }
    ],
    "sg:phone":"+1 703 757 0355",
    "sg:postcode":"22182",
    "sg:province":"VA",
    "wof:name":"Business Sales Unlimited",
    "wof:placetype":"venue"
},
  "geometry": {"coordinates":[-77.261702,38.949539],"type":"Point"}
}