{
  "type": "Feature",
  "properties": {
    "addr:full":"1100 Lee Ave Fort Lee VA 23801",
    "addr:housenumber":"1100",
    "addr:postcode":"23801",
    "addr:street":"Lee Ave",
    "iso:country":"US",
    "sg:address":"1100 Lee Ave",
    "sg:city":"Fort Lee",
    "sg:classifiers":[
        {
            "category":"Recreation",
            "type":"Entertainment"
        }
    ],
    "sg:phone":"+1 804 765 2324",
    "sg:postcode":"23801",
    "sg:province":"VA",
    "sg:tags":[
        "club",
        "membership"
    ],
    "wof:name":"Regimental Club",
    "wof:placetype":"venue"
},
  "geometry": {"coordinates":[-77.34155699999999,37.237748],"type":"Point"}
}