{
  "type": "Feature",
  "properties": {
    "iso:country":"US",
    "sg:address":"11810 Sunrise Valley Dr",
    "sg:city":"Reston",
    "sg:classifiers":[
        {
            "category":"Travel",
            "subcategory":"Hotels & Motels",
            "type":"Entertainment"
        }
    ],
    "sg:phone":"+1 703 620 9000",
    "sg:postcode":"20191",
    "sg:province":"VA",
    "sg:website":"http://clk.atdmt.com/NYC/go/156347052/direct/01/",
    "wof:name":"Sheraton Reston Hotel",
    "wof:placetype":"venue"
},
  "geometry": {"coordinates":[-77.354291,38.949102],"type":"Point"}
}