{
  "type": "Feature",
  "properties": {
    "addr:full":"74 Mizpah Rd Locust Hill VA 23092",
    "addr:housenumber":"74",
    "addr:postcode":"23092",
    "addr:street":"Mizpah Rd",
    "iso:country":"US",
    "sg:address":"74 Mizpah Rd",
    "sg:city":"Locust Hill",
    "sg:classifiers":[
        {
            "category":"Health Services",
            "subcategory":"Nursing And Care Facility",
            "type":"Services"
        }
    ],
    "sg:phone":"+1 804 758 5260",
    "sg:postcode":"23092",
    "sg:province":"VA",
    "sg:tags":[
        "home",
        "skilled",
        "convalescent"
    ],
    "wof:name":"Mizpah Health Care Center",
    "wof:placetype":"venue"
},
  "geometry": {"coordinates":[-76.508151,37.608802],"type":"Point"}
}