{
  "type": "Feature",
  "properties": {
    "iso:country":"US",
    "sg:address":"10305 Balls Ford Rd",
    "sg:city":"Manassas",
    "sg:classifiers":[
        {
            "category":"Retail",
            "subcategory":"Storage",
            "type":"Services"
        }
    ],
    "sg:phone":"+1 703 361 8868",
    "sg:postcode":"20109",
    "sg:province":"VA",
    "sg:tags":[
        "self"
    ],
    "sg:website":"publicstorage.com",
    "wof:name":"Public Storage",
    "wof:placetype":"venue"
},
  "geometry": {"coordinates":[-77.504501,38.802898],"type":"Point"}
}