{
  "type": "Feature",
  "properties": {
    "addr:full":"1600 Huguenot Rd Midlothian VA 23113",
    "addr:housenumber":"1600",
    "addr:postcode":"23113",
    "addr:street":"Huguenot Rd",
    "iso:country":"US",
    "sg:address":"1600 Huguenot Rd",
    "sg:city":"Midlothian",
    "sg:classifiers":[
        {
            "category":"Social Services",
            "type":"Services"
        }
    ],
    "sg:phone":"+1 804 378 4367",
    "sg:postcode":"23113",
    "sg:province":"VA",
    "wof:name":"Mvc Family Counseling Ctr",
    "wof:placetype":"venue"
},
  "geometry": {"coordinates":[-77.615359,37.515158],"type":"Point"}
}