{
  "type": "Feature",
  "properties": {
    "iso:country":"US",
    "sg:address":"486 Westward Pike",
    "sg:city":"Clarksville",
    "sg:classifiers":[
        {
            "category":"Retail",
            "subcategory":"Laundry & Dry Cleaning",
            "type":"Services"
        }
    ],
    "sg:phone":"+1 434 252 8501",
    "sg:postcode":"23927",
    "sg:province":"VA",
    "wof:name":"New Wave Carpet Cleaning",
    "wof:placetype":"venue"
},
  "geometry": {"coordinates":[-78.42191200000001,36.556575],"type":"Point"}
}