{
  "type": "Feature",
  "properties": {
    "addr:full":"115 Charles Parish Dr Poquoson VA 23662",
    "addr:housenumber":"115",
    "addr:postcode":"23662",
    "addr:street":"Charles Parish Dr",
    "iso:country":"US",
    "sg:address":"115 Charles Parish Dr",
    "sg:city":"Poquoson",
    "sg:classifiers":[
        {
            "category":"Insurance",
            "subcategory":"Life Insurance",
            "type":"Services"
        }
    ],
    "sg:phone":"+1 757 868 6627",
    "sg:postcode":"23662",
    "sg:province":"VA",
    "sg:tags":[
        "carrier"
    ],
    "wof:name":"Independent Order Odd Fellows",
    "wof:placetype":"venue"
},
  "geometry": {"coordinates":[-76.395624,37.13329],"type":"Point"}
}