{
  "type": "Feature",
  "properties": {
    "addr:full":"7823 Yorktown Dr Alexandria VA 22308",
    "addr:housenumber":"7823",
    "addr:postcode":"22308",
    "addr:street":"Yorktown Dr",
    "iso:country":"US",
    "sg:address":"7823 Yorktown Dr",
    "sg:city":"Alexandria",
    "sg:classifiers":[
        {
            "category":"Museum",
            "type":"Entertainment"
        }
    ],
    "sg:phone":"+1 703 721 0321",
    "sg:postcode":"22308",
    "sg:province":"VA",
    "wof:name":"Museum One Inc",
    "wof:placetype":"venue"
},
  "geometry": {"coordinates":[-77.059296,38.744897],"type":"Point"}
}