{
  "type": "Feature",
  "properties": {
    "addr:full":"1505 Harlequin Ct Chesapeake VA 23321",
    "addr:housenumber":"1505",
    "addr:postcode":"23321",
    "addr:street":"Harlequin Ct",
    "iso:country":"US",
    "sg:address":"1505 Harlequin Ct",
    "sg:city":"Chesapeake",
    "sg:classifiers":[
        {
            "category":"Professional",
            "type":"Services"
        }
    ],
    "sg:phone":"+1 757 465 5230",
    "sg:postcode":"23321",
    "sg:province":"VA",
    "wof:name":"Merrill Ashcraft",
    "wof:placetype":"venue"
},
  "geometry": {"coordinates":[-76.442589,36.799622],"type":"Point"}
}