{
  "type": "Feature",
  "properties": {
    "iso:country":"US",
    "sg:address":"122 Rappahannock Trl",
    "sg:city":"Winchester",
    "sg:classifiers":[
        {
            "category":"Manufacturing",
            "subcategory":"Toys & Sporting Goods",
            "type":"Manufacturing & Wholesale Goods"
        }
    ],
    "sg:phone":"+1 540 877 1210",
    "sg:postcode":"22602",
    "sg:province":"VA",
    "sg:tags":[
        "mfg"
    ],
    "wof:name":"Angels Little",
    "wof:placetype":"venue"
},
  "geometry": {"coordinates":[-78.338922,39.18557],"type":"Point"}
}