{
  "type": "Feature",
  "properties": {
    "addr:full":"401 W Broadway Ave Hopewell VA 23860",
    "addr:housenumber":"401",
    "addr:postcode":"23860",
    "addr:street":"W Broadway Ave",
    "iso:country":"US",
    "sg:address":"401 W Broadway Ave",
    "sg:city":"Hopewell",
    "sg:classifiers":[
        {
            "category":"Education",
            "subcategory":"School",
            "type":"Public Place"
        }
    ],
    "sg:phone":"+1 804 452 3730",
    "sg:postcode":"23860",
    "sg:province":"VA",
    "sg:tags":[
        "academic",
        "special"
    ],
    "wof:name":"Lead Center",
    "wof:placetype":"venue"
},
  "geometry": {"coordinates":[-77.29108600000001,37.303644],"type":"Point"}
}