{
  "type": "Feature",
  "properties": {
    "addr:full":"7472 Academy Dr Mechanicsville VA 23116",
    "addr:housenumber":"7472",
    "addr:postcode":"23116",
    "addr:street":"Academy Dr",
    "iso:country":"US",
    "sg:address":"7472 Academy Dr",
    "sg:city":"Mechanicsville",
    "sg:classifiers":[
        {
            "category":"Building & Trades",
            "subcategory":"Construction",
            "type":"Services"
        }
    ],
    "sg:phone":"+1 804 746 4106",
    "sg:postcode":"23116",
    "sg:province":"VA",
    "sg:tags":[
        "house"
    ],
    "wof:name":"R J Joy Inc",
    "wof:placetype":"venue"
},
  "geometry": {"coordinates":[-77.37035,37.644856],"type":"Point"}
}