{
  "type": "Feature",
  "properties": {
    "addr:full":"1003 E Main St Radford VA 24141",
    "addr:housenumber":"1003",
    "addr:postcode":"24141",
    "addr:street":"E Main St",
    "iso:country":"US",
    "sg:address":"1003 E Main St",
    "sg:city":"Radford",
    "sg:classifiers":[
        {
            "category":"Restaurant",
            "type":"Food & Drink"
        }
    ],
    "sg:phone":"+1 540 633 1015",
    "sg:postcode":"24141",
    "sg:province":"VA",
    "wof:name":"Subway Sandwiches & Salads",
    "wof:placetype":"venue"
},
  "geometry": {"coordinates":[-80.553878,37.14107],"type":"Point"}
}