{
  "type": "Feature",
  "properties": {
    "addr:full":"55 Quarry Rd Stafford VA 22554",
    "addr:housenumber":"55",
    "addr:postcode":"22554",
    "addr:street":"Quarry Rd",
    "iso:country":"US",
    "sg:address":"55 Quarry Rd",
    "sg:city":"Stafford",
    "sg:classifiers":[
        {
            "category":"Building & Trades",
            "subcategory":"Plumbing",
            "type":"Services"
        }
    ],
    "sg:phone":"+1 540 659 7765",
    "sg:postcode":"22554",
    "sg:province":"VA",
    "sg:tags":[
        "contractor"
    ],
    "wof:name":"Boling Plumbing & Heating",
    "wof:placetype":"venue"
},
  "geometry": {"coordinates":[-77.349991,38.455901],"type":"Point"}
}