{
  "type": "Feature",
  "properties": {
    "addr:full":"8157 Staples Mill Rd Richmond VA 23228",
    "addr:housenumber":"8157",
    "addr:postcode":"23228",
    "addr:street":"Staples Mill Rd",
    "iso:country":"US",
    "sg:address":"8157 Staples Mill Rd",
    "sg:city":"Richmond",
    "sg:classifiers":[
        {
            "category":"Manufacturing",
            "subcategory":"Printing",
            "type":"Manufacturing & Wholesale Goods"
        }
    ],
    "sg:phone":"+1 804 627 0500",
    "sg:postcode":"23228",
    "sg:province":"VA",
    "sg:tags":[
        "print",
        "lithographic",
        "printer",
        "commercial"
    ],
    "wof:name":"Alpha Graphics",
    "wof:placetype":"venue"
},
  "geometry": {"coordinates":[-77.504119,37.625552],"type":"Point"}
}