{
  "type": "Feature",
  "properties": {
    "addr:full":"11720 Chapel Rd Clifton VA 20124",
    "addr:housenumber":"11720",
    "addr:postcode":"20124",
    "addr:street":"Chapel Rd",
    "iso:country":"US",
    "sg:address":"11720 Chapel Rd",
    "sg:city":"Clifton",
    "sg:classifiers":[
        {
            "category":"Professional",
            "subcategory":"Business Services",
            "type":"Services"
        }
    ],
    "sg:phone":"+1 703 250 9484",
    "sg:postcode":"20124",
    "sg:province":"VA",
    "wof:name":"Castro Home",
    "wof:placetype":"venue"
},
  "geometry": {"coordinates":[-77.349228,38.781431],"type":"Point"}
}