{
  "type": "Feature",
  "properties": {
    "addr:full":"8020 Towers Crescent Dr Vienna VA 22182",
    "addr:housenumber":"8020",
    "addr:postcode":"22182",
    "addr:street":"Towers Crescent Dr",
    "iso:country":"US",
    "sg:address":"8020 Towers Crescent Dr",
    "sg:city":"Vienna",
    "sg:classifiers":[
        {
            "category":"Professional",
            "subcategory":"Employment Agencies",
            "type":"Services"
        }
    ],
    "sg:phone":"+1 703 760 7662",
    "sg:postcode":"22182",
    "sg:province":"VA",
    "sg:tags":[
        "opportunity"
    ],
    "wof:name":"Accountemps",
    "wof:placetype":"venue"
},
  "geometry": {"coordinates":[-77.220232,38.914204],"type":"Point"}
}