{
  "type": "Feature",
  "properties": {
    "addr:full":"14535 John Marshall Hwy Gainesville VA 20155",
    "addr:housenumber":"14535",
    "addr:postcode":"20155",
    "addr:street":"John Marshall Hwy",
    "iso:country":"US",
    "sg:address":"14535 John Marshall Hwy",
    "sg:city":"Gainesville",
    "sg:classifiers":[
        {
            "category":"Organizations",
            "subcategory":"Religious Organization",
            "type":"Services"
        }
    ],
    "sg:phone":"+1 703 754 8444",
    "sg:postcode":"20155",
    "sg:province":"VA",
    "wof:name":"St Stephens Catholic Center",
    "wof:placetype":"venue"
},
  "geometry": {"coordinates":[-77.625822,38.80611],"type":"Point"}
}