{
  "type": "Feature",
  "properties": {
    "addr:full":"2316 Starfish Rd Virginia Beach VA 23451",
    "addr:housenumber":"2316",
    "addr:postcode":"23451",
    "addr:street":"Starfish Rd",
    "iso:country":"US",
    "sg:address":"2316 Starfish Rd",
    "sg:city":"Virginia Beach",
    "sg:classifiers":[
        {
            "category":"Banks & Credit Unions",
            "subcategory":"Bank",
            "type":"Services"
        }
    ],
    "sg:phone":"+1 757 962 9311",
    "sg:postcode":"23451",
    "sg:province":"VA",
    "wof:name":"Credit Union Kids",
    "wof:placetype":"venue"
},
  "geometry": {"coordinates":[-76.077584,36.910555],"type":"Point"}
}