{
  "type": "Feature",
  "properties": {
    "iso:country":"US",
    "sg:address":"702 London St",
    "sg:city":"Portsmouth",
    "sg:classifiers":[
        {
            "category":"Food & Beverages",
            "subcategory":"Groceries & Convenience Stores",
            "type":"Retail Goods"
        }
    ],
    "sg:phone":"+1 757 397 2984",
    "sg:postcode":"23704",
    "sg:province":"VA",
    "sg:tags":[
        "product"
    ],
    "wof:name":"Child Care Food Program",
    "wof:placetype":"venue"
},
  "geometry": {"coordinates":[-76.304849,36.836882],"type":"Point"}
}