{
  "type": "Feature",
  "properties": {
    "addr:full":"1136 Kempsville Rd Chesapeake VA 23320",
    "addr:housenumber":"1136",
    "addr:postcode":"23320",
    "addr:street":"Kempsville Rd",
    "iso:country":"US",
    "sg:address":"1136 Kempsville Rd",
    "sg:city":"Chesapeake",
    "sg:classifiers":[
        {
            "category":"Freight",
            "type":"Transportation"
        }
    ],
    "sg:phone":"+1 757 436 2648",
    "sg:postcode":"23320",
    "sg:province":"VA",
    "sg:tags":[
        "special"
    ],
    "sg:website":"www.greenbrierselfstorage.com",
    "wof:name":"Greenbrier Self Storage",
    "wof:placetype":"venue"
},
  "geometry": {"coordinates":[-76.20577,36.756571],"type":"Point"}
}