{
  "type": "Feature",
  "properties": {
    "iso:country":"US",
    "sg:address":"1900 Cypress Ave",
    "sg:city":"Virginia Beach",
    "sg:classifiers":[
        {
            "category":"Shopping",
            "subcategory":"Clothing, Apparel, & Fashions",
            "type":"Retail Goods"
        }
    ],
    "sg:phone":"+1 757 422 8823",
    "sg:postcode":"23451",
    "sg:province":"VA",
    "sg:tags":[
        "beach",
        "surfboard",
        "mfg"
    ],
    "sg:website":"www.waveridingvehicles.com",
    "wof:name":"Wave Riding Vehicles",
    "wof:placetype":"venue"
},
  "geometry": {"coordinates":[-75.983761,36.846769],"type":"Point"}
}