{
  "type": "Feature",
  "properties": {
    "addr:full":"8677 Batesville Rd Afton VA 22920",
    "addr:housenumber":"8677",
    "addr:postcode":"22920",
    "addr:street":"Batesville Rd",
    "iso:country":"US",
    "sg:address":"8677 Batesville Rd",
    "sg:city":"Afton",
    "sg:classifiers":[
        {
            "category":"Professional",
            "subcategory":"Lawyer & Legal Services",
            "type":"Services"
        }
    ],
    "sg:phone":"+1 540 456 6487",
    "sg:postcode":"22920",
    "sg:province":"VA",
    "wof:name":"Hodgson Ltd",
    "wof:placetype":"venue"
},
  "geometry": {"coordinates":[-78.79992300000001,37.992154],"type":"Point"}
}