{
  "type": "Feature",
  "properties": {
    "addr:full":"932 Ventures Way Chesapeake VA 23320",
    "addr:housenumber":"932",
    "addr:postcode":"23320",
    "addr:street":"Ventures Way",
    "iso:country":"US",
    "sg:address":"932 Ventures Way",
    "sg:city":"Chesapeake",
    "sg:classifiers":[
        {
            "category":"Education",
            "subcategory":"Junior College",
            "type":"Public Place"
        },
        {
            "category":"Education",
            "subcategory":"Vocational School",
            "type":"Public Place"
        }
    ],
    "sg:phone":"+1 757 548 2828",
    "sg:postcode":"23320",
    "sg:province":"VA",
    "sg:tags":[
        "technical",
        "institute"
    ],
    "sg:website":"www.tidetech.com",
    "wof:name":"Tidewater Tech",
    "wof:placetype":"venue"
},
  "geometry": {"coordinates":[-76.228864,36.765704],"type":"Point"}
}