{
  "type": "Feature",
  "properties": {
    "addr:full":"18 W Broad St Richmond VA 23220",
    "addr:housenumber":"18",
    "addr:postcode":"23220",
    "addr:street":"W Broad St",
    "iso:country":"US",
    "sg:address":"18 W Broad St",
    "sg:city":"Richmond",
    "sg:classifiers":[
        {
            "category":"Professional",
            "subcategory":"Accounting & Tax Preparation",
            "type":"Services"
        }
    ],
    "sg:phone":"+1 804 649 1311",
    "sg:postcode":"23220",
    "sg:province":"VA",
    "sg:tags":[
        "return",
        "filing"
    ],
    "wof:name":"Greater Richmond Earned Income",
    "wof:placetype":"venue"
},
  "geometry": {"coordinates":[-77.44235500000001,37.54589],"type":"Point"}
}