{
  "type": "Feature",
  "properties": {
    "addr:full":"9233 Sycamore Ln King George VA 22485",
    "addr:housenumber":"9233",
    "addr:postcode":"22485",
    "addr:street":"Sycamore Ln",
    "iso:country":"US",
    "sg:address":"9233 Sycamore Ln",
    "sg:city":"King George",
    "sg:classifiers":[
        {
            "category":"Building & Trades",
            "subcategory":"Construction",
            "type":"Services"
        }
    ],
    "sg:phone":"+1 540 775 4026",
    "sg:postcode":"22485",
    "sg:province":"VA",
    "sg:tags":[
        "designer",
        "marine",
        "contractor"
    ],
    "wof:name":"Unlimited Marine Svc",
    "wof:placetype":"venue"
},
  "geometry": {"coordinates":[-77.187203,38.210727],"type":"Point"}
}