{
  "type": "Feature",
  "properties": {
    "iso:country":"US",
    "sg:address":"422 S Washington St",
    "sg:city":"Alexandria",
    "sg:classifiers":[
        {
            "category":"Personal",
            "type":"Services"
        },
        {
            "category":"Sports & Exercise",
            "subcategory":"Gym",
            "type":"Entertainment"
        }
    ],
    "sg:phone":"+1 703 549 1990",
    "sg:postcode":"22314",
    "sg:province":"VA",
    "sg:tags":[
        "facility",
        "therapist",
        "merchandise",
        "fitness",
        "massage",
        "physical"
    ],
    "sg:website":"www.fountainsdayspa.com",
    "wof:name":"The Fountains Day Spa",
    "wof:placetype":"venue"
},
  "geometry": {"coordinates":[-77.047825,38.800749],"type":"Point"}
}