{
  "type": "Feature",
  "properties": {
    "addr:full":"4134 Meadowdale Blvd Richmond VA 23234",
    "addr:housenumber":"4134",
    "addr:postcode":"23234",
    "addr:street":"Meadowdale Blvd",
    "iso:country":"US",
    "sg:address":"4134 Meadowdale Blvd",
    "sg:city":"Richmond",
    "sg:classifiers":[
        {
            "category":"Banks & Credit Unions",
            "subcategory":"Bank",
            "type":"Services"
        }
    ],
    "sg:phone":"+1 804 788 2083",
    "sg:postcode":"23234",
    "sg:province":"VA",
    "sg:tags":[
        "national",
        "commercial"
    ],
    "sg:website":"www.bankofamerica.com",
    "wof:name":"Bank Of America",
    "wof:placetype":"venue"
},
  "geometry": {"coordinates":[-77.471479,37.438126],"type":"Point"}
}