{
  "type": "Feature",
  "properties": {
    "iso:country":"US",
    "sg:address":"600 N Henry St",
    "sg:city":"Alexandria",
    "sg:classifiers":[
        {
            "category":"Shopping",
            "subcategory":"Gifts & Souvenirs",
            "type":"Retail Goods"
        }
    ],
    "sg:phone":"+1 703 535 5440",
    "sg:postcode":"22314",
    "sg:province":"VA",
    "wof:name":"Catalyst Events",
    "wof:placetype":"venue"
},
  "geometry": {"coordinates":[-77.049902,38.812442],"type":"Point"}
}