{
  "type": "Feature",
  "properties": {
    "iso:country":"US",
    "sg:address":"1610 Quail Run",
    "sg:city":"Charlottesville",
    "sg:classifiers":[
        {
            "category":"Food & Beverages",
            "subcategory":"Specialty",
            "type":"Retail Goods"
        }
    ],
    "sg:phone":"+1 434 964 1655",
    "sg:postcode":"22911",
    "sg:province":"VA",
    "wof:name":"Greenberry S Wearhouse",
    "wof:placetype":"venue"
},
  "geometry": {"coordinates":[-78.44199999999999,38.14755],"type":"Point"}
}