{
  "type": "Feature",
  "properties": {
    "addr:full":"2312 2nd St S Arlington VA 22204",
    "addr:housenumber":"2312",
    "addr:postcode":"22204",
    "addr:street":"2Nd St S",
    "iso:country":"US",
    "sg:address":"2312 2nd St S",
    "sg:city":"Arlington",
    "sg:classifiers":[
        {
            "category":"Professional",
            "type":"Services"
        }
    ],
    "sg:phone":"+1 703 486 7075",
    "sg:postcode":"22204",
    "sg:province":"VA",
    "wof:name":"Hubrisoft LLC",
    "wof:placetype":"venue"
},
  "geometry": {"coordinates":[-77.084496,38.871421],"type":"Point"}
}