{
  "type": "Feature",
  "properties": {
    "addr:full":"2742 Grandin Rd SW Roanoke VA 24015",
    "addr:housenumber":"2742",
    "addr:postcode":"24015",
    "addr:street":"Grandin Rd Sw",
    "iso:country":"US",
    "sg:address":"2742 Grandin Rd SW",
    "sg:city":"Roanoke",
    "sg:classifiers":[
        {
            "category":"Organizations",
            "subcategory":"Community Association",
            "type":"Services"
        }
    ],
    "sg:phone":"+1 540 774 5464",
    "sg:postcode":"24015",
    "sg:province":"VA",
    "sg:tags":[
        "fraternal"
    ],
    "wof:name":"Af & AM",
    "wof:placetype":"venue"
},
  "geometry": {"coordinates":[-79.99706,37.252587],"type":"Point"}
}