{
  "type": "Feature",
  "properties": {
    "iso:country":"US",
    "sg:address":"26522 Crockett Town Rd",
    "sg:city":"Onancock",
    "sg:classifiers":[
        {
            "category":"Insurance",
            "subcategory":"Insurance Agent",
            "type":"Services"
        }
    ],
    "sg:phone":"+1 757 789 5911",
    "sg:postcode":"23417",
    "sg:province":"VA",
    "wof:name":"Herbert & Herbert Inc",
    "wof:placetype":"venue"
},
  "geometry": {"coordinates":[-75.833659,37.681962],"type":"Point"}
}