{
  "type": "Feature",
  "properties": {
    "addr:full":"10420 Twisted Oak Ln Marshall VA 20115",
    "addr:housenumber":"10420",
    "addr:postcode":"20115",
    "addr:street":"Twisted Oak Ln",
    "iso:country":"US",
    "sg:address":"10420 Twisted Oak Ln",
    "sg:city":"Marshall",
    "sg:classifiers":[
        {
            "category":"Utilities",
            "subcategory":"Mobile Phone",
            "type":"Services"
        }
    ],
    "sg:phone":"+1 540 364 7360",
    "sg:postcode":"20115",
    "sg:province":"VA",
    "sg:tags":[
        "technology",
        "manufacturing",
        "design",
        "cellular",
        "wholesale"
    ],
    "wof:name":"Cobbler Inc",
    "wof:placetype":"venue"
},
  "geometry": {"coordinates":[-77.940162,38.839549],"type":"Point"}
}