{
  "type": "Feature",
  "properties": {
    "iso:country":"US",
    "sg:address":"8300 Boone Blvd Ste 562",
    "sg:city":"Vienna",
    "sg:classifiers":[
        {
            "category":"Health Services",
            "subcategory":"Nursing And Care Facility",
            "type":"Services"
        },
        {
            "category":"Social Services",
            "subcategory":"Adult Care",
            "type":"Services"
        }
    ],
    "sg:phone":"+1 703 714 6669",
    "sg:postcode":"22182",
    "sg:province":"VA",
    "sg:tags":[
        "living",
        "assisted",
        "homes-elderly",
        "elder",
        "people"
    ],
    "wof:name":"Hg Pangle",
    "wof:placetype":"venue"
},
  "geometry": {"coordinates":[-77.231842,38.91642],"type":"Point"}
}