{
  "type": "Feature",
  "properties": {
    "addr:full":"5901 Seminary Rd Falls Church VA 22041",
    "addr:housenumber":"5901",
    "addr:postcode":"22041",
    "addr:street":"Seminary Rd",
    "iso:country":"US",
    "sg:address":"5901 Seminary Rd",
    "sg:city":"Falls Church",
    "sg:classifiers":[
        {
            "category":"Retail",
            "subcategory":"Auto Repair",
            "type":"Services"
        }
    ],
    "sg:phone":"+1 703 824 8020",
    "sg:postcode":"22041",
    "sg:province":"VA",
    "sg:tags":[
        "repairing",
        "automobile"
    ],
    "wof:name":"Romero's Auto Svc",
    "wof:placetype":"venue"
},
  "geometry": {"coordinates":[-77.128753,38.849382],"type":"Point"}
}