{
  "type": "Feature",
  "properties": {
    "iso:country":"US",
    "sg:address":"1020 E Main St",
    "sg:city":"Purcellville",
    "sg:classifiers":[
        {
            "category":"Personal",
            "subcategory":"Beauty Salon",
            "type":"Services"
        }
    ],
    "sg:phone":"+1 540 751 0238",
    "sg:postcode":"20132",
    "sg:province":"VA",
    "sg:tags":[
        "shop"
    ],
    "wof:name":"Nailtiques & Spa",
    "wof:placetype":"venue"
},
  "geometry": {"coordinates":[-77.69584,39.135769],"type":"Point"}
}