{
  "type": "Feature",
  "properties": {
    "iso:country":"US",
    "sg:address":"1714 Drewlaine Dr",
    "sg:city":"Vienna",
    "sg:classifiers":[
        {
            "category":"Professional",
            "subcategory":"Computer Services",
            "type":"Services"
        }
    ],
    "sg:phone":"+1 703 938 7854",
    "sg:postcode":"22182",
    "sg:province":"VA",
    "sg:tags":[
        "related"
    ],
    "wof:name":"Glw Group Inc",
    "wof:placetype":"venue"
},
  "geometry": {"coordinates":[-77.255636,38.92488],"type":"Point"}
}