{
  "type": "Feature",
  "properties": {
    "addr:full":"5505 Annandale Dr Virginia Beach VA 23464",
    "addr:housenumber":"5505",
    "addr:postcode":"23464",
    "addr:street":"Annandale Dr",
    "iso:country":"US",
    "sg:address":"5505 Annandale Dr",
    "sg:city":"Virginia Beach",
    "sg:classifiers":[
        {
            "category":"Home & Garden",
            "subcategory":"Building Materials",
            "type":"Retail Goods"
        },
        {
            "category":"Building & Trades",
            "subcategory":"Construction",
            "type":"Services"
        }
    ],
    "sg:phone":"+1 757 479 3660",
    "sg:postcode":"23464",
    "sg:province":"VA",
    "sg:tags":[
        "residential"
    ],
    "wof:name":"Atlantic Outdoor Additions",
    "wof:placetype":"venue"
},
  "geometry": {"coordinates":[-76.19615,36.771679],"type":"Point"}
}