{
  "type": "Feature",
  "properties": {
    "addr:full":"3337 Duke St Alexandria VA 22314",
    "addr:housenumber":"3337",
    "addr:postcode":"22314",
    "addr:street":"Duke St",
    "iso:country":"US",
    "sg:address":"3337 Duke St",
    "sg:city":"Alexandria",
    "sg:classifiers":[
        {
            "category":"Wholesale",
            "subcategory":"Medical Equipment & Supplies",
            "type":"Manufacturing & Wholesale Goods"
        },
        {
            "category":"Building & Trades",
            "subcategory":"Equipment Rental",
            "type":"Services"
        }
    ],
    "sg:phone":"+1 703 370 1008",
    "sg:postcode":"22314",
    "sg:province":"VA",
    "sg:tags":[
        "physician",
        "surgeon"
    ],
    "wof:name":"Nightingles Medical Supplies",
    "wof:placetype":"venue"
},
  "geometry": {"coordinates":[-77.08825299999999,38.808496],"type":"Point"}
}