{
  "type": "Feature",
  "properties": {
    "iso:country":"US",
    "sg:address":"5368 Pole Green Rd",
    "sg:city":"Mechanicsville",
    "sg:classifiers":[
        {
            "category":"Professional",
            "type":"Services"
        }
    ],
    "sg:phone":"+1 804 779 3066",
    "sg:postcode":"23116",
    "sg:province":"VA",
    "wof:name":"Dove Services LLC",
    "wof:placetype":"venue"
},
  "geometry": {"coordinates":[-77.28980199999999,37.643109],"type":"Point"}
}