{
  "type": "Feature",
  "properties": {
    "iso:country":"US",
    "sg:address":"175 S Reynolds St",
    "sg:city":"Alexandria",
    "sg:classifiers":[
        {
            "category":"Home & Garden",
            "subcategory":"Home Furnishings",
            "type":"Retail Goods"
        },
        {
            "category":"Building & Trades",
            "subcategory":"Construction",
            "type":"Services"
        },
        {
            "category":"Home & Garden",
            "subcategory":"Furniture",
            "type":"Retail Goods"
        },
        {
            "category":"Home & Garden",
            "subcategory":"Carpets & Floor Coverings",
            "type":"Retail Goods"
        },
        {
            "category":"Building & Trades",
            "subcategory":"Cleaning & Sanitation",
            "type":"Services"
        },
        {
            "category":"Manufacturing",
            "subcategory":"Building Materials",
            "type":"Manufacturing & Wholesale Goods"
        }
    ],
    "sg:phone":"+1 866 773 6645",
    "sg:postcode":"22304",
    "sg:province":"VA",
    "sg:tags":[
        "repair",
        "washing",
        "power",
        "plastering",
        "painting",
        "materials-wholesale",
        "handyman",
        "specialty",
        "kitchen",
        "contractor",
        "refacing",
        "resurfacing",
        "cabinets-refinishing",
        "maintenance",
        "tile-contractors",
        "cabinet",
        "drywall",
        "carpenter",
        "manufacturer"
    ],
    "wof:name":"SSC Remodeling and Renovation",
    "wof:placetype":"venue"
},
  "geometry": {"coordinates":[-77.12858300000001,38.809983],"type":"Point"}
}