{
  "type": "Feature",
  "properties": {
    "addr:full":"13915 Shadow Ridge Rd Midlothian VA 23112",
    "addr:housenumber":"13915",
    "addr:postcode":"23112",
    "addr:street":"Shadow Ridge Rd",
    "iso:country":"US",
    "sg:address":"13915 Shadow Ridge Rd",
    "sg:city":"Midlothian",
    "sg:classifiers":[
        {
            "category":"Professional",
            "subcategory":"Management & Consulting",
            "type":"Services"
        }
    ],
    "sg:phone":"+1 804 744 8300",
    "sg:postcode":"23112",
    "sg:province":"VA",
    "sg:tags":[
        "public",
        "relations"
    ],
    "wof:name":"Venture Com",
    "wof:placetype":"venue"
},
  "geometry": {"coordinates":[-77.660749,37.456992],"type":"Point"}
}