{
  "type": "Feature",
  "properties": {
    "addr:full":"4406 Glen Rose St Fairfax VA 22032",
    "addr:housenumber":"4406",
    "addr:postcode":"22032",
    "addr:street":"Glen Rose St",
    "iso:country":"US",
    "sg:address":"4406 Glen Rose St",
    "sg:city":"Fairfax",
    "sg:classifiers":[
        {
            "category":"Shopping",
            "subcategory":"Musical Instruments",
            "type":"Retail Goods"
        }
    ],
    "sg:phone":"+1 703 978 5479",
    "sg:postcode":"22032",
    "sg:province":"VA",
    "wof:name":"String Pull Guitar Shop",
    "wof:placetype":"venue"
},
  "geometry": {"coordinates":[-77.27099,38.828508],"type":"Point"}
}