{
  "type": "Feature",
  "properties": {
    "addr:full":"902 Bland Blvd Newport News VA 23602",
    "addr:housenumber":"902",
    "addr:postcode":"23602",
    "addr:street":"Bland Blvd",
    "iso:country":"US",
    "sg:address":"902 Bland Blvd",
    "sg:city":"Newport News",
    "sg:classifiers":[
        {
            "category":"Government",
            "subcategory":"Office",
            "type":"Public Place"
        }
    ],
    "sg:phone":"+1 757 877 2962",
    "sg:postcode":"23602",
    "sg:province":"VA",
    "sg:tags":[
        "control",
        "airport",
        "traffic",
        "tower"
    ],
    "wof:name":"Airport Traffic Control Tower",
    "wof:placetype":"venue"
},
  "geometry": {"coordinates":[-76.510259,37.12831],"type":"Point"}
}