{
  "type": "Feature",
  "properties": {
    "iso:country":"US",
    "sg:address":"10810 Paulbrook Blvd",
    "sg:city":"Midlothian",
    "sg:classifiers":[
        {
            "category":"Recreation",
            "type":"Entertainment"
        }
    ],
    "sg:phone":"+1 804 276 7039",
    "sg:postcode":"23112",
    "sg:province":"VA",
    "sg:tags":[
        "fitness",
        "physical",
        "facility"
    ],
    "wof:name":"Virginia Intl Gymnstc Trng",
    "wof:placetype":"venue"
},
  "geometry": {"coordinates":[-77.598679,37.440816],"type":"Point"}
}