{
  "type": "Feature",
  "properties": {
    "addr:full":"2249 S Shirlington Rd Arlington VA 22206",
    "addr:housenumber":"2249",
    "addr:postcode":"22206",
    "addr:street":"S Shirlington Rd",
    "iso:country":"US",
    "sg:address":"2249 S Shirlington Rd",
    "sg:city":"Arlington",
    "sg:classifiers":[
        {
            "category":"Personal",
            "subcategory":"Nail Salon",
            "type":"Services"
        }
    ],
    "sg:phone":"+1 703 486 8888",
    "sg:postcode":"22206",
    "sg:province":"VA",
    "sg:website":"www.nailspalace.net",
    "wof:name":"Nails Palace",
    "wof:placetype":"venue"
},
  "geometry": {"coordinates":[-77.08404400000001,38.849231],"type":"Point"}
}