{
  "type": "Feature",
  "properties": {
    "iso:country":"US",
    "sg:address":"213 Wilson St",
    "sg:city":"Martinsville",
    "sg:classifiers":[
        {
            "category":"Health Services",
            "subcategory":"Nursing And Care Facility",
            "type":"Services"
        }
    ],
    "sg:phone":"+1 276 634 0345",
    "sg:postcode":"24112",
    "sg:province":"VA",
    "sg:tags":[
        "intermediate"
    ],
    "wof:name":"Tender Hearts Adult Care Home",
    "wof:placetype":"venue"
},
  "geometry": {"coordinates":[-79.87299400000001,36.680468],"type":"Point"}
}