{
  "type": "Feature",
  "properties": {
    "iso:country":"US",
    "sg:address":"42507 Waxpool Rd",
    "sg:city":"Ashburn",
    "sg:classifiers":[
        {
            "category":"Organizations",
            "subcategory":"Religious Organization",
            "type":"Services"
        }
    ],
    "sg:phone":"+1 703 729 2707",
    "sg:postcode":"20148",
    "sg:province":"VA",
    "sg:tags":[
        "church"
    ],
    "wof:name":"Mount Hope Church",
    "wof:placetype":"venue"
},
  "geometry": {"coordinates":[-77.520054,39.014393],"type":"Point"}
}