{
  "type": "Feature",
  "properties": {
    "addr:full":"12153 Hooe Rd Bristow VA 20136",
    "addr:housenumber":"12153",
    "addr:postcode":"20136",
    "addr:street":"Hooe Rd",
    "iso:country":"US",
    "sg:address":"12153 Hooe Rd",
    "sg:city":"Bristow",
    "sg:classifiers":[
        {
            "category":"School Buses",
            "type":"Transportation"
        }
    ],
    "sg:phone":"+1 703 368 0176",
    "sg:postcode":"20136",
    "sg:province":"VA",
    "wof:name":"Prince Lean County Trnsp",
    "wof:placetype":"venue"
},
  "geometry": {"coordinates":[-77.515272,38.690234],"type":"Point"}
}