{
  "type": "Feature",
  "properties": {
    "addr:full":"2730 Tinsley Dr Richmond VA 23235",
    "addr:housenumber":"2730",
    "addr:postcode":"23235",
    "addr:street":"Tinsley Dr",
    "iso:country":"US",
    "sg:address":"2730 Tinsley Dr",
    "sg:city":"Richmond",
    "sg:classifiers":[
        {
            "category":"Retail",
            "subcategory":"Auto Repair",
            "type":"Services"
        }
    ],
    "sg:phone":"+1 804 565 5681",
    "sg:postcode":"23235",
    "sg:province":"VA",
    "sg:tags":[
        "shop",
        "automotive",
        "station",
        "gasoline",
        "general"
    ],
    "wof:name":"Amoco",
    "wof:placetype":"venue"
},
  "geometry": {"coordinates":[-77.560115,37.534628],"type":"Point"}
}