{
  "type": "Feature",
  "properties": {
    "iso:country":"US",
    "sg:address":"1000 Norview Ave",
    "sg:city":"Norfolk",
    "sg:classifiers":[
        {
            "category":"Shopping",
            "subcategory":"Gifts & Souvenirs",
            "type":"Retail Goods"
        }
    ],
    "sg:phone":"+1 757 853 2319",
    "sg:postcode":"23513",
    "sg:province":"VA",
    "sg:tags":[
        "newspaper",
        "item"
    ],
    "wof:name":"Hudson Group",
    "wof:placetype":"venue"
},
  "geometry": {"coordinates":[-76.245019,36.889913],"type":"Point"}
}