{
  "type": "Feature",
  "properties": {
    "addr:full":"22505 Scojo Dr Franklin VA 23851",
    "addr:postcode":"22505;23851",
    "addr:street":"Scojo Dr",
    "iso:country":"US",
    "sg:address":"22505 Scojo Dr",
    "sg:city":"Franklin",
    "sg:classifiers":[
        {
            "category":"Organizations",
            "subcategory":"Labor Organization",
            "type":"Services"
        }
    ],
    "sg:phone":"+1 757 562 7251",
    "sg:postcode":"23851",
    "sg:province":"VA",
    "wof:name":"Pace International Union",
    "wof:placetype":"venue"
},
  "geometry": {"coordinates":[-76.984996,36.709968],"type":"Point"}
}