{
  "type": "Feature",
  "properties": {
    "iso:country":"US",
    "sg:address":"7403 Adams Park Ct",
    "sg:city":"Annandale",
    "sg:classifiers":[
        {
            "category":"Wholesale",
            "subcategory":"Electrical",
            "type":"Manufacturing & Wholesale Goods"
        }
    ],
    "sg:phone":"+1 703 256 5760",
    "sg:postcode":"22003",
    "sg:province":"VA",
    "sg:tags":[
        "alarm",
        "burglar",
        "system"
    ],
    "wof:name":"Alarm Systems By E & R",
    "wof:placetype":"venue"
},
  "geometry": {"coordinates":[-77.19934600000001,38.828147],"type":"Point"}
}