{
  "type": "Feature",
  "properties": {
    "addr:full":"9280 Old Dumfries Rd Catlett VA 20119",
    "addr:housenumber":"9280",
    "addr:postcode":"20119",
    "addr:street":"Old Dumfries Rd",
    "iso:country":"US",
    "sg:address":"9280 Old Dumfries Rd",
    "sg:city":"Catlett",
    "sg:classifiers":[
        {
            "category":"Organizations",
            "subcategory":"Religious Organization",
            "type":"Services"
        }
    ],
    "sg:phone":"+1 540 788 3621",
    "sg:postcode":"20119",
    "sg:province":"VA",
    "sg:tags":[
        "church"
    ],
    "wof:name":"Trinity United Methdst Church",
    "wof:placetype":"venue"
},
  "geometry": {"coordinates":[-77.641904,38.656334],"type":"Point"}
}