{
  "type": "Feature",
  "properties": {
    "addr:full":"15018 Washington St Haymarket VA 20169",
    "addr:housenumber":"15018",
    "addr:postcode":"20169",
    "addr:street":"Washington St",
    "iso:country":"US",
    "sg:address":"15018 Washington St",
    "sg:city":"Haymarket",
    "sg:classifiers":[
        {
            "category":"Professional",
            "subcategory":"Business Services",
            "type":"Services"
        },
        {
            "category":"Building & Trades",
            "subcategory":"Construction",
            "type":"Services"
        }
    ],
    "sg:phone":"+1 703 753 8257",
    "sg:postcode":"20169",
    "sg:province":"VA",
    "sg:tags":[
        "coping",
        "plastering",
        "tiling",
        "pool",
        "swimming"
    ],
    "wof:name":"Pool Service Company",
    "wof:placetype":"venue"
},
  "geometry": {"coordinates":[-77.637321,38.812654],"type":"Point"}
}