{
  "type": "Feature",
  "properties": {
    "addr:full":"1001 Austenwood Ct Chesapeake VA 23322",
    "addr:housenumber":"1001",
    "addr:postcode":"23322",
    "addr:street":"Austenwood Ct",
    "iso:country":"US",
    "sg:address":"1001 Austenwood Ct",
    "sg:city":"Chesapeake",
    "sg:classifiers":[
        {
            "category":"Professional",
            "subcategory":"Management & Consulting",
            "type":"Services"
        }
    ],
    "sg:phone":"+1 757 546 7761",
    "sg:postcode":"23322",
    "sg:province":"VA",
    "wof:name":"Spectrum Associates",
    "wof:placetype":"venue"
},
  "geometry": {"coordinates":[-76.218491,36.689785],"type":"Point"}
}