{
  "type": "Feature",
  "properties": {
    "addr:full":"6303 Little River Tpke Alexandria VA 22312",
    "addr:housenumber":"6303",
    "addr:postcode":"22312",
    "addr:street":"Little River Tpke",
    "iso:country":"US",
    "sg:address":"6303 Little River Tpke",
    "sg:city":"Alexandria",
    "sg:phone":"+1 703 914 8989",
    "sg:postcode":"22312",
    "sg:province":"VA",
    "wof:name":"Children's Medical Associates",
    "wof:placetype":"venue"
},
  "geometry": {"coordinates":[-77.14340199999999,38.818207],"type":"Point"}
}