{
  "type": "Feature",
  "properties": {
    "addr:full":"1401 Old Fredericksburg Rd Culpeper VA 22701",
    "addr:housenumber":"1401",
    "addr:postcode":"22701",
    "addr:street":"Old Fredericksburg Rd",
    "iso:country":"US",
    "sg:address":"1401 Old Fredericksburg Rd",
    "sg:city":"Culpeper",
    "sg:classifiers":[
        {
            "category":"Social Services",
            "subcategory":"Child Care",
            "type":"Services"
        }
    ],
    "sg:phone":"+1 540 829 2330",
    "sg:postcode":"22701",
    "sg:province":"VA",
    "sg:tags":[
        "kindergarten",
        "academic",
        "school"
    ],
    "wof:name":"CDI Headstart",
    "wof:placetype":"venue"
},
  "geometry": {"coordinates":[-77.996155,38.463088],"type":"Point"}
}