{
  "type": "Feature",
  "properties": {
    "iso:country":"US",
    "sg:address":"2250 Old Ivy Rd",
    "sg:city":"Charlottesville",
    "sg:classifiers":[
        {
            "category":"Education",
            "subcategory":"School",
            "type":"Public Place"
        }
    ],
    "sg:phone":"+1 434 295 8769",
    "sg:postcode":"22903",
    "sg:province":"VA",
    "wof:name":"National Federation of Urban-Suburban Schl Dstrcts",
    "wof:placetype":"venue"
},
  "geometry": {"coordinates":[-78.51599899999999,38.0462],"type":"Point"}
}