{
  "type": "Feature",
  "properties": {
    "addr:full":"6616 Fleet Dr Alexandria VA 22310",
    "addr:housenumber":"6616",
    "addr:postcode":"22310",
    "addr:street":"Fleet Dr",
    "iso:country":"US",
    "sg:address":"6616 Fleet Dr",
    "sg:city":"Alexandria",
    "sg:classifiers":[
        {
            "category":"Home & Garden",
            "subcategory":"Building Materials",
            "type":"Retail Goods"
        },
        {
            "category":"Retail",
            "subcategory":"Auto Repair",
            "type":"Services"
        }
    ],
    "sg:phone":"+1 703 924 4086",
    "sg:postcode":"22310",
    "sg:province":"VA",
    "sg:tags":[
        "glass",
        "window",
        "plate",
        "replacement"
    ],
    "wof:name":"Safelite Auto Glass",
    "wof:placetype":"venue"
},
  "geometry": {"coordinates":[-77.15653399999999,38.774957],"type":"Point"}
}