{
  "type": "Feature",
  "properties": {
    "iso:country":"US",
    "sg:address":"2326 Tuscora Rd",
    "sg:city":"Richmond",
    "sg:classifiers":[
        {
            "category":"Building & Trades",
            "subcategory":"Construction",
            "type":"Services"
        }
    ],
    "sg:phone":"+1 804 272 3248",
    "sg:postcode":"23235",
    "sg:province":"VA",
    "sg:tags":[
        "carpentry",
        "contractor"
    ],
    "wof:name":"Custom Mill Work",
    "wof:placetype":"venue"
},
  "geometry": {"coordinates":[-77.54776699999999,37.530353],"type":"Point"}
}