{
  "type": "Feature",
  "properties": {
    "iso:country":"US",
    "sg:address":"3000 N Washington Blvd",
    "sg:city":"Arlington",
    "sg:classifiers":[
        {
            "category":"Social Services",
            "subcategory":"Child Care",
            "type":"Services"
        }
    ],
    "sg:phone":"+1 703 465 1451",
    "sg:postcode":"22201",
    "sg:province":"VA",
    "sg:tags":[
        "day"
    ],
    "wof:name":"Escape Day Spa",
    "wof:placetype":"venue"
},
  "geometry": {"coordinates":[-77.094775,38.885698],"type":"Point"}
}