{
  "type": "Feature",
  "properties": {
    "addr:full":"12101 Colvin Ln Nokesville VA 20181",
    "addr:housenumber":"12101",
    "addr:postcode":"20181",
    "addr:street":"Colvin Ln",
    "iso:country":"US",
    "sg:address":"12101 Colvin Ln",
    "sg:city":"Nokesville",
    "sg:phone":"+1 703 856 3921",
    "sg:postcode":"20181",
    "sg:province":"VA",
    "sg:tags":[
        "straw"
    ],
    "wof:name":"Eugene Wayne Presgraves Sr",
    "wof:placetype":"venue"
},
  "geometry": {"coordinates":[-77.55645800000001,38.697857],"type":"Point"}
}