{
  "type": "Feature",
  "properties": {
    "iso:country":"US",
    "sg:address":"1878 E Ocean View Ave",
    "sg:city":"Norfolk",
    "sg:classifiers":[
        {
            "category":"Social Services",
            "type":"Services"
        }
    ],
    "sg:phone":"+1 757 583 1878",
    "sg:postcode":"23503",
    "sg:province":"VA",
    "sg:tags":[
        "worker"
    ],
    "wof:name":"Cynthia A Hansen",
    "wof:placetype":"venue"
},
  "geometry": {"coordinates":[-76.222093,36.938227],"type":"Point"}
}