{
  "type": "Feature",
  "properties": {
    "addr:full":"1220 High St Portsmouth VA 23704",
    "addr:housenumber":"1220",
    "addr:postcode":"23704",
    "addr:street":"High St",
    "iso:country":"US",
    "sg:address":"1220 High St",
    "sg:city":"Portsmouth",
    "sg:classifiers":[
        {
            "category":"Retail",
            "subcategory":"Auto Rental",
            "type":"Services"
        }
    ],
    "sg:phone":"+1 757 399 5262",
    "sg:postcode":"23704",
    "sg:province":"VA",
    "sg:tags":[
        "passenger",
        "car"
    ],
    "wof:name":"Enterprise Rent-A-Car",
    "wof:placetype":"venue"
},
  "geometry": {"coordinates":[-76.313053,36.83516],"type":"Point"}
}