{
  "type": "Feature",
  "properties": {
    "addr:full":"8298 Old Courthouse Rd Vienna VA 22182",
    "addr:housenumber":"8298",
    "addr:postcode":"22182",
    "addr:street":"Old Courthouse Rd",
    "iso:country":"US",
    "sg:address":"8298 Old Courthouse Rd",
    "sg:city":"Vienna",
    "sg:classifiers":[
        {
            "category":"Real Estate",
            "subcategory":"Real Estate Agent",
            "type":"Services"
        }
    ],
    "sg:phone":"+1 703 883 1101",
    "sg:postcode":"22182",
    "sg:province":"VA",
    "wof:name":"Allied It Professionals",
    "wof:placetype":"venue"
},
  "geometry": {"coordinates":[-77.231996,38.914157],"type":"Point"}
}