{
  "type": "Feature",
  "properties": {
    "addr:full":"111 Cybernetics Way Yorktown VA 23693",
    "addr:housenumber":"111",
    "addr:postcode":"23693",
    "addr:street":"Cybernetics Way",
    "iso:country":"US",
    "sg:address":"111 Cybernetics Way",
    "sg:city":"Yorktown",
    "sg:classifiers":[
        {
            "category":"Professional",
            "subcategory":"Management & Consulting",
            "type":"Services"
        }
    ],
    "sg:phone":"+1 757 833 5790",
    "sg:postcode":"23693",
    "sg:province":"VA",
    "wof:name":"Odyssey Systems Cnslting Group",
    "wof:placetype":"venue"
},
  "geometry": {"coordinates":[-76.46453,37.118309],"type":"Point"}
}