{
  "type": "Feature",
  "properties": {
    "iso:country":"US",
    "sg:address":"2101 N Wilson Blvd",
    "sg:city":"Arlington",
    "sg:classifiers":[
        {
            "category":"Professional",
            "type":"Services"
        }
    ],
    "sg:phone":"+1 703 247 4212",
    "sg:postcode":"22201",
    "sg:province":"VA",
    "sg:tags":[
        "establishment"
    ],
    "sg:website":"www.accsct.org",
    "wof:name":"Accrediting Commission-Career",
    "wof:placetype":"venue"
},
  "geometry": {"coordinates":[-77.08581599999999,38.89123],"type":"Point"}
}