{
  "type": "Feature",
  "properties": {
    "addr:full":"11058 Leadbetter Rd Ashland VA 23005",
    "addr:housenumber":"11058",
    "addr:postcode":"23005",
    "addr:street":"Leadbetter Rd",
    "iso:country":"US",
    "sg:address":"11058 Leadbetter Rd",
    "sg:city":"Ashland",
    "sg:classifiers":[
        {
            "category":"Wholesale",
            "subcategory":"Metals & Minerals",
            "type":"Manufacturing & Wholesale Goods"
        }
    ],
    "sg:phone":"+1 804 798 3333",
    "sg:postcode":"23005",
    "sg:province":"VA",
    "sg:tags":[
        "steel",
        "warehouse"
    ],
    "wof:name":"Steel Services Inc",
    "wof:placetype":"venue"
},
  "geometry": {"coordinates":[-77.443437,37.703501],"type":"Point"}
}