{
  "type": "Feature",
  "properties": {
    "addr:full":"14519 Potomac Mills Rd Woodbridge VA 22192",
    "addr:housenumber":"14519",
    "addr:postcode":"22192",
    "addr:street":"Potomac Mills Rd",
    "iso:country":"US",
    "sg:address":"14519 Potomac Mills Rd",
    "sg:city":"Woodbridge",
    "sg:classifiers":[
        {
            "category":"Home & Garden",
            "subcategory":"Household Appliances",
            "type":"Retail Goods"
        }
    ],
    "sg:phone":"+1 703 491 4739",
    "sg:postcode":"22192",
    "sg:province":"VA",
    "sg:tags":[
        "equipment",
        "industrial"
    ],
    "wof:name":"Bonnys Sewing Center",
    "wof:placetype":"venue"
},
  "geometry": {"coordinates":[-77.297578,38.634408],"type":"Point"}
}