{
  "type": "Feature",
  "properties": {
    "addr:full":"12401 Willow Falls Dr Herndon VA 20170",
    "addr:housenumber":"12401",
    "addr:postcode":"20170",
    "addr:street":"Willow Falls Dr",
    "iso:country":"US",
    "sg:address":"12401 Willow Falls Dr",
    "sg:city":"Herndon",
    "sg:classifiers":[
        {
            "category":"Professional",
            "subcategory":"Accounting & Tax Preparation",
            "type":"Services"
        }
    ],
    "sg:phone":"+1 703 404 4075",
    "sg:postcode":"20170",
    "sg:province":"VA",
    "wof:name":"Carol Zirkle CPA",
    "wof:placetype":"venue"
},
  "geometry": {"coordinates":[-77.37581900000001,39.006876],"type":"Point"}
}