{
  "type": "Feature",
  "properties": {
    "addr:full":"306 Old 11 Ct Abingdon VA 24210",
    "addr:housenumber":"306",
    "addr:postcode":"24210",
    "addr:street":"Old 11 Ct",
    "iso:country":"US",
    "sg:address":"306 Old 11 Ct",
    "sg:city":"Abingdon",
    "sg:classifiers":[
        {
            "category":"Government",
            "subcategory":"Office",
            "type":"Public Place"
        }
    ],
    "sg:phone":"+1 276 628 6261",
    "sg:postcode":"24210",
    "sg:province":"VA",
    "sg:tags":[
        "dept",
        "agriculture",
        "consumer"
    ],
    "wof:name":"VA Dept Agriclture Consmr Svcs",
    "wof:placetype":"venue"
},
  "geometry": {"coordinates":[-81.940192,36.713941],"type":"Point"}
}