{
  "type": "Feature",
  "properties": {
    "addr:full":"1778 Fountain Dr Reston VA 20190",
    "addr:housenumber":"1778",
    "addr:postcode":"20190",
    "addr:street":"Fountain Dr",
    "iso:country":"US",
    "sg:address":"1778 Fountain Dr",
    "sg:city":"Reston",
    "sg:classifiers":[
        {
            "category":"Social Services",
            "subcategory":"Adult Care",
            "type":"Services"
        }
    ],
    "sg:phone":"+1 703 834 5994",
    "sg:postcode":"20190",
    "sg:province":"VA",
    "sg:tags":[
        "home",
        "residential"
    ],
    "sg:website":"www.sunriseassistedliving.com",
    "wof:name":"Sunrise At Reston Town Ctr",
    "wof:placetype":"venue"
},
  "geometry": {"coordinates":[-77.35600700000001,38.964031],"type":"Point"}
}