{
  "type": "Feature",
  "properties": {
    "iso:country":"US",
    "sg:address":"2544 Georges Run Rd",
    "sg:city":"Shawsville",
    "sg:classifiers":[
        {
            "category":"Professional",
            "subcategory":"Business Services",
            "type":"Services"
        }
    ],
    "sg:phone":"+1 540 268 5885",
    "sg:postcode":"24162",
    "sg:province":"VA",
    "wof:name":"Izaak Walton League of Am",
    "wof:placetype":"venue"
},
  "geometry": {"coordinates":[-80.30326100000001,37.138159],"type":"Point"}
}