{
  "type": "Feature",
  "properties": {
    "addr:full":"5826 Westower Dr Richmond VA 23225",
    "addr:housenumber":"5826",
    "addr:postcode":"23225",
    "addr:street":"Westower Dr",
    "iso:country":"US",
    "sg:address":"5826 Westower Dr",
    "sg:city":"Richmond",
    "sg:classifiers":[
        {
            "category":"Professional",
            "type":"Services"
        },
        {
            "category":"Freight",
            "type":"Transportation"
        },
        {
            "category":"Local Transit",
            "type":"Transportation"
        }
    ],
    "sg:phone":"+1 804 658 0667",
    "sg:postcode":"23225",
    "sg:province":"VA",
    "sg:tags":[
        "trucking",
        "provider"
    ],
    "wof:name":"Unlimited Transportation",
    "wof:placetype":"venue"
},
  "geometry": {"coordinates":[-77.50503999999999,37.526373],"type":"Point"}
}