{
  "type": "Feature",
  "properties": {
    "iso:country":"US",
    "sg:address":"3803 W End Dr",
    "sg:city":"Richmond",
    "sg:classifiers":[
        {
            "category":"Government",
            "subcategory":"Fire Station",
            "type":"Public Place"
        }
    ],
    "sg:phone":"+1 804 501 4901",
    "sg:postcode":"23294",
    "sg:province":"VA",
    "sg:tags":[
        "protection"
    ],
    "wof:name":"Fire Station 12",
    "wof:placetype":"venue"
},
  "geometry": {"coordinates":[-77.54449700000001,37.640028],"type":"Point"}
}