{
  "type": "Feature",
  "properties": {
    "iso:country":"US",
    "sg:address":"211 E Cleveland Ave",
    "sg:city":"Vinton",
    "sg:classifiers":[
        {
            "category":"Insurance",
            "subcategory":"Insurance Agent",
            "type":"Services"
        }
    ],
    "sg:phone":"+1 540 343 2600",
    "sg:postcode":"24179",
    "sg:province":"VA",
    "wof:name":"Minnesota Life Insurance Co",
    "wof:placetype":"venue"
},
  "geometry": {"coordinates":[-79.896078,37.27765],"type":"Point"}
}