{
  "type": "Feature",
  "properties": {
    "addr:full":"485 Wildlife Club Rd Clarksville VA 23927",
    "addr:housenumber":"485",
    "addr:postcode":"23927",
    "addr:street":"Wildlife Club Rd",
    "iso:country":"US",
    "sg:address":"485 Wildlife Club Rd",
    "sg:city":"Clarksville",
    "sg:classifiers":[
        {
            "category":"Organizations",
            "subcategory":"Community Association",
            "type":"Services"
        }
    ],
    "sg:phone":"+1 434 374 2922",
    "sg:postcode":"23927",
    "sg:province":"VA",
    "sg:tags":[
        "club"
    ],
    "wof:name":"Buggs Island Fish & Wildlife",
    "wof:placetype":"venue"
},
  "geometry": {"coordinates":[-78.530817,36.585545],"type":"Point"}
}