{
  "type": "Feature",
  "properties": {
    "addr:full":"9805 Summerday Dr Burke VA 22015",
    "addr:housenumber":"9805",
    "addr:postcode":"22015",
    "addr:street":"Summerday Dr",
    "iso:country":"US",
    "sg:address":"9805 Summerday Dr",
    "sg:city":"Burke",
    "sg:classifiers":[
        {
            "category":"Shopping",
            "subcategory":"Gifts & Souvenirs",
            "type":"Retail Goods"
        }
    ],
    "sg:phone":"+1 703 764 1279",
    "sg:postcode":"22015",
    "sg:province":"VA",
    "wof:name":"Angels Cards & Gifts Inc",
    "wof:placetype":"venue"
},
  "geometry": {"coordinates":[-77.282838,38.778158],"type":"Point"}
}