{
  "type": "Feature",
  "properties": {
    "addr:full":"5653 Columbia Pike Ste 201 Falls Church VA 22041",
    "addr:housenumber":"5653",
    "addr:postcode":"22041",
    "addr:street":"Columbia Pike Ste 201",
    "iso:country":"US",
    "sg:address":"5653 Columbia Pike Ste 201",
    "sg:city":"Falls Church",
    "sg:classifiers":[
        {
            "category":"Personal",
            "subcategory":"Massage",
            "type":"Services"
        }
    ],
    "sg:phone":"+1 703 942 6448",
    "sg:postcode":"22041",
    "sg:province":"VA",
    "sg:website":"massagestudiova.com",
    "wof:name":"Mickey and Lee's Massage Studio",
    "wof:placetype":"venue"
},
  "geometry": {"coordinates":[-77.12517800000001,38.851581],"type":"Point"}
}