{
  "type": "Feature",
  "properties": {
    "addr:full":"13482 Photo Dr Woodbridge VA 22193",
    "addr:postcode":"13482;22193",
    "addr:street":"Photo Dr",
    "iso:country":"US",
    "sg:address":"13482 Photo Dr",
    "sg:city":"Woodbridge",
    "sg:classifiers":[
        {
            "category":"Shopping",
            "subcategory":"Bicycles & Sporting Goods",
            "type":"Retail Goods"
        }
    ],
    "sg:phone":"+1 703 590 1399",
    "sg:postcode":"22193",
    "sg:province":"VA",
    "wof:name":"Snow Hawk Enterprises",
    "wof:placetype":"venue"
},
  "geometry": {"coordinates":[-77.383336,38.660972],"type":"Point"}
}