{
  "type": "Feature",
  "properties": {
    "iso:country":"US",
    "sg:address":"946 Shillelagh Rd",
    "sg:city":"Chesapeake",
    "sg:classifiers":[
        {
            "category":"Farming",
            "subcategory":"Nursery",
            "type":"Manufacturing & Wholesale Goods"
        }
    ],
    "sg:phone":"+1 757 547 7188",
    "sg:postcode":"23323",
    "sg:province":"VA",
    "sg:tags":[
        "growing",
        "potted",
        "plant",
        "stock"
    ],
    "wof:name":"Teeuwen Greenhouses Ltd",
    "wof:placetype":"venue"
},
  "geometry": {"coordinates":[-76.30688600000001,36.707597],"type":"Point"}
}