{
  "type": "Feature",
  "properties": {
    "iso:country":"US",
    "sg:address":"512 Locust Ln",
    "sg:city":"Penhook",
    "sg:classifiers":[
        {
            "category":"Real Estate",
            "subcategory":"Architect",
            "type":"Services"
        }
    ],
    "sg:phone":"+1 434 927 5843",
    "sg:postcode":"24137",
    "sg:province":"VA",
    "sg:tags":[
        "engineer"
    ],
    "wof:name":"Versar Inc",
    "wof:placetype":"venue"
},
  "geometry": {"coordinates":[-79.589077,37.0221],"type":"Point"}
}