{
  "type": "Feature",
  "properties": {
    "addr:full":"116 W Main St Floyd VA 24091",
    "addr:housenumber":"116",
    "addr:postcode":"24091",
    "addr:street":"W Main St",
    "iso:country":"US",
    "sg:address":"116 W Main St",
    "sg:city":"Floyd",
    "sg:classifiers":[
        {
            "category":"Insurance",
            "subcategory":"Hazard Insurance",
            "type":"Services"
        }
    ],
    "sg:phone":"+1 540 745 4882",
    "sg:postcode":"24091",
    "sg:province":"VA",
    "wof:name":"Floyd Co Mutual Fire Ins Co",
    "wof:placetype":"venue"
},
  "geometry": {"coordinates":[-80.32082,36.911165],"type":"Point"}
}