{
  "type": "Feature",
  "properties": {
    "iso:country":"US",
    "sg:address":"11355 New Wade Ln",
    "sg:city":"Glen Allen",
    "sg:classifiers":[
        {
            "category":"Professional",
            "subcategory":"Accounting & Tax Preparation",
            "type":"Services"
        }
    ],
    "sg:phone":"+1 804 747 3550",
    "sg:postcode":"23059",
    "sg:province":"VA",
    "sg:tags":[
        "return",
        "filing"
    ],
    "wof:name":"Seredni's Tax Svc",
    "wof:placetype":"venue"
},
  "geometry": {"coordinates":[-77.58956999999999,37.673444],"type":"Point"}
}