{
  "type": "Feature",
  "properties": {
    "iso:country":"US",
    "sg:address":"17 Fairfield Ave",
    "sg:city":"Danville",
    "sg:classifiers":[
        {
            "category":"Organizations",
            "subcategory":"Community Association",
            "type":"Services"
        }
    ],
    "sg:phone":"+1 434 793 7531",
    "sg:postcode":"24541",
    "sg:province":"VA",
    "sg:tags":[
        "civic",
        "social"
    ],
    "wof:name":"Dan River Post",
    "wof:placetype":"venue"
},
  "geometry": {"coordinates":[-79.424448,36.567574],"type":"Point"}
}