{
  "type": "Feature",
  "properties": {
    "addr:full":"8501 Osborne Tpke Henrico VA 23231",
    "addr:housenumber":"8501",
    "addr:postcode":"23231",
    "addr:street":"Osborne Tpke",
    "iso:country":"US",
    "sg:address":"8501 Osborne Tpke",
    "sg:city":"Henrico",
    "sg:classifiers":[
        {
            "category":"Transit Center",
            "subcategory":"Freight",
            "type":"Transportation"
        }
    ],
    "sg:phone":"+1 804 795 1777",
    "sg:postcode":"23231",
    "sg:province":"VA",
    "sg:tags":[
        "trucking-light",
        "hauling"
    ],
    "wof:name":"Dw Davis Hauling Inc",
    "wof:placetype":"venue"
},
  "geometry": {"coordinates":[-77.392067,37.432468],"type":"Point"}
}