{
  "type": "Feature",
  "properties": {
    "iso:country":"US",
    "sg:address":"3701 5th St S Suite 311",
    "sg:city":"Arlington",
    "sg:classifiers":[
        {
            "category":"Building & Trades",
            "subcategory":"Cleaning & Sanitation",
            "type":"Services"
        }
    ],
    "sg:phone":"+1 703 892 8648",
    "sg:postcode":"22204",
    "sg:province":"VA",
    "sg:tags":[
        "janitorial"
    ],
    "sg:website":"http://www.acommercialcleaningserviceinc.com/",
    "wof:name":"A Cleaning Service",
    "wof:placetype":"venue"
},
  "geometry": {"coordinates":[-77.09705700000001,38.866834],"type":"Point"}
}