{
  "type": "Feature",
  "properties": {
    "addr:full":"545 Highland Ave SW Roanoke VA 24016",
    "addr:housenumber":"545",
    "addr:postcode":"24016",
    "addr:street":"Highland Ave Sw",
    "iso:country":"US",
    "sg:address":"545 Highland Ave SW",
    "sg:city":"Roanoke",
    "sg:classifiers":[
        {
            "category":"Organizations",
            "subcategory":"Religious Organization",
            "type":"Services"
        }
    ],
    "sg:phone":"+1 540 982 1911",
    "sg:postcode":"24016",
    "sg:province":"VA",
    "wof:name":"Douglas F Turner Rev",
    "wof:placetype":"venue"
},
  "geometry": {"coordinates":[-79.953142,37.265518],"type":"Point"}
}