{
  "type": "Feature",
  "properties": {
    "addr:full":"2066 Cunningham Dr Hampton VA 23666",
    "addr:housenumber":"2066",
    "addr:postcode":"23666",
    "addr:street":"Cunningham Dr",
    "iso:country":"US",
    "sg:address":"2066 Cunningham Dr",
    "sg:city":"Hampton",
    "sg:classifiers":[
        {
            "category":"Building & Trades",
            "subcategory":"Cleaning & Sanitation",
            "type":"Services"
        }
    ],
    "sg:phone":"+1 757 342 7332",
    "sg:postcode":"23666",
    "sg:province":"VA",
    "sg:tags":[
        "commercial"
    ],
    "wof:name":"Jan-Pro Cleaning Systems",
    "wof:placetype":"venue"
},
  "geometry": {"coordinates":[-76.382154,37.046404],"type":"Point"}
}