{
  "type": "Feature",
  "properties": {
    "iso:country":"US",
    "sg:address":"1148 Rose Hill Dr",
    "sg:city":"Charlottesville",
    "sg:classifiers":[
        {
            "category":"Professional",
            "subcategory":"Lawyer & Legal Services",
            "type":"Services"
        }
    ],
    "sg:phone":"+1 434 296 2240",
    "sg:postcode":"22903",
    "sg:province":"VA",
    "sg:tags":[
        "divorce",
        "law",
        "family"
    ],
    "wof:name":"Payne Mary Susan Attorney",
    "wof:placetype":"venue"
},
  "geometry": {"coordinates":[-78.483991,38.042983],"type":"Point"}
}