{
  "type": "Feature",
  "properties": {
    "addr:full":"523 Leesville Rd Lynchburg VA 24502",
    "addr:housenumber":"523",
    "addr:postcode":"24502",
    "addr:street":"Leesville Rd",
    "iso:country":"US",
    "sg:address":"523 Leesville Rd",
    "sg:city":"Lynchburg",
    "sg:classifiers":[
        {
            "category":"Organizations",
            "subcategory":"Non-profit Organization",
            "type":"Services"
        }
    ],
    "sg:phone":"+1 434 237 7799",
    "sg:postcode":"24502",
    "sg:province":"VA",
    "sg:tags":[
        "fund",
        "counselor",
        "raising"
    ],
    "sg:website":"www.kathybyron.com",
    "wof:name":"B & B Presentation",
    "wof:placetype":"venue"
},
  "geometry": {"coordinates":[-79.20890799999999,37.361252],"type":"Point"}
}