{
  "type": "Feature",
  "properties": {
    "iso:country":"US",
    "sg:address":"1420 Sailors Creek Rd",
    "sg:city":"Callands",
    "sg:classifiers":[
        {
            "category":"Farming",
            "subcategory":"Livestock Farm",
            "type":"Manufacturing & Wholesale Goods"
        }
    ],
    "sg:phone":"+1 434 724 7524",
    "sg:postcode":"24530",
    "sg:province":"VA",
    "sg:tags":[
        "animal",
        "crop",
        "general"
    ],
    "wof:name":"Swanson Farm",
    "wof:placetype":"venue"
},
  "geometry": {"coordinates":[-79.600216,36.84812],"type":"Point"}
}