{
  "type": "Feature",
  "properties": {
    "iso:country":"US",
    "sg:address":"415 Jarratt Ave",
    "sg:city":"Jarratt",
    "sg:classifiers":[
        {
            "category":"Government",
            "subcategory":"Fire Station",
            "type":"Public Place"
        }
    ],
    "sg:phone":"+1 434 535 8920",
    "sg:postcode":"23867",
    "sg:province":"VA",
    "sg:tags":[
        "protection"
    ],
    "wof:name":"Jarratt Volunteer Fire Dept",
    "wof:placetype":"venue"
},
  "geometry": {"coordinates":[-77.475768,36.819025],"type":"Point"}
}