{
  "type": "Feature",
  "properties": {
    "iso:country":"US",
    "sg:address":"5202 Andersonville Rd",
    "sg:city":"Dillwyn",
    "sg:classifiers":[
        {
            "category":"Manufacturing",
            "subcategory":"Petroleum Products",
            "type":"Manufacturing & Wholesale Goods"
        },
        {
            "category":"Wholesale",
            "subcategory":"Petroleum",
            "type":"Manufacturing & Wholesale Goods"
        }
    ],
    "sg:phone":"+1 434 315 4146",
    "sg:postcode":"23936",
    "sg:province":"VA",
    "sg:tags":[
        "manufacturer",
        "products-wholesale",
        "oils-petroleum"
    ],
    "wof:name":"Blackberry Farm Enterprises",
    "wof:placetype":"venue"
},
  "geometry": {"coordinates":[-78.56544599999999,37.471954],"type":"Point"}
}