{
  "type": "Feature",
  "properties": {
    "addr:full":"1504 Cornwell Ln Virginia Beach VA 23454",
    "addr:housenumber":"1504",
    "addr:postcode":"23454",
    "addr:street":"Cornwell Ln",
    "iso:country":"US",
    "sg:address":"1504 Cornwell Ln",
    "sg:city":"Virginia Beach",
    "sg:classifiers":[
        {
            "category":"Health Services",
            "subcategory":"Doctor",
            "type":"Services"
        }
    ],
    "sg:phone":"+1 757 496 2419",
    "sg:postcode":"23454",
    "sg:province":"VA",
    "sg:tags":[
        "medical"
    ],
    "wof:name":"Dnm Anesthesia Assoc",
    "wof:placetype":"venue"
},
  "geometry": {"coordinates":[-76.014287,36.87428],"type":"Point"}
}