{
  "type": "Feature",
  "properties": {
    "iso:country":"US",
    "sg:address":"5242 Port Royal Rd",
    "sg:city":"Springfield",
    "sg:classifiers":[
        {
            "category":"Shopping",
            "subcategory":"Florist",
            "type":"Retail Goods"
        }
    ],
    "sg:phone":"+1 703 321 8484",
    "sg:postcode":"22151",
    "sg:province":"VA",
    "sg:tags":[
        "shop"
    ],
    "wof:name":"None",
    "wof:placetype":"venue"
},
  "geometry": {"coordinates":[-77.221604,38.810321],"type":"Point"}
}