{
  "type": "Feature",
  "properties": {
    "addr:full":"160 Rosehill Dr SW Christiansburg VA 24073",
    "addr:housenumber":"160",
    "addr:postcode":"24073",
    "addr:street":"Rosehill Dr Sw",
    "iso:country":"US",
    "sg:address":"160 Rosehill Dr SW",
    "sg:city":"Christiansburg",
    "sg:classifiers":[
        {
            "category":"Building & Trades",
            "subcategory":"Construction",
            "type":"Services"
        }
    ],
    "sg:phone":"+1 540 382 8251",
    "sg:postcode":"24073",
    "sg:province":"VA",
    "sg:tags":[
        "water",
        "pump",
        "well",
        "drilling"
    ],
    "wof:name":"Haynes Drilling Co",
    "wof:placetype":"venue"
},
  "geometry": {"coordinates":[-80.398292,37.116819],"type":"Point"}
}