{
  "type": "Feature",
  "properties": {
    "iso:country":"US",
    "sg:address":"426 E Freemason St",
    "sg:city":"Norfolk",
    "sg:classifiers":[
        {
            "category":"Freight",
            "type":"Transportation"
        }
    ],
    "sg:phone":"+1 757 622 6077",
    "sg:postcode":"23510",
    "sg:province":"VA",
    "sg:tags":[
        "arrangement",
        "broker",
        "trucking"
    ],
    "wof:name":"Express Trak LLC",
    "wof:placetype":"venue"
},
  "geometry": {"coordinates":[-76.286843,36.850234],"type":"Point"}
}