{
  "type": "Feature",
  "properties": {
    "addr:full":"1333 Brunswick Ave Norfolk VA 23508",
    "addr:housenumber":"1333",
    "addr:postcode":"23508",
    "addr:street":"Brunswick Ave",
    "iso:country":"US",
    "sg:address":"1333 Brunswick Ave",
    "sg:city":"Norfolk",
    "sg:classifiers":[
        {
            "category":"Building & Trades",
            "subcategory":"Construction",
            "type":"Services"
        }
    ],
    "sg:phone":"+1 757 440 0696",
    "sg:postcode":"23508",
    "sg:province":"VA",
    "sg:tags":[
        "house"
    ],
    "wof:name":"J M Hess Contracting",
    "wof:placetype":"venue"
},
  "geometry": {"coordinates":[-76.305983,36.891838],"type":"Point"}
}