{
  "type": "Feature",
  "properties": {
    "addr:full":"1504 Santa Rosa Rd Richmond VA 23229",
    "addr:housenumber":"1504",
    "addr:postcode":"23229",
    "addr:street":"Santa Rosa Rd",
    "iso:country":"US",
    "sg:address":"1504 Santa Rosa Rd",
    "sg:city":"Richmond",
    "sg:classifiers":[
        {
            "category":"Professional",
            "subcategory":"Engineering",
            "type":"Services"
        }
    ],
    "sg:phone":"+1 804 648 6130",
    "sg:postcode":"23229",
    "sg:province":"VA",
    "wof:name":"Robson Lapina",
    "wof:placetype":"venue"
},
  "geometry": {"coordinates":[-77.54863,37.602226],"type":"Point"}
}