{
  "type": "Feature",
  "properties": {
    "addr:full":"5731 Poplar Hall Dr Norfolk VA 23502",
    "addr:housenumber":"5731",
    "addr:postcode":"23502",
    "addr:street":"Poplar Hall Dr",
    "iso:country":"US",
    "sg:address":"5731 Poplar Hall Dr",
    "sg:city":"Norfolk",
    "sg:classifiers":[
        {
            "category":"Insurance",
            "subcategory":"Insurance Agent",
            "type":"Services"
        }
    ],
    "sg:phone":"+1 757 466 8600",
    "sg:postcode":"23502",
    "sg:province":"VA",
    "wof:name":"Affordable Insurance",
    "wof:placetype":"venue"
},
  "geometry": {"coordinates":[-76.209379,36.848718],"type":"Point"}
}