{
  "type": "Feature",
  "properties": {
    "addr:full":"3119 Chaparral Dr Roanoke VA 24018",
    "addr:housenumber":"3119",
    "addr:postcode":"24018",
    "addr:street":"Chaparral Dr",
    "iso:country":"US",
    "sg:address":"3119 Chaparral Dr",
    "sg:city":"Roanoke",
    "sg:classifiers":[
        {
            "category":"Banks & Credit Unions",
            "subcategory":"Bank",
            "type":"Services"
        }
    ],
    "sg:phone":"+1 540 989 1116",
    "sg:postcode":"24018",
    "sg:province":"VA",
    "wof:name":"B B & T",
    "wof:placetype":"venue"
},
  "geometry": {"coordinates":[-79.991159,37.223971],"type":"Point"}
}