{
  "type": "Feature",
  "properties": {
    "iso:country":"US",
    "sg:address":"3211 Washington Blvd",
    "sg:city":"Arlington",
    "sg:classifiers":[
        {
            "category":"Restaurant",
            "type":"Food & Drink"
        }
    ],
    "sg:menulink":"http://www.allmenus.com/va/arlington/260429-taste-of-morraco/menu/",
    "sg:phone":"+1 703 527 7468",
    "sg:postcode":"22201",
    "sg:province":"VA",
    "sg:tags":[
        "moroccan"
    ],
    "wof:name":"Taste of Morraco",
    "wof:placetype":"venue"
},
  "geometry": {"coordinates":[-77.09728699999999,38.886075],"type":"Point"}
}