{
  "type": "Feature",
  "properties": {
    "iso:country":"US",
    "sg:address":"10076 Possum Hollow Dr",
    "sg:city":"Delaplane",
    "sg:classifiers":[
        {
            "category":"Professional",
            "subcategory":"Research",
            "type":"Services"
        }
    ],
    "sg:phone":"+1 540 592 3864",
    "sg:postcode":"20144",
    "sg:province":"VA",
    "sg:tags":[
        "commercial",
        "physical"
    ],
    "wof:name":"Shadows In The Light",
    "wof:placetype":"venue"
},
  "geometry": {"coordinates":[-77.920537,38.954682],"type":"Point"}
}