{
  "type": "Feature",
  "properties": {
    "addr:full":"1828 Dillards Hill Rd Union Hall VA 24176",
    "addr:housenumber":"1828",
    "addr:postcode":"24176",
    "addr:street":"Dillards Hill Rd",
    "iso:country":"US",
    "sg:address":"1828 Dillards Hill Rd",
    "sg:city":"Union Hall",
    "sg:classifiers":[
        {
            "category":"Freight",
            "type":"Transportation"
        },
        {
            "category":"Recreation",
            "subcategory":"Marina",
            "type":"Entertainment"
        }
    ],
    "sg:phone":"+1 540 576 2034",
    "sg:postcode":"24176",
    "sg:province":"VA",
    "sg:tags":[
        "commercial",
        "operation",
        "storage"
    ],
    "wof:name":"T P's Self Storage",
    "wof:placetype":"venue"
},
  "geometry": {"coordinates":[-79.657735,37.02339],"type":"Point"}
}