{
  "type": "Feature",
  "properties": {
    "addr:full":"1110 Cedrus Ln Mc Lean VA 22102",
    "addr:housenumber":"1110",
    "addr:postcode":"22102",
    "addr:street":"Cedrus Ln Mc Lean",
    "iso:country":"US",
    "sg:address":"1110 Cedrus Ln",
    "sg:city":"Mc Lean",
    "sg:classifiers":[
        {
            "category":"Health Services",
            "subcategory":"Doctor",
            "type":"Services"
        }
    ],
    "sg:phone":"+1 703 759 4066",
    "sg:postcode":"22102",
    "sg:province":"VA",
    "sg:tags":[
        "medical"
    ],
    "wof:name":"Jack Wheeler Dr",
    "wof:placetype":"venue"
},
  "geometry": {"coordinates":[-77.249798,38.965228],"type":"Point"}
}