{
  "type": "Feature",
  "properties": {
    "iso:country":"US",
    "sg:address":"4641 Kenmore Ave",
    "sg:city":"Alexandria",
    "sg:classifiers":[
        {
            "category":"Building & Trades",
            "subcategory":"Construction",
            "type":"Services"
        }
    ],
    "sg:phone":"+1 703 370 1441",
    "sg:postcode":"22304",
    "sg:province":"VA",
    "sg:tags":[
        "contractor"
    ],
    "wof:name":"Ravensworth Construction Co",
    "wof:placetype":"venue"
},
  "geometry": {"coordinates":[-77.110592,38.829135],"type":"Point"}
}