{
  "type": "Feature",
  "properties": {
    "addr:full":"405 Main St Gretna VA 24557",
    "addr:housenumber":"405",
    "addr:postcode":"24557",
    "addr:street":"Main St",
    "iso:country":"US",
    "sg:address":"405 Main St",
    "sg:city":"Gretna",
    "sg:classifiers":[
        {
            "category":"Autos & Motor Vehicles",
            "subcategory":"Automobile Sales",
            "type":"Retail Goods"
        }
    ],
    "sg:phone":"+1 434 656 3541",
    "sg:postcode":"24557",
    "sg:province":"VA",
    "sg:tags":[
        "car",
        "dealer"
    ],
    "wof:name":"Classic Motor Sports",
    "wof:placetype":"venue"
},
  "geometry": {"coordinates":[-79.35729000000001,36.957056],"type":"Point"}
}