{
  "type": "Feature",
  "properties": {
    "iso:country":"US",
    "sg:address":"6 Long Ct",
    "sg:city":"Fredericksburg",
    "sg:classifiers":[
        {
            "category":"Professional",
            "subcategory":"Business Services",
            "type":"Services"
        }
    ],
    "sg:phone":"+1 540 372 1299",
    "sg:postcode":"22405",
    "sg:province":"VA",
    "wof:name":"Applied Geospatial Solutions",
    "wof:placetype":"venue"
},
  "geometry": {"coordinates":[-77.43077599999999,38.332437],"type":"Point"}
}