{
  "type": "Feature",
  "properties": {
    "iso:country":"US",
    "sg:address":"412 W Franklin St",
    "sg:city":"Richmond",
    "sg:classifiers":[
        {
            "category":"Real Estate",
            "subcategory":"Architect",
            "type":"Services"
        }
    ],
    "sg:phone":"+1 804 780 0070",
    "sg:postcode":"23220",
    "sg:province":"VA",
    "sg:tags":[
        "architectural"
    ],
    "sg:website":"www.harrisarchitects.org",
    "wof:name":"Harris William Henry & Assoc",
    "wof:placetype":"venue"
},
  "geometry": {"coordinates":[-77.447757,37.546501],"type":"Point"}
}