{
  "type": "Feature",
  "properties": {
    "addr:full":"14471 Brentwood Ct Woodbridge VA 22193",
    "addr:housenumber":"14471",
    "addr:postcode":"22193",
    "addr:street":"Brentwood Ct",
    "iso:country":"US",
    "sg:address":"14471 Brentwood Ct",
    "sg:city":"Woodbridge",
    "sg:classifiers":[
        {
            "category":"Building & Trades",
            "subcategory":"Landscaping Services",
            "type":"Services"
        }
    ],
    "sg:phone":"+1 703 670 8552",
    "sg:postcode":"22193",
    "sg:province":"VA",
    "sg:tags":[
        "cultural"
    ],
    "wof:name":"Elizabeth F Sharpe",
    "wof:placetype":"venue"
},
  "geometry": {"coordinates":[-77.31291,38.638828],"type":"Point"}
}