{
  "type": "Feature",
  "properties": {
    "addr:full":"8544 Thomas Nelson Hwy Lovingston VA 22949",
    "addr:housenumber":"8544",
    "addr:postcode":"22949",
    "addr:street":"Thomas Nelson Hwy",
    "iso:country":"US",
    "sg:address":"8544 Thomas Nelson Hwy",
    "sg:city":"Lovingston",
    "sg:classifiers":[
        {
            "category":"Organizations",
            "subcategory":"Non-profit Organization",
            "type":"Services"
        }
    ],
    "sg:phone":"+1 434 263 8119",
    "sg:postcode":"22949",
    "sg:province":"VA",
    "wof:name":"Monticello Community Action",
    "wof:placetype":"venue"
},
  "geometry": {"coordinates":[-78.879414,37.749535],"type":"Point"}
}