{
  "type": "Feature",
  "properties": {
    "addr:full":"249 N Madison Rd Orange VA 22960",
    "addr:housenumber":"249",
    "addr:postcode":"22960",
    "addr:street":"N Madison Rd",
    "iso:country":"US",
    "sg:address":"249 N Madison Rd",
    "sg:city":"Orange",
    "sg:classifiers":[
        {
            "category":"Autos & Motor Vehicles",
            "subcategory":"Automobile Sales",
            "type":"Retail Goods"
        }
    ],
    "sg:phone":"+1 540 672 3700",
    "sg:postcode":"22960",
    "sg:province":"VA",
    "sg:tags":[
        "car",
        "dealer"
    ],
    "sg:website":"www.reynolds-pontiac.com",
    "wof:name":"Reynolds Subaru Of Orange",
    "wof:placetype":"venue"
},
  "geometry": {"coordinates":[-78.11308099999999,38.249611],"type":"Point"}
}