{
  "type": "Feature",
  "properties": {
    "iso:country":"US",
    "sg:address":"1118 Professional Dr",
    "sg:city":"Williamsburg",
    "sg:classifiers":[
        {
            "category":"Health Services",
            "subcategory":"Doctor",
            "type":"Services"
        }
    ],
    "sg:phone":"+1 757 229 5570",
    "sg:postcode":"23185",
    "sg:province":"VA",
    "sg:tags":[
        "dentist"
    ],
    "wof:name":"Blaney Lachine Boxx & Bowe",
    "wof:placetype":"venue"
},
  "geometry": {"coordinates":[-76.735128,37.258241],"type":"Point"}
}