{
  "type": "Feature",
  "properties": {
    "iso:country":"US",
    "sg:address":"3516 Splitwood Rd",
    "sg:city":"Toano",
    "sg:classifiers":[
        {
            "category":"Building & Trades",
            "subcategory":"Construction",
            "type":"Services"
        }
    ],
    "sg:phone":"+1 757 566 3240",
    "sg:postcode":"23168",
    "sg:province":"VA",
    "sg:tags":[
        "house"
    ],
    "wof:name":"GCR Inc",
    "wof:placetype":"venue"
},
  "geometry": {"coordinates":[-76.808074,37.438231],"type":"Point"}
}