{
  "type": "Feature",
  "properties": {
    "addr:full":"134 Copps Hill Rd Buchanan VA 24066",
    "addr:housenumber":"134",
    "addr:postcode":"24066",
    "addr:street":"Copps Hill Rd",
    "iso:country":"US",
    "sg:address":"134 Copps Hill Rd",
    "sg:city":"Buchanan",
    "sg:classifiers":[
        {
            "category":"Organizations",
            "subcategory":"Religious Organization",
            "type":"Services"
        }
    ],
    "sg:phone":"+1 540 473 3513",
    "sg:postcode":"24066",
    "sg:province":"VA",
    "sg:tags":[
        "church"
    ],
    "wof:name":"Harold E Cook Jr",
    "wof:placetype":"venue"
},
  "geometry": {"coordinates":[-79.755487,37.549095],"type":"Point"}
}