{
  "type": "Feature",
  "properties": {
    "addr:full":"3022 S Crater Rd Petersburg VA 23805",
    "addr:housenumber":"3022",
    "addr:postcode":"23805",
    "addr:street":"S Crater Rd",
    "iso:country":"US",
    "sg:address":"3022 S Crater Rd",
    "sg:city":"Petersburg",
    "sg:classifiers":[
        {
            "category":"Retail",
            "subcategory":"Auto Repair",
            "type":"Services"
        }
    ],
    "sg:phone":"+1 804 722 0264",
    "sg:postcode":"23805",
    "sg:province":"VA",
    "sg:tags":[
        "repairing",
        "automobile"
    ],
    "wof:name":"J C's Auto Ctr",
    "wof:placetype":"venue"
},
  "geometry": {"coordinates":[-77.371835,37.190207],"type":"Point"}
}