{
  "type": "Feature",
  "properties": {
    "addr:full":"15033 Cardin Pl Woodbridge VA 22193",
    "addr:postcode":"15033;22193",
    "addr:street":"Cardin Pl",
    "iso:country":"US",
    "sg:address":"15033 Cardin Pl",
    "sg:city":"Woodbridge",
    "sg:classifiers":[
        {
            "category":"Professional",
            "type":"Services"
        }
    ],
    "sg:phone":"+1 703 730 3189",
    "sg:postcode":"22193",
    "sg:province":"VA",
    "wof:name":"New Era Trim Co",
    "wof:placetype":"venue"
},
  "geometry": {"coordinates":[-77.32046200000001,38.62792],"type":"Point"}
}