{
  "type": "Feature",
  "properties": {
    "addr:full":"9697 Main St Fairfax VA 22031",
    "addr:housenumber":"9697",
    "addr:postcode":"22031",
    "addr:street":"Main St",
    "iso:country":"US",
    "sg:address":"9697 Main St",
    "sg:city":"Fairfax",
    "sg:classifiers":[
        {
            "category":"Professional",
            "subcategory":"Accounting & Tax Preparation",
            "type":"Services"
        }
    ],
    "sg:phone":"+1 703 323 5085",
    "sg:postcode":"22031",
    "sg:province":"VA",
    "sg:tags":[
        "accountant"
    ],
    "wof:name":"Roger L Miller CPA",
    "wof:placetype":"venue"
},
  "geometry": {"coordinates":[-77.27708800000001,38.841904],"type":"Point"}
}