{
  "type": "Feature",
  "properties": {
    "iso:country":"US",
    "sg:address":"5205 Leesburg Pike",
    "sg:city":"Falls Church",
    "sg:classifiers":[
        {
            "category":"Retail",
            "subcategory":"Repair Shop",
            "type":"Services"
        }
    ],
    "sg:phone":"+1 703 845 8900",
    "sg:postcode":"22041",
    "sg:province":"VA",
    "sg:tags":[
        "equipment",
        "electronic",
        "supply"
    ],
    "wof:name":"ETD Electronics & Security",
    "wof:placetype":"venue"
},
  "geometry": {"coordinates":[-77.121015,38.847083],"type":"Point"}
}