{
  "type": "Feature",
  "properties": {
    "iso:country":"US",
    "sg:address":"4902 Herkimer St",
    "sg:city":"Annandale",
    "sg:classifiers":[
        {
            "category":"Building & Trades",
            "subcategory":"Electrical",
            "type":"Services"
        }
    ],
    "sg:phone":"+1 703 283 0869",
    "sg:postcode":"22003",
    "sg:province":"VA",
    "sg:tags":[
        "electrical",
        "contractor"
    ],
    "wof:name":"Lien Ngoc Huynh",
    "wof:placetype":"venue"
},
  "geometry": {"coordinates":[-77.219589,38.819126],"type":"Point"}
}