{
  "type": "Feature",
  "properties": {
    "addr:full":"4656 King St Alexandria VA 22302",
    "addr:housenumber":"4656",
    "addr:postcode":"22302",
    "addr:street":"King St",
    "iso:country":"US",
    "sg:address":"4656 King St",
    "sg:city":"Alexandria",
    "sg:classifiers":[
        {
            "category":"Professional",
            "type":"Services"
        }
    ],
    "sg:phone":"+1 703 379 6325",
    "sg:postcode":"22302",
    "sg:province":"VA",
    "wof:name":"Meal Deal",
    "wof:placetype":"venue"
},
  "geometry": {"coordinates":[-77.106932,38.840967],"type":"Point"}
}