{
  "type": "Feature",
  "properties": {
    "addr:full":"11821 Cornwell Dr Manassas VA 20112",
    "addr:postcode":"11821;20112",
    "addr:street":"Cornwell Dr",
    "iso:country":"US",
    "sg:address":"11821 Cornwell Dr",
    "sg:city":"Manassas",
    "sg:classifiers":[
        {
            "category":"Personal",
            "type":"Services"
        }
    ],
    "sg:phone":"+1 703 791 4377",
    "sg:postcode":"20112",
    "sg:province":"VA",
    "wof:name":"Modern Marks Tattoo Studio",
    "wof:placetype":"venue"
},
  "geometry": {"coordinates":[-77.411799,38.695566],"type":"Point"}
}