{
  "type": "Feature",
  "properties": {
    "addr:full":"5200 Hampton Blvd Norfolk VA 23508",
    "addr:housenumber":"5200",
    "addr:postcode":"23508",
    "addr:street":"Hampton Blvd",
    "iso:country":"US",
    "sg:address":"5200 Hampton Blvd",
    "sg:city":"Norfolk",
    "sg:classifiers":[
        {
            "category":"Museum",
            "type":"Entertainment"
        }
    ],
    "sg:phone":"+1 757 889 9479",
    "sg:postcode":"23508",
    "sg:province":"VA",
    "sg:tags":[
        "information",
        "galleries",
        "art",
        "consultant"
    ],
    "sg:website":"www.culturalalliance.org",
    "wof:name":"Cultural Alliance-Hampton Rds",
    "wof:placetype":"venue"
},
  "geometry": {"coordinates":[-76.303293,36.890176],"type":"Point"}
}