{
  "type": "Feature",
  "properties": {
    "addr:full":"520 N Main St Marion VA 24354",
    "addr:housenumber":"520",
    "addr:postcode":"24354",
    "addr:street":"N Main St",
    "iso:country":"US",
    "sg:address":"520 N Main St",
    "sg:city":"Marion",
    "sg:classifiers":[
        {
            "category":"Manufacturing",
            "subcategory":"Tools & Machinery",
            "type":"Manufacturing & Wholesale Goods"
        }
    ],
    "sg:phone":"+1 276 783 6410",
    "sg:postcode":"24354",
    "sg:province":"VA",
    "sg:tags":[
        "air",
        "parts",
        "conditioning",
        "supply"
    ],
    "wof:name":"Rector Supply Co",
    "wof:placetype":"venue"
},
  "geometry": {"coordinates":[-81.51497500000001,36.837889],"type":"Point"}
}