{
  "type": "Feature",
  "properties": {
    "iso:country":"US",
    "sg:address":"504 Clearview Dr",
    "sg:city":"Martinsville",
    "sg:classifiers":[
        {
            "category":"Organizations",
            "subcategory":"Religious Organization",
            "type":"Services"
        }
    ],
    "sg:phone":"+1 276 632 1843",
    "sg:postcode":"24112",
    "sg:province":"VA",
    "wof:name":"Clearview Gospel Mission",
    "wof:placetype":"venue"
},
  "geometry": {"coordinates":[-79.85821199999999,36.710473],"type":"Point"}
}