{
  "type": "Feature",
  "properties": {
    "addr:full":"52 S Main St Kilmarnock VA 22482",
    "addr:housenumber":"52",
    "addr:postcode":"22482",
    "addr:street":"S Main St",
    "iso:country":"US",
    "sg:address":"52 S Main St",
    "sg:city":"Kilmarnock",
    "sg:classifiers":[
        {
            "category":"Sports & Exercise",
            "subcategory":"Gym",
            "type":"Entertainment"
        }
    ],
    "sg:phone":"+1 804 436 0202",
    "sg:postcode":"22482",
    "sg:province":"VA",
    "sg:tags":[
        "club",
        "health",
        "studio",
        "gymnasium"
    ],
    "wof:name":"Jim's Gym",
    "wof:placetype":"venue"
},
  "geometry": {"coordinates":[-76.37980899999999,37.709625],"type":"Point"}
}