{
  "type": "Feature",
  "properties": {
    "addr:full":"14672 Blunts Bridge Rd Doswell VA 23047",
    "addr:housenumber":"14672",
    "addr:postcode":"23047",
    "addr:street":"Blunts Bridge Rd",
    "iso:country":"US",
    "sg:address":"14672 Blunts Bridge Rd",
    "sg:city":"Doswell",
    "sg:classifiers":[
        {
            "category":"Building & Trades",
            "subcategory":"Construction",
            "type":"Services"
        }
    ],
    "sg:phone":"+1 804 227 3314",
    "sg:postcode":"23047",
    "sg:province":"VA",
    "sg:tags":[
        "mason"
    ],
    "wof:name":"Ds Borkey Masonry LLC",
    "wof:placetype":"venue"
},
  "geometry": {"coordinates":[-77.509636,37.807781],"type":"Point"}
}