{
  "type": "Feature",
  "properties": {
    "addr:full":"14069 Wellman Ct Manassas VA 20112",
    "addr:housenumber":"14069",
    "addr:postcode":"20112",
    "addr:street":"Wellman Ct",
    "iso:country":"US",
    "sg:address":"14069 Wellman Ct",
    "sg:city":"Manassas",
    "sg:classifiers":[
        {
            "category":"Building & Trades",
            "subcategory":"Landscaping Services",
            "type":"Services"
        }
    ],
    "sg:phone":"+1 703 368 6961",
    "sg:postcode":"20112",
    "sg:province":"VA",
    "wof:name":"E Tees Lawn Care",
    "wof:placetype":"venue"
},
  "geometry": {"coordinates":[-77.407263,38.646253],"type":"Point"}
}