{
  "type": "Feature",
  "properties": {
    "addr:full":"30 Franklin Rd SW Roanoke VA 24011",
    "addr:housenumber":"30",
    "addr:postcode":"24011",
    "addr:street":"Franklin Rd Sw",
    "iso:country":"US",
    "sg:address":"30 Franklin Rd SW",
    "sg:city":"Roanoke",
    "sg:classifiers":[
        {
            "category":"Professional",
            "subcategory":"Lawyer & Legal Services",
            "type":"Services"
        }
    ],
    "sg:phone":"+1 540 343 2956",
    "sg:postcode":"24011",
    "sg:province":"VA",
    "sg:tags":[
        "attorney"
    ],
    "wof:name":"Brumberg Mackey & Wall",
    "wof:placetype":"venue"
},
  "geometry": {"coordinates":[-79.94211199999999,37.269177],"type":"Point"}
}