{
  "type": "Feature",
  "properties": {
    "iso:country":"US",
    "sg:address":"212 5th St NE",
    "sg:city":"Charlottesville",
    "sg:classifiers":[
        {
            "category":"Shopping",
            "subcategory":"Jewelry",
            "type":"Retail Goods"
        }
    ],
    "sg:phone":"+1 434 296 6463",
    "sg:postcode":"22902",
    "sg:province":"VA",
    "sg:tags":[
        "jeweler"
    ],
    "sg:website":"www.signetgallery.com",
    "wof:name":"Signet Gallery",
    "wof:placetype":"venue"
},
  "geometry": {"coordinates":[-78.47779800000001,38.030899],"type":"Point"}
}