{
  "type": "Feature",
  "properties": {
    "addr:full":"1900 Twin Lake Dr Bedford VA 24523",
    "addr:housenumber":"1900",
    "addr:postcode":"24523",
    "addr:street":"Twin Lake Dr",
    "iso:country":"US",
    "sg:address":"1900 Twin Lake Dr",
    "sg:city":"Bedford",
    "sg:classifiers":[
        {
            "category":"Shopping",
            "subcategory":"Discount & Variety Stores",
            "type":"Retail Goods"
        }
    ],
    "sg:phone":"+1 540 587 0476",
    "sg:postcode":"24523",
    "sg:province":"VA",
    "sg:tags":[
        "merchandise",
        "general"
    ],
    "wof:name":"Hippo Enterprises",
    "wof:placetype":"venue"
},
  "geometry": {"coordinates":[-79.464508,37.305146],"type":"Point"}
}