{
  "type": "Feature",
  "properties": {
    "addr:full":"230 S Main St Amherst VA 24521",
    "addr:housenumber":"230",
    "addr:postcode":"24521",
    "addr:street":"S Main St",
    "iso:country":"US",
    "sg:address":"230 S Main St",
    "sg:city":"Amherst",
    "sg:classifiers":[
        {
            "category":"Professional",
            "subcategory":"Lawyer & Legal Services",
            "type":"Services"
        }
    ],
    "sg:phone":"+1 434 946 0900",
    "sg:postcode":"24521",
    "sg:province":"VA",
    "sg:tags":[
        "attorney"
    ],
    "wof:name":"Glenn R Hilton Law Office",
    "wof:placetype":"venue"
},
  "geometry": {"coordinates":[-79.052165,37.584876],"type":"Point"}
}