{
  "type": "Feature",
  "properties": {
    "addr:full":"8002 Atlantic Ave Virginia Beach VA 23451",
    "addr:housenumber":"8002",
    "addr:postcode":"23451",
    "addr:street":"Atlantic Ave",
    "iso:country":"US",
    "sg:address":"8002 Atlantic Ave",
    "sg:city":"Virginia Beach",
    "sg:classifiers":[
        {
            "category":"Building & Trades",
            "subcategory":"Landscaping Services",
            "type":"Services"
        }
    ],
    "sg:phone":"+1 757 428 1262",
    "sg:postcode":"23451",
    "sg:province":"VA",
    "sg:tags":[
        "landscape"
    ],
    "wof:name":"Cypress Landscaping",
    "wof:placetype":"venue"
},
  "geometry": {"coordinates":[-75.992981,36.905449],"type":"Point"}
}