{
  "type": "Feature",
  "properties": {
    "iso:country":"US",
    "sg:address":"6437 Centralia Rd",
    "sg:city":"Chesterfield",
    "sg:classifiers":[
        {
            "category":"Home & Garden",
            "subcategory":"Hardware",
            "type":"Retail Goods"
        }
    ],
    "sg:phone":"+1 804 768 9464",
    "sg:postcode":"23832",
    "sg:province":"VA",
    "wof:name":"Pleasants Hardware Inc",
    "wof:placetype":"venue"
},
  "geometry": {"coordinates":[-77.498811,37.37366],"type":"Point"}
}