{
  "type": "Feature",
  "properties": {
    "addr:full":"8415 Westpointe Dr Fairfax Station VA 22039",
    "addr:housenumber":"8415",
    "addr:postcode":"22039",
    "addr:street":"Westpointe Dr",
    "iso:country":"US",
    "sg:address":"8415 Westpointe Dr",
    "sg:city":"Fairfax Station",
    "sg:classifiers":[
        {
            "category":"Manufacturing",
            "subcategory":"Metals",
            "type":"Manufacturing & Wholesale Goods"
        }
    ],
    "sg:phone":"+1 703 690 5902",
    "sg:postcode":"22039",
    "sg:province":"VA",
    "sg:tags":[
        "rope",
        "adjusting",
        "connecting",
        "devices",
        "mfg"
    ],
    "wof:name":"Kwik Knot",
    "wof:placetype":"venue"
},
  "geometry": {"coordinates":[-77.278971,38.728551],"type":"Point"}
}