{
  "type": "Feature",
  "properties": {
    "addr:full":"170 Water St Christiansburg VA 24073",
    "addr:housenumber":"170",
    "addr:postcode":"24073",
    "addr:street":"Water St",
    "iso:country":"US",
    "sg:address":"170 Water St",
    "sg:city":"Christiansburg",
    "sg:classifiers":[
        {
            "category":"Retail",
            "subcategory":"Laundry & Dry Cleaning",
            "type":"Services"
        }
    ],
    "sg:phone":"+1 540 382 1249",
    "sg:postcode":"24073",
    "sg:province":"VA",
    "sg:tags":[
        "cleaner",
        "rug",
        "carpet"
    ],
    "wof:name":"Classic Carpet Cleaning",
    "wof:placetype":"venue"
},
  "geometry": {"coordinates":[-80.410568,37.135208],"type":"Point"}
}