{
  "type": "Feature",
  "properties": {
    "addr:full":"3261 Birchdale Sq Woodbridge VA 22193",
    "addr:housenumber":"3261",
    "addr:postcode":"22193",
    "addr:street":"Birchdale Sq",
    "iso:country":"US",
    "sg:address":"3261 Birchdale Sq",
    "sg:city":"Woodbridge",
    "sg:classifiers":[
        {
            "category":"Restaurant",
            "type":"Food & Drink"
        }
    ],
    "sg:phone":"+1 703 897 8268",
    "sg:postcode":"22193",
    "sg:province":"VA",
    "sg:tags":[
        "eating"
    ],
    "wof:name":"Moon General Corp",
    "wof:placetype":"venue"
},
  "geometry": {"coordinates":[-77.309924,38.629542],"type":"Point"}
}