{
  "type": "Feature",
  "properties": {
    "addr:full":"5508 Centralia Rd Richmond VA 23237",
    "addr:housenumber":"5508",
    "addr:postcode":"23237",
    "addr:street":"Centralia Rd",
    "iso:country":"US",
    "sg:address":"5508 Centralia Rd",
    "sg:city":"Richmond",
    "sg:classifiers":[
        {
            "category":"Building & Trades",
            "subcategory":"Construction",
            "type":"Services"
        }
    ],
    "sg:phone":"+1 804 751 0026",
    "sg:postcode":"23237",
    "sg:province":"VA",
    "sg:tags":[
        "downspout",
        "gutter",
        "contractor"
    ],
    "wof:name":"Professional Door Service",
    "wof:placetype":"venue"
},
  "geometry": {"coordinates":[-77.480176,37.377339],"type":"Point"}
}