{
  "type": "Feature",
  "properties": {
    "addr:full":"212 Dunbar Ave Dublin VA 24084",
    "addr:housenumber":"212",
    "addr:postcode":"24084",
    "addr:street":"Dunbar Ave",
    "iso:country":"US",
    "sg:address":"212 Dunbar Ave",
    "sg:city":"Dublin",
    "sg:classifiers":[
        {
            "category":"Building & Trades",
            "subcategory":"Construction",
            "type":"Services"
        }
    ],
    "sg:phone":"+1 540 674 1700",
    "sg:postcode":"24084",
    "sg:province":"VA",
    "sg:tags":[
        "altering",
        "remodeling",
        "contractor"
    ],
    "wof:name":"Hub Contractors",
    "wof:placetype":"venue"
},
  "geometry": {"coordinates":[-80.686047,37.101586],"type":"Point"}
}