{
  "type": "Feature",
  "properties": {
    "addr:full":"19365 Cypress Ridge Ter Leesburg VA 20176",
    "addr:housenumber":"19365",
    "addr:postcode":"20176",
    "addr:street":"Cypress Ridge Ter",
    "iso:country":"US",
    "sg:address":"19365 Cypress Ridge Ter",
    "sg:city":"Leesburg",
    "sg:classifiers":[
        {
            "category":"Farming",
            "subcategory":"Farm",
            "type":"Manufacturing & Wholesale Goods"
        }
    ],
    "sg:phone":"+1 540 668 6687",
    "sg:postcode":"20176",
    "sg:province":"VA",
    "sg:website":"www.kordfarm.com",
    "wof:name":"KORD Farm",
    "wof:placetype":"venue"
},
  "geometry": {"coordinates":[-77.472044,39.080208],"type":"Point"}
}