{
  "type": "Feature",
  "properties": {
    "addr:full":"121 N Bridge St Bedford VA 24523",
    "addr:housenumber":"121",
    "addr:postcode":"24523",
    "addr:street":"N Bridge St",
    "iso:country":"US",
    "sg:address":"121 N Bridge St",
    "sg:city":"Bedford",
    "sg:classifiers":[
        {
            "category":"Education",
            "subcategory":"Dance Studio",
            "type":"Public Place"
        }
    ],
    "sg:phone":"+1 540 587 7555",
    "sg:postcode":"24523",
    "sg:province":"VA",
    "sg:tags":[
        "instruction",
        "dancing"
    ],
    "wof:name":"Leeanne Ashley Studio Of Dance",
    "wof:placetype":"venue"
},
  "geometry": {"coordinates":[-79.523314,37.33511],"type":"Point"}
}