{
  "type": "Feature",
  "properties": {
    "addr:full":"1124 Old Jonesboro Rd Bristol VA 37620",
    "addr:housenumber":"1124",
    "addr:postcode":"37620",
    "addr:street":"Old Jonesboro Rd",
    "iso:country":"US",
    "sg:address":"1124 Old Jonesboro Rd",
    "sg:city":"Bristol",
    "sg:classifiers":[
        {
            "category":"Building & Trades",
            "subcategory":"Construction",
            "type":"Services"
        }
    ],
    "sg:phone":"+1 423 878 6775",
    "sg:postcode":"37620",
    "sg:province":"VA",
    "sg:tags":[
        "house"
    ],
    "wof:name":"Larry Duncan New Homes & Rmdlg",
    "wof:placetype":"venue"
},
  "geometry": {"coordinates":[-82.148622,36.56834],"type":"Point"}
}