{
  "type": "Feature",
  "properties": {
    "addr:full":"102 N Main St Culpeper VA 22701",
    "addr:housenumber":"102",
    "addr:postcode":"22701",
    "addr:street":"N Main St",
    "iso:country":"US",
    "sg:address":"102 N Main St",
    "sg:city":"Culpeper",
    "sg:classifiers":[
        {
            "category":"Banks & Credit Unions",
            "subcategory":"Bank",
            "type":"Services"
        }
    ],
    "sg:phone":"+1 540 727 8000",
    "sg:postcode":"22701",
    "sg:province":"VA",
    "sg:tags":[
        "mortgage"
    ],
    "wof:name":"Countrywide",
    "wof:placetype":"venue"
},
  "geometry": {"coordinates":[-77.995953,38.474002],"type":"Point"}
}