{
  "type": "Feature",
  "properties": {
    "addr:full":"2320 Francine Rd Richmond VA 23235",
    "addr:housenumber":"2320",
    "addr:postcode":"23235",
    "addr:street":"Francine Rd",
    "iso:country":"US",
    "sg:address":"2320 Francine Rd",
    "sg:city":"Richmond",
    "sg:classifiers":[
        {
            "category":"Professional",
            "subcategory":"Business Services",
            "type":"Services"
        }
    ],
    "sg:phone":"+1 804 272 9504",
    "sg:postcode":"23235",
    "sg:province":"VA",
    "sg:tags":[
        "interior",
        "designer"
    ],
    "wof:name":"Indesign",
    "wof:placetype":"venue"
},
  "geometry": {"coordinates":[-77.58889000000001,37.52738],"type":"Point"}
}