{
  "type": "Feature",
  "properties": {
    "addr:full":"10941 Catharpin Rd Spotsylvania VA 22553",
    "addr:housenumber":"10941",
    "addr:postcode":"22553",
    "addr:street":"Catharpin Rd",
    "iso:country":"US",
    "sg:address":"10941 Catharpin Rd",
    "sg:city":"Spotsylvania",
    "sg:classifiers":[
        {
            "category":"Food & Beverages",
            "subcategory":"Groceries & Convenience Stores",
            "type":"Retail Goods"
        }
    ],
    "sg:phone":"+1 540 786 0308",
    "sg:postcode":"22553",
    "sg:province":"VA",
    "sg:tags":[
        "station",
        "gasoline"
    ],
    "wof:name":"C & J Exxon",
    "wof:placetype":"venue"
},
  "geometry": {"coordinates":[-77.64919500000001,38.253402],"type":"Point"}
}