{
  "type": "Feature",
  "properties": {
    "addr:full":"8508 Spalding Dr Richmond VA 23229",
    "addr:housenumber":"8508",
    "addr:postcode":"23229",
    "addr:street":"Spalding Dr",
    "iso:country":"US",
    "sg:address":"8508 Spalding Dr",
    "sg:city":"Richmond",
    "sg:classifiers":[
        {
            "category":"Personal",
            "subcategory":"Beauty Salon",
            "type":"Services"
        }
    ],
    "sg:phone":"+1 804 754 2110",
    "sg:postcode":"23229",
    "sg:province":"VA",
    "sg:tags":[
        "shop"
    ],
    "wof:name":"Charles K Shears",
    "wof:placetype":"venue"
},
  "geometry": {"coordinates":[-77.564058,37.598568],"type":"Point"}
}