{
  "type": "Feature",
  "properties": {
    "addr:full":"1201 Old Franklin Tpke Rocky Mount VA 24151",
    "addr:housenumber":"1201",
    "addr:postcode":"24151",
    "addr:street":"Old Franklin Tpke",
    "iso:country":"US",
    "sg:address":"1201 Old Franklin Tpke",
    "sg:city":"Rocky Mount",
    "sg:classifiers":[
        {
            "category":"Professional",
            "subcategory":"Lawyer & Legal Services",
            "type":"Services"
        }
    ],
    "sg:phone":"+1 540 483 1216",
    "sg:postcode":"24151",
    "sg:province":"VA",
    "sg:tags":[
        "attorney"
    ],
    "wof:name":"Carolyn H Furrow",
    "wof:placetype":"venue"
},
  "geometry": {"coordinates":[-79.85848300000001,37.017967],"type":"Point"}
}