{
  "type": "Feature",
  "properties": {
    "addr:full":"3015 Jefferson Davis Hwy Richmond VA 23234",
    "addr:housenumber":"3015",
    "addr:postcode":"23234",
    "addr:street":"Jefferson Davis Hwy",
    "iso:country":"US",
    "sg:address":"3015 Jefferson Davis Hwy",
    "sg:city":"Richmond",
    "sg:classifiers":[
        {
            "category":"Travel",
            "subcategory":"Hotels & Motels",
            "type":"Entertainment"
        }
    ],
    "sg:phone":"+1 804 231 1196",
    "sg:postcode":"23234",
    "sg:province":"VA",
    "wof:name":"Econo Lodge",
    "wof:placetype":"venue"
},
  "geometry": {"coordinates":[-77.44440299999999,37.481665],"type":"Point"}
}