{
  "type": "Feature",
  "properties": {
    "addr:full":"9231 Cynthia St Manassas Park VA 20111",
    "addr:housenumber":"9231",
    "addr:postcode":"20111",
    "addr:street":"Cynthia St Manassas Park",
    "iso:country":"US",
    "sg:address":"9231 Cynthia St",
    "sg:city":"Manassas Park",
    "sg:classifiers":[
        {
            "category":"Real Estate",
            "subcategory":"Real Estate Agent",
            "type":"Services"
        }
    ],
    "sg:phone":"+1 703 368 5976",
    "sg:postcode":"20111",
    "sg:province":"VA",
    "sg:tags":[
        "appraiser"
    ],
    "wof:name":"Appraisal Services Of Virginia",
    "wof:placetype":"venue"
},
  "geometry": {"coordinates":[-77.423666,38.767135],"type":"Point"}
}