{
  "type": "Feature",
  "properties": {
    "addr:full":"416 S Main St Hillsville VA 24343",
    "addr:housenumber":"416",
    "addr:postcode":"24343",
    "addr:street":"S Main St",
    "iso:country":"US",
    "sg:address":"416 S Main St",
    "sg:city":"Hillsville",
    "sg:classifiers":[
        {
            "category":"Health Services",
            "subcategory":"Nursing And Care Facility",
            "type":"Services"
        }
    ],
    "sg:phone":"+1 276 728 2405",
    "sg:postcode":"24343",
    "sg:province":"VA",
    "sg:tags":[
        "hospice"
    ],
    "wof:name":"Hospice Of Surry Co",
    "wof:placetype":"venue"
},
  "geometry": {"coordinates":[-80.733576,36.757551],"type":"Point"}
}