{
  "type": "Feature",
  "properties": {
    "addr:full":"5140 Wilson Boulevard Arlington VA 22205",
    "addr:housenumber":"5140",
    "addr:postcode":"22205",
    "addr:street":"Wilson Boulevard",
    "iso:country":"US",
    "sg:address":"5140 Wilson Boulevard",
    "sg:city":"Arlington",
    "sg:classifiers":[
        {
            "category":"Home & Garden",
            "subcategory":"Home Furnishings",
            "type":"Retail Goods"
        },
        {
            "category":"Shopping",
            "subcategory":"Antiques",
            "type":"Retail Goods"
        },
        {
            "category":"Home & Garden",
            "subcategory":"Furniture",
            "type":"Retail Goods"
        }
    ],
    "sg:phone":"+1 703 593 2166",
    "sg:postcode":"22205",
    "sg:province":"VA",
    "sg:tags":[
        "decor",
        "store"
    ],
    "wof:name":"No Place Like Home",
    "wof:placetype":"venue"
},
  "geometry": {"coordinates":[-77.124009,38.877271],"type":"Point"}
}