{
  "type": "Feature",
  "properties": {
    "iso:country":"US",
    "sg:address":"7499 River Rd",
    "sg:city":"Newport News",
    "sg:classifiers":[
        {
            "category":"Recreation",
            "subcategory":"Marina",
            "type":"Entertainment"
        }
    ],
    "sg:phone":"+1 757 247 2359",
    "sg:postcode":"23607",
    "sg:province":"VA",
    "sg:tags":[
        "operation"
    ],
    "wof:name":"Lee Ward Municipal Marina",
    "wof:placetype":"venue"
},
  "geometry": {"coordinates":[-76.45061699999999,37.011309],"type":"Point"}
}