{
  "type": "Feature",
  "properties": {
    "addr:full":"1016 Monroe Bay Ave Colonial Beach VA 22443",
    "addr:housenumber":"1016",
    "addr:postcode":"beach;22443",
    "addr:street":"Monroe Bay Ave",
    "iso:country":"US",
    "sg:address":"1016 Monroe Bay Ave",
    "sg:city":"Colonial Beach",
    "sg:classifiers":[
        {
            "category":"Restaurant",
            "type":"Food & Drink"
        }
    ],
    "sg:phone":"+1 804 224 7090",
    "sg:postcode":"22443",
    "sg:province":"VA",
    "wof:name":"Parkers Crab Shore",
    "wof:placetype":"venue"
},
  "geometry": {"coordinates":[-76.961268,38.239401],"type":"Point"}
}