{
  "type": "Feature",
  "properties": {
    "addr:full":"1200 N Main St Suffolk VA 23434",
    "addr:housenumber":"1200",
    "addr:postcode":"23434",
    "addr:street":"N Main St",
    "iso:country":"US",
    "sg:address":"1200 N Main St",
    "sg:city":"Suffolk",
    "sg:classifiers":[
        {
            "category":"Health Services",
            "subcategory":"Optometrist",
            "type":"Services"
        }
    ],
    "sg:phone":"+1 757 925 0495",
    "sg:postcode":"23434",
    "sg:province":"VA",
    "wof:name":"Gregory P Jellenek OD & Assoc",
    "wof:placetype":"venue"
},
  "geometry": {"coordinates":[-76.58334000000001,36.750893],"type":"Point"}
}