{
  "type": "Feature",
  "properties": {
    "addr:full":"4207 40th St N Arlington VA 22207",
    "addr:housenumber":"4207",
    "addr:postcode":"22207",
    "addr:street":"40Th St N",
    "iso:country":"US",
    "sg:address":"4207 40th St N",
    "sg:city":"Arlington",
    "sg:classifiers":[
        {
            "category":"Professional",
            "subcategory":"Management & Consulting",
            "type":"Services"
        }
    ],
    "sg:phone":"+1 703 532 3239",
    "sg:postcode":"22207",
    "sg:province":"VA",
    "sg:tags":[
        "construction"
    ],
    "wof:name":"Crozier & Assoc",
    "wof:placetype":"venue"
},
  "geometry": {"coordinates":[-77.129757,38.925172],"type":"Point"}
}