{
  "type": "Feature",
  "properties": {
    "addr:full":"2692 Nestlebrook Trl Virginia Beach VA 23456",
    "addr:housenumber":"2692",
    "addr:postcode":"23456",
    "addr:street":"Nestlebrook Trl",
    "iso:country":"US",
    "sg:address":"2692 Nestlebrook Trl",
    "sg:city":"Virginia Beach",
    "sg:classifiers":[
        {
            "category":"Professional",
            "subcategory":"Management & Consulting",
            "type":"Services"
        }
    ],
    "sg:phone":"+1 757 721 5040",
    "sg:postcode":"23456",
    "sg:province":"VA",
    "sg:tags":[
        "consultant"
    ],
    "wof:name":"Klett Consulting Group Inc",
    "wof:placetype":"venue"
},
  "geometry": {"coordinates":[-76.061018,36.723967],"type":"Point"}
}