{
  "type": "Feature",
  "properties": {
    "iso:country":"US",
    "sg:address":"1932 Blue Ridge Rd",
    "sg:city":"Charlottesville",
    "sg:classifiers":[
        {
            "category":"Real Estate",
            "subcategory":"Real Estate Operator",
            "type":"Services"
        }
    ],
    "sg:phone":"+1 434 977 3163",
    "sg:postcode":"22903",
    "sg:province":"VA",
    "sg:tags":[
        "building",
        "apartment"
    ],
    "wof:name":"Sewells Park Apts LLC",
    "wof:placetype":"venue"
},
  "geometry": {"coordinates":[-78.49313600000001,38.051033],"type":"Point"}
}