{
  "type": "Feature",
  "properties": {
    "iso:country":"US",
    "sg:address":"523 W 24th St",
    "sg:city":"Norfolk",
    "sg:classifiers":[
        {
            "category":"Professional",
            "subcategory":"Business Services",
            "type":"Services"
        }
    ],
    "sg:phone":"+1 757 622 5255",
    "sg:postcode":"23517",
    "sg:province":"VA",
    "sg:tags":[
        "interior",
        "design"
    ],
    "wof:name":"Candace Altschul",
    "wof:placetype":"venue"
},
  "geometry": {"coordinates":[-76.292148,36.871838],"type":"Point"}
}