{
  "type": "Feature",
  "properties": {
    "addr:full":"111 Mayberry Rd Mouth Of Wilson VA 24363",
    "addr:housenumber":"111",
    "addr:postcode":"24363",
    "addr:street":"Mayberry Rd",
    "iso:country":"US",
    "sg:address":"111 Mayberry Rd",
    "sg:city":"Mouth Of Wilson",
    "sg:classifiers":[
        {
            "category":"Farming",
            "subcategory":"Dairy Farm",
            "type":"Manufacturing & Wholesale Goods"
        }
    ],
    "sg:phone":"+1 276 579 7865",
    "sg:postcode":"24363",
    "sg:province":"VA",
    "wof:name":"Clinton Cunningham",
    "wof:placetype":"venue"
},
  "geometry": {"coordinates":[-81.388527,36.575147],"type":"Point"}
}