{
  "type": "Feature",
  "properties": {
    "addr:full":"3551 Jefferson Davis Hwy Alexandria VA 22305",
    "addr:housenumber":"3551",
    "addr:postcode":"22305",
    "addr:street":"Jefferson Davis Hwy",
    "iso:country":"US",
    "sg:address":"3551 Jefferson Davis Hwy",
    "sg:city":"Alexandria",
    "sg:classifiers":[
        {
            "category":"Shopping",
            "subcategory":"Shoes",
            "type":"Retail Goods"
        }
    ],
    "sg:phone":"+1 703 519 3788",
    "sg:postcode":"22305",
    "sg:province":"VA",
    "sg:tags":[
        "store"
    ],
    "sg:website":"http://www.rackroomshoes.com",
    "wof:name":"Rack Room Shoes",
    "wof:placetype":"venue"
},
  "geometry": {"coordinates":[-77.051903,38.8368],"type":"Point"}
}