{
  "type": "Feature",
  "properties": {
    "iso:country":"US",
    "sg:address":"3703 S Main St",
    "sg:city":"Blacksburg",
    "sg:classifiers":[
        {
            "category":"Restaurant",
            "type":"Food & Drink"
        }
    ],
    "sg:phone":"+1 540 951 7300",
    "sg:postcode":"24060",
    "sg:province":"VA",
    "sg:tags":[
        "eating"
    ],
    "wof:name":"Cinco De Mayo Restaurant Inc",
    "wof:placetype":"venue"
},
  "geometry": {"coordinates":[-80.40641100000001,37.188186],"type":"Point"}
}