{
  "type": "Feature",
  "properties": {
    "iso:country":"US",
    "sg:address":"1856 Virginia Ave",
    "sg:city":"Martinsville",
    "sg:classifiers":[
        {
            "category":"Government",
            "subcategory":"Office",
            "type":"Public Place"
        }
    ],
    "sg:phone":"+1 276 638 8026",
    "sg:postcode":"24112",
    "sg:province":"VA",
    "sg:tags":[
        "armed",
        "force",
        "recruiting"
    ],
    "wof:name":"US Marine Corps Recruiting",
    "wof:placetype":"venue"
},
  "geometry": {"coordinates":[-79.907856,36.704282],"type":"Point"}
}