{
  "type": "Feature",
  "properties": {
    "addr:full":"17407 Halligan Park Rd Carson VA 23830",
    "addr:housenumber":"17407",
    "addr:postcode":"23830",
    "addr:street":"Halligan Park Rd",
    "iso:country":"US",
    "sg:address":"17407 Halligan Park Rd",
    "sg:city":"Carson",
    "sg:classifiers":[
        {
            "category":"Organizations",
            "subcategory":"Religious Organization",
            "type":"Services"
        }
    ],
    "sg:phone":"+1 434 246 6969",
    "sg:postcode":"23830",
    "sg:province":"VA",
    "sg:tags":[
        "church"
    ],
    "wof:name":"Carson United Methodist Church",
    "wof:placetype":"venue"
},
  "geometry": {"coordinates":[-77.39607100000001,37.031143],"type":"Point"}
}