{
  "type": "Feature",
  "properties": {
    "addr:full":"5649 Lee Hwy Arlington VA 22207",
    "addr:housenumber":"5649",
    "addr:postcode":"22207",
    "addr:street":"Lee Hwy",
    "iso:country":"US",
    "sg:address":"5649 Lee Hwy",
    "sg:city":"Arlington",
    "sg:classifiers":[
        {
            "category":"Farming",
            "subcategory":"Fish & Marine Products",
            "type":"Manufacturing & Wholesale Goods"
        },
        {
            "category":"Professional",
            "subcategory":"Art Services",
            "type":"Services"
        }
    ],
    "sg:phone":"+1 703 534 1866",
    "sg:postcode":"22207",
    "sg:province":"VA",
    "sg:tags":[
        "picture",
        "frame",
        "conservation",
        "framing",
        "restoration"
    ],
    "sg:website":"http://www.bokframing.com",
    "wof:name":"Bok Custom Framing",
    "wof:placetype":"venue"
},
  "geometry": {"coordinates":[-77.14130299999999,38.895516],"type":"Point"}
}