{
  "type": "Feature",
  "properties": {
    "addr:full":"110 James Madison St Remington VA 22734",
    "addr:housenumber":"110",
    "addr:postcode":"22734",
    "addr:street":"James Madison St",
    "iso:country":"US",
    "sg:address":"110 James Madison St",
    "sg:city":"Remington",
    "sg:classifiers":[
        {
            "category":"Retail",
            "subcategory":"Auto Repair",
            "type":"Services"
        }
    ],
    "sg:phone":"+1 540 439 6620",
    "sg:postcode":"22734",
    "sg:province":"VA",
    "sg:tags":[
        "repairing",
        "automobile"
    ],
    "wof:name":"Remington Auto Work",
    "wof:placetype":"venue"
},
  "geometry": {"coordinates":[-77.808393,38.5339],"type":"Point"}
}