{
  "type": "Feature",
  "properties": {
    "iso:country":"US",
    "sg:address":"7900 Sudley Rd Ste 409",
    "sg:city":"Manassas",
    "sg:classifiers":[
        {
            "category":"Banks & Credit Unions",
            "subcategory":"Atm",
            "type":"Services"
        }
    ],
    "sg:phone":"+1 703 335 7793",
    "sg:postcode":"20109",
    "sg:province":"VA",
    "sg:tags":[
        "bankruptcy"
    ],
    "wof:name":"Weed Robert Ross Atty",
    "wof:placetype":"venue"
},
  "geometry": {"coordinates":[-77.51309999999999,38.785],"type":"Point"}
}