{
  "type": "Feature",
  "properties": {
    "addr:full":"8513 Claypool Rd Richmond VA 23236",
    "addr:housenumber":"8513",
    "addr:postcode":"23236",
    "addr:street":"Claypool Rd",
    "iso:country":"US",
    "sg:address":"8513 Claypool Rd",
    "sg:city":"Richmond",
    "sg:classifiers":[
        {
            "category":"Recreation",
            "type":"Entertainment"
        }
    ],
    "sg:phone":"+1 804 276 9192",
    "sg:postcode":"23236",
    "sg:province":"VA",
    "wof:name":"Appling & Associates",
    "wof:placetype":"venue"
},
  "geometry": {"coordinates":[-77.556764,37.485546],"type":"Point"}
}