{
  "type": "Feature",
  "properties": {
    "addr:full":"129 Tynes St Suffolk VA 23434",
    "addr:housenumber":"129",
    "addr:postcode":"23434",
    "addr:street":"Tynes St",
    "iso:country":"US",
    "sg:address":"129 Tynes St",
    "sg:city":"Suffolk",
    "sg:classifiers":[
        {
            "category":"Personal",
            "subcategory":"Barber",
            "type":"Services"
        }
    ],
    "sg:phone":"+1 757 934 8050",
    "sg:postcode":"23434",
    "sg:province":"VA",
    "sg:tags":[
        "shop"
    ],
    "wof:name":"Styles By Impression",
    "wof:placetype":"venue"
},
  "geometry": {"coordinates":[-76.57810600000001,36.726259],"type":"Point"}
}