{
  "type": "Feature",
  "properties": {
    "addr:full":"21253 Rosetta Pl Ashburn VA 20147",
    "addr:postcode":"21253;20147",
    "addr:street":"Rosetta Pl",
    "iso:country":"US",
    "sg:address":"21253 Rosetta Pl",
    "sg:city":"Ashburn",
    "sg:classifiers":[
        {
            "category":"Professional",
            "subcategory":"Computer Services",
            "type":"Services"
        }
    ],
    "sg:phone":"+1 703 724 7887",
    "sg:postcode":"20147",
    "sg:province":"VA",
    "sg:tags":[
        "consultant",
        "designer"
    ],
    "wof:name":"It Cadre",
    "wof:placetype":"venue"
},
  "geometry": {"coordinates":[-77.47165099999999,39.028359],"type":"Point"}
}