{
  "type": "Feature",
  "properties": {
    "iso:country":"US",
    "sg:address":"244 Brake Rd",
    "sg:city":"Elliston",
    "sg:classifiers":[
        {
            "category":"Organizations",
            "subcategory":"Religious Organization",
            "type":"Services"
        }
    ],
    "sg:phone":"+1 540 268 2451",
    "sg:postcode":"24087",
    "sg:province":"VA",
    "sg:tags":[
        "clergy"
    ],
    "wof:name":"Kenneth B Wright",
    "wof:placetype":"venue"
},
  "geometry": {"coordinates":[-80.227515,37.214529],"type":"Point"}
}