{
  "type": "Feature",
  "properties": {
    "addr:full":"5641 General Washington Dr Alexandria VA 22312",
    "addr:housenumber":"5641",
    "addr:postcode":"22312",
    "addr:street":"General Washington Dr",
    "iso:country":"US",
    "sg:address":"5641 General Washington Dr",
    "sg:city":"Alexandria",
    "sg:classifiers":[
        {
            "category":"Home & Garden",
            "subcategory":"Carpets & Floor Coverings",
            "type":"Retail Goods"
        }
    ],
    "sg:phone":"+1 703 750 1601",
    "sg:postcode":"22312",
    "sg:province":"VA",
    "sg:tags":[
        "dealer",
        "rug"
    ],
    "wof:name":"Carpet Bazaar Of Northern Va",
    "wof:placetype":"venue"
},
  "geometry": {"coordinates":[-77.164445,38.797906],"type":"Point"}
}