{
  "type": "Feature",
  "properties": {
    "addr:full":"411 Keep-Away Trl Fancy Gap VA 24328",
    "addr:housenumber":"411",
    "addr:postcode":"24328",
    "addr:street":"Keep-Away Trl",
    "iso:country":"US",
    "sg:address":"411 Keep-Away Trl",
    "sg:city":"Fancy Gap",
    "sg:classifiers":[
        {
            "category":"Insurance",
            "subcategory":"Insurance Agent",
            "type":"Services"
        }
    ],
    "sg:phone":"+1 276 728 5608",
    "sg:postcode":"24328",
    "sg:province":"VA",
    "wof:name":"American General Agnt",
    "wof:placetype":"venue"
},
  "geometry": {"coordinates":[-80.71969300000001,36.642838],"type":"Point"}
}