{
  "type": "Feature",
  "properties": {
    "addr:full":"985 Maitland Dr Virginia Beach VA 23454",
    "addr:housenumber":"985",
    "addr:postcode":"23454",
    "addr:street":"Maitland Dr",
    "iso:country":"US",
    "sg:address":"985 Maitland Dr",
    "sg:city":"Virginia Beach",
    "sg:classifiers":[
        {
            "category":"Professional",
            "subcategory":"Management & Consulting",
            "type":"Services"
        }
    ],
    "sg:phone":"+1 757 426 3175",
    "sg:postcode":"23454",
    "sg:province":"VA",
    "sg:tags":[
        "logistics"
    ],
    "wof:name":"FAC Logistics",
    "wof:placetype":"venue"
},
  "geometry": {"coordinates":[-75.991947,36.776881],"type":"Point"}
}