{
  "type": "Feature",
  "properties": {
    "addr:full":"2521 Century Dr Petersburg VA 23805",
    "addr:housenumber":"2521",
    "addr:postcode":"23805",
    "addr:street":"Century Dr",
    "iso:country":"US",
    "sg:address":"2521 Century Dr",
    "sg:city":"Petersburg",
    "sg:classifiers":[
        {
            "category":"Professional",
            "subcategory":"Business Services",
            "type":"Services"
        }
    ],
    "sg:phone":"+1 804 437 9532",
    "sg:postcode":"23805",
    "sg:province":"VA",
    "wof:name":"History In Making",
    "wof:placetype":"venue"
},
  "geometry": {"coordinates":[-77.364845,37.201848],"type":"Point"}
}