{
  "type": "Feature",
  "properties": {
    "addr:full":"7101 Warwick Blvd Newport News VA 23607",
    "addr:housenumber":"7101",
    "addr:postcode":"23607",
    "addr:street":"Warwick Blvd",
    "iso:country":"US",
    "sg:address":"7101 Warwick Blvd",
    "sg:city":"Newport News",
    "sg:classifiers":[
        {
            "category":"Food & Beverages",
            "subcategory":"Groceries & Convenience Stores",
            "type":"Retail Goods"
        }
    ],
    "sg:phone":"+1 757 380 5310",
    "sg:postcode":"23607",
    "sg:province":"VA",
    "sg:website":"www.7eleven.com",
    "wof:name":"7-Eleven",
    "wof:placetype":"venue"
},
  "geometry": {"coordinates":[-76.446772,37.011758],"type":"Point"}
}