{
  "type": "Feature",
  "properties": {
    "addr:full":"3451 Brandon Ave SW Roanoke VA 24018",
    "addr:housenumber":"3451",
    "addr:postcode":"24018",
    "addr:street":"Brandon Ave Sw",
    "iso:country":"US",
    "sg:address":"3451 Brandon Ave SW",
    "sg:city":"Roanoke",
    "sg:classifiers":[
        {
            "category":"Personal",
            "subcategory":"Massage",
            "type":"Services"
        }
    ],
    "sg:phone":"+1 540 776 9212",
    "sg:postcode":"24018",
    "sg:province":"VA",
    "wof:name":"Massage Therapy",
    "wof:placetype":"venue"
},
  "geometry": {"coordinates":[-80.004096,37.263924],"type":"Point"}
}