{
  "type": "Feature",
  "properties": {
    "addr:full":"709 Laxton Rd Lynchburg VA 24502",
    "addr:housenumber":"709",
    "addr:postcode":"24502",
    "addr:street":"Laxton Rd",
    "iso:country":"US",
    "sg:address":"709 Laxton Rd",
    "sg:city":"Lynchburg",
    "sg:classifiers":[
        {
            "category":"Building & Trades",
            "subcategory":"Construction",
            "type":"Services"
        }
    ],
    "sg:phone":"+1 434 239 6520",
    "sg:postcode":"24502",
    "sg:province":"VA",
    "sg:tags":[
        "hanging",
        "contractor"
    ],
    "wof:name":"Oasis Cleaning & Painting Inc",
    "wof:placetype":"venue"
},
  "geometry": {"coordinates":[-79.245965,37.34834],"type":"Point"}
}