{
  "type": "Feature",
  "properties": {
    "addr:full":"12644 Chapel Rd Clifton VA 20124",
    "addr:housenumber":"12644",
    "addr:postcode":"20124",
    "addr:street":"Chapel Rd",
    "iso:country":"US",
    "sg:address":"12644 Chapel Rd",
    "sg:city":"Clifton",
    "sg:classifiers":[
        {
            "category":"Shopping",
            "subcategory":"Clothing, Apparel, & Fashions",
            "type":"Retail Goods"
        }
    ],
    "sg:phone":"+1 703 818 1517",
    "sg:postcode":"20124",
    "sg:province":"VA",
    "sg:tags":[
        "sportswear"
    ],
    "sg:website":"www.1824catalog.com",
    "wof:name":"Arnott Mason Corp",
    "wof:placetype":"venue"
},
  "geometry": {"coordinates":[-77.385284,38.780996],"type":"Point"}
}