{
  "type": "Feature",
  "properties": {
    "addr:full":"8714 Rustic Oak Ct Fairfax Station VA 22039",
    "addr:housenumber":"8714",
    "addr:postcode":"22039",
    "addr:street":"Rustic Oak Ct",
    "iso:country":"US",
    "sg:address":"8714 Rustic Oak Ct",
    "sg:city":"Fairfax Station",
    "sg:classifiers":[
        {
            "category":"Banks & Credit Unions",
            "subcategory":"Investment Brokerage",
            "type":"Services"
        }
    ],
    "sg:phone":"+1 703 690 3087",
    "sg:postcode":"22039",
    "sg:province":"VA",
    "sg:tags":[
        "advisory",
        "financial"
    ],
    "wof:name":"Livingston Financial Group Inc",
    "wof:placetype":"venue"
},
  "geometry": {"coordinates":[-77.292659,38.720533],"type":"Point"}
}