{
  "type": "Feature",
  "properties": {
    "addr:full":"9000 Jackson Ave Manassas VA 20110",
    "addr:housenumber":"9000",
    "addr:postcode":"20110",
    "addr:street":"Jackson Ave",
    "iso:country":"US",
    "sg:address":"9000 Jackson Ave",
    "sg:city":"Manassas",
    "sg:classifiers":[
        {
            "category":"Building & Trades",
            "subcategory":"Construction",
            "type":"Services"
        }
    ],
    "sg:phone":"+1 703 369 7492",
    "sg:postcode":"20110",
    "sg:province":"VA",
    "sg:tags":[
        "house"
    ],
    "wof:name":"Johns Home Improvements",
    "wof:placetype":"venue"
},
  "geometry": {"coordinates":[-77.47391399999999,38.759859],"type":"Point"}
}