{
  "type": "Feature",
  "properties": {
    "iso:country":"US",
    "sg:address":"7105 Woodglen Ct",
    "sg:city":"Fairfax Station",
    "sg:classifiers":[
        {
            "category":"Professional",
            "subcategory":"Engineering",
            "type":"Services"
        }
    ],
    "sg:phone":"+1 703 323 5117",
    "sg:postcode":"22039",
    "sg:province":"VA",
    "sg:tags":[
        "consulting",
        "engineer"
    ],
    "wof:name":"AVO Enterprise",
    "wof:placetype":"venue"
},
  "geometry": {"coordinates":[-77.34376,38.765982],"type":"Point"}
}