{
  "type": "Feature",
  "properties": {
    "addr:full":"600 Dulany Street Alexandria VA 22314",
    "addr:housenumber":"600",
    "addr:postcode":"22314",
    "addr:street":"Dulany Street",
    "iso:country":"US",
    "sg:address":"600 Dulany Street",
    "sg:city":"Alexandria",
    "sg:classifiers":[
        {
            "category":"Museum",
            "type":"Entertainment"
        }
    ],
    "sg:phone":"+1 571 272 0095",
    "sg:postcode":"22314",
    "sg:province":"VA",
    "sg:website":"www.invent.org/about_invent_now/...",
    "wof:name":"National Inventors Hall of Fame",
    "wof:placetype":"venue"
},
  "geometry": {"coordinates":[-77.06379099999999,38.801365],"type":"Point"}
}