{
  "type": "Feature",
  "properties": {
    "iso:country":"US",
    "sg:address":"1722 E Main St",
    "sg:city":"Richmond",
    "sg:classifiers":[
        {
            "category":"Restaurant",
            "type":"Food & Drink"
        }
    ],
    "sg:phone":"+1 804 643 5022",
    "sg:postcode":"23223",
    "sg:province":"VA",
    "wof:name":"Goodfellas Restaurant",
    "wof:placetype":"venue"
},
  "geometry": {"coordinates":[-77.427785,37.533087],"type":"Point"}
}