{
  "type": "Feature",
  "properties": {
    "addr:full":"6242 Old Dominion Dr Mc Lean VA 22101",
    "addr:housenumber":"6242",
    "addr:postcode":"22101",
    "addr:street":"Old Dominion Dr",
    "iso:country":"US",
    "sg:address":"6242 Old Dominion Dr",
    "sg:city":"Mc Lean",
    "sg:classifiers":[
        {
            "category":"Shopping",
            "subcategory":"Computers & Home Electronics",
            "type":"Retail Goods"
        }
    ],
    "sg:phone":"+1 703 534 0533",
    "sg:postcode":"22101",
    "sg:province":"VA",
    "wof:name":"Radio Shack",
    "wof:placetype":"venue"
},
  "geometry": {"coordinates":[-77.15170500000001,38.920567],"type":"Point"}
}