{
  "type": "Feature",
  "properties": {
    "addr:full":"1811 Friedens Church Rd Mount Crawford VA 22841",
    "addr:housenumber":"1811",
    "addr:postcode":"22841",
    "addr:street":"Friedens Church Rd",
    "iso:country":"US",
    "sg:address":"1811 Friedens Church Rd",
    "sg:city":"Mount Crawford",
    "sg:classifiers":[
        {
            "category":"Farming",
            "subcategory":"Farm & Veterinary Services",
            "type":"Manufacturing & Wholesale Goods"
        }
    ],
    "sg:phone":"+1 540 432 3977",
    "sg:postcode":"22841",
    "sg:province":"VA",
    "sg:tags":[
        "livestock"
    ],
    "wof:name":"Keith Figgins",
    "wof:placetype":"venue"
},
  "geometry": {"coordinates":[-78.911501,38.349828],"type":"Point"}
}