{
  "type": "Feature",
  "properties": {
    "addr:full":"4 Rexford Dr Newport News VA 23608",
    "addr:housenumber":"4",
    "addr:postcode":"23608",
    "addr:street":"Rexford Dr",
    "iso:country":"US",
    "sg:address":"4 Rexford Dr",
    "sg:city":"Newport News",
    "sg:classifiers":[
        {
            "category":"Building & Trades",
            "subcategory":"Construction",
            "type":"Services"
        }
    ],
    "sg:phone":"+1 757 872 4695",
    "sg:postcode":"23608",
    "sg:province":"VA",
    "sg:tags":[
        "hanging",
        "contractor"
    ],
    "wof:name":"Holloways Paint & Powerwash",
    "wof:placetype":"venue"
},
  "geometry": {"coordinates":[-76.55546699999999,37.150571],"type":"Point"}
}