{
  "type": "Feature",
  "properties": {
    "addr:full":"7211 Stonewall Pkwy Mechanicsville VA 23111",
    "addr:housenumber":"7211",
    "addr:postcode":"23111",
    "addr:street":"Stonewall Pkwy",
    "iso:country":"US",
    "sg:address":"7211 Stonewall Pkwy",
    "sg:city":"Mechanicsville",
    "sg:classifiers":[
        {
            "category":"Food & Beverages",
            "subcategory":"Groceries & Convenience Stores",
            "type":"Retail Goods"
        }
    ],
    "sg:phone":"+1 804 730 2900",
    "sg:postcode":"23111",
    "sg:province":"VA",
    "sg:tags":[
        "product"
    ],
    "wof:name":"Mid Atlantic Food Corp TA",
    "wof:placetype":"venue"
},
  "geometry": {"coordinates":[-77.369227,37.599459],"type":"Point"}
}