{
  "type": "Feature",
  "properties": {
    "iso:country":"US",
    "sg:address":"6400 Seven Corners Pl",
    "sg:city":"Falls Church",
    "sg:classifiers":[
        {
            "category":"Professional",
            "type":"Services"
        }
    ],
    "sg:phone":"+1 703 750 7886",
    "sg:postcode":"22044",
    "sg:province":"VA",
    "wof:name":"Willows Dev Co",
    "wof:placetype":"venue"
},
  "geometry": {"coordinates":[-77.15714199999999,38.870822],"type":"Point"}
}