{
  "type": "Feature",
  "properties": {
    "addr:full":"413 Harvest Ct Lynchburg VA 24502",
    "addr:housenumber":"413",
    "addr:postcode":"24502",
    "addr:street":"Harvest Ct",
    "iso:country":"US",
    "sg:address":"413 Harvest Ct",
    "sg:city":"Lynchburg",
    "sg:classifiers":[
        {
            "category":"Professional",
            "subcategory":"Computer Services",
            "type":"Services"
        }
    ],
    "sg:phone":"+1 434 385 1677",
    "sg:postcode":"24502",
    "sg:province":"VA",
    "sg:tags":[
        "agency",
        "advertising",
        "related"
    ],
    "wof:name":"Gombos Consulting LLC",
    "wof:placetype":"venue"
},
  "geometry": {"coordinates":[-79.24100300000001,37.424774],"type":"Point"}
}