{
  "type": "Feature",
  "properties": {
    "addr:full":"1310 Garrison Dr Williamsburg VA 23185",
    "addr:housenumber":"1310",
    "addr:postcode":"23185",
    "addr:street":"Garrison Dr",
    "iso:country":"US",
    "sg:address":"1310 Garrison Dr",
    "sg:city":"Williamsburg",
    "sg:classifiers":[
        {
            "category":"Personal",
            "subcategory":"Massage",
            "type":"Services"
        }
    ],
    "sg:phone":"+1 757 253 9070",
    "sg:postcode":"23185",
    "sg:province":"VA",
    "wof:name":"Body Rhythms Massage",
    "wof:placetype":"venue"
},
  "geometry": {"coordinates":[-76.721766,37.283257],"type":"Point"}
}