{
  "type": "Feature",
  "properties": {
    "iso:country":"US",
    "sg:address":"5001 Lee Hwy",
    "sg:city":"Arlington",
    "sg:classifiers":[
        {
            "category":"Shopping",
            "subcategory":"Computers & Home Electronics",
            "type":"Retail Goods"
        },
        {
            "category":"Professional",
            "subcategory":"Computer Services",
            "type":"Services"
        }
    ],
    "sg:phone":"+1 703 351 7881",
    "sg:postcode":"22207",
    "sg:province":"VA",
    "sg:tags":[
        "repair",
        "installation",
        "theatre"
    ],
    "sg:website":"www.intellihouse.net/",
    "wof:name":"Intelli House.Net",
    "wof:placetype":"venue"
},
  "geometry": {"coordinates":[-77.128871,38.896587],"type":"Point"}
}