{
  "type": "Feature",
  "properties": {
    "iso:country":"US",
    "sg:address":"10106 Castile Ct",
    "sg:city":"Richmond",
    "sg:classifiers":[
        {
            "category":"Building & Trades",
            "subcategory":"Construction",
            "type":"Services"
        }
    ],
    "sg:phone":"+1 804 288 1810",
    "sg:postcode":"23238",
    "sg:province":"VA",
    "sg:tags":[
        "contractor"
    ],
    "wof:name":"Cassell Drywall",
    "wof:placetype":"venue"
},
  "geometry": {"coordinates":[-77.60051300000001,37.594419],"type":"Point"}
}