{
  "type": "Feature",
  "properties": {
    "addr:full":"26285 Woodview Ln Windsor VA 23487",
    "addr:postcode":"26285;23487",
    "addr:street":"Woodview Ln",
    "iso:country":"US",
    "sg:address":"26285 Woodview Ln",
    "sg:city":"Windsor",
    "sg:classifiers":[
        {
            "category":"Organizations",
            "subcategory":"Religious Organization",
            "type":"Services"
        }
    ],
    "sg:phone":"+1 757 242 3371",
    "sg:postcode":"23487",
    "sg:province":"VA",
    "wof:name":"Dorothy Vaughan Rev",
    "wof:placetype":"venue"
},
  "geometry": {"coordinates":[-76.793317,36.780894],"type":"Point"}
}