{
  "type": "Feature",
  "properties": {
    "addr:full":"12893 Jefferson Ave Newport News VA 23608",
    "addr:housenumber":"12893",
    "addr:postcode":"23608",
    "addr:street":"Jefferson Ave",
    "iso:country":"US",
    "sg:address":"12893 Jefferson Ave",
    "sg:city":"Newport News",
    "sg:classifiers":[
        {
            "category":"Retail",
            "subcategory":"Funeral Services",
            "type":"Services"
        }
    ],
    "sg:phone":"+1 757 874 4200",
    "sg:postcode":"23608",
    "sg:province":"VA",
    "sg:website":"www.altmeyer.com",
    "wof:name":"Altmeyer Funeral Home",
    "wof:placetype":"venue"
},
  "geometry": {"coordinates":[-76.525597,37.145396],"type":"Point"}
}