{
  "type": "Feature",
  "properties": {
    "addr:full":"66 Canal Center Plaza Suite 700 Alexandria VA 22314",
    "addr:housenumber":"66",
    "addr:postcode":"22314",
    "addr:street":"Canal Center Plaza Suite 700",
    "iso:country":"US",
    "sg:address":"66 Canal Center Plaza Suite 700",
    "sg:city":"Alexandria",
    "sg:classifiers":[
        {
            "category":"Professional",
            "subcategory":"Management & Consulting",
            "type":"Services"
        }
    ],
    "sg:phone":"+1 703 548 3300",
    "sg:postcode":"22314",
    "sg:province":"VA",
    "sg:website":"http://www.yellowbrix.com/",
    "wof:name":"Yellowbrix",
    "wof:placetype":"venue"
},
  "geometry": {"coordinates":[-77.03999,38.81458],"type":"Point"}
}