{
  "type": "Feature",
  "properties": {
    "addr:full":"1412 Farmer St Petersburg VA 23803",
    "addr:housenumber":"1412",
    "addr:postcode":"23803",
    "addr:street":"Farmer St Petersburg",
    "iso:country":"US",
    "sg:address":"1412 Farmer St",
    "sg:city":"Petersburg",
    "sg:classifiers":[
        {
            "category":"Wholesale",
            "subcategory":"Construction Materials",
            "type":"Manufacturing & Wholesale Goods"
        }
    ],
    "sg:phone":"+1 804 748 3824",
    "sg:postcode":"23803",
    "sg:province":"VA",
    "wof:name":"Colonial Marble Products Ltd",
    "wof:placetype":"venue"
},
  "geometry": {"coordinates":[-77.426545,37.218262],"type":"Point"}
}