{
  "type": "Feature",
  "properties": {
    "addr:full":"1209 N King St Hampton VA 23669",
    "addr:housenumber":"1209",
    "addr:postcode":"23669",
    "addr:street":"N King St",
    "iso:country":"US",
    "sg:address":"1209 N King St",
    "sg:city":"Hampton",
    "sg:classifiers":[
        {
            "category":"Retail",
            "subcategory":"Auto Repair",
            "type":"Services"
        }
    ],
    "sg:phone":"+1 757 722 6586",
    "sg:postcode":"23669",
    "sg:province":"VA",
    "sg:tags":[
        "repairing",
        "automobile"
    ],
    "wof:name":"Madlock's Auto Repair-Wrecker",
    "wof:placetype":"venue"
},
  "geometry": {"coordinates":[-76.34804099999999,37.045368],"type":"Point"}
}