{
  "type": "Feature",
  "properties": {
    "addr:full":"2440 Wilson Blvd Suite 201 Arlington VA 22201",
    "addr:housenumber":"2440",
    "addr:postcode":"22201",
    "addr:street":"Wilson Blvd Suite 201",
    "iso:country":"US",
    "sg:address":"2440 Wilson Blvd Suite 201",
    "sg:city":"Arlington",
    "sg:classifiers":[
        {
            "category":"Sports & Exercise",
            "subcategory":"Gym",
            "type":"Entertainment"
        }
    ],
    "sg:phone":"+1 703 243 8866",
    "sg:postcode":"22201",
    "sg:province":"VA",
    "sg:tags":[
        "yoga"
    ],
    "sg:website":"www.edgeyoga.com",
    "wof:name":"Edge Yoga",
    "wof:placetype":"venue"
},
  "geometry": {"coordinates":[-77.087906,38.890522],"type":"Point"}
}