{
  "type": "Feature",
  "properties": {
    "iso:country":"US",
    "sg:address":"3227 Broad Rock Blvd",
    "sg:city":"Richmond",
    "sg:classifiers":[
        {
            "category":"Personal",
            "subcategory":"Beauty Salon",
            "type":"Services"
        }
    ],
    "sg:phone":"+1 804 231 9003",
    "sg:postcode":"23224",
    "sg:province":"VA",
    "sg:tags":[
        "shop"
    ],
    "wof:name":"Marie's Hair Salon",
    "wof:placetype":"venue"
},
  "geometry": {"coordinates":[-77.482406,37.473138],"type":"Point"}
}