{
  "type": "Feature",
  "properties": {
    "addr:full":"5222 George Washington Memorial Hwy Yorktown VA 23692",
    "addr:housenumber":"5222",
    "addr:postcode":"23692",
    "addr:street":"George Washington Memorial Hwy",
    "iso:country":"US",
    "sg:address":"5222 George Washington Memorial Hwy",
    "sg:city":"Yorktown",
    "sg:classifiers":[
        {
            "category":"Personal",
            "subcategory":"Shoe Repair & Shine",
            "type":"Services"
        }
    ],
    "sg:phone":"+1 757 898 3008",
    "sg:postcode":"23692",
    "sg:province":"VA",
    "sg:tags":[
        "repairing",
        "boot"
    ],
    "wof:name":"Lee's Shoe Repair & Altrtns",
    "wof:placetype":"venue"
},
  "geometry": {"coordinates":[-76.46260100000001,37.157958],"type":"Point"}
}