{
  "type": "Feature",
  "properties": {
    "addr:full":"214 Bollingbrook St Petersburg VA 23803",
    "addr:housenumber":"214",
    "addr:postcode":"23803",
    "addr:street":"Bollingbrook St",
    "iso:country":"US",
    "sg:address":"214 Bollingbrook St",
    "sg:city":"Petersburg",
    "sg:classifiers":[
        {
            "category":"Wholesale",
            "subcategory":"Auto Parts",
            "type":"Manufacturing & Wholesale Goods"
        }
    ],
    "sg:phone":"+1 804 861 6762",
    "sg:postcode":"23803",
    "sg:province":"VA",
    "sg:tags":[
        "brakes"
    ],
    "wof:name":"Old Town Auto Svc",
    "wof:placetype":"venue"
},
  "geometry": {"coordinates":[-77.400074,37.232762],"type":"Point"}
}