{
  "type": "Feature",
  "properties": {
    "iso:country":"US",
    "sg:address":"434 N Main St",
    "sg:city":"Suffolk",
    "sg:classifiers":[
        {
            "category":"Health Services",
            "subcategory":"Clinic",
            "type":"Services"
        }
    ],
    "sg:phone":"+1 757 539 0049",
    "sg:postcode":"23434",
    "sg:province":"VA",
    "wof:name":"Just For The Health Of It Inc",
    "wof:placetype":"venue"
},
  "geometry": {"coordinates":[-76.582054,36.735267],"type":"Point"}
}