{
  "type": "Feature",
  "properties": {
    "addr:full":"1338 W Main St Salem VA 24153",
    "addr:housenumber":"1338",
    "addr:postcode":"24153",
    "addr:street":"W Main St",
    "iso:country":"US",
    "sg:address":"1338 W Main St",
    "sg:city":"Salem",
    "sg:classifiers":[
        {
            "category":"Shopping",
            "subcategory":"Hobbies, Toys, & Games",
            "type":"Retail Goods"
        }
    ],
    "sg:phone":"+1 540 375 8367",
    "sg:postcode":"24153",
    "sg:province":"VA",
    "sg:tags":[
        "supply"
    ],
    "wof:name":"Replay Games & Dvd",
    "wof:placetype":"venue"
},
  "geometry": {"coordinates":[-80.07963100000001,37.289597],"type":"Point"}
}