{
  "type": "Feature",
  "properties": {
    "addr:full":"959 Virginia Beach Blvd Virginia Beach VA 23451",
    "addr:housenumber":"959",
    "addr:postcode":"23451",
    "addr:street":"Virginia Beach Blvd",
    "iso:country":"US",
    "sg:address":"959 Virginia Beach Blvd",
    "sg:city":"Virginia Beach",
    "sg:classifiers":[
        {
            "category":"Freight",
            "type":"Transportation"
        }
    ],
    "sg:phone":"+1 757 491 2800",
    "sg:postcode":"23451",
    "sg:province":"VA",
    "sg:tags":[
        "commercial",
        "storage"
    ],
    "wof:name":"Ocean Front Outdoor Storage",
    "wof:placetype":"venue"
},
  "geometry": {"coordinates":[-75.990635,36.842422],"type":"Point"}
}