{
  "type": "Feature",
  "properties": {
    "iso:country":"US",
    "sg:address":"44 Mine Rd",
    "sg:city":"Stafford",
    "sg:classifiers":[
        {
            "category":"Personal",
            "subcategory":"Beauty Salon",
            "type":"Services"
        }
    ],
    "sg:phone":"+1 540 657 1612",
    "sg:postcode":"22554",
    "sg:province":"VA",
    "sg:tags":[
        "shop",
        "manicuring"
    ],
    "wof:name":"Magic Nail & Hair Salon",
    "wof:placetype":"venue"
},
  "geometry": {"coordinates":[-77.416178,38.46983],"type":"Point"}
}