{
  "type": "Feature",
  "properties": {
    "iso:country":"US",
    "sg:address":"1900 Braeburn Dr",
    "sg:city":"Salem",
    "sg:classifiers":[
        {
            "category":"Health Services",
            "subcategory":"Doctor",
            "type":"Services"
        }
    ],
    "sg:phone":"+1 540 774 8500",
    "sg:postcode":"24153",
    "sg:province":"VA",
    "sg:tags":[
        "medical"
    ],
    "wof:name":"Virginia Orthopaedic",
    "wof:placetype":"venue"
},
  "geometry": {"coordinates":[-80.028673,37.264343],"type":"Point"}
}