{
  "type": "Feature",
  "properties": {
    "iso:country":"US",
    "sg:address":"3840 Mount Vernon Ave",
    "sg:city":"Alexandria",
    "sg:classifiers":[
        {
            "category":"Food & Beverages",
            "subcategory":"Supermarket",
            "type":"Retail Goods"
        },
        {
            "category":"Food & Beverages",
            "subcategory":"Groceries & Convenience Stores",
            "type":"Retail Goods"
        }
    ],
    "sg:phone":"+1 703 836 5959",
    "sg:postcode":"22305",
    "sg:province":"VA",
    "sg:tags":[
        "super"
    ],
    "wof:name":"Al Seria Grocery Store",
    "wof:placetype":"venue"
},
  "geometry": {"coordinates":[-77.06289700000001,38.8405],"type":"Point"}
}