{
  "type": "Feature",
  "properties": {
    "addr:full":"4909 Trade Center Dr Fredericksburg VA 22408",
    "addr:housenumber":"4909",
    "addr:postcode":"22408",
    "addr:street":"Trade Center Dr",
    "iso:country":"US",
    "sg:address":"4909 Trade Center Dr",
    "sg:city":"Fredericksburg",
    "sg:classifiers":[
        {
            "category":"Retail",
            "subcategory":"Auto Repair",
            "type":"Services"
        }
    ],
    "sg:phone":"+1 540 834 4150",
    "sg:postcode":"22408",
    "sg:province":"VA",
    "sg:website":"http://www.swedenautomotive.com",
    "wof:name":"Sweden Automotive",
    "wof:placetype":"venue"
},
  "geometry": {"coordinates":[-77.503766,38.258083],"type":"Point"}
}