{
  "type": "Feature",
  "properties": {
    "addr:full":"324 Poplar Lawn Rd Surry VA 23883",
    "addr:housenumber":"324",
    "addr:postcode":"23883",
    "addr:street":"Poplar Lawn Rd",
    "iso:country":"US",
    "sg:address":"324 Poplar Lawn Rd",
    "sg:city":"Surry",
    "sg:classifiers":[
        {
            "category":"Building & Trades",
            "subcategory":"Construction",
            "type":"Services"
        }
    ],
    "sg:phone":"+1 757 294 0007",
    "sg:postcode":"23883",
    "sg:province":"VA",
    "sg:tags":[
        "general",
        "contractor"
    ],
    "wof:name":"Saccone Custom Builders Inc",
    "wof:placetype":"venue"
},
  "geometry": {"coordinates":[-76.769171,37.150137],"type":"Point"}
}