{
  "type": "Feature",
  "properties": {
    "addr:full":"13508 Booker T Washington Hwy Moneta VA 24121",
    "addr:housenumber":"13508",
    "addr:postcode":"24121",
    "addr:street":"Booker T Washington Hwy",
    "iso:country":"US",
    "sg:address":"13508 Booker T Washington Hwy",
    "sg:city":"Moneta",
    "sg:classifiers":[
        {
            "category":"Shopping",
            "subcategory":"Gifts & Souvenirs",
            "type":"Retail Goods"
        }
    ],
    "sg:phone":"+1 540 721 5277",
    "sg:postcode":"24121",
    "sg:province":"VA",
    "sg:tags":[
        "business"
    ],
    "wof:name":"Lyndis",
    "wof:placetype":"venue"
},
  "geometry": {"coordinates":[-79.69653700000001,37.127708],"type":"Point"}
}