{
  "type": "Feature",
  "properties": {
    "addr:full":"303 S Loudoun St Winchester VA 22601",
    "addr:housenumber":"303",
    "addr:postcode":"22601",
    "addr:street":"S Loudoun St",
    "iso:country":"US",
    "sg:address":"303 S Loudoun St",
    "sg:city":"Winchester",
    "sg:classifiers":[
        {
            "category":"Professional",
            "subcategory":"Management & Consulting",
            "type":"Services"
        }
    ],
    "sg:phone":"+1 540 450 0400",
    "sg:postcode":"22601",
    "sg:province":"VA",
    "sg:tags":[
        "personnel",
        "consultant"
    ],
    "wof:name":"Axiom Staffing Group",
    "wof:placetype":"venue"
},
  "geometry": {"coordinates":[-78.166776,39.181291],"type":"Point"}
}