{
  "type": "Feature",
  "properties": {
    "addr:full":"4601 N Bailey Bridge Rd Midlothian VA 23112",
    "addr:housenumber":"4601",
    "addr:postcode":"23112",
    "addr:street":"N Bailey Bridge Rd",
    "iso:country":"US",
    "sg:address":"4601 N Bailey Bridge Rd",
    "sg:city":"Midlothian",
    "sg:classifiers":[
        {
            "category":"Organizations",
            "subcategory":"Religious Organization",
            "type":"Services"
        }
    ],
    "sg:phone":"+1 804 763 4773",
    "sg:postcode":"23112",
    "sg:province":"VA",
    "sg:tags":[
        "church"
    ],
    "wof:name":"Church Of Jesus Christ Of Lds",
    "wof:placetype":"venue"
},
  "geometry": {"coordinates":[-77.611824,37.422469],"type":"Point"}
}