{
  "type": "Feature",
  "properties": {
    "addr:full":"1200 5th St SW Charlottesville VA 22902",
    "addr:housenumber":"1200",
    "addr:postcode":"22902",
    "addr:street":"5Th St Sw",
    "iso:country":"US",
    "sg:address":"1200 5th St SW",
    "sg:city":"Charlottesville",
    "sg:classifiers":[
        {
            "category":"Travel",
            "subcategory":"Hotels & Motels",
            "type":"Entertainment"
        }
    ],
    "sg:phone":"+1 434 977 5100",
    "sg:postcode":"22902",
    "sg:province":"VA",
    "sg:website":"www.holidayinn.com",
    "wof:name":"Holiday Inn Charlottesville",
    "wof:placetype":"venue"
},
  "geometry": {"coordinates":[-78.504131,38.010965],"type":"Point"}
}