{
  "type": "Feature",
  "properties": {
    "addr:full":"100 W Jubal Early Dr Winchester VA 22601",
    "addr:housenumber":"100",
    "addr:postcode":"22601",
    "addr:street":"W;Early Dr",
    "iso:country":"US",
    "sg:address":"100 W Jubal Early Dr",
    "sg:city":"Winchester",
    "sg:classifiers":[
        {
            "category":"Banks & Credit Unions",
            "subcategory":"Bank",
            "type":"Services"
        }
    ],
    "sg:phone":"+1 540 678 0300",
    "sg:postcode":"22601",
    "sg:province":"VA",
    "sg:tags":[
        "national",
        "commercial"
    ],
    "sg:website":"www.shenandoahvnb.com",
    "wof:name":"Shenandoah Valley National Bnk",
    "wof:placetype":"venue"
},
  "geometry": {"coordinates":[-78.171663,39.166511],"type":"Point"}
}