{
  "type": "Feature",
  "properties": {
    "iso:country":"US",
    "sg:address":"12284 Warwick Blvd",
    "sg:city":"Newport News",
    "sg:classifiers":[
        {
            "category":"Social Services",
            "type":"Services"
        }
    ],
    "sg:phone":"+1 757 988 0400",
    "sg:postcode":"23606",
    "sg:province":"VA",
    "wof:name":"Health Care For The Homeless",
    "wof:placetype":"venue"
},
  "geometry": {"coordinates":[-76.487465,37.06196],"type":"Point"}
}