{
  "type": "Feature",
  "properties": {
    "addr:full":"3846 Whitman Rd Annandale VA 22003",
    "addr:housenumber":"3846",
    "addr:postcode":"22003",
    "addr:street":"Whitman Rd",
    "iso:country":"US",
    "sg:address":"3846 Whitman Rd",
    "sg:city":"Annandale",
    "sg:classifiers":[
        {
            "category":"Professional",
            "subcategory":"Management & Consulting",
            "type":"Services"
        }
    ],
    "sg:phone":"+1 703 280 9558",
    "sg:postcode":"22003",
    "sg:province":"VA",
    "wof:name":"Imm Tours",
    "wof:placetype":"venue"
},
  "geometry": {"coordinates":[-77.23450699999999,38.83971],"type":"Point"}
}