{
  "type": "Feature",
  "properties": {
    "iso:country":"US",
    "sg:address":"513 23rd St S",
    "sg:city":"Arlington",
    "sg:classifiers":[
        {
            "category":"Restaurant",
            "type":"Food & Drink"
        }
    ],
    "sg:phone":"+1 703 769 0786",
    "sg:postcode":"22202",
    "sg:province":"VA",
    "wof:name":"Mogul Grill",
    "wof:placetype":"venue"
},
  "geometry": {"coordinates":[-77.055104,38.853416],"type":"Point"}
}