{
  "type": "Feature",
  "properties": {
    "addr:full":"3256 Page Ave Virginia Beach VA 23451",
    "addr:housenumber":"3256",
    "addr:postcode":"23451",
    "addr:street":"Page Ave",
    "iso:country":"US",
    "sg:address":"3256 Page Ave",
    "sg:city":"Virginia Beach",
    "sg:classifiers":[
        {
            "category":"Professional",
            "subcategory":"Management & Consulting",
            "type":"Services"
        }
    ],
    "sg:phone":"+1 757 478 5551",
    "sg:postcode":"23451",
    "sg:province":"VA",
    "wof:name":"Eileen R Carpenter",
    "wof:placetype":"venue"
},
  "geometry": {"coordinates":[-76.08577699999999,36.908605],"type":"Point"}
}