{
  "type": "Feature",
  "properties": {
    "iso:country":"US",
    "sg:address":"1526 Holland Rd",
    "sg:city":"Suffolk",
    "sg:classifiers":[
        {
            "category":"Travel",
            "subcategory":"Hotels & Motels",
            "type":"Entertainment"
        }
    ],
    "sg:phone":"+1 757 539 5111",
    "sg:postcode":"23434",
    "sg:province":"VA",
    "sg:tags":[
        "operation"
    ],
    "wof:name":"Days Inn",
    "wof:placetype":"venue"
},
  "geometry": {"coordinates":[-76.63580399999999,36.724484],"type":"Point"}
}