{
  "type": "Feature",
  "properties": {
    "addr:full":"3224 Mine Rd Fredericksburg VA 22408",
    "addr:housenumber":"3224",
    "addr:postcode":"22408",
    "addr:street":"Mine Rd",
    "iso:country":"US",
    "sg:address":"3224 Mine Rd",
    "sg:city":"Fredericksburg",
    "sg:classifiers":[
        {
            "category":"Home & Garden",
            "subcategory":"Furniture",
            "type":"Retail Goods"
        }
    ],
    "sg:phone":"+1 540 898 2071",
    "sg:postcode":"22408",
    "sg:province":"VA",
    "wof:name":"Mine Road Cabinets",
    "wof:placetype":"venue"
},
  "geometry": {"coordinates":[-77.444158,38.245005],"type":"Point"}
}