{
  "type": "Feature",
  "properties": {
    "addr:full":"201 Catlin St Farmville VA 23901",
    "addr:housenumber":"201",
    "addr:postcode":"23901",
    "addr:street":"Catlin St",
    "iso:country":"US",
    "sg:address":"201 Catlin St",
    "sg:city":"Farmville",
    "sg:classifiers":[
        {
            "category":"Organizations",
            "subcategory":"Community Association",
            "type":"Services"
        }
    ],
    "sg:phone":"+1 434 392 3967",
    "sg:postcode":"23901",
    "sg:province":"VA",
    "sg:tags":[
        "fraternal"
    ],
    "wof:name":"Farmville Masonic Lodge",
    "wof:placetype":"venue"
},
  "geometry": {"coordinates":[-78.384209,37.297084],"type":"Point"}
}