{
  "type": "Feature",
  "properties": {
    "iso:country":"US",
    "sg:address":"8540 Taylor Creek Rd",
    "sg:city":"Afton",
    "sg:classifiers":[
        {
            "category":"Professional",
            "type":"Services"
        }
    ],
    "sg:phone":"+1 434 361 1718",
    "sg:postcode":"22920",
    "sg:province":"VA",
    "wof:name":"V S Drives",
    "wof:placetype":"venue"
},
  "geometry": {"coordinates":[-78.814599,37.933465],"type":"Point"}
}