{
  "type": "Feature",
  "properties": {
    "addr:full":"12905 Locksley Ct Herndon VA 20171",
    "addr:housenumber":"12905",
    "addr:postcode":"20171",
    "addr:street":"Locksley Ct",
    "iso:country":"US",
    "sg:address":"12905 Locksley Ct",
    "sg:city":"Herndon",
    "sg:classifiers":[
        {
            "category":"Freight",
            "type":"Transportation"
        }
    ],
    "sg:phone":"+1 703 435 2242",
    "sg:postcode":"20171",
    "sg:province":"VA",
    "sg:tags":[
        "local",
        "moving",
        "transfer"
    ],
    "wof:name":"Campbell Moving Inc",
    "wof:placetype":"venue"
},
  "geometry": {"coordinates":[-77.39384699999999,38.937763],"type":"Point"}
}