{
  "type": "Feature",
  "properties": {
    "addr:full":"5000 Carriage Dr Roanoke VA 24018",
    "addr:housenumber":"5000",
    "addr:postcode":"24018",
    "addr:street":"Carriage Dr",
    "iso:country":"US",
    "sg:address":"5000 Carriage Dr",
    "sg:city":"Roanoke",
    "sg:classifiers":[
        {
            "category":"Place Of Worship",
            "subcategory":"Church",
            "type":"Public Place"
        },
        {
            "category":"Place Of Worship",
            "type":"Public Place"
        }
    ],
    "sg:phone":"+1 540 774 5512",
    "sg:postcode":"24018",
    "sg:province":"VA",
    "sg:tags":[
        "churches-non-denominational",
        "christ",
        "churches-community"
    ],
    "sg:website":"http://www.vccds.com",
    "wof:name":"Valley Community Church Divine Science",
    "wof:placetype":"venue"
},
  "geometry": {"coordinates":[-80.032757,37.244896],"type":"Point"}
}