{
  "type": "Feature",
  "properties": {
    "addr:full":"4540 John Marr Dr Annandale VA 22003",
    "addr:housenumber":"4540",
    "addr:postcode":"22003",
    "addr:street":"John Marr Dr",
    "iso:country":"US",
    "sg:address":"4540 John Marr Dr",
    "sg:city":"Annandale",
    "sg:classifiers":[
        {
            "category":"Health Services",
            "subcategory":"Doctor",
            "type":"Services"
        }
    ],
    "sg:phone":"+1 703 941 6851",
    "sg:postcode":"22003",
    "sg:province":"VA",
    "sg:tags":[
        "physician",
        "surgeon",
        "medical"
    ],
    "wof:name":"Daniel I Kim MD",
    "wof:placetype":"venue"
},
  "geometry": {"coordinates":[-77.19091,38.828529],"type":"Point"}
}