{
  "type": "Feature",
  "properties": {
    "addr:full":"4428 Electric Rd Roanoke VA 24018",
    "addr:housenumber":"4428",
    "addr:postcode":"24018",
    "addr:street":"Electric Rd",
    "iso:country":"US",
    "sg:address":"4428 Electric Rd",
    "sg:city":"Roanoke",
    "sg:classifiers":[
        {
            "category":"Museum",
            "type":"Entertainment"
        }
    ],
    "sg:phone":"+1 540 776 0364",
    "sg:postcode":"24018",
    "sg:province":"VA",
    "sg:tags":[
        "gallery"
    ],
    "wof:name":"To Rescue Museum",
    "wof:placetype":"venue"
},
  "geometry": {"coordinates":[-79.975053,37.23053],"type":"Point"}
}