{
  "type": "Feature",
  "properties": {
    "addr:full":"2323 Memorial Ave Lynchburg VA 24501",
    "addr:housenumber":"2323",
    "addr:postcode":"24501",
    "addr:street":"Memorial Ave",
    "iso:country":"US",
    "sg:address":"2323 Memorial Ave",
    "sg:city":"Lynchburg",
    "sg:classifiers":[
        {
            "category":"Building & Trades",
            "subcategory":"Equipment Rental",
            "type":"Services"
        }
    ],
    "sg:phone":"+1 434 847 8500",
    "sg:postcode":"24501",
    "sg:province":"VA",
    "sg:tags":[
        "appliance",
        "furniture"
    ],
    "wof:name":"Rent-Way",
    "wof:placetype":"venue"
},
  "geometry": {"coordinates":[-79.167226,37.403697],"type":"Point"}
}