{
  "type": "Feature",
  "properties": {
    "iso:country":"US",
    "sg:address":"2071 Apperson Dr",
    "sg:city":"Salem",
    "sg:classifiers":[
        {
            "category":"Autos & Motor Vehicles",
            "subcategory":"Fuel & Gas Station",
            "type":"Retail Goods"
        },
        {
            "category":"Food & Beverages",
            "subcategory":"Groceries & Convenience Stores",
            "type":"Retail Goods"
        }
    ],
    "sg:phone":"+1 540 989 0371",
    "sg:postcode":"24153",
    "sg:province":"VA",
    "wof:name":"Happy Stores",
    "wof:placetype":"venue"
},
  "geometry": {"coordinates":[-80.025341,37.266895],"type":"Point"}
}