{
  "type": "Feature",
  "properties": {
    "addr:full":"2312 Franklin Rd SW Roanoke VA 24014",
    "addr:housenumber":"2312",
    "addr:postcode":"24014",
    "addr:street":"Franklin Rd Sw",
    "iso:country":"US",
    "sg:address":"2312 Franklin Rd SW",
    "sg:city":"Roanoke",
    "sg:classifiers":[
        {
            "category":"Building & Trades",
            "subcategory":"Electrical",
            "type":"Services"
        }
    ],
    "sg:phone":"+1 540 345 7197",
    "sg:postcode":"24014",
    "sg:province":"VA",
    "sg:tags":[
        "fiber",
        "optic",
        "cable",
        "datum",
        "contractor",
        "voice"
    ],
    "sg:website":"www.protel1.com",
    "wof:name":"Protel",
    "wof:placetype":"venue"
},
  "geometry": {"coordinates":[-79.95205,37.252621],"type":"Point"}
}