{
  "type": "Feature",
  "properties": {
    "addr:full":"2007 Rockingham St Mc Lean VA 22101",
    "addr:housenumber":"2007",
    "addr:postcode":"22101",
    "addr:street":"Rockingham St Mc Lean",
    "iso:country":"US",
    "sg:address":"2007 Rockingham St",
    "sg:city":"Mc Lean",
    "sg:classifiers":[
        {
            "category":"Professional",
            "subcategory":"Lawyer & Legal Services",
            "type":"Services"
        }
    ],
    "sg:phone":"+1 703 534 7150",
    "sg:postcode":"22101",
    "sg:province":"VA",
    "wof:name":"Eckrod Family Partnership",
    "wof:placetype":"venue"
},
  "geometry": {"coordinates":[-77.15541,38.907914],"type":"Point"}
}