{
  "type": "Feature",
  "properties": {
    "iso:country":"US",
    "sg:address":"3802 Solebury Pl",
    "sg:city":"Midlothian",
    "sg:classifiers":[
        {
            "category":"Health Services",
            "subcategory":"Doctor",
            "type":"Services"
        }
    ],
    "sg:phone":"+1 804 272 2559",
    "sg:postcode":"23113",
    "sg:province":"VA",
    "sg:tags":[
        "medical"
    ],
    "wof:name":"L J Brown Jr MD PC",
    "wof:placetype":"venue"
},
  "geometry": {"coordinates":[-77.61333500000001,37.550314],"type":"Point"}
}