{
  "type": "Feature",
  "properties": {
    "addr:full":"3025 Broad Rock Blvd Richmond VA 23224",
    "addr:housenumber":"3025",
    "addr:postcode":"23224",
    "addr:street":"Broad Rock Blvd",
    "iso:country":"US",
    "sg:address":"3025 Broad Rock Blvd",
    "sg:city":"Richmond",
    "sg:classifiers":[
        {
            "category":"Restaurant",
            "type":"Food & Drink"
        }
    ],
    "sg:phone":"+1 804 233 3320",
    "sg:postcode":"23224",
    "sg:province":"VA",
    "wof:name":"Adelita Mexican Grill",
    "wof:placetype":"venue"
},
  "geometry": {"coordinates":[-77.481891,37.474582],"type":"Point"}
}