{
  "type": "Feature",
  "properties": {
    "iso:country":"US",
    "sg:address":"4600 Holborn Ave",
    "sg:city":"Annandale",
    "sg:classifiers":[
        {
            "category":"Wholesale",
            "subcategory":"Stationery",
            "type":"Manufacturing & Wholesale Goods"
        }
    ],
    "sg:phone":"+1 703 978 4606",
    "sg:postcode":"22003",
    "sg:province":"VA",
    "sg:tags":[
        "supply"
    ],
    "wof:name":"Safeguard Business",
    "wof:placetype":"venue"
},
  "geometry": {"coordinates":[-77.235023,38.821425],"type":"Point"}
}