{
  "type": "Feature",
  "properties": {
    "addr:full":"1513 Marshall Ave Portsmouth VA 23704",
    "addr:housenumber":"1513",
    "addr:postcode":"23704",
    "addr:street":"Marshall Ave",
    "iso:country":"US",
    "sg:address":"1513 Marshall Ave",
    "sg:city":"Portsmouth",
    "sg:classifiers":[
        {
            "category":"Building & Trades",
            "subcategory":"Electrical",
            "type":"Services"
        }
    ],
    "sg:phone":"+1 757 484 6578",
    "sg:postcode":"23704",
    "sg:province":"VA",
    "sg:tags":[
        "electrical",
        "contractor"
    ],
    "wof:name":"Darden Electric",
    "wof:placetype":"venue"
},
  "geometry": {"coordinates":[-76.31759599999999,36.815208],"type":"Point"}
}