{
  "type": "Feature",
  "properties": {
    "addr:full":"7506 Bland Dr Manassas VA 20109",
    "addr:housenumber":"7506",
    "addr:postcode":"20109",
    "addr:street":"Bland Dr",
    "iso:country":"US",
    "sg:address":"7506 Bland Dr",
    "sg:city":"Manassas",
    "sg:classifiers":[
        {
            "category":"Home & Garden",
            "subcategory":"Household Appliances",
            "type":"Retail Goods"
        }
    ],
    "sg:phone":"+1 703 330 2322",
    "sg:postcode":"20109",
    "sg:province":"VA",
    "sg:tags":[
        "cleaners",
        "vacuum"
    ],
    "wof:name":"Provacs",
    "wof:placetype":"venue"
},
  "geometry": {"coordinates":[-77.49872499999999,38.791412],"type":"Point"}
}