{
  "type": "Feature",
  "properties": {
    "addr:full":"3170 Virgie Cole Rd South Boston NC 24592",
    "addr:housenumber":"3170",
    "addr:postcode":"24592",
    "addr:street":"Virgie Cole Rd",
    "iso:country":"US",
    "sg:address":"3170 Virgie Cole Rd",
    "sg:city":"South Boston",
    "sg:classifiers":[
        {
            "category":"Building & Trades",
            "subcategory":"Plumbing",
            "type":"Services"
        }
    ],
    "sg:phone":"+1 434 572 3783",
    "sg:postcode":"24592",
    "sg:province":"NC",
    "sg:tags":[
        "contractor"
    ],
    "wof:name":"Chris Cole & Assoc Inc",
    "wof:placetype":"venue"
},
  "geometry": {"coordinates":[-78.844413,36.650894],"type":"Point"}
}