{
  "type": "Feature",
  "properties": {
    "iso:country":"US",
    "sg:address":"43085 Branower St",
    "sg:city":"Ashburn",
    "sg:classifiers":[
        {
            "category":"Building & Trades",
            "subcategory":"Cleaning & Sanitation",
            "type":"Services"
        }
    ],
    "sg:phone":"+1 703 726 6902",
    "sg:postcode":"20147",
    "sg:province":"VA",
    "sg:tags":[
        "janitorial",
        "maintenance"
    ],
    "wof:name":"ATI/Tai Joint Venture Fob 2",
    "wof:placetype":"venue"
},
  "geometry": {"coordinates":[-77.510103,39.054975],"type":"Point"}
}