{
  "type": "Feature",
  "properties": {
    "addr:full":"2602 Copper Hill Rd Herndon VA 20171",
    "addr:housenumber":"2602",
    "addr:postcode":"20171",
    "addr:street":"Copper Hill Rd",
    "iso:country":"US",
    "sg:address":"2602 Copper Hill Rd",
    "sg:city":"Herndon",
    "sg:classifiers":[
        {
            "category":"Building & Trades",
            "subcategory":"Construction",
            "type":"Services"
        }
    ],
    "sg:phone":"+1 703 713 6230",
    "sg:postcode":"20171",
    "sg:province":"VA",
    "wof:name":"Vetter John",
    "wof:placetype":"venue"
},
  "geometry": {"coordinates":[-77.416004,38.939951],"type":"Point"}
}