{
  "type": "Feature",
  "properties": {
    "addr:full":"1057 Mountain Falls Rd Winchester VA 22602",
    "addr:housenumber":"1057",
    "addr:postcode":"22602",
    "addr:street":"Mountain Falls Rd",
    "iso:country":"US",
    "sg:address":"1057 Mountain Falls Rd",
    "sg:city":"Winchester",
    "sg:classifiers":[
        {
            "category":"Insurance",
            "subcategory":"Insurance Agent",
            "type":"Services"
        }
    ],
    "sg:phone":"+1 540 877 9496",
    "sg:postcode":"22602",
    "sg:province":"VA",
    "wof:name":"A L S Services",
    "wof:placetype":"venue"
},
  "geometry": {"coordinates":[-78.369919,39.101036],"type":"Point"}
}