{
  "type": "Feature",
  "properties": {
    "addr:full":"306 Silver Leaf Rd Dugspur VA 24343",
    "addr:housenumber":"306",
    "addr:postcode":"24343",
    "addr:street":"Silver Leaf Rd",
    "iso:country":"US",
    "sg:address":"306 Silver Leaf Rd",
    "sg:city":"Dugspur",
    "sg:classifiers":[
        {
            "category":"Professional",
            "subcategory":"Business Services",
            "type":"Services"
        }
    ],
    "sg:phone":"+1 276 728 5155",
    "sg:postcode":"24343",
    "sg:province":"VA",
    "wof:name":"Internet Business Services",
    "wof:placetype":"venue"
},
  "geometry": {"coordinates":[-80.64636,36.752675],"type":"Point"}
}