{
  "type": "Feature",
  "properties": {
    "addr:full":"9335 Buckman Ave Norfolk VA 23503",
    "addr:housenumber":"9335",
    "addr:postcode":"23503",
    "addr:street":"Buckman Ave",
    "iso:country":"US",
    "sg:address":"9335 Buckman Ave",
    "sg:city":"Norfolk",
    "sg:classifiers":[
        {
            "category":"Real Estate",
            "subcategory":"Real Estate Operator",
            "type":"Services"
        }
    ],
    "sg:phone":"+1 757 587 8129",
    "sg:postcode":"23503",
    "sg:province":"VA",
    "sg:tags":[
        "apartment"
    ],
    "wof:name":"Maple Manor Apartments",
    "wof:placetype":"venue"
},
  "geometry": {"coordinates":[-76.260481,36.948763],"type":"Point"}
}