{
  "type": "Feature",
  "properties": {
    "addr:full":"3101 Northside Rd NW Roanoke VA 24019",
    "addr:housenumber":"3101",
    "addr:postcode":"24019",
    "addr:street":"Northside Rd Nw",
    "iso:country":"US",
    "sg:address":"3101 Northside Rd NW",
    "sg:city":"Roanoke",
    "sg:classifiers":[
        {
            "category":"Organizations",
            "subcategory":"Religious Organization",
            "type":"Services"
        }
    ],
    "sg:phone":"+1 540 562 2064",
    "sg:postcode":"24019",
    "sg:province":"VA",
    "wof:name":"David A Kirk Rev",
    "wof:placetype":"venue"
},
  "geometry": {"coordinates":[-80.00174199999999,37.322936],"type":"Point"}
}