{
  "type": "Feature",
  "properties": {
    "addr:full":"6423 Millhiser Ave Richmond VA 23226",
    "addr:housenumber":"6423",
    "addr:postcode":"23226",
    "addr:street":"Millhiser Ave",
    "iso:country":"US",
    "sg:address":"6423 Millhiser Ave",
    "sg:city":"Richmond",
    "sg:classifiers":[
        {
            "category":"Banks & Credit Unions",
            "subcategory":"Bank",
            "type":"Services"
        }
    ],
    "sg:phone":"+1 804 673 7333",
    "sg:postcode":"23226",
    "sg:province":"VA",
    "sg:tags":[
        "mortgage"
    ],
    "wof:name":"Alcova Mortgage",
    "wof:placetype":"venue"
},
  "geometry": {"coordinates":[-77.514461,37.591791],"type":"Point"}
}