{
  "type": "Feature",
  "properties": {
    "addr:full":"630 Short St Warrenton VA 20186",
    "addr:housenumber":"630",
    "addr:postcode":"20186",
    "addr:street":"Short St",
    "iso:country":"US",
    "sg:address":"630 Short St",
    "sg:city":"Warrenton",
    "sg:classifiers":[
        {
            "category":"Professional",
            "type":"Services"
        }
    ],
    "sg:phone":"+1 540 351 0661",
    "sg:postcode":"20186",
    "sg:province":"VA",
    "wof:name":"Studiovano",
    "wof:placetype":"venue"
},
  "geometry": {"coordinates":[-77.809966,38.724312],"type":"Point"}
}