{
  "type": "Feature",
  "properties": {
    "addr:full":"13 Gobbler Ln Vesuvius VA 24483",
    "addr:housenumber":"13",
    "addr:postcode":"24483",
    "addr:street":"Gobbler Ln",
    "iso:country":"US",
    "sg:address":"13 Gobbler Ln",
    "sg:city":"Vesuvius",
    "sg:classifiers":[
        {
            "category":"Real Estate",
            "subcategory":"Real Estate Agent",
            "type":"Services"
        }
    ],
    "sg:phone":"+1 540 377 9348",
    "sg:postcode":"24483",
    "sg:province":"VA",
    "wof:name":"Norma Staton Realtor",
    "wof:placetype":"venue"
},
  "geometry": {"coordinates":[-79.23257700000001,37.823009],"type":"Point"}
}