{
  "type": "Feature",
  "properties": {
    "iso:country":"US",
    "sg:address":"304 Riley St",
    "sg:city":"Falls Church",
    "sg:classifiers":[
        {
            "category":"Building & Trades",
            "subcategory":"Construction",
            "type":"Services"
        }
    ],
    "sg:phone":"+1 703 532 4404",
    "sg:postcode":"22046",
    "sg:province":"VA",
    "sg:tags":[
        "house"
    ],
    "wof:name":"Marc Design Building",
    "wof:placetype":"venue"
},
  "geometry": {"coordinates":[-77.17435500000001,38.888277],"type":"Point"}
}