{
  "type": "Feature",
  "properties": {
    "iso:country":"US",
    "sg:address":"719 Princess Ct",
    "sg:city":"Newport News",
    "sg:classifiers":[
        {
            "category":"Building & Trades",
            "subcategory":"Cleaning & Sanitation",
            "type":"Services"
        }
    ],
    "sg:phone":"+1 757 877 4931",
    "sg:postcode":"23608",
    "sg:province":"VA",
    "sg:tags":[
        "maintenance"
    ],
    "wof:name":"Holland Cleaning Service",
    "wof:placetype":"venue"
},
  "geometry": {"coordinates":[-76.531049,37.158355],"type":"Point"}
}