{
  "type": "Feature",
  "properties": {
    "addr:full":"2262 W Great Neck Rd Virginia Beach VA 23451",
    "addr:housenumber":"2262",
    "addr:postcode":"23451",
    "addr:street":"W Great Neck Rd",
    "iso:country":"US",
    "sg:address":"2262 W Great Neck Rd",
    "sg:city":"Virginia Beach",
    "sg:classifiers":[
        {
            "category":"Professional",
            "subcategory":"Computer Services",
            "type":"Services"
        }
    ],
    "sg:phone":"+1 757 496 2844",
    "sg:postcode":"23451",
    "sg:province":"VA",
    "sg:tags":[
        "consultant",
        "designer"
    ],
    "sg:website":"www.contemporaryartglass.com",
    "wof:name":"Coastal Computer Svc Inc",
    "wof:placetype":"venue"
},
  "geometry": {"coordinates":[-76.07123300000001,36.911321],"type":"Point"}
}