{
  "type": "Feature",
  "properties": {
    "iso:country":"US",
    "sg:address":"3555 N Somerset St",
    "sg:city":"Arlington",
    "sg:classifiers":[
        {
            "category":"Organizations",
            "subcategory":"Community Association",
            "type":"Services"
        }
    ],
    "sg:phone":"+1 703 525 4224",
    "sg:postcode":"22213",
    "sg:province":"VA",
    "sg:tags":[
        "club"
    ],
    "wof:name":"Friends Of Arlington Park",
    "wof:placetype":"venue"
},
  "geometry": {"coordinates":[-77.160347,38.900446],"type":"Point"}
}