{
  "type": "Feature",
  "properties": {
    "addr:full":"704A Little St. Alexandria Alexandria VA 22301",
    "addr:housenumber":"704a",
    "addr:postcode":"22301",
    "addr:street":"Little St.",
    "iso:country":"US",
    "sg:address":"704A Little St. Alexandria",
    "sg:city":"Alexandria",
    "sg:classifiers":[
        {
            "category":"Professional",
            "subcategory":"Computer Services",
            "type":"Services"
        }
    ],
    "sg:postcode":"22301",
    "sg:province":"VA",
    "sg:tags":[
        "password-manager"
    ],
    "sg:website":"http://www.cutepasswordmanager.com",
    "wof:name":"iBit-Lab",
    "wof:placetype":"venue"
},
  "geometry": {"coordinates":[-77.058584,38.813118],"type":"Point"}
}