{
  "type": "Feature",
  "properties": {
    "addr:full":"6016 Creek Stone Ln Centreville VA 20120",
    "addr:housenumber":"6016",
    "addr:postcode":"20120",
    "addr:street":"Creek Stone Ln",
    "iso:country":"US",
    "sg:address":"6016 Creek Stone Ln",
    "sg:city":"Centreville",
    "sg:classifiers":[
        {
            "category":"Education",
            "subcategory":"Vocational School",
            "type":"Public Place"
        }
    ],
    "sg:phone":"+1 703 517 1372",
    "sg:postcode":"20120",
    "sg:province":"VA",
    "sg:tags":[
        "processing",
        "datum"
    ],
    "wof:name":"Acnts",
    "wof:placetype":"venue"
},
  "geometry": {"coordinates":[-77.454297,38.841249],"type":"Point"}
}