{
  "type": "Feature",
  "properties": {
    "addr:full":"455 Springpark Pl Herndon VA 20170",
    "addr:housenumber":"455",
    "addr:postcode":"20170",
    "addr:street":"Springpark Pl",
    "iso:country":"US",
    "sg:address":"455 Springpark Pl",
    "sg:city":"Herndon",
    "sg:classifiers":[
        {
            "category":"Real Estate",
            "subcategory":"Developer",
            "type":"Services"
        }
    ],
    "sg:phone":"+1 703 834 9700",
    "sg:postcode":"20170",
    "sg:province":"VA",
    "sg:website":"www.dullesstation.com",
    "wof:name":"Crimson Partners",
    "wof:placetype":"venue"
},
  "geometry": {"coordinates":[-77.37822199999999,38.961891],"type":"Point"}
}