{
  "type": "Feature",
  "properties": {
    "addr:full":"3205 Churchland Blvd Chesapeake VA 23321",
    "addr:housenumber":"3205",
    "addr:postcode":"23321",
    "addr:street":"Churchland Blvd",
    "iso:country":"US",
    "sg:address":"3205 Churchland Blvd",
    "sg:city":"Chesapeake",
    "sg:classifiers":[
        {
            "category":"Health Services",
            "subcategory":"Doctor",
            "type":"Services"
        }
    ],
    "sg:phone":"+1 757 483 3030",
    "sg:postcode":"23321",
    "sg:province":"VA",
    "wof:name":"Ramirez Renato F MD",
    "wof:placetype":"venue"
},
  "geometry": {"coordinates":[-76.405304,36.865638],"type":"Point"}
}