{
  "type": "Feature",
  "properties": {
    "iso:country":"US",
    "sg:address":"5224 Sylvan Rd",
    "sg:city":"Richmond",
    "sg:classifiers":[
        {
            "category":"Real Estate",
            "subcategory":"Real Estate Operator",
            "type":"Services"
        }
    ],
    "sg:phone":"+1 804 232 1976",
    "sg:postcode":"23225",
    "sg:province":"VA",
    "sg:tags":[
        "building",
        "nonresidential"
    ],
    "wof:name":"Ckd Properties LLC",
    "wof:placetype":"venue"
},
  "geometry": {"coordinates":[-77.493754,37.526061],"type":"Point"}
}