{
  "type": "Feature",
  "properties": {
    "addr:full":"4951 Lake Brook Dr Glen Allen VA 23060",
    "addr:housenumber":"4951",
    "addr:postcode":"23060",
    "addr:street":"Lake Brook Dr",
    "iso:country":"US",
    "sg:address":"4951 Lake Brook Dr",
    "sg:city":"Glen Allen",
    "sg:classifiers":[
        {
            "category":"Professional",
            "subcategory":"Lawyer & Legal Services",
            "type":"Services"
        }
    ],
    "sg:phone":"+1 804 762 8028",
    "sg:postcode":"23060",
    "sg:province":"VA",
    "wof:name":"Harmon Clayter Corrgan Wellman",
    "wof:placetype":"venue"
},
  "geometry": {"coordinates":[-77.574769,37.667233],"type":"Point"}
}