{
  "type": "Feature",
  "properties": {
    "addr:full":"180 Plainview Rd Kinsale VA 22488",
    "addr:housenumber":"180",
    "addr:postcode":"22488",
    "addr:street":"Plainview Rd",
    "iso:country":"US",
    "sg:address":"180 Plainview Rd",
    "sg:city":"Kinsale",
    "sg:classifiers":[
        {
            "category":"Autos & Motor Vehicles",
            "subcategory":"Automobile Sales",
            "type":"Retail Goods"
        }
    ],
    "sg:phone":"+1 804 472 5455",
    "sg:postcode":"22488",
    "sg:province":"VA",
    "sg:tags":[
        "car",
        "dealer"
    ],
    "wof:name":"KMH Motor Sport",
    "wof:placetype":"venue"
},
  "geometry": {"coordinates":[-76.573364,38.03382],"type":"Point"}
}