{
  "type": "Feature",
  "properties": {
    "iso:country":"US",
    "sg:address":"4600 Millridge Pkwy",
    "sg:city":"Midlothian",
    "sg:classifiers":[
        {
            "category":"Professional",
            "subcategory":"Lawyer & Legal Services",
            "type":"Services"
        }
    ],
    "sg:phone":"+1 804 744 7277",
    "sg:postcode":"23112",
    "sg:province":"VA",
    "sg:tags":[
        "attorney"
    ],
    "sg:website":"www.spinella.com",
    "wof:name":"Spinella Owings & Shaia PC",
    "wof:placetype":"venue"
},
  "geometry": {"coordinates":[-77.64674599999999,37.422462],"type":"Point"}
}