{
  "type": "Feature",
  "properties": {
    "iso:country":"US",
    "sg:address":"108 E Washington St",
    "sg:city":"Middleburg",
    "sg:classifiers":[
        {
            "category":"Professional",
            "type":"Services"
        }
    ],
    "sg:phone":"+1 540 687 3427",
    "sg:postcode":"20117",
    "sg:province":"VA",
    "sg:tags":[
        "establishment"
    ],
    "wof:name":"Carey Ellis Co",
    "wof:placetype":"venue"
},
  "geometry": {"coordinates":[-77.733081,38.969984],"type":"Point"}
}