{
  "type": "Feature",
  "properties": {
    "addr:full":"1812 N Moore St Arlington VA 22209",
    "addr:housenumber":"1812",
    "addr:postcode":"22209",
    "addr:street":"N Moore St",
    "iso:country":"US",
    "sg:address":"1812 N Moore St",
    "sg:city":"Arlington",
    "sg:classifiers":[
        {
            "category":"Restaurant",
            "type":"Food & Drink"
        }
    ],
    "sg:phone":"+1 703 528 8188",
    "sg:postcode":"22209",
    "sg:province":"VA",
    "sg:tags":[
        "chinese"
    ],
    "wof:name":"Hunen Palace",
    "wof:placetype":"venue"
},
  "geometry": {"coordinates":[-77.071619,38.895957],"type":"Point"}
}