{
  "type": "Feature",
  "properties": {
    "addr:full":"6501 W Broad St Richmond VA 23230",
    "addr:housenumber":"6501",
    "addr:postcode":"23230",
    "addr:street":"W Broad St",
    "iso:country":"US",
    "sg:address":"6501 W Broad St",
    "sg:city":"Richmond",
    "sg:classifiers":[
        {
            "category":"Banks & Credit Unions",
            "subcategory":"Bank",
            "type":"Services"
        }
    ],
    "sg:phone":"+1 804 782 5533",
    "sg:postcode":"23230",
    "sg:province":"VA",
    "sg:tags":[
        "national",
        "commercial"
    ],
    "wof:name":"SunTrust",
    "wof:placetype":"venue"
},
  "geometry": {"coordinates":[-77.513228,37.597688],"type":"Point"}
}