{
  "type": "Feature",
  "properties": {
    "addr:full":"3413 Eastside Hwy Grottoes VA 24441",
    "addr:housenumber":"3413",
    "addr:postcode":"24441",
    "addr:street":"Eastside Hwy",
    "iso:country":"US",
    "sg:address":"3413 Eastside Hwy",
    "sg:city":"Grottoes",
    "sg:classifiers":[
        {
            "category":"Building & Trades",
            "subcategory":"Cleaning & Sanitation",
            "type":"Services"
        }
    ],
    "sg:phone":"+1 540 249 5131",
    "sg:postcode":"24441",
    "sg:province":"VA",
    "sg:tags":[
        "fireplace",
        "chimney",
        "maintenance"
    ],
    "wof:name":"Frazier's Chimney Sweep",
    "wof:placetype":"venue"
},
  "geometry": {"coordinates":[-78.835142,38.202526],"type":"Point"}
}