{
  "type": "Feature",
  "properties": {
    "addr:full":"6826 Compton Heights Cir Clifton VA 20124",
    "addr:housenumber":"6826",
    "addr:postcode":"20124",
    "addr:street":"Compton Heights Cir",
    "iso:country":"US",
    "sg:address":"6826 Compton Heights Cir",
    "sg:city":"Clifton",
    "sg:classifiers":[
        {
            "category":"Manufacturing",
            "subcategory":"Printing",
            "type":"Manufacturing & Wholesale Goods"
        }
    ],
    "sg:phone":"+1 703 968 8780",
    "sg:postcode":"20124",
    "sg:province":"VA",
    "sg:tags":[
        "lithographic",
        "commercial"
    ],
    "wof:name":"Print Shack",
    "wof:placetype":"venue"
},
  "geometry": {"coordinates":[-77.432862,38.807446],"type":"Point"}
}