{
  "type": "Feature",
  "properties": {
    "iso:country":"US",
    "sg:address":"1509 Avon St Exd",
    "sg:city":"Charlottesville",
    "sg:classifiers":[
        {
            "category":"Professional",
            "subcategory":"Management & Consulting",
            "type":"Services"
        }
    ],
    "sg:phone":"+1 434 979 2580",
    "sg:postcode":"22902",
    "sg:province":"VA",
    "sg:tags":[
        "business"
    ],
    "wof:name":"American Eductl Consulting",
    "wof:placetype":"venue"
},
  "geometry": {"coordinates":[-78.487234,38.013436],"type":"Point"}
}