{
  "type": "Feature",
  "properties": {
    "iso:country":"US",
    "sg:address":"900 E Roanoke Rd",
    "sg:city":"Sterling",
    "sg:classifiers":[
        {
            "category":"Professional",
            "subcategory":"Business Services",
            "type":"Services"
        }
    ],
    "sg:phone":"+1 703 437 5884",
    "sg:postcode":"20164",
    "sg:province":"VA",
    "wof:name":"Intelcom",
    "wof:placetype":"venue"
},
  "geometry": {"coordinates":[-77.405936,38.992816],"type":"Point"}
}