{
  "type": "Feature",
  "properties": {
    "iso:country":"US",
    "sg:address":"5394 Kempsriver Dr",
    "sg:city":"Virginia Beach",
    "sg:classifiers":[
        {
            "category":"Manufacturing",
            "subcategory":"Food",
            "type":"Manufacturing & Wholesale Goods"
        }
    ],
    "sg:phone":"+1 757 366 0704",
    "sg:postcode":"23464",
    "sg:province":"VA",
    "sg:tags":[
        "product",
        "mfg"
    ],
    "wof:name":"Laguna Bakery",
    "wof:placetype":"venue"
},
  "geometry": {"coordinates":[-76.17832799999999,36.801325],"type":"Point"}
}