{
  "type": "Feature",
  "properties": {
    "iso:country":"US",
    "sg:address":"14221 Lee Hwy",
    "sg:city":"Gainesville",
    "sg:classifiers":[
        {
            "category":"Professional",
            "subcategory":"Management & Consulting",
            "type":"Services"
        }
    ],
    "sg:phone":"+1 703 754 4087",
    "sg:postcode":"20155",
    "sg:province":"VA",
    "wof:name":"Matter of Image Marketing",
    "wof:placetype":"venue"
},
  "geometry": {"coordinates":[-77.61861399999999,38.794256],"type":"Point"}
}