{
  "type": "Feature",
  "properties": {
    "addr:full":"4614 Whitaker Pl Woodbridge VA 22193",
    "addr:housenumber":"4614",
    "addr:postcode":"22193",
    "addr:street":"Whitaker Pl",
    "iso:country":"US",
    "sg:address":"4614 Whitaker Pl",
    "sg:city":"Woodbridge",
    "sg:classifiers":[
        {
            "category":"Building & Trades",
            "subcategory":"Plumbing",
            "type":"Services"
        }
    ],
    "sg:phone":"+1 703 590 0658",
    "sg:postcode":"22193",
    "sg:province":"VA",
    "sg:tags":[
        "contractor"
    ],
    "wof:name":"Weather Chasers",
    "wof:placetype":"venue"
},
  "geometry": {"coordinates":[-77.35012999999999,38.642299],"type":"Point"}
}