{
  "type": "Feature",
  "properties": {
    "addr:full":"1924 Pohick Creek Ct Woodbridge VA 22192",
    "addr:housenumber":"1924",
    "addr:postcode":"22192",
    "addr:street":"Pohick Creek Ct",
    "iso:country":"US",
    "sg:address":"1924 Pohick Creek Ct",
    "sg:city":"Woodbridge",
    "sg:classifiers":[
        {
            "category":"Building & Trades",
            "subcategory":"Construction",
            "type":"Services"
        }
    ],
    "sg:phone":"+1 703 494 8944",
    "sg:postcode":"22192",
    "sg:province":"VA",
    "sg:tags":[
        "carpentry",
        "contractor"
    ],
    "wof:name":"Old Dominion Trim Specialists",
    "wof:placetype":"venue"
},
  "geometry": {"coordinates":[-77.271145,38.676589],"type":"Point"}
}