{
  "type": "Feature",
  "properties": {
    "iso:country":"US",
    "sg:address":"231 Springfield Ave",
    "sg:city":"Hampton",
    "sg:classifiers":[
        {
            "category":"Building & Trades",
            "subcategory":"Cleaning & Sanitation",
            "type":"Services"
        }
    ],
    "sg:phone":"+1 757 726 2990",
    "sg:postcode":"23669",
    "sg:province":"VA",
    "sg:tags":[
        "maintenance",
        "library"
    ],
    "wof:name":"City Hampton Faclty Mang",
    "wof:placetype":"venue"
},
  "geometry": {"coordinates":[-76.351088,37.030141],"type":"Point"}
}