{
  "type": "Feature",
  "properties": {
    "addr:full":"47432 River Falls Dr Sterling VA 20165",
    "addr:housenumber":"47432",
    "addr:postcode":"20165",
    "addr:street":"River Falls Dr",
    "iso:country":"US",
    "sg:address":"47432 River Falls Dr",
    "sg:city":"Sterling",
    "sg:classifiers":[
        {
            "category":"Professional",
            "subcategory":"Business Services",
            "type":"Services"
        },
        {
            "category":"Professional",
            "subcategory":"Management & Consulting",
            "type":"Services"
        }
    ],
    "sg:phone":"+1 703 948 7381",
    "sg:postcode":"20165",
    "sg:province":"VA",
    "sg:tags":[
        "marketing",
        "consultant"
    ],
    "wof:name":"Potomac Falls Group Inc",
    "wof:placetype":"venue"
},
  "geometry": {"coordinates":[-77.35777,39.048818],"type":"Point"}
}