{
  "type": "Feature",
  "properties": {
    "iso:country":"US",
    "sg:address":"1903 Colonial Ave",
    "sg:city":"Norfolk",
    "sg:classifiers":[
        {
            "category":"Personal",
            "subcategory":"Beauty Salon",
            "type":"Services"
        }
    ],
    "sg:phone":"+1 757 627 5660",
    "sg:postcode":"23517",
    "sg:province":"VA",
    "sg:tags":[
        "shop"
    ],
    "wof:name":"Art & Hair Design By James Co",
    "wof:placetype":"venue"
},
  "geometry": {"coordinates":[-76.292267,36.868257],"type":"Point"}
}