{
  "type": "Feature",
  "properties": {
    "addr:full":"5160 Lad Land Dr Fredericksburg VA 22407",
    "addr:housenumber":"5160",
    "addr:postcode":"22407",
    "addr:street":"Lad Land Dr",
    "iso:country":"US",
    "sg:address":"5160 Lad Land Dr",
    "sg:city":"Fredericksburg",
    "sg:classifiers":[
        {
            "category":"Manufacturing",
            "subcategory":"Tools & Machinery",
            "type":"Manufacturing & Wholesale Goods"
        }
    ],
    "sg:phone":"+1 540 898 3700",
    "sg:postcode":"22407",
    "sg:province":"VA",
    "sg:tags":[
        "machine",
        "grinding",
        "mfg"
    ],
    "wof:name":"Walter Grinders Inc",
    "wof:placetype":"venue"
},
  "geometry": {"coordinates":[-77.51155199999999,38.198414],"type":"Point"}
}