{
  "type": "Feature",
  "properties": {
    "addr:full":"7064 Spring Garden Dr Springfield VA 22150",
    "addr:housenumber":"7064",
    "addr:postcode":"22150",
    "addr:street":"Spring Garden Dr",
    "iso:country":"US",
    "sg:address":"7064 Spring Garden Dr",
    "sg:city":"Springfield",
    "sg:classifiers":[
        {
            "category":"Recreation",
            "type":"Entertainment"
        }
    ],
    "sg:phone":"+1 703 866 7788",
    "sg:postcode":"22150",
    "sg:province":"VA",
    "sg:tags":[
        "eating"
    ],
    "wof:name":"Great Wall Billiards",
    "wof:placetype":"venue"
},
  "geometry": {"coordinates":[-77.18489099999999,38.772788],"type":"Point"}
}