{
  "type": "Feature",
  "properties": {
    "addr:full":"201 McNair Rd Arlington VA 22211",
    "addr:housenumber":"201",
    "addr:postcode":"22211",
    "addr:street":"Mcnair Rd",
    "iso:country":"US",
    "sg:address":"201 McNair Rd",
    "sg:city":"Arlington",
    "sg:classifiers":[
        {
            "category":"Social Services",
            "subcategory":"Child Care",
            "type":"Services"
        }
    ],
    "sg:phone":"+1 703 696 3095",
    "sg:postcode":"22211",
    "sg:province":"VA",
    "sg:tags":[
        "development",
        "center"
    ],
    "wof:name":"Fort Myers Child Dev Ctr",
    "wof:placetype":"venue"
},
  "geometry": {"coordinates":[-77.07925899999999,38.874877],"type":"Point"}
}