{
  "type": "Feature",
  "properties": {
    "iso:country":"US",
    "sg:address":"2031 Plank Rd",
    "sg:city":"Fredericksburg",
    "sg:classifiers":[
        {
            "category":"Shopping",
            "subcategory":"Clothing, Apparel, & Fashions",
            "type":"Retail Goods"
        }
    ],
    "sg:phone":"+1 540 373 9090",
    "sg:postcode":"22401",
    "sg:province":"VA",
    "wof:name":"Carlton Ltd",
    "wof:placetype":"venue"
},
  "geometry": {"coordinates":[-77.49522399999999,38.295919],"type":"Point"}
}