{
  "type": "Feature",
  "properties": {
    "iso:country":"US",
    "sg:address":"405 Ferguson Bend",
    "sg:city":"Yorktown",
    "sg:classifiers":[
        {
            "category":"Organizations",
            "subcategory":"Membership Organization",
            "type":"Services"
        }
    ],
    "sg:phone":"+1 757 766 2021",
    "sg:postcode":"23693",
    "sg:province":"VA",
    "wof:name":"Womens Intl Bowl Congress",
    "wof:placetype":"venue"
},
  "geometry": {"coordinates":[-76.440136,37.103799],"type":"Point"}
}