{
  "type": "Feature",
  "properties": {
    "iso:country":"US",
    "sg:address":"353 Chatham Dr",
    "sg:city":"Newport News",
    "sg:classifiers":[
        {
            "category":"Coffee & Tea",
            "type":"Food & Drink"
        }
    ],
    "sg:menulink":"http://www.allmenus.com/va/newport-news/112050-starbucks-coffee/menu/",
    "sg:phone":"+1 757 886 9259",
    "sg:postcode":"23602",
    "sg:province":"VA",
    "sg:tags":[
        "american"
    ],
    "wof:name":"Starbucks Coffee",
    "wof:placetype":"venue"
},
  "geometry": {"coordinates":[-76.51084,37.123275],"type":"Point"}
}