{
  "type": "Feature",
  "properties": {
    "addr:full":"3021 Quarter Creek Ln Richmond VA 23294",
    "addr:housenumber":"3021",
    "addr:postcode":"23294",
    "addr:street":"Quarter Creek Ln",
    "iso:country":"US",
    "sg:address":"3021 Quarter Creek Ln",
    "sg:city":"Richmond",
    "sg:classifiers":[
        {
            "category":"Wholesale",
            "subcategory":"Vending Machines",
            "type":"Manufacturing & Wholesale Goods"
        }
    ],
    "sg:phone":"+1 804 346 2432",
    "sg:postcode":"23294",
    "sg:province":"VA",
    "sg:tags":[
        "operator"
    ],
    "wof:name":"Xtreme Glow Vending & Supplies",
    "wof:placetype":"venue"
},
  "geometry": {"coordinates":[-77.561335,37.630541],"type":"Point"}
}