{
  "type": "Feature",
  "properties": {
    "iso:country":"US",
    "sg:address":"305 Diamond Ave",
    "sg:city":"Chesapeake",
    "sg:classifiers":[
        {
            "category":"Retail",
            "subcategory":"Car Wash",
            "type":"Services"
        }
    ],
    "sg:phone":"+1 757 650 2635",
    "sg:postcode":"23323",
    "sg:province":"VA",
    "sg:tags":[
        "carwash"
    ],
    "wof:name":"Good Hands Detailing",
    "wof:placetype":"venue"
},
  "geometry": {"coordinates":[-76.34010000000001,36.744034],"type":"Point"}
}