{
  "type": "Feature",
  "properties": {
    "iso:country":"US",
    "sg:address":"6105 General Hunton Rd",
    "sg:city":"Broad Run",
    "sg:classifiers":[
        {
            "category":"Wholesale",
            "subcategory":"Farm Supplies",
            "type":"Manufacturing & Wholesale Goods"
        }
    ],
    "sg:phone":"+1 540 341 7507",
    "sg:postcode":"20137",
    "sg:province":"VA",
    "sg:tags":[
        "livestock"
    ],
    "wof:name":"Chess Inc",
    "wof:placetype":"venue"
},
  "geometry": {"coordinates":[-77.72795000000001,38.7908],"type":"Point"}
}