{
  "type": "Feature",
  "properties": {
    "addr:full":"723 Back St Port Royal VA 22535",
    "addr:housenumber":"723",
    "addr:postcode":"22535",
    "addr:street":"Back St",
    "iso:country":"US",
    "sg:address":"723 Back St",
    "sg:city":"Port Royal",
    "sg:classifiers":[
        {
            "category":"Organizations",
            "subcategory":"Religious Organization",
            "type":"Services"
        }
    ],
    "sg:phone":"+1 804 742 5590",
    "sg:postcode":"22535",
    "sg:province":"VA",
    "sg:tags":[
        "clergy"
    ],
    "wof:name":"Robert G Hill",
    "wof:placetype":"venue"
},
  "geometry": {"coordinates":[-77.194174,38.168449],"type":"Point"}
}