{
  "type": "Feature",
  "properties": {
    "addr:full":"596 Central Dr Virginia Beach VA 23454",
    "addr:housenumber":"596",
    "addr:postcode":"23454",
    "addr:street":"Central Dr",
    "iso:country":"US",
    "sg:address":"596 Central Dr",
    "sg:city":"Virginia Beach",
    "sg:classifiers":[
        {
            "category":"Utilities",
            "subcategory":"Cable",
            "type":"Services"
        }
    ],
    "sg:phone":"+1 757 431 0095",
    "sg:postcode":"23454",
    "sg:province":"VA",
    "sg:tags":[
        "advisory",
        "television",
        "investment"
    ],
    "wof:name":"Diversfied Mntring Systems LLC",
    "wof:placetype":"venue"
},
  "geometry": {"coordinates":[-76.05905199999999,36.817348],"type":"Point"}
}