{
  "type": "Feature",
  "properties": {
    "iso:country":"US",
    "sg:address":"630 Tidewater Dr",
    "sg:city":"Norfolk",
    "sg:classifiers":[
        {
            "category":"Shopping",
            "subcategory":"Discount & Variety Stores",
            "type":"Retail Goods"
        }
    ],
    "sg:phone":"+1 757 621 2711",
    "sg:postcode":"23504",
    "sg:province":"VA",
    "wof:name":"Fair Price Variety Shop",
    "wof:placetype":"venue"
},
  "geometry": {"coordinates":[-76.276455,36.849403],"type":"Point"}
}