{
  "type": "Feature",
  "properties": {
    "addr:full":"9489 Elihu Hill Rd Marshall VA 20115",
    "addr:housenumber":"9489",
    "addr:postcode":"20115",
    "addr:street":"Elihu Hill Rd",
    "iso:country":"US",
    "sg:address":"9489 Elihu Hill Rd",
    "sg:city":"Marshall",
    "sg:phone":"+1 703 754 9991",
    "sg:postcode":"20115",
    "sg:province":"VA",
    "wof:name":"Gainsville Heating & Ac",
    "wof:placetype":"venue"
},
  "geometry": {"coordinates":[-77.90881299999999,38.837955],"type":"Point"}
}