{
  "type": "Feature",
  "properties": {
    "addr:full":"3666 Lonesome Mountain Rd Charlottesville VA 22911",
    "addr:housenumber":"3666",
    "addr:postcode":"22911",
    "addr:street":"Lonesome Mountain Rd",
    "iso:country":"US",
    "sg:address":"3666 Lonesome Mountain Rd",
    "sg:city":"Charlottesville",
    "sg:classifiers":[
        {
            "category":"Building & Trades",
            "subcategory":"Construction",
            "type":"Services"
        }
    ],
    "sg:phone":"+1 434 960 8777",
    "sg:postcode":"22911",
    "sg:province":"VA",
    "sg:tags":[
        "residential",
        "nonresidential"
    ],
    "wof:name":"Cpax & Company",
    "wof:placetype":"venue"
},
  "geometry": {"coordinates":[-78.37012900000001,38.073838],"type":"Point"}
}