{
  "type": "Feature",
  "properties": {
    "iso:country":"US",
    "sg:address":"250 Norfolk Ave",
    "sg:city":"Lynchburg",
    "sg:classifiers":[
        {
            "category":"Wholesale",
            "subcategory":"Apparel",
            "type":"Manufacturing & Wholesale Goods"
        }
    ],
    "sg:phone":"+1 434 528 3223",
    "sg:postcode":"24503",
    "sg:province":"VA",
    "sg:tags":[
        "infant",
        "wear"
    ],
    "wof:name":"Once Upon A Time",
    "wof:placetype":"venue"
},
  "geometry": {"coordinates":[-79.172786,37.433588],"type":"Point"}
}