{
  "type": "Feature",
  "properties": {
    "addr:full":"1065 Edwards Ferry Rd NE Leesburg VA 20176",
    "addr:housenumber":"1065",
    "addr:postcode":"20176",
    "addr:street":"Edwards Ferry Rd Ne",
    "iso:country":"US",
    "sg:address":"1065 Edwards Ferry Rd NE",
    "sg:city":"Leesburg",
    "sg:classifiers":[
        {
            "category":"Retail",
            "subcategory":"Repair Shop",
            "type":"Services"
        }
    ],
    "sg:phone":"+1 703 771 8119",
    "sg:postcode":"20176",
    "sg:province":"VA",
    "sg:tags":[
        "repairing",
        "piano",
        "refinishing"
    ],
    "sg:website":"www.pianoco.com",
    "wof:name":"Piano Co",
    "wof:placetype":"venue"
},
  "geometry": {"coordinates":[-77.537891,39.113536],"type":"Point"}
}