{
  "type": "Feature",
  "properties": {
    "addr:full":"8115 Plantation Rd Roanoke VA 24019",
    "addr:housenumber":"8115",
    "addr:postcode":"24019",
    "addr:street":"Plantation Rd",
    "iso:country":"US",
    "sg:address":"8115 Plantation Rd",
    "sg:city":"Roanoke",
    "sg:classifiers":[
        {
            "category":"Restaurant",
            "type":"Food & Drink"
        }
    ],
    "sg:menulink":"http://www.allmenus.com/va/hollins/188149-mcdonalds/menu/",
    "sg:phone":"+1 540 362 7927",
    "sg:postcode":"24019",
    "sg:province":"VA",
    "sg:tags":[
        "burger",
        "american"
    ],
    "wof:name":"McDonald's",
    "wof:placetype":"venue"
},
  "geometry": {"coordinates":[-79.956974,37.359758],"type":"Point"}
}