{
  "type": "Feature",
  "properties": {
    "addr:full":"3900 Greenway Ct N Portsmouth VA 23707",
    "addr:housenumber":"3900",
    "addr:postcode":"23707",
    "addr:street":"Greenway Ct N",
    "iso:country":"US",
    "sg:address":"3900 Greenway Ct N",
    "sg:city":"Portsmouth",
    "sg:classifiers":[
        {
            "category":"Insurance",
            "subcategory":"Insurance Agent",
            "type":"Services"
        }
    ],
    "sg:phone":"+1 757 484 8143",
    "sg:postcode":"23707",
    "sg:province":"VA",
    "wof:name":"State Farm Insurance",
    "wof:placetype":"venue"
},
  "geometry": {"coordinates":[-76.35155899999999,36.824675],"type":"Point"}
}