{
  "type": "Feature",
  "properties": {
    "iso:country":"US",
    "sg:address":"6043 Stanfield Rd",
    "sg:city":"Spotsylvania",
    "sg:classifiers":[
        {
            "category":"Government",
            "subcategory":"Office",
            "type":"Public Place"
        }
    ],
    "sg:phone":"+1 540 582 5504",
    "sg:postcode":"22551",
    "sg:province":"VA",
    "wof:name":"Berkley County Landfill",
    "wof:placetype":"venue"
},
  "geometry": {"coordinates":[-77.56981,38.124334],"type":"Point"}
}