{
  "type": "Feature",
  "properties": {
    "iso:country":"US",
    "sg:address":"972 Laskin Rd",
    "sg:city":"Virginia Beach",
    "sg:classifiers":[
        {
            "category":"Shopping",
            "subcategory":"Jewelry",
            "type":"Retail Goods"
        }
    ],
    "sg:phone":"+1 757 422 5522",
    "sg:postcode":"23451",
    "sg:province":"VA",
    "sg:tags":[
        "jeweler"
    ],
    "wof:name":"Baker's Fine Jewelry & Gifts",
    "wof:placetype":"venue"
},
  "geometry": {"coordinates":[-75.989163,36.857474],"type":"Point"}
}