{
  "type": "Feature",
  "properties": {
    "iso:country":"US",
    "sg:address":"2877 Regent Rd",
    "sg:city":"Topping",
    "sg:classifiers":[
        {
            "category":"Building & Trades",
            "subcategory":"Electrical",
            "type":"Services"
        }
    ],
    "sg:phone":"+1 804 758 1232",
    "sg:postcode":"23169",
    "sg:province":"VA",
    "sg:tags":[
        "electric",
        "contractor"
    ],
    "wof:name":"Birdseed's Electric Svc",
    "wof:placetype":"venue"
},
  "geometry": {"coordinates":[-76.442125,37.588499],"type":"Point"}
}