{
  "type": "Feature",
  "properties": {
    "addr:full":"4 Harrell Rd Fredericksburg VA 22405",
    "addr:housenumber":"4",
    "addr:postcode":"22405",
    "addr:street":"Harrell Rd",
    "iso:country":"US",
    "sg:address":"4 Harrell Rd",
    "sg:city":"Fredericksburg",
    "sg:classifiers":[
        {
            "category":"Building & Trades",
            "subcategory":"Electrical",
            "type":"Services"
        }
    ],
    "sg:phone":"+1 540 371 1678",
    "sg:postcode":"22405",
    "sg:province":"VA",
    "sg:tags":[
        "electric",
        "contractor"
    ],
    "wof:name":"Watts Electric Inc",
    "wof:placetype":"venue"
},
  "geometry": {"coordinates":[-77.457232,38.329768],"type":"Point"}
}