{
  "type": "Feature",
  "properties": {
    "iso:country":"US",
    "sg:address":"39 Fort Evans Rd NE",
    "sg:city":"Leesburg",
    "sg:classifiers":[
        {
            "category":"Real Estate",
            "subcategory":"Surveying",
            "type":"Services"
        }
    ],
    "sg:phone":"+1 703 478 1940",
    "sg:postcode":"20176",
    "sg:province":"VA",
    "sg:tags":[
        "surveyor"
    ],
    "wof:name":"Wolford & Chen Inc",
    "wof:placetype":"venue"
},
  "geometry": {"coordinates":[-77.54061900000001,39.109405],"type":"Point"}
}