{
  "type": "Feature",
  "properties": {
    "addr:full":"6711 Williamson Rd Roanoke VA 24019",
    "addr:housenumber":"6711",
    "addr:postcode":"24019",
    "addr:street":"Williamson Rd",
    "iso:country":"US",
    "sg:address":"6711 Williamson Rd",
    "sg:city":"Roanoke",
    "sg:classifiers":[
        {
            "category":"Shopping",
            "subcategory":"Used Merchandise",
            "type":"Retail Goods"
        }
    ],
    "sg:phone":"+1 540 366 5232",
    "sg:postcode":"24019",
    "sg:province":"VA",
    "wof:name":"Dick Clark Collectables Inc",
    "wof:placetype":"venue"
},
  "geometry": {"coordinates":[-79.956068,37.338425],"type":"Point"}
}