{
  "type": "Feature",
  "properties": {
    "addr:full":"1030 McConville Rd Lynchburg VA 24502",
    "addr:postcode":"1030;24502",
    "addr:street":"Mcconville Rd",
    "iso:country":"US",
    "sg:address":"1030 McConville Rd",
    "sg:city":"Lynchburg",
    "sg:classifiers":[
        {
            "category":"Real Estate",
            "subcategory":"Real Estate Agent",
            "type":"Services"
        }
    ],
    "sg:phone":"+1 434 455 2300",
    "sg:postcode":"24502",
    "sg:province":"VA",
    "sg:tags":[
        "appraiser"
    ],
    "wof:name":"Milton May Appraisal Co",
    "wof:placetype":"venue"
},
  "geometry": {"coordinates":[-79.222403,37.384742],"type":"Point"}
}