{
  "type": "Feature",
  "properties": {
    "iso:country":"US",
    "sg:address":"7071 Highfields Farm Trl",
    "sg:city":"Roanoke",
    "sg:classifiers":[
        {
            "category":"Real Estate",
            "subcategory":"Real Estate Operator",
            "type":"Services"
        }
    ],
    "sg:phone":"+1 540 772 0836",
    "sg:postcode":"24018",
    "sg:province":"VA",
    "sg:tags":[
        "building",
        "nonresidential"
    ],
    "wof:name":"Lavender Properties LLC",
    "wof:placetype":"venue"
},
  "geometry": {"coordinates":[-80.069107,37.203239],"type":"Point"}
}