{
  "type": "Feature",
  "properties": {
    "addr:full":"344 Balls Hill Rd Heathsville VA 22473",
    "addr:housenumber":"344",
    "addr:postcode":"22473",
    "addr:street":"Balls Hill Rd",
    "iso:country":"US",
    "sg:address":"344 Balls Hill Rd",
    "sg:city":"Heathsville",
    "sg:classifiers":[
        {
            "category":"Professional",
            "type":"Services"
        }
    ],
    "sg:phone":"+1 804 580 3220",
    "sg:postcode":"22473",
    "sg:province":"VA",
    "wof:name":"Lemon Tunstall",
    "wof:placetype":"venue"
},
  "geometry": {"coordinates":[-76.388459,37.846511],"type":"Point"}
}