{
  "type": "Feature",
  "properties": {
    "addr:full":"20695 Settlers Point Pl Sterling VA 20165",
    "addr:housenumber":"20695",
    "addr:postcode":"20165",
    "addr:street":"Settlers Point Pl",
    "iso:country":"US",
    "sg:address":"20695 Settlers Point Pl",
    "sg:city":"Sterling",
    "sg:classifiers":[
        {
            "category":"Professional",
            "subcategory":"Computer Services",
            "type":"Services"
        }
    ],
    "sg:phone":"+1 703 404 1082",
    "sg:postcode":"20165",
    "sg:province":"VA",
    "sg:tags":[
        "engineering",
        "consulting"
    ],
    "wof:name":"Certaintech Inc",
    "wof:placetype":"venue"
},
  "geometry": {"coordinates":[-77.38657600000001,39.044043],"type":"Point"}
}