{
  "type": "Feature",
  "properties": {
    "addr:full":"469 Herring Hall Rd Natural Bridge VA 24578",
    "addr:housenumber":"469",
    "addr:postcode":"24578",
    "addr:street":"Herring Hall Rd",
    "iso:country":"US",
    "sg:address":"469 Herring Hall Rd",
    "sg:city":"Natural Bridge",
    "sg:classifiers":[
        {
            "category":"Real Estate",
            "subcategory":"Real Estate Agent",
            "type":"Services"
        }
    ],
    "sg:phone":"+1 540 291 2463",
    "sg:postcode":"24578",
    "sg:province":"VA",
    "wof:name":"Perkins Family Real Estate LLC",
    "wof:placetype":"venue"
},
  "geometry": {"coordinates":[-79.53269899999999,37.656476],"type":"Point"}
}