{
  "type": "Feature",
  "properties": {
    "iso:country":"US",
    "sg:address":"2721 Prosperity Ave",
    "sg:city":"Fairfax",
    "sg:classifiers":[
        {
            "category":"Professional",
            "type":"Services"
        },
        {
            "category":"Professional",
            "subcategory":"Advertising",
            "type":"Services"
        },
        {
            "category":"Manufacturing",
            "subcategory":"Printing",
            "type":"Manufacturing & Wholesale Goods"
        }
    ],
    "sg:phone":"+1 703 388 1020",
    "sg:postcode":"22031",
    "sg:province":"VA",
    "sg:tags":[
        "directory",
        "establishment",
        "guide",
        "publishing"
    ],
    "wof:name":"Vega Hispanic Yellow Pages",
    "wof:placetype":"venue"
},
  "geometry": {"coordinates":[-77.228866,38.880611],"type":"Point"}
}