{
  "type": "Feature",
  "properties": {
    "addr:full":"4538 S Boston Hwy Ringgold VA 24586",
    "addr:housenumber":"4538",
    "addr:postcode":"24586",
    "addr:street":"S Boston Hwy",
    "iso:country":"US",
    "sg:address":"4538 S Boston Hwy",
    "sg:city":"Ringgold",
    "sg:classifiers":[
        {
            "category":"Home & Garden",
            "subcategory":"Mobile Homes",
            "type":"Retail Goods"
        }
    ],
    "sg:phone":"+1 434 822 6200",
    "sg:postcode":"24586",
    "sg:province":"VA",
    "wof:name":"Virgin-Carolina Mbl Hm Sls Svc",
    "wof:placetype":"venue"
},
  "geometry": {"coordinates":[-79.265564,36.580572],"type":"Point"}
}