{
  "type": "Feature",
  "properties": {
    "iso:country":"US",
    "sg:address":"2250 Murrell Rd",
    "sg:city":"Lynchburg",
    "sg:classifiers":[
        {
            "category":"Professional",
            "subcategory":"Lawyer & Legal Services",
            "type":"Services"
        }
    ],
    "sg:phone":"+1 434 384 9435",
    "sg:postcode":"24501",
    "sg:province":"VA",
    "wof:name":"Rowland Neville",
    "wof:placetype":"venue"
},
  "geometry": {"coordinates":[-79.170422,37.408106],"type":"Point"}
}