{
  "type": "Feature",
  "properties": {
    "iso:country":"US",
    "sg:address":"637 22nd St S",
    "sg:city":"Arlington",
    "sg:classifiers":[
        {
            "category":"Local Transit",
            "type":"Transportation"
        }
    ],
    "sg:phone":"+1 703 979 3753",
    "sg:postcode":"22202",
    "sg:province":"VA",
    "sg:tags":[
        "passenger"
    ],
    "wof:name":"Pauls Executive Sedan",
    "wof:placetype":"venue"
},
  "geometry": {"coordinates":[-77.05684100000001,38.854188],"type":"Point"}
}