{
  "type": "Feature",
  "properties": {
    "addr:full":"13966 Shalestone Dr Clifton VA 20124",
    "addr:housenumber":"13966",
    "addr:postcode":"20124",
    "addr:street":"Shalestone Dr",
    "iso:country":"US",
    "sg:address":"13966 Shalestone Dr",
    "sg:city":"Clifton",
    "sg:classifiers":[
        {
            "category":"Sports & Exercise",
            "subcategory":"Gym",
            "type":"Entertainment"
        }
    ],
    "sg:phone":"+1 703 222 6008",
    "sg:postcode":"20124",
    "sg:province":"VA",
    "sg:tags":[
        "fitness",
        "physical",
        "facility"
    ],
    "wof:name":"Bodys In Sync LLC",
    "wof:placetype":"venue"
},
  "geometry": {"coordinates":[-77.42854800000001,38.812196],"type":"Point"}
}