{
  "type": "Feature",
  "properties": {
    "addr:full":"219 E Main St Louisa VA 23093",
    "addr:housenumber":"219",
    "addr:postcode":"23093",
    "addr:street":"E Main St",
    "iso:country":"US",
    "sg:address":"219 E Main St",
    "sg:city":"Louisa",
    "sg:classifiers":[
        {
            "category":"Government",
            "subcategory":"Office",
            "type":"Public Place"
        }
    ],
    "sg:phone":"+1 540 967 1400",
    "sg:postcode":"23093",
    "sg:province":"VA",
    "sg:tags":[
        "village"
    ],
    "wof:name":"Louisa Main Office",
    "wof:placetype":"venue"
},
  "geometry": {"coordinates":[-78.001414,38.023377],"type":"Point"}
}