{
  "type": "Feature",
  "properties": {
    "iso:country":"US",
    "sg:address":"2885 Ps Business Center Dr",
    "sg:city":"Woodbridge",
    "sg:classifiers":[
        {
            "category":"Professional",
            "type":"Services"
        },
        {
            "category":"Shopping",
            "subcategory":"Clothing, Apparel, & Fashions",
            "type":"Retail Goods"
        }
    ],
    "sg:phone":"+1 703 878 2208",
    "sg:postcode":"22192",
    "sg:province":"VA",
    "sg:tags":[
        "sportswear"
    ],
    "wof:name":"Platinum Gear",
    "wof:placetype":"venue"
},
  "geometry": {"coordinates":[-77.30219,38.654521],"type":"Point"}
}