{
  "type": "Feature",
  "properties": {
    "addr:full":"11881 Coloriver Rd Manassas VA 20112",
    "addr:housenumber":"11881",
    "addr:postcode":"20112",
    "addr:street":"Coloriver Rd",
    "iso:country":"US",
    "sg:address":"11881 Coloriver Rd",
    "sg:city":"Manassas",
    "sg:classifiers":[
        {
            "category":"Building & Trades",
            "subcategory":"Construction",
            "type":"Services"
        }
    ],
    "sg:phone":"+1 703 366 3160",
    "sg:postcode":"20112",
    "sg:province":"VA",
    "sg:tags":[
        "home",
        "builder"
    ],
    "wof:name":"G & M Homes",
    "wof:placetype":"venue"
},
  "geometry": {"coordinates":[-77.397992,38.693924],"type":"Point"}
}