{
  "type": "Feature",
  "properties": {
    "addr:full":"10316 Spring Run Rd Chesterfield VA 23832",
    "addr:housenumber":"10316",
    "addr:postcode":"23832",
    "addr:street":"Spring Run Rd",
    "iso:country":"US",
    "sg:address":"10316 Spring Run Rd",
    "sg:city":"Chesterfield",
    "sg:classifiers":[
        {
            "category":"Wholesale",
            "subcategory":"Construction Materials",
            "type":"Manufacturing & Wholesale Goods"
        }
    ],
    "sg:phone":"+1 804 745 2228",
    "sg:postcode":"23832",
    "sg:province":"VA",
    "sg:tags":[
        "fence"
    ],
    "wof:name":"Creative Custom Structures",
    "wof:placetype":"venue"
},
  "geometry": {"coordinates":[-77.597819,37.37003],"type":"Point"}
}