{
  "type": "Feature",
  "properties": {
    "iso:country":"US",
    "sg:address":"1655 Blue Banner Rd",
    "sg:city":"Upperville",
    "sg:classifiers":[
        {
            "category":"Professional",
            "type":"Services"
        }
    ],
    "sg:phone":"+1 540 592 3956",
    "sg:postcode":"20184",
    "sg:province":"VA",
    "wof:name":"Luzerne Co",
    "wof:placetype":"venue"
},
  "geometry": {"coordinates":[-77.88545999999999,38.971461],"type":"Point"}
}