{
  "type": "Feature",
  "properties": {
    "iso:country":"US",
    "sg:address":"502 Newbern Rd",
    "sg:city":"Pulaski",
    "sg:classifiers":[
        {
            "category":"Real Estate",
            "subcategory":"Real Estate Agent",
            "type":"Services"
        }
    ],
    "sg:phone":"+1 540 674 1072",
    "sg:postcode":"24301",
    "sg:province":"VA",
    "wof:name":"Burgess Realty Co",
    "wof:placetype":"venue"
},
  "geometry": {"coordinates":[-80.763797,37.051358],"type":"Point"}
}