{
  "type": "Feature",
  "properties": {
    "iso:country":"US",
    "sg:address":"1111 Easterly Ave",
    "sg:city":"Hampton",
    "sg:classifiers":[
        {
            "category":"Building & Trades",
            "subcategory":"Construction",
            "type":"Services"
        }
    ],
    "sg:phone":"+1 757 224 3135",
    "sg:postcode":"23669",
    "sg:province":"VA",
    "sg:tags":[
        "concrete",
        "contractor"
    ],
    "sg:website":"www.milbournemasonry.com",
    "wof:name":"Richard E Milbourne Masonry",
    "wof:placetype":"venue"
},
  "geometry": {"coordinates":[-76.35174499999999,37.040528],"type":"Point"}
}