{
  "type": "Feature",
  "properties": {
    "iso:country":"US",
    "sg:address":"2121 Eisenhower Ave",
    "sg:city":"Alexandria",
    "sg:classifiers":[
        {
            "category":"Banks & Credit Unions",
            "subcategory":"Investment Brokerage",
            "type":"Services"
        }
    ],
    "sg:phone":"+1 703 535 5426",
    "sg:postcode":"22314",
    "sg:province":"VA",
    "sg:tags":[
        "consultant",
        "planning",
        "financial"
    ],
    "wof:name":"Ing Financial Partners",
    "wof:placetype":"venue"
},
  "geometry": {"coordinates":[-77.06597499999999,38.80085],"type":"Point"}
}