{
  "type": "Feature",
  "properties": {
    "addr:full":"5006 Yorktown Blvd Arlington VA 22207",
    "addr:housenumber":"5006",
    "addr:postcode":"22207",
    "addr:street":"Yorktown Blvd",
    "iso:country":"US",
    "sg:address":"5006 Yorktown Blvd",
    "sg:city":"Arlington",
    "sg:classifiers":[
        {
            "category":"Personal",
            "subcategory":"Massage",
            "type":"Services"
        }
    ],
    "sg:phone":"+1 703 241 6674",
    "sg:postcode":"22207",
    "sg:province":"VA",
    "sg:tags":[
        "therapist"
    ],
    "wof:name":"Bill Once",
    "wof:placetype":"venue"
},
  "geometry": {"coordinates":[-77.13482399999999,38.902869],"type":"Point"}
}