{
  "type": "Feature",
  "properties": {
    "iso:country":"US",
    "sg:address":"47 N Main St",
    "sg:city":"Halifax",
    "sg:classifiers":[
        {
            "category":"Shopping",
            "subcategory":"Pharmacy",
            "type":"Retail Goods"
        }
    ],
    "sg:phone":"+1 434 476 6543",
    "sg:postcode":"24558",
    "sg:province":"VA",
    "wof:name":"Halifax Pharmacy",
    "wof:placetype":"venue"
},
  "geometry": {"coordinates":[-78.927953,36.767324],"type":"Point"}
}