{
  "type": "Feature",
  "properties": {
    "addr:full":"14117 Boydton Plank Rd Dinwiddie VA 23841",
    "addr:housenumber":"14117",
    "addr:postcode":"23841",
    "addr:street":"Boydton Plank Rd",
    "iso:country":"US",
    "sg:address":"14117 Boydton Plank Rd",
    "sg:city":"Dinwiddie",
    "sg:classifiers":[
        {
            "category":"Retail",
            "subcategory":"Auto Repair",
            "type":"Services"
        }
    ],
    "sg:phone":"+1 804 469 3260",
    "sg:postcode":"23841",
    "sg:province":"VA",
    "sg:tags":[
        "repairing",
        "automobile",
        "general"
    ],
    "wof:name":"Temple's Automotive",
    "wof:placetype":"venue"
},
  "geometry": {"coordinates":[-77.586561,37.07826],"type":"Point"}
}