{
  "type": "Feature",
  "properties": {
    "iso:country":"US",
    "sg:address":"7420 Hines Rd",
    "sg:city":"Disputanta",
    "sg:classifiers":[
        {
            "category":"Farming",
            "subcategory":"Farm",
            "type":"Manufacturing & Wholesale Goods"
        }
    ],
    "sg:phone":"+1 804 458 7112",
    "sg:postcode":"23842",
    "sg:province":"VA",
    "sg:tags":[
        "crop",
        "general"
    ],
    "wof:name":"Desmarais Farm",
    "wof:placetype":"venue"
},
  "geometry": {"coordinates":[-77.144187,37.210434],"type":"Point"}
}