{
  "type": "Feature",
  "properties": {
    "addr:full":"8175 Patrick Henry Blvd Mechanicsville VA 23116",
    "addr:housenumber":"8175",
    "addr:postcode":"23116",
    "addr:street":"Patrick Henry Blvd",
    "iso:country":"US",
    "sg:address":"8175 Patrick Henry Blvd",
    "sg:city":"Mechanicsville",
    "sg:classifiers":[
        {
            "category":"Utilities",
            "type":"Services"
        }
    ],
    "sg:phone":"+1 804 779 8021",
    "sg:postcode":"23116",
    "sg:province":"VA",
    "sg:tags":[
        "sanitary"
    ],
    "wof:name":"A-1 Snow Removal",
    "wof:placetype":"venue"
},
  "geometry": {"coordinates":[-77.383135,37.682068],"type":"Point"}
}