{
  "type": "Feature",
  "properties": {
    "addr:full":"11216 S Shore Rd Reston VA 20190",
    "addr:housenumber":"11216",
    "addr:postcode":"20190",
    "addr:street":"S Shore Rd",
    "iso:country":"US",
    "sg:address":"11216 S Shore Rd",
    "sg:city":"Reston",
    "sg:classifiers":[
        {
            "category":"Wholesale",
            "subcategory":"Durable Goods & Equipment",
            "type":"Manufacturing & Wholesale Goods"
        }
    ],
    "sg:phone":"+1 703 471 4020",
    "sg:postcode":"20190",
    "sg:province":"VA",
    "sg:tags":[
        "importer"
    ],
    "wof:name":"Trident International LTD",
    "wof:placetype":"venue"
},
  "geometry": {"coordinates":[-77.334541,38.963886],"type":"Point"}
}