{
  "type": "Feature",
  "properties": {
    "addr:full":"5800 Marshall Ave Newport News VA 23605",
    "addr:housenumber":"5800",
    "addr:postcode":"23605",
    "addr:street":"Marshall Ave",
    "iso:country":"US",
    "sg:address":"5800 Marshall Ave",
    "sg:city":"Newport News",
    "sg:classifiers":[
        {
            "category":"Education",
            "subcategory":"School",
            "type":"Public Place"
        }
    ],
    "sg:phone":"+1 757 928 6100",
    "sg:postcode":"23605",
    "sg:province":"VA",
    "sg:tags":[
        "executive"
    ],
    "wof:name":"Heritage High School",
    "wof:placetype":"venue"
},
  "geometry": {"coordinates":[-76.42895799999999,37.005129],"type":"Point"}
}