{
  "type": "Feature",
  "properties": {
    "addr:full":"4101 W Wood Harbor Ct Richmond VA 23231",
    "addr:housenumber":"4101",
    "addr:postcode":"23231",
    "addr:street":"W Wood Harbor Ct",
    "iso:country":"US",
    "sg:address":"4101 W Wood Harbor Ct",
    "sg:city":"Richmond",
    "sg:classifiers":[
        {
            "category":"Organizations",
            "subcategory":"Religious Organization",
            "type":"Services"
        }
    ],
    "sg:phone":"+1 804 236 4927",
    "sg:postcode":"23231",
    "sg:province":"VA",
    "wof:name":"Trina Holiness",
    "wof:placetype":"venue"
},
  "geometry": {"coordinates":[-77.356517,37.523621],"type":"Point"}
}