{
  "type": "Feature",
  "properties": {
    "iso:country":"US",
    "sg:address":"935 Colbourne Ave",
    "sg:city":"Vinton",
    "sg:classifiers":[
        {
            "category":"Restaurant",
            "type":"Food & Drink"
        }
    ],
    "sg:phone":"+1 540 581 1242",
    "sg:postcode":"24179",
    "sg:province":"VA",
    "sg:tags":[
        "eating"
    ],
    "wof:name":"Invisible Inc",
    "wof:placetype":"venue"
},
  "geometry": {"coordinates":[-79.886753,37.268914],"type":"Point"}
}