{
  "type": "Feature",
  "properties": {
    "iso:country":"US",
    "sg:address":"823 E Piedmont St",
    "sg:city":"Culpeper",
    "sg:classifiers":[
        {
            "category":"Professional",
            "subcategory":"Computer Services",
            "type":"Services"
        }
    ],
    "sg:phone":"+1 540 727 1060",
    "sg:postcode":"22701",
    "sg:province":"VA",
    "sg:tags":[
        "information",
        "retrieval"
    ],
    "wof:name":"Icmj",
    "wof:placetype":"venue"
},
  "geometry": {"coordinates":[-77.989482,38.475631],"type":"Point"}
}