{
  "type": "Feature",
  "properties": {
    "addr:full":"164 Baileys Sawmill Rd Amherst VA 24521",
    "addr:housenumber":"164",
    "addr:postcode":"24521",
    "addr:street":"Baileys Sawmill Rd",
    "iso:country":"US",
    "sg:address":"164 Baileys Sawmill Rd",
    "sg:city":"Amherst",
    "sg:classifiers":[
        {
            "category":"Wholesale",
            "subcategory":"Construction Materials",
            "type":"Manufacturing & Wholesale Goods"
        }
    ],
    "sg:phone":"+1 434 946 7339",
    "sg:postcode":"24521",
    "sg:province":"VA",
    "sg:tags":[
        "timberland",
        "company",
        "timber"
    ],
    "wof:name":"Smith Timber Saw Mill",
    "wof:placetype":"venue"
},
  "geometry": {"coordinates":[-79.083871,37.615054],"type":"Point"}
}