{
  "type": "Feature",
  "properties": {
    "iso:country":"US",
    "sg:address":"14406 Newton Patent Ct",
    "sg:city":"Centreville",
    "sg:classifiers":[
        {
            "category":"Professional",
            "subcategory":"Business Services",
            "type":"Services"
        }
    ],
    "sg:phone":"+1 703 968 0018",
    "sg:postcode":"20120",
    "sg:province":"VA",
    "wof:name":"T Enterprises",
    "wof:placetype":"venue"
},
  "geometry": {"coordinates":[-77.446461,38.841258],"type":"Point"}
}