{
  "type": "Feature",
  "properties": {
    "addr:full":"1613 Independence Blvd Virginia Beach VA 23455",
    "addr:housenumber":"1613",
    "addr:postcode":"23455",
    "addr:street":"Independence Blvd",
    "iso:country":"US",
    "sg:address":"1613 Independence Blvd",
    "sg:city":"Virginia Beach",
    "sg:classifiers":[
        {
            "category":"Retail",
            "subcategory":"Auto Repair",
            "type":"Services"
        }
    ],
    "sg:phone":"+1 757 363 0155",
    "sg:postcode":"23455",
    "sg:province":"VA",
    "sg:tags":[
        "general"
    ],
    "wof:name":"Accu-Tune N Lube",
    "wof:placetype":"venue"
},
  "geometry": {"coordinates":[-76.140535,36.892826],"type":"Point"}
}