{
  "type": "Feature",
  "properties": {
    "iso:country":"US",
    "sg:address":"31010 Holland Dr",
    "sg:city":"Franklin",
    "sg:classifiers":[
        {
            "category":"Building & Trades",
            "subcategory":"Construction",
            "type":"Services"
        }
    ],
    "sg:phone":"+1 757 569 9490",
    "sg:postcode":"23851",
    "sg:province":"VA",
    "sg:tags":[
        "concrete",
        "contractor"
    ],
    "wof:name":"Southern Casting & Masonry",
    "wof:placetype":"venue"
},
  "geometry": {"coordinates":[-76.98229499999999,36.628689],"type":"Point"}
}