{
  "type": "Feature",
  "properties": {
    "addr:full":"1022 Duke St Alexandria VA 22314",
    "addr:housenumber":"1022",
    "addr:postcode":"22314",
    "addr:street":"Duke St",
    "iso:country":"US",
    "sg:address":"1022 Duke St",
    "sg:city":"Alexandria",
    "sg:classifiers":[
        {
            "category":"Insurance",
            "subcategory":"Insurance Agent",
            "type":"Services"
        }
    ],
    "sg:phone":"+1 703 683 4900",
    "sg:postcode":"22314",
    "sg:province":"VA",
    "wof:name":"Bezuneh Insurance",
    "wof:placetype":"venue"
},
  "geometry": {"coordinates":[-77.05167299999999,38.803232],"type":"Point"}
}