{
  "type": "Feature",
  "properties": {
    "addr:full":"7724 Frances Dr Alexandria VA 22306",
    "addr:housenumber":"7724",
    "addr:postcode":"22306",
    "addr:street":"Frances Dr",
    "iso:country":"US",
    "sg:address":"7724 Frances Dr",
    "sg:city":"Alexandria",
    "sg:classifiers":[
        {
            "category":"Shopping",
            "subcategory":"Clothing, Apparel, & Fashions",
            "type":"Retail Goods"
        }
    ],
    "sg:phone":"+1 703 765 0225",
    "sg:postcode":"22306",
    "sg:province":"VA",
    "wof:name":"Lerner Milton Cwo 3",
    "wof:placetype":"venue"
},
  "geometry": {"coordinates":[-77.077045,38.748093],"type":"Point"}
}