{
  "type": "Feature",
  "properties": {
    "addr:full":"161 Semple Farm Rd Hampton VA 23666",
    "addr:housenumber":"161",
    "addr:postcode":"23666",
    "addr:street":"Semple Farm Rd",
    "iso:country":"US",
    "sg:address":"161 Semple Farm Rd",
    "sg:city":"Hampton",
    "sg:classifiers":[
        {
            "category":"Building & Trades",
            "subcategory":"Electrical",
            "type":"Services"
        }
    ],
    "sg:phone":"+1 757 766 7929",
    "sg:postcode":"23666",
    "sg:province":"VA",
    "sg:tags":[
        "electrical",
        "wiring"
    ],
    "wof:name":"Debbies Electrical Service",
    "wof:placetype":"venue"
},
  "geometry": {"coordinates":[-76.41062100000001,37.089089],"type":"Point"}
}