{
  "type": "Feature",
  "properties": {
    "iso:country":"US",
    "sg:address":"2327 Duke St",
    "sg:city":"Alexandria",
    "sg:classifiers":[
        {
            "category":"Real Estate",
            "subcategory":"Real Estate Operator",
            "type":"Services"
        }
    ],
    "sg:phone":"+1 703 836 7814",
    "sg:postcode":"22314",
    "sg:province":"VA",
    "sg:tags":[
        "building",
        "apartment"
    ],
    "wof:name":"Mason Gardens Apartments",
    "wof:placetype":"venue"
},
  "geometry": {"coordinates":[-77.06895799999999,38.805524],"type":"Point"}
}