{
  "type": "Feature",
  "properties": {
    "addr:full":"605 Patrice Dr SE Leesburg VA 20175",
    "addr:housenumber":"605",
    "addr:postcode":"20175",
    "addr:street":"Patrice Dr Se",
    "iso:country":"US",
    "sg:address":"605 Patrice Dr SE",
    "sg:city":"Leesburg",
    "sg:classifiers":[
        {
            "category":"Professional",
            "subcategory":"Management & Consulting",
            "type":"Services"
        }
    ],
    "sg:phone":"+1 703 777 5766",
    "sg:postcode":"20175",
    "sg:province":"VA",
    "wof:name":"Dan Tabler Sales",
    "wof:placetype":"venue"
},
  "geometry": {"coordinates":[-77.538549,39.090032],"type":"Point"}
}