{
  "type": "Feature",
  "properties": {
    "addr:full":"4525 Sudley Rd Gainesville VA 20155",
    "addr:housenumber":"4525",
    "addr:postcode":"20155",
    "addr:street":"Sudley Rd",
    "iso:country":"US",
    "sg:address":"4525 Sudley Rd",
    "sg:city":"Gainesville",
    "sg:classifiers":[
        {
            "category":"Building & Trades",
            "subcategory":"Construction",
            "type":"Services"
        }
    ],
    "sg:phone":"+1 703 754 6664",
    "sg:postcode":"20155",
    "sg:province":"VA",
    "sg:tags":[
        "house"
    ],
    "wof:name":"Straight Line Builders",
    "wof:placetype":"venue"
},
  "geometry": {"coordinates":[-77.58801099999999,38.859142],"type":"Point"}
}