{
  "type": "Feature",
  "properties": {
    "addr:full":"3105 Dillard Ct Glen Allen VA 23060",
    "addr:housenumber":"3105",
    "addr:postcode":"23060",
    "addr:street":"Dillard Ct",
    "iso:country":"US",
    "sg:address":"3105 Dillard Ct",
    "sg:city":"Glen Allen",
    "sg:phone":"+1 804 755 2356",
    "sg:postcode":"23060",
    "sg:province":"VA",
    "sg:tags":[
        "operated",
        "machine",
        "coin",
        "vending"
    ],
    "wof:name":"J The V Vending Company",
    "wof:placetype":"venue"
},
  "geometry": {"coordinates":[-77.508234,37.671116],"type":"Point"}
}