{
  "type": "Feature",
  "properties": {
    "addr:full":"6420 Wrights Ln Fredericksburg VA 22407",
    "addr:housenumber":"6420",
    "addr:postcode":"22407",
    "addr:street":"Wrights Ln",
    "iso:country":"US",
    "sg:address":"6420 Wrights Ln",
    "sg:city":"Fredericksburg",
    "sg:classifiers":[
        {
            "category":"Professional",
            "subcategory":"Accounting & Tax Preparation",
            "type":"Services"
        }
    ],
    "sg:phone":"+1 540 786 1738",
    "sg:postcode":"22407",
    "sg:province":"VA",
    "sg:tags":[
        "accountant"
    ],
    "wof:name":"Piedmont Business Service Inc",
    "wof:placetype":"venue"
},
  "geometry": {"coordinates":[-77.557169,38.290239],"type":"Point"}
}