{
  "type": "Feature",
  "properties": {
    "iso:country":"US",
    "sg:address":"607 Burton St",
    "sg:city":"Hampton",
    "sg:classifiers":[
        {
            "category":"Professional",
            "subcategory":"Management & Consulting",
            "type":"Services"
        }
    ],
    "sg:phone":"+1 757 827 5406",
    "sg:postcode":"23666",
    "sg:province":"VA",
    "wof:name":"Whealton Enterprises Inc",
    "wof:placetype":"venue"
},
  "geometry": {"coordinates":[-76.417371,37.053411],"type":"Point"}
}