{
  "type": "Feature",
  "properties": {
    "addr:full":"11238 Doswell Rd Doswell VA 23047",
    "addr:postcode":"11238;23047",
    "addr:street":"Doswell Rd",
    "iso:country":"US",
    "sg:address":"11238 Doswell Rd",
    "sg:city":"Doswell",
    "sg:classifiers":[
        {
            "category":"Building & Trades",
            "subcategory":"Construction",
            "type":"Services"
        }
    ],
    "sg:phone":"+1 804 876 3572",
    "sg:postcode":"23047",
    "sg:province":"VA",
    "sg:tags":[
        "house",
        "carpentry",
        "contractor"
    ],
    "wof:name":"W C Squires",
    "wof:placetype":"venue"
},
  "geometry": {"coordinates":[-77.48754099999999,37.858305],"type":"Point"}
}