{
  "type": "Feature",
  "properties": {
    "addr:full":"152 Hillwood Ave Falls Church VA 22046",
    "addr:housenumber":"152",
    "addr:postcode":"22046",
    "addr:street":"Hillwood Ave",
    "iso:country":"US",
    "sg:address":"152 Hillwood Ave",
    "sg:city":"Falls Church",
    "sg:classifiers":[
        {
            "category":"Professional",
            "subcategory":"Business Services",
            "type":"Services"
        }
    ],
    "sg:phone":"+1 703 533 2200",
    "sg:postcode":"22046",
    "sg:province":"VA",
    "sg:tags":[
        "interior",
        "consultant",
        "design",
        "decorator"
    ],
    "wof:name":"Euro Decor",
    "wof:placetype":"venue"
},
  "geometry": {"coordinates":[-77.173091,38.879414],"type":"Point"}
}