{
  "type": "Feature",
  "properties": {
    "iso:country":"US",
    "sg:address":"9263 Corporate Cir",
    "sg:city":"Manassas",
    "sg:classifiers":[
        {
            "category":"Government",
            "subcategory":"Office",
            "type":"Public Place"
        }
    ],
    "sg:phone":"+1 703 368 6711",
    "sg:postcode":"20110",
    "sg:province":"VA",
    "sg:tags":[
        "federal"
    ],
    "wof:name":"Natural Resources Conservation",
    "wof:placetype":"venue"
},
  "geometry": {"coordinates":[-77.49455500000001,38.754457],"type":"Point"}
}