{
  "type": "Feature",
  "properties": {
    "addr:full":"772 Cottontail Trl Mt Crawford VA 22841",
    "addr:housenumber":"772",
    "addr:postcode":"22841",
    "addr:street":"Cottontail Trl Mt",
    "iso:country":"US",
    "sg:address":"772 Cottontail Trl",
    "sg:city":"Mt Crawford",
    "sg:classifiers":[
        {
            "category":"Freight",
            "type":"Transportation"
        }
    ],
    "sg:phone":"+1 540 801 8009",
    "sg:postcode":"22841",
    "sg:province":"VA",
    "sg:tags":[
        "commercial",
        "storage"
    ],
    "wof:name":"Keens Trailers LTD",
    "wof:placetype":"venue"
},
  "geometry": {"coordinates":[-78.91030600000001,38.384037],"type":"Point"}
}