{
  "type": "Feature",
  "properties": {
    "addr:full":"100 South St E Charlottesville VA 22902",
    "addr:housenumber":"100",
    "addr:postcode":"22902",
    "addr:street":"South St E",
    "iso:country":"US",
    "sg:address":"100 South St E",
    "sg:city":"Charlottesville",
    "sg:classifiers":[
        {
            "category":"Professional",
            "type":"Services"
        }
    ],
    "sg:phone":"+1 434 984 5669",
    "sg:postcode":"22902",
    "sg:province":"VA",
    "sg:tags":[
        "establishment"
    ],
    "wof:name":"Elysium",
    "wof:placetype":"venue"
},
  "geometry": {"coordinates":[-78.48141699999999,38.029122],"type":"Point"}
}