{
  "type": "Feature",
  "properties": {
    "addr:full":"8700 Centreville Rd Manassas VA 20110",
    "addr:housenumber":"8700",
    "addr:postcode":"20110",
    "addr:street":"Centreville Rd",
    "iso:country":"US",
    "sg:address":"8700 Centreville Rd",
    "sg:city":"Manassas",
    "sg:classifiers":[
        {
            "category":"Insurance",
            "subcategory":"Insurance Agent",
            "type":"Services"
        }
    ],
    "sg:phone":"+1 703 330 7977",
    "sg:postcode":"20110",
    "sg:province":"VA",
    "wof:name":"Linda Gubitosi",
    "wof:placetype":"venue"
},
  "geometry": {"coordinates":[-77.457429,38.765161],"type":"Point"}
}