{
  "type": "Feature",
  "properties": {
    "iso:country":"US",
    "sg:address":"130 Pecan St SE",
    "sg:city":"Abingdon",
    "sg:classifiers":[
        {
            "category":"Shopping",
            "type":"Retail Goods"
        }
    ],
    "sg:phone":"+1 276 623 0255",
    "sg:postcode":"24210",
    "sg:province":"VA",
    "sg:tags":[
        "limb",
        "artificial"
    ],
    "wof:name":"Excel Prosthetics & Orthotics",
    "wof:placetype":"venue"
},
  "geometry": {"coordinates":[-81.97160599999999,36.711083],"type":"Point"}
}