{
  "type": "Feature",
  "properties": {
    "addr:full":"3210 Peoples Dr Harrisonburg VA 22801",
    "addr:housenumber":"3210",
    "addr:postcode":"22801",
    "addr:street":"Peoples Dr",
    "iso:country":"US",
    "sg:address":"3210 Peoples Dr",
    "sg:city":"Harrisonburg",
    "sg:classifiers":[
        {
            "category":"Insurance",
            "subcategory":"Insurance Agent",
            "type":"Services"
        }
    ],
    "sg:phone":"+1 540 442 8486",
    "sg:postcode":"22801",
    "sg:province":"VA",
    "wof:name":"Hammond Insurance Svc Inc",
    "wof:placetype":"venue"
},
  "geometry": {"coordinates":[-78.907228,38.410222],"type":"Point"}
}