{
  "type": "Feature",
  "properties": {
    "iso:country":"US",
    "sg:address":"1700 N Moore St",
    "sg:city":"Arlington",
    "sg:classifiers":[
        {
            "category":"Personal",
            "subcategory":"Beauty Salon",
            "type":"Services"
        },
        {
            "category":"Personal",
            "subcategory":"Barber",
            "type":"Services"
        }
    ],
    "sg:phone":"+1 703 841 1069",
    "sg:postcode":"22209",
    "sg:province":"VA",
    "sg:tags":[
        "hair"
    ],
    "sg:website":"rosslynbarbershop.com/",
    "wof:name":"Rosslyn Barbershop",
    "wof:placetype":"venue"
},
  "geometry": {"coordinates":[-77.071602,38.895463],"type":"Point"}
}