{
  "type": "Feature",
  "properties": {
    "addr:full":"1508 Myrtle Ave Danville VA 24540",
    "addr:housenumber":"1508",
    "addr:postcode":"24540",
    "addr:street":"Myrtle Ave",
    "iso:country":"US",
    "sg:address":"1508 Myrtle Ave",
    "sg:city":"Danville",
    "sg:classifiers":[
        {
            "category":"Building & Trades",
            "subcategory":"Construction",
            "type":"Services"
        }
    ],
    "sg:phone":"+1 434 793 4807",
    "sg:postcode":"24540",
    "sg:province":"VA",
    "sg:tags":[
        "house"
    ],
    "wof:name":"Irvins Floor Care",
    "wof:placetype":"venue"
},
  "geometry": {"coordinates":[-79.386155,36.60469],"type":"Point"}
}