{
  "type": "Feature",
  "properties": {
    "addr:full":"2501 60th St Hampton VA 23661",
    "addr:housenumber":"2501",
    "addr:postcode":"23661",
    "addr:street":"60Th St",
    "iso:country":"US",
    "sg:address":"2501 60th St",
    "sg:city":"Hampton",
    "sg:classifiers":[
        {
            "category":"Freight",
            "type":"Transportation"
        }
    ],
    "sg:phone":"+1 757 827 1564",
    "sg:postcode":"23661",
    "sg:province":"VA",
    "sg:tags":[
        "trucking"
    ],
    "sg:website":"www.celadontrucking.com",
    "wof:name":"Highway Express",
    "wof:placetype":"venue"
},
  "geometry": {"coordinates":[-76.39791099999999,37.01471],"type":"Point"}
}