{
  "type": "Feature",
  "properties": {
    "addr:full":"110 Greenbriar Ln Boones Mill VA 24065",
    "addr:housenumber":"110",
    "addr:postcode":"24065",
    "addr:street":"Greenbriar Ln",
    "iso:country":"US",
    "sg:address":"110 Greenbriar Ln",
    "sg:city":"Boones Mill",
    "sg:classifiers":[
        {
            "category":"Farming",
            "subcategory":"Dairy Farm",
            "type":"Manufacturing & Wholesale Goods"
        }
    ],
    "sg:phone":"+1 540 334 2607",
    "sg:postcode":"24065",
    "sg:province":"VA",
    "wof:name":"Rippledale Dairy",
    "wof:placetype":"venue"
},
  "geometry": {"coordinates":[-79.96651799999999,37.061618],"type":"Point"}
}