{
  "type": "Feature",
  "properties": {
    "addr:full":"4919 Grandin Rd SW Roanoke VA 24018",
    "addr:housenumber":"4919",
    "addr:postcode":"24018",
    "addr:street":"Grandin Rd Sw",
    "iso:country":"US",
    "sg:address":"4919 Grandin Rd SW",
    "sg:city":"Roanoke",
    "sg:classifiers":[
        {
            "category":"Home & Garden",
            "subcategory":"Hardware",
            "type":"Retail Goods"
        }
    ],
    "sg:phone":"+1 540 989 8303",
    "sg:postcode":"24018",
    "sg:province":"VA",
    "sg:tags":[
        "store"
    ],
    "wof:name":"Woods Ace Home Center & Hdwr",
    "wof:placetype":"venue"
},
  "geometry": {"coordinates":[-80.03041,37.245668],"type":"Point"}
}