{
  "type": "Feature",
  "properties": {
    "iso:country":"US",
    "sg:address":"14874 Emberdale Dr",
    "sg:city":"Woodbridge",
    "sg:classifiers":[
        {
            "category":"Building & Trades",
            "subcategory":"Cleaning & Sanitation",
            "type":"Services"
        }
    ],
    "sg:phone":"+1 571 426 0814",
    "sg:postcode":"22193",
    "sg:province":"VA",
    "wof:name":"Sunshine Cleaning Co",
    "wof:placetype":"venue"
},
  "geometry": {"coordinates":[-77.339111,38.631794],"type":"Point"}
}