{
  "type": "Feature",
  "properties": {
    "addr:full":"163 S Main St Lexington VA 24450",
    "addr:housenumber":"163",
    "addr:postcode":"24450",
    "addr:street":"S Main St",
    "iso:country":"US",
    "sg:address":"163 S Main St",
    "sg:city":"Lexington",
    "sg:classifiers":[
        {
            "category":"Government",
            "subcategory":"Office",
            "type":"Public Place"
        }
    ],
    "sg:phone":"+1 540 463 7872",
    "sg:postcode":"24450",
    "sg:province":"VA",
    "sg:tags":[
        "national",
        "security"
    ],
    "wof:name":"Recruiting Station",
    "wof:placetype":"venue"
},
  "geometry": {"coordinates":[-79.44387500000001,37.783393],"type":"Point"}
}