{
  "type": "Feature",
  "properties": {
    "iso:country":"US",
    "sg:address":"7040 Haycock Road",
    "sg:city":"Falls Church",
    "sg:classifiers":[
        {
            "category":"Local Transit",
            "type":"Transportation"
        }
    ],
    "sg:postcode":"22041",
    "sg:province":"VA",
    "sg:tags":[
        "public"
    ],
    "sg:website":"www.wmata.com/metrorail/Stations...",
    "wof:name":"West Falls Church Metro",
    "wof:placetype":"venue"
},
  "geometry": {"coordinates":[-77.18849899999999,38.896702],"type":"Point"}
}