{
  "type": "Feature",
  "properties": {
    "addr:full":"9515 Percussion Way Vienna VA 22182",
    "addr:postcode":"9515;22182",
    "addr:street":"Percussion Way",
    "iso:country":"US",
    "sg:address":"9515 Percussion Way",
    "sg:city":"Vienna",
    "sg:classifiers":[
        {
            "category":"Freight",
            "type":"Transportation"
        }
    ],
    "sg:phone":"+1 703 209 3168",
    "sg:postcode":"22182",
    "sg:province":"VA",
    "sg:tags":[
        "travel",
        "aerospace"
    ],
    "wof:name":"Vela Technology Development",
    "wof:placetype":"venue"
},
  "geometry": {"coordinates":[-77.275237,38.919646],"type":"Point"}
}