{
  "type": "Feature",
  "properties": {
    "iso:country":"US",
    "sg:address":"5213 Catterton Rd",
    "sg:city":"Free Union",
    "sg:classifiers":[
        {
            "category":"Retail",
            "subcategory":"Photofinishing",
            "type":"Services"
        }
    ],
    "sg:phone":"+1 434 973 6702",
    "sg:postcode":"22940",
    "sg:province":"VA",
    "sg:tags":[
        "laboratory"
    ],
    "wof:name":"Visionary Virginia",
    "wof:placetype":"venue"
},
  "geometry": {"coordinates":[-78.568198,38.187232],"type":"Point"}
}