{
  "type": "Feature",
  "properties": {
    "addr:full":"1445 Kempsville Rd Virginia Beach VA 23464",
    "addr:housenumber":"1445",
    "addr:postcode":"23464",
    "addr:street":"Kempsville Rd",
    "iso:country":"US",
    "sg:address":"1445 Kempsville Rd",
    "sg:city":"Virginia Beach",
    "sg:classifiers":[
        {
            "category":"Real Estate",
            "subcategory":"Real Estate Agent",
            "type":"Services"
        }
    ],
    "sg:phone":"+1 757 424 0646",
    "sg:postcode":"23464",
    "sg:province":"VA",
    "wof:name":"Real Estate Professionals",
    "wof:placetype":"venue"
},
  "geometry": {"coordinates":[-76.176618,36.79439],"type":"Point"}
}