{
  "type": "Feature",
  "properties": {
    "iso:country":"US",
    "sg:address":"1603 Hawthorne Dr",
    "sg:city":"Chesapeake",
    "sg:classifiers":[
        {
            "category":"Arts & Performance",
            "subcategory":"Theater",
            "type":"Entertainment"
        }
    ],
    "sg:phone":"+1 757 543 0049",
    "sg:postcode":"23325",
    "sg:province":"VA",
    "sg:tags":[
        "group"
    ],
    "wof:name":"Magic Moments",
    "wof:placetype":"venue"
},
  "geometry": {"coordinates":[-76.23539700000001,36.809552],"type":"Point"}
}