{
  "type": "Feature",
  "properties": {
    "addr:full":"9018 Piney Grove Dr Fairfax VA 22031",
    "addr:housenumber":"9018",
    "addr:postcode":"22031",
    "addr:street":"Piney Grove Dr",
    "iso:country":"US",
    "sg:address":"9018 Piney Grove Dr",
    "sg:city":"Fairfax",
    "sg:classifiers":[
        {
            "category":"Education",
            "subcategory":"Special Training",
            "type":"Public Place"
        }
    ],
    "sg:phone":"+1 703 560 6362",
    "sg:postcode":"22031",
    "sg:province":"VA",
    "sg:tags":[
        "instructor",
        "language"
    ],
    "wof:name":"Carmen Ferrari-Carrillo",
    "wof:placetype":"venue"
},
  "geometry": {"coordinates":[-77.256343,38.87031],"type":"Point"}
}