{
  "type": "Feature",
  "properties": {
    "iso:country":"US",
    "sg:address":"6324 Beryl Rd",
    "sg:city":"Alexandria",
    "sg:classifiers":[
        {
            "category":"Professional",
            "subcategory":"Management & Consulting",
            "type":"Services"
        }
    ],
    "sg:phone":"+1 703 916 7850",
    "sg:postcode":"22312",
    "sg:province":"VA",
    "sg:tags":[
        "counselor",
        "public",
        "relations"
    ],
    "wof:name":"Fox Rinehart Assoc",
    "wof:placetype":"venue"
},
  "geometry": {"coordinates":[-77.15368100000001,38.799755],"type":"Point"}
}