{
  "type": "Feature",
  "properties": {
    "iso:country":"US",
    "sg:address":"813 High Point Ln",
    "sg:city":"Chesapeake",
    "sg:classifiers":[
        {
            "category":"Restaurant",
            "type":"Food & Drink"
        }
    ],
    "sg:phone":"+1 757 482 7431",
    "sg:postcode":"23322",
    "sg:province":"VA",
    "sg:tags":[
        "eating"
    ],
    "wof:name":"Effective Marketing",
    "wof:placetype":"venue"
},
  "geometry": {"coordinates":[-76.206396,36.701014],"type":"Point"}
}