{
  "type": "Feature",
  "properties": {
    "iso:country":"US",
    "sg:address":"1303 King St",
    "sg:city":"Alexandria",
    "sg:classifiers":[
        {
            "category":"Shopping",
            "subcategory":"Florist",
            "type":"Retail Goods"
        }
    ],
    "sg:phone":"+1 703 299 6262",
    "sg:postcode":"22314",
    "sg:province":"VA",
    "wof:name":"Embellishments Of Alexandria",
    "wof:placetype":"venue"
},
  "geometry": {"coordinates":[-77.053573,38.805911],"type":"Point"}
}