{
  "type": "Feature",
  "properties": {
    "addr:full":"2137 Colonial Ave SW Roanoke VA 24015",
    "addr:housenumber":"2137",
    "addr:postcode":"24015",
    "addr:street":"Colonial Ave Sw",
    "iso:country":"US",
    "sg:address":"2137 Colonial Ave SW",
    "sg:city":"Roanoke",
    "sg:classifiers":[
        {
            "category":"Shopping",
            "subcategory":"Books",
            "type":"Retail Goods"
        }
    ],
    "sg:phone":"+1 540 344 1237",
    "sg:postcode":"24015",
    "sg:province":"VA",
    "sg:tags":[
        "dealer"
    ],
    "wof:name":"Ram's Head Book Shop",
    "wof:placetype":"venue"
},
  "geometry": {"coordinates":[-79.95639300000001,37.254701],"type":"Point"}
}