{
  "type": "Feature",
  "properties": {
    "addr:full":"150 Park Dr Stephens City VA 22655",
    "addr:housenumber":"150",
    "addr:postcode":"22655",
    "addr:street":"Park Dr Stephens",
    "iso:country":"US",
    "sg:address":"150 Park Dr",
    "sg:city":"Stephens City",
    "sg:classifiers":[
        {
            "category":"Recreation",
            "type":"Entertainment"
        }
    ],
    "sg:phone":"+1 540 868 1029",
    "sg:postcode":"22655",
    "sg:province":"VA",
    "sg:tags":[
        "parks"
    ],
    "wof:name":"Sherando Park Maintenance",
    "wof:placetype":"venue"
},
  "geometry": {"coordinates":[-78.18311300000001,39.072676],"type":"Point"}
}