{
  "type": "Feature",
  "properties": {
    "addr:full":"3701 Marshall Ave Newport News VA 23607",
    "addr:housenumber":"3701",
    "addr:postcode":"23607",
    "addr:street":"Marshall Ave",
    "iso:country":"US",
    "sg:address":"3701 Marshall Ave",
    "sg:city":"Newport News",
    "sg:classifiers":[
        {
            "category":"Food & Beverages",
            "subcategory":"Groceries & Convenience Stores",
            "type":"Retail Goods"
        }
    ],
    "sg:phone":"+1 757 572 1209",
    "sg:postcode":"23607",
    "sg:province":"VA",
    "wof:name":"Best Yet Supermarket",
    "wof:placetype":"venue"
},
  "geometry": {"coordinates":[-76.421136,36.992186],"type":"Point"}
}