{
  "type": "Feature",
  "properties": {
    "iso:country":"US",
    "sg:address":"660 W Main St",
    "sg:city":"Abingdon",
    "sg:classifiers":[
        {
            "category":"Autos & Motor Vehicles",
            "subcategory":"Fuel & Gas Station",
            "type":"Retail Goods"
        },
        {
            "category":"Retail",
            "subcategory":"Auto Repair",
            "type":"Services"
        }
    ],
    "sg:phone":"+1 276 628 8367",
    "sg:postcode":"24210",
    "sg:province":"VA",
    "sg:tags":[
        "repairing",
        "automobile",
        "station",
        "gasoline",
        "general"
    ],
    "wof:name":"Abingdon Auto Clinic LLC",
    "wof:placetype":"venue"
},
  "geometry": {"coordinates":[-81.993545,36.706192],"type":"Point"}
}