{
  "type": "Feature",
  "properties": {
    "addr:full":"928 Chatsworth Dr Newport News VA 23601",
    "addr:housenumber":"928",
    "addr:postcode":"23601",
    "addr:street":"Chatsworth Dr",
    "iso:country":"US",
    "sg:address":"928 Chatsworth Dr",
    "sg:city":"Newport News",
    "sg:classifiers":[
        {
            "category":"Building & Trades",
            "subcategory":"Construction",
            "type":"Services"
        }
    ],
    "sg:phone":"+1 757 534 7991",
    "sg:postcode":"23601",
    "sg:province":"VA",
    "sg:tags":[
        "contractor"
    ],
    "wof:name":"Solid Masonry Inc",
    "wof:placetype":"venue"
},
  "geometry": {"coordinates":[-76.44922699999999,37.086804],"type":"Point"}
}