{
  "type": "Feature",
  "properties": {
    "iso:country":"US",
    "sg:address":"4530 Lee Hwy",
    "sg:city":"Arlington",
    "sg:classifiers":[
        {
            "category":"Shopping",
            "subcategory":"Jewelry",
            "type":"Retail Goods"
        }
    ],
    "sg:phone":"+1 703 527 4247",
    "sg:postcode":"22207",
    "sg:province":"VA",
    "sg:website":"facetsfinejewelry.com/",
    "wof:name":"Facets",
    "wof:placetype":"venue"
},
  "geometry": {"coordinates":[-77.119102,38.898701],"type":"Point"}
}