{
  "type": "Feature",
  "properties": {
    "addr:full":"1636 Dale Ave SE Roanoke VA 24013",
    "addr:housenumber":"1636",
    "addr:postcode":"24013",
    "addr:street":"Dale Ave Se",
    "iso:country":"US",
    "sg:address":"1636 Dale Ave SE",
    "sg:city":"Roanoke",
    "sg:classifiers":[
        {
            "category":"Home & Garden",
            "subcategory":"Carpets & Floor Coverings",
            "type":"Retail Goods"
        }
    ],
    "sg:phone":"+1 540 345 2252",
    "sg:postcode":"24013",
    "sg:province":"VA",
    "sg:tags":[
        "carpeting"
    ],
    "wof:name":"B & F Home Center",
    "wof:placetype":"venue"
},
  "geometry": {"coordinates":[-79.91879400000001,37.272572],"type":"Point"}
}