{
  "type": "Feature",
  "properties": {
    "addr:full":"247 E Main St Luray VA 22835",
    "addr:housenumber":"247",
    "addr:postcode":"22835",
    "addr:street":"E Main St",
    "iso:country":"US",
    "sg:address":"247 E Main St",
    "sg:city":"Luray",
    "sg:classifiers":[
        {
            "category":"Personal",
            "subcategory":"Beauty Salon",
            "type":"Services"
        }
    ],
    "sg:phone":"+1 540 743 5788",
    "sg:postcode":"22835",
    "sg:province":"VA",
    "sg:tags":[
        "shop"
    ],
    "wof:name":"Cuttin-Up",
    "wof:placetype":"venue"
},
  "geometry": {"coordinates":[-78.45481700000001,38.665514],"type":"Point"}
}