{
  "type": "Feature",
  "properties": {
    "addr:full":"2904 Moore St Richmond VA 23230",
    "addr:housenumber":"2904",
    "addr:postcode":"23230",
    "addr:street":"Moore St",
    "iso:country":"US",
    "sg:address":"2904 Moore St",
    "sg:city":"Richmond",
    "sg:classifiers":[
        {
            "category":"Manufacturing",
            "subcategory":"Paper Products",
            "type":"Manufacturing & Wholesale Goods"
        }
    ],
    "sg:phone":"+1 804 355 3737",
    "sg:postcode":"23230",
    "sg:province":"VA",
    "sg:tags":[
        "embossing"
    ],
    "wof:name":"The Embossing Company",
    "wof:placetype":"venue"
},
  "geometry": {"coordinates":[-77.46802599999999,37.566589],"type":"Point"}
}