{
  "type": "Feature",
  "properties": {
    "addr:full":"6090 Ansley Ct Manassas VA 20112",
    "addr:housenumber":"6090",
    "addr:postcode":"20112",
    "addr:street":"Ansley Ct",
    "iso:country":"US",
    "sg:address":"6090 Ansley Ct",
    "sg:city":"Manassas",
    "sg:classifiers":[
        {
            "category":"Professional",
            "type":"Services"
        }
    ],
    "sg:phone":"+1 703 580 5075",
    "sg:postcode":"20112",
    "sg:province":"VA",
    "sg:tags":[
        "establishment"
    ],
    "wof:name":"3 U Technologies",
    "wof:placetype":"venue"
},
  "geometry": {"coordinates":[-77.397986,38.711912],"type":"Point"}
}