{
  "type": "Feature",
  "properties": {
    "addr:full":"409 S Garfield St Arlington VA 22204",
    "addr:housenumber":"409",
    "addr:postcode":"22204",
    "addr:street":"S Garfield St",
    "iso:country":"US",
    "sg:address":"409 S Garfield St",
    "sg:city":"Arlington",
    "sg:classifiers":[
        {
            "category":"Professional",
            "type":"Services"
        }
    ],
    "sg:phone":"+1 703 920 4925",
    "sg:postcode":"22204",
    "sg:province":"VA",
    "sg:tags":[
        "writer"
    ],
    "wof:name":"Prowriters Inc",
    "wof:placetype":"venue"
},
  "geometry": {"coordinates":[-77.08968900000001,38.868837],"type":"Point"}
}