{
  "type": "Feature",
  "properties": {
    "addr:full":"545 S Birdneck Rd Virginia Beach VA 23451",
    "addr:housenumber":"545",
    "addr:postcode":"23451",
    "addr:street":"S Birdneck Rd",
    "iso:country":"US",
    "sg:address":"545 S Birdneck Rd",
    "sg:city":"Virginia Beach",
    "sg:classifiers":[
        {
            "category":"Autos & Motor Vehicles",
            "subcategory":"Automobile Sales",
            "type":"Retail Goods"
        }
    ],
    "sg:phone":"+1 757 422 1655",
    "sg:postcode":"23451",
    "sg:province":"VA",
    "sg:tags":[
        "car",
        "dealer"
    ],
    "wof:name":"J P House Of Cars",
    "wof:placetype":"venue"
},
  "geometry": {"coordinates":[-75.99994700000001,36.82301],"type":"Point"}
}