{
  "type": "Feature",
  "properties": {
    "addr:full":"8191 Angela Nicole Ln Mechanicsville VA 23111",
    "addr:housenumber":"8191",
    "addr:postcode":"23111",
    "addr:street":"Angela Nicole Ln",
    "iso:country":"US",
    "sg:address":"8191 Angela Nicole Ln",
    "sg:city":"Mechanicsville",
    "sg:classifiers":[
        {
            "category":"Professional",
            "subcategory":"Management & Consulting",
            "type":"Services"
        }
    ],
    "sg:phone":"+1 804 559 8545",
    "sg:postcode":"23111",
    "sg:province":"VA",
    "wof:name":"Bryan Sherman and Associates",
    "wof:placetype":"venue"
},
  "geometry": {"coordinates":[-77.332359,37.630244],"type":"Point"}
}