{
  "type": "Feature",
  "properties": {
    "iso:country":"US",
    "sg:address":"1832 E Little Creek Rd",
    "sg:city":"Norfolk",
    "sg:classifiers":[
        {
            "category":"Autos & Motor Vehicles",
            "subcategory":"Auto Supplies",
            "type":"Retail Goods"
        }
    ],
    "sg:phone":"+1 757 531 1505",
    "sg:postcode":"23518",
    "sg:province":"VA",
    "sg:tags":[
        "home"
    ],
    "wof:name":"Autozone",
    "wof:placetype":"venue"
},
  "geometry": {"coordinates":[-76.224114,36.915914],"type":"Point"}
}