{
  "type": "Feature",
  "properties": {
    "addr:full":"1 E Broad St Richmond VA 23219",
    "addr:housenumber":"1",
    "addr:postcode":"23219",
    "addr:street":"E Broad St",
    "iso:country":"US",
    "sg:address":"1 E Broad St",
    "sg:city":"Richmond",
    "sg:classifiers":[
        {
            "category":"Shopping",
            "type":"Retail Goods"
        },
        {
            "category":"Shopping",
            "subcategory":"Gifts & Souvenirs",
            "type":"Retail Goods"
        }
    ],
    "sg:phone":"+1 804 783 1218",
    "sg:postcode":"23219",
    "sg:province":"VA",
    "sg:tags":[
        "shop",
        "merchandise"
    ],
    "wof:name":"Bridges Inc",
    "wof:placetype":"venue"
},
  "geometry": {"coordinates":[-77.441092,37.545052],"type":"Point"}
}