{
  "type": "Feature",
  "properties": {
    "addr:full":"2200 Covered Bridge Way Virginia Beach VA 23454",
    "addr:housenumber":"2200",
    "addr:postcode":"23454",
    "addr:street":"Covered Bridge Way",
    "iso:country":"US",
    "sg:address":"2200 Covered Bridge Way",
    "sg:city":"Virginia Beach",
    "sg:classifiers":[
        {
            "category":"Real Estate",
            "subcategory":"Real Estate Agent",
            "type":"Services"
        }
    ],
    "sg:phone":"+1 757 481 5079",
    "sg:postcode":"23454",
    "sg:province":"VA",
    "wof:name":"Spartan Realty",
    "wof:placetype":"venue"
},
  "geometry": {"coordinates":[-76.04369199999999,36.870467],"type":"Point"}
}