{
  "type": "Feature",
  "properties": {
    "addr:full":"1661 Cedar Hollow Way Reston VA 20194",
    "addr:housenumber":"1661",
    "addr:postcode":"20194",
    "addr:street":"Cedar Hollow Way",
    "iso:country":"US",
    "sg:address":"1661 Cedar Hollow Way",
    "sg:city":"Reston",
    "sg:classifiers":[
        {
            "category":"Manufacturing",
            "subcategory":"Aerospace",
            "type":"Manufacturing & Wholesale Goods"
        }
    ],
    "sg:phone":"+1 703 207 4500",
    "sg:postcode":"20194",
    "sg:province":"VA",
    "sg:tags":[
        "component",
        "system",
        "space"
    ],
    "sg:website":"www.lunacorp.com",
    "wof:name":"Lunacorp",
    "wof:placetype":"venue"
},
  "geometry": {"coordinates":[-77.358445,38.971655],"type":"Point"}
}