{
  "type": "Feature",
  "properties": {
    "addr:full":"1 Laguna Rd Palmyra VA 22963",
    "addr:housenumber":"1",
    "addr:postcode":"22963",
    "addr:street":"Laguna Rd",
    "iso:country":"US",
    "sg:address":"1 Laguna Rd",
    "sg:city":"Palmyra",
    "sg:classifiers":[
        {
            "category":"Professional",
            "subcategory":"Computer Services",
            "type":"Services"
        }
    ],
    "sg:phone":"+1 434 591 0290",
    "sg:postcode":"22963",
    "sg:province":"VA",
    "sg:tags":[
        "related"
    ],
    "wof:name":"Database Consulting Inc",
    "wof:placetype":"venue"
},
  "geometry": {"coordinates":[-78.31632999999999,37.912847],"type":"Point"}
}