{
  "type": "Feature",
  "properties": {
    "addr:full":"1655 Hunting Creek Dr Alexandria VA 22314",
    "addr:housenumber":"1655",
    "addr:postcode":"22314",
    "addr:street":"Hunting Creek Dr",
    "iso:country":"US",
    "sg:address":"1655 Hunting Creek Dr",
    "sg:city":"Alexandria",
    "sg:classifiers":[
        {
            "category":"Health Services",
            "subcategory":"Doctor",
            "type":"Services"
        }
    ],
    "sg:phone":"+1 703 548 0142",
    "sg:postcode":"22314",
    "sg:province":"VA",
    "sg:tags":[
        "medical"
    ],
    "wof:name":"Pat Austin",
    "wof:placetype":"venue"
},
  "geometry": {"coordinates":[-77.04544799999999,38.824382],"type":"Point"}
}