{
  "type": "Feature",
  "properties": {
    "addr:full":"801 W Broad St Richmond VA 23220",
    "addr:housenumber":"801",
    "addr:postcode":"23220",
    "addr:street":"W Broad St",
    "iso:country":"US",
    "sg:address":"801 W Broad St",
    "sg:city":"Richmond",
    "sg:classifiers":[
        {
            "category":"Restaurant",
            "type":"Food & Drink"
        }
    ],
    "sg:phone":"+1 804 359 8500",
    "sg:postcode":"23220",
    "sg:province":"VA",
    "wof:name":"Aladdin Express Restaurant",
    "wof:placetype":"venue"
},
  "geometry": {"coordinates":[-77.449556,37.550117],"type":"Point"}
}