{
  "type": "Feature",
  "properties": {
    "addr:full":"2369 S Wolfsnare Dr Virginia Beach VA 23454",
    "addr:housenumber":"2369",
    "addr:postcode":"23454",
    "addr:street":"S Wolfsnare Dr",
    "iso:country":"US",
    "sg:address":"2369 S Wolfsnare Dr",
    "sg:city":"Virginia Beach",
    "sg:classifiers":[
        {
            "category":"Real Estate",
            "subcategory":"Real Estate Agent",
            "type":"Services"
        }
    ],
    "sg:phone":"+1 757 496 0760",
    "sg:postcode":"23454",
    "sg:province":"VA",
    "wof:name":"Cal-Sims Inc",
    "wof:placetype":"venue"
},
  "geometry": {"coordinates":[-76.05212400000001,36.855174],"type":"Point"}
}