{
  "type": "Feature",
  "properties": {
    "addr:full":"720 Wilborn Ave South Boston VA 24592",
    "addr:housenumber":"720",
    "addr:postcode":"24592",
    "addr:street":"Wilborn Ave",
    "iso:country":"US",
    "sg:address":"720 Wilborn Ave",
    "sg:city":"South Boston",
    "sg:classifiers":[
        {
            "category":"Retail",
            "subcategory":"Laundry & Dry Cleaning",
            "type":"Services"
        }
    ],
    "sg:phone":"+1 434 572 3097",
    "sg:postcode":"24592",
    "sg:province":"VA",
    "sg:tags":[
        "cleaners"
    ],
    "wof:name":"Edmondsons Cleaners",
    "wof:placetype":"venue"
},
  "geometry": {"coordinates":[-78.903059,36.699711],"type":"Point"}
}