{
  "type": "Feature",
  "properties": {
    "addr:full":"1919 Plantation Rd NE Roanoke VA 24012",
    "addr:housenumber":"1919",
    "addr:postcode":"24012",
    "addr:street":"Plantation Rd Ne",
    "iso:country":"US",
    "sg:address":"1919 Plantation Rd NE",
    "sg:city":"Roanoke",
    "sg:classifiers":[
        {
            "category":"Freight",
            "type":"Transportation"
        }
    ],
    "sg:phone":"+1 540 345 9422",
    "sg:postcode":"24012",
    "sg:province":"VA",
    "sg:tags":[
        "distance",
        "hauling",
        "long"
    ],
    "sg:website":"www.sfl.com",
    "wof:name":"Southeastern Freight Lines",
    "wof:placetype":"venue"
},
  "geometry": {"coordinates":[-79.92872,37.291505],"type":"Point"}
}