{
  "type": "Feature",
  "properties": {
    "addr:full":"701 High St E Charlottesville VA 22902",
    "addr:housenumber":"701",
    "addr:postcode":"22902",
    "addr:street":"High St E",
    "iso:country":"US",
    "sg:address":"701 High St E",
    "sg:city":"Charlottesville",
    "sg:classifiers":[
        {
            "category":"Professional",
            "subcategory":"Computer Services",
            "type":"Services"
        }
    ],
    "sg:phone":"+1 434 242 4777",
    "sg:postcode":"22902",
    "sg:province":"VA",
    "sg:tags":[
        "web",
        "consulting"
    ],
    "wof:name":"Ali Works Inc",
    "wof:placetype":"venue"
},
  "geometry": {"coordinates":[-78.475308,38.031439],"type":"Point"}
}