{
  "type": "Feature",
  "properties": {
    "addr:full":"147 Lake View Ct Ruckersville VA 22968",
    "addr:housenumber":"147",
    "addr:postcode":"22968",
    "addr:street":"Lake View Ct",
    "iso:country":"US",
    "sg:address":"147 Lake View Ct",
    "sg:city":"Ruckersville",
    "sg:classifiers":[
        {
            "category":"Building & Trades",
            "subcategory":"Landscaping Services",
            "type":"Services"
        }
    ],
    "sg:phone":"+1 434 985 4787",
    "sg:postcode":"22968",
    "sg:province":"VA",
    "sg:tags":[
        "landscape",
        "contractor"
    ],
    "wof:name":"Boone's Lawn Svc Inc",
    "wof:placetype":"venue"
},
  "geometry": {"coordinates":[-78.396316,38.255008],"type":"Point"}
}