{
  "type": "Feature",
  "properties": {
    "iso:country":"US",
    "sg:address":"229 E Main St",
    "sg:city":"Luray",
    "sg:classifiers":[
        {
            "category":"Restaurant",
            "type":"Food & Drink"
        }
    ],
    "sg:phone":"+1 540 843 2066",
    "sg:postcode":"22835",
    "sg:province":"VA",
    "sg:tags":[
        "eating"
    ],
    "wof:name":"Kissys Sweets & Treats LLC",
    "wof:placetype":"venue"
},
  "geometry": {"coordinates":[-78.45504800000001,38.66552],"type":"Point"}
}