{
  "type": "Feature",
  "properties": {
    "addr:full":"5616 Hatteras Rd Virginia Beach VA 23462",
    "addr:housenumber":"5616",
    "addr:postcode":"23462",
    "addr:street":"Hatteras Rd",
    "iso:country":"US",
    "sg:address":"5616 Hatteras Rd",
    "sg:city":"Virginia Beach",
    "sg:classifiers":[
        {
            "category":"Professional",
            "subcategory":"Management & Consulting",
            "type":"Services"
        }
    ],
    "sg:phone":"+1 757 552 0880",
    "sg:postcode":"23462",
    "sg:province":"VA",
    "sg:tags":[
        "business"
    ],
    "wof:name":"L & L Consulting",
    "wof:placetype":"venue"
},
  "geometry": {"coordinates":[-76.18143499999999,36.838112],"type":"Point"}
}