{
  "type": "Feature",
  "properties": {
    "iso:country":"US",
    "sg:address":"137 Spring St",
    "sg:city":"Herndon",
    "sg:classifiers":[
        {
            "category":"Restaurant",
            "type":"Food & Drink"
        }
    ],
    "sg:menulink":"http://www.allmenus.com/va/dranesville/24744-sphinx/menu/",
    "sg:phone":"+1 703 464 0001",
    "sg:postcode":"20170",
    "sg:province":"VA",
    "sg:tags":[
        "middle",
        "eastern"
    ],
    "wof:name":"Sphinx",
    "wof:placetype":"venue"
},
  "geometry": {"coordinates":[-77.373126,38.958197],"type":"Point"}
}