{
  "type": "Feature",
  "properties": {
    "iso:country":"US",
    "sg:address":"3801 N Nelly Custis Dr",
    "sg:city":"Arlington",
    "sg:classifiers":[
        {
            "category":"Shopping",
            "subcategory":"Gifts & Souvenirs",
            "type":"Retail Goods"
        }
    ],
    "sg:phone":"+1 703 522 7411",
    "sg:postcode":"22207",
    "sg:province":"VA",
    "wof:name":"Treasure LLC",
    "wof:placetype":"venue"
},
  "geometry": {"coordinates":[-77.105255,38.903253],"type":"Point"}
}