{
  "type": "Feature",
  "properties": {
    "addr:full":"13731 Santa Rosa Ct Manassas VA 20112",
    "addr:housenumber":"13731",
    "addr:postcode":"20112",
    "addr:street":"Santa Rosa Ct",
    "iso:country":"US",
    "sg:address":"13731 Santa Rosa Ct",
    "sg:city":"Manassas",
    "sg:classifiers":[
        {
            "category":"Building & Trades",
            "subcategory":"Electrical",
            "type":"Services"
        }
    ],
    "sg:phone":"+1 703 791 5310",
    "sg:postcode":"20112",
    "sg:province":"VA",
    "sg:tags":[
        "electrical",
        "contractor"
    ],
    "wof:name":"Ron Baker & Son",
    "wof:placetype":"venue"
},
  "geometry": {"coordinates":[-77.416659,38.651979],"type":"Point"}
}