{
  "type": "Feature",
  "properties": {
    "iso:country":"US",
    "sg:address":"2413 Olde Salem Dr",
    "sg:city":"Salem",
    "sg:classifiers":[
        {
            "category":"Retail",
            "subcategory":"Auto Repair",
            "type":"Services"
        }
    ],
    "sg:phone":"+1 540 389 3994",
    "sg:postcode":"24153",
    "sg:province":"VA",
    "sg:tags":[
        "body"
    ],
    "wof:name":"Colors On Parade",
    "wof:placetype":"venue"
},
  "geometry": {"coordinates":[-80.072243,37.272915],"type":"Point"}
}