{
  "type": "Feature",
  "properties": {
    "addr:full":"623 S Washington St Alexandria VA 22314",
    "addr:housenumber":"623",
    "addr:postcode":"22314",
    "addr:street":"S Washington St",
    "iso:country":"US",
    "sg:address":"623 S Washington St",
    "sg:city":"Alexandria",
    "sg:classifiers":[
        {
            "category":"Professional",
            "subcategory":"Advertising",
            "type":"Services"
        }
    ],
    "sg:phone":"+1 703 548 1555",
    "sg:postcode":"22314",
    "sg:province":"VA",
    "sg:tags":[
        "mailing",
        "shipping"
    ],
    "wof:name":"Pac-Well Inc",
    "wof:placetype":"venue"
},
  "geometry": {"coordinates":[-77.04846499999999,38.798467],"type":"Point"}
}