{
  "type": "Feature",
  "properties": {
    "iso:country":"US",
    "sg:address":"1332 Roanoke Rd",
    "sg:city":"Daleville",
    "sg:classifiers":[
        {
            "category":"Real Estate",
            "subcategory":"Real Estate Operator",
            "type":"Services"
        }
    ],
    "sg:phone":"+1 540 966 1053",
    "sg:postcode":"24083",
    "sg:province":"VA",
    "sg:tags":[
        "building",
        "nonresidential"
    ],
    "wof:name":"First Dominion & Properties",
    "wof:placetype":"venue"
},
  "geometry": {"coordinates":[-79.91292799999999,37.403908],"type":"Point"}
}