{
  "type": "Feature",
  "properties": {
    "addr:full":"8181 Kings Hwy King George VA 22485",
    "addr:housenumber":"8181",
    "addr:postcode":"22485",
    "addr:street":"Kings Hwy",
    "iso:country":"US",
    "sg:address":"8181 Kings Hwy",
    "sg:city":"King George",
    "sg:classifiers":[
        {
            "category":"Food & Beverages",
            "subcategory":"Groceries & Convenience Stores",
            "type":"Retail Goods"
        }
    ],
    "sg:phone":"+1 540 775 5070",
    "sg:postcode":"22485",
    "sg:province":"VA",
    "wof:name":"Fas Mart",
    "wof:placetype":"venue"
},
  "geometry": {"coordinates":[-77.20473800000001,38.276474],"type":"Point"}
}