{
  "type": "Feature",
  "properties": {
    "addr:full":"132 Roffinghams Way Williamsburg VA 23185",
    "addr:housenumber":"132",
    "addr:postcode":"23185",
    "addr:street":"Roffinghams Way",
    "iso:country":"US",
    "sg:address":"132 Roffinghams Way",
    "sg:city":"Williamsburg",
    "sg:classifiers":[
        {
            "category":"Banks & Credit Unions",
            "subcategory":"Investment Brokerage",
            "type":"Services"
        }
    ],
    "sg:phone":"+1 757 565 4800",
    "sg:postcode":"23185",
    "sg:province":"VA",
    "sg:tags":[
        "advisory",
        "financial"
    ],
    "wof:name":"Hamer Trading Inc",
    "wof:placetype":"venue"
},
  "geometry": {"coordinates":[-76.651847,37.225938],"type":"Point"}
}