{
  "type": "Feature",
  "properties": {
    "iso:country":"US",
    "sg:address":"9060 Andromeda Dr",
    "sg:city":"Burke",
    "sg:classifiers":[
        {
            "category":"Place Of Worship",
            "subcategory":"Mosque",
            "type":"Public Place"
        }
    ],
    "sg:phone":"+1 703 440 9167",
    "sg:postcode":"22015",
    "sg:province":"VA",
    "wof:name":"Islamic Center Of Springfield",
    "wof:placetype":"venue"
},
  "geometry": {"coordinates":[-77.258628,38.783525],"type":"Point"}
}