{
  "type": "Feature",
  "properties": {
    "addr:full":"6095 Indian River Rd Virginia Beach VA 23464",
    "addr:housenumber":"6095",
    "addr:postcode":"23464",
    "addr:street":"Indian River Rd",
    "iso:country":"US",
    "sg:address":"6095 Indian River Rd",
    "sg:city":"Virginia Beach",
    "sg:classifiers":[
        {
            "category":"Professional",
            "subcategory":"Lawyer & Legal Services",
            "type":"Services"
        }
    ],
    "sg:phone":"+1 757 692 3810",
    "sg:postcode":"23464",
    "sg:province":"VA",
    "sg:tags":[
        "attorney"
    ],
    "wof:name":"Michael C Bruno",
    "wof:placetype":"venue"
},
  "geometry": {"coordinates":[-76.204961,36.812014],"type":"Point"}
}