{
  "type": "Feature",
  "properties": {
    "addr:full":"502 Wood Ave E Big Stone Gap VA 24219",
    "addr:housenumber":"502",
    "addr:postcode":"24219",
    "addr:street":"Wood Ave E",
    "iso:country":"US",
    "sg:address":"502 Wood Ave E",
    "sg:city":"Big Stone Gap",
    "sg:classifiers":[
        {
            "category":"Personal",
            "subcategory":"Beauty Salon",
            "type":"Services"
        }
    ],
    "sg:phone":"+1 276 523 3044",
    "sg:postcode":"24219",
    "sg:province":"VA",
    "sg:tags":[
        "manicuring"
    ],
    "wof:name":"Happiness Nails LLC",
    "wof:placetype":"venue"
},
  "geometry": {"coordinates":[-82.773535,36.86815],"type":"Point"}
}