{
  "type": "Feature",
  "properties": {
    "addr:full":"5401 Pine Ct Mineral VA 23117",
    "addr:housenumber":"5401",
    "addr:postcode":"23117",
    "addr:street":"Pine Ct",
    "iso:country":"US",
    "sg:address":"5401 Pine Ct",
    "sg:city":"Mineral",
    "sg:classifiers":[
        {
            "category":"Real Estate",
            "subcategory":"Real Estate Agent",
            "type":"Services"
        }
    ],
    "sg:phone":"+1 540 854 6593",
    "sg:postcode":"23117",
    "sg:province":"VA",
    "sg:tags":[
        "appraiser"
    ],
    "wof:name":"Appraisals Plus Of Central Va",
    "wof:placetype":"venue"
},
  "geometry": {"coordinates":[-77.86887900000001,38.108394],"type":"Point"}
}