{
  "type": "Feature",
  "properties": {
    "addr:full":"3022 Williams Dr Fairfax VA 22031",
    "addr:housenumber":"3022",
    "addr:postcode":"22031",
    "addr:street":"Williams Dr",
    "iso:country":"US",
    "sg:address":"3022 Williams Dr",
    "sg:city":"Fairfax",
    "sg:classifiers":[
        {
            "category":"Health Services",
            "subcategory":"Doctor",
            "type":"Services"
        }
    ],
    "sg:phone":"+1 703 698 8960",
    "sg:postcode":"22031",
    "sg:province":"VA",
    "sg:tags":[
        "physician",
        "surgeon"
    ],
    "wof:name":"Gastroenterology Associates",
    "wof:placetype":"venue"
},
  "geometry": {"coordinates":[-77.233825,38.865932],"type":"Point"}
}