{
  "type": "Feature",
  "properties": {
    "iso:country":"US",
    "sg:address":"1957 Fairfield Rd",
    "sg:city":"Henry",
    "sg:classifiers":[
        {
            "category":"Building & Trades",
            "subcategory":"Construction",
            "type":"Services"
        }
    ],
    "sg:phone":"+1 276 629 3727",
    "sg:postcode":"24102",
    "sg:province":"VA",
    "sg:tags":[
        "house"
    ],
    "wof:name":"Poor Boys Mobile Home Service",
    "wof:placetype":"venue"
},
  "geometry": {"coordinates":[-79.939722,36.83779],"type":"Point"}
}