{
  "type": "Feature",
  "properties": {
    "iso:country":"US",
    "sg:address":"44 Synan Rd",
    "sg:city":"Fredericksburg",
    "sg:classifiers":[
        {
            "category":"Wholesale",
            "subcategory":"Scrap",
            "type":"Manufacturing & Wholesale Goods"
        }
    ],
    "sg:phone":"+1 540 373 2844",
    "sg:postcode":"22405",
    "sg:province":"VA",
    "sg:tags":[
        "recycling",
        "center"
    ],
    "wof:name":"M & C Metal",
    "wof:placetype":"venue"
},
  "geometry": {"coordinates":[-77.44828800000001,38.322006],"type":"Point"}
}