{
  "type": "Feature",
  "properties": {
    "iso:country":"US",
    "sg:address":"1339 Ingleside Rd",
    "sg:city":"Norfolk",
    "sg:classifiers":[
        {
            "category":"Wholesale",
            "subcategory":"Construction Materials",
            "type":"Manufacturing & Wholesale Goods"
        }
    ],
    "sg:phone":"+1 757 855 8017",
    "sg:postcode":"23502",
    "sg:province":"VA",
    "sg:tags":[
        "tile"
    ],
    "wof:name":"Morris Tile Distributors",
    "wof:placetype":"venue"
},
  "geometry": {"coordinates":[-76.242648,36.85915],"type":"Point"}
}