{
  "type": "Feature",
  "properties": {
    "iso:country":"US",
    "sg:address":"21383 Fultonham Cir",
    "sg:city":"Ashburn",
    "sg:classifiers":[
        {
            "category":"Professional",
            "subcategory":"Computer Services",
            "type":"Services"
        }
    ],
    "sg:phone":"+1 703 729 8858",
    "sg:postcode":"20147",
    "sg:province":"VA",
    "sg:tags":[
        "system",
        "design",
        "integrated",
        "software"
    ],
    "wof:name":"Virtual Workgroup Tech Corp",
    "wof:placetype":"venue"
},
  "geometry": {"coordinates":[-77.47600799999999,39.024741],"type":"Point"}
}