{
  "type": "Feature",
  "properties": {
    "addr:full":"12344 Coleraine Ct Reston VA 20191",
    "addr:housenumber":"12344",
    "addr:postcode":"20191",
    "addr:street":"Coleraine Ct",
    "iso:country":"US",
    "sg:address":"12344 Coleraine Ct",
    "sg:city":"Reston",
    "sg:classifiers":[
        {
            "category":"Professional",
            "subcategory":"Management & Consulting",
            "type":"Services"
        }
    ],
    "sg:phone":"+1 703 264 0972",
    "sg:postcode":"20191",
    "sg:province":"VA",
    "wof:name":"Advanced Wellness Technologies",
    "wof:placetype":"venue"
},
  "geometry": {"coordinates":[-77.374239,38.942408],"type":"Point"}
}