{
  "type": "Feature",
  "properties": {
    "addr:full":"44208 Navajo Dr Ashburn VA 20147",
    "addr:housenumber":"44208",
    "addr:postcode":"20147",
    "addr:street":"Navajo Dr",
    "iso:country":"US",
    "sg:address":"44208 Navajo Dr",
    "sg:city":"Ashburn",
    "sg:classifiers":[
        {
            "category":"Travel",
            "subcategory":"Travel Agent",
            "type":"Entertainment"
        }
    ],
    "sg:phone":"+1 703 858 5909",
    "sg:postcode":"20147",
    "sg:province":"VA",
    "sg:tags":[
        "agency"
    ],
    "wof:name":"Odyssey Travel",
    "wof:placetype":"venue"
},
  "geometry": {"coordinates":[-77.471907,39.057229],"type":"Point"}
}