{
  "type": "Feature",
  "properties": {
    "addr:full":"660 N Witchduck Rd Virginia Beach VA 23462",
    "addr:housenumber":"660",
    "addr:postcode":"23462",
    "addr:street":"N Witchduck Rd",
    "iso:country":"US",
    "sg:address":"660 N Witchduck Rd",
    "sg:city":"Virginia Beach",
    "sg:classifiers":[
        {
            "category":"Restaurant",
            "type":"Food & Drink"
        },
        {
            "category":"Organizations",
            "subcategory":"Community Association",
            "type":"Services"
        }
    ],
    "sg:phone":"+1 757 497 4701",
    "sg:postcode":"23462",
    "sg:province":"VA",
    "wof:name":"Miss Kitty's Village Inn",
    "wof:placetype":"venue"
},
  "geometry": {"coordinates":[-76.150566,36.855773],"type":"Point"}
}