{
  "type": "Feature",
  "properties": {
    "addr:full":"7010 Little River Tpke Annandale VA 22003",
    "addr:housenumber":"7010",
    "addr:postcode":"22003",
    "addr:street":"Little River Tpke",
    "iso:country":"US",
    "sg:address":"7010 Little River Tpke",
    "sg:city":"Annandale",
    "sg:classifiers":[
        {
            "category":"Professional",
            "type":"Services"
        }
    ],
    "sg:phone":"+1 703 941 8745",
    "sg:postcode":"22003",
    "sg:province":"VA",
    "wof:name":"Professional Services Intl",
    "wof:placetype":"venue"
},
  "geometry": {"coordinates":[-77.18772199999999,38.829068],"type":"Point"}
}