{
  "type": "Feature",
  "properties": {
    "addr:full":"18888 Leaf Covered Ct Triangle VA 22172",
    "addr:housenumber":"18888",
    "addr:postcode":"22172",
    "addr:street":"Leaf Covered Ct",
    "iso:country":"US",
    "sg:address":"18888 Leaf Covered Ct",
    "sg:city":"Triangle",
    "sg:classifiers":[
        {
            "category":"Professional",
            "type":"Services"
        }
    ],
    "sg:phone":"+1 703 898 4852",
    "sg:postcode":"22172",
    "sg:province":"VA",
    "sg:tags":[
        "communications"
    ],
    "wof:name":"Rutherford and Associated",
    "wof:placetype":"venue"
},
  "geometry": {"coordinates":[-77.322734,38.547141],"type":"Point"}
}