{
  "type": "Feature",
  "properties": {
    "addr:full":"1220 N Fillmore St # 400 Arlington VA 22201",
    "addr:housenumber":"1220",
    "addr:postcode":"22201",
    "addr:street":"N Fillmore St # 400",
    "iso:country":"US",
    "sg:address":"1220 N Fillmore St # 400",
    "sg:city":"Arlington",
    "sg:classifiers":[
        {
            "category":"Professional",
            "subcategory":"Business Services",
            "type":"Services"
        }
    ],
    "sg:phone":"+1 703 518 8600",
    "sg:postcode":"22201",
    "sg:province":"VA",
    "sg:tags":[
        "holding"
    ],
    "wof:name":"Fillmore Partners",
    "wof:placetype":"venue"
},
  "geometry": {"coordinates":[-77.093076,38.887669],"type":"Point"}
}