{
  "type": "Feature",
  "properties": {
    "addr:full":"105 E Market St Leesburg VA 20176",
    "addr:housenumber":"105",
    "addr:postcode":"20176",
    "addr:street":"E Market St",
    "iso:country":"US",
    "sg:address":"105 E Market St",
    "sg:city":"Leesburg",
    "sg:classifiers":[
        {
            "category":"Insurance",
            "subcategory":"Title Insurance",
            "type":"Services"
        }
    ],
    "sg:phone":"+1 703 777 8809",
    "sg:postcode":"20176",
    "sg:province":"VA",
    "sg:tags":[
        "carrier"
    ],
    "wof:name":"Chicago Title",
    "wof:placetype":"venue"
},
  "geometry": {"coordinates":[-77.563,39.114927],"type":"Point"}
}