{
  "type": "Feature",
  "properties": {
    "addr:full":"1813 E Broad St Richmond VA 23223",
    "addr:housenumber":"1813",
    "addr:postcode":"23223",
    "addr:street":"E Broad St",
    "iso:country":"US",
    "sg:address":"1813 E Broad St",
    "sg:city":"Richmond",
    "sg:classifiers":[
        {
            "category":"Professional",
            "subcategory":"Business Services",
            "type":"Services"
        }
    ],
    "sg:phone":"+1 804 344 5623",
    "sg:postcode":"23223",
    "sg:province":"VA",
    "sg:tags":[
        "recording",
        "studio"
    ],
    "sg:website":"www.lobe.com",
    "wof:name":"In Your Ear Music",
    "wof:placetype":"venue"
},
  "geometry": {"coordinates":[-77.424374,37.534964],"type":"Point"}
}