{
  "type": "Feature",
  "properties": {
    "addr:full":"2300 Snow Goose Dr Chesapeake VA 23320",
    "addr:housenumber":"2300",
    "addr:postcode":"23320",
    "addr:street":"Snow Goose Dr",
    "iso:country":"US",
    "sg:address":"2300 Snow Goose Dr",
    "sg:city":"Chesapeake",
    "sg:classifiers":[
        {
            "category":"Real Estate",
            "subcategory":"Developer",
            "type":"Services"
        }
    ],
    "sg:phone":"+1 757 545 3898",
    "sg:postcode":"23320",
    "sg:province":"VA",
    "sg:tags":[
        "mobile",
        "home"
    ],
    "wof:name":"Sturbridge Village",
    "wof:placetype":"venue"
},
  "geometry": {"coordinates":[-76.27226400000001,36.777893],"type":"Point"}
}