{
  "type": "Feature",
  "properties": {
    "iso:country":"US",
    "sg:address":"5354 Old Stage Hwy",
    "sg:city":"Smithfield",
    "sg:classifiers":[
        {
            "category":"Government",
            "subcategory":"Fire Station",
            "type":"Public Place"
        }
    ],
    "sg:phone":"+1 757 357 3207",
    "sg:postcode":"23430",
    "sg:province":"VA",
    "sg:tags":[
        "protection"
    ],
    "wof:name":"Rushmere Volunteer Fire Dept",
    "wof:placetype":"venue"
},
  "geometry": {"coordinates":[-76.676773,37.066038],"type":"Point"}
}