{
  "type": "Feature",
  "properties": {
    "iso:country":"US",
    "sg:address":"347 Effingham St",
    "sg:city":"Portsmouth",
    "sg:classifiers":[
        {
            "category":"Travel",
            "subcategory":"Hotels & Motels",
            "type":"Entertainment"
        }
    ],
    "sg:phone":"+1 757 397 7788",
    "sg:postcode":"23704",
    "sg:province":"VA",
    "wof:name":"Comfort Inn",
    "wof:placetype":"venue"
},
  "geometry": {"coordinates":[-76.306899,36.837593],"type":"Point"}
}