{
  "type": "Feature",
  "properties": {
    "addr:full":"130 S Randolph St Lexington VA 24450",
    "addr:housenumber":"130",
    "addr:postcode":"24450",
    "addr:street":"S Randolph St",
    "iso:country":"US",
    "sg:address":"130 S Randolph St",
    "sg:city":"Lexington",
    "sg:classifiers":[
        {
            "category":"Freight",
            "type":"Transportation"
        }
    ],
    "sg:phone":"+1 540 463 5647",
    "sg:postcode":"24450",
    "sg:province":"VA",
    "sg:tags":[
        "carriage"
    ],
    "wof:name":"Lexington Carriage Co",
    "wof:placetype":"venue"
},
  "geometry": {"coordinates":[-79.442497,37.783177],"type":"Point"}
}