{
  "type": "Feature",
  "properties": {
    "iso:country":"US",
    "sg:address":"716 Park St",
    "sg:city":"Charlottesville",
    "sg:classifiers":[
        {
            "category":"Social Services",
            "subcategory":"Adult Care",
            "type":"Services"
        }
    ],
    "sg:phone":"+1 434 220 0505",
    "sg:postcode":"22902",
    "sg:province":"VA",
    "sg:tags":[
        "home",
        "group"
    ],
    "wof:name":"Virginia Neurocare",
    "wof:placetype":"venue"
},
  "geometry": {"coordinates":[-78.47489400000001,38.037153],"type":"Point"}
}