{
  "type": "Feature",
  "properties": {
    "iso:country":"US",
    "sg:address":"11909 Main St",
    "sg:city":"Fredericksburg",
    "sg:classifiers":[
        {
            "category":"Real Estate",
            "subcategory":"Real Estate Agent",
            "type":"Services"
        }
    ],
    "sg:phone":"+1 540 368 9780",
    "sg:postcode":"22408",
    "sg:province":"VA",
    "sg:tags":[
        "management"
    ],
    "wof:name":"Koger Management Grp",
    "wof:placetype":"venue"
},
  "geometry": {"coordinates":[-77.44833199999999,38.278949],"type":"Point"}
}