{
  "type": "Feature",
  "properties": {
    "addr:full":"7400 Beaufont Spring Dr Richmond VA 23225",
    "addr:housenumber":"7400",
    "addr:postcode":"23225",
    "addr:street":"Beaufont Spring Dr",
    "iso:country":"US",
    "sg:address":"7400 Beaufont Spring Dr",
    "sg:city":"Richmond",
    "sg:classifiers":[
        {
            "category":"Health Services",
            "subcategory":"Clinic",
            "type":"Services"
        }
    ],
    "sg:phone":"+1 804 272 9071",
    "sg:postcode":"23225",
    "sg:province":"VA",
    "wof:name":"Prison Health Svc",
    "wof:placetype":"venue"
},
  "geometry": {"coordinates":[-77.529188,37.508256],"type":"Point"}
}