{
  "type": "Feature",
  "properties": {
    "iso:country":"US",
    "sg:address":"3102 Plank Rd",
    "sg:city":"Fredericksburg",
    "sg:classifiers":[
        {
            "category":"Coffee & Tea",
            "type":"Food & Drink"
        }
    ],
    "sg:menulink":"http://www.allmenus.com/va/fredericksburg/121489-the-coffee-beanery/menu/",
    "sg:phone":"+1 540 785 7255",
    "sg:postcode":"22407",
    "sg:province":"VA",
    "sg:tags":[
        "american",
        "diner"
    ],
    "wof:name":"The Coffee Beanery",
    "wof:placetype":"venue"
},
  "geometry": {"coordinates":[-77.512455,38.295866],"type":"Point"}
}