{
  "type": "Feature",
  "properties": {
    "addr:full":"86 N Reid St Hamilton VA 20158",
    "addr:housenumber":"86",
    "addr:postcode":"20158",
    "addr:street":"N Reid St",
    "iso:country":"US",
    "sg:address":"86 N Reid St",
    "sg:city":"Hamilton",
    "sg:classifiers":[
        {
            "category":"Home & Garden",
            "subcategory":"Garden Supply",
            "type":"Retail Goods"
        }
    ],
    "sg:phone":"+1 540 338 7760",
    "sg:postcode":"20158",
    "sg:province":"VA",
    "sg:tags":[
        "center"
    ],
    "wof:name":"Ellmore's Garden Ctr",
    "wof:placetype":"venue"
},
  "geometry": {"coordinates":[-77.673151,39.136704],"type":"Point"}
}