{
  "type": "Feature",
  "properties": {
    "iso:country":"US",
    "sg:address":"100 Springhill Cir",
    "sg:city":"Bedford",
    "sg:classifiers":[
        {
            "category":"Professional",
            "subcategory":"Management & Consulting",
            "type":"Services"
        }
    ],
    "sg:phone":"+1 540 586 2252",
    "sg:postcode":"24523",
    "sg:province":"VA",
    "wof:name":"Peaks Quality Technical Svc",
    "wof:placetype":"venue"
},
  "geometry": {"coordinates":[-79.50791599999999,37.397348],"type":"Point"}
}