{
  "type": "Feature",
  "properties": {
    "iso:country":"US",
    "sg:address":"1622 Beckoning Ridge Rd",
    "sg:city":"Charlottesville",
    "sg:classifiers":[
        {
            "category":"Building & Trades",
            "subcategory":"Construction",
            "type":"Services"
        }
    ],
    "sg:phone":"+1 434 977 7999",
    "sg:postcode":"22901",
    "sg:province":"VA",
    "sg:tags":[
        "contractor"
    ],
    "sg:website":"www.braxtondesigngroup.com",
    "wof:name":"Braxton Design Group",
    "wof:placetype":"venue"
},
  "geometry": {"coordinates":[-78.57529599999999,38.080797],"type":"Point"}
}