{
  "type": "Feature",
  "properties": {
    "addr:full":"4011 Traylor Dr Richmond VA 23235",
    "addr:housenumber":"4011",
    "addr:postcode":"23235",
    "addr:street":"Traylor Dr",
    "iso:country":"US",
    "sg:address":"4011 Traylor Dr",
    "sg:city":"Richmond",
    "sg:classifiers":[
        {
            "category":"Building & Trades",
            "subcategory":"Construction",
            "type":"Services"
        }
    ],
    "sg:phone":"+1 804 320 0571",
    "sg:postcode":"23235",
    "sg:province":"VA",
    "sg:tags":[
        "speculative",
        "general",
        "builder",
        "contractor"
    ],
    "wof:name":"Lowry Construction Co RA",
    "wof:placetype":"venue"
},
  "geometry": {"coordinates":[-77.58793,37.550782],"type":"Point"}
}