{
  "type": "Feature",
  "properties": {
    "addr:full":"3989 White Chapel Rd Lancaster VA 22503",
    "addr:housenumber":"3989",
    "addr:postcode":"22503",
    "addr:street":"White Chapel Rd",
    "iso:country":"US",
    "sg:address":"3989 White Chapel Rd",
    "sg:city":"Lancaster",
    "sg:classifiers":[
        {
            "category":"Bars & Pubs",
            "type":"Food & Drink"
        },
        {
            "category":"Organizations",
            "subcategory":"Community Association",
            "type":"Services"
        }
    ],
    "sg:phone":"+1 804 462 0187",
    "sg:postcode":"22503",
    "sg:province":"VA",
    "sg:tags":[
        "club",
        "drinking"
    ],
    "wof:name":"Upper Lancaster Ruritan CLU B",
    "wof:placetype":"venue"
},
  "geometry": {"coordinates":[-76.529099,37.762597],"type":"Point"}
}