{
  "type": "Feature",
  "properties": {
    "addr:full":"124 Cabbel Dr Manassas VA 20111",
    "addr:housenumber":"124",
    "addr:postcode":"20111",
    "addr:street":"Cabbel Dr",
    "iso:country":"US",
    "sg:address":"124 Cabbel Dr",
    "sg:city":"Manassas",
    "sg:classifiers":[
        {
            "category":"Professional",
            "type":"Services"
        }
    ],
    "sg:phone":"+1 703 599 6016",
    "sg:postcode":"20111",
    "sg:province":"VA",
    "wof:name":"Joaquin Landscaping Service",
    "wof:placetype":"venue"
},
  "geometry": {"coordinates":[-77.45841,38.776317],"type":"Point"}
}