{
  "type": "Feature",
  "properties": {
    "addr:full":"1112 Brandon Ave SW Roanoke VA 24015",
    "addr:housenumber":"1112",
    "addr:postcode":"24015",
    "addr:street":"Brandon Ave Sw",
    "iso:country":"US",
    "sg:address":"1112 Brandon Ave SW",
    "sg:city":"Roanoke",
    "sg:classifiers":[
        {
            "category":"Shopping",
            "subcategory":"Used Merchandise",
            "type":"Retail Goods"
        }
    ],
    "sg:phone":"+1 540 343 7008",
    "sg:postcode":"24015",
    "sg:province":"VA",
    "sg:tags":[
        "antique"
    ],
    "wof:name":"Bob Andersons Antiques",
    "wof:placetype":"venue"
},
  "geometry": {"coordinates":[-79.969067,37.256961],"type":"Point"}
}