{
  "type": "Feature",
  "properties": {
    "addr:full":"290 E Liberty St Wytheville VA 24382",
    "addr:housenumber":"290",
    "addr:postcode":"24382",
    "addr:street":"E Liberty St",
    "iso:country":"US",
    "sg:address":"290 E Liberty St",
    "sg:city":"Wytheville",
    "sg:classifiers":[
        {
            "category":"Organizations",
            "subcategory":"Religious Organization",
            "type":"Services"
        }
    ],
    "sg:phone":"+1 276 223 0082",
    "sg:postcode":"24382",
    "sg:province":"VA",
    "sg:tags":[
        "church"
    ],
    "wof:name":"Mt Calvary Apostolic Church",
    "wof:placetype":"venue"
},
  "geometry": {"coordinates":[-81.076815,36.94585],"type":"Point"}
}