{
  "type": "Feature",
  "properties": {
    "iso:country":"US",
    "sg:address":"9216 Center St",
    "sg:city":"Manassas",
    "sg:classifiers":[
        {
            "category":"Real Estate",
            "subcategory":"Real Estate Agent",
            "type":"Services"
        }
    ],
    "sg:phone":"+1 703 365 7500",
    "sg:postcode":"20110",
    "sg:province":"VA",
    "sg:website":"www.crossroadsrealtors.com",
    "wof:name":"Crossroads Realty",
    "wof:placetype":"venue"
},
  "geometry": {"coordinates":[-77.474638,38.7509],"type":"Point"}
}