{
  "type": "Feature",
  "properties": {
    "addr:full":"3100 Shore Dr Virginia Beach VA 23451",
    "addr:housenumber":"3100",
    "addr:postcode":"23451",
    "addr:street":"Shore Dr",
    "iso:country":"US",
    "sg:address":"3100 Shore Dr",
    "sg:city":"Virginia Beach",
    "sg:classifiers":[
        {
            "category":"Health Services",
            "subcategory":"Nursing And Care Facility",
            "type":"Services"
        }
    ],
    "sg:phone":"+1 757 496 1785",
    "sg:postcode":"23451",
    "sg:province":"VA",
    "sg:tags":[
        "home",
        "retirement",
        "community"
    ],
    "sg:website":"www.wcbay.com",
    "wof:name":"Westminster Canterbury",
    "wof:placetype":"venue"
},
  "geometry": {"coordinates":[-76.069822,36.912077],"type":"Point"}
}