{
  "type": "Feature",
  "properties": {
    "addr:full":"690 Pine St Herndon VA 20170",
    "addr:housenumber":"690",
    "addr:postcode":"20170",
    "addr:street":"Pine St",
    "iso:country":"US",
    "sg:address":"690 Pine St",
    "sg:city":"Herndon",
    "sg:classifiers":[
        {
            "category":"Professional",
            "subcategory":"Business Services",
            "type":"Services"
        }
    ],
    "sg:phone":"+1 703 435 5700",
    "sg:postcode":"20170",
    "sg:province":"VA",
    "wof:name":"Homeworks",
    "wof:placetype":"venue"
},
  "geometry": {"coordinates":[-77.384573,38.970961],"type":"Point"}
}