{
  "type": "Feature",
  "properties": {
    "iso:country":"US",
    "sg:address":"526 S Commerce St",
    "sg:city":"Marion",
    "sg:classifiers":[
        {
            "category":"Autos & Motor Vehicles",
            "subcategory":"Auto Supplies",
            "type":"Retail Goods"
        }
    ],
    "sg:phone":"+1 276 783 3181",
    "sg:postcode":"24354",
    "sg:province":"VA",
    "sg:tags":[
        "automobile",
        "parts"
    ],
    "wof:name":"Grissom Motor Parts Inc",
    "wof:placetype":"venue"
},
  "geometry": {"coordinates":[-81.512367,36.830768],"type":"Point"}
}