{
  "type": "Feature",
  "properties": {
    "addr:full":"1317 Dulles Pl Herndon VA 20170",
    "addr:housenumber":"1317",
    "addr:postcode":"20170",
    "addr:street":"Dulles Pl",
    "iso:country":"US",
    "sg:address":"1317 Dulles Pl",
    "sg:city":"Herndon",
    "sg:classifiers":[
        {
            "category":"Home & Garden",
            "subcategory":"Carpets & Floor Coverings",
            "type":"Retail Goods"
        }
    ],
    "sg:phone":"+1 703 481 5155",
    "sg:postcode":"20170",
    "sg:province":"VA",
    "wof:name":"Carpet Doctors",
    "wof:placetype":"venue"
},
  "geometry": {"coordinates":[-77.40563,38.972783],"type":"Point"}
}