{
  "type": "Feature",
  "properties": {
    "addr:full":"201 S Hill Ave South Hill VA 23970",
    "addr:housenumber":"201",
    "addr:postcode":"23970",
    "addr:street":"S Hill Ave",
    "iso:country":"US",
    "sg:address":"201 S Hill Ave",
    "sg:city":"South Hill",
    "sg:classifiers":[
        {
            "category":"Personal",
            "subcategory":"Beauty Salon",
            "type":"Services"
        }
    ],
    "sg:phone":"+1 434 447 7040",
    "sg:postcode":"23970",
    "sg:province":"VA",
    "wof:name":"Simply Wendy's A Cut Above",
    "wof:placetype":"venue"
},
  "geometry": {"coordinates":[-78.13081,36.72434],"type":"Point"}
}