{
  "type": "Feature",
  "properties": {
    "addr:full":"9004 Falcon Glen Ct Bristow VA 20136",
    "addr:housenumber":"9004",
    "addr:postcode":"20136",
    "addr:street":"Falcon Glen Ct",
    "iso:country":"US",
    "sg:address":"9004 Falcon Glen Ct",
    "sg:city":"Bristow",
    "sg:classifiers":[
        {
            "category":"Organizations",
            "subcategory":"Community Association",
            "type":"Services"
        }
    ],
    "sg:phone":"+1 703 753 2491",
    "sg:postcode":"20136",
    "sg:province":"VA",
    "wof:name":"Optimist International",
    "wof:placetype":"venue"
},
  "geometry": {"coordinates":[-77.583566,38.761764],"type":"Point"}
}