{
  "type": "Feature",
  "properties": {
    "addr:full":"11874 Spectrum Ctr Reston VA 20190",
    "addr:housenumber":"11874",
    "addr:postcode":"20190",
    "addr:street":"Spectrum Ctr",
    "iso:country":"US",
    "sg:address":"11874 Spectrum Ctr",
    "sg:city":"Reston",
    "sg:classifiers":[
        {
            "category":"Banks & Credit Unions",
            "subcategory":"Bank",
            "type":"Services"
        },
        {
            "category":"Banks & Credit Unions",
            "subcategory":"Financial Services",
            "type":"Services"
        }
    ],
    "sg:phone":"+1 703 435 1578",
    "sg:postcode":"20190",
    "sg:province":"VA",
    "sg:tags":[
        "commercial",
        "loan",
        "saving"
    ],
    "sg:website":"http://www.chevychasebank.com",
    "wof:name":"Chevy Chase Bank",
    "wof:placetype":"venue"
},
  "geometry": {"coordinates":[-77.355363,38.963999],"type":"Point"}
}