{
  "type": "Feature",
  "properties": {
    "addr:full":"310 S Adams St Arlington VA 22204",
    "addr:housenumber":"310",
    "addr:postcode":"22204",
    "addr:street":"S Adams St",
    "iso:country":"US",
    "sg:address":"310 S Adams St",
    "sg:city":"Arlington",
    "sg:classifiers":[
        {
            "category":"Professional",
            "type":"Services"
        }
    ],
    "sg:phone":"+1 703 892 6697",
    "sg:postcode":"22204",
    "sg:province":"VA",
    "wof:name":"Paula Russ",
    "wof:placetype":"venue"
},
  "geometry": {"coordinates":[-77.084626,38.869453],"type":"Point"}
}