{
  "type": "Feature",
  "properties": {
    "iso:country":"US",
    "sg:address":"5742 Floyd Hwy S",
    "sg:city":"Willis",
    "sg:classifiers":[
        {
            "category":"Autos & Motor Vehicles",
            "subcategory":"Auto Supplies",
            "type":"Retail Goods"
        }
    ],
    "sg:phone":"+1 540 789 7890",
    "sg:postcode":"24380",
    "sg:province":"VA",
    "wof:name":"B & S Tire & Lube",
    "wof:placetype":"venue"
},
  "geometry": {"coordinates":[-80.486059,36.856033],"type":"Point"}
}