{
  "type": "Feature",
  "properties": {
    "addr:full":"1900 Pavilion Dr Virginia Beach VA 23451",
    "addr:housenumber":"1900",
    "addr:postcode":"23451",
    "addr:street":"Pavilion Dr",
    "iso:country":"US",
    "sg:address":"1900 Pavilion Dr",
    "sg:city":"Virginia Beach",
    "sg:classifiers":[
        {
            "category":"Building & Trades",
            "subcategory":"Equipment Rental",
            "type":"Services"
        }
    ],
    "sg:phone":"+1 757 437 8090",
    "sg:postcode":"23451",
    "sg:province":"VA",
    "wof:name":"Presentation Services",
    "wof:placetype":"venue"
},
  "geometry": {"coordinates":[-75.99288,36.845075],"type":"Point"}
}