{
  "type": "Feature",
  "properties": {
    "addr:full":"7605 Prince George Dr Prince George VA 23875",
    "addr:housenumber":"7605",
    "addr:postcode":"23875",
    "addr:street":"Prince George Dr",
    "iso:country":"US",
    "sg:address":"7605 Prince George Dr",
    "sg:city":"Prince George",
    "sg:classifiers":[
        {
            "category":"Organizations",
            "subcategory":"Religious Organization",
            "type":"Services"
        }
    ],
    "sg:phone":"+1 804 732 5625",
    "sg:postcode":"23875",
    "sg:province":"VA",
    "wof:name":"Prince George Christian Church",
    "wof:placetype":"venue"
},
  "geometry": {"coordinates":[-77.260884,37.20848],"type":"Point"}
}