{
  "type": "Feature",
  "properties": {
    "iso:country":"US",
    "sg:address":"3160 Fairview Park Dr",
    "sg:city":"Falls Church",
    "sg:classifiers":[
        {
            "category":"Professional",
            "subcategory":"Computer Services",
            "type":"Services"
        }
    ],
    "sg:phone":"+1 703 876 1493",
    "sg:postcode":"22042",
    "sg:province":"VA",
    "sg:tags":[
        "design",
        "system"
    ],
    "wof:name":"Director of Contracts",
    "wof:placetype":"venue"
},
  "geometry": {"coordinates":[-77.217383,38.860631],"type":"Point"}
}