{
  "type": "Feature",
  "properties": {
    "addr:full":"108 Sexton Ct Sterling VA 20164",
    "addr:housenumber":"108",
    "addr:postcode":"20164",
    "addr:street":"Sexton Ct",
    "iso:country":"US",
    "sg:address":"108 Sexton Ct",
    "sg:city":"Sterling",
    "sg:classifiers":[
        {
            "category":"Social Services",
            "subcategory":"Child Care",
            "type":"Services"
        }
    ],
    "sg:phone":"+1 703 421 6780",
    "sg:postcode":"20164",
    "sg:province":"VA",
    "sg:tags":[
        "day"
    ],
    "wof:name":"Repass Family Home Day Care",
    "wof:placetype":"venue"
},
  "geometry": {"coordinates":[-77.396322,39.006328],"type":"Point"}
}