{
  "type": "Feature",
  "properties": {
    "iso:country":"US",
    "sg:address":"889 S Military Hwy",
    "sg:city":"Virginia Beach",
    "sg:classifiers":[
        {
            "category":"Taxi",
            "type":"Transportation"
        }
    ],
    "sg:phone":"+1 757 420 8722",
    "sg:postcode":"23464",
    "sg:province":"VA",
    "sg:tags":[
        "taxicab"
    ],
    "wof:name":"American Transportation",
    "wof:placetype":"venue"
},
  "geometry": {"coordinates":[-76.214947,36.816825],"type":"Point"}
}