{
  "type": "Feature",
  "properties": {
    "addr:full":"13 Catoctin Cir SE Leesburg VA 20175",
    "addr:housenumber":"13",
    "addr:postcode":"20175",
    "addr:street":"Catoctin Cir Se",
    "iso:country":"US",
    "sg:address":"13 Catoctin Cir SE",
    "sg:city":"Leesburg",
    "sg:classifiers":[
        {
            "category":"Banks & Credit Unions",
            "subcategory":"Bank",
            "type":"Services"
        }
    ],
    "sg:phone":"+1 571 258 0013",
    "sg:postcode":"20175",
    "sg:province":"VA",
    "sg:tags":[
        "cashing",
        "check"
    ],
    "wof:name":"Cash & Go",
    "wof:placetype":"venue"
},
  "geometry": {"coordinates":[-77.56704000000001,39.107259],"type":"Point"}
}