{
  "type": "Feature",
  "properties": {
    "addr:full":"6251 College Dr Suffolk VA 23435",
    "addr:housenumber":"6251",
    "addr:postcode":"23435",
    "addr:street":"College Dr",
    "iso:country":"US",
    "sg:address":"6251 College Dr",
    "sg:city":"Suffolk",
    "sg:classifiers":[
        {
            "category":"Restaurant",
            "type":"Food & Drink"
        }
    ],
    "sg:menulink":"http://www.allmenus.com/va/suffolk/192251-wendys/menu/",
    "sg:phone":"+1 757 483 5071",
    "sg:postcode":"23435",
    "sg:province":"VA",
    "sg:tags":[
        "burger",
        "american",
        "soup"
    ],
    "wof:name":"Wendy's",
    "wof:placetype":"venue"
},
  "geometry": {"coordinates":[-76.42390899999999,36.878727],"type":"Point"}
}