{
  "type": "Feature",
  "properties": {
    "iso:country":"US",
    "sg:address":"3802 Port Hope Point Rd",
    "sg:city":"Triangle",
    "sg:classifiers":[
        {
            "category":"Social Services",
            "subcategory":"Child Care",
            "type":"Services"
        },
        {
            "category":"Professional",
            "subcategory":"Employment Agencies",
            "type":"Services"
        }
    ],
    "sg:phone":"+1 703 221 1580",
    "sg:postcode":"22172",
    "sg:province":"VA",
    "sg:tags":[
        "help",
        "day",
        "contractor"
    ],
    "wof:name":"Charley's Angels Day Care",
    "wof:placetype":"venue"
},
  "geometry": {"coordinates":[-77.324974,38.559401],"type":"Point"}
}