{
  "type": "Feature",
  "properties": {
    "addr:full":"12800 Chesdin Point Ct Chesterfield VA 23838",
    "addr:housenumber":"12800",
    "addr:postcode":"23838",
    "addr:street":"Chesdin Point Ct",
    "iso:country":"US",
    "sg:address":"12800 Chesdin Point Ct",
    "sg:city":"Chesterfield",
    "sg:classifiers":[
        {
            "category":"Building & Trades",
            "subcategory":"Construction",
            "type":"Services"
        }
    ],
    "sg:phone":"+1 804 590 1100",
    "sg:postcode":"23838",
    "sg:province":"VA",
    "sg:tags":[
        "home",
        "builder"
    ],
    "wof:name":"Ridout Homes Inc",
    "wof:placetype":"venue"
},
  "geometry": {"coordinates":[-77.62009399999999,37.271155],"type":"Point"}
}