{
  "type": "Feature",
  "properties": {
    "iso:country":"US",
    "sg:address":"5203 Duke St",
    "sg:city":"Alexandria",
    "sg:classifiers":[
        {
            "category":"Personal",
            "subcategory":"Beauty Salon",
            "type":"Services"
        }
    ],
    "sg:phone":"+1 703 899 2033",
    "sg:postcode":"22304",
    "sg:province":"VA",
    "sg:tags":[
        "hair",
        "stylist"
    ],
    "wof:name":"Mata's Professional Braids & Weaves",
    "wof:placetype":"venue"
},
  "geometry": {"coordinates":[-77.122086,38.812583],"type":"Point"}
}