{
  "type": "Feature",
  "properties": {
    "iso:country":"US",
    "sg:address":"10103 Longdale Ave",
    "sg:city":"Glen Allen",
    "sg:classifiers":[
        {
            "category":"Organizations",
            "subcategory":"Religious Organization",
            "type":"Services"
        }
    ],
    "sg:phone":"+1 804 672 3829",
    "sg:postcode":"23060",
    "sg:province":"VA",
    "wof:name":"Grand Lodge AF & AM Virginia",
    "wof:placetype":"venue"
},
  "geometry": {"coordinates":[-77.468996,37.656529],"type":"Point"}
}