{
  "type": "Feature",
  "properties": {
    "iso:country":"US",
    "sg:address":"14740 Flint Lee Rd",
    "sg:city":"Chantilly",
    "sg:classifiers":[
        {
            "category":"Wholesale",
            "subcategory":"Office Equipment",
            "type":"Manufacturing & Wholesale Goods"
        }
    ],
    "sg:phone":"+1 703 961 0866",
    "sg:postcode":"20151",
    "sg:province":"VA",
    "sg:tags":[
        "copier",
        "sales"
    ],
    "wof:name":"Copier Expo Inc",
    "wof:placetype":"venue"
},
  "geometry": {"coordinates":[-77.45539100000001,38.8941],"type":"Point"}
}