{
  "type": "Feature",
  "properties": {
    "addr:full":"8290 Old Courthouse Rd Vienna VA 22182",
    "addr:housenumber":"8290",
    "addr:postcode":"22182",
    "addr:street":"Old Courthouse Rd",
    "iso:country":"US",
    "sg:address":"8290 Old Courthouse Rd",
    "sg:city":"Vienna",
    "sg:classifiers":[
        {
            "category":"Health Services",
            "subcategory":"Doctor",
            "type":"Services"
        }
    ],
    "sg:phone":"+1 703 448 4448",
    "sg:postcode":"22182",
    "sg:province":"VA",
    "sg:tags":[
        "medical"
    ],
    "wof:name":"Affordable Liposuction Clinic",
    "wof:placetype":"venue"
},
  "geometry": {"coordinates":[-77.229962,38.913048],"type":"Point"}
}