{
  "type": "Feature",
  "properties": {
    "iso:country":"US",
    "sg:address":"10505 West Dr",
    "sg:city":"Fairfax",
    "sg:classifiers":[
        {
            "category":"Professional",
            "subcategory":"Lawyer & Legal Services",
            "type":"Services"
        }
    ],
    "sg:phone":"+1 703 385 8305",
    "sg:postcode":"22030",
    "sg:province":"VA",
    "wof:name":"Mario A Bezzini PC",
    "wof:placetype":"venue"
},
  "geometry": {"coordinates":[-77.310998,38.840123],"type":"Point"}
}