{
  "type": "Feature",
  "properties": {
    "iso:country":"US",
    "sg:address":"1616 Owensville Rd",
    "sg:city":"Charlottesville",
    "sg:classifiers":[
        {
            "category":"Farming",
            "subcategory":"Livestock Farm",
            "type":"Manufacturing & Wholesale Goods"
        }
    ],
    "sg:phone":"+1 434 296 8816",
    "sg:postcode":"22901",
    "sg:province":"VA",
    "sg:tags":[
        "beef",
        "feedlot",
        "cattle"
    ],
    "wof:name":"Wayne Breeden",
    "wof:placetype":"venue"
},
  "geometry": {"coordinates":[-78.59638099999999,38.080923],"type":"Point"}
}