{
  "type": "Feature",
  "properties": {
    "iso:country":"US",
    "sg:address":"310 1st St SW",
    "sg:city":"Roanoke",
    "sg:classifiers":[
        {
            "category":"Professional",
            "subcategory":"Lawyer & Legal Services",
            "type":"Services"
        }
    ],
    "sg:phone":"+1 540 982 5547",
    "sg:postcode":"24011",
    "sg:province":"VA",
    "sg:tags":[
        "attorney"
    ],
    "wof:name":"Woodrum & Woodrum",
    "wof:placetype":"venue"
},
  "geometry": {"coordinates":[-79.94234899999999,37.270612],"type":"Point"}
}