{
  "type": "Feature",
  "properties": {
    "addr:full":"4249 Highlands Pkwy Mouth Of Wilson VA 24363",
    "addr:housenumber":"4249",
    "addr:postcode":"24363",
    "addr:street":"Highlands Pkwy",
    "iso:country":"US",
    "sg:address":"4249 Highlands Pkwy",
    "sg:city":"Mouth Of Wilson",
    "sg:classifiers":[
        {
            "category":"Shopping",
            "subcategory":"Discount & Variety Stores",
            "type":"Retail Goods"
        }
    ],
    "sg:phone":"+1 276 579 4602",
    "sg:postcode":"24363",
    "sg:province":"VA",
    "sg:tags":[
        "merchandise",
        "general"
    ],
    "wof:name":"Osborne General Store",
    "wof:placetype":"venue"
},
  "geometry": {"coordinates":[-81.447132,36.624784],"type":"Point"}
}